Workbook

Sheet Historical Financials
B2: Klarna Group plc (KLAR)
B3: Historical Financials
B4: $ mm except per share
A6: X | B6: Income Statement | C6: FYE | Q6: Quarterly | W6: LTM | AK6: LTM | AL6: LTM | AR6: Variance
B7: Fiscal Period | C7: 2022 | D7: 2023 | E7: 2024 | G7: 1Q22 | H7: 2Q22 | I7: 3Q22 | J7: 4Q22 | K7: 1Q23 | L7: 2Q23 | M7: 3Q23 | N7: 4Q23 | O7: 1Q24 | P7: 2Q24 | Q7: 3Q24 | R7: 4Q24 | S7: 1Q25 | T7: 2Q25 | U7: 3Q25 | W7: =#REF! -> #REF! | X7: =#REF! -> #REF! | Y7: =#REF! -> #REF! | Z7: =#REF! -> #REF! | AA7: =#REF! -> #REF! | AB7: =#REF! -> #REF! | AC7: =#REF! -> #REF! | AD7: =#REF! -> #REF! | ... AI7: =#REF! -> #REF! | AJ7: =O7 -> 1Q24 | AK7: =P7 -> 2Q24 | AL7: =Q7 -> 3Q24 | AM7: =R7 -> 4Q24 | AN7: =S7 -> 1Q25 | AO7: =T7 -> 2Q25 | AP7: =U7 -> 3Q25
B8: Fiscal Period End Date | C8: 44926 | D8: 45291 | E8: 45657 | G8: 44651 | H8: 44742 | I8: 44834 | J8: =C8 -> 44926 | K8: 45016 | L8: 45107 | M8: 45199 | N8: =D8 -> 45291 | O8: 45382 | P8: 45473 | Q8: 45565 | R8: =E8 -> 45657 | S8: 45747 | T8: 45838 | U8: 45930 | W8: =#REF! -> #REF! | X8: =#REF! -> #REF! | Y8: =#REF! -> #REF! | Z8: =#REF! -> #REF! | AA8: =#REF! -> #REF! | AB8: =#REF! -> #REF! | AC8: =#REF! -> #REF! | AD8: =#REF! -> #REF! | ... AI8: =#REF! -> #REF! | AJ8: =O8 -> 45382 | AK8: =P8 -> 45473 | AL8: =Q8 -> 45565 | AM8: =R8 -> 45657 | AN8: =S8 -> 45747 | AO8: =T8 -> 45838 | AP8: =U8 -> 45930
B10: Consolidated Revenue | C10: 1904 | D10: 2276 | E10: 2811 | G10: 457.87832 | H10: 483.44314 | I10: 433.10787 | J10: =SUM(C10-SUM(G10:I10)) -> 529.57067 | K10: 484.15423 | L10: 534.07557 | M10: 574.77938 | N10: =SUM(D10-SUM(K10:M10)) -> 682.99082 | O10: 635.32869 | P10: 675.93368 | Q10: 718.35223 | R10: =SUM(E10-SUM(O10:Q10)) -> 781.38539 | S10: 701.13716 | T10: 823.10162 | U10: 903 | W10: =SUM(#REF!) -> #REF! | X10: =SUM(#REF!) -> #REF! | Y10: =SUM(#REF!) -> #REF! | Z10: =SUM(#REF!) -> #REF! | AA10: =SUM(#REF!) -> #REF! | AB10: =SUM(#REF!) -> #REF! | AC10: =SUM(#REF!) -> #REF! | AD10: =SUM(#REF!) -> #REF! | ... AI10: =SUM(#REF!) -> #REF! | AJ10: =SUM(O10:O10) -> 635.32869 | AK10: =SUM(O10:P10) -> 1311.2624 | AL10: =SUM(O10:Q10) -> 2029.6146 | AM10: =SUM(O10:R10) -> 2811 | AN10: =SUM(P10:S10) -> 2876.8085 | AO10: =SUM(Q10:T10) -> 3023.9764 | AP10: =SUM(R10:U10) -> 3208.6242 | AR10: =SUM(AP10/AL10)-1 -> 0.58090317
B11: Total Revenue | C11: =+SUM(C10:C10) -> 1904 | D11: =+SUM(D10:D10) -> 2276 | E11: =+SUM(E10:E10) -> 2811 | G11: =+SUM(G10:G10) -> 457.87832 | H11: =+SUM(H10:H10) -> 483.44314 | I11: =+SUM(I10:I10) -> 433.10787 | J11: =+SUM(J10:J10) -> 529.57067 | K11: =+SUM(K10:K10) -> 484.15423 | L11: =+SUM(L10:L10) -> 534.07557 | M11: =+SUM(M10:M10) -> 574.77938 | N11: =+SUM(N10:N10) -> 682.99082 | ... U11: =+SUM(U10:U10) -> 903 | W11: =+SUM(W10:W10) -> #REF! | X11: =+SUM(X10:X10) -> #REF! | Y11: =+SUM(Y10:Y10) -> #REF! | Z11: =+SUM(Z10:Z10) -> #REF! | AA11: =+SUM(AA10:AA10) -> #REF! | AB11: =+SUM(AB10:AB10) -> #REF! | AC11: =+SUM(AC10:AC10) -> #REF! | AD11: =+SUM(AD10:AD10) -> #REF! | ... AP11: =+SUM(AP10:AP10) -> 3208.6242 | AR11: =SUM(AP11/AL11)-1 -> 0.58090317
B13: Processing and servicing costs | C13: -520 | D13: -541 | E13: -596 | G13: -122.86115 | H13: -140.3493 | I13: -119.00793 | J13: =SUM(C13-SUM(G13:I13)) -> -137.78162 | K13: -127.9813 | L13: -131.41075 | M13: -133.22809 | N13: =SUM(D13-SUM(K13:M13)) -> -148.37987 | O13: -135.90164 | P13: -148.01296 | Q13: -151.29141 | R13: =SUM(E13-SUM(O13:Q13)) -> -160.79398 | S13: -163.90402 | T13: -187.17015 | U13: -208 | W13: =SUM(#REF!) -> #REF! | X13: =SUM(#REF!) -> #REF! | Y13: =SUM(#REF!) -> #REF! | Z13: =SUM(#REF!) -> #REF! | AA13: =SUM(#REF!) -> #REF! | AB13: =SUM(#REF!) -> #REF! | AC13: =SUM(#REF!) -> #REF! | AD13: =SUM(#REF!) -> #REF! | ... AI13: =SUM(#REF!) -> #REF! | AJ13: =SUM(O13:O13) -> -135.90164 | AK13: =SUM(O13:P13) -> -283.91461 | AL13: =SUM(O13:Q13) -> -435.20602 | AM13: =SUM(O13:R13) -> -596 | AN13: =SUM(P13:S13) -> -624.00238 | AO13: =SUM(Q13:T13) -> -663.15957 | AP13: =SUM(R13:U13) -> -719.86816 | AR13: =SUM(AP13/AL13)-1 -> 0.65408593
B14: Consumer credit losses | C14: -550 | D14: -353 | E14: -495 | G14: -124.71731 | H14: -166.09766 | I14: -136.43861 | J14: =SUM(C14-SUM(G14:I14)) -> -122.74643 | K14: -72.849766 | L14: -88.327096 | M14: -72.010591 | N14: =SUM(D14-SUM(K14:M14)) -> -119.81255 | O14: -116.66508 | P14: -106.30731 | Q14: -115.60805 | R14: =SUM(E14-SUM(O14:Q14)) -> -156.41956 | S14: -136.19618 | T14: -173.5701 | U14: -235 | AL14: =SUM(O14:Q14) -> -338.58044 | AM14: =SUM(O14:R14) -> -495 | AN14: =SUM(P14:S14) -> -514.5311 | AO14: =SUM(Q14:T14) -> -581.79389 | AP14: =SUM(R14:U14) -> -701.18584 | AR14: =SUM(AP14/AL14)-1 -> 1.0709579
B15: Funding costs | C15: -147 | D15: -297 | E15: -503 | G15: -30.028678 | H15: -30.251101 | I15: -39.36219 | J15: =SUM(C15-SUM(G15:I15)) -> -47.358031 | K15: -56.835333 | L15: -62.384282 | M15: -77.893781 | N15: =SUM(D15-SUM(K15:M15)) -> -99.886603 | O15: -113.38908 | P15: -119.84023 | Q15: -122.80654 | R15: =SUM(E15-SUM(O15:Q15)) -> -146.96414 | S15: -130.27724 | T15: -147.34958 | U15: -180 | AL15: =SUM(O15:Q15) -> -356.03586 | AM15: =SUM(O15:R15) -> -503 | AN15: =SUM(P15:S15) -> -519.88816 | AO15: =SUM(Q15:T15) -> -547.39751 | AP15: =SUM(R15:U15) -> -604.59097 | AR15: =SUM(AP15/AL15)-1 -> 0.6981182
B16: Gross Profit (Transaction Margin Dollars) | C16: =+SUM(C11+SUM(C13:C15)) -> 687 | D16: =+SUM(D11+SUM(D13:D15)) -> 1085 | E16: =+SUM(E11+SUM(E13:E15)) -> 1217 | G16: =+SUM(G11+SUM(G13:G15)) -> 180.27119 | H16: =+SUM(H11+SUM(H13:H15)) -> 146.74508 | I16: =+SUM(I11+SUM(I13:I15)) -> 138.29914 | J16: =+SUM(J11+SUM(J13:J15)) -> 221.68459 | K16: =+SUM(K11+SUM(K13:K15)) -> 226.48784 | L16: =+SUM(L11+SUM(L13:L15)) -> 251.95345 | M16: =+SUM(M11+SUM(M13:M15)) -> 291.64691 | N16: =+SUM(N11+SUM(N13:N15)) -> 314.9118 | ... U16: =+SUM(U11+SUM(U13:U15)) -> 280 | W16: =+SUM(W11+SUM(W13:W13)) -> #REF! | X16: =+SUM(X11+SUM(X13:X13)) -> #REF! | Y16: =+SUM(Y11+SUM(Y13:Y13)) -> #REF! | Z16: =+SUM(Z11+SUM(Z13:Z13)) -> #REF! | AA16: =+SUM(AA11+SUM(AA13:AA13)) -> #REF! | AB16: =+SUM(AB11+SUM(AB13:AB13)) -> #REF! | AC16: =+SUM(AC11+SUM(AC13:AC13)) -> #REF! | AD16: =+SUM(AD11+SUM(AD13:AD13)) -> #REF! | ... AK16: =+SUM(AK11+SUM(AK13:AK13)) -> 1027.3478 | AL16: =+SUM(AL11+SUM(AL13:AL15)) -> 899.79229 | AM16: =+SUM(AM11+SUM(AM13:AM15)) -> 1217 | AN16: =+SUM(AN11+SUM(AN13:AN15)) -> 1218.3868 | AO16: =+SUM(AO11+SUM(AO13:AO15)) -> 1231.6254 | AP16: =+SUM(AP11+SUM(AP13:AP15)) -> 1182.9792 | AR16: =SUM(AP16/AL16)-1 -> 0.31472476
B17: Gross Margin (%) | C17: =C16/C11 -> 0.36081933 | D17: =D16/D11 -> 0.47671353 | E17: =E16/E11 -> 0.43294201 | G17: =G16/G11 -> 0.39370981 | H17: =H16/H11 -> 0.30354155 | I17: =I16/I11 -> 0.31931801 | J17: =J16/J11 -> 0.41861191 | K17: =K16/K11 -> 0.46780101 | L17: =L16/L11 -> 0.47175617 | M17: =M16/M11 -> 0.50740671 | N17: =N16/N11 -> 0.46107765 | ... U17: =U16/U11 -> 0.31007752 | W17: =W16/W11 -> #REF! | X17: =X16/X11 -> #REF! | Y17: =Y16/Y11 -> #REF! | Z17: =Z16/Z11 -> #REF! | AA17: =AA16/AA11 -> #REF! | AB17: =AB16/AB11 -> #REF! | AC17: =AC16/AC11 -> #REF! | AD17: =AD16/AD11 -> #REF! | ... AP17: =AP16/AP11 -> 0.36868737 | AR17: =SUM(AP17-AL17)*1000 -> -74.64423
B19: Technology and product development | C19: -355.14437 | D19: -276.4925 | E19: -307.83389 | G19: -96.741726 | H19: -107.08367 | I19: -69.442446 | J19: =SUM(C19-SUM(G19:I19)) -> -81.876523 | K19: -66.668118 | L19: -70.24335 | M19: -64.689124 | N19: =SUM(D19-SUM(K19:M19)) -> -74.89191 | O19: -78.315834 | P19: -80.95758 | Q19: -77.696906 | R19: =SUM(E19-SUM(O19:Q19)) -> -70.863571 | S19: -83.019928 | T19: -93.232776 | U19: -97 | AL19: =SUM(O19:Q19) -> -236.97032 | AM19: =SUM(O19:R19) -> -307.83389 | AN19: =SUM(P19:S19) -> -312.53798 | AO19: =SUM(Q19:T19) -> -324.81318 | AP19: =SUM(R19:U19) -> -344.11627 | AR19: =SUM(AP19/AL19)-1 -> 0.45214926
B20: Sales and Marketing (S&M) | C20: -523.16659 | D20: -371.67993 | E20: -309.06155 | G20: -136.26446 | H20: -154.38537 | I20: -96.270785 | J20: =SUM(C20-SUM(G20:I20)) -> -136.24597 | K20: -74.05317 | L20: -81.772555 | M20: -78.908538 | N20: =SUM(D20-SUM(K20:M20)) -> -136.94567 | O20: -76.354386 | P20: -76.742658 | Q20: -65.442832 | R20: =SUM(E20-SUM(O20:Q20)) -> -90.52167 | S20: -79.667124 | T20: -82.899178 | U20: -85 | AL20: =SUM(O20:Q20) -> -218.53988 | AM20: =SUM(O20:R20) -> -309.06155 | AN20: =SUM(P20:S20) -> -312.37428 | AO20: =SUM(Q20:T20) -> -318.5308 | AP20: =SUM(R20:U20) -> -338.08797 | AR20: =SUM(AP20/AL20)-1 -> 0.54703104
B21: Customer service and operations | C21: -285.51807 | D21: -238.31196 | E21: -192.41582 | G21: -78.401399 | H21: -80.958778 | I21: -60.835907 | J21: =SUM(C21-SUM(G21:I21)) -> -65.321982 | K21: -62.666632 | L21: -53.704776 | M21: -52.34587 | N21: =SUM(D21-SUM(K21:M21)) -> -69.594678 | O21: -56.855008 | P21: -47.379999 | Q21: -42.017432 | R21: =SUM(E21-SUM(O21:Q21)) -> -46.163386 | S21: -50.275283 | T21: -48.020048 | U21: -50 | AL21: =SUM(O21:Q21) -> -146.25244 | AM21: =SUM(O21:R21) -> -192.41582 | AN21: =SUM(P21:S21) -> -185.8361 | AO21: =SUM(Q21:T21) -> -186.47615 | AP21: =SUM(R21:U21) -> -194.45872 | AR21: =SUM(AP21/AL21)-1 -> 0.32961008
B22: General and Administrative (G&A) | C22: -248.72763 | D22: -247.95489 | E22: -226.7649 | G22: -65.534632 | H22: -53.049638 | I22: -61.373631 | J22: =SUM(C22-SUM(G22:I22)) -> -68.769733 | K22: -60.081628 | L22: -55.965976 | M22: -50.3652 | N22: =SUM(D22-SUM(K22:M22)) -> -81.542083 | O22: -50.458582 | P22: -57.564682 | Q22: -51.71173 | R22: =SUM(E22-SUM(O22:Q22)) -> -67.029906 | S22: -54.492572 | T22: -61.598968 | U22: -63 | AL22: =SUM(O22:Q22) -> -159.73499 | AM22: =SUM(O22:R22) -> -226.7649 | AN22: =SUM(P22:S22) -> -230.79889 | AO22: =SUM(Q22:T22) -> -234.83318 | AP22: =SUM(R22:U22) -> -246.12145 | AR22: =SUM(AP22/AL22)-1 -> 0.54081106
B23: Restructuring Charges | C23: -35.728705 | D23: -5.308423 | E23: -5.7080184 | G23: 0 | H23: -34.404786 | I23: 1.1317286 | J23: =SUM(C23-SUM(G23:I23)) -> -2.4556476 | K23: 0 | L23: -2.204065 | M23: 0.021758 | N23: =SUM(D23-SUM(K23:M23)) -> -3.126116 | O23: 0 | P23: 0 | Q23: -2.917737 | R23: =SUM(E23-SUM(O23:Q23)) -> -2.7902814 | S23: -4.3000001e-07 | T23: 4.2173656 | U23: -5 | AL23: =SUM(O23:Q23) -> -2.917737 | AM23: =SUM(O23:R23) -> -5.7080184 | AN23: =SUM(P23:S23) -> -5.7080188 | AO23: =SUM(Q23:T23) -> -1.4906532 | AP23: =SUM(R23:U23) -> -3.5729162 | AR23: =SUM(AP23/AL23)-1 -> 0.22455047
B24: Share based Payments | C24: -56.314768 | D24: -42.596111 | E24: -91.840168 | G24: -18.302156 | H24: -16.410189 | I24: -8.6047788 | J24: =SUM(C24-SUM(G24:I24)) -> -12.997645 | K24: -9.8012168 | L24: -12.632712 | M24: -8.7612611 | N24: =SUM(D24-SUM(K24:M24)) -> -11.400921 | O24: -5.4089236 | P24: -8.8826422 | Q24: -20.142968 | R24: =SUM(E24-SUM(O24:Q24)) -> -57.405634 | S24: -58.543661 | T24: -26.392681 | U24: -39 | AL24: =SUM(O24:Q24) -> -34.434534 | AM24: =SUM(O24:R24) -> -91.840168 | AN24: =SUM(P24:S24) -> -144.97491 | AO24: =SUM(Q24:T24) -> -162.48494 | AP24: =SUM(R24:U24) -> -181.34198 | AR24: =SUM(AP24/AL24)-1 -> 4.2662823
B25: IPO Related Charges | C25: 0 | D25: 0 | E25: -15.123364 | G25: 0 | H25: 0 | I25: 0 | J25: =SUM(C25-SUM(G25:I25)) -> 0 | K25: 0 | L25: 0 | M25: 0 | N25: =SUM(D25-SUM(K25:M25)) -> 0 | O25: -1.5503133 | P25: -2.2861342 | Q25: -6.0381063 | R25: =SUM(E25-SUM(O25:Q25)) -> -5.2488098 | S25: -8.3823611 | T25: -1.9570492 | U25: 0 | AL25: =SUM(O25:Q25) -> -9.8745538 | AM25: =SUM(O25:R25) -> -15.123364 | AN25: =SUM(P25:S25) -> -21.955411 | AO25: =SUM(Q25:T25) -> -21.626326 | AP25: =SUM(R25:U25) -> -15.58822 | AR25: =SUM(AP25/AL25)-1 -> 0.57862527
B26: Depreciation, amortization and impairments | C26: -161.9695 | D26: -226.06808 | E26: -188.8674 | G26: -29.04236 | H26: -41.805338 | I26: -46.63717 | J26: =SUM(C26-SUM(G26:I26)) -> -44.484636 | K26: -55.639149 | L26: -52.558621 | M26: -40.713393 | N26: =SUM(D26-SUM(K26:M26)) -> -77.156919 | O26: -36.23425 | P26: -37.992838 | Q26: -37.228717 | R26: =SUM(E26-SUM(O26:Q26)) -> -77.4116 | S26: -25.947516 | T26: -50.733473 | U26: -25 | AL26: =SUM(O26:Q26) -> -111.4558 | AM26: =SUM(O26:R26) -> -188.8674 | AN26: =SUM(P26:S26) -> -178.58067 | AO26: =SUM(Q26:T26) -> -191.32131 | AP26: =SUM(R26:U26) -> -179.09259 | AR26: =SUM(AP26/AL26)-1 -> 0.60684846
B27: Operating Profit | C27: =+SUM(C16+SUM(C19:C26)) -> -979.56963 | D27: =+SUM(D16+SUM(D19:D26)) -> -323.41189 | E27: =+SUM(E16+SUM(E19:E26)) -> -120.61512 | G27: =+SUM(G16+SUM(G19:G26)) -> -244.01555 | H27: =+SUM(H16+SUM(H19:H26)) -> -341.35269 | I27: =+SUM(I16+SUM(I19:I26)) -> -203.73385 | J27: =+SUM(J16+SUM(J19:J26)) -> -190.46755 | K27: =+SUM(K16+SUM(K19:K26)) -> -102.42208 | L27: =+SUM(L16+SUM(L19:L26)) -> -77.128606 | M27: =+SUM(M16+SUM(M19:M26)) -> -4.1147128 | N27: =+SUM(N16+SUM(N19:N26)) -> -139.74649 | ... U27: =+SUM(U16+SUM(U19:U26)) -> -84 | W27: =+SUM(W16+SUM(W19:W26)) -> #REF! | X27: =+SUM(X16+SUM(X19:X26)) -> #REF! | Y27: =+SUM(Y16+SUM(Y19:Y26)) -> #REF! | Z27: =+SUM(Z16+SUM(Z19:Z26)) -> #REF! | AA27: =+SUM(AA16+SUM(AA19:AA26)) -> #REF! | AB27: =+SUM(AB16+SUM(AB19:AB26)) -> #REF! | AC27: =+SUM(AC16+SUM(AC19:AC26)) -> #REF! | AD27: =+SUM(AD16+SUM(AD19:AD26)) -> #REF! | ... AP27: =+SUM(AP16+SUM(AP19:AP26)) -> -319.4009 | AR27: =SUM(AP27/AL27)-1 -> 14.666148
B28: Operating Margin (%) | C28: =C27/C11 -> -0.51447985 | D28: =D27/D11 -> -0.14209661 | E28: =E27/E11 -> -0.042908259 | G28: =G27/G11 -> -0.53292663 | H28: =H27/H11 -> -0.70608653 | I28: =I27/I11 -> -0.47039979 | J28: =J27/J11 -> -0.35966408 | K28: =K27/K11 -> -0.21154845 | L28: =L27/L11 -> -0.14441515 | M28: =M27/M11 -> -0.007158769 | N28: =N27/N11 -> -0.20460962 | ... U28: =U27/U11 -> -0.093023256 | W28: =W27/W11 -> #REF! | X28: =X27/X11 -> #REF! | Y28: =Y27/Y11 -> #REF! | Z28: =Z27/Z11 -> #REF! | AA28: =AA27/AA11 -> #REF! | AB28: =AB27/AB11 -> #REF! | AC28: =AC27/AC11 -> #REF! | AD28: =AD27/AD11 -> #REF! | ... AP28: =AP27/AP11 -> -0.099544504 | AR28: =SUM(AP28-AL28)*1000 -> -89.499264
B30: Other income (expense) | C30: -58 | D30: 19 | E30: 154 | G30: -39.595378 | H30: -41.426308 | I30: 14.249358 | J30: =SUM(C30-SUM(G30:I30)) -> 8.7723281 | K30: 3.884331 | L30: -4.4317395 | M30: 7.8084026 | N30: =SUM(D30-SUM(K30:M30)) -> 11.739006 | O30: 10.32992 | P30: 7.2860645 | Q30: -10.722127 | R30: =SUM(E30-SUM(O30:Q30)) -> 147.10614 | S30: -1.8055911 | T30: -0.23400613 | U30: -4 | W30: =SUM(#REF!) -> #REF! | X30: =SUM(#REF!) -> #REF! | Y30: =SUM(#REF!) -> #REF! | Z30: =SUM(#REF!) -> #REF! | AA30: =SUM(#REF!) -> #REF! | AB30: =SUM(#REF!) -> #REF! | AC30: =SUM(#REF!) -> #REF! | AD30: =SUM(#REF!) -> #REF! | ... AI30: =SUM(#REF!) -> #REF! | AJ30: =SUM(O30:O30) -> 10.32992 | AK30: =SUM(O30:P30) -> 17.615985 | AL30: =SUM(O30:Q30) -> 6.8938572 | AM30: =SUM(O30:R30) -> 154 | AN30: =SUM(P30:S30) -> 141.86449 | AO30: =SUM(Q30:T30) -> 134.34442 | AP30: =SUM(R30:U30) -> 141.06655 | AR30: =SUM(AP30/AL30)-1 -> 19.462644
B31: Earning Before Taxes | C31: =SUM(C27+SUM(C30:C30)) -> -1037.5696 | D31: =SUM(D27+SUM(D30:D30)) -> -304.41189 | E31: =SUM(E27+SUM(E30:E30)) -> 33.384884 | G31: =SUM(G27+SUM(G30:G30)) -> -283.61093 | H31: =SUM(H27+SUM(H30:H30)) -> -382.779 | I31: =SUM(I27+SUM(I30:I30)) -> -189.48449 | J31: =SUM(J27+SUM(J30:J30)) -> -181.69522 | K31: =SUM(K27+SUM(K30:K30)) -> -98.537746 | L31: =SUM(L27+SUM(L30:L30)) -> -81.560346 | M31: =SUM(M27+SUM(M30:M30)) -> 3.6936898 | N31: =SUM(N27+SUM(N30:N30)) -> -128.00749 | ... U31: =SUM(U27+SUM(U30:U30)) -> -88 | W31: =SUM(W27+SUM(W30:W30)) -> #REF! | X31: =SUM(X27+SUM(X30:X30)) -> #REF! | Y31: =SUM(Y27+SUM(Y30:Y30)) -> #REF! | Z31: =SUM(Z27+SUM(Z30:Z30)) -> #REF! | AA31: =SUM(AA27+SUM(AA30:AA30)) -> #REF! | AB31: =SUM(AB27+SUM(AB30:AB30)) -> #REF! | AC31: =SUM(AC27+SUM(AC30:AC30)) -> #REF! | AD31: =SUM(AD27+SUM(AD30:AD30)) -> #REF! | ... AP31: =SUM(AP27+SUM(AP30:AP30)) -> -178.33436 | AR31: =SUM(AP31/AL31)-1 -> 12.215719
B32: EBT Margin (%) | C32: =C31/C11 -> -0.54494203 | D32: =D31/D11 -> -0.13374863 | E32: =E31/E11 -> 0.011876515 | G32: =G31/G11 -> -0.61940239 | H32: =H31/H11 -> -0.79177666 | I32: =I31/I11 -> -0.43749954 | J32: =J31/J11 -> -0.3430991 | K32: =K31/K11 -> -0.20352553 | L32: =L31/L11 -> -0.15271312 | M32: =M31/M11 -> 0.0064262741 | N32: =N31/N11 -> -0.18742197 | ... U32: =U31/U11 -> -0.097452935 | W32: =W31/W11 -> #REF! | X32: =X31/X11 -> #REF! | Y32: =Y31/Y11 -> #REF! | Z32: =Z31/Z11 -> #REF! | AA32: =AA31/AA11 -> #REF! | AB32: =AB31/AB11 -> #REF! | AC32: =AC31/AC11 -> #REF! | AD32: =AD31/AD11 -> #REF! | ... AP32: =AP31/AP11 -> -0.055579696 | AR32: =SUM(AP32-AL32)*1000 -> -48.931089
B34: Provision for taxes | C34: -8.2544085 | D34: 60 | E34: -12 | G34: -3.0776812 | H34: -1.036735 | I34: -3.3575318 | J34: =SUM(C34-SUM(G34:I34)) -> -0.78246048 | K34: 54.984441 | L34: -10.274186 | M34: 0.35908703 | N34: =SUM(D34-SUM(K34:M34)) -> 14.930658 | O34: -4.9203694 | P34: 0.93651644 | Q34: -2.3003912 | R34: =SUM(E34-SUM(O34:Q34)) -> -5.7157559 | S34: -7.4439852 | T34: -7.0970093 | U34: -8 | W34: =SUM(#REF!) -> #REF! | X34: =SUM(#REF!) -> #REF! | Y34: =SUM(#REF!) -> #REF! | Z34: =SUM(#REF!) -> #REF! | AA34: =SUM(#REF!) -> #REF! | AB34: =SUM(#REF!) -> #REF! | AC34: =SUM(#REF!) -> #REF! | AD34: =SUM(#REF!) -> #REF! | ... AI34: =SUM(#REF!) -> #REF! | AJ34: =SUM(O34:O34) -> -4.9203694 | AK34: =SUM(O34:P34) -> -3.9838529 | AL34: =SUM(O34:Q34) -> -6.2842441 | AM34: =SUM(O34:R34) -> -12 | AN34: =SUM(P34:S34) -> -14.523616 | AO34: =SUM(Q34:T34) -> -22.557142 | AP34: =SUM(R34:U34) -> -28.25675 | AR34: =SUM(AP34/AL34)-1 -> 3.4964438
B35: Net loss | C35: =SUM(C31+SUM(C34:C34)) -> -1045.824 | D35: =SUM(D31+SUM(D34:D34)) -> -244.41189 | E35: =SUM(E31+SUM(E34:E34)) -> 21.384884 | G35: =SUM(G31+SUM(G34:G34)) -> -286.68861 | H35: =SUM(H31+SUM(H34:H34)) -> -383.81573 | I35: =SUM(I31+SUM(I34:I34)) -> -192.84202 | J35: =SUM(J31+SUM(J34:J34)) -> -182.47768 | K35: =SUM(K31+SUM(K34:K34)) -> -43.553305 | L35: =SUM(L31+SUM(L34:L34)) -> -91.834532 | M35: =SUM(M31+SUM(M34:M34)) -> 4.0527769 | N35: =SUM(N31+SUM(N34:N34)) -> -113.07683 | ... U35: =SUM(U31+SUM(U34:U34)) -> -96 | W35: =SUM(W31+SUM(W34:W34)) -> #REF! | X35: =SUM(X31+SUM(X34:X34)) -> #REF! | Y35: =SUM(Y31+SUM(Y34:Y34)) -> #REF! | Z35: =SUM(Z31+SUM(Z34:Z34)) -> #REF! | AA35: =SUM(AA31+SUM(AA34:AA34)) -> #REF! | AB35: =SUM(AB31+SUM(AB34:AB34)) -> #REF! | AC35: =SUM(AC31+SUM(AC34:AC34)) -> #REF! | AD35: =SUM(AD31+SUM(AD34:AD34)) -> #REF! | ... AP35: =SUM(AP31+SUM(AP34:AP34)) -> -206.59111 | AR35: =SUM(AP35/AL35)-1 -> 9.4453137
B36: Net Margin (%) | C36: =C35/C11 -> -0.54927733 | D36: =D35/D11 -> -0.10738659 | E36: =E35/E11 -> 0.0076075716 | G36: =G35/G11 -> -0.62612401 | H36: =H35/H11 -> -0.79392114 | I36: =I35/I11 -> -0.44525172 | J36: =J35/J11 -> -0.34457663 | K36: =K35/K11 -> -0.089957502 | L36: =L35/L11 -> -0.17195044 | M36: =M35/M11 -> 0.007051013 | N36: =N35/N11 -> -0.16556127 | ... U36: =U35/U11 -> -0.10631229 | W36: =W35/W11 -> #REF! | X36: =X35/X11 -> #REF! | Y36: =Y35/Y11 -> #REF! | Z36: =Z35/Z11 -> #REF! | AA36: =AA35/AA11 -> #REF! | AB36: =AB35/AB11 -> #REF! | AC36: =AC35/AC11 -> #REF! | AD36: =AD35/AD11 -> #REF! | ... AP36: =AP35/AP11 -> -0.064386197 | AR36: =SUM(AP36-AL36)*1000 -> -54.641315
B38: Basic Shares | C38: 382.33536 | D38: 382.33536 | E38: 382.33536 | G38: 382.33536 | H38: 382.33536 | I38: 382.33536 | J38: =C38 -> 382.33536 | K38: 382.33536 | L38: 382.33536 | M38: 382.33536 | N38: =D38 -> 382.33536 | O38: 382.33536 | P38: 382.33536 | Q38: 382.33536 | R38: =E38 -> 382.33536 | S38: 382.33536 | T38: 382.33536 | U38: 382.33536 | W38: =B38 -> Basic Shares | X38: =C38 -> 382.33536 | Y38: =D38 -> 382.33536 | Z38: =E38 -> 382.33536 | AA38: =F38 -> 0 | AB38: =G38 -> 382.33536 | AC38: =H38 -> 382.33536 | AD38: =I38 -> 382.33536 | ... AP38: =U38 -> 382.33536 | AR38: =SUM(AP38/AL38)-1 -> 0
B39: Basic EPS | C39: =C35/C38 -> -2.7353579 | D39: =D35/D38 -> -0.63926049 | E39: =E35/E38 -> 0.055932268 | G39: =G35/G38 -> -0.74983546 | H39: =H35/H38 -> -1.0038719 | I39: =I35/I38 -> -0.50437925 | J39: =J35/J38 -> -0.47727126 | K39: =K35/K38 -> -0.11391388 | L39: =L35/L38 -> -0.24019367 | M39: =M35/M38 -> 0.010600058 | N39: =N35/N38 -> -0.295753 | ... U39: =U35/U38 -> -0.25108847 | W39: =W35/W38 -> #REF! | X39: =X35/X38 -> #REF! | Y39: =Y35/Y38 -> #REF! | Z39: =Z35/Z38 -> #REF! | AA39: =AA35/AA38 -> #REF! | AB39: =AB35/AB38 -> #REF! | AC39: =AC35/AC38 -> #REF! | AD39: =AD35/AD38 -> #REF! | ... AP39: =AP35/AP38 -> -0.54034005 | AR39: =SUM(AP39/AL39)-1 -> 9.4453137
B41: Fully Diluted Shares | C41: 385.56633 | D41: 385.56633 | E41: 385.56633 | G41: 385.56633 | H41: 385.56633 | I41: 385.56633 | J41: =C41 -> 385.56633 | K41: 385.56633 | L41: 385.56633 | M41: 385.56633 | N41: =D41 -> 385.56633 | O41: 385.56633 | P41: 385.56633 | Q41: 385.56633 | R41: =E41 -> 385.56633 | S41: 385.56633 | T41: 385.56633 | U41: 385.56633 | W41: =B41 -> Fully Diluted Shares | X41: =C41 -> 385.56633 | Y41: =D41 -> 385.56633 | Z41: =E41 -> 385.56633 | AA41: =F41 -> 0 | AB41: =G41 -> 385.56633 | AC41: =H41 -> 385.56633 | AD41: =I41 -> 385.56633 | ... AP41: =U41 -> 385.56633 | AR41: =SUM(AP41/AL41)-1 -> 0
B42: Fully Diluted EPS | C42: =C35/C41 -> -2.7124361 | D42: =D35/D41 -> -0.63390362 | E42: =E35/E41 -> 0.055463567 | G42: =G35/G41 -> -0.74355199 | H42: =H35/H41 -> -0.99545968 | I42: =I35/I41 -> -0.50015266 | J42: =J35/J41 -> -0.47327182 | K42: =K35/K41 -> -0.11295931 | L42: =L35/L41 -> -0.23818089 | M42: =M35/M41 -> 0.010511231 | N42: =N35/N41 -> -0.29327465 | ... U42: =U35/U41 -> -0.2489844 | W42: =W35/W41 -> #REF! | X42: =X35/X41 -> #REF! | Y42: =Y35/Y41 -> #REF! | Z42: =Z35/Z41 -> #REF! | AA42: =AA35/AA41 -> #REF! | AB42: =AB35/AB41 -> #REF! | AC42: =AC35/AC41 -> #REF! | AD42: =AD35/AD41 -> #REF! | ... AP42: =AP35/AP41 -> -0.53581211 | AR42: =SUM(AP42/AL42)-1 -> 9.4453137
A44: X | B44: Balance Sheet | AK44: LTM | AR44: Variance
B45: =B7 -> Fiscal Period | C45: =C7 -> 2022 | D45: =D7 -> 2023 | E45: =E7 -> 2024 | G45: =G7 -> 1Q22 | H45: =H7 -> 2Q22 | I45: =I7 -> 3Q22 | J45: =J7 -> 4Q22 | K45: =K7 -> 1Q23 | L45: =L7 -> 2Q23 | M45: =M7 -> 3Q23 | N45: =N7 -> 4Q23 | ... U45: =U7 -> 3Q25 | W45: =W7 -> #REF! | X45: =X7 -> #REF! | Y45: =Y7 -> #REF! | Z45: =Z7 -> #REF! | AA45: =AA7 -> #REF! | AB45: =AB7 -> #REF! | AC45: =AC7 -> #REF! | AD45: =AD7 -> #REF! | ... AP45: =AP7 -> 3Q25
B46: =B8 -> Fiscal Period End Date | C46: =C8 -> 44926 | D46: =D8 -> 45291 | E46: =E8 -> 45657 | G46: =G8 -> 44651 | H46: =H8 -> 44742 | I46: =I8 -> 44834 | J46: =J8 -> 44926 | K46: =K8 -> 45016 | L46: =L8 -> 45107 | M46: =M8 -> 45199 | N46: =N8 -> 45291 | ... U46: =U8 -> 45930 | W46: =W8 -> #REF! | X46: =X8 -> #REF! | Y46: =Y8 -> #REF! | Z46: =Z8 -> #REF! | AA46: =AA8 -> #REF! | AB46: =AB8 -> #REF! | AC46: =AC8 -> #REF! | AD46: =AD8 -> #REF! | ... AP46: =AP8 -> 45930
B48: Assets
B49: Cash and cash equivalents | C49: 1694.2579 | D49: 2390.1 | E49: 3242.9703 | G49: 1253.2419 | H49: 907.76546 | I49: 1545.2618 | J49: =C49 -> 1694.2579 | K49: 2162.3429 | L49: 1263.809 | M49: 2344.1758 | N49: =D49 -> 2390.1 | O49: 3629 | P49: 3419.4387 | Q49: 3843.3251 | R49: =E49 -> 3242.9703 | S49: 4104.9278 | T49: 5503.6166 | U49: 6795 | W49: =#REF! -> #REF! | X49: =#REF! -> #REF! | Y49: =#REF! -> #REF! | Z49: =#REF! -> #REF! | AA49: =#REF! -> #REF! | AB49: =#REF! -> #REF! | AC49: =#REF! -> #REF! | AD49: =#REF! -> #REF! | ... AI49: =#REF! -> #REF! | AJ49: =O49 -> 3629 | AK49: =P49 -> 3419.4387 | AL49: =Q49 -> 3843.3251 | AM49: =R49 -> 3242.9703 | AN49: =S49 -> 4104.9278 | AO49: =T49 -> 5503.6166 | AP49: =U49 -> 6795 | AR49: =SUM(AP49/AL49)-1 -> 0.76800031
B50: Debt securities | C50: 1121.1853 | D50: 798.6 | E50: 453.71243 | G50: 1580.4882 | H50: 1272.571 | I50: 1192.9042 | J50: =C50 -> 1121.1853 | K50: 1089.7286 | L50: 970.11563 | M50: 872.75237 | N50: =D50 -> 798.6 | O50: 1014.1019 | P50: 972.36892 | Q50: 785.17702 | R50: =E50 -> 453.71243 | S50: 1187.7035 | T50: 1380.9545 | U50: 1657 | W50: =#REF! -> #REF! | X50: =#REF! -> #REF! | Y50: =#REF! -> #REF! | Z50: =#REF! -> #REF! | AA50: =#REF! -> #REF! | AB50: =#REF! -> #REF! | AC50: =#REF! -> #REF! | AD50: =#REF! -> #REF! | ... AI50: =#REF! -> #REF! | AJ50: =O50 -> 1014.1019 | AK50: =P50 -> 972.36892 | AL50: =Q50 -> 785.17702 | AM50: =R50 -> 453.71243 | AN50: =S50 -> 1187.7035 | AO50: =T50 -> 1380.9545 | AP50: =U50 -> 1657 | AR50: =SUM(AP50/AL50)-1 -> 1.1103521
B51: Consumer receivables | C51: 6756.7639 | D51: 8082.9 | E51: 8141.0163 | G51: 6406.4419 | H51: 6397.3181 | I51: 5649.0709 | J51: =C51 -> 6756.7639 | K51: 6209.947 | L51: 6801.8853 | M51: 6681.2242 | N51: =D51 -> 8082.9 | O51: 7501.6233 | P51: 7954.5852 | Q51: 8548.41 | R51: =E51 -> 8141.0163 | S51: 8123.756 | T51: 9950.1662 | U51: 10095 | W51: =#REF! -> #REF! | X51: =#REF! -> #REF! | Y51: =#REF! -> #REF! | Z51: =#REF! -> #REF! | AA51: =#REF! -> #REF! | AB51: =#REF! -> #REF! | AC51: =#REF! -> #REF! | AD51: =#REF! -> #REF! | ... AI51: =#REF! -> #REF! | AJ51: =O51 -> 7501.6233 | AK51: =P51 -> 7954.5852 | AL51: =Q51 -> 8548.41 | AM51: =R51 -> 8141.0163 | AN51: =S51 -> 8123.756 | AO51: =T51 -> 9950.1662 | AP51: =U51 -> 10095 | AR51: =SUM(AP51/AL51)-1 -> 0.18092137
B52: Goodwill & intangible assets | C52: 1226.5482 | D52: 1200.12 | E52: 988.86466 | G52: 748.49248 | H52: 1220.8034 | I52: 1138.2559 | J52: =C52 -> 1226.5482 | K52: 1234.0831 | L52: 1195.6168 | M52: 1175.5251 | N52: =D52 -> 1200.12 | O52: 1134.1202 | P52: 1097.4511 | Q52: 1127.9642 | R52: =E52 -> 988.86466 | S52: 1040.0581 | T52: 1082.1445 | U52: =681+392 -> 1073 | AL52: =Q52 -> 1127.9642 | AM52: =R52 -> 988.86466 | AN52: =S52 -> 1040.0581 | AO52: =T52 -> 1082.1445 | AP52: =U52 -> 1073
B53: Other assets | C53: 1210.4586 | D53: 1275.2 | E53: 977.97848 | G53: 1179.7509 | H53: 1185.9725 | I53: 1200.697 | J53: =C53 -> 1210.4586 | K53: 890.50141 | L53: 993.43786 | M53: 959.65157 | N53: =D53 -> 1275.2 | O53: 1103.0534 | P53: 1185.324 | Q53: 1136.8275 | R53: =E53 -> 977.97848 | S53: 1068.7323 | T53: 1272.0399 | U53: =553+54+36+519 -> 1162 | AL53: =Q53 -> 1136.8275 | AM53: =R53 -> 977.97848 | AN53: =S53 -> 1068.7323 | AO53: =T53 -> 1272.0399 | AP53: =U53 -> 1162
B54: Total Assets | C54: =SUM(C49:C53) -> 12009.214 | D54: =SUM(D49:D53) -> 13746.92 | E54: =SUM(E49:E53) -> 13804.542 | G54: =SUM(G49:G53) -> 11168.415 | H54: =SUM(H49:H53) -> 10984.43 | I54: =SUM(I49:I53) -> 10726.19 | J54: =SUM(J49:J53) -> 12009.214 | K54: =SUM(K49:K53) -> 11586.603 | L54: =SUM(L49:L53) -> 11224.865 | M54: =SUM(M49:M53) -> 12033.329 | N54: =SUM(N49:N53) -> 13746.92 | ... U54: =SUM(U49:U53) -> 20782 | W54: =SUM(W49:W53) -> #REF! | X54: =SUM(X49:X53) -> #REF! | Y54: =SUM(Y49:Y53) -> #REF! | Z54: =SUM(Z49:Z53) -> #REF! | AA54: =SUM(AA49:AA53) -> #REF! | AB54: =SUM(AB49:AB53) -> #REF! | AC54: =SUM(AC49:AC53) -> #REF! | AD54: =SUM(AD49:AD53) -> #REF! | ... AP54: =SUM(AP49:AP53) -> 20782 | AR54: =SUM(AP54/AL54)-1 -> 0.34583594
B56: Liabilities
B57: Notes payable and other borrowings | C57: 465.83046 | D57: 323.98098 | E57: 512.97118 | G57: 874.71387 | H57: 1137.0308 | I57: 582.5067 | J57: =C57 -> 465.83046 | K57: 297.28842 | L57: 328.50657 | M57: 285.38506 | N57: =D57 -> 323.98098 | O57: 343.43314 | P57: 534.70785 | Q57: 537.81767 | R57: =E57 -> 512.97118 | S57: 534.25309 | T57: 727.09814 | U57: 2623 | W57: =#REF! -> #REF! | X57: =#REF! -> #REF! | Y57: =#REF! -> #REF! | Z57: =#REF! -> #REF! | AA57: =#REF! -> #REF! | AB57: =#REF! -> #REF! | AC57: =#REF! -> #REF! | AD57: =#REF! -> #REF! | ... AI57: =#REF! -> #REF! | AJ57: =O57 -> 343.43314 | AK57: =P57 -> 534.70785 | AL57: =Q57 -> 537.81767 | AM57: =R57 -> 512.97118 | AN57: =S57 -> 534.25309 | AO57: =T57 -> 727.09814 | AP57: =U57 -> 2623 | AR57: =SUM(AP57/AL57)-1 -> 3.8771176
B58: Consumer deposits | C58: 7660.4992 | D58: 9478.2357 | E58: 9510.222 | G58: 6404.2907 | H58: 6342.9924 | I58: 6375.3098 | J58: =C58 -> 7660.4992 | K58: 7497.5427 | L58: 7155.6965 | M58: 7946.2446 | N58: =D58 -> 9478.2357 | O58: 9890.3677 | P58: 9726.1396 | Q58: 10446.724 | R58: =E58 -> 9510.222 | S58: 10842.854 | T58: 13970.416 | U58: 13972 | AL58: =Q58 -> 10446.724 | AM58: =R58 -> 9510.222 | AN58: =S58 -> 10842.854 | AO58: =T58 -> 13970.416 | AP58: =U58 -> 13972
B59: Payables to merchants | C59: 660.45831 | D59: 857.09602 | E59: 696.16549 | G59: 650.79022 | H59: 608.74286 | I59: 595.20431 | J59: =C59 -> 660.45831 | K59: 725.76548 | L59: 815.37586 | M59: 857.61869 | N59: =D59 -> 857.09602 | O59: 1066.9874 | P59: 1085.7274 | Q59: 926.46989 | R59: =E59 -> 696.16549 | S59: 986.77512 | T59: 1168.3717 | U59: 753 | AL59: =Q59 -> 926.46989 | AM59: =R59 -> 696.16549 | AN59: =S59 -> 986.77512 | AO59: =T59 -> 1168.3717 | AP59: =U59 -> 753
B60: Accounts payable and accrued expenses | C60: 437.24043 | D60: 595.77581 | E60: 572.04812 | G60: 411.53388 | H60: 448.34316 | I60: 364.36255 | J60: =C60 -> 437.24043 | K60: 419.77583 | L60: 448.8751 | M60: 464.29795 | N60: =D60 -> 595.77581 | O60: 575.11981 | P60: 684.9762 | Q60: 835.42854 | R60: =E60 -> 572.04812 | S60: 523.46139 | T60: 546.6542 | U60: 562 | AL60: =Q60 -> 835.42854 | AM60: =R60 -> 572.04812 | AN60: =S60 -> 523.46139 | AO60: =T60 -> 546.6542 | AP60: =U60 -> 562
B61: Other liabilities | C61: 458.27039 | D61: 295.08887 | E61: 255.16567 | G61: 448.83619 | H61: 553.16535 | I61: 554.30832 | J61: =C61 -> 458.27039 | K61: 333.68363 | L61: 308.0914 | M61: 281.87061 | N61: =D61 -> 295.08887 | O61: 279.07436 | P61: 360.81684 | Q61: 344.99726 | R61: =E61 -> 255.16567 | S61: 294.86315 | T61: 266.88418 | U61: =3+249 -> 252 | AL61: =Q61 -> 344.99726 | AM61: =R61 -> 255.16567 | AN61: =S61 -> 294.86315 | AO61: =T61 -> 266.88418 | AP61: =U61 -> 252
B62: Total Liabilities | C62: =SUM(C57:C61) -> 9682.2987 | D62: =SUM(D57:D61) -> 11550.177 | E62: =SUM(E57:E61) -> 11546.573 | G62: =SUM(G57:G61) -> 8790.1649 | H62: =SUM(H57:H61) -> 9090.2746 | I62: =SUM(I57:I61) -> 8471.6917 | J62: =SUM(J57:J61) -> 9682.2987 | K62: =SUM(K57:K61) -> 9274.0561 | L62: =SUM(L57:L61) -> 9056.5454 | M62: =SUM(M57:M61) -> 9835.4169 | N62: =SUM(N57:N61) -> 11550.177 | ... U62: =SUM(U57:U61) -> 18162 | W62: =SUM(W57:W61) -> #REF! | X62: =SUM(X57:X61) -> #REF! | Y62: =SUM(Y57:Y61) -> #REF! | Z62: =SUM(Z57:Z61) -> #REF! | AA62: =SUM(AA57:AA61) -> #REF! | AB62: =SUM(AB57:AB61) -> #REF! | AC62: =SUM(AC57:AC61) -> #REF! | AD62: =SUM(AD57:AD61) -> #REF! | ... AP62: =SUM(AP57:AP61) -> 18162 | AR62: =SUM(AP62/AL62)-1 -> 0.38731902
B64: Share capital | C64: 0 | D64: 0 | J64: =C64 -> 0 | N64: =D64 -> 0 | W64: =#REF! -> #REF! | X64: =#REF! -> #REF! | Y64: =#REF! -> #REF! | Z64: =#REF! -> #REF! | AA64: =#REF! -> #REF! | AB64: =#REF! -> #REF! | AC64: =#REF! -> #REF! | AD64: =#REF! -> #REF! | ... AI64: =#REF! -> #REF! | AJ64: =O64 -> 0 | AK64: =P64 -> 0 | AL64: =Q64 -> 0 | AM64: =R64 -> 0 | AN64: =S64 -> 0 | AO64: =T64 -> 0 | AP64: =U64 -> 0
B65: Additional paid-in capital | C65: 4577 | D65: 4625 | J65: =C65 -> 4577 | N65: =D65 -> 4625 | W65: =#REF! -> #REF! | X65: =#REF! -> #REF! | Y65: =#REF! -> #REF! | Z65: =#REF! -> #REF! | AA65: =#REF! -> #REF! | AB65: =#REF! -> #REF! | AC65: =#REF! -> #REF! | AD65: =#REF! -> #REF! | ... AI65: =#REF! -> #REF! | AJ65: =O65 -> 0 | AK65: =P65 -> 0 | AL65: =Q65 -> 0 | AM65: =R65 -> 0 | AN65: =S65 -> 0 | AO65: =T65 -> 0 | AP65: =U65 -> 0
B66: Other equity instruments | C66: 61 | D66: 37 | J66: =C66 -> 61 | N66: =D66 -> 37 | W66: =#REF! -> #REF! | X66: =#REF! -> #REF! | Y66: =#REF! -> #REF! | Z66: =#REF! -> #REF! | AA66: =#REF! -> #REF! | AB66: =#REF! -> #REF! | AC66: =#REF! -> #REF! | AD66: =#REF! -> #REF! | ... AI66: =#REF! -> #REF! | AJ66: =O66 -> 0 | AK66: =P66 -> 0 | AL66: =Q66 -> 0 | AM66: =R66 -> 0 | AN66: =S66 -> 0 | AO66: =T66 -> 0 | AP66: =U66 -> 0
B67: Reserves | C67: -369 | D67: -311 | J67: =C67 -> -369 | N67: =D67 -> -311 | AL67: =Q67 -> 0 | AM67: =R67 -> 0 | AN67: =S67 -> 0 | AO67: =T67 -> 0 | AP67: =U67 -> 0
B68: Accumulated deficit | C68: -1948 | D68: -2159 | J68: =C68 -> -1948 | N68: =D68 -> -2159 | AL68: =Q68 -> 0 | AM68: =R68 -> 0 | AN68: =S68 -> 0 | AO68: =T68 -> 0 | AP68: =U68 -> 0
B69: Total equity excluding non-controlling interests | C69: =SUM(C64:C68) -> 2321 | D69: =SUM(D64:D68) -> 2192 | E69: 2257.9696 | G69: 2378.2504 | H69: 1894.1558 | I69: 2254.498 | J69: =SUM(J64:J68) -> 2321 | K69: 2312.547 | L69: 2168.3191 | M69: 2197.9121 | N69: =SUM(N64:N68) -> 2192 | O69: 2227.1712 | P69: 2236.8001 | Q69: 2350.2665 | R69: =E69 -> 2257.9696 | S69: 2342.971 | T69: 2509.498 | U69: 2449 | W69: =B69 -> Total equity excluding non-controlling interests | X69: =C69 -> 2321 | Y69: =D69 -> 2192 | Z69: =E69 -> 2257.9696 | AA69: =F69 -> 0 | AB69: =G69 -> 2378.2504 | AC69: =H69 -> 1894.1558 | AD69: =I69 -> 2254.498 | ... AP69: =U69 -> 2449 | AR69: =SUM(AP69/AL69)-1 -> 0.04200948
B71: Non-controlling interests | C71: 6 | D71: 5 | E71: 0 | J71: =C71 -> 6 | N71: =D71 -> 5 | R71: =E71 -> 0 | U71: 171 | W71: =B71 -> Non-controlling interests | X71: =C71 -> 6 | Y71: =D71 -> 5 | Z71: =E71 -> 0 | AA71: =F71 -> 0 | AB71: =G71 -> 0 | AC71: =H71 -> 0 | AD71: =I71 -> 0 | ... AP71: =U71 -> 171
B72: Total equity | C72: =+C71+C69 -> 2327 | D72: =+D71+D69 -> 2197 | E72: =+E71+E69 -> 2257.9696 | G72: =+G71+G69 -> 2378.2504 | H72: =+H71+H69 -> 1894.1558 | I72: =+I71+I69 -> 2254.498 | J72: =+J71+J69 -> 2327 | K72: =+K71+K69 -> 2312.547 | L72: =+L71+L69 -> 2168.3191 | M72: =+M71+M69 -> 2197.9121 | N72: =+N71+N69 -> 2197 | ... U72: =+U71+U69 -> 2620 | AL72: =+AL71+AL69 -> 2350.2665 | AM72: =+AM71+AM69 -> 2257.9696 | AN72: =+AN71+AN69 -> 2342.971 | AO72: =+AO71+AO69 -> 2509.498 | AP72: =+AP71+AP69 -> 2620
B73: Total liabilities and stockholders' equity | C73: =SUM(C72+C62) -> 12009.299 | D73: =SUM(D72+D62) -> 13747.177 | E73: =SUM(E72+E62) -> 13804.542 | G73: =SUM(G72+G62) -> 11168.415 | H73: =SUM(H72+H62) -> 10984.43 | I73: =SUM(I72+I62) -> 10726.19 | J73: =SUM(J72+J62) -> 12009.299 | K73: =SUM(K72+K62) -> 11586.603 | L73: =SUM(L72+L62) -> 11224.865 | M73: =SUM(M72+M62) -> 12033.329 | N73: =SUM(N72+N62) -> 13747.177 | ... U73: =SUM(U72+U62) -> 20782 | W73: =SUM(W72+W62) -> #REF! | X73: =SUM(X72+X62) -> #REF! | Y73: =SUM(Y72+Y62) -> #REF! | Z73: =SUM(Z72+Z62) -> #REF! | AA73: =SUM(AA72+AA62) -> #REF! | AB73: =SUM(AB72+AB62) -> #REF! | AC73: =SUM(AC72+AC62) -> #REF! | AD73: =SUM(AD72+AD62) -> #REF! | ... AP73: =SUM(AP72+AP62) -> 20782 | AR73: =SUM(AP73/AL73)-1 -> 0.34583594
B75: Balance Check | C75: =ROUND(C73-C54,0.1) -> 0 | D75: =ROUND(D73-D54,0.01) -> 0 | E75: =ROUND(E73-E54,0.1) -> 0 | G75: =ROUND(G73-G54,0.1) -> 0 | H75: =ROUND(H73-H54,0.1) -> 0 | I75: =ROUND(I73-I54,0.1) -> 0 | J75: =ROUND(J73-J54,0.1) -> 0 | K75: =ROUND(K73-K54,0.1) -> 0 | L75: =ROUND(L73-L54,0.1) -> 0 | M75: =ROUND(M73-M54,0.1) -> 0 | N75: =ROUND(N73-N54,0.1) -> 0 | ... U75: =ROUND(U73-U54,0.1) -> 0 | W75: =ROUND(W73-W54,0.1) -> #REF! | X75: =ROUND(X73-X54,0.1) -> #REF! | Y75: =ROUND(Y73-Y54,0.1) -> #REF! | Z75: =ROUND(Z73-Z54,0.1) -> #REF! | AA75: =ROUND(AA73-AA54,0.1) -> #REF! | AB75: =ROUND(AB73-AB54,0.1) -> #REF! | AC75: =ROUND(AC73-AC54,0.1) -> #REF! | AD75: =ROUND(AD73-AD54,0.1) -> #REF! | ... AP75: =ROUND(AP73-AP54,0.1) -> 0
A78: X | B78: Cash-Flows Statement | AK78: LTM | AR78: Variance
B79: =B7 -> Fiscal Period | C79: =C7 -> 2022 | D79: =D7 -> 2023 | E79: =E7 -> 2024 | G79: =G7 -> 1Q22 | H79: =H7 -> 2Q22 | I79: =I7 -> 3Q22 | J79: =J7 -> 4Q22 | K79: =K7 -> 1Q23 | L79: =L7 -> 2Q23 | M79: =M7 -> 3Q23 | N79: =N7 -> 4Q23 | ... U79: =U7 -> 3Q25 | W79: =W7 -> #REF! | X79: =X7 -> #REF! | Y79: =Y7 -> #REF! | Z79: =Z7 -> #REF! | AA79: =AA7 -> #REF! | AB79: =AB7 -> #REF! | AC79: =AC7 -> #REF! | AD79: =AD7 -> #REF! | ... AP79: =AP7 -> 3Q25
B80: =B8 -> Fiscal Period End Date | C80: =C8 -> 44926 | D80: =D8 -> 45291 | E80: =E8 -> 45657 | G80: =G8 -> 44651 | H80: =H8 -> 44742 | I80: =I8 -> 44834 | J80: =J8 -> 44926 | K80: =K8 -> 45016 | L80: =L8 -> 45107 | M80: =M8 -> 45199 | N80: =N8 -> 45291 | ... U80: =U8 -> 45930 | W80: =W8 -> #REF! | X80: =X8 -> #REF! | Y80: =Y8 -> #REF! | Z80: =Z8 -> #REF! | AA80: =AA8 -> #REF! | AB80: =AB8 -> #REF! | AC80: =AC8 -> #REF! | AD80: =AD8 -> #REF! | ... AP80: =AP8 -> 45930
B82: Cash-Flows From Operating Activities
B83: Profit (loss) before taxes | C83: -1038.5721 | D83: -303.99809 | E83: 33.132482 | G83: -283.61093 | H83: -382.77908 | I83: -189.48449 | J83: =SUM(C83-SUM(G83:I83)) -> -182.69764 | K83: -98.522226 | L83: -81.560221 | M83: 3.6937226 | N83: =SUM(D83-SUM(K83:M83)) -> -127.60936 | O83: -25.474492 | P83: -2.7472897 | Q83: 14.727664 | R83: =SUM(E83-SUM(O83:Q83)) -> 46.6266 | S83: -92 | T83: -46 | U83: -87 | W83: =SUM(#REF!) -> #REF! | X83: =SUM(#REF!) -> #REF! | Y83: =SUM(#REF!) -> #REF! | Z83: =SUM(#REF!) -> #REF! | AA83: =SUM(#REF!) -> #REF! | AB83: =SUM(#REF!) -> #REF! | AC83: =SUM(#REF!) -> #REF! | AD83: =SUM(#REF!) -> #REF! | ... AI83: =SUM(#REF!) -> #REF! | AJ83: =SUM(O83:O83) -> -25.474492 | AK83: =SUM(O83:P83) -> -28.221782 | AL83: =SUM(O83:Q83) -> -13.494118 | AM83: =SUM(O83:R83) -> 33.132482 | AN83: =SUM(P83:S83) -> -33.393026 | AO83: =SUM(Q83:T83) -> -76.645736 | AP83: =SUM(R83:U83) -> -178.3734 | AR83: =SUM(AP83/AL83)-1 -> 12.218604
B85: Adjustments to reconcile net income:
B86: Income taxes paid | C86: -21 | D86: -11 | E86: -14.932039 | G86: -5.25 | H86: -5.25 | I86: -5.25 | J86: =SUM(C86-SUM(G86:I86)) -> -5.25 | K86: -2.75 | L86: -2.75 | M86: -2.75 | N86: =SUM(D86-SUM(K86:M86)) -> -2.75 | O86: -5.4552931 | P86: -8.1022379 | Q86: -7.8227018 | R86: =SUM(E86-SUM(O86:Q86)) -> 6.448194 | S86: 0 | T86: -36 | U86: -12 | W86: =SUM(#REF!) -> #REF! | X86: =SUM(#REF!) -> #REF! | Y86: =SUM(#REF!) -> #REF! | Z86: =SUM(#REF!) -> #REF! | AA86: =SUM(#REF!) -> #REF! | AB86: =SUM(#REF!) -> #REF! | AC86: =SUM(#REF!) -> #REF! | AD86: =SUM(#REF!) -> #REF! | ... AI86: =SUM(#REF!) -> #REF! | AJ86: =SUM(O86:O86) -> -5.4552931 | AK86: =SUM(O86:P86) -> -13.557531 | AL86: =SUM(O86:Q86) -> -21.380233 | AM86: =SUM(O86:R86) -> -14.932039 | AN86: =SUM(P86:S86) -> -9.4767457 | AO86: =SUM(Q86:T86) -> -37.374508 | AP86: =SUM(R86:U86) -> -41.551806 | AR86: =SUM(AP86/AL86)-1 -> 0.94346837
B87: Depreciation, amortization, and impairment | C87: 161.9695 | D87: 226.06808 | E87: 188.86741 | G87: 29.042361 | H87: 41.805338 | I87: 46.63717 | J87: =SUM(C87-SUM(G87:I87)) -> 44.484636 | K87: 55.639148 | L87: 52.55862 | M87: 40.713393 | N87: =SUM(D87-SUM(K87:M87)) -> 77.15692 | O87: 36.234251 | P87: 37.992838 | Q87: 37.228717 | R87: =SUM(E87-SUM(O87:Q87)) -> 77.4116 | S87: 25.947518 | T87: 51.052482 | U87: 25 | W87: =SUM(#REF!) -> #REF! | X87: =SUM(#REF!) -> #REF! | Y87: =SUM(#REF!) -> #REF! | Z87: =SUM(#REF!) -> #REF! | AA87: =SUM(#REF!) -> #REF! | AB87: =SUM(#REF!) -> #REF! | AC87: =SUM(#REF!) -> #REF! | AD87: =SUM(#REF!) -> #REF! | ... AI87: =SUM(#REF!) -> #REF! | AJ87: =SUM(O87:O87) -> 36.234251 | AK87: =SUM(O87:P87) -> 74.227089 | AL87: =SUM(O87:Q87) -> 111.45581 | AM87: =SUM(O87:R87) -> 188.86741 | AN87: =SUM(P87:S87) -> 178.58067 | AO87: =SUM(Q87:T87) -> 191.64032 | AP87: =SUM(R87:U87) -> 179.4116 | AR87: =SUM(AP87/AL87)-1 -> 0.60971067
B88: Adjustments for share-based payments and RSU costs | C88: 56.31 | D88: 42.596111 | E88: 91.940168 | G88: 18.302156 | H88: 16.410189 | I88: 8.6047789 | J88: =SUM(C88-SUM(G88:I88)) -> 12.992877 | K88: 9.8012168 | L88: 12.632712 | M88: 8.761261 | N88: =SUM(D88-SUM(K88:M88)) -> 11.400921 | O88: 5.4089237 | P88: 8.882642 | Q88: 20.142968 | R88: =SUM(E88-SUM(O88:Q88)) -> 57.505634 | S88: 58.543701 | T88: 26.456299 | U88: 39 | AL88: =SUM(O88:Q88) -> 34.434534 | AM88: =SUM(O88:R88) -> 91.940168 | AN88: =SUM(P88:S88) -> 145.07495 | AO88: =SUM(Q88:T88) -> 162.6486 | AP88: =SUM(R88:U88) -> 181.50563
B89: Provisions for credit losses | C89: 709.54797 | D89: 505.87676 | E89: 671.46971 | G89: 162.36697 | H89: 206.50799 | I89: 173.14917 | J89: =SUM(C89-SUM(G89:I89)) -> 167.52383 | K89: 108.79503 | L89: 122.90964 | M89: 102.56344 | N89: =SUM(D89-SUM(K89:M89)) -> 171.60865 | O89: 159.97943 | P89: 146.59504 | Q89: 161.25725 | R89: =SUM(E89-SUM(O89:Q89)) -> 203.63798 | S89: 178.2891 | T89: 219.7109 | U89: 278 | AL89: =SUM(O89:Q89) -> 467.83173 | AM89: =SUM(O89:R89) -> 671.46971 | AN89: =SUM(P89:S89) -> 689.77938 | AO89: =SUM(Q89:T89) -> 762.89524 | AP89: =SUM(R89:U89) -> 879.63798
B90: Net gain from divestment | C90: 0 | D90: 0 | E90: -190 | G90: 0 | H90: 0 | I90: 0 | J90: =SUM(C90-SUM(G90:I90)) -> 0 | K90: 0 | L90: 0 | M90: 0 | N90: =SUM(D90-SUM(K90:M90)) -> 0 | O90: 0 | P90: 0 | Q90: 0 | R90: =SUM(E90-SUM(O90:Q90)) -> -190 | S90: 0 | T90: 0 | U90: 0 | AL90: =SUM(O90:Q90) -> 0 | AM90: =SUM(O90:R90) -> -190 | AN90: =SUM(P90:S90) -> -190 | AO90: =SUM(Q90:T90) -> -190 | AP90: =SUM(R90:U90) -> -190
B91: Net losses from divestment of shares in equity investments | C91: -0.12882616 | D91: 0 | E91: 7.749081 | G91: 0 | H91: 0 | I91: -0.08138382 | J91: =SUM(C91-SUM(G91:I91)) -> -0.04744234 | K91: 0 | L91: 0 | M91: 0 | N91: =SUM(D91-SUM(K91:M91)) -> 0 | O91: 0 | P91: 0 | Q91: -2.7450373 | R91: =SUM(E91-SUM(O91:Q91)) -> 10.494118 | S91: 3.051823 | T91: -3.051823 | U91: 0 | AL91: =SUM(O91:Q91) -> -2.7450373 | AM91: =SUM(O91:R91) -> 7.749081 | AN91: =SUM(P91:S91) -> 10.800904 | AO91: =SUM(Q91:T91) -> 7.749081 | AP91: =SUM(R91:U91) -> 10.494118
B92: Financial items, net | C92: 380 | D92: -19 | E92: -35.565138 | G92: 95 | H92: 95 | I92: 95 | J92: =SUM(C92-SUM(G92:I92)) -> 95 | K92: -4.75 | L92: -4.75 | M92: -4.75 | N92: =SUM(D92-SUM(K92:M92)) -> -4.75 | O92: -31.334342 | P92: 11.930985 | Q92: -14.131459 | R92: =SUM(E92-SUM(O92:Q92)) -> -2.0303223 | S92: -15.984592 | T92: -34.015408 | U92: -36 | AL92: =SUM(O92:Q92) -> -33.534816 | AM92: =SUM(O92:R92) -> -35.565138 | AN92: =SUM(P92:S92) -> -20.215388 | AO92: =SUM(Q92:T92) -> -66.161781 | AP92: =SUM(R92:U92) -> -88.030322
B93: Changes in assets and liabilities: | AL93: =SUM(O93:Q93) -> 0 | AM93: =SUM(O93:R93) -> 0 | AN93: =SUM(P93:S93) -> 0 | AO93: =SUM(Q93:T93) -> 0 | AP93: =SUM(R93:U93) -> 0
B94: Change in consumer receivables, net | C94: -1677.1251 | D94: -1552.4919 | E94: -1372.5631 | G94: -170.64883 | H94: -797.63789 | I94: 176.89243 | J94: =SUM(C94-SUM(G94:I94)) -> -885.73078 | K94: 456.30333 | L94: -1003.88 | M94: 20.448281 | N94: =SUM(D94-SUM(K94:M94)) -> -1025.3635 | O94: 18.062416 | P94: -568.44754 | Q94: -376.7922 | R94: =SUM(E94-SUM(O94:Q94)) -> -445.38577 | S94: 300 | T94: -1785 | U94: -477 | W94: =SUM(#REF!) -> #REF! | X94: =SUM(#REF!) -> #REF! | Y94: =SUM(#REF!) -> #REF! | Z94: =SUM(#REF!) -> #REF! | AA94: =SUM(#REF!) -> #REF! | AB94: =SUM(#REF!) -> #REF! | AC94: =SUM(#REF!) -> #REF! | AD94: =SUM(#REF!) -> #REF! | ... AI94: =SUM(#REF!) -> #REF! | AJ94: =SUM(O94:O94) -> 18.062416 | AK94: =SUM(O94:P94) -> -550.38512 | AL94: =SUM(O94:Q94) -> -927.17732 | AM94: =SUM(O94:R94) -> -1372.5631 | AN94: =SUM(P94:S94) -> -1090.6255 | AO94: =SUM(Q94:T94) -> -2307.178 | AP94: =SUM(R94:U94) -> -2407.3858 | AR94: =SUM(AP94/AL94)-1 -> 1.5964675
B95: Change in settlement and trade receivables | C95: -83.5 | D95: -171.78315 | E95: 196.59958 | G95: 43.425266 | H95: -36.729096 | I95: -17.425468 | J95: =SUM(C95-SUM(G95:I95)) -> -72.770703 | K95: 233.38157 | L95: -99.815303 | M95: -17.482313 | N95: =SUM(D95-SUM(K95:M95)) -> -287.8671 | O95: 90.90833 | P95: -46.397626 | Q95: 121.87553 | R95: =SUM(E95-SUM(O95:Q95)) -> 30.213342 | S95: 8.334692 | T95: -186.33469 | U95: 146 | W95: =SUM(#REF!) -> #REF! | X95: =SUM(#REF!) -> #REF! | Y95: =SUM(#REF!) -> #REF! | Z95: =SUM(#REF!) -> #REF! | AA95: =SUM(#REF!) -> #REF! | AB95: =SUM(#REF!) -> #REF! | AC95: =SUM(#REF!) -> #REF! | AD95: =SUM(#REF!) -> #REF! | ... AI95: =SUM(#REF!) -> #REF! | AJ95: =SUM(O95:O95) -> 90.90833 | AK95: =SUM(O95:P95) -> 44.510704 | AL95: =SUM(O95:Q95) -> 166.38623 | AM95: =SUM(O95:R95) -> 196.59958 | AN95: =SUM(P95:S95) -> 114.02594 | AO95: =SUM(Q95:T95) -> -25.911127 | AP95: =SUM(R95:U95) -> -1.786658 | AR95: =SUM(AP95/AL95)-1 -> -1.010738
B96: Change in notes payable and other borrowings | C96: 180.8 | D96: -115.49867 | E96: -16.197744 | G96: 25.028661 | H96: 353.2632 | I96: -315.74206 | J96: =SUM(C96-SUM(G96:I96)) -> 118.2502 | K96: -167.40888 | L96: -0.98162514 | M96: 4.6695831 | N96: =SUM(D96-SUM(K96:M96)) -> 48.222252 | O96: 13.591672 | P96: -0.29105 | Q96: -29.752866 | R96: =SUM(E96-SUM(O96:Q96)) -> 0.2545003 | S96: -26.784466 | T96: 35.784466 | U96: 1258 | W96: =SUM(#REF!) -> #REF! | X96: =SUM(#REF!) -> #REF! | Y96: =SUM(#REF!) -> #REF! | Z96: =SUM(#REF!) -> #REF! | AA96: =SUM(#REF!) -> #REF! | AB96: =SUM(#REF!) -> #REF! | AC96: =SUM(#REF!) -> #REF! | AD96: =SUM(#REF!) -> #REF! | ... AI96: =SUM(#REF!) -> #REF! | AJ96: =SUM(O96:O96) -> 13.591672 | AK96: =SUM(O96:P96) -> 13.300622 | AL96: =SUM(O96:Q96) -> -16.452244 | AM96: =SUM(O96:R96) -> -16.197744 | AN96: =SUM(P96:S96) -> -56.573882 | AO96: =SUM(Q96:T96) -> -20.498366 | AP96: =SUM(R96:U96) -> 1267.2545 | AR96: =SUM(AP96/AL96)-1 -> -78.026239
B97: Change in consumer deposits | C97: 2084.41 | D97: 1515.7342 | E97: 820.25117 | G97: 159.93526 | H97: 580.4353 | I97: 550.96549 | J97: =SUM(C97-SUM(G97:I97)) -> 793.07395 | K97: -207.25385 | L97: -63.17709 | M97: 856.53245 | N97: =SUM(D97-SUM(K97:M97)) -> 929.63271 | O97: 882.8224 | P97: -186.95904 | Q97: 247.64174 | R97: =SUM(E97-SUM(O97:Q97)) -> -123.25394 | S97: 694 | T97: 2461 | U97: 34 | W97: =SUM(#REF!) -> #REF! | X97: =SUM(#REF!) -> #REF! | Y97: =SUM(#REF!) -> #REF! | Z97: =SUM(#REF!) -> #REF! | AA97: =SUM(#REF!) -> #REF! | AB97: =SUM(#REF!) -> #REF! | AC97: =SUM(#REF!) -> #REF! | AD97: =SUM(#REF!) -> #REF! | ... AI97: =SUM(#REF!) -> #REF! | AJ97: =SUM(O97:O97) -> 882.8224 | AK97: =SUM(O97:P97) -> 695.86337 | AL97: =SUM(O97:Q97) -> 943.50511 | AM97: =SUM(O97:R97) -> 820.25117 | AN97: =SUM(P97:S97) -> 631.42877 | AO97: =SUM(Q97:T97) -> 3279.3878 | AP97: =SUM(R97:U97) -> 3065.7461 | AR97: =SUM(AP97/AL97)-1 -> 2.2493158
B98: Change in other assets and liabilities, net | C98: -417.12 | D98: 690.29185 | E98: 207.11761 | G98: -531.85094 | H98: 172.01455 | I98: -210.81997 | J98: =SUM(C98-SUM(G98:I98)) -> 153.53635 | K98: 101.9702 | L98: 241.5706 | M98: 158.4123 | N98: =SUM(D98-SUM(K98:M98)) -> 188.33875 | O98: 30.342347 | P98: 258.00029 | Q98: 55.492149 | R98: =SUM(E98-SUM(O98:Q98)) -> -136.71717 | S98: -575.01349 | T98: 918.01349 | U98: -1462 | W98: =SUM(#REF!) -> #REF! | X98: =SUM(#REF!) -> #REF! | Y98: =SUM(#REF!) -> #REF! | Z98: =SUM(#REF!) -> #REF! | AA98: =SUM(#REF!) -> #REF! | AB98: =SUM(#REF!) -> #REF! | AC98: =SUM(#REF!) -> #REF! | AD98: =SUM(#REF!) -> #REF! | ... AI98: =SUM(#REF!) -> #REF! | AJ98: =SUM(O98:O98) -> 30.342347 | AK98: =SUM(O98:P98) -> 288.34263 | AL98: =SUM(O98:Q98) -> 343.83478 | AM98: =SUM(O98:R98) -> 207.11761 | AN98: =SUM(P98:S98) -> -398.23823 | AO98: =SUM(Q98:T98) -> 261.77498 | AP98: =SUM(R98:U98) -> -1255.7172 | AR98: =SUM(AP98/AL98)-1 -> -4.6520947
B99: Net cash used in operating activities | C99: =SUM(C83:C98) -> 335.59144 | D99: =SUM(D83:D98) -> 806.79523 | E99: =SUM(E83:E98) -> 587.86919 | G99: =SUM(G83:G98) -> -458.26002 | H99: =SUM(H83:H98) -> 243.0405 | I99: =SUM(I83:I98) -> 312.44568 | J99: =SUM(J83:J98) -> 238.36528 | K99: =SUM(K83:K98) -> 485.20553 | L99: =SUM(L83:L98) -> -827.24265 | M99: =SUM(M83:M98) -> 1170.8121 | N99: =SUM(N83:N98) -> -21.979766 | ... U99: =SUM(U83:U98) -> -294 | W99: =SUM(W83:W98) -> #REF! | X99: =SUM(X83:X98) -> #REF! | Y99: =SUM(Y83:Y98) -> #REF! | Z99: =SUM(Z83:Z98) -> #REF! | AA99: =SUM(AA83:AA98) -> #REF! | AB99: =SUM(AB83:AB98) -> #REF! | AC99: =SUM(AC83:AC98) -> #REF! | AD99: =SUM(AD83:AD98) -> #REF! | ... AP99: =SUM(AP83:AP98) -> 1421.2048 | AR99: =SUM(AP99/AL99)-1 -> 0.3501024
B101: Cash flows from investing activities:
B102: Investment in intangible assets | C102: -93.804987 | D102: -83.883577 | E102: -44.220937 | G102: -16.115202 | H102: -23.099543 | I102: -24.864189 | J102: =SUM(C102-SUM(G102:I102)) -> -29.726053 | K102: -23.983099 | L102: -22.294403 | M102: -21.919426 | N102: =SUM(D102-SUM(K102:M102)) -> -15.686649 | O102: -10.595325 | P102: -12.890727 | Q102: -12.662766 | R102: =SUM(E102-SUM(O102:Q102)) -> -8.072119 | S102: -6.344298 | T102: -6.667381 | U102: -7.988321 | W102: =SUM(#REF!) -> #REF! | X102: =SUM(#REF!) -> #REF! | Y102: =SUM(#REF!) -> #REF! | Z102: =SUM(#REF!) -> #REF! | AA102: =SUM(#REF!) -> #REF! | AB102: =SUM(#REF!) -> #REF! | AC102: =SUM(#REF!) -> #REF! | AD102: =SUM(#REF!) -> #REF! | ... AI102: =SUM(#REF!) -> #REF! | AJ102: =SUM(O102:O102) -> -10.595325 | AK102: =SUM(O102:P102) -> -23.486052 | AL102: =SUM(O102:Q102) -> -36.148818 | AM102: =SUM(O102:R102) -> -44.220937 | AN102: =SUM(P102:S102) -> -39.969909 | AO102: =SUM(Q102:T102) -> -33.746564 | AP102: =SUM(R102:U102) -> -29.072119 | AR102: =SUM(AP102/AL102)-1 -> -0.1957657
B103: Investment in tangible assets | C103: -11.7484 | D103: -0.62023605 | E103: -0.97468662 | G103: -4.0814049 | H103: -6.1376978 | I103: -3.9623526 | J103: =SUM(C103-SUM(G103:I103)) -> 2.4330549 | K103: -1.1736541 | L103: 0.74769386 | M103: -0.08535594 | N103: =SUM(D103-SUM(K103:M103)) -> -0.10891986 | O103: -0.01017104 | P103: -0.04842063 | Q103: -0.05019635 | R103: =SUM(E103-SUM(O103:Q103)) -> -0.8658986 | S103: -0.585361 | T103: -0.265028 | U103: -0.149611 | AL103: =SUM(O103:Q103) -> -0.10878802 | AM103: =SUM(O103:R103) -> -0.97468662 | AN103: =SUM(P103:S103) -> -1.5498766 | AO103: =SUM(Q103:T103) -> -1.766484 | AP103: =SUM(R103:U103) -> -1.8658986 | AR103: =SUM(AP103/AL103)-1 -> 16.151692
B104: Other cash flow from investment activities | C104: -354 | D104: 1 | E104: 198.71762 | G104: 0 | H104: -354 | I104: 0 | J104: =SUM(C104-SUM(G104:I104)) -> 0 | K104: 0 | L104: 1 | M104: 0 | N104: =SUM(D104-SUM(K104:M104)) -> 0 | O104: 0 | P104: 0 | Q104: 21.717624 | R104: =SUM(E104-SUM(O104:Q104)) -> 177 | AL104: =SUM(O104:Q104) -> 21.717624 | AM104: =SUM(O104:R104) -> 198.71762 | AN104: =SUM(P104:S104) -> 198.71762 | AO104: =SUM(Q104:T104) -> 198.71762 | AP104: =SUM(R104:U104) -> 177 | AR104: =SUM(AP104/AL104)-1 -> 7.1500627
B105: Net cash used in investing activities | C105: =SUM(C102:C104) -> -459.55339 | D105: =SUM(D102:D104) -> -83.503813 | E105: =SUM(E102:E104) -> 153.522 | G105: =SUM(G102:G104) -> -20.196607 | H105: =SUM(H102:H104) -> -383.23724 | I105: =SUM(I102:I104) -> -28.826542 | J105: =SUM(J102:J104) -> -27.292998 | K105: =SUM(K102:K104) -> -25.156753 | L105: =SUM(L102:L104) -> -20.546709 | M105: =SUM(M102:M104) -> -22.004782 | N105: =SUM(N102:N104) -> -15.795569 | ... U105: =SUM(U102:U104) -> -8.137932 | W105: =SUM(W102:W104) -> #REF! | X105: =SUM(X102:X104) -> #REF! | Y105: =SUM(Y102:Y104) -> #REF! | Z105: =SUM(Z102:Z104) -> #REF! | AA105: =SUM(AA102:AA104) -> #REF! | AB105: =SUM(AB102:AB104) -> #REF! | AC105: =SUM(AC102:AC104) -> #REF! | AD105: =SUM(AD102:AD104) -> #REF! | ... AP105: =SUM(AP102:AP104) -> 146.06198 | AR105: =SUM(AP105/AL105)-1 -> -11.045541
B107: Cash flows from financing activities: | W107: =SUM(#REF!) -> #REF! | X107: =SUM(#REF!) -> #REF! | Y107: =SUM(#REF!) -> #REF! | Z107: =SUM(#REF!) -> #REF! | AA107: =SUM(#REF!) -> #REF! | AB107: =SUM(#REF!) -> #REF! | AC107: =SUM(#REF!) -> #REF! | AD107: =SUM(#REF!) -> #REF! | ... AI107: =SUM(#REF!) -> #REF! | AJ107: =SUM(O107:O107) -> 0 | AK107: =SUM(O107:P107) -> 0 | AL107: =SUM(O107:Q107) -> 0 | AM107: =SUM(O107:R107) -> 0 | AN107: =SUM(P107:S107) -> 0 | AO107: =SUM(Q107:T107) -> 0 | AP107: =SUM(R107:U107) -> 0 | AR107: =SUM(AP107/AL107)-1 -> #DIV/0!
B108: New share issue | C108: 799 | D108: 39 | E108: 0 | G108: 0 | H108: 0 | I108: 740.8851 | J108: =SUM(C108-SUM(G108:I108)) -> 58.114898 | K108: 4.567208 | L108: 0.36564527 | M108: 32.2458 | N108: =SUM(D108-SUM(K108:M108)) -> 1.8213465 | O108: 0 | P108: 0 | Q108: 0 | R108: =SUM(E108-SUM(O108:Q108)) -> 0 | S108: 0 | T108: 0 | U108: 192 | W108: =SUM(#REF!) -> #REF! | X108: =SUM(#REF!) -> #REF! | Y108: =SUM(#REF!) -> #REF! | Z108: =SUM(#REF!) -> #REF! | AA108: =SUM(#REF!) -> #REF! | AB108: =SUM(#REF!) -> #REF! | AC108: =SUM(#REF!) -> #REF! | AD108: =SUM(#REF!) -> #REF! | ... AI108: =SUM(#REF!) -> #REF! | AJ108: =SUM(O108:O108) -> 0 | AK108: =SUM(O108:P108) -> 0 | AL108: =SUM(O108:Q108) -> 0 | AM108: =SUM(O108:R108) -> 0 | AN108: =SUM(P108:S108) -> 0 | AO108: =SUM(Q108:T108) -> 0 | AP108: =SUM(R108:U108) -> 192 | AR108: =SUM(AP108/AL108)-1 -> #DIV/0!
B109: Share warrants | C109: 0 | D109: 1 | E109: 0.4980723 | G109: 0 | H109: 0 | I109: 0 | J109: =SUM(C109-SUM(G109:I109)) -> 0 | K109: 0 | L109: 0 | M109: 1 | N109: =SUM(D109-SUM(K109:M109)) -> 0 | O109: 0 | P109: 0.548745 | Q109: -0.014562865 | R109: =SUM(E109-SUM(O109:Q109)) -> -0.03610983 | S109: -0.104197 | T109: -0.037451 | U109: 0.141648 | W109: =SUM(#REF!) -> #REF! | X109: =SUM(#REF!) -> #REF! | Y109: =SUM(#REF!) -> #REF! | Z109: =SUM(#REF!) -> #REF! | AA109: =SUM(#REF!) -> #REF! | AB109: =SUM(#REF!) -> #REF! | AC109: =SUM(#REF!) -> #REF! | AD109: =SUM(#REF!) -> #REF! | ... AI109: =SUM(#REF!) -> #REF! | AJ109: =SUM(O109:O109) -> 0 | AK109: =SUM(O109:P109) -> 0.548745 | AL109: =SUM(O109:Q109) -> 0.53418213 | AM109: =SUM(O109:R109) -> 0.4980723 | AN109: =SUM(P109:S109) -> 0.3938753 | AO109: =SUM(Q109:T109) -> -0.1923207 | AP109: =SUM(R109:U109) -> -0.03610983 | AR109: =SUM(AP109/AL109)-1 -> -1.0675983
B110: Other equity instruments issues and redeemed (AT1) | C110: 2.5700588 | D110: -24 | E110: 141.77661 | G110: 27.282163 | H110: -24.712104 | I110: 0 | J110: =SUM(C110-SUM(G110:I110)) -> 0 | K110: 0 | L110: -24 | M110: 0 | N110: =SUM(D110-SUM(K110:M110)) -> 0 | O110: 144.37945 | P110: -2.172236 | Q110: 0.4739137 | R110: =SUM(E110-SUM(O110:Q110)) -> -0.9045154 | S110: 0 | T110: 0 | U110: 0 | AL110: =SUM(O110:Q110) -> 142.68113 | AM110: =SUM(O110:R110) -> 141.77661 | AN110: =SUM(P110:S110) -> -2.6028377 | AO110: =SUM(Q110:T110) -> -0.4306017 | AP110: =SUM(R110:U110) -> -0.9045154
B111: Convertible promissory notes | C111: 9 | D111: -32.268166 | E111: 0 | G111: 0 | H111: 9 | I111: 0 | J111: =SUM(C111-SUM(G111:I111)) -> 0 | K111: 0 | L111: 0 | M111: -32.268166 | N111: =SUM(D111-SUM(K111:M111)) -> 0 | O111: 0 | P111: 0 | Q111: 0 | R111: =SUM(E111-SUM(O111:Q111)) -> 0 | S111: 0 | T111: 0 | U111: 0 | AL111: =SUM(O111:Q111) -> 0 | AM111: =SUM(O111:R111) -> 0 | AN111: =SUM(P111:S111) -> 0 | AO111: =SUM(Q111:T111) -> 0 | AP111: =SUM(R111:U111) -> 0
B112: Subordinated debt | C112: 0 | D112: 42 | E112: 100 | G112: 0 | H112: 0 | I112: 0 | J112: =SUM(C112-SUM(G112:I112)) -> 0 | K112: 0 | L112: 50 | M112: -8 | N112: =SUM(D112-SUM(K112:M112)) -> 0 | O112: 27.627291 | P112: 72.372078 | Q112: 0 | R112: =SUM(E112-SUM(O112:Q112)) -> 0.000631 | S112: 0 | T112: 0 | U112: 0 | AL112: =SUM(O112:Q112) -> 99.999369 | AM112: =SUM(O112:R112) -> 100 | AN112: =SUM(P112:S112) -> 72.372709 | AO112: =SUM(Q112:T112) -> 0.000631 | AP112: =SUM(R112:U112) -> 0.000631
B113: Notes payable and other borrowings issued | C113: -756 | D113: -46 | E113: 94.790227 | G113: -285.12033 | H113: -61.72291 | I113: -298.02303 | J113: =SUM(C113-SUM(G113:I113)) -> -111.13373 | K113: -2.1920347 | L113: -40.341926 | M113: -3.3932461 | N113: =SUM(D113-SUM(K113:M113)) -> -0.072793047 | O113: 0 | P113: 101.04674 | Q113: 30.233915 | R113: =SUM(E113-SUM(O113:Q113)) -> -36.490428 | S113: 30 | T113: 167 | U113: 644 | AL113: =SUM(O113:Q113) -> 131.28065 | AM113: =SUM(O113:R113) -> 94.790227 | AN113: =SUM(P113:S113) -> 124.79023 | AO113: =SUM(Q113:T113) -> 190.74349 | AP113: =SUM(R113:U113) -> 804.50957
B114: Notes payable and other borrowings redeemed | C114: 0 | D114: 0 | E114: 0 | G114: 0 | H114: 0 | I114: 0 | J114: =SUM(C114-SUM(G114:I114)) -> 0 | K114: 0 | L114: 0 | M114: 0 | N114: =SUM(D114-SUM(K114:M114)) -> 0 | O114: 0 | P114: 0 | Q114: 0 | R114: =SUM(E114-SUM(O114:Q114)) -> 0 | S114: -15 | T114: -15 | U114: -26 | AL114: =SUM(O114:Q114) -> 0 | AM114: =SUM(O114:R114) -> 0 | AN114: =SUM(P114:S114) -> -15 | AO114: =SUM(Q114:T114) -> -30 | AP114: =SUM(R114:U114) -> -56
B115: Change in non-controlling interests | C115: -2.6134101 | D115: 0 | E115: 0 | G115: 0 | H115: -2.6134101 | I115: 0 | J115: =SUM(C115-SUM(G115:I115)) -> 0 | K115: 0 | L115: 0 | M115: 0 | N115: =SUM(D115-SUM(K115:M115)) -> 0 | O115: 0 | P115: 0 | Q115: 0 | R115: =SUM(E115-SUM(O115:Q115)) -> 0 | S115: 0 | T115: 0 | U115: 0 | AL115: =SUM(O115:Q115) -> 0 | AM115: =SUM(O115:R115) -> 0 | AN115: =SUM(P115:S115) -> 0 | AO115: =SUM(Q115:T115) -> 0 | AP115: =SUM(R115:U115) -> 0
B116: Principal payments under operating lease obligations | C116: -35 | D116: -42 | E116: -25.082499 | G116: -8.75 | H116: -8.75 | I116: -8.75 | J116: =SUM(C116-SUM(G116:I116)) -> -8.75 | K116: -10.5 | L116: -10.5 | M116: -10.5 | N116: =SUM(D116-SUM(K116:M116)) -> -10.5 | O116: -9.025585 | P116: -10.936726 | Q116: -3.4157649 | R116: =SUM(E116-SUM(O116:Q116)) -> -1.7044229 | S116: -6.313865 | T116: -6.319011 | U116: -1.367124 | W116: =SUM(#REF!) -> #REF! | X116: =SUM(#REF!) -> #REF! | Y116: =SUM(#REF!) -> #REF! | Z116: =SUM(#REF!) -> #REF! | AA116: =SUM(#REF!) -> #REF! | AB116: =SUM(#REF!) -> #REF! | AC116: =SUM(#REF!) -> #REF! | AD116: =SUM(#REF!) -> #REF! | ... AI116: =SUM(#REF!) -> #REF! | AJ116: =SUM(O116:O116) -> -9.025585 | AK116: =SUM(O116:P116) -> -19.962311 | AL116: =SUM(O116:Q116) -> -23.378076 | AM116: =SUM(O116:R116) -> -25.082499 | AN116: =SUM(P116:S116) -> -22.370779 | AO116: =SUM(Q116:T116) -> -17.753064 | AP116: =SUM(R116:U116) -> -15.704423 | AR116: =SUM(AP116/AL116)-1 -> -0.32824143
B117: Net cash provided by financing activities | C117: =SUM(C108:C116) -> 16.956649 | D117: =SUM(D108:D116) -> -62.268166 | E117: =SUM(E108:E116) -> 311.98241 | G117: =SUM(G108:G116) -> -266.58817 | H117: =SUM(H108:H116) -> -88.798424 | I117: =SUM(I108:I116) -> 434.11207 | J117: =SUM(J108:J116) -> -61.768831 | K117: =SUM(K108:K116) -> -8.1248268 | L117: =SUM(L108:L116) -> -24.476281 | M117: =SUM(M108:M116) -> -20.915612 | N117: =SUM(N108:N116) -> -8.7514465 | ... U117: =SUM(U108:U116) -> 808.77452 | W117: =SUM(W108:W116) -> #REF! | X117: =SUM(X108:X116) -> #REF! | Y117: =SUM(Y108:Y116) -> #REF! | Z117: =SUM(Z108:Z116) -> #REF! | AA117: =SUM(AA108:AA116) -> #REF! | AB117: =SUM(AB108:AB116) -> #REF! | AC117: =SUM(AC108:AC116) -> #REF! | AD117: =SUM(AD108:AD116) -> #REF! | ... AP117: =SUM(AP108:AP116) -> 923.86516 | AR117: =SUM(AP117/AL117)-1 -> 1.6312154
B120: Unrestricted Cash BOP | C120: 2071.4704 | D120: =C126 -> 1694.2697 | E120: =D126 -> 2390.1256 | G120: 2071.4704 | H120: =G126 -> 1253.2419 | I120: =H126 -> 907.76546 | J120: =I126 -> 1545.2618 | K120: =J126 -> 1694.2697 | L120: =K126 -> 2162.6126 | M120: =L126 -> 1264.0786 | N120: =M126 -> 2344.4454 | O120: =N126 -> 2390.1256 | ... U120: =T126 -> 6150.2222 | W120: =#REF! -> #REF! | X120: =#REF! -> #REF! | Y120: =#REF! -> #REF! | Z120: =#REF! -> #REF! | AA120: =#REF! -> #REF! | AB120: =#REF! -> #REF! | AC120: =#REF! -> #REF! | AD120: =#REF! -> #REF! | ... AM120: =#REF! -> #REF! | AN120: =O126 -> 3628.2869 | AO120: =P126 -> 3418.3369 | AP120: =Q126 -> 3843.0304
B121: BOP FX Adjustment | C121: 0 | D121: 0 | E121: 0 | G121: 0 | H121: 0 | I121: 0 | J121: 0 | K121: 0 | L121: 0 | M121: 0 | N121: 0 | O121: 0 | P121: 0 | Q121: 0 | R121: =SUM(E121-SUM(O121:Q121)) -> 0 | S121: 0 | T121: 0 | U121: 0 | W121: =SUM(#REF!) -> #REF! | X121: =SUM(#REF!) -> #REF! | Y121: =SUM(#REF!) -> #REF! | Z121: =SUM(#REF!) -> #REF! | AA121: =SUM(#REF!) -> #REF! | AB121: =SUM(#REF!) -> #REF! | AC121: =SUM(#REF!) -> #REF! | AD121: =SUM(#REF!) -> #REF! | ... AI121: =SUM(#REF!) -> #REF! | AJ121: =SUM(O121:O121) -> 0 | AK121: =SUM(O121:P121) -> 0 | AL121: =SUM(O121:Q121) -> 0 | AM121: =SUM(O121:R121) -> 0 | AN121: =SUM(P121:S121) -> 0 | AO121: =SUM(Q121:T121) -> 0 | AP121: =SUM(R121:U121) -> 0
B122: Adjusted Cash Position BOP | C122: =SUM(C120:C121) -> 2071.4704 | D122: =SUM(D120:D121) -> 1694.2697 | E122: =SUM(E120:E121) -> 2390.1256 | G122: =SUM(G120:G121) -> 2071.4704 | H122: =SUM(H120:H121) -> 1253.2419 | I122: =SUM(I120:I121) -> 907.76546 | J122: =SUM(J120:J121) -> 1545.2618 | K122: =SUM(K120:K121) -> 1694.2697 | L122: =SUM(L120:L121) -> 2162.6126 | M122: =SUM(M120:M121) -> 1264.0786 | N122: =SUM(N120:N121) -> 2344.4454 | ... U122: =SUM(U120:U121) -> 6150.2222 | W122: =SUM(W120:W121) -> #REF! | X122: =SUM(X120:X121) -> #REF! | Y122: =SUM(Y120:Y121) -> #REF! | Z122: =SUM(Z120:Z121) -> #REF! | AA122: =SUM(AA120:AA121) -> #REF! | AB122: =SUM(AB120:AB121) -> #REF! | AC122: =SUM(AC120:AC121) -> #REF! | AD122: =SUM(AD120:AD121) -> #REF! | ... AP122: =SUM(AP120:AP121) -> 3843.0304
B124: EOP FX Adjustment | C124: -270.19542 | D124: 34.832695 | E124: -200.85672 | G124: -73.183697 | H124: -116.48126 | I124: -80.234851 | J124: =SUM(C124-SUM(G124:I124)) -> -0.29561342 | K124: 16.41898 | L124: -26.268321 | M124: -47.524942 | N124: =SUM(D124-SUM(K124:M124)) -> 92.206979 | O124: -89.3 | P124: -8.326474 | Q124: 161.28961 | R124: =SUM(E124-SUM(O124:Q124)) -> -264.51985 | S124: 252.56087 | T124: 334.65542 | U124: 17.783716 | W124: =SUM(#REF!) -> #REF! | X124: =SUM(#REF!) -> #REF! | Y124: =SUM(#REF!) -> #REF! | Z124: =SUM(#REF!) -> #REF! | AA124: =SUM(#REF!) -> #REF! | AB124: =SUM(#REF!) -> #REF! | AC124: =SUM(#REF!) -> #REF! | AD124: =SUM(#REF!) -> #REF! | ... AI124: =SUM(#REF!) -> #REF! | AJ124: =SUM(O124:O124) -> -89.3 | AK124: =SUM(O124:P124) -> -97.626474 | AL124: =SUM(O124:Q124) -> 63.663134 | AM124: =SUM(O124:R124) -> -200.85672 | AN124: =SUM(P124:S124) -> 141.00415 | AO124: =SUM(Q124:T124) -> 483.98604 | AP124: =SUM(R124:U124) -> 340.48015
...

Sheet Revenue Drivers
B2: ='Historical Financials'!B2 -> Klarna Group plc (KLAR) | C2: FYE | G2: Quarterly | H2: Quarterly | O2: Quarterly | P2: Quarterly | W2: LTM | AA2: LTM | AC2: LTM | AI2: Variance
B3: Segment Anaysis | C3: ='Historical Financials'!C7 -> 2022 | D3: ='Historical Financials'!D7 -> 2023 | E3: ='Historical Financials'!E7 -> 2024 | G3: ='Historical Financials'!G7 -> 1Q22 | H3: ='Historical Financials'!H7 -> 2Q22 | I3: ='Historical Financials'!I7 -> 3Q22 | J3: ='Historical Financials'!J7 -> 4Q22 | K3: ='Historical Financials'!K7 -> 1Q23 | L3: ='Historical Financials'!L7 -> 2Q23 | M3: ='Historical Financials'!M7 -> 3Q23 | N3: ='Historical Financials'!N7 -> 4Q23 | ... U3: ='Historical Financials'!U7 -> 3Q25 | W3: =#REF! -> #REF! | X3: =#REF! -> #REF! | Y3: =#REF! -> #REF! | Z3: =#REF! -> #REF! | AA3: =O3 -> 1Q24 | AB3: =P3 -> 2Q24 | AC3: =Q3 -> 3Q24 | AD3: =R3 -> 4Q24 | AE3: =S3 -> 1Q25 | AF3: =T3 -> 2Q25 | AG3: =U3 -> 3Q25
B4: $ mm except per share | C4: ='Historical Financials'!C8 -> 44926 | D4: ='Historical Financials'!D8 -> 45291 | E4: ='Historical Financials'!E8 -> 45657 | G4: ='Historical Financials'!G8 -> 44651 | H4: ='Historical Financials'!H8 -> 44742 | I4: ='Historical Financials'!I8 -> 44834 | J4: ='Historical Financials'!J8 -> 44926 | K4: ='Historical Financials'!K8 -> 45016 | L4: ='Historical Financials'!L8 -> 45107 | M4: ='Historical Financials'!M8 -> 45199 | N4: ='Historical Financials'!N8 -> 45291 | ... U4: ='Historical Financials'!U8 -> 45930 | W4: =#REF! -> #REF! | X4: =#REF! -> #REF! | Y4: =#REF! -> #REF! | Z4: =#REF! -> #REF! | AA4: =O4 -> 45382 | AB4: =P4 -> 45473 | AC4: =Q4 -> 45565 | AD4: =R4 -> 45657 | AE4: =S4 -> 45747 | AF4: =T4 -> 45838 | AG4: =U4 -> 45930
A6: X | B6: Offerings Drivers
B8: Disaggregated Revenues
B9: Transaction and service revenue | C9: 1468 | D9: 1768 | E9: 2136 | G9: 344.58814 | H9: 369.20095 | I9: 331.21869 | J9: =SUM(C9-SUM(G9:I9)) -> 422.99222 | K9: 368.13111 | L9: 417.98173 | M9: 440.43433 | N9: =SUM(D9-SUM(K9:M9)) -> 541.45284 | O9: 478.72442 | P9: 512.16003 | Q9: 544.55104 | R9: =SUM(E9-SUM(O9:Q9)) -> 600.56451 | S9: 519.31403 | T9: 603.94886 | U9: 634 | W9: =SUM(#REF!) -> #REF! | X9: =SUM(#REF!) -> #REF! | Y9: =SUM(#REF!) -> #REF! | Z9: =SUM(#REF!) -> #REF! | AA9: =SUM(O9:O9) -> 478.72442 | AB9: =SUM(O9:P9) -> 990.88445 | AC9: =SUM(O9:Q9) -> 1535.4355 | AD9: =SUM(O9:R9) -> 2136 | AE9: =SUM(P9:S9) -> 2176.5896 | AF9: =SUM(Q9:T9) -> 2268.3784 | AG9: =SUM(R9:U9) -> 2357.8274 | AI9: =SUM(AG9/AC9)-1 -> 0.53560825
B10: Interest income | C10: 436 | D10: 508 | E10: 675 | G10: 113.29018 | H10: 114.24219 | I10: 101.88917 | J10: =SUM(C10-SUM(G10:I10)) -> 106.57845 | K10: 116.02312 | L10: 116.09384 | M10: 134.34505 | N10: =SUM(D10-SUM(K10:M10)) -> 141.53799 | O10: 156.60428 | P10: 163.77365 | Q10: 173.80119 | R10: =SUM(E10-SUM(O10:Q10)) -> 180.82088 | S10: 181.82312 | T10: 219.15276 | U10: 269 | AC10: =SUM(O10:Q10) -> 494.17912 | AD10: =SUM(O10:R10) -> 675 | AE10: =SUM(P10:S10) -> 700.21885 | AF10: =SUM(Q10:T10) -> 755.59796 | AG10: =SUM(R10:U10) -> 850.79676 | AI10: =SUM(AG10/AC10)-1 -> 0.72163641
B11: Total Net Revenue | C11: =SUM(C9:C10) -> 1904 | D11: =SUM(D9:D10) -> 2276 | E11: =SUM(E9:E10) -> 2811 | G11: =SUM(G9:G10) -> 457.87832 | H11: =SUM(H9:H10) -> 483.44314 | I11: =SUM(I9:I10) -> 433.10787 | J11: =SUM(J9:J10) -> 529.57067 | K11: =SUM(K9:K10) -> 484.15423 | L11: =SUM(L9:L10) -> 534.07557 | M11: =SUM(M9:M10) -> 574.77938 | N11: =SUM(N9:N10) -> 682.99082 | ... U11: =SUM(U9:U10) -> 903 | W11: =SUM(W9:W10) -> #REF! | X11: =SUM(X9:X10) -> #REF! | Y11: =SUM(Y9:Y10) -> #REF! | Z11: =SUM(Z9:Z10) -> #REF! | AA11: =SUM(AA9:AA10) -> 478.72442 | AB11: =SUM(AB9:AB10) -> 990.88445 | AC11: =SUM(AC9:AC10) -> 2029.6146 | AD11: =SUM(AD9:AD10) -> 2811 | ... AG11: =SUM(AG9:AG10) -> 3208.6242 | AI11: =SUM(AG11/AC11)-1 -> 0.58090317
B12: Variance Check | C12: =+C11-'Historical Financials'!C11 -> 0 | D12: =+D11-'Historical Financials'!D11 -> 0 | E12: =+E11-'Historical Financials'!E11 -> 0 | G12: =G11-'Historical Financials'!G11 -> 0 | H12: =H11-'Historical Financials'!H11 -> 0 | I12: =I11-'Historical Financials'!I11 -> 0 | J12: =J11-'Historical Financials'!J11 -> 0 | K12: =K11-'Historical Financials'!K11 -> 0 | L12: =L11-'Historical Financials'!L11 -> 0 | M12: =M11-'Historical Financials'!M11 -> 0 | N12: =N11-'Historical Financials'!N11 -> 0 | ... U12: =U11-'Historical Financials'!U11 -> 0 | W12: =+W11-'Historical Financials'!AF11 -> #REF! | X12: =+X11-'Historical Financials'!AG11 -> #REF! | Y12: =+Y11-'Historical Financials'!AH11 -> #REF! | Z12: =+Z11-'Historical Financials'!AI11 -> #REF! | AA12: =+AA11-'Historical Financials'!AJ11 -> -156.60428 | AB12: =+AB11-'Historical Financials'!AK11 -> -320.37793 | AC12: =+AC11-'Historical Financials'!AL11 -> 0 | AD12: =+AD11-'Historical Financials'!AM11 -> 0 | ... AF12: =+AF11-'Historical Financials'!AO11 -> 0 | AG12: =AG11-'Historical Financials'!AP11 -> 0
B14: Transaction and Service Revenue
B15: Merchant Revenue | C15: =C$9*C22 -> 1115.68 | D15: =D$9*D22 -> 1343.68 | E15: =E$9*E22 -> 1602 | J15: =SUM(C15-SUM(G15:I15)) -> 1115.68 | R15: =SUM(E15-SUM(O15:Q15)) -> 1602 | W15: =SUM(#REF!) -> #REF! | X15: =SUM(#REF!) -> #REF! | Y15: =SUM(#REF!) -> #REF! | Z15: =SUM(#REF!) -> #REF! | AA15: =SUM(O15:O15) -> 0 | AB15: =SUM(O15:P15) -> 0 | AC15: =SUM(O15:Q15) -> 0 | AD15: =SUM(O15:R15) -> 1602 | AE15: =SUM(P15:S15) -> 1602 | AF15: =SUM(Q15:T15) -> 1602 | AG15: =SUM(R15:U15) -> 1602 | AI15: =SUM(AG15/AC15)-1 -> #DIV/0!
B16: Advertising Revenue | C16: =C$9*C23 -> 161.48 | D16: =D$9*D23 -> 159.12 | E16: =E$9*E23 -> 170.88 | J16: =SUM(C16-SUM(G16:I16)) -> 161.48 | R16: =SUM(E16-SUM(O16:Q16)) -> 170.88
B17: Consumer Service Revenue | C17: =C$9*C24 -> 176.16 | D17: =D$9*D24 -> 229.84 | E17: =E$9*E24 -> 341.76 | J17: =SUM(C17-SUM(G17:I17)) -> 176.16 | R17: =SUM(E17-SUM(O17:Q17)) -> 341.76 | AC17: =SUM(O17:Q17) -> 0 | AD17: =SUM(O17:R17) -> 341.76 | AE17: =SUM(P17:S17) -> 341.76 | AF17: =SUM(Q17:T17) -> 341.76 | AG17: =SUM(R17:U17) -> 341.76 | AI17: =SUM(AG17/AC17)-1 -> #DIV/0!
B18: Intersegment Elimination | C18: =+SUM(C9-SUM(C15:C17)) -> 14.68 | D18: =+SUM(D9-SUM(D15:D17)) -> 35.36 | E18: =+SUM(E9-SUM(E15:E17)) -> 21.36 | J18: =SUM(C18-SUM(G18:I18)) -> 14.68 | R18: =SUM(E18-SUM(O18:Q18)) -> 21.36
B19: Total Transaction & Service Revenue | C19: =SUM(C15:C18) -> 1468 | D19: =SUM(D15:D18) -> 1768 | E19: =SUM(E15:E18) -> 2136 | G19: =SUM(G15:G17) -> 0 | H19: =SUM(H15:H17) -> 0 | I19: =SUM(I15:I17) -> 0 | J19: =SUM(J15:J17) -> 1453.32 | K19: =SUM(K15:K17) -> 0 | L19: =SUM(L15:L17) -> 0 | M19: =SUM(M15:M17) -> 0 | N19: =SUM(N15:N17) -> 0 | ... U19: =SUM(U15:U17) -> 0 | W19: =SUM(W15:W17) -> #REF! | X19: =SUM(X15:X17) -> #REF! | Y19: =SUM(Y15:Y17) -> #REF! | Z19: =SUM(Z15:Z17) -> #REF! | AA19: =SUM(AA15:AA17) -> 0 | AB19: =SUM(AB15:AB17) -> 0 | AC19: =SUM(AC15:AC17) -> 0 | AD19: =SUM(AD15:AD17) -> 1943.76 | ... AG19: =SUM(AG15:AG17) -> 1943.76 | AI19: =SUM(AG19/AC19)-1 -> #DIV/0!
B20: Variance Check | C20: =+C19-C9 -> 0 | D20: =+D19-D9 -> 0 | E20: =+E19-E9 -> 0 | G20: =G19-'Historical Financials'!#REF! -> #REF! | H20: =H19-'Historical Financials'!#REF! -> #REF! | I20: =I19-'Historical Financials'!#REF! -> #REF! | J20: =J19-'Historical Financials'!#REF! -> #REF! | K20: =K19-'Historical Financials'!#REF! -> #REF! | L20: =L19-'Historical Financials'!#REF! -> #REF! | M20: =M19-'Historical Financials'!#REF! -> #REF! | N20: =N19-'Historical Financials'!#REF! -> #REF! | ... U20: =U19-'Historical Financials'!#REF! -> #REF! | W20: =+W19-'Historical Financials'!#REF! -> #REF! | X20: =+X19-'Historical Financials'!#REF! -> #REF! | Y20: =+Y19-'Historical Financials'!#REF! -> #REF! | Z20: =+Z19-'Historical Financials'!#REF! -> #REF! | AA20: =+AA19-'Historical Financials'!#REF! -> #REF! | AB20: =+AB19-'Historical Financials'!#REF! -> #REF! | AC20: =+AC19-'Historical Financials'!#REF! -> #REF! | AD20: =+AD19-'Historical Financials'!#REF! -> #REF! | ... AF20: =+AF19-'Historical Financials'!#REF! -> #REF! | AG20: =AG19-'Historical Financials'!#REF! -> #REF!
B22: Merchant Revenue (%) | C22: 0.76 | D22: 0.76 | E22: 0.75
B23: Advertising Revenue (%) | C23: 0.11 | D23: 0.09 | E23: 0.08
B24: Consumer Service Revenue (%) | C24: 0.12 | D24: 0.13 | E24: 0.16
B26: Consumer Service Revenue
B27: Reminder Fees | C27: =C$17*C32 -> 165.5904 | D27: =D$17*D32 -> 190.7672 | E27: =E$17*E32 -> 252.9024 | J27: =SUM(C27-SUM(G27:I27)) -> 165.5904 | R27: =SUM(E27-SUM(O27:Q27)) -> 252.9024 | AC27: =SUM(O27:Q27) -> 0 | AD27: =SUM(O27:R27) -> 252.9024 | AE27: =SUM(P27:S27) -> 252.9024 | AF27: =SUM(Q27:T27) -> 252.9024 | AG27: =SUM(R27:U27) -> 252.9024 | AI27: =SUM(AG27/AC27)-1 -> #DIV/0!
B28: Other Revenues | C28: =C$17*C33 -> 10.5696 | D28: =D$17*D33 -> 39.0728 | E28: =E$17*E33 -> 88.8576 | J28: =SUM(C28-SUM(G28:I28)) -> 10.5696 | R28: =SUM(E28-SUM(O28:Q28)) -> 88.8576
B29: Total Transaction & Service Revenue | C29: =SUM(C27:C28) -> 176.16 | D29: =SUM(D27:D28) -> 229.84 | E29: =SUM(E27:E28) -> 341.76 | G29: =SUM(G27:G27) -> 0 | H29: =SUM(H27:H27) -> 0 | I29: =SUM(I27:I27) -> 0 | J29: =SUM(J27:J27) -> 165.5904 | K29: =SUM(K27:K27) -> 0 | L29: =SUM(L27:L27) -> 0 | M29: =SUM(M27:M27) -> 0 | N29: =SUM(N27:N27) -> 0 | ... U29: =SUM(U27:U27) -> 0 | W29: =SUM(W27:W27) -> 0 | X29: =SUM(X27:X27) -> 0 | Y29: =SUM(Y27:Y27) -> 0 | Z29: =SUM(Z27:Z27) -> 0 | AA29: =SUM(AA27:AA27) -> 0 | AB29: =SUM(AB27:AB27) -> 0 | AC29: =SUM(AC27:AC27) -> 0 | AD29: =SUM(AD27:AD27) -> 252.9024 | ... AG29: =SUM(AG27:AG27) -> 252.9024 | AI29: =SUM(AG29/AC29)-1 -> #DIV/0!
B30: Variance Check | C30: =C29-C17 -> 0 | D30: =D29-D17 -> 0 | E30: =E29-E17 -> 0 | G30: =G29-'Historical Financials'!G31 -> 283.61093 | H30: =H29-'Historical Financials'!H31 -> 382.779 | I30: =I29-'Historical Financials'!I31 -> 189.48449 | J30: =J29-'Historical Financials'!J31 -> 347.28562 | K30: =K29-'Historical Financials'!K31 -> 98.537746 | L30: =L29-'Historical Financials'!L31 -> 81.560346 | M30: =M29-'Historical Financials'!M31 -> -3.6936898 | N30: =N29-'Historical Financials'!N31 -> 128.00749 | ... U30: =U29-'Historical Financials'!U31 -> 88 | W30: =+W29-'Historical Financials'!AF31 -> #REF! | X30: =+X29-'Historical Financials'!AG31 -> #REF! | Y30: =+Y29-'Historical Financials'!AH31 -> #REF! | Z30: =+Z29-'Historical Financials'!AI31 -> #REF! | AA30: =+AA29-'Historical Financials'!AJ31 -> -509.75697 | AB30: =+AB29-'Historical Financials'!AK31 -> -1044.9638 | AC30: =+AC29-'Historical Financials'!AL31 -> 13.494109 | AD30: =+AD29-'Historical Financials'!AM31 -> 219.51752 | ... AF30: =+AF29-'Historical Financials'!AO31 -> 328.50908 | AG30: =AG29-'Historical Financials'!AP31 -> 431.23676
B32: Merchant Revenue (%) | C32: 0.94 | D32: 0.83 | E32: 0.74
B33: Consumer Service Revenue (%) | C33: =1-C32 -> 0.06 | D33: =1-D32 -> 0.17 | E33: =1-E32 -> 0.26
A35: X | B35: KPIs
B37: GMV Per Channel
B38: Merchant checkout | C38: 75239 | D38: 84642 | E38: 95623 | R38: =SUM(E38-SUM(O38:Q38)) -> 95623
B39: Direct-to-consumer | C39: 7598 | D39: 7823 | E39: 9392 | R39: =SUM(E39-SUM(O39:Q39)) -> 9392 | W39: =SUM(#REF!) -> #REF! | X39: =SUM(#REF!) -> #REF! | Y39: =SUM(#REF!) -> #REF! | Z39: =SUM(#REF!) -> #REF! | AA39: =SUM(O39:O39) -> 0 | AB39: =SUM(O39:P39) -> 0 | AC39: =SUM(O39:Q39) -> 0 | AD39: =SUM(O39:R39) -> 9392 | AE39: =SUM(P39:S39) -> 9392 | AF39: =SUM(Q39:T39) -> 9392 | AG39: =SUM(R39:U39) -> 9392 | AI39: =SUM(AG39/AC39)-1 -> #DIV/0!
B40: Total GMW | C40: =SUM(C38:C39) -> 82837 | D40: =SUM(D38:D39) -> 92465 | E40: =SUM(E38:E39) -> 105015 | G40: =SUM(G38:G39) -> 0 | H40: =SUM(H38:H39) -> 0 | I40: =SUM(I38:I39) -> 0 | J40: =SUM(J38:J39) -> 0 | K40: =SUM(K38:K39) -> 0 | L40: =SUM(L38:L39) -> 0 | M40: =SUM(M38:M39) -> 0 | N40: =SUM(N38:N39) -> 0 | ... U40: =SUM(U38:U39) -> 0 | W40: =SUM(W39:W39) -> #REF! | X40: =SUM(X39:X39) -> #REF! | Y40: =SUM(Y39:Y39) -> #REF! | Z40: =SUM(Z39:Z39) -> #REF! | AA40: =SUM(AA39:AA39) -> 0 | AB40: =SUM(AB39:AB39) -> 0 | AC40: =SUM(AC39:AC39) -> 0 | AD40: =SUM(AD39:AD39) -> 9392 | ... AG40: =SUM(AG39:AG39) -> 9392 | AI40: =SUM(AG40/AC40)-1 -> #DIV/0!
B42: Pay in Full (%) | C42: 0.26 | D42: 0.21 | E42: 0.16
B43: Pay Later (%) | C43: 0.7 | D43: 0.75 | E43: 0.79
B44: Fair Financing (%) | C44: 0.04 | D44: 0.04 | E44: 0.05
B46: GMV Per Payment Structure
B47: Pay in Full | C47: =C42*C40 -> 21537.62 | D47: =D42*D40 -> 19417.65 | E47: =E42*E40 -> 16802.4 | R47: =SUM(E47-SUM(O47:Q47)) -> 16802.4
B48: Pay Later | C48: =C43*C40 -> 57985.9 | D48: =D43*D40 -> 69348.75 | E48: =E43*E40 -> 82961.85 | R48: =SUM(E48-SUM(O48:Q48)) -> 82961.85
B49: Fair Financing | C49: =C44*C40 -> 3313.48 | D49: =D44*D40 -> 3698.6 | E49: =E44*E40 -> 5250.75 | R49: =SUM(E49-SUM(O49:Q49)) -> 5250.75 | W49: =SUM(#REF!) -> #REF! | X49: =SUM(#REF!) -> #REF! | Y49: =SUM(#REF!) -> #REF! | Z49: =SUM(#REF!) -> #REF! | AA49: =SUM(O49:O49) -> 0 | AB49: =SUM(O49:P49) -> 0 | AC49: =SUM(O49:Q49) -> 0 | AD49: =SUM(O49:R49) -> 5250.75 | AE49: =SUM(P49:S49) -> 5250.75 | AF49: =SUM(Q49:T49) -> 5250.75 | AG49: =SUM(R49:U49) -> 5250.75 | AI49: =SUM(AG49/AC49)-1 -> #DIV/0!
B50: Total GMW | C50: =SUM(C47:C49) -> 82837 | D50: =SUM(D47:D49) -> 92465 | E50: =SUM(E47:E49) -> 105015 | G50: =SUM(G47:G49) -> 0 | H50: =SUM(H47:H49) -> 0 | I50: =SUM(I47:I49) -> 0 | J50: =SUM(J47:J49) -> 0 | K50: =SUM(K47:K49) -> 0 | L50: =SUM(L47:L49) -> 0 | M50: =SUM(M47:M49) -> 0 | N50: =SUM(N47:N49) -> 0 | ... U50: =SUM(U47:U49) -> 0 | W50: =SUM(W49:W49) -> #REF! | X50: =SUM(X49:X49) -> #REF! | Y50: =SUM(Y49:Y49) -> #REF! | Z50: =SUM(Z49:Z49) -> #REF! | AA50: =SUM(AA49:AA49) -> 0 | AB50: =SUM(AB49:AB49) -> 0 | AC50: =SUM(AC49:AC49) -> 0 | AD50: =SUM(AD49:AD49) -> 5250.75 | ... AG50: =SUM(AG49:AG49) -> 5250.75 | AI50: =SUM(AG50/AC50)-1 -> #DIV/0!
B52: Number of Active Klarna Consumers
B53: Number of Active Klarna Consumers | C53: 79 | D53: 84 | E53: 93 | R53: =SUM(E53-SUM(O53:Q53)) -> 93 | W53: =SUM(#REF!) -> #REF! | X53: =SUM(#REF!) -> #REF! | Y53: =SUM(#REF!) -> #REF! | Z53: =SUM(#REF!) -> #REF! | AA53: =SUM(O53:O53) -> 0 | AB53: =SUM(O53:P53) -> 0 | AC53: =SUM(O53:Q53) -> 0 | AD53: =SUM(O53:R53) -> 93 | AE53: =SUM(P53:S53) -> 93 | AF53: =SUM(Q53:T53) -> 93 | AG53: =SUM(R53:U53) -> 93 | AI53: =SUM(AG53/AC53)-1 -> #DIV/0!
B54: Total GMW | C54: =SUM(C53:C53) -> 79 | D54: =SUM(D53:D53) -> 84 | E54: =SUM(E53:E53) -> 93 | G54: =SUM(G53:G53) -> 0 | H54: =SUM(H53:H53) -> 0 | I54: =SUM(I53:I53) -> 0 | J54: =SUM(J53:J53) -> 0 | K54: =SUM(K53:K53) -> 0 | L54: =SUM(L53:L53) -> 0 | M54: =SUM(M53:M53) -> 0 | N54: =SUM(N53:N53) -> 0 | ... U54: =SUM(U53:U53) -> 0 | W54: =SUM(W53:W53) -> #REF! | X54: =SUM(X53:X53) -> #REF! | Y54: =SUM(Y53:Y53) -> #REF! | Z54: =SUM(Z53:Z53) -> #REF! | AA54: =SUM(AA53:AA53) -> 0 | AB54: =SUM(AB53:AB53) -> 0 | AC54: =SUM(AC53:AC53) -> 0 | AD54: =SUM(AD53:AD53) -> 93 | ... AG54: =SUM(AG53:AG53) -> 93 | AI54: =SUM(AG54/AC54)-1 -> #DIV/0!
B56: ARPAC
B57: ARPAC | C57: 24 | D57: 27 | E57: 30 | R57: =SUM(E57-SUM(O57:Q57)) -> 30 | W57: =SUM(#REF!) -> #REF! | X57: =SUM(#REF!) -> #REF! | Y57: =SUM(#REF!) -> #REF! | Z57: =SUM(#REF!) -> #REF! | AA57: =SUM(O57:O57) -> 0 | AB57: =SUM(O57:P57) -> 0 | AC57: =SUM(O57:Q57) -> 0 | AD57: =SUM(O57:R57) -> 30 | AE57: =SUM(P57:S57) -> 30 | AF57: =SUM(Q57:T57) -> 30 | AG57: =SUM(R57:U57) -> 30 | AI57: =SUM(AG57/AC57)-1 -> #DIV/0!
B58: Total GMW | C58: =SUM(C57:C57) -> 24 | D58: =SUM(D57:D57) -> 27 | E58: =SUM(E57:E57) -> 30 | G58: =SUM(G57:G57) -> 0 | H58: =SUM(H57:H57) -> 0 | I58: =SUM(I57:I57) -> 0 | J58: =SUM(J57:J57) -> 0 | K58: =SUM(K57:K57) -> 0 | L58: =SUM(L57:L57) -> 0 | M58: =SUM(M57:M57) -> 0 | N58: =SUM(N57:N57) -> 0 | ... U58: =SUM(U57:U57) -> 0 | W58: =SUM(W57:W57) -> #REF! | X58: =SUM(X57:X57) -> #REF! | Y58: =SUM(Y57:Y57) -> #REF! | Z58: =SUM(Z57:Z57) -> #REF! | AA58: =SUM(AA57:AA57) -> 0 | AB58: =SUM(AB57:AB57) -> 0 | AC58: =SUM(AC57:AC57) -> 0 | AD58: =SUM(AD57:AD57) -> 30 | ... AG58: =SUM(AG57:AG57) -> 30 | AI58: =SUM(AG58/AC58)-1 -> #DIV/0!
B60: Transaction Margin Dollars
B61: Transaction Margin Dollars | C61: 687 | D61: 1085 | E61: 1217 | R61: =SUM(E61-SUM(O61:Q61)) -> 1217 | W61: =SUM(#REF!) -> #REF! | X61: =SUM(#REF!) -> #REF! | Y61: =SUM(#REF!) -> #REF! | Z61: =SUM(#REF!) -> #REF! | AA61: =SUM(O61:O61) -> 0 | AB61: =SUM(O61:P61) -> 0 | AC61: =SUM(O61:Q61) -> 0 | AD61: =SUM(O61:R61) -> 1217 | AE61: =SUM(P61:S61) -> 1217 | AF61: =SUM(Q61:T61) -> 1217 | AG61: =SUM(R61:U61) -> 1217 | AI61: =SUM(AG61/AC61)-1 -> #DIV/0!
B62: Total GMW | C62: =SUM(C61:C61) -> 687 | D62: =SUM(D61:D61) -> 1085 | E62: =SUM(E61:E61) -> 1217 | G62: =SUM(G61:G61) -> 0 | H62: =SUM(H61:H61) -> 0 | I62: =SUM(I61:I61) -> 0 | J62: =SUM(J61:J61) -> 0 | K62: =SUM(K61:K61) -> 0 | L62: =SUM(L61:L61) -> 0 | M62: =SUM(M61:M61) -> 0 | N62: =SUM(N61:N61) -> 0 | ... U62: =SUM(U61:U61) -> 0 | W62: =SUM(W61:W61) -> #REF! | X62: =SUM(X61:X61) -> #REF! | Y62: =SUM(Y61:Y61) -> #REF! | Z62: =SUM(Z61:Z61) -> #REF! | AA62: =SUM(AA61:AA61) -> 0 | AB62: =SUM(AB61:AB61) -> 0 | AC62: =SUM(AC61:AC61) -> 0 | AD62: =SUM(AD61:AD61) -> 1217 | ... AG62: =SUM(AG61:AG61) -> 1217 | AI62: =SUM(AG62/AC62)-1 -> #DIV/0!
B64: Average Purchase Frequency
B65: Average Purchase Frequency | C65: 10.4 | D65: 10.9 | E65: 11.3 | R65: =SUM(E65-SUM(O65:Q65)) -> 11.3 | W65: =SUM(#REF!) -> #REF! | X65: =SUM(#REF!) -> #REF! | Y65: =SUM(#REF!) -> #REF! | Z65: =SUM(#REF!) -> #REF! | AA65: =SUM(O65:O65) -> 0 | AB65: =SUM(O65:P65) -> 0 | AC65: =SUM(O65:Q65) -> 0 | AD65: =SUM(O65:R65) -> 11.3 | AE65: =SUM(P65:S65) -> 11.3 | AF65: =SUM(Q65:T65) -> 11.3 | AG65: =SUM(R65:U65) -> 11.3 | AI65: =SUM(AG65/AC65)-1 -> #DIV/0!
B66: Total Average Purchase Frequency | C66: =SUM(C65:C65) -> 10.4 | D66: =SUM(D65:D65) -> 10.9 | E66: =SUM(E65:E65) -> 11.3 | G66: =SUM(G65:G65) -> 0 | H66: =SUM(H65:H65) -> 0 | I66: =SUM(I65:I65) -> 0 | J66: =SUM(J65:J65) -> 0 | K66: =SUM(K65:K65) -> 0 | L66: =SUM(L65:L65) -> 0 | M66: =SUM(M65:M65) -> 0 | N66: =SUM(N65:N65) -> 0 | ... U66: =SUM(U65:U65) -> 0 | W66: =SUM(W65:W65) -> #REF! | X66: =SUM(X65:X65) -> #REF! | Y66: =SUM(Y65:Y65) -> #REF! | Z66: =SUM(Z65:Z65) -> #REF! | AA66: =SUM(AA65:AA65) -> 0 | AB66: =SUM(AB65:AB65) -> 0 | AC66: =SUM(AC65:AC65) -> 0 | AD66: =SUM(AD65:AD65) -> 11.3 | ... AG66: =SUM(AG65:AG65) -> 11.3 | AI66: =SUM(AG66/AC66)-1 -> #DIV/0!
B68: Dollar NRR
B69: Dollar NRR | D69: 1.15 | F69: 114 | R69: =SUM(E69-SUM(O69:Q69)) -> 0 | W69: =SUM(#REF!) -> #REF! | X69: =SUM(#REF!) -> #REF! | Y69: =SUM(#REF!) -> #REF! | Z69: =SUM(#REF!) -> #REF! | AA69: =SUM(O69:O69) -> 0 | AB69: =SUM(O69:P69) -> 0 | AC69: =SUM(O69:Q69) -> 0 | AD69: =SUM(O69:R69) -> 0 | AE69: =SUM(P69:S69) -> 0 | AF69: =SUM(Q69:T69) -> 0 | AG69: =SUM(R69:U69) -> 0 | AI69: =SUM(AG69/AC69)-1 -> #DIV/0!
B70: Total Average Purchase Frequency | C70: =SUM(C69:C69) -> 0 | D70: =SUM(D69:D69) -> 1.15 | E70: =SUM(E69:E69) -> 0 | G70: =SUM(G69:G69) -> 0 | H70: =SUM(H69:H69) -> 0 | I70: =SUM(I69:I69) -> 0 | J70: =SUM(J69:J69) -> 0 | K70: =SUM(K69:K69) -> 0 | L70: =SUM(L69:L69) -> 0 | M70: =SUM(M69:M69) -> 0 | N70: =SUM(N69:N69) -> 0 | ... U70: =SUM(U69:U69) -> 0 | W70: =SUM(W69:W69) -> #REF! | X70: =SUM(X69:X69) -> #REF! | Y70: =SUM(Y69:Y69) -> #REF! | Z70: =SUM(Z69:Z69) -> #REF! | AA70: =SUM(AA69:AA69) -> 0 | AB70: =SUM(AB69:AB69) -> 0 | AC70: =SUM(AC69:AC69) -> 0 | AD70: =SUM(AD69:AD69) -> 0 | ... AG70: =SUM(AG69:AG69) -> 0 | AI70: =SUM(AG70/AC70)-1 -> #DIV/0!

Sheet Other Segment Analysis
B2: ='Historical Financials'!B2 -> Klarna Group plc (KLAR) | C2: FYE | G2: Quarterly | H2: Quarterly | O2: LTM | S2: LTM | U2: LTM | AA2: Variance
B3: Other Segment Analysis | C3: ='Historical Financials'!C7 -> 2022 | D3: ='Historical Financials'!D7 -> 2023 | E3: ='Historical Financials'!E7 -> 2024 | G3: ='Historical Financials'!O7 -> 1Q24 | H3: ='Historical Financials'!P7 -> 2Q24 | I3: ='Historical Financials'!Q7 -> 3Q24 | J3: ='Historical Financials'!R7 -> 4Q24 | K3: ='Historical Financials'!S7 -> 1Q25 | L3: ='Historical Financials'!T7 -> 2Q25 | M3: ='Historical Financials'!U7 -> 3Q25 | O3: =#REF! -> #REF! | P3: =#REF! -> #REF! | Q3: =#REF! -> #REF! | R3: =#REF! -> #REF! | S3: =G3 -> 1Q24 | T3: =H3 -> 2Q24 | U3: =I3 -> 3Q24 | V3: =J3 -> 4Q24 | W3: =K3 -> 1Q25 | X3: =L3 -> 2Q25 | Y3: =M3 -> 3Q25
B4: $ mm except per share | C4: ='Historical Financials'!C8 -> 44926 | D4: ='Historical Financials'!D8 -> 45291 | E4: ='Historical Financials'!E8 -> 45657 | G4: ='Historical Financials'!O8 -> 45382 | H4: ='Historical Financials'!P8 -> 45473 | I4: ='Historical Financials'!Q8 -> 45565 | J4: ='Historical Financials'!R8 -> 45657 | K4: ='Historical Financials'!S8 -> 45747 | L4: ='Historical Financials'!T8 -> 45838 | M4: ='Historical Financials'!U8 -> 45930 | O4: =#REF! -> #REF! | P4: =#REF! -> #REF! | Q4: =#REF! -> #REF! | R4: =#REF! -> #REF! | S4: =G4 -> 45382 | T4: =H4 -> 45473 | U4: =I4 -> 45565 | V4: =J4 -> 45657 | W4: =K4 -> 45747 | X4: =L4 -> 45838 | Y4: =M4 -> 45930
A6: X | B6: Operating Expenses
B8: Funding Costs
B9: Processing and servicing costs | C9: -520 | D9: -541 | E9: -596 | J9: =SUM(E9-SUM(G9:I9)) -> -596 | O9: =SUM(#REF!) -> #REF! | P9: =SUM(#REF!) -> #REF! | Q9: =SUM(#REF!) -> #REF! | R9: =SUM(#REF!) -> #REF! | S9: =SUM(G9:G9) -> 0 | T9: =SUM(G9:H9) -> 0 | U9: =SUM(G9:I9) -> 0 | V9: =SUM(G9:J9) -> -596 | W9: =SUM(H9:K9) -> -596 | X9: =SUM(I9:L9) -> -596 | Y9: =SUM(J9:M9) -> -596 | AA9: =SUM(Y9/U9)-1 -> #DIV/0!
B10: Consumer credit losses | C10: -550 | D10: -353 | E10: -495
B11: Funding costs | C11: -147 | D11: -297 | E11: -503 | J11: =SUM(E11-SUM(G11:I11)) -> -503 | U11: =SUM(G11:I11) -> 0 | V11: =SUM(G11:J11) -> -503 | W11: =SUM(H11:K11) -> -503 | X11: =SUM(I11:L11) -> -503 | Y11: =SUM(J11:M11) -> -503 | AA11: =SUM(Y11/U11)-1 -> #DIV/0!
B12: Total Funding Costs | C12: =SUM(C9:C11) -> -1217 | D12: =SUM(D9:D11) -> -1191 | E12: =SUM(E9:E11) -> -1594 | G12: =SUM(G9:G11) -> 0 | H12: =SUM(H9:H11) -> 0 | I12: =SUM(I9:I11) -> 0 | J12: =SUM(J9:J11) -> -1099 | K12: =SUM(K9:K11) -> 0 | L12: =SUM(L9:L11) -> 0 | M12: =SUM(M9:M11) -> 0 | O12: =SUM(O9:O11) -> #REF! | P12: =SUM(P9:P11) -> #REF! | Q12: =SUM(Q9:Q11) -> #REF! | R12: =SUM(R9:R11) -> #REF! | S12: =SUM(S9:S11) -> 0 | T12: =SUM(T9:T11) -> 0 | U12: =SUM(U9:U11) -> 0 | V12: =SUM(V9:V11) -> -1099 | ... Y12: =SUM(Y9:Y11) -> -1099 | AA12: =SUM(Y12/U12)-1 -> #DIV/0!
B13: Variance Check | C13: =C12-'Historical Financials'!#REF! -> #REF! | D13: =+D12-'Historical Financials'!D11 -> -3467 | E13: =+E12-'Historical Financials'!E11 -> -4405 | G13: =G12-'Historical Financials'!O11 -> -635.32869 | H13: =H12-'Historical Financials'!P11 -> -675.93368 | I13: =I12-'Historical Financials'!Q11 -> -718.35223 | J13: =J12-'Historical Financials'!R11 -> -1880.3854 | K13: =K12-'Historical Financials'!S11 -> -701.13716 | L13: =L12-'Historical Financials'!T11 -> -823.10162 | M13: =M12-'Historical Financials'!U11 -> -903 | O13: =+O12-'Historical Financials'!AF11 -> #REF! | P13: =+P12-'Historical Financials'!AG11 -> #REF! | Q13: =+Q12-'Historical Financials'!AH11 -> #REF! | R13: =+R12-'Historical Financials'!AI11 -> #REF! | S13: =+S12-'Historical Financials'!AJ11 -> -635.32869 | T13: =+T12-'Historical Financials'!AK11 -> -1311.2624 | U13: =+U12-'Historical Financials'!AL11 -> -2029.6146 | V13: =+V12-'Historical Financials'!AM11 -> -3910 | ... X13: =+X12-'Historical Financials'!AO11 -> -4122.9764 | Y13: =Y12-'Historical Financials'!AP11 -> -4307.6242
B15: Transaction and Service Revenue
B16: Merchant Revenue | C16: =C$9*C23 -> -395.2 | D16: =D$9*D23 -> -411.16 | E16: =E$9*E23 -> -447 | J16: =SUM(E16-SUM(G16:I16)) -> -447 | O16: =SUM(#REF!) -> #REF! | P16: =SUM(#REF!) -> #REF! | Q16: =SUM(#REF!) -> #REF! | R16: =SUM(#REF!) -> #REF! | S16: =SUM(G16:G16) -> 0 | T16: =SUM(G16:H16) -> 0 | U16: =SUM(G16:I16) -> 0 | V16: =SUM(G16:J16) -> -447 | W16: =SUM(H16:K16) -> -447 | X16: =SUM(I16:L16) -> -447 | Y16: =SUM(J16:M16) -> -447 | AA16: =SUM(Y16/U16)-1 -> #DIV/0!
B17: Advertising Revenue | C17: =C$9*C24 -> -57.2 | D17: =D$9*D24 -> -48.69 | E17: =E$9*E24 -> -47.68
B18: Consumer Service Revenue | C18: =C$9*C25 -> -62.4 | D18: =D$9*D25 -> -70.33 | E18: =E$9*E25 -> -95.36 | J18: =SUM(E18-SUM(G18:I18)) -> -95.36 | U18: =SUM(G18:I18) -> 0 | V18: =SUM(G18:J18) -> -95.36 | W18: =SUM(H18:K18) -> -95.36 | X18: =SUM(I18:L18) -> -95.36 | Y18: =SUM(J18:M18) -> -95.36 | AA18: =SUM(Y18/U18)-1 -> #DIV/0!
B19: Intersegment Elimination | C19: =+SUM(C9-SUM(C16:C18)) -> -5.2 | D19: =+SUM(D9-SUM(D16:D18)) -> -10.82 | E19: =+SUM(E9-SUM(E16:E18)) -> -5.96
B20: Total Transaction & Service Revenue | C20: =SUM(C16:C19) -> -520 | D20: =SUM(D16:D19) -> -541 | E20: =SUM(E16:E19) -> -596 | G20: =SUM(G16:G18) -> 0 | H20: =SUM(H16:H18) -> 0 | I20: =SUM(I16:I18) -> 0 | J20: =SUM(J16:J18) -> -542.36 | K20: =SUM(K16:K18) -> 0 | L20: =SUM(L16:L18) -> 0 | M20: =SUM(M16:M18) -> 0 | O20: =SUM(O16:O18) -> #REF! | P20: =SUM(P16:P18) -> #REF! | Q20: =SUM(Q16:Q18) -> #REF! | R20: =SUM(R16:R18) -> #REF! | S20: =SUM(S16:S18) -> 0 | T20: =SUM(T16:T18) -> 0 | U20: =SUM(U16:U18) -> 0 | V20: =SUM(V16:V18) -> -542.36 | ... Y20: =SUM(Y16:Y18) -> -542.36 | AA20: =SUM(Y20/U20)-1 -> #DIV/0!
B21: Variance Check | C21: =+C20-C9 -> 0 | D21: =+D20-D9 -> 0 | E21: =+E20-E9 -> 0 | G21: =G20-'Historical Financials'!#REF! -> #REF! | H21: =H20-'Historical Financials'!#REF! -> #REF! | I21: =I20-'Historical Financials'!#REF! -> #REF! | J21: =J20-'Historical Financials'!#REF! -> #REF! | K21: =K20-'Historical Financials'!#REF! -> #REF! | L21: =L20-'Historical Financials'!#REF! -> #REF! | M21: =M20-'Historical Financials'!#REF! -> #REF! | O21: =+O20-'Historical Financials'!#REF! -> #REF! | P21: =+P20-'Historical Financials'!#REF! -> #REF! | Q21: =+Q20-'Historical Financials'!#REF! -> #REF! | R21: =+R20-'Historical Financials'!#REF! -> #REF! | S21: =+S20-'Historical Financials'!#REF! -> #REF! | T21: =+T20-'Historical Financials'!#REF! -> #REF! | U21: =+U20-'Historical Financials'!#REF! -> #REF! | V21: =+V20-'Historical Financials'!#REF! -> #REF! | ... X21: =+X20-'Historical Financials'!#REF! -> #REF! | Y21: =Y20-'Historical Financials'!#REF! -> #REF!
B23: Merchant Revenue (%) | C23: 0.76 | D23: 0.76 | E23: 0.75
B24: Advertising Revenue (%) | C24: 0.11 | D24: 0.09 | E24: 0.08
B25: Consumer Service Revenue (%) | C25: 0.12 | D25: 0.13 | E25: 0.16
B27: Consumer Service Revenue
B28: Reminder Fees | C28: =C$18*C33 -> -58.656 | D28: =D$18*D33 -> -58.3739 | E28: =E$18*E33 -> -70.5664 | J28: =SUM(E28-SUM(G28:I28)) -> -70.5664 | U28: =SUM(G28:I28) -> 0 | V28: =SUM(G28:J28) -> -70.5664 | W28: =SUM(H28:K28) -> -70.5664 | X28: =SUM(I28:L28) -> -70.5664 | Y28: =SUM(J28:M28) -> -70.5664 | AA28: =SUM(Y28/U28)-1 -> #DIV/0!
B29: Other Revenues | C29: =C$18*C34 -> -3.744 | D29: =D$18*D34 -> -11.9561 | E29: =E$18*E34 -> -24.7936
B30: Total Transaction & Service Revenue | C30: =SUM(C28:C29) -> -62.4 | D30: =SUM(D28:D29) -> -70.33 | E30: =SUM(E28:E29) -> -95.36 | G30: =SUM(G28:G28) -> 0 | H30: =SUM(H28:H28) -> 0 | I30: =SUM(I28:I28) -> 0 | J30: =SUM(J28:J28) -> -70.5664 | K30: =SUM(K28:K28) -> 0 | L30: =SUM(L28:L28) -> 0 | M30: =SUM(M28:M28) -> 0 | O30: =SUM(O28:O28) -> 0 | P30: =SUM(P28:P28) -> 0 | Q30: =SUM(Q28:Q28) -> 0 | R30: =SUM(R28:R28) -> 0 | S30: =SUM(S28:S28) -> 0 | T30: =SUM(T28:T28) -> 0 | U30: =SUM(U28:U28) -> 0 | V30: =SUM(V28:V28) -> -70.5664 | ... Y30: =SUM(Y28:Y28) -> -70.5664 | AA30: =SUM(Y30/U30)-1 -> #DIV/0!
B31: Variance Check | C31: =C30-C18 -> 0 | D31: =D30-D18 -> 0 | E31: =E30-E18 -> 0 | G31: =G30-'Historical Financials'!O31 -> 25.474493 | H31: =H30-'Historical Financials'!P31 -> 2.7472887 | I31: =I30-'Historical Financials'!Q31 -> -14.727673 | J31: =J30-'Historical Financials'!R31 -> -117.44539 | K31: =K30-'Historical Financials'!S31 -> 91.374325 | L31: =L30-'Historical Financials'!T31 -> 45.839025 | M31: =M30-'Historical Financials'!U31 -> 88 | O31: =+O30-'Historical Financials'!AF31 -> #REF! | P31: =+P30-'Historical Financials'!AG31 -> #REF! | Q31: =+Q30-'Historical Financials'!AH31 -> #REF! | R31: =+R30-'Historical Financials'!AI31 -> #REF! | S31: =+S30-'Historical Financials'!AJ31 -> -509.75697 | T31: =+T30-'Historical Financials'!AK31 -> -1044.9638 | U31: =+U30-'Historical Financials'!AL31 -> 13.494109 | V31: =+V30-'Historical Financials'!AM31 -> -103.95128 | ... X31: =+X30-'Historical Financials'!AO31 -> 5.0402839 | Y31: =Y30-'Historical Financials'!AP31 -> 107.76796
B33: Merchant Revenue (%) | C33: 0.94 | D33: 0.83 | E33: 0.74
B34: Consumer Service Revenue (%) | C34: =1-C33 -> 0.06 | D34: =1-D33 -> 0.17 | E34: =1-E33 -> 0.26
A36: X | B36: KPIs
B38: % of Purchases by Vertical (U.S)
B39: Apparel & Accessories | J39: =SUM(E39-SUM(G39:I39)) -> 0
B40: Health & Beauty
B41: Home & Electronics
B42: Food & Beverage
B43: Leisure
B44: Events & Services
B45: Travel
B46: Total U.S Purchases by Vertical | C46: =SUM(C39:C45) -> 0 | D46: =SUM(D39:D45) -> 0 | E46: =SUM(E39:E45) -> 0 | G46: =SUM(G39:G45) -> 0 | H46: =SUM(H39:H45) -> 0 | I46: =SUM(I39:I45) -> 0 | J46: =SUM(J39:J45) -> 0 | K46: =SUM(K39:K45) -> 0 | L46: =SUM(L39:L45) -> 0 | M46: =SUM(M39:M45) -> 0 | O46: =SUM(#REF!) -> #REF! | P46: =SUM(#REF!) -> #REF! | Q46: =SUM(#REF!) -> #REF! | R46: =SUM(#REF!) -> #REF! | S46: =SUM(#REF!) -> #REF! | T46: =SUM(#REF!) -> #REF! | U46: =SUM(#REF!) -> #REF! | V46: =SUM(#REF!) -> #REF! | ... Y46: =SUM(#REF!) -> #REF! | AA46: =SUM(Y46/U46)-1 -> #REF!
B48: =B39&"(%)" -> Apparel & Accessories (%) | E48: 0.69
B49: =B40&"(%)" -> Health & Beauty (%) | E49: 0.03
B50: =B41&"(%)" -> Home & Electronics (%) | E50: 0.04
B51: =B42&"(%)" -> Food & Beverage (%) | E51: 0.05
B52: =B43&"(%)" -> Leisure (%) | E52: 0.12
B53: =B44&"(%)" -> Events & Services (%) | E53: 0.04
B54: =B45&"(%)" -> Travel (%) | E54: 0.03
B56: % of Purchases by Vertical (Germany)
B57: Apparel & Accessories | J57: =SUM(E57-SUM(G57:I57)) -> 0
B58: Health & Beauty
B59: Home & Electronics
B60: Food & Beverage
B61: Leisure
B62: Events & Services
B63: Travel
B64: Total Germany Purchases by Vertical | C64: =SUM(C57:C63) -> 0 | D64: =SUM(D57:D63) -> 0 | E64: =SUM(E57:E63) -> 0 | G64: =SUM(G57:G63) -> 0 | H64: =SUM(H57:H63) -> 0 | I64: =SUM(I57:I63) -> 0 | J64: =SUM(J57:J63) -> 0 | K64: =SUM(K57:K63) -> 0 | L64: =SUM(L57:L63) -> 0 | M64: =SUM(M57:M63) -> 0 | O64: =SUM(#REF!) -> #REF! | P64: =SUM(#REF!) -> #REF! | Q64: =SUM(#REF!) -> #REF! | R64: =SUM(#REF!) -> #REF! | S64: =SUM(#REF!) -> #REF! | T64: =SUM(#REF!) -> #REF! | U64: =SUM(#REF!) -> #REF! | V64: =SUM(#REF!) -> #REF! | ... Y64: =SUM(#REF!) -> #REF! | AA64: =SUM(Y64/U64)-1 -> #REF!
B66: =B57&"(%)" -> Apparel & Accessories (%) | E66: 0.26
B67: =B58&"(%)" -> Health & Beauty (%) | E67: 0.08
B68: =B59&"(%)" -> Home & Electronics (%) | E68: 0.14
B69: =B60&"(%)" -> Food & Beverage (%) | E69: 0.05
B70: =B61&"(%)" -> Leisure (%) | E70: 0.15
B71: =B62&"(%)" -> Events & Services (%) | E71: 0.29
B72: =B63&"(%)" -> Travel (%) | E72: 0.03
B74: % of Purchases by Vertical (Sweden)
B75: Apparel & Accessories | J75: =SUM(E75-SUM(G75:I75)) -> 0
B76: Health & Beauty
B77: Home & Electronics
B78: Food & Beverage
B79: Leisure
B80: Events & Services
B81: Travel
B82: Total Sweden Purchases by Vertical | C82: =SUM(C75:C81) -> 0 | D82: =SUM(D75:D81) -> 0 | E82: =SUM(E75:E81) -> 0 | G82: =SUM(G75:G81) -> 0 | H82: =SUM(H75:H81) -> 0 | I82: =SUM(I75:I81) -> 0 | J82: =SUM(J75:J81) -> 0 | K82: =SUM(K75:K81) -> 0 | L82: =SUM(L75:L81) -> 0 | M82: =SUM(M75:M81) -> 0 | O82: =SUM(#REF!) -> #REF! | P82: =SUM(#REF!) -> #REF! | Q82: =SUM(#REF!) -> #REF! | R82: =SUM(#REF!) -> #REF! | S82: =SUM(#REF!) -> #REF! | T82: =SUM(#REF!) -> #REF! | U82: =SUM(#REF!) -> #REF! | V82: =SUM(#REF!) -> #REF! | ... Y82: =SUM(#REF!) -> #REF! | AA82: =SUM(Y82/U82)-1 -> #REF!
B84: =B75&"(%)" -> Apparel & Accessories (%) | E84: 0.18
B85: =B76&"(%)" -> Health & Beauty (%) | E85: 0.19
B86: =B77&"(%)" -> Home & Electronics (%) | E86: 0.19
B87: =B78&"(%)" -> Food & Beverage (%) | E87: 0.13
B88: =B79&"(%)" -> Leisure (%) | E88: 0.14
B89: =B80&"(%)" -> Events & Services (%) | E89: 0.12
B90: =B81&"(%)" -> Travel (%) | E90: 0.05

Sheet FCF
B2: ='Historical Financials'!B2 -> Klarna Group plc (KLAR) | C2: FYE | G2: Quarterly | Q2: Quarterly | W2: LTM | AD2: LTM | AE2: LTM | AK2: Variance
B3: FCF Analysis | C3: ='Historical Financials'!C7 -> 2022 | D3: ='Historical Financials'!D7 -> 2023 | E3: ='Historical Financials'!E7 -> 2024 | G3: ='Historical Financials'!G7 -> 1Q22 | H3: ='Historical Financials'!H7 -> 2Q22 | I3: ='Historical Financials'!I7 -> 3Q22 | J3: ='Historical Financials'!J7 -> 4Q22 | K3: ='Historical Financials'!K7 -> 1Q23 | L3: ='Historical Financials'!L7 -> 2Q23 | M3: ='Historical Financials'!M7 -> 3Q23 | N3: ='Historical Financials'!N7 -> 4Q23 | ... U3: ='Historical Financials'!U7 -> 3Q25 | W3: =I3 -> 3Q22 | X3: =J3 -> 4Q22 | Y3: =K3 -> 1Q23 | Z3: =L3 -> 2Q23 | AA3: =M3 -> 3Q23 | AB3: =N3 -> 4Q23 | AC3: =O3 -> 1Q24 | AD3: =P3 -> 2Q24 | ... AI3: =U3 -> 3Q25
B4: $ mm except per share | C4: ='Historical Financials'!C8 -> 44926 | D4: ='Historical Financials'!D8 -> 45291 | E4: ='Historical Financials'!E8 -> 45657 | G4: ='Historical Financials'!G8 -> 44651 | H4: ='Historical Financials'!H8 -> 44742 | I4: ='Historical Financials'!I8 -> 44834 | J4: ='Historical Financials'!J8 -> 44926 | K4: ='Historical Financials'!K8 -> 45016 | L4: ='Historical Financials'!L8 -> 45107 | M4: ='Historical Financials'!M8 -> 45199 | N4: ='Historical Financials'!N8 -> 45291 | ... U4: ='Historical Financials'!U8 -> 45930 | W4: =I4 -> 44834 | X4: =J4 -> 44926 | Y4: =K4 -> 45016 | Z4: =L4 -> 45107 | AA4: =M4 -> 45199 | AB4: =N4 -> 45291 | AC4: =O4 -> 45382 | AD4: =P4 -> 45473 | ... AI4: =U4 -> 45930
B6: ='Revenue Drivers'!B9 -> Transaction and service revenue | C6: ='Revenue Drivers'!C9 -> 1468 | D6: ='Revenue Drivers'!D9 -> 1768 | E6: ='Revenue Drivers'!E9 -> 2136 | G6: ='Revenue Drivers'!G9 -> 344.58814 | H6: ='Revenue Drivers'!H9 -> 369.20095 | I6: ='Revenue Drivers'!I9 -> 331.21869 | J6: ='Revenue Drivers'!J9 -> 422.99222 | K6: ='Revenue Drivers'!K9 -> 368.13111 | L6: ='Revenue Drivers'!L9 -> 417.98173 | M6: ='Revenue Drivers'!M9 -> 440.43433 | N6: ='Revenue Drivers'!N9 -> 541.45284 | ... U6: ='Revenue Drivers'!U9 -> 634 | W6: =SUM(F6:I6) -> 1045.0078 | X6: =SUM(G6:J6) -> 1468 | Y6: =SUM(H6:K6) -> 1491.543 | Z6: =SUM(I6:L6) -> 1540.3237 | AA6: =SUM(J6:M6) -> 1649.5394 | AB6: =SUM(K6:N6) -> 1768 | AC6: =SUM(L6:O6) -> 1878.5933 | AD6: =SUM(M6:P6) -> 1972.7716 | ... AI6: =SUM(R6:U6) -> 2357.8274 | AK6: =SUM(AI6/AE6)-1 -> 0.13526923
B7: ='Revenue Drivers'!B10 -> Interest income | C7: ='Revenue Drivers'!C10 -> 436 | D7: ='Revenue Drivers'!D10 -> 508 | E7: ='Revenue Drivers'!E10 -> 675 | G7: ='Revenue Drivers'!G10 -> 113.29018 | H7: ='Revenue Drivers'!H10 -> 114.24219 | I7: ='Revenue Drivers'!I10 -> 101.88917 | J7: ='Revenue Drivers'!J10 -> 106.57845 | K7: ='Revenue Drivers'!K10 -> 116.02312 | L7: ='Revenue Drivers'!L10 -> 116.09384 | M7: ='Revenue Drivers'!M10 -> 134.34505 | N7: ='Revenue Drivers'!N10 -> 141.53799 | ... U7: ='Revenue Drivers'!U10 -> 269 | AE7: =SUM(N7:Q7) -> 635.71711 | AF7: =SUM(O7:R7) -> 675 | AG7: =SUM(P7:S7) -> 700.21885 | AH7: =SUM(Q7:T7) -> 755.59796 | AI7: =SUM(R7:U7) -> 850.79676 | AK7: =SUM(AI7/AE7)-1 -> 0.33832605
B8: Total Revenue | C8: =SUM(C6:C7) -> 1904 | D8: =SUM(D6:D7) -> 2276 | E8: =SUM(E6:E7) -> 2811 | G8: =SUM(G6:G7) -> 457.87832 | H8: =SUM(H6:H7) -> 483.44314 | I8: =SUM(I6:I7) -> 433.10787 | J8: =SUM(J6:J7) -> 529.57067 | K8: =SUM(K6:K7) -> 484.15423 | L8: =SUM(L6:L7) -> 534.07557 | M8: =SUM(M6:M7) -> 574.77938 | N8: =SUM(N6:N7) -> 682.99082 | ... U8: =SUM(U6:U7) -> 903 | W8: =SUM(W6:W7) -> 1045.0078 | X8: =SUM(X6:X7) -> 1468 | Y8: =SUM(Y6:Y7) -> 1491.543 | Z8: =SUM(Z6:Z7) -> 1540.3237 | AA8: =SUM(AA6:AA7) -> 1649.5394 | AB8: =SUM(AB6:AB7) -> 1768 | AC8: =SUM(AC6:AC7) -> 1878.5933 | AD8: =SUM(AD6:AD7) -> 1972.7716 | ... AI8: =SUM(AI6:AI7) -> 3208.6242 | AK8: =SUM(AI8/AE8)-1 -> 0.18285694
B9: Y/Y Growth (%) | C9: =SUM(C8/#REF!)-1 -> #REF! | D9: =SUM(D8/C8)-1 -> 0.19537815 | E9: =SUM(E8/D8)-1 -> 0.23506151 | K9: =SUM(K8/G8)-1 -> 0.057386227 | L9: =SUM(L8/H8)-1 -> 0.10473296 | M9: =SUM(M8/I8)-1 -> 0.32710445 | N9: =SUM(N8/J8)-1 -> 0.28970666 | O9: =SUM(O8/K8)-1 -> 0.31224443 | P9: =SUM(P8/L8)-1 -> 0.26561431 | Q9: =SUM(Q8/M8)-1 -> 0.24978777 | R9: =SUM(R8/N8)-1 -> 0.14406426 | ... U9: =SUM(U8/Q8)-1 -> 0.25704349 | AA9: =SUM(AA8/W8)-1 -> 0.57849483 | AB9: =SUM(AB8/X8)-1 -> 0.20435967 | AC9: =SUM(AC8/Y8)-1 -> 0.25949661 | AD9: =SUM(AD8/Z8)-1 -> 0.28075128 | AE9: =SUM(AE8/AA8)-1 -> 0.64446236 | AF9: =SUM(AF8/AB8)-1 -> 0.58993213 | AG9: =SUM(AG8/AC8)-1 -> 0.53136309 | AH9: =SUM(AH8/AD8)-1 -> 0.53285681 | AI9: =SUM(AI8/AE8)-1 -> 0.18285694 | AK9: =SUM(AI9-AE9)*10000 -> -4616.0542
B10: Q/Q Growth (%) | C10: N/A | D10: N/A | E10: N/A | H10: =SUM(H8/G8)-1 -> 0.055833218 | I10: =SUM(I8/H8)-1 -> -0.10411829 | J10: =SUM(J8/I8)-1 -> 0.22272236 | K10: =SUM(K8/J8)-1 -> -0.085760867 | L10: =SUM(L8/K8)-1 -> 0.10311041 | M10: =SUM(M8/L8)-1 -> 0.076213565 | N10: =SUM(N8/M8)-1 -> 0.18826606 | O10: =SUM(O8/N8)-1 -> -0.069784437 | ... U10: =SUM(U8/T8)-1 -> 0.09706988 | W10: N/A | X10: N/A | Y10: N/A | Z10: N/A | AA10: N/A | AB10: N/A | AC10: N/A | AD10: N/A | AE10: N/A | AF10: N/A | AG10: N/A | AH10: N/A | AI10: N/A
B12: (-) Processing and servicing costs | C12: ='Historical Financials'!C13 -> -520 | D12: ='Historical Financials'!D13 -> -541 | E12: ='Historical Financials'!E13 -> -596 | G12: ='Historical Financials'!G13 -> -122.86115 | H12: ='Historical Financials'!H13 -> -140.3493 | I12: ='Historical Financials'!I13 -> -119.00793 | J12: ='Historical Financials'!J13 -> -137.78162 | K12: ='Historical Financials'!K13 -> -127.9813 | L12: ='Historical Financials'!L13 -> -131.41075 | M12: ='Historical Financials'!M13 -> -133.22809 | N12: ='Historical Financials'!N13 -> -148.37987 | ... U12: ='Historical Financials'!U13 -> -208 | W12: =SUM(F12:I12) -> -382.21838 | X12: =SUM(G12:J12) -> -520 | Y12: =SUM(H12:K12) -> -525.12015 | Z12: =SUM(I12:L12) -> -516.18159 | AA12: =SUM(J12:M12) -> -530.40175 | AB12: =SUM(K12:N12) -> -541 | AC12: =SUM(L12:O12) -> -548.92035 | AD12: =SUM(M12:P12) -> -565.52257 | ... AI12: =SUM(R12:U12) -> -719.86816 | AK12: =SUM(AI12/AE12)-1 -> 0.23352563
B13: (-) Consumer credit losses | C13: ='Historical Financials'!C14 -> -550 | D13: ='Historical Financials'!D14 -> -353 | E13: ='Historical Financials'!E14 -> -495 | G13: ='Historical Financials'!G14 -> -124.71731 | H13: ='Historical Financials'!H14 -> -166.09766 | I13: ='Historical Financials'!I14 -> -136.43861 | J13: ='Historical Financials'!J14 -> -122.74643 | K13: ='Historical Financials'!K14 -> -72.849766 | L13: ='Historical Financials'!L14 -> -88.327096 | M13: ='Historical Financials'!M14 -> -72.010591 | N13: ='Historical Financials'!N14 -> -119.81255 | ... U13: ='Historical Financials'!U14 -> -235 | W13: =SUM(F13:I13) -> -427.25357 | X13: =SUM(G13:J13) -> -550 | Y13: =SUM(H13:K13) -> -498.13245 | Z13: =SUM(I13:L13) -> -420.36189 | AA13: =SUM(J13:M13) -> -355.93388 | AB13: =SUM(K13:N13) -> -353 | AC13: =SUM(L13:O13) -> -396.81531 | AD13: =SUM(M13:P13) -> -414.79553 | ... AI13: =SUM(R13:U13) -> -701.18584 | AK13: =SUM(AI13/AE13)-1 -> 0.52966092
B14: (-) Funding costs | C14: ='Historical Financials'!C15 -> -147 | D14: ='Historical Financials'!D15 -> -297 | E14: ='Historical Financials'!E15 -> -503 | G14: ='Historical Financials'!G15 -> -30.028678 | H14: ='Historical Financials'!H15 -> -30.251101 | I14: ='Historical Financials'!I15 -> -39.36219 | J14: ='Historical Financials'!J15 -> -47.358031 | K14: ='Historical Financials'!K15 -> -56.835333 | L14: ='Historical Financials'!L15 -> -62.384282 | M14: ='Historical Financials'!M15 -> -77.893781 | N14: ='Historical Financials'!N15 -> -99.886603 | ... U14: ='Historical Financials'!U15 -> -180 | W14: =SUM(F14:I14) -> -99.641969 | X14: =SUM(G14:J14) -> -147 | Y14: =SUM(H14:K14) -> -173.80666 | Z14: =SUM(I14:L14) -> -205.93984 | AA14: =SUM(J14:M14) -> -244.47143 | AB14: =SUM(K14:N14) -> -297 | AC14: =SUM(L14:O14) -> -353.55375 | AD14: =SUM(M14:P14) -> -411.0097 | ... AI14: =SUM(R14:U14) -> -604.59097 | AK14: =SUM(AI14/AE14)-1 -> 0.32608288
B15: Gross Profit | C15: =+C8+SUM(C12:C14) -> 687 | D15: =+D8+SUM(D12:D14) -> 1085 | E15: =+E8+SUM(E12:E14) -> 1217 | G15: =+G8+SUM(G12:G14) -> 180.27119 | H15: =+H8+SUM(H12:H14) -> 146.74508 | I15: =+I8+SUM(I12:I14) -> 138.29914 | J15: =+J8+SUM(J12:J14) -> 221.68459 | K15: =+K8+SUM(K12:K14) -> 226.48784 | L15: =+L8+SUM(L12:L14) -> 251.95345 | M15: =+M8+SUM(M12:M14) -> 291.64691 | N15: =+N8+SUM(N12:N14) -> 314.9118 | ... U15: =+U8+SUM(U12:U14) -> 280 | W15: =+W8+W12 -> 662.7894 | X15: =+X8+X12 -> 948 | Y15: =+Y8+Y12 -> 966.42282 | Z15: =+Z8+Z12 -> 1024.1422 | AA15: =+AA8+AA12 -> 1119.1376 | AB15: =+AB8+AB12 -> 1227 | AC15: =+AC8+AC12 -> 1329.673 | AD15: =+AD8+AD12 -> 1407.249 | AE15: =+AE8+SUM(AE12:AE14) -> 1214.7041 | AF15: =+AF8+SUM(AF12:AF14) -> 1217 | AG15: =+AG8+SUM(AG12:AG14) -> 1218.3868 | AH15: =+AH8+SUM(AH12:AH14) -> 1231.6254 | AI15: =+AI8+SUM(AI12:AI14) -> 1182.9792 | AK15: =SUM(AI15/AE15)-1 -> -0.026117377
B16: Gross Margin (%) | C16: =C15/C8 -> 0.36081933 | D16: =D15/D8 -> 0.47671353 | E16: =E15/E8 -> 0.43294201 | G16: =G15/G8 -> 0.39370981 | H16: =H15/H8 -> 0.30354155 | I16: =I15/I8 -> 0.31931801 | J16: =J15/J8 -> 0.41861191 | K16: =K15/K8 -> 0.46780101 | L16: =L15/L8 -> 0.47175617 | M16: =M15/M8 -> 0.50740671 | N16: =N15/N8 -> 0.46107765 | ... U16: =U15/U8 -> 0.31007752 | W16: =W15/W8 -> 0.63424351 | X16: =X15/X8 -> 0.64577657 | Y16: =Y15/Y8 -> 0.64793495 | Z16: =Z15/Z8 -> 0.6648876 | AA16: =AA15/AA8 -> 0.67845463 | AB16: =AB15/AB8 -> 0.69400452 | AC16: =AC15/AC8 -> 0.70780246 | AD16: =AD15/AD8 -> 0.71333602 | ... AI16: =AI15/AI8 -> 0.36868737 | AK16: =SUM(AI16-AE16)*10000 -> -791.12402
B18: (-) Technology and product development | C18: ='Historical Financials'!C19 -> -355.14437 | D18: ='Historical Financials'!D19 -> -276.4925 | E18: ='Historical Financials'!E19 -> -307.83389 | G18: ='Historical Financials'!G19 -> -96.741726 | H18: ='Historical Financials'!H19 -> -107.08367 | I18: ='Historical Financials'!I19 -> -69.442446 | J18: ='Historical Financials'!J19 -> -81.876523 | K18: ='Historical Financials'!K19 -> -66.668118 | L18: ='Historical Financials'!L19 -> -70.24335 | M18: ='Historical Financials'!M19 -> -64.689124 | N18: ='Historical Financials'!N19 -> -74.89191 | ... U18: ='Historical Financials'!U19 -> -97 | W18: =SUM(F18:I18) -> -273.26784 | X18: =SUM(G18:J18) -> -355.14437 | Y18: =SUM(H18:K18) -> -325.07076 | Z18: =SUM(I18:L18) -> -288.23044 | AA18: =SUM(J18:M18) -> -283.47711 | AB18: =SUM(K18:N18) -> -276.4925 | AC18: =SUM(L18:O18) -> -288.14022 | AD18: =SUM(M18:P18) -> -298.85445 | ... AI18: =SUM(R18:U18) -> -344.11627 | AK18: =SUM(AI18/AE18)-1 -> 0.10342402
B19: (-) Sales and Marketing (S&M) | C19: ='Historical Financials'!C20 -> -523.16659 | D19: ='Historical Financials'!D20 -> -371.67993 | E19: ='Historical Financials'!E20 -> -309.06155 | G19: ='Historical Financials'!G20 -> -136.26446 | H19: ='Historical Financials'!H20 -> -154.38537 | I19: ='Historical Financials'!I20 -> -96.270785 | J19: ='Historical Financials'!J20 -> -136.24597 | K19: ='Historical Financials'!K20 -> -74.05317 | L19: ='Historical Financials'!L20 -> -81.772555 | M19: ='Historical Financials'!M20 -> -78.908538 | N19: ='Historical Financials'!N20 -> -136.94567 | ... U19: ='Historical Financials'!U20 -> -85 | W19: =SUM(F19:I19) -> -386.92062 | X19: =SUM(G19:J19) -> -523.16659 | Y19: =SUM(H19:K19) -> -460.9553 | Z19: =SUM(I19:L19) -> -388.34248 | AA19: =SUM(J19:M19) -> -370.98024 | AB19: =SUM(K19:N19) -> -371.67993 | AC19: =SUM(L19:O19) -> -373.98115 | AD19: =SUM(M19:P19) -> -368.95125 | ... AI19: =SUM(R19:U19) -> -338.08797 | AK19: =SUM(AI19/AE19)-1 -> -0.048940303
B20: (-) Customer service and operations | C20: ='Historical Financials'!C21 -> -285.51807 | D20: ='Historical Financials'!D21 -> -238.31196 | E20: ='Historical Financials'!E21 -> -192.41582 | G20: ='Historical Financials'!G21 -> -78.401399 | H20: ='Historical Financials'!H21 -> -80.958778 | I20: ='Historical Financials'!I21 -> -60.835907 | J20: ='Historical Financials'!J21 -> -65.321982 | K20: ='Historical Financials'!K21 -> -62.666632 | L20: ='Historical Financials'!L21 -> -53.704776 | M20: ='Historical Financials'!M21 -> -52.34587 | N20: ='Historical Financials'!N21 -> -69.594678 | ... U20: ='Historical Financials'!U21 -> -50 | W20: =SUM(F20:I20) -> -220.19608 | X20: =SUM(G20:J20) -> -285.51807 | Y20: =SUM(H20:K20) -> -269.7833 | Z20: =SUM(I20:L20) -> -242.5293 | AA20: =SUM(J20:M20) -> -234.03926 | AB20: =SUM(K20:N20) -> -238.31196 | AC20: =SUM(L20:O20) -> -232.50033 | AD20: =SUM(M20:P20) -> -226.17556 | ... AI20: =SUM(R20:U20) -> -194.45872 | AK20: =SUM(AI20/AE20)-1 -> -0.099090507
B21: (-) General and Administrative (G&A) | C21: ='Historical Financials'!C22 -> -248.72763 | D21: ='Historical Financials'!D22 -> -247.95489 | E21: ='Historical Financials'!E22 -> -226.7649 | G21: ='Historical Financials'!G22 -> -65.534632 | H21: ='Historical Financials'!H22 -> -53.049638 | I21: ='Historical Financials'!I22 -> -61.373631 | J21: ='Historical Financials'!J22 -> -68.769733 | K21: ='Historical Financials'!K22 -> -60.081628 | L21: ='Historical Financials'!L22 -> -55.965976 | M21: ='Historical Financials'!M22 -> -50.3652 | N21: ='Historical Financials'!N22 -> -81.542083 | ... U21: ='Historical Financials'!U22 -> -63 | W21: =SUM(F21:I21) -> -179.9579 | X21: =SUM(G21:J21) -> -248.72763 | Y21: =SUM(H21:K21) -> -243.27463 | Z21: =SUM(I21:L21) -> -246.19097 | AA21: =SUM(J21:M21) -> -235.18254 | AB21: =SUM(K21:N21) -> -247.95489 | AC21: =SUM(L21:O21) -> -238.33184 | AD21: =SUM(M21:P21) -> -239.93055 | ... AI21: =SUM(R21:U21) -> -246.12145 | AK21: =SUM(AI21/AE21)-1 -> 0.020078031
B22: (-) Restructuring Charges | C22: ='Historical Financials'!C23 -> -35.728705 | D22: ='Historical Financials'!D23 -> -5.308423 | E22: ='Historical Financials'!E23 -> -5.7080184 | G22: ='Historical Financials'!G23 -> 0 | H22: ='Historical Financials'!H23 -> -34.404786 | I22: ='Historical Financials'!I23 -> 1.1317286 | J22: ='Historical Financials'!J23 -> -2.4556476 | K22: ='Historical Financials'!K23 -> 0 | L22: ='Historical Financials'!L23 -> -2.204065 | M22: ='Historical Financials'!M23 -> 0.021758 | N22: ='Historical Financials'!N23 -> -3.126116 | ... U22: ='Historical Financials'!U23 -> -5 | W22: =SUM(F22:I22) -> -33.273058 | X22: =SUM(G22:J22) -> -35.728705 | Y22: =SUM(H22:K22) -> -35.728705 | Z22: =SUM(I22:L22) -> -3.527984 | AA22: =SUM(J22:M22) -> -4.6379546 | AB22: =SUM(K22:N22) -> -5.308423 | AC22: =SUM(L22:O22) -> -5.308423 | AD22: =SUM(M22:P22) -> -3.104358 | ... AI22: =SUM(R22:U22) -> -3.5729162 | AK22: =SUM(AI22/AE22)-1 -> -0.4088347
B23: (-) Share based Payments | C23: ='Historical Financials'!C24 -> -56.314768 | D23: ='Historical Financials'!D24 -> -42.596111 | E23: ='Historical Financials'!E24 -> -91.840168 | G23: ='Historical Financials'!G24 -> -18.302156 | H23: ='Historical Financials'!H24 -> -16.410189 | I23: ='Historical Financials'!I24 -> -8.6047788 | J23: ='Historical Financials'!J24 -> -12.997645 | K23: ='Historical Financials'!K24 -> -9.8012168 | L23: ='Historical Financials'!L24 -> -12.632712 | M23: ='Historical Financials'!M24 -> -8.7612611 | N23: ='Historical Financials'!N24 -> -11.400921 | ... U23: ='Historical Financials'!U24 -> -39 | W23: =SUM(F23:I23) -> -43.317123 | X23: =SUM(G23:J23) -> -56.314768 | Y23: =SUM(H23:K23) -> -47.813829 | Z23: =SUM(I23:L23) -> -44.036353 | AA23: =SUM(J23:M23) -> -44.192836 | AB23: =SUM(K23:N23) -> -42.596111 | AC23: =SUM(L23:O23) -> -38.203818 | AD23: =SUM(M23:P23) -> -34.453748 | ... AI23: =SUM(R23:U23) -> -181.34198 | AK23: =SUM(AI23/AE23)-1 -> 2.956369
B24: (-) IPO Related Charges | C24: ='Historical Financials'!C25 -> 0 | D24: ='Historical Financials'!D25 -> 0 | E24: ='Historical Financials'!E25 -> -15.123364 | G24: ='Historical Financials'!G25 -> 0 | H24: ='Historical Financials'!H25 -> 0 | I24: ='Historical Financials'!I25 -> 0 | J24: ='Historical Financials'!J25 -> 0 | K24: ='Historical Financials'!K25 -> 0 | L24: ='Historical Financials'!L25 -> 0 | M24: ='Historical Financials'!M25 -> 0 | N24: ='Historical Financials'!N25 -> 0 | ... U24: ='Historical Financials'!U25 -> 0 | W24: =SUM(F24:I24) -> 0 | X24: =SUM(G24:J24) -> 0 | Y24: =SUM(H24:K24) -> 0 | Z24: =SUM(I24:L24) -> 0 | AA24: =SUM(J24:M24) -> 0 | AB24: =SUM(K24:N24) -> 0 | AC24: =SUM(L24:O24) -> -1.5503133 | AD24: =SUM(M24:P24) -> -3.8364475 | ... AI24: =SUM(R24:U24) -> -15.58822 | AK24: =SUM(AI24/AE24)-1 -> 0.57862527
B25: (-) Depreciation, amortization and impairments | C25: ='Historical Financials'!C26 -> -161.9695 | D25: ='Historical Financials'!D26 -> -226.06808 | E25: ='Historical Financials'!E26 -> -188.8674 | G25: ='Historical Financials'!G26 -> -29.04236 | H25: ='Historical Financials'!H26 -> -41.805338 | I25: ='Historical Financials'!I26 -> -46.63717 | J25: ='Historical Financials'!J26 -> -44.484636 | K25: ='Historical Financials'!K26 -> -55.639149 | L25: ='Historical Financials'!L26 -> -52.558621 | M25: ='Historical Financials'!M26 -> -40.713393 | N25: ='Historical Financials'!N26 -> -77.156919 | ... U25: ='Historical Financials'!U26 -> -25 | W25: =SUM(F25:I25) -> -117.48487 | X25: =SUM(G25:J25) -> -161.9695 | Y25: =SUM(H25:K25) -> -188.56629 | Z25: =SUM(I25:L25) -> -199.31958 | AA25: =SUM(J25:M25) -> -193.3958 | AB25: =SUM(K25:N25) -> -226.06808 | AC25: =SUM(L25:O25) -> -206.66318 | AD25: =SUM(M25:P25) -> -192.0974 | ... AI25: =SUM(R25:U25) -> -179.09259 | AK25: =SUM(AI25/AE25)-1 -> -0.050474512
B26: Earning before Interest & Taxes (EBIT) | C26: =SUM(C15+SUM(C18:C25)) -> -979.56963 | D26: =SUM(D15+SUM(D18:D25)) -> -323.41189 | E26: =SUM(E15+SUM(E18:E25)) -> -120.61512 | G26: =SUM(G15+SUM(G18:G25)) -> -244.01555 | H26: =SUM(H15+SUM(H18:H25)) -> -341.35269 | I26: =SUM(I15+SUM(I18:I25)) -> -203.73385 | J26: =SUM(J15+SUM(J18:J25)) -> -190.46755 | K26: =SUM(K15+SUM(K18:K25)) -> -102.42208 | L26: =SUM(L15+SUM(L18:L25)) -> -77.128606 | M26: =SUM(M15+SUM(M18:M25)) -> -4.1147128 | N26: =SUM(N15+SUM(N18:N25)) -> -139.74649 | ... U26: =SUM(U15+SUM(U18:U25)) -> -84 | W26: =SUM(W15+SUM(W18:W25)) -> -591.62809 | X26: =SUM(X15+SUM(X18:X25)) -> -718.56963 | Y26: =SUM(Y15+SUM(Y18:Y25)) -> -604.76999 | Z26: =SUM(Z15+SUM(Z18:Z25)) -> -388.03494 | AA26: =SUM(AA15+SUM(AA18:AA25)) -> -246.7681 | AB26: =SUM(AB15+SUM(AB18:AB25)) -> -181.41189 | AC26: =SUM(AC15+SUM(AC18:AC25)) -> -55.006313 | AD26: =SUM(AD15+SUM(AD18:AD25)) -> 39.845293 | ... AI26: =SUM(AI15+SUM(AI18:AI25)) -> -319.4009 | AK26: =SUM(AI26/AE26)-1 -> 0.99457946
B27: Operating Margin (%) | C27: =C26/C8 -> -0.51447985 | D27: =D26/D8 -> -0.14209661 | E27: =E26/E8 -> -0.042908259 | G27: =G26/G8 -> -0.53292663 | H27: =H26/H8 -> -0.70608653 | I27: =I26/I8 -> -0.47039979 | J27: =J26/J8 -> -0.35966408 | K27: =K26/K8 -> -0.21154845 | L27: =L26/L8 -> -0.14441515 | M27: =M26/M8 -> -0.007158769 | N27: =N26/N8 -> -0.20460962 | ... U27: =U26/U8 -> -0.093023256 | W27: =W26/W8 -> -0.56614707 | X27: =X26/X8 -> -0.48948885 | Y27: =Y26/Y8 -> -0.40546602 | Z27: =Z26/Z8 -> -0.25191778 | AA27: =AA26/AA8 -> -0.14959819 | AB27: =AB26/AB8 -> -0.10260853 | AC27: =AC26/AC8 -> -0.029280586 | AD27: =AD26/AD8 -> 0.020197621 | ... AI27: =AI26/AI8 -> -0.099544504 | AK27: =SUM(AI27-AE27)*10000 -> -405.11053
B29: (+) Depreciation, amortization and impairments | C29: =-C25 -> 161.9695 | D29: =-D25 -> 226.06808 | E29: =-E25 -> 188.8674 | G29: =-G25 -> 29.04236 | H29: =-H25 -> 41.805338 | I29: =-I25 -> 46.63717 | J29: =-J25 -> 44.484636 | K29: =-K25 -> 55.639149 | L29: =-L25 -> 52.558621 | M29: =-M25 -> 40.713393 | N29: =-N25 -> 77.156919 | ... U29: =-U25 -> 25 | W29: =SUM(F29:I29) -> 117.48487 | X29: =SUM(G29:J29) -> 161.9695 | Y29: =SUM(H29:K29) -> 188.56629 | Z29: =SUM(I29:L29) -> 199.31958 | AA29: =SUM(J29:M29) -> 193.3958 | AB29: =SUM(K29:N29) -> 226.06808 | AC29: =SUM(L29:O29) -> 206.66318 | AD29: =SUM(M29:P29) -> 192.0974 | ... AI29: =SUM(R29:U29) -> 179.09259 | AK29: =SUM(AI29/AE29)-1 -> -0.050474512
B30: EBITDA | C30: =SUM(C26+C29) -> -817.60013 | D30: =SUM(D26+D29) -> -97.343807 | E30: =SUM(E26+E29) -> 68.252288 | G30: =SUM(G26+G29) -> -214.97319 | H30: =SUM(H26+H29) -> -299.54735 | I30: =SUM(I26+I29) -> -157.09668 | J30: =SUM(J26+J29) -> -145.98291 | K30: =SUM(K26+K29) -> -46.782928 | L30: =SUM(L26+L29) -> -24.569986 | M30: =SUM(M26+M29) -> 36.59868 | N30: =SUM(N26+N29) -> -62.589573 | ... U30: =SUM(U26+U29) -> -59 | W30: =SUM(W26+W29) -> -474.14322 | X30: =SUM(X26+X29) -> -556.60013 | Y30: =SUM(Y26+Y29) -> -416.2037 | Z30: =SUM(Z26+Z29) -> -188.71537 | AA30: =SUM(AA26+AA29) -> -53.372304 | AB30: =SUM(AB26+AB29) -> 44.656193 | AC30: =SUM(AC26+AC29) -> 151.65687 | AD30: =SUM(AD26+AD29) -> 231.94269 | ... AI30: =SUM(AI26+AI29) -> -140.30831 | AK30: =SUM(AI30/AE30)-1 -> -5.9268561
B31: EBITDA Margin (%) | C31: =C30/C8 -> -0.42941183 | D31: =D30/D8 -> -0.042769687 | E31: =E30/E8 -> 0.02428043 | G31: =G30/G8 -> -0.46949851 | H31: =H30/H8 -> -0.61961237 | I31: =I30/I8 -> -0.36271953 | J31: =J30/J8 -> -0.27566276 | K31: =K30/K8 -> -0.096628151 | L31: =L30/L8 -> -0.046004698 | M31: =M30/M8 -> 0.06367431 | N31: =N30/N8 -> -0.091640431 | ... U31: =U30/U8 -> -0.065337763 | W31: =W30/W8 -> -0.45372219 | X31: =X30/X8 -> -0.3791554 | Y31: =Y30/Y8 -> -0.27904238 | Z31: =Z30/Z8 -> -0.12251669 | AA31: =AA30/AA8 -> -0.032355883 | AB31: =AB30/AB8 -> 0.025258028 | AC31: =AC30/AC8 -> 0.080728953 | AD31: =AD30/AD8 -> 0.11757199 | ... AI31: =AI30/AI8 -> -0.043728497 | AK31: =SUM(AI31-AE31)*10000 -> -542.26989
B33: (+) Restructuring Charges | C33: =-C22 -> 35.728705 | D33: =-D22 -> 5.308423 | E33: =-E22 -> 5.7080184 | G33: =-G22 -> 0 | H33: =-H22 -> 34.404786 | I33: =-I22 -> -1.1317286 | J33: =-J22 -> 2.4556476 | K33: =-K22 -> 0 | L33: =-L22 -> 2.204065 | M33: =-M22 -> -0.021758 | N33: =-N22 -> 3.126116 | ... U33: =-U22 -> 5 | W33: =SUM(F33:F33) -> 0 | X33: =SUM(#REF!) -> #REF! | Y33: =SUM(#REF!) -> #REF! | Z33: =SUM(#REF!) -> #REF! | AA33: =SUM(#REF!) -> #REF! | AB33: =SUM(#REF!) -> #REF! | AC33: =SUM(#REF!) -> #REF! | AD33: =SUM(#REF!) -> #REF! | AE33: =SUM(N33:Q33) -> 6.043853 | AF33: =SUM(O33:R33) -> 5.7080184 | AG33: =SUM(P33:S33) -> 5.7080188 | AH33: =SUM(Q33:T33) -> 1.4906532 | AI33: =SUM(R33:U33) -> 3.5729162 | AK33: =SUM(AI33/AE33)-1 -> -0.4088347
B34: (+) Share based Payments | C34: =-C23 -> 56.314768 | D34: =-D23 -> 42.596111 | E34: =-E23 -> 91.840168 | G34: =-G23 -> 18.302156 | H34: =-H23 -> 16.410189 | I34: =-I23 -> 8.6047788 | J34: =-J23 -> 12.997645 | K34: =-K23 -> 9.8012168 | L34: =-L23 -> 12.632712 | M34: =-M23 -> 8.7612611 | N34: =-N23 -> 11.400921 | ... U34: =-U23 -> 39 | AE34: =SUM(N34:Q34) -> 45.835455 | AF34: =SUM(O34:R34) -> 91.840168 | AG34: =SUM(P34:S34) -> 144.97491 | AH34: =SUM(Q34:T34) -> 162.48494 | AI34: =SUM(R34:U34) -> 181.34198 | AK34: =SUM(AI34/AE34)-1 -> 2.956369
B35: (+) IPO Related Charges | C35: =-C24 -> 0 | D35: =-D24 -> 0 | E35: =-E24 -> 15.123364 | G35: =-G24 -> 0 | H35: =-H24 -> 0 | I35: =-I24 -> 0 | J35: =-J24 -> 0 | K35: =-K24 -> 0 | L35: =-L24 -> 0 | M35: =-M24 -> 0 | N35: =-N24 -> 0 | ... U35: =-U24 -> 0 | AE35: =SUM(N35:Q35) -> 9.8745538 | AF35: =SUM(O35:R35) -> 15.123364 | AG35: =SUM(P35:S35) -> 21.955411 | AH35: =SUM(Q35:T35) -> 21.626326 | AI35: =SUM(R35:U35) -> 15.58822 | AK35: =SUM(AI35/AE35)-1 -> 0.57862527
B36: Adj. EBITDA | C36: =+SUM(C30+SUM(C33:C35)) -> -725.55666 | D36: =+SUM(D30+SUM(D33:D35)) -> -49.439273 | E36: =+SUM(E30+SUM(E33:E35)) -> 180.92384 | G36: =+SUM(G30+SUM(G33:G35)) -> -196.67103 | H36: =+SUM(H30+SUM(H33:H35)) -> -248.73238 | I36: =+SUM(I30+SUM(I33:I35)) -> -149.62363 | J36: =+SUM(J30+SUM(J33:J35)) -> -130.52962 | K36: =+SUM(K30+SUM(K33:K35)) -> -36.981711 | L36: =+SUM(L30+SUM(L33:L35)) -> -9.7332083 | M36: =+SUM(M30+SUM(M33:M35)) -> 45.338183 | N36: =+SUM(N30+SUM(N33:N35)) -> -48.062536 | ... U36: =+SUM(U30+SUM(U33:U35)) -> -15 | W36: =+SUM(W30+SUM(W33:W33)) -> -474.14322 | X36: =+SUM(X30+SUM(X33:X33)) -> #REF! | Y36: =+SUM(Y30+SUM(Y33:Y33)) -> #REF! | Z36: =+SUM(Z30+SUM(Z33:Z33)) -> #REF! | AA36: =+SUM(AA30+SUM(AA33:AA33)) -> #REF! | AB36: =+SUM(AB30+SUM(AB33:AB33)) -> #REF! | AC36: =+SUM(AC30+SUM(AC33:AC33)) -> #REF! | AD36: =+SUM(AD30+SUM(AD33:AD33)) -> #REF! | AE36: =+SUM(AE30+SUM(AE33:AE35)) -> 90.232127 | AF36: =+SUM(AF30+SUM(AF33:AF35)) -> 180.92384 | AG36: =+SUM(AG30+SUM(AG33:AG35)) -> 176.83957 | AH36: =+SUM(AH30+SUM(AH33:AH35)) -> 166.97213 | AI36: =+SUM(AI30+SUM(AI33:AI35)) -> 60.194798 | AK36: =SUM(AI36/AE36)-1 -> -0.33288951
B37: Adj. EBITDA Margin (%) | C37: =C36/C8 -> -0.38106967 | D37: =D36/D8 -> -0.021722 | E37: =E36/E8 -> 0.064362803 | G37: =G36/G8 -> -0.42952685 | H37: =H36/H8 -> -0.51450182 | I37: =I36/I8 -> -0.34546505 | J37: =J36/J8 -> -0.24648196 | K37: =K36/K8 -> -0.076384154 | L37: =L36/L8 -> -0.018224403 | M37: =M36/M8 -> 0.07887928 | N37: =N36/N8 -> -0.070370691 | ... U37: =U36/U8 -> -0.016611296 | W37: =W36/W8 -> -0.45372219 | X37: =X36/X8 -> #REF! | Y37: =Y36/Y8 -> #REF! | Z37: =Z36/Z8 -> #REF! | AA37: =AA36/AA8 -> #REF! | AB37: =AB36/AB8 -> #REF! | AC37: =AC36/AC8 -> #REF! | AD37: =AD36/AD8 -> #REF! | ... AI37: =AI36/AI8 -> 0.018760314 | AK37: =SUM(AI37-AE37)*10000 -> -145.03693
B39: (-) Capital Expenditures | C39: =SUM('Historical Financials'!C102:C103) -> -105.55339 | D39: =SUM('Historical Financials'!D102:D103) -> -84.503813 | E39: =SUM('Historical Financials'!E102:E103) -> -45.195623 | G39: =SUM('Historical Financials'!G102:G103) -> -20.196607 | H39: =SUM('Historical Financials'!H102:H103) -> -29.237241 | I39: =SUM('Historical Financials'!I102:I103) -> -28.826542 | J39: =SUM('Historical Financials'!J102:J103) -> -27.292998 | K39: =SUM('Historical Financials'!K102:K103) -> -25.156753 | L39: =SUM('Historical Financials'!L102:L103) -> -21.546709 | M39: =SUM('Historical Financials'!M102:M103) -> -22.004782 | N39: =SUM('Historical Financials'!N102:N103) -> -15.795569 | ... U39: =SUM('Historical Financials'!U102:U103) -> -8.137932 | W39: =SUM(F39:I39) -> -78.26039 | X39: =SUM(G39:J39) -> -105.55339 | Y39: =SUM(H39:K39) -> -110.51353 | Z39: =SUM(I39:L39) -> -102.823 | AA39: =SUM(J39:M39) -> -96.001243 | AB39: =SUM(K39:N39) -> -84.503813 | AC39: =SUM(L39:O39) -> -69.952557 | AD39: =SUM(M39:P39) -> -61.344994 | ... AI39: =SUM(R39:U39) -> -30.938018 | AK39: =SUM(AI39/AE39)-1 -> -0.4056459
B40: (-) Cash Taxes | C40: ='Historical Financials'!C86 -> -21 | D40: ='Historical Financials'!D86 -> -11 | E40: ='Historical Financials'!E86 -> -14.932039 | G40: ='Historical Financials'!G86 -> -5.25 | H40: ='Historical Financials'!H86 -> -5.25 | I40: ='Historical Financials'!I86 -> -5.25 | J40: ='Historical Financials'!J86 -> -5.25 | K40: ='Historical Financials'!K86 -> -2.75 | L40: ='Historical Financials'!L86 -> -2.75 | M40: ='Historical Financials'!M86 -> -2.75 | N40: ='Historical Financials'!N86 -> -2.75 | ... U40: ='Historical Financials'!U86 -> -12 | W40: =SUM(F40:I40) -> -15.75 | X40: =SUM(G40:J40) -> -21 | Y40: =SUM(H40:K40) -> -18.5 | Z40: =SUM(I40:L40) -> -16 | AA40: =SUM(J40:M40) -> -13.5 | AB40: =SUM(K40:N40) -> -11 | AC40: =SUM(L40:O40) -> -13.705293 | AD40: =SUM(M40:P40) -> -19.057531 | ... AI40: =SUM(R40:U40) -> -41.551806 | AK40: =SUM(AI40/AE40)-1 -> 0.72198115
B41: (-) Cash Interest | C41: 0 | D41: 0 | E41: 0 | G41: 0 | H41: 0 | I41: 0 | J41: 0 | K41: 0 | L41: 0 | M41: 0 | N41: 0 | O41: 0 | P41: 0 | Q41: 0 | R41: 0 | S41: 0 | T41: 0 | U41: 0 | W41: =SUM(F41:I41) -> 0 | X41: =SUM(G41:J41) -> 0 | Y41: =SUM(H41:K41) -> 0 | Z41: =SUM(I41:L41) -> 0 | AA41: =SUM(J41:M41) -> 0 | AB41: =SUM(K41:N41) -> 0 | AC41: =SUM(L41:O41) -> 0 | AD41: =SUM(M41:P41) -> 0 | ... AI41: =SUM(R41:U41) -> 0 | AK41: =SUM(AI41/AE41)-1 -> #DIV/0!
B42: (+/-) Changes in NWC | C42: =SUM('Historical Financials'!C94:C98) -> 87.464928 | D42: =SUM('Historical Financials'!D94:D98) -> 366.25236 | E42: =SUM('Historical Financials'!E94:E98) -> -164.79248 | G42: =SUM('Historical Financials'!G94:G98) -> -474.11058 | H42: =SUM('Historical Financials'!H94:H98) -> 271.34606 | I42: =SUM('Historical Financials'!I94:I98) -> 183.87043 | J42: =SUM('Historical Financials'!J94:J98) -> 106.35902 | K42: =SUM('Historical Financials'!K94:K98) -> 416.99236 | L42: =SUM('Historical Financials'!L94:L98) -> -926.28341 | M42: =SUM('Historical Financials'!M94:M98) -> 1022.5803 | N42: =SUM('Historical Financials'!N94:N98) -> -147.03689 | ... U42: =SUM('Historical Financials'!U94:U98) -> -501 | W42: =SUM(F42:I42) -> -18.894089 | X42: =SUM(G42:J42) -> 87.464928 | Y42: =SUM(H42:K42) -> 978.56787 | Z42: =SUM(I42:L42) -> -219.0616 | AA42: =SUM(J42:M42) -> 619.64828 | AB42: =SUM(K42:N42) -> 366.25236 | AC42: =SUM(L42:O42) -> 984.98717 | AD42: =SUM(M42:P42) -> 1367.1756 | ... AI42: =SUM(R42:U42) -> 668.11096 | AK42: =SUM(AI42/AE42)-1 -> 0.84022358
B43: Discretionary Cash-Flows | C43: =SUM(C36+SUM(C39:C42)) -> -764.64512 | D43: =SUM(D36+SUM(D39:D42)) -> 221.30928 | E43: =SUM(E36+SUM(E39:E42)) -> -43.996301 | G43: =SUM(G36+SUM(G39:G42)) -> -696.22822 | H43: =SUM(H36+SUM(H39:H42)) -> -11.873552 | I43: =SUM(I36+SUM(I39:I42)) -> 0.17025812 | J43: =SUM(J36+SUM(J39:J42)) -> -56.713598 | K43: =SUM(K36+SUM(K39:K42)) -> 352.1039 | L43: =SUM(L36+SUM(L39:L42)) -> -960.31333 | M43: =SUM(M36+SUM(M39:M42)) -> 1043.1637 | N43: =SUM(N36+SUM(N39:N42)) -> -213.645 | ... U43: =SUM(U36+SUM(U39:U42)) -> -536.13793 | W43: =SUM(W36+SUM(W39:W42)) -> -587.0477 | X43: =SUM(X36+SUM(X39:X42)) -> #REF! | Y43: =SUM(Y36+SUM(Y39:Y42)) -> #REF! | Z43: =SUM(Z36+SUM(Z39:Z42)) -> #REF! | AA43: =SUM(AA36+SUM(AA39:AA42)) -> #REF! | AB43: =SUM(AB36+SUM(AB39:AB42)) -> #REF! | AC43: =SUM(AC36+SUM(AC39:AC42)) -> #REF! | AD43: =SUM(AD36+SUM(AD39:AD42)) -> #REF! | ... AI43: =SUM(AI36+SUM(AI39:AI42)) -> 655.81594 | AK43: =SUM(AI43/AE43)-1 -> 0.73906484
B45: (-) Issuances / (Share Repurchases) | C45: =SUM('Historical Financials'!C108:C110) -> 801.57006 | D45: =SUM('Historical Financials'!D108:D110) -> 16 | E45: =SUM('Historical Financials'!E108:E110) -> 142.27469 | G45: =SUM('Historical Financials'!G108:G110) -> 27.282163 | H45: =SUM('Historical Financials'!H108:H110) -> -24.712104 | I45: =SUM('Historical Financials'!I108:I110) -> 740.8851 | J45: =SUM('Historical Financials'!J108:J110) -> 58.114898 | K45: =SUM('Historical Financials'!K108:K110) -> 4.567208 | L45: =SUM('Historical Financials'!L108:L110) -> -23.634355 | M45: =SUM('Historical Financials'!M108:M110) -> 33.2458 | N45: =SUM('Historical Financials'!N108:N110) -> 1.8213465 | ... U45: =SUM('Historical Financials'!U108:U110) -> 192.14165 | AE45: =SUM(N45:Q45) -> 145.03666 | AF45: =SUM(O45:R45) -> 142.27469 | AG45: =SUM(P45:S45) -> -2.2089624 | AH45: =SUM(Q45:T45) -> -0.6229224 | AI45: =SUM(R45:U45) -> 191.05937
B46: (-) Debt Issuances / (Repayment) | C46: =SUM('Historical Financials'!C111:C114) -> -747 | D46: =SUM('Historical Financials'!D111:D114) -> -36.268166 | E46: =SUM('Historical Financials'!E111:E114) -> 194.79023 | G46: =SUM('Historical Financials'!G111:G114) -> -285.12033 | H46: =SUM('Historical Financials'!H111:H114) -> -52.72291 | I46: =SUM('Historical Financials'!I111:I114) -> -298.02303 | J46: =SUM('Historical Financials'!J111:J114) -> -111.13373 | K46: =SUM('Historical Financials'!K111:K114) -> -2.1920347 | L46: =SUM('Historical Financials'!L111:L114) -> 9.6580739 | M46: =SUM('Historical Financials'!M111:M114) -> -43.661412 | N46: =SUM('Historical Financials'!N111:N114) -> -0.072793047 | ... U46: =SUM('Historical Financials'!U111:U114) -> 618 | AE46: =SUM(N46:Q46) -> 231.20723 | AF46: =SUM(O46:R46) -> 194.79023 | AG46: =SUM(P46:S46) -> 182.16294 | AH46: =SUM(Q46:T46) -> 160.74412 | AI46: =SUM(R46:U46) -> 748.5102
B47: (+/-) Other Investing Activities | C47: ='Historical Financials'!C104 -> -354 | D47: ='Historical Financials'!D104 -> 1 | E47: ='Historical Financials'!E104 -> 198.71762 | G47: ='Historical Financials'!G104 -> 0 | H47: ='Historical Financials'!H104 -> -354 | I47: ='Historical Financials'!I104 -> 0 | J47: ='Historical Financials'!J104 -> 0 | K47: ='Historical Financials'!K104 -> 0 | L47: ='Historical Financials'!L104 -> 1 | M47: ='Historical Financials'!M104 -> 0 | N47: ='Historical Financials'!N104 -> 0 | ... U47: ='Historical Financials'!U104 -> 0 | AD47: =SUM(M47:P47) -> 0 | AE47: =SUM(N47:Q47) -> 21.717624 | AF47: =SUM(O47:R47) -> 198.71762 | AG47: =SUM(P47:S47) -> 198.71762 | AH47: =SUM(Q47:T47) -> 198.71762 | AI47: =SUM(R47:U47) -> 177
B48: (-) Principal payments under operating lease obligations | C48: ='Historical Financials'!C116 -> -35 | D48: ='Historical Financials'!D116 -> -42 | E48: ='Historical Financials'!E116 -> -25.082499 | G48: ='Historical Financials'!G116 -> -8.75 | H48: ='Historical Financials'!H116 -> -8.75 | I48: ='Historical Financials'!I116 -> -8.75 | J48: ='Historical Financials'!J116 -> -8.75 | K48: ='Historical Financials'!K116 -> -10.5 | L48: ='Historical Financials'!L116 -> -10.5 | M48: ='Historical Financials'!M116 -> -10.5 | N48: ='Historical Financials'!N116 -> -10.5 | ... U48: ='Historical Financials'!U116 -> -1.367124 | AE48: =SUM(N48:Q48) -> -33.878076 | AF48: =SUM(O48:R48) -> -25.082499 | AG48: =SUM(P48:S48) -> -22.370779 | AH48: =SUM(Q48:T48) -> -17.753064 | AI48: =SUM(R48:U48) -> -15.704423
B49: (+/-) Other | D49: =SUM(D54-C54)-SUM(D43:D47) -> 493.80099 | E49: =SUM(E54-D54)-SUM(E43:E48) -> 386.16659 | H49: =SUM(H54-G54)-SUM(H43:H48) -> 106.58215 | I49: =SUM(I54-H54)-SUM(I43:I48) -> 203.21403 | J49: =SUM(J54-I54)-SUM(J43:J48) -> 267.47851 | K49: =SUM(K54-J54)-SUM(K43:K48) -> 124.10596 | L49: =SUM(L54-K54)-SUM(L43:L48) -> 85.255641 | M49: =SUM(M54-L54)-SUM(M43:M48) -> 58.118691 | N49: =SUM(N54-M54)-SUM(N43:N48) -> 268.32069 | O49: =SUM(O54-N54)-SUM(O43:O48) -> 48.863389 | ... U49: =SUM(U54-T54)-SUM(U43:U48) -> 1018.7468 | W49: =SUM(F49:I49) -> 309.79618 | X49: =SUM(G49:J49) -> 577.27468 | Y49: =SUM(H49:K49) -> 701.38065 | Z49: =SUM(I49:L49) -> 680.05414 | AA49: =SUM(J49:M49) -> 534.9588 | AB49: =SUM(K49:N49) -> 535.80099 | AC49: =SUM(L49:O49) -> 460.55841 | AD49: =SUM(M49:P49) -> 530.89094 | ... AI49: =SUM(R49:U49) -> 1194.9938
B50: Free-Cash Flows | C50: =SUM(C43+SUM(C45:C49)) -> -1099.0751 | D50: =SUM(D43+SUM(D45:D49)) -> 653.8421 | E50: =SUM(E43+SUM(E45:E49)) -> 852.87033 | G50: =SUM(G43+SUM(G45:G49)) -> -962.81639 | H50: =SUM(H43+SUM(H45:H49)) -> -345.47642 | I50: =SUM(I43+SUM(I45:I49)) -> 637.49636 | J50: =SUM(J43+SUM(J45:J49)) -> 148.99608 | K50: =SUM(K43+SUM(K45:K49)) -> 468.08503 | L50: =SUM(L43+SUM(L45:L49)) -> -898.53397 | M50: =SUM(M43+SUM(M45:M49)) -> 1080.3668 | N50: =SUM(N43+SUM(N45:N49)) -> 45.924247 | ... U50: =SUM(U43+SUM(U45:U49)) -> 1291.3834 | W50: =SUM(W43+SUM(W45:W49)) -> -277.25153 | X50: =SUM(X43+SUM(X45:X49)) -> #REF! | Y50: =SUM(Y43+SUM(Y45:Y49)) -> #REF! | Z50: =SUM(Z43+SUM(Z45:Z49)) -> #REF! | AA50: =SUM(AA43+SUM(AA45:AA49)) -> #REF! | AB50: =SUM(AB43+SUM(AB45:AB49)) -> #REF! | AC50: =SUM(AC43+SUM(AC45:AC49)) -> #REF! | AD50: =SUM(AD43+SUM(AD45:AD49)) -> #REF! | ... AI50: =SUM(AI43+SUM(AI45:AI49)) -> 2951.6749
B52: Capitalization
B54: Cash & Cash Equivelants | C54: ='Historical Financials'!C49 -> 1694.2579 | D54: ='Historical Financials'!D49 -> 2390.1 | E54: ='Historical Financials'!E49 -> 3242.9703 | G54: ='Historical Financials'!G49 -> 1253.2419 | H54: ='Historical Financials'!H49 -> 907.76546 | I54: ='Historical Financials'!I49 -> 1545.2618 | J54: ='Historical Financials'!J49 -> 1694.2579 | K54: ='Historical Financials'!K49 -> 2162.3429 | L54: ='Historical Financials'!L49 -> 1263.809 | M54: ='Historical Financials'!M49 -> 2344.1758 | N54: ='Historical Financials'!N49 -> 2390.1 | ... U54: ='Historical Financials'!U49 -> 6795 | W54: =I54 -> 1545.2618 | X54: =J54 -> 1694.2579 | Y54: =K54 -> 2162.3429 | Z54: =L54 -> 1263.809 | AA54: =M54 -> 2344.1758 | AB54: =N54 -> 2390.1 | AC54: =O54 -> 3629 | AD54: =P54 -> 3419.4387 | ... AI54: =U54 -> 6795
B55: Total Liquidity | C55: =SUM(C54:C54) -> 1694.2579 | D55: =SUM(D54:D54) -> 2390.1 | E55: =SUM(E54:E54) -> 3242.9703 | G55: =SUM(G54:G54) -> 1253.2419 | H55: =SUM(H54:H54) -> 907.76546 | I55: =SUM(I54:I54) -> 1545.2618 | J55: =SUM(J54:J54) -> 1694.2579 | K55: =SUM(K54:K54) -> 2162.3429 | L55: =SUM(L54:L54) -> 1263.809 | M55: =SUM(M54:M54) -> 2344.1758 | N55: =SUM(N54:N54) -> 2390.1 | ... U55: =SUM(U54:U54) -> 6795 | W55: =SUM(W54:W54) -> 1545.2618 | X55: =SUM(X54:X54) -> 1694.2579 | Y55: =SUM(Y54:Y54) -> 2162.3429 | Z55: =SUM(Z54:Z54) -> 1263.809 | AA55: =SUM(AA54:AA54) -> 2344.1758 | AB55: =SUM(AB54:AB54) -> 2390.1 | AC55: =SUM(AC54:AC54) -> 3629 | AD55: =SUM(AD54:AD54) -> 3419.4387 | ... AI55: =SUM(AI54:AI54) -> 6795
B57: Balance Sheet Metrics:
B58: Consumer receivables | C58: ='Historical Financials'!C51 -> 6756.7639 | D58: ='Historical Financials'!D51 -> 8082.9 | E58: ='Historical Financials'!E51 -> 8141.0163 | G58: ='Historical Financials'!G51 -> 6406.4419 | H58: ='Historical Financials'!H51 -> 6397.3181 | I58: ='Historical Financials'!I51 -> 5649.0709 | J58: ='Historical Financials'!J51 -> 6756.7639 | K58: ='Historical Financials'!K51 -> 6209.947 | L58: ='Historical Financials'!L51 -> 6801.8853 | M58: ='Historical Financials'!M51 -> 6681.2242 | N58: ='Historical Financials'!N51 -> 8082.9 | ... U58: ='Historical Financials'!U51 -> 10095 | W58: =I58 -> 5649.0709 | X58: =J58 -> 6756.7639 | Y58: =K58 -> 6209.947 | Z58: =L58 -> 6801.8853 | AA58: =M58 -> 6681.2242 | AB58: =N58 -> 8082.9 | AC58: =O58 -> 7501.6233 | AD58: =P58 -> 7954.5852 | ... AI58: =U58 -> 10095
B59: Consumer receivables | C59: ='Historical Financials'!C51 -> 6756.7639 | D59: ='Historical Financials'!D51 -> 8082.9 | E59: ='Historical Financials'!E51 -> 8141.0163 | G59: ='Historical Financials'!G51 -> 6406.4419 | H59: ='Historical Financials'!H51 -> 6397.3181 | I59: ='Historical Financials'!I51 -> 5649.0709 | J59: ='Historical Financials'!J51 -> 6756.7639 | K59: ='Historical Financials'!K51 -> 6209.947 | L59: ='Historical Financials'!L51 -> 6801.8853 | M59: ='Historical Financials'!M51 -> 6681.2242 | N59: ='Historical Financials'!N51 -> 8082.9 | ... U59: ='Historical Financials'!U51 -> 10095 | W59: =I59 -> 5649.0709 | X59: =J59 -> 6756.7639 | Y59: =K59 -> 6209.947 | Z59: =L59 -> 6801.8853 | AA59: =M59 -> 6681.2242 | AB59: =N59 -> 8082.9 | AC59: =O59 -> 7501.6233 | AD59: =P59 -> 7954.5852 | ... AI59: =U59 -> 10095
B60: Consumer deposits | C60: ='Historical Financials'!C58 -> 7660.4992 | D60: ='Historical Financials'!D58 -> 9478.2357 | E60: ='Historical Financials'!E58 -> 9510.222 | G60: ='Historical Financials'!G58 -> 6404.2907 | H60: ='Historical Financials'!H58 -> 6342.9924 | I60: ='Historical Financials'!I58 -> 6375.3098 | J60: ='Historical Financials'!J58 -> 7660.4992 | K60: ='Historical Financials'!K58 -> 7497.5427 | L60: ='Historical Financials'!L58 -> 7155.6965 | M60: ='Historical Financials'!M58 -> 7946.2446 | N60: ='Historical Financials'!N58 -> 9478.2357 | ... U60: ='Historical Financials'!U58 -> 13972 | W60: =I60 -> 6375.3098 | X60: =J60 -> 7660.4992 | Y60: =K60 -> 7497.5427 | Z60: =L60 -> 7155.6965 | AA60: =M60 -> 7946.2446 | AB60: =N60 -> 9478.2357 | AC60: =O60 -> 9890.3677 | AD60: =P60 -> 9726.1396 | ... AI60: =U60 -> 13972
B61: Accounts payable and accrued expenses | C61: ='Historical Financials'!C60 -> 437.24043 | D61: ='Historical Financials'!D60 -> 595.77581 | E61: ='Historical Financials'!E60 -> 572.04812 | G61: ='Historical Financials'!G60 -> 411.53388 | H61: ='Historical Financials'!H60 -> 448.34316 | I61: ='Historical Financials'!I60 -> 364.36255 | J61: ='Historical Financials'!J60 -> 437.24043 | K61: ='Historical Financials'!K60 -> 419.77583 | L61: ='Historical Financials'!L60 -> 448.8751 | M61: ='Historical Financials'!M60 -> 464.29795 | N61: ='Historical Financials'!N60 -> 595.77581 | ... U61: ='Historical Financials'!U60 -> 562 | W61: =I61 -> 364.36255 | X61: =J61 -> 437.24043 | Y61: =K61 -> 419.77583 | Z61: =L61 -> 448.8751 | AA61: =M61 -> 464.29795 | AB61: =N61 -> 595.77581 | AC61: =O61 -> 575.11981 | AD61: =P61 -> 684.9762 | ... AI61: =U61 -> 562
B62: Total Assets | C62: ='Historical Financials'!C54 -> 12009.214 | D62: ='Historical Financials'!D54 -> 13746.92 | E62: ='Historical Financials'!E54 -> 13804.542 | G62: ='Historical Financials'!G54 -> 11168.415 | H62: ='Historical Financials'!H54 -> 10984.43 | I62: ='Historical Financials'!I54 -> 10726.19 | J62: ='Historical Financials'!J54 -> 12009.214 | K62: ='Historical Financials'!K54 -> 11586.603 | L62: ='Historical Financials'!L54 -> 11224.865 | M62: ='Historical Financials'!M54 -> 12033.329 | N62: ='Historical Financials'!N54 -> 13746.92 | ... U62: ='Historical Financials'!U54 -> 20782 | W62: =I62 -> 10726.19 | X62: =J62 -> 12009.214 | Y62: =K62 -> 11586.603 | Z62: =L62 -> 11224.865 | AA62: =M62 -> 12033.329 | AB62: =N62 -> 13746.92 | AC62: =O62 -> 14381.899 | AD62: =P62 -> 14629.168 | ... AI62: =U62 -> 20782
B63: Total Liabilities | C63: ='Historical Financials'!C62 -> 9682.2987 | D63: ='Historical Financials'!D62 -> 11550.177 | E63: ='Historical Financials'!E62 -> 11546.573 | G63: ='Historical Financials'!G62 -> 8790.1649 | H63: ='Historical Financials'!H62 -> 9090.2746 | I63: ='Historical Financials'!I62 -> 8471.6917 | J63: ='Historical Financials'!J62 -> 9682.2987 | K63: ='Historical Financials'!K62 -> 9274.0561 | L63: ='Historical Financials'!L62 -> 9056.5454 | M63: ='Historical Financials'!M62 -> 9835.4169 | N63: ='Historical Financials'!N62 -> 11550.177 | ... U63: ='Historical Financials'!U62 -> 18162 | W63: =I63 -> 8471.6917 | X63: =J63 -> 9682.2987 | Y63: =K63 -> 9274.0561 | Z63: =L63 -> 9056.5454 | AA63: =M63 -> 9835.4169 | AB63: =N63 -> 11550.177 | AC63: =O63 -> 12154.982 | AD63: =P63 -> 12392.368 | ... AI63: =U63 -> 18162
B65: Notes payable and other borrowings | C65: ='Historical Financials'!C57 -> 465.83046 | D65: ='Historical Financials'!D57 -> 323.98098 | E65: ='Historical Financials'!E57 -> 512.97118 | G65: ='Historical Financials'!G57 -> 874.71387 | H65: ='Historical Financials'!H57 -> 1137.0308 | I65: ='Historical Financials'!I57 -> 582.5067 | J65: ='Historical Financials'!J57 -> 465.83046 | K65: ='Historical Financials'!K57 -> 297.28842 | L65: ='Historical Financials'!L57 -> 328.50657 | M65: ='Historical Financials'!M57 -> 285.38506 | N65: ='Historical Financials'!N57 -> 323.98098 | ... U65: ='Historical Financials'!U57 -> 2623 | W65: =I65 -> 582.5067 | X65: =J65 -> 465.83046 | Y65: =K65 -> 297.28842 | Z65: =L65 -> 328.50657 | AA65: =M65 -> 285.38506 | AB65: =N65 -> 323.98098 | AC65: =O65 -> 343.43314 | AD65: =P65 -> 534.70785 | ... AI65: =U65 -> 2623
B66: Total Debt | C66: =SUM(C65:C65) -> 465.83046 | D66: =SUM(D65:D65) -> 323.98098 | E66: =SUM(E65:E65) -> 512.97118 | G66: =SUM(G65:G65) -> 874.71387 | H66: =SUM(H65:H65) -> 1137.0308 | I66: =SUM(I65:I65) -> 582.5067 | J66: =SUM(J65:J65) -> 465.83046 | K66: =SUM(K65:K65) -> 297.28842 | L66: =SUM(L65:L65) -> 328.50657 | M66: =SUM(M65:M65) -> 285.38506 | N66: =SUM(N65:N65) -> 323.98098 | ... U66: =SUM(U65:U65) -> 2623 | W66: =SUM(W65:W65) -> 582.5067 | X66: =SUM(X65:X65) -> 465.83046 | Y66: =SUM(Y65:Y65) -> 297.28842 | Z66: =SUM(Z65:Z65) -> 328.50657 | AA66: =SUM(AA65:AA65) -> 285.38506 | AB66: =SUM(AB65:AB65) -> 323.98098 | AC66: =SUM(AC65:AC65) -> 343.43314 | AD66: =SUM(AD65:AD65) -> 534.70785 | ... AI66: =SUM(AI65:AI65) -> 2623
B68: Total Shareholder Equity | C68: ='Historical Financials'!C72 -> 2327 | D68: ='Historical Financials'!D72 -> 2197 | E68: ='Historical Financials'!E72 -> 2257.9696 | G68: ='Historical Financials'!G72 -> 2378.2504 | H68: ='Historical Financials'!H72 -> 1894.1558 | I68: ='Historical Financials'!I72 -> 2254.498 | J68: ='Historical Financials'!J72 -> 2327 | K68: ='Historical Financials'!K72 -> 2312.547 | L68: ='Historical Financials'!L72 -> 2168.3191 | M68: ='Historical Financials'!M72 -> 2197.9121 | N68: ='Historical Financials'!N72 -> 2197 | ... U68: ='Historical Financials'!U72 -> 2620 | W68: =I68 -> 2254.498 | X68: =J68 -> 2327 | Y68: =K68 -> 2312.547 | Z68: =L68 -> 2168.3191 | AA68: =M68 -> 2197.9121 | AB68: =N68 -> 2197 | AC68: =O68 -> 2227.1712 | AD68: =P68 -> 2236.8001 | ... AI68: =U68 -> 2620
B69: Total Book Capitalization | C69: =SUM(C66:C68) -> 2792.8305 | D69: =SUM(D66:D68) -> 2520.981 | E69: =SUM(E66:E68) -> 2770.9408 | G69: =SUM(G66:G68) -> 3252.9643 | H69: =SUM(H66:H68) -> 3031.1866 | I69: =SUM(I66:I68) -> 2837.0047 | J69: =SUM(J66:J68) -> 2792.8305 | K69: =SUM(K66:K68) -> 2609.8354 | L69: =SUM(L66:L68) -> 2496.8257 | M69: =SUM(M66:M68) -> 2483.2971 | N69: =SUM(N66:N68) -> 2520.981 | ... U69: =SUM(U66:U68) -> 5243 | W69: =SUM(W66:W68) -> 2837.0047 | X69: =SUM(X66:X68) -> 2792.8305 | Y69: =SUM(Y66:Y68) -> 2609.8354 | Z69: =SUM(Z66:Z68) -> 2496.8257 | AA69: =SUM(AA66:AA68) -> 2483.2971 | AB69: =SUM(AB66:AB68) -> 2520.981 | AC69: =SUM(AC66:AC68) -> 2570.6043 | AD69: =SUM(AD66:AD68) -> 2771.5079 | ... AI69: =SUM(AI66:AI68) -> 5243
B71: Credit Metrics
B73: LTM Total Leverage | C73: =C66/C36 -> -0.64203181 | D73: =D66/D36 -> -6.5531096 | E73: =E66/E36 -> 2.835288 | J73: =SUM(J66/SUM(G36:J36)) -> -0.64203181 | K73: =SUM(K66/SUM(H36:K36)) -> -0.5253677 | L73: =SUM(L66/SUM(I36:L36)) -> -1.0050124 | M73: =SUM(M66/SUM(J36:M36)) -> -2.1635429 | N73: =SUM(N66/SUM(K36:N36)) -> -6.5531096 | O73: =SUM(O66/SUM(L36:O36)) -> -67.758505 | P73: =SUM(P66/SUM(M36:P36)) -> 12.209898 | Q73: =SUM(Q66/SUM(N36:Q36)) -> 5.960379 | ... U73: =SUM(U66/SUM(R36:U36)) -> 43.575194 | W73: =W66/W36 -> -1.2285459 | X73: =X66/X36 -> #REF! | Y73: =Y66/Y36 -> #REF! | Z73: =Z66/Z36 -> #REF! | AA73: =AA66/AA36 -> #REF! | AB73: =AB66/AB36 -> #REF! | AC73: =AC66/AC36 -> #REF! | AD73: =AD66/AD36 -> #REF! | ... AI73: =AI66/AI36 -> 43.575194
B74: LTM Net Leverage | C74: =SUM(C66-C54)/C36 -> 1.6930827 | D74: =SUM(D66-D54)/D36 -> 41.791048 | E74: =SUM(E66-E54)/E36 -> -15.089218 | J74: =SUM(J66-J54)/SUM(G36:J36) -> 1.6930827 | K74: =SUM(K66-K54)/SUM(H36:K36) -> 3.2959219 | L74: =SUM(L66-L54)/SUM(I36:L36) -> 2.8614056 | M74: =SUM(M66-M54)/SUM(J36:M36) -> 15.607972 | N74: =SUM(N66-N54)/SUM(K36:N36) -> 41.791048 | O74: =SUM(O66-O54)/SUM(L36:O36) -> 648.23418 | P74: =SUM(P66-P54)/SUM(M36:P36) -> -65.871989 | Q74: =SUM(Q66-Q54)/SUM(N36:Q36) -> -36.633376 | ... U74: =SUM(U66-U54)/SUM(R36:U36) -> -69.308315 | W74: =SUM(W66-W54)/W36 -> 2.0305154 | X74: =SUM(X66-X54)/X36 -> #REF! | Y74: =SUM(Y66-Y54)/Y36 -> #REF! | Z74: =SUM(Z66-Z54)/Z36 -> #REF! | AA74: =SUM(AA66-AA54)/AA36 -> #REF! | AB74: =SUM(AB66-AB54)/AB36 -> #REF! | AC74: =SUM(AC66-AC54)/AC36 -> #REF! | AD74: =SUM(AD66-AD54)/AD36 -> #REF! | ... AI74: =SUM(AI66-AI54)/AI36 -> -69.308315
B75: LTM Interest Coverage | C75: =C36/-C41 -> #DIV/0! | D75: =D36/-D41 -> #DIV/0! | E75: =E36/-E41 -> #DIV/0! | J75: {=SUM(G36:J36)/SUM(-G41:J41)} -> #DIV/0! | K75: {=SUM(H36:K36)/SUM(-H41:K41)} -> #DIV/0! | L75: {=SUM(I36:L36)/SUM(-I41:L41)} -> #DIV/0! | M75: {=SUM(J36:M36)/SUM(-J41:M41)} -> #DIV/0! | N75: {=SUM(K36:N36)/SUM(-K41:N41)} -> #DIV/0! | O75: {=SUM(L36:O36)/SUM(-L41:O41)} -> #DIV/0! | P75: {=SUM(M36:P36)/SUM(-M41:P41)} -> #DIV/0! | Q75: {=SUM(N36:Q36)/SUM(-N41:Q41)} -> #DIV/0! | ... U75: {=SUM(R36:U36)/SUM(-R41:U41)} -> #DIV/0! | W75: =W36/-W41 -> #DIV/0! | X75: =X36/-X41 -> #REF! | Y75: =Y36/-Y41 -> #REF! | Z75: =Z36/-Z41 -> #REF! | AA75: =AA36/-AA41 -> #REF! | AB75: =AB36/-AB41 -> #REF! | AC75: =AC36/-AC41 -> #REF! | AD75: =AD36/-AD41 -> #REF! | ... AI75: =AI36/-AI41 -> #DIV/0!
B76: LTM Debt Service Coverage | C76: {=SUM(C36+C39)/SUM(-C40:C41)} -> -39.576669 | D76: {=SUM(D36+D39)/SUM(-D40:D41)} -> -12.176644 | E76: {=SUM(E36+E39)/SUM(-E40:E41)} -> 9.0897309 | J76: {=SUM(G36:J36+G39:J39)/SUM(-G40:J41)} -> -39.576669 | K76: {=SUM(H36:K36+H39:K39)/SUM(-H40:K41)} -> -36.561128 | L76: {=SUM(I36:L36+I39:L39)/SUM(-I40:L41)} -> -26.855698 | M76: {=SUM(J36:M36+J39:M39)/SUM(-J40:M41)} -> -16.882044 | N76: {=SUM(K36:N36+K39:N39)/SUM(-K40:N41)} -> -12.176644 | O76: {=SUM(L36:O36+L39:O39)/SUM(-L40:O41)} -> -5.4738738 | P76: {=SUM(M36:P36+M39:P39)/SUM(-M40:P41)} -> -0.92100139 | Q76: {=SUM(N36:Q36+N39:Q39)/SUM(-N40:Q41)} -> 1.5822041 | ... U76: {=SUM(R36:U36+R39:U39)/SUM(-R40:U41)} -> 0.7041037 | W76: {=SUM(W36+W39)/SUM(-W40:W41)} -> -35.073245 | X76: {=SUM(X36+X39)/SUM(-X40:X41)} -> #REF! | Y76: {=SUM(Y36+Y39)/SUM(-Y40:Y41)} -> #REF! | Z76: {=SUM(Z36+Z39)/SUM(-Z40:Z41)} -> #REF! | AA76: {=SUM(AA36+AA39)/SUM(-AA40:AA41)} -> #REF! | AB76: {=SUM(AB36+AB39)/SUM(-AB40:AB41)} -> #REF! | AC76: {=SUM(AC36+AC39)/SUM(-AC40:AC41)} -> #REF! | AD76: {=SUM(AD36+AD39)/SUM(-AD40:AD41)} -> #REF! | ... AI76: {=SUM(AI36+AI39)/SUM(-AI40:AI41)} -> 0.7041037
B77: LTM Fixed Charge Coverage | C77: {=SUM(C36)/SUM(-C39:C41)} -> -5.7332061 | D77: {=SUM(D36)/SUM(-D39:D41)} -> -0.51766805 | E77: {=SUM(E36)/SUM(-E39:E41)} -> 3.0089951 | J77: {=SUM(G36:J36)/SUM(-G39:J41)} -> -5.7332061 | K77: {=SUM(H36:K36)/SUM(-H39:K41)} -> -4.3861083 | L77: {=SUM(I36:L36)/SUM(-I39:L41)} -> -2.7508829 | M77: {=SUM(J36:M36)/SUM(-J39:M41)} -> -1.2046106 | N77: {=SUM(K36:N36)/SUM(-K39:N41)} -> -0.51766805 | O77: {=SUM(L36:O36)/SUM(-L39:O41)} -> -0.060585917 | P77: {=SUM(M36:P36)/SUM(-M39:P41)} -> 0.54467172 | Q77: {=SUM(N36:Q36)/SUM(-N39:Q41)} -> 1.1844066 | ... U77: {=SUM(R36:U36)/SUM(-R39:U41)} -> 0.83038963 | W77: {=SUM(W36)/SUM(-W39:W41)} -> -5.0435194 | X77: {=SUM(X36)/SUM(-X39:X41)} -> #REF! | Y77: {=SUM(Y36)/SUM(-Y39:Y41)} -> #REF! | Z77: {=SUM(Z36)/SUM(-Z39:Z41)} -> #REF! | AA77: {=SUM(AA36)/SUM(-AA39:AA41)} -> #REF! | AB77: {=SUM(AB36)/SUM(-AB39:AB41)} -> #REF! | AC77: {=SUM(AC36)/SUM(-AC39:AC41)} -> #REF! | AD77: {=SUM(AD36)/SUM(-AD39:AD41)} -> #REF! | ... AI77: {=SUM(AI36)/SUM(-AI39:AI41)} -> 0.83038963
B78: Debt-to-Book Capitalization | C78: =C69/C66 -> 5.9953797 | D78: =D69/D66 -> 7.7812624 | E78: =E69/E66 -> 5.4017475 | J78: =J69/J66 -> 5.9953797 | K78: =K69/K66 -> 8.7787994 | L78: =L69/L66 -> 7.6005349 | M78: =M69/M66 -> 8.7015668 | N78: =N69/N66 -> 7.7812624 | O78: =O69/O66 -> 7.4850212 | P78: =P69/P66 -> 5.183219 | Q78: =Q69/Q66 -> 5.3700061 | ... U78: =U69/U66 -> 1.9988563 | W78: =W69/W66 -> 4.8703383 | X78: =X69/X66 -> 5.9953797 | Y78: =Y69/Y66 -> 8.7787994 | Z78: =Z69/Z66 -> 7.6005349 | AA78: =AA69/AA66 -> 8.7015668 | AB78: =AB69/AB66 -> 7.7812624 | AC78: =AC69/AC66 -> 7.4850212 | AD78: =AD69/AD66 -> 5.183219 | ... AI78: =AI69/AI66 -> 1.9988563
