Workbook

Sheet Historical Financials
B2: IonQ, Inc. (NASDAQ: IONQ)
B3: Historical Financials
B4: $ in thousands except per share
A6: X | B6: Income Statement | D6: FYE | H6: Quarterly | R6: Quarterly | AD6: LTM | AJ6: Variance
B7: Fiscal Period | C7: 2021 | D7: 2022 | E7: 2023 | F7: 2024 | H7: 1Q22 | I7: 2Q22 | J7: 3Q22 | K7: 4Q22 | L7: 1Q23 | M7: 2Q23 | N7: 3Q23 | O7: 4Q23 | P7: 1Q24 | Q7: 2Q24 | R7: 3Q24 | S7: 4Q24 | T7: 1Q25 | U7: 2Q25 | V7: 3Q25 | X7: =L7 -> 1Q23 | Y7: =M7 -> 2Q23 | Z7: =N7 -> 3Q23 | AA7: =O7 -> 4Q23 | AB7: =P7 -> 1Q24 | AC7: =Q7 -> 2Q24 | AD7: =R7 -> 3Q24 | AE7: =S7 -> 4Q24 | ... AH7: =V7 -> 3Q25
B8: Fiscal Period End Date | C8: 44561 | D8: 44926 | E8: 45291 | F8: 45657 | H8: 44651 | I8: 44742 | J8: 44834 | K8: 44926 | L8: 45016 | M8: 45107 | N8: 45199 | O8: 45291 | P8: 45382 | Q8: 45473 | R8: 45565 | S8: 45657 | T8: 45747 | U8: 45838 | V8: 45930 | X8: =L8 -> 45016 | Y8: =M8 -> 45107 | Z8: =N8 -> 45199 | AA8: =O8 -> 45291 | AB8: =P8 -> 45382 | AC8: =Q8 -> 45473 | AD8: =R8 -> 45565 | AE8: =S8 -> 45657 | ... AH8: =V8 -> 45930
B10: Consolidated Revenue | C10: 2099 | D10: 11131 | E10: 22042 | F10: 43073 | H10: 1953 | I10: 2608 | J10: 2763 | K10: =SUM(D10-SUM(H10:J10)) -> 3807 | L10: 4285 | M10: 5515 | N10: 6136 | O10: =SUM(E10-SUM(L10:N10)) -> 6106 | P10: 7582 | Q10: 11381 | R10: 12400 | S10: =SUM(F10-SUM(P10:R10)) -> 11710 | T10: 7566 | U10: 20694 | V10: 39866 | X10: =SUM(I10:L10) -> 13463 | Y10: =SUM(J10:M10) -> 16370 | Z10: =SUM(K10:N10) -> 19743 | AA10: =SUM(L10:O10) -> 22042 | AB10: =SUM(M10:P10) -> 25339 | AC10: =SUM(N10:Q10) -> 31205 | AD10: =SUM(O10:R10) -> 37469 | AE10: =SUM(P10:S10) -> 43073 | ... AH10: =SUM(S10:V10) -> 79836 | AJ10: =SUM(AH10/AD10)-1 -> 1.1307214
B11: Total Revenue | C11: =+SUM(C10:C10) -> 2099 | D11: =+SUM(D10:D10) -> 11131 | E11: =+SUM(E10:E10) -> 22042 | F11: =+SUM(F10:F10) -> 43073 | H11: =+SUM(H10:H10) -> 1953 | I11: =+SUM(I10:I10) -> 2608 | J11: =+SUM(J10:J10) -> 2763 | K11: =+SUM(K10:K10) -> 3807 | L11: =+SUM(L10:L10) -> 4285 | M11: =+SUM(M10:M10) -> 5515 | N11: =+SUM(N10:N10) -> 6136 | O11: =+SUM(O10:O10) -> 6106 | ... V11: =+SUM(V10:V10) -> 39866 | X11: =+SUM(X10:X10) -> 13463 | Y11: =+SUM(Y10:Y10) -> 16370 | Z11: =+SUM(Z10:Z10) -> 19743 | AA11: =+SUM(AA10:AA10) -> 22042 | AB11: =+SUM(AB10:AB10) -> 25339 | AC11: =+SUM(AC10:AC10) -> 31205 | AD11: =+SUM(AD10:AD10) -> 37469 | AE11: =+SUM(AE10:AE10) -> 43073 | ... AH11: =+SUM(AH10:AH10) -> 79836 | AJ11: =SUM(AH11/AD11)-1 -> 1.1307214
B13: Cost of Sales | C13: -1040 | D13: -2944 | E13: -8108 | F13: -20597 | H13: -568 | I13: -742 | J13: -733 | K13: =SUM(D13-SUM(H13:J13)) -> -901 | L13: -1036 | M13: -1901 | N13: -2008 | O13: =SUM(E13-SUM(L13:N13)) -> -3163 | P13: -3414 | Q13: -5623 | R13: -6515 | S13: =SUM(F13-SUM(P13:R13)) -> -5045 | T13: -4315 | U13: -8327 | V13: -21253 | X13: =SUM(I13:L13) -> -3412 | Y13: =SUM(J13:M13) -> -4571 | Z13: =SUM(K13:N13) -> -5846 | AA13: =SUM(L13:O13) -> -8108 | AB13: =SUM(M13:P13) -> -10486 | AC13: =SUM(N13:Q13) -> -14208 | AD13: =SUM(O13:R13) -> -18715 | AE13: =SUM(P13:S13) -> -20597 | ... AH13: =SUM(S13:V13) -> -38940 | AJ13: =SUM(AH13/AD13)-1 -> 1.0806839
B14: Gross Profit | C14: =+SUM(C11+SUM(C13:C13)) -> 1059 | D14: =+SUM(D11+SUM(D13:D13)) -> 8187 | E14: =+SUM(E11+SUM(E13:E13)) -> 13934 | F14: =+SUM(F11+SUM(F13:F13)) -> 22476 | H14: =+SUM(H11+SUM(H13:H13)) -> 1385 | I14: =+SUM(I11+SUM(I13:I13)) -> 1866 | J14: =+SUM(J11+SUM(J13:J13)) -> 2030 | K14: =+SUM(K11+SUM(K13:K13)) -> 2906 | L14: =+SUM(L11+SUM(L13:L13)) -> 3249 | M14: =+SUM(M11+SUM(M13:M13)) -> 3614 | N14: =+SUM(N11+SUM(N13:N13)) -> 4128 | O14: =+SUM(O11+SUM(O13:O13)) -> 2943 | ... V14: =+SUM(V11+SUM(V13:V13)) -> 18613 | X14: =+SUM(X11+SUM(X13:X13)) -> 10051 | Y14: =+SUM(Y11+SUM(Y13:Y13)) -> 11799 | Z14: =+SUM(Z11+SUM(Z13:Z13)) -> 13897 | AA14: =+SUM(AA11+SUM(AA13:AA13)) -> 13934 | AB14: =+SUM(AB11+SUM(AB13:AB13)) -> 14853 | AC14: =+SUM(AC11+SUM(AC13:AC13)) -> 16997 | AD14: =+SUM(AD11+SUM(AD13:AD13)) -> 18754 | AE14: =+SUM(AE11+SUM(AE13:AE13)) -> 22476 | ... AH14: =+SUM(AH11+SUM(AH13:AH13)) -> 40896 | AJ14: =SUM(AH14/AD14)-1 -> 1.1806548
B15: Gross Margin (%) | C15: =C14/C11 -> 0.50452596 | D15: =D14/D11 -> 0.73551343 | E15: =E14/E11 -> 0.63215679 | F15: =F14/F11 -> 0.52181181 | H15: =H14/H11 -> 0.70916539 | I15: =I14/I11 -> 0.7154908 | J15: =J14/J11 -> 0.73470865 | K15: =K14/K11 -> 0.76333071 | L15: =L14/L11 -> 0.75822637 | M15: =M14/M11 -> 0.65530372 | N15: =N14/N11 -> 0.67275098 | O15: =O14/O11 -> 0.48198493 | ... V15: =V14/V11 -> 0.46688908 | X15: =X14/X11 -> 0.74656466 | Y15: =Y14/Y11 -> 0.7207697 | Z15: =Z14/Z11 -> 0.70389505 | AA15: =AA14/AA11 -> 0.63215679 | AB15: =AB14/AB11 -> 0.58617151 | AC15: =AC14/AC11 -> 0.54468835 | AD15: =AD14/AD11 -> 0.50052043 | AE15: =AE14/AE11 -> 0.52181181 | ... AH15: =AH14/AH11 -> 0.51225011 | AJ15: =SUM(AH15-AD15)*1000 -> 11.729683
B17: Research and development | C17: -20228 | D17: -43978 | E17: -92321 | F17: -136827 | H17: -7338 | I17: -9653 | J17: -13292 | K17: =SUM(D17-SUM(H17:J17)) -> -13695 | L17: -16233 | M17: -19869 | N17: -24599 | O17: =SUM(E17-SUM(L17:N17)) -> -31620 | P17: -32368 | Q17: -31204 | R17: -33178 | S17: =SUM(F17-SUM(P17:R17)) -> -40077 | T17: -39953 | U17: -103359 | V17: -66298 | X17: =SUM(I17:L17) -> -52873 | Y17: =SUM(J17:M17) -> -63089 | Z17: =SUM(K17:N17) -> -74396 | AA17: =SUM(L17:O17) -> -92321 | AB17: =SUM(M17:P17) -> -108456 | AC17: =SUM(N17:Q17) -> -119791 | AD17: =SUM(O17:R17) -> -128370 | AE17: =SUM(P17:S17) -> -136827 | ... AH17: =SUM(S17:V17) -> -249687 | AJ17: =SUM(AH17/AD17)-1 -> 0.94505726
B18: Sales and marketing | C18: -3233 | D18: -8385 | E18: -18270 | F18: -28395 | H18: -1871 | I18: -2132 | J18: -1969 | K18: =SUM(D18-SUM(H18:J18)) -> -2413 | L18: -2667 | M18: -3575 | N18: -5047 | O18: =SUM(E18-SUM(L18:N18)) -> -6981 | P18: -6701 | Q18: -6137 | R18: -6630 | S18: =SUM(F18-SUM(P18:R18)) -> -8927 | T18: -8610 | U18: -10877 | V18: -14441 | X18: =SUM(I18:L18) -> -9181 | Y18: =SUM(J18:M18) -> -10624 | Z18: =SUM(K18:N18) -> -13702 | AA18: =SUM(L18:O18) -> -18270 | AB18: =SUM(M18:P18) -> -22304 | AC18: =SUM(N18:Q18) -> -24866 | AD18: =SUM(O18:R18) -> -26449 | AE18: =SUM(P18:S18) -> -28395 | ... AH18: =SUM(S18:V18) -> -42855 | AJ18: =SUM(AH18/AD18)-1 -> 0.6202881
B19: General and administrative | C19: -13737 | D19: -35966 | E19: -50722 | F19: -71055 | H19: -9194 | I19: -7558 | J19: -10149 | K19: =SUM(D19-SUM(H19:J19)) -> -9065 | L19: -10581 | M19: -10930 | N19: -13927 | O19: =SUM(E19-SUM(L19:N19)) -> -15284 | P19: -14020 | Q19: -13053 | R19: -14322 | S19: =SUM(F19-SUM(P19:R19)) -> -29660 | T19: -23806 | U19: -48107 | V19: -82505 | X19: =SUM(I19:L19) -> -37353 | Y19: =SUM(J19:M19) -> -40725 | Z19: =SUM(K19:N19) -> -44503 | AA19: =SUM(L19:O19) -> -50722 | AB19: =SUM(M19:P19) -> -54161 | AC19: =SUM(N19:Q19) -> -56284 | AD19: =SUM(O19:R19) -> -56679 | AE19: =SUM(P19:S19) -> -71055 | ... AH19: =SUM(S19:V19) -> -184078 | AJ19: =SUM(AH19/AD19)-1 -> 2.2477284
B20: Depreciation and amortization | C20: -2548 | D20: -5604 | E20: -10375 | F20: -18654 | H20: -1266 | I20: -1451 | J20: -1531 | K20: =SUM(D20-SUM(H20:J20)) -> -1356 | L20: -1791 | M20: -2329 | N20: -2749 | O20: =SUM(E20-SUM(L20:N20)) -> -3506 | P20: -3955 | Q20: -4305 | R20: -4890 | S20: =SUM(F20-SUM(P20:R20)) -> -5504 | T20: -6561 | U20: =-10616 -> -10616 | V20: -24182 | X20: =SUM(I20:L20) -> -6129 | Y20: =SUM(J20:M20) -> -7007 | Z20: =SUM(K20:N20) -> -8225 | AA20: =SUM(L20:O20) -> -10375 | AB20: =SUM(M20:P20) -> -12539 | AC20: =SUM(N20:Q20) -> -14515 | AD20: =SUM(O20:R20) -> -16656 | AE20: =SUM(P20:S20) -> -18654 | ... AH20: =SUM(S20:V20) -> -46863 | AJ20: =SUM(AH20/AD20)-1 -> 1.8135807
B21: Operating Profit | C21: =+SUM(C14+SUM(C17:C20)) -> -38687 | D21: =+SUM(D14+SUM(D17:D20)) -> -85746 | E21: =+SUM(E14+SUM(E17:E20)) -> -157754 | F21: =+SUM(F14+SUM(F17:F20)) -> -232455 | H21: =+SUM(H14+SUM(H17:H20)) -> -18284 | I21: =+SUM(I14+SUM(I17:I20)) -> -18928 | J21: =+SUM(J14+SUM(J17:J20)) -> -24911 | K21: =+SUM(K14+SUM(K17:K20)) -> -23623 | L21: =+SUM(L14+SUM(L17:L20)) -> -28023 | M21: =+SUM(M14+SUM(M17:M20)) -> -33089 | N21: =+SUM(N14+SUM(N17:N20)) -> -42194 | O21: =+SUM(O14+SUM(O17:O20)) -> -54448 | ... V21: =+SUM(V14+SUM(V17:V20)) -> -168813 | X21: =+SUM(X14+SUM(X17:X20)) -> -95485 | Y21: =+SUM(Y14+SUM(Y17:Y20)) -> -109646 | Z21: =+SUM(Z14+SUM(Z17:Z20)) -> -126929 | AA21: =+SUM(AA14+SUM(AA17:AA20)) -> -157754 | AB21: =+SUM(AB14+SUM(AB17:AB20)) -> -182607 | AC21: =+SUM(AC14+SUM(AC17:AC20)) -> -198459 | AD21: =+SUM(AD14+SUM(AD17:AD20)) -> -209400 | AE21: =+SUM(AE14+SUM(AE17:AE20)) -> -232455 | ... AH21: =+SUM(AH14+SUM(AH17:AH20)) -> -482587 | AJ21: =SUM(AH21/AD21)-1 -> 1.304618
B22: Operating Margin (%) | C22: =C21/C11 -> -18.431158 | D22: =D21/D11 -> -7.703351 | E22: =E21/E11 -> -7.1569731 | F22: =F21/F11 -> -5.3967683 | H22: =H21/H11 -> -9.3620072 | I22: =I21/I11 -> -7.2576687 | J22: =J21/J11 -> -9.0159247 | K22: =K21/K11 -> -6.2051484 | L22: =L21/L11 -> -6.53979 | M22: =M21/M11 -> -5.9998187 | N22: =N21/N11 -> -6.8764668 | O22: =O21/O11 -> -8.9171307 | ... V22: =V21/V11 -> -4.2345106 | X22: =X21/X11 -> -7.0924014 | Y22: =Y21/Y11 -> -6.6979841 | Z22: =Z21/Z11 -> -6.4290635 | AA22: =AA21/AA11 -> -7.1569731 | AB22: =AB21/AB11 -> -7.2065591 | AC22: =AC21/AC11 -> -6.3598462 | AD22: =AD21/AD11 -> -5.5886199 | AE22: =AE21/AE11 -> -5.3967683 | ... AH22: =AH21/AH11 -> -6.0447292 | AJ22: =SUM(AH22-AD22)*1000 -> -456.10927
B24: Gain (loss) on change in fair value of warrant liabilities | C24: -63332 | D24: 30136 | E24: -19206 | F24: -117107 | H24: 13448 | I24: 16061 | J24: -1151 | K24: =SUM(D24-SUM(H24:J24)) -> 1778 | L24: -3610 | M24: -15537 | N24: -7640 | O24: =SUM(E24-SUM(L24:N24)) -> 7581 | P24: 8627 | Q24: 6639 | R24: -3868 | S24: =SUM(F24-SUM(P24:R24)) -> -128505 | T24: 38494 | U24: -39577 | V24: -881847 | X24: =SUM(I24:L24) -> 13078 | Y24: =SUM(J24:M24) -> -18520 | Z24: =SUM(K24:N24) -> -25009 | AA24: =SUM(L24:O24) -> -19206 | AB24: =SUM(M24:P24) -> -6969 | AC24: =SUM(N24:Q24) -> 15207 | AD24: =SUM(O24:R24) -> 18979 | AE24: =SUM(P24:S24) -> -117107 | ... AH24: =SUM(S24:V24) -> -1011435 | AJ24: =SUM(AH24/AD24)-1 -> -54.292323
B25: Interest income, net | C25: 64 | D25: 7093 | E25: 19322 | F25: 18249 | H25: 0 | I25: 1259 | J25: 2059 | K25: =SUM(D25-SUM(H25:J25)) -> 3775 | L25: 4231 | M25: 4877 | N25: 5007 | O25: =SUM(E25-SUM(L25:N25)) -> 5207 | P25: 4799 | Q25: 4801 | R25: 4508 | S25: =SUM(F25-SUM(P25:R25)) -> 4141 | T25: 4894 | U25: 7138 | V25: 14437 | X25: =SUM(I25:L25) -> 11324 | Y25: =SUM(J25:M25) -> 14942 | Z25: =SUM(K25:N25) -> 17890 | AA25: =SUM(L25:O25) -> 19322 | AB25: =SUM(M25:P25) -> 19890 | AC25: =SUM(N25:Q25) -> 19814 | AD25: =SUM(O25:R25) -> 19315 | AE25: =SUM(P25:S25) -> 18249 | ... AH25: =SUM(S25:V25) -> 30610 | AJ25: =SUM(AH25/AD25)-1 -> 0.58477867
B26: Other income (expense), net | C26: =28-4259 -> -4231 | D26: 6 | E26: -85 | F26: -275 | H26: 609 | I26: -46 | J26: 20 | K26: =SUM(D26-SUM(H26:J26)) -> -577 | L26: 64 | M26: 31 | N26: 55 | O26: =SUM(E26-SUM(L26:N26)) -> -235 | P26: -134 | Q26: -45 | R26: 15 | S26: =SUM(F26-SUM(P26:R26)) -> -111 | T26: 51 | U26: 232 | V26: =-22847-980 -> -23827 | X26: =SUM(I26:L26) -> -539 | Y26: =SUM(J26:M26) -> -462 | Z26: =SUM(K26:N26) -> -427 | AA26: =SUM(L26:O26) -> -85 | AB26: =SUM(M26:P26) -> -283 | AC26: =SUM(N26:Q26) -> -359 | AD26: =SUM(O26:R26) -> -399 | AE26: =SUM(P26:S26) -> -275 | ... AH26: =SUM(S26:V26) -> -23655 | AJ26: =SUM(AH26/AD26)-1 -> 58.285714
B27: Earning Before Taxes | C27: =SUM(C21+SUM(C24:C26)) -> -106186 | D27: =SUM(D21+SUM(D24:D26)) -> -48511 | E27: =SUM(E21+SUM(E24:E26)) -> -157723 | F27: =SUM(F21+SUM(F24:F26)) -> -331588 | H27: =SUM(H21+SUM(H24:H26)) -> -4227 | I27: =SUM(I21+SUM(I24:I26)) -> -1654 | J27: =SUM(J21+SUM(J24:J26)) -> -23983 | K27: =SUM(K21+SUM(K24:K26)) -> -18647 | L27: =SUM(L21+SUM(L24:L26)) -> -27338 | M27: =SUM(M21+SUM(M24:M26)) -> -43718 | N27: =SUM(N21+SUM(N24:N26)) -> -44772 | O27: =SUM(O21+SUM(O24:O26)) -> -41895 | ... V27: =SUM(V21+SUM(V24:V26)) -> -1060050 | X27: =SUM(X21+SUM(X24:X26)) -> -71622 | Y27: =SUM(Y21+SUM(Y24:Y26)) -> -113686 | Z27: =SUM(Z21+SUM(Z24:Z26)) -> -134475 | AA27: =SUM(AA21+SUM(AA24:AA26)) -> -157723 | AB27: =SUM(AB21+SUM(AB24:AB26)) -> -169969 | AC27: =SUM(AC21+SUM(AC24:AC26)) -> -163797 | AD27: =SUM(AD21+SUM(AD24:AD26)) -> -171505 | AE27: =SUM(AE21+SUM(AE24:AE26)) -> -331588 | ... AH27: =SUM(AH21+SUM(AH24:AH26)) -> -1487067 | AJ27: =SUM(AH27/AD27)-1 -> 7.6706918
B28: EBT Margin (%) | C28: =C27/C11 -> -50.588852 | D28: =D27/D11 -> -4.3581888 | E28: =E27/E11 -> -7.1555666 | F28: =F27/F11 -> -7.6982797 | H28: =H27/H11 -> -2.1643625 | I28: =I27/I11 -> -0.63420245 | J28: =J27/J11 -> -8.6800579 | K28: =K27/K11 -> -4.8980825 | L28: =L27/L11 -> -6.37993 | M28: =M27/M11 -> -7.9271079 | N28: =N27/N11 -> -7.2966102 | O28: =O27/O11 -> -6.861284 | ... V28: =V27/V11 -> -26.590328 | X28: =X27/X11 -> -5.3199138 | Y28: =Y27/Y11 -> -6.944777 | Z28: =Z27/Z11 -> -6.8112749 | AA28: =AA27/AA11 -> -7.1555666 | AB28: =AB27/AB11 -> -6.7078022 | AC28: =AC27/AC11 -> -5.2490627 | AD28: =AD27/AD11 -> -4.5772505 | AE28: =AE27/AE11 -> -7.6982797 | ... AH28: =AH27/AH11 -> -18.626522 | AJ28: =SUM(AH28-AD28)*1000 -> -14049.271
B30: Provision for taxes | C30: 0 | D30: 0 | E30: -48 | F30: -59 | H30: 0 | I30: 0 | J30: 0 | K30: =SUM(D30-SUM(H30:J30)) -> 0 | L30: 0 | M30: 0 | N30: -39 | O30: =SUM(E30-SUM(L30:N30)) -> -9 | P30: -8 | Q30: -15 | R30: -16 | S30: =SUM(F30-SUM(P30:R30)) -> -20 | T30: -12 | U30: 15269 | V30: 4438 | X30: =SUM(I30:L30) -> 0 | Y30: =SUM(J30:M30) -> 0 | Z30: =SUM(K30:N30) -> -39 | AA30: =SUM(L30:O30) -> -48 | AB30: =SUM(M30:P30) -> -56 | AC30: =SUM(N30:Q30) -> -71 | AD30: =SUM(O30:R30) -> -48 | AE30: =SUM(P30:S30) -> -59 | ... AH30: =SUM(S30:V30) -> 19675 | AJ30: =SUM(AH30/AD30)-1 -> -410.89583
B31: Net loss | C31: =SUM(C27+C30) -> -106186 | D31: =SUM(D27+D30) -> -48511 | E31: =SUM(E27+E30) -> -157771 | F31: =SUM(F27+F30) -> -331647 | H31: =SUM(H27+H30) -> -4227 | I31: =SUM(I27+I30) -> -1654 | J31: =SUM(J27+J30) -> -23983 | K31: =SUM(K27+K30) -> -18647 | L31: =SUM(L27+L30) -> -27338 | M31: =SUM(M27+M30) -> -43718 | N31: =SUM(N27+N30) -> -44811 | O31: =SUM(O27+O30) -> -41904 | ... V31: =SUM(V27+V30) -> -1055612 | X31: =SUM(X27+X30) -> -71622 | Y31: =SUM(Y27+Y30) -> -113686 | Z31: =SUM(Z27+Z30) -> -134514 | AA31: =SUM(AA27+AA30) -> -157771 | AB31: =SUM(AB27+AB30) -> -170025 | AC31: =SUM(AC27+AC30) -> -163868 | AD31: =SUM(AD27+AD30) -> -171553 | AE31: =SUM(AE27+AE30) -> -331647 | ... AH31: =SUM(AH27+AH30) -> -1467392 | AJ31: =SUM(AH31/AD31)-1 -> 7.5535782
B32: Net Margin (%) | C32: =C31/C11 -> -50.588852 | D32: =D31/D11 -> -4.3581888 | E32: =E31/E11 -> -7.1577443 | F32: =F31/F11 -> -7.6996494 | H32: =H31/H11 -> -2.1643625 | I32: =I31/I11 -> -0.63420245 | J32: =J31/J11 -> -8.6800579 | K32: =K31/K11 -> -4.8980825 | L32: =L31/L11 -> -6.37993 | M32: =M31/M11 -> -7.9271079 | N32: =N31/N11 -> -7.3029661 | O32: =O31/O11 -> -6.8627579 | ... V32: =V31/V11 -> -26.479005 | X32: =X31/X11 -> -5.3199138 | Y32: =Y31/Y11 -> -6.944777 | Z32: =Z31/Z11 -> -6.8132503 | AA32: =AA31/AA11 -> -7.1577443 | AB32: =AB31/AB11 -> -6.7100122 | AC32: =AC31/AC11 -> -5.2513379 | AD32: =AD31/AD11 -> -4.5785316 | AE32: =AE31/AE11 -> -7.6996494 | ... AH32: =AH31/AH11 -> -18.380079 | AJ32: =SUM(AH32-AD32)*1000 -> -13801.548
B34: Basic shares | C34: 197671.49 | D34: 201551.44 | E34: 208229.52 | F34: 222842.18 | H34: 198140.45 | I34: 199207.57 | J34: 199958.81 | K34: =D34 -> 201551.44 | L34: 201028.32 | M34: 202595.36 | N34: 204704.61 | O34: =E34 -> 208229.52 | P34: 211454.93 | Q34: 214076.15 | R34: 216392.24 | S34: =F34 -> 222842.18 | T34: 247783.09 | U34: 296837.8 | V34: 354279.59 | X34: =L34 -> 201028.32 | Y34: =M34 -> 202595.36 | Z34: =N34 -> 204704.61 | AA34: =O34 -> 208229.52 | AB34: =P34 -> 211454.93 | AC34: =Q34 -> 214076.15 | AD34: =R34 -> 216392.24 | AE34: =S34 -> 222842.18 | ... AH34: =V34 -> 354279.59 | AJ34: =SUM(AH34/AD34)-1 -> 0.63721022
B35: Basic EPS | C35: =C31/C34 -> -0.53718418 | D35: =D31/D34 -> -0.24068794 | E35: =E31/E34 -> -0.75767836 | F35: =F31/F34 -> -1.4882595 | H35: =H31/H34 -> -0.021333353 | I35: =I31/I34 -> -0.0083028972 | J35: =J31/J34 -> -0.1199397 | K35: =K31/K34 -> -0.092517326 | L35: =L31/L34 -> -0.13599079 | M35: =M31/M34 -> -0.21578974 | N35: =N31/N34 -> -0.21890567 | O35: =O31/O34 -> -0.20123948 | ... V35: =V31/V34 -> -2.9796015 | X35: =X31/X34 -> -0.35627816 | Y35: =Y31/Y34 -> -0.5611481 | Z35: =Z31/Z34 -> -0.6571127 | AA35: =AA31/AA34 -> -0.75767836 | AB35: =AB31/AB34 -> -0.80407207 | AC35: =AC31/AC34 -> -0.76546593 | AD35: =AD31/AD34 -> -0.7927872 | AE35: =AE31/AE34 -> -1.4882595 | ... AH35: =AH31/AH34 -> -4.1419038 | AJ35: =SUM(AH35/AD35)-1 -> 4.2244837
B37: Fully Diluted Shares | C37: 137609.62 | D37: 197727.64 | E37: 202576.49 | F37: 213029.36 | H37: 196183.25 | I37: 197214.02 | J37: 198301.24 | K37: =D37 -> 197727.64 | L37: 200112.86 | M37: 201431.49 | N37: 203390.38 | O37: =E37 -> 202576.49 | P37: 208159.44 | Q37: 211637.48 | R37: 214305.05 | S37: =F37 -> 213029.36 | T37: 228759.21 | U37: 250967.45 | V37: 294524.79 | X37: =L37 -> 200112.86 | Y37: =M37 -> 201431.49 | Z37: =N37 -> 203390.38 | AA37: =O37 -> 202576.49 | AB37: =P37 -> 208159.44 | AC37: =Q37 -> 211637.48 | AD37: =R37 -> 214305.05 | AE37: =S37 -> 213029.36 | ... AH37: =V37 -> 294524.79 | AJ37: =SUM(AH37/AD37)-1 -> 0.37432497
B38: Diluted EPS | C38: =C31/C37 -> -0.77164663 | D38: =D31/D37 -> -0.24534253 | E38: =E31/E37 -> -0.77882186 | F38: =F31/F37 -> -1.5568135 | H38: =H31/H37 -> -0.021546182 | I38: =I31/I37 -> -0.0083868276 | J38: =J31/J37 -> -0.12094226 | K38: =K31/K37 -> -0.094306491 | L38: =L31/L37 -> -0.13661291 | M38: =M31/M37 -> -0.21703657 | N38: =N31/N37 -> -0.22032015 | O38: =O31/O37 -> -0.2068552 | ... V38: =V31/V37 -> -3.5841194 | X38: =X31/X37 -> -0.35790804 | Y38: =Y31/Y37 -> -0.56439039 | Z38: =Z31/Z37 -> -0.6613587 | AA38: =AA31/AA37 -> -0.77882186 | AB38: =AB31/AB37 -> -0.81680178 | AC38: =AC31/AC37 -> -0.7742863 | AD38: =AD31/AD37 -> -0.80050842 | AE38: =AE31/AE37 -> -1.5568135 | ... AH38: =AH31/AH37 -> -4.982236 | AJ38: =SUM(AH38/AD38)-1 -> 5.2238396
A40: X | B40: Balance Sheet | D40: FYE | H40: Quarterly | R40: Quarterly | AD40: LTM | AJ40: Variance
B41: =B7 -> Fiscal Period | C41: =C7 -> 2021 | D41: =D7 -> 2022 | E41: =E7 -> 2023 | F41: =F7 -> 2024 | H41: =H7 -> 1Q22 | I41: =I7 -> 2Q22 | J41: =J7 -> 3Q22 | K41: =K7 -> 4Q22 | L41: =L7 -> 1Q23 | M41: =M7 -> 2Q23 | N41: =N7 -> 3Q23 | O41: =O7 -> 4Q23 | ... V41: =V7 -> 3Q25 | X41: =X7 -> 1Q23 | Y41: =Y7 -> 2Q23 | Z41: =Z7 -> 3Q23 | AA41: =AA7 -> 4Q23 | AB41: =AB7 -> 1Q24 | AC41: =AC7 -> 2Q24 | AD41: =AD7 -> 3Q24 | AE41: =AE7 -> 4Q24 | ... AH41: =AH7 -> 3Q25
B42: =B8 -> Fiscal Period End Date | C42: =C8 -> 44561 | D42: =D8 -> 44926 | E42: =E8 -> 45291 | F42: =F8 -> 45657 | H42: =H8 -> 44651 | I42: =I8 -> 44742 | J42: =J8 -> 44834 | K42: =K8 -> 44926 | L42: =L8 -> 45016 | M42: =M8 -> 45107 | N42: =N8 -> 45199 | O42: =O8 -> 45291 | ... V42: =V8 -> 45930 | X42: =X8 -> 45016 | Y42: =Y8 -> 45107 | Z42: =Z8 -> 45199 | AA42: =AA8 -> 45291 | AB42: =AB8 -> 45382 | AC42: =AC8 -> 45473 | AD42: =AD8 -> 45565 | AE42: =AE8 -> 45657 | ... AH42: =AH8 -> 45930
B44: Current Assets
B45: Cash and cash equivalents | C45: 399025 | D45: =44367-D46 -> 42367 | E45: =35665-E46 -> 33249 | F45: =54393-F46 -> 51946 | H45: 86751 | I45: 43968 | J45: 57198 | K45: =D45 -> 42367 | L45: =51901-L46 -> 49901 | M45: =13984-M46 -> 11882 | N45: =37137-N46 -> 34721 | O45: =E45 -> 33249 | P45: =60074-P46 -> 57640 | Q45: =41752-Q46 -> 39313 | R45: =30172-R46 -> 27734 | S45: =F45 -> 51946 | T45: =159681-T46 -> 157002 | U45: =140067-U46 -> 136622 | V45: =346032-V46 -> 339742 | X45: =L45 -> 49901 | Y45: =M45 -> 11882 | Z45: =N45 -> 34721 | AA45: =O45 -> 33249 | AB45: =P45 -> 57640 | AC45: =Q45 -> 39313 | AD45: =R45 -> 27734 | AE45: =S45 -> 51946 | ... AH45: =V45 -> 339742 | AJ45: =SUM(AH45/AD45)-1 -> 11.250018
B46: Restricted Cash | C46: 0 | D46: 2000 | E46: 2416 | F46: 2447 | H46: 0 | I46: 0 | J46: 0 | K46: =D46 -> 2000 | L46: 2000 | M46: 2102 | N46: 2416 | O46: =E46 -> 2416 | P46: 2434 | Q46: 2439 | R46: 2438 | S46: =F46 -> 2447 | T46: 2679 | U46: 3445 | V46: 6290 | AD46: =R46 -> 2438 | AE46: =S46 -> 2447 | AF46: =T46 -> 2679 | AG46: =U46 -> 3445 | AH46: =V46 -> 6290
B47: Short-term investments | C47: 123443 | D47: 311430 | E47: 319776 | F47: 285896 | H47: 329157 | I47: 379383 | J47: 348435 | K47: =D47 -> 311430 | L47: 335966 | M47: 361677 | N47: 346853 | O47: =E47 -> 319776 | P47: 315276 | Q47: 328045 | R47: 335538 | S47: =F47 -> 285896 | T47: 428605 | U47: 406784 | V47: 736333 | X47: =L47 -> 335966 | Y47: =M47 -> 361677 | Z47: =N47 -> 346853 | AA47: =O47 -> 319776 | AB47: =P47 -> 315276 | AC47: =Q47 -> 328045 | AD47: =R47 -> 335538 | AE47: =S47 -> 285896 | ... AH47: =V47 -> 736333 | AJ47: =SUM(AH47/AD47)-1 -> 1.1944847
B48: Accounts receivable | C48: 707 | D48: 3292 | E48: 11467 | F48: 10188 | H48: 569 | I48: 1782 | J48: 2876 | K48: =D48 -> 3292 | L48: 1837 | M48: 2428 | N48: 3033 | O48: =E48 -> 11467 | P48: 9556 | Q48: 7893 | R48: 4137 | S48: =F48 -> 10188 | T48: 9471 | U48: 19114 | V48: 36912 | X48: =L48 -> 1837 | Y48: =M48 -> 2428 | Z48: =N48 -> 3033 | AA48: =O48 -> 11467 | AB48: =P48 -> 9556 | AC48: =Q48 -> 7893 | AD48: =R48 -> 4137 | AE48: =S48 -> 10188 | ... AH48: =V48 -> 36912 | AJ48: =SUM(AH48/AD48)-1 -> 7.9224075
B49: Prepaid expenses and other current assets | C49: 6442 | D49: 12539 | E49: 23081 | F49: 28325 | H49: 5826 | I49: 5113 | J49: 8134 | K49: =D49 -> 12539 | L49: 12638 | M49: 13236 | N49: 16816 | O49: =E49 -> 23081 | P49: 25022 | Q49: 27165 | R49: 25553 | S49: =F49 -> 28325 | T49: 39227 | U49: 59922 | V49: 96025 | X49: =L49 -> 12638 | Y49: =M49 -> 13236 | Z49: =N49 -> 16816 | AA49: =O49 -> 23081 | AB49: =P49 -> 25022 | AC49: =Q49 -> 27165 | AD49: =R49 -> 25553 | AE49: =S49 -> 28325 | ... AH49: =V49 -> 96025 | AJ49: =SUM(AH49/AD49)-1 -> 2.7578758
B50: Total Current Assets | C50: =SUM(C45:C49) -> 529617 | D50: =SUM(D45:D49) -> 371628 | E50: =SUM(E45:E49) -> 389989 | F50: =SUM(F45:F49) -> 378802 | H50: =SUM(H45:H49) -> 422303 | I50: =SUM(I45:I49) -> 430246 | J50: =SUM(J45:J49) -> 416643 | K50: =SUM(K45:K49) -> 371628 | L50: =SUM(L45:L49) -> 402342 | M50: =SUM(M45:M49) -> 391325 | N50: =SUM(N45:N49) -> 403839 | O50: =SUM(O45:O49) -> 389989 | ... V50: =SUM(V45:V49) -> 1215302 | X50: =SUM(X45:X49) -> 400342 | Y50: =SUM(Y45:Y49) -> 389223 | Z50: =SUM(Z45:Z49) -> 401423 | AA50: =SUM(AA45:AA49) -> 387573 | AB50: =SUM(AB45:AB49) -> 407494 | AC50: =SUM(AC45:AC49) -> 402416 | AD50: =SUM(AD45:AD49) -> 395400 | AE50: =SUM(AE45:AE49) -> 378802 | ... AH50: =SUM(AH45:AH49) -> 1215302 | AJ50: =SUM(AH50/AD50)-1 -> 2.0736014
B52: Non-Current Assets
B53: Long-term investments | C53: 80110 | D53: 182001 | E53: 100489 | F53: 23545 | H53: 170460 | I53: 147992 | J53: 150154 | K53: =D53 -> 182001 | L53: 137646 | M53: 133542 | N53: 101115 | O53: =E53 -> 100489 | P53: 59090 | Q53: 32171 | R53: 17131 | S53: =F53 -> 23545 | T53: 108861 | U53: 109902 | V53: 402603 | X53: =L53 -> 137646 | Y53: =M53 -> 133542 | Z53: =N53 -> 101115 | AA53: =O53 -> 100489 | AB53: =P53 -> 59090 | AC53: =Q53 -> 32171 | AD53: =R53 -> 17131 | AE53: =S53 -> 23545 | ... AH53: =V53 -> 402603 | AJ53: =SUM(AH53/AD53)-1 -> 22.50143
B54: Property and equipment, net | C54: 18870 | D54: 26014 | E54: 37515 | F54: 52761 | H54: 21131 | I54: 24872 | J54: 25065 | K54: =D54 -> 26014 | L54: 26488 | M54: 29089 | N54: 35356 | O54: =E54 -> 37515 | P54: 42380 | Q54: 47883 | R54: 49454 | S54: =F54 -> 52761 | T54: 51644 | U54: 58558 | V54: 119564 | X54: =L54 -> 26488 | Y54: =M54 -> 29089 | Z54: =N54 -> 35356 | AA54: =O54 -> 37515 | AB54: =P54 -> 42380 | AC54: =Q54 -> 47883 | AD54: =R54 -> 49454 | AE54: =S54 -> 52761 | ... AH54: =V54 -> 119564 | AJ54: =SUM(AH54/AD54)-1 -> 1.4176811
B55: Operating lease right-of-use assets | C55: 4032 | D55: 3753 | E55: 4613 | F55: 9470 | H55: 3964 | I55: 3894 | J55: 3824 | K55: =D55 -> 3753 | L55: 5796 | M55: 5605 | N55: 5587 | O55: =E55 -> 4613 | P55: 9261 | Q55: 9938 | R55: 10029 | S55: =F55 -> 9470 | T55: 9232 | U55: 11254 | V55: 20940 | X55: =L55 -> 5796 | Y55: =M55 -> 5605 | Z55: =N55 -> 5587 | AA55: =O55 -> 4613 | AB55: =P55 -> 9261 | AC55: =Q55 -> 9938 | AD55: =R55 -> 10029 | AE55: =S55 -> 9470 | ... AH55: =V55 -> 20940 | AJ55: =SUM(AH55/AD55)-1 -> 1.087945
B56: Intangible assets, net | C56: 5841 | D56: 8944 | E56: 15077 | F56: 29469 | H56: 6175 | I56: 6839 | J56: 0 | K56: =D56 -> 8944 | L56: 10051 | M56: 11548 | N56: 13059 | O56: =E56 -> 15077 | P56: 16865 | Q56: 16969 | R56: 17487 | S56: =F56 -> 29469 | T56: 28216 | U56: 143241 | V56: 655909 | X56: =L56 -> 10051 | Y56: =M56 -> 11548 | Z56: =N56 -> 13059 | AA56: =O56 -> 15077 | AB56: =P56 -> 16865 | AC56: =Q56 -> 16969 | AD56: =R56 -> 17487 | AE56: =S56 -> 29469 | ... AH56: =V56 -> 655909 | AJ56: =SUM(AH56/AD56)-1 -> 36.508378
B57: Goodwill | C57: 0 | D57: 742 | E57: 742 | F57: 9904 | H57: 0 | I57: 0 | J57: 7600 | K57: =D57 -> 742 | L57: 742 | M57: 742 | N57: 742 | O57: =E57 -> 742 | P57: 726 | Q57: 719 | R57: 727 | S57: =F57 -> 9904 | T57: 10669 | U57: 370720 | V57: 1865841 | X57: =L57 -> 742 | Y57: =M57 -> 742 | Z57: =N57 -> 742 | AA57: =O57 -> 742 | AB57: =P57 -> 726 | AC57: =Q57 -> 719 | AD57: =R57 -> 727 | AE57: =S57 -> 9904 | ... AH57: =V57 -> 1865841 | AJ57: =SUM(AH57/AD57)-1 -> 2565.4938
B58: Other noncurrent assets | C58: 3558 | D58: 4910 | E58: 5155 | F58: 4437 | H58: 3418 | I58: 3149 | J58: 3315 | K58: =D58 -> 4910 | L58: 4857 | M58: 5001 | N58: 5680 | O58: =E58 -> 5155 | P58: 5612 | Q58: 4900 | R58: 7683 | S58: =F58 -> 4437 | T58: 4468 | U58: 27046 | V58: 39189 | X58: =L58 -> 4857 | Y58: =M58 -> 5001 | Z58: =N58 -> 5680 | AA58: =O58 -> 5155 | AB58: =P58 -> 5612 | AC58: =Q58 -> 4900 | AD58: =R58 -> 7683 | AE58: =S58 -> 4437 | ... AH58: =V58 -> 39189 | AJ58: =SUM(AH58/AD58)-1 -> 4.1007419
B59: Total Assets | C59: =SUM(C53:C58)+C50 -> 642028 | D59: =SUM(D53:D58)+D50 -> 597992 | E59: =SUM(E53:E58)+E50 -> 553580 | F59: =SUM(F53:F58)+F50 -> 508388 | H59: =SUM(H53:H58)+H50 -> 627451 | I59: =SUM(I53:I58)+I50 -> 616992 | J59: =SUM(J53:J58)+J50 -> 606601 | K59: =SUM(K53:K58)+K50 -> 597992 | L59: =SUM(L53:L58)+L50 -> 587922 | M59: =SUM(M53:M58)+M50 -> 576852 | N59: =SUM(N53:N58)+N50 -> 565378 | O59: =SUM(O53:O58)+O50 -> 553580 | ... V59: =SUM(V53:V58)+V50 -> 4319348 | X59: =SUM(X53:X58)+X50 -> 585922 | Y59: =SUM(Y53:Y58)+Y50 -> 574750 | Z59: =SUM(Z53:Z58)+Z50 -> 562962 | AA59: =SUM(AA53:AA58)+AA50 -> 551164 | AB59: =SUM(AB53:AB58)+AB50 -> 541428 | AC59: =SUM(AC53:AC58)+AC50 -> 514996 | AD59: =SUM(AD53:AD58)+AD50 -> 497911 | AE59: =SUM(AE53:AE58)+AE50 -> 508388 | ... AH59: =SUM(AH53:AH58)+AH50 -> 4319348 | AJ59: =SUM(AH59/AD59)-1 -> 7.6749399
B61: Current Liabilities
B62: Accounts payable | C62: 1882 | D62: 3055 | E62: 5599 | F62: 5230 | H62: 1967 | I62: 3680 | J62: 5042 | K62: =D62 -> 3055 | L62: 3597 | M62: 4560 | N62: 6408 | O62: =E62 -> 5599 | P62: 5852 | Q62: 6324 | R62: 4854 | S62: =F62 -> 5230 | T62: 8752 | U62: 8938 | V62: 16970 | X62: =L62 -> 3597 | Y62: =M62 -> 4560 | Z62: =N62 -> 6408 | AA62: =O62 -> 5599 | AB62: =P62 -> 5852 | AC62: =Q62 -> 6324 | AD62: =R62 -> 4854 | AE62: =S62 -> 5230 | ... AH62: =V62 -> 16970 | AJ62: =SUM(AH62/AD62)-1 -> 2.4960857
B63: Accrued expenses | C63: 2647 | D63: 6655 | E63: 18376 | F63: 16424 | H63: 4298 | I63: 4019 | J63: 8177 | K63: =D63 -> 6655 | L63: 9414 | M63: 9251 | N63: 15703 | O63: =E63 -> 18376 | P63: 10541 | Q63: 8925 | R63: 15657 | S63: =F63 -> 16424 | T63: 23595 | U63: 49190 | V63: 91856 | X63: =L63 -> 9414 | Y63: =M63 -> 9251 | Z63: =N63 -> 15703 | AA63: =O63 -> 18376 | AB63: =P63 -> 10541 | AC63: =Q63 -> 8925 | AD63: =R63 -> 15657 | AE63: =S63 -> 16424 | ... AH63: =V63 -> 91856 | AJ63: =SUM(AH63/AD63)-1 -> 4.8667689
B64: Current portion of operating lease liabilities | C64: 568 | D64: 591 | E64: 710 | F64: 3366 | H64: 573 | I64: 577 | J64: 582 | K64: =D64 -> 591 | L64: 610 | M64: 628 | N64: 695 | O64: =E64 -> 710 | P64: 1178 | Q64: 1479 | R64: 3089 | S64: =F64 -> 3366 | T64: 3621 | U64: 5528 | V64: 8599 | X64: =L64 -> 610 | Y64: =M64 -> 628 | Z64: =N64 -> 695 | AA64: =O64 -> 710 | AB64: =P64 -> 1178 | AC64: =Q64 -> 1479 | AD64: =R64 -> 3089 | AE64: =S64 -> 3366 | ... AH64: =V64 -> 8599 | AJ64: =SUM(AH64/AD64)-1 -> 1.7837488
B65: Unearned revenue | C65: 3430 | D65: 8729 | E65: 12087 | F65: 10678 | H65: 3417 | I65: 4885 | J65: 4700 | K65: =D65 -> 8729 | L65: 6294 | M65: 8428 | N65: 5216 | O65: =E65 -> 12087 | P65: 16742 | Q65: 13668 | R65: 8332 | S65: =F65 -> 10678 | T65: 12061 | U65: 16726 | V65: 21855 | X65: =L65 -> 6294 | Y65: =M65 -> 8428 | Z65: =N65 -> 5216 | AA65: =O65 -> 12087 | AB65: =P65 -> 16742 | AC65: =Q65 -> 13668 | AD65: =R65 -> 8332 | AE65: =S65 -> 10678 | ... AH65: =V65 -> 21855 | AJ65: =SUM(AH65/AD65)-1 -> 1.6230197
B66: Current portion of stock option early exercise liabilities | C66: 1164 | D66: 1130 | E66: 392 | F66: 387 | H66: 1130 | I66: 1130 | J66: 1130 | K66: =D66 -> 1130 | L66: 945 | M66: 761 | N66: 576 | O66: =E66 -> 392 | P66: 392 | Q66: 392 | R66: 392 | S66: =F66 -> 387 | T66: 350 | U66: 252 | V66: 0 | X66: =L66 -> 945 | Y66: =M66 -> 761 | Z66: =N66 -> 576 | AA66: =O66 -> 392 | AB66: =P66 -> 392 | AC66: =Q66 -> 392 | AD66: =R66 -> 392 | AE66: =S66 -> 387 | ... AH66: =V66 -> 0 | AJ66: =SUM(AH66/AD66)-1 -> -1
B67: Total Current Liabilities | C67: =SUM(C62:C66) -> 9691 | D67: =SUM(D62:D66) -> 20160 | E67: =SUM(E62:E66) -> 37164 | F67: =SUM(F62:F66) -> 36085 | H67: =SUM(H62:H66) -> 11385 | I67: =SUM(I62:I66) -> 14291 | J67: =SUM(J62:J66) -> 19631 | K67: =SUM(K62:K66) -> 20160 | L67: =SUM(L62:L66) -> 20860 | M67: =SUM(M62:M66) -> 23628 | N67: =SUM(N62:N66) -> 28598 | O67: =SUM(O62:O66) -> 37164 | ... V67: =SUM(V62:V66) -> 139280 | X67: =SUM(X62:X66) -> 20860 | Y67: =SUM(Y62:Y66) -> 23628 | Z67: =SUM(Z62:Z66) -> 28598 | AA67: =SUM(AA62:AA66) -> 37164 | AB67: =SUM(AB62:AB66) -> 34705 | AC67: =SUM(AC62:AC66) -> 30788 | AD67: =SUM(AD62:AD66) -> 32324 | AE67: =SUM(AE62:AE66) -> 36085 | ... AH67: =SUM(AH62:AH66) -> 139280 | AJ67: =SUM(AH67/AD67)-1 -> 3.3088727
B69: Non-Current Liabilities
B70: Operating lease liabilities, net of current portion | C70: 3643 | D70: 3459 | E70: 7395 | F70: 14359 | H70: 3600 | I70: 3556 | J70: 3512 | K70: =D70 -> 3459 | L70: 5624 | M70: 5609 | N70: 6500 | O70: =E70 -> 7395 | P70: 14452 | Q70: 15152 | R70: 15214 | S70: =F70 -> 14359 | T70: 13739 | U70: 13737 | V70: 19917 | X70: =L70 -> 5624 | Y70: =M70 -> 5609 | Z70: =N70 -> 6500 | AA70: =O70 -> 7395 | AB70: =P70 -> 14452 | AC70: =Q70 -> 15152 | AD70: =R70 -> 15214 | AE70: =S70 -> 14359 | ... AH70: =V70 -> 19917 | AJ70: =SUM(AH70/AD70)-1 -> 0.30912318
B71: Unearned revenue, net of current portion | C71: 1533 | D71: 1201 | E71: 447 | F71: 0 | H71: 489 | I71: 616 | J71: 741 | K71: =D71 -> 1201 | L71: 954 | M71: 707 | N71: 457 | O71: =E71 -> 447 | P71: 181 | Q71: 121 | R71: 60 | S71: =F71 -> 0 | T71: 0 | U71: 2770 | V71: 3384 | X71: =L71 -> 954 | Y71: =M71 -> 707 | Z71: =N71 -> 457 | AA71: =O71 -> 447 | AB71: =P71 -> 181 | AC71: =Q71 -> 121 | AD71: =R71 -> 60 | AE71: =S71 -> 0 | ... AH71: =V71 -> 3384 | AJ71: =SUM(AH71/AD71)-1 -> 55.4
B72: Warrant liabilities | C72: 33962 | D72: 3819 | E72: 23004 | F72: 70688 | H72: 20508 | I72: 4447 | J72: 5598 | K72: =D72 -> 3819 | L72: 7429 | M72: 22966 | N72: 30599 | O72: =E72 -> 23004 | P72: 14378 | Q72: 7738 | R72: 11607 | S72: =F72 -> 70688 | T72: 21241 | U72: 58042 | V72: 1768232 | X72: =L72 -> 7429 | Y72: =M72 -> 22966 | Z72: =N72 -> 30599 | AA72: =O72 -> 23004 | AB72: =P72 -> 14378 | AC72: =Q72 -> 7738 | AD72: =R72 -> 11607 | AE72: =S72 -> 70688 | ... AH72: =V72 -> 1768232 | AJ72: =SUM(AH72/AD72)-1 -> 151.34186
B73: Other Non-Current Liabilities (1) | C73: 1969 | D73: =303+839 -> 1142 | E73: =128+448 -> 576 | F73: =3333+61 -> 3394 | H73: 1686 | I73: 1404 | J73: =367+1122 -> 1489 | K73: =D73 -> 1142 | L73: =77+741 -> 818 | M73: =53+643 -> 696 | N73: =183+545 -> 728 | O73: =E73 -> 576 | P73: =27+350 -> 377 | Q73: =110+252 -> 362 | R73: =2869+154 -> 3023 | S73: =F73 -> 3394 | T73: 1667 | U73: 12979 | V73: 100736 | X73: =L73 -> 818 | Y73: =M73 -> 696 | Z73: =N73 -> 728 | AA73: =O73 -> 576 | AB73: =P73 -> 377 | AC73: =Q73 -> 362 | AD73: =R73 -> 3023 | AE73: =S73 -> 3394 | ... AH73: =V73 -> 100736 | AJ73: =SUM(AH73/AD73)-1 -> 32.323189
B74: Total Liabilities | C74: =SUM(C70:C73)+C67 -> 50798 | D74: =SUM(D70:D73)+D67 -> 29781 | E74: =SUM(E70:E73)+E67 -> 68586 | F74: =SUM(F70:F73)+F67 -> 124526 | H74: =SUM(H70:H73)+H67 -> 37668 | I74: =SUM(I70:I73)+I67 -> 24314 | J74: =SUM(J70:J73)+J67 -> 30971 | K74: =SUM(K70:K73)+K67 -> 29781 | L74: =SUM(L70:L73)+L67 -> 35685 | M74: =SUM(M70:M73)+M67 -> 53606 | N74: =SUM(N70:N73)+N67 -> 66882 | O74: =SUM(O70:O73)+O67 -> 68586 | ... V74: =SUM(V70:V73)+V67 -> 2031549 | X74: =SUM(X70:X73)+X67 -> 35685 | Y74: =SUM(Y70:Y73)+Y67 -> 53606 | Z74: =SUM(Z70:Z73)+Z67 -> 66882 | AA74: =SUM(AA70:AA73)+AA67 -> 68586 | AB74: =SUM(AB70:AB73)+AB67 -> 64093 | AC74: =SUM(AC70:AC73)+AC67 -> 54161 | AD74: =SUM(AD70:AD73)+AD67 -> 62228 | AE74: =SUM(AE70:AE73)+AE67 -> 124526 | ... AH74: =SUM(AH70:AH73)+AH67 -> 2031549 | AJ74: =SUM(AH74/AD74)-1 -> 31.646863
B76: Common stock | C76: 19 | D76: 20 | E76: 20 | F76: 22 | H76: 20 | I76: 20 | J76: 20 | K76: =D76 -> 20 | L76: 20 | M76: 20 | N76: 20 | O76: =E76 -> 20 | P76: 21 | Q76: 21 | R76: 22 | S76: =F76 -> 22 | T76: 24 | U76: 27 | V76: 32 | X76: =L76 -> 20 | Y76: =M76 -> 20 | Z76: =N76 -> 20 | AA76: =O76 -> 20 | AB76: =P76 -> 21 | AC76: =Q76 -> 21 | AD76: =R76 -> 22 | AE76: =S76 -> 22 | ... AH76: =V76 -> 32 | AJ76: =SUM(AH76/AD76)-1 -> 0.45454545
B77: Additional paid-in capital | C77: 737150 | D77: 769848 | E77: 839014 | F77: 1067403 | H77: 744469 | I77: 751259 | J77: 760389 | K77: =D77 -> 769848 | L77: 779286 | M77: 794671 | N77: 813439 | O77: =E77 -> 839014 | P77: 873133 | Q77: 893797 | R77: 917048 | S77: =F77 -> 1067403 | T77: 1481007 | U77: 2050344 | V77: 4237882 | X77: =L77 -> 779286 | Y77: =M77 -> 794671 | Z77: =N77 -> 813439 | AA77: =O77 -> 839014 | AB77: =P77 -> 873133 | AC77: =Q77 -> 893797 | AD77: =R77 -> 917048 | AE77: =S77 -> 1067403 | ... AH77: =V77 -> 4237882 | AJ77: =SUM(AH77/AD77)-1 -> 3.6212216
B78: Accumulated deficit | C78: -145791 | D78: -194302 | E78: -352073 | F78: -683720 | H78: -150018 | I78: -151672 | J78: -175655 | K78: =D78 -> -194302 | L78: -221640 | M78: -265358 | N78: -310169 | O78: =E78 -> -352073 | P78: -391665 | Q78: -429226 | R78: -481722 | S78: =F78 -> -683720 | T78: -715972 | U78: -892810 | V78: -1947765 | X78: =L78 -> -221640 | Y78: =M78 -> -265358 | Z78: =N78 -> -310169 | AA78: =O78 -> -352073 | AB78: =P78 -> -391665 | AC78: =Q78 -> -429226 | AD78: =R78 -> -481722 | AE78: =S78 -> -683720 | ... AH78: =V78 -> -1947765 | AJ78: =SUM(AH78/AD78)-1 -> 3.0433383
B79: Accumulated other comprehensive loss | C79: -148 | D79: -7355 | E79: -1967 | F79: 157 | H79: -4688 | I79: -6929 | J79: -9124 | K79: =D79 -> -7355 | L79: -5429 | M79: -6087 | N79: -4794 | O79: =E79 -> -1967 | P79: -1720 | Q79: -1318 | R79: 335 | S79: =F79 -> 157 | T79: -11 | U79: 4072 | V79: -16788 | X79: =L79 -> -5429 | Y79: =M79 -> -6087 | Z79: =N79 -> -4794 | AA79: =O79 -> -1967 | AB79: =P79 -> -1720 | AC79: =Q79 -> -1318 | AD79: =R79 -> 335 | AE79: =S79 -> 157 | ... AH79: =V79 -> -16788 | AJ79: =SUM(AH79/AD79)-1 -> -51.113433
B80: Noncontrolling interests | C80: 0 | D80: 0 | E80: 0 | F80: 0 | H80: 0 | I80: 0 | J80: 0 | K80: =D80 -> 0 | L80: 0 | M80: 0 | N80: 0 | O80: =E80 -> 0 | P80: 0 | Q80: 0 | R80: 0 | S80: =F80 -> 0 | T80: 0 | U80: 16813 | V80: 14438 | X80: =L80 -> 0 | Y80: =M80 -> 0 | Z80: =N80 -> 0 | AA80: =O80 -> 0 | AB80: =P80 -> 0 | AC80: =Q80 -> 0 | AD80: =R80 -> 0 | AE80: =S80 -> 0 | ... AH80: =V80 -> 14438 | AJ80: =SUM(AH80/AD80)-1 -> #DIV/0!
B81: Total stockholders' equity | C81: =SUM(C76:C80) -> 591230 | D81: =SUM(D76:D80) -> 568211 | E81: =SUM(E76:E80) -> 484994 | F81: =SUM(F76:F80) -> 383862 | H81: =SUM(H76:H80) -> 589783 | I81: =SUM(I76:I80) -> 592678 | J81: =SUM(J76:J80) -> 575630 | K81: =SUM(K76:K80) -> 568211 | L81: =SUM(L76:L80) -> 552237 | M81: =SUM(M76:M80) -> 523246 | N81: =SUM(N76:N80) -> 498496 | O81: =SUM(O76:O80) -> 484994 | ... V81: =SUM(V76:V80) -> 2287799 | X81: =SUM(X76:X80) -> 552237 | Y81: =SUM(Y76:Y80) -> 523246 | Z81: =SUM(Z76:Z80) -> 498496 | AA81: =SUM(AA76:AA80) -> 484994 | AB81: =SUM(AB76:AB80) -> 479769 | AC81: =SUM(AC76:AC80) -> 463274 | AD81: =SUM(AD76:AD80) -> 435683 | AE81: =SUM(AE76:AE80) -> 383862 | ... AH81: =SUM(AH76:AH80) -> 2287799 | AJ81: =SUM(AH81/AD81)-1 -> 4.2510633
B82: Total liabilities and stockholders' equity | C82: =SUM(C81+C74) -> 642028 | D82: =SUM(D81+D74) -> 597992 | E82: =SUM(E81+E74) -> 553580 | F82: =SUM(F81+F74) -> 508388 | H82: =SUM(H81+H74) -> 627451 | I82: =SUM(I81+I74) -> 616992 | J82: =SUM(J81+J74) -> 606601 | K82: =SUM(K81+K74) -> 597992 | L82: =SUM(L81+L74) -> 587922 | M82: =SUM(M81+M74) -> 576852 | N82: =SUM(N81+N74) -> 565378 | O82: =SUM(O81+O74) -> 553580 | ... V82: =SUM(V81+V74) -> 4319348 | X82: =SUM(X81+X74) -> 587922 | Y82: =SUM(Y81+Y74) -> 576852 | Z82: =SUM(Z81+Z74) -> 565378 | AA82: =SUM(AA81+AA74) -> 553580 | AB82: =SUM(AB81+AB74) -> 543862 | AC82: =SUM(AC81+AC74) -> 517435 | AD82: =SUM(AD81+AD74) -> 497911 | AE82: =SUM(AE81+AE74) -> 508388 | ... AH82: =SUM(AH81+AH74) -> 4319348 | AJ82: =SUM(AH82/AD82)-1 -> 7.6749399
B84: Balance Check | C84: =C82-C59 -> 0 | D84: =D82-D59 -> 0 | E84: =E82-E59 -> 0 | F84: =F82-F59 -> 0 | H84: =H82-H59 -> 0 | I84: =I82-I59 -> 0 | J84: =J82-J59 -> 0 | K84: =K82-K59 -> 0 | L84: =L82-L59 -> 0 | M84: =M82-M59 -> 0 | N84: =N82-N59 -> 0 | O84: =O82-O59 -> 0 | ... V84: =V82-V59 -> 0 | X84: =X82-X59 -> 2000 | Y84: =Y82-Y59 -> 2102 | Z84: =Z82-Z59 -> 2416 | AA84: =AA82-AA59 -> 2416 | AB84: =AB82-AB59 -> 2434 | AC84: =AC82-AC59 -> 2439 | AD84: =AD82-AD59 -> 0 | AE84: =AE82-AE59 -> 0 | ... AH84: =AH82-AH59 -> 0
B86: 1) Other noncurrent liabilities consists of: Other noncurrent liabilities + Stock option early exercise liabilities, net of current portion.
A88: X | B88: Cash-Flows Statement | D88: FYE | H88: Quarterly | R88: Quarterly | AD88: LTM | AJ88: Variance
B89: =B7 -> Fiscal Period | C89: =C7 -> 2021 | D89: =D7 -> 2022 | E89: =E7 -> 2023 | F89: =F7 -> 2024 | H89: =H7 -> 1Q22 | I89: =I7 -> 2Q22 | J89: =J7 -> 3Q22 | K89: =K7 -> 4Q22 | L89: =L7 -> 1Q23 | M89: =M7 -> 2Q23 | N89: =N7 -> 3Q23 | O89: =O7 -> 4Q23 | ... V89: =V7 -> 3Q25 | X89: =X7 -> 1Q23 | Y89: =Y7 -> 2Q23 | Z89: =Z7 -> 3Q23 | AA89: =AA7 -> 4Q23 | AB89: =AB7 -> 1Q24 | AC89: =AC7 -> 2Q24 | AD89: =AD7 -> 3Q24 | AE89: =AE7 -> 4Q24 | ... AH89: =AH7 -> 3Q25
B90: =B8 -> Fiscal Period End Date | C90: =C8 -> 44561 | D90: =D8 -> 44926 | E90: =E8 -> 45291 | F90: =F8 -> 45657 | H90: =H8 -> 44651 | I90: =I8 -> 44742 | J90: =J8 -> 44834 | K90: =K8 -> 44926 | L90: =L8 -> 45016 | M90: =M8 -> 45107 | N90: =N8 -> 45199 | O90: =O8 -> 45291 | ... V90: =V8 -> 45930 | X90: =X8 -> 45016 | Y90: =Y8 -> 45107 | Z90: =Z8 -> 45199 | AA90: =AA8 -> 45291 | AB90: =AB8 -> 45382 | AC90: =AC8 -> 45473 | AD90: =AD8 -> 45565 | AE90: =AE8 -> 45657 | ... AH90: =AH8 -> 45930
B92: Cash-Flows From Operating Activities
B93: Net income (loss) | C93: =C31 -> -106186 | D93: =D31 -> -48511 | E93: =E31 -> -157771 | F93: =F31 -> -331647 | H93: =H31 -> -4227 | I93: =I31 -> -1654 | J93: =J31 -> -23983 | K93: =K31 -> -18647 | L93: =L31 -> -27338 | M93: =M31 -> -43718 | N93: =N31 -> -44811 | O93: =SUM(E93-SUM(L93:N93)) -> -41904 | P93: =P31 -> -39592 | Q93: =Q31 -> -37561 | R93: =R31 -> -52496 | S93: =SUM(F93-SUM(P93:R93)) -> -201998 | T93: =T31 -> -32252 | U93: =U31 -> -177530 | V93: =V31 -> -1055612 | X93: =SUM(I93:L93) -> -71622 | Y93: =SUM(J93:M93) -> -113686 | Z93: =SUM(K93:N93) -> -134514 | AA93: =SUM(L93:O93) -> -157771 | AB93: =SUM(M93:P93) -> -170025 | AC93: =SUM(N93:Q93) -> -163868 | AD93: =SUM(O93:R93) -> -171553 | AE93: =SUM(P93:S93) -> -331647 | ... AH93: =SUM(S93:V93) -> -1467392 | AJ93: =SUM(AH93/AD93)-1 -> 7.5535782
B95: Adjustments to reconcile net income:
B96: Depreciation and amortization | C96: 2548 | D96: 5604 | E96: 10375 | F96: 18654 | H96: 1266 | I96: =2717-H96 -> 1451 | J96: =4248-I96-H96 -> 1531 | K96: =SUM(D96-SUM(H96:J96)) -> 1356 | L96: 1791 | M96: =4120-L96 -> 2329 | N96: =6869-M96-L96 -> 2749 | O96: =SUM(E96-SUM(L96:N96)) -> 3506 | P96: 3955 | Q96: =8260-P96 -> 4305 | R96: =13150-Q96-P96 -> 4890 | S96: =SUM(F96-SUM(P96:R96)) -> 5504 | T96: 6561 | U96: =17177-T96 -> 10616 | V96: =41359-U96-T96 -> 24182 | X96: =SUM(I96:L96) -> 6129 | Y96: =SUM(J96:M96) -> 7007 | Z96: =SUM(K96:N96) -> 8225 | AA96: =SUM(L96:O96) -> 10375 | AB96: =SUM(M96:P96) -> 12539 | AC96: =SUM(N96:Q96) -> 14515 | AD96: =SUM(O96:R96) -> 16656 | AE96: =SUM(P96:S96) -> 18654 | ... AH96: =SUM(S96:V96) -> 46863 | AJ96: =SUM(AH96/AD96)-1 -> 1.8135807
B97: Stock-based compensation | C97: 7748 | D97: 31456 | E97: 69743 | F97: 106878 | H97: 6672 | I97: =12556-H97 -> 5884 | J97: =22561-I97-H97 -> 10005 | K97: =SUM(D97-SUM(H97:J97)) -> 8895 | L97: 10268 | M97: =21572-L97 -> 11304 | N97: =38549-M97-L97 -> 16977 | O97: =SUM(E97-SUM(L97:N97)) -> 31194 | P97: 22061 | Q97: =43040-P97 -> 20979 | R97: =67607-Q97-P97 -> 24567 | S97: =SUM(F97-SUM(P97:R97)) -> 39271 | T97: 33253 | U97: =132421-T97 -> 99168 | V97: =205366-U97-T97 -> 72945 | X97: =SUM(I97:L97) -> 35052 | Y97: =SUM(J97:M97) -> 40472 | Z97: =SUM(K97:N97) -> 47444 | AA97: =SUM(L97:O97) -> 69743 | AB97: =SUM(M97:P97) -> 81536 | AC97: =SUM(N97:Q97) -> 91211 | AD97: =SUM(O97:R97) -> 98801 | AE97: =SUM(P97:S97) -> 106878 | ... AH97: =SUM(S97:V97) -> 244637 | AJ97: =SUM(AH97/AD97)-1 -> 1.4760579
B98: (Gain) loss on change in fair value of warrant liabilities | C98: 63332 | D98: -30136 | E98: 19206 | F98: 117107 | H98: -13448 | I98: =-29509-H98 -> -16061 | J98: =-28358-I98-H98 -> 1151 | K98: =SUM(D98-SUM(H98:J98)) -> -1778 | L98: 3610 | M98: =19147-L98 -> 15537 | N98: =26787-M98-L98 -> 7640 | O98: =SUM(E98-SUM(L98:N98)) -> -7581 | P98: -8627 | Q98: =-15266-P98 -> -6639 | R98: =-11398-Q98-P98 -> 3868 | S98: =SUM(F98-SUM(P98:R98)) -> 128505 | T98: -38494 | U98: =1083-T98 -> 39577 | V98: =882930-U98-T98 -> 881847 | X98: =SUM(I98:L98) -> -13078 | Y98: =SUM(J98:M98) -> 18520 | Z98: =SUM(K98:N98) -> 25009 | AA98: =SUM(L98:O98) -> 19206 | AB98: =SUM(M98:P98) -> 6969 | AC98: =SUM(N98:Q98) -> -15207 | AD98: =SUM(O98:R98) -> -18979 | AE98: =SUM(P98:S98) -> 117107 | ... AH98: =SUM(S98:V98) -> 1011435 | AJ98: =SUM(AH98/AD98)-1 -> -54.292323
B99: Amortization of premiums and accretion of discounts on available-for-sale securities | C99: 0 | D99: -1577 | E99: -9746 | F99: -8804 | H99: 0 | I99: 0 | J99: 0 | K99: =SUM(D99-SUM(H99:J99)) -> -1577 | L99: 0 | M99: =-4593-L99 -> -4593 | N99: =-7287-M99-L99 -> -2694 | O99: =SUM(E99-SUM(L99:N99)) -> -2459 | P99: -2302 | Q99: =-4787-P99 -> -2485 | R99: =-7086-Q99-P99 -> -2299 | S99: =SUM(F99-SUM(P99:R99)) -> -1718 | T99: -1409 | U99: =-3540-T99 -> -2131 | V99: =-6167-U99-T99 -> -2627 | X99: =SUM(I99:L99) -> -1577 | Y99: =SUM(J99:M99) -> -6170 | Z99: =SUM(K99:N99) -> -8864 | AA99: =SUM(L99:O99) -> -9746 | AB99: =SUM(M99:P99) -> -12048 | AC99: =SUM(N99:Q99) -> -9940 | AD99: =SUM(O99:R99) -> -9545 | AE99: =SUM(P99:S99) -> -8804 | ... AH99: =SUM(S99:V99) -> -7885 | AJ99: =SUM(AH99/AD99)-1 -> -0.17391304
B100: Other Operating, net (1) | C100: =101+528+4259+1335 -> 6223 | D100: =441+520 -> 961 | E100: =1474+520 -> 1994 | F100: =4803+520 -> 5323 | H100: =-490+130 -> -360 | I100: =-1618+260-H100 -> -998 | J100: =-38+390-I100-H100 -> 1710 | K100: =SUM(D100-SUM(H100:J100)) -> 609 | L100: =-1570+130 -> -1440 | M100: =736+260-L100 -> 2436 | N100: =1036+390-M100-L100 -> 430 | O100: =SUM(E100-SUM(L100:N100)) -> 568 | P100: =809+130 -> 939 | Q100: =1896+260-P100 -> 1217 | R100: =3901+390-Q100-P100 -> 2135 | S100: =SUM(F100-SUM(P100:R100)) -> 1032 | T100: 825 | U100: =1502-15300-T100 -> -14623 | V100: =-19885+5872-U100-T100 -> -215 | X100: =SUM(I100:L100) -> -119 | Y100: =SUM(J100:M100) -> 3315 | Z100: =SUM(K100:N100) -> 2035 | AA100: =SUM(L100:O100) -> 1994 | AB100: =SUM(M100:P100) -> 4373 | AC100: =SUM(N100:Q100) -> 3154 | AD100: =SUM(O100:R100) -> 4859 | AE100: =SUM(P100:S100) -> 5323 | ... AH100: =SUM(S100:V100) -> -12981 | AJ100: =SUM(AH100/AD100)-1 -> -3.6715374
K101: =SUM(D101-SUM(H101:J101)) -> 0
B102: Changes in assets and liabilities:
B103: Accounts receivable | C103: -317 | D103: -1510 | E103: -8175 | F103: 1609 | H103: 138 | I103: =-801-H103 -> -939 | J103: =-1135-I103-H103 -> -334 | K103: =SUM(D103-SUM(H103:J103)) -> -375 | L103: 2044 | M103: =2074-L103 -> 30 | N103: =946-M103-L103 -> -1128 | O103: =SUM(E103-SUM(L103:N103)) -> -9121 | P103: 1897 | Q103: =3558-P103 -> 1661 | R103: =7341-Q103-P103 -> 3783 | S103: =SUM(F103-SUM(P103:R103)) -> -5732 | T103: 748 | U103: =-3595-T103 -> -4343 | V103: =-15849-U103-T103 -> -12254 | X103: =SUM(I103:L103) -> 396 | Y103: =SUM(J103:M103) -> 1365 | Z103: =SUM(K103:N103) -> 571 | AA103: =SUM(L103:O103) -> -8175 | AB103: =SUM(M103:P103) -> -8322 | AC103: =SUM(N103:Q103) -> -6691 | AD103: =SUM(O103:R103) -> -1780 | AE103: =SUM(P103:S103) -> 1609 | ... AH103: =SUM(S103:V103) -> -21581 | AJ103: =SUM(AH103/AD103)-1 -> 11.124157
B104: Prepaid expenses and other current assets | C104: -3790 | D104: -7012 | E104: -14413 | F104: -15200 | H104: 1516 | I104: =3576-H104 -> 2060 | J104: =-1842-I104-H104 -> -5418 | K104: =SUM(D104-SUM(H104:J104)) -> -5170 | L104: -939 | M104: =-2928-L104 -> -1989 | N104: =-7545-M104-L104 -> -4617 | O104: =SUM(E104-SUM(L104:N104)) -> -6868 | P104: -4656 | Q104: =-8341-P104 -> -3685 | R104: =-9899-Q104-P104 -> -1558 | S104: =SUM(F104-SUM(P104:R104)) -> -5301 | T104: -12471 | U104: =-25142-T104 -> -12671 | V104: =-42572-U104-T104 -> -17430 | X104: =SUM(I104:L104) -> -9467 | Y104: =SUM(J104:M104) -> -13516 | Z104: =SUM(K104:N104) -> -12715 | AA104: =SUM(L104:O104) -> -14413 | AB104: =SUM(M104:P104) -> -18130 | AC104: =SUM(N104:Q104) -> -19826 | AD104: =SUM(O104:R104) -> -16767 | AE104: =SUM(P104:S104) -> -15200 | ... AH104: =SUM(S104:V104) -> -47873 | AJ104: =SUM(AH104/AD104)-1 -> 1.8551917
B105: Accounts payable | C105: 763 | D105: 1060 | E105: 2188 | F105: -601 | H105: -291 | I105: =1156-H105 -> 1447 | J105: =2992-I105-H105 -> 1836 | K105: =SUM(D105-SUM(H105:J105)) -> -1932 | L105: 728 | M105: =479-L105 -> -249 | N105: =975-M105-L105 -> 496 | O105: =SUM(E105-SUM(L105:N105)) -> 1213 | P105: -521 | Q105: =-165-P105 -> 356 | R105: =-463-Q105-P105 -> -298 | S105: =SUM(F105-SUM(P105:R105)) -> -138 | T105: 3272 | U105: =1094-T105 -> -2178 | V105: =-17413-U105-T105 -> -18507 | X105: =SUM(I105:L105) -> 2079 | Y105: =SUM(J105:M105) -> 383 | Z105: =SUM(K105:N105) -> -957 | AA105: =SUM(L105:O105) -> 2188 | AB105: =SUM(M105:P105) -> 939 | AC105: =SUM(N105:Q105) -> 1544 | AD105: =SUM(O105:R105) -> 750 | AE105: =SUM(P105:S105) -> -601 | ... AH105: =SUM(S105:V105) -> -17551 | AJ105: =SUM(AH105/AD105)-1 -> -24.401333
B106: Accrued expenses | C106: 1259 | D106: 1344 | E106: 3319 | F106: -411 | H106: 1571 | I106: =484-H106 -> -1087 | J106: =1996-I106-H106 -> 1512 | K106: =SUM(D106-SUM(H106:J106)) -> -652 | L106: 920 | M106: =2267-L106 -> 1347 | N106: =8066-M106-L106 -> 5799 | O106: =SUM(E106-SUM(L106:N106)) -> -4747 | P106: -554 | Q106: =-2116-P106 -> -1562 | R106: =612-Q106-P106 -> 2728 | S106: =SUM(F106-SUM(P106:R106)) -> -1023 | T106: 6123 | U106: =20741-T106 -> 14618 | V106: =27777-U106-T106 -> 7036 | X106: =SUM(I106:L106) -> 693 | Y106: =SUM(J106:M106) -> 3127 | Z106: =SUM(K106:N106) -> 7414 | AA106: =SUM(L106:O106) -> 3319 | AB106: =SUM(M106:P106) -> 1845 | AC106: =SUM(N106:Q106) -> -1064 | AD106: =SUM(O106:R106) -> -4135 | AE106: =SUM(P106:S106) -> -411 | ... AH106: =SUM(S106:V106) -> 26754 | AJ106: =SUM(AH106/AD106)-1 -> -7.470133
B107: Unearned revenue | C107: 3605 | D107: 3892 | E107: 2604 | F107: -1752 | H107: -1058 | I107: =264-H107 -> 1322 | J107: =-555-I107-H107 -> -819 | K107: =SUM(D107-SUM(H107:J107)) -> 4447 | L107: -3271 | M107: =-2005-L107 -> 1266 | N107: =-4944-M107-L107 -> -2939 | O107: =SUM(E107-SUM(L107:N107)) -> 7548 | P107: 4389 | Q107: =1262-P107 -> -3127 | R107: =-4232-Q107-P107 -> -5494 | S107: =SUM(F107-SUM(P107:R107)) -> 2480 | T107: 1299 | U107: =-4-T107 -> -1303 | V107: =268-U107-T107 -> 272 | X107: =SUM(I107:L107) -> 1679 | Y107: =SUM(J107:M107) -> 1623 | Z107: =SUM(K107:N107) -> -497 | AA107: =SUM(L107:O107) -> 2604 | AB107: =SUM(M107:P107) -> 10264 | AC107: =SUM(N107:Q107) -> 5871 | AD107: =SUM(O107:R107) -> 3316 | AE107: =SUM(P107:S107) -> -1752 | ... AH107: =SUM(S107:V107) -> 2748 | AJ107: =SUM(AH107/AD107)-1 -> -0.17129071
B108: Other assets and liabilities | C108: -1722 | D108: -269 | E108: 1865 | F108: 3161 | H108: -103 | I108: =-133-H108 -> -30 | J108: =-180-I108-H108 -> -47 | K108: =SUM(D108-SUM(H108:J108)) -> -89 | L108: -188 | M108: =26-L108 -> 214 | N108: =-156-M108-L108 -> -182 | O108: =SUM(E108-SUM(L108:N108)) -> 2021 | P108: 2546 | Q108: =2508-P108 -> -38 | R108: =3471-Q108-P108 -> 963 | S108: =SUM(F108-SUM(P108:R108)) -> -310 | T108: -480 | U108: =-2254-T108 -> -1774 | V108: =-4969-U108-T108 -> -2715 | X108: =SUM(I108:L108) -> -354 | Y108: =SUM(J108:M108) -> -110 | Z108: =SUM(K108:N108) -> -245 | AA108: =SUM(L108:O108) -> 1865 | AB108: =SUM(M108:P108) -> 4599 | AC108: =SUM(N108:Q108) -> 4347 | AD108: =SUM(O108:R108) -> 5492 | AE108: =SUM(P108:S108) -> 3161 | ... AH108: =SUM(S108:V108) -> -5279 | AJ108: =SUM(AH108/AD108)-1 -> -1.9612163
B109: Net cash used in operating activities | C109: =SUM(C93:C108) -> -26537 | D109: =SUM(D93:D108) -> -44698 | E109: =SUM(E93:E108) -> -78811 | F109: =SUM(F93:F108) -> -105683 | H109: =SUM(H93:H108) -> -8324 | I109: =SUM(I93:I108) -> -8605 | J109: =SUM(J93:J108) -> -12856 | K109: =SUM(K93:K108) -> -14913 | L109: =SUM(L93:L108) -> -13815 | M109: =SUM(M93:M108) -> -16086 | N109: =SUM(N93:N108) -> -22280 | O109: =SUM(O93:O108) -> -26630 | ... V109: =SUM(V93:V108) -> -123078 | X109: =SUM(X93:X108) -> -50189 | Y109: =SUM(Y93:Y108) -> -57670 | Z109: =SUM(Z93:Z108) -> -67094 | AA109: =SUM(AA93:AA108) -> -78811 | AB109: =SUM(AB93:AB108) -> -85461 | AC109: =SUM(AC93:AC108) -> -95954 | AD109: =SUM(AD93:AD108) -> -92885 | AE109: =SUM(AE93:AE108) -> -105683 | ... AH109: =SUM(AH93:AH108) -> -248105 | AJ109: =SUM(AH109/AD109)-1 -> 1.6710987
B111: Cash flows from investing activities:
B112: Purchases of property and equipment | C112: -7783 | D112: -9336 | E112: -13703 | F112: -17992 | H112: -2672 | I112: =-7022-H112 -> -4350 | J112: =-8381-I112-H112 -> -1359 | K112: =SUM(D112-SUM(H112:J112)) -> -955 | L112: -1185 | M112: =-2411-L112 -> -1226 | N112: =-6544-M112-L112 -> -4133 | O112: =SUM(E112-SUM(L112:N112)) -> -7159 | P112: -3140 | Q112: =-10629-P112 -> -7489 | R112: =-14399-Q112-P112 -> -3770 | S112: =SUM(F112-SUM(P112:R112)) -> -3593 | T112: -2308 | U112: =-3501-T112 -> -1193 | V112: =-7628-U112-T112 -> -4127 | X112: =SUM(I112:L112) -> -7849 | Y112: =SUM(J112:M112) -> -4725 | Z112: =SUM(K112:N112) -> -7499 | AA112: =SUM(L112:O112) -> -13703 | AB112: =SUM(M112:P112) -> -15658 | AC112: =SUM(N112:Q112) -> -21921 | AD112: =SUM(O112:R112) -> -21558 | AE112: =SUM(P112:S112) -> -17992 | ... AH112: =SUM(S112:V112) -> -11221 | AJ112: =SUM(AH112/AD112)-1 -> -0.47949717
B113: Capitalized software development costs | C113: -1621 | D113: -2179 | E113: -4558 | F113: -3905 | H113: -457 | I113: =-982-H113 -> -525 | J113: =-1491-I113-H113 -> -509 | K113: =SUM(D113-SUM(H113:J113)) -> -688 | L113: -843 | M113: =-1950-L113 -> -1107 | N113: =-3134-M113-L113 -> -1184 | O113: =SUM(E113-SUM(L113:N113)) -> -1424 | P113: -1400 | Q113: =-2129-P113 -> -729 | R113: =-3064-Q113-P113 -> -935 | S113: =SUM(F113-SUM(P113:R113)) -> -841 | T113: -882 | U113: =-1886-T113 -> -1004 | V113: =-2961-U113-T113 -> -1075 | X113: =SUM(I113:L113) -> -2565 | Y113: =SUM(J113:M113) -> -3147 | Z113: =SUM(K113:N113) -> -3822 | AA113: =SUM(L113:O113) -> -4558 | AB113: =SUM(M113:P113) -> -5115 | AC113: =SUM(N113:Q113) -> -4737 | AD113: =SUM(O113:R113) -> -4488 | AE113: =SUM(P113:S113) -> -3905 | ... AH113: =SUM(S113:V113) -> -3802 | AJ113: =SUM(AH113/AD113)-1 -> -0.15285205
B114: Purchases of available-for-sale securities | C114: -203761 | D114: -605689 | E114: -298445 | F114: -296329 | H114: -311235 | I114: =-403899-H114 -> -92664 | J114: =-488887-I114-H114 -> -84988 | K114: =SUM(D114-SUM(H114:J114)) -> -116802 | L114: -64430 | M114: =-185377-L114 -> -120947 | N114: =-230350-M114-L114 -> -44973 | O114: =SUM(E114-SUM(L114:N114)) -> -68095 | P114: -66619 | Q114: =-146098-P114 -> -79479 | R114: =-241162-Q114-P114 -> -95064 | S114: =SUM(F114-SUM(P114:R114)) -> -55167 | T114: -320571 | U114: =-435130-T114 -> -114559 | V114: =-1252367-U114-T114 -> -817237 | X114: =SUM(I114:L114) -> -358884 | Y114: =SUM(J114:M114) -> -387167 | Z114: =SUM(K114:N114) -> -347152 | AA114: =SUM(L114:O114) -> -298445 | AB114: =SUM(M114:P114) -> -300634 | AC114: =SUM(N114:Q114) -> -259166 | AD114: =SUM(O114:R114) -> -309257 | AE114: =SUM(P114:S114) -> -296329 | ... AH114: =SUM(S114:V114) -> -1307534 | AJ114: =SUM(AH114/AD114)-1 -> 3.2279851
B115: Maturities and sales of available-for-sale securities | C115: 0 | D115: 310045 | E115: 386760 | F115: 418082 | H115: 10400 | I115: =73090-H115 -> 62690 | J115: =185150-I115-H115 -> 112060 | K115: =SUM(D115-SUM(H115:J115)) -> 124895 | L115: 88091 | M115: =189446-L115 -> 101355 | N115: =285665-M115-L115 -> 96219 | O115: =SUM(E115-SUM(L115:N115)) -> 101095 | P115: 115045 | Q115: =211572-P115 -> 96527 | R115: =318192-Q115-P115 -> 106620 | S115: =SUM(F115-SUM(P115:R115)) -> 99890 | T115: 93805 | U115: =211180-T115 -> 117375 | V115: =407730-U115-T115 -> 196550 | X115: =SUM(I115:L115) -> 387736 | Y115: =SUM(J115:M115) -> 426401 | Z115: =SUM(K115:N115) -> 410560 | AA115: =SUM(L115:O115) -> 386760 | AB115: =SUM(M115:P115) -> 413714 | AC115: =SUM(N115:Q115) -> 408886 | AD115: =SUM(O115:R115) -> 419287 | AE115: =SUM(P115:S115) -> 418082 | ... AH115: =SUM(S115:V115) -> 507620 | AJ115: =SUM(AH115/AD115)-1 -> 0.21067431
B116: Business acquired | C116: 0 | D116: -848 | E116: 0 | F116: -15454 | H116: 0 | I116: 0 | J116: 0 | K116: =SUM(D116-SUM(H116:J116)) -> -848 | L116: 0 | M116: 0 | N116: 0 | O116: =SUM(E116-SUM(L116:N116)) -> 0 | P116: 0 | Q116: 0 | R116: 0 | S116: =SUM(F116-SUM(P116:R116)) -> -15454 | T116: 0 | U116: =28667-T116 -> 28667 | V116: =-13100-U116-T116 -> -41767 | X116: =SUM(I116:L116) -> -848 | Y116: =SUM(J116:M116) -> -848 | Z116: =SUM(K116:N116) -> -848 | AA116: =SUM(L116:O116) -> 0 | AB116: =SUM(M116:P116) -> 0 | AC116: =SUM(N116:Q116) -> 0 | AD116: =SUM(O116:R116) -> 0 | AE116: =SUM(P116:S116) -> -15454 | ... AH116: =SUM(S116:V116) -> -28554 | AJ116: =SUM(AH116/AD116)-1 -> #DIV/0!
B117: Other investing, net (2) | C117: -620 | D117: -1049 | E117: -1288 | F117: -1672 | H117: -134 | I117: =-370-H117 -> -236 | J117: =-598-I117-H117 -> -228 | K117: =SUM(D117-SUM(H117:J117)) -> -451 | L117: -318 | M117: =-628-L117 -> -310 | N117: =-1057-M117-L117 -> -429 | O117: =SUM(E117-SUM(L117:N117)) -> -231 | P117: -357 | Q117: =-892-P117 -> -535 | R117: =-1201-Q117-P117 -> -309 | S117: =SUM(F117-SUM(P117:R117)) -> -471 | T117: -220 | U117: =-307-T117 -> -87 | V117: =-5306-U117-T117 -> -4999 | X117: =SUM(I117:L117) -> -1233 | Y117: =SUM(J117:M117) -> -1307 | Z117: =SUM(K117:N117) -> -1508 | AA117: =SUM(L117:O117) -> -1288 | AB117: =SUM(M117:P117) -> -1327 | AC117: =SUM(N117:Q117) -> -1552 | AD117: =SUM(O117:R117) -> -1432 | AE117: =SUM(P117:S117) -> -1672 | ... AH117: =SUM(S117:V117) -> -5777 | AJ117: =SUM(AH117/AD117)-1 -> 3.0342179
B118: Net cash used in investing activities | C118: =SUM(C112:C117) -> -213785 | D118: =SUM(D112:D117) -> -309056 | E118: =SUM(E112:E117) -> 68766 | F118: =SUM(F112:F117) -> 82730 | H118: =SUM(H112:H117) -> -304098 | I118: =SUM(I112:I117) -> -35085 | J118: =SUM(J112:J117) -> 24976 | K118: =SUM(K112:K117) -> 5151 | L118: =SUM(L112:L117) -> 21315 | M118: =SUM(M112:M117) -> -22235 | N118: =SUM(N112:N117) -> 45500 | O118: =SUM(O112:O117) -> 24186 | ... V118: =SUM(V112:V117) -> -672655 | X118: =SUM(X112:X117) -> 16357 | Y118: =SUM(Y112:Y117) -> 29207 | Z118: =SUM(Z112:Z117) -> 49731 | AA118: =SUM(AA112:AA117) -> 68766 | AB118: =SUM(AB112:AB117) -> 90980 | AC118: =SUM(AC112:AC117) -> 121510 | AD118: =SUM(AD112:AD117) -> 82552 | AE118: =SUM(AE112:AE117) -> 82730 | ... AH118: =SUM(AH112:AH117) -> -849268 | AJ118: =SUM(AH118/AD118)-1 -> -11.287673
B120: Cash flows from financing activities:
B121: (+/-) Proceeds / (Purchases) of Equity, net | C121: =5457+26070-968 -> 30559 | D121: 1059 | E121: 1954 | F121: =8012+33437 -> 41449 | H121: =132+16 -> 148 | I121: =567+16+472-H121 -> 907 | J121: =953+1195+17-I121-H121 -> 1110 | K121: =SUM(D121-SUM(H121:J121)) -> -1106 | L121: 52 | M121: =541-L121 -> 489 | N121: =775-M121-L121 -> 234 | O121: =SUM(E121-SUM(L121:N121)) -> 1179 | P121: =486+873 -> 1359 | Q121: =1185-P121 -> -174 | R121: =2270-Q121-P121 -> 1085 | S121: =SUM(F121-SUM(P121:R121)) -> 39179 | T121: =362303+1213+516+4702 -> 368734 | U121: =358254+7564+5592+1447-T121 -> 4123 | V121: =1358254+11468+6708-U121-T121 -> 1003573 | X121: =SUM(I121:L121) -> 963 | Y121: =SUM(J121:M121) -> 545 | Z121: =SUM(K121:N121) -> -331 | AA121: =SUM(L121:O121) -> 1954 | AB121: =SUM(M121:P121) -> 3261 | AC121: =SUM(N121:Q121) -> 2598 | AD121: =SUM(O121:R121) -> 3449 | AE121: =SUM(P121:S121) -> 41449 | ... AH121: =SUM(S121:V121) -> 1415609 | AJ121: =SUM(AH121/AD121)-1 -> 409.44042
B122: (+/-) Other Financing Activities | C122: 572668 | D122: 37 | E122: -193 | F122: 238 | H122: 0 | I122: 0 | J122: 0 | K122: =SUM(D122-SUM(H122:J122)) -> 37 | L122: -18 | M122: =-1-L122 -> 17 | N122: =9-M122-L122 -> 10 | O122: =SUM(E122-SUM(L122:N122)) -> -202 | P122: 0 | Q122: =141-P122 -> 141 | R122: =144-Q122-P122 -> 3 | S122: =SUM(F122-SUM(P122:R122)) -> 94 | T122: 0 | U122: 0 | V122: =986-U122-T122 -> 986 | X122: =SUM(I122:L122) -> 19 | Y122: =SUM(J122:M122) -> 36 | Z122: =SUM(K122:N122) -> 46 | AA122: =SUM(L122:O122) -> -193 | AB122: =SUM(M122:P122) -> -175 | AC122: =SUM(N122:Q122) -> -51 | AD122: =SUM(O122:R122) -> -58 | AE122: =SUM(P122:S122) -> 238 | ... AH122: =SUM(S122:V122) -> 1080 | AJ122: =SUM(AH122/AD122)-1 -> -19.62069
...

Sheet Revenue Drivers
B2: IonQ, Inc. (NASDAQ: IONQ) | H2: Quarterly | P2: Quarterly | Q2: Quarterly | X2: LTM | AB2: LTM | AD2: LTM
B3: Segment Anaysis | C3: ='Historical Financials'!C7 -> 2021 | D3: ='Historical Financials'!D7 -> 2022 | E3: ='Historical Financials'!E7 -> 2023 | F3: ='Historical Financials'!F7 -> 2024 | H3: ='Historical Financials'!H7 -> 1Q22 | I3: ='Historical Financials'!I7 -> 2Q22 | J3: ='Historical Financials'!J7 -> 3Q22 | K3: ='Historical Financials'!K7 -> 4Q22 | L3: ='Historical Financials'!L7 -> 1Q23 | M3: ='Historical Financials'!M7 -> 2Q23 | N3: ='Historical Financials'!N7 -> 3Q23 | O3: ='Historical Financials'!O7 -> 4Q23 | ... V3: ='Historical Financials'!V7 -> 3Q25 | X3: =L3 -> 1Q23 | Y3: =M3 -> 2Q23 | Z3: =N3 -> 3Q23 | AA3: =O3 -> 4Q23 | AB3: =P3 -> 1Q24 | AC3: =Q3 -> 2Q24 | AD3: =S3 -> 4Q24 | AE3: =T3 -> 1Q25 | AF3: =U3 -> 2Q25 | AG3: =V3 -> 3Q25
B4: $ in thousands except per share | C4: ='Historical Financials'!C8 -> 44561 | D4: ='Historical Financials'!D8 -> 44926 | E4: ='Historical Financials'!E8 -> 45291 | F4: ='Historical Financials'!F8 -> 45657 | H4: ='Historical Financials'!H8 -> 44651 | I4: ='Historical Financials'!I8 -> 44742 | J4: ='Historical Financials'!J8 -> 44834 | K4: ='Historical Financials'!K8 -> 44926 | L4: ='Historical Financials'!L8 -> 45016 | M4: ='Historical Financials'!M8 -> 45107 | N4: ='Historical Financials'!N8 -> 45199 | O4: ='Historical Financials'!O8 -> 45291 | ... V4: ='Historical Financials'!V8 -> 45930 | X4: =L4 -> 45016 | Y4: =M4 -> 45107 | Z4: =N4 -> 45199 | AA4: =O4 -> 45291 | AB4: =P4 -> 45382 | AC4: =Q4 -> 45473 | AD4: =S4 -> 45657 | AE4: =T4 -> 45747 | AF4: =U4 -> 45838 | AG4: =V4 -> 45930
A6: X | B6: Net Revenues by Channel
B7: Quantum computing and networking hardware | D7: 239 | E7: 7083 | F7: 21594 | P7: 3619 | Q7: 7338 | R7: 6345 | S7: =SUM(F7-SUM(P7:R7)) -> 4292 | T7: 3063 | U7: 14066 | V7: 21584 | X7: =SUM(I7:L7) -> 0 | Y7: =SUM(J7:M7) -> 0 | Z7: =SUM(K7:N7) -> 0 | AA7: =SUM(L7:O7) -> 0 | AB7: =SUM(M7:P7) -> 3619 | AC7: =SUM(N7:Q7) -> 10957 | AD7: =SUM(P7:S7) -> 21594 | AE7: =SUM(Q7:T7) -> 21038 | AF7: =SUM(R7:U7) -> 27766 | AG7: =SUM(S7:V7) -> 43005
B8: Platform, consulting and support services | D8: 10892 | E8: 14959 | F8: 21479 | P8: 3963 | Q8: 4043 | R8: 6055 | S8: =SUM(F8-SUM(P8:R8)) -> 7418 | T8: 4503 | U8: 6628 | V8: 18282 | X8: =SUM(I8:L8) -> 0 | Y8: =SUM(J8:M8) -> 0 | Z8: =SUM(K8:N8) -> 0 | AA8: =SUM(L8:O8) -> 0 | AB8: =SUM(M8:P8) -> 3963 | AC8: =SUM(N8:Q8) -> 8006 | AD8: =SUM(P8:S8) -> 21479 | AE8: =SUM(Q8:T8) -> 22019 | AF8: =SUM(R8:U8) -> 24604 | AG8: =SUM(S8:V8) -> 36831
B9: Total Net Revenue | D9: =SUM(D7:D8) -> 11131 | E9: =SUM(E7:E8) -> 22042 | F9: =SUM(F7:F8) -> 43073 | P9: =SUM(P7:P8) -> 7582 | Q9: =SUM(Q7:Q8) -> 11381 | R9: =SUM(R7:R8) -> 12400 | S9: =SUM(S7:S8) -> 11710 | T9: =SUM(T7:T8) -> 7566 | U9: =SUM(U7:U8) -> 20694 | V9: =SUM(V7:V8) -> 39866 | X9: =SUM(X7:X8) -> 0 | Y9: =SUM(Y7:Y8) -> 0 | Z9: =SUM(Z7:Z8) -> 0 | AA9: =SUM(AA7:AA8) -> 0 | AB9: =SUM(AB7:AB8) -> 7582 | AC9: =SUM(AC7:AC8) -> 18963 | AD9: =SUM(AD7:AD8) -> 43073 | AE9: =SUM(AE7:AE8) -> 43057 | ... AG9: =SUM(AG7:AG8) -> 79836
B10: Balance Check | D10: =+D9-'Historical Financials'!D11 -> 0 | E10: =+E9-'Historical Financials'!E11 -> 0 | F10: =+F9-'Historical Financials'!F11 -> 0 | P10: =+P9-'Historical Financials'!P11 -> 0 | Q10: =+Q9-'Historical Financials'!Q11 -> 0 | R10: =+R9-'Historical Financials'!R11 -> 0 | S10: =+S9-'Historical Financials'!S11 -> 0 | T10: =+T9-'Historical Financials'!T11 -> 0 | U10: =+U9-'Historical Financials'!U11 -> 0 | V10: =+V9-'Historical Financials'!V11 -> 0 | X10: =X9-'Historical Financials'!X11 -> -13463 | Y10: =Y9-'Historical Financials'!Y11 -> -16370 | Z10: =Z9-'Historical Financials'!Z11 -> -19743 | AA10: =AA9-'Historical Financials'!AA11 -> -22042 | AB10: =AB9-'Historical Financials'!AB11 -> -17757 | AC10: =AC9-'Historical Financials'!AC11 -> -12242 | AD10: =AD9-'Historical Financials'!AE11 -> 0 | AE10: =AE9-'Historical Financials'!AF11 -> 0 | AF10: =AF9-'Historical Financials'!AG11 -> 0 | AG10: =AG9-'Historical Financials'!AH11 -> 0
A12: X | B12: Revenue by Channel: U.S
B13: United States | D13: 9175 | E13: 18703 | F13: 40714 | P13: 7062 | Q13: 10953 | R13: 11895 | S13: =SUM(F13-SUM(P13:R13)) -> 10804 | T13: 5289 | U13: 15990 | V13: 28742 | X13: =SUM(I13:L13) -> 0 | Y13: =SUM(J13:M13) -> 0 | Z13: =SUM(K13:N13) -> 0 | AA13: =SUM(L13:O13) -> 0 | AB13: =SUM(M13:P13) -> 7062 | AC13: =SUM(N13:Q13) -> 18015 | AD13: =SUM(P13:S13) -> 40714 | AE13: =SUM(Q13:T13) -> 38941 | AF13: =SUM(R13:U13) -> 43978 | AG13: =SUM(S13:V13) -> 60825
B14: International | D14: 1956 | E14: 3339 | F14: 2359 | P14: 520 | Q14: 428 | R14: 505 | S14: =SUM(F14-SUM(P14:R14)) -> 906 | T14: 2277 | U14: 4704 | V14: 11124 | X14: =SUM(I14:L14) -> 0 | Y14: =SUM(J14:M14) -> 0 | Z14: =SUM(K14:N14) -> 0 | AA14: =SUM(L14:O14) -> 0 | AB14: =SUM(M14:P14) -> 520 | AC14: =SUM(N14:Q14) -> 948 | AD14: =SUM(P14:S14) -> 2359 | AE14: =SUM(Q14:T14) -> 4116 | AF14: =SUM(R14:U14) -> 8392 | AG14: =SUM(S14:V14) -> 19011
B15: Total Net U.S Revenue | D15: =SUM(D13:D14) -> 11131 | E15: =SUM(E13:E14) -> 22042 | F15: =SUM(F13:F14) -> 43073 | P15: =SUM(P13:P14) -> 7582 | Q15: =SUM(Q13:Q14) -> 11381 | R15: =SUM(R13:R14) -> 12400 | S15: =SUM(S13:S14) -> 11710 | T15: =SUM(T13:T14) -> 7566 | U15: =SUM(U13:U14) -> 20694 | V15: =SUM(V13:V14) -> 39866 | X15: =SUM(X13:X14) -> 0 | Y15: =SUM(Y13:Y14) -> 0 | Z15: =SUM(Z13:Z14) -> 0 | AA15: =SUM(AA13:AA14) -> 0 | AB15: =SUM(AB13:AB14) -> 7582 | AC15: =SUM(AC13:AC14) -> 18963 | AD15: =SUM(AD13:AD14) -> 43073 | AE15: =SUM(AE13:AE14) -> 43057 | ... AG15: =SUM(AG13:AG14) -> 79836
B16: Balance Check | D16: =+D15-D9 -> 0 | E16: =+E15-E9 -> 0 | F16: =+F15-F9 -> 0 | P16: =+P15-P9 -> 0 | Q16: =+Q15-Q9 -> 0 | R16: =+R15-R9 -> 0 | S16: =+S15-S9 -> 0 | T16: =+T15-T9 -> 0 | U16: =+U15-U9 -> 0 | V16: =+V15-V9 -> 0 | X16: =X15-'Historical Financials'!X17 -> 52873 | Y16: =Y15-'Historical Financials'!Y17 -> 63089 | Z16: =Z15-'Historical Financials'!Z17 -> 74396 | AA16: =AA15-'Historical Financials'!AA17 -> 92321 | AB16: =AB15-'Historical Financials'!AB17 -> 116038 | AC16: =AC15-'Historical Financials'!AC17 -> 138754 | AD16: =+AD15-AD9 -> 0 | AE16: =+AE15-AE9 -> 0 | AF16: =+AF15-AF9 -> 0 | AG16: =+AG15-AG9 -> 0

Sheet FCF
B2: IonQ, Inc. (NASDAQ: IONQ) | D2: FYE | H2: Quarterly | Q2: Quarterly | R2: Quarterly | X2: LTM | AE2: LTM | AK2: Variance
B3: FCF Analysis | C3: ='Historical Financials'!C7 -> 2021 | D3: ='Historical Financials'!D7 -> 2022 | E3: ='Historical Financials'!E7 -> 2023 | F3: ='Historical Financials'!F7 -> 2024 | H3: ='Historical Financials'!H7 -> 1Q22 | I3: ='Historical Financials'!I7 -> 2Q22 | J3: ='Historical Financials'!J7 -> 3Q22 | K3: ='Historical Financials'!K7 -> 4Q22 | L3: ='Historical Financials'!L7 -> 1Q23 | M3: ='Historical Financials'!M7 -> 2Q23 | N3: ='Historical Financials'!N7 -> 3Q23 | O3: ='Historical Financials'!O7 -> 4Q23 | ... V3: ='Historical Financials'!V7 -> 3Q25 | X3: =K3 -> 4Q22 | Y3: =L3 -> 1Q23 | Z3: =M3 -> 2Q23 | AA3: =N3 -> 3Q23 | AB3: =O3 -> 4Q23 | AC3: =P3 -> 1Q24 | AD3: =Q3 -> 2Q24 | AE3: =R3 -> 3Q24 | ... AI3: =V3 -> 3Q25
B4: $ in thousands except per share | C4: ='Historical Financials'!C8 -> 44561 | D4: ='Historical Financials'!D8 -> 44926 | E4: ='Historical Financials'!E8 -> 45291 | F4: ='Historical Financials'!F8 -> 45657 | H4: ='Historical Financials'!H8 -> 44651 | I4: ='Historical Financials'!I8 -> 44742 | J4: ='Historical Financials'!J8 -> 44834 | K4: ='Historical Financials'!K8 -> 44926 | L4: ='Historical Financials'!L8 -> 45016 | M4: ='Historical Financials'!M8 -> 45107 | N4: ='Historical Financials'!N8 -> 45199 | O4: ='Historical Financials'!O8 -> 45291 | ... V4: ='Historical Financials'!V8 -> 45930 | X4: =K4 -> 44926 | Y4: =L4 -> 45016 | Z4: =M4 -> 45107 | AA4: =N4 -> 45199 | AB4: =O4 -> 45291 | AC4: =P4 -> 45382 | AD4: =Q4 -> 45473 | AE4: =R4 -> 45565 | ... AI4: =V4 -> 45930
B6: ='Revenue Drivers'!B7 -> Quantum computing and networking hardware | D6: ='Revenue Drivers'!D7 -> 239 | E6: ='Revenue Drivers'!E7 -> 7083 | F6: ='Revenue Drivers'!F7 -> 21594 | P6: ='Revenue Drivers'!P7 -> 3619 | Q6: ='Revenue Drivers'!Q7 -> 7338 | R6: ='Revenue Drivers'!R7 -> 6345 | S6: ='Revenue Drivers'!S7 -> 4292 | T6: ='Revenue Drivers'!T7 -> 3063 | U6: ='Revenue Drivers'!U7 -> 14066 | V6: ='Revenue Drivers'!V7 -> 21584 | AC6: =SUM(M6:P6) -> 3619 | AD6: =SUM(N6:Q6) -> 10957 | AE6: =SUM(O6:R6) -> 17302 | AF6: =SUM(P6:S6) -> 21594 | AG6: =SUM(Q6:T6) -> 21038 | AH6: =SUM(R6:U6) -> 27766 | AI6: =SUM(S6:V6) -> 43005 | AK6: =SUM(AI6/AE6)-1 -> 1.4855508
B7: ='Revenue Drivers'!B8 -> Platform, consulting and support services | D7: ='Revenue Drivers'!D8 -> 10892 | E7: ='Revenue Drivers'!E8 -> 14959 | F7: ='Revenue Drivers'!F8 -> 21479 | P7: ='Revenue Drivers'!P8 -> 3963 | Q7: ='Revenue Drivers'!Q8 -> 4043 | R7: ='Revenue Drivers'!R8 -> 6055 | S7: ='Revenue Drivers'!S8 -> 7418 | T7: ='Revenue Drivers'!T8 -> 4503 | U7: ='Revenue Drivers'!U8 -> 6628 | V7: ='Revenue Drivers'!V8 -> 18282 | AC7: =SUM(M7:P7) -> 3963 | AD7: =SUM(N7:Q7) -> 8006 | AE7: =SUM(O7:R7) -> 14061 | AF7: =SUM(P7:S7) -> 21479 | AG7: =SUM(Q7:T7) -> 22019 | AH7: =SUM(R7:U7) -> 24604 | AI7: =SUM(S7:V7) -> 36831 | AK7: =SUM(AI7/AE7)-1 -> 1.6193727
B8: Total Revenue | C8: ='Historical Financials'!C11 -> 2099 | D8: =SUM(D6:D7) -> 11131 | E8: =SUM(E6:E7) -> 22042 | F8: =SUM(F6:F7) -> 43073 | H8: ='Historical Financials'!H11 -> 1953 | I8: ='Historical Financials'!I11 -> 2608 | J8: ='Historical Financials'!J11 -> 2763 | K8: ='Historical Financials'!K11 -> 3807 | L8: ='Historical Financials'!L11 -> 4285 | M8: ='Historical Financials'!M11 -> 5515 | N8: ='Historical Financials'!N11 -> 6136 | O8: ='Historical Financials'!O11 -> 6106 | P8: =SUM(P6:P7) -> 7582 | Q8: =SUM(Q6:Q7) -> 11381 | R8: =SUM(R6:R7) -> 12400 | S8: =SUM(S6:S7) -> 11710 | T8: =SUM(T6:T7) -> 7566 | U8: =SUM(U6:U7) -> 20694 | V8: =SUM(V6:V7) -> 39866 | X8: =SUM(H8:K8) -> 11131 | Y8: =SUM(I8:L8) -> 13463 | Z8: =SUM(J8:M8) -> 16370 | AA8: =SUM(K8:N8) -> 19743 | AB8: =SUM(L8:O8) -> 22042 | AC8: =SUM(AC6:AC7) -> 7582 | AD8: =SUM(AD6:AD7) -> 18963 | AE8: =SUM(AE6:AE7) -> 31363 | AF8: =SUM(AF6:AF7) -> 43073 | AG8: =SUM(AG6:AG7) -> 43057 | AH8: =SUM(AH6:AH7) -> 52370 | AI8: =SUM(AI6:AI7) -> 79836 | AK8: =SUM(AI8/AE8)-1 -> 1.5455473
B9: Y/Y Growth (%) | D9: =SUM(D8/C8)-1 -> 4.3030014 | E9: =SUM(E8/D8)-1 -> 0.98023538 | F9: =SUM(F8/E8)-1 -> 0.95413302 | M9: =SUM(M8/I8)-1 -> 1.1146472 | N9: =SUM(N8/J8)-1 -> 1.2207745 | O9: =SUM(O8/K8)-1 -> 0.60388758 | P9: =SUM(P8/L8)-1 -> 0.76942824 | Q9: =SUM(Q8/M8)-1 -> 1.0636446 | R9: =SUM(R8/N8)-1 -> 1.0208605 | S9: =SUM(S8/O8)-1 -> 0.91778578 | T9: =SUM(T8/P8)-1 -> -0.0021102611 | ... V9: =SUM(V8/R8)-1 -> 2.215 | AB9: =SUM(AB8/X8)-1 -> 0.98023538 | AC9: =SUM(AC8/Y8)-1 -> -0.43682686 | AD9: =SUM(AD8/Z8)-1 -> 0.15839951 | AE9: =SUM(AE8/AA8)-1 -> 0.58856303 | AF9: =SUM(AF8/AB8)-1 -> 0.95413302 | AG9: =SUM(AG8/AC8)-1 -> 4.6788446 | AH9: =SUM(AH8/AD8)-1 -> 1.7616938 | AI9: =SUM(AI8/AE8)-1 -> 1.5455473 | AK9: =SUM(AI9-AE9)*10000 -> 9569.8427
B10: Q/Q Growth (%) | C10: N/A | D10: N/A | E10: N/A | F10: N/A | J10: =SUM(J8/I8)-1 -> 0.059432515 | K10: =SUM(K8/J8)-1 -> 0.37785016 | L10: =SUM(L8/K8)-1 -> 0.12555818 | M10: =SUM(M8/L8)-1 -> 0.28704784 | N10: =SUM(N8/M8)-1 -> 0.11260199 | O10: =SUM(O8/N8)-1 -> -0.0048891786 | P10: =SUM(P8/O8)-1 -> 0.24172945 | Q10: =SUM(Q8/P8)-1 -> 0.50105513 | ... V10: =SUM(V8/U8)-1 -> 0.92645211 | X10: N/A | Y10: N/A | Z10: N/A | AA10: N/A | AB10: N/A | AC10: N/A | AD10: N/A | AE10: N/A | AF10: N/A | AG10: N/A | AH10: N/A | AI10: N/A
B12: (-) Cost of Sales | C12: ='Historical Financials'!C13 -> -1040 | D12: ='Historical Financials'!D13 -> -2944 | E12: ='Historical Financials'!E13 -> -8108 | F12: ='Historical Financials'!F13 -> -20597 | H12: ='Historical Financials'!H13 -> -568 | I12: ='Historical Financials'!I13 -> -742 | J12: ='Historical Financials'!J13 -> -733 | K12: ='Historical Financials'!K13 -> -901 | L12: ='Historical Financials'!L13 -> -1036 | M12: ='Historical Financials'!M13 -> -1901 | N12: ='Historical Financials'!N13 -> -2008 | O12: ='Historical Financials'!O13 -> -3163 | ... V12: ='Historical Financials'!V13 -> -21253 | X12: =SUM(G12:K12) -> -2944 | Y12: =SUM(I12:L12) -> -3412 | Z12: =SUM(J12:M12) -> -4571 | AA12: =SUM(K12:N12) -> -5846 | AB12: =SUM(L12:O12) -> -8108 | AC12: =SUM(M12:P12) -> -10486 | AD12: =SUM(N12:Q12) -> -14208 | AE12: =SUM(O12:R12) -> -18715 | AF12: =SUM(P12:S12) -> -20597 | ... AI12: =SUM(S12:V12) -> -38940 | AK12: =SUM(AI12/AE12)-1 -> 1.0806839
B13: Gross Profit | C13: =+C8+C12 -> 1059 | D13: =+D8+D12 -> 8187 | E13: =+E8+E12 -> 13934 | F13: =+F8+F12 -> 22476 | H13: =+H8+H12 -> 1385 | I13: =+I8+I12 -> 1866 | J13: =+J8+J12 -> 2030 | K13: =+K8+K12 -> 2906 | L13: =+L8+L12 -> 3249 | M13: =+M8+M12 -> 3614 | N13: =+N8+N12 -> 4128 | O13: =+O8+O12 -> 2943 | ... V13: =+V8+V12 -> 18613 | X13: =+X8+X12 -> 8187 | Y13: =+Y8+Y12 -> 10051 | Z13: =+Z8+Z12 -> 11799 | AA13: =+AA8+AA12 -> 13897 | AB13: =+AB8+AB12 -> 13934 | AC13: =+AC8+AC12 -> -2904 | AD13: =+AD8+AD12 -> 4755 | AE13: =+AE8+AE12 -> 12648 | ... AI13: =+AI8+AI12 -> 40896 | AK13: =SUM(AI13/AE13)-1 -> 2.2333966
B14: Gross Margin (%) | C14: =C13/C8 -> 0.50452596 | D14: =D13/D8 -> 0.73551343 | E14: =E13/E8 -> 0.63215679 | F14: =F13/F8 -> 0.52181181 | H14: =H13/H8 -> 0.70916539 | I14: =I13/I8 -> 0.7154908 | J14: =J13/J8 -> 0.73470865 | K14: =K13/K8 -> 0.76333071 | L14: =L13/L8 -> 0.75822637 | M14: =M13/M8 -> 0.65530372 | N14: =N13/N8 -> 0.67275098 | O14: =O13/O8 -> 0.48198493 | ... V14: =V13/V8 -> 0.46688908 | X14: =X13/X8 -> 0.73551343 | Y14: =Y13/Y8 -> 0.74656466 | Z14: =Z13/Z8 -> 0.7207697 | AA14: =AA13/AA8 -> 0.70389505 | AB14: =AB13/AB8 -> 0.63215679 | AC14: =AC13/AC8 -> -0.3830124 | AD14: =AD13/AD8 -> 0.25075146 | AE14: =AE13/AE8 -> 0.40327775 | ... AI14: =AI13/AI8 -> 0.51225011 | AK14: =SUM(AI14-AE14)*10000 -> 1089.7237
B16: (-) Research and development | C16: ='Historical Financials'!C17 -> -20228 | D16: ='Historical Financials'!D17 -> -43978 | E16: ='Historical Financials'!E17 -> -92321 | F16: ='Historical Financials'!F17 -> -136827 | H16: ='Historical Financials'!H17 -> -7338 | I16: ='Historical Financials'!I17 -> -9653 | J16: ='Historical Financials'!J17 -> -13292 | K16: ='Historical Financials'!K17 -> -13695 | L16: ='Historical Financials'!L17 -> -16233 | M16: ='Historical Financials'!M17 -> -19869 | N16: ='Historical Financials'!N17 -> -24599 | O16: ='Historical Financials'!O17 -> -31620 | ... V16: ='Historical Financials'!V17 -> -66298 | X16: =SUM(G16:K16) -> -43978 | Y16: =SUM(I16:L16) -> -52873 | Z16: =SUM(J16:M16) -> -63089 | AA16: =SUM(K16:N16) -> -74396 | AB16: =SUM(L16:O16) -> -92321 | AC16: =SUM(M16:P16) -> -108456 | AD16: =SUM(N16:Q16) -> -119791 | AE16: =SUM(O16:R16) -> -128370 | AF16: =SUM(P16:S16) -> -136827 | ... AI16: =SUM(S16:V16) -> -249687 | AK16: =SUM(AI16/AE16)-1 -> 0.94505726
B17: (-) Sales and marketing | C17: ='Historical Financials'!C18 -> -3233 | D17: ='Historical Financials'!D18 -> -8385 | E17: ='Historical Financials'!E18 -> -18270 | F17: ='Historical Financials'!F18 -> -28395 | H17: ='Historical Financials'!H18 -> -1871 | I17: ='Historical Financials'!I18 -> -2132 | J17: ='Historical Financials'!J18 -> -1969 | K17: ='Historical Financials'!K18 -> -2413 | L17: ='Historical Financials'!L18 -> -2667 | M17: ='Historical Financials'!M18 -> -3575 | N17: ='Historical Financials'!N18 -> -5047 | O17: ='Historical Financials'!O18 -> -6981 | ... V17: ='Historical Financials'!V18 -> -14441 | X17: =SUM(G17:K17) -> -8385 | Y17: =SUM(I17:L17) -> -9181 | Z17: =SUM(J17:M17) -> -10624 | AA17: =SUM(K17:N17) -> -13702 | AB17: =SUM(L17:O17) -> -18270 | AC17: =SUM(M17:P17) -> -22304 | AD17: =SUM(N17:Q17) -> -24866 | AE17: =SUM(O17:R17) -> -26449 | AF17: =SUM(P17:S17) -> -28395 | ... AI17: =SUM(S17:V17) -> -42855 | AK17: =SUM(AI17/AE17)-1 -> 0.6202881
B18: (-) General and administrative | C18: ='Historical Financials'!C19 -> -13737 | D18: ='Historical Financials'!D19 -> -35966 | E18: ='Historical Financials'!E19 -> -50722 | F18: ='Historical Financials'!F19 -> -71055 | H18: ='Historical Financials'!H19 -> -9194 | I18: ='Historical Financials'!I19 -> -7558 | J18: ='Historical Financials'!J19 -> -10149 | K18: ='Historical Financials'!K19 -> -9065 | L18: ='Historical Financials'!L19 -> -10581 | M18: ='Historical Financials'!M19 -> -10930 | N18: ='Historical Financials'!N19 -> -13927 | O18: ='Historical Financials'!O19 -> -15284 | ... V18: ='Historical Financials'!V19 -> -82505 | X18: =SUM(G18:K18) -> -35966 | Y18: =SUM(I18:L18) -> -37353 | Z18: =SUM(J18:M18) -> -40725 | AA18: =SUM(K18:N18) -> -44503 | AB18: =SUM(L18:O18) -> -50722 | AC18: =SUM(M18:P18) -> -54161 | AD18: =SUM(N18:Q18) -> -56284 | AE18: =SUM(O18:R18) -> -56679 | AF18: =SUM(P18:S18) -> -71055 | ... AI18: =SUM(S18:V18) -> -184078 | AK18: =SUM(AI18/AE18)-1 -> 2.2477284
B19: (-) Depreciation and amortization | C19: ='Historical Financials'!C20 -> -2548 | D19: ='Historical Financials'!D20 -> -5604 | E19: ='Historical Financials'!E20 -> -10375 | F19: ='Historical Financials'!F20 -> -18654 | H19: ='Historical Financials'!H20 -> -1266 | I19: ='Historical Financials'!I20 -> -1451 | J19: ='Historical Financials'!J20 -> -1531 | K19: ='Historical Financials'!K20 -> -1356 | L19: ='Historical Financials'!L20 -> -1791 | M19: ='Historical Financials'!M20 -> -2329 | N19: ='Historical Financials'!N20 -> -2749 | O19: ='Historical Financials'!O20 -> -3506 | ... V19: ='Historical Financials'!V20 -> -24182 | X19: =SUM(G19:K19) -> -5604 | Y19: =SUM(I19:L19) -> -6129 | Z19: =SUM(J19:M19) -> -7007 | AA19: =SUM(K19:N19) -> -8225 | AB19: =SUM(L19:O19) -> -10375 | AC19: =SUM(M19:P19) -> -12539 | AD19: =SUM(N19:Q19) -> -14515 | AE19: =SUM(O19:R19) -> -16656 | AF19: =SUM(P19:S19) -> -18654 | ... AI19: =SUM(S19:V19) -> -46863 | AK19: =SUM(AI19/AE19)-1 -> 1.8135807
B20: Earning before Interest & Taxes (EBIT) | C20: =SUM(C13+SUM(C16:C19)) -> -38687 | D20: =SUM(D13+SUM(D16:D19)) -> -85746 | E20: =SUM(E13+SUM(E16:E19)) -> -157754 | F20: =SUM(F13+SUM(F16:F19)) -> -232455 | H20: =SUM(H13+SUM(H16:H19)) -> -18284 | I20: =SUM(I13+SUM(I16:I19)) -> -18928 | J20: =SUM(J13+SUM(J16:J19)) -> -24911 | K20: =SUM(K13+SUM(K16:K19)) -> -23623 | L20: =SUM(L13+SUM(L16:L19)) -> -28023 | M20: =SUM(M13+SUM(M16:M19)) -> -33089 | N20: =SUM(N13+SUM(N16:N19)) -> -42194 | O20: =SUM(O13+SUM(O16:O19)) -> -54448 | ... V20: =SUM(V13+SUM(V16:V19)) -> -168813 | X20: =SUM(X13+SUM(X16:X19)) -> -85746 | Y20: =SUM(Y13+SUM(Y16:Y19)) -> -95485 | Z20: =SUM(Z13+SUM(Z16:Z19)) -> -109646 | AA20: =SUM(AA13+SUM(AA16:AA19)) -> -126929 | AB20: =SUM(AB13+SUM(AB16:AB19)) -> -157754 | AC20: =SUM(AC13+SUM(AC16:AC19)) -> -200364 | AD20: =SUM(AD13+SUM(AD16:AD19)) -> -210701 | AE20: =SUM(AE13+SUM(AE16:AE19)) -> -215506 | ... AI20: =SUM(AI13+SUM(AI16:AI19)) -> -482587 | AK20: =SUM(AI20/AE20)-1 -> 1.2393205
B21: Operating Margin (%) | C21: =C20/C8 -> -18.431158 | D21: =D20/D8 -> -7.703351 | E21: =E20/E8 -> -7.1569731 | F21: =F20/F8 -> -5.3967683 | H21: =H20/H8 -> -9.3620072 | I21: =I20/I8 -> -7.2576687 | J21: =J20/J8 -> -9.0159247 | K21: =K20/K8 -> -6.2051484 | L21: =L20/L8 -> -6.53979 | M21: =M20/M8 -> -5.9998187 | N21: =N20/N8 -> -6.8764668 | O21: =O20/O8 -> -8.9171307 | ... V21: =V20/V8 -> -4.2345106 | X21: =X20/X8 -> -7.703351 | Y21: =Y20/Y8 -> -7.0924014 | Z21: =Z20/Z8 -> -6.6979841 | AA21: =AA20/AA8 -> -6.4290635 | AB21: =AB20/AB8 -> -7.1569731 | AC21: =AC20/AC8 -> -26.426273 | AD21: =AD20/AD8 -> -11.111164 | AE21: =AE20/AE8 -> -6.8713452 | ... AI21: =AI20/AI8 -> -6.0447292 | AK21: =SUM(AI21-AE21)*10000 -> 8266.1602
B23: (+) Depreciation and Amortization | C23: =-C19 -> 2548 | D23: =-D19 -> 5604 | E23: =-E19 -> 10375 | F23: =-F19 -> 18654 | H23: =-H19 -> 1266 | I23: =-I19 -> 1451 | J23: =-J19 -> 1531 | K23: =-K19 -> 1356 | L23: =-L19 -> 1791 | M23: =-M19 -> 2329 | N23: =-N19 -> 2749 | O23: =-O19 -> 3506 | ... V23: =-V19 -> 24182 | X23: =SUM(G23:K23) -> 5604 | Y23: =SUM(I23:L23) -> 6129 | Z23: =SUM(J23:M23) -> 7007 | AA23: =SUM(K23:N23) -> 8225 | AB23: =SUM(L23:O23) -> 10375 | AC23: =SUM(M23:P23) -> 12539 | AD23: =SUM(N23:Q23) -> 14515 | AE23: =SUM(O23:R23) -> 16656 | AF23: =SUM(P23:S23) -> 18654 | ... AI23: =SUM(S23:V23) -> 46863 | AK23: =SUM(AI23/AE23)-1 -> 1.8135807
B24: EBITDA | C24: =SUM(C20+C23) -> -36139 | D24: =SUM(D20+D23) -> -80142 | E24: =SUM(E20+E23) -> -147379 | F24: =SUM(F20+F23) -> -213801 | H24: =SUM(H20+H23) -> -17018 | I24: =SUM(I20+I23) -> -17477 | J24: =SUM(J20+J23) -> -23380 | K24: =SUM(K20+K23) -> -22267 | L24: =SUM(L20+L23) -> -26232 | M24: =SUM(M20+M23) -> -30760 | N24: =SUM(N20+N23) -> -39445 | O24: =SUM(O20+O23) -> -50942 | ... V24: =SUM(V20+V23) -> -144631 | X24: =SUM(X20+X23) -> -80142 | Y24: =SUM(Y20+Y23) -> -89356 | Z24: =SUM(Z20+Z23) -> -102639 | AA24: =SUM(AA20+AA23) -> -118704 | AB24: =SUM(AB20+AB23) -> -147379 | AC24: =SUM(AC20+AC23) -> -187825 | AD24: =SUM(AD20+AD23) -> -196186 | AE24: =SUM(AE20+AE23) -> -198850 | ... AI24: =SUM(AI20+AI23) -> -435724 | AK24: =SUM(AI24/AE24)-1 -> 1.1912195
B25: EBITDA Margin (%) | C25: =C24/C8 -> -17.217246 | D25: =D24/D8 -> -7.1998922 | E25: =E24/E8 -> -6.6862807 | F25: =F24/F8 -> -4.9636896 | H25: =H24/H8 -> -8.7137737 | I25: =I24/I8 -> -6.7013037 | J25: =J24/J8 -> -8.4618169 | K25: =K24/K8 -> -5.8489624 | L25: =L24/L8 -> -6.1218203 | M25: =M24/M8 -> -5.5775159 | N25: =N24/N8 -> -6.428455 | O25: =O24/O8 -> -8.3429414 | ... V25: =V24/V8 -> -3.6279286 | X25: =X24/X8 -> -7.1998922 | Y25: =Y24/Y8 -> -6.6371537 | Z25: =Z24/Z8 -> -6.269945 | AA25: =AA24/AA8 -> -6.0124601 | AB25: =AB24/AB8 -> -6.6862807 | AC25: =AC24/AC8 -> -24.772487 | AD25: =AD24/AD8 -> -10.345726 | AE25: =AE24/AE8 -> -6.3402736 | ... AI25: =AI24/AI8 -> -5.4577384 | AK25: =SUM(AI25-AE25)*10000 -> 8825.3521
B27: (+) Share-based Compensation | C27: ='Historical Financials'!C97 -> 7748 | D27: ='Historical Financials'!D97 -> 31456 | E27: ='Historical Financials'!E97 -> 69743 | F27: ='Historical Financials'!F97 -> 106878 | H27: ='Historical Financials'!H97 -> 6672 | I27: ='Historical Financials'!I97 -> 5884 | J27: ='Historical Financials'!J97 -> 10005 | K27: ='Historical Financials'!K97 -> 8895 | L27: ='Historical Financials'!L97 -> 10268 | M27: ='Historical Financials'!M97 -> 11304 | N27: ='Historical Financials'!N97 -> 16977 | O27: ='Historical Financials'!O97 -> 31194 | ... V27: ='Historical Financials'!V97 -> 72945 | X27: =SUM(G27:K27) -> 31456 | Y27: =SUM(I27:L27) -> 35052 | Z27: =SUM(J27:M27) -> 40472 | AA27: =SUM(K27:N27) -> 47444 | AB27: =SUM(L27:O27) -> 69743 | AC27: =SUM(M27:P27) -> 81536 | AD27: =SUM(N27:Q27) -> 91211 | AE27: =SUM(O27:R27) -> 98801 | AF27: =SUM(P27:S27) -> 106878 | ... AI27: =SUM(S27:V27) -> 244637 | AK27: =SUM(AI27/AE27)-1 -> 1.4760579
B28: Adj. EBITDA | C28: =+SUM(C24+SUM(C27:C27)) -> -28391 | D28: =+SUM(D24+SUM(D27:D27)) -> -48686 | E28: =+SUM(E24+SUM(E27:E27)) -> -77636 | F28: =+SUM(F24+SUM(F27:F27)) -> -106923 | H28: =+SUM(H24+SUM(H27:H27)) -> -10346 | I28: =+SUM(I24+SUM(I27:I27)) -> -11593 | J28: =+SUM(J24+SUM(J27:J27)) -> -13375 | K28: =+SUM(K24+SUM(K27:K27)) -> -13372 | L28: =+SUM(L24+SUM(L27:L27)) -> -15964 | M28: =+SUM(M24+SUM(M27:M27)) -> -19456 | N28: =+SUM(N24+SUM(N27:N27)) -> -22468 | O28: =+SUM(O24+SUM(O27:O27)) -> -19748 | ... V28: =+SUM(V24+SUM(V27:V27)) -> -71686 | X28: =+SUM(X24+SUM(X27:X27)) -> -48686 | Y28: =+SUM(Y24+SUM(Y27:Y27)) -> -54304 | Z28: =+SUM(Z24+SUM(Z27:Z27)) -> -62167 | AA28: =+SUM(AA24+SUM(AA27:AA27)) -> -71260 | AB28: =+SUM(AB24+SUM(AB27:AB27)) -> -77636 | AC28: =+SUM(AC24+SUM(AC27:AC27)) -> -106289 | AD28: =+SUM(AD24+SUM(AD27:AD27)) -> -104975 | AE28: =+SUM(AE24+SUM(AE27:AE27)) -> -100049 | ... AI28: =+SUM(AI24+SUM(AI27:AI27)) -> -191087 | AK28: =SUM(AI28/AE28)-1 -> 0.90993413
B29: Adj. EBITDA Margin (%) | C29: =C28/C8 -> -13.525965 | D29: =D28/D8 -> -4.3739107 | E29: =E28/E8 -> -3.5221849 | F29: =F28/F8 -> -2.4823671 | H29: =H28/H8 -> -5.297491 | I29: =I28/I8 -> -4.4451687 | J29: =J28/J8 -> -4.8407528 | K29: =K28/K8 -> -3.512477 | L29: =L28/L8 -> -3.7255543 | M29: =M28/M8 -> -3.5278332 | N29: =N28/N8 -> -3.6616688 | O29: =O28/O8 -> -3.2341959 | ... V29: =V28/V8 -> -1.7981739 | X29: =X28/X8 -> -4.3739107 | Y29: =Y28/Y8 -> -4.0335735 | Z29: =Z28/Z8 -> -3.7976176 | AA29: =AA28/AA8 -> -3.6093805 | AB29: =AB28/AB8 -> -3.5221849 | AC29: =AC28/AC8 -> -14.018597 | AD29: =AD28/AD8 -> -5.5357802 | AE29: =AE28/AE8 -> -3.1900328 | ... AI29: =AI28/AI8 -> -2.3934942 | AK29: =SUM(AI29-AE29)*10000 -> 7965.3868
B31: (-) Capital Expenditures | C31: =SUM('Historical Financials'!C112+'Historical Financials'!C113) -> -9404 | D31: =SUM('Historical Financials'!D112+'Historical Financials'!D113) -> -11515 | E31: =SUM('Historical Financials'!E112+'Historical Financials'!E113) -> -18261 | F31: =SUM('Historical Financials'!F112+'Historical Financials'!F113) -> -21897 | H31: =SUM('Historical Financials'!H112+'Historical Financials'!H113) -> -3129 | I31: =SUM('Historical Financials'!I112+'Historical Financials'!I113) -> -4875 | J31: =SUM('Historical Financials'!J112+'Historical Financials'!J113) -> -1868 | K31: =SUM('Historical Financials'!K112+'Historical Financials'!K113) -> -1643 | L31: =SUM('Historical Financials'!L112+'Historical Financials'!L113) -> -2028 | M31: =SUM('Historical Financials'!M112+'Historical Financials'!M113) -> -2333 | N31: =SUM('Historical Financials'!N112+'Historical Financials'!N113) -> -5317 | O31: =SUM('Historical Financials'!O112+'Historical Financials'!O113) -> -8583 | ... V31: =SUM('Historical Financials'!V112+'Historical Financials'!V113) -> -5202 | X31: =SUM(G31:K31) -> -11515 | Y31: =SUM(I31:L31) -> -10414 | Z31: =SUM(J31:M31) -> -7872 | AA31: =SUM(K31:N31) -> -11321 | AB31: =SUM(L31:O31) -> -18261 | AC31: =SUM(M31:P31) -> -20773 | AD31: =SUM(N31:Q31) -> -26658 | AE31: =SUM(O31:R31) -> -26046 | AF31: =SUM(P31:S31) -> -21897 | ... AI31: =SUM(S31:V31) -> -15023 | AK31: =SUM(AI31/AE31)-1 -> -0.42321278
B32: (-) Cash Taxes | C32: ='Historical Financials'!C30 -> 0 | D32: ='Historical Financials'!D30 -> 0 | E32: ='Historical Financials'!E30 -> -48 | F32: ='Historical Financials'!F30 -> -59 | H32: ='Historical Financials'!H30 -> 0 | I32: ='Historical Financials'!I30 -> 0 | J32: ='Historical Financials'!J30 -> 0 | K32: ='Historical Financials'!K30 -> 0 | L32: ='Historical Financials'!L30 -> 0 | M32: ='Historical Financials'!M30 -> 0 | N32: ='Historical Financials'!N30 -> -39 | O32: ='Historical Financials'!O30 -> -9 | ... V32: ='Historical Financials'!V30 -> 4438 | X32: =SUM(G32:K32) -> 0 | Y32: =SUM(I32:L32) -> 0 | Z32: =SUM(J32:M32) -> 0 | AA32: =SUM(K32:N32) -> -39 | AB32: =SUM(L32:O32) -> -48 | AC32: =SUM(M32:P32) -> -56 | AD32: =SUM(N32:Q32) -> -71 | AE32: =SUM(O32:R32) -> -48 | AF32: =SUM(P32:S32) -> -59 | ... AI32: =SUM(S32:V32) -> 19675 | AK32: =SUM(AI32/AE32)-1 -> -410.89583
B33: (-) Cash Interest | C33: 0 | D33: 0 | E33: 0 | F33: 0 | H33: 0 | I33: 0 | J33: 0 | K33: =D33 -> 0 | L33: 0 | M33: 0 | N33: 0 | O33: =E33 -> 0 | P33: 0 | Q33: 0 | R33: 0 | S33: =F33 -> 0 | T33: 0 | U33: 0 | V33: 0 | X33: =SUM(G33:K33) -> 0 | Y33: =SUM(I33:L33) -> 0 | Z33: =SUM(J33:M33) -> 0 | AA33: =SUM(K33:N33) -> 0 | AB33: =SUM(L33:O33) -> 0 | AC33: =SUM(M33:P33) -> 0 | AD33: =SUM(N33:Q33) -> 0 | AE33: =SUM(O33:R33) -> 0 | AF33: =SUM(P33:S33) -> 0 | ... AI33: =SUM(S33:V33) -> 0 | AK33: =SUM(AI33/AE33)-1 -> #DIV/0!
B34: (+/-) Changes in NWC | C34: =SUM('Historical Financials'!C103:C108) -> -202 | D34: =SUM('Historical Financials'!D103:D108) -> -2495 | E34: =SUM('Historical Financials'!E103:E108) -> -12612 | F34: =SUM('Historical Financials'!F103:F108) -> -13194 | H34: =SUM('Historical Financials'!H103:H108) -> 1773 | I34: =SUM('Historical Financials'!I103:I108) -> 2773 | J34: =SUM('Historical Financials'!J103:J108) -> -3270 | K34: =SUM('Historical Financials'!K103:K108) -> -3771 | L34: =SUM('Historical Financials'!L103:L108) -> -706 | M34: =SUM('Historical Financials'!M103:M108) -> 619 | N34: =SUM('Historical Financials'!N103:N108) -> -2571 | O34: =SUM('Historical Financials'!O103:O108) -> -9954 | ... V34: =SUM('Historical Financials'!V103:V108) -> -43598 | X34: =SUM(G34:K34) -> -2495 | Y34: =SUM(I34:L34) -> -4974 | Z34: =SUM(J34:M34) -> -7128 | AA34: =SUM(K34:N34) -> -6429 | AB34: =SUM(L34:O34) -> -12612 | AC34: =SUM(M34:P34) -> -8805 | AD34: =SUM(N34:Q34) -> -15819 | AE34: =SUM(O34:R34) -> -13124 | AF34: =SUM(P34:S34) -> -13194 | ... AI34: =SUM(S34:V34) -> -62782 | AK34: =SUM(AI34/AE34)-1 -> 3.783755
B35: Discretionary Cash-Flows | C35: =SUM(C28+SUM(C31:C34)) -> -37997 | D35: =SUM(D28+SUM(D31:D34)) -> -62696 | E35: =SUM(E28+SUM(E31:E34)) -> -108557 | F35: =SUM(F28+SUM(F31:F34)) -> -142073 | H35: =SUM(H28+SUM(H31:H34)) -> -11702 | I35: =SUM(I28+SUM(I31:I34)) -> -13695 | J35: =SUM(J28+SUM(J31:J34)) -> -18513 | K35: =SUM(K28+SUM(K31:K34)) -> -18786 | L35: =SUM(L28+SUM(L31:L34)) -> -18698 | M35: =SUM(M28+SUM(M31:M34)) -> -21170 | N35: =SUM(N28+SUM(N31:N34)) -> -30395 | O35: =SUM(O28+SUM(O31:O34)) -> -38294 | ... V35: =SUM(V28+SUM(V31:V34)) -> -116048 | X35: =SUM(X28+SUM(X31:X34)) -> -62696 | Y35: =SUM(Y28+SUM(Y31:Y34)) -> -69692 | Z35: =SUM(Z28+SUM(Z31:Z34)) -> -77167 | AA35: =SUM(AA28+SUM(AA31:AA34)) -> -89049 | AB35: =SUM(AB28+SUM(AB31:AB34)) -> -108557 | AC35: =SUM(AC28+SUM(AC31:AC34)) -> -135923 | AD35: =SUM(AD28+SUM(AD31:AD34)) -> -147523 | AE35: =SUM(AE28+SUM(AE31:AE34)) -> -139267 | ... AI35: =SUM(AI28+SUM(AI31:AI34)) -> -249217 | AK35: =SUM(AI35/AE35)-1 -> 0.78949069
B37: (+/-) Proceeds / (Purchases) of Equity, net | C37: ='Historical Financials'!C121 -> 30559 | D37: ='Historical Financials'!D121 -> 1059 | E37: ='Historical Financials'!E121 -> 1954 | F37: ='Historical Financials'!F121 -> 41449 | H37: ='Historical Financials'!H121 -> 148 | I37: ='Historical Financials'!I121 -> 907 | J37: ='Historical Financials'!J121 -> 1110 | K37: ='Historical Financials'!K121 -> -1106 | L37: ='Historical Financials'!L121 -> 52 | M37: ='Historical Financials'!M121 -> 489 | N37: ='Historical Financials'!N121 -> 234 | O37: ='Historical Financials'!O121 -> 1179 | ... V37: ='Historical Financials'!V121 -> 1003573 | X37: =SUM(G37:K37) -> 1059 | Y37: =SUM(I37:L37) -> 963 | Z37: =SUM(J37:M37) -> 545 | AA37: =SUM(K37:N37) -> -331 | AB37: =SUM(L37:O37) -> 1954 | AC37: =SUM(M37:P37) -> 3261 | AD37: =SUM(N37:Q37) -> 2598 | AE37: =SUM(O37:R37) -> 3449 | AF37: =SUM(P37:S37) -> 41449 | ... AI37: =SUM(S37:V37) -> 1415609
B38: (+/-) Maturities / (Purchases) of available-for-sale securities | C38: =SUM('Historical Financials'!C114:C115) -> -203761 | D38: =SUM('Historical Financials'!D114:D115) -> -295644 | E38: =SUM('Historical Financials'!E114:E115) -> 88315 | F38: =SUM('Historical Financials'!F114:F115) -> 121753 | H38: =SUM('Historical Financials'!H114:H115) -> -300835 | I38: =SUM('Historical Financials'!I114:I115) -> -29974 | J38: =SUM('Historical Financials'!J114:J115) -> 27072 | K38: =SUM('Historical Financials'!K114:K115) -> 8093 | L38: =SUM('Historical Financials'!L114:L115) -> 23661 | M38: =SUM('Historical Financials'!M114:M115) -> -19592 | N38: =SUM('Historical Financials'!N114:N115) -> 51246 | O38: =SUM('Historical Financials'!O114:O115) -> 33000 | ... V38: =SUM('Historical Financials'!V114:V115) -> -620687 | X38: =SUM(G38:K38) -> -295644 | Y38: =SUM(I38:L38) -> 28852 | Z38: =SUM(J38:M38) -> 39234 | AA38: =SUM(K38:N38) -> 63408 | AB38: =SUM(L38:O38) -> 88315 | AC38: =SUM(M38:P38) -> 113080 | AD38: =SUM(N38:Q38) -> 149720 | AE38: =SUM(O38:R38) -> 110030 | AF38: =SUM(P38:S38) -> 121753 | ... AI38: =SUM(S38:V38) -> -799914
B39: (+/-) Divestitures / (Acquisitions) | C39: ='Historical Financials'!C116 -> 0 | D39: ='Historical Financials'!D116 -> -848 | E39: ='Historical Financials'!E116 -> 0 | F39: ='Historical Financials'!F116 -> -15454 | H39: ='Historical Financials'!H116 -> 0 | I39: ='Historical Financials'!I116 -> 0 | J39: ='Historical Financials'!J116 -> 0 | K39: ='Historical Financials'!K116 -> -848 | L39: ='Historical Financials'!L116 -> 0 | M39: ='Historical Financials'!M116 -> 0 | N39: ='Historical Financials'!N116 -> 0 | O39: ='Historical Financials'!O116 -> 0 | ... V39: ='Historical Financials'!V116 -> -41767 | X39: =SUM(G39:K39) -> -848 | Y39: =SUM(I39:L39) -> -848 | Z39: =SUM(J39:M39) -> -848 | AA39: =SUM(K39:N39) -> -848 | AB39: =SUM(L39:O39) -> 0 | AC39: =SUM(M39:P39) -> 0 | AD39: =SUM(N39:Q39) -> 0 | AE39: =SUM(O39:R39) -> 0 | AF39: =SUM(P39:S39) -> -15454 | ... AI39: =SUM(S39:V39) -> -28554
B40: (+/-) Other Investing Activities | C40: ='Historical Financials'!C117 -> -620 | D40: ='Historical Financials'!D117 -> -1049 | E40: ='Historical Financials'!E117 -> -1288 | F40: ='Historical Financials'!F117 -> -1672 | H40: ='Historical Financials'!H117 -> -134 | I40: ='Historical Financials'!I117 -> -236 | J40: ='Historical Financials'!J117 -> -228 | K40: ='Historical Financials'!K117 -> -451 | L40: ='Historical Financials'!L117 -> -318 | M40: ='Historical Financials'!M117 -> -310 | N40: ='Historical Financials'!N117 -> -429 | O40: ='Historical Financials'!O117 -> -231 | ... V40: ='Historical Financials'!V117 -> -4999 | X40: =SUM(G40:K40) -> -1049 | Y40: =SUM(I40:L40) -> -1233 | Z40: =SUM(J40:M40) -> -1307 | AA40: =SUM(K40:N40) -> -1508 | AB40: =SUM(L40:O40) -> -1288 | AC40: =SUM(M40:P40) -> -1327 | AD40: =SUM(N40:Q40) -> -1552 | AE40: =SUM(O40:R40) -> -1432 | AF40: =SUM(P40:S40) -> -1672 | ... AI40: =SUM(S40:V40) -> -5777
B41: (+/-) Other Financing Activities | C41: ='Historical Financials'!C122 -> 572668 | D41: ='Historical Financials'!D122 -> 37 | E41: ='Historical Financials'!E122 -> -193 | F41: ='Historical Financials'!F122 -> 238 | H41: ='Historical Financials'!H122 -> 0 | I41: ='Historical Financials'!I122 -> 0 | J41: ='Historical Financials'!J122 -> 0 | K41: ='Historical Financials'!K122 -> 37 | L41: ='Historical Financials'!L122 -> -18 | M41: ='Historical Financials'!M122 -> 17 | N41: ='Historical Financials'!N122 -> 10 | O41: ='Historical Financials'!O122 -> -202 | ... V41: ='Historical Financials'!V122 -> 986 | X41: =SUM(G41:K41) -> 37 | Y41: =SUM(I41:L41) -> 19 | Z41: =SUM(J41:M41) -> 36 | AA41: =SUM(K41:N41) -> 46 | AB41: =SUM(L41:O41) -> -193 | AC41: =SUM(M41:P41) -> -175 | AD41: =SUM(N41:Q41) -> -51 | AE41: =SUM(O41:R41) -> -58 | AF41: =SUM(P41:S41) -> 238 | ... AI41: =SUM(S41:V41) -> 1080
B42: (+/-) Other Operating Activities | C42: ='Historical Financials'!C100 -> 6223 | D42: ='Historical Financials'!D100 -> 961 | E42: ='Historical Financials'!E100 -> 1994 | F42: ='Historical Financials'!F100 -> 5323 | H42: ='Historical Financials'!H100 -> -360 | I42: ='Historical Financials'!I100 -> -998 | J42: ='Historical Financials'!J100 -> 1710 | K42: ='Historical Financials'!K100 -> 609 | L42: ='Historical Financials'!L100 -> -1440 | M42: ='Historical Financials'!M100 -> 2436 | N42: ='Historical Financials'!N100 -> 430 | O42: ='Historical Financials'!O100 -> 568 | ... V42: ='Historical Financials'!V100 -> -215 | X42: =SUM(G42:K42) -> 961 | Y42: =SUM(I42:L42) -> -119 | Z42: =SUM(J42:M42) -> 3315 | AA42: =SUM(K42:N42) -> 2035 | AB42: =SUM(L42:O42) -> 1994 | AC42: =SUM(M42:P42) -> 4373 | AD42: =SUM(N42:Q42) -> 3154 | AE42: =SUM(O42:R42) -> 4859 | AF42: =SUM(P42:S42) -> 5323 | ... AI42: =SUM(S42:V42) -> -12981
B43: (+/-) Other | D43: =SUM(D48:D49)-SUM(C48:C49)-SUM(D35:D42) -> 3522 | E43: =SUM(E48:E49)-SUM(D48:D49)-SUM(E35:E42) -> 9073 | F43: =SUM(F48:F49)-SUM(E48:E49)-SUM(F35:F42) -> 9164 | H43: =SUM(H48:H49)-SUM(C48:C49)-SUM(H35:H42) -> 609 | I43: =SUM(I48:I49)-SUM(H48:H49)-SUM(I35:I42) -> 1213 | J43: =SUM(J48:J49)-SUM(I48:I49)-SUM(J35:J42) -> 2079 | K43: =SUM(K48:K49)-SUM(J48:J49)-SUM(K35:K42) -> -379 | L43: =SUM(L48:L49)-SUM(K48:K49)-SUM(L35:L42) -> 4295 | M43: =SUM(M48:M49)-SUM(L48:L49)-SUM(M35:M42) -> 213 | N43: =SUM(N48:N49)-SUM(M48:M49)-SUM(N35:N42) -> 2057 | O43: =SUM(O48:O49)-SUM(N48:N49)-SUM(O35:O42) -> 2508 | P43: =SUM(P48:P49)-SUM(O48:O49)-SUM(P35:P42) -> 2349 | ... V43: =SUM(V48:V49)-SUM(U48:U49)-SUM(V35:V42) -> -14878 | X43: =SUM(G43:K43) -> 3522 | Y43: =SUM(I43:L43) -> 7208 | Z43: =SUM(J43:M43) -> 6208 | AA43: =SUM(K43:N43) -> 6186 | AB43: =SUM(L43:O43) -> 9073 | AC43: =SUM(M43:P43) -> 7127 | AD43: =SUM(N43:Q43) -> 9180 | AE43: =SUM(O43:R43) -> 9348 | AF43: =SUM(P43:S43) -> 9164 | ... AI43: =SUM(S43:V43) -> -4386
B44: Free-Cash Flows | C44: =SUM(C35+SUM(C37:C43)) -> 367072 | D44: =SUM(D35+SUM(D37:D43)) -> -354658 | E44: =SUM(E35+SUM(E37:E43)) -> -8702 | F44: =SUM(F35+SUM(F37:F43)) -> 18728 | H44: =SUM(H35+SUM(H37:H43)) -> -312274 | I44: =SUM(I35+SUM(I37:I43)) -> -42783 | J44: =SUM(J35+SUM(J37:J43)) -> 13230 | K44: =SUM(K35+SUM(K37:K43)) -> -12831 | L44: =SUM(L35+SUM(L37:L43)) -> 7534 | M44: =SUM(M35+SUM(M37:M43)) -> -37917 | N44: =SUM(N35+SUM(N37:N43)) -> 23153 | O44: =SUM(O35+SUM(O37:O43)) -> -1472 | ... V44: =SUM(V35+SUM(V37:V43)) -> 205965 | X44: =SUM(X35+SUM(X37:X43)) -> -354658 | Y44: =SUM(Y35+SUM(Y37:Y43)) -> -34850 | Z44: =SUM(Z35+SUM(Z37:Z43)) -> -29984 | AA44: =SUM(AA35+SUM(AA37:AA43)) -> -20061 | AB44: =SUM(AB35+SUM(AB37:AB43)) -> -8702 | AC44: =SUM(AC35+SUM(AC37:AC43)) -> -9584 | AD44: =SUM(AD35+SUM(AD37:AD43)) -> 15526 | AE44: =SUM(AE35+SUM(AE37:AE43)) -> -13071 | ... AI44: =SUM(AI35+SUM(AI37:AI43)) -> 315860
B46: Capitalization
B48: Cash & Cash Equivelants | C48: ='Historical Financials'!C45 -> 399025 | D48: ='Historical Financials'!D45 -> 42367 | E48: ='Historical Financials'!E45 -> 33249 | F48: ='Historical Financials'!F45 -> 51946 | H48: ='Historical Financials'!H45 -> 86751 | I48: ='Historical Financials'!I45 -> 43968 | J48: ='Historical Financials'!J45 -> 57198 | K48: ='Historical Financials'!K45 -> 42367 | L48: ='Historical Financials'!L45 -> 49901 | M48: ='Historical Financials'!M45 -> 11882 | N48: ='Historical Financials'!N45 -> 34721 | O48: ='Historical Financials'!O45 -> 33249 | ... V48: ='Historical Financials'!V45 -> 339742 | X48: =K48 -> 42367 | Y48: =L48 -> 49901 | Z48: =M48 -> 11882 | AA48: =N48 -> 34721 | AB48: =O48 -> 33249 | AC48: =P48 -> 57640 | AD48: =Q48 -> 39313 | AE48: =R48 -> 27734 | ... AI48: =V48 -> 339742
B49: Restricted Cash | C49: ='Historical Financials'!C46 -> 0 | D49: ='Historical Financials'!D46 -> 2000 | E49: ='Historical Financials'!E46 -> 2416 | F49: ='Historical Financials'!F46 -> 2447 | H49: ='Historical Financials'!H46 -> 0 | I49: ='Historical Financials'!I46 -> 0 | J49: ='Historical Financials'!J46 -> 0 | K49: ='Historical Financials'!K46 -> 2000 | L49: ='Historical Financials'!L46 -> 2000 | M49: ='Historical Financials'!M46 -> 2102 | N49: ='Historical Financials'!N46 -> 2416 | O49: ='Historical Financials'!O46 -> 2416 | ... V49: ='Historical Financials'!V46 -> 6290 | X49: =K49 -> 2000 | Y49: =L49 -> 2000 | Z49: =M49 -> 2102 | AA49: =N49 -> 2416 | AB49: =O49 -> 2416 | AC49: =P49 -> 2434 | AD49: =Q49 -> 2439 | AE49: =R49 -> 2438 | ... AI49: =V49 -> 6290
B50: Short-term Investments | C50: ='Historical Financials'!C47 -> 123443 | D50: ='Historical Financials'!D47 -> 311430 | E50: ='Historical Financials'!E47 -> 319776 | F50: ='Historical Financials'!F47 -> 285896 | H50: ='Historical Financials'!H47 -> 329157 | I50: ='Historical Financials'!I47 -> 379383 | J50: ='Historical Financials'!J47 -> 348435 | K50: ='Historical Financials'!K47 -> 311430 | L50: ='Historical Financials'!L47 -> 335966 | M50: ='Historical Financials'!M47 -> 361677 | N50: ='Historical Financials'!N47 -> 346853 | O50: ='Historical Financials'!O47 -> 319776 | ... V50: ='Historical Financials'!V47 -> 736333 | X50: =K50 -> 311430 | Y50: =L50 -> 335966 | Z50: =M50 -> 361677 | AA50: =N50 -> 346853 | AB50: =O50 -> 319776 | AC50: =P50 -> 315276 | AD50: =Q50 -> 328045 | AE50: =R50 -> 335538 | ... AI50: =V50 -> 736333
B51: Long-term Investments | C51: ='Historical Financials'!C53 -> 80110 | D51: ='Historical Financials'!D53 -> 182001 | E51: ='Historical Financials'!E53 -> 100489 | F51: ='Historical Financials'!F53 -> 23545 | H51: ='Historical Financials'!H53 -> 170460 | I51: ='Historical Financials'!I53 -> 147992 | J51: ='Historical Financials'!J53 -> 150154 | K51: ='Historical Financials'!K53 -> 182001 | L51: ='Historical Financials'!L53 -> 137646 | M51: ='Historical Financials'!M53 -> 133542 | N51: ='Historical Financials'!N53 -> 101115 | O51: ='Historical Financials'!O53 -> 100489 | ... V51: ='Historical Financials'!V53 -> 402603 | X51: =K51 -> 182001 | Y51: =L51 -> 137646 | Z51: =M51 -> 133542 | AA51: =N51 -> 101115 | AB51: =O51 -> 100489 | AC51: =P51 -> 59090 | AD51: =Q51 -> 32171 | AE51: =R51 -> 17131 | ... AI51: =V51 -> 402603
B52: Total Liquidity | C52: =SUM(C48:C51) -> 602578 | D52: =SUM(D48:D51) -> 537798 | E52: =SUM(E48:E51) -> 455930 | F52: =SUM(F48:F51) -> 363834 | H52: =SUM(H48:H51) -> 586368 | I52: =SUM(I48:I51) -> 571343 | J52: =SUM(J48:J51) -> 555787 | K52: =SUM(K48:K51) -> 537798 | L52: =SUM(L48:L51) -> 525513 | M52: =SUM(M48:M51) -> 509203 | N52: =SUM(N48:N51) -> 485105 | O52: =SUM(O48:O51) -> 455930 | ... V52: =SUM(V48:V51) -> 1484968 | X52: =SUM(X48:X51) -> 537798 | Y52: =SUM(Y48:Y51) -> 525513 | Z52: =SUM(Z48:Z51) -> 509203 | AA52: =SUM(AA48:AA51) -> 485105 | AB52: =SUM(AB48:AB51) -> 455930 | AC52: =SUM(AC48:AC51) -> 434440 | AD52: =SUM(AD48:AD51) -> 401968 | AE52: =SUM(AE48:AE51) -> 382841 | ... AI52: =SUM(AI48:AI51) -> 1484968
B54: Balance Sheet Metrics:
B55: Accounts Receivable | C55: ='Historical Financials'!C48 -> 707 | D55: ='Historical Financials'!D48 -> 3292 | E55: ='Historical Financials'!E48 -> 11467 | F55: ='Historical Financials'!F48 -> 10188 | H55: ='Historical Financials'!H48 -> 569 | I55: ='Historical Financials'!I48 -> 1782 | J55: ='Historical Financials'!J48 -> 2876 | K55: ='Historical Financials'!K48 -> 3292 | L55: ='Historical Financials'!L48 -> 1837 | M55: ='Historical Financials'!M48 -> 2428 | N55: ='Historical Financials'!N48 -> 3033 | O55: ='Historical Financials'!O48 -> 11467 | ... V55: ='Historical Financials'!V48 -> 36912 | X55: =K55 -> 3292 | Y55: =L55 -> 1837 | Z55: =M55 -> 2428 | AA55: =N55 -> 3033 | AB55: =O55 -> 11467 | AC55: =P55 -> 9556 | AD55: =Q55 -> 7893 | AE55: =R55 -> 4137 | ... AI55: =V55 -> 36912
B56: Accounts Payable | C56: ='Historical Financials'!C62 -> 1882 | D56: ='Historical Financials'!D62 -> 3055 | E56: ='Historical Financials'!E62 -> 5599 | F56: ='Historical Financials'!F62 -> 5230 | H56: ='Historical Financials'!H62 -> 1967 | I56: ='Historical Financials'!I62 -> 3680 | J56: ='Historical Financials'!J62 -> 5042 | K56: ='Historical Financials'!K62 -> 3055 | L56: ='Historical Financials'!L62 -> 3597 | M56: ='Historical Financials'!M62 -> 4560 | N56: ='Historical Financials'!N62 -> 6408 | O56: ='Historical Financials'!O62 -> 5599 | ... V56: ='Historical Financials'!V62 -> 16970 | X56: =K56 -> 3055 | Y56: =L56 -> 3597 | Z56: =M56 -> 4560 | AA56: =N56 -> 6408 | AB56: =O56 -> 5599 | AC56: =P56 -> 5852 | AD56: =Q56 -> 6324 | AE56: =R56 -> 4854 | ... AI56: =V56 -> 16970
B57: Unearned Revenue, Current | C57: ='Historical Financials'!C65 -> 3430 | D57: ='Historical Financials'!D65 -> 8729 | E57: ='Historical Financials'!E65 -> 12087 | F57: ='Historical Financials'!F65 -> 10678 | H57: ='Historical Financials'!H65 -> 3417 | I57: ='Historical Financials'!I65 -> 4885 | J57: ='Historical Financials'!J65 -> 4700 | K57: ='Historical Financials'!K65 -> 8729 | L57: ='Historical Financials'!L65 -> 6294 | M57: ='Historical Financials'!M65 -> 8428 | N57: ='Historical Financials'!N65 -> 5216 | O57: ='Historical Financials'!O65 -> 12087 | ... V57: ='Historical Financials'!V65 -> 21855 | X57: =K57 -> 8729 | Y57: =L57 -> 6294 | Z57: =M57 -> 8428 | AA57: =N57 -> 5216 | AB57: =O57 -> 12087 | AC57: =P57 -> 16742 | AD57: =Q57 -> 13668 | AE57: =R57 -> 8332 | ... AI57: =V57 -> 21855
B58: Unearned Revenue, Non-Current | C58: ='Historical Financials'!C71 -> 1533 | D58: ='Historical Financials'!D71 -> 1201 | E58: ='Historical Financials'!E71 -> 447 | F58: ='Historical Financials'!F71 -> 0 | H58: ='Historical Financials'!H71 -> 489 | I58: ='Historical Financials'!I71 -> 616 | J58: ='Historical Financials'!J71 -> 741 | K58: ='Historical Financials'!K71 -> 1201 | L58: ='Historical Financials'!L71 -> 954 | M58: ='Historical Financials'!M71 -> 707 | N58: ='Historical Financials'!N71 -> 457 | O58: ='Historical Financials'!O71 -> 447 | ... V58: ='Historical Financials'!V71 -> 3384 | X58: =K58 -> 1201 | Y58: =L58 -> 954 | Z58: =M58 -> 707 | AA58: =N58 -> 457 | AB58: =O58 -> 447 | AC58: =P58 -> 181 | AD58: =Q58 -> 121 | AE58: =R58 -> 60 | ... AI58: =V58 -> 3384
B59: Property Plant, and Equiptment | C59: ='Historical Financials'!C54 -> 18870 | D59: ='Historical Financials'!D54 -> 26014 | E59: ='Historical Financials'!E54 -> 37515 | F59: ='Historical Financials'!F54 -> 52761 | H59: ='Historical Financials'!H54 -> 21131 | I59: ='Historical Financials'!I54 -> 24872 | J59: ='Historical Financials'!J54 -> 25065 | K59: ='Historical Financials'!K54 -> 26014 | L59: ='Historical Financials'!L54 -> 26488 | M59: ='Historical Financials'!M54 -> 29089 | N59: ='Historical Financials'!N54 -> 35356 | O59: ='Historical Financials'!O54 -> 37515 | ... V59: ='Historical Financials'!V54 -> 119564 | X59: =K59 -> 26014 | Y59: =L59 -> 26488 | Z59: =M59 -> 29089 | AA59: =N59 -> 35356 | AB59: =O59 -> 37515 | AC59: =P59 -> 42380 | AD59: =Q59 -> 47883 | AE59: =R59 -> 49454 | ... AI59: =V59 -> 119564
B60: Current Liabilities | C60: ='Historical Financials'!C67 -> 9691 | D60: ='Historical Financials'!D67 -> 20160 | E60: ='Historical Financials'!E67 -> 37164 | F60: ='Historical Financials'!F67 -> 36085 | H60: ='Historical Financials'!H67 -> 11385 | I60: ='Historical Financials'!I67 -> 14291 | J60: ='Historical Financials'!J67 -> 19631 | K60: ='Historical Financials'!K67 -> 20160 | L60: ='Historical Financials'!L67 -> 20860 | M60: ='Historical Financials'!M67 -> 23628 | N60: ='Historical Financials'!N67 -> 28598 | O60: ='Historical Financials'!O67 -> 37164 | ... V60: ='Historical Financials'!V67 -> 139280 | X60: =K60 -> 20160 | Y60: =L60 -> 20860 | Z60: =M60 -> 23628 | AA60: =N60 -> 28598 | AB60: =O60 -> 37164 | AC60: =P60 -> 34705 | AD60: =Q60 -> 30788 | AE60: =R60 -> 32324 | ... AI60: =V60 -> 139280
B61: Total Liabilities | C61: ='Historical Financials'!C74 -> 50798 | D61: ='Historical Financials'!D74 -> 29781 | E61: ='Historical Financials'!E74 -> 68586 | F61: ='Historical Financials'!F74 -> 124526 | H61: ='Historical Financials'!H74 -> 37668 | I61: ='Historical Financials'!I74 -> 24314 | J61: ='Historical Financials'!J74 -> 30971 | K61: ='Historical Financials'!K74 -> 29781 | L61: ='Historical Financials'!L74 -> 35685 | M61: ='Historical Financials'!M74 -> 53606 | N61: ='Historical Financials'!N74 -> 66882 | O61: ='Historical Financials'!O74 -> 68586 | ... V61: ='Historical Financials'!V74 -> 2031549 | X61: =K61 -> 29781 | Y61: =L61 -> 35685 | Z61: =M61 -> 53606 | AA61: =N61 -> 66882 | AB61: =O61 -> 68586 | AC61: =P61 -> 64093 | AD61: =Q61 -> 54161 | AE61: =R61 -> 62228 | ... AI61: =V61 -> 2031549
B63: Consolidated Debt | C63: 0 | D63: 0 | E63: 0 | F63: 0 | H63: 0 | I63: 0 | J63: 0 | K63: =D63 -> 0 | L63: 0 | M63: 0 | N63: 0 | O63: =E63 -> 0 | P63: 0 | Q63: 0 | R63: 0 | S63: =F63 -> 0 | T63: 0 | U63: 0 | V63: 0 | X63: =K63 -> 0 | Y63: =L63 -> 0 | Z63: =M63 -> 0 | AA63: =N63 -> 0 | AB63: =O63 -> 0 | AC63: =P63 -> 0 | AD63: =Q63 -> 0 | AE63: =R63 -> 0 | ... AI63: =V63 -> 0
B64: Total Debt | C64: =SUM(C63:C63) -> 0 | D64: =SUM(D63:D63) -> 0 | E64: =SUM(E63:E63) -> 0 | F64: =SUM(F63:F63) -> 0 | H64: =SUM(H63:H63) -> 0 | I64: =SUM(I63:I63) -> 0 | J64: =SUM(J63:J63) -> 0 | K64: =SUM(K63:K63) -> 0 | L64: =SUM(L63:L63) -> 0 | M64: =SUM(M63:M63) -> 0 | N64: =SUM(N63:N63) -> 0 | O64: =SUM(O63:O63) -> 0 | ... V64: =SUM(V63:V63) -> 0 | X64: =SUM(X63:X63) -> 0 | Y64: =SUM(Y63:Y63) -> 0 | Z64: =SUM(Z63:Z63) -> 0 | AA64: =SUM(AA63:AA63) -> 0 | AB64: =SUM(AB63:AB63) -> 0 | AC64: =SUM(AC63:AC63) -> 0 | AD64: =SUM(AD63:AD63) -> 0 | AE64: =SUM(AE63:AE63) -> 0 | ... AI64: =SUM(AI63:AI63) -> 0
B66: Total Shareholder Equity | C66: ='Historical Financials'!C81 -> 591230 | D66: ='Historical Financials'!D81 -> 568211 | E66: ='Historical Financials'!E81 -> 484994 | F66: ='Historical Financials'!F81 -> 383862 | H66: ='Historical Financials'!H81 -> 589783 | I66: ='Historical Financials'!I81 -> 592678 | J66: ='Historical Financials'!J81 -> 575630 | K66: ='Historical Financials'!K81 -> 568211 | L66: ='Historical Financials'!L81 -> 552237 | M66: ='Historical Financials'!M81 -> 523246 | N66: ='Historical Financials'!N81 -> 498496 | O66: ='Historical Financials'!O81 -> 484994 | ... V66: ='Historical Financials'!V81 -> 2287799 | X66: =K66 -> 568211 | Y66: =L66 -> 552237 | Z66: =M66 -> 523246 | AA66: =N66 -> 498496 | AB66: =O66 -> 484994 | AC66: =P66 -> 479769 | AD66: =Q66 -> 463274 | AE66: =R66 -> 435683 | ... AI66: =V66 -> 2287799
B67: Total Book Capitalization | C67: =SUM(C64:C66) -> 591230 | D67: =SUM(D64:D66) -> 568211 | E67: =SUM(E64:E66) -> 484994 | F67: =SUM(F64:F66) -> 383862 | H67: =SUM(H64:H66) -> 589783 | I67: =SUM(I64:I66) -> 592678 | J67: =SUM(J64:J66) -> 575630 | K67: =SUM(K64:K66) -> 568211 | L67: =SUM(L64:L66) -> 552237 | M67: =SUM(M64:M66) -> 523246 | N67: =SUM(N64:N66) -> 498496 | O67: =SUM(O64:O66) -> 484994 | ... V67: =SUM(V64:V66) -> 2287799 | X67: =SUM(X64:X66) -> 568211 | Y67: =SUM(Y64:Y66) -> 552237 | Z67: =SUM(Z64:Z66) -> 523246 | AA67: =SUM(AA64:AA66) -> 498496 | AB67: =SUM(AB64:AB66) -> 484994 | AC67: =SUM(AC64:AC66) -> 479769 | AD67: =SUM(AD64:AD66) -> 463274 | AE67: =SUM(AE64:AE66) -> 435683 | ... AI67: =SUM(AI64:AI66) -> 2287799
B69: Credit Metrics
B71: Total Leverage | C71: NM | D71: NM | E71: NM | F71: NM | L71: NM | M71: NM | N71: NM | O71: NM | P71: NM | Q71: NM | R71: NM | S71: NM | T71: NM | U71: NM | V71: NM | X71: NM | Y71: NM | Z71: NM | AA71: NM | AB71: NM | AC71: NM | AD71: NM | AE71: NM | AF71: NM | AG71: NM | AH71: NM | AI71: NM
B72: Net Leverage (C&CE) | C72: NM | D72: NM | E72: NM | F72: NM | L72: NM | M72: NM | N72: NM | O72: NM | P72: NM | Q72: NM | R72: NM | S72: NM | T72: NM | U72: NM | V72: NM | X72: NM | Y72: NM | Z72: NM | AA72: NM | AB72: NM | AC72: NM | AD72: NM | AE72: NM | AF72: NM | AG72: NM | AH72: NM | AI72: NM
B73: Interest Coverage | C73: NM | D73: NM | E73: NM | F73: NM | L73: NM | M73: NM | N73: NM | O73: NM | P73: NM | Q73: NM | R73: NM | S73: NM | T73: NM | U73: NM | V73: NM | X73: NM | Y73: NM | Z73: NM | AA73: NM | AB73: NM | AC73: NM | AD73: NM | AE73: NM | AF73: NM | AG73: NM | AH73: NM | AI73: NM
B74: Debt Service Coverage | C74: NM | D74: NM | E74: NM | F74: NM | L74: NM | M74: NM | N74: NM | O74: NM | P74: NM | Q74: NM | R74: NM | S74: NM | T74: NM | U74: NM | V74: NM | X74: NM | Y74: NM | Z74: NM | AA74: NM | AB74: NM | AC74: NM | AD74: NM | AE74: NM | AF74: NM | AG74: NM | AH74: NM | AI74: NM
B75: Fixed Charge Coverage | C75: NM | D75: NM | E75: NM | F75: NM | L75: NM | M75: NM | N75: NM | O75: NM | P75: NM | Q75: NM | R75: NM | S75: NM | T75: NM | U75: NM | V75: NM | X75: NM | Y75: NM | Z75: NM | AA75: NM | AB75: NM | AC75: NM | AD75: NM | AE75: NM | AF75: NM | AG75: NM | AH75: NM | AI75: NM
B76: Debt-to-Book Capitalization | C76: NM | D76: NM | E76: NM | F76: NM | L76: NM | M76: NM | N76: NM | O76: NM | P76: NM | Q76: NM | R76: NM | S76: NM | T76: NM | U76: NM | V76: NM | X76: NM | Y76: NM | Z76: NM | AA76: NM | AB76: NM | AC76: NM | AD76: NM | AE76: NM | AF76: NM | AG76: NM | AH76: NM | AI76: NM
