Workbook

Sheet Background
B2: Company Name | C2: Ticker
B3: #VALUE! | C3: HUMA
B5: Pipeline
B6: Target | C6: Drug | D6: Indication | E6: Stage | F6: Data Release
B7: ACELLULAR TISSUE ENGINEERED VESSELS:
B8: TRAUMA | C8: N/A | E8: 3
B9: DIALYSIS (AV ACCESS) | C9: N/A | E9: 3
B10: PERIPHERAL ARTERY DISEASE (PAD) | C10: N/A | E10: 2
B11: CORONARY ARTERY BYPASS GRAFTING (CABG) | C11: N/A | E11: PRECLINICAL
B12: PEDIATRIC HEART DISEASE | C12: N/A | E12: PRECLINICAL
B13: ADVANCED ORGAN SYSTEMS:
B14: BIOVASCULAR PANCREAS™ (TYPE 1 DIABETES) | C14: N/A | E14: PRECLINICAL
B15: LUNG | C15: N/A | E15: PRECLINICAL
B16: ADVANCED TISSUE CONSTRUCTS:
B17: URINARY CONDUIT | C17: N/A | E17: PRECLINICAL
B18: TRACHEAL REPLACEMENT | C18: N/A | E18: PRECLINICAL
B19: ESOPHAGEAL REPLACEMENT | C19: N/A | E19: PRECLINICAL

Sheet Base Financials
B2: Humacyte Inc (NASDAQ: HUMA) | D2: FYE | H2: Quarterly | Q2: Quarterly | W2: LTM | AC2: LTM | AI2: Variance
B3: 3-Statement Model | C3: 2021 | D3: 2022 | E3: 2023 | F3: 2024 | H3: 1Q22 | I3: 2Q22 | J3: 3Q22 | K3: 4Q22 | L3: 1Q23 | M3: 2Q23 | N3: 3Q23 | O3: 4Q23 | P3: 1Q24 | Q3: 2Q24 | R3: 3Q24 | S3: 4Q24 | T3: 1Q25 | U3: 2Q25 | W3: =K3 -> 4Q22 | X3: =L3 -> 1Q23 | Y3: =M3 -> 2Q23 | Z3: =N3 -> 3Q23 | AA3: =O3 -> 4Q23 | AB3: =P3 -> 1Q24 | AC3: =Q3 -> 2Q24 | AD3: =R3 -> 3Q24 | ... AG3: =U3 -> 2Q25
B4: ($ In Thousands) | C4: 44561 | D4: 44926 | E4: 45291 | F4: 45657 | H4: 44651 | I4: 44742 | J4: 44834 | K4: 44926 | L4: 45016 | M4: 45107 | N4: 45199 | O4: 45291 | P4: 45382 | Q4: 45473 | R4: 45565 | S4: 45657 | T4: 45747 | U4: 45838 | W4: =K4 -> 44926 | X4: =L4 -> 45016 | Y4: =M4 -> 45107 | Z4: =N4 -> 45199 | AA4: =O4 -> 45291 | AB4: =P4 -> 45382 | AC4: =Q4 -> 45473 | AD4: =R4 -> 45565 | ... AG4: =U4 -> 45838
A6: X | B6: Income Statement
B8: Product Revenue | C8: 0 | D8: 0 | E8: 0 | F8: 0 | H8: 0 | I8: 0 | J8: 0 | K8: =SUM(D8-SUM(H8:J8)) -> 0 | L8: 0 | M8: 0 | N8: 0 | O8: =SUM(E8-SUM(L8:N8)) -> 0 | P8: 0 | Q8: 0 | R8: 0 | S8: =SUM(F8-SUM(P8:R8)) -> 0 | T8: 147 | U8: 100 | W8: =SUM(H8:K8) -> 0 | X8: =SUM(I8:L8) -> 0 | Y8: =SUM(J8:M8) -> 0 | Z8: =SUM(K8:N8) -> 0 | AA8: =SUM(L8:O8) -> 0 | AB8: =SUM(M8:P8) -> 0 | AC8: =SUM(N8:Q8) -> 0 | AD8: =SUM(O8:R8) -> 0 | ... AG8: =SUM(R8:U8) -> 247 | AI8: =SUM(AG8/AC8)-1 -> #DIV/0!
B9: Contract Revenue | C9: 0 | D9: 0 | E9: 0 | F9: 0 | H9: 0 | I9: 0 | J9: 0 | K9: =SUM(D9-SUM(H9:J9)) -> 0 | L9: 0 | M9: 0 | N9: 0 | O9: =SUM(E9-SUM(L9:N9)) -> 0 | P9: 0 | Q9: 0 | R9: 0 | S9: =SUM(F9-SUM(P9:R9)) -> 0 | T9: 370 | U9: 201 | W9: =SUM(H9:K9) -> 0 | X9: =SUM(I9:L9) -> 0 | Y9: =SUM(J9:M9) -> 0 | Z9: =SUM(K9:N9) -> 0 | AA9: =SUM(L9:O9) -> 0 | AB9: =SUM(M9:P9) -> 0 | AC9: =SUM(N9:Q9) -> 0 | AD9: =SUM(O9:R9) -> 0 | ... AG9: =SUM(R9:U9) -> 571 | AI9: =SUM(AG9/AC9)-1 -> #DIV/0!
B10: Grant Revenue | C10: 1263 | D10: 1565 | E10: 0 | F10: 0 | H10: 233 | I10: 1301 | J10: 31 | K10: =SUM(D10-SUM(H10:J10)) -> 0 | L10: 0 | M10: 0 | N10: 0 | O10: =SUM(E10-SUM(L10:N10)) -> 0 | P10: 0 | Q10: 0 | R10: 0 | S10: =SUM(F10-SUM(P10:R10)) -> 0 | T10: 0 | U10: 0 | W10: =SUM(H10:K10) -> 1565 | X10: =SUM(I10:L10) -> 1332 | Y10: =SUM(J10:M10) -> 31 | Z10: =SUM(K10:N10) -> 0 | AA10: =SUM(L10:O10) -> 0 | AB10: =SUM(M10:P10) -> 0 | AC10: =SUM(N10:Q10) -> 0 | AD10: =SUM(O10:R10) -> 0 | ... AG10: =SUM(R10:U10) -> 0 | AI10: =SUM(AG10/AC10)-1 -> #DIV/0!
B11: Total Revenue | C11: =SUM(C8:C10) -> 1263 | D11: =SUM(D8:D10) -> 1565 | E11: =SUM(E8:E10) -> 0 | F11: =SUM(F8:F10) -> 0 | H11: =SUM(H8:H10) -> 233 | I11: =SUM(I8:I10) -> 1301 | J11: =SUM(J8:J10) -> 31 | K11: =SUM(K8:K10) -> 0 | L11: =SUM(L8:L10) -> 0 | M11: =SUM(M8:M10) -> 0 | N11: =SUM(N8:N10) -> 0 | O11: =SUM(O8:O10) -> 0 | ... U11: =SUM(U8:U10) -> 301 | W11: =SUM(W8:W10) -> 1565 | X11: =SUM(X8:X10) -> 1332 | Y11: =SUM(Y8:Y10) -> 31 | Z11: =SUM(Z8:Z10) -> 0 | AA11: =SUM(AA8:AA10) -> 0 | AB11: =SUM(AB8:AB10) -> 0 | AC11: =SUM(AC8:AC10) -> 0 | AD11: =SUM(AD8:AD10) -> 0 | ... AG11: =SUM(AG8:AG10) -> 818 | AI11: =SUM(AG11/AC11)-1 -> #DIV/0!
B13: Cost of Goods Sold | C13: 0 | D13: 0 | E13: 0 | F13: 0 | H13: 0 | I13: 0 | J13: 0 | K13: =SUM(D13-SUM(H13:J13)) -> 0 | L13: 0 | M13: 0 | N13: 0 | O13: =SUM(E13-SUM(L13:N13)) -> 0 | P13: 0 | Q13: 0 | R13: 0 | S13: =SUM(F13-SUM(P13:R13)) -> 0 | T13: -147 | U13: -213 | W13: =SUM(H13:K13) -> 0 | X13: =SUM(I13:L13) -> 0 | Y13: =SUM(J13:M13) -> 0 | Z13: =SUM(K13:N13) -> 0 | AA13: =SUM(L13:O13) -> 0 | AB13: =SUM(M13:P13) -> 0 | AC13: =SUM(N13:Q13) -> 0 | AD13: =SUM(O13:R13) -> 0 | ... AG13: =SUM(R13:U13) -> -360 | AI13: =SUM(AG13/AC13)-1 -> #DIV/0!
B14: Gross Profit (Loss) | C14: =+SUM(C11+C13) -> 1263 | D14: =+SUM(D11+D13) -> 1565 | E14: =+SUM(E11+E13) -> 0 | F14: =+SUM(F11+F13) -> 0 | H14: =+SUM(H11+H13) -> 233 | I14: =+SUM(I11+I13) -> 1301 | J14: =+SUM(J11+J13) -> 31 | K14: =+SUM(K11+K13) -> 0 | L14: =+SUM(L11+L13) -> 0 | M14: =+SUM(M11+M13) -> 0 | N14: =+SUM(N11+N13) -> 0 | O14: =+SUM(O11+O13) -> 0 | ... U14: =+SUM(U11+U13) -> 88 | W14: =+SUM(W11+W13) -> 1565 | X14: =+SUM(X11+X13) -> 1332 | Y14: =+SUM(Y11+Y13) -> 31 | Z14: =+SUM(Z11+Z13) -> 0 | AA14: =+SUM(AA11+AA13) -> 0 | AB14: =+SUM(AB11+AB13) -> 0 | AC14: =+SUM(AC11+AC13) -> 0 | AD14: =+SUM(AD11+AD13) -> 0 | ... AG14: =+SUM(AG11+AG13) -> 458 | AI14: =SUM(AG14/AC14)-1 -> #DIV/0!
B16: Research and Development (R&D) | C16: -61341 | D16: -63260 | E16: -76550 | F16: -88599 | H16: -16314 | I16: -14652 | J16: -17337 | K16: =SUM(D16-SUM(H16:J16)) -> -14957 | L16: -17278 | M16: -20540 | N16: -18552 | O16: =SUM(E16-SUM(L16:N16)) -> -20180 | P16: -21264 | Q16: -23753 | R16: -22926 | S16: =SUM(F16-SUM(P16:R16)) -> -20656 | T16: -15418 | U16: -22006 | W16: =SUM(H16:K16) -> -63260 | X16: =SUM(I16:L16) -> -64224 | Y16: =SUM(J16:M16) -> -70112 | Z16: =SUM(K16:N16) -> -71327 | AA16: =SUM(L16:O16) -> -76550 | AB16: =SUM(M16:P16) -> -80536 | AC16: =SUM(N16:Q16) -> -83749 | AD16: =SUM(O16:R16) -> -88123 | ... AG16: =SUM(R16:U16) -> -81006 | AI16: =SUM(AG16/AC16)-1 -> -0.03275263
B17: General and Administrative (G&A) | C17: -21130 | D17: -22883 | E17: -23497 | F17: -25799 | H17: -5682 | I17: -5180 | J17: -6188 | K17: =SUM(D17-SUM(H17:J17)) -> -5833 | L17: -5234 | M17: -6191 | N17: -6070 | O17: =SUM(E17-SUM(L17:N17)) -> -6002 | P17: -5314 | Q17: -5746 | R17: -7307 | S17: =SUM(F17-SUM(P17:R17)) -> -7432 | T17: -8136 | U17: -7809 | W17: =SUM(H17:K17) -> -22883 | X17: =SUM(I17:L17) -> -22435 | Y17: =SUM(J17:M17) -> -23446 | Z17: =SUM(K17:N17) -> -23328 | AA17: =SUM(L17:O17) -> -23497 | AB17: =SUM(M17:P17) -> -23577 | AC17: =SUM(N17:Q17) -> -23132 | AD17: =SUM(O17:R17) -> -24369 | ... AG17: =SUM(R17:U17) -> -30684 | AI17: =SUM(AG17/AC17)-1 -> 0.32647415
B18: Total Operating Profit (Loss) | C18: =+SUM(C14+SUM(C16:C17)) -> -81208 | D18: =+SUM(D14+SUM(D16:D17)) -> -84578 | E18: =+SUM(E14+SUM(E16:E17)) -> -100047 | F18: =+SUM(F14+SUM(F16:F17)) -> -114398 | H18: =+SUM(H14+SUM(H16:H17)) -> -21763 | I18: =+SUM(I14+SUM(I16:I17)) -> -18531 | J18: =+SUM(J14+SUM(J16:J17)) -> -23494 | K18: =+SUM(K14+SUM(K16:K17)) -> -20790 | L18: =+SUM(L14+SUM(L16:L17)) -> -22512 | M18: =+SUM(M14+SUM(M16:M17)) -> -26731 | N18: =+SUM(N14+SUM(N16:N17)) -> -24622 | O18: =+SUM(O14+SUM(O16:O17)) -> -26182 | ... U18: =+SUM(U14+SUM(U16:U17)) -> -29727 | W18: =+SUM(W14+SUM(W16:W17)) -> -84578 | X18: =+SUM(X14+SUM(X16:X17)) -> -85327 | Y18: =+SUM(Y14+SUM(Y16:Y17)) -> -93527 | Z18: =+SUM(Z14+SUM(Z16:Z17)) -> -94655 | AA18: =+SUM(AA14+SUM(AA16:AA17)) -> -100047 | AB18: =+SUM(AB14+SUM(AB16:AB17)) -> -104113 | AC18: =+SUM(AC14+SUM(AC16:AC17)) -> -106881 | AD18: =+SUM(AD14+SUM(AD16:AD17)) -> -112492 | ... AG18: =+SUM(AG14+SUM(AG16:AG17)) -> -111232 | AI18: =SUM(AG18/AC18)-1 -> 0.040708826
B20: Interest income | C20: 16 | D20: 2629 | E20: 5467 | F20: 4104 | H20: 31 | I20: 301 | J20: 883 | K20: =SUM(D20-SUM(H20:J20)) -> 1414 | L20: 1475 | M20: 1479 | N20: 1369 | O20: =SUM(E20-SUM(L20:N20)) -> 1144 | P20: 1031 | Q20: 1310 | R20: 911 | S20: =SUM(F20-SUM(P20:R20)) -> 852 | T20: 662 | U20: 832 | W20: =SUM(H20:K20) -> 2629 | X20: =SUM(I20:L20) -> 4073 | Y20: =SUM(J20:M20) -> 5251 | Z20: =SUM(K20:N20) -> 5737 | AA20: =SUM(L20:O20) -> 5467 | AB20: =SUM(M20:P20) -> 5023 | AC20: =SUM(N20:Q20) -> 4854 | AD20: =SUM(O20:R20) -> 4396 | ... AG20: =SUM(R20:U20) -> 3257 | AI20: =SUM(AG20/AC20)-1 -> -0.329007
B21: Interest expense | C21: -4348 | D21: -6200 | E21: -6599 | F21: -9277 | H21: -1432 | I21: -1488 | J21: -1641 | K21: =SUM(D21-SUM(H21:J21)) -> -1639 | L21: -1699 | M21: -1710 | N21: -1463 | O21: =SUM(E21-SUM(L21:N21)) -> -1727 | P21: -1816 | Q21: -2515 | R21: -2438 | S21: =SUM(F21-SUM(P21:R21)) -> -2508 | T21: -3000 | U21: -2545 | W21: =SUM(H21:K21) -> -6200 | X21: =SUM(I21:L21) -> -6467 | Y21: =SUM(J21:M21) -> -6689 | Z21: =SUM(K21:N21) -> -6511 | AA21: =SUM(L21:O21) -> -6599 | AB21: =SUM(M21:P21) -> -6716 | AC21: =SUM(N21:Q21) -> -7521 | AD21: =SUM(O21:R21) -> -8496 | ... AG21: =SUM(R21:U21) -> -10491 | AI21: =SUM(AG21/AC21)-1 -> 0.3948943
B22: Change in fair value of Contingent Earnout Liability | C22: 55772 | D22: 75767 | E22: -10023 | F22: -33045 | H22: 3258 | I22: 56353 | J22: -962 | K22: =SUM(D22-SUM(H22:J22)) -> 17118 | L22: -14191 | M22: 3627 | N22: -1144 | O22: =SUM(E22-SUM(L22:N22)) -> 1685 | P22: -4593 | Q22: -25571 | R22: -8489 | S22: =SUM(F22-SUM(P22:R22)) -> 5608 | T22: 49731 | U22: -5470 | W22: =SUM(H22:K22) -> 75767 | X22: =SUM(I22:L22) -> 58318 | Y22: =SUM(J22:M22) -> 5592 | Z22: =SUM(K22:N22) -> 5410 | AA22: =SUM(L22:O22) -> -10023 | AB22: =SUM(M22:P22) -> -425 | AC22: =SUM(N22:Q22) -> -29623 | AD22: =SUM(O22:R22) -> -36968 | ... AG22: =SUM(R22:U22) -> 41380 | AI22: =SUM(AG22/AC22)-1 -> -2.3968876
B23: Change in fair value of derivative liabilities | C23: 0 | D23: 417 | E23: -260 | F23: 3915 | H23: 0 | I23: 0 | J23: 0 | K23: =SUM(D23-SUM(H23:J23)) -> 417 | L23: 0 | M23: -57 | N23: -135 | O23: =SUM(E23-SUM(L23:N23)) -> -68 | P23: 60 | Q23: -388 | R23: 1047 | S23: =SUM(F23-SUM(P23:R23)) -> 3196 | T23: 14930 | U23: -748 | W23: =SUM(H23:K23) -> 417 | X23: =SUM(I23:L23) -> 417 | Y23: =SUM(J23:M23) -> 360 | Z23: =SUM(K23:N23) -> 225 | AA23: =SUM(L23:O23) -> -260 | AB23: =SUM(M23:P23) -> -200 | AC23: =SUM(N23:Q23) -> -531 | AD23: =SUM(O23:R23) -> 651 | ... AG23: =SUM(R23:U23) -> 18425 | AI23: =SUM(AG23/AC23)-1 -> -35.698682
B24: Other Gains, Losses, and Adjustments (1) | C24: =56+3284-49 -> 3291 | D24: 0 | E24: =3107-2421 -> 686 | F24: 0 | H24: 74 | I24: 233 | J24: -67 | K24: =SUM(D24-SUM(H24:J24)) -> -240 | L24: -42 | M24: =3107-2421 -> 686 | N24: 0 | O24: =SUM(E24-SUM(L24:N24)) -> 42 | P24: 0 | Q24: 0 | R24: 0 | S24: =SUM(F24-SUM(P24:R24)) -> 0 | T24: 0 | U24: 0 | AC24: =SUM(N24:Q24) -> 42 | AD24: =SUM(O24:R24) -> 42 | AE24: =SUM(P24:S24) -> 0 | AF24: =SUM(Q24:T24) -> 0 | AG24: =SUM(R24:U24) -> 0 | AI24: =SUM(AG24/AC24)-1 -> -1
B25: Net loss | C25: =SUM(C18+SUM(C20:C24)) -> -26477 | D25: =SUM(D18+SUM(D20:D24)) -> -11965 | E25: =SUM(E18+SUM(E20:E24)) -> -110776 | F25: =SUM(F18+SUM(F20:F24)) -> -148701 | H25: =SUM(H18+SUM(H20:H24)) -> -19832 | I25: =SUM(I18+SUM(I20:I24)) -> 36868 | J25: =SUM(J18+SUM(J20:J24)) -> -25281 | K25: =SUM(K18+SUM(K20:K24)) -> -3720 | L25: =SUM(L18+SUM(L20:L24)) -> -36969 | M25: =SUM(M18+SUM(M20:M24)) -> -22706 | N25: =SUM(N18+SUM(N20:N24)) -> -25995 | O25: =SUM(O18+SUM(O20:O24)) -> -25106 | ... U25: =SUM(U18+SUM(U20:U24)) -> -37658 | W25: =SUM(W20:W24)-W18 -> 157191 | X25: =SUM(X20:X24)-X18 -> 141668 | Y25: =SUM(Y20:Y24)-Y18 -> 98041 | Z25: =SUM(Z20:Z24)-Z18 -> 99516 | AA25: =SUM(AA20:AA24)-AA18 -> 88632 | AB25: =SUM(AB20:AB24)-AB18 -> 101795 | AC25: =SUM(AC20:AC24)-AC18 -> 74102 | AD25: =SUM(AD20:AD24)-AD18 -> 72117 | ... AG25: =SUM(AG20:AG24)-AG18 -> 163803 | AI25: =SUM(AG25/AC25)-1 -> 1.2105071
B27: Weighted-average shares outstanding, diluted | C27: 39970.398 | D27: 103051.37 | E27: 103420.24 | F27: 118479.1 | H27: 103004.09 | I27: 103908.44 | J27: 103031.98 | K27: =D27 -> 103051.37 | L27: 103263.53 | M27: 103361.5 | N27: 103444.25 | O27: =E27 -> 103420.24 | P27: 108246.01 | Q27: 119174.68 | R27: 119408.57 | S27: =F27 -> 118479.1 | T27: 131759.3 | U27: 155437.28 | W27: =K27 -> 103051.37 | X27: =L27 -> 103263.53 | Y27: =M27 -> 103361.5 | Z27: =N27 -> 103444.25 | AA27: =O27 -> 103420.24 | AB27: =P27 -> 108246.01 | AC27: =Q27 -> 119174.68 | AD27: =R27 -> 119408.57 | ... AG27: =U27 -> 155437.28
B28: Earnings (Net Loss) Per Share | C28: =C25/C27 -> -0.66241522 | D28: =D25/D27 -> -0.11610715 | E28: =E25/E27 -> -1.071125 | F28: =F25/F27 -> -1.2550822 | H28: =H25/H27 -> -0.19253605 | I28: =I25/I27 -> 0.35481237 | J28: =J25/J27 -> -0.24537042 | K28: =K25/K27 -> -0.036098503 | L28: =L25/L27 -> -0.35800636 | M28: =M25/M27 -> -0.2196756 | N28: =N25/N27 -> -0.25129479 | O28: =O25/O27 -> -0.24275713 | ... U28: =U25/U27 -> -0.24227135 | W28: =W25/W27 -> 1.5253655 | X28: =X25/X27 -> 1.3719074 | Y28: =Y25/Y27 -> 0.94852531 | Z28: =Z25/Z27 -> 0.96202548 | AA28: =AA25/AA27 -> 0.85700828 | AB28: =AB25/AB27 -> 0.94040419 | AC28: =AC25/AC27 -> 0.62179315 | AD28: =AD25/AD27 -> 0.60395165 | ... AG28: =AG25/AG27 -> 1.0538205 | AI28: =SUM(AG28/AC28)-1 -> 0.69480887
B30: 1) "Other Gains, Losses, and Adjustments Consist of: Change in fair value of common stock warrant liabilities, Gain on PPP loan forgiveness, Employee retention credit, Loss on extinguishment of debt, and Transaction costs expensed.
A32: X | B32: Balance Sheet
B34: Current Assets
B35: Cash and cash equivalents | C35: 217502 | D35: 149772 | E35: 80448 | F35: 44937 | H35: 198222 | I35: 181035 | J35: 163731 | K35: =D35 -> 149772 | L35: 129570 | M35: 114604 | N35: 99986 | O35: =E35 -> 80448 | P35: 115505 | Q35: 93563 | R35: 20571 | S35: =F35 -> 44937 | T35: 62847 | U35: 38032 | W35: =K35 -> 149772 | X35: =L35 -> 129570 | Y35: =M35 -> 114604 | Z35: =N35 -> 99986 | AA35: =O35 -> 80448 | AB35: =P35 -> 115505 | AC35: =Q35 -> 93563 | AD35: =R35 -> 20571 | ... AG35: =U35 -> 38032 | AI35: =SUM(AG35/AC35)-1 -> -0.59351453
B36: Accounts receivable | C36: 176 | D36: 31 | E36: 0 | F36: 0 | H36: 233 | I36: 1301 | J36: 31 | K36: =D36 -> 31 | L36: 0 | M36: 0 | N36: 0 | O36: =E36 -> 0 | P36: 0 | Q36: 0 | R36: 0 | S36: =F36 -> 0 | T36: 488 | U36: 394 | W36: =K36 -> 31 | X36: =L36 -> 0 | Y36: =M36 -> 0 | Z36: =N36 -> 0 | AA36: =O36 -> 0 | AB36: =P36 -> 0 | AC36: =Q36 -> 0 | AD36: =R36 -> 0 | ... AG36: =U36 -> 394 | AI36: =SUM(AG36/AC36)-1 -> #DIV/0!
B37: Short-term investments | C37: 8000 | D37: 2107 | E37: 0 | F37: 0 | H37: 8000 | I37: 8000 | J37: 8000 | K37: =D37 -> 2107 | L37: 2107 | M37: 0 | N37: 0 | O37: =E37 -> 0 | P37: 0 | Q37: 0 | R37: 0 | S37: =F37 -> 0 | T37: 0 | U37: 0 | W37: =K37 -> 2107 | X37: =L37 -> 2107 | Y37: =M37 -> 0 | Z37: =N37 -> 0 | AA37: =O37 -> 0 | AB37: =P37 -> 0 | AC37: =Q37 -> 0 | AD37: =R37 -> 0 | ... AG37: =U37 -> 0 | AI37: =SUM(AG37/AC37)-1 -> #DIV/0!
B38: Inventory | C38: 0 | D38: 0 | E38: 0 | F38: 0 | H38: 0 | I38: 0 | J38: 0 | K38: =D38 -> 0 | L38: 0 | M38: 0 | N38: 0 | O38: =E38 -> 0 | P38: 0 | Q38: 0 | R38: 0 | S38: =F38 -> 0 | T38: 8020 | U38: 11067 | W38: =K38 -> 0 | X38: =L38 -> 0 | Y38: =M38 -> 0 | Z38: =N38 -> 0 | AA38: =O38 -> 0 | AB38: =P38 -> 0 | AC38: =Q38 -> 0 | AD38: =R38 -> 0 | ... AG38: =U38 -> 11067 | AI38: =SUM(AG38/AC38)-1 -> #DIV/0!
B39: Prepaid expenses and other current assets | C39: 3662 | D39: 2298 | E39: 2830 | F39: 2922 | H39: 2840 | I39: 2694 | J39: 2850 | K39: =D39 -> 2298 | L39: 2178 | M39: 5958 | N39: 2865 | O39: =E39 -> 2830 | P39: 2421 | Q39: 2547 | R39: 2434 | S39: =F39 -> 2922 | T39: 2350 | U39: 2237 | W39: =K39 -> 2298 | X39: =L39 -> 2178 | Y39: =M39 -> 5958 | Z39: =N39 -> 2865 | AA39: =O39 -> 2830 | AB39: =P39 -> 2421 | AC39: =Q39 -> 2547 | AD39: =R39 -> 2434 | ... AG39: =U39 -> 2237 | AI39: =SUM(AG39/AC39)-1 -> -0.12171182
B40: Total Current Assets | C40: =SUM(C35:C39) -> 229340 | D40: =SUM(D35:D39) -> 154208 | E40: =SUM(E35:E39) -> 83278 | F40: =SUM(F35:F39) -> 47859 | H40: =SUM(H35:H39) -> 209295 | I40: =SUM(I35:I39) -> 193030 | J40: =SUM(J35:J39) -> 174612 | K40: =SUM(K35:K39) -> 154208 | L40: =SUM(L35:L39) -> 133855 | M40: =SUM(M35:M39) -> 120562 | N40: =SUM(N35:N39) -> 102851 | O40: =SUM(O35:O39) -> 83278 | ... U40: =SUM(U35:U39) -> 51730 | W40: =SUM(W35:W39) -> 154208 | X40: =SUM(X35:X39) -> 133855 | Y40: =SUM(Y35:Y39) -> 120562 | Z40: =SUM(Z35:Z39) -> 102851 | AA40: =SUM(AA35:AA39) -> 83278 | AB40: =SUM(AB35:AB39) -> 117926 | AC40: =SUM(AC35:AC39) -> 96110 | AD40: =SUM(AD35:AD39) -> 23005 | ... AG40: =SUM(AG35:AG39) -> 51730 | AI40: =SUM(AG40/AC40)-1 -> -0.46176256
B42: Long-Term Assets
B43: Restricted cash | C43: 0 | D43: 0 | E43: 0 | F43: 50209 | H43: 0 | I43: 0 | J43: 0 | K43: =D43 -> 0 | L43: 0 | M43: 0 | N43: 0 | O43: =E43 -> 0 | P43: 0 | Q43: 0 | R43: 50209 | S43: =F43 -> 50209 | T43: 50209 | U43: 50209 | W43: =K43 -> 0 | X43: =L43 -> 0 | Y43: =M43 -> 0 | Z43: =N43 -> 0 | AA43: =O43 -> 0 | AB43: =P43 -> 0 | AC43: =Q43 -> 0 | AD43: =R43 -> 50209 | ... AG43: =U43 -> 50209 | AI43: =SUM(AG43/AC43)-1 -> #DIV/0!
B44: Property and equipment, net | C44: 35034 | D44: 30039 | E44: 26791 | F44: 23063 | H44: 33540 | I44: 32227 | J44: 31026 | K44: =D44 -> 30039 | L44: 29593 | M44: 28543 | N44: 27851 | O44: =E44 -> 26791 | P44: 25653 | Q44: 24820 | R44: 24250 | S44: =F44 -> 23063 | T44: 22436 | U44: 21191 | W44: =K44 -> 30039 | X44: =L44 -> 29593 | Y44: =M44 -> 28543 | Z44: =N44 -> 27851 | AA44: =O44 -> 26791 | AB44: =P44 -> 25653 | AC44: =Q44 -> 24820 | AD44: =R44 -> 24250 | ... AG44: =U44 -> 21191 | AI44: =SUM(AG44/AC44)-1 -> -0.14621273
B45: Finance lease right-of-use assets, net | C45: 21432 | D45: 19373 | E45: 17313 | F45: 15490 | H45: 20917 | I45: 20403 | J45: 19888 | K45: =D45 -> 19373 | L45: 18858 | M45: 18343 | N45: 17828 | O45: =E45 -> 17313 | P45: 17059 | Q45: 16536 | R45: 16013 | S45: =F45 -> 15490 | T45: 14966 | U45: 14443 | W45: =K45 -> 19373 | X45: =L45 -> 18858 | Y45: =M45 -> 18343 | Z45: =N45 -> 17828 | AA45: =O45 -> 17313 | AB45: =P45 -> 17059 | AC45: =Q45 -> 16536 | AD45: =R45 -> 16013 | ... AG45: =U45 -> 14443 | AI45: =SUM(AG45/AC45)-1 -> -0.12657233
B46: Other long-term assets | C46: 727 | D46: 682 | E46: 841 | F46: 1251 | H46: 716 | I46: 705 | J46: 693 | K46: =D46 -> 682 | L46: 670 | M46: 658 | N46: 855 | O46: =E46 -> 841 | P46: 828 | Q46: 815 | R46: 1287 | S46: =F46 -> 1251 | T46: 1237 | U46: 1222 | W46: =K46 -> 682 | X46: =L46 -> 670 | Y46: =M46 -> 658 | Z46: =N46 -> 855 | AA46: =O46 -> 841 | AB46: =P46 -> 828 | AC46: =Q46 -> 815 | AD46: =R46 -> 1287 | ... AG46: =U46 -> 1222 | AI46: =SUM(AG46/AC46)-1 -> 0.4993865
B47: Total Assets | C47: =SUM(C43:C46)+C40 -> 286533 | D47: =SUM(D43:D46)+D40 -> 204302 | E47: =SUM(E43:E46)+E40 -> 128223 | F47: =SUM(F43:F46)+F40 -> 137872 | H47: =SUM(H43:H46)+H40 -> 264468 | I47: =SUM(I43:I46)+I40 -> 246365 | J47: =SUM(J43:J46)+J40 -> 226219 | K47: =SUM(K43:K46)+K40 -> 204302 | L47: =SUM(L43:L46)+L40 -> 182976 | M47: =SUM(M43:M46)+M40 -> 168106 | N47: =SUM(N43:N46)+N40 -> 149385 | O47: =SUM(O43:O46)+O40 -> 128223 | ... U47: =SUM(U43:U46)+U40 -> 138795 | W47: =SUM(W43:W46)+W40 -> 204302 | X47: =SUM(X43:X46)+X40 -> 182976 | Y47: =SUM(Y43:Y46)+Y40 -> 168106 | Z47: =SUM(Z43:Z46)+Z40 -> 149385 | AA47: =SUM(AA43:AA46)+AA40 -> 128223 | AB47: =SUM(AB43:AB46)+AB40 -> 161466 | AC47: =SUM(AC43:AC46)+AC40 -> 138281 | AD47: =SUM(AD43:AD46)+AD40 -> 114764 | ... AG47: =SUM(AG43:AG46)+AG40 -> 138795 | AI47: =SUM(AG47/AC47)-1 -> 0.0037170689
B49: Current Liabilities
B50: Accounts payable | C50: 2094 | D50: 1595 | E50: 6490 | F50: 4490 | H50: 3037 | I50: 2537 | J50: 3255 | K50: =D50 -> 1595 | L50: 1954 | M50: 2362 | N50: 3018 | O50: =E50 -> 6490 | P50: 3452 | Q50: 6005 | R50: 6903 | S50: =F50 -> 4490 | T50: 5572 | U50: 6629 | W50: =K50 -> 1595 | X50: =L50 -> 1954 | Y50: =M50 -> 2362 | Z50: =N50 -> 3018 | AA50: =O50 -> 6490 | AB50: =P50 -> 3452 | AC50: =Q50 -> 6005 | AD50: =R50 -> 6903 | ... AG50: =U50 -> 6629 | AI50: =SUM(AG50/AC50)-1 -> 0.10391341
B51: Accrued expenses | C51: 6757 | D51: 7108 | E51: 9340 | F51: 11424 | H51: 5460 | I51: 6186 | J51: 7959 | K51: =D51 -> 7108 | L51: 6411 | M51: 6571 | N51: 9586 | O51: =E51 -> 9340 | P51: 7917 | Q51: 8950 | R51: 11151 | S51: =F51 -> 11424 | T51: 9701 | U51: 9186 | W51: =K51 -> 7108 | X51: =L51 -> 6411 | Y51: =M51 -> 6571 | Z51: =N51 -> 9586 | AA51: =O51 -> 9340 | AB51: =P51 -> 7917 | AC51: =Q51 -> 8950 | AD51: =R51 -> 11151 | ... AG51: =U51 -> 9186 | AI51: =SUM(AG51/AC51)-1 -> 0.026368715
B52: Finance lease obligation, current portion | C52: 1981 | D52: 2256 | E52: 2560 | F52: 2917 | H52: 2047 | I52: 2115 | J52: 2185 | K52: =D52 -> 2256 | L52: 2329 | M52: 2404 | N52: 2481 | O52: =E52 -> 2560 | P52: 2663 | Q52: 2746 | R52: 2831 | S52: =F52 -> 2917 | T52: 3006 | U52: 3093 | W52: =K52 -> 2256 | X52: =L52 -> 2329 | Y52: =M52 -> 2404 | Z52: =N52 -> 2481 | AA52: =O52 -> 2560 | AB52: =P52 -> 2663 | AC52: =Q52 -> 2746 | AD52: =R52 -> 2831 | ... AG52: =U52 -> 3093 | AI52: =SUM(AG52/AC52)-1 -> 0.12636562
B53: Revenue interest liability, current portion | C53: 0 | D53: 0 | E53: 0 | F53: 0 | H53: 0 | I53: 0 | J53: 0 | K53: =D53 -> 0 | L53: 0 | M53: 0 | N53: 0 | O53: =E53 -> 0 | P53: 0 | Q53: 0 | R53: 0 | S53: =F53 -> 0 | T53: 1690 | U53: 2116 | AC53: =Q53 -> 0 | AD53: =R53 -> 0 | AE53: =S53 -> 0 | AF53: =T53 -> 1690 | AG53: =U53 -> 2116 | AI53: =SUM(AG53/AC53)-1 -> #DIV/0!
B54: SVB loan payable, current portion | C54: 0 | D54: 8571 | E54: 0 | F54: 0 | H54: 0 | I54: 0 | J54: 4286 | K54: =D54 -> 8571 | L54: 12857 | M54: 0 | N54: 0 | O54: =E54 -> 0 | P54: 0 | Q54: 0 | R54: 0 | S54: =F54 -> 0 | T54: 0 | U54: 0 | AC54: =Q54 -> 0 | AD54: =R54 -> 0 | AE54: =S54 -> 0 | AF54: =T54 -> 0 | AG54: =U54 -> 0 | AI54: =SUM(AG54/AC54)-1 -> #DIV/0!
B55: Other Current liabilities (1) | C55: =45+173 -> 218 | D55: =50 -> 50 | E55: 53 | F55: 1123 | H55: =46+173 -> 219 | I55: =47+173 -> 220 | J55: =48+173 -> 221 | K55: =D55 -> 50 | L55: =50 -> 50 | M55: 51 | N55: 52 | O55: =E55 -> 53 | P55: 55 | Q55: 56 | R55: 57 | S55: =F55 -> 1123 | T55: =60 -> 60 | U55: =61 -> 61 | AC55: =Q55 -> 56 | AD55: =R55 -> 57 | AE55: =S55 -> 1123 | AF55: =T55 -> 60 | AG55: =U55 -> 61 | AI55: =SUM(AG55/AC55)-1 -> 0.089285714
B56: Total Current Liabilities | C56: =SUM(C50:C55) -> 11050 | D56: =SUM(D50:D55) -> 19580 | E56: =SUM(E50:E55) -> 18443 | F56: =SUM(F50:F55) -> 19954 | H56: =SUM(H50:H55) -> 10763 | I56: =SUM(I50:I55) -> 11058 | J56: =SUM(J50:J55) -> 17906 | K56: =SUM(K50:K55) -> 19580 | L56: =SUM(L50:L55) -> 23601 | M56: =SUM(M50:M55) -> 11388 | N56: =SUM(N50:N55) -> 15137 | O56: =SUM(O50:O55) -> 18443 | ... U56: =SUM(U50:U55) -> 21085 | W56: =SUM(W50:W55) -> 10959 | X56: =SUM(X50:X55) -> 10694 | Y56: =SUM(Y50:Y55) -> 11337 | Z56: =SUM(Z50:Z55) -> 15085 | AA56: =SUM(AA50:AA55) -> 18390 | AB56: =SUM(AB50:AB55) -> 14032 | AC56: =SUM(AC50:AC55) -> 17757 | AD56: =SUM(AD50:AD55) -> 20942 | ... AG56: =SUM(AG50:AG55) -> 21085 | AI56: =SUM(AG56/AC56)-1 -> 0.18741905
B58: Long-Term Liabilities
B59: Revenue interest liability, Non-Current | C59: 0 | D59: 0 | E59: 38600 | F59: 63354 | H59: 0 | I59: 0 | J59: 0 | K59: =D59 -> 0 | L59: 0 | M59: 36248 | N59: 37286 | O59: =E59 -> 38600 | P59: 57959 | Q59: 60078 | R59: 62117 | S59: =F59 -> 63354 | T59: 64672 | U59: 66425 | W59: =K59 -> 0 | X59: =L59 -> 0 | Y59: =M59 -> 36248 | Z59: =N59 -> 37286 | AA59: =O59 -> 38600 | AB59: =P59 -> 57959 | AC59: =Q59 -> 60078 | AD59: =R59 -> 62117 | ... AG59: =U59 -> 66425 | AI59: =SUM(AG59/AC59)-1 -> 0.10564599
B60: Contingent Earnout Liability | C60: 103660 | D60: 27893 | E60: 37916 | F60: 70961 | H60: 100402 | I60: 44049 | J60: 45011 | K60: =D60 -> 27893 | L60: 42084 | M60: 38457 | N60: 39601 | O60: =E60 -> 37916 | P60: 42509 | Q60: 68080 | R60: 76569 | S60: =F60 -> 70961 | T60: 21230 | U60: 26700 | W60: =K60 -> 27893 | X60: =L60 -> 42084 | Y60: =M60 -> 38457 | Z60: =N60 -> 39601 | AA60: =O60 -> 37916 | AB60: =P60 -> 42509 | AC60: =Q60 -> 68080 | AD60: =R60 -> 76569 | ... AG60: =U60 -> 26700 | AI60: =SUM(AG60/AC60)-1 -> -0.60781434
B61: Finance lease obligation, net of current portion | C61: 21109 | D61: 18853 | E61: 16293 | F61: 13620 | H61: 20581 | I61: 20018 | J61: 19442 | K61: =D61 -> 18853 | L61: 18252 | M61: 17614 | N61: 16960 | O61: =E61 -> 16293 | P61: 15850 | Q61: 15123 | R61: 14379 | S61: =F61 -> 13620 | T61: 12844 | U61: 12030 | W61: =K61 -> 18853 | X61: =L61 -> 18252 | Y61: =M61 -> 17614 | Z61: =N61 -> 16960 | AA61: =O61 -> 16293 | AB61: =P61 -> 15850 | AC61: =Q61 -> 15123 | AD61: =R61 -> 14379 | ... AG61: =U61 -> 12030 | AI61: =SUM(AG61/AC61)-1 -> -0.20452291
B62: SVB loan payable , Non-Current | C62: 27361 | D62: 20336 | E62: 0 | F62: 0 | H62: 27739 | I62: 28132 | J62: 24286 | K62: =D62 -> 20336 | L62: 16410 | M62: 0 | N62: 0 | O62: =E62 -> 0 | P62: 0 | Q62: 0 | R62: 0 | S62: =F62 -> 0 | T62: 0 | U62: 0 | AC62: =Q62 -> 0 | AD62: =R62 -> 0 | AE62: =S62 -> 0 | AF62: =T62 -> 0 | AG62: =U62 -> 0
B63: Other Non-Current Liabilities (2) | C63: =1179 -> 1179 | D63: =712 -> 712 | E63: =789+2636 -> 3425 | F63: =983+19254+2415 -> 22652 | H63: =670+423 -> 1093 | I63: =658+190 -> 848 | J63: =645+257 -> 902 | K63: =D63 -> 712 | L63: =620+122 -> 742 | M63: =890+2392 -> 3282 | N63: =872+2536 -> 3408 | O63: =E63 -> 3425 | P63: =830+4079 -> 4909 | Q63: =1264+4266 -> 5530 | R63: =1373+3105 -> 4478 | S63: =F63 -> 22652 | T63: =951+3320+3464 -> 7735 | U63: =984+4358+3161 -> 8503 | AC63: =Q63 -> 5530 | AD63: =R63 -> 4478 | AE63: =S63 -> 22652 | AF63: =T63 -> 7735 | AG63: =U63 -> 8503 | AI63: =SUM(AG63/AC63)-1 -> 0.53761302
B64: Total Liabilities | C64: =SUM(C59:C63)+C56 -> 164359 | D64: =SUM(D59:D63)+D56 -> 87374 | E64: =SUM(E59:E63)+E56 -> 114677 | F64: =SUM(F59:F63)+F56 -> 190541 | H64: =SUM(H59:H63)+H56 -> 160578 | I64: =SUM(I59:I63)+I56 -> 104105 | J64: =SUM(J59:J63)+J56 -> 107547 | K64: =SUM(K59:K63)+K56 -> 87374 | L64: =SUM(L59:L63)+L56 -> 101089 | M64: =SUM(M59:M63)+M56 -> 106989 | N64: =SUM(N59:N63)+N56 -> 112392 | O64: =SUM(O59:O63)+O56 -> 114677 | ... U64: =SUM(U59:U63)+U56 -> 134743 | W64: =SUM(W59:W63)+W56 -> 57705 | X64: =SUM(X59:X63)+X56 -> 71030 | Y64: =SUM(Y59:Y63)+Y56 -> 103656 | Z64: =SUM(Z59:Z63)+Z56 -> 108932 | AA64: =SUM(AA59:AA63)+AA56 -> 111199 | AB64: =SUM(AB59:AB63)+AB56 -> 130350 | AC64: =SUM(AC59:AC63)+AC56 -> 166568 | AD64: =SUM(AD59:AD63)+AD56 -> 178485 | ... AG64: =SUM(AG59:AG63)+AG56 -> 134743 | AI64: =SUM(AG64/AC64)-1 -> -0.19106311
B66: Stockholders’ Equity
B67: Common Stock | C67: 10 | D67: 10 | E67: 10 | F67: 13 | H67: 10 | I67: 10 | J67: 10 | K67: =D67 -> 10 | L67: 10 | M67: 10 | N67: 10 | O67: =E67 -> 10 | P67: 12 | Q67: 12 | R67: 12 | S67: =F67 -> 13 | T67: 16 | U67: 16 | W67: =K67 -> 10 | X67: =L67 -> 10 | Y67: =M67 -> 10 | Z67: =N67 -> 10 | AA67: =O67 -> 10 | AB67: =P67 -> 12 | AC67: =Q67 -> 12 | AD67: =R67 -> 12 | ... AG67: =U67 -> 16 | AI67: =SUM(AG67/AC67)-1 -> 0.33333333
B68: Additional paid-in capital | C68: 536737 | D68: 543456 | E68: 550850 | F68: 633333 | H68: 538285 | I68: 539787 | J68: 541480 | K68: =D68 -> 543456 | L68: 545384 | M68: 547320 | N68: 549191 | O68: =E68 -> 550850 | P68: 595350 | Q68: 597574 | R68: 601342 | S68: =F68 -> 633333 | T68: 682903 | U68: 688570 | W68: =K68 -> 543456 | X68: =L68 -> 545384 | Y68: =M68 -> 547320 | Z68: =N68 -> 549191 | AA68: =O68 -> 550850 | AB68: =P68 -> 595350 | AC68: =Q68 -> 597574 | AD68: =R68 -> 601342 | ... AG68: =U68 -> 688570 | AI68: =SUM(AG68/AC68)-1 -> 0.1522757
B69: Accumulated deficit | C69: -414573 | D69: -426538 | E69: -537314 | F69: -686015 | H69: -434405 | I69: -397537 | J69: -422818 | K69: =D69 -> -426538 | L69: -463507 | M69: -486213 | N69: -512208 | O69: =E69 -> -537314 | P69: -569210 | Q69: -625873 | R69: -665075 | S69: =F69 -> -686015 | T69: -646876 | U69: -684534 | W69: =K69 -> -426538 | X69: =L69 -> -463507 | Y69: =M69 -> -486213 | Z69: =N69 -> -512208 | AA69: =O69 -> -537314 | AB69: =P69 -> -569210 | AC69: =Q69 -> -625873 | AD69: =R69 -> -665075 | ... AG69: =U69 -> -684534 | AI69: =SUM(AG69/AC69)-1 -> 0.093726683
B70: Total Stockholders' Equity | C70: =SUM(C67:C69) -> 122174 | D70: =SUM(D67:D69) -> 116928 | E70: =SUM(E67:E69) -> 13546 | F70: =SUM(F67:F69) -> -52669 | H70: =SUM(H67:H69) -> 103890 | I70: =SUM(I67:I69) -> 142260 | J70: =SUM(J67:J69) -> 118672 | K70: =SUM(K67:K69) -> 116928 | L70: =SUM(L67:L69) -> 81887 | M70: =SUM(M67:M69) -> 61117 | N70: =SUM(N67:N69) -> 36993 | O70: =SUM(O67:O69) -> 13546 | ... U70: =SUM(U67:U69) -> 4052 | W70: =SUM(W67:W69) -> 116928 | X70: =SUM(X67:X69) -> 81887 | Y70: =SUM(Y67:Y69) -> 61117 | Z70: =SUM(Z67:Z69) -> 36993 | AA70: =SUM(AA67:AA69) -> 13546 | AB70: =SUM(AB67:AB69) -> 26152 | AC70: =SUM(AC67:AC69) -> -28287 | AD70: =SUM(AD67:AD69) -> -63721 | ... AG70: =SUM(AG67:AG69) -> 4052 | AI70: =SUM(AG70/AC70)-1 -> -1.143246
B71: Total Liabilities and Stockholders' Equity | C71: =SUM(C70+C64) -> 286533 | D71: =SUM(D70+D64) -> 204302 | E71: =SUM(E70+E64) -> 128223 | F71: =SUM(F70+F64) -> 137872 | H71: =SUM(H70+H64) -> 264468 | I71: =SUM(I70+I64) -> 246365 | J71: =SUM(J70+J64) -> 226219 | K71: =SUM(K70+K64) -> 204302 | L71: =SUM(L70+L64) -> 182976 | M71: =SUM(M70+M64) -> 168106 | N71: =SUM(N70+N64) -> 149385 | O71: =SUM(O70+O64) -> 128223 | ... U71: =SUM(U70+U64) -> 138795 | W71: =SUM(W70+W64) -> 174633 | X71: =SUM(X70+X64) -> 152917 | Y71: =SUM(Y70+Y64) -> 164773 | Z71: =SUM(Z70+Z64) -> 145925 | AA71: =SUM(AA70+AA64) -> 124745 | AB71: =SUM(AB70+AB64) -> 156502 | AC71: =SUM(AC70+AC64) -> 138281 | AD71: =SUM(AD70+AD64) -> 114764 | ... AG71: =SUM(AG70+AG64) -> 138795 | AI71: =SUM(AG71/AC71)-1 -> 0.0037170689
B73: Balance Check | C73: =C71-C47 -> 0 | D73: =D71-D47 -> 0 | E73: =E71-E47 -> 0 | F73: =F71-F47 -> 0 | H73: =H71-H47 -> 0 | I73: =I71-I47 -> 0 | J73: =J71-J47 -> 0 | K73: =K71-K47 -> 0 | L73: =L71-L47 -> 0 | M73: =M71-M47 -> 0 | N73: =N71-N47 -> 0 | O73: =O71-O47 -> 0 | ... U73: =U71-U47 -> 0 | W73: =W71-W47 -> -29669 | X73: =X71-X47 -> -30059 | Y73: =Y71-Y47 -> -3333 | Z73: =Z71-Z47 -> -3460 | AA73: =AA71-AA47 -> -3478 | AB73: =AB71-AB47 -> -4964 | AC73: =AC71-AC47 -> 0 | AD73: =AD71-AD47 -> 0 | ... AG73: =AG71-AG47 -> 0
B75: 1) "Other Current Liabilities" Consists of: Other Current Liabilities, Deferred payroll tax, and Operating lease obligation, current portion.
B76: 2) "Other Non-Current Liabilities" Consists of: Other long-term liabilities, Operating lease obligation, net of current portion, Common stock warrant liabilities, and Contingent derivative liability.
A78: X | B78: Cash-Flows Statement
B80: Cash flows from Operating Activities
B81: Net loss | C81: =C25 -> -26477 | D81: =D25 -> -11965 | E81: =E25 -> -110776 | F81: =F25 -> -148701 | H81: =H25 -> -19832 | I81: =I25 -> 36868 | J81: =J25 -> -25281 | K81: =K25 -> -3720 | L81: =L25 -> -36969 | M81: =M25 -> -22706 | N81: =N25 -> -25995 | O81: =O25 -> -25106 | ... U81: =U25 -> -37658 | W81: =SUM(H81:K81) -> -11965 | X81: =SUM(I81:L81) -> -29102 | Y81: =SUM(J81:M81) -> -88676 | Z81: =SUM(K81:N81) -> -89390 | AA81: =SUM(L81:O81) -> -110776 | AB81: =SUM(M81:P81) -> -105703 | AC81: =SUM(N81:Q81) -> -139660 | AD81: =SUM(O81:R81) -> -152867 | ... AG81: =SUM(R81:U81) -> -58661 | AI81: =SUM(AG81/AC81)-1 -> -0.57997279
B83: Adjustments to reconcile net loss to net cash from operating activities
B84: Depreciation expense | C84: 6181 | D84: 6151 | E84: 5659 | F84: 5104 | H84: 1525 | I84: =3032-H84 -> 1507 | J84: =4552-I84-H84 -> 1520 | K84: =SUM(D84-SUM(H84:J84)) -> 1599 | L84: 1558 | M84: =3026-L84 -> 1468 | N84: =4341-M84-L84 -> 1315 | O84: =SUM(E84-SUM(L84:N84)) -> 1318 | P84: 1274 | Q84: =2530-P84 -> 1256 | R84: =3819-Q84-P84 -> 1289 | S84: =SUM(F84-SUM(P84:R84)) -> 1285 | T84: 1308 | U84: =2645-T84 -> 1337 | W84: =SUM(H84:K84) -> 6151 | X84: =SUM(I84:L84) -> 6184 | Y84: =SUM(J84:M84) -> 6145 | Z84: =SUM(K84:N84) -> 5940 | AA84: =SUM(L84:O84) -> 5659 | AB84: =SUM(M84:P84) -> 5375 | AC84: =SUM(N84:Q84) -> 5163 | AD84: =SUM(O84:R84) -> 5137 | ... AG84: =SUM(R84:U84) -> 5219 | AI84: =SUM(AG84/AC84)-1 -> 0.010846407
B85: Amortization expense | C85: 2060 | D85: 2059 | E85: 2060 | F85: 2086 | H85: 515 | I85: =1029-H85 -> 514 | J85: =1544-I85-H85 -> 515 | K85: =SUM(D85-SUM(H85:J85)) -> 515 | L85: 515 | M85: =1030-L85 -> 515 | N85: =1545-M85-L85 -> 515 | O85: =SUM(E85-SUM(L85:N85)) -> 515 | P85: 517 | Q85: =1040-P85 -> 523 | R85: =1563-Q85-P85 -> 523 | S85: =SUM(F85-SUM(P85:R85)) -> 523 | T85: 524 | U85: =1047-T85 -> 523 | W85: =SUM(H85:K85) -> 2059 | X85: =SUM(I85:L85) -> 2059 | Y85: =SUM(J85:M85) -> 2060 | Z85: =SUM(K85:N85) -> 2060 | AA85: =SUM(L85:O85) -> 2060 | AB85: =SUM(M85:P85) -> 2062 | AC85: =SUM(N85:Q85) -> 2070 | AD85: =SUM(O85:R85) -> 2078 | ... AG85: =SUM(R85:U85) -> 2093 | AI85: =SUM(AG85/AC85)-1 -> 0.011111111
B86: Stock-based compensation expense | C86: 10146 | D86: 6184 | E86: 6828 | F86: 6137 | H86: 1547 | I86: =3038-H86 -> 1491 | J86: =4514-I86-H86 -> 1476 | K86: =SUM(D86-SUM(H86:J86)) -> 1670 | L86: 1809 | M86: =3650-L86 -> 1841 | N86: =5422-M86-L86 -> 1772 | O86: =SUM(E86-SUM(L86:N86)) -> 1406 | P86: 1454 | Q86: =2891-P86 -> 1437 | R86: =4443-Q86-P86 -> 1552 | S86: =SUM(F86-SUM(P86:R86)) -> 1694 | T86: 2487 | U86: =4822-T86 -> 2335 | W86: =SUM(H86:K86) -> 6184 | X86: =SUM(I86:L86) -> 6446 | Y86: =SUM(J86:M86) -> 6796 | Z86: =SUM(K86:N86) -> 7092 | AA86: =SUM(L86:O86) -> 6828 | AB86: =SUM(M86:P86) -> 6473 | AC86: =SUM(N86:Q86) -> 6069 | AD86: =SUM(O86:R86) -> 5849 | ... AG86: =SUM(R86:U86) -> 8068 | AI86: =SUM(AG86/AC86)-1 -> 0.32937881
B87: Change in fair value of Contingent Earnout Liability | C87: -55772 | D87: -75767 | E87: 10023 | F87: 33045 | H87: -3258 | I87: =-59611-H87 -> -56353 | J87: =-58649-I87-H87 -> 962 | K87: =SUM(D87-SUM(H87:J87)) -> -17118 | L87: 14191 | M87: =10564-L87 -> -3627 | N87: =11708-M87-L87 -> 1144 | O87: =SUM(E87-SUM(L87:N87)) -> -1685 | P87: 4593 | Q87: =30164-P87 -> 25571 | R87: =38653-Q87-P87 -> 8489 | S87: =SUM(F87-SUM(P87:R87)) -> -5608 | T87: -49731 | U87: =-44261-T87 -> 5470 | W87: =SUM(H87:K87) -> -75767 | X87: =SUM(I87:L87) -> -58318 | Y87: =SUM(J87:M87) -> -5592 | Z87: =SUM(K87:N87) -> -5410 | AA87: =SUM(L87:O87) -> 10023 | AB87: =SUM(M87:P87) -> 425 | AC87: =SUM(N87:Q87) -> 29623 | AD87: =SUM(O87:R87) -> 36968 | ... AG87: =SUM(R87:U87) -> -41380 | AI87: =SUM(AG87/AC87)-1 -> -2.3968876
B88: Change in fair value of derivative liabilities | C88: -56 | D88: -417 | E88: 260 | F88: -3915 | H88: 0 | I88: 0 | J88: 0 | K88: 0 | L88: 0 | M88: =99-L88 -> 99 | N88: =234-M88-L88 -> 135 | O88: =SUM(E88-SUM(L88:N88)) -> 26 | P88: -60 | Q88: =328-P88 -> 388 | R88: =-719-Q88-P88 -> -1047 | S88: =SUM(F88-SUM(P88:R88)) -> -3196 | T88: -14930 | U88: =-14182-T88 -> 748 | W88: =SUM(H88:K88) -> 0 | X88: =SUM(I88:L88) -> 0 | Y88: =SUM(J88:M88) -> 99 | Z88: =SUM(K88:N88) -> 234 | AA88: =SUM(L88:O88) -> 260 | AB88: =SUM(M88:P88) -> 200 | AC88: =SUM(N88:Q88) -> 489 | AD88: =SUM(O88:R88) -> -693 | ... AG88: =SUM(R88:U88) -> -18425 | AI88: =SUM(AG88/AC88)-1 -> -38.678937
B89: Non-cash interest expense | C89: 0 | D89: 0 | E89: 3099 | F89: 7754 | H89: 0 | I89: 0 | J89: 0 | K89: 0 | L89: 0 | M89: =737-L89 -> 737 | N89: =1780-M89-L89 -> 1043 | O89: =SUM(E89-SUM(L89:N89)) -> 1319 | P89: 1418 | Q89: =3544-P89 -> 2126 | R89: =5606-Q89-P89 -> 2062 | S89: =SUM(F89-SUM(P89:R89)) -> 2148 | T89: 2152 | U89: =4367-T89 -> 2215 | W89: =SUM(H89:K89) -> 0 | X89: =SUM(I89:L89) -> 0 | Y89: =SUM(J89:M89) -> 737 | Z89: =SUM(K89:N89) -> 1780 | AA89: =SUM(L89:O89) -> 3099 | AB89: =SUM(M89:P89) -> 4517 | AC89: =SUM(N89:Q89) -> 5906 | AD89: =SUM(O89:R89) -> 6925 | ... AG89: =SUM(R89:U89) -> 8577 | AI89: =SUM(AG89/AC89)-1 -> 0.45225195
B90: Non-cash operating lease costs | C90: 42 | D90: 45 | E90: 50 | F90: 53 | H90: 11 | I90: =22-H90 -> 11 | J90: =34-I90-H90 -> 12 | K90: =SUM(D90-SUM(H90:J90)) -> 11 | L90: 12 | M90: =24-L90 -> 12 | N90: =37-M90-L90 -> 13 | O90: =SUM(E90-SUM(L90:N90)) -> 13 | P90: 13 | Q90: =26-P90 -> 13 | R90: =39-Q90-P90 -> 13 | S90: =SUM(F90-SUM(P90:R90)) -> 14 | T90: 14 | U90: =29-T90 -> 15 | W90: =SUM(H90:K90) -> 45 | X90: =SUM(I90:L90) -> 46 | Y90: =SUM(J90:M90) -> 47 | Z90: =SUM(K90:N90) -> 48 | AA90: =SUM(L90:O90) -> 50 | AB90: =SUM(M90:P90) -> 51 | AC90: =SUM(N90:Q90) -> 52 | AD90: =SUM(O90:R90) -> 52 | ... AG90: =SUM(R90:U90) -> 56 | AI90: =SUM(AG90/AC90)-1 -> 0.076923077
B91: Loss on disposal of property and equipment | C91: 0 | D91: 6 | E91: 18 | F91: 4 | H91: 0 | I91: 0 | J91: 0 | K91: 0 | L91: 0 | M91: =9-L91 -> 9 | N91: =9-M91-L91 -> 0 | O91: =SUM(E91-SUM(L91:N91)) -> 9 | P91: 0 | Q91: 0 | R91: 0 | S91: =SUM(F91-SUM(P91:R91)) -> 4 | T91: 0 | U91: 0 | W91: =SUM(H91:K91) -> 0 | X91: =SUM(I91:L91) -> 0 | Y91: =SUM(J91:M91) -> 9 | Z91: =SUM(K91:N91) -> 9 | AA91: =SUM(L91:O91) -> 18 | AB91: =SUM(M91:P91) -> 18 | AC91: =SUM(N91:Q91) -> 9 | AD91: =SUM(O91:R91) -> 9 | ... AG91: =SUM(R91:U91) -> 4 | AI91: =SUM(AG91/AC91)-1 -> -0.55555556
B92: Other Gains, Losses, and Adjustments (1) | C92: =977+11-3284-14461 -> -16757 | D92: 1546 | E92: =2421+482 -> 2903 | F92: 0 | H92: =-74+378 -> 304 | I92: =-307+771-H92 -> 160 | J92: =-240+1211-I92-H92 -> 507 | K92: =SUM(D92-SUM(H92:J92)) -> 575 | L92: =42+360 -> 402 | M92: =2421+482-L92 -> 2501 | N92: =0-M92-L92 -> -2903 | O92: =SUM(E92-SUM(L92:N92)) -> 2903 | P92: 0 | Q92: 0 | R92: 0 | S92: =SUM(F92-SUM(P92:R92)) -> 0 | T92: 0 | U92: 0
B94: Changes in Operating Assets and Liabilities | W94: =SUM(H94:K94) -> 0 | X94: =SUM(I94:L94) -> 0 | Y94: =SUM(J94:M94) -> 0 | Z94: =SUM(K94:N94) -> 0 | AA94: =SUM(L94:O94) -> 0 | AB94: =SUM(M94:P94) -> 0 | AC94: =SUM(N94:Q94) -> 0 | AD94: =SUM(O94:R94) -> 0 | ... AG94: =SUM(R94:U94) -> 0 | AI94: =SUM(AG94/AC94)-1 -> #DIV/0!
B95: Accounts Receivable | C95: -63 | D95: 145 | E95: 31 | F95: 0 | H95: -57 | I95: =-1125-H95 -> -1068 | J95: =145-I95-H95 -> 1270 | K95: =SUM(D95-SUM(H95:J95)) -> 0 | L95: 31 | M95: =31-L95 -> 0 | N95: =31-M95-L95 -> 0 | O95: =SUM(E95-SUM(L95:N95)) -> 0 | P95: 0 | Q95: =0-P95 -> 0 | R95: =0-Q95-P95 -> 0 | S95: =SUM(F95-SUM(P95:R95)) -> 0 | T95: -308 | U95: =-214-T95 -> 94 | W95: =SUM(H95:K95) -> 145 | X95: =SUM(I95:L95) -> 233 | Y95: =SUM(J95:M95) -> 1301 | Z95: =SUM(K95:N95) -> 31 | AA95: =SUM(L95:O95) -> 31 | AB95: =SUM(M95:P95) -> 0 | AC95: =SUM(N95:Q95) -> 0 | AD95: =SUM(O95:R95) -> 0 | ... AG95: =SUM(R95:U95) -> -214 | AI95: =SUM(AG95/AC95)-1 -> #DIV/0!
B96: Inventory | C96: 0 | D96: 0 | E96: 0 | F96: 0 | H96: 0 | I96: 0 | J96: 0 | K96: =SUM(D96-SUM(H96:J96)) -> 0 | L96: 0 | M96: 0 | N96: 0 | O96: =SUM(E96-SUM(L96:N96)) -> 0 | P96: 0 | Q96: 0 | R96: 0 | S96: =SUM(F96-SUM(P96:R96)) -> 0 | T96: -8020 | U96: =-10968-T96 -> -2948 | W96: =SUM(H96:K96) -> 0 | X96: =SUM(I96:L96) -> 0 | Y96: =SUM(J96:M96) -> 0 | Z96: =SUM(K96:N96) -> 0 | AA96: =SUM(L96:O96) -> 0 | AB96: =SUM(M96:P96) -> 0 | AC96: =SUM(N96:Q96) -> 0 | AD96: =SUM(O96:R96) -> 0 | ... AG96: =SUM(R96:U96) -> -10968 | AI96: =SUM(AG96/AC96)-1 -> #DIV/0!
B97: Prepaid expenses and other current assets | C97: -2174 | D97: 1364 | E97: -388 | F97: 88 | H97: 822 | I97: =968-H97 -> 146 | J97: =812-I97-H97 -> -156 | K97: =SUM(D97-SUM(H97:J97)) -> 552 | L97: 120 | M97: =-3660-L97 -> -3780 | N97: =-423-M97-L97 -> 3237 | O97: =SUM(E97-SUM(L97:N97)) -> 35 | P97: 409 | Q97: =283-P97 -> -126 | R97: =396-Q97-P97 -> 113 | S97: =SUM(F97-SUM(P97:R97)) -> -308 | T97: 392 | U97: =505-T97 -> 113 | W97: =SUM(H97:K97) -> 1364 | X97: =SUM(I97:L97) -> 662 | Y97: =SUM(J97:M97) -> -3264 | Z97: =SUM(K97:N97) -> 129 | AA97: =SUM(L97:O97) -> -388 | AB97: =SUM(M97:P97) -> -99 | AC97: =SUM(N97:Q97) -> 3555 | AD97: =SUM(O97:R97) -> 431 | ... AG97: =SUM(R97:U97) -> 310 | AI97: =SUM(AG97/AC97)-1 -> -0.91279887
B98: Accounts payable | C98: -197 | D98: -509 | E98: 4811 | F98: -1962 | H98: 934 | I98: =374-H98 -> -560 | J98: =984-I98-H98 -> 610 | K98: =SUM(D98-SUM(H98:J98)) -> -1493 | L98: 299 | M98: =766-L98 -> 467 | N98: =1292-M98-L98 -> 526 | O98: =SUM(E98-SUM(L98:N98)) -> 3519 | P98: -2949 | Q98: =-638-P98 -> 2311 | R98: =475-Q98-P98 -> 1113 | S98: =SUM(F98-SUM(P98:R98)) -> -2437 | T98: 653 | U98: =2147-T98 -> 1494 | W98: =SUM(H98:K98) -> -509 | X98: =SUM(I98:L98) -> -1144 | Y98: =SUM(J98:M98) -> -117 | Z98: =SUM(K98:N98) -> -201 | AA98: =SUM(L98:O98) -> 4811 | AB98: =SUM(M98:P98) -> 1563 | AC98: =SUM(N98:Q98) -> 3407 | AD98: =SUM(O98:R98) -> 3994 | ... AG98: =SUM(R98:U98) -> 823 | AI98: =SUM(AG98/AC98)-1 -> -0.75843851
B99: Other Liabilities (2) | C99: =2035-42-116 -> 1877 | D99: =247-45-173 -> 29 | E99: =2167-50 -> 2117 | F99: =2238-53 -> 2185 | H99: =-1297-11 -> -1308 | I99: =-571-22-H99 -> 715 | J99: =1202-34-I99-H99 -> 1761 | K99: =SUM(D99-SUM(H99:J99)) -> -1139 | L99: =-597-12 -> -609 | M99: =-724-24-L99 -> -139 | N99: =2577-37-M99-L99 -> 3288 | O99: =SUM(E99-SUM(L99:N99)) -> -423 | P99: =-2107-13 -> -2120 | Q99: =-221-26-P99 -> 1873 | R99: =1980-39-Q99-P99 -> 2188 | S99: =SUM(F99-SUM(P99:R99)) -> 244 | T99: =-2267-14 -> -2281 | U99: =-2403-29-T99 -> -151 | AC99: =SUM(N99:Q99) -> 2618 | AD99: =SUM(O99:R99) -> 1518 | AE99: =SUM(P99:S99) -> 2185 | AF99: =SUM(Q99:T99) -> 2024 | AG99: =SUM(R99:U99) -> 0 | AI99: =SUM(AG99/AC99)-1 -> -1
B100: Net Cash Used in Operating Activities | C100: =SUM(C81:C99) -> -81190 | D100: =SUM(D81:D99) -> -71129 | E100: =SUM(E81:E99) -> -73305 | F100: =SUM(F81:F99) -> -98122 | H100: =SUM(H81:H99) -> -18797 | I100: =SUM(I81:I99) -> -16569 | J100: =SUM(J81:J99) -> -16804 | K100: =SUM(K81:K99) -> -18548 | L100: =SUM(L81:L99) -> -18641 | M100: =SUM(M81:M99) -> -22603 | N100: =SUM(N81:N99) -> -15910 | O100: =SUM(O81:O99) -> -16151 | ... U100: =SUM(U81:U99) -> -26413 | W100: =SUM(W81:W99) -> -72293 | X100: =SUM(X81:X99) -> -72934 | Y100: =SUM(Y81:Y99) -> -80455 | Z100: =SUM(Z81:Z99) -> -77678 | AA100: =SUM(AA81:AA99) -> -78325 | AB100: =SUM(AB81:AB99) -> -85118 | AC100: =SUM(AC81:AC99) -> -80699 | AD100: =SUM(AD81:AD99) -> -90599 | ... AG100: =SUM(AG81:AG99) -> -104498 | AI100: =SUM(AG100/AC100)-1 -> 0.29491072
B102: Cash flows from Investing Activities
B103: Purchase of property and equipment | C103: -220 | D103: -1048 | E103: -2280 | F103: -1572 | H103: -22 | I103: =-156-H103 -> -134 | J103: =-367-I103-H103 -> -211 | K103: =SUM(D103-SUM(H103:J103)) -> -681 | L103: -1152 | M103: =-1637-L103 -> -485 | N103: =-2130-M103-L103 -> -493 | O103: =SUM(E103-SUM(L103:N103)) -> -150 | P103: -391 | Q103: =-575-P103 -> -184 | R103: =-1509-Q103-P103 -> -934 | S103: =SUM(F103-SUM(P103:R103)) -> -63 | T103: -228 | U103: =-796-T103 -> -568 | W103: =SUM(H103:K103) -> -1048 | X103: =SUM(I103:L103) -> -2178 | Y103: =SUM(J103:M103) -> -2529 | Z103: =SUM(K103:N103) -> -2811 | AA103: =SUM(L103:O103) -> -2280 | AB103: =SUM(M103:P103) -> -1519 | AC103: =SUM(N103:Q103) -> -1218 | AD103: =SUM(O103:R103) -> -1659 | ... AG103: =SUM(R103:U103) -> -1793 | AI103: =SUM(AG103/AC103)-1 -> 0.47208539
B104: Proceeds (Purchase) of short-term investments (CDs) | C104: -8000 | D104: =16000-10107 -> 5893 | E104: 2107 | F104: 0 | H104: 0 | I104: =8000-8000-H104 -> 0 | J104: =8000-8000-I104-H104 -> 0 | K104: =SUM(D104-SUM(H104:J104)) -> 5893 | L104: 0 | M104: =2107-L104 -> 2107 | N104: =2107-M104-L104 -> 0 | O104: =SUM(E104-SUM(L104:N104)) -> 0 | P104: 0 | Q104: 0 | R104: 0 | S104: =SUM(F104-SUM(P104:R104)) -> 0 | T104: 0 | U104: 0 | W104: =SUM(H104:K104) -> 5893 | X104: =SUM(I104:L104) -> 5893 | Y104: =SUM(J104:M104) -> 8000 | Z104: =SUM(K104:N104) -> 8000 | AA104: =SUM(L104:O104) -> 2107 | AB104: =SUM(M104:P104) -> 2107 | AC104: =SUM(N104:Q104) -> 0 | AD104: =SUM(O104:R104) -> 0 | ... AG104: =SUM(R104:U104) -> 0 | AI104: =SUM(AG104/AC104)-1 -> #DIV/0!
B105: Net Cash Used in Investing Activities | C105: =SUM(C103:C104) -> -8220 | D105: =SUM(D103:D104) -> 4845 | E105: =SUM(E103:E104) -> -173 | F105: =SUM(F103:F104) -> -1572 | H105: =SUM(H103:H104) -> -22 | I105: =SUM(I103:I104) -> -134 | J105: =SUM(J103:J104) -> -211 | K105: =SUM(K103:K104) -> 5212 | L105: =SUM(L103:L104) -> -1152 | M105: =SUM(M103:M104) -> 1622 | N105: =SUM(N103:N104) -> -493 | O105: =SUM(O103:O104) -> -150 | ... U105: =SUM(U103:U104) -> -568 | W105: =SUM(W104:W104) -> 5893 | X105: =SUM(X104:X104) -> 5893 | Y105: =SUM(Y104:Y104) -> 8000 | Z105: =SUM(Z104:Z104) -> 8000 | AA105: =SUM(AA104:AA104) -> 2107 | AB105: =SUM(AB104:AB104) -> 2107 | AC105: =SUM(AC103:AC104) -> -1218 | AD105: =SUM(AD103:AD104) -> -1659 | AE105: =SUM(AE103:AE104) -> -1572 | AF105: =SUM(AF103:AF104) -> -1409 | AG105: =SUM(AG103:AG104) -> -1793 | AI105: =SUM(AG105/AC105)-1 -> 0.47208539
A107: X | B107: Cash flows from Financing Activities
B108: Net Equity Issuances / (Share Repurchases) (3) | C108: 598 | D108: 535 | E108: 566 | F108: =43396+43126+6809-350+2530+1511 -> 97022 | H108: 1 | I108: =12-H108 -> 11 | J108: =229-I108-H108 -> 217 | K108: =SUM(D108-SUM(H108:J108)) -> 306 | L108: 119 | M108: =214-L108 -> 95 | N108: =313-M108-L108 -> 99 | O108: =SUM(E108-SUM(L108:N108)) -> 253 | P108: =43396+2 -> 43398 | Q108: =43396-350+789-P108 -> 437 | R108: =43396-350+1013+1284-Q108-P108 -> 1508 | S108: =SUM(F108-SUM(P108:R108)) -> 51679 | T108: =47000+370+56 -> 47426 | U108: =47000+3603-340+56 -T108 -> 2893 | AC108: =SUM(N108:Q108) -> 44187 | AD108: =SUM(O108:R108) -> 45596 | AE108: =SUM(P108:S108) -> 97022 | AF108: =SUM(Q108:T108) -> 101050 | AG108: =SUM(R108:U108) -> 103506 | AI108: =SUM(AG108/AC108)-1 -> 1.3424537
B109: Net Issuance / (Repayment) of Debt (4) | C109: =-1729+29659 -> 27930 | D109: -1981 | E109: =-2256-31500-310 -> -34066 | F109: -2579 | H109: -462 | I109: =-957-H109 -> -495 | J109: =-1463-I109-H109 -> -506 | K109: =SUM(D109-SUM(H109:J109)) -> -518 | L109: -528 | M109: =-1091-31500-310-L109 -> -32373 | N109: =-1668-31500-310-M109-L109 -> -577 | O109: =SUM(E109-SUM(L109:N109)) -> -588 | P109: -603 | Q109: =-1247-P109 -> -644 | R109: =-1906-Q109-P109 -> -659 | S109: =SUM(F109-SUM(P109:R109)) -> -673 | T109: -687 | U109: =-1414-T109 -> -727 | AC109: =SUM(N109:Q109) -> -2412 | AD109: =SUM(O109:R109) -> -2494 | AE109: =SUM(P109:S109) -> -2579 | AF109: =SUM(Q109:T109) -> -2663 | AG109: =SUM(R109:U109) -> -2746 | AI109: =SUM(AG109/AC109)-1 -> 0.1384743
B110: Net Divestitures / (Acquisitions) (5) | C110: =242400-3945 -> 238455 | D110: 0 | E110: 0 | F110: 0 | H110: 0 | I110: 0 | J110: 0 | K110: =SUM(D110-SUM(H110:J110)) -> 0 | L110: 0 | M110: 0 | N110: 0 | O110: =SUM(E110-SUM(L110:N110)) -> 0 | P110: 0 | Q110: 0 | R110: 0 | S110: =SUM(F110-SUM(P110:R110)) -> 0 | T110: 0 | U110: 0 | AC110: =SUM(N110:Q110) -> 0 | AD110: =SUM(O110:R110) -> 0 | AE110: =SUM(P110:S110) -> 0 | AF110: =SUM(Q110:T110) -> 0 | AG110: =SUM(R110:U110) -> 0 | AI110: =SUM(AG110/AC110)-1 -> #DIV/0!
B111: Proceeds / (Payments) with revenue interest purchase agreement (6) | C111: 0 | D111: 0 | E111: =39377-1450 -> 37927 | F111: =20000-500 -> 19500 | H111: 0 | I111: 0 | J111: 0 | K111: =SUM(D111-SUM(H111:J111)) -> 0 | L111: 0 | M111: =39377-1164-L111 -> 38213 | N111: =39377-1450-M111-L111 -> -286 | O111: =SUM(E111-SUM(L111:N111)) -> 0 | P111: 20000 | Q111: =20000-500-P111 -> -500 | R111: =20000-500-Q111-P111 -> 0 | S111: =SUM(F111-SUM(P111:R111)) -> 0 | T111: 0 | U111: 0 | W111: =SUM(H111:K111) -> 0 | X111: =SUM(I111:L111) -> 0 | Y111: =SUM(J111:M111) -> 38213 | Z111: =SUM(K111:N111) -> 37927 | AA111: =SUM(L111:O111) -> 37927 | AB111: =SUM(M111:P111) -> 57927 | AC111: =SUM(N111:Q111) -> 19214 | AD111: =SUM(O111:R111) -> 19500 | ... AG111: =SUM(R111:U111) -> 0 | AI111: =SUM(AG111/AC111)-1 -> -1
B112: Proceeds from JDRF Agreement (7) | C112: 0 | D112: 0 | E112: 80 | F112: 240 | H112: 0 | I112: 0 | J112: 0 | K112: =SUM(D112-SUM(H112:J112)) -> 0 | L112: 0 | M112: =80-L112 -> 80 | N112: =80-M112-L112 -> 0 | O112: =SUM(E112-SUM(L112:N112)) -> 0 | P112: 0 | Q112: =240-P112 -> 240 | R112: =240-Q112-P1223 -> 0 | S112: =SUM(F112-SUM(P112:R112)) -> 0 | T112: 0 | U112: 0 | W112: =SUM(H112:K112) -> 0 | X112: =SUM(I112:L112) -> 0 | Y112: =SUM(J112:M112) -> 80 | Z112: =SUM(K112:N112) -> 80 | AA112: =SUM(L112:O112) -> 80 | AB112: =SUM(M112:P112) -> 80 | AC112: =SUM(N112:Q112) -> 240 | AD112: =SUM(O112:R112) -> 240 | ... AG112: =SUM(R112:U112) -> 0 | AI112: =SUM(AG112/AC112)-1 -> -1
B113: Net Cash Provided by Financing Activities | C113: =SUM(C108:C112) -> 266983 | D113: =SUM(D108:D112) -> -1446 | E113: =SUM(E108:E112) -> 4507 | F113: =SUM(F108:F112) -> 114183 | H113: =SUM(H108:H112) -> -461 | I113: =SUM(I108:I112) -> -484 | J113: =SUM(J108:J112) -> -289 | K113: =SUM(K108:K112) -> -212 | L113: =SUM(L108:L112) -> -409 | M113: =SUM(M108:M112) -> 6015 | N113: =SUM(N108:N112) -> -764 | O113: =SUM(O108:O112) -> -335 | ... U113: =SUM(U108:U112) -> 2166 | W113: =SUM(W109:W112) -> 0 | X113: =SUM(X109:X112) -> 0 | Y113: =SUM(Y109:Y112) -> 38293 | Z113: =SUM(Z109:Z112) -> 38007 | AA113: =SUM(AA109:AA112) -> 38007 | AB113: =SUM(AB109:AB112) -> 58007 | AC113: =SUM(AC108:AC112) -> 61229 | AD113: =SUM(AD108:AD112) -> 62842 | AE113: =SUM(AE108:AE112) -> 114183 | AF113: =SUM(AF108:AF112) -> 98127 | AG113: =SUM(AG108:AG112) -> 100760 | AI113: =SUM(AG113/AC113)-1 -> 0.64562544
B115: Net Change in Cash | C115: =+C113+C105+C100 -> 177573 | D115: =+D113+D105+D100 -> -67730 | E115: =+E113+E105+E100 -> -68971 | F115: =+F113+F105+F100 -> 14489 | H115: =+H113+H105+H100 -> -19280 | I115: =+I113+I105+I100 -> -17187 | J115: =+J113+J105+J100 -> -17304 | K115: =+K113+K105+K100 -> -13548 | L115: =+L113+L105+L100 -> -20202 | M115: =+M113+M105+M100 -> -14966 | N115: =+N113+N105+N100 -> -17167 | O115: =+O113+O105+O100 -> -16636 | ... U115: =+U113+U105+U100 -> -24815 | W115: =SUM(H115:K115) -> -67319 | X115: =SUM(I115:L115) -> -68241 | Y115: =SUM(J115:M115) -> -66020 | Z115: =SUM(K115:N115) -> -65883 | AA115: =SUM(L115:O115) -> -68971 | AB115: =SUM(M115:P115) -> -13712 | AC115: =SUM(N115:Q115) -> -20688 | AD115: =SUM(O115:R115) -> -26513 | ... AG115: =SUM(R115:U115) -> -5531
B116: Cash, cash equivalents and restricted cash at the beginning of the period | C116: 39929 | D116: 217502 | E116: 149772 | F116: 80801 | H116: 217502 | I116: 217502 | J116: 217502 | K116: =D116 -> 217502 | L116: 149772 | M116: 149772 | N116: 149772 | O116: =E116 -> 149772 | P116: 80801 | Q116: 80801 | R116: 80801 | S116: =F116 -> 80801 | T116: 95290 | U116: 95290 | W116: =K116 -> 217502 | X116: =L116 -> 149772 | Y116: =M116 -> 149772 | Z116: =N116 -> 149772 | AA116: =O116 -> 149772 | AB116: =P116 -> 80801 | AC116: =Q116 -> 80801 | AD116: =R116 -> 80801 | ... AG116: =U116 -> 95290
B117: Cash, cash equivalents and restricted cash at the end of the period | C117: 217502 | D117: 149772 | E117: 80801 | F117: 95290 | H117: 198222 | I117: 181035 | J117: 163731 | K117: =D117 -> 149772 | L117: 129570 | M117: 114604 | N117: 100340 | O117: =E117 -> 80801 | P117: 115858 | Q117: 93916 | R117: 70924 | S117: =F117 -> 95290 | T117: 113200 | U117: 88385 | W117: =K117 -> 149772 | X117: =L117 -> 129570 | Y117: =M117 -> 114604 | Z117: =N117 -> 100340 | AA117: =O117 -> 80801 | AB117: =P117 -> 115858 | AC117: =Q117 -> 93916 | AD117: =R117 -> 70924 | ... AG117: =U117 -> 88385
B119: Supplemental disclosure:
B120: Cash paid for interest on SVB loan | C120: 1123 | D120: 2668 | E120: 1613 | F120: 0 | H120: 563 | I120: =1165-H120 -> 602 | J120: =1867-I120-H120 -> 702 | K120: =SUM(H120:J120)-D120 -> -801 | L120: 881 | M120: =1613-L120 -> 732 | N120: =1613-M120-L120 -> 0 | O120: =SUM(L120:N120)-E120 -> 0 | P120: 0 | Q120: 0 | R120: 0 | S120: =SUM(F120-SUM(P120:R120)) -> 0 | T120: 0 | U120: 0 | W120: =SUM(H120:K120) -> 1066 | X120: =SUM(I120:L120) -> 1384 | Y120: =SUM(J120:M120) -> 1514 | Z120: =SUM(K120:N120) -> 812 | AA120: =SUM(L120:O120) -> 1613 | AB120: =SUM(M120:P120) -> 732 | AC120: =SUM(N120:Q120) -> 0 | AD120: =SUM(O120:R120) -> 0 | ... AG120: =SUM(R120:U120) -> 0
A122: X | B122: 1) "Other Gains, Losses, and Adjustments Consist of: Change in fair value of common stock warrant liabilities, Loss on extinguishment of debt. Amortization of SVB debt discount, Accrued interest on PPP loan obligation, Gain on PPP loan forgiveness, and Payment of liabilities assumed in Merger.
B123: 2) "Other Liabilities consists of: Accrued expenses, Operating lease obligation, and Deferred payroll taxes.
B124: 3) "Net Equity Issuances / (Share Repurchases)" consists of: Proceeds from issuance of stock in public offering, net of underwriting fees, Proceeds from issuance of stock and warrants in registered direct offerings, net of placement agent fees, Proceeds from issuance of stock under ATM Facility, net of issuance costs, Payments of costs related to public offering, Proceeds from sale of common stock under Common Stock Purchase Agreement, and Proceeds from the exercise of stock options.
B125: 4) "Net Issuance / (Repayment) of Debt" consists of: Principal payments on SVB loan, Payments for debt prepayment and extinguishment costs, and Payments of finance lease principal.
...

Sheet FCF Analysis
B2: Humacyte Inc (NASDAQ: HUMA) | C2: FYE | D2: FYE | H2: Quarterly | P2: Quarterly | Q2: Quarterly | W2: LTM | AA2: LTM | AC2: LTM | AI2: Variance
B3: FCF Analysis | C3: 2021 | D3: 2022 | E3: 2023 | F3: 2024 | H3: 1Q22 | I3: 2Q22 | J3: 3Q22 | K3: 4Q22 | L3: 1Q23 | M3: 2Q23 | N3: 3Q23 | O3: 4Q23 | P3: 1Q24 | Q3: 2Q24 | R3: 3Q24 | S3: 4Q24 | T3: 1Q25 | U3: 2Q25 | W3: =K3 -> 4Q22 | X3: =L3 -> 1Q23 | Y3: =M3 -> 2Q23 | Z3: =N3 -> 3Q23 | AA3: =O3 -> 4Q23 | AB3: =P3 -> 1Q24 | AC3: =Q3 -> 2Q24 | AD3: =R3 -> 3Q24 | ... AG3: =U3 -> 2Q25
B4: ($ In Thousands) | C4: 44561 | D4: 44926 | E4: 45291 | F4: 45657 | H4: 44651 | I4: 44742 | J4: 44834 | K4: 44926 | L4: 45016 | M4: 45107 | N4: 45199 | O4: 45291 | P4: 45382 | Q4: 45473 | R4: 45565 | S4: 45657 | T4: 45747 | U4: 45838 | W4: =K4 -> 44926 | X4: =L4 -> 45016 | Y4: =M4 -> 45107 | Z4: =N4 -> 45199 | AA4: =O4 -> 45291 | AB4: =P4 -> 45382 | AC4: =Q4 -> 45473 | AD4: =R4 -> 45565 | ... AG4: =U4 -> 45838
B6: Product Revenue | C6: ='Base Financials'!C8 -> 0 | D6: ='Base Financials'!D8 -> 0 | E6: ='Base Financials'!E8 -> 0 | F6: ='Base Financials'!F8 -> 0 | H6: ='Base Financials'!H8 -> 0 | I6: ='Base Financials'!I8 -> 0 | J6: ='Base Financials'!J8 -> 0 | K6: ='Base Financials'!K8 -> 0 | L6: ='Base Financials'!L8 -> 0 | M6: ='Base Financials'!M8 -> 0 | N6: ='Base Financials'!N8 -> 0 | O6: ='Base Financials'!O8 -> 0 | ... U6: ='Base Financials'!U8 -> 100 | W6: =SUM(H6:K6) -> 0 | X6: =SUM(I6:L6) -> 0 | Y6: =SUM(J6:M6) -> 0 | Z6: =SUM(K6:N6) -> 0 | AA6: =SUM(L6:O6) -> 0 | AB6: =SUM(M6:P6) -> 0 | AC6: =SUM(N6:Q6) -> 0 | AD6: =SUM(O6:R6) -> 0 | ... AG6: =SUM(R6:U6) -> 247 | AI6: =SUM(AG6/AC6)-1 -> #DIV/0!
B7: Contract Revenue | C7: ='Base Financials'!C9 -> 0 | D7: ='Base Financials'!D9 -> 0 | E7: ='Base Financials'!E9 -> 0 | F7: ='Base Financials'!F9 -> 0 | H7: ='Base Financials'!H9 -> 0 | I7: ='Base Financials'!I9 -> 0 | J7: ='Base Financials'!J9 -> 0 | K7: ='Base Financials'!K9 -> 0 | L7: ='Base Financials'!L9 -> 0 | M7: ='Base Financials'!M9 -> 0 | N7: ='Base Financials'!N9 -> 0 | O7: ='Base Financials'!O9 -> 0 | ... U7: ='Base Financials'!U9 -> 201 | W7: =SUM(H7:K7) -> 0 | X7: =SUM(I7:L7) -> 0 | Y7: =SUM(J7:M7) -> 0 | Z7: =SUM(K7:N7) -> 0 | AA7: =SUM(L7:O7) -> 0 | AB7: =SUM(M7:P7) -> 0 | AC7: =SUM(N7:Q7) -> 0 | AD7: =SUM(O7:R7) -> 0 | ... AG7: =SUM(R7:U7) -> 571 | AI7: =SUM(AG7/AC7)-1 -> #DIV/0!
B8: Grant Revenue | C8: ='Base Financials'!C10 -> 1263 | D8: ='Base Financials'!D10 -> 1565 | E8: ='Base Financials'!E10 -> 0 | F8: ='Base Financials'!F10 -> 0 | H8: ='Base Financials'!H10 -> 233 | I8: ='Base Financials'!I10 -> 1301 | J8: ='Base Financials'!J10 -> 31 | K8: ='Base Financials'!K10 -> 0 | L8: ='Base Financials'!L10 -> 0 | M8: ='Base Financials'!M10 -> 0 | N8: ='Base Financials'!N10 -> 0 | O8: ='Base Financials'!O10 -> 0 | ... U8: ='Base Financials'!U10 -> 0 | W8: =SUM(H8:K8) -> 1565 | X8: =SUM(I8:L8) -> 1332 | Y8: =SUM(J8:M8) -> 31 | Z8: =SUM(K8:N8) -> 0 | AA8: =SUM(L8:O8) -> 0 | AB8: =SUM(M8:P8) -> 0 | AC8: =SUM(N8:Q8) -> 0 | AD8: =SUM(O8:R8) -> 0 | ... AG8: =SUM(R8:U8) -> 0 | AI8: =SUM(AG8/AC8)-1 -> #DIV/0!
B9: Total Revenue | C9: =SUM(C6:C8) -> 1263 | D9: =SUM(D6:D8) -> 1565 | E9: =SUM(E6:E8) -> 0 | F9: =SUM(F6:F8) -> 0 | H9: =SUM(H6:H8) -> 233 | I9: =SUM(I6:I8) -> 1301 | J9: =SUM(J6:J8) -> 31 | K9: =SUM(K6:K8) -> 0 | L9: =SUM(L6:L8) -> 0 | M9: =SUM(M6:M8) -> 0 | N9: =SUM(N6:N8) -> 0 | O9: =SUM(O6:O8) -> 0 | ... U9: =SUM(U6:U8) -> 301 | W9: =SUM(W6:W8) -> 1565 | X9: =SUM(X6:X8) -> 1332 | Y9: =SUM(Y6:Y8) -> 31 | Z9: =SUM(Z6:Z8) -> 0 | AA9: =SUM(AA6:AA8) -> 0 | AB9: =SUM(AB6:AB8) -> 0 | AC9: =SUM(AC6:AC8) -> 0 | AD9: =SUM(AD6:AD8) -> 0 | ... AG9: =SUM(AG6:AG8) -> 818 | AI9: =SUM(AG9/AC9)-1 -> #DIV/0!
B10: Y/Y Growth (%) | D10: =SUM(D9/C9)-1 -> 0.23911322 | E10: =SUM(E9/D9)-1 -> -1 | F10: =SUM(F9/E9)-1 -> #DIV/0! | L10: =SUM(L9/H9)-1 -> -1 | M10: =SUM(M9/I9)-1 -> -1 | N10: =SUM(N9/J9)-1 -> -1 | O10: =SUM(O9/K9)-1 -> #DIV/0! | P10: =SUM(P9/L9)-1 -> #DIV/0! | Q10: =SUM(Q9/M9)-1 -> #DIV/0! | R10: =SUM(R9/N9)-1 -> #DIV/0! | S10: =SUM(S9/O9)-1 -> #DIV/0! | ... U10: =SUM(U9/Q9)-1 -> #DIV/0! | AA10: =SUM(AA9/W9)-1 -> -1 | AB10: =SUM(AB9/X9)-1 -> -1 | AC10: =SUM(AC9/Y9)-1 -> -1 | AD10: =SUM(AD9/Z9)-1 -> #DIV/0! | AE10: =SUM(AE9/AA9)-1 -> #DIV/0! | AF10: =SUM(AF9/AB9)-1 -> #DIV/0! | AG10: =SUM(AG9/AC9)-1 -> #DIV/0! | AI10: =SUM(AG10-AC10)*10000 -> #DIV/0!
B11: Q/Q Growth (%) | C11: N/A | D11: N/A | E11: N/A | F11: N/A | I11: =SUM(I9/H9)-1 -> 4.583691 | J11: =SUM(J9/I9)-1 -> -0.97617218 | K11: =SUM(K9/J9)-1 -> -1 | L11: =SUM(L9/K9)-1 -> #DIV/0! | M11: =SUM(M9/L9)-1 -> #DIV/0! | N11: =SUM(N9/M9)-1 -> #DIV/0! | O11: =SUM(O9/N9)-1 -> #DIV/0! | P11: =SUM(P9/O9)-1 -> #DIV/0! | ... U11: =SUM(U9/T9)-1 -> -0.41779497 | W11: N/A | X11: N/A | Y11: N/A | Z11: N/A | AA11: N/A | AB11: N/A | AC11: N/A | AD11: N/A | AE11: N/A | AF11: N/A | AG11: N/A
B13: (-) Cost of Goods Sold | C13: ='Base Financials'!C13 -> 0 | D13: ='Base Financials'!D13 -> 0 | E13: ='Base Financials'!E13 -> 0 | F13: ='Base Financials'!F13 -> 0 | H13: ='Base Financials'!H13 -> 0 | I13: ='Base Financials'!I13 -> 0 | J13: ='Base Financials'!J13 -> 0 | K13: ='Base Financials'!K13 -> 0 | L13: ='Base Financials'!L13 -> 0 | M13: ='Base Financials'!M13 -> 0 | N13: ='Base Financials'!N13 -> 0 | O13: ='Base Financials'!O13 -> 0 | ... U13: ='Base Financials'!U13 -> -213 | W13: =SUM(H13:K13) -> 0 | X13: =SUM(I13:L13) -> 0 | Y13: =SUM(J13:M13) -> 0 | Z13: =SUM(K13:N13) -> 0 | AA13: =SUM(L13:O13) -> 0 | AB13: =SUM(M13:P13) -> 0 | AC13: =SUM(N13:Q13) -> 0 | AD13: =SUM(O13:R13) -> 0 | ... AG13: =SUM(R13:U13) -> -360 | AI13: =SUM(AG13/AC13)-1 -> #DIV/0!
B14: Gross Profit | C14: =+C9+C13 -> 1263 | D14: =+D9+D13 -> 1565 | E14: =+E9+E13 -> 0 | F14: =+F9+F13 -> 0 | H14: =+H9+H13 -> 233 | I14: =+I9+I13 -> 1301 | J14: =+J9+J13 -> 31 | K14: =+K9+K13 -> 0 | L14: =+L9+L13 -> 0 | M14: =+M9+M13 -> 0 | N14: =+N9+N13 -> 0 | O14: =+O9+O13 -> 0 | ... U14: =+U9+U13 -> 88 | W14: =+W9+W13 -> 1565 | X14: =+X9+X13 -> 1332 | Y14: =+Y9+Y13 -> 31 | Z14: =+Z9+Z13 -> 0 | AA14: =+AA9+AA13 -> 0 | AB14: =+AB9+AB13 -> 0 | AC14: =+AC9+AC13 -> 0 | AD14: =+AD9+AD13 -> 0 | ... AG14: =+AG9+AG13 -> 458 | AI14: =SUM(AG14/AC14)-1 -> #DIV/0!
B15: Gross Margin (%) | C15: =C14/C9 -> 1 | D15: =D14/D9 -> 1 | E15: =E14/E9 -> #DIV/0! | F15: =F14/F9 -> #DIV/0! | H15: =H14/H9 -> 1 | I15: =I14/I9 -> 1 | J15: =J14/J9 -> 1 | K15: =K14/K9 -> #DIV/0! | L15: =L14/L9 -> #DIV/0! | M15: =M14/M9 -> #DIV/0! | N15: =N14/N9 -> #DIV/0! | O15: =O14/O9 -> #DIV/0! | ... U15: =U14/U9 -> 0.2923588 | W15: =W14/W9 -> 1 | X15: =X14/X9 -> 1 | Y15: =Y14/Y9 -> 1 | Z15: =Z14/Z9 -> #DIV/0! | AA15: =AA14/AA9 -> #DIV/0! | AB15: =AB14/AB9 -> #DIV/0! | AC15: =AC14/AC9 -> #DIV/0! | AD15: =AD14/AD9 -> #DIV/0! | ... AG15: =AG14/AG9 -> 0.5599022 | AI15: =SUM(AG15-AC15)*10000 -> #DIV/0!
B17: (-) Research and Development (R&D) | C17: ='Base Financials'!C16 -> -61341 | D17: ='Base Financials'!D16 -> -63260 | E17: ='Base Financials'!E16 -> -76550 | F17: ='Base Financials'!F16 -> -88599 | H17: ='Base Financials'!H16 -> -16314 | I17: ='Base Financials'!I16 -> -14652 | J17: ='Base Financials'!J16 -> -17337 | K17: ='Base Financials'!K16 -> -14957 | L17: ='Base Financials'!L16 -> -17278 | M17: ='Base Financials'!M16 -> -20540 | N17: ='Base Financials'!N16 -> -18552 | O17: ='Base Financials'!O16 -> -20180 | ... U17: ='Base Financials'!U16 -> -22006 | W17: =SUM(H17:K17) -> -63260 | X17: =SUM(I17:L17) -> -64224 | Y17: =SUM(J17:M17) -> -70112 | Z17: =SUM(K17:N17) -> -71327 | AA17: =SUM(L17:O17) -> -76550 | AB17: =SUM(M17:P17) -> -80536 | AC17: =SUM(N17:Q17) -> -83749 | AD17: =SUM(O17:R17) -> -88123 | ... AG17: =SUM(R17:U17) -> -81006 | AI17: =SUM(AG17/AC17)-1 -> -0.03275263
B18: (-) General and Administrative (G&A) | C18: ='Base Financials'!C17 -> -21130 | D18: ='Base Financials'!D17 -> -22883 | E18: ='Base Financials'!E17 -> -23497 | F18: ='Base Financials'!F17 -> -25799 | H18: ='Base Financials'!H17 -> -5682 | I18: ='Base Financials'!I17 -> -5180 | J18: ='Base Financials'!J17 -> -6188 | K18: ='Base Financials'!K17 -> -5833 | L18: ='Base Financials'!L17 -> -5234 | M18: ='Base Financials'!M17 -> -6191 | N18: ='Base Financials'!N17 -> -6070 | O18: ='Base Financials'!O17 -> -6002 | ... U18: ='Base Financials'!U17 -> -7809 | W18: =SUM(H18:K18) -> -22883 | X18: =SUM(I18:L18) -> -22435 | Y18: =SUM(J18:M18) -> -23446 | Z18: =SUM(K18:N18) -> -23328 | AA18: =SUM(L18:O18) -> -23497 | AB18: =SUM(M18:P18) -> -23577 | AC18: =SUM(N18:Q18) -> -23132 | AD18: =SUM(O18:R18) -> -24369 | ... AG18: =SUM(R18:U18) -> -30684 | AI18: =SUM(AG18/AC18)-1 -> 0.32647415
B19: Earning before Interest & Taxes (EBIT) | C19: =SUM(C14+SUM(C17:C18)) -> -81208 | D19: =SUM(D14+SUM(D17:D18)) -> -84578 | E19: =SUM(E14+SUM(E17:E18)) -> -100047 | F19: =SUM(F14+SUM(F17:F18)) -> -114398 | H19: =SUM(H14+SUM(H17:H18)) -> -21763 | I19: =SUM(I14+SUM(I17:I18)) -> -18531 | J19: =SUM(J14+SUM(J17:J18)) -> -23494 | K19: =SUM(K14+SUM(K17:K18)) -> -20790 | L19: =SUM(L14+SUM(L17:L18)) -> -22512 | M19: =SUM(M14+SUM(M17:M18)) -> -26731 | N19: =SUM(N14+SUM(N17:N18)) -> -24622 | O19: =SUM(O14+SUM(O17:O18)) -> -26182 | ... U19: =SUM(U14+SUM(U17:U18)) -> -29727 | W19: =SUM(W14+SUM(W17:W18)) -> -84578 | X19: =SUM(X14+SUM(X17:X18)) -> -85327 | Y19: =SUM(Y14+SUM(Y17:Y18)) -> -93527 | Z19: =SUM(Z14+SUM(Z17:Z18)) -> -94655 | AA19: =SUM(AA14+SUM(AA17:AA18)) -> -100047 | AB19: =SUM(AB14+SUM(AB17:AB18)) -> -104113 | AC19: =SUM(AC14+SUM(AC17:AC18)) -> -106881 | AD19: =SUM(AD14+SUM(AD17:AD18)) -> -112492 | ... AG19: =SUM(AG14+SUM(AG17:AG18)) -> -111232 | AI19: =SUM(AG19/AC19)-1 -> 0.040708826
B20: Operating Margin (%) | C20: =C19/C9 -> -64.297704 | D20: =D19/D9 -> -54.04345 | E20: =E19/E9 -> #DIV/0! | F20: =F19/F9 -> #DIV/0! | H20: =H19/H9 -> -93.403433 | I20: =I19/I9 -> -14.243659 | J20: =J19/J9 -> -757.87097 | K20: =K19/K9 -> #DIV/0! | L20: =L19/L9 -> #DIV/0! | M20: =M19/M9 -> #DIV/0! | N20: =N19/N9 -> #DIV/0! | O20: =O19/O9 -> #DIV/0! | ... U20: =U19/U9 -> -98.760797 | W20: =W19/W9 -> -54.04345 | X20: =X19/X9 -> -64.059309 | Y20: =Y19/Y9 -> -3017 | Z20: =Z19/Z9 -> #DIV/0! | AA20: =AA19/AA9 -> #DIV/0! | AB20: =AB19/AB9 -> #DIV/0! | AC20: =AC19/AC9 -> #DIV/0! | AD20: =AD19/AD9 -> #DIV/0! | ... AG20: =AG19/AG9 -> -135.98044 | AI20: =SUM(AG20-AC20)*10000 -> #DIV/0!
B22: (+) Depreciation and Amortization | C22: =SUM('Base Financials'!C84:C85) -> 8241 | D22: =SUM('Base Financials'!D84:D85) -> 8210 | E22: =SUM('Base Financials'!E84:E85) -> 7719 | F22: =SUM('Base Financials'!F84:F85) -> 7190 | H22: =SUM('Base Financials'!H84:H85) -> 2040 | I22: =SUM('Base Financials'!I84:I85) -> 2021 | J22: =SUM('Base Financials'!J84:J85) -> 2035 | K22: =SUM('Base Financials'!K84:K85) -> 2114 | L22: =SUM('Base Financials'!L84:L85) -> 2073 | M22: =SUM('Base Financials'!M84:M85) -> 1983 | N22: =SUM('Base Financials'!N84:N85) -> 1830 | O22: =SUM('Base Financials'!O84:O85) -> 1833 | ... U22: =SUM('Base Financials'!U84:U85) -> 1860 | W22: =SUM(H22:K22) -> 8210 | X22: =SUM(I22:L22) -> 8243 | Y22: =SUM(J22:M22) -> 8205 | Z22: =SUM(K22:N22) -> 8000 | AA22: =SUM(L22:O22) -> 7719 | AB22: =SUM(M22:P22) -> 7437 | AC22: =SUM(N22:Q22) -> 7233 | AD22: =SUM(O22:R22) -> 7215 | ... AG22: =SUM(R22:U22) -> 7312 | AI22: =SUM(AG22/AC22)-1 -> 0.010922162
B23: EBITDA | C23: =SUM(C19+C22) -> -72967 | D23: =SUM(D19+D22) -> -76368 | E23: =SUM(E19+E22) -> -92328 | F23: =SUM(F19+F22) -> -107208 | H23: =SUM(H19+H22) -> -19723 | I23: =SUM(I19+I22) -> -16510 | J23: =SUM(J19+J22) -> -21459 | K23: =SUM(K19+K22) -> -18676 | L23: =SUM(L19+L22) -> -20439 | M23: =SUM(M19+M22) -> -24748 | N23: =SUM(N19+N22) -> -22792 | O23: =SUM(O19+O22) -> -24349 | ... U23: =SUM(U19+U22) -> -27867 | W23: =SUM(W19+W22) -> -76368 | X23: =SUM(X19+X22) -> -77084 | Y23: =SUM(Y19+Y22) -> -85322 | Z23: =SUM(Z19+Z22) -> -86655 | AA23: =SUM(AA19+AA22) -> -92328 | AB23: =SUM(AB19+AB22) -> -96676 | AC23: =SUM(AC19+AC22) -> -99648 | AD23: =SUM(AD19+AD22) -> -105277 | ... AG23: =SUM(AG19+AG22) -> -103920 | AI23: =SUM(AG23/AC23)-1 -> 0.042870906
B24: EBITDA Margin (%) | C24: =C23/C9 -> -57.772763 | D24: =D23/D9 -> -48.797444 | E24: =E23/E9 -> #DIV/0! | F24: =F23/F9 -> #DIV/0! | H24: =H23/H9 -> -84.648069 | I24: =I23/I9 -> -12.690238 | J24: =J23/J9 -> -692.22581 | K24: =K23/K9 -> #DIV/0! | L24: =L23/L9 -> #DIV/0! | M24: =M23/M9 -> #DIV/0! | N24: =N23/N9 -> #DIV/0! | O24: =O23/O9 -> #DIV/0! | ... U24: =U23/U9 -> -92.581395 | W24: =W23/W9 -> -48.797444 | X24: =X23/X9 -> -57.870871 | Y24: =Y23/Y9 -> -2752.3226 | Z24: =Z23/Z9 -> #DIV/0! | AA24: =AA23/AA9 -> #DIV/0! | AB24: =AB23/AB9 -> #DIV/0! | AC24: =AC23/AC9 -> #DIV/0! | AD24: =AD23/AD9 -> #DIV/0! | ... AG24: =AG23/AG9 -> -127.04156 | AI24: =SUM(AG24-AC24)*10000 -> #DIV/0!
B26: (+) Share-based Compensation (SBC) | C26: ='Base Financials'!C86 -> 10146 | D26: ='Base Financials'!D86 -> 6184 | E26: ='Base Financials'!E86 -> 6828 | F26: ='Base Financials'!F86 -> 6137 | H26: ='Base Financials'!H86 -> 1547 | I26: ='Base Financials'!I86 -> 1491 | J26: ='Base Financials'!J86 -> 1476 | K26: ='Base Financials'!K86 -> 1670 | L26: ='Base Financials'!L86 -> 1809 | M26: ='Base Financials'!M86 -> 1841 | N26: ='Base Financials'!N86 -> 1772 | O26: ='Base Financials'!O86 -> 1406 | ... U26: ='Base Financials'!U86 -> 2335 | W26: =SUM(H26:K26) -> 6184 | X26: =SUM(I26:L26) -> 6446 | Y26: =SUM(J26:M26) -> 6796 | Z26: =SUM(K26:N26) -> 7092 | AA26: =SUM(L26:O26) -> 6828 | AB26: =SUM(M26:P26) -> 6473 | AC26: =SUM(N26:Q26) -> 6069 | AD26: =SUM(O26:R26) -> 5849 | ... AG26: =SUM(R26:U26) -> 8068 | AI26: =SUM(AG26/AC26)-1 -> 0.32937881
B27: (+/-) Change in Fair Value of Contingent Earnout Liability | C27: ='Base Financials'!C87 -> -55772 | D27: ='Base Financials'!D87 -> -75767 | E27: ='Base Financials'!E87 -> 10023 | F27: ='Base Financials'!F87 -> 33045 | H27: ='Base Financials'!H87 -> -3258 | I27: ='Base Financials'!I87 -> -56353 | J27: ='Base Financials'!J87 -> 962 | K27: ='Base Financials'!K87 -> -17118 | L27: ='Base Financials'!L87 -> 14191 | M27: ='Base Financials'!M87 -> -3627 | N27: ='Base Financials'!N87 -> 1144 | O27: ='Base Financials'!O87 -> -1685 | ... U27: ='Base Financials'!U87 -> 5470 | W27: =SUM(H27:K27) -> -75767 | X27: =SUM(I27:L27) -> -58318 | Y27: =SUM(J27:M27) -> -5592 | Z27: =SUM(K27:N27) -> -5410 | AA27: =SUM(L27:O27) -> 10023 | AB27: =SUM(M27:P27) -> 425 | AC27: =SUM(N27:Q27) -> 29623 | AD27: =SUM(O27:R27) -> 36968 | ... AG27: =SUM(R27:U27) -> -41380 | AI27: =SUM(AG27/AC27)-1 -> -2.3968876
B28: (+/-) Change in Fair Value of Derivative Liabilities | C28: ='Base Financials'!C88 -> -56 | D28: ='Base Financials'!D88 -> -417 | E28: ='Base Financials'!E88 -> 260 | F28: ='Base Financials'!F88 -> -3915 | H28: ='Base Financials'!H88 -> 0 | I28: ='Base Financials'!I88 -> 0 | J28: ='Base Financials'!J88 -> 0 | K28: ='Base Financials'!K88 -> 0 | L28: ='Base Financials'!L88 -> 0 | M28: ='Base Financials'!M88 -> 99 | N28: ='Base Financials'!N88 -> 135 | O28: ='Base Financials'!O88 -> 26 | ... U28: ='Base Financials'!U88 -> 748 | AC28: =SUM(N28:Q28) -> 489 | AD28: =SUM(O28:R28) -> -693 | AE28: =SUM(P28:S28) -> -3915 | AF28: =SUM(Q28:T28) -> -18785 | AG28: =SUM(R28:U28) -> -18425 | AI28: =SUM(AG28/AC28)-1 -> -38.678937
B29: Adj. EBITDA | C29: =+SUM(C23+SUM(C26:C28)) -> -118649 | D29: =+SUM(D23+SUM(D26:D28)) -> -146368 | E29: =+SUM(E23+SUM(E26:E28)) -> -75217 | F29: =+SUM(F23+SUM(F26:F28)) -> -71941 | H29: =+SUM(H23+SUM(H26:H28)) -> -21434 | I29: =+SUM(I23+SUM(I26:I28)) -> -71372 | J29: =+SUM(J23+SUM(J26:J28)) -> -19021 | K29: =+SUM(K23+SUM(K26:K28)) -> -34124 | L29: =+SUM(L23+SUM(L26:L28)) -> -4439 | M29: =+SUM(M23+SUM(M26:M28)) -> -26435 | N29: =+SUM(N23+SUM(N26:N28)) -> -19741 | O29: =+SUM(O23+SUM(O26:O28)) -> -24602 | ... U29: =+SUM(U23+SUM(U26:U28)) -> -19314 | W29: =+SUM(W23+SUM(W26:W27)) -> -145951 | X29: =+SUM(X23+SUM(X26:X27)) -> -128956 | Y29: =+SUM(Y23+SUM(Y26:Y27)) -> -84118 | Z29: =+SUM(Z23+SUM(Z26:Z27)) -> -84973 | AA29: =+SUM(AA23+SUM(AA26:AA27)) -> -75477 | AB29: =+SUM(AB23+SUM(AB26:AB27)) -> -89778 | AC29: =+SUM(AC23+SUM(AC26:AC28)) -> -63467 | AD29: =+SUM(AD23+SUM(AD26:AD28)) -> -63153 | AE29: =+SUM(AE23+SUM(AE26:AE28)) -> -71941 | AF29: =+SUM(AF23+SUM(AF26:AF28)) -> -136667 | AG29: =+SUM(AG23+SUM(AG26:AG28)) -> -155657 | AI29: =SUM(AG29/AC29)-1 -> 1.4525659
B30: Adj. EBITDA Margin (%) | C30: =C29/C9 -> -93.942201 | D30: =D29/D9 -> -93.525879 | E30: =E29/E9 -> #DIV/0! | F30: =F29/F9 -> #DIV/0! | H30: =H29/H9 -> -91.991416 | I30: =I29/I9 -> -54.859339 | J30: =J29/J9 -> -613.58065 | K30: =K29/K9 -> #DIV/0! | L30: =L29/L9 -> #DIV/0! | M30: =M29/M9 -> #DIV/0! | N30: =N29/N9 -> #DIV/0! | O30: =O29/O9 -> #DIV/0! | ... U30: =U29/U9 -> -64.166113 | W30: =W29/W9 -> -93.259425 | X30: =X29/X9 -> -96.813814 | Y30: =Y29/Y9 -> -2713.4839 | Z30: =Z29/Z9 -> #DIV/0! | AA30: =AA29/AA9 -> #DIV/0! | AB30: =AB29/AB9 -> #DIV/0! | AC30: =AC29/AC9 -> #DIV/0! | AD30: =AD29/AD9 -> #DIV/0! | ... AG30: =AG29/AG9 -> -190.28973 | AI30: =SUM(AG30-AC30)*10000 -> #DIV/0!
B32: (-) Capital Expenditures | C32: ='Base Financials'!C103 -> -220 | D32: ='Base Financials'!D103 -> -1048 | E32: ='Base Financials'!E103 -> -2280 | F32: ='Base Financials'!F103 -> -1572 | H32: ='Base Financials'!H103 -> -22 | I32: ='Base Financials'!I103 -> -134 | J32: ='Base Financials'!J103 -> -211 | K32: ='Base Financials'!K103 -> -681 | L32: ='Base Financials'!L103 -> -1152 | M32: ='Base Financials'!M103 -> -485 | N32: ='Base Financials'!N103 -> -493 | O32: ='Base Financials'!O103 -> -150 | ... U32: ='Base Financials'!U103 -> -568 | W32: =SUM(H32:K32) -> -1048 | X32: =SUM(I32:L32) -> -2178 | Y32: =SUM(J32:M32) -> -2529 | Z32: =SUM(K32:N32) -> -2811 | AA32: =SUM(L32:O32) -> -2280 | AB32: =SUM(M32:P32) -> -1519 | AC32: =SUM(N32:Q32) -> -1218 | AD32: =SUM(O32:R32) -> -1659 | ... AG32: =SUM(R32:U32) -> -1793 | AI32: =SUM(AG32/AC32)-1 -> 0.47208539
B33: (-) Cash Interest | C33: ='Base Financials'!C21 -> -4348 | D33: ='Base Financials'!D21 -> -6200 | E33: ='Base Financials'!E21 -> -6599 | F33: ='Base Financials'!F21 -> -9277 | H33: ='Base Financials'!H21 -> -1432 | I33: ='Base Financials'!I21 -> -1488 | J33: ='Base Financials'!J21 -> -1641 | K33: ='Base Financials'!K21 -> -1639 | L33: ='Base Financials'!L21 -> -1699 | M33: ='Base Financials'!M21 -> -1710 | N33: ='Base Financials'!N21 -> -1463 | O33: ='Base Financials'!O21 -> -1727 | ... U33: ='Base Financials'!U21 -> -2545 | W33: =SUM(H33:K33) -> -6200 | X33: =SUM(I33:L33) -> -6467 | Y33: =SUM(J33:M33) -> -6689 | Z33: =SUM(K33:N33) -> -6511 | AA33: =SUM(L33:O33) -> -6599 | AB33: =SUM(M33:P33) -> -6716 | AC33: =SUM(N33:Q33) -> -7521 | AD33: =SUM(O33:R33) -> -8496 | ... AG33: =SUM(R33:U33) -> -10491 | AI33: =SUM(AG33/AC33)-1 -> 0.3948943
B34: (-) Cash Taxes | C34: 0 | D34: 0 | E34: 0 | F34: 0 | H34: 0 | I34: 0 | J34: 0 | K34: 0 | L34: 0 | M34: 0 | N34: 0 | O34: 0 | P34: 0 | Q34: 0 | R34: 0 | S34: 0 | T34: 0 | U34: 0 | W34: =SUM(H34:K34) -> 0 | X34: =SUM(I34:L34) -> 0 | Y34: =SUM(J34:M34) -> 0 | Z34: =SUM(K34:N34) -> 0 | AA34: =SUM(L34:O34) -> 0 | AB34: =SUM(M34:P34) -> 0 | AC34: =SUM(N34:Q34) -> 0 | AD34: =SUM(O34:R34) -> 0 | ... AG34: =SUM(R34:U34) -> 0 | AI34: =SUM(AG34/AC34)-1 -> #DIV/0!
B35: (-) Mandatory Amortization | C35: 0 | D35: 0 | E35: 0 | F35: 0 | H35: 0 | I35: 0 | J35: 0 | K35: 0 | L35: 0 | M35: 0 | N35: 0 | O35: 0 | P35: 0 | Q35: 0 | R35: 0 | S35: 0 | T35: 0 | U35: 0 | W35: =SUM(H35:K35) -> 0 | X35: =SUM(I35:L35) -> 0 | Y35: =SUM(J35:M35) -> 0 | Z35: =SUM(K35:N35) -> 0 | AA35: =SUM(L35:O35) -> 0 | AB35: =SUM(M35:P35) -> 0 | AC35: =SUM(N35:Q35) -> 0 | AD35: =SUM(O35:R35) -> 0 | ... AG35: =SUM(R35:U35) -> 0 | AI35: =SUM(AG35/AC35)-1 -> #DIV/0!
B36: (+/-) Changes in NWC | C36: =SUM('Base Financials'!C95:C99) -> -557 | D36: =SUM('Base Financials'!D95:D99) -> 1029 | E36: =SUM('Base Financials'!E95:E99) -> 6571 | F36: =SUM('Base Financials'!F95:F99) -> 311 | H36: =SUM('Base Financials'!H95:H99) -> 391 | I36: =SUM('Base Financials'!I95:I99) -> -767 | J36: =SUM('Base Financials'!J95:J99) -> 3485 | K36: =SUM('Base Financials'!K95:K99) -> -2080 | L36: =SUM('Base Financials'!L95:L99) -> -159 | M36: =SUM('Base Financials'!M95:M99) -> -3452 | N36: =SUM('Base Financials'!N95:N99) -> 7051 | O36: =SUM('Base Financials'!O95:O99) -> 3131 | ... U36: =SUM('Base Financials'!U95:U99) -> -1398 | W36: =SUM(H36:K36) -> 1029 | X36: =SUM(I36:L36) -> 479 | Y36: =SUM(J36:M36) -> -2206 | Z36: =SUM(K36:N36) -> 1360 | AA36: =SUM(L36:O36) -> 6571 | AB36: =SUM(M36:P36) -> 2070 | AC36: =SUM(N36:Q36) -> 9580 | AD36: =SUM(O36:R36) -> 5943 | ... AG36: =SUM(R36:U36) -> -10049 | AI36: =SUM(AG36/AC36)-1 -> -2.0489562
B37: Discretionary Cash-Flows | C37: =SUM(C29+SUM(C32:C36)) -> -123774 | D37: =SUM(D29+SUM(D32:D36)) -> -152587 | E37: =SUM(E29+SUM(E32:E36)) -> -77525 | F37: =SUM(F29+SUM(F32:F36)) -> -82479 | H37: =SUM(H29+SUM(H32:H36)) -> -22497 | I37: =SUM(I29+SUM(I32:I36)) -> -73761 | J37: =SUM(J29+SUM(J32:J36)) -> -17388 | K37: =SUM(K29+SUM(K32:K36)) -> -38524 | L37: =SUM(L29+SUM(L32:L36)) -> -7449 | M37: =SUM(M29+SUM(M32:M36)) -> -32082 | N37: =SUM(N29+SUM(N32:N36)) -> -14646 | O37: =SUM(O29+SUM(O32:O36)) -> -23348 | ... U37: =SUM(U29+SUM(U32:U36)) -> -23825 | W37: =SUM(W29+SUM(W32:W36)) -> -152170 | X37: =SUM(X29+SUM(X32:X36)) -> -137122 | Y37: =SUM(Y29+SUM(Y32:Y36)) -> -95542 | Z37: =SUM(Z29+SUM(Z32:Z36)) -> -92935 | AA37: =SUM(AA29+SUM(AA32:AA36)) -> -77785 | AB37: =SUM(AB29+SUM(AB32:AB36)) -> -95943 | AC37: =SUM(AC29+SUM(AC32:AC36)) -> -62626 | AD37: =SUM(AD29+SUM(AD32:AD36)) -> -67365 | ... AG37: =SUM(AG29+SUM(AG32:AG36)) -> -177990 | AI37: =SUM(AG37/AC37)-1 -> 1.8421103
B39: (+/-) Net Equity Issuances / (Share Repurchases) | C39: ='Base Financials'!C108 -> 598 | D39: ='Base Financials'!D108 -> 535 | E39: ='Base Financials'!E108 -> 566 | F39: ='Base Financials'!F108 -> 97022 | H39: ='Base Financials'!H108 -> 1 | I39: ='Base Financials'!I108 -> 11 | J39: ='Base Financials'!J108 -> 217 | K39: ='Base Financials'!K108 -> 306 | L39: ='Base Financials'!L108 -> 119 | M39: ='Base Financials'!M108 -> 95 | N39: ='Base Financials'!N108 -> 99 | O39: ='Base Financials'!O108 -> 253 | ... U39: ='Base Financials'!U108 -> 2893 | W39: =SUM(H39:K39) -> 535 | X39: =SUM(I39:L39) -> 653 | Y39: =SUM(J39:M39) -> 737 | Z39: =SUM(K39:N39) -> 619 | AA39: =SUM(L39:O39) -> 566 | AB39: =SUM(M39:P39) -> 43845 | AC39: =SUM(N39:Q39) -> 44187 | AD39: =SUM(O39:R39) -> 45596 | ... AG39: =SUM(R39:U39) -> 103506 | AI39: =SUM(AG39/AC39)-1 -> 1.3424537
B40: (+/-) Net Issuance / (Repayment) of Debt | C40: ='Base Financials'!C109 -> 27930 | D40: ='Base Financials'!D109 -> -1981 | E40: ='Base Financials'!E109 -> -34066 | F40: ='Base Financials'!F109 -> -2579 | H40: ='Base Financials'!H109 -> -462 | I40: ='Base Financials'!I109 -> -495 | J40: ='Base Financials'!J109 -> -506 | K40: ='Base Financials'!K109 -> -518 | L40: ='Base Financials'!L109 -> -528 | M40: ='Base Financials'!M109 -> -32373 | N40: ='Base Financials'!N109 -> -577 | O40: ='Base Financials'!O109 -> -588 | ... U40: ='Base Financials'!U109 -> -727 | W40: =SUM(H40:K40) -> -1981 | X40: =SUM(I40:L40) -> -2047 | Y40: =SUM(J40:M40) -> -33925 | Z40: =SUM(K40:N40) -> -33996 | AA40: =SUM(L40:O40) -> -34066 | AB40: =SUM(M40:P40) -> -34141 | AC40: =SUM(N40:Q40) -> -2412 | AD40: =SUM(O40:R40) -> -2494 | ... AG40: =SUM(R40:U40) -> -2746 | AI40: =SUM(AG40/AC40)-1 -> 0.1384743
B41: (+/-) Net Divestitures / (Acquisitions) | C41: ='Base Financials'!C110 -> 238455 | D41: ='Base Financials'!D110 -> 0 | E41: ='Base Financials'!E110 -> 0 | F41: ='Base Financials'!F110 -> 0 | H41: ='Base Financials'!H110 -> 0 | I41: ='Base Financials'!I110 -> 0 | J41: ='Base Financials'!J110 -> 0 | K41: ='Base Financials'!K110 -> 0 | L41: ='Base Financials'!L110 -> 0 | M41: ='Base Financials'!M110 -> 0 | N41: ='Base Financials'!N110 -> 0 | O41: ='Base Financials'!O110 -> 0 | ... U41: ='Base Financials'!U110 -> 0 | W41: =SUM(H41:K41) -> 0 | X41: =SUM(I41:L41) -> 0 | Y41: =SUM(J41:M41) -> 0 | Z41: =SUM(K41:N41) -> 0 | AA41: =SUM(L41:O41) -> 0 | AB41: =SUM(M41:P41) -> 0 | AC41: =SUM(N41:Q41) -> 0 | AD41: =SUM(O41:R41) -> 0 | ... AG41: =SUM(R41:U41) -> 0 | AI41: =SUM(AG41/AC41)-1 -> #DIV/0!
B42: (+/-) Proceeds / (Payments) with Revenue Interest Purchase Agreement | C42: ='Base Financials'!C111 -> 0 | D42: ='Base Financials'!D111 -> 0 | E42: ='Base Financials'!E111 -> 37927 | F42: ='Base Financials'!F111 -> 19500 | H42: ='Base Financials'!H111 -> 0 | I42: ='Base Financials'!I111 -> 0 | J42: ='Base Financials'!J111 -> 0 | K42: ='Base Financials'!K111 -> 0 | L42: ='Base Financials'!L111 -> 0 | M42: ='Base Financials'!M111 -> 38213 | N42: ='Base Financials'!N111 -> -286 | O42: ='Base Financials'!O111 -> 0 | ... U42: ='Base Financials'!U111 -> 0 | W42: =SUM(H42:K42) -> 0 | X42: =SUM(I42:L42) -> 0 | Y42: =SUM(J42:M42) -> 38213 | Z42: =SUM(K42:N42) -> 37927 | AA42: =SUM(L42:O42) -> 37927 | AB42: =SUM(M42:P42) -> 57927 | AC42: =SUM(N42:Q42) -> 19214 | AD42: =SUM(O42:R42) -> 19500 | ... AG42: =SUM(R42:U42) -> 0 | AI42: =SUM(AG42/AC42)-1 -> -1
B43: (+/-) Proceeds from JDRF Agreement | C43: ='Base Financials'!C112 -> 0 | D43: ='Base Financials'!D112 -> 0 | E43: ='Base Financials'!E112 -> 80 | F43: ='Base Financials'!F112 -> 240 | H43: ='Base Financials'!H112 -> 0 | I43: ='Base Financials'!I112 -> 0 | J43: ='Base Financials'!J112 -> 0 | K43: ='Base Financials'!K112 -> 0 | L43: ='Base Financials'!L112 -> 0 | M43: ='Base Financials'!M112 -> 80 | N43: ='Base Financials'!N112 -> 0 | O43: ='Base Financials'!O112 -> 0 | ... U43: ='Base Financials'!U112 -> 0 | W43: =SUM(H43:K43) -> 0 | X43: =SUM(I43:L43) -> 0 | Y43: =SUM(J43:M43) -> 80 | Z43: =SUM(K43:N43) -> 80 | AA43: =SUM(L43:O43) -> 80 | AB43: =SUM(M43:P43) -> 80 | AC43: =SUM(N43:Q43) -> 240 | AD43: =SUM(O43:R43) -> 240 | ... AG43: =SUM(R43:U43) -> 0 | AI43: =SUM(AG43/AC43)-1 -> -1
B44: (+/-) Other Adjustments | C44: =SUM(C37:C43)-C49 -> -74293 | D44: =SUM(D49-C49)-SUM(D37:D43) -> 86303 | E44: =SUM(E49-D49)-SUM(E37:E43) -> 3694 | F44: =SUM(F49-E49)-SUM(F37:F43) -> -67215 | H44: =SUM(H49-C49)-SUM(H37:H43) -> 3678 | I44: =SUM(I49-H49)-SUM(I37:I43) -> 57058 | J44: =SUM(J49-I49)-SUM(J37:J43) -> 373 | K44: =SUM(K49-J49)-SUM(K37:K43) -> 24777 | L44: =SUM(L49-K49)-SUM(L37:L43) -> -12344 | M44: =SUM(M49-L49)-SUM(M37:M43) -> 11101 | N44: =SUM(N49-M49)-SUM(N37:N43) -> 792 | O44: =SUM(O49-N49)-SUM(O37:O43) -> 4145 | P44: =SUM(P49-O49)-SUM(P37:P43) -> -2071 | ... U44: =SUM(U49-T49)-SUM(U37:U43) -> -3156 | W44: =SUM(H44:K44) -> 85886 | X44: =SUM(I44:L44) -> 69864 | Y44: =SUM(J44:M44) -> 23907 | Z44: =SUM(K44:N44) -> 24326 | AA44: =SUM(L44:O44) -> 3694 | AB44: =SUM(M44:P44) -> 13967 | AC44: =SUM(N44:Q44) -> -19644 | AD44: =SUM(O44:R44) -> -74892 | ... AG44: =SUM(R44:U44) -> 21699 | AI44: =SUM(AG44/AC44)-1 -> -2.1046121
B45: Free-Cash Flows | C45: =SUM(C37:C44) -> 68916 | D45: =SUM(D37+SUM(D39:D44)) -> -67730 | E45: =SUM(E37+SUM(E39:E44)) -> -69324 | F45: =SUM(F37+SUM(F39:F44)) -> -35511 | H45: =SUM(H37+SUM(H39:H44)) -> -19280 | I45: =SUM(I37+SUM(I39:I44)) -> -17187 | J45: =SUM(J37+SUM(J39:J44)) -> -17304 | K45: =SUM(K37+SUM(K39:K44)) -> -13959 | L45: =SUM(L37+SUM(L39:L44)) -> -20202 | M45: =SUM(M37+SUM(M39:M44)) -> -14966 | N45: =SUM(N37+SUM(N39:N44)) -> -14618 | O45: =SUM(O37+SUM(O39:O44)) -> -19538 | ... U45: =SUM(U37+SUM(U39:U44)) -> -24815 | W45: =SUM(W37+SUM(W39:W44)) -> -67730 | X45: =SUM(X37+SUM(X39:X44)) -> -68652 | Y45: =SUM(Y37+SUM(Y39:Y44)) -> -66530 | Z45: =SUM(Z37+SUM(Z39:Z44)) -> -63979 | AA45: =SUM(AA37+SUM(AA39:AA44)) -> -69584 | AB45: =SUM(AB37+SUM(AB39:AB44)) -> -14265 | AC45: =SUM(AC37+SUM(AC39:AC44)) -> -21041 | AD45: =SUM(AD37+SUM(AD39:AD44)) -> -79415 | ... AG45: =SUM(AG37+SUM(AG39:AG44)) -> -55531 | AI45: =SUM(AG45/AC45)-1 -> 1.6391806
B47: Capitalization
B49: Cash & Cash Equivelants | C49: ='Base Financials'!C35 -> 217502 | D49: ='Base Financials'!D35 -> 149772 | E49: ='Base Financials'!E35 -> 80448 | F49: ='Base Financials'!F35 -> 44937 | H49: ='Base Financials'!H35 -> 198222 | I49: ='Base Financials'!I35 -> 181035 | J49: ='Base Financials'!J35 -> 163731 | K49: ='Base Financials'!K35 -> 149772 | L49: ='Base Financials'!L35 -> 129570 | M49: ='Base Financials'!M35 -> 114604 | N49: ='Base Financials'!N35 -> 99986 | O49: ='Base Financials'!O35 -> 80448 | ... U49: ='Base Financials'!U35 -> 38032 | W49: =K49 -> 149772 | X49: =L49 -> 129570 | Y49: =M49 -> 114604 | Z49: =N49 -> 99986 | AA49: =O49 -> 80448 | AB49: =P49 -> 115505 | AC49: =Q49 -> 93563 | AD49: =R49 -> 20571 | ... AG49: =U49 -> 38032
B50: Short-Term Investments | C50: ='Base Financials'!C37 -> 8000 | D50: ='Base Financials'!D37 -> 2107 | E50: ='Base Financials'!E37 -> 0 | F50: ='Base Financials'!F37 -> 0 | H50: ='Base Financials'!H37 -> 8000 | I50: ='Base Financials'!I37 -> 8000 | J50: ='Base Financials'!J37 -> 8000 | K50: ='Base Financials'!K37 -> 2107 | L50: ='Base Financials'!L37 -> 2107 | M50: ='Base Financials'!M37 -> 0 | N50: ='Base Financials'!N37 -> 0 | O50: ='Base Financials'!O37 -> 0 | ... U50: ='Base Financials'!U37 -> 0 | W50: =K50 -> 2107 | X50: =L50 -> 2107 | Y50: =M50 -> 0 | Z50: =N50 -> 0 | AA50: =O50 -> 0 | AB50: =P50 -> 0 | AC50: =Q50 -> 0 | AD50: =R50 -> 0 | ... AG50: =U50 -> 0
B51: Total Liquidity | C51: =SUM(C49:C50) -> 225502 | D51: =SUM(D49:D50) -> 151879 | E51: =SUM(E49:E50) -> 80448 | F51: =SUM(F49:F50) -> 44937 | H51: =SUM(H49:H50) -> 206222 | I51: =SUM(I49:I50) -> 189035 | J51: =SUM(J49:J50) -> 171731 | K51: =SUM(K49:K50) -> 151879 | L51: =SUM(L49:L50) -> 131677 | M51: =SUM(M49:M50) -> 114604 | N51: =SUM(N49:N50) -> 99986 | O51: =SUM(O49:O50) -> 80448 | ... U51: =SUM(U49:U50) -> 38032 | W51: =SUM(W49:W50) -> 151879 | X51: =SUM(X49:X50) -> 131677 | Y51: =SUM(Y49:Y50) -> 114604 | Z51: =SUM(Z49:Z50) -> 99986 | AA51: =SUM(AA49:AA50) -> 80448 | AB51: =SUM(AB49:AB50) -> 115505 | AC51: =SUM(AC49:AC50) -> 93563 | AD51: =SUM(AD49:AD50) -> 20571 | ... AG51: =SUM(AG49:AG50) -> 38032
B54: Balance Sheet Metrics:
B55: Accounts Receivable | C55: ='Base Financials'!C36 -> 176 | D55: ='Base Financials'!D36 -> 31 | E55: ='Base Financials'!E36 -> 0 | F55: ='Base Financials'!F36 -> 0 | H55: ='Base Financials'!H36 -> 233 | I55: ='Base Financials'!I36 -> 1301 | J55: ='Base Financials'!J36 -> 31 | K55: ='Base Financials'!K36 -> 31 | L55: ='Base Financials'!L36 -> 0 | M55: ='Base Financials'!M36 -> 0 | N55: ='Base Financials'!N36 -> 0 | O55: ='Base Financials'!O36 -> 0 | ... U55: ='Base Financials'!U36 -> 394 | W55: =K55 -> 31 | X55: =L55 -> 0 | Y55: =M55 -> 0 | Z55: =N55 -> 0 | AA55: =O55 -> 0 | AB55: =P55 -> 0 | AC55: =Q55 -> 0 | AD55: =R55 -> 0 | ... AG55: =U55 -> 394
B56: Accounts Payable | C56: ='Base Financials'!C50 -> 2094 | D56: ='Base Financials'!D50 -> 1595 | E56: ='Base Financials'!E50 -> 6490 | F56: ='Base Financials'!F50 -> 4490 | H56: ='Base Financials'!H50 -> 3037 | I56: ='Base Financials'!I50 -> 2537 | J56: ='Base Financials'!J50 -> 3255 | K56: ='Base Financials'!K50 -> 1595 | L56: ='Base Financials'!L50 -> 1954 | M56: ='Base Financials'!M50 -> 2362 | N56: ='Base Financials'!N50 -> 3018 | O56: ='Base Financials'!O50 -> 6490 | ... U56: ='Base Financials'!U50 -> 6629 | W56: =K56 -> 1595 | X56: =L56 -> 1954 | Y56: =M56 -> 2362 | Z56: =N56 -> 3018 | AA56: =O56 -> 6490 | AB56: =P56 -> 3452 | AC56: =Q56 -> 6005 | AD56: =R56 -> 6903 | ... AG56: =U56 -> 6629
B57: Property Plant, and Equiptment | C57: ='Base Financials'!C44 -> 35034 | D57: ='Base Financials'!D44 -> 30039 | E57: ='Base Financials'!E44 -> 26791 | F57: ='Base Financials'!F44 -> 23063 | H57: ='Base Financials'!H44 -> 33540 | I57: ='Base Financials'!I44 -> 32227 | J57: ='Base Financials'!J44 -> 31026 | K57: ='Base Financials'!K44 -> 30039 | L57: ='Base Financials'!L44 -> 29593 | M57: ='Base Financials'!M44 -> 28543 | N57: ='Base Financials'!N44 -> 27851 | O57: ='Base Financials'!O44 -> 26791 | ... U57: ='Base Financials'!U44 -> 21191 | W57: =K57 -> 30039 | X57: =L57 -> 29593 | Y57: =M57 -> 28543 | Z57: =N57 -> 27851 | AA57: =O57 -> 26791 | AB57: =P57 -> 25653 | AC57: =Q57 -> 24820 | AD57: =R57 -> 24250 | ... AG57: =U57 -> 21191
B58: Revenue interest liability, Current | C58: ='Base Financials'!C53 -> 0 | D58: ='Base Financials'!D53 -> 0 | E58: ='Base Financials'!E53 -> 0 | F58: ='Base Financials'!F53 -> 0 | H58: ='Base Financials'!H53 -> 0 | I58: ='Base Financials'!I53 -> 0 | J58: ='Base Financials'!J53 -> 0 | K58: ='Base Financials'!K53 -> 0 | L58: ='Base Financials'!L53 -> 0 | M58: ='Base Financials'!M53 -> 0 | N58: ='Base Financials'!N53 -> 0 | O58: ='Base Financials'!O53 -> 0 | ... U58: ='Base Financials'!U53 -> 2116 | AC58: =Q58 -> 0 | AD58: =R58 -> 0 | AE58: =S58 -> 0 | AF58: =T58 -> 1690 | AG58: =U58 -> 2116
B59: Revenue interest liability, Non-Current | C59: ='Base Financials'!C59 -> 0 | D59: ='Base Financials'!D59 -> 0 | E59: ='Base Financials'!E59 -> 38600 | F59: ='Base Financials'!F59 -> 63354 | H59: ='Base Financials'!H59 -> 0 | I59: ='Base Financials'!I59 -> 0 | J59: ='Base Financials'!J59 -> 0 | K59: ='Base Financials'!K59 -> 0 | L59: ='Base Financials'!L59 -> 0 | M59: ='Base Financials'!M59 -> 36248 | N59: ='Base Financials'!N59 -> 37286 | O59: ='Base Financials'!O59 -> 38600 | ... U59: ='Base Financials'!U59 -> 66425 | AC59: =Q59 -> 60078 | AD59: =R59 -> 62117 | AE59: =S59 -> 63354 | AF59: =T59 -> 64672 | AG59: =U59 -> 66425
B60: Contingent Earnout Liability, Non-Current | C60: ='Base Financials'!C60 -> 103660 | D60: ='Base Financials'!D60 -> 27893 | E60: ='Base Financials'!E60 -> 37916 | F60: ='Base Financials'!F60 -> 70961 | H60: ='Base Financials'!H60 -> 100402 | I60: ='Base Financials'!I60 -> 44049 | J60: ='Base Financials'!J60 -> 45011 | K60: ='Base Financials'!K60 -> 27893 | L60: ='Base Financials'!L60 -> 42084 | M60: ='Base Financials'!M60 -> 38457 | N60: ='Base Financials'!N60 -> 39601 | O60: ='Base Financials'!O60 -> 37916 | ... U60: ='Base Financials'!U60 -> 26700 | AC60: =Q60 -> 68080 | AD60: =R60 -> 76569 | AE60: =S60 -> 70961 | AF60: =T60 -> 21230 | AG60: =U60 -> 26700
B61: Current Liabilities | C61: ='Base Financials'!C56 -> 11050 | D61: ='Base Financials'!D56 -> 19580 | E61: ='Base Financials'!E56 -> 18443 | F61: ='Base Financials'!F56 -> 19954 | H61: ='Base Financials'!H56 -> 10763 | I61: ='Base Financials'!I56 -> 11058 | J61: ='Base Financials'!J56 -> 17906 | K61: ='Base Financials'!K56 -> 19580 | L61: ='Base Financials'!L56 -> 23601 | M61: ='Base Financials'!M56 -> 11388 | N61: ='Base Financials'!N56 -> 15137 | O61: ='Base Financials'!O56 -> 18443 | ... U61: ='Base Financials'!U56 -> 21085 | W61: =K61 -> 19580 | X61: =L61 -> 23601 | Y61: =M61 -> 11388 | Z61: =N61 -> 15137 | AA61: =O61 -> 18443 | AB61: =P61 -> 14087 | AC61: =Q61 -> 17757 | AD61: =R61 -> 20942 | ... AG61: =U61 -> 21085
B62: Total Liabilities | C62: ='Base Financials'!C64 -> 164359 | D62: ='Base Financials'!D64 -> 87374 | E62: ='Base Financials'!E64 -> 114677 | F62: ='Base Financials'!F64 -> 190541 | H62: ='Base Financials'!H64 -> 160578 | I62: ='Base Financials'!I64 -> 104105 | J62: ='Base Financials'!J64 -> 107547 | K62: ='Base Financials'!K64 -> 87374 | L62: ='Base Financials'!L64 -> 101089 | M62: ='Base Financials'!M64 -> 106989 | N62: ='Base Financials'!N64 -> 112392 | O62: ='Base Financials'!O64 -> 114677 | ... U62: ='Base Financials'!U64 -> 134743 | W62: =K62 -> 87374 | X62: =L62 -> 101089 | Y62: =M62 -> 106989 | Z62: =N62 -> 112392 | AA62: =O62 -> 114677 | AB62: =P62 -> 135314 | AC62: =Q62 -> 166568 | AD62: =R62 -> 178485 | ... AG62: =U62 -> 134743
B64: Summary Debt (BS):
B65: CPLTD | C65: =SUM('Base Financials'!C52+'Base Financials'!C53+'Base Financials'!C54) -> 1981 | D65: =SUM('Base Financials'!D52+'Base Financials'!D53+'Base Financials'!D54) -> 10827 | E65: =SUM('Base Financials'!E52+'Base Financials'!E53+'Base Financials'!E54) -> 2560 | F65: =SUM('Base Financials'!F52+'Base Financials'!F53+'Base Financials'!F54) -> 2917 | H65: =SUM('Base Financials'!H52+'Base Financials'!H53+'Base Financials'!H54) -> 2047 | I65: =SUM('Base Financials'!I52+'Base Financials'!I53+'Base Financials'!I54) -> 2115 | J65: =SUM('Base Financials'!J52+'Base Financials'!J53+'Base Financials'!J54) -> 6471 | K65: =SUM('Base Financials'!K52+'Base Financials'!K53+'Base Financials'!K54) -> 10827 | L65: =SUM('Base Financials'!L52+'Base Financials'!L53+'Base Financials'!L54) -> 15186 | M65: =SUM('Base Financials'!M52+'Base Financials'!M53+'Base Financials'!M54) -> 2404 | N65: =SUM('Base Financials'!N52+'Base Financials'!N53+'Base Financials'!N54) -> 2481 | O65: =SUM('Base Financials'!O52+'Base Financials'!O53+'Base Financials'!O54) -> 2560 | ... U65: =SUM('Base Financials'!U52+'Base Financials'!U53+'Base Financials'!U54) -> 5209 | W65: =K65 -> 10827 | X65: =L65 -> 15186 | Y65: =M65 -> 2404 | Z65: =N65 -> 2481 | AA65: =O65 -> 2560 | AB65: =P65 -> 2663 | AC65: =Q65 -> 2746 | AD65: =R65 -> 2831 | ... AG65: =U65 -> 5209
B66: LTD | C66: =SUM('Base Financials'!C59+'Base Financials'!C61+'Base Financials'!C62) -> 48470 | D66: =SUM('Base Financials'!D59+'Base Financials'!D61+'Base Financials'!D62) -> 39189 | E66: =SUM('Base Financials'!E59+'Base Financials'!E61+'Base Financials'!E62) -> 54893 | F66: =SUM('Base Financials'!F59+'Base Financials'!F61+'Base Financials'!F62) -> 76974 | H66: =SUM('Base Financials'!H59+'Base Financials'!H61+'Base Financials'!H62) -> 48320 | I66: =SUM('Base Financials'!I59+'Base Financials'!I61+'Base Financials'!I62) -> 48150 | J66: =SUM('Base Financials'!J59+'Base Financials'!J61+'Base Financials'!J62) -> 43728 | K66: =SUM('Base Financials'!K59+'Base Financials'!K61+'Base Financials'!K62) -> 39189 | L66: =SUM('Base Financials'!L59+'Base Financials'!L61+'Base Financials'!L62) -> 34662 | M66: =SUM('Base Financials'!M59+'Base Financials'!M61+'Base Financials'!M62) -> 53862 | N66: =SUM('Base Financials'!N59+'Base Financials'!N61+'Base Financials'!N62) -> 54246 | O66: =SUM('Base Financials'!O59+'Base Financials'!O61+'Base Financials'!O62) -> 54893 | ... U66: =SUM('Base Financials'!U59+'Base Financials'!U61+'Base Financials'!U62) -> 78455 | W66: =K66 -> 39189 | X66: =L66 -> 34662 | Y66: =M66 -> 53862 | Z66: =N66 -> 54246 | AA66: =O66 -> 54893 | AB66: =P66 -> 73809 | AC66: =Q66 -> 75201 | AD66: =R66 -> 76496 | ... AG66: =U66 -> 78455
B68: Finance Lease Obligations | C68: =SUM('Base Financials'!C52+'Base Financials'!C61) -> 23090 | D68: =SUM('Base Financials'!D52+'Base Financials'!D61) -> 21109 | E68: =SUM('Base Financials'!E52+'Base Financials'!E61) -> 18853 | F68: =SUM('Base Financials'!F52+'Base Financials'!F61) -> 16537 | H68: =SUM('Base Financials'!H52+'Base Financials'!H61) -> 22628 | I68: =SUM('Base Financials'!I52+'Base Financials'!I61) -> 22133 | J68: =SUM('Base Financials'!J52+'Base Financials'!J61) -> 21627 | K68: =SUM('Base Financials'!K52+'Base Financials'!K61) -> 21109 | L68: =SUM('Base Financials'!L52+'Base Financials'!L61) -> 20581 | M68: =SUM('Base Financials'!M52+'Base Financials'!M61) -> 20018 | N68: =SUM('Base Financials'!N52+'Base Financials'!N61) -> 19441 | O68: =SUM('Base Financials'!O52+'Base Financials'!O61) -> 18853 | ... U68: =SUM('Base Financials'!U52+'Base Financials'!U61) -> 15123 | W68: =K68 -> 21109 | X68: =L68 -> 20581 | Y68: =M68 -> 20018 | Z68: =N68 -> 19441 | AA68: =O68 -> 18853 | AB68: =P68 -> 18513 | AC68: =Q68 -> 17869 | AD68: =R68 -> 17210 | ... AG68: =U68 -> 15123
B69: Revenue Interest Liability | C69: =SUM('Base Financials'!C53+'Base Financials'!C59) -> 0 | D69: =SUM('Base Financials'!D53+'Base Financials'!D59) -> 0 | E69: =SUM('Base Financials'!E53+'Base Financials'!E59) -> 38600 | F69: =SUM('Base Financials'!F53+'Base Financials'!F59) -> 63354 | H69: =SUM('Base Financials'!H53+'Base Financials'!H59) -> 0 | I69: =SUM('Base Financials'!I53+'Base Financials'!I59) -> 0 | J69: =SUM('Base Financials'!J53+'Base Financials'!J59) -> 0 | K69: =SUM('Base Financials'!K53+'Base Financials'!K59) -> 0 | L69: =SUM('Base Financials'!L53+'Base Financials'!L59) -> 0 | M69: =SUM('Base Financials'!M53+'Base Financials'!M59) -> 36248 | N69: =SUM('Base Financials'!N53+'Base Financials'!N59) -> 37286 | O69: =SUM('Base Financials'!O53+'Base Financials'!O59) -> 38600 | ... U69: =SUM('Base Financials'!U53+'Base Financials'!U59) -> 68541 | W69: =K69 -> 0 | X69: =L69 -> 0 | Y69: =M69 -> 36248 | Z69: =N69 -> 37286 | AA69: =O69 -> 38600 | AB69: =P69 -> 57959 | AC69: =Q69 -> 60078 | AD69: =R69 -> 62117 | ... AG69: =U69 -> 68541
B70: SVB loan Payable | C70: =SUM('Base Financials'!C54+'Base Financials'!C62) -> 27361 | D70: =SUM('Base Financials'!D54+'Base Financials'!D62) -> 28907 | E70: =SUM('Base Financials'!E54+'Base Financials'!E62) -> 0 | F70: =SUM('Base Financials'!F54+'Base Financials'!F62) -> 0 | H70: =SUM('Base Financials'!H54+'Base Financials'!H62) -> 27739 | I70: =SUM('Base Financials'!I54+'Base Financials'!I62) -> 28132 | J70: =SUM('Base Financials'!J54+'Base Financials'!J62) -> 28572 | K70: =SUM('Base Financials'!K54+'Base Financials'!K62) -> 28907 | L70: =SUM('Base Financials'!L54+'Base Financials'!L62) -> 29267 | M70: =SUM('Base Financials'!M54+'Base Financials'!M62) -> 0 | N70: =SUM('Base Financials'!N54+'Base Financials'!N62) -> 0 | O70: =SUM('Base Financials'!O54+'Base Financials'!O62) -> 0 | ... U70: =SUM('Base Financials'!U54+'Base Financials'!U62) -> 0 | W70: =K70 -> 28907 | X70: =L70 -> 29267 | Y70: =M70 -> 0 | Z70: =N70 -> 0 | AA70: =O70 -> 0 | AB70: =P70 -> 0 | AC70: =Q70 -> 0 | AD70: =R70 -> 0 | ... AG70: =U70 -> 0
B71: Total Debt | C71: =SUM(C68:C70) -> 50451 | D71: =SUM(D68:D70) -> 50016 | E71: =SUM(E68:E70) -> 57453 | F71: =SUM(F68:F70) -> 79891 | H71: =SUM(H68:H70) -> 50367 | I71: =SUM(I68:I70) -> 50265 | J71: =SUM(J68:J70) -> 50199 | K71: =SUM(K68:K70) -> 50016 | L71: =SUM(L68:L70) -> 49848 | M71: =SUM(M68:M70) -> 56266 | N71: =SUM(N68:N70) -> 56727 | O71: =SUM(O68:O70) -> 57453 | ... U71: =SUM(U68:U70) -> 83664 | W71: =SUM(W68:W70) -> 50016 | X71: =SUM(X68:X70) -> 49848 | Y71: =SUM(Y68:Y70) -> 56266 | Z71: =SUM(Z68:Z70) -> 56727 | AA71: =SUM(AA68:AA70) -> 57453 | AB71: =SUM(AB68:AB70) -> 76472 | AC71: =SUM(AC68:AC70) -> 77947 | AD71: =SUM(AD68:AD70) -> 79327 | ... AG71: =SUM(AG68:AG70) -> 83664
B73: Total Shareholder Equity | C73: ='Base Financials'!C70 -> 122174 | D73: ='Base Financials'!D70 -> 116928 | E73: ='Base Financials'!E70 -> 13546 | F73: ='Base Financials'!F70 -> -52669 | H73: ='Base Financials'!H70 -> 103890 | I73: ='Base Financials'!I70 -> 142260 | J73: ='Base Financials'!J70 -> 118672 | K73: ='Base Financials'!K70 -> 116928 | L73: ='Base Financials'!L70 -> 81887 | M73: ='Base Financials'!M70 -> 61117 | N73: ='Base Financials'!N70 -> 36993 | O73: ='Base Financials'!O70 -> 13546 | ... U73: ='Base Financials'!U70 -> 4052 | W73: =K73 -> 116928 | X73: =L73 -> 81887 | Y73: =M73 -> 61117 | Z73: =N73 -> 36993 | AA73: =O73 -> 13546 | AB73: =P73 -> 26152 | AC73: =Q73 -> -28287 | AD73: =R73 -> -63721 | ... AG73: =U73 -> 4052
B74: Total Book Capitalization | C74: =SUM(C71:C73) -> 172625 | D74: =SUM(D71:D73) -> 166944 | E74: =SUM(E71:E73) -> 70999 | F74: =SUM(F71:F73) -> 27222 | H74: =SUM(H71:H73) -> 154257 | I74: =SUM(I71:I73) -> 192525 | J74: =SUM(J71:J73) -> 168871 | K74: =SUM(K71:K73) -> 166944 | L74: =SUM(L71:L73) -> 131735 | M74: =SUM(M71:M73) -> 117383 | N74: =SUM(N71:N73) -> 93720 | O74: =SUM(O71:O73) -> 70999 | ... U74: =SUM(U71:U73) -> 87716 | W74: =SUM(W71:W73) -> 166944 | X74: =SUM(X71:X73) -> 131735 | Y74: =SUM(Y71:Y73) -> 117383 | Z74: =SUM(Z71:Z73) -> 93720 | AA74: =SUM(AA71:AA73) -> 70999 | AB74: =SUM(AB71:AB73) -> 102624 | AC74: =SUM(AC71:AC73) -> 49660 | AD74: =SUM(AD71:AD73) -> 15606 | ... AG74: =SUM(AG71:AG73) -> 87716
B76: Ratio Analysis
B78: LTM Total Leverage | C78: =C71/C29 -> -0.42521218 | D78: =D71/D29 -> -0.34171404 | E78: =E71/E29 -> -0.76382999 | F78: =F71/F29 -> -1.1105072 | K78: =SUM(K71/SUM(H29:K29)) -> -0.34269035 | L78: =SUM(L71/SUM(I29:L29)) -> -0.38655045 | M78: =SUM(M71/SUM(J29:M29)) -> -0.66968186 | N78: =SUM(N71/SUM(K29:N29)) -> -0.66943202 | O78: =SUM(O71/SUM(L29:O29)) -> -0.76382999 | P78: =SUM(P71/SUM(M29:P29)) -> -0.85369175 | Q78: =SUM(Q71/SUM(N29:Q29)) -> -1.2281501 | R78: =SUM(R71/SUM(O29:R29)) -> -1.2561082 | ... U78: =SUM(U71/SUM(R29:U29)) -> -0.53748948 | W78: =W71/W29 -> -0.34269035 | X78: =X71/X29 -> -0.38655045 | Y78: =Y71/Y29 -> -0.6688937 | Z78: =Z71/Z29 -> -0.66758853 | AA78: =AA71/AA29 -> -0.76119878 | AB78: =AB71/AB29 -> -0.85178997 | AC78: =AC71/AC29 -> -1.2281501 | AD78: =AD71/AD29 -> -1.2561082 | ... AG78: =AG71/AG29 -> -0.53748948
B79: LTM Net Debt | C79: =SUM(C71-C49)/C29 -> 1.4079428 | D79: =SUM(D71-D49)/D29 -> 0.68154241 | E79: =SUM(E71-E49)/E29 -> 0.30571546 | F79: =SUM(F71-F49)/F29 -> -0.48587037 | K79: =SUM(K71-K49)/SUM(H29:K29) -> 0.68348966 | L79: =SUM(L71-L49)/SUM(I29:L29) -> 0.61821086 | M79: =SUM(M71-M49)/SUM(J29:M29) -> 0.69434295 | N79: =SUM(N71-N49)/SUM(K29:N29) -> 0.51049694 | O79: =SUM(O71-O49)/SUM(L29:O29) -> 0.30571546 | P79: =SUM(P71-P49)/SUM(M29:P29) -> 0.43574315 | Q79: =SUM(Q71-Q49)/SUM(N29:Q29) -> 0.24604913 | R79: =SUM(R71-R49)/SUM(O29:R29) -> -0.93037544 | ... U79: =SUM(U71-U49)/SUM(R29:U29) -> -0.29315739 | W79: =SUM(W71-W49)/W29 -> 0.68348966 | X79: =SUM(X71-X49)/X29 -> 0.61821086 | Y79: =SUM(Y71-Y49)/Y29 -> 0.69352576 | Z79: =SUM(Z71-Z49)/Z29 -> 0.50909112 | AA79: =SUM(AA71-AA49)/AA29 -> 0.30466235 | AB79: =SUM(AB71-AB49)/AB29 -> 0.43477244 | AC79: =SUM(AC71-AC49)/AC29 -> 0.24604913 | AD79: =SUM(AD71-AD49)/AD29 -> -0.93037544 | ... AG79: =SUM(AG71-AG49)/AG29 -> -0.29315739
B80: LTM Interest Coverage | C80: =C29/-C33 -> -27.288178 | D80: =D29/-D33 -> -23.607742 | E80: =E29/-E33 -> -11.398242 | F80: =F29/-F33 -> -7.7547699 | K80: {=SUM(H29:K29)/SUM(-H33:K33)} -> -23.540484 | L80: {=SUM(I29:L29)/SUM(-I33:L33)} -> -19.940622 | M80: {=SUM(J29:M29)/SUM(-J33:M33)} -> -12.560771 | N80: {=SUM(K29:N29)/SUM(-K33:N33)} -> -13.014744 | O80: {=SUM(L29:O29)/SUM(-L33:O33)} -> -11.398242 | P80: {=SUM(M29:P29)/SUM(-M33:P33)} -> -13.337999 | Q80: {=SUM(N29:Q29)/SUM(-N33:Q33)} -> -8.4386385 | R80: {=SUM(O29:R29)/SUM(-O33:R33)} -> -7.4332627 | ... U80: {=SUM(R29:U29)/SUM(-R33:U33)} -> -14.837194 | W80: =W29/-W33 -> -23.540484 | X80: =X29/-X33 -> -19.940622 | Y80: =Y29/-Y33 -> -12.575572 | Z80: =Z29/-Z33 -> -13.050683 | AA80: =AA29/-AA33 -> -11.437642 | AB80: =AB29/-AB33 -> -13.367778 | AC80: =AC29/-AC33 -> -8.4386385 | AD80: =AD29/-AD33 -> -7.4332627 | ... AG80: =AG29/-AG33 -> -14.837194
B81: LTM Debt Service Coverage | C81: {=SUM(C29+C32)/SUM(-C33:C35)} -> -27.338776 | D81: {=SUM(D29+D32)/SUM(-D33:D35)} -> -23.776774 | E81: {=SUM(E29+E32)/SUM(-E33:E35)} -> -11.743749 | F81: {=SUM(F29+F32)/SUM(-F33:F35)} -> -7.9242212 | K81: {=SUM(H29:K29+H32:K32)/SUM(-H33:K35)} -> -23.709516 | L81: {=SUM(I29:L29+I32:L32)/SUM(-I33:L35)} -> -20.277408 | M81: {=SUM(J29:M29+J32:M32)/SUM(-J33:M35)} -> -12.938855 | N81: {=SUM(K29:N29+K32:N32)/SUM(-K33:N35)} -> -13.446475 | O81: {=SUM(L29:O29+L32:O32)/SUM(-L33:O35)} -> -11.743749 | P81: {=SUM(M29:P29+M32:P32)/SUM(-M33:P35)} -> -13.564175 | Q81: {=SUM(N29:Q29+N32:Q32)/SUM(-N33:Q35)} -> -8.600585 | R81: {=SUM(O29:R29+O32:R32)/SUM(-O33:R35)} -> -7.6285311 | ... U81: {=SUM(R29:U29+R32:U32)/SUM(-R33:U35)} -> -15.008102 | W81: {=SUM(W29+W32)/SUM(-W33:W35)} -> -23.709516 | X81: {=SUM(X29+X32)/SUM(-X33:X35)} -> -20.277408 | Y81: {=SUM(Y29+Y32)/SUM(-Y33:Y35)} -> -12.953655 | Z81: {=SUM(Z29+Z32)/SUM(-Z33:Z35)} -> -13.482414 | AA81: {=SUM(AA29+AA32)/SUM(-AA33:AA35)} -> -11.783149 | AB81: {=SUM(AB29+AB32)/SUM(-AB33:AB35)} -> -13.593955 | AC81: {=SUM(AC29+AC32)/SUM(-AC33:AC35)} -> -8.600585 | AD81: {=SUM(AD29+AD32)/SUM(-AD33:AD35)} -> -7.6285311 | ... AG81: {=SUM(AG29+AG32)/SUM(-AG33:AG35)} -> -15.008102
B82: LTM Fixed Charge Coverage | C82: {=SUM(C29)/SUM(-C32:C35)} -> -25.973949 | D82: {=SUM(D29)/SUM(-D32:D35)} -> -20.19426 | E82: {=SUM(E29)/SUM(-E32:E35)} -> -8.4713369 | F82: {=SUM(F29)/SUM(-F32:F35)} -> -6.6311181 | K82: {=SUM(H29:K29)/SUM(-H32:K35)} -> -20.136727 | L82: {=SUM(I29:L29)/SUM(-I32:L35)} -> -14.916831 | M82: {=SUM(J29:M29)/SUM(-J32:M35)} -> -9.114667 | N82: {=SUM(K29:N29)/SUM(-K32:N35)} -> -9.0902167 | O82: {=SUM(L29:O29)/SUM(-L32:O35)} -> -8.4713369 | P82: {=SUM(M29:P29)/SUM(-M32:P35)} -> -10.877717 | Q82: {=SUM(N29:Q29)/SUM(-N32:Q35)} -> -7.2625014 | R82: {=SUM(O29:R29)/SUM(-O32:R35)} -> -6.2189069 | ... U82: {=SUM(R29:U29)/SUM(-R32:U35)} -> -12.671524 | W82: {=SUM(W29)/SUM(-W32:W35)} -> -20.136727 | X82: {=SUM(X29)/SUM(-X32:X35)} -> -14.916831 | Y82: {=SUM(Y29)/SUM(-Y32:Y35)} -> -9.1254068 | Z82: {=SUM(Z29)/SUM(-Z32:Z35)} -> -9.1153186 | AA82: {=SUM(AA29)/SUM(-AA32:AA35)} -> -8.5006194 | AB82: {=SUM(AB29)/SUM(-AB32:AB35)} -> -10.902004 | AC82: {=SUM(AC29)/SUM(-AC32:AC35)} -> -7.2625014 | AD82: {=SUM(AD29)/SUM(-AD32:AD35)} -> -6.2189069 | ... AG82: {=SUM(AG29)/SUM(-AG32:AG35)} -> -12.671524
B83: Debt-to-Book Capitalization | C83: =C74/C71 -> 3.4216368 | D83: =D74/D71 -> 3.3378119 | E83: =E74/E71 -> 1.2357753 | F83: =F74/F71 -> 0.34073926 | K83: =K74/K71 -> 3.3378119 | L83: =L74/L71 -> 2.6427339 | M83: =M74/M71 -> 2.0862155 | N83: =N74/N71 -> 1.6521233 | O83: =O74/O71 -> 1.2357753 | P83: =P74/P71 -> 1.3419814 | Q83: =Q74/Q71 -> 0.63709957 | R83: =R74/R71 -> 0.19672999 | ... U83: =U74/U71 -> 1.0484318 | W83: =W74/W71 -> 3.3378119 | X83: =X74/X71 -> 2.6427339 | Y83: =Y74/Y71 -> 2.0862155 | Z83: =Z74/Z71 -> 1.6521233 | AA83: =AA74/AA71 -> 1.2357753 | AB83: =AB74/AB71 -> 1.3419814 | AC83: =AC74/AC71 -> 0.63709957 | AD83: =AD74/AD71 -> 0.19672999 | ... AG83: =AG74/AG71 -> 1.0484318

Sheet Cash Analysis
B2: Humacyte Inc (NASDAQ: HUMA) | C2: FYE | D2: FYE | H2: Quarterly | P2: Quarterly | Q2: Quarterly | W2: LTM | AA2: LTM | AC2: LTM
B3: Cash Analysis | C3: 2021 | D3: 2022 | E3: 2023 | F3: 2024 | H3: 1Q22 | I3: 2Q22 | J3: 3Q22 | K3: 4Q22 | L3: 1Q23 | M3: 2Q23 | N3: 3Q23 | O3: 4Q23 | P3: 1Q24 | Q3: 2Q24 | R3: 3Q24 | S3: 4Q24 | T3: 1Q25 | U3: 2Q25 | W3: =K3 -> 4Q22 | X3: =L3 -> 1Q23 | Y3: =M3 -> 2Q23 | Z3: =N3 -> 3Q23 | AA3: =O3 -> 4Q23 | AB3: =P3 -> 1Q24 | AC3: =Q3 -> 2Q24 | AD3: =R3 -> 3Q24 | ... AG3: =U3 -> 2Q25
B4: ($ In Thousands) | C4: 44561 | D4: 44926 | E4: 45291 | F4: 45657 | H4: 44651 | I4: 44742 | J4: 44834 | K4: 44926 | L4: 45016 | M4: 45107 | N4: 45199 | O4: 45291 | P4: 45382 | Q4: 45473 | R4: 45565 | S4: 45657 | T4: 45747 | U4: 45838 | W4: =K4 -> 44926 | X4: =L4 -> 45016 | Y4: =M4 -> 45107 | Z4: =N4 -> 45199 | AA4: =O4 -> 45291 | AB4: =P4 -> 45382 | AC4: =Q4 -> 45473 | AD4: =R4 -> 45565 | ... AG4: =U4 -> 45838
B6: Cash & Cash Equivelants | C6: ='Base Financials'!C35 -> 217502 | D6: ='Base Financials'!D35 -> 149772 | E6: ='Base Financials'!E35 -> 80448 | F6: ='Base Financials'!F35 -> 44937 | H6: ='Base Financials'!H35 -> 198222 | I6: ='Base Financials'!I35 -> 181035 | J6: ='Base Financials'!J35 -> 163731 | K6: ='Base Financials'!K35 -> 149772 | L6: ='Base Financials'!L35 -> 129570 | M6: ='Base Financials'!M35 -> 114604 | N6: ='Base Financials'!N35 -> 99986 | O6: ='Base Financials'!O35 -> 80448 | ... U6: ='Base Financials'!U35 -> 38032 | W6: =K6 -> 149772 | X6: =L6 -> 129570 | Y6: =M6 -> 114604 | Z6: =N6 -> 99986 | AA6: =O6 -> 80448 | AB6: =P6 -> 115505 | AC6: =Q6 -> 93563 | AD6: =R6 -> 20571 | ... AG6: =U6 -> 38032
B7: Total Liquidity (Exclusive of ST Investments) | C7: =SUM(C6:C6) -> 217502 | D7: =SUM(D6:D6) -> 149772 | E7: =SUM(E6:E6) -> 80448 | F7: =SUM(F6:F6) -> 44937 | H7: =SUM(H6:H6) -> 198222 | I7: =SUM(I6:I6) -> 181035 | J7: =SUM(J6:J6) -> 163731 | K7: =SUM(K6:K6) -> 149772 | L7: =SUM(L6:L6) -> 129570 | M7: =SUM(M6:M6) -> 114604 | N7: =SUM(N6:N6) -> 99986 | O7: =SUM(O6:O6) -> 80448 | ... U7: =SUM(U6:U6) -> 38032 | W7: =SUM(W6:W6) -> 149772 | X7: =SUM(X6:X6) -> 129570 | Y7: =SUM(Y6:Y6) -> 114604 | Z7: =SUM(Z6:Z6) -> 99986 | AA7: =SUM(AA6:AA6) -> 80448 | AB7: =SUM(AB6:AB6) -> 115505 | AC7: =SUM(AC6:AC6) -> 93563 | AD7: =SUM(AD6:AD6) -> 20571 | ... AG7: =SUM(AG6:AG6) -> 38032
B9: Cash Burn Rate
B10: CFO | C10: ='Base Financials'!C100 -> -81190 | D10: ='Base Financials'!D100 -> -71129 | E10: ='Base Financials'!E100 -> -73305 | F10: ='Base Financials'!F100 -> -98122 | H10: ='Base Financials'!H100 -> -18797 | I10: ='Base Financials'!I100 -> -16569 | J10: ='Base Financials'!J100 -> -16804 | K10: ='Base Financials'!K100 -> -18548 | L10: ='Base Financials'!L100 -> -18641 | M10: ='Base Financials'!M100 -> -22603 | N10: ='Base Financials'!N100 -> -15910 | O10: ='Base Financials'!O100 -> -16151 | ... U10: ='Base Financials'!U100 -> -26413 | W10: =SUM(H10:K10) -> -70718 | X10: =SUM(I10:L10) -> -70562 | Y10: =SUM(J10:M10) -> -76596 | Z10: =SUM(K10:N10) -> -75702 | AA10: =SUM(L10:O10) -> -73305 | AB10: =SUM(M10:P10) -> -82011 | AC10: =SUM(N10:Q10) -> -80699 | AD10: =SUM(O10:R10) -> -87696 | ... AG10: =SUM(R10:U10) -> -104498
B11: Capex | C11: ='Base Financials'!C103 -> -220 | D11: ='Base Financials'!D103 -> -1048 | E11: ='Base Financials'!E103 -> -2280 | F11: ='Base Financials'!F103 -> -1572 | H11: ='Base Financials'!H103 -> -22 | I11: ='Base Financials'!I103 -> -134 | J11: ='Base Financials'!J103 -> -211 | K11: ='Base Financials'!K103 -> -681 | L11: ='Base Financials'!L103 -> -1152 | M11: ='Base Financials'!M103 -> -485 | N11: ='Base Financials'!N103 -> -493 | O11: ='Base Financials'!O103 -> -150 | ... U11: ='Base Financials'!U103 -> -568 | W11: =SUM(H11:K11) -> -1048 | X11: =SUM(I11:L11) -> -2178 | Y11: =SUM(J11:M11) -> -2529 | Z11: =SUM(K11:N11) -> -2811 | AA11: =SUM(L11:O11) -> -2280 | AB11: =SUM(M11:P11) -> -1519 | AC11: =SUM(N11:Q11) -> -1218 | AD11: =SUM(O11:R11) -> -1659 | ... AG11: =SUM(R11:U11) -> -1793
B12: Total Cash Burn Rate | C12: =+SUM(C10:C11)/12 -> -6784.1667 | D12: =+SUM(D10:D11)/12 -> -6014.75 | E12: =+SUM(E10:E11)/12 -> -6298.75 | F12: =+SUM(F10:F11)/12 -> -8307.8333 | H12: =+SUM(H10:H11)/12 -> -1568.25 | I12: =+SUM(I10:I11)/12 -> -1391.9167 | J12: =+SUM(J10:J11)/12 -> -1417.9167 | K12: =+SUM(K10:K11)/12 -> -1602.4167 | L12: =+SUM(L10:L11)/12 -> -1649.4167 | M12: =+SUM(M10:M11)/12 -> -1924 | N12: =+SUM(N10:N11)/12 -> -1366.9167 | O12: =+SUM(O10:O11)/12 -> -1358.4167 | ... U12: =+SUM(U10:U11)/12 -> -2248.4167 | W12: =+SUM(W10:W11) -> -71766 | X12: =+SUM(X10:X11) -> -72740 | Y12: =+SUM(Y10:Y11) -> -79125 | Z12: =+SUM(Z10:Z11) -> -78513 | AA12: =+SUM(AA10:AA11) -> -75585 | AB12: =+SUM(AB10:AB11) -> -83530 | AC12: =+SUM(AC10:AC11)/12 -> -6826.4167 | AD12: =+SUM(AD10:AD11)/12 -> -7446.25 | AE12: =+SUM(AE10:AE11)/12 -> -8307.8333 | AF12: =+SUM(AF10:AF11)/12 -> -8398.75 | AG12: =+SUM(AG10:AG11)/12 -> -8857.5833
B14: Cash Runway
B15: Total Liquidity | C15: =C7 -> 217502 | D15: =D7 -> 149772 | E15: =E7 -> 80448 | F15: =F7 -> 44937 | H15: =H7 -> 198222 | I15: =I7 -> 181035 | J15: =J7 -> 163731 | K15: =K7 -> 149772 | L15: =L7 -> 129570 | M15: =M7 -> 114604 | N15: =N7 -> 99986 | O15: =O7 -> 80448 | ... U15: =U7 -> 38032 | W15: =W7 -> 149772 | X15: =X7 -> 129570 | Y15: =Y7 -> 114604 | Z15: =Z7 -> 99986 | AA15: =AA7 -> 80448 | AB15: =AB7 -> 115505 | AC15: =AC7 -> 93563 | AD15: =AD7 -> 20571 | ... AG15: =AG7 -> 38032
B16: Monthly Cash Burn Rate | C16: =C12 -> -6784.1667 | D16: =D12 -> -6014.75 | E16: =E12 -> -6298.75 | F16: =F12 -> -8307.8333 | H16: =H12 -> -1568.25 | I16: =I12 -> -1391.9167 | J16: =J12 -> -1417.9167 | K16: =K12 -> -1602.4167 | L16: =L12 -> -1649.4167 | M16: =M12 -> -1924 | N16: =N12 -> -1366.9167 | O16: =O12 -> -1358.4167 | ... U16: =U12 -> -2248.4167 | W16: =W12 -> -71766 | X16: =X12 -> -72740 | Y16: =Y12 -> -79125 | Z16: =Z12 -> -78513 | AA16: =AA12 -> -75585 | AB16: =AB12 -> -83530 | AC16: =AC12 -> -6826.4167 | AD16: =AD12 -> -7446.25 | ... AG16: =AG12 -> -8857.5833
B17: Cash Runway | C17: =C15/-C16 -> 32.060238 | D17: =D15/-D16 -> 24.900786 | E17: =E15/-E16 -> 12.772058 | F17: =F15/-F16 -> 5.4089915 | H17: =H15/-H16 -> 126.39694 | I17: =I15/-I16 -> 130.06167 | J17: =J15/-J16 -> 115.47294 | K17: =K15/-K16 -> 93.466327 | L17: =L15/-L16 -> 78.555045 | M17: =M15/-M16 -> 59.565489 | N17: =N15/-N16 -> 73.147107 | O17: =O15/-O16 -> 59.221888 | ... U17: =U15/-U16 -> 16.915014 | W17: =W15/-W16 -> 2.0869493 | X17: =X15/-X16 -> 1.7812758 | Y17: =Y15/-Y16 -> 1.4483918 | Z17: =Z15/-Z16 -> 1.2734961 | AA17: =AA15/-AA16 -> 1.0643382 | AB17: =AB15/-AB16 -> 1.3827966 | AC17: =AC15/-AC16 -> 13.70602 | AD17: =AD15/-AD16 -> 2.7625986 | ... AG17: =AG15/-AG16 -> 4.293722
B19: Cash Per Shares Outstanding, Diluted
B20: Weighted-average shares outstanding, Diluted | C20: ='Base Financials'!C27 -> 39970.398 | D20: ='Base Financials'!D27 -> 103051.37 | E20: ='Base Financials'!E27 -> 103420.24 | F20: ='Base Financials'!F27 -> 118479.1 | H20: ='Base Financials'!H27 -> 103004.09 | I20: ='Base Financials'!I27 -> 103908.44 | J20: ='Base Financials'!J27 -> 103031.98 | K20: ='Base Financials'!K27 -> 103051.37 | L20: ='Base Financials'!L27 -> 103263.53 | M20: ='Base Financials'!M27 -> 103361.5 | N20: ='Base Financials'!N27 -> 103444.25 | O20: ='Base Financials'!O27 -> 103420.24 | ... U20: ='Base Financials'!U27 -> 155437.28 | W20: =K20 -> 103051.37 | X20: =L20 -> 103263.53 | Y20: =M20 -> 103361.5 | Z20: =N20 -> 103444.25 | AA20: =O20 -> 103420.24 | AB20: =P20 -> 108246.01 | AC20: =Q20 -> 119174.68 | AD20: =R20 -> 119408.57 | ... AG20: =U20 -> 155437.28
B21: Cash Per Share | C21: =C6/C20 -> 5.441577 | D21: =D6/D20 -> 1.4533723 | E21: =E6/E20 -> 0.77787483 | F21: =F6/F20 -> 0.37928209 | H21: =H6/H20 -> 1.9244091 | I21: =I6/I20 -> 1.742255 | J21: =J6/J20 -> 1.589128 | K21: =K6/K20 -> 1.4533723 | L21: =L6/L20 -> 1.2547509 | M21: =M6/M20 -> 1.1087687 | N21: =N6/N20 -> 0.96656899 | O21: =O6/O20 -> 0.77787483 | ... U21: =U6/U20 -> 0.24467747 | W21: =W6/W20 -> 1.4533723 | X21: =X6/X20 -> 1.2547509 | Y21: =Y6/Y20 -> 1.1087687 | Z21: =Z6/Z20 -> 0.96656899 | AA21: =AA6/AA20 -> 0.77787483 | AB21: =AB6/AB20 -> 1.0670601 | AC21: =AC6/AC20 -> 0.78509126 | AD21: =AD6/AD20 -> 0.17227407 | ... AG21: =AG6/AG20 -> 0.24467747
