Workbook

Sheet Historical Financials
B2: ADMA Biologics Inc (NASDAQ: ADMA)
B3: Historical Financials
B4: $ in thousands except per share
A6: X | B6: Income Statement | C6: FYE | G6: Quarterly | Q6: Quarterly | AB6: LTM | AH6: Variance
B7: Fiscal Period | C7: 2021 | D7: 2022 | E7: 2023 | G7: 1Q22 | H7: 2Q22 | I7: 3Q22 | J7: 4Q22 | K7: 1Q23 | L7: 2Q23 | M7: 3Q23 | N7: 4Q23 | O7: 1Q24 | P7: 2Q24 | Q7: 3Q24 | R7: 4Q24 | S7: 1Q25 | T7: 2Q25 | V7: =J7 -> 4Q22 | W7: =K7 -> 1Q23 | X7: =L7 -> 2Q23 | Y7: =M7 -> 3Q23 | Z7: =N7 -> 4Q23 | AA7: =O7 -> 1Q24 | AB7: =P7 -> 2Q24 | AC7: =Q7 -> 3Q24 | ... AF7: =T7 -> 2Q25
B8: Fiscal Period End Date | C8: 44561 | D8: 44926 | E8: 45291 | G8: 44651 | H8: 44742 | I8: 44834 | J8: 44926 | K8: 45016 | L8: 45107 | M8: 45199 | N8: 45291 | O8: 45382 | P8: 45473 | Q8: 45565 | R8: 45657 | S8: 45747 | T8: 45838 | V8: =J8 -> 44926 | W8: =K8 -> 45016 | X8: =L8 -> 45107 | Y8: =M8 -> 45199 | Z8: =N8 -> 45291 | AA8: =O8 -> 45382 | AB8: =P8 -> 45473 | AC8: =Q8 -> 45565 | ... AF8: =T8 -> 45838
B10: Consolidated Revenue | C10: 80943 | D10: 154080 | E10: 258215 | G10: 29103.093 | H10: 33905.007 | I10: 41090.137 | J10: =SUM(D10-SUM(G10:I10)) -> 49981.763 | K10: 56913.534 | L10: 60123.191 | M10: 67274.598 | N10: =SUM(E10-SUM(K10:M10)) -> 73903.677 | O10: 81875 | P10: 107191 | R10: =SUM(E10-SUM(O10:Q10)) -> 69149 | V10: =SUM(G10:J10) -> 154080 | W10: =SUM(H10:K10) -> 181890.44 | X10: =SUM(I10:L10) -> 208108.62 | Y10: =SUM(J10:M10) -> 234293.09 | Z10: =SUM(K10:N10) -> 258215 | AA10: =SUM(L10:O10) -> 283176.47 | AB10: =SUM(M10:P10) -> 330244.28 | AC10: =SUM(N10:Q10) -> 262969.68 | ... AF10: =SUM(Q10:T10) -> 69149 | AH10: =SUM(AF10/AB10)-1 -> -0.79061257
B11: Total Revenue | C11: =+SUM(C10:C10) -> 80943 | D11: =+SUM(D10:D10) -> 154080 | E11: =+SUM(E10:E10) -> 258215 | G11: =+SUM(G10:G10) -> 29103.093 | H11: =+SUM(H10:H10) -> 33905.007 | I11: =+SUM(I10:I10) -> 41090.137 | J11: =+SUM(J10:J10) -> 49981.763 | K11: =+SUM(K10:K10) -> 56913.534 | L11: =+SUM(L10:L10) -> 60123.191 | M11: =+SUM(M10:M10) -> 67274.598 | N11: =+SUM(N10:N10) -> 73903.677 | ... T11: =+SUM(T10:T10) -> 0 | V11: =+SUM(V10:V10) -> 154080 | W11: =+SUM(W10:W10) -> 181890.44 | X11: =+SUM(X10:X10) -> 208108.62 | Y11: =+SUM(Y10:Y10) -> 234293.09 | Z11: =+SUM(Z10:Z10) -> 258215 | AA11: =+SUM(AA10:AA10) -> 283176.47 | AB11: =+SUM(AB10:AB10) -> 330244.28 | AC11: =+SUM(AC10:AC10) -> 262969.68 | ... AF11: =+SUM(AF10:AF10) -> 69149 | AH11: =SUM(AF11/AB11)-1 -> -0.79061257
B13: Cost of Sales | C13: -79770 | D13: -118815 | E13: -169273 | G13: -25441.046 | H13: -26135.614 | I13: -31433.496 | J13: =SUM(D13-SUM(G13:I13)) -> -35804.844 | K13: -40400.544 | L13: -43433.188 | M13: -42622.013 | N13: =SUM(E13-SUM(K13:M13)) -> -42817.255 | O13: -42767 | P13: -49738 | R13: =SUM(E13-SUM(O13:Q13)) -> -76768 | V13: =SUM(H13:K13) -> -133774.5 | W13: =SUM(I13:L13) -> -151072.07 | X13: =SUM(J13:M13) -> -162260.59 | Y13: =SUM(K13:N13) -> -169273 | Z13: =SUM(L13:O13) -> -171639.46 | AA13: =SUM(M13:P13) -> -177944.27 | AB13: =SUM(M13:P13) -> -177944.27 | AC13: =SUM(N13:Q13) -> -135322.26 | AD13: =SUM(O13:R13) -> -169273 | AE13: =SUM(P13:S13) -> -126506 | AF13: =SUM(Q13:T13) -> -76768 | AH13: =SUM(AF13/AB13)-1 -> -0.56858402
B14: Gross Profit | C14: =+SUM(C11+SUM(C13:C13)) -> 1173 | D14: =+SUM(D11+SUM(D13:D13)) -> 35265 | E14: =+SUM(E11+SUM(E13:E13)) -> 88942 | G14: =+SUM(G11+SUM(G13:G13)) -> 3662.047 | H14: =+SUM(H11+SUM(H13:H13)) -> 7769.393 | I14: =+SUM(I11+SUM(I13:I13)) -> 9656.641 | J14: =+SUM(J11+SUM(J13:J13)) -> 14176.919 | K14: =+SUM(K11+SUM(K13:K13)) -> 16512.99 | L14: =+SUM(L11+SUM(L13:L13)) -> 16690.003 | M14: =+SUM(M11+SUM(M13:M13)) -> 24652.585 | N14: =+SUM(N11+SUM(N13:N13)) -> 31086.422 | ... T14: =+SUM(T11+SUM(T13:T13)) -> 0 | V14: =+SUM(V11+SUM(V13:V13)) -> 20305.502 | W14: =+SUM(W11+SUM(W13:W13)) -> 30818.369 | X14: =+SUM(X11+SUM(X13:X13)) -> 45848.036 | Y14: =+SUM(Y11+SUM(Y13:Y13)) -> 65020.086 | Z14: =+SUM(Z11+SUM(Z13:Z13)) -> 86575.544 | AA14: =+SUM(AA11+SUM(AA13:AA13)) -> 105232.2 | AB14: =+SUM(AB11+SUM(AB13:AB13)) -> 152300.01 | AC14: =+SUM(AC11+SUM(AC13:AC13)) -> 127647.42 | ... AF14: =+SUM(AF11+SUM(AF13:AF13)) -> -7619 | AH14: =SUM(AF14/AB14)-1 -> -1.0500263
B15: Gross Margin (%) | C15: =C14/C11 -> 0.014491679 | D15: =D14/D11 -> 0.22887461 | E15: =E14/E11 -> 0.34444939 | G15: =G14/G11 -> 0.12583017 | H15: =H14/H11 -> 0.22915179 | I15: =I14/I11 -> 0.23501117 | J15: =J14/J11 -> 0.28364184 | K15: =K14/K11 -> 0.29014171 | L15: =L14/L11 -> 0.27759676 | M15: =M14/M11 -> 0.36644715 | N15: =N14/N11 -> 0.42063431 | ... T15: =T14/T11 -> #DIV/0! | V15: =V14/V11 -> 0.13178545 | W15: =W14/W11 -> 0.16943369 | X15: =X14/X11 -> 0.2203082 | Y15: =Y14/Y11 -> 0.27751603 | Z15: =Z14/Z11 -> 0.33528472 | AA15: =AA14/AA11 -> 0.3716135 | AB15: =AB14/AB11 -> 0.4611738 | AC15: =AC14/AC11 -> 0.48540738 | ... AF15: =AF14/AF11 -> -0.11018236 | AH15: =SUM(AF15-AB15)*1000 -> -571.35616
B17: Research and development | C17: -3646 | D17: -3614 | E17: -3300 | G17: -624.111 | H17: -873.386 | I17: -1041.947 | J17: =SUM(D17-SUM(G17:I17)) -> -1074.556 | K17: -855.351 | L17: -1403.26 | M17: -595.903 | N17: =SUM(E17-SUM(K17:M17)) -> -445.486 | O17: -450 | P17: -560 | R17: =SUM(E17-SUM(O17:Q17)) -> -2290 | V17: =SUM(H17:K17) -> -3845.24 | W17: =SUM(I17:L17) -> -4375.114 | X17: =SUM(J17:M17) -> -3929.07 | Y17: =SUM(K17:N17) -> -3300 | Z17: =SUM(L17:O17) -> -2894.649 | AA17: =SUM(M17:P17) -> -2051.389 | AB17: =SUM(M17:P17) -> -2051.389 | AC17: =SUM(N17:Q17) -> -1455.486 | AD17: =SUM(O17:R17) -> -3300 | AE17: =SUM(P17:S17) -> -2850 | AF17: =SUM(Q17:T17) -> -2290 | AH17: =SUM(AF17/AB17)-1 -> 0.1163168
B18: Plasma center operating expenses | C18: -12289 | D18: -17843 | E18: -4266 | G18: -3974.589 | H18: -3921.486 | I18: -4859.45 | J18: =SUM(D18-SUM(G18:I18)) -> -5087.475 | K18: -1780.463 | L18: -1333.424 | M18: -466.898 | N18: =SUM(E18-SUM(K18:M18)) -> -685.215 | O18: -1005 | P18: -942 | R18: =SUM(E18-SUM(O18:Q18)) -> -2319
B19: Amortization of intangible assets | C19: -715 | D19: -715 | E19: -724 | G19: -178.838 | H19: -178.838 | I19: -178.838 | J19: =SUM(D19-SUM(G19:I19)) -> -178.486 | K19: -178.838 | L19: -178.838 | M19: -178.838 | N19: =SUM(E19-SUM(K19:M19)) -> -187.486 | O19: -193 | P19: -142 | R19: =SUM(E19-SUM(O19:Q19)) -> -389 | V19: =SUM(H19:K19) -> -715 | W19: =SUM(I19:L19) -> -715 | X19: =SUM(J19:M19) -> -715 | Y19: =SUM(K19:N19) -> -724 | Z19: =SUM(L19:O19) -> -738.162 | AA19: =SUM(M19:P19) -> -701.324 | AB19: =SUM(M19:P19) -> -701.324 | AC19: =SUM(N19:Q19) -> -522.486 | AD19: =SUM(O19:R19) -> -724 | AE19: =SUM(P19:S19) -> -531 | AF19: =SUM(Q19:T19) -> -389 | AH19: =SUM(AF19/AB19)-1 -> -0.44533482
B20: Selling, general and administrative | C20: -42897 | D20: -52458 | E20: -59020 | G20: -13699.575 | H20: -11970.422 | I20: -12893.139 | J20: =SUM(D20-SUM(G20:I20)) -> -13894.864 | K20: -14511.656 | L20: -14247.558 | M20: -14725.787 | N20: =SUM(E20-SUM(K20:M20)) -> -15534.999 | O20: -15639 | P20: -16608 | R20: =SUM(E20-SUM(O20:Q20)) -> -26773 | V20: =SUM(H20:K20) -> -53270.081 | W20: =SUM(I20:L20) -> -55547.217 | X20: =SUM(J20:M20) -> -57379.865 | Y20: =SUM(K20:N20) -> -59020 | Z20: =SUM(L20:O20) -> -60147.344 | AA20: =SUM(M20:P20) -> -62507.786 | AB20: =SUM(M20:P20) -> -62507.786 | AC20: =SUM(N20:Q20) -> -47781.999 | AD20: =SUM(O20:R20) -> -59020 | AE20: =SUM(P20:S20) -> -43381 | AF20: =SUM(Q20:T20) -> -26773 | AH20: =SUM(AF20/AB20)-1 -> -0.57168536
B21: Operating Profit | C21: =+SUM(C14+SUM(C17:C20)) -> -58374 | D21: =+SUM(D14+SUM(D17:D20)) -> -39365 | E21: =+SUM(E14+SUM(E17:E20)) -> 21632 | G21: =+SUM(G14+SUM(G17:G20)) -> -14815.066 | H21: =+SUM(H14+SUM(H17:H20)) -> -9174.739 | I21: =+SUM(I14+SUM(I17:I20)) -> -9316.733 | J21: =+SUM(J14+SUM(J17:J20)) -> -6058.462 | K21: =+SUM(K14+SUM(K17:K20)) -> -813.318 | L21: =+SUM(L14+SUM(L17:L20)) -> -473.077 | M21: =+SUM(M14+SUM(M17:M20)) -> 8685.159 | N21: =+SUM(N14+SUM(N17:N20)) -> 14233.236 | ... T21: =+SUM(T14+SUM(T17:T20)) -> 0 | V21: =+SUM(V14+SUM(V17:V20)) -> -37524.819 | W21: =+SUM(W14+SUM(W17:W20)) -> -29818.962 | X21: =+SUM(X14+SUM(X17:X20)) -> -16175.899 | Y21: =+SUM(Y14+SUM(Y17:Y20)) -> 1976.086 | Z21: =+SUM(Z14+SUM(Z17:Z20)) -> 22795.389 | AA21: =+SUM(AA14+SUM(AA17:AA20)) -> 39971.699 | AB21: =+SUM(AB14+SUM(AB17:AB20)) -> 87039.508 | AC21: =+SUM(AC14+SUM(AC17:AC20)) -> 77887.451 | ... AF21: =+SUM(AF14+SUM(AF17:AF20)) -> -37071 | AH21: =SUM(AF21/AB21)-1 -> -1.42591
B22: Operating Margin (%) | C22: =C21/C11 -> -0.72117416 | D22: =D21/D11 -> -0.25548416 | E22: =E21/E11 -> 0.083775149 | G22: =G21/G11 -> -0.50905469 | H22: =H21/H11 -> -0.2706013 | I22: =I21/I11 -> -0.22673891 | J22: =J21/J11 -> -0.12121345 | K22: =K21/K11 -> -0.014290415 | L22: =L21/L11 -> -0.0078684613 | M22: =M21/M11 -> 0.12910012 | N22: =N21/N11 -> 0.19259172 | ... T22: =T21/T11 -> #DIV/0! | V22: =V21/V11 -> -0.24354114 | W22: =W21/W11 -> -0.16393914 | X22: =X21/X11 -> -0.077728153 | Y22: =Y21/Y11 -> 0.008434248 | Z22: =Z21/Z11 -> 0.088280654 | AA22: =AA21/AA11 -> 0.14115473 | AB22: =AB21/AB11 -> 0.26356099 | AC22: =AC21/AC11 -> 0.29618415 | ... AF22: =AF21/AF11 -> -0.5361032 | AH22: =SUM(AF22-AB22)*1000 -> -799.66419
B24: Interest income | C24: 35 | D24: 45 | E24: 1617 | G24: 33.068 | H24: 2.269 | I24: 7.236 | J24: =SUM(D24-SUM(G24:I24)) -> 2.427 | K24: 166.971 | L24: 414.304 | M24: 423.276 | N24: =SUM(E24-SUM(K24:M24)) -> 612.449 | O24: 384 | P24: 449 | R24: =SUM(E24-SUM(O24:Q24)) -> 784 | V24: =SUM(H24:K24) -> 178.903 | W24: =SUM(I24:L24) -> 590.938 | X24: =SUM(J24:M24) -> 1006.978 | Y24: =SUM(K24:N24) -> 1617 | Z24: =SUM(L24:O24) -> 1834.029 | AA24: =SUM(M24:P24) -> 1868.725 | AB24: =SUM(M24:P24) -> 1868.725 | AC24: =SUM(N24:Q24) -> 1445.449 | AD24: =SUM(O24:R24) -> 1617 | AE24: =SUM(P24:S24) -> 1233 | AF24: =SUM(Q24:T24) -> 784 | AH24: =SUM(AF24/AB24)-1 -> -0.58046261
B25: Interest expense | C25: -13057 | D25: -19279 | E25: -25027 | G25: -3389.038 | H25: -4573.015 | I25: -5580.366 | J25: =SUM(D25-SUM(G25:I25)) -> -5736.581 | K25: -6115.484 | L25: -6299.107 | M25: -6397.553 | N25: =SUM(E25-SUM(K25:M25)) -> -6214.856 | O25: -3769 | P25: -3783 | R25: =SUM(E25-SUM(O25:Q25)) -> -17475 | AB25: =SUM(M25:P25) -> -20164.409 | AC25: =SUM(N25:Q25) -> -13766.856 | AD25: =SUM(O25:R25) -> -25027 | AE25: =SUM(P25:S25) -> -21258 | AF25: =SUM(Q25:T25) -> -17475 | AH25: =SUM(AF25/AB25)-1 -> -0.13337406
B26: Loss on extinguishment of debt | C26: 0 | D26: -6670 | E26: -26174 | G26: -6669.941 | H26: - | I26: - | J26: =SUM(D26-SUM(G26:I26)) -> -0.059 | K26: - | L26: - | N26: =SUM(E26-SUM(K26:M26)) -> -26174 | R26: =SUM(E26-SUM(O26:Q26)) -> -26174 | AB26: =SUM(M26:P26) -> -26174 | AC26: =SUM(N26:Q26) -> -26174 | AD26: =SUM(O26:R26) -> -26174 | AE26: =SUM(P26:S26) -> -26174 | AF26: =SUM(Q26:T26) -> -26174 | AH26: =SUM(AF26/AB26)-1 -> 0
B27: Other expense | C27: -252 | D27: -635 | E27: -287 | G27: -166.88 | H27: -19.421 | I27: -9.641 | J27: =SUM(D27-SUM(G27:I27)) -> -439.058 | K27: -26.984 | L27: -12.827 | M27: -145.827 | N27: =SUM(E27-SUM(K27:M27)) -> -101.362 | R27: =SUM(E27-SUM(O27:Q27)) -> -287 | AB27: =SUM(M27:P27) -> -247.189 | AC27: =SUM(N27:Q27) -> -101.362 | AD27: =SUM(O27:R27) -> -287 | AE27: =SUM(P27:S27) -> -287 | AF27: =SUM(Q27:T27) -> -287 | AH27: =SUM(AF27/AB27)-1 -> 0.1610549
B28: Earning Before Taxes | C28: =SUM(C21+SUM(C24:C27)) -> -71648 | D28: =SUM(D21+SUM(D24:D27)) -> -65904 | E28: =SUM(E21+SUM(E24:E27)) -> -28239 | G28: =SUM(G21+SUM(G24:G27)) -> -25007.857 | H28: =SUM(H21+SUM(H24:H27)) -> -13764.906 | I28: =SUM(I21+SUM(I24:I27)) -> -14899.504 | J28: =SUM(J21+SUM(J24:J27)) -> -12231.733 | K28: =SUM(K21+SUM(K24:K27)) -> -6788.815 | L28: =SUM(L21+SUM(L24:L27)) -> -6370.707 | M28: =SUM(M21+SUM(M24:M27)) -> 2565.055 | N28: =SUM(N21+SUM(N24:N27)) -> -17644.533 | ... T28: =SUM(T21+SUM(T24:T27)) -> 0 | V28: =SUM(V21+SUM(V24:V27)) -> -37345.916 | W28: =SUM(W21+SUM(W24:W27)) -> -29228.024 | X28: =SUM(X21+SUM(X24:X27)) -> -15168.921 | Y28: =SUM(Y21+SUM(Y24:Y27)) -> 3593.086 | Z28: =SUM(Z21+SUM(Z24:Z27)) -> 24629.418 | AA28: =SUM(AA21+SUM(AA24:AA27)) -> 41840.424 | AB28: =SUM(AB21+SUM(AB24:AB27)) -> 42322.635 | AC28: =SUM(AC21+SUM(AC24:AC27)) -> 39290.682 | ... AF28: =SUM(AF21+SUM(AF24:AF27)) -> -80223 | AH28: =SUM(AF28/AB28)-1 -> -2.8955105
B29: EBT Margin (%) | C29: =C28/C11 -> -0.8851661 | D29: =D28/D11 -> -0.42772586 | E29: =E28/E11 -> -0.10936235 | G29: =G28/G11 -> -0.8592852 | H29: =H28/H11 -> -0.40598446 | I29: =I28/I11 -> -0.36260536 | J29: =J28/J11 -> -0.24472392 | K29: =K28/K11 -> -0.11928296 | L29: =L28/L11 -> -0.10596089 | M29: =M28/M11 -> 0.038128136 | N29: =N28/N11 -> -0.23875041 | ... T29: =T28/T11 -> #DIV/0! | V29: =V28/V11 -> -0.24238004 | W29: =W28/W11 -> -0.16069027 | X29: =X28/X11 -> -0.072889439 | Y29: =Y28/Y11 -> 0.01533586 | Z29: =Z28/Z11 -> 0.095383374 | AA29: =AA28/AA11 -> 0.14775389 | AB29: =AB28/AB11 -> 0.12815554 | AC29: =AC28/AC11 -> 0.14941145 | ... AF29: =AF28/AF11 -> -1.1601469 | AH29: =SUM(AF29-AB29)*1000 -> -1288.3025
B31: Provision for taxes | C31: 0 | D31: 0 | E31: 0 | G31: 0 | H31: 0 | I31: 0 | J31: =SUM(D31-SUM(G31:I31)) -> 0 | K31: 0 | L31: 0 | M31: 0 | N31: =SUM(E31-SUM(K31:M31)) -> 0 | O31: -595 | P31: -3789 | R31: =SUM(E31-SUM(O31:Q31)) -> 4384 | S31: 0 | V31: =SUM(H31:K31) -> 0 | W31: =SUM(I31:L31) -> 0 | X31: =SUM(J31:M31) -> 0 | Y31: =SUM(K31:N31) -> 0 | Z31: =SUM(L31:O31) -> -595 | AA31: =SUM(M31:P31) -> -4384 | AB31: =SUM(M31:P31) -> -4384 | AC31: =SUM(N31:Q31) -> -4384 | AD31: =SUM(O31:R31) -> 0 | AE31: =SUM(P31:S31) -> 595 | AF31: =SUM(Q31:T31) -> 4384 | AH31: =SUM(AF31/AB31)-1 -> -2
B32: Net loss | C32: =SUM(C28+C31) -> -71648 | D32: =SUM(D28+D31) -> -65904 | E32: =SUM(E28+E31) -> -28239 | G32: =SUM(G28+G31) -> -25007.857 | H32: =SUM(H28+H31) -> -13764.906 | I32: =SUM(I28+I31) -> -14899.504 | J32: =SUM(J28+J31) -> -12231.733 | K32: =SUM(K28+K31) -> -6788.815 | L32: =SUM(L28+L31) -> -6370.707 | M32: =SUM(M28+M31) -> 2565.055 | N32: =SUM(N28+N31) -> -17644.533 | ... T32: =SUM(T28+T31) -> 0 | V32: =SUM(V28+V31) -> -37345.916 | W32: =SUM(W28+W31) -> -29228.024 | X32: =SUM(X28+X31) -> -15168.921 | Y32: =SUM(Y28+Y31) -> 3593.086 | Z32: =SUM(Z28+Z31) -> 24034.418 | AA32: =SUM(AA28+AA31) -> 37456.424 | AB32: =SUM(AB28+AB31) -> 37938.635 | AC32: =SUM(AC28+AC31) -> 34906.682 | ... AF32: =SUM(AF28+AF31) -> -75839 | AH32: =SUM(AF32/AB32)-1 -> -2.9989913
B33: Net Margin (%) | C33: =C32/C11 -> -0.8851661 | D33: =D32/D11 -> -0.42772586 | E33: =E32/E11 -> -0.10936235 | G33: =G32/G11 -> -0.8592852 | H33: =H32/H11 -> -0.40598446 | I33: =I32/I11 -> -0.36260536 | J33: =J32/J11 -> -0.24472392 | K33: =K32/K11 -> -0.11928296 | L33: =L32/L11 -> -0.10596089 | M33: =M32/M11 -> 0.038128136 | N33: =N32/N11 -> -0.23875041 | ... T33: =T32/T11 -> #DIV/0! | V33: =V32/V11 -> -0.24238004 | W33: =W32/W11 -> -0.16069027 | X33: =X32/X11 -> -0.072889439 | Y33: =Y32/Y11 -> 0.01533586 | Z33: =Z32/Z11 -> 0.093079093 | AA33: =AA32/AA11 -> 0.13227238 | AB33: =AB32/AB11 -> 0.11488052 | AC33: =AC32/AC11 -> 0.13274033 | ... AF33: =AF32/AF11 -> -1.0967476 | AH33: =SUM(AF33-AB33)*1000 -> -1211.6281
B35: Basic shares | J35: =D35 -> 0 | N35: =E35 -> 0 | R35: =E35 -> 0 | V35: =J35 -> 0 | W35: =K35 -> 0 | X35: =L35 -> 0 | Y35: =M35 -> 0 | Z35: =N35 -> 0 | AA35: =O35 -> 0 | AB35: =P35 -> 0 | AC35: =Q35 -> 0 | ... AF35: =T35 -> 0 | AH35: =SUM(AF35/AB35)-1 -> #DIV/0!
B36: Basic EPS | C36: =C32/C35 -> #DIV/0! | D36: =D32/D35 -> #DIV/0! | E36: =E32/E35 -> #DIV/0! | G36: =G32/G35 -> #DIV/0! | H36: =H32/H35 -> #DIV/0! | I36: =I32/I35 -> #DIV/0! | J36: =J32/J35 -> #DIV/0! | K36: =K32/K35 -> #DIV/0! | L36: =L32/L35 -> #DIV/0! | M36: =M32/M35 -> #DIV/0! | N36: =N32/N35 -> #DIV/0! | ... T36: =T32/T35 -> #DIV/0! | V36: =V32/V35 -> #DIV/0! | W36: =W32/W35 -> #DIV/0! | X36: =X32/X35 -> #DIV/0! | Y36: =Y32/Y35 -> #DIV/0! | Z36: =Z32/Z35 -> #DIV/0! | AA36: =AA32/AA35 -> #DIV/0! | AB36: =AB32/AB35 -> #DIV/0! | AC36: =AC32/AC35 -> #DIV/0! | ... AF36: =AF32/AF35 -> #DIV/0! | AH36: =SUM(AF36/AB36)-1 -> #DIV/0!
B38: Fully Diluted Shares | C38: 139578.54 | D38: 197874.89 | E38: 223977.32 | G38: 195871.93 | H38: 196353.18 | I38: 196383.93 | J38: =D38 -> 197874.89 | K38: 221921.75 | L38: 222683.39 | M38: 233761.26 | N38: =E38 -> 223977.32 | O38: 236414.37 | P38: 242167.07 | Q38: 1000 | R38: =E38 -> 223977.32 | V38: =K38 -> 221921.75 | W38: =L38 -> 222683.39 | X38: =M38 -> 233761.26 | Y38: =N38 -> 223977.32 | Z38: =O38 -> 236414.37 | AA38: =P38 -> 242167.07 | AB38: =P38 -> 242167.07 | AC38: =Q38 -> 1000 | AD38: =R38 -> 223977.32 | AE38: =S38 -> 0 | AF38: =T38 -> 0 | AH38: =SUM(AF38/AB38)-1 -> -1
B39: Diluted EPS | C39: =C32/C38 -> -0.51331674 | D39: =D32/D38 -> -0.33305893 | E39: =E32/E38 -> -0.12607973 | G39: =G32/G38 -> -0.12767453 | H39: =H32/H38 -> -0.07010279 | I39: =I32/I38 -> -0.075869261 | J39: =J32/J38 -> -0.061815487 | K39: =K32/K38 -> -0.03059103 | L39: =L32/L38 -> -0.028608811 | M39: =M32/M38 -> 0.010972969 | N39: =N32/N38 -> -0.078778215 | ... T39: =T32/T38 -> #DIV/0! | V39: =V32/V38 -> -0.16828416 | W39: =W32/W38 -> -0.13125372 | X39: =X32/X38 -> -0.064890653 | Y39: =Y32/Y38 -> 0.016042187 | Z39: =Z32/Z38 -> 0.10166225 | AA39: =AA32/AA38 -> 0.15467183 | AB39: =AB32/AB38 -> 0.15666306 | AC39: =AC32/AC38 -> 34.906682 | ... AF39: =AF32/AF38 -> #DIV/0! | AH39: =SUM(AF39/AB39)-1 -> #DIV/0!
A41: X | B41: Balance Sheet | C41: FYE | G41: Quarterly | Q41: Quarterly | AB41: LTM | AH41: Variance
B42: =B7 -> Fiscal Period | C42: =C7 -> 2021 | D42: =D7 -> 2022 | E42: =E7 -> 2023 | G42: =G7 -> 1Q22 | H42: =H7 -> 2Q22 | I42: =I7 -> 3Q22 | J42: =J7 -> 4Q22 | K42: =K7 -> 1Q23 | L42: =L7 -> 2Q23 | M42: =M7 -> 3Q23 | N42: =N7 -> 4Q23 | ... T42: =T7 -> 2Q25 | V42: =V7 -> 4Q22 | W42: =W7 -> 1Q23 | X42: =X7 -> 2Q23 | Y42: =Y7 -> 3Q23 | Z42: =Z7 -> 4Q23 | AA42: =AA7 -> 1Q24 | AB42: =AB7 -> 2Q24 | AC42: =AC7 -> 3Q24 | ... AF42: =AF7 -> 2Q25
B43: =B8 -> Fiscal Period End Date | C43: =C8 -> 44561 | D43: =D8 -> 44926 | E43: =E8 -> 45291 | G43: =G8 -> 44651 | H43: =H8 -> 44742 | I43: =I8 -> 44834 | J43: =J8 -> 44926 | K43: =K8 -> 45016 | L43: =L8 -> 45107 | M43: =M8 -> 45199 | N43: =N8 -> 45291 | ... T43: =T8 -> 45838 | V43: =V8 -> 44926 | W43: =W8 -> 45016 | X43: =X8 -> 45107 | Y43: =Y8 -> 45199 | Z43: =Z8 -> 45291 | AA43: =AA8 -> 45382 | AB43: =AB8 -> 45473 | AC43: =AC8 -> 45565 | ... AF43: =AF8 -> 45838
B45: Current Assets
B46: Cash and cash equivalents | D46: 86522 | E46: 51352 | G46: 69504.946 | H46: 52415.053 | I46: 34906.02 | J46: =D46 -> 86522 | K46: 69204.163 | L46: 62512.889 | M46: 74156.765 | N46: =E46 -> 51352 | O46: 45325 | P46: 88244 | R46: =E46 -> 51352 | V46: =J46 -> 86522 | W46: =K46 -> 69204.163 | X46: =L46 -> 62512.889 | Y46: =M46 -> 74156.765 | Z46: =N46 -> 51352 | AA46: =O46 -> 45325 | AB46: =P46 -> 88244 | AC46: =Q46 -> 0 | ... AF46: =T46 -> 0 | AH46: =SUM(AF46/AB46)-1 -> -1
B47: Accounts receivable, net | D47: 15505 | E47: 27421 | G47: 25629.625 | H47: 18883.847 | I47: 20902.385 | J47: =D47 -> 15505 | K47: 26518.495 | L47: 36731.612 | M47: 31318.68 | N47: =E47 -> 27421 | O47: 49621 | P47: 30113 | R47: =E47 -> 27421 | V47: =J47 -> 15505 | W47: =K47 -> 26518.495 | X47: =L47 -> 36731.612 | Y47: =M47 -> 31318.68 | Z47: =N47 -> 27421 | AA47: =O47 -> 49621 | AB47: =P47 -> 30113 | AC47: =Q47 -> 0 | ... AF47: =T47 -> 0 | AH47: =SUM(AF47/AB47)-1 -> -1
B48: Inventories | D48: 163280 | E48: 172906 | G48: 139146.31 | H48: 146075.46 | I48: 162913.63 | J48: =D48 -> 163280 | K48: 163984.87 | L48: 161780.06 | M48: 163116.11 | N48: =E48 -> 172906 | O48: 177732 | P48: 179810 | R48: =E48 -> 172906 | V48: =J48 -> 163280 | W48: =K48 -> 163984.87 | X48: =L48 -> 161780.06 | Y48: =M48 -> 163116.11 | Z48: =N48 -> 172906 | AA48: =O48 -> 177732 | AB48: =P48 -> 179810 | AC48: =Q48 -> 0 | ... AF48: =T48 -> 0 | AH48: =SUM(AF48/AB48)-1 -> -1
B49: Prepaid expenses and other current assets | D49: 5095 | E49: 5334 | G49: 5519.301 | H49: 5399.928 | I49: 5372.484 | J49: =D49 -> 5095 | K49: 4378.681 | L49: 5218.735 | M49: 5107.455 | N49: =E49 -> 5334 | O49: 3741 | P49: 5524 | R49: =E49 -> 5334 | V49: =J49 -> 5095 | W49: =K49 -> 4378.681 | X49: =L49 -> 5218.735 | Y49: =M49 -> 5107.455 | Z49: =N49 -> 5334 | AA49: =O49 -> 3741 | AB49: =P49 -> 5524 | AC49: =Q49 -> 0 | ... AF49: =T49 -> 0 | AH49: =SUM(AF49/AB49)-1 -> -1
B50: Total Current Assets | C50: =SUM(C46:C49) -> 0 | D50: =SUM(D46:D49) -> 270402 | E50: =SUM(E46:E49) -> 257013 | G50: =SUM(G46:G49) -> 239800.18 | H50: =SUM(H46:H49) -> 222774.29 | I50: =SUM(I46:I49) -> 224094.52 | J50: =SUM(J46:J49) -> 270402 | K50: =SUM(K46:K49) -> 264086.21 | L50: =SUM(L46:L49) -> 266243.3 | M50: =SUM(M46:M49) -> 273699.01 | N50: =SUM(N46:N49) -> 257013 | ... T50: =SUM(T46:T49) -> 0 | V50: =SUM(V46:V49) -> 270402 | W50: =SUM(W46:W49) -> 264086.21 | X50: =SUM(X46:X49) -> 266243.3 | Y50: =SUM(Y46:Y49) -> 273699.01 | Z50: =SUM(Z46:Z49) -> 257013 | AA50: =SUM(AA46:AA49) -> 276419 | AB50: =SUM(AB46:AB49) -> 303691 | AC50: =SUM(AC46:AC49) -> 0 | ... AF50: =SUM(AF46:AF49) -> 0 | AH50: =SUM(AF50/AB50)-1 -> -1
B52: Non-Current Assets
B53: Property and equipment, net | D53: 58261 | E53: 53835 | G53: 53220.048 | H53: 54951.267 | I53: 56946.009 | J53: =D53 -> 58261 | K53: 57370.783 | L53: 56305.62 | M53: 54814.607 | N53: =E53 -> 53835 | O53: 55317 | P53: 54326 | R53: =E53 -> 53835 | V53: =J53 -> 58261 | W53: =K53 -> 57370.783 | X53: =L53 -> 56305.62 | Y53: =M53 -> 54814.607 | Z53: =N53 -> 53835 | AA53: =O53 -> 55317 | AB53: =P53 -> 54326 | AC53: =Q53 -> 0 | ... AF53: =T53 -> 0 | AH53: =SUM(AF53/AB53)-1 -> -1
B54: Intangible assets, net | D54: 1013 | E54: 499 | G54: 154.993 | H54: 1371.092 | I54: 1192.254 | J54: =D54 -> 1013 | K54: 834.577 | L54: 655.74 | M54: 476.902 | N54: =E54 -> 499 | O54: 321 | P54: 479 | R54: =E54 -> 499 | V54: =K54 -> 834.577 | W54: =L54 -> 655.74 | X54: =M54 -> 476.902 | Y54: =N54 -> 499 | Z54: =O54 -> 321 | AA54: =P54 -> 479 | AB54: =P54 -> 479 | AC54: =Q54 -> 0 | AD54: =R54 -> 499 | AE54: =S54 -> 0 | AF54: =T54 -> 0 | AH54: =SUM(AF54/AB54)-1 -> -1
B55: Goodwill | D55: 3530 | E55: 3530 | G55: 3529.509 | H55: 3529.509 | I55: 3529.509 | J55: =D55 -> 3530 | K55: 3529.509 | L55: 3529.509 | M55: 3529.509 | N55: =E55 -> 3530 | O55: 3530 | P55: 3530 | R55: =E55 -> 3530 | V55: =K55 -> 3529.509 | W55: =L55 -> 3529.509 | X55: =M55 -> 3529.509 | Y55: =N55 -> 3530 | Z55: =O55 -> 3530 | AA55: =P55 -> 3530 | AB55: =P55 -> 3530 | AC55: =Q55 -> 0 | AD55: =R55 -> 3530 | AE55: =S55 -> 0 | AF55: =T55 -> 0 | AH55: =SUM(AF55/AB55)-1 -> -1
B56: Right-to-use assets | D56: 10485 | E56: 9635 | G56: 7106.642 | H56: 10550.236 | I56: 10335.873 | J56: =D56 -> 10485 | K56: 102.477 | L56: 10003.826 | M56: 9753.725 | N56: =E56 -> 9635 | O56: 9397 | P56: 9152 | R56: =E56 -> 9635 | V56: =K56 -> 102.477 | W56: =L56 -> 10003.826 | X56: =M56 -> 9753.725 | Y56: =N56 -> 9635 | Z56: =O56 -> 9397 | AA56: =P56 -> 9152 | AB56: =P56 -> 9152 | AC56: =Q56 -> 0 | AD56: =R56 -> 9635 | AE56: =S56 -> 0 | AF56: =T56 -> 0 | AH56: =SUM(AF56/AB56)-1 -> -1
B57: Deposits and other assets | D57: 4770 | E57: 4670 | G57: 28250.748 | H57: 3755.938 | I57: 4459.322 | J57: =D57 -> 4770 | K57: 4718.761 | L57: 6289.048 | M57: 6722.817 | N57: =E57 -> 4670 | O57: 5891 | P57: 5221 | R57: =E57 -> 4670 | V57: =K57 -> 4718.761 | W57: =L57 -> 6289.048 | X57: =M57 -> 6722.817 | Y57: =N57 -> 4670 | Z57: =O57 -> 5891 | AA57: =P57 -> 5221 | AB57: =P57 -> 5221 | AC57: =Q57 -> 0 | AD57: =R57 -> 4670 | AE57: =S57 -> 0 | AF57: =T57 -> 0 | AH57: =SUM(AF57/AB57)-1 -> -1
B58: Total Assets | C58: =SUM(C53:C57)+C50 -> 0 | D58: =SUM(D53:D57)+D50 -> 348461 | E58: =SUM(E53:E57)+E50 -> 329182 | G58: =SUM(G53:G57)+G50 -> 332062.12 | H58: =SUM(H53:H57)+H50 -> 296932.33 | I58: =SUM(I53:I57)+I50 -> 300557.49 | J58: =SUM(J53:J57)+J50 -> 348461 | K58: =SUM(K53:K57)+K50 -> 330642.32 | L58: =SUM(L53:L57)+L50 -> 343027.04 | M58: =SUM(M53:M57)+M50 -> 348996.57 | N58: =SUM(N53:N57)+N50 -> 329182 | ... T58: =SUM(T53:T57)+T50 -> 0 | V58: =SUM(V53:V57)+V50 -> 337848.32 | W58: =SUM(W53:W57)+W50 -> 341935.12 | X58: =SUM(X53:X57)+X50 -> 343031.87 | Y58: =SUM(Y53:Y57)+Y50 -> 346847.61 | Z58: =SUM(Z53:Z57)+Z50 -> 329987 | AA58: =SUM(AA53:AA57)+AA50 -> 350118 | AB58: =SUM(AB53:AB57)+AB50 -> 376399 | AC58: =SUM(AC53:AC57)+AC50 -> 0 | ... AF58: =SUM(AF53:AF57)+AF50 -> 0 | AH58: =SUM(AF58/AB58)-1 -> -1
B60: Current Liabilities
B61: Accounts payable | D61: 13229 | E61: 15660 | G61: 14115.135 | H61: 11388.048 | I61: 25197.806 | J61: =D61 -> 13229 | K61: 12956.486 | L61: 12084.529 | M61: 10851.446 | N61: =E61 -> 15660 | O61: 17186 | P61: 14179 | R61: =E61 -> 15660 | V61: =K61 -> 12956.486 | W61: =L61 -> 12084.529 | X61: =M61 -> 10851.446 | Y61: =N61 -> 15660 | Z61: =O61 -> 17186 | AA61: =P61 -> 14179 | AB61: =P61 -> 14179 | AC61: =Q61 -> 0 | AD61: =R61 -> 15660 | AE61: =S61 -> 0 | AF61: =T61 -> 0 | AH61: =SUM(AF61/AB61)-1 -> -1
B62: Accrued expenses and other current liabilities | D62: 24990 | E62: 32919 | G62: 16654.54 | H62: 15961.07 | I62: 18378.932 | J62: =D62 -> 24990 | K62: 22672.464 | L62: 28745.598 | M62: 29863.726 | N62: =E62 -> 32919 | O62: 33691 | P62: 27726 | R62: =E62 -> 32919 | V62: =K62 -> 22672.464 | W62: =L62 -> 28745.598 | X62: =M62 -> 29863.726 | Y62: =N62 -> 32919 | Z62: =O62 -> 33691 | AA62: =P62 -> 27726 | AB62: =P62 -> 27726 | AC62: =Q62 -> 0 | AD62: =R62 -> 32919 | AE62: =S62 -> 0 | AF62: =T62 -> 0 | AH62: =SUM(AF62/AB62)-1 -> -1
B63: Current portion of deferred revenue | D63: 143 | E63: 182 | G63: 142.834 | H63: 142.834 | I63: 142.834 | J63: =D63 -> 143 | K63: 142.834 | L63: 142.834 | M63: 142.834 | N63: =E63 -> 182 | O63: 1118 | P63: 1130 | R63: =E63 -> 182 | AB63: =P63 -> 1130 | AC63: =Q63 -> 0 | AD63: =R63 -> 182 | AE63: =S63 -> 0 | AF63: =T63 -> 0 | AH63: =SUM(AF63/AB63)-1 -> -1
B64: Current portion of lease obligations | D64: 905 | E64: 1045 | G64: 654.003 | H64: 579.661 | I64: 720.755 | J64: =D64 -> 905 | K64: 956.045 | L64: 979.536 | M64: 982.891 | N64: =E64 -> 1045 | O64: 1093 | P64: 1142 | R64: =E64 -> 1045 | AB64: =P64 -> 1142 | AC64: =Q64 -> 0 | AD64: =R64 -> 1045 | AE64: =S64 -> 0 | AF64: =T64 -> 0 | AH64: =SUM(AF64/AB64)-1 -> -1
B65: Total Current Liabilities | C65: =SUM(C61:C64) -> 0 | D65: =SUM(D61:D64) -> 39267 | E65: =SUM(E61:E64) -> 49806 | G65: =SUM(G61:G64) -> 31566.512 | H65: =SUM(H61:H64) -> 28071.613 | I65: =SUM(I61:I64) -> 44440.327 | J65: =SUM(J61:J64) -> 39267 | K65: =SUM(K61:K64) -> 36727.829 | L65: =SUM(L61:L64) -> 41952.497 | M65: =SUM(M61:M64) -> 41840.897 | N65: =SUM(N61:N64) -> 49806 | ... T65: =SUM(T61:T64) -> 0 | V65: =SUM(V61:V64) -> 35628.95 | W65: =SUM(W61:W64) -> 40830.127 | X65: =SUM(X61:X64) -> 40715.172 | Y65: =SUM(Y61:Y64) -> 48579 | Z65: =SUM(Z61:Z64) -> 50877 | AA65: =SUM(AA61:AA64) -> 41905 | AB65: =SUM(AB61:AB64) -> 44177 | AC65: =SUM(AC61:AC64) -> 0 | ... AF65: =SUM(AF61:AF64) -> 0 | AH65: =SUM(AF65/AB65)-1 -> -1
B67: Non-Current Liabilities
B68: Senior notes payable, net of discount | D68: 142833 | E68: 130594 | G68: 138423.05 | H68: 139810.93 | I68: 141365.71 | J68: =D68 -> 142833 | K68: 144300.93 | L68: 140312.07 | M68: 142025.54 | N68: =E68 -> 130594 | O68: 130847 | P68: 131074 | R68: =E68 -> 130594 | V68: =K68 -> 144300.93 | W68: =L68 -> 140312.07 | X68: =M68 -> 142025.54 | Y68: =N68 -> 130594 | Z68: =O68 -> 130847 | AA68: =P68 -> 131074 | AB68: =P68 -> 131074 | AC68: =Q68 -> 0 | AD68: =R68 -> 130594 | AE68: =S68 -> 0 | AF68: =T68 -> 0 | AH68: =SUM(AF68/AB68)-1 -> -1
B69: Deferred revenue, net of current portion | D69: 1833 | E69: 1690 | G69: 1940.156 | H69: 1904.448 | I69: 1868.739 | J69: =D69 -> 1833 | K69: 1797.323 | L69: 1761.614 | M69: 1725.906 | N69: =E69 -> 1690 | O69: 1654 | P69: 1619 | R69: =E69 -> 1690 | V69: =K69 -> 1797.323 | W69: =L69 -> 1761.614 | X69: =M69 -> 1725.906 | Y69: =N69 -> 1690 | Z69: =O69 -> 1654 | AA69: =P69 -> 1619 | AB69: =P69 -> 1619 | AC69: =Q69 -> 0 | AD69: =R69 -> 1690 | AE69: =S69 -> 0 | AF69: =T69 -> 0 | AH69: =SUM(AF69/AB69)-1 -> -1
B70: End of term fee | D70: 1500 | E70: 1688 | G70: 1500 | H70: 1500 | I70: 1500 | J70: =D70 -> 1500 | K70: 1500 | L70: 1567.139 | M70: 1567.139 | N70: =E70 -> 1688 | O70: 1688 | P70: 1688 | R70: =E70 -> 1688 | AB70: =P70 -> 1688 | AC70: =Q70 -> 0 | AD70: =R70 -> 1688 | AE70: =S70 -> 0 | AF70: =T70 -> 0 | AH70: =SUM(AF70/AB70)-1 -> -1
B71: Lease obligations, net of current portion | D71: 10704 | E71: 9779 | G71: 7284.079 | H71: 10870.907 | I71: 10636.083 | J71: =D71 -> 10704 | K71: 10468.109 | L71: 10221.914 | M71: 9965.088 | N71: =E71 -> 9779 | O71: 9487 | P71: 9182 | R71: =E71 -> 9779 | AB71: =P71 -> 9182 | AC71: =Q71 -> 0 | AD71: =R71 -> 9779 | AE71: =S71 -> 0 | AF71: =T71 -> 0 | AH71: =SUM(AF71/AB71)-1 -> -1
B72: Other non-current liabilities | D72: 350 | E72: 419 | G72: 385.628 | H72: 373.903 | I72: 362.179 | J72: =D72 -> 350 | K72: 338.731 | L72: 449.513 | M72: 434.647 | N72: =E72 -> 419 | O72: 405 | P72: 390 | R72: =E72 -> 419 | AB72: =P72 -> 390 | AC72: =Q72 -> 0 | AD72: =R72 -> 419 | AE72: =S72 -> 0 | AF72: =T72 -> 0 | AH72: =SUM(AF72/AB72)-1 -> -1
B73: Total Liabilities | C73: =SUM(C68:C72)+C65 -> 0 | D73: =SUM(D68:D72)+D65 -> 196487 | E73: =SUM(E68:E72)+E65 -> 193976 | G73: =SUM(G68:G72)+G65 -> 181099.43 | H73: =SUM(H68:H72)+H65 -> 182531.8 | I73: =SUM(I68:I72)+I65 -> 200173.03 | J73: =SUM(J68:J72)+J65 -> 196487 | K73: =SUM(K68:K72)+K65 -> 195132.92 | L73: =SUM(L68:L72)+L65 -> 196264.75 | M73: =SUM(M68:M72)+M65 -> 197559.22 | N73: =SUM(N68:N72)+N65 -> 193976 | ... T73: =SUM(T68:T72)+T65 -> 0 | V73: =SUM(V68:V72)+V65 -> 181727.2 | W73: =SUM(W68:W72)+W65 -> 182903.81 | X73: =SUM(X68:X72)+X65 -> 184466.62 | Y73: =SUM(Y68:Y72)+Y65 -> 180863 | Z73: =SUM(Z68:Z72)+Z65 -> 183378 | AA73: =SUM(AA68:AA72)+AA65 -> 174598 | AB73: =SUM(AB68:AB72)+AB65 -> 188130 | AC73: =SUM(AC68:AC72)+AC65 -> 0 | ... AF73: =SUM(AF68:AF72)+AF65 -> 0 | AH73: =SUM(AF73/AB73)-1 -> -1
B75: Preferred Stock | D75: - | E75: - | G75: - | H75: - | I75: - | J75: =D75 -> - | K75: - | L75: - | M75: 0 | N75: =E75 -> - | O75: - | P75: - | R75: =E75 -> - | V75: =K75 -> - | W75: =L75 -> - | X75: =M75 -> 0 | Y75: =N75 -> - | Z75: =O75 -> - | AA75: =P75 -> - | AB75: =P75 -> - | AC75: =Q75 -> 0 | AD75: =R75 -> - | AE75: =S75 -> 0 | AF75: =T75 -> 0 | AH75: =SUM(AF75/AB75)-1 -> #VALUE!
B76: Common Stock | D76: 22 | E76: 23 | G76: 19.635 | H76: 19.636 | I76: 19.678 | J76: =D76 -> 22 | K76: 22.226 | L76: 22.453 | M76: 22.596 | N76: =E76 -> 23 | O76: 23 | P76: 23 | R76: =E76 -> 23 | AB76: =P76 -> 23 | AC76: =Q76 -> 0 | AD76: =R76 -> 23 | AE76: =S76 -> 0 | AF76: =T76 -> 0 | AH76: =SUM(AF76/AB76)-1 -> -1
B77: Additional paid-in capital | D77: 629969 | E77: 641439 | G77: 564034.01 | H77: 565266.38 | I77: 566149.85 | J77: =D77 -> 629969 | K77: 630437.88 | L77: 637916.04 | M77: 640025.89 | N77: =E77 -> 641439 | O77: 642133 | P77: 644634 | R77: =E77 -> 641439 | AB77: =P77 -> 644634 | AC77: =Q77 -> 0 | AD77: =R77 -> 641439 | AE77: =S77 -> 0 | AF77: =T77 -> 0 | AH77: =SUM(AF77/AB77)-1 -> -1
B78: Accumulated deficit | D78: -478017 | E78: -506256 | G78: -437120.58 | H78: -450885.48 | I78: -465784.99 | J78: =D78 -> -478017 | K78: -484805.49 | L78: -491176.19 | M78: -488611.14 | N78: =E78 -> -506256 | O78: -488450 | P78: -456388 | R78: =E78 -> -506256 | V78: =K78 -> -484805.49 | W78: =L78 -> -491176.19 | X78: =M78 -> -488611.14 | Y78: =N78 -> -506256 | Z78: =O78 -> -488450 | AA78: =P78 -> -456388 | AB78: =P78 -> -456388 | AC78: =Q78 -> 0 | AD78: =R78 -> -506256 | AE78: =S78 -> 0 | AF78: =T78 -> 0 | AH78: =SUM(AF78/AB78)-1 -> -1
B79: Total stockholders' equity | C79: =SUM(C75:C78) -> 0 | D79: =SUM(D75:D78) -> 151974 | E79: =SUM(E75:E78) -> 135206 | G79: =SUM(G75:G78) -> 126933.07 | H79: =SUM(H75:H78) -> 114400.53 | I79: =SUM(I75:I78) -> 100384.54 | J79: =SUM(J75:J78) -> 151974 | K79: =SUM(K75:K78) -> 145654.62 | L79: =SUM(L75:L78) -> 146762.29 | M79: =SUM(M75:M78) -> 151437.35 | N79: =SUM(N75:N78) -> 135206 | ... T79: =SUM(T75:T78) -> 0 | V79: =SUM(V75:V78) -> -484805.49 | W79: =SUM(W75:W78) -> -491176.19 | X79: =SUM(X75:X78) -> -488611.14 | Y79: =SUM(Y75:Y78) -> -506256 | Z79: =SUM(Z75:Z78) -> -488450 | AA79: =SUM(AA75:AA78) -> -456388 | AB79: =SUM(AB75:AB78) -> 188269 | AC79: =SUM(AC75:AC78) -> 0 | ... AF79: =SUM(AF75:AF78) -> 0 | AH79: =SUM(AF79/AB79)-1 -> -1
B80: Total liabilities and stockholders' equity | C80: =SUM(C79+C73) -> 0 | D80: =SUM(D79+D73) -> 348461 | E80: =SUM(E79+E73) -> 329182 | G80: =SUM(G79+G73) -> 308032.49 | H80: =SUM(H79+H73) -> 296932.33 | I80: =SUM(I79+I73) -> 300557.57 | J80: =SUM(J79+J73) -> 348461 | K80: =SUM(K79+K73) -> 340787.54 | L80: =SUM(L79+L73) -> 343027.04 | M80: =SUM(M79+M73) -> 348996.57 | N80: =SUM(N79+N73) -> 329182 | ... T80: =SUM(T79+T73) -> 0 | V80: =SUM(V79+V73) -> -303078.28 | W80: =SUM(W79+W73) -> -308272.38 | X80: =SUM(X79+X73) -> -304144.52 | Y80: =SUM(Y79+Y73) -> -325393 | Z80: =SUM(Z79+Z73) -> -305072 | AA80: =SUM(AA79+AA73) -> -281790 | AB80: =SUM(AB79+AB73) -> 376399 | AC80: =SUM(AC79+AC73) -> 0 | ... AF80: =SUM(AF79+AF73) -> 0 | AH80: =SUM(AF80/AB80)-1 -> -1
B82: Balance Check | C82: =C80-C58 -> 0 | D82: =D80-D58 -> 0 | E82: =E80-E58 -> 0 | G82: =G80-G58 -> -24029.631 | H82: =H80-H58 -> 0 | I82: =I80-I58 -> 0.081 | J82: =J80-J58 -> 0 | K82: =K80-K58 -> 10145.223 | L82: =L80-L58 -> 0 | M82: =M80-M58 -> 0 | N82: =N80-N58 -> 0 | ... T82: =T80-T58 -> 0 | V82: =V80-V58 -> -640926.61 | W82: =W80-W58 -> -650207.5 | X82: =X80-X58 -> -647176.39 | Y82: =Y80-Y58 -> -672240.61 | Z82: =Z80-Z58 -> -635059 | AA82: =AA80-AA58 -> -631908 | AB82: =AB80-AB58 -> 0 | AC82: =AC80-AC58 -> 0 | ... AF82: =AF80-AF58 -> 0
B84: 1) Prepaid expenses and other current assets consists of: Prepaid expenses and other current assets + Forward contracts + Deferred offering costs.
A86: X | B86: Cash-Flows Statement | C86: FYE | G86: Quarterly | Q86: Quarterly | AB86: LTM | AH86: Variance
B87: =B7 -> Fiscal Period | C87: =C7 -> 2021 | D87: =D7 -> 2022 | E87: =E7 -> 2023 | G87: =G7 -> 1Q22 | H87: =H7 -> 2Q22 | I87: =I7 -> 3Q22 | J87: =J7 -> 4Q22 | K87: =K7 -> 1Q23 | L87: =L7 -> 2Q23 | M87: =M7 -> 3Q23 | N87: =N7 -> 4Q23 | ... T87: =T7 -> 2Q25 | V87: =V7 -> 4Q22 | W87: =W7 -> 1Q23 | X87: =X7 -> 2Q23 | Y87: =Y7 -> 3Q23 | Z87: =Z7 -> 4Q23 | AA87: =AA7 -> 1Q24 | AB87: =AB7 -> 2Q24 | AC87: =AC7 -> 3Q24 | ... AF87: =AF7 -> 2Q25
B88: =B8 -> Fiscal Period End Date | C88: =C8 -> 44561 | D88: =D8 -> 44926 | E88: =E8 -> 45291 | G88: =G8 -> 44651 | H88: =H8 -> 44742 | I88: =I8 -> 44834 | J88: =J8 -> 44926 | K88: =K8 -> 45016 | L88: =L8 -> 45107 | M88: =M8 -> 45199 | N88: =N8 -> 45291 | ... T88: =T8 -> 45838 | V88: =V8 -> 44926 | W88: =W8 -> 45016 | X88: =X8 -> 45107 | Y88: =Y8 -> 45199 | Z88: =Z8 -> 45291 | AA88: =AA8 -> 45382 | AB88: =AB8 -> 45473 | AC88: =AC8 -> 45565 | ... AF88: =AF8 -> 45838
B90: Cash-Flows From Operating Activities
B91: Net income (loss) | C91: =C32 -> -71648 | D91: =D32 -> -65904 | E91: =E32 -> -28239 | G91: =G32 -> -25007.857 | H91: =H32 -> -13764.906 | I91: =I32 -> -14899.504 | J91: =J32 -> -12231.733 | K91: =K32 -> -6788.815 | L91: =L32 -> -6370.707 | M91: =M32 -> 2565.055 | N91: =SUM(D91-SUM(K91:M91)) -> -55309.533 | O91: =O32 -> 17841 | P91: =P32 -> 32078 | Q91: =Q32 -> 0 | R91: =SUM(E91-SUM(O91:Q91)) -> -78158 | S91: =S32 -> 0 | T91: =T32 -> 0 | V91: =SUM(H91:K91) -> -47684.958 | W91: =SUM(I91:L91) -> -40290.759 | X91: =SUM(J91:M91) -> -22826.2 | Y91: =SUM(K91:N91) -> -65904 | Z91: =SUM(L91:O91) -> -41274.185 | AA91: =SUM(M91:P91) -> -2825.478 | AB91: =SUM(M91:P91) -> -2825.478 | AC91: =SUM(N91:Q91) -> -5390.533 | AD91: =SUM(O91:R91) -> -28239 | AE91: =SUM(P91:S91) -> -46080 | AF91: =SUM(Q91:T91) -> -78158 | AH91: =SUM(AF91/AB91)-1 -> 26.661868
B93: Adjustments to reconcile net income:
B94: Depreciation and amortization | C94: 5496 | D94: 7113 | E94: 8332 | G94: 1590217 | H94: 3314500 | I94: 5176492 | J94: =SUM(C94-SUM(G94:I94)) -> -10075713 | K94: 2032965 | L94: 4130542 | M94: 6223050 | N94: =SUM(D94-SUM(K94:M94)) -> -12379444 | O94: 2114 | P94: 4161 | R94: =SUM(E94-SUM(O94:Q94)) -> 2057 | V94: =SUM(H94:K94) -> 448244 | W94: =SUM(I94:L94) -> 1264286 | X94: =SUM(J94:M94) -> 2310844 | Y94: =SUM(K94:N94) -> 7113 | Z94: =SUM(L94:O94) -> -2023738 | AA94: =SUM(M94:P94) -> -6150119 | AB94: =SUM(M94:P94) -> -6150119 | AC94: =SUM(N94:Q94) -> -12373169 | AD94: =SUM(O94:R94) -> 8332 | AE94: =SUM(P94:S94) -> 6218 | AF94: =SUM(Q94:T94) -> 2057 | AH94: =SUM(AF94/AB94)-1 -> -1.0003345
B95: Loss on disposal of fixed assets | C95: 221 | D95: 427 | E95: 182 | G95: 2000 | H95: 2638 | I95: 8408 | J95: =SUM(C95-SUM(G95:I95)) -> -12825 | K95: 18096 | L95: 18096 | M95: 110947 | N95: =SUM(D95-SUM(K95:M95)) -> -146712 | O95: 23 | P95: 24 | R95: =SUM(E95-SUM(O95:Q95)) -> 135 | V95: =SUM(H95:K95) -> 16317 | W95: =SUM(I95:L95) -> 31775 | X95: =SUM(J95:M95) -> 134314 | Y95: =SUM(K95:N95) -> 427 | Z95: =SUM(L95:O95) -> -17646 | AA95: =SUM(M95:P95) -> -35718 | AB95: =SUM(M95:P95) -> -35718 | AC95: =SUM(N95:Q95) -> -146665 | AD95: =SUM(O95:R95) -> 182 | AE95: =SUM(P95:S95) -> 159 | AF95: =SUM(Q95:T95) -> 135 | AH95: =SUM(AF95/AB95)-1 -> -1.0037796
B96: Interest paid in kind | C96: 0 | D96: 2998 | E96: 3836 | H96: 1045660 | I96: 2023932 | J96: =SUM(C96-SUM(G96:I96)) -> -3069592 | K96: 979978 | L96: 1966160 | M96: 2958592 | N96: =SUM(D96-SUM(K96:M96)) -> -5901732 | O96: - | P96: - | R96: =SUM(E96-SUM(O96:Q96)) -> 3836 | V96: =SUM(H96:K96) -> 979978 | W96: =SUM(I96:L96) -> 1900478 | X96: =SUM(J96:M96) -> 2835138 | Y96: =SUM(K96:N96) -> 2998 | Z96: =SUM(L96:O96) -> -976980 | AA96: =SUM(M96:P96) -> -2943140 | AB96: =SUM(M96:P96) -> -2943140 | AC96: =SUM(N96:Q96) -> -5901732 | AD96: =SUM(O96:R96) -> 3836 | AE96: =SUM(P96:S96) -> 3836 | AF96: =SUM(Q96:T96) -> 3836 | AH96: =SUM(AF96/AB96)-1 -> -1.0013034
B97: Stock-based compensation | C97: 3488 | D97: 5215 | E97: 6187 | G97: 1641388 | H97: 2832435 | I97: 4145929 | J97: =SUM(C97-SUM(G97:I97)) -> -8616264 | K97: 1110166 | L97: 2747204 | M97: 4441845 | N97: =SUM(D97-SUM(K97:M97)) -> -8294000 | O97: 2141 | P97: 5004 | R97: =SUM(E97-SUM(O97:Q97)) -> -958 | V97: =SUM(H97:K97) -> -527734 | W97: =SUM(I97:L97) -> -612965 | X97: =SUM(J97:M97) -> -317049 | Y97: =SUM(K97:N97) -> 5215 | Z97: =SUM(L97:O97) -> -1102810 | AA97: =SUM(M97:P97) -> -3845010 | AB97: =SUM(M97:P97) -> -3845010 | AC97: =SUM(N97:Q97) -> -8286855 | AD97: =SUM(O97:R97) -> 6187 | AE97: =SUM(P97:S97) -> 4046 | AF97: =SUM(Q97:T97) -> -958 | AH97: =SUM(AF97/AB97)-1 -> -0.99975085
B98: Amortization of debt discount | C98: 1897 | D98: 2402 | E98: 2594 | G98: 584842 | H98: 927061 | I98: 1908127 | J98: =SUM(C98-SUM(G98:I98)) -> -3418133 | K98: 487889 | L98: 1174750 | M98: 1895790 | N98: =SUM(D98-SUM(K98:M98)) -> -3556027 | O98: 253 | P98: 480 | R98: =SUM(E98-SUM(O98:Q98)) -> 1861 | AB98: =SUM(M98:P98) -> -1659504 | AC98: =SUM(N98:Q98) -> -3555294 | AD98: =SUM(O98:R98) -> 2594 | AE98: =SUM(P98:S98) -> 2341 | AF98: =SUM(Q98:T98) -> 1861 | AH98: =SUM(AF98/AB98)-1 -> -1.0011214
B99: Loss on extinguishment of debt | C99: 0 | D99: 6670 | E99: 26174 | G99: 6669941 | H99: 6669941 | I99: 6669941 | J99: =SUM(C99-SUM(G99:I99)) -> -20009823 | K99: - | L99: - | M99: 0 | N99: =SUM(D99-SUM(K99:M99)) -> 6670 | R99: =SUM(E99-SUM(O99:Q99)) -> 26174 | AB99: =SUM(M99:P99) -> 6670 | AC99: =SUM(N99:Q99) -> 6670 | AD99: =SUM(O99:R99) -> 26174 | AE99: =SUM(P99:S99) -> 26174 | AF99: =SUM(Q99:T99) -> 26174 | AH99: =SUM(AF99/AB99)-1 -> 2.9241379
B100: Amortization of license revenue | C100: -143 | D100: -143 | E100: -143 | G100: -35708 | H100: -71417 | I100: -107125 | J100: =SUM(C100-SUM(G100:I100)) -> 214107 | K100: -35708 | L100: -71417 | M100: -107125 | N100: =SUM(D100-SUM(K100:M100)) -> 214107 | O100: -36 | P100: -71 | R100: =SUM(E100-SUM(O100:Q100)) -> -36 | AB100: =SUM(M100:P100) -> 106875 | AC100: =SUM(N100:Q100) -> 214000 | AD100: =SUM(O100:R100) -> -143 | AE100: =SUM(P100:S100) -> -107 | AF100: =SUM(Q100:T100) -> -36 | AH100: =SUM(AF100/AB100)-1 -> -1.0003368
B102: Changes in assets and liabilities:
B103: Accounts receivable | C103: -15340 | D103: 13072 | E103: -11916 | G103: 2947233 | H103: 9693011 | I103: 7674472 | J103: =SUM(C103-SUM(G103:I103)) -> -20330056 | K103: -11013446 | L103: -21226562 | M103: -15813632 | N103: =SUM(D103-SUM(K103:M103)) -> 48066712 | O103: -22200 | P103: -2692 | R103: =SUM(E103-SUM(O103:Q103)) -> 12976 | V103: =SUM(H103:K103) -> -13976019 | W103: =SUM(I103:L103) -> -44895592 | X103: =SUM(J103:M103) -> -68383696 | Y103: =SUM(K103:N103) -> 13072 | Z103: =SUM(L103:O103) -> 11004318 | AA103: =SUM(M103:P103) -> 32228188 | AB103: =SUM(M103:P103) -> 32228188 | AC103: =SUM(N103:Q103) -> 48041820 | AD103: =SUM(O103:R103) -> -11916 | AE103: =SUM(P103:S103) -> 10284 | AF103: =SUM(Q103:T103) -> 12976 | AH103: =SUM(AF103/AB103)-1 -> -0.99959737
B104: Inventories | C104: -43188 | D104: -38556 | E104: -9626 | G104: -14422219 | H104: -21351368 | I104: -38189543 | J104: =SUM(C104-SUM(G104:I104)) -> 73919942 | K104: -704826 | L104: 1499984 | M104: 163942 | N104: =SUM(D104-SUM(K104:M104)) -> -997656 | O104: -4826 | P104: -6904
B105: Prepaid expenses and other current assets | C105: -1293 | D105: -756 | E105: -239 | G105: -1180056 | H105: -1060683 | I105: -1033238 | J105: =SUM(C105-SUM(G105:I105)) -> 3272684 | K105: 716465 | L105: -123590 | M105: -12309 | N105: =SUM(D105-SUM(K105:M105)) -> -581322 | O105: 1593 | P105: -190 | R105: =SUM(E105-SUM(O105:Q105)) -> -1642 | V105: =SUM(H105:K105) -> 1895228 | W105: =SUM(I105:L105) -> 2832321 | X105: =SUM(J105:M105) -> 3853250 | Y105: =SUM(K105:N105) -> -756 | Z105: =SUM(L105:O105) -> -715628 | AA105: =SUM(M105:P105) -> -592228 | AB105: =SUM(M105:P105) -> -592228 | AC105: =SUM(N105:Q105) -> -579919 | AD105: =SUM(O105:R105) -> -239 | AE105: =SUM(P105:S105) -> -1832 | AF105: =SUM(Q105:T105) -> -1642 | AH105: =SUM(AF105/AB105)-1 -> -0.99722742
B106: Deposits and other assets | C106: -1775 | D106: 122 | E106: 1080 | G106: 1397672 | H106: 684777 | I106: 195756 | J106: =SUM(C106-SUM(G106:I106)) -> -2279980 | K106: 289232 | L106: -1037181 | M106: -1220849 | N106: =SUM(D106-SUM(K106:M106)) -> 1968920 | O106: -982 | P106: -68 | R106: =SUM(E106-SUM(O106:Q106)) -> 2130 | V106: =SUM(H106:K106) -> -1110215 | W106: =SUM(I106:L106) -> -2832173 | X106: =SUM(J106:M106) -> -4248778 | Y106: =SUM(K106:N106) -> 122 | Z106: =SUM(L106:O106) -> -290092 | AA106: =SUM(M106:P106) -> 747021 | AB106: =SUM(M106:P106) -> 747021 | AC106: =SUM(N106:Q106) -> 1967870 | AD106: =SUM(O106:R106) -> 1080 | AE106: =SUM(P106:S106) -> 2062 | AF106: =SUM(Q106:T106) -> 2130 | AH106: =SUM(AF106/AB106)-1 -> -0.99714867
B107: Accounts payable | C107: 1356 | D107: 800 | E107: 3839 | G107: 1685724 | H107: -1041361 | I107: 12768396 | J107: =SUM(C107-SUM(G107:I107)) -> -13411403 | K107: -272904 | L107: -1144862 | M107: -1154769 | N107: =SUM(D107-SUM(K107:M107)) -> 2573335 | O107: 447 | P107: -1410 | R107: =SUM(E107-SUM(O107:Q107)) -> 4802 | V107: =SUM(H107:K107) -> -1957272 | W107: =SUM(I107:L107) -> -2060773 | X107: =SUM(J107:M107) -> -15983938 | Y107: =SUM(K107:N107) -> 800 | Z107: =SUM(L107:O107) -> 274151 | AA107: =SUM(M107:P107) -> 1417603 | AB107: =SUM(M107:P107) -> 1417603 | AC107: =SUM(N107:Q107) -> 2572372 | AD107: =SUM(O107:R107) -> 3839 | AE107: =SUM(P107:S107) -> 3392 | AF107: =SUM(Q107:T107) -> 4802 | AH107: =SUM(AF107/AB107)-1 -> -0.99661259
B108: Accrued expenses | C108: 8341 | D108: 7534 | E108: 7530 | G108: -1775526 | H108: -1461621 | I108: 667193 | J108: =SUM(C108-SUM(G108:I108)) -> 2578295 | K108: -1353815 | L108: 4738377 | M108: 4874378 | N108: =SUM(D108-SUM(K108:M108)) -> -8251406 | O108: 772 | P108: -5193 | R108: =SUM(E108-SUM(O108:Q108)) -> 11951 | V108: =SUM(H108:K108) -> 430052 | W108: =SUM(I108:L108) -> 6630050 | X108: =SUM(J108:M108) -> 10837235 | Y108: =SUM(K108:N108) -> 7534 | Z108: =SUM(L108:O108) -> 1362121 | AA108: =SUM(M108:P108) -> -3381449 | AB108: =SUM(M108:P108) -> -3381449 | AC108: =SUM(N108:Q108) -> -8255827 | AD108: =SUM(O108:R108) -> 7530 | AE108: =SUM(P108:S108) -> 6758 | AF108: =SUM(Q108:T108) -> 11951 | AH108: =SUM(AF108/AB108)-1 -> -1.0035343
B109: Other current and non-current liabilities | C109: 219 | D109: -502 | E109: -791 | G109: -111064 | H109: -254991 | I109: -365415 | J109: =SUM(C109-SUM(G109:I109)) -> 731689 | K109: -187551 | L109: -293009 | M109: -561345 | N109: =SUM(D109-SUM(K109:M109)) -> 1041403 | O109: 677 | P109: 419 | R109: =SUM(E109-SUM(O109:Q109)) -> -1887 | V109: =SUM(H109:K109) -> -76268 | W109: =SUM(I109:L109) -> -114286 | X109: =SUM(J109:M109) -> -310216 | Y109: =SUM(K109:N109) -> -502 | Z109: =SUM(L109:O109) -> 187726 | AA109: =SUM(M109:P109) -> 481154 | AB109: =SUM(M109:P109) -> 481154 | AC109: =SUM(N109:Q109) -> 1042499 | AD109: =SUM(O109:R109) -> -791 | AE109: =SUM(P109:S109) -> -1468 | AF109: =SUM(Q109:T109) -> -1887 | AH109: =SUM(AF109/AB109)-1 -> -1.0039218
B110: Net cash used in operating activities | C110: =SUM(C91:C109) -> -112369 | D110: =SUM(D91:D109) -> -59508 | E110: =SUM(E91:E109) -> 8800 | G110: =SUM(G91:G109) -> -1030563.9 | H110: =SUM(H91:H109) -> -85182.906 | I110: =SUM(I91:I109) -> 1528425.5 | J110: =SUM(J91:J109) -> -519303.73 | K110: =SUM(K91:K109) -> -7940247.8 | L110: =SUM(L91:L109) -> -7627878.7 | M110: =SUM(M91:M109) -> 1801080.1 | N110: =SUM(N91:N109) -> 13707538 | ... T110: =SUM(T91:T109) -> 0 | V110: =SUM(V91:V109) -> -13925374 | W110: =SUM(W91:W109) -> -37897170 | X110: =SUM(X91:X109) -> -69295722 | Y110: =SUM(Y91:Y109) -> -29881 | Z110: =SUM(Z91:Z109) -> 7660147.8 | AA110: =SUM(AA91:AA109) -> 17923477 | AB110: =SUM(AB91:AB109) -> 16377518 | AC110: =SUM(AC91:AC109) -> 14740379 | ... AF110: =SUM(AF91:AF109) -> -16759 | AH110: =SUM(AF110/AB110)-1 -> -1.0010233
B112: Cash flows from investing activities:
B113: Purchase of property and equipment | C113: -13511 | D113: -13911 | E113: -4771 | G113: -2842085 | H113: -6782169 | I113: -10162650 | J113: =SUM(C113-SUM(G113:I113)) -> 19773393 | K113: -1944596 | L113: -2817229 | M113: -3573786 | N113: =SUM(D113-SUM(K113:M113)) -> 8321700 | O113: -2347 | P113: -4413 | R113: =SUM(E113-SUM(O113:Q113)) -> 1989 | V113: =SUM(H113:K113) -> 883978 | W113: =SUM(I113:L113) -> 4848918 | X113: =SUM(J113:M113) -> 11437782 | Y113: =SUM(K113:N113) -> -13911 | Z113: =SUM(L113:O113) -> 1928338 | AA113: =SUM(M113:P113) -> 4741154 | AB113: =SUM(M113:P113) -> 4741154 | AC113: =SUM(N113:Q113) -> 8314940 | AD113: =SUM(O113:R113) -> -4771 | AE113: =SUM(P113:S113) -> -2424 | AF113: =SUM(Q113:T113) -> 1989 | AH113: =SUM(AF113/AB113)-1 -> -0.99958048
B114: Acquisition of intangible assets | C114: 0 | D114: 0 | E114: -210 | J114: =SUM(C114-SUM(G114:I114)) -> 0 | N114: =SUM(D114-SUM(K114:M114)) -> 0 | O114: -15 | P114: -314 | R114: =SUM(E114-SUM(O114:Q114)) -> 119 | V114: =SUM(H114:K114) -> 0 | W114: =SUM(I114:L114) -> 0 | X114: =SUM(J114:M114) -> 0 | Y114: =SUM(K114:N114) -> 0 | Z114: =SUM(L114:O114) -> -15 | AA114: =SUM(M114:P114) -> -329 | AB114: =SUM(M114:P114) -> -329 | AC114: =SUM(N114:Q114) -> -329 | AD114: =SUM(O114:R114) -> -210 | AE114: =SUM(P114:S114) -> -195 | AF114: =SUM(Q114:T114) -> 119 | AH114: =SUM(AF114/AB114)-1 -> -1.3617021
B115: Net cash used in investing activities | C115: =SUM(C113:C114) -> -13511 | D115: =SUM(D113:D114) -> -13911 | E115: =SUM(E113:E114) -> -4981 | G115: =SUM(G113:G114) -> -2842085 | H115: =SUM(H113:H114) -> -6782169 | I115: =SUM(I113:I114) -> -10162650 | J115: =SUM(J113:J114) -> 19773393 | K115: =SUM(K113:K114) -> -1944596 | L115: =SUM(L113:L114) -> -2817229 | M115: =SUM(M113:M114) -> -3573786 | N115: =SUM(N113:N114) -> 8321700 | ... T115: =SUM(T113:T114) -> 0 | V115: =SUM(V113:V114) -> 883978 | W115: =SUM(W113:W114) -> 4848918 | X115: =SUM(X113:X114) -> 11437782 | Y115: =SUM(Y113:Y114) -> -13911 | Z115: =SUM(Z113:Z114) -> 1928323 | AA115: =SUM(AA113:AA114) -> 4740825 | AB115: =SUM(AB113:AB114) -> 4740825 | AC115: =SUM(AC113:AC114) -> 8314611 | ... AF115: =SUM(AF113:AF114) -> 2108 | AH115: =SUM(AF115/AB115)-1 -> -0.99955535
B117: Cash flows from financing activities:
B118: Principal payments on notes payable | C118: 0 | D118: -100000 | E118: -158584 | G118: -100000000 | H118: -100000000 | I118: -100000000 | J118: =SUM(C118-SUM(G118:I118)) -> 300000000 | L118: - | N118: =SUM(D118-SUM(K118:M118)) -> -100000 | R118: =SUM(E118-SUM(O118:Q118)) -> -158584 | AB118: =SUM(M118:P118) -> -100000 | AC118: =SUM(N118:Q118) -> -100000 | AD118: =SUM(O118:R118) -> -158584 | AE118: =SUM(P118:S118) -> -158584 | AF118: =SUM(Q118:T118) -> -158584 | AH118: =SUM(AF118/AB118)-1 -> 0.58584
B119: Proceeds from issuance of common stock, net of offering expenses | C119: 121144 | D119: 64645 | E119: 0 | J119: =SUM(C119-SUM(G119:I119)) -> 121144 | N119: =SUM(D119-SUM(K119:M119)) -> 64645 | R119: =SUM(E119-SUM(O119:Q119)) -> 0 | AB119: =SUM(M119:P119) -> 64645 | AC119: =SUM(N119:Q119) -> 64645 | AD119: =SUM(O119:R119) -> 0 | AE119: =SUM(P119:S119) -> 0 | AF119: =SUM(Q119:T119) -> 0 | AH119: =SUM(AF119/AB119)-1 -> -1
B120: Payment of debt refinancing fees | C120: 0 | D120: -2000 | E120: -11140 | G120: -2000000 | H120: -2000000 | I120: -2000000 | J120: =SUM(C120-SUM(G120:I120)) -> 6000000 | L120: - | N120: =SUM(D120-SUM(K120:M120)) -> -2000 | R120: =SUM(E120-SUM(O120:Q120)) -> -11140
B121: Proceeds from issuance of note payable | C121: 0 | D121: 151750 | E121: 135000 | G121: 151750000 | H121: 151750000 | I121: 151750000 | J121: =SUM(C121-SUM(G121:I121)) -> -455250000 | N121: =SUM(D121-SUM(K121:M121)) -> 151750 | R121: =SUM(E121-SUM(O121:Q121)) -> 135000
B122: Taxes paid on vested Restricted Stock Units | C122: -62 | D122: -2899 | E122: -1415 | G122: -91367 | H122: -401315 | I122: -831297 | J122: =SUM(C122-SUM(G122:I122)) -> 1323917 | K122: -640946 | L122: -865912 | M122: -1074550 | N122: =SUM(D122-SUM(K122:M122)) -> 2578509 | O122: -2476 | P122: -3169 | R122: =SUM(E122-SUM(O122:Q122)) -> 4230
B123: Payments on finance lease obligations | C123: -34 | D123: -36 | E123: -17 | G123: -8941 | H123: -18034 | I123: -27281 | J123: =SUM(C123-SUM(G123:I123)) -> 54222 | K123: -9563 | L123: -16028 | M123: -16028 | N123: =SUM(D123-SUM(K123:M123)) -> 41583 | O123: - | P123: - | R123: =SUM(E123-SUM(O123:Q123)) -> -17
...

Sheet Revenue Drivers
B2: ADMA Biologics Inc (NASDAQ: ADMA) | G2: Quarterly | O2: Quarterly | P2: Quarterly | V2: LTM | Z2: LTM | AB2: LTM
B3: Segment Anaysis | C3: ='Historical Financials'!C7 -> 2021 | D3: ='Historical Financials'!D7 -> 2022 | E3: ='Historical Financials'!E7 -> 2023 | G3: ='Historical Financials'!G7 -> 1Q22 | H3: ='Historical Financials'!H7 -> 2Q22 | I3: ='Historical Financials'!I7 -> 3Q22 | J3: ='Historical Financials'!J7 -> 4Q22 | K3: ='Historical Financials'!K7 -> 1Q23 | L3: ='Historical Financials'!L7 -> 2Q23 | M3: ='Historical Financials'!M7 -> 3Q23 | N3: ='Historical Financials'!N7 -> 4Q23 | ... T3: ='Historical Financials'!T7 -> 2Q25 | V3: =K3 -> 1Q23 | W3: =L3 -> 2Q23 | X3: =M3 -> 3Q23 | Y3: =N3 -> 4Q23 | Z3: =O3 -> 1Q24 | AA3: =P3 -> 2Q24 | AB3: =R3 -> 4Q24 | AC3: =S3 -> 1Q25 | AD3: =T3 -> 2Q25 | AE3: =#REF! -> #REF!
B4: $ in thousands except per share | C4: ='Historical Financials'!C8 -> 44561 | D4: ='Historical Financials'!D8 -> 44926 | E4: ='Historical Financials'!E8 -> 45291 | G4: ='Historical Financials'!G8 -> 44651 | H4: ='Historical Financials'!H8 -> 44742 | I4: ='Historical Financials'!I8 -> 44834 | J4: ='Historical Financials'!J8 -> 44926 | K4: ='Historical Financials'!K8 -> 45016 | L4: ='Historical Financials'!L8 -> 45107 | M4: ='Historical Financials'!M8 -> 45199 | N4: ='Historical Financials'!N8 -> 45291 | ... T4: ='Historical Financials'!T8 -> 45838 | V4: =K4 -> 45016 | W4: =L4 -> 45107 | X4: =M4 -> 45199 | Y4: =N4 -> 45291 | Z4: =O4 -> 45382 | AA4: =P4 -> 45473 | AB4: =R4 -> 45657 | AC4: =S4 -> 45747 | AD4: =T4 -> 45838 | AE4: =#REF! -> #REF!
A6: X | B6: Net Revenues by Channel
V7: =SUM(H7:K7) -> 0 | W7: =SUM(I7:L7) -> 0 | X7: =SUM(J7:M7) -> 0 | Y7: =SUM(K7:N7) -> 0 | Z7: =SUM(L7:O7) -> 0 | AA7: =SUM(M7:P7) -> 0 | AB7: =SUM(O7:R7) -> 0 | AC7: =SUM(P7:S7) -> 0 | AD7: =SUM(Q7:T7) -> 0 | AE7: =SUM(R7:T7) -> 0
V8: =SUM(H8:K8) -> 0 | W8: =SUM(I8:L8) -> 0 | X8: =SUM(J8:M8) -> 0 | Y8: =SUM(K8:N8) -> 0 | Z8: =SUM(L8:O8) -> 0 | AA8: =SUM(M8:P8) -> 0 | AB8: =SUM(O8:R8) -> 0 | AC8: =SUM(P8:S8) -> 0 | AD8: =SUM(Q8:T8) -> 0 | AE8: =SUM(R8:T8) -> 0
B9: Total Net Revenue | C9: =SUM(C7:C8) -> 0 | D9: =SUM(D7:D8) -> 0 | E9: =SUM(E7:E8) -> 0 | O9: =SUM(O7:O8) -> 0 | P9: =SUM(P7:P8) -> 0 | Q9: =SUM(Q7:Q8) -> 0 | R9: =SUM(R7:R8) -> 0 | S9: =SUM(S7:S8) -> 0 | T9: =SUM(T7:T8) -> 0 | V9: =SUM(V7:V8) -> 0 | W9: =SUM(W7:W8) -> 0 | X9: =SUM(X7:X8) -> 0 | Y9: =SUM(Y7:Y8) -> 0 | Z9: =SUM(Z7:Z8) -> 0 | AA9: =SUM(AA7:AA8) -> 0 | AB9: =SUM(AB7:AB8) -> 0 | AC9: =SUM(AC7:AC8) -> 0 | ... AE9: =SUM(AE7:AE8) -> 0
B10: Balance Check | C10: =+C9-'Historical Financials'!C11 -> -80943 | D10: =+D9-'Historical Financials'!D11 -> -154080 | E10: =+E9-'Historical Financials'!E11 -> -258215 | O10: =+O9-'Historical Financials'!O11 -> -81875 | P10: =+P9-'Historical Financials'!P11 -> -107191 | Q10: =+Q9-'Historical Financials'!Q11 -> 0 | R10: =+R9-'Historical Financials'!R11 -> -69149 | S10: =+S9-'Historical Financials'!S11 -> 0 | T10: =+T9-'Historical Financials'!T11 -> 0 | V10: =V9-'Historical Financials'!V11 -> -154080 | W10: =W9-'Historical Financials'!W11 -> -181890.44 | X10: =X9-'Historical Financials'!X11 -> -208108.62 | Y10: =Y9-'Historical Financials'!Y11 -> -234293.09 | Z10: =Z9-'Historical Financials'!Z11 -> -258215 | AA10: =AA9-'Historical Financials'!AA11 -> -283176.47 | AB10: =AB9-'Historical Financials'!AC11 -> -262969.68 | AC10: =AC9-'Historical Financials'!AD11 -> -258215 | AD10: =AD9-'Historical Financials'!AE11 -> -176340 | AE10: =AE9-'Historical Financials'!AF11 -> -69149
A12: X | B12: Revenue by Channel
B13: United States | C13: 70626 | D13: 146427 | E13: 244881 | G13: 27316.151 | H13: 31274.844 | I13: 37854.167 | J13: 49981.838 | K13: 52694.723 | L13: 56607.815 | M13: 64617.747 | N13: 70960.715 | O13: 77991 | P13: 102726 | V13: =SUM(H13:K13) -> 171805.57 | W13: =SUM(I13:L13) -> 197138.54 | X13: =SUM(J13:M13) -> 223902.12 | Y13: =SUM(K13:N13) -> 244881 | Z13: =SUM(L13:O13) -> 270177.28 | AA13: =SUM(M13:P13) -> 316295.46 | AB13: =SUM(O13:R13) -> 180717 | AC13: =SUM(P13:S13) -> 102726 | AD13: =SUM(Q13:T13) -> 0 | AE13: =SUM(R13:T13) -> 0
B14: International | C14: 10317 | D14: 7653 | E14: 13334 | G14: 1786.942 | H14: 2630.163 | I14: 3235.97 | J14: -0.075 | K14: 4218.811 | L14: 3515.376 | M14: 2656.851 | N14: 2942.962 | O14: 3884 | P14: 4465 | V14: =SUM(H14:K14) -> 10084.869 | W14: =SUM(I14:L14) -> 10970.082 | X14: =SUM(J14:M14) -> 10390.963 | Y14: =SUM(K14:N14) -> 13334 | Z14: =SUM(L14:O14) -> 12999.189 | AA14: =SUM(M14:P14) -> 13948.813 | AB14: =SUM(O14:R14) -> 8349 | AC14: =SUM(P14:S14) -> 4465 | AD14: =SUM(Q14:T14) -> 0 | AE14: =SUM(R14:T14) -> 0
B15: Total Net U.S Revenue | C15: =SUM(C13:C14) -> 80943 | D15: =SUM(D13:D14) -> 154080 | E15: =SUM(E13:E14) -> 258215 | O15: =SUM(O13:O14) -> 81875 | P15: =SUM(P13:P14) -> 107191 | Q15: =SUM(Q13:Q14) -> 0 | R15: =SUM(R13:R14) -> 0 | S15: =SUM(S13:S14) -> 0 | T15: =SUM(T13:T14) -> 0 | V15: =SUM(V13:V14) -> 181890.44 | W15: =SUM(W13:W14) -> 208108.62 | X15: =SUM(X13:X14) -> 234293.09 | Y15: =SUM(Y13:Y14) -> 258215 | Z15: =SUM(Z13:Z14) -> 283176.47 | AA15: =SUM(AA13:AA14) -> 330244.28 | AB15: =SUM(AB13:AB14) -> 189066 | AC15: =SUM(AC13:AC14) -> 107191 | ... AE15: =SUM(AE13:AE14) -> 0
B16: Balance Check | C16: =+C15-C9 -> 80943 | D16: =+D15-D9 -> 154080 | E16: =+E15-E9 -> 258215 | O16: =+O15-O9 -> 81875 | P16: =+P15-P9 -> 107191 | Q16: =+Q15-Q9 -> 0 | R16: =+R15-R9 -> 0 | S16: =+S15-S9 -> 0 | T16: =+T15-T9 -> 0 | V16: =V15-'Historical Financials'!V17 -> 185735.68 | W16: =W15-'Historical Financials'!W17 -> 212483.74 | X16: =X15-'Historical Financials'!X17 -> 238222.16 | Y16: =Y15-'Historical Financials'!Y17 -> 261515 | Z16: =Z15-'Historical Financials'!Z17 -> 286071.11 | AA16: =AA15-'Historical Financials'!AA17 -> 332295.66 | AB16: =+AB15-AB9 -> 189066 | AC16: =+AC15-AC9 -> 107191 | AD16: =+AD15-AD9 -> 0 | AE16: =+AE15-AE9 -> 0

Sheet FCF
B2: ADMA Biologics Inc (NASDAQ: ADMA) | D2: FYE | H2: Quarterly | Q2: Quarterly | R2: Quarterly | X2: LTM | AE2: LTM | AK2: Variance
B3: FCF Analysis | C3: ='Historical Financials'!#REF! -> #REF! | D3: ='Historical Financials'!C7 -> 2021 | E3: ='Historical Financials'!D7 -> 2022 | F3: ='Historical Financials'!E7 -> 2023 | H3: ='Historical Financials'!G7 -> 1Q22 | I3: ='Historical Financials'!H7 -> 2Q22 | J3: ='Historical Financials'!I7 -> 3Q22 | K3: ='Historical Financials'!J7 -> 4Q22 | L3: ='Historical Financials'!K7 -> 1Q23 | M3: ='Historical Financials'!L7 -> 2Q23 | N3: ='Historical Financials'!M7 -> 3Q23 | O3: ='Historical Financials'!N7 -> 4Q23 | ... U3: ='Historical Financials'!T7 -> 2Q25 | V3: ='Historical Financials'!#REF! -> #REF! | X3: =K3 -> 4Q22 | Y3: =L3 -> 1Q23 | Z3: =M3 -> 2Q23 | AA3: =N3 -> 3Q23 | AB3: =O3 -> 4Q23 | AC3: =P3 -> 1Q24 | AD3: =Q3 -> 2Q24 | AE3: =R3 -> 3Q24 | ... AI3: =V3 -> #REF!
B4: $ in thousands except per share | C4: ='Historical Financials'!#REF! -> #REF! | D4: ='Historical Financials'!C8 -> 44561 | E4: ='Historical Financials'!D8 -> 44926 | F4: ='Historical Financials'!E8 -> 45291 | H4: ='Historical Financials'!G8 -> 44651 | I4: ='Historical Financials'!H8 -> 44742 | J4: ='Historical Financials'!I8 -> 44834 | K4: ='Historical Financials'!J8 -> 44926 | L4: ='Historical Financials'!K8 -> 45016 | M4: ='Historical Financials'!L8 -> 45107 | N4: ='Historical Financials'!M8 -> 45199 | O4: ='Historical Financials'!N8 -> 45291 | ... U4: ='Historical Financials'!T8 -> 45838 | V4: ='Historical Financials'!#REF! -> #REF! | X4: =K4 -> 44926 | Y4: =L4 -> 45016 | Z4: =M4 -> 45107 | AA4: =N4 -> 45199 | AB4: =O4 -> 45291 | AC4: =P4 -> 45382 | AD4: =Q4 -> 45473 | AE4: =R4 -> 45565 | ... AI4: =V4 -> #REF!
P6: ='Revenue Drivers'!O7 -> 0 | Q6: ='Revenue Drivers'!P7 -> 0 | AC6: =SUM(M6:P6) -> 0 | AD6: =SUM(N6:Q6) -> 0 | AE6: =SUM(O6:R6) -> 0 | AF6: =SUM(P6:S6) -> 0 | AG6: =SUM(Q6:T6) -> 0 | AH6: =SUM(R6:U6) -> 0 | AI6: =SUM(S6:V6) -> 0 | AK6: =SUM(AI6/AE6)-1 -> #DIV/0!
P7: ='Revenue Drivers'!O8 -> 0 | Q7: ='Revenue Drivers'!P8 -> 0 | AC7: =SUM(M7:P7) -> 0 | AD7: =SUM(N7:Q7) -> 0 | AE7: =SUM(O7:R7) -> 0 | AF7: =SUM(P7:S7) -> 0 | AG7: =SUM(Q7:T7) -> 0 | AH7: =SUM(R7:U7) -> 0 | AI7: =SUM(S7:V7) -> 0 | AK7: =SUM(AI7/AE7)-1 -> #DIV/0!
B8: Total Revenue | C8: ='Historical Financials'!#REF! -> #REF! | D8: =SUM(D6:D7) -> 0 | E8: =SUM(E6:E7) -> 0 | F8: =SUM(F6:F7) -> 0 | H8: ='Historical Financials'!G11 -> 29103.093 | I8: ='Historical Financials'!H11 -> 33905.007 | J8: ='Historical Financials'!I11 -> 41090.137 | K8: ='Historical Financials'!J11 -> 49981.763 | L8: ='Historical Financials'!K11 -> 56913.534 | M8: ='Historical Financials'!L11 -> 60123.191 | N8: ='Historical Financials'!M11 -> 67274.598 | O8: ='Historical Financials'!N11 -> 73903.677 | P8: =SUM(P6:P7) -> 0 | Q8: =SUM(Q6:Q7) -> 0 | R8: =SUM(R6:R7) -> 0 | S8: =SUM(S6:S7) -> 0 | T8: =SUM(T6:T7) -> 0 | U8: =SUM(U6:U7) -> 0 | V8: =SUM(V6:V7) -> 0 | X8: =SUM(H8:K8) -> 154080 | Y8: =SUM(I8:L8) -> 181890.44 | Z8: =SUM(J8:M8) -> 208108.62 | AA8: =SUM(K8:N8) -> 234293.09 | AB8: =SUM(L8:O8) -> 258215 | AC8: =SUM(AC6:AC7) -> 0 | AD8: =SUM(AD6:AD7) -> 0 | AE8: =SUM(AE6:AE7) -> 0 | AF8: =SUM(AF6:AF7) -> 0 | AG8: =SUM(AG6:AG7) -> 0 | AH8: =SUM(AH6:AH7) -> 0 | AI8: =SUM(AI6:AI7) -> 0 | AK8: =SUM(AI8/AE8)-1 -> #DIV/0!
B9: Y/Y Growth (%) | D9: =SUM(D8/C8)-1 -> #REF! | E9: =SUM(E8/D8)-1 -> #DIV/0! | F9: =SUM(F8/E8)-1 -> #DIV/0! | M9: =SUM(M8/I8)-1 -> 0.77328354 | N9: =SUM(N8/J8)-1 -> 0.63724443 | O9: =SUM(O8/K8)-1 -> 0.47861285 | P9: =SUM(P8/L8)-1 -> -1 | Q9: =SUM(Q8/M8)-1 -> -1 | R9: =SUM(R8/N8)-1 -> -1 | S9: =SUM(S8/O8)-1 -> -1 | T9: =SUM(T8/P8)-1 -> #DIV/0! | ... V9: =SUM(V8/R8)-1 -> #DIV/0! | AB9: =SUM(AB8/X8)-1 -> 0.67585021 | AC9: =SUM(AC8/Y8)-1 -> -1 | AD9: =SUM(AD8/Z8)-1 -> -1 | AE9: =SUM(AE8/AA8)-1 -> -1 | AF9: =SUM(AF8/AB8)-1 -> -1 | AG9: =SUM(AG8/AC8)-1 -> #DIV/0! | AH9: =SUM(AH8/AD8)-1 -> #DIV/0! | AI9: =SUM(AI8/AE8)-1 -> #DIV/0! | AK9: =SUM(AI9-AE9)*10000 -> #DIV/0!
B10: Q/Q Growth (%) | C10: N/A | D10: N/A | E10: N/A | F10: N/A | J10: =SUM(J8/I8)-1 -> 0.21191944 | K10: =SUM(K8/J8)-1 -> 0.21639319 | L10: =SUM(L8/K8)-1 -> 0.138686 | M10: =SUM(M8/L8)-1 -> 0.056395321 | N10: =SUM(N8/M8)-1 -> 0.1189459 | O10: =SUM(O8/N8)-1 -> 0.098537623 | P10: =SUM(P8/O8)-1 -> -1 | Q10: =SUM(Q8/P8)-1 -> #DIV/0! | ... V10: =SUM(V8/U8)-1 -> #DIV/0! | X10: N/A | Y10: N/A | Z10: N/A | AA10: N/A | AB10: N/A | AC10: N/A | AD10: N/A | AE10: N/A | AF10: N/A | AG10: N/A | AH10: N/A | AI10: N/A
B12: (-) Cost of Sales | C12: ='Historical Financials'!#REF! -> #REF! | H12: ='Historical Financials'!G13 -> -25441.046 | I12: ='Historical Financials'!H13 -> -26135.614 | J12: ='Historical Financials'!I13 -> -31433.496 | K12: ='Historical Financials'!J13 -> -35804.844 | L12: ='Historical Financials'!K13 -> -40400.544 | M12: ='Historical Financials'!L13 -> -43433.188 | N12: ='Historical Financials'!M13 -> -42622.013 | O12: ='Historical Financials'!N13 -> -42817.255 | ... Q12: ='Historical Financials'!P13 -> -49738 | X12: =SUM(G12:K12) -> -118815 | Y12: =SUM(I12:L12) -> -133774.5 | Z12: =SUM(J12:M12) -> -151072.07 | AA12: =SUM(K12:N12) -> -162260.59 | AB12: =SUM(L12:O12) -> -169273 | AC12: =SUM(M12:P12) -> -171639.46 | AD12: =SUM(N12:Q12) -> -177944.27 | AE12: =SUM(O12:R12) -> -135322.26 | AF12: =SUM(P12:S12) -> -92505 | ... AI12: =SUM(S12:V12) -> 0 | AK12: =SUM(AI12/AE12)-1 -> -1
B13: Gross Profit | C13: =+C8+C12 -> #REF! | D13: =+D8+D12 -> 0 | E13: =+E8+E12 -> 0 | F13: =+F8+F12 -> 0 | H13: =+H8+H12 -> 3662.047 | I13: =+I8+I12 -> 7769.393 | J13: =+J8+J12 -> 9656.641 | K13: =+K8+K12 -> 14176.919 | L13: =+L8+L12 -> 16512.99 | M13: =+M8+M12 -> 16690.003 | N13: =+N8+N12 -> 24652.585 | O13: =+O8+O12 -> 31086.422 | ... V13: =+V8+V12 -> 0 | X13: =+X8+X12 -> 35265 | Y13: =+Y8+Y12 -> 48115.943 | Z13: =+Z8+Z12 -> 57036.553 | AA13: =+AA8+AA12 -> 72032.497 | AB13: =+AB8+AB12 -> 88942 | AC13: =+AC8+AC12 -> -171639.46 | AD13: =+AD8+AD12 -> -177944.27 | AE13: =+AE8+AE12 -> -135322.26 | ... AI13: =+AI8+AI12 -> 0 | AK13: =SUM(AI13/AE13)-1 -> -1
B14: Gross Margin (%) | C14: =C13/C8 -> #REF! | D14: =D13/D8 -> #DIV/0! | E14: =E13/E8 -> #DIV/0! | F14: =F13/F8 -> #DIV/0! | H14: =H13/H8 -> 0.12583017 | I14: =I13/I8 -> 0.22915179 | J14: =J13/J8 -> 0.23501117 | K14: =K13/K8 -> 0.28364184 | L14: =L13/L8 -> 0.29014171 | M14: =M13/M8 -> 0.27759676 | N14: =N13/N8 -> 0.36644715 | O14: =O13/O8 -> 0.42063431 | ... V14: =V13/V8 -> #DIV/0! | X14: =X13/X8 -> 0.22887461 | Y14: =Y13/Y8 -> 0.26453255 | Z14: =Z13/Z8 -> 0.27407107 | AA14: =AA13/AA8 -> 0.30744611 | AB14: =AB13/AB8 -> 0.34444939 | AC14: =AC13/AC8 -> #DIV/0! | AD14: =AD13/AD8 -> #DIV/0! | AE14: =AE13/AE8 -> #DIV/0! | ... AI14: =AI13/AI8 -> #DIV/0! | AK14: =SUM(AI14-AE14)*10000 -> #DIV/0!
B16: (-) Research and development | C16: ='Historical Financials'!#REF! -> #REF! | H16: ='Historical Financials'!G17 -> -624.111 | I16: ='Historical Financials'!H17 -> -873.386 | J16: ='Historical Financials'!I17 -> -1041.947 | K16: ='Historical Financials'!J17 -> -1074.556 | L16: ='Historical Financials'!K17 -> -855.351 | M16: ='Historical Financials'!L17 -> -1403.26 | N16: ='Historical Financials'!M17 -> -595.903 | O16: ='Historical Financials'!N17 -> -445.486 | ... Q16: ='Historical Financials'!P17 -> -560 | X16: =SUM(G16:K16) -> -3614 | Y16: =SUM(I16:L16) -> -3845.24 | Z16: =SUM(J16:M16) -> -4375.114 | AA16: =SUM(K16:N16) -> -3929.07 | AB16: =SUM(L16:O16) -> -3300 | AC16: =SUM(M16:P16) -> -2894.649 | AD16: =SUM(N16:Q16) -> -2051.389 | AE16: =SUM(O16:R16) -> -1455.486 | AF16: =SUM(P16:S16) -> -1010 | ... AI16: =SUM(S16:V16) -> 0 | AK16: =SUM(AI16/AE16)-1 -> -1
B17: (-) Sales and marketing | C17: ='Historical Financials'!#REF! -> #REF! | H17: ='Historical Financials'!G19 -> -178.838 | I17: ='Historical Financials'!H19 -> -178.838 | J17: ='Historical Financials'!I19 -> -178.838 | K17: ='Historical Financials'!J19 -> -178.486 | L17: ='Historical Financials'!K19 -> -178.838 | M17: ='Historical Financials'!L19 -> -178.838 | N17: ='Historical Financials'!M19 -> -178.838 | O17: ='Historical Financials'!N19 -> -187.486 | ... Q17: ='Historical Financials'!P19 -> -142 | X17: =SUM(G17:K17) -> -715 | Y17: =SUM(I17:L17) -> -715 | Z17: =SUM(J17:M17) -> -715 | AA17: =SUM(K17:N17) -> -715 | AB17: =SUM(L17:O17) -> -724 | AC17: =SUM(M17:P17) -> -738.162 | AD17: =SUM(N17:Q17) -> -701.324 | AE17: =SUM(O17:R17) -> -522.486 | AF17: =SUM(P17:S17) -> -335 | ... AI17: =SUM(S17:V17) -> 0 | AK17: =SUM(AI17/AE17)-1 -> -1
B18: (-) General and administrative | C18: ='Historical Financials'!#REF! -> #REF! | H18: ='Historical Financials'!#REF! -> #REF! | I18: ='Historical Financials'!#REF! -> #REF! | J18: ='Historical Financials'!#REF! -> #REF! | K18: ='Historical Financials'!#REF! -> #REF! | L18: ='Historical Financials'!#REF! -> #REF! | M18: ='Historical Financials'!#REF! -> #REF! | N18: ='Historical Financials'!#REF! -> #REF! | O18: ='Historical Financials'!#REF! -> #REF! | ... Q18: ='Historical Financials'!#REF! -> #REF! | X18: =SUM(G18:K18) -> #REF! | Y18: =SUM(I18:L18) -> #REF! | Z18: =SUM(J18:M18) -> #REF! | AA18: =SUM(K18:N18) -> #REF! | AB18: =SUM(L18:O18) -> #REF! | AC18: =SUM(M18:P18) -> #REF! | AD18: =SUM(N18:Q18) -> #REF! | AE18: =SUM(O18:R18) -> #REF! | AF18: =SUM(P18:S18) -> #REF! | ... AI18: =SUM(S18:V18) -> 0 | AK18: =SUM(AI18/AE18)-1 -> #REF!
B19: (-) Depreciation and amortization | C19: ='Historical Financials'!#REF! -> #REF! | H19: ='Historical Financials'!G20 -> -13699.575 | I19: ='Historical Financials'!H20 -> -11970.422 | J19: ='Historical Financials'!I20 -> -12893.139 | K19: ='Historical Financials'!J20 -> -13894.864 | L19: ='Historical Financials'!K20 -> -14511.656 | M19: ='Historical Financials'!L20 -> -14247.558 | N19: ='Historical Financials'!M20 -> -14725.787 | O19: ='Historical Financials'!N20 -> -15534.999 | ... Q19: ='Historical Financials'!P20 -> -16608 | X19: =SUM(G19:K19) -> -52458 | Y19: =SUM(I19:L19) -> -53270.081 | Z19: =SUM(J19:M19) -> -55547.217 | AA19: =SUM(K19:N19) -> -57379.865 | AB19: =SUM(L19:O19) -> -59020 | AC19: =SUM(M19:P19) -> -60147.344 | AD19: =SUM(N19:Q19) -> -62507.786 | AE19: =SUM(O19:R19) -> -47781.999 | AF19: =SUM(P19:S19) -> -32247 | ... AI19: =SUM(S19:V19) -> 0 | AK19: =SUM(AI19/AE19)-1 -> -1
B20: Earning before Interest & Taxes (EBIT) | C20: =SUM(C13+SUM(C16:C19)) -> #REF! | D20: =SUM(D13+SUM(D16:D19)) -> 0 | E20: =SUM(E13+SUM(E16:E19)) -> 0 | F20: =SUM(F13+SUM(F16:F19)) -> 0 | H20: =SUM(H13+SUM(H16:H19)) -> #REF! | I20: =SUM(I13+SUM(I16:I19)) -> #REF! | J20: =SUM(J13+SUM(J16:J19)) -> #REF! | K20: =SUM(K13+SUM(K16:K19)) -> #REF! | L20: =SUM(L13+SUM(L16:L19)) -> #REF! | M20: =SUM(M13+SUM(M16:M19)) -> #REF! | N20: =SUM(N13+SUM(N16:N19)) -> #REF! | O20: =SUM(O13+SUM(O16:O19)) -> #REF! | ... V20: =SUM(V13+SUM(V16:V19)) -> 0 | X20: =SUM(X13+SUM(X16:X19)) -> #REF! | Y20: =SUM(Y13+SUM(Y16:Y19)) -> #REF! | Z20: =SUM(Z13+SUM(Z16:Z19)) -> #REF! | AA20: =SUM(AA13+SUM(AA16:AA19)) -> #REF! | AB20: =SUM(AB13+SUM(AB16:AB19)) -> #REF! | AC20: =SUM(AC13+SUM(AC16:AC19)) -> #REF! | AD20: =SUM(AD13+SUM(AD16:AD19)) -> #REF! | AE20: =SUM(AE13+SUM(AE16:AE19)) -> #REF! | ... AI20: =SUM(AI13+SUM(AI16:AI19)) -> 0 | AK20: =SUM(AI20/AE20)-1 -> #REF!
B21: Operating Margin (%) | C21: =C20/C8 -> #REF! | D21: =D20/D8 -> #DIV/0! | E21: =E20/E8 -> #DIV/0! | F21: =F20/F8 -> #DIV/0! | H21: =H20/H8 -> #REF! | I21: =I20/I8 -> #REF! | J21: =J20/J8 -> #REF! | K21: =K20/K8 -> #REF! | L21: =L20/L8 -> #REF! | M21: =M20/M8 -> #REF! | N21: =N20/N8 -> #REF! | O21: =O20/O8 -> #REF! | ... V21: =V20/V8 -> #DIV/0! | X21: =X20/X8 -> #REF! | Y21: =Y20/Y8 -> #REF! | Z21: =Z20/Z8 -> #REF! | AA21: =AA20/AA8 -> #REF! | AB21: =AB20/AB8 -> #REF! | AC21: =AC20/AC8 -> #REF! | AD21: =AD20/AD8 -> #REF! | AE21: =AE20/AE8 -> #REF! | ... AI21: =AI20/AI8 -> #DIV/0! | AK21: =SUM(AI21-AE21)*10000 -> #DIV/0!
B23: (+) Depreciation and Amortization | C23: =-C19 -> #REF! | H23: =-H19 -> 13699.575 | I23: =-I19 -> 11970.422 | J23: =-J19 -> 12893.139 | K23: =-K19 -> 13894.864 | L23: =-L19 -> 14511.656 | M23: =-M19 -> 14247.558 | N23: =-N19 -> 14725.787 | O23: =-O19 -> 15534.999 | ... Q23: =-Q19 -> 16608 | X23: =SUM(G23:K23) -> 52458 | Y23: =SUM(I23:L23) -> 53270.081 | Z23: =SUM(J23:M23) -> 55547.217 | AA23: =SUM(K23:N23) -> 57379.865 | AB23: =SUM(L23:O23) -> 59020 | AC23: =SUM(M23:P23) -> 60147.344 | AD23: =SUM(N23:Q23) -> 62507.786 | AE23: =SUM(O23:R23) -> 47781.999 | AF23: =SUM(P23:S23) -> 32247 | ... AI23: =SUM(S23:V23) -> 0 | AK23: =SUM(AI23/AE23)-1 -> -1
B24: EBITDA | C24: =SUM(C20+C23) -> #REF! | D24: =SUM(D20+D23) -> 0 | E24: =SUM(E20+E23) -> 0 | F24: =SUM(F20+F23) -> 0 | H24: =SUM(H20+H23) -> #REF! | I24: =SUM(I20+I23) -> #REF! | J24: =SUM(J20+J23) -> #REF! | K24: =SUM(K20+K23) -> #REF! | L24: =SUM(L20+L23) -> #REF! | M24: =SUM(M20+M23) -> #REF! | N24: =SUM(N20+N23) -> #REF! | O24: =SUM(O20+O23) -> #REF! | ... V24: =SUM(V20+V23) -> 0 | X24: =SUM(X20+X23) -> #REF! | Y24: =SUM(Y20+Y23) -> #REF! | Z24: =SUM(Z20+Z23) -> #REF! | AA24: =SUM(AA20+AA23) -> #REF! | AB24: =SUM(AB20+AB23) -> #REF! | AC24: =SUM(AC20+AC23) -> #REF! | AD24: =SUM(AD20+AD23) -> #REF! | AE24: =SUM(AE20+AE23) -> #REF! | ... AI24: =SUM(AI20+AI23) -> 0 | AK24: =SUM(AI24/AE24)-1 -> #REF!
B25: EBITDA Margin (%) | C25: =C24/C8 -> #REF! | D25: =D24/D8 -> #DIV/0! | E25: =E24/E8 -> #DIV/0! | F25: =F24/F8 -> #DIV/0! | H25: =H24/H8 -> #REF! | I25: =I24/I8 -> #REF! | J25: =J24/J8 -> #REF! | K25: =K24/K8 -> #REF! | L25: =L24/L8 -> #REF! | M25: =M24/M8 -> #REF! | N25: =N24/N8 -> #REF! | O25: =O24/O8 -> #REF! | ... V25: =V24/V8 -> #DIV/0! | X25: =X24/X8 -> #REF! | Y25: =Y24/Y8 -> #REF! | Z25: =Z24/Z8 -> #REF! | AA25: =AA24/AA8 -> #REF! | AB25: =AB24/AB8 -> #REF! | AC25: =AC24/AC8 -> #REF! | AD25: =AD24/AD8 -> #REF! | AE25: =AE24/AE8 -> #REF! | ... AI25: =AI24/AI8 -> #DIV/0! | AK25: =SUM(AI25-AE25)*10000 -> #DIV/0!
B27: (+) Share-based Compensation | C27: ='Historical Financials'!#REF! -> #REF! | H27: ='Historical Financials'!G95 -> 2000 | I27: ='Historical Financials'!H95 -> 2638 | J27: ='Historical Financials'!I95 -> 8408 | K27: ='Historical Financials'!J95 -> -12825 | L27: ='Historical Financials'!K95 -> 18096 | M27: ='Historical Financials'!L95 -> 18096 | N27: ='Historical Financials'!M95 -> 110947 | O27: ='Historical Financials'!N95 -> -146712 | ... Q27: ='Historical Financials'!P95 -> 24 | X27: =SUM(G27:K27) -> 221 | Y27: =SUM(I27:L27) -> 16317 | Z27: =SUM(J27:M27) -> 31775 | AA27: =SUM(K27:N27) -> 134314 | AB27: =SUM(L27:O27) -> 427 | AC27: =SUM(M27:P27) -> -17646 | AD27: =SUM(N27:Q27) -> -35718 | AE27: =SUM(O27:R27) -> -146665 | AF27: =SUM(P27:S27) -> 47 | ... AI27: =SUM(S27:V27) -> 0 | AK27: =SUM(AI27/AE27)-1 -> -1
B28: Adj. EBITDA | C28: =+SUM(C24+SUM(C27:C27)) -> #REF! | D28: =+SUM(D24+SUM(D27:D27)) -> 0 | E28: =+SUM(E24+SUM(E27:E27)) -> 0 | F28: =+SUM(F24+SUM(F27:F27)) -> 0 | H28: =+SUM(H24+SUM(H27:H27)) -> #REF! | I28: =+SUM(I24+SUM(I27:I27)) -> #REF! | J28: =+SUM(J24+SUM(J27:J27)) -> #REF! | K28: =+SUM(K24+SUM(K27:K27)) -> #REF! | L28: =+SUM(L24+SUM(L27:L27)) -> #REF! | M28: =+SUM(M24+SUM(M27:M27)) -> #REF! | N28: =+SUM(N24+SUM(N27:N27)) -> #REF! | O28: =+SUM(O24+SUM(O27:O27)) -> #REF! | ... V28: =+SUM(V24+SUM(V27:V27)) -> 0 | X28: =+SUM(X24+SUM(X27:X27)) -> #REF! | Y28: =+SUM(Y24+SUM(Y27:Y27)) -> #REF! | Z28: =+SUM(Z24+SUM(Z27:Z27)) -> #REF! | AA28: =+SUM(AA24+SUM(AA27:AA27)) -> #REF! | AB28: =+SUM(AB24+SUM(AB27:AB27)) -> #REF! | AC28: =+SUM(AC24+SUM(AC27:AC27)) -> #REF! | AD28: =+SUM(AD24+SUM(AD27:AD27)) -> #REF! | AE28: =+SUM(AE24+SUM(AE27:AE27)) -> #REF! | ... AI28: =+SUM(AI24+SUM(AI27:AI27)) -> 0 | AK28: =SUM(AI28/AE28)-1 -> #REF!
B29: Adj. EBITDA Margin (%) | C29: =C28/C8 -> #REF! | D29: =D28/D8 -> #DIV/0! | E29: =E28/E8 -> #DIV/0! | F29: =F28/F8 -> #DIV/0! | H29: =H28/H8 -> #REF! | I29: =I28/I8 -> #REF! | J29: =J28/J8 -> #REF! | K29: =K28/K8 -> #REF! | L29: =L28/L8 -> #REF! | M29: =M28/M8 -> #REF! | N29: =N28/N8 -> #REF! | O29: =O28/O8 -> #REF! | ... V29: =V28/V8 -> #DIV/0! | X29: =X28/X8 -> #REF! | Y29: =Y28/Y8 -> #REF! | Z29: =Z28/Z8 -> #REF! | AA29: =AA28/AA8 -> #REF! | AB29: =AB28/AB8 -> #REF! | AC29: =AC28/AC8 -> #REF! | AD29: =AD28/AD8 -> #REF! | AE29: =AE28/AE8 -> #REF! | ... AI29: =AI28/AI8 -> #DIV/0! | AK29: =SUM(AI29-AE29)*10000 -> #DIV/0!
B31: (-) Capital Expenditures | C31: =SUM('Historical Financials'!#REF!+'Historical Financials'!#REF!) -> #REF! | H31: =SUM('Historical Financials'!G113+'Historical Financials'!G114) -> -2842085 | I31: =SUM('Historical Financials'!H113+'Historical Financials'!H114) -> -6782169 | J31: =SUM('Historical Financials'!I113+'Historical Financials'!I114) -> -10162650 | K31: =SUM('Historical Financials'!J113+'Historical Financials'!J114) -> 19773393 | L31: =SUM('Historical Financials'!K113+'Historical Financials'!K114) -> -1944596 | M31: =SUM('Historical Financials'!L113+'Historical Financials'!L114) -> -2817229 | N31: =SUM('Historical Financials'!M113+'Historical Financials'!M114) -> -3573786 | O31: =SUM('Historical Financials'!N113+'Historical Financials'!N114) -> 8321700 | ... Q31: =SUM('Historical Financials'!P113+'Historical Financials'!P114) -> -4727 | X31: =SUM(G31:K31) -> -13511 | Y31: =SUM(I31:L31) -> 883978 | Z31: =SUM(J31:M31) -> 4848918 | AA31: =SUM(K31:N31) -> 11437782 | AB31: =SUM(L31:O31) -> -13911 | AC31: =SUM(M31:P31) -> 1928323 | AD31: =SUM(N31:Q31) -> 4740825 | AE31: =SUM(O31:R31) -> 8314611 | AF31: =SUM(P31:S31) -> -7089 | ... AI31: =SUM(S31:V31) -> 0 | AK31: =SUM(AI31/AE31)-1 -> -1
B32: (-) Cash Taxes | C32: ='Historical Financials'!#REF! -> #REF! | H32: ='Historical Financials'!G31 -> 0 | I32: ='Historical Financials'!H31 -> 0 | J32: ='Historical Financials'!I31 -> 0 | K32: ='Historical Financials'!J31 -> 0 | L32: ='Historical Financials'!K31 -> 0 | M32: ='Historical Financials'!L31 -> 0 | N32: ='Historical Financials'!M31 -> 0 | O32: ='Historical Financials'!N31 -> 0 | ... Q32: ='Historical Financials'!P31 -> -3789 | X32: =SUM(G32:K32) -> 0 | Y32: =SUM(I32:L32) -> 0 | Z32: =SUM(J32:M32) -> 0 | AA32: =SUM(K32:N32) -> 0 | AB32: =SUM(L32:O32) -> 0 | AC32: =SUM(M32:P32) -> -595 | AD32: =SUM(N32:Q32) -> -4384 | AE32: =SUM(O32:R32) -> -4384 | AF32: =SUM(P32:S32) -> -4384 | ... AI32: =SUM(S32:V32) -> 0 | AK32: =SUM(AI32/AE32)-1 -> -1
B33: (-) Cash Interest | C33: 0 | H33: 0 | I33: 0 | J33: 0 | K33: =D33 -> 0 | L33: 0 | M33: 0 | N33: 0 | O33: =E33 -> 0 | P33: 0 | Q33: 0 | X33: =SUM(G33:K33) -> 0 | Y33: =SUM(I33:L33) -> 0 | Z33: =SUM(J33:M33) -> 0 | AA33: =SUM(K33:N33) -> 0 | AB33: =SUM(L33:O33) -> 0 | AC33: =SUM(M33:P33) -> 0 | AD33: =SUM(N33:Q33) -> 0 | AE33: =SUM(O33:R33) -> 0 | AF33: =SUM(P33:S33) -> 0 | ... AI33: =SUM(S33:V33) -> 0 | AK33: =SUM(AI33/AE33)-1 -> #DIV/0!
B34: (+/-) Changes in NWC | C34: =SUM('Historical Financials'!#REF!) -> #REF! | H34: =SUM('Historical Financials'!G103:G109) -> -11458236 | I34: =SUM('Historical Financials'!H103:H109) -> -14792236 | J34: =SUM('Historical Financials'!I103:I109) -> -18282379 | K34: =SUM('Historical Financials'!J103:J109) -> 44481171 | L34: =SUM('Historical Financials'!K103:K109) -> -12526845 | M34: =SUM('Historical Financials'!L103:L109) -> -17586843 | N34: =SUM('Historical Financials'!M103:M109) -> -13724584 | O34: =SUM('Historical Financials'!N103:N109) -> 43819986 | ... Q34: =SUM('Historical Financials'!P103:P109) -> -16038 | X34: =SUM(G34:K34) -> -51680 | Y34: =SUM(I34:L34) -> -1120289 | Z34: =SUM(J34:M34) -> -3914896 | AA34: =SUM(K34:N34) -> 642899 | AB34: =SUM(L34:O34) -> -18286 | AC34: =SUM(M34:P34) -> 12484040 | AD34: =SUM(N34:Q34) -> 30054845 | AE34: =SUM(O34:R34) -> 43779429 | AF34: =SUM(P34:S34) -> -40557 | ... AI34: =SUM(S34:V34) -> 0 | AK34: =SUM(AI34/AE34)-1 -> -1
B35: Discretionary Cash-Flows | C35: =SUM(C28+SUM(C31:C34)) -> #REF! | D35: =SUM(D28+SUM(D31:D34)) -> 0 | E35: =SUM(E28+SUM(E31:E34)) -> 0 | F35: =SUM(F28+SUM(F31:F34)) -> 0 | H35: =SUM(H28+SUM(H31:H34)) -> #REF! | I35: =SUM(I28+SUM(I31:I34)) -> #REF! | J35: =SUM(J28+SUM(J31:J34)) -> #REF! | K35: =SUM(K28+SUM(K31:K34)) -> #REF! | L35: =SUM(L28+SUM(L31:L34)) -> #REF! | M35: =SUM(M28+SUM(M31:M34)) -> #REF! | N35: =SUM(N28+SUM(N31:N34)) -> #REF! | O35: =SUM(O28+SUM(O31:O34)) -> #REF! | ... V35: =SUM(V28+SUM(V31:V34)) -> 0 | X35: =SUM(X28+SUM(X31:X34)) -> #REF! | Y35: =SUM(Y28+SUM(Y31:Y34)) -> #REF! | Z35: =SUM(Z28+SUM(Z31:Z34)) -> #REF! | AA35: =SUM(AA28+SUM(AA31:AA34)) -> #REF! | AB35: =SUM(AB28+SUM(AB31:AB34)) -> #REF! | AC35: =SUM(AC28+SUM(AC31:AC34)) -> #REF! | AD35: =SUM(AD28+SUM(AD31:AD34)) -> #REF! | AE35: =SUM(AE28+SUM(AE31:AE34)) -> #REF! | ... AI35: =SUM(AI28+SUM(AI31:AI34)) -> 0 | AK35: =SUM(AI35/AE35)-1 -> #REF!
B37: (+/-) Proceeds / (Purchases) of Equity, net | C37: ='Historical Financials'!#REF! -> #REF! | H37: ='Historical Financials'!#REF! -> #REF! | I37: ='Historical Financials'!#REF! -> #REF! | J37: ='Historical Financials'!#REF! -> #REF! | K37: ='Historical Financials'!#REF! -> #REF! | L37: ='Historical Financials'!#REF! -> #REF! | M37: ='Historical Financials'!#REF! -> #REF! | N37: ='Historical Financials'!#REF! -> #REF! | O37: ='Historical Financials'!#REF! -> #REF! | ... Q37: ='Historical Financials'!#REF! -> #REF! | X37: =SUM(G37:K37) -> #REF! | Y37: =SUM(I37:L37) -> #REF! | Z37: =SUM(J37:M37) -> #REF! | AA37: =SUM(K37:N37) -> #REF! | AB37: =SUM(L37:O37) -> #REF! | AC37: =SUM(M37:P37) -> #REF! | AD37: =SUM(N37:Q37) -> #REF! | AE37: =SUM(O37:R37) -> #REF! | AF37: =SUM(P37:S37) -> #REF! | ... AI37: =SUM(S37:V37) -> 0
B38: (+/-) Maturities / (Purchases) of available-for-sale securities | C38: =SUM('Historical Financials'!#REF!) -> #REF! | H38: =SUM('Historical Financials'!#REF!) -> #REF! | I38: =SUM('Historical Financials'!#REF!) -> #REF! | J38: =SUM('Historical Financials'!#REF!) -> #REF! | K38: =SUM('Historical Financials'!#REF!) -> #REF! | L38: =SUM('Historical Financials'!#REF!) -> #REF! | M38: =SUM('Historical Financials'!#REF!) -> #REF! | N38: =SUM('Historical Financials'!#REF!) -> #REF! | O38: =SUM('Historical Financials'!#REF!) -> #REF! | ... Q38: =SUM('Historical Financials'!#REF!) -> #REF! | X38: =SUM(G38:K38) -> #REF! | Y38: =SUM(I38:L38) -> #REF! | Z38: =SUM(J38:M38) -> #REF! | AA38: =SUM(K38:N38) -> #REF! | AB38: =SUM(L38:O38) -> #REF! | AC38: =SUM(M38:P38) -> #REF! | AD38: =SUM(N38:Q38) -> #REF! | AE38: =SUM(O38:R38) -> #REF! | AF38: =SUM(P38:S38) -> #REF! | ... AI38: =SUM(S38:V38) -> 0
B39: (+/-) Divestitures / (Acquisitions) | C39: ='Historical Financials'!#REF! -> #REF! | H39: ='Historical Financials'!#REF! -> #REF! | I39: ='Historical Financials'!#REF! -> #REF! | J39: ='Historical Financials'!#REF! -> #REF! | K39: ='Historical Financials'!#REF! -> #REF! | L39: ='Historical Financials'!#REF! -> #REF! | M39: ='Historical Financials'!#REF! -> #REF! | N39: ='Historical Financials'!#REF! -> #REF! | O39: ='Historical Financials'!#REF! -> #REF! | ... Q39: ='Historical Financials'!#REF! -> #REF! | X39: =SUM(G39:K39) -> #REF! | Y39: =SUM(I39:L39) -> #REF! | Z39: =SUM(J39:M39) -> #REF! | AA39: =SUM(K39:N39) -> #REF! | AB39: =SUM(L39:O39) -> #REF! | AC39: =SUM(M39:P39) -> #REF! | AD39: =SUM(N39:Q39) -> #REF! | AE39: =SUM(O39:R39) -> #REF! | AF39: =SUM(P39:S39) -> #REF! | ... AI39: =SUM(S39:V39) -> 0
B40: (+/-) Other Investing Activities | C40: ='Historical Financials'!#REF! -> #REF! | H40: ='Historical Financials'!#REF! -> #REF! | I40: ='Historical Financials'!#REF! -> #REF! | J40: ='Historical Financials'!#REF! -> #REF! | K40: ='Historical Financials'!#REF! -> #REF! | L40: ='Historical Financials'!#REF! -> #REF! | M40: ='Historical Financials'!#REF! -> #REF! | N40: ='Historical Financials'!#REF! -> #REF! | O40: ='Historical Financials'!#REF! -> #REF! | ... Q40: ='Historical Financials'!#REF! -> #REF! | X40: =SUM(G40:K40) -> #REF! | Y40: =SUM(I40:L40) -> #REF! | Z40: =SUM(J40:M40) -> #REF! | AA40: =SUM(K40:N40) -> #REF! | AB40: =SUM(L40:O40) -> #REF! | AC40: =SUM(M40:P40) -> #REF! | AD40: =SUM(N40:Q40) -> #REF! | AE40: =SUM(O40:R40) -> #REF! | AF40: =SUM(P40:S40) -> #REF! | ... AI40: =SUM(S40:V40) -> 0
B41: (+/-) Other Financing Activities | C41: ='Historical Financials'!#REF! -> #REF! | H41: ='Historical Financials'!#REF! -> #REF! | I41: ='Historical Financials'!#REF! -> #REF! | J41: ='Historical Financials'!#REF! -> #REF! | K41: ='Historical Financials'!#REF! -> #REF! | L41: ='Historical Financials'!#REF! -> #REF! | M41: ='Historical Financials'!#REF! -> #REF! | N41: ='Historical Financials'!#REF! -> #REF! | O41: ='Historical Financials'!#REF! -> #REF! | ... Q41: ='Historical Financials'!#REF! -> #REF! | X41: =SUM(G41:K41) -> #REF! | Y41: =SUM(I41:L41) -> #REF! | Z41: =SUM(J41:M41) -> #REF! | AA41: =SUM(K41:N41) -> #REF! | AB41: =SUM(L41:O41) -> #REF! | AC41: =SUM(M41:P41) -> #REF! | AD41: =SUM(N41:Q41) -> #REF! | AE41: =SUM(O41:R41) -> #REF! | AF41: =SUM(P41:S41) -> #REF! | ... AI41: =SUM(S41:V41) -> 0
B42: (+/-) Other Operating Activities | C42: ='Historical Financials'!#REF! -> #REF! | H42: ='Historical Financials'!#REF! -> #REF! | I42: ='Historical Financials'!#REF! -> #REF! | J42: ='Historical Financials'!#REF! -> #REF! | K42: ='Historical Financials'!#REF! -> #REF! | L42: ='Historical Financials'!#REF! -> #REF! | M42: ='Historical Financials'!#REF! -> #REF! | N42: ='Historical Financials'!#REF! -> #REF! | O42: ='Historical Financials'!#REF! -> #REF! | ... Q42: ='Historical Financials'!#REF! -> #REF! | X42: =SUM(G42:K42) -> #REF! | Y42: =SUM(I42:L42) -> #REF! | Z42: =SUM(J42:M42) -> #REF! | AA42: =SUM(K42:N42) -> #REF! | AB42: =SUM(L42:O42) -> #REF! | AC42: =SUM(M42:P42) -> #REF! | AD42: =SUM(N42:Q42) -> #REF! | AE42: =SUM(O42:R42) -> #REF! | AF42: =SUM(P42:S42) -> #REF! | ... AI42: =SUM(S42:V42) -> 0
B43: (+/-) Other | H43: =SUM(H48:H49)-SUM(C48:C49)-SUM(H35:H42) -> #REF! | I43: =SUM(I48:I49)-SUM(H48:H49)-SUM(I35:I42) -> #REF! | J43: =SUM(J48:J49)-SUM(I48:I49)-SUM(J35:J42) -> #REF! | K43: =SUM(K48:K49)-SUM(J48:J49)-SUM(K35:K42) -> #REF! | L43: =SUM(L48:L49)-SUM(K48:K49)-SUM(L35:L42) -> #REF! | M43: =SUM(M48:M49)-SUM(L48:L49)-SUM(M35:M42) -> #REF! | N43: =SUM(N48:N49)-SUM(M48:M49)-SUM(N35:N42) -> #REF! | O43: =SUM(O48:O49)-SUM(N48:N49)-SUM(O35:O42) -> #REF! | P43: =SUM(P48:P49)-SUM(O48:O49)-SUM(P35:P42) -> #REF! | Q43: =SUM(Q48:Q49)-SUM(P48:P49)-SUM(Q35:Q42) -> #REF! | X43: =SUM(G43:K43) -> #REF! | Y43: =SUM(I43:L43) -> #REF! | Z43: =SUM(J43:M43) -> #REF! | AA43: =SUM(K43:N43) -> #REF! | AB43: =SUM(L43:O43) -> #REF! | AC43: =SUM(M43:P43) -> #REF! | AD43: =SUM(N43:Q43) -> #REF! | AE43: =SUM(O43:R43) -> #REF! | AF43: =SUM(P43:S43) -> #REF! | ... AI43: =SUM(S43:V43) -> 0
B44: Free-Cash Flows | C44: =SUM(C35+SUM(C37:C43)) -> #REF! | D44: =SUM(D35+SUM(D37:D43)) -> 0 | E44: =SUM(E35+SUM(E37:E43)) -> 0 | F44: =SUM(F35+SUM(F37:F43)) -> 0 | H44: =SUM(H35+SUM(H37:H43)) -> #REF! | I44: =SUM(I35+SUM(I37:I43)) -> #REF! | J44: =SUM(J35+SUM(J37:J43)) -> #REF! | K44: =SUM(K35+SUM(K37:K43)) -> #REF! | L44: =SUM(L35+SUM(L37:L43)) -> #REF! | M44: =SUM(M35+SUM(M37:M43)) -> #REF! | N44: =SUM(N35+SUM(N37:N43)) -> #REF! | O44: =SUM(O35+SUM(O37:O43)) -> #REF! | ... V44: =SUM(V35+SUM(V37:V43)) -> 0 | X44: =SUM(X35+SUM(X37:X43)) -> #REF! | Y44: =SUM(Y35+SUM(Y37:Y43)) -> #REF! | Z44: =SUM(Z35+SUM(Z37:Z43)) -> #REF! | AA44: =SUM(AA35+SUM(AA37:AA43)) -> #REF! | AB44: =SUM(AB35+SUM(AB37:AB43)) -> #REF! | AC44: =SUM(AC35+SUM(AC37:AC43)) -> #REF! | AD44: =SUM(AD35+SUM(AD37:AD43)) -> #REF! | AE44: =SUM(AE35+SUM(AE37:AE43)) -> #REF! | ... AI44: =SUM(AI35+SUM(AI37:AI43)) -> 0
B46: Capitalization
B48: Cash & Cash Equivelants | C48: ='Historical Financials'!#REF! -> #REF! | H48: ='Historical Financials'!G46 -> 69504.946 | I48: ='Historical Financials'!H46 -> 52415.053 | J48: ='Historical Financials'!I46 -> 34906.02 | K48: ='Historical Financials'!J46 -> 86522 | L48: ='Historical Financials'!K46 -> 69204.163 | M48: ='Historical Financials'!L46 -> 62512.889 | N48: ='Historical Financials'!M46 -> 74156.765 | O48: ='Historical Financials'!N46 -> 51352 | ... Q48: ='Historical Financials'!P46 -> 88244 | X48: =K48 -> 86522 | Y48: =L48 -> 69204.163 | Z48: =M48 -> 62512.889 | AA48: =N48 -> 74156.765 | AB48: =O48 -> 51352 | AC48: =P48 -> 45325 | AD48: =Q48 -> 88244 | AE48: =R48 -> 0 | ... AI48: =V48 -> 0
B49: Restricted Cash | C49: ='Historical Financials'!#REF! -> #REF! | H49: ='Historical Financials'!G49 -> 5519.301 | I49: ='Historical Financials'!H49 -> 5399.928 | J49: ='Historical Financials'!I49 -> 5372.484 | K49: ='Historical Financials'!J49 -> 5095 | L49: ='Historical Financials'!K49 -> 4378.681 | M49: ='Historical Financials'!L49 -> 5218.735 | N49: ='Historical Financials'!M49 -> 5107.455 | O49: ='Historical Financials'!N49 -> 5334 | ... Q49: ='Historical Financials'!P49 -> 5524 | X49: =K49 -> 5095 | Y49: =L49 -> 4378.681 | Z49: =M49 -> 5218.735 | AA49: =N49 -> 5107.455 | AB49: =O49 -> 5334 | AC49: =P49 -> 3741 | AD49: =Q49 -> 5524 | AE49: =R49 -> 0 | ... AI49: =V49 -> 0
B50: Short-term Investments | C50: ='Historical Financials'!#REF! -> #REF! | H50: ='Historical Financials'!#REF! -> #REF! | I50: ='Historical Financials'!#REF! -> #REF! | J50: ='Historical Financials'!#REF! -> #REF! | K50: ='Historical Financials'!#REF! -> #REF! | L50: ='Historical Financials'!#REF! -> #REF! | M50: ='Historical Financials'!#REF! -> #REF! | N50: ='Historical Financials'!#REF! -> #REF! | O50: ='Historical Financials'!#REF! -> #REF! | ... Q50: ='Historical Financials'!#REF! -> #REF! | X50: =K50 -> #REF! | Y50: =L50 -> #REF! | Z50: =M50 -> #REF! | AA50: =N50 -> #REF! | AB50: =O50 -> #REF! | AC50: =P50 -> #REF! | AD50: =Q50 -> #REF! | AE50: =R50 -> 0 | ... AI50: =V50 -> 0
B51: Long-term Investments | C51: ='Historical Financials'!#REF! -> #REF! | H51: ='Historical Financials'!G53 -> 53220.048 | I51: ='Historical Financials'!H53 -> 54951.267 | J51: ='Historical Financials'!I53 -> 56946.009 | K51: ='Historical Financials'!J53 -> 58261 | L51: ='Historical Financials'!K53 -> 57370.783 | M51: ='Historical Financials'!L53 -> 56305.62 | N51: ='Historical Financials'!M53 -> 54814.607 | O51: ='Historical Financials'!N53 -> 53835 | ... Q51: ='Historical Financials'!P53 -> 54326 | X51: =K51 -> 58261 | Y51: =L51 -> 57370.783 | Z51: =M51 -> 56305.62 | AA51: =N51 -> 54814.607 | AB51: =O51 -> 53835 | AC51: =P51 -> 55317 | AD51: =Q51 -> 54326 | AE51: =R51 -> 0 | ... AI51: =V51 -> 0
B52: Total Liquidity | C52: =SUM(C48:C51) -> #REF! | D52: =SUM(D48:D51) -> 0 | E52: =SUM(E48:E51) -> 0 | F52: =SUM(F48:F51) -> 0 | H52: =SUM(H48:H51) -> #REF! | I52: =SUM(I48:I51) -> #REF! | J52: =SUM(J48:J51) -> #REF! | K52: =SUM(K48:K51) -> #REF! | L52: =SUM(L48:L51) -> #REF! | M52: =SUM(M48:M51) -> #REF! | N52: =SUM(N48:N51) -> #REF! | O52: =SUM(O48:O51) -> #REF! | ... V52: =SUM(V48:V51) -> 0 | X52: =SUM(X48:X51) -> #REF! | Y52: =SUM(Y48:Y51) -> #REF! | Z52: =SUM(Z48:Z51) -> #REF! | AA52: =SUM(AA48:AA51) -> #REF! | AB52: =SUM(AB48:AB51) -> #REF! | AC52: =SUM(AC48:AC51) -> #REF! | AD52: =SUM(AD48:AD51) -> #REF! | AE52: =SUM(AE48:AE51) -> 0 | ... AI52: =SUM(AI48:AI51) -> 0
B54: Balance Sheet Metrics:
B55: Accounts Receivable | C55: ='Historical Financials'!#REF! -> #REF! | H55: ='Historical Financials'!#REF! -> #REF! | I55: ='Historical Financials'!#REF! -> #REF! | J55: ='Historical Financials'!#REF! -> #REF! | K55: ='Historical Financials'!#REF! -> #REF! | L55: ='Historical Financials'!#REF! -> #REF! | M55: ='Historical Financials'!#REF! -> #REF! | N55: ='Historical Financials'!#REF! -> #REF! | O55: ='Historical Financials'!#REF! -> #REF! | ... Q55: ='Historical Financials'!#REF! -> #REF! | X55: =K55 -> #REF! | Y55: =L55 -> #REF! | Z55: =M55 -> #REF! | AA55: =N55 -> #REF! | AB55: =O55 -> #REF! | AC55: =P55 -> #REF! | AD55: =Q55 -> #REF! | AE55: =R55 -> 0 | ... AI55: =V55 -> 0
B56: Accounts Payable | C56: ='Historical Financials'!#REF! -> #REF! | H56: ='Historical Financials'!G61 -> 14115.135 | I56: ='Historical Financials'!H61 -> 11388.048 | J56: ='Historical Financials'!I61 -> 25197.806 | K56: ='Historical Financials'!J61 -> 13229 | L56: ='Historical Financials'!K61 -> 12956.486 | M56: ='Historical Financials'!L61 -> 12084.529 | N56: ='Historical Financials'!M61 -> 10851.446 | O56: ='Historical Financials'!N61 -> 15660 | ... Q56: ='Historical Financials'!P61 -> 14179 | X56: =K56 -> 13229 | Y56: =L56 -> 12956.486 | Z56: =M56 -> 12084.529 | AA56: =N56 -> 10851.446 | AB56: =O56 -> 15660 | AC56: =P56 -> 17186 | AD56: =Q56 -> 14179 | AE56: =R56 -> 0 | ... AI56: =V56 -> 0
B57: Unearned Revenue, Current | C57: ='Historical Financials'!#REF! -> #REF! | H57: ='Historical Financials'!#REF! -> #REF! | I57: ='Historical Financials'!#REF! -> #REF! | J57: ='Historical Financials'!#REF! -> #REF! | K57: ='Historical Financials'!#REF! -> #REF! | L57: ='Historical Financials'!#REF! -> #REF! | M57: ='Historical Financials'!#REF! -> #REF! | N57: ='Historical Financials'!#REF! -> #REF! | O57: ='Historical Financials'!#REF! -> #REF! | ... Q57: ='Historical Financials'!#REF! -> #REF! | X57: =K57 -> #REF! | Y57: =L57 -> #REF! | Z57: =M57 -> #REF! | AA57: =N57 -> #REF! | AB57: =O57 -> #REF! | AC57: =P57 -> #REF! | AD57: =Q57 -> #REF! | AE57: =R57 -> 0 | ... AI57: =V57 -> 0
B58: Unearned Revenue, Non-Current | C58: ='Historical Financials'!#REF! -> #REF! | H58: ='Historical Financials'!#REF! -> #REF! | I58: ='Historical Financials'!#REF! -> #REF! | J58: ='Historical Financials'!#REF! -> #REF! | K58: ='Historical Financials'!#REF! -> #REF! | L58: ='Historical Financials'!#REF! -> #REF! | M58: ='Historical Financials'!#REF! -> #REF! | N58: ='Historical Financials'!#REF! -> #REF! | O58: ='Historical Financials'!#REF! -> #REF! | ... Q58: ='Historical Financials'!#REF! -> #REF! | X58: =K58 -> #REF! | Y58: =L58 -> #REF! | Z58: =M58 -> #REF! | AA58: =N58 -> #REF! | AB58: =O58 -> #REF! | AC58: =P58 -> #REF! | AD58: =Q58 -> #REF! | AE58: =R58 -> 0 | ... AI58: =V58 -> 0
B59: Property Plant, and Equiptment | C59: ='Historical Financials'!#REF! -> #REF! | H59: ='Historical Financials'!G55 -> 3529.509 | I59: ='Historical Financials'!H55 -> 3529.509 | J59: ='Historical Financials'!I55 -> 3529.509 | K59: ='Historical Financials'!J55 -> 3530 | L59: ='Historical Financials'!K55 -> 3529.509 | M59: ='Historical Financials'!L55 -> 3529.509 | N59: ='Historical Financials'!M55 -> 3529.509 | O59: ='Historical Financials'!N55 -> 3530 | ... Q59: ='Historical Financials'!P55 -> 3530 | X59: =K59 -> 3530 | Y59: =L59 -> 3529.509 | Z59: =M59 -> 3529.509 | AA59: =N59 -> 3529.509 | AB59: =O59 -> 3530 | AC59: =P59 -> 3530 | AD59: =Q59 -> 3530 | AE59: =R59 -> 0 | ... AI59: =V59 -> 0
B60: Current Liabilities | C60: ='Historical Financials'!#REF! -> #REF! | H60: ='Historical Financials'!G65 -> 31566.512 | I60: ='Historical Financials'!H65 -> 28071.613 | J60: ='Historical Financials'!I65 -> 44440.327 | K60: ='Historical Financials'!J65 -> 39267 | L60: ='Historical Financials'!K65 -> 36727.829 | M60: ='Historical Financials'!L65 -> 41952.497 | N60: ='Historical Financials'!M65 -> 41840.897 | O60: ='Historical Financials'!N65 -> 49806 | ... Q60: ='Historical Financials'!P65 -> 44177 | X60: =K60 -> 39267 | Y60: =L60 -> 36727.829 | Z60: =M60 -> 41952.497 | AA60: =N60 -> 41840.897 | AB60: =O60 -> 49806 | AC60: =P60 -> 53088 | AD60: =Q60 -> 44177 | AE60: =R60 -> 0 | ... AI60: =V60 -> 0
B61: Total Liabilities | C61: ='Historical Financials'!#REF! -> #REF! | H61: ='Historical Financials'!G73 -> 181099.43 | I61: ='Historical Financials'!H73 -> 182531.8 | J61: ='Historical Financials'!I73 -> 200173.03 | K61: ='Historical Financials'!J73 -> 196487 | L61: ='Historical Financials'!K73 -> 195132.92 | M61: ='Historical Financials'!L73 -> 196264.75 | N61: ='Historical Financials'!M73 -> 197559.22 | O61: ='Historical Financials'!N73 -> 193976 | ... Q61: ='Historical Financials'!P73 -> 188130 | X61: =K61 -> 196487 | Y61: =L61 -> 195132.92 | Z61: =M61 -> 196264.75 | AA61: =N61 -> 197559.22 | AB61: =O61 -> 193976 | AC61: =P61 -> 197169 | AD61: =Q61 -> 188130 | AE61: =R61 -> 0 | ... AI61: =V61 -> 0
B63: Consolidated Debt | C63: 0 | H63: 0 | I63: 0 | J63: 0 | K63: =D63 -> 0 | L63: 0 | M63: 0 | N63: 0 | O63: =E63 -> 0 | P63: 0 | Q63: 0 | X63: =K63 -> 0 | Y63: =L63 -> 0 | Z63: =M63 -> 0 | AA63: =N63 -> 0 | AB63: =O63 -> 0 | AC63: =P63 -> 0 | AD63: =Q63 -> 0 | AE63: =R63 -> 0 | ... AI63: =V63 -> 0
B64: Total Debt | C64: =SUM(C63:C63) -> 0 | D64: =SUM(D63:D63) -> 0 | E64: =SUM(E63:E63) -> 0 | F64: =SUM(F63:F63) -> 0 | H64: =SUM(H63:H63) -> 0 | I64: =SUM(I63:I63) -> 0 | J64: =SUM(J63:J63) -> 0 | K64: =SUM(K63:K63) -> 0 | L64: =SUM(L63:L63) -> 0 | M64: =SUM(M63:M63) -> 0 | N64: =SUM(N63:N63) -> 0 | O64: =SUM(O63:O63) -> 0 | ... V64: =SUM(V63:V63) -> 0 | X64: =SUM(X63:X63) -> 0 | Y64: =SUM(Y63:Y63) -> 0 | Z64: =SUM(Z63:Z63) -> 0 | AA64: =SUM(AA63:AA63) -> 0 | AB64: =SUM(AB63:AB63) -> 0 | AC64: =SUM(AC63:AC63) -> 0 | AD64: =SUM(AD63:AD63) -> 0 | AE64: =SUM(AE63:AE63) -> 0 | ... AI64: =SUM(AI63:AI63) -> 0
B66: Total Shareholder Equity | C66: ='Historical Financials'!#REF! -> #REF! | H66: ='Historical Financials'!G79 -> 126933.07 | I66: ='Historical Financials'!H79 -> 114400.53 | J66: ='Historical Financials'!I79 -> 100384.54 | K66: ='Historical Financials'!J79 -> 151974 | L66: ='Historical Financials'!K79 -> 145654.62 | M66: ='Historical Financials'!L79 -> 146762.29 | N66: ='Historical Financials'!M79 -> 151437.35 | O66: ='Historical Financials'!N79 -> 135206 | ... Q66: ='Historical Financials'!P79 -> 188269 | X66: =K66 -> 151974 | Y66: =L66 -> 145654.62 | Z66: =M66 -> 146762.29 | AA66: =N66 -> 151437.35 | AB66: =O66 -> 135206 | AC66: =P66 -> 153706 | AD66: =Q66 -> 188269 | AE66: =R66 -> 0 | ... AI66: =V66 -> 0
B67: Total Book Capitalization | C67: =SUM(C64:C66) -> #REF! | D67: =SUM(D64:D66) -> 0 | E67: =SUM(E64:E66) -> 0 | F67: =SUM(F64:F66) -> 0 | H67: =SUM(H64:H66) -> 126933.07 | I67: =SUM(I64:I66) -> 114400.53 | J67: =SUM(J64:J66) -> 100384.54 | K67: =SUM(K64:K66) -> 151974 | L67: =SUM(L64:L66) -> 145654.62 | M67: =SUM(M64:M66) -> 146762.29 | N67: =SUM(N64:N66) -> 151437.35 | O67: =SUM(O64:O66) -> 135206 | ... V67: =SUM(V64:V66) -> 0 | X67: =SUM(X64:X66) -> 151974 | Y67: =SUM(Y64:Y66) -> 145654.62 | Z67: =SUM(Z64:Z66) -> 146762.29 | AA67: =SUM(AA64:AA66) -> 151437.35 | AB67: =SUM(AB64:AB66) -> 135206 | AC67: =SUM(AC64:AC66) -> 153706 | AD67: =SUM(AD64:AD66) -> 188269 | AE67: =SUM(AE64:AE66) -> 0 | ... AI67: =SUM(AI64:AI66) -> 0
B69: Credit Metrics
B71: Total Leverage | C71: NM | L71: NM | M71: NM | N71: NM | O71: NM | P71: NM | Q71: NM | X71: NM | Y71: NM | Z71: NM | AA71: NM | AB71: NM | AC71: NM | AD71: NM
B72: Net Leverage (C&CE) | C72: NM | L72: NM | M72: NM | N72: NM | O72: NM | P72: NM | Q72: NM | X72: NM | Y72: NM | Z72: NM | AA72: NM | AB72: NM | AC72: NM | AD72: NM
B73: Interest Coverage | C73: NM | L73: NM | M73: NM | N73: NM | O73: NM | P73: NM | Q73: NM | X73: NM | Y73: NM | Z73: NM | AA73: NM | AB73: NM | AC73: NM | AD73: NM
B74: Debt Service Coverage | C74: NM | L74: NM | M74: NM | N74: NM | O74: NM | P74: NM | Q74: NM | X74: NM | Y74: NM | Z74: NM | AA74: NM | AB74: NM | AC74: NM | AD74: NM
B75: Fixed Charge Coverage | C75: NM | L75: NM | M75: NM | N75: NM | O75: NM | P75: NM | Q75: NM | X75: NM | Y75: NM | Z75: NM | AA75: NM | AB75: NM | AC75: NM | AD75: NM
B76: Debt-to-Book Capitalization | C76: NM | L76: NM | M76: NM | N76: NM | O76: NM | P76: NM | Q76: NM | X76: NM | Y76: NM | Z76: NM | AA76: NM | AB76: NM | AC76: NM | AD76: NM
