Workbook

Sheet Historical Financials
B2: Paramount Global (NASDAQ: PARA)
B3: Historical Financials
B4: ($ In Millions, except EPS)
A6: X | B6: Income Statement | D6: FYE | H6: Quarterly | N6: Quarterly | AA6: LTM | AG6: Variance
B7: Fiscal Period | C7: 2021 | D7: 2022 | E7: 2023 | F7: 2024 | H7: 1Q23 | I7: 2Q23 | J7: 3Q23 | K7: 4Q23 | L7: 1Q24 | M7: 2Q24 | N7: 3Q24 | O7: 4Q24 | P7: 1Q25 | Q7: 2Q25 | R7: 3Q25 | S7: 4Q25 | T7: 1Q26 | V7: =K7 -> 4Q23 | W7: =L7 -> 1Q24 | X7: =M7 -> 2Q24 | Y7: =N7 -> 3Q24 | Z7: =O7 -> 4Q24 | AA7: =P7 -> 1Q25 | AB7: =Q7 -> 2Q25 | AC7: =R7 -> 3Q25 | ... AE7: =T7 -> 1Q26
B8: Fiscal Period End Date | C8: 44561 | D8: 44926 | E8: 45291 | F8: 45657 | H8: XXX | I8: XXX | J8: XXX | K8: =D8 -> 44926 | L8: XXX | M8: XXX | N8: XXX | O8: =E8 -> 45291 | P8: XXX | Q8: XXX | R8: XXX | S8: =F8 -> 45657 | T8: XXX | V8: =K8 -> 44926 | W8: =L8 -> XXX | X8: =M8 -> XXX | Y8: =N8 -> XXX | Z8: =O8 -> 45291 | AA8: =P8 -> XXX | AB8: =Q8 -> XXX | AC8: =R8 -> XXX | ... AE8: =T8 -> XXX
B10: Consolidated Revenue | C10: 28586 | D10: 30154 | E10: 29652 | F10: 29213 | K10: =SUM(D10-SUM(H10:J10)) -> 30154 | O10: =SUM(E10-SUM(L10:N10)) -> 29652 | S10: =SUM(F10-SUM(P10:R10)) -> 29213 | V10: =SUM(H10:K10) -> 30154 | W10: =SUM(I10:L10) -> 30154 | X10: =SUM(J10:M10) -> 30154 | Y10: =SUM(K10:N10) -> 30154 | Z10: =SUM(L10:O10) -> 29652 | AA10: =SUM(M10:P10) -> 29652 | AB10: =SUM(N10:Q10) -> 29652 | AC10: =SUM(O10:R10) -> 29652 | ... AE10: =SUM(Q10:T10) -> 29213 | AG10: =SUM(AE10/AA10)-1 -> -0.014805072
B11: Total Revenue | C11: =+SUM(C10:C10) -> 28586 | D11: =+SUM(D10:D10) -> 30154 | E11: =+SUM(E10:E10) -> 29652 | F11: =+SUM(F10:F10) -> 29213 | H11: =+SUM(H10:H10) -> 0 | I11: =+SUM(I10:I10) -> 0 | J11: =+SUM(J10:J10) -> 0 | K11: =+SUM(K10:K10) -> 30154 | L11: =+SUM(L10:L10) -> 0 | M11: =+SUM(M10:M10) -> 0 | N11: =+SUM(N10:N10) -> 0 | O11: =+SUM(O10:O10) -> 29652 | ... T11: =+SUM(T10:T10) -> 0 | V11: =+SUM(V10:V10) -> 30154 | W11: =+SUM(W10:W10) -> 30154 | X11: =+SUM(X10:X10) -> 30154 | Y11: =+SUM(Y10:Y10) -> 30154 | Z11: =+SUM(Z10:Z10) -> 29652 | AA11: =+SUM(AA10:AA10) -> 29652 | AB11: =+SUM(AB10:AB10) -> 29652 | AC11: =+SUM(AC10:AC10) -> 29652 | ... AE11: =+SUM(AE10:AE10) -> 29213 | AG11: =SUM(AE11/AA11)-1 -> -0.014805072
B13: Operating | C13: -17744 | D13: -19845 | E13: -20017 | F13: -19437 | K13: =SUM(D13-SUM(H13:J13)) -> -19845 | O13: =SUM(E13-SUM(L13:N13)) -> -20017 | S13: =SUM(F13-SUM(P13:R13)) -> -19437 | V13: =SUM(H13:K13) -> -19845 | W13: =SUM(I13:L13) -> -19845 | X13: =SUM(J13:M13) -> -19845 | Y13: =SUM(K13:N13) -> -19845 | Z13: =SUM(L13:O13) -> -20017 | AA13: =SUM(M13:P13) -> -20017 | AB13: =SUM(N13:Q13) -> -20017 | AC13: =SUM(O13:R13) -> -20017 | ... AE13: =SUM(Q13:T13) -> -19437 | AG13: =SUM(AE13/AA13)-1 -> -0.028975371
B14: Programming charges | C14: 0 | D14: 0 | E14: -2371 | F14: -1118 | K14: =SUM(D14-SUM(H14:J14)) -> 0 | O14: =SUM(E14-SUM(L14:N14)) -> -2371 | S14: =SUM(F14-SUM(P14:R14)) -> -1118 | T14: 0 | V14: =SUM(H14:K14) -> 0 | W14: =SUM(I14:L14) -> 0 | X14: =SUM(J14:M14) -> 0 | Y14: =SUM(K14:N14) -> 0 | Z14: =SUM(L14:O14) -> -2371 | AA14: =SUM(M14:P14) -> -2371 | AB14: =SUM(N14:Q14) -> -2371 | AC14: =SUM(O14:R14) -> -2371 | ... AE14: =SUM(Q14:T14) -> -1118 | AG14: =SUM(AE14/AA14)-1 -> -0.528469
B15: Selling, general and administrative | C15: -6398 | D15: -7033 | E15: -7245 | F15: -6658 | K15: =SUM(D15-SUM(H15:J15)) -> -7033 | O15: =SUM(E15-SUM(L15:N15)) -> -7245 | S15: =SUM(F15-SUM(P15:R15)) -> -6658 | V15: =SUM(H15:K15) -> -7033 | W15: =SUM(I15:L15) -> -7033 | X15: =SUM(J15:M15) -> -7033 | Y15: =SUM(K15:N15) -> -7033 | Z15: =SUM(L15:O15) -> -7245 | AA15: =SUM(M15:P15) -> -7245 | AB15: =SUM(N15:Q15) -> -7245 | AC15: =SUM(O15:R15) -> -7245 | ... AE15: =SUM(Q15:T15) -> -6658 | AG15: =SUM(AE15/AA15)-1 -> -0.081021394
B16: Depreciation and amortization | C16: -390 | D16: -378 | E16: -418 | F16: -392 | K16: =SUM(D16-SUM(H16:J16)) -> -378 | O16: =SUM(E16-SUM(L16:N16)) -> -418 | S16: =SUM(F16-SUM(P16:R16)) -> -392 | V16: =SUM(H16:K16) -> -378 | W16: =SUM(I16:L16) -> -378 | X16: =SUM(J16:M16) -> -378 | Y16: =SUM(K16:N16) -> -378 | Z16: =SUM(L16:O16) -> -418 | AA16: =SUM(M16:P16) -> -418 | AB16: =SUM(N16:Q16) -> -418 | AC16: =SUM(O16:R16) -> -418 | ... AE16: =SUM(Q16:T16) -> -392 | AG16: =SUM(AE16/AA16)-1 -> -0.062200957
B17: Impairment charges | C17: 0 | D17: -27 | E17: -83 | F17: -6130 | K17: =SUM(D17-SUM(H17:J17)) -> -27 | O17: =SUM(E17-SUM(L17:N17)) -> -83 | S17: =SUM(F17-SUM(P17:R17)) -> -6130 | V17: =SUM(H17:K17) -> -27 | W17: =SUM(I17:L17) -> -27 | X17: =SUM(J17:M17) -> -27 | Y17: =SUM(K17:N17) -> -27 | Z17: =SUM(L17:O17) -> -83 | AA17: =SUM(M17:P17) -> -83 | AB17: =SUM(N17:Q17) -> -83 | AC17: =SUM(O17:R17) -> -83 | ... AE17: =SUM(Q17:T17) -> -6130 | AG17: =SUM(AE17/AA17)-1 -> 72.855422
B18: Restructuring, transaction-related items, and other corporate matters | C18: -100 | D18: -585 | E18: 31 | F18: -747 | K18: =SUM(D18-SUM(H18:J18)) -> -585 | O18: =SUM(E18-SUM(L18:N18)) -> 31 | S18: =SUM(F18-SUM(P18:R18)) -> -747 | V18: =SUM(H18:K18) -> -585 | W18: =SUM(I18:L18) -> -585 | X18: =SUM(J18:M18) -> -585 | Y18: =SUM(K18:N18) -> -585 | Z18: =SUM(L18:O18) -> 31 | AA18: =SUM(M18:P18) -> 31 | AB18: =SUM(N18:Q18) -> 31 | AC18: =SUM(O18:R18) -> 31 | ... AE18: =SUM(Q18:T18) -> -747 | AG18: =SUM(AE18/AA18)-1 -> -25.096774
B19: Gains on dispositions | C19: 2343 | D19: 56 | E19: 0 | F19: 0 | K19: =SUM(D19-SUM(H19:J19)) -> 56 | O19: =SUM(E19-SUM(L19:N19)) -> 0 | S19: =SUM(F19-SUM(P19:R19)) -> 0 | V19: =SUM(H19:K19) -> 56 | W19: =SUM(I19:L19) -> 56 | X19: =SUM(J19:M19) -> 56 | Y19: =SUM(K19:N19) -> 56 | Z19: =SUM(L19:O19) -> 0 | AA19: =SUM(M19:P19) -> 0 | AB19: =SUM(N19:Q19) -> 0 | AC19: =SUM(O19:R19) -> 0 | ... AE19: =SUM(Q19:T19) -> 0 | AG19: =SUM(AE19/AA19)-1 -> #DIV/0!
B20: Operating Profit | C20: =+SUM(C11+SUM(C13:C19)) -> 6297 | D20: =+SUM(D11+SUM(D13:D19)) -> 2342 | E20: =+SUM(E11+SUM(E13:E19)) -> -451 | F20: =+SUM(F11+SUM(F13:F19)) -> -5269 | H20: =+SUM(H11+SUM(H13:H19)) -> 0 | I20: =+SUM(I11+SUM(I13:I19)) -> 0 | J20: =+SUM(J11+SUM(J13:J19)) -> 0 | K20: =+SUM(K11+SUM(K13:K19)) -> 2342 | L20: =+SUM(L11+SUM(L13:L19)) -> 0 | M20: =+SUM(M11+SUM(M13:M19)) -> 0 | N20: =+SUM(N11+SUM(N13:N19)) -> 0 | O20: =+SUM(O11+SUM(O13:O19)) -> -451 | ... T20: =+SUM(T11+SUM(T13:T19)) -> 0 | V20: =+SUM(V11+SUM(V13:V19)) -> 2342 | W20: =+SUM(W11+SUM(W13:W19)) -> 2342 | X20: =+SUM(X11+SUM(X13:X19)) -> 2342 | Y20: =+SUM(Y11+SUM(Y13:Y19)) -> 2342 | Z20: =+SUM(Z11+SUM(Z13:Z19)) -> -451 | AA20: =+SUM(AA11+SUM(AA13:AA19)) -> -451 | AB20: =+SUM(AB11+SUM(AB13:AB19)) -> -451 | AC20: =+SUM(AC11+SUM(AC13:AC19)) -> -451 | ... AE20: =+SUM(AE11+SUM(AE13:AE19)) -> -5269 | AG20: =SUM(AE20/AA20)-1 -> 10.682927
B21: Operating Margin (%) | C21: =C20/C11 -> 0.22028266 | D21: =D20/D11 -> 0.077667971 | E21: =E20/E11 -> -0.015209767 | F21: =F20/F11 -> -0.18036491 | H21: =H20/H11 -> #DIV/0! | I21: =I20/I11 -> #DIV/0! | J21: =J20/J11 -> #DIV/0! | K21: =K20/K11 -> 0.077667971 | L21: =L20/L11 -> #DIV/0! | M21: =M20/M11 -> #DIV/0! | N21: =N20/N11 -> #DIV/0! | O21: =O20/O11 -> -0.015209767 | ... T21: =T20/T11 -> #DIV/0! | V21: =V20/V11 -> 0.077667971 | W21: =W20/W11 -> 0.077667971 | X21: =X20/X11 -> 0.077667971 | Y21: =Y20/Y11 -> 0.077667971 | Z21: =Z20/Z11 -> -0.015209767 | AA21: =AA20/AA11 -> -0.015209767 | AB21: =AB20/AB11 -> -0.015209767 | AC21: =AC20/AC11 -> -0.015209767 | ... AE21: =AE20/AE11 -> -0.18036491 | AG21: =SUM(AE21-AA21)*1000 -> -165.15514
B23: Interest expense | C23: -986 | D23: -931 | E23: -920 | F23: -860 | K23: =SUM(D23-SUM(H23:J23)) -> -931 | O23: =SUM(E23-SUM(L23:N23)) -> -920 | S23: =SUM(F23-SUM(P23:R23)) -> -860 | V23: =SUM(H23:K23) -> -931 | W23: =SUM(I23:L23) -> -931 | X23: =SUM(J23:M23) -> -931 | Y23: =SUM(K23:N23) -> -931 | Z23: =SUM(L23:O23) -> -920 | AA23: =SUM(M23:P23) -> -920 | AB23: =SUM(N23:Q23) -> -920 | AC23: =SUM(O23:R23) -> -920 | ... AE23: =SUM(Q23:T23) -> -860 | AG23: =SUM(AE23/AA23)-1 -> -0.065217391
B24: Interest income | C24: 53 | D24: 108 | E24: 137 | F24: 151 | K24: =SUM(D24-SUM(H24:J24)) -> 108 | O24: =SUM(E24-SUM(L24:N24)) -> 137 | S24: =SUM(F24-SUM(P24:R24)) -> 151 | V24: =SUM(H24:K24) -> 108 | W24: =SUM(I24:L24) -> 108 | X24: =SUM(J24:M24) -> 108 | Y24: =SUM(K24:N24) -> 108 | Z24: =SUM(L24:O24) -> 137 | AA24: =SUM(M24:P24) -> 137 | AB24: =SUM(N24:Q24) -> 137 | AC24: =SUM(O24:R24) -> 137 | ... AE24: =SUM(Q24:T24) -> 151 | AG24: =SUM(AE24/AA24)-1 -> 0.10218978
B25: Gain (loss) from investments | C25: 47 | D25: -9 | E25: 168 | F25: -17 | K25: =SUM(D25-SUM(H25:J25)) -> -9 | O25: =SUM(E25-SUM(L25:N25)) -> 168 | S25: =SUM(F25-SUM(P25:R25)) -> -17 | V25: =SUM(H25:K25) -> -9 | W25: =SUM(I25:L25) -> -9 | X25: =SUM(J25:M25) -> -9 | Y25: =SUM(K25:N25) -> -9 | Z25: =SUM(L25:O25) -> 168 | AA25: =SUM(M25:P25) -> 168 | AB25: =SUM(N25:Q25) -> 168 | AC25: =SUM(O25:R25) -> 168 | ... AE25: =SUM(Q25:T25) -> -17 | AG25: =SUM(AE25/AA25)-1 -> -1.1011905
B26: Gain (loss) on extinguishment of debt | C26: -128 | D26: -120 | E26: 29 | F26: 0 | K26: =SUM(D26-SUM(H26:J26)) -> -120 | O26: =SUM(E26-SUM(L26:N26)) -> 29 | S26: =SUM(F26-SUM(P26:R26)) -> 0 | V26: =SUM(H26:K26) -> -120 | W26: =SUM(I26:L26) -> -120 | X26: =SUM(J26:M26) -> -120 | Y26: =SUM(K26:N26) -> -120 | Z26: =SUM(L26:O26) -> 29 | AA26: =SUM(M26:P26) -> 29 | AB26: =SUM(N26:Q26) -> 29 | AC26: =SUM(O26:R26) -> 29 | ... AE26: =SUM(Q26:T26) -> 0 | AG26: =SUM(AE26/AA26)-1 -> -1
B27: Other items, net | C27: -77 | D27: -124 | E27: -216 | F27: -182 | K27: =SUM(D27-SUM(H27:J27)) -> -124 | O27: =SUM(E27-SUM(L27:N27)) -> -216 | S27: =SUM(F27-SUM(P27:R27)) -> -182 | V27: =SUM(H27:K27) -> -124 | W27: =SUM(I27:L27) -> -124 | X27: =SUM(J27:M27) -> -124 | Y27: =SUM(K27:N27) -> -124 | Z27: =SUM(L27:O27) -> -216 | AA27: =SUM(M27:P27) -> -216 | AB27: =SUM(N27:Q27) -> -216 | AC27: =SUM(O27:R27) -> -216 | ... AE27: =SUM(Q27:T27) -> -182 | AG27: =SUM(AE27/AA27)-1 -> -0.15740741
B28: Earnings (loss) from Continuing Operations before Taxes & Equity | C28: =SUM(C23:C27)+C20 -> 5206 | D28: =SUM(D23:D27)+D20 -> 1266 | E28: =SUM(E23:E27)+E20 -> -1253 | F28: =SUM(F23:F27)+F20 -> -6177 | H28: =SUM(H23:H27)+H20 -> 0 | I28: =SUM(I23:I27)+I20 -> 0 | J28: =SUM(J23:J27)+J20 -> 0 | K28: =SUM(K23:K27)+K20 -> 1266 | L28: =SUM(L23:L27)+L20 -> 0 | M28: =SUM(M23:M27)+M20 -> 0 | N28: =SUM(N23:N27)+N20 -> 0 | O28: =SUM(O23:O27)+O20 -> -1253 | ... T28: =SUM(T23:T27)+T20 -> 0 | V28: =SUM(V23:V27)+V20 -> 1266 | W28: =SUM(W23:W27)+W20 -> 1266 | X28: =SUM(X23:X27)+X20 -> 1266 | Y28: =SUM(Y23:Y27)+Y20 -> 1266 | Z28: =SUM(Z23:Z27)+Z20 -> -1253 | AA28: =SUM(AA23:AA27)+AA20 -> -1253 | AB28: =SUM(AB23:AB27)+AB20 -> -1253 | AC28: =SUM(AC23:AC27)+AC20 -> -1253 | ... AE28: =SUM(AE23:AE27)+AE20 -> -6177 | AG28: =SUM(AE28/AA28)-1 -> 3.9297686
B29: EBT Margin (%) | C29: =C28/C11 -> 0.18211712 | D29: =D28/D11 -> 0.04198448 | E29: =E28/E11 -> -0.042256846 | F29: =F28/F11 -> -0.21144696 | H29: =H28/H11 -> #DIV/0! | I29: =I28/I11 -> #DIV/0! | J29: =J28/J11 -> #DIV/0! | K29: =K28/K11 -> 0.04198448 | L29: =L28/L11 -> #DIV/0! | M29: =M28/M11 -> #DIV/0! | N29: =N28/N11 -> #DIV/0! | O29: =O28/O11 -> -0.042256846 | ... T29: =T28/T11 -> #DIV/0! | V29: =V28/V11 -> 0.04198448 | W29: =W28/W11 -> 0.04198448 | X29: =X28/X11 -> 0.04198448 | Y29: =Y28/Y11 -> 0.04198448 | Z29: =Z28/Z11 -> -0.042256846 | AA29: =AA28/AA11 -> -0.042256846 | AB29: =AB28/AB11 -> -0.042256846 | AC29: =AC28/AC11 -> -0.042256846 | ... AE29: =AE28/AE11 -> -0.21144696 | AG29: =SUM(AE29-AA29)*1000 -> -169.19011
B31: Income tax expense | C31: -646 | D31: -227 | E31: 361 | F31: 305 | K31: =SUM(D31-SUM(H31:J31)) -> -227 | O31: =SUM(E31-SUM(L31:N31)) -> 361 | S31: =SUM(F31-SUM(P31:R31)) -> 305 | V31: =SUM(H31:K31) -> -227 | W31: =SUM(I31:L31) -> -227 | X31: =SUM(J31:M31) -> -227 | Y31: =SUM(K31:N31) -> -227 | Z31: =SUM(L31:O31) -> 361 | AA31: =SUM(M31:P31) -> 361 | AB31: =SUM(N31:Q31) -> 361 | AC31: =SUM(O31:R31) -> 361 | ... AE31: =SUM(Q31:T31) -> 305 | AG31: =SUM(AE31/AA31)-1 -> -0.15512465
B32: Equity in loss of investee companies, net of tax | C32: -91 | D32: -204 | E32: -360 | F32: -291 | K32: =SUM(D32-SUM(H32:J32)) -> -204 | O32: =SUM(E32-SUM(L32:N32)) -> -360 | S32: =SUM(F32-SUM(P32:R32)) -> -291 | V32: =SUM(H32:K32) -> -204 | W32: =SUM(I32:L32) -> -204 | X32: =SUM(J32:M32) -> -204 | Y32: =SUM(K32:N32) -> -204 | Z32: =SUM(L32:O32) -> -360 | AA32: =SUM(M32:P32) -> -360 | AB32: =SUM(N32:Q32) -> -360 | AC32: =SUM(O32:R32) -> -360 | ... AE32: =SUM(Q32:T32) -> -291
B33: Net earnings (loss) from continuing operations | C33: =SUM(C28+SUM(C31:C32)) -> 4469 | D33: =SUM(D28+SUM(D31:D32)) -> 835 | E33: =SUM(E28+SUM(E31:E32)) -> -1252 | F33: =SUM(F28+SUM(F31:F32)) -> -6163 | H33: =SUM(H28+SUM(H31:H32)) -> 0 | I33: =SUM(I28+SUM(I31:I32)) -> 0 | J33: =SUM(J28+SUM(J31:J32)) -> 0 | K33: =SUM(K28+SUM(K31:K32)) -> 835 | L33: =SUM(L28+SUM(L31:L32)) -> 0 | M33: =SUM(M28+SUM(M31:M32)) -> 0 | N33: =SUM(N28+SUM(N31:N32)) -> 0 | O33: =SUM(O28+SUM(O31:O32)) -> -1252 | ... T33: =SUM(T28+SUM(T31:T32)) -> 0 | V33: =SUM(V23+SUM(V31:V32)) -> -1362 | W33: =SUM(W23+SUM(W31:W32)) -> -1362 | X33: =SUM(X23+SUM(X31:X32)) -> -1362 | Y33: =SUM(Y23+SUM(Y31:Y32)) -> -1362 | Z33: =SUM(Z23+SUM(Z31:Z32)) -> -919 | AA33: =SUM(AA23+SUM(AA31:AA32)) -> -919 | AB33: =SUM(AB23+SUM(AB31:AB32)) -> -919 | AC33: =SUM(AC23+SUM(AC31:AC32)) -> -919 | ... AE33: =SUM(AE23+SUM(AE31:AE32)) -> -846 | AG33: =SUM(AE33/AA33)-1 -> -0.079434168
B35: Net earnings from discontinued operations, net of tax | C35: 162 | D35: 379 | E35: 676 | F35: 14 | K35: =SUM(D35-SUM(H35:J35)) -> 379 | O35: =SUM(E35-SUM(L35:N35)) -> 676 | S35: =SUM(F35-SUM(P35:R35)) -> 14 | V35: =SUM(H35:K35) -> 379 | W35: =SUM(I35:L35) -> 379 | X35: =SUM(J35:M35) -> 379 | Y35: =SUM(K35:N35) -> 379 | Z35: =SUM(L35:O35) -> 676 | AA35: =SUM(M35:P35) -> 676 | AB35: =SUM(N35:Q35) -> 676 | AC35: =SUM(O35:R35) -> 676 | ... AE35: =SUM(Q35:T35) -> 14 | AG35: =SUM(AE35/AA35)-1 -> -0.97928994
B36: Net earnings (loss) (Paramount and noncontrolling interests) | C36: =SUM(C33)+SUM(C35:C35) -> 4631 | D36: =SUM(D33)+SUM(D35:D35) -> 1214 | E36: =SUM(E33)+SUM(E35:E35) -> -576 | F36: =SUM(F33)+SUM(F35:F35) -> -6149 | H36: =SUM(H33)+SUM(H35:H35) -> 0 | I36: =SUM(I33)+SUM(I35:I35) -> 0 | J36: =SUM(J33)+SUM(J35:J35) -> 0 | K36: =SUM(K33)+SUM(K35:K35) -> 1214 | L36: =SUM(L33)+SUM(L35:L35) -> 0 | M36: =SUM(M33)+SUM(M35:M35) -> 0 | N36: =SUM(N33)+SUM(N35:N35) -> 0 | O36: =SUM(O33)+SUM(O35:O35) -> -576 | ... T36: =SUM(T33)+SUM(T35:T35) -> 0 | V36: =SUM(V33)+SUM(V35:V35) -> -983 | W36: =SUM(W33)+SUM(W35:W35) -> -983 | X36: =SUM(X33)+SUM(X35:X35) -> -983 | Y36: =SUM(Y33)+SUM(Y35:Y35) -> -983 | Z36: =SUM(Z33)+SUM(Z35:Z35) -> -243 | AA36: =SUM(AA33)+SUM(AA35:AA35) -> -243 | AB36: =SUM(AB33)+SUM(AB35:AB35) -> -243 | AC36: =SUM(AC33)+SUM(AC35:AC35) -> -243 | ... AE36: =SUM(AE33)+SUM(AE35:AE35) -> -832 | AG36: =SUM(AE36/AA36)-1 -> 2.4238683
B38: Net earnings attributable to noncontrolling interests | C38: -88 | D38: -110 | E38: -32 | F38: -41 | K38: =SUM(D38-SUM(H38:J38)) -> -110 | O38: =SUM(E38-SUM(L38:N38)) -> -32 | S38: =SUM(F38-SUM(P38:R38)) -> -41 | V38: =SUM(H38:K38) -> -110 | W38: =SUM(I38:L38) -> -110 | X38: =SUM(J38:M38) -> -110 | Y38: =SUM(K38:N38) -> -110 | Z38: =SUM(L38:O38) -> -32 | AA38: =SUM(M38:P38) -> -32 | AB38: =SUM(N38:Q38) -> -32 | AC38: =SUM(O38:R38) -> -32 | ... AE38: =SUM(Q38:T38) -> -41 | AG38: =SUM(AE38/AA38)-1 -> 0.28125
B39: Net earnings (loss) attributable to Paramount | C39: =SUM(C36+SUM(C38:C38)) -> 4543 | D39: =SUM(D36+SUM(D38:D38)) -> 1104 | E39: =SUM(E36+SUM(E38:E38)) -> -608 | F39: =SUM(F36+SUM(F38:F38)) -> -6190 | H39: =SUM(H36+SUM(H38:H38)) -> 0 | I39: =SUM(I36+SUM(I38:I38)) -> 0 | J39: =SUM(J36+SUM(J38:J38)) -> 0 | K39: =SUM(K36+SUM(K38:K38)) -> 1104 | L39: =SUM(L36+SUM(L38:L38)) -> 0 | M39: =SUM(M36+SUM(M38:M38)) -> 0 | N39: =SUM(N36+SUM(N38:N38)) -> 0 | O39: =SUM(O36+SUM(O38:O38)) -> -608 | ... T39: =SUM(T36+SUM(T38:T38)) -> 0 | V39: =SUM(V36+SUM(V38:V38)) -> -1093 | W39: =SUM(W36+SUM(W38:W38)) -> -1093 | X39: =SUM(X36+SUM(X38:X38)) -> -1093 | Y39: =SUM(Y36+SUM(Y38:Y38)) -> -1093 | Z39: =SUM(Z36+SUM(Z38:Z38)) -> -275 | AA39: =SUM(AA36+SUM(AA38:AA38)) -> -275 | AB39: =SUM(AB36+SUM(AB38:AB38)) -> -275 | AC39: =SUM(AC36+SUM(AC38:AC38)) -> -275 | ... AE39: =SUM(AE36+SUM(AE38:AE38)) -> -873 | AG39: =SUM(AE39/AA39)-1 -> 2.1745455
B40: Net Margin (%) | C40: =C39/C11 -> 0.15892395 | D40: =D39/D11 -> 0.036612058 | E40: =E39/E11 -> -0.020504519 | F40: =F39/F11 -> -0.21189197 | H40: =H39/H11 -> #DIV/0! | I40: =I39/I11 -> #DIV/0! | J40: =J39/J11 -> #DIV/0! | K40: =K39/K11 -> 0.036612058 | L40: =L39/L11 -> #DIV/0! | M40: =M39/M11 -> #DIV/0! | N40: =N39/N11 -> #DIV/0! | O40: =O39/O11 -> -0.020504519 | ... T40: =T39/T11 -> #DIV/0! | V40: =V39/V11 -> -0.036247264 | W40: =W39/W11 -> -0.036247264 | X40: =X39/X11 -> -0.036247264 | Y40: =Y39/Y11 -> -0.036247264 | Z40: =Z39/Z11 -> -0.0092742479 | AA40: =AA39/AA11 -> -0.0092742479 | AB40: =AB39/AB11 -> -0.0092742479 | AC40: =AC39/AC11 -> -0.0092742479 | ... AE40: =AE39/AE11 -> -0.029883956 | AG40: =SUM(AE40-AA40)*1000 -> -20.609708
B42: Basic shares | C42: 641 | K42: =D42 -> 0 | O42: =E42 -> 0 | S42: =F42 -> 0 | V42: =K42 -> 0 | W42: =L42 -> 0 | X42: =M42 -> 0 | Y42: =N42 -> 0 | Z42: =O42 -> 0 | AA42: =P42 -> 0 | AB42: =Q42 -> 0 | AC42: =R42 -> 0 | ... AE42: =T42 -> 0 | AG42: =SUM(AE42/AA42)-1 -> #DIV/0!
B43: Basic EPS | C43: =C39/C42 -> 7.0873635 | D43: =D39/D42 -> #DIV/0! | E43: =E39/E42 -> #DIV/0! | F43: =F39/F42 -> #DIV/0! | H43: =H39/H42 -> #DIV/0! | I43: =I39/I42 -> #DIV/0! | J43: =J39/J42 -> #DIV/0! | K43: =K39/K42 -> #DIV/0! | L43: =L39/L42 -> #DIV/0! | M43: =M39/M42 -> #DIV/0! | N43: =N39/N42 -> #DIV/0! | O43: =O39/O42 -> #DIV/0! | ... T43: =T39/T42 -> #DIV/0! | V43: =V39/V42 -> #DIV/0! | W43: =W39/W42 -> #DIV/0! | X43: =X39/X42 -> #DIV/0! | Y43: =Y39/Y42 -> #DIV/0! | Z43: =Z39/Z42 -> #DIV/0! | AA43: =AA39/AA42 -> #DIV/0! | AB43: =AB39/AB42 -> #DIV/0! | AC43: =AC39/AC42 -> #DIV/0! | ... AE43: =AE39/AE42 -> #DIV/0! | AG43: =SUM(AE43/AA43)-1 -> #DIV/0!
B45: Fully Diluted Shares | C45: 655 | K45: =D45 -> 0 | O45: =E45 -> 0 | S45: =F45 -> 0 | V45: =K45 -> 0 | W45: =L45 -> 0 | X45: =M45 -> 0 | Y45: =N45 -> 0 | Z45: =O45 -> 0 | AA45: =P45 -> 0 | AB45: =Q45 -> 0 | AC45: =R45 -> 0 | ... AE45: =T45 -> 0 | AG45: =SUM(AE45/AA45)-1 -> #DIV/0!
B46: Diluted EPS | C46: =C39/C45 -> 6.9358779 | D46: =D39/D45 -> #DIV/0! | E46: =E39/E45 -> #DIV/0! | F46: =F39/F45 -> #DIV/0! | H46: =H39/H45 -> #DIV/0! | I46: =I39/I45 -> #DIV/0! | J46: =J39/J45 -> #DIV/0! | K46: =K39/K45 -> #DIV/0! | L46: =L39/L45 -> #DIV/0! | M46: =M39/M45 -> #DIV/0! | N46: =N39/N45 -> #DIV/0! | O46: =O39/O45 -> #DIV/0! | ... T46: =T39/T45 -> #DIV/0! | V46: =V39/V45 -> #DIV/0! | W46: =W39/W45 -> #DIV/0! | X46: =X39/X45 -> #DIV/0! | Y46: =Y39/Y45 -> #DIV/0! | Z46: =Z39/Z45 -> #DIV/0! | AA46: =AA39/AA45 -> #DIV/0! | AB46: =AB39/AB45 -> #DIV/0! | AC46: =AC39/AC45 -> #DIV/0! | ... AE46: =AE39/AE45 -> #DIV/0! | AG46: =SUM(AE46/AA46)-1 -> #DIV/0!
A48: X | B48: Balance Sheet | C48: FYE | N48: Quarterly | AA48: LTM | AG48: Variance
B49: =B7 -> Fiscal Period | C49: =C7 -> 2021 | D49: =D7 -> 2022 | E49: =E7 -> 2023 | F49: =F7 -> 2024 | H49: =H7 -> 1Q23 | I49: =I7 -> 2Q23 | J49: =J7 -> 3Q23 | K49: =K7 -> 4Q23 | L49: =L7 -> 1Q24 | M49: =M7 -> 2Q24 | N49: =N7 -> 3Q24 | O49: =O7 -> 4Q24 | ... T49: =T7 -> 1Q26 | V49: =V7 -> 4Q23 | W49: =W7 -> 1Q24 | X49: =X7 -> 2Q24 | Y49: =Y7 -> 3Q24 | Z49: =Z7 -> 4Q24 | AA49: =AA7 -> 1Q25 | AB49: =AB7 -> 2Q25 | AC49: =AC7 -> 3Q25 | ... AE49: =AE7 -> 1Q26
B50: =B8 -> Fiscal Period End Date | C50: =C8 -> 44561 | D50: =D8 -> 44926 | E50: =E8 -> 45291 | F50: =F8 -> 45657 | H50: =H8 -> XXX | I50: =I8 -> XXX | J50: =J8 -> XXX | K50: =K8 -> 44926 | L50: =L8 -> XXX | M50: =M8 -> XXX | N50: =N8 -> XXX | O50: =O8 -> 45291 | ... T50: =T8 -> XXX | V50: =V8 -> 44926 | W50: =W8 -> XXX | X50: =X8 -> XXX | Y50: =Y8 -> XXX | Z50: =Z8 -> 45291 | AA50: =AA8 -> XXX | AB50: =AB8 -> XXX | AC50: =AC8 -> XXX | ... AE50: =AE8 -> XXX
B52: Current Assets
B53: Cash and cash equivalents | C53: 6267 | D53: 2885 | E53: 2460 | F53: 2661 | K53: =D53 -> 2885 | O53: =E53 -> 2460 | S53: =F53 -> 2661 | V53: =K53 -> 2885 | W53: =L53 -> 0 | X53: =M53 -> 0 | Y53: =N53 -> 0 | Z53: =O53 -> 2460 | AA53: =P53 -> 0 | AB53: =Q53 -> 0 | AC53: =R53 -> 0 | ... AE53: =T53 -> 0 | AG53: =SUM(AE53/AA53)-1 -> #DIV/0!
B54: Receivables, net | C54: 6984 | D54: 7412 | E54: 7115 | F54: 6920 | K54: =D54 -> 7412 | O54: =E54 -> 7115 | S54: =F54 -> 6920 | V54: =K54 -> 7412 | W54: =L54 -> 0 | X54: =M54 -> 0 | Y54: =N54 -> 0 | Z54: =O54 -> 7115 | AA54: =P54 -> 0 | AB54: =Q54 -> 0 | AC54: =R54 -> 0 | ... AE54: =T54 -> 0 | AG54: =SUM(AE54/AA54)-1 -> #DIV/0!
B55: Programming and other inventory | C55: 1504 | D55: 1342 | E55: 1414 | F55: 1429 | K55: =D55 -> 1342 | O55: =E55 -> 1414 | S55: =F55 -> 1429 | V55: =K55 -> 1342 | W55: =L55 -> 0 | X55: =M55 -> 0 | Y55: =N55 -> 0 | Z55: =O55 -> 1414 | AA55: =P55 -> 0 | AB55: =Q55 -> 0 | AC55: =R55 -> 0 | ... AE55: =T55 -> 0 | AG55: =SUM(AE55/AA55)-1 -> #DIV/0!
B56: Prepaid expenses and other current assets | C56: 1176 | D56: 1308 | E56: 1677 | F56: 1532 | K56: =D56 -> 1308 | O56: =E56 -> 1677 | S56: =F56 -> 1532 | V56: =K56 -> 1308 | W56: =L56 -> 0 | X56: =M56 -> 0 | Y56: =N56 -> 0 | Z56: =O56 -> 1677 | AA56: =P56 -> 0 | AB56: =Q56 -> 0 | AC56: =R56 -> 0 | ... AE56: =T56 -> 0 | AG56: =SUM(AE56/AA56)-1 -> #DIV/0!
B57: Current assets of discontinued operations | C57: 745 | D57: 787 | E57: 37 | F57: 0 | K57: =D57 -> 787 | O57: =E57 -> 37 | S57: =F57 -> 0 | V57: =K57 -> 787 | W57: =L57 -> 0 | X57: =M57 -> 0 | Y57: =N57 -> 0 | Z57: =O57 -> 37 | AA57: =P57 -> 0 | AB57: =Q57 -> 0 | AC57: =R57 -> 0 | ... AE57: =T57 -> 0 | AG57: =SUM(AE57/AA57)-1 -> #DIV/0!
B58: Total Current Assets | C58: =SUM(C53:C57) -> 16676 | D58: =SUM(D53:D57) -> 13734 | E58: =SUM(E53:E57) -> 12703 | F58: =SUM(F53:F57) -> 12542 | H58: =SUM(H53:H57) -> 0 | I58: =SUM(I53:I57) -> 0 | J58: =SUM(J53:J57) -> 0 | K58: =SUM(K53:K57) -> 13734 | L58: =SUM(L53:L57) -> 0 | M58: =SUM(M53:M57) -> 0 | N58: =SUM(N53:N57) -> 0 | O58: =SUM(O53:O57) -> 12703 | ... T58: =SUM(T53:T57) -> 0 | V58: =SUM(V53:V57) -> 13734 | W58: =SUM(W53:W57) -> 0 | X58: =SUM(X53:X57) -> 0 | Y58: =SUM(Y53:Y57) -> 0 | Z58: =SUM(Z53:Z57) -> 12703 | AA58: =SUM(AA53:AA57) -> 0 | AB58: =SUM(AB53:AB57) -> 0 | AC58: =SUM(AC53:AC57) -> 0 | ... AE58: =SUM(AE53:AE57) -> 0 | AG58: =SUM(AE58/AA58)-1 -> #DIV/0!
B60: Non-Current Assets
B61: Property and equipment, net | C61: 1736 | D61: 1762 | E61: 1666 | F61: 1566 | K61: =D61 -> 1762 | O61: =E61 -> 1666 | S61: =F61 -> 1566 | V61: =K61 -> 1762 | W61: =L61 -> 0 | X61: =M61 -> 0 | Y61: =N61 -> 0 | Z61: =O61 -> 1666 | AA61: =P61 -> 0 | AB61: =Q61 -> 0 | AC61: =R61 -> 0 | ... AE61: =T61 -> 0 | AG61: =SUM(AE61/AA61)-1 -> #DIV/0!
B62: Programming and other inventory | C62: 13358 | D62: 16278 | E62: 13851 | F62: 13924 | K62: =D62 -> 16278 | O62: =E62 -> 13851 | S62: =F62 -> 13924 | V62: =K62 -> 16278 | W62: =L62 -> 0 | X62: =M62 -> 0 | Y62: =N62 -> 0 | Z62: =O62 -> 13851 | AA62: =P62 -> 0 | AB62: =Q62 -> 0 | AC62: =R62 -> 0 | ... AE62: =T62 -> 0 | AG62: =SUM(AE62/AA62)-1 -> #DIV/0!
B63: Goodwill | C63: 16584 | D63: 16499 | E63: 16516 | F63: 10508 | K63: =D63 -> 16499 | O63: =E63 -> 16516 | S63: =F63 -> 10508 | V63: =K63 -> 16499 | W63: =L63 -> 0 | X63: =M63 -> 0 | Y63: =N63 -> 0 | Z63: =O63 -> 16516 | AA63: =P63 -> 0 | AB63: =Q63 -> 0 | AC63: =R63 -> 0 | ... AE63: =T63 -> 0 | AG63: =SUM(AE63/AA63)-1 -> #DIV/0!
B64: Intangible assets, net | C64: 2772 | D64: 2694 | E64: 2589 | F64: 2406 | K64: =D64 -> 2694 | O64: =E64 -> 2589 | S64: =F64 -> 2406 | V64: =K64 -> 2694 | W64: =L64 -> 0 | X64: =M64 -> 0 | Y64: =N64 -> 0 | Z64: =O64 -> 2589 | AA64: =P64 -> 0 | AB64: =Q64 -> 0 | AC64: =R64 -> 0 | ... AE64: =T64 -> 0 | AG64: =SUM(AE64/AA64)-1 -> #DIV/0!
B65: Operating lease assets | C65: 1630 | D65: 1391 | E65: 1183 | F65: 1012 | K65: =D65 -> 1391 | O65: =E65 -> 1183 | S65: =F65 -> 1012 | V65: =K65 -> 1391 | W65: =L65 -> 0 | X65: =M65 -> 0 | Y65: =N65 -> 0 | Z65: =O65 -> 1183 | AA65: =P65 -> 0 | AB65: =Q65 -> 0 | AC65: =R65 -> 0 | ... AE65: =T65 -> 0 | AG65: =SUM(AE65/AA65)-1 -> #DIV/0!
B66: Deferred income tax assets, net | C66: 1206 | D66: 1242 | E66: 1242 | F66: 1386 | K66: =D66 -> 1242 | O66: =E66 -> 1242 | S66: =F66 -> 1386 | V66: =K66 -> 1242 | W66: =L66 -> 0 | X66: =M66 -> 0 | Y66: =N66 -> 0 | Z66: =O66 -> 1242 | AA66: =P66 -> 0 | AB66: =Q66 -> 0 | AC66: =R66 -> 0 | ... AE66: =T66 -> 0 | AG66: =SUM(AE66/AA66)-1 -> #DIV/0!
B67: Other assets | C67: =3824+19+815 -> 4658 | D67: =3991+802 -> 4793 | E67: 3793 | F67: 2828 | K67: =D67 -> 4793 | O67: =E67 -> 3793 | S67: =F67 -> 2828 | V67: =K67 -> 4793 | W67: =L67 -> 0 | X67: =M67 -> 0 | Y67: =N67 -> 0 | Z67: =O67 -> 3793 | AA67: =P67 -> 0 | AB67: =Q67 -> 0 | AC67: =R67 -> 0 | ... AE67: =T67 -> 0 | AG67: =SUM(AE67/AA67)-1 -> #DIV/0!
B68: Total Assets | C68: =SUM(C61:C67)+C58 -> 58620 | D68: =SUM(D61:D67)+D58 -> 58393 | E68: =SUM(E61:E67)+E58 -> 53543 | F68: =SUM(F61:F67)+F58 -> 46172 | H68: =SUM(H61:H67)+H58 -> 0 | I68: =SUM(I61:I67)+I58 -> 0 | J68: =SUM(J61:J67)+J58 -> 0 | K68: =SUM(K61:K67)+K58 -> 58393 | L68: =SUM(L61:L67)+L58 -> 0 | M68: =SUM(M61:M67)+M58 -> 0 | N68: =SUM(N61:N67)+N58 -> 0 | O68: =SUM(O61:O67)+O58 -> 53543 | ... T68: =SUM(T61:T67)+T58 -> 0 | V68: =SUM(V61:V67)+V58 -> 58393 | W68: =SUM(W61:W67)+W58 -> 0 | X68: =SUM(X61:X67)+X58 -> 0 | Y68: =SUM(Y61:Y67)+Y58 -> 0 | Z68: =SUM(Z61:Z67)+Z58 -> 53543 | AA68: =SUM(AA61:AA67)+AA58 -> 0 | AB68: =SUM(AB61:AB67)+AB58 -> 0 | AC68: =SUM(AC61:AC67)+AC58 -> 0 | ... AE68: =SUM(AE61:AE67)+AE58 -> 0 | AG68: =SUM(AE68/AA68)-1 -> #DIV/0!
B70: Current Liabilities
B71: Accounts payable | C71: 800 | D71: 1403 | E71: 1100 | F71: 953 | K71: =D71 -> 1403 | O71: =E71 -> 1100 | S71: =F71 -> 953 | V71: =K71 -> 1403 | W71: =L71 -> 0 | X71: =M71 -> 0 | Y71: =N71 -> 0 | Z71: =O71 -> 1100 | AA71: =P71 -> 0 | AB71: =Q71 -> 0 | AC71: =R71 -> 0 | ... AE71: =T71 -> 0 | AG71: =SUM(AE71/AA71)-1 -> #DIV/0!
B72: Accrued expenses | C72: 2323 | D72: 2071 | E72: 2104 | F72: 2199 | K72: =D72 -> 2071 | O72: =E72 -> 2104 | S72: =F72 -> 2199 | V72: =K72 -> 2071 | W72: =L72 -> 0 | X72: =M72 -> 0 | Y72: =N72 -> 0 | Z72: =O72 -> 2104 | AA72: =P72 -> 0 | AB72: =Q72 -> 0 | AC72: =R72 -> 0 | ... AE72: =T72 -> 0 | AG72: =SUM(AE72/AA72)-1 -> #DIV/0!
B73: Participants’ share and royalties payable | C73: 2159 | D73: 2416 | E73: 2702 | F73: 2574 | K73: =D73 -> 2416 | O73: =E73 -> 2702 | S73: =F73 -> 2574 | V73: =K73 -> 2416 | W73: =L73 -> 0 | X73: =M73 -> 0 | Y73: =N73 -> 0 | Z73: =O73 -> 2702 | AA73: =P73 -> 0 | AB73: =Q73 -> 0 | AC73: =R73 -> 0 | ... AE73: =T73 -> 0 | AG73: =SUM(AE73/AA73)-1 -> #DIV/0!
B74: Accrued programming and production costs | C74: 1342 | D74: 2063 | E74: 1842 | F74: 1720 | K74: =D74 -> 2063 | O74: =E74 -> 1842 | S74: =F74 -> 1720 | V74: =K74 -> 2063 | W74: =L74 -> 0 | X74: =M74 -> 0 | Y74: =N74 -> 0 | Z74: =O74 -> 1842 | AA74: =P74 -> 0 | AB74: =Q74 -> 0 | AC74: =R74 -> 0 | ... AE74: =T74 -> 0 | AG74: =SUM(AE74/AA74)-1 -> #DIV/0!
B75: Deferred revenues | C75: 1091 | D75: 973 | E75: 746 | F75: 825 | K75: =D75 -> 973 | O75: =E75 -> 746 | S75: =F75 -> 825 | V75: =K75 -> 973 | W75: =L75 -> 0 | X75: =M75 -> 0 | Y75: =N75 -> 0 | Z75: =O75 -> 746 | AA75: =P75 -> 0 | AB75: =Q75 -> 0 | AC75: =R75 -> 0 | ... AE75: =T75 -> 0 | AG75: =SUM(AE75/AA75)-1 -> #DIV/0!
B76: Debt | C76: 11 | D76: 239 | E76: 1 | F76: 0 | K76: =D76 -> 239 | O76: =E76 -> 1 | S76: =F76 -> 0 | V76: =K76 -> 239 | W76: =L76 -> 0 | X76: =M76 -> 0 | Y76: =N76 -> 0 | Z76: =O76 -> 1 | AA76: =P76 -> 0 | AB76: =Q76 -> 0 | AC76: =R76 -> 0 | ... AE76: =T76 -> 0 | AG76: =SUM(AE76/AA76)-1 -> #DIV/0!
B77: Other current liabilities | C77: =1182+571 -> 1753 | D77: =1477+549 -> 2026 | E77: 1161 | F77: 1360 | K77: =D77 -> 2026 | O77: =E77 -> 1161 | S77: =F77 -> 1360 | V77: =K77 -> 2026 | W77: =L77 -> 0 | X77: =M77 -> 0 | Y77: =N77 -> 0 | Z77: =O77 -> 1161 | AA77: =P77 -> 0 | AB77: =Q77 -> 0 | AC77: =R77 -> 0 | ... AE77: =T77 -> 0
B78: Total Current Liabilities | C78: =SUM(C71:C77) -> 9479 | D78: =SUM(D71:D77) -> 11191 | E78: =SUM(E71:E77) -> 9656 | F78: =SUM(F71:F77) -> 9631 | H78: =SUM(H71:H77) -> 0 | I78: =SUM(I71:I77) -> 0 | J78: =SUM(J71:J77) -> 0 | K78: =SUM(K71:K77) -> 11191 | L78: =SUM(L71:L77) -> 0 | M78: =SUM(M71:M77) -> 0 | N78: =SUM(N71:N77) -> 0 | O78: =SUM(O71:O77) -> 9656 | ... T78: =SUM(T71:T77) -> 0 | V78: =SUM(V71:V77) -> 11191 | W78: =SUM(W71:W77) -> 0 | X78: =SUM(X71:X77) -> 0 | Y78: =SUM(Y71:Y77) -> 0 | Z78: =SUM(Z71:Z77) -> 9656 | AA78: =SUM(AA71:AA77) -> 0 | AB78: =SUM(AB71:AB77) -> 0 | AC78: =SUM(AC71:AC77) -> 0 | ... AE78: =SUM(AE71:AE77) -> 0 | AG78: =SUM(AE78/AA78)-1 -> #DIV/0!
B80: Non-Current Liabilities
B81: Long-term debt | C81: 17698 | D81: 15607 | E81: 14601 | F81: 14501 | K81: =D81 -> 15607 | O81: =E81 -> 14601 | S81: =F81 -> 14501 | V81: =K81 -> 15607 | W81: =L81 -> 0 | X81: =M81 -> 0 | Y81: =N81 -> 0 | Z81: =O81 -> 14601 | AA81: =P81 -> 0 | AB81: =Q81 -> 0 | AC81: =R81 -> 0 | ... AE81: =T81 -> 0 | AG81: =SUM(AE81/AA81)-1 -> #DIV/0!
B82: Participants’ share and royalties payable | C82: 1244 | D82: 1744 | E82: 1394 | F82: 1310 | K82: =D82 -> 1744 | O82: =E82 -> 1394 | S82: =F82 -> 1310 | V82: =K82 -> 1744 | W82: =L82 -> 0 | X82: =M82 -> 0 | Y82: =N82 -> 0 | Z82: =O82 -> 1394 | AA82: =P82 -> 0 | AB82: =Q82 -> 0 | AC82: =R82 -> 0 | ... AE82: =T82 -> 0 | AG82: =SUM(AE82/AA82)-1 -> #DIV/0!
B83: Pension and postretirement benefit obligations | C83: 1946 | D83: 1458 | E83: 1337 | F83: 1226 | K83: =D83 -> 1458 | O83: =E83 -> 1337 | S83: =F83 -> 1226 | V83: =K83 -> 1458 | W83: =L83 -> 0 | X83: =M83 -> 0 | Y83: =N83 -> 0 | Z83: =O83 -> 1337 | AA83: =P83 -> 0 | AB83: =Q83 -> 0 | AC83: =R83 -> 0 | ... AE83: =T83 -> 0 | AG83: =SUM(AE83/AA83)-1 -> #DIV/0!
B84: Deferred income tax liabilities, net | C84: 1063 | D84: 1077 | E84: 503 | F84: 34 | K84: =D84 -> 1077 | O84: =E84 -> 503 | S84: =F84 -> 34 | V84: =K84 -> 1077 | W84: =L84 -> 0 | X84: =M84 -> 0 | Y84: =N84 -> 0 | Z84: =O84 -> 503 | AA84: =P84 -> 0 | AB84: =Q84 -> 0 | AC84: =R84 -> 0 | ... AE84: =T84 -> 0 | AG84: =SUM(AE84/AA84)-1 -> #DIV/0!
B85: Operating lease liabilities | C85: 1598 | D85: 1428 | E85: 1256 | F85: 1048 | K85: =D85 -> 1428 | O85: =E85 -> 1256 | S85: =F85 -> 1048 | V85: =K85 -> 1428 | W85: =L85 -> 0 | X85: =M85 -> 0 | Y85: =N85 -> 0 | Z85: =O85 -> 1256 | AA85: =P85 -> 0 | AB85: =Q85 -> 0 | AC85: =R85 -> 0 | ... AE85: =T85 -> 0 | AG85: =SUM(AE85/AA85)-1 -> #DIV/0!
B86: Program rights obligations | C86: 404 | D86: 367 | E86: 204 | F86: 260 | K86: =D86 -> 367 | O86: =E86 -> 204 | S86: =F86 -> 260 | V86: =K86 -> 367 | W86: =L86 -> 0 | X86: =M86 -> 0 | Y86: =N86 -> 0 | Z86: =O86 -> 204 | AA86: =P86 -> 0 | AB86: =Q86 -> 0 | AC86: =R86 -> 0 | ... AE86: =T86 -> 0 | AG86: =SUM(AE86/AA86)-1 -> #DIV/0!
B87: Other liabilities | C87: =1898+213+107 -> 2218 | D87: =1715+200 -> 1915 | E87: 1542 | F87: 1380 | K87: =D87 -> 1915 | O87: =E87 -> 1542 | S87: =F87 -> 1380 | V87: =K87 -> 1915 | W87: =L87 -> 0 | X87: =M87 -> 0 | Y87: =N87 -> 0 | Z87: =O87 -> 1542 | AA87: =P87 -> 0 | AB87: =Q87 -> 0 | AC87: =R87 -> 0 | ... AE87: =T87 -> 0 | AG87: =SUM(AE87/AA87)-1 -> #DIV/0!
B88: Total Liabilities | C88: =SUM(C81:C87)+C78 -> 35650 | D88: =SUM(D81:D87)+D78 -> 34787 | E88: =SUM(E81:E87)+E78 -> 30493 | F88: =SUM(F81:F87)+F78 -> 29390 | H88: =SUM(H81:H87)+H78 -> 0 | I88: =SUM(I81:I87)+I78 -> 0 | J88: =SUM(J81:J87)+J78 -> 0 | K88: =SUM(K81:K87)+K78 -> 34787 | L88: =SUM(L81:L87)+L78 -> 0 | M88: =SUM(M81:M87)+M78 -> 0 | N88: =SUM(N81:N87)+N78 -> 0 | O88: =SUM(O81:O87)+O78 -> 30493 | ... T88: =SUM(T81:T87)+T78 -> 0 | V88: =SUM(V81:V87)+V78 -> 34787 | W88: =SUM(W81:W87)+W78 -> 0 | X88: =SUM(X81:X87)+X78 -> 0 | Y88: =SUM(Y81:Y87)+Y78 -> 0 | Z88: =SUM(Z81:Z87)+Z78 -> 30493 | AA88: =SUM(AA81:AA87)+AA78 -> 0 | AB88: =SUM(AB81:AB87)+AB78 -> 0 | AC88: =SUM(AC81:AC87)+AC78 -> 0 | ... AE88: =SUM(AE81:AE87)+AE78 -> 0 | AG88: =SUM(AE88/AA88)-1 -> #DIV/0!
B90: Common Stock | C90: 1 | D90: 1 | E90: 1 | F90: 1 | K90: =D90 -> 1 | O90: =E90 -> 1 | S90: =F90 -> 1 | V90: =K90 -> 1 | W90: =L90 -> 0 | X90: =M90 -> 0 | Y90: =N90 -> 0 | Z90: =O90 -> 1 | AA90: =P90 -> 0 | AB90: =Q90 -> 0 | AC90: =R90 -> 0 | ... AE90: =T90 -> 0 | AG90: =SUM(AE90/AA90)-1 -> #DIV/0!
B91: Additional paid-in capital | C91: 32918 | D91: 33063 | E91: 33210 | F91: 33394 | K91: =D91 -> 33063 | O91: =E91 -> 33210 | S91: =F91 -> 33394 | V91: =K91 -> 33063 | W91: =L91 -> 0 | X91: =M91 -> 0 | Y91: =N91 -> 0 | Z91: =O91 -> 33210 | AA91: =P91 -> 0 | AB91: =Q91 -> 0 | AC91: =R91 -> 0 | ... AE91: =T91 -> 0 | AG91: =SUM(AE91/AA91)-1 -> #DIV/0!
B92: Treasury stock | C92: -22958 | D92: -22958 | E92: -22958 | F92: -22958 | K92: =D92 -> -22958 | O92: =E92 -> -22958 | S92: =F92 -> -22958 | V92: =K92 -> -22958 | W92: =L92 -> 0 | X92: =M92 -> 0 | Y92: =N92 -> 0 | Z92: =O92 -> -22958 | AA92: =P92 -> 0 | AB92: =Q92 -> 0 | AC92: =R92 -> 0 | ... AE92: =T92 -> 0 | AG92: =SUM(AE92/AA92)-1 -> #DIV/0!
B93: Retained earnings | C93: 14343 | D93: 14737 | E93: 13829 | F93: 7487 | K93: =D93 -> 14737 | O93: =E93 -> 13829 | S93: =F93 -> 7487 | V93: =K93 -> 14737 | W93: =L93 -> 0 | X93: =M93 -> 0 | Y93: =N93 -> 0 | Z93: =O93 -> 13829 | AA93: =P93 -> 0 | AB93: =Q93 -> 0 | AC93: =R93 -> 0 | ... AE93: =T93 -> 0 | AG93: =SUM(AE93/AA93)-1 -> #DIV/0!
B94: Accumulated other comprehensive loss | C94: -1902 | D94: -1807 | E94: -1556 | F94: -1604 | K94: =D94 -> -1807 | O94: =E94 -> -1556 | S94: =F94 -> -1604 | V94: =K94 -> -1807 | W94: =L94 -> 0 | X94: =M94 -> 0 | Y94: =N94 -> 0 | Z94: =O94 -> -1556 | AA94: =P94 -> 0 | AB94: =Q94 -> 0 | AC94: =R94 -> 0 | ... AE94: =T94 -> 0 | AG94: =SUM(AE94/AA94)-1 -> #DIV/0!
B95: Total Paramount stockholders’ equity | C95: =SUM(C90:C94) -> 22402 | D95: =SUM(D90:D94) -> 23036 | E95: =SUM(E90:E94) -> 22526 | F95: =SUM(F90:F94) -> 16320 | H95: =SUM(H90:H94) -> 0 | I95: =SUM(I90:I94) -> 0 | J95: =SUM(J90:J94) -> 0 | K95: =SUM(K90:K94) -> 23036 | L95: =SUM(L90:L94) -> 0 | M95: =SUM(M90:M94) -> 0 | N95: =SUM(N90:N94) -> 0 | O95: =SUM(O90:O94) -> 22526 | ... T95: =SUM(T90:T94) -> 0 | V95: =SUM(V90:V94) -> 23036 | W95: =SUM(W90:W94) -> 0 | X95: =SUM(X90:X94) -> 0 | Y95: =SUM(Y90:Y94) -> 0 | Z95: =SUM(Z90:Z94) -> 22526 | AA95: =SUM(AA90:AA94) -> 0 | AB95: =SUM(AB90:AB94) -> 0 | AC95: =SUM(AC90:AC94) -> 0 | ... AE95: =SUM(AE90:AE94) -> 0 | AG95: =SUM(AE95/AA95)-1 -> #DIV/0!
B97: Noncontrolling interests | C97: =568 -> 568 | D97: 570 | E97: 524 | F97: 462 | K97: =D97 -> 570 | O97: =E97 -> 524 | S97: =F97 -> 462 | V97: =K97 -> 570 | W97: =L97 -> 0 | X97: =M97 -> 0 | Y97: =N97 -> 0 | Z97: =O97 -> 524 | AA97: =P97 -> 0 | AB97: =Q97 -> 0 | AC97: =R97 -> 0 | ... AE97: =T97 -> 0
B98: Total Equity | C98: =SUM(C95+C97) -> 22970 | D98: =SUM(D95+D97) -> 23606 | E98: =SUM(E95+E97) -> 23050 | F98: =SUM(F95+F97) -> 16782 | H98: =SUM(H95+H97) -> 0 | I98: =SUM(I95+I97) -> 0 | J98: =SUM(J95+J97) -> 0 | K98: =SUM(K95+K97) -> 23606 | L98: =SUM(L95+L97) -> 0 | M98: =SUM(M95+M97) -> 0 | N98: =SUM(N95+N97) -> 0 | O98: =SUM(O95+O97) -> 23050 | ... T98: =SUM(T95+T97) -> 0 | V98: =SUM(V95+V97) -> 23606 | W98: =SUM(W95+W97) -> 0 | X98: =SUM(X95+X97) -> 0 | Y98: =SUM(Y95+Y97) -> 0 | Z98: =SUM(Z95+Z97) -> 23050 | AA98: =SUM(AA95+AA97) -> 0 | AB98: =SUM(AB95+AB97) -> 0 | AC98: =SUM(AC95+AC97) -> 0 | ... AE98: =SUM(AE95+AE97) -> 0
B99: Total liabilities and stockholders' equity | C99: =SUM(C98+C88) -> 58620 | D99: =SUM(D98+D88) -> 58393 | E99: =SUM(E98+E88) -> 53543 | F99: =SUM(F98+F88) -> 46172 | H99: =SUM(H98+H88) -> 0 | I99: =SUM(I98+I88) -> 0 | J99: =SUM(J98+J88) -> 0 | K99: =SUM(K98+K88) -> 58393 | L99: =SUM(L98+L88) -> 0 | M99: =SUM(M98+M88) -> 0 | N99: =SUM(N98+N88) -> 0 | O99: =SUM(O98+O88) -> 53543 | ... T99: =SUM(T98+T88) -> 0 | V99: =SUM(V98+V88) -> 58393 | W99: =SUM(W98+W88) -> 0 | X99: =SUM(X98+X88) -> 0 | Y99: =SUM(Y98+Y88) -> 0 | Z99: =SUM(Z98+Z88) -> 53543 | AA99: =SUM(AA98+AA88) -> 0 | AB99: =SUM(AB98+AB88) -> 0 | AC99: =SUM(AC98+AC88) -> 0 | ... AE99: =SUM(AE98+AE88) -> 0 | AG99: =SUM(AE99/AA99)-1 -> #DIV/0!
B101: Balance Check | C101: =C99-C68 -> 0 | D101: =D99-D68 -> 0 | E101: =E99-E68 -> 0 | F101: =F99-F68 -> 0 | H101: =H99-H68 -> 0 | I101: =I99-I68 -> 0 | J101: =J99-J68 -> 0 | K101: =K99-K68 -> 0 | L101: =L99-L68 -> 0 | M101: =M99-M68 -> 0 | N101: =N99-N68 -> 0 | O101: =O99-O68 -> 0 | ... T101: =T99-T68 -> 0 | V101: =V99-V68 -> 0 | W101: =W99-W68 -> 0 | X101: =X99-X68 -> 0 | Y101: =Y99-Y68 -> 0 | Z101: =Z99-Z68 -> 0 | AA101: =AA99-AA68 -> 0 | AB101: =AB99-AB68 -> 0 | AC101: =AC99-AC68 -> 0 | ... AE101: =AE99-AE68 -> 0
A104: X | B104: Cash-Flows Statement | C104: FYE | N104: Quarterly | AA104: LTM | AG104: Variance
B105: =B7 -> Fiscal Period | C105: =C7 -> 2021 | D105: =D7 -> 2022 | E105: =E7 -> 2023 | F105: =F7 -> 2024 | H105: =H7 -> 1Q23 | I105: =I7 -> 2Q23 | J105: =J7 -> 3Q23 | K105: =K7 -> 4Q23 | L105: =L7 -> 1Q24 | M105: =M7 -> 2Q24 | N105: =N7 -> 3Q24 | O105: =O7 -> 4Q24 | ... T105: =T7 -> 1Q26 | V105: =V7 -> 4Q23 | W105: =W7 -> 1Q24 | X105: =X7 -> 2Q24 | Y105: =Y7 -> 3Q24 | Z105: =Z7 -> 4Q24 | AA105: =AA7 -> 1Q25 | AB105: =AB7 -> 2Q25 | AC105: =AC7 -> 3Q25 | ... AE105: =AE7 -> 1Q26
B106: =B8 -> Fiscal Period End Date | C106: =C8 -> 44561 | D106: =D8 -> 44926 | E106: =E8 -> 45291 | F106: =F8 -> 45657 | H106: =H8 -> XXX | I106: =I8 -> XXX | J106: =J8 -> XXX | K106: =K8 -> 44926 | L106: =L8 -> XXX | M106: =M8 -> XXX | N106: =N8 -> XXX | O106: =O8 -> 45291 | ... T106: =T8 -> XXX | V106: =V8 -> 44926 | W106: =W8 -> XXX | X106: =X8 -> XXX | Y106: =Y8 -> XXX | Z106: =Z8 -> 45291 | AA106: =AA8 -> XXX | AB106: =AB8 -> XXX | AC106: =AC8 -> XXX | ... AE106: =AE8 -> XXX
B108: Cash-Flows From Operating Activities
B109: Net earnings (loss) from continuing operations | C109: =C33 -> 4469 | D109: =D33 -> 835 | E109: =E33 -> -1252 | F109: =F33 -> -6163 | H109: =H33 -> 0 | I109: =I33 -> 0 | J109: =J33 -> 0 | K109: =K33 -> 835 | L109: =L33 -> 0 | M109: =M33 -> 0 | N109: =N33 -> 0 | O109: =O33 -> -1252 | ... T109: =T33 -> 0 | V109: =V39 -> -1093 | W109: =W39 -> -1093 | X109: =X39 -> -1093 | Y109: =Y39 -> -1093 | Z109: =Z39 -> -275 | AA109: =AA39 -> -275 | AB109: =AB39 -> -275 | AC109: =AC39 -> -275 | ... AE109: =AE39 -> -873 | AG109: =SUM(AE109/AA109)-1 -> 2.1745455
B111: Adjustments to reconcile net income:
B112: Programming charges | C112: — | D112: 0 | E112: 2371 | F112: 1118 | K112: =SUM(D112-SUM(H112:J112)) -> 0 | O112: =SUM(E112-SUM(L112:N112)) -> 2371 | S112: =SUM(F112-SUM(P112:R112)) -> 1118 | V112: =SUM(H112:K112) -> 0 | W112: =SUM(I112:L112) -> 0 | X112: =SUM(J112:M112) -> 0 | Y112: =SUM(K112:N112) -> 0 | Z112: =SUM(L112:O112) -> 2371 | AA112: =SUM(M112:P112) -> 2371 | AB112: =SUM(N112:Q112) -> 2371 | AC112: =SUM(O112:R112) -> 2371 | ... AE112: =SUM(Q112:T112) -> 1118 | AG112: =SUM(AE112/AA112)-1 -> -0.528469
B113: Depreciation and amortization | C113: 390 | D113: 378 | E113: 418 | F113: 392 | K113: =SUM(D113-SUM(H113:J113)) -> 378 | O113: =SUM(E113-SUM(L113:N113)) -> 418 | S113: =SUM(F113-SUM(P113:R113)) -> 392 | V113: =SUM(H113:K113) -> 378 | W113: =SUM(I113:L113) -> 378 | X113: =SUM(J113:M113) -> 378 | Y113: =SUM(K113:N113) -> 378 | Z113: =SUM(L113:O113) -> 418 | AA113: =SUM(M113:P113) -> 418 | AB113: =SUM(N113:Q113) -> 418 | AC113: =SUM(O113:R113) -> 418 | ... AE113: =SUM(Q113:T113) -> 392 | AG113: =SUM(AE113/AA113)-1 -> -0.062200957
B114: Impairment charges | C114: — | D114: 27 | E114: 83 | F114: 6130 | K114: =SUM(D114-SUM(H114:J114)) -> 27 | O114: =SUM(E114-SUM(L114:N114)) -> 83 | S114: =SUM(F114-SUM(P114:R114)) -> 6130 | V114: =SUM(H114:K114) -> 27 | W114: =SUM(I114:L114) -> 27 | X114: =SUM(J114:M114) -> 27 | Y114: =SUM(K114:N114) -> 27 | Z114: =SUM(L114:O114) -> 83 | AA114: =SUM(M114:P114) -> 83 | AB114: =SUM(N114:Q114) -> 83 | AC114: =SUM(O114:R114) -> 83 | ... AE114: =SUM(Q114:T114) -> 6130 | AG114: =SUM(AE114/AA114)-1 -> 72.855422
B115: Amortization of content costs and participation and residuals expense | C115: 13649 | D115: 14951 | E115: 14713 | F115: 13888 | K115: =SUM(D115-SUM(H115:J115)) -> 14951 | O115: =SUM(E115-SUM(L115:N115)) -> 14713 | S115: =SUM(F115-SUM(P115:R115)) -> 13888 | V115: =SUM(H115:K115) -> 14951 | W115: =SUM(I115:L115) -> 14951 | X115: =SUM(J115:M115) -> 14951 | Y115: =SUM(K115:N115) -> 14951 | Z115: =SUM(L115:O115) -> 14713 | AA115: =SUM(M115:P115) -> 14713 | AB115: =SUM(N115:Q115) -> 14713 | AC115: =SUM(O115:R115) -> 14713 | ... AE115: =SUM(Q115:T115) -> 13888 | AG115: =SUM(AE115/AA115)-1 -> -0.056072861
B116: Deferred tax benefit | C116: 90 | D116: -106 | E116: -650 | F116: -630 | K116: =SUM(D116-SUM(H116:J116)) -> -106 | O116: =SUM(E116-SUM(L116:N116)) -> -650 | S116: =SUM(F116-SUM(P116:R116)) -> -630 | V116: =SUM(H116:K116) -> -106 | W116: =SUM(I116:L116) -> -106 | X116: =SUM(J116:M116) -> -106 | Y116: =SUM(K116:N116) -> -106 | Z116: =SUM(L116:O116) -> -650 | AA116: =SUM(M116:P116) -> -650 | AB116: =SUM(N116:Q116) -> -650 | AC116: =SUM(O116:R116) -> -650 | ... AE116: =SUM(Q116:T116) -> -630 | AG116: =SUM(AE116/AA116)-1 -> -0.030769231
B117: Stock-based compensation | C117: 192 | D117: 172 | E117: 177 | F117: 245 | K117: =SUM(D117-SUM(H117:J117)) -> 172 | O117: =SUM(E117-SUM(L117:N117)) -> 177 | S117: =SUM(F117-SUM(P117:R117)) -> 245 | V117: =SUM(H117:K117) -> 172 | W117: =SUM(I117:L117) -> 172 | X117: =SUM(J117:M117) -> 172 | Y117: =SUM(K117:N117) -> 172 | Z117: =SUM(L117:O117) -> 177 | AA117: =SUM(M117:P117) -> 177 | AB117: =SUM(N117:Q117) -> 177 | AC117: =SUM(O117:R117) -> 177 | ... AE117: =SUM(Q117:T117) -> 245 | AG117: =SUM(AE117/AA117)-1 -> 0.38418079
B118: Gains on dispositions | C118: -2343 | D118: -56 | E118: 0 | F118: 0 | K118: =SUM(D118-SUM(H118:J118)) -> -56 | O118: =SUM(E118-SUM(L118:N118)) -> 0 | S118: =SUM(F118-SUM(P118:R118)) -> 0 | V118: =SUM(H118:K118) -> -56 | W118: =SUM(I118:L118) -> -56 | X118: =SUM(J118:M118) -> -56 | Y118: =SUM(K118:N118) -> -56 | Z118: =SUM(L118:O118) -> 0 | AA118: =SUM(M118:P118) -> 0 | AB118: =SUM(N118:Q118) -> 0 | AC118: =SUM(O118:R118) -> 0 | ... AE118: =SUM(Q118:T118) -> 0 | AG118: =SUM(AE118/AA118)-1 -> #DIV/0!
B119: (Gain) loss from investments | C119: -47 | D119: 9 | E119: -168 | F119: 17 | K119: =SUM(D119-SUM(H119:J119)) -> 9 | O119: =SUM(E119-SUM(L119:N119)) -> -168 | S119: =SUM(F119-SUM(P119:R119)) -> 17 | V119: =SUM(H119:K119) -> 9 | W119: =SUM(I119:L119) -> 9 | X119: =SUM(J119:M119) -> 9 | Y119: =SUM(K119:N119) -> 9 | Z119: =SUM(L119:O119) -> -168 | AA119: =SUM(M119:P119) -> -168 | AB119: =SUM(N119:Q119) -> -168 | AC119: =SUM(O119:R119) -> -168 | ... AE119: =SUM(Q119:T119) -> 17 | AG119: =SUM(AE119/AA119)-1 -> -1.1011905
B120: (Gain) loss on extinguishment of debt | C120: 128 | D120: 120 | E120: -29 | F120: 0 | K120: =SUM(D120-SUM(H120:J120)) -> 120 | O120: =SUM(E120-SUM(L120:N120)) -> -29 | S120: =SUM(F120-SUM(P120:R120)) -> 0 | V120: =SUM(H120:K120) -> 120 | W120: =SUM(I120:L120) -> 120 | X120: =SUM(J120:M120) -> 120 | Y120: =SUM(K120:N120) -> 120 | Z120: =SUM(L120:O120) -> -29 | AA120: =SUM(M120:P120) -> -29 | AB120: =SUM(N120:Q120) -> -29 | AC120: =SUM(O120:R120) -> -29 | ... AE120: =SUM(Q120:T120) -> 0 | AG120: =SUM(AE120/AA120)-1 -> -1
B121: Equity in loss of investee companies, net of tax and distributions | C121: 96 | D121: 207 | E121: 363 | F121: 304 | K121: =SUM(D121-SUM(H121:J121)) -> 207 | O121: =SUM(E121-SUM(L121:N121)) -> 363 | S121: =SUM(F121-SUM(P121:R121)) -> 304 | V121: =SUM(H121:K121) -> 207 | W121: =SUM(I121:L121) -> 207 | X121: =SUM(J121:M121) -> 207 | Y121: =SUM(K121:N121) -> 207 | Z121: =SUM(L121:O121) -> 363 | AA121: =SUM(M121:P121) -> 363 | AB121: =SUM(N121:Q121) -> 363 | AC121: =SUM(O121:R121) -> 363 | ... AE121: =SUM(Q121:T121) -> 304 | AG121: =SUM(AE121/AA121)-1 -> -0.16253444
B122: Other, net | C122: -51 | D122: -159 | E122: -186 | F122: 227 | K122: =SUM(D122-SUM(H122:J122)) -> -159 | O122: =SUM(E122-SUM(L122:N122)) -> -186 | S122: =SUM(F122-SUM(P122:R122)) -> 227 | V122: =SUM(H122:K122) -> -159 | W122: =SUM(I122:L122) -> -159 | X122: =SUM(J122:M122) -> -159 | Y122: =SUM(K122:N122) -> -159 | Z122: =SUM(L122:O122) -> -186 | AA122: =SUM(M122:P122) -> -186 | AB122: =SUM(N122:Q122) -> -186 | AC122: =SUM(O122:R122) -> -186 | ... AE122: =SUM(Q122:T122) -> 227 | AG122: =SUM(AE122/AA122)-1 -> -2.2204301
...

Sheet Revenue Drivers
B2: ='Historical Financials'!B2 -> Paramount Global (NASDAQ: PARA) | C2: FYE | N2: Quarterly | AA2: LTM
B3: Segment Anaysis | C3: ='Historical Financials'!C7 -> 2021 | D3: ='Historical Financials'!D7 -> 2022 | E3: ='Historical Financials'!E7 -> 2023 | F3: ='Historical Financials'!F7 -> 2024 | H3: ='Historical Financials'!H7 -> 1Q23 | I3: ='Historical Financials'!I7 -> 2Q23 | J3: ='Historical Financials'!J7 -> 3Q23 | K3: ='Historical Financials'!K7 -> 4Q23 | L3: ='Historical Financials'!L7 -> 1Q24 | M3: ='Historical Financials'!M7 -> 2Q24 | N3: ='Historical Financials'!N7 -> 3Q24 | O3: ='Historical Financials'!O7 -> 4Q24 | ... T3: ='Historical Financials'!T7 -> 1Q26 | V3: =K3 -> 4Q23 | W3: =L3 -> 1Q24 | X3: =M3 -> 2Q24 | Y3: =N3 -> 3Q24 | Z3: =O3 -> 4Q24 | AA3: =P3 -> 1Q25 | AB3: =Q3 -> 2Q25 | AC3: =R3 -> 3Q25 | ... AE3: =T3 -> 1Q26
B4: ($ In Millions) | C4: ='Historical Financials'!C8 -> 44561 | D4: ='Historical Financials'!D8 -> 44926 | E4: ='Historical Financials'!E8 -> 45291 | F4: ='Historical Financials'!F8 -> 45657 | H4: ='Historical Financials'!H8 -> XXX | I4: ='Historical Financials'!I8 -> XXX | J4: ='Historical Financials'!J8 -> XXX | K4: ='Historical Financials'!K8 -> 44926 | L4: ='Historical Financials'!L8 -> XXX | M4: ='Historical Financials'!M8 -> XXX | N4: ='Historical Financials'!N8 -> XXX | O4: ='Historical Financials'!O8 -> 45291 | ... T4: ='Historical Financials'!T8 -> XXX | V4: =K4 -> 44926 | W4: =L4 -> XXX | X4: =M4 -> XXX | Y4: =N4 -> XXX | Z4: =O4 -> 45291 | AA4: =P4 -> XXX | AB4: =Q4 -> XXX | AC4: =R4 -> XXX | ... AE4: =T4 -> XXX
A6: X | B6: Revenue by reportable segment
A8: X | B8: Revenue by Type
B9: Advertising | C9: 11412 | D9: 10890 | E9: 9989 | F9: 10295 | K9: =SUM(D9-SUM(H9:J9)) -> 10890 | O9: =SUM(E9-SUM(L9:N9)) -> 9989 | S9: =SUM(F9-SUM(P9:R9)) -> 10295 | V9: =SUM(H9:K9) -> 10890 | W9: =SUM(I9:L9) -> 10890 | X9: =SUM(J9:M9) -> 10890 | Y9: =SUM(K9:N9) -> 10890 | Z9: =SUM(L9:O9) -> 9989 | AA9: =SUM(M9:P9) -> 9989 | AB9: =SUM(N9:Q9) -> 9989 | AC9: =SUM(O9:R9) -> 9989 | ... AE9: =SUM(Q9:T9) -> 10295
B10: Affiliate and subscription | C10: 10442 | D10: 11551 | E10: 13018 | F10: 13153 | K10: =SUM(D10-SUM(H10:J10)) -> 11551 | O10: =SUM(E10-SUM(L10:N10)) -> 13018 | S10: =SUM(F10-SUM(P10:R10)) -> 13153 | V10: =SUM(H10:K10) -> 11551 | W10: =SUM(I10:L10) -> 11551 | X10: =SUM(J10:M10) -> 11551 | Y10: =SUM(K10:N10) -> 11551 | Z10: =SUM(L10:O10) -> 13018 | AA10: =SUM(M10:P10) -> 13018 | AB10: =SUM(N10:Q10) -> 13018 | AC10: =SUM(O10:R10) -> 13018 | ... AE10: =SUM(Q10:T10) -> 13153
B11: Theatrical | C11: 241 | D11: 1223 | E11: 813 | F11: 813 | K11: =SUM(D11-SUM(H11:J11)) -> 1223 | O11: =SUM(E11-SUM(L11:N11)) -> 813 | S11: =SUM(F11-SUM(P11:R11)) -> 813 | V11: =SUM(H11:K11) -> 1223 | W11: =SUM(I11:L11) -> 1223 | X11: =SUM(J11:M11) -> 1223 | Y11: =SUM(K11:N11) -> 1223 | Z11: =SUM(L11:O11) -> 813 | AA11: =SUM(M11:P11) -> 813 | AB11: =SUM(N11:Q11) -> 813 | AC11: =SUM(O11:R11) -> 813 | ... AE11: =SUM(Q11:T11) -> 813
B12: Licensing and other | C12: 6491 | D12: 6490 | E12: 5832 | F12: 4952 | K12: =SUM(D12-SUM(H12:J12)) -> 6490 | O12: =SUM(E12-SUM(L12:N12)) -> 5832 | S12: =SUM(F12-SUM(P12:R12)) -> 4952 | V12: =SUM(H12:K12) -> 6490 | W12: =SUM(I12:L12) -> 6490 | X12: =SUM(J12:M12) -> 6490 | Y12: =SUM(K12:N12) -> 6490 | Z12: =SUM(L12:O12) -> 5832 | AA12: =SUM(M12:P12) -> 5832 | AB12: =SUM(N12:Q12) -> 5832 | AC12: =SUM(O12:R12) -> 5832 | ... AE12: =SUM(Q12:T12) -> 4952
B13: Total Net Revenue | C13: =SUM(C9:C12) -> 28586 | D13: =SUM(D9:D12) -> 30154 | E13: =SUM(E9:E12) -> 29652 | F13: =SUM(F9:F12) -> 29213 | H13: =SUM(H9:H12) -> 0 | I13: =SUM(I9:I12) -> 0 | J13: =SUM(J9:J12) -> 0 | K13: =SUM(K9:K12) -> 30154 | L13: =SUM(L9:L12) -> 0 | M13: =SUM(M9:M12) -> 0 | N13: =SUM(N9:N12) -> 0 | O13: =SUM(O9:O12) -> 29652 | ... T13: =SUM(T9:T12) -> 0 | V13: =SUM(V9:V12) -> 30154 | W13: =SUM(W9:W12) -> 30154 | X13: =SUM(X9:X12) -> 30154 | Y13: =SUM(Y9:Y12) -> 30154 | Z13: =SUM(Z9:Z12) -> 29652 | AA13: =SUM(AA9:AA12) -> 29652 | AB13: =SUM(AB9:AB12) -> 29652 | AC13: =SUM(AC9:AC12) -> 29652 | ... AE13: =SUM(AE9:AE12) -> 29213
B14: Variance Check | C14: =+C13-'Historical Financials'!C11 -> 0 | D14: =+D13-'Historical Financials'!D11 -> 0 | E14: =+E13-'Historical Financials'!E11 -> 0 | F14: =+F13-'Historical Financials'!F11 -> 0 | H14: =+H13-'Historical Financials'!H11 -> 0 | I14: =+I13-'Historical Financials'!I11 -> 0 | J14: =+J13-'Historical Financials'!J11 -> 0 | K14: =+K13-'Historical Financials'!K11 -> 0 | L14: =+L13-'Historical Financials'!L11 -> 0 | M14: =+M13-'Historical Financials'!M11 -> 0 | N14: =+N13-'Historical Financials'!N11 -> 0 | O14: =+O13-'Historical Financials'!O11 -> 0 | ... T14: =+T13-'Historical Financials'!T11 -> 0 | V14: =+V13-'Historical Financials'!V11 -> 0 | W14: =+W13-'Historical Financials'!W11 -> 0 | X14: =+X13-'Historical Financials'!X11 -> 0 | Y14: =+Y13-'Historical Financials'!Y11 -> 0 | Z14: =+Z13-'Historical Financials'!Z11 -> 0 | AA14: =+AA13-'Historical Financials'!AA11 -> 0 | AB14: =+AB13-'Historical Financials'!AB11 -> 0 | AC14: =+AC13-'Historical Financials'!AC11 -> 0 | ... AE14: =+AE13-'Historical Financials'!AE11 -> 0
B16: =B9&"(%)" -> Advertising(%) | C16: =SUM(C9/C$13) -> 0.3992164 | D16: =SUM(D9/D$13) -> 0.36114612 | E16: =SUM(E9/E$13) -> 0.33687441 | F16: =SUM(F9/F$13) -> 0.3524116 | H16: =SUM(H9/H$13) -> #DIV/0! | I16: =SUM(I9/I$13) -> #DIV/0! | J16: =SUM(J9/J$13) -> #DIV/0! | K16: =SUM(K9/K$13) -> 0.36114612 | L16: =SUM(L9/L$13) -> #DIV/0! | M16: =SUM(M9/M$13) -> #DIV/0! | N16: =SUM(N9/N$13) -> #DIV/0! | O16: =SUM(O9/O$13) -> 0.33687441 | ... T16: =SUM(T9/T$13) -> #DIV/0! | V16: =I16 -> #DIV/0! | W16: =J16 -> #DIV/0! | X16: =K16 -> 0.36114612 | Y16: =L16 -> #DIV/0! | Z16: =M16 -> #DIV/0! | AA16: =N16 -> #DIV/0! | AB16: =O16 -> 0.33687441 | AC16: =P16 -> #DIV/0! | ... AE16: =R16 -> #DIV/0!
B17: =B10&"(%)" -> Affiliate and subscription(%) | C17: =SUM(C10/C$13) -> 0.36528371 | D17: =SUM(D10/D$13) -> 0.38306692 | E17: =SUM(E10/E$13) -> 0.43902604 | F17: =SUM(F10/F$13) -> 0.45024475 | H17: =SUM(H10/H$13) -> #DIV/0! | I17: =SUM(I10/I$13) -> #DIV/0! | J17: =SUM(J10/J$13) -> #DIV/0! | K17: =SUM(K10/K$13) -> 0.38306692 | L17: =SUM(L10/L$13) -> #DIV/0! | M17: =SUM(M10/M$13) -> #DIV/0! | N17: =SUM(N10/N$13) -> #DIV/0! | O17: =SUM(O10/O$13) -> 0.43902604 | ... T17: =SUM(T10/T$13) -> #DIV/0! | V17: =I17 -> #DIV/0! | W17: =J17 -> #DIV/0! | X17: =K17 -> 0.38306692 | Y17: =L17 -> #DIV/0! | Z17: =M17 -> #DIV/0! | AA17: =N17 -> #DIV/0! | AB17: =O17 -> 0.43902604 | AC17: =P17 -> #DIV/0! | ... AE17: =R17 -> #DIV/0!
B18: =B11&"(%)" -> Theatrical(%) | C18: =SUM(C11/C$13) -> 0.0084307003 | D18: =SUM(D11/D$13) -> 0.040558467 | E18: =SUM(E11/E$13) -> 0.027418049 | F18: =SUM(F11/F$13) -> 0.027830076 | H18: =SUM(H11/H$13) -> #DIV/0! | I18: =SUM(I11/I$13) -> #DIV/0! | J18: =SUM(J11/J$13) -> #DIV/0! | K18: =SUM(K11/K$13) -> 0.040558467 | L18: =SUM(L11/L$13) -> #DIV/0! | M18: =SUM(M11/M$13) -> #DIV/0! | N18: =SUM(N11/N$13) -> #DIV/0! | O18: =SUM(O11/O$13) -> 0.027418049 | ... T18: =SUM(T11/T$13) -> #DIV/0! | V18: =I18 -> #DIV/0! | W18: =J18 -> #DIV/0! | X18: =K18 -> 0.040558467 | Y18: =L18 -> #DIV/0! | Z18: =M18 -> #DIV/0! | AA18: =N18 -> #DIV/0! | AB18: =O18 -> 0.027418049 | AC18: =P18 -> #DIV/0! | ... AE18: =R18 -> #DIV/0!
B19: =B12&"(%)" -> Licensing and other(%) | C19: =SUM(C12/C$13) -> 0.22706919 | D19: =SUM(D12/D$13) -> 0.21522849 | E19: =SUM(E12/E$13) -> 0.19668151 | F19: =SUM(F12/F$13) -> 0.16951357 | H19: =SUM(H12/H$13) -> #DIV/0! | I19: =SUM(I12/I$13) -> #DIV/0! | J19: =SUM(J12/J$13) -> #DIV/0! | K19: =SUM(K12/K$13) -> 0.21522849 | L19: =SUM(L12/L$13) -> #DIV/0! | M19: =SUM(M12/M$13) -> #DIV/0! | N19: =SUM(N12/N$13) -> #DIV/0! | O19: =SUM(O12/O$13) -> 0.19668151 | ... T19: =SUM(T12/T$13) -> #DIV/0! | V19: =I19 -> #DIV/0! | W19: =J19 -> #DIV/0! | X19: =K19 -> 0.21522849 | Y19: =L19 -> #DIV/0! | Z19: =M19 -> #DIV/0! | AA19: =N19 -> #DIV/0! | AB19: =O19 -> 0.19668151 | AC19: =P19 -> #DIV/0! | ... AE19: =R19 -> #DIV/0!
A21: X | B21: Revenue by Type
B22: TV Media | C22: 22734 | D22: 21732 | E22: 20085 | F22: 18779 | K22: =SUM(D22-SUM(H22:J22)) -> 21732 | O22: =SUM(E22-SUM(L22:N22)) -> 20085 | S22: =SUM(F22-SUM(P22:R22)) -> 18779 | V22: =SUM(H22:K22) -> 21732 | W22: =SUM(I22:L22) -> 21732 | X22: =SUM(J22:M22) -> 21732 | Y22: =SUM(K22:N22) -> 21732 | Z22: =SUM(L22:O22) -> 20085 | AA22: =SUM(M22:P22) -> 20085 | AB22: =SUM(N22:Q22) -> 20085 | AC22: =SUM(O22:R22) -> 20085 | ... AE22: =SUM(Q22:T22) -> 18779
B23: Direct-to-Consumer | C23: 3327 | D23: 4904 | E23: 6736 | F23: 7632 | K23: =SUM(D23-SUM(H23:J23)) -> 4904 | O23: =SUM(E23-SUM(L23:N23)) -> 6736 | S23: =SUM(F23-SUM(P23:R23)) -> 7632 | V23: =SUM(H23:K23) -> 4904 | W23: =SUM(I23:L23) -> 4904 | X23: =SUM(J23:M23) -> 4904 | Y23: =SUM(K23:N23) -> 4904 | Z23: =SUM(L23:O23) -> 6736 | AA23: =SUM(M23:P23) -> 6736 | AB23: =SUM(N23:Q23) -> 6736 | AC23: =SUM(O23:R23) -> 6736 | ... AE23: =SUM(Q23:T23) -> 7632
B24: Filmed Entertainment | C24: 2687 | D24: 3706 | E24: 2957 | F24: 2955 | K24: =SUM(D24-SUM(H24:J24)) -> 3706 | O24: =SUM(E24-SUM(L24:N24)) -> 2957 | S24: =SUM(F24-SUM(P24:R24)) -> 2955 | V24: =SUM(H24:K24) -> 3706 | W24: =SUM(I24:L24) -> 3706 | X24: =SUM(J24:M24) -> 3706 | Y24: =SUM(K24:N24) -> 3706 | Z24: =SUM(L24:O24) -> 2957 | AA24: =SUM(M24:P24) -> 2957 | AB24: =SUM(N24:Q24) -> 2957 | AC24: =SUM(O24:R24) -> 2957 | ... AE24: =SUM(Q24:T24) -> 2955
B25: Eliminations | C25: -162 | D25: -188 | E25: -126 | F25: -153 | K25: =SUM(D25-SUM(H25:J25)) -> -188 | O25: =SUM(E25-SUM(L25:N25)) -> -126 | S25: =SUM(F25-SUM(P25:R25)) -> -153 | V25: =SUM(H25:K25) -> -188 | W25: =SUM(I25:L25) -> -188 | X25: =SUM(J25:M25) -> -188 | Y25: =SUM(K25:N25) -> -188 | Z25: =SUM(L25:O25) -> -126 | AA25: =SUM(M25:P25) -> -126 | AB25: =SUM(N25:Q25) -> -126 | AC25: =SUM(O25:R25) -> -126 | ... AE25: =SUM(Q25:T25) -> -153
B26: Total Net Revenue | C26: =SUM(C22:C25) -> 28586 | D26: =SUM(D22:D25) -> 30154 | E26: =SUM(E22:E25) -> 29652 | F26: =SUM(F22:F25) -> 29213 | H26: =SUM(H22:H25) -> 0 | I26: =SUM(I22:I25) -> 0 | J26: =SUM(J22:J25) -> 0 | K26: =SUM(K22:K25) -> 30154 | L26: =SUM(L22:L25) -> 0 | M26: =SUM(M22:M25) -> 0 | N26: =SUM(N22:N25) -> 0 | O26: =SUM(O22:O25) -> 29652 | ... T26: =SUM(T22:T25) -> 0 | V26: =SUM(V22:V25) -> 30154 | W26: =SUM(W22:W25) -> 30154 | X26: =SUM(X22:X25) -> 30154 | Y26: =SUM(Y22:Y25) -> 30154 | Z26: =SUM(Z22:Z25) -> 29652 | AA26: =SUM(AA22:AA25) -> 29652 | AB26: =SUM(AB22:AB25) -> 29652 | AC26: =SUM(AC22:AC25) -> 29652 | ... AE26: =SUM(AE22:AE25) -> 29213
B27: Variance Check | C27: =+C26-C13 -> 0 | D27: =+D26-D13 -> 0 | E27: =+E26-E13 -> 0 | F27: =+F26-F13 -> 0 | H27: =+H26-H13 -> 0 | I27: =+I26-I13 -> 0 | J27: =+J26-J13 -> 0 | K27: =+K26-K13 -> 0 | L27: =+L26-L13 -> 0 | M27: =+M26-M13 -> 0 | N27: =+N26-N13 -> 0 | O27: =+O26-O13 -> 0 | ... T27: =+T26-T13 -> 0 | V27: =+V26-V13 -> 0 | W27: =+W26-W13 -> 0 | X27: =+X26-X13 -> 0 | Y27: =+Y26-Y13 -> 0 | Z27: =+Z26-Z13 -> 0 | AA27: =+AA26-AA13 -> 0 | AB27: =+AB26-AB13 -> 0 | AC27: =+AC26-AC13 -> 0 | ... AE27: =+AE26-AE13 -> 0
B29: =B22&"(%)" -> TV Media(%) | C29: =SUM(C22/C$26) -> 0.7952844 | D29: =SUM(D22/D$26) -> 0.7207004 | E29: =SUM(E22/E$26) -> 0.67735735 | F29: =SUM(F22/F$26) -> 0.64283025 | H29: =SUM(H22/H$26) -> #DIV/0! | I29: =SUM(I22/I$26) -> #DIV/0! | J29: =SUM(J22/J$26) -> #DIV/0! | K29: =SUM(K22/K$26) -> 0.7207004 | L29: =SUM(L22/L$26) -> #DIV/0! | M29: =SUM(M22/M$26) -> #DIV/0! | N29: =SUM(N22/N$26) -> #DIV/0! | O29: =SUM(O22/O$26) -> 0.67735735 | ... T29: =SUM(T22/T$26) -> #DIV/0! | V29: =SUM(V22/V$26) -> 0.7207004 | W29: =SUM(W22/W$26) -> 0.7207004 | X29: =SUM(X22/X$26) -> 0.7207004 | Y29: =SUM(Y22/Y$26) -> 0.7207004 | Z29: =SUM(Z22/Z$26) -> 0.67735735 | AA29: =SUM(AA22/AA$26) -> 0.67735735 | AB29: =SUM(AB22/AB$26) -> 0.67735735 | AC29: =SUM(AC22/AC$26) -> 0.67735735 | ... AE29: =SUM(AE22/AE$26) -> 0.64283025
B30: =B23&"(%)" -> Direct-to-Consumer(%) | C30: =SUM(C23/C$26) -> 0.11638564 | D30: =SUM(D23/D$26) -> 0.16263182 | E30: =SUM(E23/E$26) -> 0.22716849 | F30: =SUM(F23/F$26) -> 0.26125355 | H30: =SUM(H23/H$26) -> #DIV/0! | I30: =SUM(I23/I$26) -> #DIV/0! | J30: =SUM(J23/J$26) -> #DIV/0! | K30: =SUM(K23/K$26) -> 0.16263182 | L30: =SUM(L23/L$26) -> #DIV/0! | M30: =SUM(M23/M$26) -> #DIV/0! | N30: =SUM(N23/N$26) -> #DIV/0! | O30: =SUM(O23/O$26) -> 0.22716849 | ... T30: =SUM(T23/T$26) -> #DIV/0! | V30: =SUM(V23/V$26) -> 0.16263182 | W30: =SUM(W23/W$26) -> 0.16263182 | X30: =SUM(X23/X$26) -> 0.16263182 | Y30: =SUM(Y23/Y$26) -> 0.16263182 | Z30: =SUM(Z23/Z$26) -> 0.22716849 | AA30: =SUM(AA23/AA$26) -> 0.22716849 | AB30: =SUM(AB23/AB$26) -> 0.22716849 | AC30: =SUM(AC23/AC$26) -> 0.22716849 | ... AE30: =SUM(AE23/AE$26) -> 0.26125355
B31: =B24&"(%)" -> Filmed Entertainment(%) | C31: =SUM(C24/C$26) -> 0.093997061 | D31: =SUM(D24/D$26) -> 0.12290243 | E31: =SUM(E24/E$26) -> 0.099723459 | F31: =SUM(F24/F$26) -> 0.1011536 | H31: =SUM(H24/H$26) -> #DIV/0! | I31: =SUM(I24/I$26) -> #DIV/0! | J31: =SUM(J24/J$26) -> #DIV/0! | K31: =SUM(K24/K$26) -> 0.12290243 | L31: =SUM(L24/L$26) -> #DIV/0! | M31: =SUM(M24/M$26) -> #DIV/0! | N31: =SUM(N24/N$26) -> #DIV/0! | O31: =SUM(O24/O$26) -> 0.099723459 | ... T31: =SUM(T24/T$26) -> #DIV/0! | V31: =SUM(V24/V$26) -> 0.12290243 | W31: =SUM(W24/W$26) -> 0.12290243 | X31: =SUM(X24/X$26) -> 0.12290243 | Y31: =SUM(Y24/Y$26) -> 0.12290243 | Z31: =SUM(Z24/Z$26) -> 0.099723459 | AA31: =SUM(AA24/AA$26) -> 0.099723459 | AB31: =SUM(AB24/AB$26) -> 0.099723459 | AC31: =SUM(AC24/AC$26) -> 0.099723459 | ... AE31: =SUM(AE24/AE$26) -> 0.1011536
A33: X | B33: Revenue by product category: Revenue by TV Media
A35: X | B35: Revenue by TV Media
B36: Advertising | C36: 10105 | D36: 9350 | E36: 8188 | F36: 8180 | K36: =SUM(D36-SUM(H36:J36)) -> 9350 | O36: =SUM(E36-SUM(L36:N36)) -> 8188 | S36: =SUM(F36-SUM(P36:R36)) -> 8180 | V36: =SUM(H36:K36) -> 9350 | W36: =SUM(I36:L36) -> 9350 | X36: =SUM(J36:M36) -> 9350 | Y36: =SUM(K36:N36) -> 9350 | Z36: =SUM(L36:O36) -> 8188 | AA36: =SUM(M36:P36) -> 8188 | AB36: =SUM(N36:Q36) -> 8188 | AC36: =SUM(O36:R36) -> 8188 | ... AE36: =SUM(Q36:T36) -> 8180
B37: Affiliate and subscription | C37: 8413 | D37: 8180 | E37: 8085 | F37: 7647 | K37: =SUM(D37-SUM(H37:J37)) -> 8180 | O37: =SUM(E37-SUM(L37:N37)) -> 8085 | S37: =SUM(F37-SUM(P37:R37)) -> 7647 | V37: =SUM(H37:K37) -> 8180 | W37: =SUM(I37:L37) -> 8180 | X37: =SUM(J37:M37) -> 8180 | Y37: =SUM(K37:N37) -> 8180 | Z37: =SUM(L37:O37) -> 8085 | AA37: =SUM(M37:P37) -> 8085 | AB37: =SUM(N37:Q37) -> 8085 | AC37: =SUM(O37:R37) -> 8085 | ... AE37: =SUM(Q37:T37) -> 7647
B38: Licensing and other | C38: 4216 | D38: 4202 | E38: 3812 | F38: 2952 | K38: =SUM(D38-SUM(H38:J38)) -> 4202 | O38: =SUM(E38-SUM(L38:N38)) -> 3812 | S38: =SUM(F38-SUM(P38:R38)) -> 2952 | V38: =SUM(H38:K38) -> 4202 | W38: =SUM(I38:L38) -> 4202 | X38: =SUM(J38:M38) -> 4202 | Y38: =SUM(K38:N38) -> 4202 | Z38: =SUM(L38:O38) -> 3812 | AA38: =SUM(M38:P38) -> 3812 | AB38: =SUM(N38:Q38) -> 3812 | AC38: =SUM(O38:R38) -> 3812 | ... AE38: =SUM(Q38:T38) -> 2952
B39: Total Revenue from TV Media | C39: =SUM(C36:C38) -> 22734 | D39: =SUM(D36:D38) -> 21732 | E39: =SUM(E36:E38) -> 20085 | F39: =SUM(F36:F38) -> 18779 | H39: =SUM(H36:H38) -> 0 | I39: =SUM(I36:I38) -> 0 | J39: =SUM(J36:J38) -> 0 | K39: =SUM(K36:K38) -> 21732 | L39: =SUM(L36:L38) -> 0 | M39: =SUM(M36:M38) -> 0 | N39: =SUM(N36:N38) -> 0 | O39: =SUM(O36:O38) -> 20085 | ... T39: =SUM(T36:T38) -> 0 | V39: =SUM(V36:V38) -> 21732 | W39: =SUM(W36:W38) -> 21732 | X39: =SUM(X36:X38) -> 21732 | Y39: =SUM(Y36:Y38) -> 21732 | Z39: =SUM(Z36:Z38) -> 20085 | AA39: =SUM(AA36:AA38) -> 20085 | AB39: =SUM(AB36:AB38) -> 20085 | AC39: =SUM(AC36:AC38) -> 20085 | ... AE39: =SUM(AE36:AE38) -> 18779
B40: Variance Check | C40: =+C39-C22 -> 0 | D40: =+D39-D22 -> 0 | E40: =+E39-E22 -> 0 | F40: =+F39-F22 -> 0 | H40: =+H39-H22 -> 0 | I40: =+I39-I22 -> 0 | J40: =+J39-J22 -> 0 | K40: =+K39-K22 -> 0 | L40: =+L39-L22 -> 0 | M40: =+M39-M22 -> 0 | N40: =+N39-N22 -> 0 | O40: =+O39-O22 -> 0 | ... T40: =+T39-T22 -> 0 | V40: =+V39-V22 -> 0 | W40: =+W39-W22 -> 0 | X40: =+X39-X22 -> 0 | Y40: =+Y39-Y22 -> 0 | Z40: =+Z39-Z22 -> 0 | AA40: =+AA39-AA22 -> 0 | AB40: =+AB39-AB22 -> 0 | AC40: =+AC39-AC22 -> 0 | ... AE40: =+AE39-AE22 -> 0
B42: =B36&"(%)" -> Advertising(%) | C42: =C36/C$39 -> 0.44448843 | D42: =D36/D$39 -> 0.43024112 | E42: =E36/E$39 -> 0.40766741 | F42: =F36/F$39 -> 0.43559295 | H42: =H36/H$39 -> #DIV/0! | I42: =I36/I$39 -> #DIV/0! | J42: =J36/J$39 -> #DIV/0! | K42: =K36/K$39 -> 0.43024112 | L42: =L36/L$39 -> #DIV/0! | M42: =M36/M$39 -> #DIV/0! | N42: =N36/N$39 -> #DIV/0! | O42: =O36/O$39 -> 0.40766741 | ... T42: =T36/T$39 -> #DIV/0! | V42: =V36/V$39 -> 0.43024112 | W42: =W36/W$39 -> 0.43024112 | X42: =X36/X$39 -> 0.43024112 | Y42: =Y36/Y$39 -> 0.43024112 | Z42: =Z36/Z$39 -> 0.40766741 | AA42: =AA36/AA$39 -> 0.40766741 | AB42: =AB36/AB$39 -> 0.40766741 | AC42: =AC36/AC$39 -> 0.40766741 | ... AE42: =AE36/AE$39 -> 0.43559295
B43: =B37&"(%)" -> Affiliate and subscription(%) | C43: =C37/C$39 -> 0.37006246 | D43: =D37/D$39 -> 0.37640346 | E43: =E37/E$39 -> 0.40253921 | F43: =F37/F$39 -> 0.40721018 | H43: =H37/H$39 -> #DIV/0! | I43: =I37/I$39 -> #DIV/0! | J43: =J37/J$39 -> #DIV/0! | K43: =K37/K$39 -> 0.37640346 | L43: =L37/L$39 -> #DIV/0! | M43: =M37/M$39 -> #DIV/0! | N43: =N37/N$39 -> #DIV/0! | O43: =O37/O$39 -> 0.40253921 | ... T43: =T37/T$39 -> #DIV/0! | V43: =V37/V$39 -> 0.37640346 | W43: =W37/W$39 -> 0.37640346 | X43: =X37/X$39 -> 0.37640346 | Y43: =Y37/Y$39 -> 0.37640346 | Z43: =Z37/Z$39 -> 0.40253921 | AA43: =AA37/AA$39 -> 0.40253921 | AB43: =AB37/AB$39 -> 0.40253921 | AC43: =AC37/AC$39 -> 0.40253921 | ... AE43: =AE37/AE$39 -> 0.40721018
B44: =B38&"(%)" -> Licensing and other(%) | C44: =C38/C$39 -> 0.18544911 | D44: =D38/D$39 -> 0.19335542 | E44: =E38/E$39 -> 0.18979338 | F44: =F38/F$39 -> 0.15719687 | H44: =H38/H$39 -> #DIV/0! | I44: =I38/I$39 -> #DIV/0! | J44: =J38/J$39 -> #DIV/0! | K44: =K38/K$39 -> 0.19335542 | L44: =L38/L$39 -> #DIV/0! | M44: =M38/M$39 -> #DIV/0! | N44: =N38/N$39 -> #DIV/0! | O44: =O38/O$39 -> 0.18979338 | ... T44: =T38/T$39 -> #DIV/0! | V44: =V38/V$39 -> 0.19335542 | W44: =W38/W$39 -> 0.19335542 | X44: =X38/X$39 -> 0.19335542 | Y44: =Y38/Y$39 -> 0.19335542 | Z44: =Z38/Z$39 -> 0.18979338 | AA44: =AA38/AA$39 -> 0.18979338 | AB44: =AB38/AB$39 -> 0.18979338 | AC44: =AC38/AC$39 -> 0.18979338 | ... AE44: =AE38/AE$39 -> 0.15719687
A46: X | B46: Revenue by product category: Direct to Consumer
A48: X | B48: Revenue by Direct-to-Consumer
B49: Advertising | C49: 1298 | D49: 1533 | E49: 1795 | F49: 2114 | K49: =SUM(D49-SUM(H49:J49)) -> 1533 | O49: =SUM(E49-SUM(L49:N49)) -> 1795 | S49: =SUM(F49-SUM(P49:R49)) -> 2114 | V49: =SUM(H49:K49) -> 1533 | W49: =SUM(I49:L49) -> 1533 | X49: =SUM(J49:M49) -> 1533 | Y49: =SUM(K49:N49) -> 1533 | Z49: =SUM(L49:O49) -> 1795 | AA49: =SUM(M49:P49) -> 1795 | AB49: =SUM(N49:Q49) -> 1795 | AC49: =SUM(O49:R49) -> 1795 | ... AE49: =SUM(Q49:T49) -> 2114
B50: Subscription & Licensing | C50: 2029 | D50: 3371 | E50: =4933+8 -> 4941 | F50: =5506+12 -> 5518 | K50: =SUM(D50-SUM(H50:J50)) -> 3371 | O50: =SUM(E50-SUM(L50:N50)) -> 4941 | S50: =SUM(F50-SUM(P50:R50)) -> 5518 | V50: =SUM(H50:K50) -> 3371 | W50: =SUM(I50:L50) -> 3371 | X50: =SUM(J50:M50) -> 3371 | Y50: =SUM(K50:N50) -> 3371 | Z50: =SUM(L50:O50) -> 4941 | AA50: =SUM(M50:P50) -> 4941 | AB50: =SUM(N50:Q50) -> 4941 | AC50: =SUM(O50:R50) -> 4941 | ... AE50: =SUM(Q50:T50) -> 5518
B51: Total Revenue from Direct-to-Consumer | C51: =SUM(C49:C50) -> 3327 | D51: =SUM(D49:D50) -> 4904 | E51: =SUM(E49:E50) -> 6736 | F51: =SUM(F49:F50) -> 7632 | H51: =SUM(H49:H50) -> 0 | I51: =SUM(I49:I50) -> 0 | J51: =SUM(J49:J50) -> 0 | K51: =SUM(K49:K50) -> 4904 | L51: =SUM(L49:L50) -> 0 | M51: =SUM(M49:M50) -> 0 | N51: =SUM(N49:N50) -> 0 | O51: =SUM(O49:O50) -> 6736 | ... T51: =SUM(T49:T50) -> 0 | V51: =SUM(V49:V50) -> 4904 | W51: =SUM(W49:W50) -> 4904 | X51: =SUM(X49:X50) -> 4904 | Y51: =SUM(Y49:Y50) -> 4904 | Z51: =SUM(Z49:Z50) -> 6736 | AA51: =SUM(AA49:AA50) -> 6736 | AB51: =SUM(AB49:AB50) -> 6736 | AC51: =SUM(AC49:AC50) -> 6736 | ... AE51: =SUM(AE49:AE50) -> 7632
B52: Variance Check | C52: =+C51-C35 -> 3327 | D52: =+D51-D35 -> 4904 | E52: =+E51-E35 -> 6736 | F52: =+F51-F35 -> 7632 | H52: =+H51-H35 -> 0 | I52: =+I51-I35 -> 0 | J52: =+J51-J35 -> 0 | K52: =+K51-K35 -> 4904 | L52: =+L51-L35 -> 0 | M52: =+M51-M35 -> 0 | N52: =+N51-N35 -> 0 | O52: =+O51-O35 -> 6736 | ... T52: =+T51-T35 -> 0 | V52: =+V51-V35 -> 4904 | W52: =+W51-W35 -> 4904 | X52: =+X51-X35 -> 4904 | Y52: =+Y51-Y35 -> 4904 | Z52: =+Z51-Z35 -> 6736 | AA52: =+AA51-AA35 -> 6736 | AB52: =+AB51-AB35 -> 6736 | AC52: =+AC51-AC35 -> 6736 | ... AE52: =+AE51-AE35 -> 7632
B54: =B49&"(%)" -> Advertising(%) | C54: =C49/C$51 -> 0.39014127 | D54: =D49/D$51 -> 0.31260196 | E54: =E49/E$51 -> 0.26647862 | F54: =F49/F$51 -> 0.27699161 | H54: =H49/H$51 -> #DIV/0! | I54: =I49/I$51 -> #DIV/0! | J54: =J49/J$51 -> #DIV/0! | K54: =K49/K$51 -> 0.31260196 | L54: =L49/L$51 -> #DIV/0! | M54: =M49/M$51 -> #DIV/0! | N54: =N49/N$51 -> #DIV/0! | O54: =O49/O$51 -> 0.26647862 | ... T54: =T49/T$51 -> #DIV/0! | V54: =V49/V$51 -> 0.31260196 | W54: =W49/W$51 -> 0.31260196 | X54: =X49/X$51 -> 0.31260196 | Y54: =Y49/Y$51 -> 0.31260196 | Z54: =Z49/Z$51 -> 0.26647862 | AA54: =AA49/AA$51 -> 0.26647862 | AB54: =AB49/AB$51 -> 0.26647862 | AC54: =AC49/AC$51 -> 0.26647862 | ... AE54: =AE49/AE$51 -> 0.27699161
B55: =B50&"(%)" -> Subscription & Licensing(%) | C55: =C50/C$51 -> 0.60985873 | D55: =D50/D$51 -> 0.68739804 | E55: =E50/E$51 -> 0.73352138 | F55: =F50/F$51 -> 0.72300839 | H55: =H50/H$51 -> #DIV/0! | I55: =I50/I$51 -> #DIV/0! | J55: =J50/J$51 -> #DIV/0! | K55: =K50/K$51 -> 0.68739804 | L55: =L50/L$51 -> #DIV/0! | M55: =M50/M$51 -> #DIV/0! | N55: =N50/N$51 -> #DIV/0! | O55: =O50/O$51 -> 0.73352138 | ... T55: =T50/T$51 -> #DIV/0! | V55: =V50/V$51 -> 0.68739804 | W55: =W50/W$51 -> 0.68739804 | X55: =X50/X$51 -> 0.68739804 | Y55: =Y50/Y$51 -> 0.68739804 | Z55: =Z50/Z$51 -> 0.73352138 | AA55: =AA50/AA$51 -> 0.73352138 | AB55: =AB50/AB$51 -> 0.73352138 | AC55: =AC50/AC$51 -> 0.73352138 | ... AE55: =AE50/AE$51 -> 0.72300839
B57: Direct-to-Consumer KPIs
B59: Paramount+ (Global) Streaming Subscribers | C59: 32.8 | D59: 55.9 | E59: 67.5 | F59: 77.5
A61: X | B61: Paramount+ (Global) Streaming Revenue
B62: Paramount+ (Global) Streaming Revenue | C62: 1347 | D62: 2767 | E62: 4446 | F62: 5896 | K62: =SUM(D62-SUM(H62:J62)) -> 2767 | O62: =SUM(E62-SUM(L62:N62)) -> 4446 | S62: =SUM(F62-SUM(P62:R62)) -> 5896 | V62: =SUM(H62:K62) -> 2767 | W62: =SUM(I62:L62) -> 2767 | X62: =SUM(J62:M62) -> 2767 | Y62: =SUM(K62:N62) -> 2767 | Z62: =SUM(L62:O62) -> 4446 | AA62: =SUM(M62:P62) -> 4446 | AB62: =SUM(N62:Q62) -> 4446 | AC62: =SUM(O62:R62) -> 4446 | ... AE62: =SUM(Q62:T62) -> 5896
B63: Total Paramount+ (Global) Streaming Revenue | C63: =SUM(C62:C62) -> 1347 | D63: =SUM(D62:D62) -> 2767 | E63: =SUM(E62:E62) -> 4446 | F63: =SUM(F62:F62) -> 5896 | H63: =SUM(H62:H62) -> 0 | I63: =SUM(I62:I62) -> 0 | J63: =SUM(J62:J62) -> 0 | K63: =SUM(K62:K62) -> 2767 | L63: =SUM(L62:L62) -> 0 | M63: =SUM(M62:M62) -> 0 | N63: =SUM(N62:N62) -> 0 | O63: =SUM(O62:O62) -> 4446 | ... T63: =SUM(T62:T62) -> 0 | V63: =SUM(V62:V62) -> 2767 | W63: =SUM(W62:W62) -> 2767 | X63: =SUM(X62:X62) -> 2767 | Y63: =SUM(Y62:Y62) -> 2767 | Z63: =SUM(Z62:Z62) -> 4446 | AA63: =SUM(AA62:AA62) -> 4446 | AB63: =SUM(AB62:AB62) -> 4446 | AC63: =SUM(AC62:AC62) -> 4446 | ... AE63: =SUM(AE62:AE62) -> 5896
A65: X | B65: Revenue by product category: Filmed Entertainment
A67: X | B67: Revenue by Filmed Entertainment
B68: Advertising | C68: 18 | D68: 23 | E68: 24 | F68: 16 | K68: =SUM(D68-SUM(H68:J68)) -> 23 | O68: =SUM(E68-SUM(L68:N68)) -> 24 | S68: =SUM(F68-SUM(P68:R68)) -> 16 | V68: =SUM(H68:K68) -> 23 | W68: =SUM(I68:L68) -> 23 | X68: =SUM(J68:M68) -> 23 | Y68: =SUM(K68:N68) -> 23 | Z68: =SUM(L68:O68) -> 24 | AA68: =SUM(M68:P68) -> 24 | AB68: =SUM(N68:Q68) -> 24 | AC68: =SUM(O68:R68) -> 24 | ... AE68: =SUM(Q68:T68) -> 16
B69: Theatrical | C69: 241 | D69: 1223 | E69: 813 | F69: 813 | K69: =SUM(D69-SUM(H69:J69)) -> 1223 | O69: =SUM(E69-SUM(L69:N69)) -> 813 | S69: =SUM(F69-SUM(P69:R69)) -> 813 | V69: =SUM(H69:K69) -> 1223 | W69: =SUM(I69:L69) -> 1223 | X69: =SUM(J69:M69) -> 1223 | Y69: =SUM(K69:N69) -> 1223 | Z69: =SUM(L69:O69) -> 813 | AA69: =SUM(M69:P69) -> 813 | AB69: =SUM(N69:Q69) -> 813 | AC69: =SUM(O69:R69) -> 813 | ... AE69: =SUM(Q69:T69) -> 813
B70: Licensing and other | C70: 2428 | D70: 2460 | E70: 2120 | F70: 2126 | K70: =SUM(D70-SUM(H70:J70)) -> 2460 | O70: =SUM(E70-SUM(L70:N70)) -> 2120 | S70: =SUM(F70-SUM(P70:R70)) -> 2126 | V70: =SUM(H70:K70) -> 2460 | W70: =SUM(I70:L70) -> 2460 | X70: =SUM(J70:M70) -> 2460 | Y70: =SUM(K70:N70) -> 2460 | Z70: =SUM(L70:O70) -> 2120 | AA70: =SUM(M70:P70) -> 2120 | AB70: =SUM(N70:Q70) -> 2120 | AC70: =SUM(O70:R70) -> 2120 | ... AE70: =SUM(Q70:T70) -> 2126
B71: Total Revenue from Filmed Entertainment | C71: =SUM(C68:C70) -> 2687 | D71: =SUM(D68:D70) -> 3706 | E71: =SUM(E68:E70) -> 2957 | F71: =SUM(F68:F70) -> 2955 | H71: =SUM(H68:H70) -> 0 | I71: =SUM(I68:I70) -> 0 | J71: =SUM(J68:J70) -> 0 | K71: =SUM(K68:K70) -> 3706 | L71: =SUM(L68:L70) -> 0 | M71: =SUM(M68:M70) -> 0 | N71: =SUM(N68:N70) -> 0 | O71: =SUM(O68:O70) -> 2957 | ... T71: =SUM(T68:T70) -> 0 | V71: =SUM(V68:V70) -> 3706 | W71: =SUM(W68:W70) -> 3706 | X71: =SUM(X68:X70) -> 3706 | Y71: =SUM(Y68:Y70) -> 3706 | Z71: =SUM(Z68:Z70) -> 2957 | AA71: =SUM(AA68:AA70) -> 2957 | AB71: =SUM(AB68:AB70) -> 2957 | AC71: =SUM(AC68:AC70) -> 2957 | ... AE71: =SUM(AE68:AE70) -> 2955
B72: Variance Check | C72: =+C71-C24 -> 0 | D72: =+D71-D24 -> 0 | E72: =+E71-E24 -> 0 | F72: =+F71-F24 -> 0 | H72: =+H71-H24 -> 0 | I72: =+I71-I24 -> 0 | J72: =+J71-J24 -> 0 | K72: =+K71-K24 -> 0 | L72: =+L71-L24 -> 0 | M72: =+M71-M24 -> 0 | N72: =+N71-N24 -> 0 | O72: =+O71-O24 -> 0 | ... T72: =+T71-T24 -> 0 | V72: =+V71-V24 -> 0 | W72: =+W71-W24 -> 0 | X72: =+X71-X24 -> 0 | Y72: =+Y71-Y24 -> 0 | Z72: =+Z71-Z24 -> 0 | AA72: =+AA71-AA24 -> 0 | AB72: =+AB71-AB24 -> 0 | AC72: =+AC71-AC24 -> 0 | ... AE72: =+AE71-AE24 -> 0
B74: =B68&"(%)" -> Advertising(%) | C74: =C68/C$39 -> 0.00079176564 | D74: =D68/D$39 -> 0.0010583471 | E74: =E68/E$39 -> 0.0011949216 | F74: =F68/F$39 -> 0.00085201555 | H74: =H68/H$39 -> #DIV/0! | I74: =I68/I$39 -> #DIV/0! | J74: =J68/J$39 -> #DIV/0! | K74: =K68/K$39 -> 0.0010583471 | L74: =L68/L$39 -> #DIV/0! | M74: =M68/M$39 -> #DIV/0! | N74: =N68/N$39 -> #DIV/0! | O74: =O68/O$39 -> 0.0011949216 | ... T74: =T68/T$39 -> #DIV/0! | V74: =V68/V$39 -> 0.0010583471 | W74: =W68/W$39 -> 0.0010583471 | X74: =X68/X$39 -> 0.0010583471 | Y74: =Y68/Y$39 -> 0.0010583471 | Z74: =Z68/Z$39 -> 0.0011949216 | AA74: =AA68/AA$39 -> 0.0011949216 | AB74: =AB68/AB$39 -> 0.0011949216 | AC74: =AC68/AC$39 -> 0.0011949216 | ... AE74: =AE68/AE$39 -> 0.00085201555
B75: =B69&"(%)" -> Theatrical(%) | C75: =C69/C$39 -> 0.010600862 | D75: =D69/D$39 -> 0.056276459 | E75: =E69/E$39 -> 0.040477969 | F75: =F69/F$39 -> 0.04329304 | H75: =H69/H$39 -> #DIV/0! | I75: =I69/I$39 -> #DIV/0! | J75: =J69/J$39 -> #DIV/0! | K75: =K69/K$39 -> 0.056276459 | L75: =L69/L$39 -> #DIV/0! | M75: =M69/M$39 -> #DIV/0! | N75: =N69/N$39 -> #DIV/0! | O75: =O69/O$39 -> 0.040477969 | ... T75: =T69/T$39 -> #DIV/0! | V75: =V69/V$39 -> 0.056276459 | W75: =W69/W$39 -> 0.056276459 | X75: =X69/X$39 -> 0.056276459 | Y75: =Y69/Y$39 -> 0.056276459 | Z75: =Z69/Z$39 -> 0.040477969 | AA75: =AA69/AA$39 -> 0.040477969 | AB75: =AB69/AB$39 -> 0.040477969 | AC75: =AC69/AC$39 -> 0.040477969 | ... AE75: =AE69/AE$39 -> 0.04329304
B76: =B70&"(%)" -> Licensing and other(%) | C76: =C70/C$39 -> 0.10680039 | D76: =D70/D$39 -> 0.11319713 | E76: =E70/E$39 -> 0.10555141 | F76: =F70/F$39 -> 0.11321157 | H76: =H70/H$39 -> #DIV/0! | I76: =I70/I$39 -> #DIV/0! | J76: =J70/J$39 -> #DIV/0! | K76: =K70/K$39 -> 0.11319713 | L76: =L70/L$39 -> #DIV/0! | M76: =M70/M$39 -> #DIV/0! | N76: =N70/N$39 -> #DIV/0! | O76: =O70/O$39 -> 0.10555141 | ... T76: =T70/T$39 -> #DIV/0! | V76: =V70/V$39 -> 0.11319713 | W76: =W70/W$39 -> 0.11319713 | X76: =X70/X$39 -> 0.11319713 | Y76: =Y70/Y$39 -> 0.11319713 | Z76: =Z70/Z$39 -> 0.10555141 | AA76: =AA70/AA$39 -> 0.10555141 | AB76: =AB70/AB$39 -> 0.10555141 | AC76: =AC70/AC$39 -> 0.10555141 | ... AE76: =AE70/AE$39 -> 0.11321157

Sheet FCF
B2: ='Historical Financials'!B2 -> Paramount Global (NASDAQ: PARA) | D2: FYE | H2: Quarterly | R2: Quarterly | Z2: LTM | AA2: LTM | AG2: Variance
B3: FCF Analysis | C3: ='Historical Financials'!C7 -> 2021 | D3: ='Historical Financials'!D7 -> 2022 | E3: ='Historical Financials'!E7 -> 2023 | F3: ='Historical Financials'!F7 -> 2024 | H3: ='Historical Financials'!H7 -> 1Q23 | I3: ='Historical Financials'!I7 -> 2Q23 | J3: ='Historical Financials'!J7 -> 3Q23 | K3: ='Historical Financials'!K7 -> 4Q23 | L3: ='Historical Financials'!L7 -> 1Q24 | M3: ='Historical Financials'!M7 -> 2Q24 | N3: ='Historical Financials'!N7 -> 3Q24 | O3: ='Historical Financials'!O7 -> 4Q24 | ... T3: ='Historical Financials'!T7 -> 1Q26 | V3: =K3 -> 4Q23 | W3: =L3 -> 1Q24 | X3: =M3 -> 2Q24 | Y3: =N3 -> 3Q24 | Z3: =O3 -> 4Q24 | AA3: =P3 -> 1Q25 | AB3: =Q3 -> 2Q25 | AC3: =R3 -> 3Q25 | ... AE3: =T3 -> 1Q26
B4: ($ In Millions) | C4: ='Historical Financials'!C8 -> 44561 | D4: ='Historical Financials'!D8 -> 44926 | E4: ='Historical Financials'!E8 -> 45291 | F4: ='Historical Financials'!F8 -> 45657 | H4: ='Historical Financials'!H8 -> XXX | I4: ='Historical Financials'!I8 -> XXX | J4: ='Historical Financials'!J8 -> XXX | K4: ='Historical Financials'!K8 -> 44926 | L4: ='Historical Financials'!L8 -> XXX | M4: ='Historical Financials'!M8 -> XXX | N4: ='Historical Financials'!N8 -> XXX | O4: ='Historical Financials'!O8 -> 45291 | ... T4: ='Historical Financials'!T8 -> XXX | V4: =K4 -> 44926 | W4: =L4 -> XXX | X4: =M4 -> XXX | Y4: =N4 -> XXX | Z4: =O4 -> 45291 | AA4: =P4 -> XXX | AB4: =Q4 -> XXX | AC4: =R4 -> XXX | ... AE4: =T4 -> XXX
B6: XXX | V6: =SUM(H6:K6) -> 0 | W6: =SUM(I6:L6) -> 0 | X6: =SUM(J6:M6) -> 0 | Y6: =SUM(K6:N6) -> 0 | Z6: =SUM(L6:O6) -> 0 | AA6: =SUM(M6:P6) -> 0 | AB6: =SUM(N6:Q6) -> 0 | AC6: =SUM(O6:R6) -> 0 | ... AE6: =SUM(Q6:T6) -> 0 | AG6: =SUM(AE6/AA6)-1 -> #DIV/0!
B7: XXX | V7: =SUM(H7:K7) -> 0 | W7: =SUM(I7:L7) -> 0 | X7: =SUM(J7:M7) -> 0 | Y7: =SUM(K7:N7) -> 0 | Z7: =SUM(L7:O7) -> 0 | AA7: =SUM(M7:P7) -> 0 | AB7: =SUM(N7:Q7) -> 0 | AC7: =SUM(O7:R7) -> 0 | ... AE7: =SUM(Q7:T7) -> 0 | AG7: =SUM(AE7/AA7)-1 -> #DIV/0!
B8: XXX | V8: =SUM(H8:K8) -> 0 | W8: =SUM(I8:L8) -> 0 | X8: =SUM(J8:M8) -> 0 | Y8: =SUM(K8:N8) -> 0 | Z8: =SUM(L8:O8) -> 0 | AA8: =SUM(M8:P8) -> 0 | AB8: =SUM(N8:Q8) -> 0 | AC8: =SUM(O8:R8) -> 0 | ... AE8: =SUM(Q8:T8) -> 0 | AG8: =SUM(AE8/AA8)-1 -> #DIV/0!
B9: XXX | V9: =SUM(H9:K9) -> 0 | W9: =SUM(I9:L9) -> 0 | X9: =SUM(J9:M9) -> 0 | Y9: =SUM(K9:N9) -> 0 | Z9: =SUM(L9:O9) -> 0 | AA9: =SUM(M9:P9) -> 0 | AB9: =SUM(N9:Q9) -> 0 | AC9: =SUM(O9:R9) -> 0 | ... AE9: =SUM(Q9:T9) -> 0 | AG9: =SUM(AE9/AA9)-1 -> #DIV/0!
B10: XXX | V10: =SUM(H10:K10) -> 0 | W10: =SUM(I10:L10) -> 0 | X10: =SUM(J10:M10) -> 0 | Y10: =SUM(K10:N10) -> 0 | Z10: =SUM(L10:O10) -> 0 | AA10: =SUM(M10:P10) -> 0 | AB10: =SUM(N10:Q10) -> 0 | AC10: =SUM(O10:R10) -> 0 | ... AE10: =SUM(Q10:T10) -> 0 | AG10: =SUM(AE10/AA10)-1 -> #DIV/0!
B11: XXX | V11: =SUM(H11:K11) -> 0 | W11: =SUM(I11:L11) -> 0 | X11: =SUM(J11:M11) -> 0 | Y11: =SUM(K11:N11) -> 0 | Z11: =SUM(L11:O11) -> 0 | AA11: =SUM(M11:P11) -> 0 | AB11: =SUM(N11:Q11) -> 0 | AC11: =SUM(O11:R11) -> 0 | ... AE11: =SUM(Q11:T11) -> 0 | AG11: =SUM(AE11/AA11)-1 -> #DIV/0!
B12: Total Revenue | C12: =SUM(C6:C11) -> 0 | D12: =SUM(D6:D11) -> 0 | E12: =SUM(E6:E11) -> 0 | F12: =SUM(F6:F11) -> 0 | H12: =SUM(H6:H11) -> 0 | I12: =SUM(I6:I11) -> 0 | J12: =SUM(J6:J11) -> 0 | K12: =SUM(K6:K11) -> 0 | L12: =SUM(L6:L11) -> 0 | M12: =SUM(M6:M11) -> 0 | N12: =SUM(N6:N11) -> 0 | O12: =SUM(O6:O11) -> 0 | ... T12: =SUM(T6:T11) -> 0 | V12: =SUM(V6:V11) -> 0 | W12: =SUM(W6:W11) -> 0 | X12: =SUM(X6:X11) -> 0 | Y12: =SUM(Y6:Y11) -> 0 | Z12: =SUM(Z6:Z11) -> 0 | AA12: =SUM(AA6:AA11) -> 0 | AB12: =SUM(AB6:AB11) -> 0 | AC12: =SUM(AC6:AC11) -> 0 | ... AE12: =SUM(AE6:AE11) -> 0 | AG12: =SUM(AE12/AA12)-1 -> #DIV/0!
B13: Y/Y Growth (%) | C13: =SUM(C12/#REF!)-1 -> #REF! | D13: =SUM(D12/C12)-1 -> #DIV/0! | E13: =SUM(E12/D12)-1 -> #DIV/0! | F13: =SUM(F12/E12)-1 -> #DIV/0! | L13: =SUM(L12/H12)-1 -> #DIV/0! | M13: =SUM(M12/I12)-1 -> #DIV/0! | N13: =SUM(N12/J12)-1 -> #DIV/0! | O13: =SUM(O12/K12)-1 -> #DIV/0! | P13: =SUM(P12/L12)-1 -> #DIV/0! | Q13: =SUM(Q12/M12)-1 -> #DIV/0! | R13: =SUM(R12/N12)-1 -> #DIV/0! | S13: =SUM(S12/O12)-1 -> #DIV/0! | T13: =SUM(T12/P12)-1 -> #DIV/0! | Z13: =SUM(Z12/V12)-1 -> #DIV/0! | AA13: =SUM(AA12/W12)-1 -> #DIV/0! | AB13: =SUM(AB12/X12)-1 -> #DIV/0! | AC13: =SUM(AC12/Y12)-1 -> #DIV/0! | AD13: =SUM(AD12/Z12)-1 -> #DIV/0! | AE13: =SUM(AE12/AA12)-1 -> #DIV/0! | AG13: =SUM(AE13-AA13)*10000 -> #DIV/0!
B14: Q/Q Growth (%) | C14: N/A | D14: N/A | E14: N/A | F14: N/A | I14: =SUM(I12/H12)-1 -> #DIV/0! | J14: =SUM(J12/I12)-1 -> #DIV/0! | K14: =SUM(K12/J12)-1 -> #DIV/0! | L14: =SUM(L12/K12)-1 -> #DIV/0! | M14: =SUM(M12/L12)-1 -> #DIV/0! | N14: =SUM(N12/M12)-1 -> #DIV/0! | O14: =SUM(O12/N12)-1 -> #DIV/0! | P14: =SUM(P12/O12)-1 -> #DIV/0! | ... T14: =SUM(T12/S12)-1 -> #DIV/0! | V14: N/A | W14: N/A | X14: N/A | Y14: N/A | Z14: N/A | AA14: N/A | AB14: N/A | AC14: N/A | AD14: N/A | AE14: N/A
B16: (-) Cost of Sales | V16: =SUM(H16:K16) -> 0 | W16: =SUM(I16:L16) -> 0 | X16: =SUM(J16:M16) -> 0 | Y16: =SUM(K16:N16) -> 0 | Z16: =SUM(L16:O16) -> 0 | AA16: =SUM(M16:P16) -> 0 | AB16: =SUM(N16:Q16) -> 0 | AC16: =SUM(O16:R16) -> 0 | ... AE16: =SUM(Q16:T16) -> 0 | AG16: =SUM(AE16/AA16)-1 -> #DIV/0!
B17: Gross Profit | C17: =SUM(C12+SUM(C16:C16)) -> 0 | D17: =SUM(D12+SUM(D16:D16)) -> 0 | E17: =SUM(E12+SUM(E16:E16)) -> 0 | F17: =SUM(F12+SUM(F16:F16)) -> 0 | H17: =SUM(H12+SUM(H16:H16)) -> 0 | I17: =SUM(I12+SUM(I16:I16)) -> 0 | J17: =SUM(J12+SUM(J16:J16)) -> 0 | K17: =SUM(K12+SUM(K16:K16)) -> 0 | L17: =SUM(L12+SUM(L16:L16)) -> 0 | M17: =SUM(M12+SUM(M16:M16)) -> 0 | N17: =SUM(N12+SUM(N16:N16)) -> 0 | O17: =SUM(O12+SUM(O16:O16)) -> 0 | ... T17: =SUM(T12+SUM(T16:T16)) -> 0 | V17: =SUM(V12+SUM(V16:V16)) -> 0 | W17: =SUM(W12+SUM(W16:W16)) -> 0 | X17: =SUM(X12+SUM(X16:X16)) -> 0 | Y17: =SUM(Y12+SUM(Y16:Y16)) -> 0 | Z17: =SUM(Z12+SUM(Z16:Z16)) -> 0 | AA17: =SUM(AA12+SUM(AA16:AA16)) -> 0 | AB17: =SUM(AB12+SUM(AB16:AB16)) -> 0 | AC17: =SUM(AC12+SUM(AC16:AC16)) -> 0 | ... AE17: =SUM(AE12+SUM(AE16:AE16)) -> 0 | AG17: =SUM(AE17/AA17)-1 -> #DIV/0!
B18: Gross Margin (%) | C18: =C17/C12 -> #DIV/0! | D18: =D17/D12 -> #DIV/0! | E18: =E17/E12 -> #DIV/0! | F18: =F17/F12 -> #DIV/0! | H18: =H17/H12 -> #DIV/0! | I18: =I17/I12 -> #DIV/0! | J18: =J17/J12 -> #DIV/0! | K18: =K17/K12 -> #DIV/0! | L18: =L17/L12 -> #DIV/0! | M18: =M17/M12 -> #DIV/0! | N18: =N17/N12 -> #DIV/0! | O18: =O17/O12 -> #DIV/0! | ... T18: =T17/T12 -> #DIV/0! | V18: =V17/V12 -> #DIV/0! | W18: =W17/W12 -> #DIV/0! | X18: =X17/X12 -> #DIV/0! | Y18: =Y17/Y12 -> #DIV/0! | Z18: =Z17/Z12 -> #DIV/0! | AA18: =AA17/AA12 -> #DIV/0! | AB18: =AB17/AB12 -> #DIV/0! | AC18: =AC17/AC12 -> #DIV/0! | ... AE18: =AE17/AE12 -> #DIV/0! | AG18: =SUM(AE18-AA18)*10000 -> #DIV/0!
B20: (-) XXX | V20: =SUM(H20:K20) -> 0 | W20: =SUM(I20:L20) -> 0 | X20: =SUM(J20:M20) -> 0 | Y20: =SUM(K20:N20) -> 0 | Z20: =SUM(L20:O20) -> 0 | AA20: =SUM(M20:P20) -> 0 | AB20: =SUM(N20:Q20) -> 0 | AC20: =SUM(O20:R20) -> 0 | ... AE20: =SUM(Q20:T20) -> 0 | AG20: =SUM(AE20/AA20)-1 -> #DIV/0!
B21: (-) XXX | V21: =SUM(H21:K21) -> 0 | W21: =SUM(I21:L21) -> 0 | X21: =SUM(J21:M21) -> 0 | Y21: =SUM(K21:N21) -> 0 | Z21: =SUM(L21:O21) -> 0 | AA21: =SUM(M21:P21) -> 0 | AB21: =SUM(N21:Q21) -> 0 | AC21: =SUM(O21:R21) -> 0 | ... AE21: =SUM(Q21:T21) -> 0 | AG21: =SUM(AE21/AA21)-1 -> #DIV/0!
B22: (-) XXX | V22: =SUM(H22:K22) -> 0 | W22: =SUM(I22:L22) -> 0 | X22: =SUM(J22:M22) -> 0 | Y22: =SUM(K22:N22) -> 0 | Z22: =SUM(L22:O22) -> 0 | AA22: =SUM(M22:P22) -> 0 | AB22: =SUM(N22:Q22) -> 0 | AC22: =SUM(O22:R22) -> 0 | ... AE22: =SUM(Q22:T22) -> 0 | AG22: =SUM(AE22/AA22)-1 -> #DIV/0!
B23: (-) XXX | V23: =SUM(H23:K23) -> 0 | W23: =SUM(I23:L23) -> 0 | X23: =SUM(J23:M23) -> 0 | Y23: =SUM(K23:N23) -> 0 | Z23: =SUM(L23:O23) -> 0 | AA23: =SUM(M23:P23) -> 0 | AB23: =SUM(N23:Q23) -> 0 | AC23: =SUM(O23:R23) -> 0 | ... AE23: =SUM(Q23:T23) -> 0 | AG23: =SUM(AE23/AA23)-1 -> #DIV/0!
B24: (-) XXX | V24: =SUM(H24:K24) -> 0 | W24: =SUM(I24:L24) -> 0 | X24: =SUM(J24:M24) -> 0 | Y24: =SUM(K24:N24) -> 0 | Z24: =SUM(L24:O24) -> 0 | AA24: =SUM(M24:P24) -> 0 | AB24: =SUM(N24:Q24) -> 0 | AC24: =SUM(O24:R24) -> 0 | ... AE24: =SUM(Q24:T24) -> 0 | AG24: =SUM(AE24/AA24)-1 -> #DIV/0!
B25: Earning before Interest & Taxes (EBIT) | C25: =SUM(C17+SUM(C20:C24)) -> 0 | D25: =SUM(D17+SUM(D20:D24)) -> 0 | E25: =SUM(E17+SUM(E20:E24)) -> 0 | F25: =SUM(F17+SUM(F20:F24)) -> 0 | H25: =SUM(H17+SUM(H20:H24)) -> 0 | I25: =SUM(I17+SUM(I20:I24)) -> 0 | J25: =SUM(J17+SUM(J20:J24)) -> 0 | K25: =SUM(K17+SUM(K20:K24)) -> 0 | L25: =SUM(L17+SUM(L20:L24)) -> 0 | M25: =SUM(M17+SUM(M20:M24)) -> 0 | N25: =SUM(N17+SUM(N20:N24)) -> 0 | O25: =SUM(O17+SUM(O20:O24)) -> 0 | ... T25: =SUM(T17+SUM(T20:T24)) -> 0 | V25: =SUM(V17+SUM(V20:V24)) -> 0 | W25: =SUM(W17+SUM(W20:W24)) -> 0 | X25: =SUM(X17+SUM(X20:X24)) -> 0 | Y25: =SUM(Y17+SUM(Y20:Y24)) -> 0 | Z25: =SUM(Z17+SUM(Z20:Z24)) -> 0 | AA25: =SUM(AA17+SUM(AA20:AA24)) -> 0 | AB25: =SUM(AB17+SUM(AB20:AB24)) -> 0 | AC25: =SUM(AC17+SUM(AC20:AC24)) -> 0 | ... AE25: =SUM(AE17+SUM(AE20:AE24)) -> 0 | AG25: =SUM(AE25/AA25)-1 -> #DIV/0!
B26: Operating Margin (%) | C26: =C25/C12 -> #DIV/0! | D26: =D25/D12 -> #DIV/0! | E26: =E25/E12 -> #DIV/0! | F26: =F25/F12 -> #DIV/0! | H26: =H25/H12 -> #DIV/0! | I26: =I25/I12 -> #DIV/0! | J26: =J25/J12 -> #DIV/0! | K26: =K25/K12 -> #DIV/0! | L26: =L25/L12 -> #DIV/0! | M26: =M25/M12 -> #DIV/0! | N26: =N25/N12 -> #DIV/0! | O26: =O25/O12 -> #DIV/0! | ... T26: =T25/T12 -> #DIV/0! | V26: =V25/V12 -> #DIV/0! | W26: =W25/W12 -> #DIV/0! | X26: =X25/X12 -> #DIV/0! | Y26: =Y25/Y12 -> #DIV/0! | Z26: =Z25/Z12 -> #DIV/0! | AA26: =AA25/AA12 -> #DIV/0! | AB26: =AB25/AB12 -> #DIV/0! | AC26: =AC25/AC12 -> #DIV/0! | ... AE26: =AE25/AE12 -> #DIV/0! | AG26: =SUM(AE26-AA26)*10000 -> #DIV/0!
B28: (+) Depreciation and Amortization (D&A) | V28: =SUM(H28:K28) -> 0 | W28: =SUM(I28:L28) -> 0 | X28: =SUM(J28:M28) -> 0 | Y28: =SUM(K28:N28) -> 0 | Z28: =SUM(L28:O28) -> 0 | AA28: =SUM(M28:P28) -> 0 | AB28: =SUM(N28:Q28) -> 0 | AC28: =SUM(O28:R28) -> 0 | ... AE28: =SUM(Q28:T28) -> 0 | AG28: =SUM(AE28/AA28)-1 -> #DIV/0!
B29: EBITDA | C29: =SUM(C25+SUM(C28:C28)) -> 0 | D29: =SUM(D25+SUM(D28:D28)) -> 0 | E29: =SUM(E25+SUM(E28:E28)) -> 0 | F29: =SUM(F25+SUM(F28:F28)) -> 0 | H29: =SUM(H25+SUM(H28:H28)) -> 0 | I29: =SUM(I25+SUM(I28:I28)) -> 0 | J29: =SUM(J25+SUM(J28:J28)) -> 0 | K29: =SUM(K25+SUM(K28:K28)) -> 0 | L29: =SUM(L25+SUM(L28:L28)) -> 0 | M29: =SUM(M25+SUM(M28:M28)) -> 0 | N29: =SUM(N25+SUM(N28:N28)) -> 0 | O29: =SUM(O25+SUM(O28:O28)) -> 0 | ... T29: =SUM(T25+SUM(T28:T28)) -> 0 | V29: =SUM(V25+SUM(V28:V28)) -> 0 | W29: =SUM(W25+SUM(W28:W28)) -> 0 | X29: =SUM(X25+SUM(X28:X28)) -> 0 | Y29: =SUM(Y25+SUM(Y28:Y28)) -> 0 | Z29: =SUM(Z25+SUM(Z28:Z28)) -> 0 | AA29: =SUM(AA25+SUM(AA28:AA28)) -> 0 | AB29: =SUM(AB25+SUM(AB28:AB28)) -> 0 | AC29: =SUM(AC25+SUM(AC28:AC28)) -> 0 | ... AE29: =SUM(AE25+SUM(AE28:AE28)) -> 0 | AG29: =SUM(AE29/AA29)-1 -> #DIV/0!
B30: EBITDA Margin (%) | C30: =C29/C12 -> #DIV/0! | D30: =D29/D12 -> #DIV/0! | E30: =E29/E12 -> #DIV/0! | F30: =F29/F12 -> #DIV/0! | H30: =H29/H12 -> #DIV/0! | I30: =I29/I12 -> #DIV/0! | J30: =J29/J12 -> #DIV/0! | K30: =K29/K12 -> #DIV/0! | L30: =L29/L12 -> #DIV/0! | M30: =M29/M12 -> #DIV/0! | N30: =N29/N12 -> #DIV/0! | O30: =O29/O12 -> #DIV/0! | ... T30: =T29/T12 -> #DIV/0! | V30: =V29/V12 -> #DIV/0! | W30: =W29/W12 -> #DIV/0! | X30: =X29/X12 -> #DIV/0! | Y30: =Y29/Y12 -> #DIV/0! | Z30: =Z29/Z12 -> #DIV/0! | AA30: =AA29/AA12 -> #DIV/0! | AB30: =AB29/AB12 -> #DIV/0! | AC30: =AC29/AC12 -> #DIV/0! | ... AE30: =AE29/AE12 -> #DIV/0! | AG30: =SUM(AE30-AA30)*10000 -> #DIV/0!
B32: (+) Stock-Based Compensation (SBC) | V32: =SUM(H32:K32) -> 0 | W32: =SUM(I32:L32) -> 0 | X32: =SUM(J32:M32) -> 0 | Y32: =SUM(K32:N32) -> 0 | Z32: =SUM(L32:O32) -> 0 | AA32: =SUM(M32:P32) -> 0 | AB32: =SUM(N32:Q32) -> 0 | AC32: =SUM(O32:R32) -> 0 | ... AE32: =SUM(Q32:T32) -> 0 | AG32: =SUM(AE32/AA32)-1 -> #DIV/0!
B33: (+) XXX | V33: =SUM(H33:K33) -> 0 | W33: =SUM(I33:L33) -> 0 | X33: =SUM(J33:M33) -> 0 | Y33: =SUM(K33:N33) -> 0 | Z33: =SUM(L33:O33) -> 0 | AA33: =SUM(M33:P33) -> 0 | AB33: =SUM(N33:Q33) -> 0 | AC33: =SUM(O33:R33) -> 0 | ... AE33: =SUM(Q33:T33) -> 0 | AG33: =SUM(AE33/AA33)-1 -> #DIV/0!
B34: Adj. EBITDA | C34: =+SUM(C29+SUM(C32:C32)) -> 0 | D34: =+SUM(D29+SUM(D32:D32)) -> 0 | E34: =+SUM(E29+SUM(E32:E32)) -> 0 | F34: =+SUM(F29+SUM(F32:F32)) -> 0 | H34: =+SUM(H29+SUM(H32:H32)) -> 0 | I34: =+SUM(I29+SUM(I32:I32)) -> 0 | J34: =+SUM(J29+SUM(J32:J32)) -> 0 | K34: =+SUM(K29+SUM(K32:K32)) -> 0 | L34: =+SUM(L29+SUM(L32:L32)) -> 0 | M34: =+SUM(M29+SUM(M32:M32)) -> 0 | N34: =+SUM(N29+SUM(N32:N32)) -> 0 | O34: =+SUM(O29+SUM(O32:O32)) -> 0 | ... T34: =+SUM(T29+SUM(T32:T32)) -> 0 | V34: =+SUM(V29+SUM(V32:V32)) -> 0 | W34: =+SUM(W29+SUM(W32:W32)) -> 0 | X34: =+SUM(X29+SUM(X32:X32)) -> 0 | Y34: =+SUM(Y29+SUM(Y32:Y32)) -> 0 | Z34: =+SUM(Z29+SUM(Z32:Z32)) -> 0 | AA34: =+SUM(AA29+SUM(AA32:AA32)) -> 0 | AB34: =+SUM(AB29+SUM(AB32:AB32)) -> 0 | AC34: =+SUM(AC29+SUM(AC32:AC32)) -> 0 | ... AE34: =+SUM(AE29+SUM(AE32:AE32)) -> 0 | AG34: =SUM(AE34/AA34)-1 -> #DIV/0!
B35: Adj. EBITDA Margin (%) | C35: =C34/C12 -> #DIV/0! | D35: =D34/D12 -> #DIV/0! | E35: =E34/E12 -> #DIV/0! | F35: =F34/F12 -> #DIV/0! | H35: =H34/H12 -> #DIV/0! | I35: =I34/I12 -> #DIV/0! | J35: =J34/J12 -> #DIV/0! | K35: =K34/K12 -> #DIV/0! | L35: =L34/L12 -> #DIV/0! | M35: =M34/M12 -> #DIV/0! | N35: =N34/N12 -> #DIV/0! | O35: =O34/O12 -> #DIV/0! | ... T35: =T34/T12 -> #DIV/0! | V35: =V34/V12 -> #DIV/0! | W35: =W34/W12 -> #DIV/0! | X35: =X34/X12 -> #DIV/0! | Y35: =Y34/Y12 -> #DIV/0! | Z35: =Z34/Z12 -> #DIV/0! | AA35: =AA34/AA12 -> #DIV/0! | AB35: =AB34/AB12 -> #DIV/0! | AC35: =AC34/AC12 -> #DIV/0! | ... AE35: =AE34/AE12 -> #DIV/0! | AG35: =SUM(AE35-AA35)*10000 -> #DIV/0!
B37: (-) Capital Expenditures | V37: =SUM(H37:K37) -> 0 | W37: =SUM(I37:L37) -> 0 | X37: =SUM(J37:M37) -> 0 | Y37: =SUM(K37:N37) -> 0 | Z37: =SUM(L37:O37) -> 0 | AA37: =SUM(M37:P37) -> 0 | AB37: =SUM(N37:Q37) -> 0 | AC37: =SUM(O37:R37) -> 0 | ... AE37: =SUM(Q37:T37) -> 0 | AG37: =SUM(AE37/AA37)-1 -> #DIV/0!
B38: (-) Cash Taxes | V38: =SUM(H38:K38) -> 0 | W38: =SUM(I38:L38) -> 0 | X38: =SUM(J38:M38) -> 0 | Y38: =SUM(K38:N38) -> 0 | Z38: =SUM(L38:O38) -> 0 | AA38: =SUM(M38:P38) -> 0 | AB38: =SUM(N38:Q38) -> 0 | AC38: =SUM(O38:R38) -> 0 | ... AE38: =SUM(Q38:T38) -> 0 | AG38: =SUM(AE38/AA38)-1 -> #DIV/0!
B39: (-) Cash Interest | V39: =SUM(H39:K39) -> 0 | W39: =SUM(I39:L39) -> 0 | X39: =SUM(J39:M39) -> 0 | Y39: =SUM(K39:N39) -> 0 | Z39: =SUM(L39:O39) -> 0 | AA39: =SUM(M39:P39) -> 0 | AB39: =SUM(N39:Q39) -> 0 | AC39: =SUM(O39:R39) -> 0 | ... AE39: =SUM(Q39:T39) -> 0 | AG39: =SUM(AE39/AA39)-1 -> #DIV/0!
B40: (-) Mandatory Outflows | V40: =SUM(H40:K40) -> 0 | W40: =SUM(I40:L40) -> 0 | X40: =SUM(J40:M40) -> 0 | Y40: =SUM(K40:N40) -> 0 | Z40: =SUM(L40:O40) -> 0 | AA40: =SUM(M40:P40) -> 0 | AB40: =SUM(N40:Q40) -> 0 | AC40: =SUM(O40:R40) -> 0 | ... AE40: =SUM(Q40:T40) -> 0 | AG40: =SUM(AE40/AA40)-1 -> #DIV/0!
B41: (+/-) Changes in NWC | V41: =SUM(H41:K41) -> 0 | W41: =SUM(I41:L41) -> 0 | X41: =SUM(J41:M41) -> 0 | Y41: =SUM(K41:N41) -> 0 | Z41: =SUM(L41:O41) -> 0 | AA41: =SUM(M41:P41) -> 0 | AB41: =SUM(N41:Q41) -> 0 | AC41: =SUM(O41:R41) -> 0 | ... AE41: =SUM(Q41:T41) -> 0 | AG41: =SUM(AE41/AA41)-1 -> #DIV/0!
B42: Discretionary Cash-Flows | C42: =SUM(C34+SUM(C37:C41)) -> 0 | D42: =SUM(D34+SUM(D37:D41)) -> 0 | E42: =SUM(E34+SUM(E37:E41)) -> 0 | F42: =SUM(F34+SUM(F37:F41)) -> 0 | H42: =SUM(H34+SUM(H37:H41)) -> 0 | I42: =SUM(I34+SUM(I37:I41)) -> 0 | J42: =SUM(J34+SUM(J37:J41)) -> 0 | K42: =SUM(K34+SUM(K37:K41)) -> 0 | L42: =SUM(L34+SUM(L37:L41)) -> 0 | M42: =SUM(M34+SUM(M37:M41)) -> 0 | N42: =SUM(N34+SUM(N37:N41)) -> 0 | O42: =SUM(O34+SUM(O37:O41)) -> 0 | ... T42: =SUM(T34+SUM(T37:T41)) -> 0 | V42: =SUM(V34+SUM(V37:V41)) -> 0 | W42: =SUM(W34+SUM(W37:W41)) -> 0 | X42: =SUM(X34+SUM(X37:X41)) -> 0 | Y42: =SUM(Y34+SUM(Y37:Y41)) -> 0 | Z42: =SUM(Z34+SUM(Z37:Z41)) -> 0 | AA42: =SUM(AA34+SUM(AA37:AA41)) -> 0 | AB42: =SUM(AB34+SUM(AB37:AB41)) -> 0 | AC42: =SUM(AC34+SUM(AC37:AC41)) -> 0 | ... AE42: =SUM(AE34+SUM(AE37:AE41)) -> 0 | AG42: =SUM(AE42/AA42)-1 -> #DIV/0!
B44: (+/-) XXX | V44: =SUM(H44:K44) -> 0 | W44: =SUM(I44:L44) -> 0 | X44: =SUM(J44:M44) -> 0 | Y44: =SUM(K44:N44) -> 0 | Z44: =SUM(L44:O44) -> 0 | AA44: =SUM(M44:P44) -> 0 | AB44: =SUM(N44:Q44) -> 0 | AC44: =SUM(O44:R44) -> 0 | ... AE44: =SUM(Q44:T44) -> 0
B45: (+/-) XXX | V45: =SUM(H45:K45) -> 0 | W45: =SUM(I45:L45) -> 0 | X45: =SUM(J45:M45) -> 0 | Y45: =SUM(K45:N45) -> 0 | Z45: =SUM(L45:O45) -> 0 | AA45: =SUM(M45:P45) -> 0 | AB45: =SUM(N45:Q45) -> 0 | AC45: =SUM(O45:R45) -> 0 | ... AE45: =SUM(Q45:T45) -> 0
B46: (+/-) XXX | V46: =SUM(H46:K46) -> 0 | W46: =SUM(I46:L46) -> 0 | X46: =SUM(J46:M46) -> 0 | Y46: =SUM(K46:N46) -> 0 | Z46: =SUM(L46:O46) -> 0 | AA46: =SUM(M46:P46) -> 0 | AB46: =SUM(N46:Q46) -> 0 | AC46: =SUM(O46:R46) -> 0 | ... AE46: =SUM(Q46:T46) -> 0
B47: (+/-) XXX | V47: =SUM(H47:K47) -> 0 | W47: =SUM(I47:L47) -> 0 | X47: =SUM(J47:M47) -> 0 | Y47: =SUM(K47:N47) -> 0 | Z47: =SUM(L47:O47) -> 0 | AA47: =SUM(M47:P47) -> 0 | AB47: =SUM(N47:Q47) -> 0 | AC47: =SUM(O47:R47) -> 0 | ... AE47: =SUM(Q47:T47) -> 0
B48: (+/-) XXX | V48: =SUM(H48:K48) -> 0 | W48: =SUM(I48:L48) -> 0 | X48: =SUM(J48:M48) -> 0 | Y48: =SUM(K48:N48) -> 0 | Z48: =SUM(L48:O48) -> 0 | AA48: =SUM(M48:P48) -> 0 | AB48: =SUM(N48:Q48) -> 0 | AC48: =SUM(O48:R48) -> 0 | ... AE48: =SUM(Q48:T48) -> 0
B49: (+/-) Other | D49: =SUM(D54)-SUM(C54)-SUM(D42:D48) -> 0 | E49: =SUM(E54)-SUM(D54)-SUM(E42:E48) -> 0 | F49: =SUM(F54)-SUM(E54)-SUM(F42:F48) -> 0 | H49: =SUM(H54)-SUM(C54)-SUM(H42:H48) -> 0 | I49: =SUM(I54)-SUM(H54)-SUM(I42:I48) -> 0 | J49: =SUM(J54)-SUM(I54)-SUM(J42:J48) -> 0 | K49: =SUM(K54)-SUM(J54)-SUM(K42:K48) -> 2885 | L49: =SUM(L54)-SUM(K54)-SUM(L42:L48) -> -2885 | M49: =SUM(M54)-SUM(L54)-SUM(M42:M48) -> 0 | N49: =SUM(N54)-SUM(M54)-SUM(N42:N48) -> 0 | O49: =SUM(O54)-SUM(N54)-SUM(O42:O48) -> 2460 | P49: =SUM(P54)-SUM(O54)-SUM(P42:P48) -> -2460 | ... T49: =SUM(T54)-SUM(S54)-SUM(T42:T48) -> -2661 | V49: =SUM(H49:K49) -> 2885 | W49: =SUM(I49:L49) -> 0 | X49: =SUM(J49:M49) -> 0 | Y49: =SUM(K49:N49) -> 0 | Z49: =SUM(L49:O49) -> -425 | AA49: =SUM(M49:P49) -> 0 | AB49: =SUM(N49:Q49) -> 0 | AC49: =SUM(O49:R49) -> 0 | ... AE49: =SUM(Q49:T49) -> 0
B50: Free-Cash Flows | C50: =SUM(C42+SUM(C44:C49)) -> 0 | D50: =SUM(D42+SUM(D44:D49)) -> 0 | E50: =SUM(E42+SUM(E44:E49)) -> 0 | F50: =SUM(F42+SUM(F44:F49)) -> 0 | H50: =SUM(H42+SUM(H44:H49)) -> 0 | I50: =SUM(I42+SUM(I44:I49)) -> 0 | J50: =SUM(J42+SUM(J44:J49)) -> 0 | K50: =SUM(K42+SUM(K44:K49)) -> 2885 | L50: =SUM(L42+SUM(L44:L49)) -> -2885 | M50: =SUM(M42+SUM(M44:M49)) -> 0 | N50: =SUM(N42+SUM(N44:N49)) -> 0 | O50: =SUM(O42+SUM(O44:O49)) -> 2460 | ... T50: =SUM(T42+SUM(T44:T49)) -> -2661 | V50: =SUM(V42+SUM(V44:V49)) -> 2885 | W50: =SUM(W42+SUM(W44:W49)) -> 0 | X50: =SUM(X42+SUM(X44:X49)) -> 0 | Y50: =SUM(Y42+SUM(Y44:Y49)) -> 0 | Z50: =SUM(Z42+SUM(Z44:Z49)) -> -425 | AA50: =SUM(AA42+SUM(AA44:AA49)) -> 0 | AB50: =SUM(AB42+SUM(AB44:AB49)) -> 0 | AC50: =SUM(AC42+SUM(AC44:AC49)) -> 0 | ... AE50: =SUM(AE42+SUM(AE44:AE49)) -> 0
B52: Capitalization
B54: Cash & Cash Equivelants | K54: ='Historical Financials'!K53 -> 2885 | O54: ='Historical Financials'!O53 -> 2460 | S54: ='Historical Financials'!S53 -> 2661 | V54: =K54 -> 2885 | W54: =L54 -> 0 | X54: =M54 -> 0 | Y54: =N54 -> 0 | Z54: =O54 -> 2460 | AA54: =P54 -> 0 | AB54: =Q54 -> 0 | AC54: =R54 -> 0 | ... AE54: =T54 -> 0
B55: XXX | K55: ='Historical Financials'!K54 -> 7412 | O55: ='Historical Financials'!O54 -> 7115 | S55: ='Historical Financials'!S54 -> 6920 | V55: =K55 -> 7412 | W55: =L55 -> 0 | X55: =M55 -> 0 | Y55: =N55 -> 0 | Z55: =O55 -> 7115 | AA55: =P55 -> 0 | AB55: =Q55 -> 0 | AC55: =R55 -> 0 | ... AE55: =T55 -> 0
B56: XXX | K56: =D56 -> 0 | O56: =E56 -> 0 | S56: =F56 -> 0 | V56: =K56 -> 0 | W56: =L56 -> 0 | X56: =M56 -> 0 | Y56: =N56 -> 0 | Z56: =O56 -> 0 | AA56: =P56 -> 0 | AB56: =Q56 -> 0 | AC56: =R56 -> 0 | ... AE56: =T56 -> 0
B57: Total Liquidity | C57: =SUM(C54:C56) -> 0 | D57: =SUM(D54:D56) -> 0 | E57: =SUM(E54:E56) -> 0 | F57: =SUM(F54:F56) -> 0 | H57: =SUM(H54:H56) -> 0 | I57: =SUM(I54:I56) -> 0 | J57: =SUM(J54:J56) -> 0 | K57: =SUM(K54:K56) -> 10297 | L57: =SUM(L54:L56) -> 0 | M57: =SUM(M54:M56) -> 0 | N57: =SUM(N54:N56) -> 0 | O57: =SUM(O54:O56) -> 9575 | ... T57: =SUM(T54:T56) -> 0 | V57: =SUM(V54:V56) -> 10297 | W57: =SUM(W54:W56) -> 0 | X57: =SUM(X54:X56) -> 0 | Y57: =SUM(Y54:Y56) -> 0 | Z57: =SUM(Z54:Z56) -> 9575 | AA57: =SUM(AA54:AA56) -> 0 | AB57: =SUM(AB54:AB56) -> 0 | AC57: =SUM(AC54:AC56) -> 0 | ... AE57: =SUM(AE54:AE56) -> 0
B59: Balance Sheet Metrics:
B60: XXX | V60: =K60 -> 0 | W60: =L60 -> 0 | X60: =M60 -> 0 | Y60: =N60 -> 0 | Z60: =O60 -> 0 | AA60: =P60 -> 0 | AB60: =Q60 -> 0 | AC60: =R60 -> 0 | ... AE60: =T60 -> 0
B61: XXX | V61: =K61 -> 0 | W61: =L61 -> 0 | X61: =M61 -> 0 | Y61: =N61 -> 0 | Z61: =O61 -> 0 | AA61: =P61 -> 0 | AB61: =Q61 -> 0 | AC61: =R61 -> 0 | ... AE61: =T61 -> 0
B62: XXX | V62: =K62 -> 0 | W62: =L62 -> 0 | X62: =M62 -> 0 | Y62: =N62 -> 0 | Z62: =O62 -> 0 | AA62: =P62 -> 0 | AB62: =Q62 -> 0 | AC62: =R62 -> 0 | ... AE62: =T62 -> 0
B63: XXX | V63: =K63 -> 0 | W63: =L63 -> 0 | X63: =M63 -> 0 | Y63: =N63 -> 0 | Z63: =O63 -> 0 | AA63: =P63 -> 0 | AB63: =Q63 -> 0 | AC63: =R63 -> 0 | ... AE63: =T63 -> 0
B64: XXX | V64: =K64 -> 0 | W64: =L64 -> 0 | X64: =M64 -> 0 | Y64: =N64 -> 0 | Z64: =O64 -> 0 | AA64: =P64 -> 0 | AB64: =Q64 -> 0 | AC64: =R64 -> 0 | ... AE64: =T64 -> 0
B65: XXX | V65: =K65 -> 0 | W65: =L65 -> 0 | X65: =M65 -> 0 | Y65: =N65 -> 0 | Z65: =O65 -> 0 | AA65: =P65 -> 0 | AB65: =Q65 -> 0 | AC65: =R65 -> 0 | ... AE65: =T65 -> 0
B66: XXX | V66: =K66 -> 0 | W66: =L66 -> 0 | X66: =M66 -> 0 | Y66: =N66 -> 0 | Z66: =O66 -> 0 | AA66: =P66 -> 0 | AB66: =Q66 -> 0 | AC66: =R66 -> 0 | ... AE66: =T66 -> 0
B68: Summary Debt:
B69: CPLTD | V69: =K69 -> 0 | W69: =L69 -> 0 | X69: =M69 -> 0 | Y69: =N69 -> 0 | Z69: =O69 -> 0 | AA69: =P69 -> 0 | AB69: =Q69 -> 0 | AC69: =R69 -> 0 | ... AE69: =T69 -> 0
B70: LTD | V70: =K70 -> 0 | W70: =L70 -> 0 | X70: =M70 -> 0 | Y70: =N70 -> 0 | Z70: =O70 -> 0 | AA70: =P70 -> 0 | AB70: =Q70 -> 0 | AC70: =R70 -> 0 | ... AE70: =T70 -> 0
B72: XXX | K72: =D72 -> 0 | O72: =E72 -> 0 | S72: =F72 -> 0 | V72: =K72 -> 0 | W72: =L72 -> 0 | X72: =M72 -> 0 | Y72: =N72 -> 0 | Z72: =O72 -> 0 | AA72: =P72 -> 0 | AB72: =Q72 -> 0 | AC72: =R72 -> 0 | ... AE72: =T72 -> 0
B73: XXX | K73: =D73 -> 0 | O73: =E73 -> 0 | S73: =F73 -> 0 | V73: =K73 -> 0 | W73: =L73 -> 0 | X73: =M73 -> 0 | Y73: =N73 -> 0 | Z73: =O73 -> 0 | AA73: =P73 -> 0 | AB73: =Q73 -> 0 | AC73: =R73 -> 0 | ... AE73: =T73 -> 0
B74: XXX | K74: =D74 -> 0 | O74: =E74 -> 0 | S74: =F74 -> 0 | V74: =K74 -> 0 | W74: =L74 -> 0 | X74: =M74 -> 0 | Y74: =N74 -> 0 | Z74: =O74 -> 0 | AA74: =P74 -> 0 | AB74: =Q74 -> 0 | AC74: =R74 -> 0 | ... AE74: =T74 -> 0
B75: XXX | K75: ='Historical Financials'!K77+'Historical Financials'!K86 -> 2393 | O75: ='Historical Financials'!O77+'Historical Financials'!O86 -> 1365 | S75: ='Historical Financials'!S77+'Historical Financials'!S86 -> 1620 | V75: =K75 -> 2393 | W75: =L75 -> 0 | X75: =M75 -> 0 | Y75: =N75 -> 0 | Z75: =O75 -> 1365 | AA75: =P75 -> 0 | AB75: =Q75 -> 0 | AC75: =R75 -> 0 | ... AE75: =T75 -> 0
B76: Total Debt | C76: =SUM(C72:C75) -> 0 | D76: =SUM(D72:D75) -> 0 | E76: =SUM(E72:E75) -> 0 | F76: =SUM(F72:F75) -> 0 | H76: =SUM(H72:H75) -> 0 | I76: =SUM(I72:I75) -> 0 | J76: =SUM(J72:J75) -> 0 | K76: =SUM(K72:K75) -> 2393 | L76: =SUM(L72:L75) -> 0 | M76: =SUM(M72:M75) -> 0 | N76: =SUM(N72:N75) -> 0 | O76: =SUM(O72:O75) -> 1365 | ... T76: =SUM(T72:T75) -> 0 | V76: =SUM(V72:V75) -> 2393 | W76: =SUM(W72:W75) -> 0 | X76: =SUM(X72:X75) -> 0 | Y76: =SUM(Y72:Y75) -> 0 | Z76: =SUM(Z72:Z75) -> 1365 | AA76: =SUM(AA72:AA75) -> 0 | AB76: =SUM(AB72:AB75) -> 0 | AC76: =SUM(AC72:AC75) -> 0 | ... AE76: =SUM(AE72:AE75) -> 0
B78: Total Shareholder Equity | V78: =K78 -> 0 | W78: =L78 -> 0 | X78: =M78 -> 0 | Y78: =N78 -> 0 | Z78: =O78 -> 0 | AA78: =P78 -> 0 | AB78: =Q78 -> 0 | AC78: =R78 -> 0 | ... AE78: =T78 -> 0
B79: Total Book Capitalization | C79: =SUM(C76:C78) -> 0 | D79: =SUM(D76:D78) -> 0 | E79: =SUM(E76:E78) -> 0 | F79: =SUM(F76:F78) -> 0 | H79: =SUM(H76:H78) -> 0 | I79: =SUM(I76:I78) -> 0 | J79: =SUM(J76:J78) -> 0 | K79: =SUM(K76:K78) -> 2393 | L79: =SUM(L76:L78) -> 0 | M79: =SUM(M76:M78) -> 0 | N79: =SUM(N76:N78) -> 0 | O79: =SUM(O76:O78) -> 1365 | ... T79: =SUM(T76:T78) -> 0 | V79: =SUM(V76:V78) -> 2393 | W79: =SUM(W76:W78) -> 0 | X79: =SUM(X76:X78) -> 0 | Y79: =SUM(Y76:Y78) -> 0 | Z79: =SUM(Z76:Z78) -> 1365 | AA79: =SUM(AA76:AA78) -> 0 | AB79: =SUM(AB76:AB78) -> 0 | AC79: =SUM(AC76:AC78) -> 0 | ... AE79: =SUM(AE76:AE78) -> 0
B81: Credit Metrics
B83: LTM Total Leverage | C83: =C76/C34 -> #DIV/0! | D83: =D76/D34 -> #DIV/0! | E83: =E76/E34 -> #DIV/0! | F83: =F76/F34 -> #DIV/0! | K83: =SUM(K76/SUM(H34:K34)) -> #DIV/0! | L83: =SUM(L76/SUM(I34:L34)) -> #DIV/0! | M83: =SUM(M76/SUM(J34:M34)) -> #DIV/0! | N83: =SUM(N76/SUM(K34:N34)) -> #DIV/0! | O83: =SUM(O76/SUM(L34:O34)) -> #DIV/0! | P83: =SUM(P76/SUM(M34:P34)) -> #DIV/0! | Q83: =SUM(Q76/SUM(N34:Q34)) -> #DIV/0! | R83: =SUM(R76/SUM(O34:R34)) -> #DIV/0! | ... T83: =SUM(T76/SUM(Q34:T34)) -> #DIV/0! | V83: =V76/V34 -> #DIV/0! | W83: =W76/W34 -> #DIV/0! | X83: =X76/X34 -> #DIV/0! | Y83: =Y76/Y34 -> #DIV/0! | Z83: =Z76/Z34 -> #DIV/0! | AA83: =AA76/AA34 -> #DIV/0! | AB83: =AB76/AB34 -> #DIV/0! | AC83: =AC76/AC34 -> #DIV/0! | ... AE83: =AE76/AE34 -> #DIV/0!
B84: LTM Net Leverage | C84: =SUM(C76-C54)/C34 -> #DIV/0! | D84: =SUM(D76-D54)/D34 -> #DIV/0! | E84: =SUM(E76-E54)/E34 -> #DIV/0! | F84: =SUM(F76-F54)/F34 -> #DIV/0! | K84: =SUM(K76-K54)/SUM(H34:K34) -> #DIV/0! | L84: =SUM(L76-L54)/SUM(I34:L34) -> #DIV/0! | M84: =SUM(M76-M54)/SUM(J34:M34) -> #DIV/0! | N84: =SUM(N76-N54)/SUM(K34:N34) -> #DIV/0! | O84: =SUM(O76-O54)/SUM(L34:O34) -> #DIV/0! | P84: =SUM(P76-P54)/SUM(M34:P34) -> #DIV/0! | Q84: =SUM(Q76-Q54)/SUM(N34:Q34) -> #DIV/0! | R84: =SUM(R76-R54)/SUM(O34:R34) -> #DIV/0! | ... T84: =SUM(T76-T54)/SUM(Q34:T34) -> #DIV/0! | V84: =SUM(V76-V54)/V34 -> #DIV/0! | W84: =SUM(W76-W54)/W34 -> #DIV/0! | X84: =SUM(X76-X54)/X34 -> #DIV/0! | Y84: =SUM(Y76-Y54)/Y34 -> #DIV/0! | Z84: =SUM(Z76-Z54)/Z34 -> #DIV/0! | AA84: =SUM(AA76-AA54)/AA34 -> #DIV/0! | AB84: =SUM(AB76-AB54)/AB34 -> #DIV/0! | AC84: =SUM(AC76-AC54)/AC34 -> #DIV/0! | ... AE84: =SUM(AE76-AE54)/AE34 -> #DIV/0!
B85: LTM Interest Coverage | C85: =C34/-C39 -> #DIV/0! | D85: =D34/-D39 -> #DIV/0! | E85: =E34/-E39 -> #DIV/0! | F85: =F34/-F39 -> #DIV/0! | K85: {=SUM(H34:K34)/SUM(-H39:K39)} -> #DIV/0! | L85: {=SUM(I34:L34)/SUM(-I39:L39)} -> #DIV/0! | M85: {=SUM(J34:M34)/SUM(-J39:M39)} -> #DIV/0! | N85: {=SUM(K34:N34)/SUM(-K39:N39)} -> #DIV/0! | O85: {=SUM(L34:O34)/SUM(-L39:O39)} -> #DIV/0! | P85: {=SUM(M34:P34)/SUM(-M39:P39)} -> #DIV/0! | Q85: {=SUM(N34:Q34)/SUM(-N39:Q39)} -> #DIV/0! | R85: {=SUM(O34:R34)/SUM(-O39:R39)} -> #DIV/0! | ... T85: {=SUM(Q34:T34)/SUM(-Q39:T39)} -> #DIV/0! | V85: =V34/-V39 -> #DIV/0! | W85: =W34/-W39 -> #DIV/0! | X85: =X34/-X39 -> #DIV/0! | Y85: =Y34/-Y39 -> #DIV/0! | Z85: =Z34/-Z39 -> #DIV/0! | AA85: =AA34/-AA39 -> #DIV/0! | AB85: =AB34/-AB39 -> #DIV/0! | AC85: =AC34/-AC39 -> #DIV/0! | ... AE85: =AE34/-AE39 -> #DIV/0!
B86: LTM Debt Service Coverage | C86: {=SUM(C34+C37)/SUM(-C38:C39)} -> #DIV/0! | D86: {=SUM(D34+D37)/SUM(-D38:D39)} -> #DIV/0! | E86: {=SUM(E34+E37)/SUM(-E38:E39)} -> #DIV/0! | F86: {=SUM(F34+F37)/SUM(-F38:F39)} -> #DIV/0! | K86: {=SUM(H34:K34+H37:K37)/SUM(-H38:K39)} -> #DIV/0! | L86: {=SUM(I34:L34+I37:L37)/SUM(-I38:L39)} -> #DIV/0! | M86: {=SUM(J34:M34+J37:M37)/SUM(-J38:M39)} -> #DIV/0! | N86: {=SUM(K34:N34+K37:N37)/SUM(-K38:N39)} -> #DIV/0! | O86: {=SUM(L34:O34+L37:O37)/SUM(-L38:O39)} -> #DIV/0! | P86: {=SUM(M34:P34+M37:P37)/SUM(-M38:P39)} -> #DIV/0! | Q86: {=SUM(N34:Q34+N37:Q37)/SUM(-N38:Q39)} -> #DIV/0! | R86: {=SUM(O34:R34+O37:R37)/SUM(-O38:R39)} -> #DIV/0! | ... T86: {=SUM(Q34:T34+Q37:T37)/SUM(-Q38:T39)} -> #DIV/0! | V86: {=SUM(V34+V37)/SUM(-V38:V39)} -> #DIV/0! | W86: {=SUM(W34+W37)/SUM(-W38:W39)} -> #DIV/0! | X86: {=SUM(X34+X37)/SUM(-X38:X39)} -> #DIV/0! | Y86: {=SUM(Y34+Y37)/SUM(-Y38:Y39)} -> #DIV/0! | Z86: {=SUM(Z34+Z37)/SUM(-Z38:Z39)} -> #DIV/0! | AA86: {=SUM(AA34+AA37)/SUM(-AA38:AA39)} -> #DIV/0! | AB86: {=SUM(AB34+AB37)/SUM(-AB38:AB39)} -> #DIV/0! | AC86: {=SUM(AC34+AC37)/SUM(-AC38:AC39)} -> #DIV/0! | ... AE86: {=SUM(AE34+AE37)/SUM(-AE38:AE39)} -> #DIV/0!
B87: LTM Fixed Charge Coverage | C87: {=SUM(C34)/SUM(-C37:C39)} -> #DIV/0! | D87: {=SUM(D34)/SUM(-D37:D39)} -> #DIV/0! | E87: {=SUM(E34)/SUM(-E37:E39)} -> #DIV/0! | F87: {=SUM(F34)/SUM(-F37:F39)} -> #DIV/0! | K87: {=SUM(H34:K34)/SUM(-H37:K39)} -> #DIV/0! | L87: {=SUM(I34:L34)/SUM(-I37:L39)} -> #DIV/0! | M87: {=SUM(J34:M34)/SUM(-J37:M39)} -> #DIV/0! | N87: {=SUM(K34:N34)/SUM(-K37:N39)} -> #DIV/0! | O87: {=SUM(L34:O34)/SUM(-L37:O39)} -> #DIV/0! | P87: {=SUM(M34:P34)/SUM(-M37:P39)} -> #DIV/0! | Q87: {=SUM(N34:Q34)/SUM(-N37:Q39)} -> #DIV/0! | R87: {=SUM(O34:R34)/SUM(-O37:R39)} -> #DIV/0! | ... T87: {=SUM(Q34:T34)/SUM(-Q37:T39)} -> #DIV/0! | V87: {=SUM(V34)/SUM(-V37:V39)} -> #DIV/0! | W87: {=SUM(W34)/SUM(-W37:W39)} -> #DIV/0! | X87: {=SUM(X34)/SUM(-X37:X39)} -> #DIV/0! | Y87: {=SUM(Y34)/SUM(-Y37:Y39)} -> #DIV/0! | Z87: {=SUM(Z34)/SUM(-Z37:Z39)} -> #DIV/0! | AA87: {=SUM(AA34)/SUM(-AA37:AA39)} -> #DIV/0! | AB87: {=SUM(AB34)/SUM(-AB37:AB39)} -> #DIV/0! | AC87: {=SUM(AC34)/SUM(-AC37:AC39)} -> #DIV/0! | ... AE87: {=SUM(AE34)/SUM(-AE37:AE39)} -> #DIV/0!
B88: Debt-to-Book Capitalization | C88: =C79/C76 -> #DIV/0! | D88: =D79/D76 -> #DIV/0! | E88: =E79/E76 -> #DIV/0! | F88: =F79/F76 -> #DIV/0! | K88: =K79/K76 -> 1 | L88: =L79/L76 -> #DIV/0! | M88: =M79/M76 -> #DIV/0! | N88: =N79/N76 -> #DIV/0! | O88: =O79/O76 -> 1 | P88: =P79/P76 -> #DIV/0! | Q88: =Q79/Q76 -> #DIV/0! | R88: =R79/R76 -> #DIV/0! | ... T88: =T79/T76 -> #DIV/0! | V88: =V79/V76 -> 1 | W88: =W79/W76 -> #DIV/0! | X88: =X79/X76 -> #DIV/0! | Y88: =Y79/Y76 -> #DIV/0! | Z88: =Z79/Z76 -> 1 | AA88: =AA79/AA76 -> #DIV/0! | AB88: =AB79/AB76 -> #DIV/0! | AC88: =AC79/AC76 -> #DIV/0! | ... AE88: =AE79/AE76 -> #DIV/0!
