Workbook

Sheet Base Financials
B2: Intel, Corporation. (NASDAQ: INTC) | C2: FYE | E2: FYE | I2: Quarterly | O2: Quarterly | R2: Quarterly | S2: Quarterly | AE2: LTM | AK2: Variance
B3: Base Financials | C3: 2020 | D3: 2021 | E3: 2022 | F3: 2023 | G3: 2024 | I3: 1Q22 | J3: 2Q22 | K3: 3Q22 | L3: 4Q22 | M3: 1Q23 | N3: 2Q23 | O3: 3Q23 | P3: 4Q23 | Q3: 1Q24 | R3: 2Q24 | S3: 3Q24 | T3: 4Q24 | U3: 1Q25 | V3: 2Q25 | W3: 3Q25 | Y3: =M3 -> 1Q23 | Z3: =N3 -> 2Q23 | AA3: =O3 -> 3Q23 | AB3: =P3 -> 4Q23 | AC3: =Q3 -> 1Q24 | AD3: =R3 -> 2Q24 | AE3: =S3 -> 3Q24 | AF3: =T3 -> 4Q24 | ... AI3: =W3 -> 3Q25
B4: ($ In Millions) | C4: 44191 | D4: 44555 | E4: 44926 | F4: 45290 | G4: 45654 | I4: 44653 | J4: 44744 | K4: 44835 | L4: =E4 -> 44926 | M4: 45017 | N4: 45108 | O4: 45199 | P4: =F4 -> 45290 | Q4: 45381 | R4: 45472 | S4: 45563 | T4: =G4 -> 45654 | U4: 45745 | V4: 45836 | W4: 45925 | Y4: =M4 -> 45017 | Z4: =N4 -> 45108 | AA4: =O4 -> 45199 | AB4: =P4 -> 45290 | AC4: =Q4 -> 45381 | AD4: =R4 -> 45472 | AE4: =S4 -> 45563 | AF4: =T4 -> 45654 | ... AI4: =W4 -> 45925
A6: X | B6: Income Statement
B8: Consolidated Revenue | C8: 77867 | D8: 79024 | E8: 63054 | F8: 54228 | G8: 53101 | I8: 18353 | J8: 15321 | K8: 15338 | L8: =SUM(E8-SUM(I8:K8)) -> 14042 | M8: 11715 | N8: 12949 | O8: 14158 | P8: =SUM(F8-SUM(M8:O8)) -> 15406 | Q8: 12724 | R8: 12833 | S8: 13284 | T8: =SUM(G8-SUM(Q8:S8)) -> 14260 | U8: 12667 | V8: 12859 | W8: 13653 | Y8: =SUM(J8:M8) -> 56416 | Z8: =SUM(K8:N8) -> 54044 | AA8: =SUM(L8:O8) -> 52864 | AB8: =SUM(M8:P8) -> 54228 | AC8: =SUM(N8:Q8) -> 55237 | AD8: =SUM(O8:R8) -> 55121 | AE8: =SUM(P8:S8) -> 54247 | AF8: =SUM(Q8:T8) -> 53101 | ... AI8: =SUM(T8:W8) -> 53439 | AK8: =SUM(AI8/AE8)-1 -> -0.014894833
B9: Total Revenue | C9: =+SUM(C8:C8) -> 77867 | D9: =+SUM(D8:D8) -> 79024 | E9: =+SUM(E8:E8) -> 63054 | F9: =+SUM(F8:F8) -> 54228 | G9: =+SUM(G8:G8) -> 53101 | I9: =+SUM(I8:I8) -> 18353 | J9: =+SUM(J8:J8) -> 15321 | K9: =+SUM(K8:K8) -> 15338 | L9: =+SUM(L8:L8) -> 14042 | M9: =+SUM(M8:M8) -> 11715 | N9: =+SUM(N8:N8) -> 12949 | O9: =+SUM(O8:O8) -> 14158 | P9: =+SUM(P8:P8) -> 15406 | ... W9: =+SUM(W8:W8) -> 13653 | Y9: =+SUM(Y8:Y8) -> 56416 | Z9: =+SUM(Z8:Z8) -> 54044 | AA9: =+SUM(AA8:AA8) -> 52864 | AB9: =+SUM(AB8:AB8) -> 54228 | AC9: =+SUM(AC8:AC8) -> 55237 | AD9: =+SUM(AD8:AD8) -> 55121 | AE9: =+SUM(AE8:AE8) -> 54247 | AF9: =+SUM(AF8:AF8) -> 53101 | ... AI9: =+SUM(AI8:AI8) -> 53439 | AK9: =SUM(AI9/AE9)-1 -> -0.014894833
B11: Cost of Sales | C11: -34255 | D11: -35209 | E11: -36188 | F11: -32517 | G11: -35756 | I11: -9109 | J11: -9734 | K11: -8803 | L11: =SUM(E11-SUM(I11:K11)) -> -8542 | M11: -7707 | N11: -8311 | O11: -8140 | P11: =SUM(F11-SUM(M11:O11)) -> -8359 | Q11: -7507 | R11: -8286 | S11: -11287 | T11: =SUM(G11-SUM(Q11:S11)) -> -8676 | U11: -7995 | V11: -9317 | W11: -8435 | Y11: =SUM(J11:M11) -> -34786 | Z11: =SUM(K11:N11) -> -33363 | AA11: =SUM(L11:O11) -> -32700 | AB11: =SUM(M11:P11) -> -32517 | AC11: =SUM(N11:Q11) -> -32317 | AD11: =SUM(O11:R11) -> -32292 | AE11: =SUM(P11:S11) -> -35439 | AF11: =SUM(Q11:T11) -> -35756 | ... AI11: =SUM(T11:W11) -> -34423 | AK11: =SUM(AI11/AE11)-1 -> -0.028668981
B12: Gross Profit | C12: =+SUM(C9+SUM(C11:C11)) -> 43612 | D12: =+SUM(D9+SUM(D11:D11)) -> 43815 | E12: =+SUM(E9+SUM(E11:E11)) -> 26866 | F12: =+SUM(F9+SUM(F11:F11)) -> 21711 | G12: =+SUM(G9+SUM(G11:G11)) -> 17345 | I12: =+SUM(I9+SUM(I11:I11)) -> 9244 | J12: =+SUM(J9+SUM(J11:J11)) -> 5587 | K12: =+SUM(K9+SUM(K11:K11)) -> 6535 | L12: =+SUM(L9+SUM(L11:L11)) -> 5500 | M12: =+SUM(M9+SUM(M11:M11)) -> 4008 | N12: =+SUM(N9+SUM(N11:N11)) -> 4638 | O12: =+SUM(O9+SUM(O11:O11)) -> 6018 | P12: =+SUM(P9+SUM(P11:P11)) -> 7047 | ... W12: =+SUM(W9+SUM(W11:W11)) -> 5218 | Y12: =+SUM(Y9+SUM(Y11:Y11)) -> 21630 | Z12: =+SUM(Z9+SUM(Z11:Z11)) -> 20681 | AA12: =+SUM(AA9+SUM(AA11:AA11)) -> 20164 | AB12: =+SUM(AB9+SUM(AB11:AB11)) -> 21711 | AC12: =+SUM(AC9+SUM(AC11:AC11)) -> 22920 | AD12: =+SUM(AD9+SUM(AD11:AD11)) -> 22829 | AE12: =+SUM(AE9+SUM(AE11:AE11)) -> 18808 | AF12: =+SUM(AF9+SUM(AF11:AF11)) -> 17345 | ... AI12: =+SUM(AI9+SUM(AI11:AI11)) -> 19016 | AK12: =SUM(AI12/AE12)-1 -> 0.011059124
B13: Gross Margin (%) | C13: =C12/C9 -> 0.56008322 | D13: =D12/D9 -> 0.55445181 | E13: =E12/E9 -> 0.42607923 | F13: =F12/F9 -> 0.40036513 | G13: =G12/G9 -> 0.32664168 | I13: =I12/I9 -> 0.50367787 | J13: =J12/J9 -> 0.36466288 | K13: =K12/K9 -> 0.42606598 | L13: =L12/L9 -> 0.3916821 | M13: =M12/M9 -> 0.34212548 | N13: =N12/N9 -> 0.35817438 | O13: =O12/O9 -> 0.42506004 | P13: =P12/P9 -> 0.45741919 | ... W13: =W12/W9 -> 0.38218707 | Y13: =Y12/Y9 -> 0.38340187 | Z13: =Z12/Z9 -> 0.38266968 | AA13: =AA12/AA9 -> 0.3814316 | AB13: =AB12/AB9 -> 0.40036513 | AC13: =AC12/AC9 -> 0.41493926 | AD13: =AD12/AD9 -> 0.41416157 | AE13: =AE12/AE9 -> 0.34671042 | AF13: =AF12/AF9 -> 0.32664168 | ... AI13: =AI12/AI9 -> 0.35584498 | AK13: =SUM(AI13-AE13)*1000 -> 9.134565
B15: Marketing, General, and Administrative (MG&A) | C15: -6180 | D15: -6543 | E15: -7002 | F15: -5634 | G15: -5507 | I15: -1752 | J15: -1800 | K15: -1744 | L15: =SUM(E15-SUM(I15:K15)) -> -1706 | M15: -1303 | N15: -1374 | O15: -1340 | P15: =SUM(F15-SUM(M15:O15)) -> -1617 | Q15: -1556 | R15: -1329 | S15: -1383 | T15: =SUM(G15-SUM(Q15:S15)) -> -1239 | U15: -1177 | V15: -1144 | W15: -1129 | Y15: =SUM(J15:M15) -> -6553 | Z15: =SUM(K15:N15) -> -6127 | AA15: =SUM(L15:O15) -> -5723 | AB15: =SUM(M15:P15) -> -5634 | AC15: =SUM(N15:Q15) -> -5887 | AD15: =SUM(O15:R15) -> -5842 | AE15: =SUM(P15:S15) -> -5885 | AF15: =SUM(Q15:T15) -> -5507 | ... AI15: =SUM(T15:W15) -> -4689 | AK15: =SUM(AI15/AE15)-1 -> -0.20322855
B16: Research and Development (R&D) | C16: -13556 | D16: -15190 | E16: -17528 | F16: -16046 | G16: -16546 | I16: -4362 | J16: -4400 | K16: -4302 | L16: =SUM(E16-SUM(I16:K16)) -> -4464 | M16: -4109 | N16: -4080 | O16: -3870 | P16: =SUM(F16-SUM(M16:O16)) -> -3987 | Q16: -4382 | R16: -4239 | S16: -4049 | T16: =SUM(G16-SUM(Q16:S16)) -> -3876 | U16: -3640 | V16: -3684 | W16: -3231 | Y16: =SUM(J16:M16) -> -17275 | Z16: =SUM(K16:N16) -> -16955 | AA16: =SUM(L16:O16) -> -16523 | AB16: =SUM(M16:P16) -> -16046 | AC16: =SUM(N16:Q16) -> -16319 | AD16: =SUM(O16:R16) -> -16478 | AE16: =SUM(P16:S16) -> -16657 | AF16: =SUM(Q16:T16) -> -16546 | ... AI16: =SUM(T16:W16) -> -14431 | AK16: =SUM(AI16/AE16)-1 -> -0.13363751
B17: Restructuring and Other Charges | C17: -198 | D17: -2626 | E17: -2 | F17: 62 | G17: -6970 | I17: 1211 | J17: -87 | K17: -664 | L17: =SUM(E17-SUM(I17:K17)) -> -462 | M17: -64 | N17: -200 | O17: -816 | P17: =SUM(F17-SUM(M17:O17)) -> 1142 | Q17: -348 | R17: -943 | S17: -5622 | T17: =SUM(G17-SUM(Q17:S17)) -> -57 | U17: -156 | V17: -1890 | W17: -175 | Y17: =SUM(J17:M17) -> -1277 | Z17: =SUM(K17:N17) -> -1390 | AA17: =SUM(L17:O17) -> -1542 | AB17: =SUM(M17:P17) -> 62 | AC17: =SUM(N17:Q17) -> -222 | AD17: =SUM(O17:R17) -> -965 | AE17: =SUM(P17:S17) -> -5771 | AF17: =SUM(Q17:T17) -> -6970 | ... AI17: =SUM(T17:W17) -> -2278 | AK17: =SUM(AI17/AE17)-1 -> -0.60526772
B18: Profit From Operations | C18: =SUM(C12+SUM(C15:C17)) -> 23678 | D18: =SUM(D12+SUM(D15:D17)) -> 19456 | E18: =SUM(E12+SUM(E15:E17)) -> 2334 | F18: =SUM(F12+SUM(F15:F17)) -> 93 | G18: =SUM(G12+SUM(G15:G17)) -> -11678 | I18: =SUM(I12+SUM(I15:I17)) -> 4341 | J18: =SUM(J12+SUM(J15:J17)) -> -700 | K18: =SUM(K12+SUM(K15:K17)) -> -175 | L18: =SUM(L12+SUM(L15:L17)) -> -1132 | M18: =SUM(M12+SUM(M15:M17)) -> -1468 | N18: =SUM(N12+SUM(N15:N17)) -> -1016 | O18: =SUM(O12+SUM(O15:O17)) -> -8 | P18: =SUM(P12+SUM(P15:P17)) -> 2585 | ... W18: =SUM(W12+SUM(W15:W17)) -> 683 | Y18: =SUM(Y12+SUM(Y15:Y17)) -> -3475 | Z18: =SUM(Z12+SUM(Z15:Z17)) -> -3791 | AA18: =SUM(AA12+SUM(AA15:AA17)) -> -3624 | AB18: =SUM(AB12+SUM(AB15:AB17)) -> 93 | AC18: =SUM(AC12+SUM(AC15:AC17)) -> 492 | AD18: =SUM(AD12+SUM(AD15:AD17)) -> -456 | AE18: =SUM(AE12+SUM(AE15:AE17)) -> -9505 | AF18: =SUM(AF12+SUM(AF15:AF17)) -> -11678 | ... AI18: =SUM(AI12+SUM(AI15:AI17)) -> -2382 | AK18: =SUM(AI18/AE18)-1 -> -0.74939506
B19: Operating Margin (%) | C19: =C18/C9 -> 0.3040826 | D19: =D18/D9 -> 0.24620368 | E19: =E18/E9 -> 0.037015891 | F19: =F18/F9 -> 0.0017149812 | G19: =G18/G9 -> -0.21992053 | I19: =I18/I9 -> 0.23652809 | J19: =J18/J9 -> -0.045688924 | K19: =K18/K9 -> -0.011409571 | L19: =L18/L9 -> -0.080615297 | M19: =M18/M9 -> -0.12530943 | N19: =N18/N9 -> -0.078461657 | O19: =O18/O9 -> -0.00056505156 | P19: =P18/P9 -> 0.16779177 | ... W19: =W18/W9 -> 0.050025635 | Y19: =Y18/Y9 -> -0.061596001 | Z19: =Z18/Z9 -> -0.070146547 | AA19: =AA18/AA9 -> -0.068553269 | AB19: =AB18/AB9 -> 0.0017149812 | AC19: =AC18/AC9 -> 0.0089070732 | AD19: =AD18/AD9 -> -0.0082727091 | AE19: =AE18/AE9 -> -0.17521706 | AF19: =AF18/AF9 -> -0.21992053 | ... AI19: =AI18/AI9 -> -0.044574187 | AK19: =SUM(AI19-AE19)*1000 -> 130.64288
B21: Interest and other, net | C21: -504 | D21: -482 | E21: 1166 | F21: 629 | G21: 226 | I21: 997 | J21: -119 | K21: 138 | L21: =SUM(E21-SUM(I21:K21)) -> 150 | M21: 141 | N21: 224 | O21: 147 | P21: =SUM(F21-SUM(M21:O21)) -> 117 | Q21: 145 | R21: 80 | S21: 130 | T21: =SUM(G21-SUM(Q21:S21)) -> -129 | U21: -173 | V21: -95 | W21: 3670 | Y21: =SUM(J21:M21) -> 310 | Z21: =SUM(K21:N21) -> 653 | AA21: =SUM(L21:O21) -> 662 | AB21: =SUM(M21:P21) -> 629 | AC21: =SUM(N21:Q21) -> 633 | AD21: =SUM(O21:R21) -> 489 | AE21: =SUM(P21:S21) -> 472 | AF21: =SUM(Q21:T21) -> 226 | ... AI21: =SUM(T21:W21) -> 3273 | AK21: =SUM(AI21/AE21)-1 -> 5.934322
B22: Gains (losses) on equity investments, net | C22: 1904 | D22: 2729 | E22: 4268 | F22: 40 | G22: 242 | I22: 4323 | J22: -90 | K22: -151 | L22: =SUM(E22-SUM(I22:K22)) -> 186 | M22: 169 | N22: -24 | O22: -191 | P22: =SUM(F22-SUM(M22:O22)) -> 86 | Q22: 205 | R22: -120 | S22: -159 | T22: =SUM(G22-SUM(Q22:S22)) -> 316 | U22: -112 | V22: 502 | W22: 221 | Y22: =SUM(J22:M22) -> 114 | Z22: =SUM(K22:N22) -> 180 | AA22: =SUM(L22:O22) -> 140 | AB22: =SUM(M22:P22) -> 40 | AC22: =SUM(N22:Q22) -> 76 | AD22: =SUM(O22:R22) -> -20 | AE22: =SUM(P22:S22) -> 12 | AF22: =SUM(Q22:T22) -> 242 | ... AI22: =SUM(T22:W22) -> 927 | AK22: =SUM(AI22/AE22)-1 -> 76.25
B23: Gains (losses) from divestitures | C23: 0 | D23: 0 | E23: 0 | F23: 0 | G23: 0 | I23: 0 | J23: 0 | K23: 0 | L23: =SUM(E23-SUM(I23:K23)) -> 0 | M23: 0 | N23: 0 | O23: 0 | P23: =SUM(F23-SUM(M23:O23)) -> 0 | Q23: 0 | R23: 0 | S23: 0 | T23: =SUM(G23-SUM(Q23:S23)) -> 0 | U23: 0 | V23: 0 | W23: 0 | Y23: =SUM(J23:M23) -> 0 | Z23: =SUM(K23:N23) -> 0 | AA23: =SUM(L23:O23) -> 0 | AB23: =SUM(M23:P23) -> 0 | AC23: =SUM(N23:Q23) -> 0 | AD23: =SUM(O23:R23) -> 0 | AE23: =SUM(P23:S23) -> 0 | AF23: =SUM(Q23:T23) -> 0 | ... AI23: =SUM(T23:W23) -> 0 | AK23: =SUM(AI23/AE23)-1 -> #DIV/0!
B24: Net loss before provision for income taxes | C24: =SUM(C21:C23)+C18 -> 25078 | D24: =SUM(D21:D23)+D18 -> 21703 | E24: =SUM(E21:E23)+E18 -> 7768 | F24: =SUM(F21:F23)+F18 -> 762 | G24: =SUM(G21:G23)+G18 -> -11210 | I24: =SUM(I21:I23)+I18 -> 9661 | J24: =SUM(J21:J23)+J18 -> -909 | K24: =SUM(K21:K23)+K18 -> -188 | L24: =SUM(L21:L23)+L18 -> -796 | M24: =SUM(M21:M23)+M18 -> -1158 | N24: =SUM(N21:N23)+N18 -> -816 | O24: =SUM(O21:O23)+O18 -> -52 | P24: =SUM(P21:P23)+P18 -> 2788 | ... W24: =SUM(W21:W23)+W18 -> 4574 | Y24: =SUM(Y21:Y23)+Y18 -> -3051 | Z24: =SUM(Z21:Z23)+Z18 -> -2958 | AA24: =SUM(AA21:AA23)+AA18 -> -2822 | AB24: =SUM(AB21:AB23)+AB18 -> 762 | AC24: =SUM(AC21:AC23)+AC18 -> 1201 | AD24: =SUM(AD21:AD23)+AD18 -> 13 | AE24: =SUM(AE21:AE23)+AE18 -> -9021 | AF24: =SUM(AF21:AF23)+AF18 -> -11210 | ... AI24: =SUM(AI21:AI23)+AI18 -> 1818 | AK24: =SUM(AI24/AE24)-1 -> -1.2015298
B26: Provision for taxes | C26: -4179 | D26: -1835 | E26: 249 | F26: 913 | G26: -8023 | I26: -1548 | J26: 455 | K26: 1207 | L26: =SUM(E26-SUM(I26:K26)) -> 135 | M26: -1610 | N26: 2289 | O26: 362 | P26: =SUM(F26-SUM(M26:O26)) -> -128 | Q26: 282 | R26: 350 | S26: -7903 | T26: =SUM(G26-SUM(Q26:S26)) -> -752 | U26: -301 | V26: -255 | W26: -304 | Y26: =SUM(J26:M26) -> 187 | Z26: =SUM(K26:N26) -> 2021 | AA26: =SUM(L26:O26) -> 1176 | AB26: =SUM(M26:P26) -> 913 | AC26: =SUM(N26:Q26) -> 2805 | AD26: =SUM(O26:R26) -> 866 | AE26: =SUM(P26:S26) -> -7399 | AF26: =SUM(Q26:T26) -> -8023 | ... AI26: =SUM(T26:W26) -> -1612 | AK26: =SUM(AI26/AE26)-1 -> -0.78213272
B27: Net loss | C27: =SUM(C24+C26) -> 20899 | D27: =SUM(D24+D26) -> 19868 | E27: =SUM(E24+E26) -> 8017 | F27: =SUM(F24+F26) -> 1675 | G27: =SUM(G24+G26) -> -19233 | I27: =SUM(I24+I26) -> 8113 | J27: =SUM(J24+J26) -> -454 | K27: =SUM(K24+K26) -> 1019 | L27: =SUM(L24+L26) -> -661 | M27: =SUM(M24+M26) -> -2768 | N27: =SUM(N24+N26) -> 1473 | O27: =SUM(O24+O26) -> 310 | P27: =SUM(P24+P26) -> 2660 | ... W27: =SUM(W24+W26) -> 4270 | Y27: =SUM(Y24+Y26) -> -2864 | Z27: =SUM(Z24+Z26) -> -937 | AA27: =SUM(AA24+AA26) -> -1646 | AB27: =SUM(AB24+AB26) -> 1675 | AC27: =SUM(AC24+AC26) -> 4006 | AD27: =SUM(AD24+AD26) -> 879 | AE27: =SUM(AE24+AE26) -> -16420 | AF27: =SUM(AF24+AF26) -> -19233 | ... AI27: =SUM(AI24+AI26) -> 206 | AK27: =SUM(AI27/AE27)-1 -> -1.0125457
B28: Net Margin (%) | C28: =C27/C9 -> 0.26839354 | D28: =D27/D9 -> 0.25141729 | E28: =E27/E9 -> 0.12714499 | F28: =F27/F9 -> 0.030888102 | G28: =G27/G9 -> -0.36219657 | I28: =I27/I9 -> 0.44205307 | J28: =J27/J9 -> -0.029632531 | K28: =K27/K9 -> 0.066436302 | L28: =L27/L9 -> -0.047073067 | M28: =M27/M9 -> -0.23627828 | N28: =N27/N9 -> 0.11375396 | O28: =O27/O9 -> 0.021895748 | P28: =P27/P9 -> 0.17266 | ... W28: =W27/W9 -> 0.31275178 | Y28: =Y27/Y9 -> -0.05076574 | Z28: =Z27/Z9 -> -0.017337725 | AA28: =AA27/AA9 -> -0.031136501 | AB28: =AB27/AB9 -> 0.030888102 | AC28: =AC27/AC9 -> 0.072523852 | AD28: =AD27/AD9 -> 0.015946735 | AE28: =AE27/AE9 -> -0.30268955 | AF28: =AF27/AF9 -> -0.36219657 | ... AI28: =AI27/AI9 -> 0.0038548626 | AK28: =SUM(AI28-AE28)*1000 -> 306.54441
B30: Basic shares | C30: 4198.5 | D30: 4058.75 | E30: 4107.5 | F30: 4190 | G30: 4280 | I30: 4079 | J30: 4100 | K30: 4118 | L30: 4133 | M30: 4154 | N30: 4182 | O30: 4202 | P30: 4222 | Q30: 4242 | R30: 4267 | S30: 4292 | T30: 4319 | U30: 4343 | V30: 4369 | W30: 4514 | AE30: =S30 -> 4292 | AF30: =T30 -> 4319 | AG30: =U30 -> 4343 | AH30: =V30 -> 4369 | AI30: =W30 -> 4514
B31: Basic EPS | C31: =C27/C30 -> 4.9777301 | D31: =D27/D30 -> 4.8951032 | E31: =E27/E30 -> 1.9517955 | F31: =F27/F30 -> 0.39976134 | G31: =G27/G30 -> -4.4936916 | I31: =I27/I30 -> 1.9889679 | J31: =J27/J30 -> -0.11073171 | K31: =K27/K30 -> 0.24745022 | L31: =L27/L30 -> -0.15993225 | M31: =M27/M30 -> -0.66634569 | N31: =N27/N30 -> 0.35222382 | O31: =O27/O30 -> 0.073774393 | P31: =P27/P30 -> 0.63003316 | ... W31: =W27/W30 -> 0.94594595 | Y31: =Y27/Y30 -> #DIV/0! | Z31: =Z27/Z30 -> #DIV/0! | AA31: =AA27/AA30 -> #DIV/0! | AB31: =AB27/AB30 -> #DIV/0! | AC31: =AC27/AC30 -> #DIV/0! | AD31: =AD27/AD30 -> #DIV/0! | AE31: =AE27/AE30 -> -3.8257223 | AF31: =AF27/AF30 -> -4.4531141 | ... AI31: =AI27/AI30 -> 0.0456358 | AK31: =SUM(AI31/AE31)-1 -> -1.0119287
B33: Fully Diluted Shares | C33: 4231.5 | D33: 4090.25 | E33: 4116.25 | F33: 4209.75 | G33: 4280 | I33: 4107 | J33: 4100 | K33: 4125 | L33: 4133 | M33: 4154 | N33: 4196 | O33: 4229 | P33: 4260 | Q33: 4242 | R33: 4267 | S33: 4292 | T33: 4319 | U33: 4343 | V33: 4369 | W33: 4531 | Y33: =M33 -> 4154 | Z33: =N33 -> 4196 | AA33: =O33 -> 4229 | AB33: =P33 -> 4260 | AC33: =Q33 -> 4242 | AD33: =R33 -> 4267 | AE33: =S33 -> 4292 | AF33: =T33 -> 4319 | ... AI33: =W33 -> 4531
B34: Diluted EPS | C34: =C27/C33 -> 4.9389106 | D34: =D27/D33 -> 4.8574048 | E34: =E27/E33 -> 1.9476465 | F34: =F27/F33 -> 0.39788586 | G34: =G27/G33 -> -4.4936916 | I34: =I27/I33 -> 1.9754078 | J34: =J27/J33 -> -0.11073171 | K34: =K27/K33 -> 0.2470303 | L34: =L27/L33 -> -0.15993225 | M34: =M27/M33 -> -0.66634569 | N34: =N27/N33 -> 0.35104862 | O34: =O27/O33 -> 0.073303381 | P34: =P27/P33 -> 0.62441315 | ... W34: =W27/W33 -> 0.94239682 | Y34: =Y27/Y33 -> -0.68945595 | Z34: =Z27/Z33 -> -0.22330791 | AA34: =AA27/AA33 -> -0.38921731 | AB34: =AB27/AB33 -> 0.39319249 | AC34: =AC27/AC33 -> 0.94436587 | AD34: =AD27/AD33 -> 0.20599953 | AE34: =AE27/AE33 -> -3.8257223 | AF34: =AF27/AF33 -> -4.4531141 | ... AI34: =AI27/AI33 -> 0.045464577 | AK34: =SUM(AI34/AE34)-1 -> -1.0118839
A36: X | B36: Balance Sheet Statement
B38: Cash and cash equivalents | C38: 5865 | D38: 4827 | E38: 11144 | F38: 7079 | G38: 8249 | I38: 6215 | J38: 4390 | K38: 4529 | L38: =E38 -> 11144 | M38: 8232 | N38: 8349 | O38: 7621 | P38: =F38 -> 7079 | Q38: 6923 | R38: 11287 | S38: 8785 | T38: =G38 -> 8249 | U38: 8947 | V38: 9643 | W38: 11141 | Y38: =M38 -> 8232 | Z38: =N38 -> 8349 | AA38: =O38 -> 7621 | AB38: =P38 -> 7079 | AC38: =Q38 -> 6923 | AD38: =R38 -> 11287 | AE38: =S38 -> 8785 | AF38: =T38 -> 8249 | ... AI38: =W38 -> 11141 | AK38: =SUM(AI38/AE38)-1 -> 0.26818441
B39: Short-term investments | C39: 2292 | D39: 2103 | E39: 0 | F39: 0 | G39: 0 | I39: 10998 | J39: 0 | K39: 0 | L39: =E39 -> 0 | M39: 0 | N39: 0 | O39: 0 | P39: =F39 -> 0 | Q39: 0 | R39: 0 | S39: 0 | T39: =G39 -> 0 | U39: 0 | V39: 0 | W39: 0 | Y39: =M39 -> 0 | Z39: =N39 -> 0 | AA39: =O39 -> 0 | AB39: =P39 -> 0 | AC39: =Q39 -> 0 | AD39: =R39 -> 0 | AE39: =S39 -> 0 | AF39: =T39 -> 0 | ... AI39: =W39 -> 0 | AK39: =SUM(AI39/AE39)-1 -> #DIV/0!
B40: Trading assets | C40: 15738 | D40: 21483 | E40: 17194 | F40: 17955 | G40: 13813 | I40: 21483 | J40: 22654 | K40: 18030 | L40: =E40 -> 17194 | M40: 19302 | N40: 15908 | O40: 17409 | P40: =F40 -> 17955 | Q40: 14388 | R40: 17986 | S40: 15301 | T40: =G40 -> 13813 | U40: 12101 | V40: 11563 | W40: 19794 | Y40: =M40 -> 19302 | Z40: =N40 -> 15908 | AA40: =O40 -> 17409 | AB40: =P40 -> 17955 | AC40: =Q40 -> 14388 | AD40: =R40 -> 17986 | AE40: =S40 -> 15301 | AF40: =T40 -> 13813 | ... AI40: =W40 -> 19794 | AK40: =SUM(AI40/AE40)-1 -> 0.29364094
B41: Accounts receivable, net | C41: 6782 | D41: 9457 | E41: 4133 | F41: 3402 | G41: 3478 | I41: 7074 | J41: 6063 | K41: 7469 | L41: =E41 -> 4133 | M41: 3847 | N41: 2996 | O41: 2843 | P41: =F41 -> 3402 | Q41: 3323 | R41: 3131 | S41: 3121 | T41: =G41 -> 3478 | U41: 3064 | V41: 2360 | W41: 3202 | Y41: =M41 -> 3847 | Z41: =N41 -> 2996 | AA41: =O41 -> 2843 | AB41: =P41 -> 3402 | AC41: =Q41 -> 3323 | AD41: =R41 -> 3131 | AE41: =S41 -> 3121 | AF41: =T41 -> 3478 | ... AI41: =W41 -> 3202 | AK41: =SUM(AI41/AE41)-1 -> 0.02595322
B42: Inventories | C42: 8427 | D42: 10776 | E42: 13224 | F42: 11127 | G42: 12198 | I42: 11935 | J42: 12174 | K42: 12831 | L42: 13224 | M42: 12993 | N42: 11984 | O42: 11466 | P42: 11127 | Q42: 11494 | R42: 11244 | S42: 12062 | T42: 12198 | U42: 12281 | V42: 11377 | W42: 11489 | Y42: =M42 -> 12993 | Z42: =N42 -> 11984 | AA42: =O42 -> 11466 | AB42: =P42 -> 11127 | AC42: =Q42 -> 11494 | AD42: =R42 -> 11244 | AE42: =S42 -> 12062 | AF42: =T42 -> 12198 | ... AI42: =W42 -> 11489 | AK42: =SUM(AI42/AE42)-1 -> -0.04750456
B43: Deferred tax assets | C43: 0 | D43: 0 | E43: 0 | F43: 0 | G43: 0 | I43: 0 | J43: 0 | K43: 0 | L43: =E43 -> 0 | M43: 0 | N43: 0 | O43: 0 | P43: =F43 -> 0 | Q43: 0 | R43: 0 | S43: 0 | T43: =G43 -> 0 | U43: 0 | V43: 0 | W43: 0 | Y43: =M43 -> 0 | Z43: =N43 -> 0 | AA43: =O43 -> 0 | AB43: =P43 -> 0 | AC43: =Q43 -> 0 | AD43: =R43 -> 0 | AE43: =S43 -> 0 | AF43: =T43 -> 0 | ... AI43: =W43 -> 0 | AK43: =SUM(AI43/AE43)-1 -> #DIV/0!
B44: Other current assets | C44: 8145 | D44: 9072 | E44: 4712 | F44: 3706 | G44: 9586 | I44: 4863 | J44: 5307 | K44: 6404 | L44: =E44 -> 4712 | M44: 3940 | N44: 4119 | O44: 4472 | P44: =F44 -> 3706 | Q44: 6480 | R44: 7181 | S44: 6868 | T44: =G44 -> 9586 | U44: 5741 | V44: 8432 | W44: 6105 | Y44: =M44 -> 3940 | Z44: =N44 -> 4119 | AA44: =O44 -> 4472 | AB44: =P44 -> 3706 | AC44: =Q44 -> 6480 | AD44: =R44 -> 7181 | AE44: =S44 -> 6868 | AF44: =T44 -> 9586 | ... AI44: =W44 -> 6105 | AK44: =SUM(AI44/AE44)-1 -> -0.11109493
B45: Total Current Assets | C45: =SUM(C38:C44) -> 47249 | D45: =SUM(D38:D44) -> 57718 | E45: =SUM(E38:E44) -> 50407 | F45: =SUM(F38:F44) -> 43269 | G45: =SUM(G38:G44) -> 47324 | I45: =SUM(I38:I44) -> 62568 | J45: =SUM(J38:J44) -> 50588 | K45: =SUM(K38:K44) -> 49263 | L45: =SUM(L38:L44) -> 50407 | M45: =SUM(M38:M44) -> 48314 | N45: =SUM(N38:N44) -> 43356 | O45: =SUM(O38:O44) -> 43811 | P45: =SUM(P38:P44) -> 43269 | ... W45: =SUM(W38:W44) -> 51731 | Y45: =SUM(Y38:Y44) -> 48314 | Z45: =SUM(Z38:Z44) -> 43356 | AA45: =SUM(AA38:AA44) -> 43811 | AB45: =SUM(AB38:AB44) -> 43269 | AC45: =SUM(AC38:AC44) -> 42608 | AD45: =SUM(AD38:AD44) -> 50829 | AE45: =SUM(AE38:AE44) -> 46137 | AF45: =SUM(AF38:AF44) -> 47324 | ... AI45: =SUM(AI38:AI44) -> 51731 | AK45: =SUM(AI45/AE45)-1 -> 0.12124759
B47: Property, plant and equipment | C47: 56584 | D47: 63245 | E47: 80860 | F47: 96647 | G47: 107919 | I47: 66718 | J47: 71660 | K47: 75763 | L47: =E47 -> 80860 | M47: 85734 | N47: 90945 | O47: 93352 | P47: =F47 -> 96647 | Q47: 99924 | R47: 103398 | S47: 104248 | T47: =G47 -> 107919 | U47: 109763 | V47: 109510 | W47: 105047 | Y47: =M47 -> 85734 | Z47: =N47 -> 90945 | AA47: =O47 -> 93352 | AB47: =P47 -> 96647 | AC47: =Q47 -> 99924 | AD47: =R47 -> 103398 | AE47: =S47 -> 104248 | AF47: =T47 -> 107919 | ... AI47: =W47 -> 105047 | AK47: =SUM(AI47/AE47)-1 -> 0.0076644156
B48: Marketable equity securities | C48: 5152 | D48: 6298 | E48: 5912 | F48: 5829 | G48: 5383 | I48: 6036 | J48: 5929 | K48: 5822 | L48: =E48 -> 5912 | M48: 6029 | N48: 5893 | O48: 5700 | P48: =F48 -> 5829 | Q48: 6139 | R48: 5824 | S48: 5496 | T48: =G48 -> 5383 | U48: 5027 | V48: 5383 | W48: 8667 | Y48: =M48 -> 6029 | Z48: =N48 -> 5893 | AA48: =O48 -> 5700 | AB48: =P48 -> 5829 | AC48: =Q48 -> 6139 | AD48: =R48 -> 5824 | AE48: =S48 -> 5496 | AF48: =T48 -> 5383 | ... AI48: =W48 -> 8667 | AK48: =SUM(AI48/AE48)-1 -> 0.57696507
B49: Other long-term investments | C49: 2192 | D49: 840 | E49: 0 | F49: 0 | G49: 0 | I49: 0 | J49: 0 | K49: 0 | L49: =E49 -> 0 | M49: 0 | N49: 0 | O49: 0 | P49: =F49 -> 0 | Q49: 0 | R49: 0 | S49: 0 | T49: =G49 -> 0 | U49: 0 | V49: 0 | W49: 0 | Y49: =M49 -> 0 | Z49: =N49 -> 0 | AA49: =O49 -> 0 | AB49: =P49 -> 0 | AC49: =Q49 -> 0 | AD49: =R49 -> 0 | AE49: =S49 -> 0 | AF49: =T49 -> 0 | ... AI49: =W49 -> 0 | AK49: =SUM(AI49/AE49)-1 -> #DIV/0!
B50: Goodwill & intangibles | C50: 35997 | D50: 26963 | E50: 27591 | F50: 27591 | G50: 24693 | I50: 27011 | J50: 27587 | K50: 27591 | L50: =E50 -> 27591 | M50: 27591 | N50: 27591 | O50: 27591 | P50: =F50 -> 27591 | Q50: 27440 | R50: 27442 | S50: 24680 | T50: =G50 -> 24693 | U50: 24693 | V50: 23912 | W50: 23912 | Y50: =M50 -> 27591 | Z50: =N50 -> 27591 | AA50: =O50 -> 27591 | AB50: =P50 -> 27591 | AC50: =Q50 -> 27440 | AD50: =R50 -> 27442 | AE50: =S50 -> 24680 | AF50: =T50 -> 24693 | ... AI50: =W50 -> 23912 | AK50: =SUM(AI50/AE50)-1 -> -0.031118314
B51: Other long-term assets | C51: 5917 | D51: 13342 | E51: 17333 | F51: 18236 | G51: 11166 | I51: 14023 | J51: 14654 | K51: 16402 | L51: =E51 -> 17333 | M51: 17635 | N51: 17844 | O51: 18383 | P51: =F51 -> 18236 | Q51: 16622 | R51: 18712 | S51: 12981 | T51: =G51 -> 11166 | U51: 10625 | V51: 10340 | W51: 15157 | Y51: =M51 -> 17635 | Z51: =N51 -> 17844 | AA51: =O51 -> 18383 | AB51: =P51 -> 18236 | AC51: =Q51 -> 16622 | AD51: =R51 -> 18712 | AE51: =S51 -> 12981 | AF51: =T51 -> 11166 | ... AI51: =W51 -> 15157 | AK51: =SUM(AI51/AE51)-1 -> 0.16762961
B52: Total Assets | C52: =SUM(C47:C51)+C45 -> 153091 | D52: =SUM(D47:D51)+D45 -> 168406 | E52: =SUM(E47:E51)+E45 -> 182103 | F52: =SUM(F47:F51)+F45 -> 191572 | G52: =SUM(G47:G51)+G45 -> 196485 | I52: =SUM(I47:I51)+I45 -> 176356 | J52: =SUM(J47:J51)+J45 -> 170418 | K52: =SUM(K47:K51)+K45 -> 174841 | L52: =SUM(L47:L51)+L45 -> 182103 | M52: =SUM(M47:M51)+M45 -> 185303 | N52: =SUM(N47:N51)+N45 -> 185629 | O52: =SUM(O47:O51)+O45 -> 188837 | P52: =SUM(P47:P51)+P45 -> 191572 | ... W52: =SUM(W47:W51)+W45 -> 204514 | Y52: =SUM(Y47:Y51)+Y45 -> 185303 | Z52: =SUM(Z47:Z51)+Z45 -> 185629 | AA52: =SUM(AA47:AA51)+AA45 -> 188837 | AB52: =SUM(AB47:AB51)+AB45 -> 191572 | AC52: =SUM(AC47:AC51)+AC45 -> 192733 | AD52: =SUM(AD47:AD51)+AD45 -> 206205 | AE52: =SUM(AE47:AE51)+AE45 -> 193542 | AF52: =SUM(AF47:AF51)+AF45 -> 196485 | ... AI52: =SUM(AI47:AI51)+AI45 -> 204514 | AK52: =SUM(AI52/AE52)-1 -> 0.056690537
B54: Short-term debt | C54: 2504 | D54: 4591 | E54: 4367 | F54: 2288 | G54: 3729 | I54: 4459 | J54: 2882 | K54: 2283 | L54: =E54 -> 4367 | M54: 1437 | N54: 2711 | O54: 2288 | P54: =F54 -> 2288 | Q54: 4581 | R54: 4695 | S54: 3765 | T54: =G54 -> 3729 | U54: 5240 | V54: 6731 | W54: 2496 | Y54: =M54 -> 1437 | Z54: =N54 -> 2711 | AA54: =O54 -> 2288 | AB54: =P54 -> 2288 | AC54: =Q54 -> 4581 | AD54: =R54 -> 4695 | AE54: =S54 -> 3765 | AF54: =T54 -> 3729 | ... AI54: =W54 -> 2496 | AK54: =SUM(AI54/AE54)-1 -> -0.33705179
B55: Accounts payable | C55: 5581 | D55: 5747 | E55: 9595 | F55: 8578 | G55: 12556 | I55: 7210 | J55: 7945 | K55: 7133 | L55: =E55 -> 9595 | M55: 8083 | N55: 8757 | O55: 8669 | P55: =F55 -> 8578 | Q55: 8559 | R55: 9618 | S55: 11074 | T55: =G55 -> 12556 | U55: 10896 | V55: 10666 | W55: 10268 | Y55: =M55 -> 8083 | Z55: =N55 -> 8757 | AA55: =O55 -> 8669 | AB55: =P55 -> 8578 | AC55: =Q55 -> 8559 | AD55: =R55 -> 9618 | AE55: =S55 -> 11074 | AF55: =T55 -> 12556 | ... AI55: =W55 -> 10268 | AK55: =SUM(AI55/AE55)-1 -> -0.072783096
B56: Accrued compensation and benefits | C56: 3999 | D56: 4535 | E56: 4084 | F56: 3655 | G56: 3343 | I56: 2731 | J56: 2730 | K56: 3421 | L56: =E56 -> 4084 | M56: 2497 | N56: 2887 | O56: 3115 | P56: =F56 -> 3655 | Q56: 2506 | R56: 2651 | S56: 5015 | T56: =G56 -> 3343 | U56: 2652 | V56: 4249 | W56: 3756 | Y56: =M56 -> 2497 | Z56: =N56 -> 2887 | AA56: =O56 -> 3115 | AB56: =P56 -> 3655 | AC56: =Q56 -> 2506 | AD56: =R56 -> 2651 | AE56: =S56 -> 5015 | AF56: =T56 -> 3343 | ... AI56: =W56 -> 3756 | AK56: =SUM(AI56/AE56)-1 -> -0.25104686
B57: Accrued advertising | C57: 0 | D57: 0 | E57: 0 | F57: 0 | G57: 0 | I57: 0 | J57: 0 | K57: 0 | L57: =E57 -> 0 | M57: 0 | N57: 0 | O57: 0 | P57: =F57 -> 0 | Q57: 0 | R57: 0 | S57: 0 | T57: =G57 -> 0 | U57: 0 | V57: 0 | W57: 0 | Y57: =M57 -> 0 | Z57: =N57 -> 0 | AA57: =O57 -> 0 | AB57: =P57 -> 0 | AC57: =Q57 -> 0 | AD57: =R57 -> 0 | AE57: =S57 -> 0 | AF57: =T57 -> 0 | ... AI57: =W57 -> 0 | AK57: =SUM(AI57/AE57)-1 -> #DIV/0!
B58: Deferred income on shipments to disti | C58: 0 | D58: 0 | E58: 0 | F58: 0 | G58: 0 | I58: 0 | J58: 0 | K58: 0 | L58: =E58 -> 0 | M58: 0 | N58: 0 | O58: 0 | P58: =F58 -> 0 | Q58: 0 | R58: 0 | S58: 0 | T58: =G58 -> 0 | U58: 0 | V58: 0 | W58: 0 | Y58: =M58 -> 0 | Z58: =N58 -> 0 | AA58: =O58 -> 0 | AB58: =P58 -> 0 | AC58: =Q58 -> 0 | AD58: =R58 -> 0 | AE58: =S58 -> 0 | AF58: =T58 -> 0 | ... AI58: =W58 -> 0 | AK58: =SUM(AI58/AE58)-1 -> #DIV/0!
B59: Income taxes payable | C59: 0 | D59: 0 | E59: 0 | F59: 1107 | G59: 1756 | I59: 0 | J59: 0 | K59: 0 | L59: =E59 -> 0 | M59: 0 | N59: 0 | O59: 0 | P59: =F59 -> 1107 | Q59: 346 | R59: 1856 | S59: 2440 | T59: =G59 -> 1756 | U59: 1873 | V59: 887 | W59: 825 | Y59: =M59 -> 0 | Z59: =N59 -> 0 | AA59: =O59 -> 0 | AB59: =P59 -> 1107 | AC59: =Q59 -> 346 | AD59: =R59 -> 1856 | AE59: =S59 -> 2440 | AF59: =T59 -> 1756 | ... AI59: =W59 -> 825 | AK59: =SUM(AI59/AE59)-1 -> -0.66188525
B60: Other accrued liabilities | C60: 12670 | D60: 12589 | E60: 14109 | F60: 12425 | G60: 14282 | I60: 14922 | J60: 13661 | K60: 14976 | L60: =E60 -> 14109 | M60: 15376 | N60: 12825 | O60: 14542 | P60: =F60 -> 12425 | Q60: 11221 | R60: 13207 | S60: 12865 | T60: =G60 -> 14282 | U60: 11513 | V60: 12433 | W60: 14952 | Y60: =M60 -> 15376 | Z60: =N60 -> 12825 | AA60: =O60 -> 14542 | AB60: =P60 -> 12425 | AC60: =Q60 -> 11221 | AD60: =R60 -> 13207 | AE60: =S60 -> 12865 | AF60: =T60 -> 14282 | ... AI60: =W60 -> 14952 | AK60: =SUM(AI60/AE60)-1 -> 0.16222309
B61: Total Current Liabilities | C61: =SUM(C54:C60) -> 24754 | D61: =SUM(D54:D60) -> 27462 | E61: =SUM(E54:E60) -> 32155 | F61: =SUM(F54:F60) -> 28053 | G61: =SUM(G54:G60) -> 35666 | I61: =SUM(I54:I60) -> 29322 | J61: =SUM(J54:J60) -> 27218 | K61: =SUM(K54:K60) -> 27813 | L61: =SUM(L54:L60) -> 32155 | M61: =SUM(M54:M60) -> 27393 | N61: =SUM(N54:N60) -> 27180 | O61: =SUM(O54:O60) -> 28614 | P61: =SUM(P54:P60) -> 28053 | ... W61: =SUM(W54:W60) -> 32297 | Y61: =SUM(Y54:Y60) -> 27393 | Z61: =SUM(Z54:Z60) -> 27180 | AA61: =SUM(AA54:AA60) -> 28614 | AB61: =SUM(AB54:AB60) -> 28053 | AC61: =SUM(AC54:AC60) -> 27213 | AD61: =SUM(AD54:AD60) -> 32027 | AE61: =SUM(AE54:AE60) -> 35159 | AF61: =SUM(AF54:AF60) -> 35666 | ... AI61: =SUM(AI54:AI60) -> 32297 | AK61: =SUM(AI61/AE61)-1 -> -0.081401633
B63: Long-term debt | C63: 33897 | D63: 33510 | E63: 37684 | F63: 46978 | G63: 46282 | I63: 32788 | J63: 32548 | K63: 37240 | L63: =E63 -> 37684 | M63: 48836 | N63: 46335 | O63: 46591 | P63: =F63 -> 46978 | Q63: 47869 | R63: 48334 | S63: 46471 | T63: =G63 -> 46282 | U63: 44911 | V63: 44026 | W63: 44057 | Y63: =M63 -> 48836 | Z63: =N63 -> 46335 | AA63: =O63 -> 46591 | AB63: =P63 -> 46978 | AC63: =Q63 -> 47869 | AD63: =R63 -> 48334 | AE63: =S63 -> 46471 | AF63: =T63 -> 46282 | ... AI63: =W63 -> 44057 | AK63: =SUM(AI63/AE63)-1 -> -0.051946375
B64: Long-term deferred tax liabilities | C64: 3843 | D64: 2667 | E64: 202 | F64: 0 | G64: 0 | I64: 1547 | J64: 572 | K64: 361 | L64: =E64 -> 202 | M64: 0 | N64: 0 | O64: 0 | P64: =F64 -> 0 | Q64: 0 | R64: 0 | S64: 0 | T64: =G64 -> 0 | U64: 0 | V64: 0 | W64: 0 | Y64: =M64 -> 0 | Z64: =N64 -> 0 | AA64: =O64 -> 0 | AB64: =P64 -> 0 | AC64: =Q64 -> 0 | AD64: =R64 -> 0 | AE64: =S64 -> 0 | AF64: =T64 -> 0 | ... AI64: =W64 -> 0 | AK64: =SUM(AI64/AE64)-1 -> #DIV/0!
B65: Other long-term liabilities | C65: 9559 | D65: 9376 | E65: 8776 | F65: 6576 | G65: 9505 | I65: 9563 | J65: 8862 | K65: 9542 | L65: =E65 -> 8776 | M65: 8671 | N65: 7643 | O65: 7946 | P65: =F65 -> 6576 | Q65: 6895 | R65: 5410 | S65: 7048 | T65: =G65 -> 9505 | U65: 8744 | V65: 7777 | W65: 11430 | Y65: =M65 -> 8671 | Z65: =N65 -> 7643 | AA65: =O65 -> 7946 | AB65: =P65 -> 6576 | AC65: =Q65 -> 6895 | AD65: =R65 -> 5410 | AE65: =S65 -> 7048 | AF65: =T65 -> 9505 | ... AI65: =W65 -> 11430 | AK65: =SUM(AI65/AE65)-1 -> 0.62173666
B66: Total Liabilities | C66: =SUM(C63:C65)+C61 -> 72053 | D66: =SUM(D63:D65)+D61 -> 73015 | E66: =SUM(E63:E65)+E61 -> 78817 | F66: =SUM(F63:F65)+F61 -> 81607 | G66: =SUM(G63:G65)+G61 -> 91453 | I66: =SUM(I63:I65)+I61 -> 73220 | J66: =SUM(J63:J65)+J61 -> 69200 | K66: =SUM(K63:K65)+K61 -> 74956 | L66: =SUM(L63:L65)+L61 -> 78817 | M66: =SUM(M63:M65)+M61 -> 84900 | N66: =SUM(N63:N65)+N61 -> 81158 | O66: =SUM(O63:O65)+O61 -> 83151 | P66: =SUM(P63:P65)+P61 -> 81607 | ... W66: =SUM(W63:W65)+W61 -> 87784 | Y66: =SUM(Y63:Y65)+Y61 -> 84900 | Z66: =SUM(Z63:Z65)+Z61 -> 81158 | AA66: =SUM(AA63:AA65)+AA61 -> 83151 | AB66: =SUM(AB63:AB65)+AB61 -> 81607 | AC66: =SUM(AC63:AC65)+AC61 -> 81977 | AD66: =SUM(AD63:AD65)+AD61 -> 85771 | AE66: =SUM(AE63:AE65)+AE61 -> 88678 | AF66: =SUM(AF63:AF65)+AF61 -> 91453 | ... AI66: =SUM(AI63:AI65)+AI61 -> 87784 | AK66: =SUM(AI66/AE66)-1 -> -0.010081418
B68: Preferred Stock | D68: 0 | E68: 0 | F68: 0 | G68: 0 | I68: 0 | J68: 0 | K68: 0 | L68: =E68 -> 0 | M68: 0 | N68: 0 | O68: 0 | P68: =F68 -> 0 | Q68: 0 | R68: 0 | S68: 0 | T68: =G68 -> 0 | U68: 0 | V68: 0 | W68: 0 | Y68: =M68 -> 0 | Z68: =N68 -> 0 | AA68: =O68 -> 0 | AB68: =P68 -> 0 | AC68: =Q68 -> 0 | AD68: =R68 -> 0 | AE68: =S68 -> 0 | AF68: =T68 -> 0 | ... AI68: =W68 -> 0 | AK68: =SUM(AI68/AE68)-1 -> #DIV/0!
B69: Common Stock | C69: 25556 | D69: 28006 | E69: 31580 | F69: 36649 | G69: 50949 | I69: 29244 | J69: 29858 | K69: 30912 | L69: =E69 -> 31580 | M69: 32829 | N69: 34330 | O69: 35653 | P69: =F69 -> 36649 | Q69: 38291 | R69: 49763 | S69: 50665 | T69: =G69 -> 50949 | U69: 51920 | V69: 52334 | W69: 56755 | Y69: =M69 -> 32829 | Z69: =N69 -> 34330 | AA69: =O69 -> 35653 | AB69: =P69 -> 36649 | AC69: =Q69 -> 38291 | AD69: =R69 -> 49763 | AE69: =S69 -> 50665 | AF69: =T69 -> 50949 | ... AI69: =W69 -> 56755 | AK69: =SUM(AI69/AE69)-1 -> 0.12020132
B70: Additional Paid-in Capital | C70: -751 | D70: -880 | E70: -562 | F70: -215 | G70: -711 | I70: -1002 | J70: -1625 | K70: -2051 | L70: =E70 -> -562 | M70: -419 | N70: -544 | O70: -861 | P70: =F70 -> -215 | Q70: -542 | R70: -696 | S70: -185 | T70: =G70 -> -711 | U70: -486 | V70: 65 | W70: 0 | Y70: =M70 -> -419 | Z70: =N70 -> -544 | AA70: =O70 -> -861 | AB70: =P70 -> -215 | AC70: =Q70 -> -542 | AD70: =R70 -> -696 | AE70: =S70 -> -185 | AF70: =T70 -> -711 | ... AI70: =W70 -> 0 | AK70: =SUM(AI70/AE70)-1 -> -1
B71: (Accumulated deficit) retained earnings | C71: 56233 | D71: 68265 | E71: 70405 | F71: 69156 | G71: 49032 | I71: 74894 | J71: 72985 | K71: 71024 | L71: =E71 -> 70405 | M71: 65649 | N71: 67231 | O71: 67021 | P71: =F71 -> 69156 | Q71: 68224 | R71: 66162 | S71: 49052 | T71: =G71 -> 49032 | U71: 48322 | V71: 45484 | W71: 49602 | Y71: =M71 -> 65649 | Z71: =N71 -> 67231 | AA71: =O71 -> 67021 | AB71: =P71 -> 69156 | AC71: =Q71 -> 68224 | AD71: =R71 -> 66162 | AE71: =S71 -> 49052 | AF71: =T71 -> 49032 | ... AI71: =W71 -> 49602 | AK71: =SUM(AI71/AE71)-1 -> 0.011212591
B72: Accumulated other comprehensive income (loss) | W72: 19 | Y72: =M72 -> 0 | Z72: =N72 -> 0 | AA72: =O72 -> 0 | AB72: =P72 -> 0 | AC72: =Q72 -> 0 | AD72: =R72 -> 0 | AE72: =S72 -> 0 | AF72: =T72 -> 0 | ... AI72: =W72 -> 19 | AK72: =SUM(AI72/AE72)-1 -> #DIV/0!
B73: Non-controlling interests | C73: 0 | D73: 0 | E73: 1863 | F73: 4375 | G73: 5762 | I73: 0 | J73: 0 | K73: 0 | L73: =E73 -> 1863 | M73: 2344 | N73: 3454 | O73: 3873 | P73: =F73 -> 4375 | Q73: 4783 | R73: 5205 | S73: 5332 | T73: =G73 -> 5762 | U73: 6657 | V73: 7868 | W73: 10354 | Y73: =M73 -> 2344 | Z73: =N73 -> 3454 | AA73: =O73 -> 3873 | AB73: =P73 -> 4375 | AC73: =Q73 -> 4783 | AD73: =R73 -> 5205 | AE73: =S73 -> 5332 | AF73: =T73 -> 5762 | ... AI73: =W73 -> 10354 | AK73: =SUM(AI73/AE73)-1 -> 0.94186047
B74: Total stockholders' equity | C74: =SUM(C68:C73) -> 81038 | D74: =SUM(D68:D73) -> 95391 | E74: =SUM(E68:E73) -> 103286 | F74: =SUM(F68:F73) -> 109965 | G74: =SUM(G68:G73) -> 105032 | I74: =SUM(I68:I73) -> 103136 | J74: =SUM(J68:J73) -> 101218 | K74: =SUM(K68:K73) -> 99885 | L74: =SUM(L68:L73) -> 103286 | M74: =SUM(M68:M73) -> 100403 | N74: =SUM(N68:N73) -> 104471 | O74: =SUM(O68:O73) -> 105686 | P74: =SUM(P68:P73) -> 109965 | ... W74: =SUM(W68:W73) -> 116730 | Y74: =SUM(Y68:Y73) -> 100403 | Z74: =SUM(Z68:Z73) -> 104471 | AA74: =SUM(AA68:AA73) -> 105686 | AB74: =SUM(AB68:AB73) -> 109965 | AC74: =SUM(AC68:AC73) -> 110756 | AD74: =SUM(AD68:AD73) -> 120434 | AE74: =SUM(AE68:AE73) -> 104864 | AF74: =SUM(AF68:AF73) -> 105032 | ... AI74: =SUM(AI68:AI73) -> 116730 | AK74: =SUM(AI74/AE74)-1 -> 0.11315609
B75: Total liabilities and stockholders' equity | C75: =SUM(C74+C66) -> 153091 | D75: =SUM(D74+D66) -> 168406 | E75: =SUM(E74+E66) -> 182103 | F75: =SUM(F74+F66) -> 191572 | G75: =SUM(G74+G66) -> 196485 | I75: =SUM(I74+I66) -> 176356 | J75: =SUM(J74+J66) -> 170418 | K75: =SUM(K74+K66) -> 174841 | L75: =SUM(L74+L66) -> 182103 | M75: =SUM(M74+M66) -> 185303 | N75: =SUM(N74+N66) -> 185629 | O75: =SUM(O74+O66) -> 188837 | P75: =SUM(P74+P66) -> 191572 | ... W75: =SUM(W74+W66) -> 204514 | Y75: =SUM(Y74+Y66) -> 185303 | Z75: =SUM(Z74+Z66) -> 185629 | AA75: =SUM(AA74+AA66) -> 188837 | AB75: =SUM(AB74+AB66) -> 191572 | AC75: =SUM(AC74+AC66) -> 192733 | AD75: =SUM(AD74+AD66) -> 206205 | AE75: =SUM(AE74+AE66) -> 193542 | AF75: =SUM(AF74+AF66) -> 196485 | ... AI75: =SUM(AI74+AI66) -> 204514 | AK75: =SUM(AI75/AE75)-1 -> 0.056690537
B77: Balance Check | C77: =C75-C52 -> 0 | D77: =D75-D52 -> 0 | E77: =E75-E52 -> 0 | F77: =F75-F52 -> 0 | G77: =G75-G52 -> 0 | I77: =I75-I52 -> 0 | J77: =J75-J52 -> 0 | K77: =K75-K52 -> 0 | L77: =L75-L52 -> 0 | M77: =M75-M52 -> 0 | N77: =N75-N52 -> 0 | O77: =O75-O52 -> 0 | P77: =P75-P52 -> 0 | ... W77: =W75-W52 -> 0 | Y77: =Y75-Y52 -> 0 | Z77: =Z75-Z52 -> 0 | AA77: =AA75-AA52 -> 0 | AB77: =AB75-AB52 -> 0 | AC77: =AC75-AC52 -> 0 | AD77: =AD75-AD52 -> 0 | AE77: =AE75-AE52 -> 0 | AF77: =AF75-AF52 -> 0 | ... AI77: =AI75-AI52 -> 0
A79: X | B79: Cash-Flows Statement
B81: Cash-Flows From Operating Activities
B82: Net income (loss) | C82: =C27 -> 20899 | D82: =D27 -> 19868 | E82: =E27 -> 8017 | F82: =F27 -> 1675 | G82: =G27 -> -19233 | I82: =I27 -> 8113 | J82: =J27 -> -454 | K82: =K27 -> 1019 | L82: =L27 -> -661 | M82: =M27 -> -2768 | N82: =N27 -> 1473 | O82: =O27 -> 310 | P82: =P27 -> 2660 | ... W82: =W27 -> 4270 | Y82: =SUM(J82:M82) -> -2864 | Z82: =SUM(K82:N82) -> -937 | AA82: =SUM(L82:O82) -> -1646 | AB82: =SUM(M82:P82) -> 1675 | AC82: =SUM(N82:Q82) -> 4006 | AD82: =SUM(O82:R82) -> 879 | AE82: =SUM(P82:S82) -> -16420 | AF82: =SUM(Q82:T82) -> -19233 | ... AI82: =SUM(T82:W82) -> 206
B84: Adjustments to reconcile net income:
B85: Depreciation | C85: 10482 | D85: 9953 | E85: 11128 | F85: 7847 | G85: 9951 | I85: 2847 | J85: =5528-I85 -> 2681 | K85: =8309-J85-I85 -> 2781 | L85: =SUM(E85-SUM(I85:K85)) -> 2819 | M85: 1901 | N85: =3733-M85 -> 1832 | O85: =5753-N85-M85 -> 2020 | P85: =SUM(F85-SUM(M85:O85)) -> 2094 | Q85: 2200 | R85: =4403-Q85 -> 2203 | S85: =7651-R85-Q85 -> 3248 | T85: =SUM(G85-SUM(Q85:S85)) -> 2300 | U85: 2425 | V85: =5213-U85 -> 2788 | W85: =7971-V85-U85 -> 2758 | Y85: =SUM(J85:M85) -> 10182 | Z85: =SUM(K85:N85) -> 9333 | AA85: =SUM(L85:O85) -> 8572 | AB85: =SUM(M85:P85) -> 7847 | AC85: =SUM(N85:Q85) -> 8146 | AD85: =SUM(O85:R85) -> 8517 | AE85: =SUM(P85:S85) -> 9745 | AF85: =SUM(Q85:T85) -> 9951 | ... AI85: =SUM(T85:W85) -> 10271
B86: Impairment of goodwill | C86: 0 | D86: 0 | E86: 0 | F86: 0 | G86: 0 | I86: 0 | J86: 0 | K86: 0 | L86: =SUM(E86-SUM(I86:K86)) -> 0 | M86: 0 | N86: 0 | O86: 0 | P86: =SUM(F86-SUM(M86:O86)) -> 0 | Q86: 0 | R86: 0 | S86: 0 | T86: =SUM(G86-SUM(Q86:S86)) -> 0 | U86: 0 | V86: 0 | W86: 0 | Y86: =SUM(J86:M86) -> 0 | Z86: =SUM(K86:N86) -> 0 | AA86: =SUM(L86:O86) -> 0 | AB86: =SUM(M86:P86) -> 0 | AC86: =SUM(N86:Q86) -> 0 | AD86: =SUM(O86:R86) -> 0 | AE86: =SUM(P86:S86) -> 0 | AF86: =SUM(Q86:T86) -> 0 | ... AI86: =SUM(T86:W86) -> 0
B87: Amortization of goodwill | C87: 0 | D87: 0 | E87: 0 | F87: 0 | G87: 0 | I87: 0 | J87: 0 | K87: 0 | L87: =SUM(E87-SUM(I87:K87)) -> 0 | M87: 0 | N87: 0 | O87: 0 | P87: =SUM(F87-SUM(M87:O87)) -> 0 | Q87: 0 | R87: 0 | S87: 0 | T87: =SUM(G87-SUM(Q87:S87)) -> 0 | U87: 0 | V87: 0 | W87: 0 | Y87: =SUM(J87:M87) -> 0 | Z87: =SUM(K87:N87) -> 0 | AA87: =SUM(L87:O87) -> 0 | AB87: =SUM(M87:P87) -> 0 | AC87: =SUM(N87:Q87) -> 0 | AD87: =SUM(O87:R87) -> 0 | AE87: =SUM(P87:S87) -> 0 | AF87: =SUM(Q87:T87) -> 0 | ... AI87: =SUM(T87:W87) -> 0
B88: Share-based compensation | C88: 1854 | D88: 2036 | E88: 3128 | F88: 3229 | G88: 3410 | I88: 707 | J88: =1599-I88 -> 892 | K88: =2392-J88-I88 -> 793 | L88: =SUM(E88-SUM(I88:K88)) -> 736 | M88: 739 | N88: =1661-M88 -> 922 | O88: =2433-N88-M88 -> 772 | P88: =SUM(F88-SUM(M88:O88)) -> 796 | Q88: 1179 | R88: =1959-Q88 -> 780 | S88: =2759-R88-Q88 -> 800 | T88: =SUM(G88-SUM(Q88:S88)) -> 651 | U88: 684 | V88: =1348-U88 -> 664 | W88: =1896-V88-U88 -> 548 | Y88: =SUM(J88:M88) -> 3160 | Z88: =SUM(K88:N88) -> 3190 | AA88: =SUM(L88:O88) -> 3169 | AB88: =SUM(M88:P88) -> 3229 | AC88: =SUM(N88:Q88) -> 3669 | AD88: =SUM(O88:R88) -> 3527 | AE88: =SUM(P88:S88) -> 3555 | AF88: =SUM(Q88:T88) -> 3410 | ... AI88: =SUM(T88:W88) -> 2547
B89: Restructuring, asset impairment, etc. | C89: 0 | D89: 2626 | E89: 1074 | F89: -424 | G89: 3491 | I89: 17 | J89: =73-I89 -> 56 | K89: =665-J89-I89 -> 592 | L89: =SUM(E89-SUM(I89:K89)) -> 409 | M89: 55 | N89: =255-M89 -> 200 | O89: =718-N89-M89 -> 463 | P89: =SUM(F89-SUM(M89:O89)) -> -1142 | Q89: 348 | R89: =1291-Q89 -> 943 | S89: =3626-R89-Q89 -> 2335 | T89: =SUM(G89-SUM(Q89:S89)) -> -135 | U89: 0 | V89: =382-U89 -> 382 | W89: =372-V89-U89 -> -10 | Y89: =SUM(J89:M89) -> 1112 | Z89: =SUM(K89:N89) -> 1256 | AA89: =SUM(L89:O89) -> 1127 | AB89: =SUM(M89:P89) -> -424 | AC89: =SUM(N89:Q89) -> -131 | AD89: =SUM(O89:R89) -> 612 | AE89: =SUM(P89:S89) -> 2484 | AF89: =SUM(Q89:T89) -> 3491 | ... AI89: =SUM(T89:W89) -> 237
B90: Amortization of debt discount | C90: 0 | D90: 0 | E90: 0 | F90: 0 | G90: 0 | I90: 0 | J90: 0 | K90: 0 | L90: =SUM(E90-SUM(I90:K90)) -> 0 | M90: 0 | N90: 0 | O90: 0 | P90: =SUM(F90-SUM(M90:O90)) -> 0 | Q90: 0 | R90: 0 | S90: 0 | T90: =SUM(G90-SUM(Q90:S90)) -> 0 | U90: 0 | V90: 0 | W90: 0 | Y90: =SUM(J90:M90) -> 0 | Z90: =SUM(K90:N90) -> 0 | AA90: =SUM(L90:O90) -> 0 | AB90: =SUM(M90:P90) -> 0 | AC90: =SUM(N90:Q90) -> 0 | AD90: =SUM(O90:R90) -> 0 | AE90: =SUM(P90:S90) -> 0 | AF90: =SUM(Q90:T90) -> 0 | ... AI90: =SUM(T90:W90) -> 0
B91: Excess tax benefit from stock comp | C91: 0 | D91: 0 | E91: 0 | F91: 0 | G91: 0 | I91: 0 | J91: 0 | K91: 0 | L91: =SUM(E91-SUM(I91:K91)) -> 0 | M91: 0 | N91: 0 | O91: 0 | P91: =SUM(F91-SUM(M91:O91)) -> 0 | Q91: 0 | R91: 0 | S91: 0 | T91: =SUM(G91-SUM(Q91:S91)) -> 0 | U91: 0 | V91: 0 | W91: 0 | Y91: =SUM(J91:M91) -> 0 | Z91: =SUM(K91:N91) -> 0 | AA91: =SUM(L91:O91) -> 0 | AB91: =SUM(M91:P91) -> 0 | AC91: =SUM(N91:Q91) -> 0 | AD91: =SUM(O91:R91) -> 0 | AE91: =SUM(P91:S91) -> 0 | AF91: =SUM(Q91:T91) -> 0 | ... AI91: =SUM(T91:W91) -> 0
B92: Amortization of intangibles, acquisition costs | C92: 1757 | D92: 1839 | E92: 1907 | F92: 1755 | G92: 1428 | I92: 501 | J92: =968-I92 -> 467 | K92: =1439-J92-I92 -> 471 | L92: =SUM(E92-SUM(I92:K92)) -> 468 | M92: 465 | N92: =909-M92 -> 444 | O92: =1336-N92-M92 -> 427 | P92: =SUM(F92-SUM(M92:O92)) -> 419 | Q92: 351 | R92: =717-Q92 -> 366 | S92: =1081-R92-Q92 -> 364 | T92: =SUM(G92-SUM(Q92:S92)) -> 347 | U92: 249 | V92: =474-U92 -> 225 | W92: =708-V92-U92 -> 234 | Y92: =SUM(J92:M92) -> 1871 | Z92: =SUM(K92:N92) -> 1848 | AA92: =SUM(L92:O92) -> 1804 | AB92: =SUM(M92:P92) -> 1755 | AC92: =SUM(N92:Q92) -> 1641 | AD92: =SUM(O92:R92) -> 1563 | AE92: =SUM(P92:S92) -> 1500 | AF92: =SUM(Q92:T92) -> 1428 | ... AI92: =SUM(T92:W92) -> 1055
B93: Purchased in-process R&D | C93: 0 | D93: 0 | E93: 0 | F93: 0 | G93: 0 | I93: 0 | J93: 0 | K93: 0 | L93: =SUM(E93-SUM(I93:K93)) -> 0 | M93: 0 | N93: 0 | O93: 0 | P93: =SUM(F93-SUM(M93:O93)) -> 0 | Q93: 0 | R93: 0 | S93: 0 | T93: =SUM(G93-SUM(Q93:S93)) -> 0 | U93: 0 | V93: 0 | W93: 0 | Y93: =SUM(J93:M93) -> 0 | Z93: =SUM(K93:N93) -> 0 | AA93: =SUM(L93:O93) -> 0 | AB93: =SUM(M93:P93) -> 0 | AC93: =SUM(N93:Q93) -> 0 | AD93: =SUM(O93:R93) -> 0 | AE93: =SUM(P93:S93) -> 0 | AF93: =SUM(Q93:T93) -> 0 | ... AI93: =SUM(T93:W93) -> 0
B94: (Gains) losses on equity method investments | C94: -1757 | D94: -1458 | E94: -4254 | F94: -42 | G94: -246 | I94: -4325 | J94: =-4230-I94 -> 95 | K94: =-4075-J94-I94 -> 155 | L94: =SUM(E94-SUM(I94:K94)) -> -179 | M94: -167 | N94: =-146-M94 -> 21 | O94: =47-N94-M94 -> 193 | P94: =SUM(F94-SUM(M94:O94)) -> -89 | Q94: -208 | R94: =-84-Q94 -> 124 | S94: =75-R94-Q94 -> 159 | T94: =SUM(G94-SUM(Q94:S94)) -> -321 | U94: 112 | V94: =-390-U94 -> -502 | W94: =-611-V94-U94 -> -221 | Y94: =SUM(J94:M94) -> -96 | Z94: =SUM(K94:N94) -> -170 | AA94: =SUM(L94:O94) -> -132 | AB94: =SUM(M94:P94) -> -42 | AC94: =SUM(N94:Q94) -> -83 | AD94: =SUM(O94:R94) -> 20 | AE94: =SUM(P94:S94) -> -14 | AF94: =SUM(Q94:T94) -> -246 | ... AI94: =SUM(T94:W94) -> -932
B95: (Gains) losses on other equity investments | C95: 0 | D95: 0 | E95: 0 | F95: 0 | G95: 0 | I95: 0 | J95: 0 | K95: 0 | L95: =SUM(E95-SUM(I95:K95)) -> 0 | M95: 0 | N95: 0 | O95: 0 | P95: =SUM(F95-SUM(M95:O95)) -> 0 | Q95: 0 | R95: 0 | S95: 0 | T95: =SUM(G95-SUM(Q95:S95)) -> 0 | U95: 0 | V95: 0 | W95: 0 | Y95: =SUM(J95:M95) -> 0 | Z95: =SUM(K95:N95) -> 0 | AA95: =SUM(L95:O95) -> 0 | AB95: =SUM(M95:P95) -> 0 | AC95: =SUM(N95:Q95) -> 0 | AD95: =SUM(O95:R95) -> 0 | AE95: =SUM(P95:S95) -> 0 | AF95: =SUM(Q95:T95) -> 0 | ... AI95: =SUM(T95:W95) -> 0
B96: (Gains) losses on divestitures | C96: -30 | D96: 0 | E96: -1059 | F96: 0 | G96: 0 | I96: -1121 | J96: =-1072-I96 -> 49 | K96: =-1072-J96-I96 -> 0 | L96: =SUM(E96-SUM(I96:K96)) -> 13 | M96: 0 | N96: =0-M96 -> 0 | O96: 0 | P96: =SUM(F96-SUM(M96:O96)) -> 0 | Q96: 0 | R96: 0 | S96: 0 | T96: =SUM(G96-SUM(Q96:S96)) -> 0 | U96: 0 | V96: 0 | W96: =-5355-V96-U96 -> -5355 | Y96: =SUM(J96:M96) -> 62 | Z96: =SUM(K96:N96) -> 13 | AA96: =SUM(L96:O96) -> 13 | AB96: =SUM(M96:P96) -> 0 | AC96: =SUM(N96:Q96) -> 0 | AD96: =SUM(O96:R96) -> 0 | AE96: =SUM(P96:S96) -> 0 | AF96: =SUM(Q96:T96) -> 0 | ... AI96: =SUM(T96:W96) -> -5355
B97: Deferred taxes | C97: 0 | D97: 0 | E97: 0 | F97: 0 | G97: 6132 | I97: 0 | J97: 0 | K97: 0 | L97: =SUM(E97-SUM(I97:K97)) -> 0 | M97: 0 | N97: 0 | O97: 0 | P97: =SUM(F97-SUM(M97:O97)) -> 0 | Q97: 0 | R97: 0 | S97: =6368-R97-Q97 -> 6368 | T97: =SUM(G97-SUM(Q97:S97)) -> -236 | U97: 19 | V97: =106-U97 -> 87 | W97: =123-V97-U97 -> 17 | Y97: =SUM(J97:M97) -> 0 | Z97: =SUM(K97:N97) -> 0 | AA97: =SUM(L97:O97) -> 0 | AB97: =SUM(M97:P97) -> 0 | AC97: =SUM(N97:Q97) -> 0 | AD97: =SUM(O97:R97) -> 0 | AE97: =SUM(P97:S97) -> 6368 | AF97: =SUM(Q97:T97) -> 6132 | ... AI97: =SUM(T97:W97) -> -113
B98: Other | C98: 0 | D98: 0 | E98: 0 | F98: 0 | G98: 2252 | I98: 0 | J98: 0 | K98: 0 | L98: =SUM(E98-SUM(I98:K98)) -> 0 | M98: 0 | N98: 0 | O98: 0 | P98: =SUM(F98-SUM(M98:O98)) -> 0 | Q98: 0 | R98: 0 | S98: =2290-R98-Q98 -> 2290 | T98: =SUM(G98-SUM(Q98:S98)) -> -38 | U98: 0 | V98: =482-U98 -> 482 | W98: =465+1687-V98-U98 -> 1670 | Y98: =SUM(J98:M98) -> 0 | Z98: =SUM(K98:N98) -> 0 | AA98: =SUM(L98:O98) -> 0 | AB98: =SUM(M98:P98) -> 0 | AC98: =SUM(N98:Q98) -> 0 | AD98: =SUM(O98:R98) -> 0 | AE98: =SUM(P98:S98) -> 2290 | AF98: =SUM(Q98:T98) -> 2252 | ... AI98: =SUM(T98:W98) -> 2114
B100: Changes in assets and liabilities:
B101: Trading assets | C101: 0 | D101: 0 | E101: 0 | F101: 0 | G101: 0 | I101: 0 | J101: 0 | K101: 0 | L101: =SUM(E101-SUM(I101:K101)) -> 0 | M101: 0 | N101: 0 | O101: 0 | P101: =SUM(F101-SUM(M101:O101)) -> 0 | Q101: 0 | R101: 0 | S101: 0 | T101: =SUM(G101-SUM(Q101:S101)) -> 0 | U101: 0 | V101: 0 | W101: 0 | Y101: =SUM(J101:M101) -> 0 | Z101: =SUM(K101:N101) -> 0 | AA101: =SUM(L101:O101) -> 0 | AB101: =SUM(M101:P101) -> 0 | AC101: =SUM(N101:Q101) -> 0 | AD101: =SUM(O101:R101) -> 0 | AE101: =SUM(P101:S101) -> 0 | AF101: =SUM(Q101:T101) -> 0 | ... AI101: =SUM(T101:W101) -> 0
B102: Accounts receivable | C102: 883 | D102: -2674 | E102: 5327 | F102: 731 | G102: -75 | I102: 2384 | J102: =3397-I102 -> 1013 | K102: =1991-J102-I102 -> -1406 | L102: =SUM(E102-SUM(I102:K102)) -> 3336 | M102: 286 | N102: =1137-M102 -> 851 | O102: =1290-N102-M102 -> 153 | P102: =SUM(F102-SUM(M102:O102)) -> -559 | Q102: 80 | R102: =272-Q102 -> 192 | S102: =282-R102-Q102 -> 10 | T102: =SUM(G102-SUM(Q102:S102)) -> -357 | U102: 414 | V102: =1004-U102 -> 590 | W102: =162-V102-U102 -> -842 | Y102: =SUM(J102:M102) -> 3229 | Z102: =SUM(K102:N102) -> 3067 | AA102: =SUM(L102:O102) -> 4626 | AB102: =SUM(M102:P102) -> 731 | AC102: =SUM(N102:Q102) -> 525 | AD102: =SUM(O102:R102) -> -134 | AE102: =SUM(P102:S102) -> -277 | AF102: =SUM(Q102:T102) -> -75 | ... AI102: =SUM(T102:W102) -> -195
B103: Inventories | C103: -687 | D103: -2339 | E103: -2436 | F103: 2097 | G103: -1105 | I103: -1147 | J103: =-1386-I103 -> -239 | K103: =-2043-J103-I103 -> -657 | L103: =SUM(E103-SUM(I103:K103)) -> -393 | M103: 231 | N103: =1240-M103 -> 1009 | O103: =1758-N103-M103 -> 518 | P103: =SUM(F103-SUM(M103:O103)) -> 339 | Q103: -366 | R103: =-116-Q103 -> 250 | S103: =-969-R103-Q103 -> -853 | T103: =SUM(G103-SUM(Q103:S103)) -> -136 | U103: -83 | V103: =99-U103 -> 182 | W103: =-9-V103-U103 -> -108 | Y103: =SUM(J103:M103) -> -1058 | Z103: =SUM(K103:N103) -> 190 | AA103: =SUM(L103:O103) -> 1365 | AB103: =SUM(M103:P103) -> 2097 | AC103: =SUM(N103:Q103) -> 1500 | AD103: =SUM(O103:R103) -> 741 | AE103: =SUM(P103:S103) -> -630 | AF103: =SUM(Q103:T103) -> -1105 | ... AI103: =SUM(T103:W103) -> -145
B104: Accounts payable | C104: 412 | D104: 1190 | E104: -29 | F104: -801 | G104: 634 | I104: -128 | J104: =117-I104 -> 245 | K104: =-485-J104-I104 -> -602 | L104: =SUM(E104-SUM(I104:K104)) -> 456 | M104: -771 | N104: =-1102-M104 -> -331 | O104: =-1082-N104-M104 -> 20 | P104: =SUM(F104-SUM(M104:O104)) -> 281 | Q104: -386 | R104: =184-Q104 -> 570 | S104: =566-R104-Q104 -> 382 | T104: =SUM(G104-SUM(Q104:S104)) -> 68 | U104: -240 | V104: =114-U104 -> 354 | W104: =-281-V104-U104 -> -395 | Y104: =SUM(J104:M104) -> -672 | Z104: =SUM(K104:N104) -> -1248 | AA104: =SUM(L104:O104) -> -626 | AB104: =SUM(M104:P104) -> -801 | AC104: =SUM(N104:Q104) -> -416 | AD104: =SUM(O104:R104) -> 485 | AE104: =SUM(P104:S104) -> 847 | AF104: =SUM(Q104:T104) -> 634 | ... AI104: =SUM(T104:W104) -> -213
B105: Accrued compensation and benefits | C105: 463 | D105: 515 | E105: -1533 | F105: -614 | G105: -218 | I105: -1884 | J105: =-1985-I105 -> -101 | K105: =-1912-J105-I105 -> 73 | L105: =SUM(E105-SUM(I105:K105)) -> 379 | M105: -1560 | N105: =-1340-M105 -> 220 | O105: =-1171-N105-M105 -> 169 | P105: =SUM(F105-SUM(M105:O105)) -> 557 | Q105: -1289 | R105: =-1309-Q105 -> -20 | S105: =1384-R105-Q105 -> 2693 | T105: =SUM(G105-SUM(Q105:S105)) -> -1602 | U105: -741 | V105: =1022-U105 -> 1763 | W105: =541-V105-U105 -> -481 | Y105: =SUM(J105:M105) -> -1209 | Z105: =SUM(K105:N105) -> -888 | AA105: =SUM(L105:O105) -> -792 | AB105: =SUM(M105:P105) -> -614 | AC105: =SUM(N105:Q105) -> -343 | AD105: =SUM(O105:R105) -> -583 | AE105: =SUM(P105:S105) -> 1941 | AF105: =SUM(Q105:T105) -> -218 | ... AI105: =SUM(T105:W105) -> -1061
B106: Cust. deposits & prepaid supply agreements | C106: -181 | D106: -1583 | E106: -24 | F106: 0 | G106: 0 | I106: -6 | J106: =-12-I106 -> -6 | K106: =-18-J106-I106 -> -6 | L106: =SUM(E106-SUM(I106:K106)) -> -6 | P106: =SUM(F106-SUM(M106:O106)) -> 0 | R106: 0 | S106: 0 | T106: =SUM(G106-SUM(Q106:S106)) -> 0 | U106: 0 | V106: 0 | W106: 0 | Y106: =SUM(J106:M106) -> -18 | Z106: =SUM(K106:N106) -> -12 | AA106: =SUM(L106:O106) -> -6 | AB106: =SUM(M106:P106) -> 0 | AC106: =SUM(N106:Q106) -> 0 | AD106: =SUM(O106:R106) -> 0 | AE106: =SUM(P106:S106) -> 0 | AF106: =SUM(Q106:T106) -> 0 | ... AI106: =SUM(T106:W106) -> 0
B107: Income taxes payable and receivable | C107: 1620 | D107: -441 | E107: -4535 | F107: -3531 | G107: -356 | I107: 1219 | J107: =-2232-I107 -> -3451 | K107: =-4062-J107-I107 -> -1830 | L107: =SUM(E107-SUM(I107:K107)) -> -473 | M107: 1344 | N107: =-2186-M107 -> -3530 | O107: =-2676-N107-M107 -> -490 | P107: =SUM(F107-SUM(M107:O107)) -> -855 | Q107: -591 | R107: =-2174-Q107 -> -1583 | S107: =-930-R107-Q107 -> 1244 | T107: =SUM(G107-SUM(Q107:S107)) -> 574 | U107: 67 | V107: =-1338-U107 -> -1405 | W107: =-1196-V107-U107 -> 142 | Y107: =SUM(J107:M107) -> -4410 | Z107: =SUM(K107:N107) -> -4489 | AA107: =SUM(L107:O107) -> -3149 | AB107: =SUM(M107:P107) -> -3531 | AC107: =SUM(N107:Q107) -> -5466 | AD107: =SUM(O107:R107) -> -3519 | AE107: =SUM(P107:S107) -> -1785 | AF107: =SUM(Q107:T107) -> -356 | ... AI107: =SUM(T107:W107) -> -622
B108: Other assets and liabilities | C108: -331 | D108: 459 | E108: -1278 | F108: -451 | G108: 2223 | I108: -1286 | J108: =-1724-I108 -> -438 | K108: =-2077-J108-I108 -> -353 | L108: =SUM(E108-SUM(I108:K108)) -> 799 | M108: -1540 | N108: =-1843-M108 -> -303 | O108: =-574-N108-M108 -> 1269 | P108: =SUM(F108-SUM(M108:O108)) -> 123 | Q108: -2104 | R108: =-1983-Q108 -> 121 | S108: =20-R108-Q108 -> 2003 | T108: =SUM(G108-SUM(Q108:S108)) -> 2203 | U108: -1206 | V108: =-1742-U108 -> -536 | W108: =-1423-V108-U108 -> 319 | Y108: =SUM(J108:M108) -> -1532 | Z108: =SUM(K108:N108) -> -1397 | AA108: =SUM(L108:O108) -> 225 | AB108: =SUM(M108:P108) -> -451 | AC108: =SUM(N108:Q108) -> -1015 | AD108: =SUM(O108:R108) -> -591 | AE108: =SUM(P108:S108) -> 143 | AF108: =SUM(Q108:T108) -> 2223 | ... AI108: =SUM(T108:W108) -> 780
B109: Net cash used in operating activities | C109: =SUM(C82:C108) -> 35384 | D109: =SUM(D82:D108) -> 29991 | E109: =SUM(E82:E108) -> 15433 | F109: =SUM(F82:F108) -> 11471 | G109: =SUM(G82:G108) -> 8288 | I109: =SUM(I82:I108) -> 5891 | J109: =SUM(J82:J108) -> 809 | K109: =SUM(K82:K108) -> 1030 | L109: =SUM(L82:L108) -> 7703 | M109: =SUM(M82:M108) -> -1785 | N109: =SUM(N82:N108) -> 2808 | O109: =SUM(O82:O108) -> 5824 | P109: =SUM(P82:P108) -> 4624 | ... W109: =SUM(W82:W108) -> 2546 | Y109: =SUM(Y82:Y108) -> 7757 | Z109: =SUM(Z82:Z108) -> 9756 | AA109: =SUM(AA82:AA108) -> 14550 | AB109: =SUM(AB82:AB108) -> 11471 | AC109: =SUM(AC82:AC108) -> 12033 | AD109: =SUM(AD82:AD108) -> 11517 | AE109: =SUM(AE82:AE108) -> 9747 | AF109: =SUM(AF82:AF108) -> 8288 | ... AI109: =SUM(AI82:AI108) -> 8574
B111: Cash flows from investing activities:
B112: Additions to property, plant and equipment | C112: -14259 | D112: -18733 | E112: -24844 | F112: -25750 | G112: -23944 | I112: -4604 | J112: =-11846-I112 -> -7242 | K112: =-19145-J112-I112 -> -7299 | L112: =SUM(E112-SUM(I112:K112)) -> -5699 | M112: -7413 | N112: =-13301-M112 -> -5888 | O112: =-19054-N112-M112 -> -5753 | P112: =SUM(F112-SUM(M112:O112)) -> -6696 | Q112: -5970 | R112: =-11652-Q112 -> -5682 | S112: =-18110-R112-Q112 -> -6458 | T112: =SUM(G112-SUM(Q112:S112)) -> -5834 | U112: -5183 | V112: =-8733-U112 -> -3550 | W112: =-11158-V112-U112 -> -2425 | Y112: =SUM(J112:M112) -> -27653 | Z112: =SUM(K112:N112) -> -26299 | AA112: =SUM(L112:O112) -> -24753 | AB112: =SUM(M112:P112) -> -25750 | AC112: =SUM(N112:Q112) -> -24307 | AD112: =SUM(O112:R112) -> -24101 | AE112: =SUM(P112:S112) -> -24806 | AF112: =SUM(Q112:T112) -> -23944 | ... AI112: =SUM(T112:W112) -> -16992
B113: Acquisitions, net of cash acquired | C113: 0 | D113: 0 | E113: 0 | F113: 0 | G113: -82 | I113: 0 | J113: 0 | K113: 0 | L113: =SUM(E113-SUM(I113:K113)) -> 0 | M113: 0 | N113: 0 | O113: 0 | P113: =SUM(F113-SUM(M113:O113)) -> 0 | Q113: 0 | R113: 0 | S113: 0 | T113: =SUM(G113-SUM(Q113:S113)) -> -82 | U113: 0 | V113: 0 | W113: 0 | Y113: =SUM(J113:M113) -> 0 | Z113: =SUM(K113:N113) -> 0 | AA113: =SUM(L113:O113) -> 0 | AB113: =SUM(M113:P113) -> 0 | AC113: =SUM(N113:Q113) -> 0 | AD113: =SUM(O113:R113) -> 0 | AE113: =SUM(P113:S113) -> 0 | AF113: =SUM(Q113:T113) -> -82 | ... AI113: =SUM(T113:W113) -> -82
B114: Proceeds from divestitures | C114: 123 | D114: -1596 | E114: 6579 | F114: 0 | G114: 0 | I114: =6544-193 -> 6351 | J114: =6579-206-I114 -> 22 | K114: =6579-J114-I114 -> 206 | L114: =SUM(E114-SUM(I114:K114)) -> 0 | M114: 0 | N114: 0 | O114: 0 | P114: =SUM(F114-SUM(M114:O114)) -> 0 | Q114: 0 | R114: 0 | S114: 0 | T114: =SUM(G114-SUM(Q114:S114)) -> 0 | U114: 1935 | V114: =1935-U114 -> 0 | W114: =6186-V114-U114 -> 4251 | Y114: =SUM(J114:M114) -> 228 | Z114: =SUM(K114:N114) -> 206 | AA114: =SUM(L114:O114) -> 0 | AB114: =SUM(M114:P114) -> 0 | AC114: =SUM(N114:Q114) -> 0 | AD114: =SUM(O114:R114) -> 0 | AE114: =SUM(P114:S114) -> 0 | AF114: =SUM(Q114:T114) -> 0 | ... AI114: =SUM(T114:W114) -> 6186
B115: Purchases of available-for-sale investments | C115: -6862 | D115: -5051 | E115: -510 | F115: -44414 | G115: -37940 | I115: 0 | J115: 0 | K115: 0 | L115: =SUM(E115-SUM(I115:K115)) -> -510 | M115: -16132 | N115: =-25696-M115 -> -9564 | O115: =-37287-N115-M115 -> -11591 | P115: =SUM(F115-SUM(M115:O115)) -> -7127 | Q115: -6460 | R115: =-17634-Q115 -> -11174 | S115: =-31519-R115-Q115 -> -13885 | T115: =SUM(G115-SUM(Q115:S115)) -> -6421 | U115: -3386 | V115: =-5730-U115 -> -2344 | W115: =-16401-V115-U115 -> -10671 | Y115: =SUM(J115:M115) -> -16642 | Z115: =SUM(K115:N115) -> -26206 | AA115: =SUM(L115:O115) -> -37797 | AB115: =SUM(M115:P115) -> -44414 | AC115: =SUM(N115:Q115) -> -34742 | AD115: =SUM(O115:R115) -> -36352 | AE115: =SUM(P115:S115) -> -38646 | AF115: =SUM(Q115:T115) -> -37940 | ... AI115: =SUM(T115:W115) -> -22822
B116: Maturities and sales of investments | C116: 6781 | D116: 6467 | E116: 4961 | F116: 44077 | G116: 41463 | I116: 10490 | J116: =25407-I116 -> 14917 | K116: =4880-J116-I116 -> -20527 | L116: =SUM(E116-SUM(I116:K116)) -> 81 | M116: 14173 | N116: =26957-M116 -> 12784 | O116: =36725-N116-M116 -> 9768 | P116: =SUM(F116-SUM(M116:O116)) -> 7352 | Q116: 9598 | R116: =17214-Q116 -> 7616 | S116: =34268-R116-Q116 -> 17054 | T116: =SUM(G116-SUM(Q116:S116)) -> 7195 | U116: 5327 | V116: =8575-U116 -> 3248 | W116: =10964-V116-U116 -> 2389 | Y116: =SUM(J116:M116) -> 8644 | Z116: =SUM(K116:N116) -> 6511 | AA116: =SUM(L116:O116) -> 36806 | AB116: =SUM(M116:P116) -> 44077 | AC116: =SUM(N116:Q116) -> 39502 | AD116: =SUM(O116:R116) -> 34334 | AE116: =SUM(P116:S116) -> 41620 | AF116: =SUM(Q116:T116) -> 41463 | ... AI116: =SUM(T116:W116) -> 18159
B117: Purchases of trading assets | C117: -22377 | D117: -35503 | E117: -43647 | F117: -399 | G117: 0 | I117: -19091 | J117: =-25514-I117 -> -6423 | K117: =-31669-J117-I117 -> -6155 | L117: =SUM(E117-SUM(I117:K117)) -> -11978 | M117: 0 | N117: 0 | O117: 0 | P117: =SUM(F117-SUM(M117:O117)) -> -399 | Q117: 0 | R117: 0 | S117: 0 | T117: =SUM(G117-SUM(Q117:S117)) -> 0 | U117: 0 | V117: 0 | W117: 0 | Y117: =SUM(J117:M117) -> -24556 | Z117: =SUM(K117:N117) -> -18133 | AA117: =SUM(L117:O117) -> -11978 | AB117: =SUM(M117:P117) -> -399 | AC117: =SUM(N117:Q117) -> -399 | AD117: =SUM(O117:R117) -> -399 | AE117: =SUM(P117:S117) -> -399 | AF117: =SUM(Q117:T117) -> 0 | ... AI117: =SUM(T117:W117) -> 0
B118: Maturities and sales of trading assets | C118: 15377 | D118: 28832 | E118: 48730 | F118: 472 | G118: 1047 | I118: 4682 | J118: =4775-I118 -> 93 | K118: =35129-J118-I118 -> 30354 | L118: =SUM(E118-SUM(I118:K118)) -> 13601 | M118: 116 | N118: =253-M118 -> 137 | O118: =375-N118-M118 -> 122 | P118: =SUM(F118-SUM(M118:O118)) -> 97 | Q118: 0 | R118: 0 | S118: 0 | T118: =SUM(G118-SUM(Q118:S118)) -> 1047 | U118: 0 | V118: 0 | W118: =642-V118-U118 -> 642 | Y118: =SUM(J118:M118) -> 44164 | Z118: =SUM(K118:N118) -> 44208 | AA118: =SUM(L118:O118) -> 13976 | AB118: =SUM(M118:P118) -> 472 | AC118: =SUM(N118:Q118) -> 356 | AD118: =SUM(O118:R118) -> 219 | AE118: =SUM(P118:S118) -> 97 | AF118: =SUM(Q118:T118) -> 1047 | ... AI118: =SUM(T118:W118) -> 1689
B119: Loans receivable | C119: 0 | D119: 0 | E119: 0 | F119: 0 | G119: 0 | I119: 0 | J119: 0 | K119: 0 | L119: =SUM(E119-SUM(I119:K119)) -> 0 | M119: 0 | N119: 0 | O119: 0 | P119: =SUM(F119-SUM(M119:O119)) -> 0 | Q119: 0 | R119: 0 | S119: 0 | T119: =SUM(G119-SUM(Q119:S119)) -> 0 | U119: 0 | V119: 0 | W119: 0 | Y119: =SUM(J119:M119) -> 0 | Z119: =SUM(K119:N119) -> 0 | AA119: =SUM(L119:O119) -> 0 | AB119: =SUM(M119:P119) -> 0 | AC119: =SUM(N119:Q119) -> 0 | AD119: =SUM(O119:R119) -> 0 | AE119: =SUM(P119:S119) -> 0 | AF119: =SUM(Q119:T119) -> 0 | ... AI119: =SUM(T119:W119) -> 0
B120: Investments in non-marketable equities | C120: 0 | D120: 0 | E120: 0 | F120: 0 | G120: 0 | I120: 0 | J120: 0 | K120: 0 | L120: =SUM(E120-SUM(I120:K120)) -> 0 | M120: 0 | N120: 0 | O120: 0 | P120: =SUM(F120-SUM(M120:O120)) -> 0 | Q120: 0 | R120: 0 | S120: 0 | T120: =SUM(G120-SUM(Q120:S120)) -> 0 | U120: 0 | V120: 0 | W120: 0 | Y120: =SUM(J120:M120) -> 0 | Z120: =SUM(K120:N120) -> 0 | AA120: =SUM(L120:O120) -> 0 | AB120: =SUM(M120:P120) -> 0 | AC120: =SUM(N120:Q120) -> 0 | AD120: =SUM(O120:R120) -> 0 | AE120: =SUM(P120:S120) -> 0 | AF120: =SUM(Q120:T120) -> 0 | ... AI120: =SUM(T120:W120) -> 0
B121: Return of equity method investment | C121: 190 | D121: -613 | E121: 0 | F121: 0 | G121: 0 | I121: 0 | J121: 0 | K121: 0 | L121: =SUM(E121-SUM(I121:K121)) -> 0 | M121: 0 | N121: 0 | O121: 0 | P121: =SUM(F121-SUM(M121:O121)) -> 0 | Q121: 0 | R121: 0 | S121: 0 | T121: =SUM(G121-SUM(Q121:S121)) -> 0 | U121: 0 | V121: 0 | W121: 0 | Y121: =SUM(J121:M121) -> 0 | Z121: =SUM(K121:N121) -> 0 | AA121: =SUM(L121:O121) -> 0 | AB121: =SUM(M121:P121) -> 0 | AC121: =SUM(N121:Q121) -> 0 | AD121: =SUM(O121:R121) -> 0 | AE121: =SUM(P121:S121) -> 0 | AF121: =SUM(Q121:T121) -> 0 | ... AI121: =SUM(T121:W121) -> 0
...

Sheet 3-Statement Model
C2: ="Financial Statement Model for "&D5 -> Financial Statement Model for Intel
C3: $ in thousands except per share
C5: Company name | D5: Intel | I5: Select an operating scenario: | L5: Base case
C6: Ticker | D6: INTC
C7: Circ break 1=off, 0=on | D7: 1
C8: Latest closing share price | D8: 293.65
C9: Latest closing share price date | D9: =NOW() -> 45956.565
C10: Latest fiscal year end date | D10: ='Base Financials'!G4 -> 45654
C11: Shares outstanding (millions) | D11: =4377*1000 -> 4377000
C13: INCOME STATEMENT
C14: Fiscal year | D14: =E14-1 -> 2021 | E14: =F14-1 -> 2022 | F14: =G14-1 -> 2023 | G14: =YEAR(D10) -> 2024 | H14: =G14+1 -> 2025 | I14: =H14+1 -> 2026 | J14: =I14+1 -> 2027 | K14: =J14+1 -> 2028 | L14: =K14+1 -> 2029
C15: Fiscal year end date | D15: =EOMONTH(E15,-12) -> 44561 | E15: =EOMONTH(F15,-12) -> 44926 | F15: =EOMONTH(G15,-12) -> 45291 | G15: =D10 -> 45654 | H15: =EOMONTH(G15,12) -> 46022 | I15: =EOMONTH(H15,12) -> 46387 | J15: =EOMONTH(I15,12) -> 46752 | K15: =EOMONTH(J15,12) -> 47118 | L15: =EOMONTH(K15,12) -> 47483 | N15: Comments
C17: Revenue | D17: ='Base Financials'!D8 -> 79024 | E17: ='Base Financials'!E8 -> 63054 | F17: ='Base Financials'!F8 -> 54228 | G17: ='Base Financials'!G8 -> 53101 | H17: =G17*(1+H37) -> 52038.98 | I17: =H17*(1+I37) -> 53652.188 | J17: =I17*(1+J37) -> 56012.885 | K17: =J17*(1+K37) -> 58813.529 | L17: =K17*(1+L37) -> 61401.324 | N17: Street Consensus
C18: (-) Cost of sales | D18: ='Base Financials'!C11 -> -34255 | E18: ='Base Financials'!D11 -> -35209 | F18: ='Base Financials'!E11 -> -36188 | G18: ='Base Financials'!F11 -> -32517 | H18: =H19-H17 -> -33334.745 | I18: =I19-I17 -> -33413.323 | J18: =J19-J17 -> -32691.279 | K18: =K19-K17 -> -34325.843 | L18: =L19-L17 -> -35836.18 | N18: Plug = Revenue - Gross Profit
C19: Gross Profit | D19: =SUM(D17:D18) -> 44769 | E19: =SUM(E17:E18) -> 27845 | F19: =SUM(F17:F18) -> 18040 | G19: =SUM(G17:G18) -> 20584 | H19: =H17*H38 -> 18704.235 | I19: =I17*I38 -> 20238.865 | J19: =J17*J38 -> 23321.605 | K19: =K17*K38 -> 24487.686 | L19: =L17*L38 -> 25565.144 | N19: Revenue x Gross Profit Margin forecast
C20: (-) Research & Development (R&D) | D20: ='Base Financials'!D16 -> -15190 | E20: ='Base Financials'!E16 -> -17528 | F20: ='Base Financials'!F16 -> -16046 | G20: ='Base Financials'!G16 -> -16546 | H20: =-H39*H17 -> -13826.648 | I20: =-I39*I17 -> -13168.534 | J20: =-J39*J17 -> -13210.932 | K20: =-K39*K17 -> -13871.479 | L20: =-L39*L17 -> -14481.824 | N20: Street Consensus
C21: (-) Marketing, General, and Administrative (MG&A) | D21: ='Base Financials'!D15 -> -6543 | E21: ='Base Financials'!E15 -> -7002 | F21: ='Base Financials'!F15 -> -5634 | G21: ='Base Financials'!G15 -> -5507 | H21: =-H17*H40 -> -4627.383 | I21: =-I17*I40 -> -4772.3425 | J21: =-J17*J40 -> -4880.1244 | K21: =-K17*K40 -> -5124.1307 | L21: =-L17*L40 -> -5349.5924 | N21: Street Consensus
C22: (-) Restructuring and Other Charges | D22: ='Base Financials'!D17 -> -2626 | E22: ='Base Financials'!E17 -> -2 | F22: ='Base Financials'!F17 -> 62 | G22: ='Base Financials'!G17 -> -6970 | H22: =AVERAGE(D22:G22) -> -2384 | I22: =H22 -> -2384 | J22: =I22 -> -2384 | K22: =J22 -> -2384 | L22: =K22 -> -2384 | N22: Average of Historical
C23: Operating profit (EBIT) | D23: =D19+D20+D21+D22 -> 20410 | E23: =E19+E20+E21+E22 -> 3313 | F23: =F19+F20+F21+F22 -> -3578 | G23: =G19+G20+G21+G22 -> -8439 | H23: =H19+H20+H21+H22 -> -2133.7956 | I23: =I19+I20+I21+I22 -> -86.011305 | J23: =J19+J20+J21+J22 -> 2846.5489 | K23: =K19+K20+K21+K22 -> 3108.0764 | L23: =L19+L20+L21+L22 -> 3349.7277 | N23: Gross Profit - R&D - SG&A
C24: (+) Interest income | D24: 144 | E24: 589 | F24: 1335 | G24: 1245 | H24: =H169 -> 0 | I24: =I169 -> 0 | J24: =J169 -> 0 | K24: =K169 -> 0 | L24: =L169 -> 0 | N24: Reference from interest on cash schedule
C25: (-) Interest expense | D25: -597 | E25: -496 | F25: -878 | G25: -1034 | H25: =-H155 -> #REF! | I25: =-I155 -> #REF! | J25: =-J155 -> #REF! | K25: =-K155 -> #REF! | L25: =-L155 -> #REF! | N25: Reference from interest expense schedule
C26: (-) Other expense, net | D26: -29 | E26: 1073 | F26: 172 | G26: 15 | H26: =G26 -> 15 | I26: =H26 -> 15 | J26: =I26 -> 15 | K26: =J26 -> 15 | L26: =K26 -> 15 | N26: Straight-line
C27: Pretax profit | D27: =SUM(D23:D26) -> 19928 | E27: =SUM(E23:E26) -> 4479 | F27: =SUM(F23:F26) -> -2949 | G27: =SUM(G23:G26) -> -8213 | H27: =SUM(H23:H26) -> #REF! | I27: =SUM(I23:I26) -> #REF! | J27: =SUM(J23:J26) -> #REF! | K27: =SUM(K23:K26) -> #REF! | L27: =SUM(L23:L26) -> #REF! | N27: EBIT + interest income less interest expense less other expense
C28: (-) Taxes | D28: ='Base Financials'!D26 -> -1835 | E28: ='Base Financials'!E26 -> 249 | F28: ='Base Financials'!F26 -> 913 | G28: ='Base Financials'!G26 -> -8023 | H28: =-H41*H27 -> #REF! | I28: =-I41*I27 -> #REF! | J28: =-J41*J27 -> #REF! | K28: =-K41*K27 -> #REF! | L28: =-L41*L27 -> #REF! | N28: Street Consensus
C29: Net income | D29: =SUM(D27:D28) -> 18093 | E29: =SUM(E27:E28) -> 4728 | F29: =SUM(F27:F28) -> -2036 | G29: =SUM(G27:G28) -> -16236 | H29: =SUM(H27:H28) -> #REF! | I29: =SUM(I27:I28) -> #REF! | J29: =SUM(J27:J28) -> #REF! | K29: =SUM(K27:K28) -> #REF! | L29: =SUM(L27:L28) -> #REF! | N29: Pre-tax Profit less taxes
C31: Depreciation & amortization | D31: ='Base Financials'!D85+'Base Financials'!D92 -> 11792 | E31: ='Base Financials'!E85+'Base Financials'!E92 -> 13035 | F31: ='Base Financials'!F85+'Base Financials'!F92 -> 9602 | G31: ='Base Financials'!G85+'Base Financials'!G92 -> 11379 | H31: =H119 -> 11151.42 | I31: =I119 -> 11737.114 | J31: =J119 -> 12482.987 | K31: =K119 -> 13323.136 | L31: =L119 -> 14117.674 | N31: Reference from D&A schedule
C32: EBITDA | D32: =D23+D31 -> 32202 | E32: =E23+E31 -> 16348 | F32: =F23+F31 -> 6024 | G32: =G23+G31 -> 2940 | H32: =H23+H31 -> 9017.6244 | I32: =I23+I31 -> 11651.103 | J32: =J23+J31 -> 15329.536 | K32: =K23+K31 -> 16431.213 | L32: =L23+L31 -> 17467.402 | N32: EBIT + D&A
C33: Stock based compensation | D33: ='Base Financials'!D88 -> 2036 | E33: ='Base Financials'!E88 -> 3128 | F33: ='Base Financials'!F88 -> 3229 | G33: ='Base Financials'!G88 -> 3410 | H33: =G33*(1+H37) -> 3341.8 | I33: =H33*(1+I37) -> 3445.3958 | J33: =I33*(1+J37) -> 3596.9932 | K33: =J33*(1+K37) -> 3776.8429 | L33: =K33*(1+L37) -> 3943.024 | N33: WSP assumption: grow SBC in-line with revenue growth
C34: Adjusted EBITDA | D34: =SUM(D32:D33) -> 34238 | E34: =SUM(E32:E33) -> 19476 | F34: =SUM(F32:F33) -> 9253 | G34: =SUM(G32:G33) -> 6350 | H34: =SUM(H32:H33) -> 12359.424 | I34: =SUM(I32:I33) -> 15096.499 | J34: =SUM(J32:J33) -> 18926.529 | K34: =SUM(K32:K33) -> 20208.056 | L34: =SUM(L32:L33) -> 21410.426 | N34: EBITDA + Stock-based compensation
C36: Growth rates & margins
C37: Revenue growth | E37: =E17/D17-1 -> -0.2020905 | F37: =F17/E17-1 -> -0.13997526 | G37: =G17/F17-1 -> -0.020782622 | H37: ='Street Consensus'!C21 -> -0.02 | I37: ='Street Consensus'!D21 -> 0.031 | J37: ='Street Consensus'!E21 -> 0.044 | K37: ='Street Consensus'!F21 -> 0.05 | L37: ='Street Consensus'!G21 -> 0.044 | N37: Consensus estimates through 2021; straight-line growth rate thereafter
C38: Gross profit margin | D38: =D19/D17 -> 0.56652409 | E38: =E19/E17 -> 0.44160561 | F38: =F19/F17 -> 0.33266947 | G38: =G19/G17 -> 0.38763865 | H38: ='Street Consensus'!C38 -> 0.3594274 | I38: ='Street Consensus'!D38 -> 0.37722348 | J38: ='Street Consensus'!E38 -> 0.41636144 | K38: ='Street Consensus'!F38 -> 0.41636144 | L38: ='Street Consensus'!G38 -> 0.41636144 | N38: Straight line last historical year
C39: R&D % of sales | D39: =-D20/D17 -> 0.19222009 | E39: =-E20/E17 -> 0.27798395 | F39: =-F20/F17 -> 0.2958988 | G39: =-G20/G17 -> 0.31159489 | H39: ='Street Consensus'!C44 -> 0.26569791 | I39: ='Street Consensus'!D44 -> 0.24544262 | J39: ='Street Consensus'!E44 -> 0.23585523 | K39: ='Street Consensus'!F44 -> 0.23585523 | L39: ='Street Consensus'!G44 -> 0.23585523 | N39: Straight line last historical year
C40: SG&A % of sales | D40: =-D21/D17 -> 0.082797631 | E40: =-E21/E17 -> 0.11104767 | F40: =-F21/F17 -> 0.10389467 | G40: =-G21/G17 -> 0.10370803 | H40: ='Street Consensus'!C50 -> 0.088921477 | I40: ='Street Consensus'!D50 -> 0.088949633 | J40: ='Street Consensus'!E50 -> 0.087125033 | K40: ='Street Consensus'!F50 -> 0.087125033 | L40: ='Street Consensus'!G50 -> 0.087125033 | N40: Straight line last historical year
C41: Tax rate | D41: =-(D28/D27) -> 0.092081493 | E41: =-(E28/E27) -> -0.055592766 | F41: =-(F28/F27) -> 0.30959647 | G41: =-(G28/G27) -> -0.97686594 | H41: ='Street Consensus'!C55 -> 0.12 | I41: ='Street Consensus'!D55 -> 0.12 | J41: ='Street Consensus'!E55 -> 0.12 | K41: ='Street Consensus'!F55 -> 0.12 | L41: ='Street Consensus'!G55 -> 0.12 | N41: Straight line last historical year
C43: BALANCE SHEET
C44: =C14 -> Fiscal year | D44: =D14 -> 2021 | E44: =E14 -> 2022 | F44: =F14 -> 2023 | G44: =G14 -> 2024 | H44: =H14 -> 2025 | I44: =I14 -> 2026 | J44: =J14 -> 2027 | ... L44: =L14 -> 2029
C45: =C15 -> Fiscal year end date | D45: =D15 -> 44561 | E45: =E15 -> 44926 | F45: =F15 -> 45291 | G45: =G15 -> 45654 | H45: =H15 -> 46022 | I45: =I15 -> 46387 | J45: =J15 -> 46752 | ... L45: =L15 -> 47483
C47: Cash & equivalents, ST Marketable Securities | D47: =+SUM('Base Financials'!D38+'Base Financials'!D39) -> 6930 | E47: =+SUM('Base Financials'!E38+'Base Financials'!E39) -> 11144 | F47: =+SUM('Base Financials'!F38+'Base Financials'!F39) -> 7079 | G47: =+SUM('Base Financials'!G38+'Base Financials'!G39) -> 8249 | H47: =H103+G47 -> #REF! | I47: =I103+H47 -> #REF! | J47: =J103+I47 -> #REF! | K47: =K103+J47 -> #REF! | L47: =L103+K47 -> #REF! | N47: Reference from 'net change in cash' line on the cash flow statement
C48: Trading Assets | D48: ='Base Financials'!D40 -> 21483 | E48: ='Base Financials'!E40 -> 17194 | F48: ='Base Financials'!F40 -> 17955 | G48: ='Base Financials'!G40 -> 13813 | H48: =G48*(1+H37) -> 13536.74 | I48: =H48*(1+I37) -> 13956.379 | J48: =I48*(1+J37) -> 14570.46 | K48: =J48*(1+K37) -> 15298.983 | L48: =K48*(1+L37) -> 15972.138 | N48: Grow in-line with revenue growth
C49: Accounts receivable | D49: ='Base Financials'!D41 -> 9457 | E49: ='Base Financials'!E41 -> 4133 | F49: ='Base Financials'!F41 -> 3402 | G49: ='Base Financials'!G41 -> 3478 | H49: =G49*(1+H37) -> 3408.44 | I49: =H49*(1+I37) -> 3514.1016 | J49: =I49*(1+J37) -> 3668.7221 | K49: =J49*(1+K37) -> 3852.1582 | L49: =K49*(1+L37) -> 4021.6532 | N49: Grow in-line with revenue growth
C50: Inventories | D50: ='Base Financials'!D42 -> 10776 | E50: ='Base Financials'!E42 -> 13224 | F50: ='Base Financials'!F42 -> 11127 | G50: ='Base Financials'!G42 -> 12198 | H50: =G50*H18/G18 -> 12504.758 | I50: =H50*I18/H18 -> 12534.235 | J50: =I50*J18/I18 -> 12263.377 | K50: =J50*K18/J18 -> 12876.546 | L50: =K50*L18/K18 -> 13443.114 | N50: Grow in-line with cost of sales growth
C51: Other current assets | D51: ='Base Financials'!D43+'Base Financials'!D44 -> 9072 | E51: ='Base Financials'!E43+'Base Financials'!E44 -> 4712 | F51: ='Base Financials'!F43+'Base Financials'!F44 -> 3706 | G51: ='Base Financials'!G43+'Base Financials'!G44 -> 9586 | H51: =G51*(1+H37) -> 9394.28 | I51: =H51*(1+I37) -> 9685.5027 | J51: =I51*(1+J37) -> 10111.665 | K51: =J51*(1+K37) -> 10617.248 | L51: =K51*(1+L37) -> 11084.407 | N51: Grow in-line with revenue growth
C52: Total Current Assets | D52: =SUM(D47:D51) -> 57718 | E52: =SUM(E47:E51) -> 50407 | F52: =SUM(F47:F51) -> 43269 | G52: =SUM(G47:G51) -> 47324 | H52: =SUM(H47:H51) -> #REF! | I52: =SUM(I47:I51) -> #REF! | J52: =SUM(J47:J51) -> #REF! | K52: =SUM(K47:K51) -> #REF! | L52: =SUM(L47:L51) -> #REF!
C54: LT Marketable equity securities | D54: ='Base Financials'!D48 -> 6298 | E54: ='Base Financials'!E48 -> 5912 | F54: ='Base Financials'!F48 -> 5829 | G54: ='Base Financials'!G48 -> 5383 | H54: =G54 -> 5383 | I54: =H54 -> 5383 | J54: =I54 -> 5383 | K54: =J54 -> 5383 | L54: =K54 -> 5383 | N54: Reference from 'net change in cash' line on the cash flow statement
C55: Goodwill & intangibles | D55: ='Base Financials'!D50 -> 26963 | E55: ='Base Financials'!E50 -> 27591 | F55: ='Base Financials'!F50 -> 27591 | G55: ='Base Financials'!G50 -> 24693 | H55: =G55*H18/G18 -> 25313.985 | I55: =H55*I18/H18 -> 25373.657 | J55: =I55*J18/I18 -> 24825.345 | K55: =J55*K18/J18 -> 26066.613 | L55: =K55*L18/K18 -> 27213.544 | N55: Grow in-line with cost of sales growth
C56: Property, plant & equipment | D56: ='Base Financials'!D47 -> 63245 | E56: ='Base Financials'!E47 -> 80860 | F56: ='Base Financials'!F47 -> 96647 | G56: ='Base Financials'!G47 -> 107919 | H56: =H112 -> 122577 | I56: =I112 -> 134337 | J56: =J112 -> 145857 | K56: =K112 -> 157137 | L56: =L112 -> 168177 | N56: Reference from PP&E schedule
C57: Other long-term assets | D57: ='Base Financials'!D49+'Base Financials'!D51 -> 14182 | E57: ='Base Financials'!E49+'Base Financials'!E51 -> 17333 | F57: ='Base Financials'!F49+'Base Financials'!F51 -> 18236 | G57: ='Base Financials'!G49+'Base Financials'!G51 -> 11166 | H57: =G57*(1+H37) -> 10942.68 | I57: =H57*(1+I37) -> 11281.903 | J57: =I57*(1+J37) -> 11778.307 | K57: =J57*(1+K37) -> 12367.222 | L57: =K57*(1+L37) -> 12911.38 | N57: Grow in-line with revenue growth
C58: Total Assets | D58: =SUM(D54:D57)+D52 -> 168406 | E58: =SUM(E54:E57)+E52 -> 182103 | F58: =SUM(F54:F57)+F52 -> 191572 | G58: =SUM(G54:G57)+G52 -> 196485 | H58: =SUM(H54:H57)+H52 -> #REF! | I58: =SUM(I54:I57)+I52 -> #REF! | J58: =SUM(J54:J57)+J52 -> #REF! | K58: =SUM(K54:K57)+K52 -> #REF! | L58: =SUM(L54:L57)+L52 -> #REF!
C60: Short-term debt (Commercial paper / revolver) | D60: ='Base Financials'!D54 -> 4591 | E60: ='Base Financials'!E54 -> 4367 | F60: ='Base Financials'!F54 -> 2288 | G60: ='Base Financials'!G54 -> 3729 | N60: Reference EOP balance from CP/revolver schedule
C61: Accounts payable | D61: ='Base Financials'!D55 -> 5747 | E61: ='Base Financials'!E55 -> 9595 | F61: ='Base Financials'!F55 -> 8578 | G61: ='Base Financials'!G55 -> 12556 | H61: =G61*(1+H30) -> 12556 | I61: =H61*(1+I30) -> 12556 | J61: =I61*(1+J30) -> 12556 | K61: =J61*(1+K30) -> 12556 | L61: =K61*(1+L30) -> 12556 | N61: Grow in-line with revenue growth
C62: Accrued compensation and benefits | D62: ='Base Financials'!D56 -> 4535 | E62: ='Base Financials'!E56 -> 4084 | F62: ='Base Financials'!F56 -> 3655 | G62: ='Base Financials'!G56 -> 3343 | H62: =G62*(1+H30) -> 3343 | I62: =H62*(1+I30) -> 3343 | J62: =I62*(1+J30) -> 3343 | K62: =J62*(1+K30) -> 3343 | L62: =K62*(1+L30) -> 3343 | N62: Grow in-line with revenue growth
C63: Other non current liabilities | D63: =SUM('Base Financials'!D57+'Base Financials'!D58+'Base Financials'!D59+'Base Financials'!D60) -> 12589 | E63: =SUM('Base Financials'!E57+'Base Financials'!E58+'Base Financials'!E59+'Base Financials'!E60) -> 14109 | F63: =SUM('Base Financials'!F57+'Base Financials'!F58+'Base Financials'!F59+'Base Financials'!F60) -> 13532 | G63: =SUM('Base Financials'!G57+'Base Financials'!G58+'Base Financials'!G59+'Base Financials'!G60) -> 16038 | H63: =G63*(1+H37) -> 15717.24 | I63: =H63*(1+I37) -> 16204.474 | J63: =I63*(1+J37) -> 16917.471 | K63: =J63*(1+K37) -> 17763.345 | L63: =K63*(1+L37) -> 18544.932 | N63: Reference EOP balance from CP/revolver schedule
C64: Total liabilities | D64: =SUM(D60:D63) -> 27462 | E64: =SUM(E60:E63) -> 32155 | F64: =SUM(F60:F63) -> 28053 | G64: =SUM(G60:G63) -> 35666 | H64: =SUM(H60:H63) -> 31616.24 | I64: =SUM(I60:I63) -> 32103.474 | J64: =SUM(J60:J63) -> 32816.471 | K64: =SUM(K60:K63) -> 33662.345 | L64: =SUM(L60:L63) -> 34443.932
C66: Long-term debt | D66: ='Base Financials'!D63 -> 33510 | E66: ='Base Financials'!E63 -> 37684 | F66: ='Base Financials'!F63 -> 46978 | G66: ='Base Financials'!G63 -> 46282 | H66: =G66*H18/G18 -> 47445.91 | I66: =H66*I18/H18 -> 47557.752 | J66: =I66*J18/I18 -> 46530.055 | K66: =J66*K18/J18 -> 48856.557 | L66: =K66*L18/K18 -> 51006.246 | N66: Grow in-line with cost of sales growth
C67: Long-term deferred tax liabilities | D67: ='Base Financials'!D64 -> 2667 | E67: ='Base Financials'!E64 -> 202 | F67: ='Base Financials'!F64 -> 0 | G67: ='Base Financials'!G64 -> 0 | H67: =G67*(1+H37) -> 0 | I67: =H67*(1+I37) -> 0 | J67: =I67*(1+J37) -> 0 | K67: =J67*(1+K37) -> 0 | L67: =K67*(1+L37) -> 0 | N67: Grow in-line with revenue growth
C68: Other long-term liabilities | D68: ='Base Financials'!D65 -> 9376 | E68: ='Base Financials'!E65 -> 8776 | F68: ='Base Financials'!F65 -> 6576 | G68: ='Base Financials'!G65 -> 9505 | H68: =G68*(1+H37) -> 9314.9 | I68: =H68*(1+I37) -> 9603.6619 | J68: =I68*(1+J37) -> 10026.223 | K68: =J68*(1+K37) -> 10527.534 | L68: =K68*(1+L37) -> 10990.746 | N68: Grow in-line with revenue growth
C69: Total liabilities | D69: =SUM(D66:D68)+D64 -> 73015 | E69: =SUM(E66:E68)+E64 -> 78817 | F69: =SUM(F66:F68)+F64 -> 81607 | G69: =SUM(G66:G68)+G64 -> 91453 | H69: =SUM(H66:H68)+H64 -> 88377.05 | I69: =SUM(I66:I68)+I64 -> 89264.889 | J69: =SUM(J66:J68)+J64 -> 89372.749 | K69: =SUM(K66:K68)+K64 -> 93046.436 | L69: =SUM(L66:L68)+L64 -> 96440.924
C71: Preferred Stock | D71: ='Base Financials'!D68 -> 0 | E71: ='Base Financials'!E68 -> 0 | F71: ='Base Financials'!F68 -> 0 | G71: ='Base Financials'!G68 -> 0 | H71: =G71 -> 0 | I71: =H71 -> 0 | J71: =I71 -> 0 | K71: =J71 -> 0 | L71: =K71 -> 0 | N71: Increase by stock-based compensation forecasted in the I/S section
C72: Common Stock | D72: ='Base Financials'!D69 -> 28006 | E72: ='Base Financials'!E69 -> 31580 | F72: ='Base Financials'!F69 -> 36649 | G72: ='Base Financials'!G69 -> 50949 | H72: =H132 -> #REF! | I72: =I132 -> #REF! | J72: =J132 -> #REF! | K72: =K132 -> #REF! | L72: =L132 -> #REF! | N72: Reference from Retained Earnings schedule
C73: Additional Paid-in Capital | D73: ='Base Financials'!D70 -> -880 | E73: ='Base Financials'!E70 -> -562 | F73: ='Base Financials'!F70 -> -215 | G73: ='Base Financials'!G70 -> -711 | H73: =G73 -> -711 | I73: =H73 -> -711 | J73: =I73 -> -711 | K73: =J73 -> -711 | L73: =K73 -> -711
C74: (Accumulated deficit) retained earnings | D74: ='Base Financials'!D71 -> 68265 | E74: ='Base Financials'!E71 -> 70405 | F74: ='Base Financials'!F71 -> 69156 | G74: ='Base Financials'!G71 -> 49032 | H74: =G74 -> 49032 | I74: =H74 -> 49032 | J74: =I74 -> 49032 | K74: =J74 -> 49032 | L74: =K74 -> 49032
C75: Accumulated other comprehensive income (loss) | D75: ='Base Financials'!D72 -> 0 | E75: ='Base Financials'!E72 -> 0 | F75: ='Base Financials'!F72 -> 0 | G75: ='Base Financials'!G72 -> 0 | H75: =G75 -> 0 | I75: =H75 -> 0 | J75: =I75 -> 0 | K75: =J75 -> 0 | L75: =K75 -> 0 | N75: WSP assumption: straight-line
C76: Non-controlling interests | D76: ='Base Financials'!D73 -> 0 | E76: ='Base Financials'!E73 -> 1863 | F76: ='Base Financials'!F73 -> 4375 | G76: ='Base Financials'!G73 -> 5762 | H76: =G76 -> 5762 | I76: =H76 -> 5762 | J76: =I76 -> 5762 | K76: =J76 -> 5762 | L76: =K76 -> 5762 | N76: WSP assumption: straight-line
C77: Total equity | D77: =SUM(D71:D76) -> 95391 | E77: =SUM(E71:E76) -> 103286 | F77: =SUM(F71:F76) -> 109965 | G77: =SUM(G71:G76) -> 105032 | H77: =SUM(H71:H76) -> #REF! | I77: =SUM(I71:I76) -> #REF! | J77: =SUM(J71:J76) -> #REF! | K77: =SUM(K71:K76) -> #REF! | L77: =SUM(L71:L76) -> #REF!
C79: Balance check | D79: =ROUND(D58-D69-D77,3) -> 0 | E79: =ROUND(E58-E69-E77,3) -> 0 | F79: =ROUND(F58-F69-F77,3) -> 0 | G79: =ROUND(G58-G69-G77,3) -> 0 | H79: =ROUND(H58-H69-H77,3) -> #REF! | I79: =ROUND(I58-I69-I77,3) -> #REF! | J79: =ROUND(J58-J69-J77,3) -> #REF! | K79: =ROUND(K58-K69-K77,3) -> #REF! | L79: =ROUND(L58-L69-L77,3) -> #REF!
C81: CASH FLOW STATEMENT
C82: =C14 -> Fiscal year | D82: =D14 -> 2021 | E82: =E14 -> 2022 | F82: =F14 -> 2023 | G82: =G14 -> 2024 | H82: =H14 -> 2025 | I82: =I14 -> 2026 | J82: =J14 -> 2027 | ... L82: =L14 -> 2029
C83: =C15 -> Fiscal year end date | D83: =D15 -> 44561 | E83: =E15 -> 44926 | F83: =F15 -> 45291 | G83: =G15 -> 45654 | H83: =H15 -> 46022 | I83: =I15 -> 46387 | J83: =J15 -> 46752 | ... L83: =L15 -> 47483
C85: Net income | D85: =D29 -> 18093 | E85: =E29 -> 4728 | F85: =F29 -> -2036 | G85: =G29 -> -16236 | H85: =H29 -> #REF! | I85: =I29 -> #REF! | J85: =J29 -> #REF! | K85: =K29 -> #REF! | L85: =L29 -> #REF!
C86: Depreciation and amortization | D86: =D31 -> 11792 | E86: =E31 -> 13035 | F86: =F31 -> 9602 | G86: =G31 -> 11379 | H86: =H31 -> 11151.42 | I86: =I31 -> 11737.114 | J86: =J31 -> 12482.987 | K86: =K31 -> 13323.136 | L86: =L31 -> 14117.674 | N86: Reference from the I/S
C87: Stock based compensation | D87: =D33 -> 2036 | E87: =E33 -> 3128 | F87: =F33 -> 3229 | G87: =G33 -> 3410 | H87: =H33 -> 3341.8 | I87: =I33 -> 3445.3958 | J87: =J33 -> 3596.9932 | K87: =K33 -> 3776.8429 | L87: =L33 -> 3943.024
C88: Decreases / (Increases) in working capital assets | H88: =SUM(G55:G55)-SUM(H55:H55) -> -620.98493 | I88: =SUM(H55:H55)-SUM(I55:I55) -> -59.671681 | J88: =SUM(I55:I55)-SUM(J55:J55) -> 548.31113 | K88: =SUM(J55:J55)-SUM(K55:K55) -> -1241.2673 | L88: =SUM(K55:K55)-SUM(L55:L55) -> -1146.931
C89: Increases / (Decreases) in working capital liabilities | H89: =SUM(H66:H68)-SUM(G66:G68) -> 973.80979 | I89: =SUM(I66:I68)-SUM(H66:H68) -> 400.60431 | J89: =SUM(J66:J68)-SUM(I66:I68) -> -605.13642 | K89: =SUM(K66:K68)-SUM(J66:J68) -> 2827.8139 | L89: =SUM(L66:L68)-SUM(K66:K68) -> 2612.9
C90: Other non current assets | H90: =-H124 -> -10928.1 | I90: =-I124 -> -11836.337 | J90: =-J124 -> -12499.391 | K90: =-K124 -> -13192.052 | L90: =-L124 -> -13701.832 | N90: Reference from schedule NOT the B/S: Only include 'Additions' (as outflow)
C91: Other non current liabilities | H91: =#REF!-#REF! -> #REF! | I91: =#REF!-#REF! -> #REF! | J91: =#REF!-#REF! -> #REF! | K91: =#REF!-#REF! -> #REF! | L91: =#REF!-#REF! -> #REF!
C92: Cash from operating activities | D92: =SUM(D85:D91) -> 31921 | E92: =SUM(E85:E91) -> 20891 | F92: =SUM(F85:F91) -> 10795 | G92: =SUM(G85:G91) -> -1447 | H92: =SUM(H85:H91) -> #REF! | I92: =SUM(I85:I91) -> #REF! | J92: =SUM(J85:J91) -> #REF! | K92: =SUM(K85:K91) -> #REF! | L92: =SUM(L85:L91) -> #REF!
C94: Capital expenditures | D94: ='Base Financials'!D112 -> -18733 | E94: ='Base Financials'!E112 -> -24844 | F94: ='Base Financials'!F112 -> -25750 | G94: ='Base Financials'!G112 -> -23944 | H94: =-(H110) -> -14658 | I94: =-(I110) -> -12000 | J94: =-(J110) -> -12000 | K94: =-(K110) -> -12000 | L94: =-(L110) -> -12000 | N94: Reference from PP&E schedule
C95: Cash from investing activities | D95: =IFERROR(D94,"NA") -> -18733 | E95: =IFERROR(E94,"NA") -> -24844 | F95: =IFERROR(F94,"NA") -> -25750 | G95: =IFERROR(G94,"NA") -> -23944 | H95: =IFERROR(H94,"NA") -> -14658 | I95: =IFERROR(I94,"NA") -> -12000 | J95: =IFERROR(J94,"NA") -> -12000 | K95: =IFERROR(K94,"NA") -> -12000 | L95: =IFERROR(L94,"NA") -> -12000
C97: Long term debt | H97: =#REF!-#REF! -> #REF! | I97: =#REF!-#REF! -> #REF! | J97: =#REF!-#REF! -> #REF! | K97: =#REF!-#REF! -> #REF! | L97: =#REF!-#REF! -> #REF!
C98: Commercial paper/ Revolver | H98: =#REF!-#REF! -> #REF! | I98: =#REF!-#REF! -> #REF! | J98: =#REF!-#REF! -> #REF! | K98: =#REF!-#REF! -> #REF! | L98: =#REF!-#REF! -> #REF! | N98: Reference from B/S
C99: Share repurchases | H99: =H131 -> 0 | I99: =I131 -> 0 | J99: =J131 -> 0 | K99: =K131 -> 0 | L99: =L131 -> 0 | N99: Reference from Retained Earnings schedule
C100: Common dividends | H100: =H130 -> #REF! | I100: =I130 -> #REF! | J100: =J130 -> #REF! | K100: =K130 -> #REF! | L100: =L130 -> #REF! | N100: Reference from Retained Earnings schedule
C101: Cash from financing activities | D101: =SUM(D97:D100) -> 0 | E101: =SUM(E97:E100) -> 0 | F101: =SUM(F97:F100) -> 0 | G101: =SUM(G97:G100) -> 0 | H101: =SUM(H97:H100) -> #REF! | I101: =SUM(I97:I100) -> #REF! | J101: =SUM(J97:J100) -> #REF! | K101: =SUM(K97:K100) -> #REF! | L101: =SUM(L97:L100) -> #REF!
C103: Net change in cash during period | D103: =D92+D95+D101 -> 13188 | E103: =E92+E95+E101 -> -3953 | F103: =F92+F95+F101 -> -14955 | G103: =G92+G95+G101 -> -25391 | H103: =H92+H95+H101 -> #REF! | I103: =I92+I95+I101 -> #REF! | J103: =J92+J95+J101 -> #REF! | K103: =K92+K95+K101 -> #REF! | L103: =L92+L95+L101 -> #REF!
C105: PROPERTY, PLANT & EQUIPMENT
C106: =C14 -> Fiscal year | E106: =E14 -> 2022 | F106: =F14 -> 2023 | G106: =G14 -> 2024 | H106: =H14 -> 2025 | I106: =I14 -> 2026 | J106: =J14 -> 2027 | K106: =K14 -> 2028 | L106: =L14 -> 2029
C107: =C15 -> Fiscal year end date | E107: =E15 -> 44926 | F107: =F15 -> 45291 | G107: =G15 -> 45654 | H107: =H15 -> 46022 | I107: =I15 -> 46387 | J107: =J15 -> 46752 | K107: =K15 -> 47118 | L107: =L15 -> 47483
H108: Forecast
C109: Beginning of period | H109: =G112 -> 107919 | I109: =H112 -> 122577 | J109: =I112 -> 134337 | K109: =J112 -> 145857 | L109: =K112 -> 157137 | N109: BOP = Previous year EOP
C110: Plus: Capital expenditures | D110: =D94 -> -18733 | E110: =E94 -> -24844 | F110: =F94 -> -25750 | G110: =G94 -> -23944 | H110: ='Street Consensus'!C65 -> 14658 | I110: ='Street Consensus'!D65 -> 12000 | J110: ='Street Consensus'!E65 -> 12000 | K110: ='Street Consensus'!F65 -> 12000 | L110: ='Street Consensus'!G65 -> 12000 | N110: First two years - consensus estimates, then grow with revenue
C111: Less: Depreciation | H111: =-(H114*H110) -> 0 | I111: =-(I114*I110) -> -240 | J111: =-(J114*J110) -> -480 | K111: =-(K114*K110) -> -720 | L111: =-(L114*L110) -> -960 | N111: Capex x 'D&A related to PP&E as a % of capex' ratio (below)
C112: End of period | D112: =D56 -> 63245 | E112: =E56 -> 80860 | F112: =F56 -> 96647 | G112: =G56 -> 107919 | H112: =SUM(H109:H111) -> 122577 | I112: =SUM(I109:I111) -> 134337 | J112: =SUM(J109:J111) -> 145857 | K112: =SUM(K109:K111) -> 157137 | L112: =SUM(L109:L111) -> 168177 | N112: BOP + Capex - Depreciation
N113: Step
C114: D&A related to PP&E as a % of capex | D114: =-(D111/D110) -> 0 | E114: =-(E111/E110) -> 0 | F114: =-(F111/F110) -> 0 | G114: =-(G111/G110) -> 0 | H114: =AVERAGE(E114:G114) -> 0 | I114: =H114+$N$114 -> 0.02 | J114: =I114+$N$114 -> 0.04 | K114: =J114+$N$114 -> 0.06 | L114: =K114+$N$114 -> 0.08 | N114: 0.02
C116: IMPUTING TOTAL DEPRECIATION & AMORTIZATION
C117: D&A not related to PP&E | D117: =D119+D111 -> 11792 | E117: =E119+E111 -> 13035 | F117: =F119+F111 -> 9602 | G117: =G119+G111 -> 11379 | H117: =H118*H17 -> 11151.42 | I117: =I118*I17 -> 11497.114 | J117: =J118*J17 -> 12002.987 | K117: =K118*K17 -> 12603.136 | L117: =L118*L17 -> 13157.674 | N117: Revenue x 'as % of revenue' assumption
C118: as % of revenue | D118: =D117/D17 -> 0.14922049 | E118: =E117/E17 -> 0.20672757 | F118: =F117/F17 -> 0.1770672 | G118: =G117/G17 -> 0.21428975 | H118: =G118 -> 0.21428975 | I118: =H118 -> 0.21428975 | J118: =I118 -> 0.21428975 | K118: =J118 -> 0.21428975 | L118: =K118 -> 0.21428975 | N118: Straight line last historical % of revenue - WSP assumption
C119: Depreciation & Amortization - Total | D119: =D31 -> 11792 | E119: =E31 -> 13035 | F119: =F31 -> 9602 | G119: =G31 -> 11379 | H119: =-H111+H117 -> 11151.42 | I119: =-I111+I117 -> 11737.114 | J119: =-J111+J117 -> 12482.987 | K119: =-K111+K117 -> 13323.136 | L119: =-L111+L117 -> 14117.674 | N119: D&A from PP&E + D&A not from PP&E
C121: OTHER NON-CURRENT ASSETS
...

Sheet FCF
B2: Intel, Corporation. (NASDAQ: INTC) | C2: FYE | I2: Quarterly | Q2: Quarterly | R2: Quarterly | Y2: LTM | AC2: LTM | AK2: Variance
B3: FCF Analysis | C3: ='Base Financials'!C3 -> 2020 | D3: ='Base Financials'!D3 -> 2021 | E3: ='Base Financials'!E3 -> 2022 | F3: ='Base Financials'!F3 -> 2023 | G3: ='Base Financials'!G3 -> 2024 | I3: ='Base Financials'!I3 -> 1Q22 | J3: ='Base Financials'!J3 -> 2Q22 | K3: ='Base Financials'!K3 -> 3Q22 | L3: ='Base Financials'!L3 -> 4Q22 | M3: ='Base Financials'!M3 -> 1Q23 | N3: ='Base Financials'!N3 -> 2Q23 | O3: ='Base Financials'!O3 -> 3Q23 | P3: ='Base Financials'!P3 -> 4Q23 | ... W3: ='Base Financials'!W3 -> 3Q25 | Y3: =L3 -> 4Q22 | Z3: =M3 -> 1Q23 | AA3: =N3 -> 2Q23 | AB3: =O3 -> 3Q23 | AC3: =P3 -> 4Q23 | AD3: =Q3 -> 1Q24 | AE3: =R3 -> 2Q24 | AF3: =S3 -> 3Q24 | ... AI3: =V3 -> 2Q25
B4: ($ In Thousands) | C4: ='Base Financials'!C4 -> 44191 | D4: ='Base Financials'!D4 -> 44555 | E4: ='Base Financials'!E4 -> 44926 | F4: ='Base Financials'!F4 -> 45290 | G4: ='Base Financials'!G4 -> 45654 | I4: ='Base Financials'!I4 -> 44653 | J4: ='Base Financials'!J4 -> 44744 | K4: ='Base Financials'!K4 -> 44835 | L4: ='Base Financials'!L4 -> 44926 | M4: ='Base Financials'!M4 -> 45017 | N4: ='Base Financials'!N4 -> 45108 | O4: ='Base Financials'!O4 -> 45199 | P4: ='Base Financials'!P4 -> 45290 | ... W4: ='Base Financials'!W4 -> 45925 | Y4: =L4 -> 44926 | Z4: =M4 -> 45017 | AA4: =N4 -> 45108 | AB4: =O4 -> 45199 | AC4: =P4 -> 45290 | AD4: =Q4 -> 45381 | AE4: =R4 -> 45472 | AF4: =S4 -> 45563 | ... AI4: =V4 -> 45836
B6: ='Revenue Drivers'!B7 -> Intel Products | C6: ='Revenue Drivers'!C7 -> 71080 | D6: ='Revenue Drivers'!D7 -> 69532 | E6: ='Revenue Drivers'!E7 -> 57038 | F6: ='Revenue Drivers'!F7 -> 47667 | G6: ='Revenue Drivers'!G7 -> 48949 | I6: ='Revenue Drivers'!I7 -> 17467 | J6: ='Revenue Drivers'!J7 -> 14073 | K6: ='Revenue Drivers'!K7 -> 13881 | L6: ='Revenue Drivers'!L7 -> 11617 | M6: ='Revenue Drivers'!M7 -> 10157 | N6: ='Revenue Drivers'!N7 -> 11299 | O6: ='Revenue Drivers'!O7 -> 12393 | P6: ='Revenue Drivers'!P7 -> 13818 | ... W6: ='Revenue Drivers'!W7 -> 12652 | Y6: =SUM(I6:L6) -> 57038 | Z6: =SUM(J6:M6) -> 49728 | AA6: =SUM(K6:N6) -> 46954 | AB6: =SUM(L6:O6) -> 45466 | AC6: =SUM(M6:P6) -> 47667 | AD6: =SUM(N6:Q6) -> 49443 | AE6: =SUM(O6:R6) -> 49943 | AF6: =SUM(P6:S6) -> 49740 | ... AI6: =SUM(S6:V6) -> 48782 | AK6: =SUM(AI6/AE6)-1 -> -0.023246501
B7: ='Revenue Drivers'!B8 -> Intel Foundry | C7: ='Revenue Drivers'!C8 -> 715 | D7: ='Revenue Drivers'!D8 -> 22849 | E7: ='Revenue Drivers'!E8 -> 27491.2 | F7: ='Revenue Drivers'!F8 -> 18910 | G7: ='Revenue Drivers'!G8 -> 17543 | I7: ='Revenue Drivers'!I8 -> 6958.517 | J7: ='Revenue Drivers'!J8 -> 7324.9181 | K7: ='Revenue Drivers'!K8 -> 6651.167 | L7: ='Revenue Drivers'!L8 -> 6556.5979 | M7: ='Revenue Drivers'!M8 -> 4831 | N7: ='Revenue Drivers'!N8 -> 4172 | O7: ='Revenue Drivers'!O8 -> 4732 | P7: ='Revenue Drivers'!P8 -> 5175 | ... W7: ='Revenue Drivers'!W8 -> 4235 | Y7: =SUM(I7:L7) -> 27491.2 | Z7: =SUM(J7:M7) -> 25363.683 | AA7: =SUM(K7:N7) -> 22210.765 | AB7: =SUM(L7:O7) -> 20291.598 | AC7: =SUM(M7:P7) -> 18910 | AD7: =SUM(N7:Q7) -> 18448 | AE7: =SUM(O7:R7) -> 18596 | AF7: =SUM(P7:S7) -> 18216 | ... AI7: =SUM(S7:V7) -> 17938 | AK7: =SUM(AI7/AE7)-1 -> -0.035383954
B8: ='Revenue Drivers'!B9 -> All Other | C8: ='Revenue Drivers'!C9 -> 6709 | D8: ='Revenue Drivers'!D9 -> 9137 | E8: ='Revenue Drivers'!E9 -> 5529.8 | F8: ='Revenue Drivers'!F9 -> 5608 | G8: ='Revenue Drivers'!G9 -> 3824 | I8: ='Revenue Drivers'!I9 -> 1121.0484 | J8: ='Revenue Drivers'!J9 -> 1160.0163 | K8: ='Revenue Drivers'!K9 -> 1499.9821 | L8: ='Revenue Drivers'!L9 -> 1748.7532 | M8: ='Revenue Drivers'!M9 -> 1440 | N8: ='Revenue Drivers'!N9 -> 1419 | O8: ='Revenue Drivers'!O9 -> 1452 | P8: ='Revenue Drivers'!P9 -> 1297 | ... W8: ='Revenue Drivers'!W9 -> 993 | Y8: =SUM(I8:L8) -> 5529.8 | Z8: =SUM(J8:M8) -> 5848.7516 | AA8: =SUM(K8:N8) -> 6107.7353 | AB8: =SUM(L8:O8) -> 6059.7532 | AC8: =SUM(M8:P8) -> 5608 | AD8: =SUM(N8:Q8) -> 4943 | AE8: =SUM(O8:R8) -> 4492 | AF8: =SUM(P8:S8) -> 4079 | ... AI8: =SUM(S8:V8) -> 4077 | AK8: =SUM(AI8/AE8)-1 -> -0.092386465
B9: Intersegment Elimination | C9: ='Revenue Drivers'!C12 -> -637 | D9: ='Revenue Drivers'!D12 -> -22494 | E9: ='Revenue Drivers'!E12 -> -27005 | F9: ='Revenue Drivers'!F12 -> -17957 | G9: ='Revenue Drivers'!G12 -> -17215 | I9: ='Revenue Drivers'!I12 -> -6797.517 | J9: ='Revenue Drivers'!J12 -> -7263.9181 | K9: ='Revenue Drivers'!K12 -> -6569.167 | L9: ='Revenue Drivers'!L12 -> -6374.3979 | M9: ='Revenue Drivers'!M12 -> -4713 | N9: ='Revenue Drivers'!N12 -> -3941 | O9: ='Revenue Drivers'!O12 -> -4419 | P9: ='Revenue Drivers'!P12 -> -4884 | ... W9: ='Revenue Drivers'!W12 -> -4227 | Y9: =SUM(I9:L9) -> -27005 | Z9: =SUM(J9:M9) -> -24920.483 | AA9: =SUM(K9:N9) -> -21597.565 | AB9: =SUM(L9:O9) -> -19447.398 | AC9: =SUM(M9:P9) -> -17957 | AD9: =SUM(N9:Q9) -> -17597 | AE9: =SUM(O9:R9) -> -17910 | AF9: =SUM(P9:S9) -> -17788 | ... AI9: =SUM(S9:V9) -> -17727 | AK9: =SUM(AI9/AE9)-1 -> -0.010217755
B10: Total Revenue | C10: =SUM(C6:C9) -> 77867 | D10: =SUM(D6:D9) -> 79024 | E10: =SUM(E6:E9) -> 63054 | F10: =SUM(F6:F9) -> 54228 | G10: =SUM(G6:G9) -> 53101 | I10: =SUM(I6:I9) -> 18749.048 | J10: =SUM(J6:J9) -> 15294.016 | K10: =SUM(K6:K9) -> 15462.982 | L10: =SUM(L6:L9) -> 13547.953 | M10: =SUM(M6:M9) -> 11715 | N10: =SUM(N6:N9) -> 12949 | O10: =SUM(O6:O9) -> 14158 | P10: =SUM(P6:P9) -> 15406 | ... W10: =SUM(W6:W9) -> 13653 | Y10: =SUM(Y6:Y9) -> 63054 | Z10: =SUM(Z6:Z9) -> 56019.952 | AA10: =SUM(AA6:AA9) -> 53674.935 | AB10: =SUM(AB6:AB9) -> 52369.953 | AC10: =SUM(AC6:AC9) -> 54228 | AD10: =SUM(AD6:AD9) -> 55237 | AE10: =SUM(AE6:AE9) -> 55121 | AF10: =SUM(AF6:AF9) -> 54247 | ... AI10: =SUM(AI6:AI9) -> 53070 | AK10: =SUM(AI10/AE10)-1 -> -0.037209049
B11: Y/Y Growth (%) | D11: =SUM(D10/C10)-1 -> 0.014858669 | E11: =SUM(E10/D10)-1 -> -0.2020905 | F11: =SUM(F10/E10)-1 -> -0.13997526 | G11: =SUM(G10/F10)-1 -> -0.020782622 | M11: =SUM(M10/I10)-1 -> -0.37516829 | N11: =SUM(N10/J10)-1 -> -0.15332901 | O11: =SUM(O10/K10)-1 -> -0.084393949 | P11: =SUM(P10/L10)-1 -> 0.13714594 | Q11: =SUM(Q10/M10)-1 -> 0.086128895 | R11: =SUM(R10/N10)-1 -> -0.0089582207 | S11: =SUM(S10/O10)-1 -> -0.061731883 | T11: =SUM(T10/P10)-1 -> -0.074386603 | ... W11: =SUM(W10/S10)-1 -> 0.027777778 | AC11: =SUM(AC10/Y10)-1 -> -0.13997526 | AD11: =SUM(AD10/Z10)-1 -> -0.013976299 | AE11: =SUM(AE10/AA10)-1 -> 0.026941154 | AF11: =SUM(AF10/AB10)-1 -> 0.035842057 | AG11: =SUM(AG10/AC10)-1 -> -0.020782622 | AH11: =SUM(AH10/AD10)-1 -> -0.039701649 | AI11: =SUM(AI10/AE10)-1 -> -0.037209049 | AK11: =SUM(AI11-AE11)*10000 -> -641.50203
B12: Q/Q Growth (%) | C12: N/A | D12: N/A | E12: N/A | F12: N/A | G12: N/A | J12: =SUM(J10/I10)-1 -> -0.18427773 | K12: =SUM(K10/J10)-1 -> 0.011047838 | L12: =SUM(L10/K10)-1 -> -0.12384603 | M12: =SUM(M10/L10)-1 -> -0.13529373 | N12: =SUM(N10/M10)-1 -> 0.10533504 | O12: =SUM(O10/N10)-1 -> 0.093366283 | P12: =SUM(P10/O10)-1 -> 0.088148044 | Q12: =SUM(Q10/P10)-1 -> -0.17408802 | ... W12: =SUM(W10/V10)-1 -> 0.061746637 | Y12: N/A | Z12: N/A | AA12: N/A | AB12: N/A | AC12: N/A | AD12: N/A | AE12: N/A | AF12: N/A | AG12: N/A | AH12: N/A | AI12: N/A
B14: (-) Cost of Sales | C14: ='Base Financials'!C11 -> -34255 | D14: ='Base Financials'!D11 -> -35209 | E14: ='Base Financials'!E11 -> -36188 | F14: ='Base Financials'!F11 -> -32517 | G14: ='Base Financials'!G11 -> -35756 | I14: ='Base Financials'!I11 -> -9109 | J14: ='Base Financials'!J11 -> -9734 | K14: ='Base Financials'!K11 -> -8803 | L14: ='Base Financials'!L11 -> -8542 | M14: ='Base Financials'!M11 -> -7707 | N14: ='Base Financials'!N11 -> -8311 | O14: ='Base Financials'!O11 -> -8140 | P14: ='Base Financials'!P11 -> -8359 | ... W14: ='Base Financials'!W11 -> -8435 | Y14: =SUM(I14:L14) -> -36188 | Z14: =SUM(J14:M14) -> -34786 | AA14: =SUM(K14:N14) -> -33363 | AB14: =SUM(L14:O14) -> -32700 | AC14: =SUM(M14:P14) -> -32517 | AD14: =SUM(N14:Q14) -> -32317 | AE14: =SUM(O14:R14) -> -32292 | AF14: =SUM(P14:S14) -> -35439 | ... AI14: =SUM(S14:V14) -> -37275 | AK14: =SUM(AI14/AE14)-1 -> 0.15431067
B15: Gross Profit | C15: =+C10+C14 -> 43612 | D15: =+D10+D14 -> 43815 | E15: =+E10+E14 -> 26866 | F15: =+F10+F14 -> 21711 | G15: =+G10+G14 -> 17345 | I15: =+I10+I14 -> 9640.0484 | J15: =+J10+J14 -> 5560.0163 | K15: =+K10+K14 -> 6659.9821 | L15: =+L10+L14 -> 5005.9532 | M15: =+M10+M14 -> 4008 | N15: =+N10+N14 -> 4638 | O15: =+O10+O14 -> 6018 | P15: =+P10+P14 -> 7047 | ... W15: =+W10+W14 -> 5218 | Y15: =+Y10+Y14 -> 26866 | Z15: =+Z10+Z14 -> 21233.952 | AA15: =+AA10+AA14 -> 20311.935 | AB15: =+AB10+AB14 -> 19669.953 | AC15: =+AC10+AC14 -> 21711 | AD15: =+AD10+AD14 -> 22920 | AE15: =+AE10+AE14 -> 22829 | AF15: =+AF10+AF14 -> 18808 | ... AI15: =+AI10+AI14 -> 15795 | AK15: =SUM(AI15/AE15)-1 -> -0.30811687
B16: Gross Margin (%) | C16: =C15/C10 -> 0.56008322 | D16: =D15/D10 -> 0.55445181 | E16: =E15/E10 -> 0.42607923 | F16: =F15/F10 -> 0.40036513 | G16: =G15/G10 -> 0.32664168 | I16: =I15/I10 -> 0.51416201 | J16: =J15/J10 -> 0.36354194 | K16: =K15/K10 -> 0.4307049 | L16: =L15/L10 -> 0.36949885 | M16: =M15/M10 -> 0.34212548 | N16: =N15/N10 -> 0.35817438 | O16: =O15/O10 -> 0.42506004 | P16: =P15/P10 -> 0.45741919 | ... W16: =W15/W10 -> 0.38218707 | Y16: =Y15/Y10 -> 0.42607923 | Z16: =Z15/Z10 -> 0.37904266 | AA16: =AA15/AA10 -> 0.37842496 | AB16: =AB15/AB10 -> 0.37559616 | AC16: =AC15/AC10 -> 0.40036513 | AD16: =AD15/AD10 -> 0.41493926 | AE16: =AE15/AE10 -> 0.41416157 | AF16: =AF15/AF10 -> 0.34671042 | ... AI16: =AI15/AI10 -> 0.29762578 | AK16: =SUM(AI16-AE16)*10000 -> -1165.3579
B18: (-) Marketing, General, and Administrative (MG&A) | C18: ='Base Financials'!C15 -> -6180 | D18: ='Base Financials'!D15 -> -6543 | E18: ='Base Financials'!E15 -> -7002 | F18: ='Base Financials'!F15 -> -5634 | G18: ='Base Financials'!G15 -> -5507 | I18: ='Base Financials'!I15 -> -1752 | J18: ='Base Financials'!J15 -> -1800 | K18: ='Base Financials'!K15 -> -1744 | L18: ='Base Financials'!L15 -> -1706 | M18: ='Base Financials'!M15 -> -1303 | N18: ='Base Financials'!N15 -> -1374 | O18: ='Base Financials'!O15 -> -1340 | P18: ='Base Financials'!P15 -> -1617 | ... W18: ='Base Financials'!W15 -> -1129 | Y18: =SUM(I18:L18) -> -7002 | Z18: =SUM(J18:M18) -> -6553 | AA18: =SUM(K18:N18) -> -6127 | AB18: =SUM(L18:O18) -> -5723 | AC18: =SUM(M18:P18) -> -5634 | AD18: =SUM(N18:Q18) -> -5887 | AE18: =SUM(O18:R18) -> -5842 | AF18: =SUM(P18:S18) -> -5885 | ... AI18: =SUM(S18:V18) -> -4943 | AK18: =SUM(AI18/AE18)-1 -> -0.15388566
B19: (-) Research and Development (R&D) | C19: ='Base Financials'!C16 -> -13556 | D19: ='Base Financials'!D16 -> -15190 | E19: ='Base Financials'!E16 -> -17528 | F19: ='Base Financials'!F16 -> -16046 | G19: ='Base Financials'!G16 -> -16546 | I19: ='Base Financials'!I16 -> -4362 | J19: ='Base Financials'!J16 -> -4400 | K19: ='Base Financials'!K16 -> -4302 | L19: ='Base Financials'!L16 -> -4464 | M19: ='Base Financials'!M16 -> -4109 | N19: ='Base Financials'!N16 -> -4080 | O19: ='Base Financials'!O16 -> -3870 | P19: ='Base Financials'!P16 -> -3987 | ... W19: ='Base Financials'!W16 -> -3231 | Y19: =SUM(I19:L19) -> -17528 | Z19: =SUM(J19:M19) -> -17275 | AA19: =SUM(K19:N19) -> -16955 | AB19: =SUM(L19:O19) -> -16523 | AC19: =SUM(M19:P19) -> -16046 | AD19: =SUM(N19:Q19) -> -16319 | AE19: =SUM(O19:R19) -> -16478 | AF19: =SUM(P19:S19) -> -16657 | ... AI19: =SUM(S19:V19) -> -15249 | AK19: =SUM(AI19/AE19)-1 -> -0.074584294
B20: (-) Restructuring and Other Charges | C20: ='Base Financials'!C17 -> -198 | D20: ='Base Financials'!D17 -> -2626 | E20: ='Base Financials'!E17 -> -2 | F20: ='Base Financials'!F17 -> 62 | G20: ='Base Financials'!G17 -> -6970 | I20: ='Base Financials'!I17 -> 1211 | J20: ='Base Financials'!J17 -> -87 | K20: ='Base Financials'!K17 -> -664 | L20: ='Base Financials'!L17 -> -462 | M20: ='Base Financials'!M17 -> -64 | N20: ='Base Financials'!N17 -> -200 | O20: ='Base Financials'!O17 -> -816 | P20: ='Base Financials'!P17 -> 1142 | ... W20: ='Base Financials'!W17 -> -175 | Y20: =SUM(I20:L20) -> -2 | Z20: =SUM(J20:M20) -> -1277 | AA20: =SUM(K20:N20) -> -1390 | AB20: =SUM(L20:O20) -> -1542 | AC20: =SUM(M20:P20) -> 62 | AD20: =SUM(N20:Q20) -> -222 | AE20: =SUM(O20:R20) -> -965 | AF20: =SUM(P20:S20) -> -5771 | ... AI20: =SUM(S20:V20) -> -7725 | AK20: =SUM(AI20/AE20)-1 -> 7.0051813
B21: Earning before Interest & Taxes (EBIT) | C21: =SUM(C15+SUM(C18:C20)) -> 23678 | D21: =SUM(D15+SUM(D18:D20)) -> 19456 | E21: =SUM(E15+SUM(E18:E20)) -> 2334 | F21: =SUM(F15+SUM(F18:F20)) -> 93 | G21: =SUM(G15+SUM(G18:G20)) -> -11678 | I21: =SUM(I15+SUM(I18:I20)) -> 4737.0484 | J21: =SUM(J15+SUM(J18:J20)) -> -726.98369 | K21: =SUM(K15+SUM(K18:K20)) -> -50.01787 | L21: =SUM(L15+SUM(L18:L20)) -> -1626.0468 | M21: =SUM(M15+SUM(M18:M20)) -> -1468 | N21: =SUM(N15+SUM(N18:N20)) -> -1016 | O21: =SUM(O15+SUM(O18:O20)) -> -8 | P21: =SUM(P15+SUM(P18:P20)) -> 2585 | ... W21: =SUM(W15+SUM(W18:W20)) -> 683 | Y21: =SUM(Y15+SUM(Y18:Y20)) -> 2334 | Z21: =SUM(Z15+SUM(Z18:Z20)) -> -3871.0484 | AA21: =SUM(AA15+SUM(AA18:AA20)) -> -4160.0647 | AB21: =SUM(AB15+SUM(AB18:AB20)) -> -4118.0468 | AC21: =SUM(AC15+SUM(AC18:AC20)) -> 93 | AD21: =SUM(AD15+SUM(AD18:AD20)) -> 492 | AE21: =SUM(AE15+SUM(AE18:AE20)) -> -456 | AF21: =SUM(AF15+SUM(AF18:AF20)) -> -9505 | ... AI21: =SUM(AI15+SUM(AI18:AI20)) -> -12122 | AK21: =SUM(AI21/AE21)-1 -> 25.583333
B22: Operating Margin (%) | C22: =C21/C10 -> 0.3040826 | D22: =D21/D10 -> 0.24620368 | E22: =E21/E10 -> 0.037015891 | F22: =F21/F10 -> 0.0017149812 | G22: =G21/G10 -> -0.21992053 | I22: =I21/I10 -> 0.2526554 | J22: =J21/J10 -> -0.047533864 | K22: =K21/K10 -> -0.0032346846 | L22: =L21/L10 -> -0.12002159 | M22: =M21/M10 -> -0.12530943 | N22: =N21/N10 -> -0.078461657 | O22: =O21/O10 -> -0.00056505156 | P22: =P21/P10 -> 0.16779177 | ... W22: =W21/W10 -> 0.050025635 | Y22: =Y21/Y10 -> 0.037015891 | Z22: =Z21/Z10 -> -0.069101245 | AA22: =AA21/AA10 -> -0.077504792 | AB22: =AB21/AB10 -> -0.07863377 | AC22: =AC21/AC10 -> 0.0017149812 | AD22: =AD21/AD10 -> 0.0089070732 | AE22: =AE21/AE10 -> -0.0082727091 | AF22: =AF21/AF10 -> -0.17521706 | ... AI22: =AI21/AI10 -> -0.2284153 | AK22: =SUM(AI22-AE22)*10000 -> -2201.4259
B24: (+) Depreciation and Amortization | C24: ='Base Financials'!C85+'Base Financials'!C87+'Base Financials'!C92 -> 12239 | D24: ='Base Financials'!D85+'Base Financials'!D87+'Base Financials'!D92 -> 11792 | E24: ='Base Financials'!E85+'Base Financials'!E87+'Base Financials'!E92 -> 13035 | F24: ='Base Financials'!F85+'Base Financials'!F87+'Base Financials'!F92 -> 9602 | G24: ='Base Financials'!G85+'Base Financials'!G87+'Base Financials'!G92 -> 11379 | I24: ='Base Financials'!I85+'Base Financials'!I87+'Base Financials'!I92 -> 3348 | J24: ='Base Financials'!J85+'Base Financials'!J87+'Base Financials'!J92 -> 3148 | K24: ='Base Financials'!K85+'Base Financials'!K87+'Base Financials'!K92 -> 3252 | L24: ='Base Financials'!L85+'Base Financials'!L87+'Base Financials'!L92 -> 3287 | M24: ='Base Financials'!M85+'Base Financials'!M87+'Base Financials'!M92 -> 2366 | N24: ='Base Financials'!N85+'Base Financials'!N87+'Base Financials'!N92 -> 2276 | O24: ='Base Financials'!O85+'Base Financials'!O87+'Base Financials'!O92 -> 2447 | P24: ='Base Financials'!P85+'Base Financials'!P87+'Base Financials'!P92 -> 2513 | ... W24: ='Base Financials'!W85+'Base Financials'!W87+'Base Financials'!W92 -> 2992 | Y24: =SUM(I24:L24) -> 13035 | Z24: =SUM(J24:M24) -> 12053 | AA24: =SUM(K24:N24) -> 11181 | AB24: =SUM(L24:O24) -> 10376 | AC24: =SUM(M24:P24) -> 9602 | AD24: =SUM(N24:Q24) -> 9787 | AE24: =SUM(O24:R24) -> 10080 | AF24: =SUM(P24:S24) -> 11245 | ... AI24: =SUM(S24:V24) -> 11946 | AK24: =SUM(AI24/AE24)-1 -> 0.18511905
B25: EBITDA | C25: =SUM(C21+C24) -> 35917 | D25: =SUM(D21+D24) -> 31248 | E25: =SUM(E21+E24) -> 15369 | F25: =SUM(F21+F24) -> 9695 | G25: =SUM(G21+G24) -> -299 | I25: =SUM(I21+I24) -> 8085.0484 | J25: =SUM(J21+J24) -> 2421.0163 | K25: =SUM(K21+K24) -> 3201.9821 | L25: =SUM(L21+L24) -> 1660.9532 | M25: =SUM(M21+M24) -> 898 | N25: =SUM(N21+N24) -> 1260 | O25: =SUM(O21+O24) -> 2439 | P25: =SUM(P21+P24) -> 5098 | ... W25: =SUM(W21+W24) -> 3675 | Y25: =SUM(Y21+Y24) -> 15369 | Z25: =SUM(Z21+Z24) -> 8181.9516 | AA25: =SUM(AA21+AA24) -> 7020.9353 | AB25: =SUM(AB21+AB24) -> 6257.9532 | AC25: =SUM(AC21+AC24) -> 9695 | AD25: =SUM(AD21+AD24) -> 10279 | AE25: =SUM(AE21+AE24) -> 9624 | AF25: =SUM(AF21+AF24) -> 1740 | ... AI25: =SUM(AI21+AI24) -> -176 | AK25: =SUM(AI25/AE25)-1 -> -1.0182876
B26: EBITDA Margin (%) | C26: =C25/C10 -> 0.46126087 | D26: =D25/D10 -> 0.39542417 | E26: =E25/E10 -> 0.24374346 | F26: =F25/F10 -> 0.17878218 | G26: =G25/G10 -> -0.0056307791 | I26: =I25/I10 -> 0.43122447 | J26: =J25/J10 -> 0.15829827 | K26: =K25/K10 -> 0.20707404 | L26: =L25/L10 -> 0.12259809 | M26: =M25/M10 -> 0.076653863 | N26: =N25/N10 -> 0.097304811 | O26: =O25/O10 -> 0.17227009 | P26: =P25/P10 -> 0.33091004 | ... W26: =W25/W10 -> 0.26917161 | Y26: =Y25/Y10 -> 0.24374346 | Z26: =Z25/Z10 -> 0.14605424 | AA26: =AA25/AA10 -> 0.13080473 | AB26: =AB25/AB10 -> 0.11949511 | AC26: =AC25/AC10 -> 0.17878218 | AD26: =AD25/AD10 -> 0.18608903 | AE26: =AE25/AE10 -> 0.1745977 | AF26: =AF25/AF10 -> 0.032075506 | ... AI26: =AI25/AI10 -> -0.0033163746 | AK26: =SUM(AI26-AE26)*10000 -> -1779.1408
B28: (+) Share-based Compensation | C28: ='Base Financials'!C88 -> 1854 | D28: ='Base Financials'!D88 -> 2036 | E28: ='Base Financials'!E88 -> 3128 | F28: ='Base Financials'!F88 -> 3229 | G28: ='Base Financials'!G88 -> 3410 | I28: ='Base Financials'!I88 -> 707 | J28: ='Base Financials'!J88 -> 892 | K28: ='Base Financials'!K88 -> 793 | L28: ='Base Financials'!L88 -> 736 | M28: ='Base Financials'!M88 -> 739 | N28: ='Base Financials'!N88 -> 922 | O28: ='Base Financials'!O88 -> 772 | P28: ='Base Financials'!P88 -> 796 | ... W28: ='Base Financials'!W88 -> 548 | Y28: =SUM(I28:L28) -> 3128 | Z28: =SUM(J28:M28) -> 3160 | AA28: =SUM(K28:N28) -> 3190 | AB28: =SUM(L28:O28) -> 3169 | AC28: =SUM(M28:P28) -> 3229 | AD28: =SUM(N28:Q28) -> 3669 | AE28: =SUM(O28:R28) -> 3527 | AF28: =SUM(P28:S28) -> 3555 | ... AI28: =SUM(S28:V28) -> 2799 | AK28: =SUM(AI28/AE28)-1 -> -0.20640771
B29: (+/-) Restructuring, asset impairment, and Other | C29: ='Base Financials'!C89 -> 0 | D29: ='Base Financials'!D89 -> 2626 | E29: ='Base Financials'!E89 -> 1074 | F29: ='Base Financials'!F89 -> -424 | G29: ='Base Financials'!G89 -> 3491 | I29: ='Base Financials'!I89 -> 17 | J29: ='Base Financials'!J89 -> 56 | K29: ='Base Financials'!K89 -> 592 | L29: ='Base Financials'!L89 -> 409 | M29: ='Base Financials'!M89 -> 55 | N29: ='Base Financials'!N89 -> 200 | O29: ='Base Financials'!O89 -> 463 | P29: ='Base Financials'!P89 -> -1142 | ... W29: ='Base Financials'!W89 -> -10 | Y29: =SUM(I29:L29) -> 1074 | Z29: =SUM(J29:M29) -> 1112 | AA29: =SUM(K29:N29) -> 1256 | AB29: =SUM(L29:O29) -> 1127 | AC29: =SUM(M29:P29) -> -424 | AD29: =SUM(N29:Q29) -> -131 | AE29: =SUM(O29:R29) -> 612 | AF29: =SUM(P29:S29) -> 2484 | ... AI29: =SUM(S29:V29) -> 2582 | AK29: =SUM(AI29/AE29)-1 -> 3.2189542
B30: (+/-) (Gains) losses on equity method investments | C30: ='Base Financials'!C94 -> -1757 | D30: ='Base Financials'!D94 -> -1458 | E30: ='Base Financials'!E94 -> -4254 | F30: ='Base Financials'!F94 -> -42 | G30: ='Base Financials'!G94 -> -246 | I30: ='Base Financials'!I94 -> -4325 | J30: ='Base Financials'!J94 -> 95 | K30: ='Base Financials'!K94 -> 155 | L30: ='Base Financials'!L94 -> -179 | M30: ='Base Financials'!M94 -> -167 | N30: ='Base Financials'!N94 -> 21 | O30: ='Base Financials'!O94 -> 193 | P30: ='Base Financials'!P94 -> -89 | ... W30: ='Base Financials'!W94 -> -221 | AE30: =SUM(O30:R30) -> 20 | AF30: =SUM(P30:S30) -> -14 | AG30: =SUM(Q30:T30) -> -246 | AH30: =SUM(R30:U30) -> 74 | AI30: =SUM(S30:V30) -> -552
B31: (+/-) (Gains) losses on divestitures | C31: ='Base Financials'!C96 -> -30 | D31: ='Base Financials'!D96 -> 0 | E31: ='Base Financials'!E96 -> -1059 | F31: ='Base Financials'!F96 -> 0 | G31: ='Base Financials'!G96 -> 0 | I31: ='Base Financials'!I96 -> -1121 | J31: ='Base Financials'!J96 -> 49 | K31: ='Base Financials'!K96 -> 0 | L31: ='Base Financials'!L96 -> 13 | M31: ='Base Financials'!M96 -> 0 | N31: ='Base Financials'!N96 -> 0 | O31: ='Base Financials'!O96 -> 0 | P31: ='Base Financials'!P96 -> 0 | ... W31: ='Base Financials'!W96 -> -5355 | AE31: =SUM(O31:R31) -> 0 | AF31: =SUM(P31:S31) -> 0 | AG31: =SUM(Q31:T31) -> 0 | AH31: =SUM(R31:U31) -> 0 | AI31: =SUM(S31:V31) -> 0
B32: Adj. EBITDA | C32: =+SUM(C25+SUM(C28:C31)) -> 35984 | D32: =+SUM(D25+SUM(D28:D31)) -> 34452 | E32: =+SUM(E25+SUM(E28:E31)) -> 14258 | F32: =+SUM(F25+SUM(F28:F31)) -> 12458 | G32: =+SUM(G25+SUM(G28:G31)) -> 6356 | I32: =+SUM(I25+SUM(I28:I31)) -> 3363.0484 | J32: =+SUM(J25+SUM(J28:J31)) -> 3513.0163 | K32: =+SUM(K25+SUM(K28:K31)) -> 4741.9821 | L32: =+SUM(L25+SUM(L28:L31)) -> 2639.9532 | M32: =+SUM(M25+SUM(M28:M31)) -> 1525 | N32: =+SUM(N25+SUM(N28:N31)) -> 2403 | O32: =+SUM(O25+SUM(O28:O31)) -> 3867 | P32: =+SUM(P25+SUM(P28:P31)) -> 4663 | ... W32: =+SUM(W25+SUM(W28:W31)) -> -1363 | Y32: =+SUM(Y25+SUM(Y28:Y29)) -> 19571 | Z32: =+SUM(Z25+SUM(Z28:Z29)) -> 12453.952 | AA32: =+SUM(AA25+SUM(AA28:AA29)) -> 11466.935 | AB32: =+SUM(AB25+SUM(AB28:AB29)) -> 10553.953 | AC32: =+SUM(AC25+SUM(AC28:AC29)) -> 12500 | AD32: =+SUM(AD25+SUM(AD28:AD29)) -> 13817 | AE32: =+SUM(AE25+SUM(AE28:AE31)) -> 13783 | AF32: =+SUM(AF25+SUM(AF28:AF31)) -> 7765 | AG32: =+SUM(AG25+SUM(AG28:AG31)) -> 6356 | AH32: =+SUM(AH25+SUM(AH28:AH31)) -> 6724 | AI32: =+SUM(AI25+SUM(AI28:AI31)) -> 4653 | AK32: =SUM(AI32/AE32)-1 -> -0.66241022
B33: Adj. EBITDA Margin (%) | C33: =C32/C10 -> 0.46212131 | D33: =D32/D10 -> 0.43596882 | E33: =E32/E10 -> 0.22612364 | F33: =F32/F10 -> 0.22973372 | G33: =G32/G10 -> 0.11969643 | I33: =I32/I10 -> 0.17937168 | J33: =J32/J10 -> 0.22969874 | K33: =K32/K10 -> 0.30666673 | L33: =L32/L10 -> 0.19485993 | M33: =M32/M10 -> 0.13017499 | N33: =N32/N10 -> 0.18557418 | O33: =O32/O10 -> 0.2731318 | P33: =P32/P10 -> 0.30267428 | ... W33: =W32/W10 -> -0.099831539 | Y33: =Y32/Y10 -> 0.31038475 | Z33: =Z32/Z10 -> 0.22231279 | AA33: =AA32/AA10 -> 0.21363669 | AB33: =AB32/AB10 -> 0.20152688 | AC33: =AC32/AC10 -> 0.23050822 | AD33: =AD32/AD10 -> 0.2501403 | AE33: =AE32/AE10 -> 0.25004989 | AF33: =AF32/AF10 -> 0.14314156 | ... AI33: =AI32/AI10 -> 0.087676653 | AK33: =SUM(AI33-AE33)*10000 -> -1623.7324
B35: (-) Capital Expenditures | C35: ='Base Financials'!C112 -> -14259 | D35: ='Base Financials'!D112 -> -18733 | E35: ='Base Financials'!E112 -> -24844 | F35: ='Base Financials'!F112 -> -25750 | G35: ='Base Financials'!G112 -> -23944 | I35: ='Base Financials'!I112 -> -4604 | J35: ='Base Financials'!J112 -> -7242 | K35: ='Base Financials'!K112 -> -7299 | L35: ='Base Financials'!L112 -> -5699 | M35: ='Base Financials'!M112 -> -7413 | N35: ='Base Financials'!N112 -> -5888 | O35: ='Base Financials'!O112 -> -5753 | P35: ='Base Financials'!P112 -> -6696 | ... W35: ='Base Financials'!W112 -> -2425 | Y35: =SUM(I35:L35) -> -24844 | Z35: =SUM(J35:M35) -> -27653 | AA35: =SUM(K35:N35) -> -26299 | AB35: =SUM(L35:O35) -> -24753 | AC35: =SUM(M35:P35) -> -25750 | AD35: =SUM(N35:Q35) -> -24307 | AE35: =SUM(O35:R35) -> -24101 | AF35: =SUM(P35:S35) -> -24806 | ... AI35: =SUM(S35:V35) -> -21025 | AK35: =SUM(AI35/AE35)-1 -> -0.12762956
B36: (-) Cash Interest | C36: =-('Base Financials'!C147) -> -594 | D36: =-('Base Financials'!D147) -> -545 | E36: =-('Base Financials'!E147) -> -459 | F36: =-('Base Financials'!F147) -> -613 | G36: =-('Base Financials'!G147) -> -987 | I36: =-('Base Financials'!I147) -> -177 | J36: =-('Base Financials'!J147) -> -37 | K36: =-('Base Financials'!K147) -> -101 | L36: =-('Base Financials'!L147) -> -144 | M36: =-('Base Financials'!M147) -> -239 | N36: =-('Base Financials'!N147) -> 78 | O36: =-('Base Financials'!O147) -> -502 | P36: =-('Base Financials'!P147) -> 50 | ... W36: =-('Base Financials'!W147) -> 121 | Y36: =SUM(I36:L36) -> -459 | Z36: =SUM(J36:M36) -> -521 | AA36: =SUM(K36:N36) -> -406 | AB36: =SUM(L36:O36) -> -807 | AC36: =SUM(M36:P36) -> -613 | AD36: =SUM(N36:Q36) -> -914 | AE36: =SUM(O36:R36) -> -940 | AF36: =SUM(P36:S36) -> -1049 | ... AI36: =SUM(S36:V36) -> -1013 | AK36: =SUM(AI36/AE36)-1 -> 0.077659574
B37: (-) Cash Taxes | C37: =-('Base Financials'!C148) -> -2436 | D37: =-('Base Financials'!D148) -> -2263 | E37: =-('Base Financials'!E148) -> -4282 | F37: =-('Base Financials'!F148) -> -2621 | G37: =-('Base Financials'!G148) -> -2202 | I37: =-('Base Financials'!I148) -> -335 | J37: =-('Base Financials'!J148) -> -2991 | K37: =-('Base Financials'!K148) -> -634 | L37: =-('Base Financials'!L148) -> -322 | M37: =-('Base Financials'!M148) -> -267 | N37: =-('Base Financials'!N148) -> -1253 | O37: =-('Base Financials'!O148) -> -129 | P37: =-('Base Financials'!P148) -> -972 | ... W37: =-('Base Financials'!W148) -> -1572 | Y37: =SUM(I37:L37) -> -4282 | Z37: =SUM(J37:M37) -> -4214 | AA37: =SUM(K37:N37) -> -2476 | AB37: =SUM(L37:O37) -> -1971 | AC37: =SUM(M37:P37) -> -2621 | AD37: =SUM(N37:Q37) -> -2669 | AE37: =SUM(O37:R37) -> -2656 | AF37: =SUM(P37:S37) -> -2852 | ... AI37: =SUM(S37:V37) -> -2440 | AK37: =SUM(AI37/AE37)-1 -> -0.081325301
B38: (-) Mandatory Amortization | C38: 0 | D38: 0 | E38: 0 | F38: 0 | G38: 0 | I38: 0 | J38: 0 | K38: 0 | L38: 0 | M38: 0 | N38: 0 | O38: 0 | P38: 0 | Q38: 0 | R38: 0 | S38: 0 | T38: 0 | U38: 0 | V38: 0 | W38: 0 | Y38: =SUM(I38:L38) -> 0 | Z38: =SUM(J38:M38) -> 0 | AA38: =SUM(K38:N38) -> 0 | AB38: =SUM(L38:O38) -> 0 | AC38: =SUM(M38:P38) -> 0 | AD38: =SUM(N38:Q38) -> 0 | AE38: =SUM(O38:R38) -> 0 | AF38: =SUM(P38:S38) -> 0 | ... AI38: =SUM(S38:V38) -> 0 | AK38: =SUM(AI38/AE38)-1 -> #DIV/0!
B39: (+/-) Changes in NWC | C39: =SUM('Base Financials'!C101:C108) -> 2179 | D39: =SUM('Base Financials'!D101:D108) -> -4873 | E39: =SUM('Base Financials'!E101:E108) -> -4508 | F39: =SUM('Base Financials'!F101:F108) -> -2569 | G39: =SUM('Base Financials'!G101:G108) -> 1103 | I39: =SUM('Base Financials'!I101:I108) -> -848 | J39: =SUM('Base Financials'!J101:J108) -> -2977 | K39: =SUM('Base Financials'!K101:K108) -> -4781 | L39: =SUM('Base Financials'!L101:L108) -> 4098 | M39: =SUM('Base Financials'!M101:M108) -> -2010 | N39: =SUM('Base Financials'!N101:N108) -> -2084 | O39: =SUM('Base Financials'!O101:O108) -> 1639 | P39: =SUM('Base Financials'!P101:P108) -> -114 | ... W39: =SUM('Base Financials'!W101:W108) -> -1365 | Y39: =SUM(I39:L39) -> -4508 | Z39: =SUM(J39:M39) -> -5670 | AA39: =SUM(K39:N39) -> -4777 | AB39: =SUM(L39:O39) -> 1643 | AC39: =SUM(M39:P39) -> -2569 | AD39: =SUM(N39:Q39) -> -5215 | AE39: =SUM(O39:R39) -> -3601 | AF39: =SUM(P39:S39) -> 239 | ... AI39: =SUM(S39:V39) -> 5388 | AK39: =SUM(AI39/AE39)-1 -> -2.496251
B40: Discretionary Cash-Flows | C40: =SUM(C32+SUM(C35:C39)) -> 20874 | D40: =SUM(D32+SUM(D35:D39)) -> 8038 | E40: =SUM(E32+SUM(E35:E39)) -> -19835 | F40: =SUM(F32+SUM(F35:F39)) -> -19095 | G40: =SUM(G32+SUM(G35:G39)) -> -19674 | I40: =SUM(I32+SUM(I35:I39)) -> -2600.9516 | J40: =SUM(J32+SUM(J35:J39)) -> -9733.9837 | K40: =SUM(K32+SUM(K35:K39)) -> -8073.0179 | L40: =SUM(L32+SUM(L35:L39)) -> 572.95317 | M40: =SUM(M32+SUM(M35:M39)) -> -8404 | N40: =SUM(N32+SUM(N35:N39)) -> -6744 | O40: =SUM(O32+SUM(O35:O39)) -> -878 | P40: =SUM(P32+SUM(P35:P39)) -> -3069 | ... W40: =SUM(W32+SUM(W35:W39)) -> -6604 | Y40: =SUM(Y32+SUM(Y35:Y39)) -> -14522 | Z40: =SUM(Z32+SUM(Z35:Z39)) -> -25604.048 | AA40: =SUM(AA32+SUM(AA35:AA39)) -> -22491.065 | AB40: =SUM(AB32+SUM(AB35:AB39)) -> -15334.047 | AC40: =SUM(AC32+SUM(AC35:AC39)) -> -19053 | AD40: =SUM(AD32+SUM(AD35:AD39)) -> -19288 | AE40: =SUM(AE32+SUM(AE35:AE39)) -> -17515 | AF40: =SUM(AF32+SUM(AF35:AF39)) -> -20703 | ... AI40: =SUM(AI32+SUM(AI35:AI39)) -> -14437 | AK40: =SUM(AI40/AE40)-1 -> -0.17573508
B42: (+/-) Divestitures / Acquisitions | C42: =SUM('Base Financials'!C113+'Base Financials'!C114) -> 123 | D42: =SUM('Base Financials'!D113+'Base Financials'!D114) -> -1596 | E42: =SUM('Base Financials'!E113+'Base Financials'!E114) -> 6579 | F42: =SUM('Base Financials'!F113+'Base Financials'!F114) -> 0 | G42: =SUM('Base Financials'!G113+'Base Financials'!G114) -> -82 | I42: =SUM('Base Financials'!I113+'Base Financials'!I114) -> 6351 | J42: =SUM('Base Financials'!J113+'Base Financials'!J114) -> 22 | K42: =SUM('Base Financials'!K113+'Base Financials'!K114) -> 206 | L42: =SUM('Base Financials'!L113+'Base Financials'!L114) -> 0 | M42: =SUM('Base Financials'!M113+'Base Financials'!M114) -> 0 | N42: =SUM('Base Financials'!N113+'Base Financials'!N114) -> 0 | O42: =SUM('Base Financials'!O113+'Base Financials'!O114) -> 0 | P42: =SUM('Base Financials'!P113+'Base Financials'!P114) -> 0 | ... W42: =SUM('Base Financials'!W113+'Base Financials'!W114) -> 4251 | Y42: =SUM(I42:L42) -> 6579 | Z42: =SUM(J42:M42) -> 228 | AA42: =SUM(K42:N42) -> 206 | AB42: =SUM(L42:O42) -> 0 | AC42: =SUM(M42:P42) -> 0 | AD42: =SUM(N42:Q42) -> 0 | AE42: =SUM(O42:R42) -> 0 | AF42: =SUM(P42:S42) -> 0 | ... AI42: =SUM(S42:V42) -> 1853
B43: (+/-) Maturities and Sales / (Purchases) of Investments | C43: =SUM('Base Financials'!C115:C116) -> -81 | D43: =SUM('Base Financials'!D115:D116) -> 1416 | E43: =SUM('Base Financials'!E115:E116) -> 4451 | F43: =SUM('Base Financials'!F115:F116) -> -337 | G43: =SUM('Base Financials'!G115:G116) -> 3523 | I43: =SUM('Base Financials'!I115:I116) -> 10490 | J43: =SUM('Base Financials'!J115:J116) -> 14917 | K43: =SUM('Base Financials'!K115:K116) -> -20527 | L43: =SUM('Base Financials'!L115:L116) -> -429 | M43: =SUM('Base Financials'!M115:M116) -> -1959 | N43: =SUM('Base Financials'!N115:N116) -> 3220 | O43: =SUM('Base Financials'!O115:O116) -> -1823 | P43: =SUM('Base Financials'!P115:P116) -> 225 | ... W43: =SUM('Base Financials'!W115:W116) -> -8282 | Y43: =SUM(I43:L43) -> 4451 | Z43: =SUM(J43:M43) -> -7998 | AA43: =SUM(K43:N43) -> -19695 | AB43: =SUM(L43:O43) -> -991 | AC43: =SUM(M43:P43) -> -337 | AD43: =SUM(N43:Q43) -> 4760 | AE43: =SUM(O43:R43) -> -2018 | AF43: =SUM(P43:S43) -> 2974 | ... AI43: =SUM(S43:V43) -> 6788
B44: (+/-) Maturities and Sales / (Purchases) of Trading Assets | C44: =SUM('Base Financials'!C117:C118) -> -7000 | D44: =SUM('Base Financials'!D117:D118) -> -6671 | E44: =SUM('Base Financials'!E117:E118) -> 5083 | F44: =SUM('Base Financials'!F117:F118) -> 73 | G44: =SUM('Base Financials'!G117:G118) -> 1047 | I44: =SUM('Base Financials'!I117:I118) -> -14409 | J44: =SUM('Base Financials'!J117:J118) -> -6330 | K44: =SUM('Base Financials'!K117:K118) -> 24199 | L44: =SUM('Base Financials'!L117:L118) -> 1623 | M44: =SUM('Base Financials'!M117:M118) -> 116 | N44: =SUM('Base Financials'!N117:N118) -> 137 | O44: =SUM('Base Financials'!O117:O118) -> 122 | P44: =SUM('Base Financials'!P117:P118) -> -302 | ... W44: =SUM('Base Financials'!W117:W118) -> 642 | Y44: =SUM(I44:L44) -> 5083 | Z44: =SUM(J44:M44) -> 19608 | AA44: =SUM(K44:N44) -> 26075 | AB44: =SUM(L44:O44) -> 1998 | AC44: =SUM(M44:P44) -> 73 | AD44: =SUM(N44:Q44) -> -43 | AE44: =SUM(O44:R44) -> -180 | AF44: =SUM(P44:S44) -> -302 | ... AI44: =SUM(S44:V44) -> 1047
B45: (+/-) Issuance / (Repayment) of Debt | C45: =SUM('Base Financials'!C127:C129) -> 5722 | D45: =SUM('Base Financials'!D127:D129) -> 2474 | E45: =SUM('Base Financials'!E127:E129) -> 5509 | F45: =SUM('Base Financials'!F127:F129) -> 7024 | G45: =SUM('Base Financials'!G127:G129) -> 687 | I45: =SUM('Base Financials'!I127:I129) -> -299 | J45: =SUM('Base Financials'!J127:J129) -> -1688 | K45: =SUM('Base Financials'!K127:K129) -> 5002 | L45: =SUM('Base Financials'!L127:L129) -> 2494 | M45: =SUM('Base Financials'!M127:M129) -> 8023 | N45: =SUM('Base Financials'!N127:N129) -> -1095 | O45: =SUM('Base Financials'!O127:O129) -> 96 | P45: =SUM('Base Financials'!P127:P129) -> 0 | ... W45: =SUM('Base Financials'!W127:W129) -> -4247 | Y45: =SUM(I45:L45) -> 5509 | Z45: =SUM(J45:M45) -> 13831 | AA45: =SUM(K45:N45) -> 14424 | AB45: =SUM(L45:O45) -> 9518 | AC45: =SUM(M45:P45) -> 7024 | AD45: =SUM(N45:Q45) -> 2331 | AE45: =SUM(O45:R45) -> 3978 | AF45: =SUM(P45:S45) -> 687 | ... AI45: =SUM(S45:V45) -> -2698
B46: (+/-) Share Repurchases | C46: ='Base Financials'!C133 -> -14229 | D46: ='Base Financials'!D133 -> -2415 | E46: ='Base Financials'!E133 -> 0 | F46: ='Base Financials'!F133 -> 0 | G46: ='Base Financials'!G133 -> 0 | I46: ='Base Financials'!I133 -> 0 | J46: ='Base Financials'!J133 -> 0 | K46: ='Base Financials'!K133 -> 0 | L46: ='Base Financials'!L133 -> 0 | M46: ='Base Financials'!M133 -> 0 | N46: ='Base Financials'!N133 -> 0 | O46: ='Base Financials'!O133 -> 0 | P46: ='Base Financials'!P133 -> 0 | ... W46: ='Base Financials'!W133 -> 0 | Y46: =SUM(I46:L46) -> 0 | Z46: =SUM(J46:M46) -> 0 | AA46: =SUM(K46:N46) -> 0 | AB46: =SUM(L46:O46) -> 0 | AC46: =SUM(M46:P46) -> 0 | AD46: =SUM(N46:Q46) -> 0 | AE46: =SUM(O46:R46) -> 0 | AF46: =SUM(P46:S46) -> 0 | ... AI46: =SUM(S46:V46) -> 0
B47: (+/-) Other Equity Activity | C47: =SUM('Base Financials'!C131:C132) -> 897 | D47: =SUM('Base Financials'!D131:D132) -> 1020 | E47: =SUM('Base Financials'!E131:E132) -> 977 | F47: =SUM('Base Financials'!F131:F132) -> 2959 | G47: =SUM('Base Financials'!G131:G132) -> 987 | I47: =SUM('Base Financials'!I131:I132) -> 589 | J47: =SUM('Base Financials'!J131:J132) -> 0 | K47: =SUM('Base Financials'!K131:K132) -> 383 | L47: =SUM('Base Financials'!L131:L132) -> 5 | M47: =SUM('Base Financials'!M131:M132) -> 659 | N47: =SUM('Base Financials'!N131:N132) -> 914 | O47: =SUM('Base Financials'!O131:O132) -> 850 | P47: =SUM('Base Financials'!P131:P132) -> 536 | ... W47: =SUM('Base Financials'!W131:W132) -> 4023 | Y47: =SUM(I47:L47) -> 977 | Z47: =SUM(J47:M47) -> 1047 | AA47: =SUM(K47:N47) -> 1961 | AB47: =SUM(L47:O47) -> 2428 | AC47: =SUM(M47:P47) -> 2959 | AD47: =SUM(N47:Q47) -> 2926 | AE47: =SUM(O47:R47) -> 2017 | AF47: =SUM(P47:S47) -> 1522 | ... AI47: =SUM(S47:V47) -> 847
B48: (+/-) Dividends | C48: ='Base Financials'!C134 -> -5568 | D48: ='Base Financials'!D134 -> -5644 | E48: ='Base Financials'!E134 -> -5997 | F48: ='Base Financials'!F134 -> -3088 | G48: ='Base Financials'!G134 -> -1599 | I48: ='Base Financials'!I134 -> -1487 | J48: ='Base Financials'!J134 -> -1499 | K48: ='Base Financials'!K134 -> -1502 | L48: ='Base Financials'!L134 -> -1509 | M48: ='Base Financials'!M134 -> -1512 | N48: ='Base Financials'!N134 -> -524 | O48: ='Base Financials'!O134 -> -525 | P48: ='Base Financials'!P134 -> -527 | ... W48: ='Base Financials'!W134 -> 0 | AE48: =SUM(O48:R48) -> -2115 | AF48: =SUM(P48:S48) -> -2126 | AG48: =SUM(Q48:T48) -> -1599 | AH48: =SUM(R48:U48) -> -1070 | AI48: =SUM(S48:V48) -> -536
B49: (+/-) Proceeds from capital-related government incentives | C49: ='Base Financials'!C121 -> 190 | D49: ='Base Financials'!D121 -> -613 | E49: ='Base Financials'!E121 -> 0 | F49: ='Base Financials'!F121 -> 0 | G49: ='Base Financials'!G121 -> 0 | I49: ='Base Financials'!I121 -> 0 | J49: ='Base Financials'!J121 -> 0 | K49: ='Base Financials'!K121 -> 0 | L49: ='Base Financials'!L121 -> 0 | M49: ='Base Financials'!M121 -> 0 | N49: ='Base Financials'!N121 -> 0 | O49: ='Base Financials'!O121 -> 0 | P49: ='Base Financials'!P121 -> 0 | ... W49: ='Base Financials'!W121 -> 0 | AE49: =SUM(O49:R49) -> 0 | AF49: =SUM(P49:S49) -> 0 | AG49: =SUM(Q49:T49) -> 0 | AH49: =SUM(R49:U49) -> 0 | AI49: =SUM(S49:V49) -> 0
B50: (+/-) Proceeds from gov't grants, partner contributions | C50: ='Base Financials'!C130 -> 0 | D50: ='Base Financials'!D130 -> 0 | E50: ='Base Financials'!E130 -> 874 | F50: ='Base Financials'!F130 -> 1511 | G50: ='Base Financials'!G130 -> 12714 | I50: ='Base Financials'!I130 -> 0 | J50: ='Base Financials'!J130 -> 0 | K50: ='Base Financials'!K130 -> 0 | L50: ='Base Financials'!L130 -> 874 | M50: ='Base Financials'!M130 -> 449 | N50: ='Base Financials'!N130 -> 385 | O50: ='Base Financials'!O130 -> 272 | P50: ='Base Financials'!P130 -> 405 | ... W50: ='Base Financials'!W130 -> 1414 | AE50: =SUM(O50:R50) -> 12538 | AF50: =SUM(P50:S50) -> 12683 | AG50: =SUM(Q50:T50) -> 12714 | AH50: =SUM(R50:U50) -> 13246 | AI50: =SUM(S50:V50) -> 3091
B51: (+/-) Additions to property, plant and equipment | C51: ='Base Financials'!C135 -> 0 | D51: ='Base Financials'!D135 -> 0 | E51: ='Base Financials'!E135 -> 0 | F51: ='Base Financials'!F135 -> 0 | G51: ='Base Financials'!G135 -> -1178 | I51: ='Base Financials'!I135 -> 0 | J51: ='Base Financials'!J135 -> 0 | K51: ='Base Financials'!K135 -> 0 | L51: ='Base Financials'!L135 -> 0 | M51: ='Base Financials'!M135 -> 0 | N51: ='Base Financials'!N135 -> 0 | O51: ='Base Financials'!O135 -> 0 | P51: ='Base Financials'!P135 -> 0 | ... W51: ='Base Financials'!W135 -> -531 | AE51: =SUM(O51:R51) -> 0 | AF51: =SUM(P51:S51) -> 0 | AG51: =SUM(Q51:T51) -> -1178 | AH51: =SUM(R51:U51) -> -2198 | AI51: =SUM(S51:V51) -> -3140
B52: (+/-) Other | D52: =SUM(D57-C57)-SUM(D40:D51) -> 2953 | E52: =SUM(E57-D57)-SUM(E40:E51) -> 8676 | F52: =SUM(F57-E57)-SUM(F40:F51) -> 6888 | G52: =SUM(G57-F57)-SUM(G40:G51) -> 4745 | I52: =SUM(I57-D57)-SUM(I40:I51) -> 2753.9516 | J52: =SUM(J57-I57)-SUM(J40:J51) -> 2486.9837 | K52: =SUM(K57-J57)-SUM(K40:K51) -> 451.01787 | L52: =SUM(L57-K57)-SUM(L40:L51) -> 2984.0468 | M52: =SUM(M57-L57)-SUM(M40:M51) -> -284 | N52: =SUM(N57-M57)-SUM(N40:N51) -> 3824 | O52: =SUM(O57-N57)-SUM(O40:O51) -> 1158 | P52: =SUM(P57-O57)-SUM(P40:P51) -> 2190 | Q52: =SUM(Q57-P57)-SUM(Q40:Q51) -> 1536 | ... W52: =SUM(W57-V57)-SUM(W40:W51) -> 10832 | Y52: =SUM(I52:L52) -> 8676 | Z52: =SUM(J52:M52) -> 5638.0484 | AA52: =SUM(K52:N52) -> 6975.0647 | AB52: =SUM(L52:O52) -> 7682.0468 | AC52: =SUM(M52:P52) -> 6888 | AD52: =SUM(N52:Q52) -> 8708 | AE52: =SUM(O52:R52) -> 6233 | AF52: =SUM(P52:S52) -> 6429 | ... AI52: =SUM(S52:V52) -> 5541
B53: Free-Cash Flows | C53: =SUM(C40+SUM(C42:C52)) -> 928 | D53: =SUM(D40+SUM(D42:D52)) -> -1038 | E53: =SUM(E40+SUM(E42:E52)) -> 6317 | F53: =SUM(F40+SUM(F42:F52)) -> -4065 | G53: =SUM(G40+SUM(G42:G52)) -> 1170 | I53: =SUM(I40+SUM(I42:I52)) -> 1388 | J53: =SUM(J40+SUM(J42:J52)) -> -1825 | K53: =SUM(K40+SUM(K42:K52)) -> 139 | L53: =SUM(L40+SUM(L42:L52)) -> 6615 | M53: =SUM(M40+SUM(M42:M52)) -> -2912 | N53: =SUM(N40+SUM(N42:N52)) -> 117 | O53: =SUM(O40+SUM(O42:O52)) -> -728 | P53: =SUM(P40+SUM(P42:P52)) -> -542 | ... W53: =SUM(W40+SUM(W42:W52)) -> 1498 | Y53: =SUM(Y40+SUM(Y42:Y52)) -> 16753 | Z53: =SUM(Z40+SUM(Z42:Z52)) -> 6750 | AA53: =SUM(AA40+SUM(AA42:AA52)) -> 7455 | AB53: =SUM(AB40+SUM(AB42:AB52)) -> 5301 | AC53: =SUM(AC40+SUM(AC42:AC52)) -> -2446 | AD53: =SUM(AD40+SUM(AD42:AD52)) -> -606 | AE53: =SUM(AE40+SUM(AE42:AE52)) -> 2938 | AF53: =SUM(AF40+SUM(AF42:AF52)) -> 1164 | ... AI53: =SUM(AI40+SUM(AI42:AI52)) -> -1644
B55: Capitalization
B57: Cash & Cash Equivelants | C57: ='Base Financials'!C38 -> 5865 | D57: ='Base Financials'!D38 -> 4827 | E57: ='Base Financials'!E38 -> 11144 | F57: ='Base Financials'!F38 -> 7079 | G57: ='Base Financials'!G38 -> 8249 | I57: ='Base Financials'!I38 -> 6215 | J57: ='Base Financials'!J38 -> 4390 | K57: ='Base Financials'!K38 -> 4529 | L57: ='Base Financials'!L38 -> 11144 | M57: ='Base Financials'!M38 -> 8232 | N57: ='Base Financials'!N38 -> 8349 | O57: ='Base Financials'!O38 -> 7621 | P57: ='Base Financials'!P38 -> 7079 | ... W57: ='Base Financials'!W38 -> 11141 | Y57: =L57 -> 11144 | Z57: =M57 -> 8232 | AA57: =N57 -> 8349 | AB57: =O57 -> 7621 | AC57: =P57 -> 7079 | AD57: =Q57 -> 6923 | AE57: =R57 -> 11287 | AF57: =S57 -> 8785 | ... AI57: =V57 -> 9643
B58: Trading Assets | C58: ='Base Financials'!C40 -> 15738 | D58: ='Base Financials'!D40 -> 21483 | E58: ='Base Financials'!E40 -> 17194 | F58: ='Base Financials'!F40 -> 17955 | G58: ='Base Financials'!G40 -> 13813 | I58: ='Base Financials'!I40 -> 21483 | J58: ='Base Financials'!J40 -> 22654 | K58: ='Base Financials'!K40 -> 18030 | L58: ='Base Financials'!L40 -> 17194 | M58: ='Base Financials'!M40 -> 19302 | N58: ='Base Financials'!N40 -> 15908 | O58: ='Base Financials'!O40 -> 17409 | P58: ='Base Financials'!P40 -> 17955 | ... W58: ='Base Financials'!W40 -> 19794 | Y58: =L58 -> 17194 | Z58: =M58 -> 19302 | AA58: =N58 -> 15908 | AB58: =O58 -> 17409 | AC58: =P58 -> 17955 | AD58: =Q58 -> 14388 | AE58: =R58 -> 17986 | AF58: =S58 -> 15301 | ... AI58: =V58 -> 11563
B59: $7.0Bn Revolving Credit Facility (5-Year Tenor) due 2029 | C59: 0 | D59: 5000 | E59: 5000 | F59: 7000 | G59: 7000 | I59: 5000 | J59: 5000 | K59: 5000 | L59: =E59 -> 5000 | M59: 5000 | N59: 5000 | O59: 5000 | P59: =F59 -> 7000 | Q59: 7000 | R59: 7000 | S59: 7000 | T59: 7000 | U59: 7000 | V59: 7000 | W59: 7000 | AE59: =R59 -> 7000 | AF59: =S59 -> 7000 | AG59: =T59 -> 7000 | AH59: =U59 -> 7000 | AI59: =V59 -> 7000
B60: $5.0Bn Revolving Credit Facility (364-Day CP Backstop) due 2026 | C60: 0 | D60: 0 | E60: =5000-E75 -> 1100 | F60: =5000-F75 -> 5000 | G60: =5000-G75 -> 5000 | I60: 0 | J60: 0 | K60: 0 | L60: =5000-L75 -> 1100 | M60: =5000-M75 -> 4000 | N60: =5000-N75 -> 5000 | O60: =5000-O75 -> 5000 | P60: =5000-P75 -> 5000 | Q60: =8000-Q75 -> 7207 | R60: =8000-R75 -> 4800 | S60: =8000-S75 -> 8000 | T60: =5000-T75 -> 5000 | U60: =5000-U75 -> 3500 | V60: =5000-V75 -> 3000 | W60: =5000-W75 -> 3000 | AE60: =R60 -> 4800 | AF60: =S60 -> 8000 | AG60: =T60 -> 5000 | AH60: =U60 -> 3500 | AI60: =V60 -> 3000
B61: Total Liquidity | C61: =SUM(C57:C60) -> 21603 | D61: =SUM(D57:D60) -> 31310 | E61: =SUM(E57:E60) -> 34438 | F61: =SUM(F57:F60) -> 37034 | G61: =SUM(G57:G60) -> 34062 | I61: =SUM(I57:I60) -> 32698 | J61: =SUM(J57:J60) -> 32044 | K61: =SUM(K57:K60) -> 27559 | L61: =SUM(L57:L60) -> 34438 | M61: =SUM(M57:M60) -> 36534 | N61: =SUM(N57:N60) -> 34257 | O61: =SUM(O57:O60) -> 35030 | P61: =SUM(P57:P60) -> 37034 | ... W61: =SUM(W57:W60) -> 40935 | Y61: =SUM(Y57:Y58) -> 28338 | Z61: =SUM(Z57:Z58) -> 27534 | AA61: =SUM(AA57:AA58) -> 24257 | AB61: =SUM(AB57:AB58) -> 25030 | AC61: =SUM(AC57:AC58) -> 25034 | AD61: =SUM(AD57:AD58) -> 21311 | AE61: =SUM(AE57:AE60) -> 41073 | AF61: =SUM(AF57:AF60) -> 39086 | AG61: =SUM(AG57:AG60) -> 34062 | AH61: =SUM(AH57:AH60) -> 31548 | AI61: =SUM(AI57:AI60) -> 31206
B63: Balance Sheet Metrics:
B64: Accounts Receivable | C64: ='Base Financials'!C41 -> 6782 | D64: ='Base Financials'!D41 -> 9457 | E64: ='Base Financials'!E41 -> 4133 | F64: ='Base Financials'!F41 -> 3402 | G64: ='Base Financials'!G41 -> 3478 | I64: ='Base Financials'!I41 -> 7074 | J64: ='Base Financials'!J41 -> 6063 | K64: ='Base Financials'!K41 -> 7469 | L64: ='Base Financials'!L41 -> 4133 | M64: ='Base Financials'!M41 -> 3847 | N64: ='Base Financials'!N41 -> 2996 | O64: ='Base Financials'!O41 -> 2843 | P64: ='Base Financials'!P41 -> 3402 | ... W64: ='Base Financials'!W41 -> 3202 | Y64: =L64 -> 4133 | Z64: =M64 -> 3847 | AA64: =N64 -> 2996 | AB64: =O64 -> 2843 | AC64: =P64 -> 3402 | AD64: =Q64 -> 3323 | AE64: =R64 -> 3131 | AF64: =S64 -> 3121 | ... AI64: =V64 -> 2360
B65: Accounts Payable | C65: ='Base Financials'!C55 -> 5581 | D65: ='Base Financials'!D55 -> 5747 | E65: ='Base Financials'!E55 -> 9595 | F65: ='Base Financials'!F55 -> 8578 | G65: ='Base Financials'!G55 -> 12556 | I65: ='Base Financials'!I55 -> 7210 | J65: ='Base Financials'!J55 -> 7945 | K65: ='Base Financials'!K55 -> 7133 | L65: ='Base Financials'!L55 -> 9595 | M65: ='Base Financials'!M55 -> 8083 | N65: ='Base Financials'!N55 -> 8757 | O65: ='Base Financials'!O55 -> 8669 | P65: ='Base Financials'!P55 -> 8578 | ... W65: ='Base Financials'!W55 -> 10268 | Y65: =L65 -> 9595 | Z65: =M65 -> 8083 | AA65: =N65 -> 8757 | AB65: =O65 -> 8669 | AC65: =P65 -> 8578 | AD65: =Q65 -> 8559 | AE65: =R65 -> 9618 | AF65: =S65 -> 11074 | ... AI65: =V65 -> 10666
B66: Inventories | C66: ='Base Financials'!C42 -> 8427 | D66: ='Base Financials'!D42 -> 10776 | E66: ='Base Financials'!E42 -> 13224 | F66: ='Base Financials'!F42 -> 11127 | G66: ='Base Financials'!G42 -> 12198 | I66: ='Base Financials'!I42 -> 11935 | J66: ='Base Financials'!J42 -> 12174 | K66: ='Base Financials'!K42 -> 12831 | L66: ='Base Financials'!L42 -> 13224 | M66: ='Base Financials'!M42 -> 12993 | N66: ='Base Financials'!N42 -> 11984 | O66: ='Base Financials'!O42 -> 11466 | P66: ='Base Financials'!P42 -> 11127 | ... W66: ='Base Financials'!W42 -> 11489 | AE66: =R66 -> 11244 | AF66: =S66 -> 12062 | AG66: =T66 -> 12198 | AH66: =U66 -> 12281 | AI66: =V66 -> 11377
B67: Property Plant, and Equiptment | C67: ='Base Financials'!C47 -> 56584 | D67: ='Base Financials'!D47 -> 63245 | E67: ='Base Financials'!E47 -> 80860 | F67: ='Base Financials'!F47 -> 96647 | G67: ='Base Financials'!G47 -> 107919 | I67: ='Base Financials'!I47 -> 66718 | J67: ='Base Financials'!J47 -> 71660 | K67: ='Base Financials'!K47 -> 75763 | L67: ='Base Financials'!L47 -> 80860 | M67: ='Base Financials'!M47 -> 85734 | N67: ='Base Financials'!N47 -> 90945 | O67: ='Base Financials'!O47 -> 93352 | P67: ='Base Financials'!P47 -> 96647 | ... W67: ='Base Financials'!W47 -> 105047 | Y67: =L67 -> 80860 | Z67: =M67 -> 85734 | AA67: =N67 -> 90945 | AB67: =O67 -> 93352 | AC67: =P67 -> 96647 | AD67: =Q67 -> 99924 | AE67: =R67 -> 103398 | AF67: =S67 -> 104248 | ... AI67: =V67 -> 109510
B68: Current Liabilities | C68: ='Base Financials'!C61 -> 24754 | D68: ='Base Financials'!D61 -> 27462 | E68: ='Base Financials'!E61 -> 32155 | F68: ='Base Financials'!F61 -> 28053 | G68: ='Base Financials'!G61 -> 35666 | I68: ='Base Financials'!I61 -> 29322 | J68: ='Base Financials'!J61 -> 27218 | K68: ='Base Financials'!K61 -> 27813 | L68: ='Base Financials'!L61 -> 32155 | M68: ='Base Financials'!M61 -> 27393 | N68: ='Base Financials'!N61 -> 27180 | O68: ='Base Financials'!O61 -> 28614 | P68: ='Base Financials'!P61 -> 28053 | ... W68: ='Base Financials'!W61 -> 32297 | Y68: =L68 -> 32155 | Z68: =M68 -> 27393 | AA68: =N68 -> 27180 | AB68: =O68 -> 28614 | AC68: =P68 -> 28053 | AD68: =Q68 -> 27213 | AE68: =R68 -> 32027 | AF68: =S68 -> 35159 | ... AI68: =V68 -> 34966
B69: Total Liabilities | C69: ='Base Financials'!C66 -> 72053 | D69: ='Base Financials'!D66 -> 73015 | E69: ='Base Financials'!E66 -> 78817 | F69: ='Base Financials'!F66 -> 81607 | G69: ='Base Financials'!G66 -> 91453 | I69: ='Base Financials'!I66 -> 73220 | J69: ='Base Financials'!J66 -> 69200 | K69: ='Base Financials'!K66 -> 74956 | L69: ='Base Financials'!L66 -> 78817 | M69: ='Base Financials'!M66 -> 84900 | N69: ='Base Financials'!N66 -> 81158 | O69: ='Base Financials'!O66 -> 83151 | P69: ='Base Financials'!P66 -> 81607 | ... W69: ='Base Financials'!W66 -> 87784 | Y69: =L69 -> 78817 | Z69: =M69 -> 84900 | AA69: =N69 -> 81158 | AB69: =O69 -> 83151 | AC69: =P69 -> 81607 | AD69: =Q69 -> 81977 | AE69: =R69 -> 85771 | AF69: =S69 -> 88678 | ... AI69: =V69 -> 86769
B71: Summary Debt (BS):
B72: CPLTD | C72: ='Base Financials'!C54 -> 2504 | D72: ='Base Financials'!D54 -> 4591 | E72: ='Base Financials'!E54 -> 4367 | F72: ='Base Financials'!F54 -> 2288 | G72: ='Base Financials'!G54 -> 3729 | I72: ='Base Financials'!I54 -> 4459 | J72: ='Base Financials'!J54 -> 2882 | K72: ='Base Financials'!K54 -> 2283 | L72: ='Base Financials'!L54 -> 4367 | M72: ='Base Financials'!M54 -> 1437 | N72: ='Base Financials'!N54 -> 2711 | O72: ='Base Financials'!O54 -> 2288 | P72: ='Base Financials'!P54 -> 2288 | ... W72: ='Base Financials'!W54 -> 2496 | Y72: =L72 -> 4367 | Z72: =M72 -> 1437 | AA72: =N72 -> 2711 | AB72: =O72 -> 2288 | AC72: =P72 -> 2288 | AD72: =Q72 -> 4581 | AE72: =R72 -> 4695 | AF72: =S72 -> 3765 | ... AI72: =V72 -> 6731
B73: LTD | C73: ='Base Financials'!C63 -> 33897 | D73: ='Base Financials'!D63 -> 33510 | E73: ='Base Financials'!E63 -> 37684 | F73: ='Base Financials'!F63 -> 46978 | G73: ='Base Financials'!G63 -> 46282 | I73: ='Base Financials'!I63 -> 32788 | J73: ='Base Financials'!J63 -> 32548 | K73: ='Base Financials'!K63 -> 37240 | L73: ='Base Financials'!L63 -> 37684 | M73: ='Base Financials'!M63 -> 48836 | N73: ='Base Financials'!N63 -> 46335 | O73: ='Base Financials'!O63 -> 46591 | P73: ='Base Financials'!P63 -> 46978 | ... W73: ='Base Financials'!W63 -> 44057 | Y73: =L73 -> 37684 | Z73: =M73 -> 48836 | AA73: =N73 -> 46335 | AB73: =O73 -> 46591 | AC73: =P73 -> 46978 | AD73: =Q73 -> 47869 | AE73: =R73 -> 48334 | AF73: =S73 -> 46471 | ... AI73: =V73 -> 44026
B75: $10.0Bn 4.60% Commercial Paper Program | C75: 0 | D75: 0 | E75: 3900 | F75: 0 | G75: 0 | I75: 0 | J75: 0 | K75: 0 | L75: =E75 -> 3900 | M75: 1000 | N75: 0 | O75: 0 | P75: =F75 -> 0 | Q75: 793 | R75: 3200 | S75: 0 | T75: =G75 -> 0 | U75: 1500 | V75: =3500-1500 -> 2000 | W75: =V75 -> 2000 | Y75: =L75 -> 3900 | Z75: =M75 -> 1000 | AA75: =N75 -> 0 | AB75: =O75 -> 0 | AC75: =P75 -> 0 | AD75: =Q75 -> 793 | AE75: =R75 -> 3200 | AF75: =S75 -> 0 | ... AI75: =V75 -> 2000
B76: Aggregate Sr. Unsecured Notes & Other Borrowings, Current | C76: =C72-C75 -> 2504 | D76: =D72-D75 -> 4591 | E76: =E72-E75 -> 467 | F76: =F72-F75 -> 2288 | G76: =G72-G75 -> 3729 | I76: =I72-I75 -> 4459 | J76: =J72-J75 -> 2882 | K76: =K72-K75 -> 2283 | L76: =L72-L75 -> 467 | M76: =M72-M75 -> 437 | N76: =N72-N75 -> 2711 | O76: =O72-O75 -> 2288 | P76: =P72-P75 -> 2288 | ... W76: =W72-W75 -> 496 | Y76: =L76 -> 467 | Z76: =M76 -> 437 | AA76: =N76 -> 2711 | AB76: =O76 -> 2288 | AC76: =P76 -> 2288 | AD76: =Q76 -> 3788 | AE76: =R76 -> 1495 | AF76: =S76 -> 3765 | ... AI76: =V76 -> 4731
B77: Aggregate Sr. Unsecured Notes & Other Borrowings, Non-Current | C77: =C73 -> 33897 | D77: =D73 -> 33510 | E77: =E73 -> 37684 | F77: =F73 -> 46978 | G77: =G73 -> 46282 | I77: =I73 -> 32788 | J77: =J73 -> 32548 | K77: =K73 -> 37240 | L77: =L73 -> 37684 | M77: =M73 -> 48836 | N77: =N73 -> 46335 | O77: =O73 -> 46591 | P77: =P73 -> 46978 | ... W77: =W73 -> 44057 | Y77: =L77 -> 37684 | Z77: =M77 -> 48836 | AA77: =N77 -> 46335 | AB77: =O77 -> 46591 | AC77: =P77 -> 46978 | AD77: =Q77 -> 47869 | AE77: =R77 -> 48334 | AF77: =S77 -> 46471 | ... AI77: =V77 -> 44026
B78: Total Debt | C78: =SUM(C75:C77) -> 36401 | D78: =SUM(D75:D77) -> 38101 | E78: =SUM(E75:E77) -> 42051 | F78: =SUM(F75:F77) -> 49266 | G78: =SUM(G75:G77) -> 50011 | I78: =SUM(I75:I77) -> 37247 | J78: =SUM(J75:J77) -> 35430 | K78: =SUM(K75:K77) -> 39523 | L78: =SUM(L75:L77) -> 42051 | M78: =SUM(M75:M77) -> 50273 | N78: =SUM(N75:N77) -> 49046 | O78: =SUM(O75:O77) -> 48879 | P78: =SUM(P75:P77) -> 49266 | ... W78: =SUM(W75:W77) -> 46553 | Y78: =SUM(Y75:Y77) -> 42051 | Z78: =SUM(Z75:Z77) -> 50273 | AA78: =SUM(AA75:AA77) -> 49046 | AB78: =SUM(AB75:AB77) -> 48879 | AC78: =SUM(AC75:AC77) -> 49266 | AD78: =SUM(AD75:AD77) -> 52450 | AE78: =SUM(AE75:AE77) -> 53029 | AF78: =SUM(AF75:AF77) -> 50236 | ... AI78: =SUM(AI75:AI77) -> 50757
B80: Total Shareholder Equity | C80: ='Base Financials'!C74 -> 81038 | D80: ='Base Financials'!D74 -> 95391 | E80: ='Base Financials'!E74 -> 103286 | F80: ='Base Financials'!F74 -> 109965 | G80: ='Base Financials'!G74 -> 105032 | I80: ='Base Financials'!I74 -> 103136 | J80: ='Base Financials'!J74 -> 101218 | K80: ='Base Financials'!K74 -> 99885 | L80: ='Base Financials'!L74 -> 103286 | M80: ='Base Financials'!M74 -> 100403 | N80: ='Base Financials'!N74 -> 104471 | O80: ='Base Financials'!O74 -> 105686 | P80: ='Base Financials'!P74 -> 109965 | ... W80: ='Base Financials'!W74 -> 116730 | Y80: =L80 -> 103286 | Z80: =M80 -> 100403 | AA80: =N80 -> 104471 | AB80: =O80 -> 105686 | AC80: =P80 -> 109965 | AD80: =Q80 -> 110756 | AE80: =R80 -> 120434 | AF80: =S80 -> 104864 | ... AI80: =V80 -> 105751
B81: Total Book Capitalization | C81: =SUM(C78:C80) -> 117439 | D81: =SUM(D78:D80) -> 133492 | E81: =SUM(E78:E80) -> 145337 | F81: =SUM(F78:F80) -> 159231 | G81: =SUM(G78:G80) -> 155043 | I81: =SUM(I78:I80) -> 140383 | J81: =SUM(J78:J80) -> 136648 | K81: =SUM(K78:K80) -> 139408 | L81: =SUM(L78:L80) -> 145337 | M81: =SUM(M78:M80) -> 150676 | N81: =SUM(N78:N80) -> 153517 | O81: =SUM(O78:O80) -> 154565 | P81: =SUM(P78:P80) -> 159231 | ... W81: =SUM(W78:W80) -> 163283 | Y81: =SUM(Y78:Y80) -> 145337 | Z81: =SUM(Z78:Z80) -> 150676 | AA81: =SUM(AA78:AA80) -> 153517 | AB81: =SUM(AB78:AB80) -> 154565 | AC81: =SUM(AC78:AC80) -> 159231 | AD81: =SUM(AD78:AD80) -> 163206 | AE81: =SUM(AE78:AE80) -> 173463 | AF81: =SUM(AF78:AF80) -> 155100 | ... AI81: =SUM(AI78:AI80) -> 156508
B83: Credit Metrics
B85: Total Leverage | C85: =C78/C32 -> 1.0115885 | D85: =D78/D32 -> 1.1059155 | E85: =E78/E32 -> 2.9492916 | F85: =F78/F32 -> 3.9545673 | G85: =G78/G32 -> 7.8683134 | L85: =SUM(L78/SUM(I32:L32)) -> 2.9492916 | M85: =SUM(M78/SUM(J32:M32)) -> 4.0477613 | N85: =SUM(N78/SUM(K32:N32)) -> 4.3365412 | O85: =SUM(O78/SUM(L32:O32)) -> 4.6841609 | P85: =SUM(P78/SUM(M32:P32)) -> 3.9545673 | Q85: =SUM(Q78/SUM(N32:Q32)) -> 3.8189894 | R85: =SUM(R78/SUM(O32:R32)) -> 3.8474207 | S85: =SUM(S78/SUM(P32:S32)) -> 6.4695428 | ... W85: =SUM(W78/SUM(T32:W32)) -> 8.555964 | Y85: =Y78/Y32 -> 2.1486383 | Z85: =Z78/Z32 -> 4.0367107 | AA85: =AA78/AA32 -> 4.2771672 | AB85: =AB78/AB32 -> 4.6313452 | AC85: =AC78/AC32 -> 3.94128 | AD85: =AD78/AD32 -> 3.7960483 | AE85: =AE78/AE32 -> 3.8474207 | AF85: =AF78/AF32 -> 6.4695428 | ... AI85: =AI78/AI32 -> 10.908446
B86: Net Leverage (C&CE) | C86: =SUM(C78-C57)/C32 -> 0.84859938 | D86: =SUM(D78-D57)/D32 -> 0.9658075 | E86: =SUM(E78-E57)/E32 -> 2.1676953 | F86: =SUM(F78-F57)/F32 -> 3.3863381 | G86: =SUM(G78-G57)/G32 -> 6.5704846 | L86: =SUM(L78-L57)/SUM(I32:L32) -> 2.1676953 | M86: =SUM(M78-M57)/SUM(J32:M32) -> 3.3849568 | N86: =SUM(N78-N57)/SUM(K32:N32) -> 3.5983407 | O86: =SUM(O78-O57)/SUM(L32:O32) -> 3.953827 | P86: =SUM(P78-P57)/SUM(M32:P32) -> 3.3863381 | Q86: =SUM(Q78-Q57)/SUM(N32:Q32) -> 3.3149119 | R86: =SUM(R78-R57)/SUM(O32:R32) -> 3.0285134 | S86: =SUM(S78-S57)/SUM(P32:S32) -> 5.3381842 | ... W86: =SUM(W78-W57)/SUM(T32:W32) -> 6.5083624 | Y86: =SUM(Y78-Y57)/Y32 -> 1.5792244 | Z86: =SUM(Z78-Z57)/Z32 -> 3.3757157 | AA86: =SUM(AA78-AA57)/AA32 -> 3.5490738 | AB86: =SUM(AB78-AB57)/AB32 -> 3.9092461 | AC86: =SUM(AC78-AC57)/AC32 -> 3.37496 | AD86: =SUM(AD78-AD57)/AD32 -> 3.2949989 | AE86: =SUM(AE78-AE57)/AE32 -> 3.0285134 | AF86: =SUM(AF78-AF57)/AF32 -> 5.3381842 | ... AI86: =SUM(AI78-AI57)/AI32 -> 8.8360198
B87: Interest Coverage | C87: =C32/-C36 -> 60.579125 | D87: =D32/-D36 -> 63.214679 | E87: =E32/-E36 -> 31.063181 | F87: =F32/-F36 -> 20.323002 | G87: =G32/-G36 -> 6.4397163 | L87: {=SUM(I32:L32)/SUM(-I36:L36)} -> 31.063181 | M87: {=SUM(J32:M32)/SUM(-J36:M36)} -> 23.838679 | N87: {=SUM(K32:N32)/SUM(-K36:N36)} -> 27.856984 | O87: {=SUM(L32:O32)/SUM(-L36:O36)} -> 12.930549 | P87: {=SUM(M32:P32)/SUM(-M36:P36)} -> 20.323002 | Q87: {=SUM(N32:Q32)/SUM(-N36:Q36)} -> 15.026258 | R87: {=SUM(O32:R32)/SUM(-O36:R36)} -> 14.662766 | S87: {=SUM(P32:S32)/SUM(-P36:S36)} -> 7.4022879 | ... W87: {=SUM(T32:W32)/SUM(-T36:W36)} -> 19.362989 | Y87: =Y32/-Y36 -> 42.638344 | Z87: =Z32/-Z36 -> 23.903938 | AA87: =AA32/-AA36 -> 28.243683 | AB87: =AB32/-AB36 -> 13.078009 | AC87: =AC32/-AC36 -> 20.391517 | AD87: =AD32/-AD36 -> 15.117068 | AE87: =AE32/-AE36 -> 14.662766 | AF87: =AF32/-AF36 -> 7.4022879 | ... AI87: =AI32/-AI36 -> 4.5932873
B88: Debt Service Coverage | C88: {=SUM(C32+C35)/SUM(-C36:C38)} -> 7.169967 | D88: {=SUM(D32+D35)/SUM(-D36:D38)} -> 5.5979345 | E88: {=SUM(E32+E35)/SUM(-E36:E38)} -> -2.2328623 | F88: {=SUM(F32+F35)/SUM(-F36:F38)} -> -4.1100804 | G88: {=SUM(G32+G35)/SUM(-G36:G38)} -> -5.5152085 | L88: {=SUM(I32:L32+I35:L35)/SUM(-I36:L38)} -> -2.2328623 | M88: {=SUM(J32:M32+J35:M35)/SUM(-J36:M38)} -> -3.2171169 | N88: {=SUM(K32:N32+K35:N35)/SUM(-K36:N38)} -> -5.2009246 | O88: {=SUM(L32:O32+L35:O35)/SUM(-L36:O38)} -> -5.1540845 | P88: {=SUM(M32:P32+M35:P35)/SUM(-M36:P38)} -> -4.1100804 | Q88: {=SUM(N32:Q32+N35:Q35)/SUM(-N36:Q38)} -> -2.9508792 | R88: {=SUM(O32:R32+O35:R35)/SUM(-O36:R38)} -> -2.8692992 | S88: {=SUM(P32:S32+P35:S35)/SUM(-P36:S38)} -> -4.3683671 | ... W88: {=SUM(T32:W32+T35:W35)/SUM(-T36:W38)} -> -2.9110383 | Y88: {=SUM(Y32+Y35)/SUM(-Y36:Y38)} -> -1.1122126 | Z88: {=SUM(Z32+Z35)/SUM(-Z36:Z38)} -> -3.2099363 | AA88: {=SUM(AA32+AA35)/SUM(-AA36:AA38)} -> -5.1464485 | AB88: {=SUM(AB32+AB35)/SUM(-AB36:AB38)} -> -5.111248 | AC88: {=SUM(AC32+AC35)/SUM(-AC36:AC38)} -> -4.0970934 | AD88: {=SUM(AD32+AD35)/SUM(-AD36:AD38)} -> -2.9277142 | AE88: {=SUM(AE32+AE35)/SUM(-AE36:AE38)} -> -2.8692992 | AF88: {=SUM(AF32+AF35)/SUM(-AF36:AF38)} -> -4.3683671 | ... AI88: {=SUM(AI32+AI35)/SUM(-AI36:AI38)} -> -4.7413843
B89: Fixed Charge Coverage | C89: {=SUM(C32)/SUM(-C35:C38)} -> 2.0813234 | D89: {=SUM(D32)/SUM(-D35:D38)} -> 1.5993686 | E89: {=SUM(E32)/SUM(-E35:E38)} -> 0.48193341 | F89: {=SUM(F32)/SUM(-F35:F38)} -> 0.42982335 | G89: {=SUM(G32)/SUM(-G35:G38)} -> 0.23425349 | L89: {=SUM(I32:L32)/SUM(-I35:L38)} -> 0.48193341 | M89: {=SUM(J32:M32)/SUM(-J35:M38)} -> 0.38347387 | N89: {=SUM(K32:N32)/SUM(-K35:N38)} -> 0.38757874 | O89: {=SUM(L32:O32)/SUM(-L35:O38)} -> 0.37902558 | P89: {=SUM(M32:P32)/SUM(-M35:P38)} -> 0.42982335 | Q89: {=SUM(N32:Q32)/SUM(-N35:Q38)} -> 0.49243456 | R89: {=SUM(O32:R32)/SUM(-O35:R38)} -> 0.49763512 | S89: {=SUM(P32:S32)/SUM(-P35:S38)} -> 0.27049152 | ... W89: {=SUM(T32:W32)/SUM(-T35:W38)} -> 0.25958969 | Y89: {=SUM(Y32)/SUM(-Y35:Y38)} -> 0.66151766 | Z89: {=SUM(Z32)/SUM(-Z35:Z38)} -> 0.38452364 | AA89: {=SUM(AA32)/SUM(-AA35:AA38)} -> 0.39295896 | AB89: {=SUM(AB32)/SUM(-AB35:AB38)} -> 0.38334798 | AC89: {=SUM(AC32)/SUM(-AC35:AC38)} -> 0.43127243 | AD89: {=SUM(AD32)/SUM(-AD35:AD38)} -> 0.49541054 | AE89: {=SUM(AE32)/SUM(-AE35:AE38)} -> 0.49763512 | AF89: {=SUM(AF32)/SUM(-AF35:AF38)} -> 0.27049152 | ... AI89: {=SUM(AI32)/SUM(-AI35:AI38)} -> 0.19008906
B90: Debt-to-Book Capitalization | C90: =C81/C78 -> 3.2262575 | D90: =D81/D78 -> 3.5036351 | E90: =E81/E78 -> 3.4562079 | F90: =F81/F78 -> 3.2320667 | G90: =G81/G78 -> 3.100178 | L90: =L81/L78 -> 3.4562079 | M90: =M81/M78 -> 2.9971555 | N90: =N81/N78 -> 3.1300616 | O90: =O81/O78 -> 3.1621964 | P90: =P81/P78 -> 3.2320667 | Q90: =Q81/Q78 -> 3.1116492 | R90: =R81/R78 -> 3.2710969 | S90: =S81/S78 -> 3.0874273 | ... W90: =W81/W78 -> 3.5074646 | Y90: =Y81/Y78 -> 3.4562079 | Z90: =Z81/Z78 -> 2.9971555 | AA90: =AA81/AA78 -> 3.1300616 | AB90: =AB81/AB78 -> 3.1621964 | AC90: =AC81/AC78 -> 3.2320667 | AD90: =AD81/AD78 -> 3.1116492 | AE90: =AE81/AE78 -> 3.2710969 | AF90: =AF81/AF78 -> 3.0874273 | ... AI90: =AI81/AI78 -> 3.0834762

Sheet Revenue Drivers
B2: Intel, Corporation. (NASDAQ: INTC) | C2: FYE | D2: FYE | E2: FYE | I2: Quarterly | Q2: Quarterly | R2: Quarterly | Y2: LTM | AC2: LTM | AK2: Variance
B3: Segment Anaysis | C3: ='Base Financials'!C3 -> 2020 | D3: ='Base Financials'!D3 -> 2021 | E3: ='Base Financials'!E3 -> 2022 | F3: ='Base Financials'!F3 -> 2023 | G3: ='Base Financials'!G3 -> 2024 | I3: ='Base Financials'!I3 -> 1Q22 | J3: ='Base Financials'!J3 -> 2Q22 | K3: ='Base Financials'!K3 -> 3Q22 | L3: ='Base Financials'!L3 -> 4Q22 | M3: ='Base Financials'!M3 -> 1Q23 | N3: ='Base Financials'!N3 -> 2Q23 | O3: ='Base Financials'!O3 -> 3Q23 | P3: ='Base Financials'!P3 -> 4Q23 | ... W3: ='Base Financials'!W3 -> 3Q25 | Y3: =M3 -> 1Q23 | Z3: =N3 -> 2Q23 | AA3: =O3 -> 3Q23 | AB3: =P3 -> 4Q23 | AC3: =Q3 -> 1Q24 | AD3: =R3 -> 2Q24 | AE3: =S3 -> 3Q24 | AF3: =T3 -> 4Q24 | ... AI3: =W3 -> 3Q25
B4: ($ In Millions) | C4: ='Base Financials'!C4 -> 44191 | D4: ='Base Financials'!D4 -> 44555 | E4: ='Base Financials'!E4 -> 44926 | F4: ='Base Financials'!F4 -> 45290 | G4: ='Base Financials'!G4 -> 45654 | I4: ='Base Financials'!I4 -> 44653 | J4: ='Base Financials'!J4 -> 44744 | K4: ='Base Financials'!K4 -> 44835 | L4: ='Base Financials'!L4 -> 44926 | M4: ='Base Financials'!M4 -> 45017 | N4: ='Base Financials'!N4 -> 45108 | O4: ='Base Financials'!O4 -> 45199 | P4: ='Base Financials'!P4 -> 45290 | ... W4: ='Base Financials'!W4 -> 45925 | Y4: =M4 -> 45017 | Z4: =N4 -> 45108 | AA4: =O4 -> 45199 | AB4: =P4 -> 45290 | AC4: =Q4 -> 45381 | AD4: =R4 -> 45472 | AE4: =S4 -> 45563 | AF4: =T4 -> 45654 | ... AI4: =W4 -> 45925
A6: X | B6: Revenue by End Market
B7: Intel Products | C7: =C20 -> 71080 | D7: =D20 -> 69532 | E7: =E20 -> 57038 | F7: =F20 -> 47667 | G7: =G20 -> 48949 | I7: =I20 -> 17467 | J7: =J20 -> 14073 | K7: =K20 -> 13881 | L7: =SUM(E7-SUM(I7:K7)) -> 11617 | M7: =M20 -> 10157 | N7: =N20 -> 11299 | O7: =O20 -> 12393 | P7: =SUM(F7-SUM(M7:O7)) -> 13818 | Q7: 11933 | R7: 11799 | S7: 12190 | T7: =SUM(G7-SUM(Q7:S7)) -> 13027 | U7: =U20 -> 11755 | V7: =V20 -> 11810 | W7: =W20 -> 12652 | Y7: =SUM(J7:M7) -> 49728 | Z7: =SUM(K7:N7) -> 46954 | AA7: =SUM(L7:O7) -> 45466 | AB7: =SUM(M7:P7) -> 47667 | AC7: =SUM(N7:Q7) -> 49443 | AD7: =SUM(O7:R7) -> 49943 | AE7: =SUM(P7:S7) -> 49740 | AF7: =SUM(Q7:T7) -> 48949 | ... AI7: =SUM(T7:W7) -> 49244 | AK7: =SUM(AI7/AE7)-1 -> -0.0099718536
B8: Intel Foundry | C8: =C32 -> 715 | D8: =D32 -> 22849 | E8: =E32 -> 27491.2 | F8: =F32 -> 18910 | G8: 17543 | I8: =I32 -> 6958.517 | J8: =J32 -> 7324.9181 | K8: =K32 -> 6651.167 | L8: =SUM(E8-SUM(I8:K8)) -> 6556.5979 | M8: =M32 -> 4831 | N8: =N32 -> 4172 | O8: =O32 -> 4732 | P8: =SUM(F8-SUM(M8:O8)) -> 5175 | Q8: 4369 | R8: 4320 | S8: 4352 | T8: =SUM(G8-SUM(Q8:S8)) -> 4502 | U8: =U32 -> 4667 | V8: =V32 -> 4417 | W8: =W32 -> 4235 | Y8: =SUM(J8:M8) -> 25363.683 | Z8: =SUM(K8:N8) -> 22210.765 | AA8: =SUM(L8:O8) -> 20291.598 | AB8: =SUM(M8:P8) -> 18910 | AC8: =SUM(N8:Q8) -> 18448 | AD8: =SUM(O8:R8) -> 18596 | AE8: =SUM(P8:S8) -> 18216 | AF8: =SUM(Q8:T8) -> 17543 | ... AI8: =SUM(T8:W8) -> 17821 | AK8: =SUM(AI8/AE8)-1 -> -0.021684234
B9: All Other | C9: =5091+651+967 -> 6709 | D9: =D39 -> 9137 | E9: =E39 -> 5529.8 | F9: =F39 -> 5608 | G9: 3824 | I9: =I39 -> 1121.0484 | J9: =J39 -> 1160.0163 | K9: =K39 -> 1499.9821 | L9: =SUM(E9-SUM(I9:K9)) -> 1748.7532 | M9: =M39 -> 1440 | N9: =N39 -> 1419 | O9: =O39 -> 1452 | P9: =SUM(F9-SUM(M9:O9)) -> 1297 | Q9: 775 | R9: 968 | S9: 1039 | T9: =SUM(G9-SUM(Q9:S9)) -> 1042 | U9: =U39 -> 943 | V9: =V39 -> 1053 | W9: =W39 -> 993 | Y9: =SUM(J9:M9) -> 5848.7516 | Z9: =SUM(K9:N9) -> 6107.7353 | AA9: =SUM(L9:O9) -> 6059.7532 | AB9: =SUM(M9:P9) -> 5608 | AC9: =SUM(N9:Q9) -> 4943 | AD9: =SUM(O9:R9) -> 4492 | AE9: =SUM(P9:S9) -> 4079 | AF9: =SUM(Q9:T9) -> 3824 | ... AI9: =SUM(T9:W9) -> 4031 | AK9: =SUM(AI9/AE9)-1 -> -0.01176759
B10: Total Gross Revenue | C10: =SUM(C7:C9) -> 78504 | D10: =SUM(D7:D9) -> 101518 | E10: =SUM(E7:E9) -> 90059 | F10: =SUM(F7:F9) -> 72185 | G10: =SUM(G7:G9) -> 70316 | I10: =SUM(I7:I9) -> 25546.565 | J10: =SUM(J7:J9) -> 22557.934 | K10: =SUM(K7:K9) -> 22032.149 | L10: =SUM(L7:L9) -> 19922.351 | M10: =SUM(M7:M9) -> 16428 | N10: =SUM(N7:N9) -> 16890 | O10: =SUM(O7:O9) -> 18577 | P10: =SUM(P7:P9) -> 20290 | ... W10: =SUM(W7:W9) -> 17880 | Y10: =SUM(Y7:Y9) -> 80940.435 | Z10: =SUM(Z7:Z9) -> 75272.5 | AA10: =SUM(AA7:AA9) -> 71817.351 | AB10: =SUM(AB7:AB9) -> 72185 | AC10: =SUM(AC7:AC9) -> 72834 | AD10: =SUM(AD7:AD9) -> 73031 | AE10: =SUM(AE7:AE9) -> 72035 | AF10: =SUM(AF7:AF9) -> 70316 | ... AI10: =SUM(AI7:AI9) -> 71096 | AK10: =SUM(AI10/AE10)-1 -> -0.01303533
B12: (-) Intersegment Elimination | C12: -637 | D12: -22494 | E12: -27005 | F12: -17957 | G12: -17215 | I12: -6797.517 | J12: -7263.9181 | K12: -6569.167 | L12: =SUM(E12-SUM(I12:K12)) -> -6374.3979 | M12: -4713 | N12: -3941 | O12: -4419 | P12: -4884 | Q12: -4353 | R12: -4254 | S12: -4297 | T12: =SUM(G12-SUM(Q12:S12)) -> -4311 | U12: -4698 | V12: -4421 | W12: -4227 | Y12: =SUM(J12:M12) -> -24920.483 | Z12: =SUM(K12:N12) -> -21597.565 | AA12: =SUM(L12:O12) -> -19447.398 | AB12: =SUM(M12:P12) -> -17957 | AC12: =SUM(N12:Q12) -> -17597 | AD12: =SUM(O12:R12) -> -17910 | AE12: =SUM(P12:S12) -> -17788 | AF12: =SUM(Q12:T12) -> -17215 | ... AI12: =SUM(T12:W12) -> -17657 | AK12: =SUM(AI12/AE12)-1 -> -0.0073645154
B13: Total Net Revenue | C13: =SUM(C10+C12) -> 77867 | D13: =SUM(D10+D12) -> 79024 | E13: =SUM(E10+E12) -> 63054 | F13: =SUM(F10+F12) -> 54228 | G13: =SUM(G10+G12) -> 53101 | I13: =SUM(I10+I12) -> 18749.048 | J13: =SUM(J10+J12) -> 15294.016 | K13: =SUM(K10+K12) -> 15462.982 | L13: =SUM(L10+L12) -> 13547.953 | M13: =SUM(M10+M12) -> 11715 | N13: =SUM(N10+N12) -> 12949 | O13: =SUM(O10+O12) -> 14158 | P13: =SUM(P10+P12) -> 15406 | ... W13: =SUM(W10+W12) -> 13653 | Y13: =SUM(Y10+Y12) -> 56019.952 | Z13: =SUM(Z10+Z12) -> 53674.935 | AA13: =SUM(AA10+AA12) -> 52369.953 | AB13: =SUM(AB10+AB12) -> 54228 | AC13: =SUM(AC10+AC12) -> 55237 | AD13: =SUM(AD10+AD12) -> 55121 | AE13: =SUM(AE10+AE12) -> 54247 | AF13: =SUM(AF10+AF12) -> 53101 | ... AI13: =SUM(AI10+AI12) -> 53439 | AK13: =SUM(AI13/AE13)-1 -> -0.014894833
B14: Balance Check | C14: =C13-'Base Financials'!C9 -> 0 | D14: =D13-'Base Financials'!D9 -> 0 | E14: =E13-'Base Financials'!E9 -> 0 | F14: =F13-'Base Financials'!F9 -> 0 | G14: =G13-'Base Financials'!G9 -> 0 | I14: =I13-'Base Financials'!I9 -> 396.04839 | J14: =J13-'Base Financials'!J9 -> -26.983687 | K14: =K13-'Base Financials'!K9 -> 124.98213 | L14: =L13-'Base Financials'!L9 -> -494.04683 | M14: =M13-'Base Financials'!M9 -> 0 | N14: =N13-'Base Financials'!N9 -> 0 | O14: =O13-'Base Financials'!O9 -> 0 | P14: =P13-'Base Financials'!P9 -> 0 | ... W14: =W13-'Base Financials'!W9 -> 0 | Y14: =Y13-'Base Financials'!Y9 -> -396.04839 | Z14: =Z13-'Base Financials'!Z9 -> -369.0647 | AA14: =AA13-'Base Financials'!AA9 -> -494.04683 | AB14: =AB13-'Base Financials'!AB9 -> 0 | AC14: =AC13-'Base Financials'!AC9 -> 0 | AD14: =AD13-'Base Financials'!AD9 -> 0 | AE14: =AE13-'Base Financials'!AE9 -> 0 | AF14: =AF13-'Base Financials'!AF9 -> 0 | ... AI14: =AI13-'Base Financials'!AI9 -> 0
A16: X | B16: Revenue by Product Offerings: Intel Products
B17: Client Computing Group (CCG) | C17: 40535 | D17: 41081 | E17: 31773 | F17: 29258 | G17: 30290 | I17: 9294 | J17: 7678 | K17: 8129 | L17: =SUM(E17-SUM(I17:K17)) -> 6672 | M17: 5767 | N17: 6780 | O17: 7867 | P17: =SUM(F17-SUM(M17:O17)) -> 8844 | Q17: 8273 | R17: 8143 | S17: 8161 | T17: =SUM(G17-SUM(Q17:S17)) -> 5713 | U17: 7629 | V17: 7871 | W17: 8535 | Y17: =SUM(J17:M17) -> 28246 | Z17: =SUM(K17:N17) -> 27348 | AA17: =SUM(L17:O17) -> 27086 | AB17: =SUM(M17:P17) -> 29258 | AC17: =SUM(N17:Q17) -> 31764 | AD17: =SUM(O17:R17) -> 33127 | AE17: =SUM(P17:S17) -> 33421 | AF17: =SUM(Q17:T17) -> 30290 | ... AI17: =SUM(T17:W17) -> 29748 | AK17: =SUM(AI17/AE17)-1 -> -0.10990096
B18: Data Center & AI (DCAI) | C18: 23413 | D18: =D26 -> 20786 | E18: =E26 -> 16856 | F18: =F26 -> 12635 | G18: 12817 | I18: 6034 | J18: 4185 | K18: 3619 | L18: =SUM(E18-SUM(I18:K18)) -> 3018 | M18: 2901 | N18: 3155 | O18: 3076 | P18: =SUM(F18-SUM(M18:O18)) -> 3503 | Q18: 3828 | R18: 3805 | S18: 4141 | T18: =SUM(G18-SUM(Q18:S18)) -> 1043 | U18: 4126 | V18: 3939 | W18: 4117 | Y18: =SUM(J18:M18) -> 13723 | Z18: =SUM(K18:N18) -> 12693 | AA18: =SUM(L18:O18) -> 12150 | AB18: =SUM(M18:P18) -> 12635 | AC18: =SUM(N18:Q18) -> 13562 | AD18: =SUM(O18:R18) -> 14212 | AE18: =SUM(P18:S18) -> 15277 | AF18: =SUM(Q18:T18) -> 12817 | ... AI18: =SUM(T18:W18) -> 13225 | AK18: =SUM(AI18/AE18)-1 -> -0.13431957
B19: Networking & Edge (NEX) | C19: 7132 | D19: 7665 | E19: 8409 | F19: 5774 | G19: 5842 | I19: 2139 | J19: 2210 | K19: 2133 | L19: =SUM(E19-SUM(I19:K19)) -> 1927 | M19: 1489 | N19: 1364 | O19: 1450 | P19: =SUM(F19-SUM(M19:O19)) -> 1471 | Q19: 1364 | R19: 1344 | S19: 1511 | T19: =SUM(G19-SUM(Q19:S19)) -> 1623 | U19: 0 | V19: 0 | W19: 0 | Y19: =SUM(J19:M19) -> 7759 | Z19: =SUM(K19:N19) -> 6913 | AA19: =SUM(L19:O19) -> 6230 | AB19: =SUM(M19:P19) -> 5774 | AC19: =SUM(N19:Q19) -> 5649 | AD19: =SUM(O19:R19) -> 5629 | AE19: =SUM(P19:S19) -> 5690 | AF19: =SUM(Q19:T19) -> 5842 | ... AI19: =SUM(T19:W19) -> 1623 | AK19: =SUM(AI19/AE19)-1 -> -0.71476274
B20: Total Intel Products Revenue | C20: =SUM(C17:C19) -> 71080 | D20: =SUM(D17:D19) -> 69532 | E20: =SUM(E17:E19) -> 57038 | F20: =SUM(F17:F19) -> 47667 | G20: =SUM(G17:G19) -> 48949 | I20: =SUM(I17:I19) -> 17467 | J20: =SUM(J17:J19) -> 14073 | K20: =SUM(K17:K19) -> 13881 | L20: =SUM(L17:L19) -> 11617 | M20: =SUM(M17:M19) -> 10157 | N20: =SUM(N17:N19) -> 11299 | O20: =SUM(O17:O19) -> 12393 | P20: =SUM(P17:P19) -> 13818 | ... W20: =SUM(W17:W19) -> 12652 | Y20: =SUM(Y17:Y19) -> 49728 | Z20: =SUM(Z17:Z19) -> 46954 | AA20: =SUM(AA17:AA19) -> 45466 | AB20: =SUM(AB17:AB19) -> 47667 | AC20: =SUM(AC17:AC19) -> 50975 | AD20: =SUM(AD17:AD19) -> 52968 | AE20: =SUM(AE17:AE19) -> 54388 | AF20: =SUM(AF17:AF19) -> 48949 | ... AI20: =SUM(AI17:AI19) -> 44596 | AK20: =SUM(AI20/AE20)-1 -> -0.18003971
B21: Balance Check | C21: =C7-C20 -> 0 | D21: =D7-D20 -> 0 | E21: =E7-E20 -> 0 | F21: =F7-F20 -> 0 | G21: =G7-G20 -> 0 | I21: =I7-I20 -> 0 | J21: =J7-J20 -> 0 | K21: =K7-K20 -> 0 | L21: =L7-L20 -> 0 | M21: =M7-M20 -> 0 | N21: =N7-N20 -> 0 | O21: =O7-O20 -> 0 | P21: =P7-P20 -> 0 | ... W21: =W7-W20 -> 0 | Y21: =Y7-Y20 -> 0 | Z21: =Z7-Z20 -> 0 | AA21: =AA7-AA20 -> 0 | AB21: =AB7-AB20 -> 0 | AC21: =AC7-AC20 -> -1532 | AD21: =AD7-AD20 -> -3025 | AE21: =AE7-AE20 -> -4648 | AF21: =AF7-AF20 -> 0 | ... AI21: =AI7-AI20 -> 4648
A23: X | B23: Revenue by Product Offerings: Intel Products: Data Center & AI (DCAI)
B24: Server CPU | C24: 21735.865 | D24: 20756.489 | E24: 16817.566 | F24: 12353.643 | G24: 12777.653 | I24: 5522.311 | J24: 4177.2577 | K24: 3609.1776 | L24: =SUM(E24-SUM(I24:K24)) -> 3508.8194 | M24: 2748.5314 | N24: 3026.112 | O24: 3076 | P24: =SUM(F24-SUM(M24:O24)) -> 3503 | Q24: 3017.7612 | R24: 3095.0084 | S24: 3307.4416 | T24: =SUM(G24-SUM(Q24:S24)) -> 3357.4422 | U24: 3018.5815 | V24: 2994.0267 | W24: 3285.6195 | Y24: =SUM(J24:M24) -> 14043.786 | Z24: =SUM(K24:N24) -> 12892.64 | AA24: =SUM(L24:O24) -> 12359.463 | AB24: =SUM(M24:P24) -> 12353.643 | AC24: =SUM(N24:Q24) -> 12622.873 | AD24: =SUM(O24:R24) -> 12691.77 | AE24: =SUM(P24:S24) -> 12923.211 | AF24: =SUM(Q24:T24) -> 12777.653 | ... AI24: =SUM(T24:W24) -> 12655.67 | AK24: =SUM(AI24/AE24)-1 -> -0.020702379
B25: Accelerator & Other | D25: 29.511485 | E25: 38.434366 | F25: 281.35654 | G25: 3347.3466 | I25: 4.6890102 | J25: 7.7423099 | K25: 9.8224 | L25: =SUM(E25-SUM(I25:K25)) -> 16.180646 | M25: 152.46856 | N25: 128.88798 | O25: 0 | P25: =SUM(F25-SUM(M25:O25)) -> 0 | Q25: 810.2388 | R25: 709.99164 | S25: 833.55841 | T25: =SUM(G25-SUM(Q25:S25)) -> 993.55776 | U25: 1107.4185 | V25: 944.97325 | W25: 831.38053 | Y25: =SUM(J25:M25) -> 186.21391 | Z25: =SUM(K25:N25) -> 307.35958 | AA25: =SUM(L25:O25) -> 297.53718 | AB25: =SUM(M25:P25) -> 281.35654 | AC25: =SUM(N25:Q25) -> 939.12678 | AD25: =SUM(O25:R25) -> 1520.2304 | AE25: =SUM(P25:S25) -> 2353.7889 | AF25: =SUM(Q25:T25) -> 3347.3466 | ... AI25: =SUM(T25:W25) -> 3877.3301 | AK25: =SUM(AI25/AE25)-1 -> 0.64727183
B26: Total Intel Products Revenue | C26: =SUM(C24:C25) -> 21735.865 | D26: =SUM(D24:D25) -> 20786 | E26: =SUM(E24:E25) -> 16856 | F26: =SUM(F24:F25) -> 12635 | G26: =SUM(G24:G25) -> 16125 | I26: =SUM(I24:I25) -> 5527 | J26: =SUM(J24:J25) -> 4185 | K26: =SUM(K24:K25) -> 3619 | L26: =SUM(L24:L25) -> 3525 | M26: =SUM(M24:M25) -> 2901 | N26: =SUM(N24:N25) -> 3155 | O26: =SUM(O24:O25) -> 3076 | P26: =SUM(P24:P25) -> 3503 | ... W26: =SUM(W24:W25) -> 4117 | Y26: =SUM(Y24:Y25) -> 14230 | Z26: =SUM(Z24:Z25) -> 13200 | AA26: =SUM(AA24:AA25) -> 12657 | AB26: =SUM(AB24:AB25) -> 12635 | AC26: =SUM(AC24:AC25) -> 13562 | AD26: =SUM(AD24:AD25) -> 14212 | AE26: =SUM(AE24:AE25) -> 15277 | AF26: =SUM(AF24:AF25) -> 16125 | ... AI26: =SUM(AI24:AI25) -> 16533 | AK26: =SUM(AI26/AE26)-1 -> 0.082215095
B27: Balance Check | C27: =C18-C26 -> 1677.1345 | D27: =D18-D26 -> 0 | E27: =E18-E26 -> 0 | F27: =F18-F26 -> 0 | G27: =G18-G26 -> -3308 | I27: =I18-I26 -> 507 | J27: =J18-J26 -> 0 | K27: =K18-K26 -> 0 | L27: =L18-L26 -> -507 | M27: =M18-M26 -> 0 | N27: =N18-N26 -> 0 | O27: =O18-O26 -> 0 | P27: =P18-P26 -> 0 | ... W27: =W18-W26 -> 0 | Y27: =Y18-Y26 -> -507 | Z27: =Z18-Z26 -> -507 | AA27: =AA18-AA26 -> -507 | AB27: =AB18-AB26 -> 0 | AC27: =AC18-AC26 -> 0 | AD27: =AD18-AD26 -> 0 | AE27: =AE18-AE26 -> 0 | AF27: =AF18-AF26 -> -3308 | ... AI27: =AI18-AI26 -> -3308
A29: X | B29: Revenue by Product Offerings: Intel Foundry
B30: Internal Only | C30: 0 | D30: 22494 | E30: 27005 | F30: 17957 | G30: 17288 | I30: 6797.517 | J30: 7263.9181 | K30: 6569.167 | L30: =SUM(E30-SUM(I30:K30)) -> 6374.3979 | M30: 4713 | N30: 3941 | O30: 4419 | P30: =SUM(F30-SUM(M30:O30)) -> 4884 | Q30: 4376 | R30: 4278 | S30: 4321 | T30: =SUM(G30-SUM(Q30:S30)) -> 4313 | U30: 4698 | V30: 4421 | W30: 4227 | Y30: =SUM(J30:M30) -> 24920.483 | Z30: =SUM(K30:N30) -> 21597.565 | AA30: =SUM(L30:O30) -> 19447.398 | AB30: =SUM(M30:P30) -> 17957 | AC30: =SUM(N30:Q30) -> 17620 | AD30: =SUM(O30:R30) -> 17957 | AE30: =SUM(P30:S30) -> 17859 | AF30: =SUM(Q30:T30) -> 17288 | ... AI30: =SUM(T30:W30) -> 17659 | AK30: =SUM(AI30/AE30)-1 -> -0.011198835
B31: External Only | C31: 715 | D31: 355 | E31: 486.2 | F31: 953 | G31: 29 | I31: 161 | J31: 61 | K31: 82 | L31: =SUM(E31-SUM(I31:K31)) -> 182.2 | M31: 118 | N31: 231 | O31: 313 | P31: =SUM(F31-SUM(M31:O31)) -> 291 | Q31: -20 | R31: 4 | S31: 18 | T31: =SUM(G31-SUM(Q31:S31)) -> 27 | U31: -31 | V31: -4 | W31: 8 | Y31: =SUM(J31:M31) -> 443.2 | Z31: =SUM(K31:N31) -> 613.2 | AA31: =SUM(L31:O31) -> 844.2 | AB31: =SUM(M31:P31) -> 953 | AC31: =SUM(N31:Q31) -> 815 | AD31: =SUM(O31:R31) -> 588 | AE31: =SUM(P31:S31) -> 293 | AF31: =SUM(Q31:T31) -> 29 | ... AI31: =SUM(T31:W31) -> 0 | AK31: =SUM(AI31/AE31)-1 -> -1
B32: Total Intel Products Revenue | C32: =SUM(C30:C31) -> 715 | D32: =SUM(D30:D31) -> 22849 | E32: =SUM(E30:E31) -> 27491.2 | F32: =SUM(F30:F31) -> 18910 | G32: =SUM(G30:G31) -> 17317 | I32: =SUM(I30:I31) -> 6958.517 | J32: =SUM(J30:J31) -> 7324.9181 | K32: =SUM(K30:K31) -> 6651.167 | L32: =SUM(L30:L31) -> 6556.5979 | M32: =SUM(M30:M31) -> 4831 | N32: =SUM(N30:N31) -> 4172 | O32: =SUM(O30:O31) -> 4732 | P32: =SUM(P30:P31) -> 5175 | ... W32: =SUM(W30:W31) -> 4235 | Y32: =SUM(Y30:Y31) -> 25363.683 | Z32: =SUM(Z30:Z31) -> 22210.765 | AA32: =SUM(AA30:AA31) -> 20291.598 | AB32: =SUM(AB30:AB31) -> 18910 | AC32: =SUM(AC30:AC31) -> 18435 | AD32: =SUM(AD30:AD31) -> 18545 | AE32: =SUM(AE30:AE31) -> 18152 | AF32: =SUM(AF30:AF31) -> 17317 | ... AI32: =SUM(AI30:AI31) -> 17659 | AK32: =SUM(AI32/AE32)-1 -> -0.027159542
B33: Balance Check | C33: =C8-C32 -> 0 | D33: =D8-D32 -> 0 | E33: =E8-E32 -> 0 | F33: =F8-F32 -> 0 | G33: =G8-G32 -> 226 | I33: =I8-I32 -> 0 | J33: =J8-J32 -> 0 | K33: =K8-K32 -> 0 | L33: =L8-L32 -> 0 | M33: =M8-M32 -> 0 | N33: =N8-N32 -> 0 | O33: =O8-O32 -> 0 | P33: =P8-P32 -> 0 | ... W33: =W8-W32 -> 0 | Y33: =Y8-Y32 -> 0 | Z33: =Z8-Z32 -> 0 | AA33: =AA8-AA32 -> 0 | AB33: =AB8-AB32 -> 0 | AC33: =AC8-AC32 -> 13 | AD33: =AD8-AD32 -> 51 | AE33: =AE8-AE32 -> 64 | AF33: =AF8-AF32 -> 226 | ... AI33: =AI8-AI32 -> 162
A35: X | B35: Revenue by Product Offerings: All Other
B36: Altera (ALTR/PSG) | C36: 1853 | D36: 1972 | E36: 2565.3 | F36: 2879 | G36: 1544 | I36: 457.44839 | J36: 478.11631 | K36: 754.68213 | L36: =SUM(E36-SUM(I36:K36)) -> 875.05317 | M36: 816 | N36: 848 | O36: 735 | P36: =SUM(F36-SUM(M36:O36)) -> 480 | Q36: 342 | R36: 361 | S36: 412 | T36: =SUM(G36-SUM(Q36:S36)) -> 429 | U36: 394.68 | V36: 430 | W36: 361.91667 | Y36: =SUM(J36:M36) -> 2923.8516 | Z36: =SUM(K36:N36) -> 3293.7353 | AA36: =SUM(L36:O36) -> 3274.0532 | AB36: =SUM(M36:P36) -> 2879 | AC36: =SUM(N36:Q36) -> 2405 | AD36: =SUM(O36:R36) -> 1918 | AE36: =SUM(P36:S36) -> 1595 | AF36: =SUM(Q36:T36) -> 1544 | ... AI36: =SUM(T36:W36) -> 1615.5967 | AK36: =SUM(AI36/AE36)-1 -> 0.012913271
B37: Intel Automotive | C37: 967 | D37: 1386 | E37: 1869 | F37: 2079 | G37: 1654 | I37: 394 | J37: 460 | K37: 450 | L37: =SUM(E37-SUM(I37:K37)) -> 565 | M37: 458 | N37: 454 | O37: 530 | P37: =SUM(F37-SUM(M37:O37)) -> 637 | Q37: 239 | R37: 440 | S37: 485 | T37: =SUM(G37-SUM(Q37:S37)) -> 490 | U37: 438 | V37: 506 | W37: 504 | Y37: =SUM(J37:M37) -> 1933 | Z37: =SUM(K37:N37) -> 1927 | AA37: =SUM(L37:O37) -> 2007 | AB37: =SUM(M37:P37) -> 2079 | AC37: =SUM(N37:Q37) -> 1860 | AD37: =SUM(O37:R37) -> 1846 | AE37: =SUM(P37:S37) -> 1801 | AF37: =SUM(Q37:T37) -> 1654 | ... AI37: =SUM(T37:W37) -> 1938 | AK37: =SUM(AI37/AE37)-1 -> 0.076068851
B38: Other | C38: 5556.8 | D38: 5779 | E38: 1095.5 | F38: 650 | G38: 403 | I38: 269.6 | J38: 221.9 | K38: 295.3 | L38: =SUM(E38-SUM(I38:K38)) -> 308.7 | M38: 166 | N38: 117 | O38: 187 | P38: =SUM(F38-SUM(M38:O38)) -> 180 | Q38: 62 | R38: 80 | S38: 67 | T38: =SUM(G38-SUM(Q38:S38)) -> 194 | U38: 110.32 | V38: 117 | W38: 127.08333 | Y38: =SUM(J38:M38) -> 991.9 | Z38: =SUM(K38:N38) -> 887 | AA38: =SUM(L38:O38) -> 778.7 | AB38: =SUM(M38:P38) -> 650 | AC38: =SUM(N38:Q38) -> 546 | AD38: =SUM(O38:R38) -> 509 | AE38: =SUM(P38:S38) -> 389 | AF38: =SUM(Q38:T38) -> 403 | ... AI38: =SUM(T38:W38) -> 548.40333 | AK38: =SUM(AI38/AE38)-1 -> 0.40977721
B39: Total Intel Products Revenue | C39: =SUM(C36:C38) -> 8376.8 | D39: =SUM(D36:D38) -> 9137 | E39: =SUM(E36:E38) -> 5529.8 | F39: =SUM(F36:F38) -> 5608 | G39: =SUM(G36:G38) -> 3601 | I39: =SUM(I36:I38) -> 1121.0484 | J39: =SUM(J36:J38) -> 1160.0163 | K39: =SUM(K36:K38) -> 1499.9821 | L39: =SUM(L36:L38) -> 1748.7532 | M39: =SUM(M36:M38) -> 1440 | N39: =SUM(N36:N38) -> 1419 | O39: =SUM(O36:O38) -> 1452 | P39: =SUM(P36:P38) -> 1297 | ... W39: =SUM(W36:W38) -> 993 | Y39: =SUM(Y36:Y38) -> 5848.7516 | Z39: =SUM(Z36:Z38) -> 6107.7353 | AA39: =SUM(AA36:AA38) -> 6059.7532 | AB39: =SUM(AB36:AB38) -> 5608 | AC39: =SUM(AC36:AC38) -> 4811 | AD39: =SUM(AD36:AD38) -> 4273 | AE39: =SUM(AE36:AE38) -> 3785 | AF39: =SUM(AF36:AF38) -> 3601 | ... AI39: =SUM(AI36:AI38) -> 4102 | AK39: =SUM(AI39/AE39)-1 -> 0.083751651
B40: Balance Check | C40: =C9-C39 -> -1667.8 | D40: =D9-D39 -> 0 | E40: =E9-E39 -> 0 | F40: =F9-F39 -> 0 | G40: =G9-G39 -> 223 | I40: =I9-I39 -> 0 | J40: =J9-J39 -> 0 | K40: =K9-K39 -> 0 | L40: =L9-L39 -> 0 | M40: =M9-M39 -> 0 | N40: =N9-N39 -> 0 | O40: =O9-O39 -> 0 | P40: =P9-P39 -> 0 | ... W40: =W9-W39 -> 0 | Y40: =Y9-Y39 -> 0 | Z40: =Z9-Z39 -> 0 | AA40: =AA9-AA39 -> 0 | AB40: =AB9-AB39 -> 0 | AC40: =AC9-AC39 -> 132 | AD40: =AD9-AD39 -> 219 | AE40: =AE9-AE39 -> 294 | AF40: =AF9-AF39 -> 223 | ... AI40: =AI9-AI39 -> -71

Sheet Street Consensus
B2: Intel, Corporation. (NASDAQ: INTC) | C2: Street Consensus
B3: Street Consensus | C3: 2025E | D3: 2026E | E3: 2027E | F3: 2028E | G3: 2029E | H3: 2030E
B4: ($ In Millions) | C4: 12/28/2024E | D4: 12/26/2026E | E4: 12/26/2027E | F4: 12/26/2028E | G4: 12/26/2029E | H4: 12/26/2030E
A6: X | B6: Revenue
B7: BofA | C7: 52507 | D7: 54143 | E7: 56505 | F7: =E7 -> 56505 | G7: =F7 -> 56505 | H7: =G7 -> 56505
B8: Y/Y Growth (%) | C8: 0.011 | D8: 0.031 | E8: 0.044 | F8: =E8 -> 0.044 | G8: =F8 -> 0.044 | H8: =G8 -> 0.044
B9: Wells Fargo | C9: 51666 | D9: 52415 | E9: 55153 | F9: =E9 -> 55153 | G9: =F9 -> 55153 | H9: =G9 -> 55153
B10: Y/Y Growth (%) | C10: -0.03 | D10: 0.01 | E10: 0.05 | F10: =E10 -> 0.05 | G10: =F10 -> 0.05 | H10: =G10 -> 0.05
B11: HSBC | C11: 52210 | D11: 54842 | E11: 55974 | F11: =E11 -> 55974 | G11: =F11 -> 55974 | H11: =G11 -> 55974
B12: Y/Y Growth (%) | C12: -0.02 | D12: 0.05 | E12: 0.02 | F12: =E12 -> 0.02 | G12: =F12 -> 0.02 | H12: =G12 -> 0.02
B13: WedBush | C13: 52479 | D13: 54111 | E13: 58582 | F13: =E13 -> 58582 | G13: =F13 -> 58582 | H13: =G13 -> 58582
B14: Y/Y Growth (%) | C14: =SUM(C13/'Base Financials'!$G$9)-1 -> -0.011713527 | D14: =SUM(D13/C13)-1 -> 0.031098154 | E14: =SUM(E13/D13)-1 -> 0.082626453 | F14: =E14 -> 0.082626453 | G14: =F14 -> 0.082626453 | H14: =G14 -> 0.082626453
B15: UBS | C15: 51784 | D15: 52029 | E15: 54248 | F15: 57110 | G15: 59187 | H15: =G15 -> 59187
B16: Y/Y Growth (%) | C16: =SUM(C15/'Base Financials'!$G$9)-1 -> -0.024801793 | D16: =SUM(D15/C15)-1 -> 0.0047311911 | E16: =SUM(E15/D15)-1 -> 0.042649292 | F16: =SUM(F15/E15)-1 -> 0.052757705 | G16: =SUM(G15/F15)-1 -> 0.036368412 | H16: =G16 -> 0.036368412
B18: High | C18: =MAX(C$7,C$9,C$11,C$13,C$15) -> 52507 | D18: =MAX(D$7,D$9,D$11,D$13,D$15) -> 54842 | E18: =MAX(E$7,E$9,E$11,E$13,E$15) -> 58582 | F18: =MAX(F$7,F$9,F$11,F$13,F$15) -> 58582 | G18: =MAX(G$7,G$9,G$11,G$13,G$15) -> 59187 | H18: =MAX(H$7,H$9,H$11,H$13,H$15) -> 59187
B19: (%) | C19: =MAX(C$8,C$10,C$12,C$14,C$16) -> 0.011 | D19: =MAX(D$8,D$10,D$12,D$14,D$16) -> 0.05 | E19: =MAX(E$8,E$10,E$12,E$14,E$16) -> 0.082626453 | F19: =MAX(F$8,F$10,F$12,F$14,F$16) -> 0.082626453 | G19: =MAX(G$8,G$10,G$12,G$14,G$16) -> 0.082626453 | H19: =MAX(H$8,H$10,H$12,H$14,H$16) -> 0.082626453
B20: Median | C20: =MEDIAN(C$7,C$9,C$11,C$13,C$15) -> 52210 | D20: =MEDIAN(D$7,D$9,D$11,D$13,D$15) -> 54111 | E20: =MEDIAN(E$7,E$9,E$11,E$13,E$15) -> 55974 | F20: =MEDIAN(F$7,F$9,F$11,F$13,F$15) -> 56505 | G20: =MEDIAN(G$7,G$9,G$11,G$13,G$15) -> 56505 | H20: =MEDIAN(H$7,H$9,H$11,H$13,H$15) -> 56505
B21: (%) | C21: =MEDIAN(C$8,C$10,C$12,C$14,C$16) -> -0.02 | D21: =MEDIAN(D$8,D$10,D$12,D$14,D$16) -> 0.031 | E21: =MEDIAN(E$8,E$10,E$12,E$14,E$16) -> 0.044 | F21: =MEDIAN(F$8,F$10,F$12,F$14,F$16) -> 0.05 | G21: =MEDIAN(G$8,G$10,G$12,G$14,G$16) -> 0.044 | H21: =MEDIAN(H$8,H$10,H$12,H$14,H$16) -> 0.044
B22: Low | C22: =MIN(C$7,C$9,C$11,C$13,C$15) -> 51666 | D22: =MIN(D$7,D$9,D$11,D$13,D$15) -> 52029 | E22: =MIN(E$7,E$9,E$11,E$13,E$15) -> 54248 | F22: =MIN(F$7,F$9,F$11,F$13,F$15) -> 55153 | G22: =MIN(G$7,G$9,G$11,G$13,G$15) -> 55153 | H22: =MIN(H$7,H$9,H$11,H$13,H$15) -> 55153
B23: (%) | C23: =MIN(C$8,C$10,C$12,C$14,C$16) -> -0.03 | D23: =MIN(D$8,D$10,D$12,D$14,D$16) -> 0.0047311911 | E23: =MIN(E$8,E$10,E$12,E$14,E$16) -> 0.02 | F23: =MIN(F$8,F$10,F$12,F$14,F$16) -> 0.02 | G23: =MIN(G$8,G$10,G$12,G$14,G$16) -> 0.02 | H23: =MIN(H$8,H$10,H$12,H$14,H$16) -> 0.02
A25: X | B25: Gross Profit
B26: BofA | C26: 19095 | D26: 20508 | E26: 22623 | F26: =E26 -> 22623 | G26: =F26 -> 22623 | H26: =G26 -> 22623
B27: Margin (%) | C27: =C26/C7 -> 0.3636658 | D27: =D26/D7 -> 0.37877473 | E27: =E26/E7 -> 0.40037165 | F27: =F26/F7 -> 0.40037165 | G27: =G26/G7 -> 0.40037165 | H27: =H26/H7 -> 0.40037165
B28: Wells Fargo | C28: 18352 | D28: 20847 | E28: 24682 | F28: =E28 -> 24682 | G28: =F28 -> 24682 | H28: =G28 -> 24682
B29: Margin (%) | C29: =C28/C9 -> 0.35520458 | D29: =D28/D9 -> 0.39772966 | E29: =E28/E9 -> 0.44751872 | F29: =F28/F9 -> 0.44751872 | G29: =G28/G9 -> 0.44751872 | H29: =H28/H9 -> 0.44751872
B30: HSBC | C30: 17295 | D30: 19496 | E30: 20954 | F30: =E30 -> 20954 | G30: =F30 -> 20954 | H30: =G30 -> 20954
B31: Margin (%) | C31: =C30/C11 -> 0.33125838 | D31: =D30/D11 -> 0.35549396 | E31: =E30/E11 -> 0.37435238 | F31: =F30/F11 -> 0.37435238 | G31: =G30/G11 -> 0.37435238 | H31: =H30/H11 -> 0.37435238
B32: WedBush | C32: 19084 | D32: 20328 | E32: 25328 | F32: =E32 -> 25328 | G32: =F32 -> 25328 | H32: =G32 -> 25328
B33: Margin (%) | C33: =C32/C13 -> 0.36365022 | D33: =D32/D13 -> 0.37567223 | E33: =E32/E13 -> 0.43235123 | F33: =F32/F13 -> 0.43235123 | G33: =G32/G13 -> 0.43235123 | H33: =H32/H13 -> 0.43235123
B35: High | C35: =MAX(C$26,C$28,C$30,C$32) -> 19095 | D35: =MAX(D$26,D$28,D$30,D$32) -> 20847 | E35: =MAX(E$26,E$28,E$30,E$32) -> 25328 | F35: =MAX(F$26,F$28,F$30,F$32) -> 25328 | G35: =MAX(G$26,G$28,G$30,G$32) -> 25328 | H35: =MAX(H$26,H$28,H$30,H$32) -> 25328
B36: (%) | C36: =MAX(C$27,C$29,C$31,C$33) -> 0.3636658 | D36: =MAX(D$27,D$29,D$31,D$33) -> 0.39772966 | E36: =MAX(E$27,E$29,E$31,E$33) -> 0.44751872 | F36: =MAX(F$27,F$29,F$31,F$33) -> 0.44751872 | G36: =MAX(G$27,G$29,G$31,G$33) -> 0.44751872 | H36: =MAX(H$27,H$29,H$31,H$33) -> 0.44751872
B37: Median | C37: =MEDIAN(C$26,C$28,C$30,C$32) -> 18718 | D37: =MEDIAN(D$26,D$28,D$30,D$32) -> 20418 | E37: =MEDIAN(E$26,E$28,E$30,E$32) -> 23652.5 | F37: =MEDIAN(F$26,F$28,F$30,F$32) -> 23652.5 | G37: =MEDIAN(G$26,G$28,G$30,G$32) -> 23652.5 | H37: =MEDIAN(H$26,H$28,H$30,H$32) -> 23652.5
B38: (%) | C38: =MEDIAN(C$27,C$29,C$31,C$33) -> 0.3594274 | D38: =MEDIAN(D$27,D$29,D$31,D$33) -> 0.37722348 | E38: =MEDIAN(E$27,E$29,E$31,E$33) -> 0.41636144 | F38: =MEDIAN(F$27,F$29,F$31,F$33) -> 0.41636144 | G38: =MEDIAN(G$27,G$29,G$31,G$33) -> 0.41636144 | H38: =MEDIAN(H$27,H$29,H$31,H$33) -> 0.41636144
B39: Low | C39: =MIN(C$26,C$28,C$30,C$32) -> 17295 | D39: =MIN(D$26,D$28,D$30,D$32) -> 19496 | E39: =MIN(E$26,E$28,E$30,E$32) -> 20954 | F39: =MIN(F$26,F$28,F$30,F$32) -> 20954 | G39: =MIN(G$26,G$28,G$30,G$32) -> 20954 | H39: =MIN(H$26,H$28,H$30,H$32) -> 20954
B40: (%) | C40: =MIN(C$27,C$29,C$31,C$33) -> 0.33125838 | D40: =MIN(D$27,D$29,D$31,D$33) -> 0.35549396 | E40: =MIN(E$27,E$29,E$31,E$33) -> 0.37435238 | F40: =MIN(F$27,F$29,F$31,F$33) -> 0.37435238 | G40: =MIN(G$27,G$29,G$31,G$33) -> 0.37435238 | H40: =MIN(H$27,H$29,H$31,H$33) -> 0.37435238
A42: X | B42: R&D
B43: BofA | C43: 13951 | D43: 13289 | E43: 13327 | F43: =E43 -> 13327 | G43: =F43 -> 13327 | H43: =G43 -> 13327
B44: Margin (%) | C44: =C43/C7 -> 0.26569791 | D44: =D43/D7 -> 0.24544262 | E44: =E43/E7 -> 0.23585523 | F44: =F43/F7 -> 0.23585523 | G44: =G43/G7 -> 0.23585523 | H44: =H43/H7 -> 0.23585523
B45: Wells Fargo | C45: 13126 | D45: 11467 | E45: 11528 | F45: =E45 -> 11528 | G45: =F45 -> 11528 | H45: =G45 -> 11528
B46: Margin (%) | C46: =C45/C9 -> 0.25405489 | D46: =D45/D9 -> 0.21877325 | E46: =E45/E9 -> 0.20901855 | F46: =F45/F9 -> 0.20901855 | G46: =G45/G9 -> 0.20901855 | H46: =H45/H9 -> 0.20901855
A48: X | B48: SG&A
B49: BofA | C49: 4669 | D49: 4816 | E49: 4923 | F49: =E49 -> 4923 | G49: =F49 -> 4923 | H49: =G49 -> 4923
B50: Margin (%) | C50: =C49/C7 -> 0.088921477 | D50: =D49/D7 -> 0.088949633 | E50: =E49/E7 -> 0.087125033 | F50: =F49/F7 -> 0.087125033 | G50: =G49/G7 -> 0.087125033 | H50: =H49/H7 -> 0.087125033
B51: Wells Fargo | C51: 4028 | D51: 3887 | E51: 3848 | F51: =E51 -> 3848 | G51: =F51 -> 3848 | H51: =G51 -> 3848
B52: Margin (%) | C52: =C51/C9 -> 0.077962296 | D52: =D51/D9 -> 0.074158161 | E52: =E51/E9 -> 0.06976955 | F52: =F51/F9 -> 0.06976955 | G52: =G51/G9 -> 0.06976955 | H52: =H51/H9 -> 0.06976955
A54: X | B54: Tax Expense
B55: BofA | C55: 0.12 | D55: 0.12 | E55: 0.12 | F55: =E55 -> 0.12 | G55: =F55 -> 0.12 | H55: =G55 -> 0.12
B56: HSBC | C56: =SUM(596/5344) -> 0.11152695 | D56: =SUM(596/4784) -> 0.12458194 | E56: 0.12 | F56: =E56 -> 0.12 | G56: =F56 -> 0.12 | H56: =G56 -> 0.12
B57: WedBush | C57: 0.12 | D57: 0.13 | E57: 0.13 | F57: =E57 -> 0.13 | G57: =F57 -> 0.13 | H57: =G57 -> 0.13
A59: X | B59: Capex
B60: BofA | C60: 14658 | D60: 12000 | E60: 12000 | F60: =E60 -> 12000 | G60: =F60 -> 12000 | H60: =G60 -> 12000
B61: HSBC | C61: 9137 | D61: 6855 | E61: 5597 | F61: =E61 -> 5597 | G61: =F61 -> 5597 | H61: =G61 -> 5597
B62: WedBush | C62: 16269 | D62: 16000 | E62: 20000 | F62: =E62 -> 20000 | G62: =F62 -> 20000 | H62: =G62 -> 20000
B64: High | C64: =MAX(C$60,C$61,C$62) -> 16269 | D64: =MAX(D$60,D$61,D$62) -> 16000 | E64: =MAX(E$60,E$61,E$62) -> 20000 | F64: =MAX(F$60,F$61,F$62) -> 20000 | G64: =MAX(G$60,G$61,G$62) -> 20000 | H64: =MAX(H$60,H$61,H$62) -> 20000
B65: Median | C65: =MEDIAN(C$60,C$61,C$62) -> 14658 | D65: =MEDIAN(D$60,D$61,D$62) -> 12000 | E65: =MEDIAN(E$60,E$61,E$62) -> 12000 | F65: =MEDIAN(F$60,F$61,F$62) -> 12000 | G65: =MEDIAN(G$60,G$61,G$62) -> 12000 | H65: =MEDIAN(H$60,H$61,H$62) -> 12000
B66: Low | C66: =MIN(C$60,C$61,C$62) -> 9137 | D66: =MIN(D$60,D$61,D$62) -> 6855 | E66: =MIN(E$60,E$61,E$62) -> 5597 | F66: =MIN(F$60,F$61,F$62) -> 5597 | G66: =MIN(G$60,G$61,G$62) -> 5597 | H66: =MIN(H$60,H$61,H$62) -> 5597

Sheet DCF
