Workbook

Sheet Historical Financials
B2: Lululemon Athletica Inc (NASDAQ: LULU)
B3: Historical Financials
B4: ($ In Millions, except EPS)
A6: X | B6: Income Statement | D6: FYE | G6: Quarterly | M6: Quarterly | T6: LTM | Z6: Variance
B7: Fiscal Period | C7: 2022 | D7: 2023 | E7: 2024 | G7: 1Q23 | H7: 2Q23 | I7: 3Q23 | J7: 4Q23 | K7: 1Q24 | L7: 2Q24 | M7: 3Q24 | N7: 4Q24 | O7: 1Q25 | P7: 2Q25 | R7: =J7 -> 4Q23 | S7: =K7 -> 1Q24 | T7: =L7 -> 2Q24 | U7: =M7 -> 3Q24 | V7: =N7 -> 4Q24 | W7: =O7 -> 1Q25 | X7: =P7 -> 2Q25
B8: Fiscal Period End Date | C8: XXX | D8: XXX | E8: XXX | G8: XXX | H8: XXX | I8: XXX | J8: =D8 -> XXX | K8: XXX | L8: XXX | M8: XXX | N8: =E8 -> XXX | O8: XXX | P8: XXX | R8: =J8 -> XXX | S8: =K8 -> XXX | T8: =L8 -> XXX | U8: =M8 -> XXX | V8: =N8 -> XXX | W8: =O8 -> XXX | X8: =P8 -> XXX
B10: Consolidated Revenue | C10: 8111 | D10: 9619 | E10: 10588 | G10: 988.6 | H10: 1067.7 | I10: 1188.6 | J10: =SUM(D10-SUM(G10:I10)) -> 6374.1 | K10: 1194.8 | L10: 1236.8 | M10: 1372.6 | N10: =SUM(E10-SUM(K10:M10)) -> 6783.8 | O10: 1363.2 | P10: 1344.9 | R10: =SUM(G10:J10) -> 9619 | S10: =SUM(H10:K10) -> 9825.2 | T10: =SUM(I10:L10) -> 9994.3 | U10: =SUM(J10:M10) -> 10178.3 | V10: =SUM(K10:N10) -> 10588 | W10: =SUM(L10:O10) -> 10756.4 | X10: =SUM(M10:P10) -> 10864.5 | Z10: =SUM(X10/T10)-1 -> 0.08706963
B11: Total Revenue | C11: =+SUM(C10:C10) -> 8111 | D11: =+SUM(D10:D10) -> 9619 | E11: =+SUM(E10:E10) -> 10588 | G11: =+SUM(G10:G10) -> 988.6 | H11: =+SUM(H10:H10) -> 1067.7 | I11: =+SUM(I10:I10) -> 1188.6 | J11: =+SUM(J10:J10) -> 6374.1 | K11: =+SUM(K10:K10) -> 1194.8 | L11: =+SUM(L10:L10) -> 1236.8 | M11: =+SUM(M10:M10) -> 1372.6 | N11: =+SUM(N10:N10) -> 6783.8 | ... P11: =+SUM(P10:P10) -> 1344.9 | R11: =+SUM(R10:R10) -> 9619 | S11: =+SUM(S10:S10) -> 9825.2 | T11: =+SUM(T10:T10) -> 9994.3 | U11: =+SUM(U10:U10) -> 10178.3 | V11: =+SUM(V10:V10) -> 10588 | W11: =+SUM(W10:W10) -> 10756.4 | X11: =+SUM(X10:X10) -> 10864.5 | Z11: =SUM(X11/T11)-1 -> 0.08706963
B13: Cost of Sales | C13: -3618 | D13: -4010 | E13: -4317 | G13: -850 | H13: -911 | I13: -948 | J13: -1302 | K13: -934 | L13: -959 | M13: -995 | N13: =SUM(E13-SUM(K13:M13)) -> -1429 | O13: -988 | P13: -1048 | R13: =SUM(G13:J13) -> -4011 | S13: =SUM(H13:K13) -> -4095 | T13: =SUM(I13:L13) -> -4143 | U13: =SUM(J13:M13) -> -4190 | V13: =SUM(K13:N13) -> -4317 | W13: =SUM(L13:O13) -> -4371 | X13: =SUM(M13:P13) -> -4460 | Z13: =SUM(X13/T13)-1 -> 0.076514603
B14: Gross Profit | C14: =+SUM(C11+SUM(C13:C13)) -> 4493 | D14: =+SUM(D11+SUM(D13:D13)) -> 5609 | E14: =+SUM(E11+SUM(E13:E13)) -> 6271 | G14: =+SUM(G11+SUM(G13:G13)) -> 138.6 | H14: =+SUM(H11+SUM(H13:H13)) -> 156.7 | I14: =+SUM(I11+SUM(I13:I13)) -> 240.6 | J14: =+SUM(J11+SUM(J13:J13)) -> 5072.1 | K14: =+SUM(K11+SUM(K13:K13)) -> 260.8 | L14: =+SUM(L11+SUM(L13:L13)) -> 277.8 | M14: =+SUM(M11+SUM(M13:M13)) -> 377.6 | N14: =+SUM(N11+SUM(N13:N13)) -> 5354.8 | ... P14: =+SUM(P11+SUM(P13:P13)) -> 296.9 | R14: =+SUM(R11+SUM(R13:R13)) -> 5608 | S14: =+SUM(S11+SUM(S13:S13)) -> 5730.2 | T14: =+SUM(T11+SUM(T13:T13)) -> 5851.3 | U14: =+SUM(U11+SUM(U13:U13)) -> 5988.3 | V14: =+SUM(V11+SUM(V13:V13)) -> 6271 | W14: =+SUM(W11+SUM(W13:W13)) -> 6385.4 | X14: =+SUM(X11+SUM(X13:X13)) -> 6404.5 | Z14: =SUM(X14/T14)-1 -> 0.094543093
B15: Gross Margin (%) | C15: =C14/C11 -> 0.5539391 | D15: =D14/D11 -> 0.58311675 | E15: =E14/E11 -> 0.59227427 | G15: =G14/G11 -> 0.14019826 | H15: =H14/H11 -> 0.14676407 | I15: =I14/I11 -> 0.20242302 | J15: =J14/J11 -> 0.79573587 | K15: =K14/K11 -> 0.21827921 | L15: =L14/L11 -> 0.2246119 | M15: =M14/M11 -> 0.27509835 | N15: =N14/N11 -> 0.7893511 | ... P15: =P14/P11 -> 0.22075991 | R15: =R14/R11 -> 0.58301279 | S15: =S14/S11 -> 0.58321459 | T15: =T14/T11 -> 0.58546371 | U15: =U14/U11 -> 0.5883399 | V15: =V14/V11 -> 0.59227427 | W15: =W14/W11 -> 0.59363728 | X15: =X14/X11 -> 0.5894887 | Z15: =SUM(X15-T15)*1000 -> 4.0249874
B17: Selling, General, and Administrative | C17: -2758 | D17: -3397 | E17: -3762 | G17: -748 | H17: -817 | I17: -843 | J17: =SUM(D17-SUM(G17:I17)) -> -989 | K17: -842 | L17: -872 | M17: -910 | N17: =SUM(E17-SUM(K17:M17)) -> -1138 | O17: -943 | P17: -952 | R17: =SUM(G17:J17) -> -3397 | S17: =SUM(H17:K17) -> -3491 | T17: =SUM(I17:L17) -> -3546 | U17: =SUM(J17:M17) -> -3613 | V17: =SUM(K17:N17) -> -3762 | W17: =SUM(L17:O17) -> -3863 | X17: =SUM(M17:P17) -> -3943 | Z17: =SUM(X17/T17)-1 -> 0.11195713
B18: Amortization of Intangibles | C18: -406 | D18: -80 | E18: -3 | G18: -2 | H18: -2 | I18: -76 | J18: =SUM(D18-SUM(G18:I18)) -> 0 | K18: 0 | L18: 0 | M18: -1 | N18: =SUM(E18-SUM(K18:M18)) -> -2 | O18: -2 | P18: -2 | R18: =SUM(G18:J18) -> -80 | S18: =SUM(H18:K18) -> -78 | T18: =SUM(I18:L18) -> -76 | U18: =SUM(J18:M18) -> -1 | V18: =SUM(K18:N18) -> -3 | W18: =SUM(L18:O18) -> -5 | X18: =SUM(M18:P18) -> -7 | Z18: =SUM(X18/T18)-1 -> -0.90789474
B19: Operating Profit | C19: =+SUM(C14+SUM(C17:C18)) -> 1329 | D19: =+SUM(D14+SUM(D17:D18)) -> 2132 | E19: =+SUM(E14+SUM(E17:E18)) -> 2506 | G19: =+SUM(G14+SUM(G17:G18)) -> -611.4 | H19: =+SUM(H14+SUM(H17:H18)) -> -662.3 | I19: =+SUM(I14+SUM(I17:I18)) -> -678.4 | J19: =+SUM(J14+SUM(J17:J18)) -> 4083.1 | K19: =+SUM(K14+SUM(K17:K18)) -> -581.2 | L19: =+SUM(L14+SUM(L17:L18)) -> -594.2 | M19: =+SUM(M14+SUM(M17:M18)) -> -533.4 | N19: =+SUM(N14+SUM(N17:N18)) -> 4214.8 | ... P19: =+SUM(P14+SUM(P17:P18)) -> -657.1 | R19: =+SUM(R14+SUM(R17:R18)) -> 2131 | S19: =+SUM(S14+SUM(S17:S18)) -> 2161.2 | T19: =+SUM(T14+SUM(T17:T18)) -> 2229.3 | U19: =+SUM(U14+SUM(U17:U18)) -> 2374.3 | V19: =+SUM(V14+SUM(V17:V18)) -> 2506 | W19: =+SUM(W14+SUM(W17:W18)) -> 2517.4 | X19: =+SUM(X14+SUM(X17:X18)) -> 2454.5 | Z19: =SUM(X19/T19)-1 -> 0.10101826
B20: Operating Margin (%) | C20: =C19/C11 -> 0.16385156 | D20: =D19/D11 -> 0.22164466 | E20: =E19/E11 -> 0.23668304 | G20: =G19/G11 -> -0.61845033 | H20: =H19/H11 -> -0.62030533 | I20: =I19/I11 -> -0.57075551 | J20: =J19/J11 -> 0.64057671 | K20: =K19/K11 -> -0.48644125 | L20: =L19/L11 -> -0.48043338 | M20: =M19/M11 -> -0.38860557 | N20: =N19/N11 -> 0.62130369 | ... P20: =P19/P11 -> -0.48858651 | R20: =R19/R11 -> 0.2215407 | S20: =S19/S11 -> 0.21996499 | T20: =T19/T11 -> 0.22305714 | U20: =U19/U11 -> 0.23327078 | V20: =V19/V11 -> 0.23668304 | W20: =W19/W11 -> 0.23403741 | X20: =X19/X11 -> 0.22591928 | Z20: =SUM(X20-T20)*1000 -> 2.8621358
B22: Other Income | C22: 4 | D22: 43 | E22: 70 | G22: 8 | H22: 7 | I22: 10 | J22: =SUM(D22-SUM(G22:I22)) -> 18 | K22: 23 | L22: 18 | M22: 14 | N22: =SUM(E22-SUM(K22:M22)) -> 15 | O22: 12 | P22: 10 | R22: =SUM(G22:J22) -> 43 | S22: =SUM(H22:K22) -> 58 | T22: =SUM(I22:L22) -> 69 | U22: =SUM(J22:M22) -> 73 | V22: =SUM(K22:N22) -> 70 | W22: =SUM(L22:O22) -> 59 | X22: =SUM(M22:P22) -> 51 | Z22: =SUM(X22/T22)-1 -> -0.26086957
B23: Earnings before Taxes | C23: =SUM(C22:C22)+C19 -> 1333 | D23: =SUM(D22:D22)+D19 -> 2175 | E23: =SUM(E22:E22)+E19 -> 2576 | G23: =SUM(G22:G22)+G19 -> -603.4 | H23: =SUM(H22:H22)+H19 -> -655.3 | I23: =SUM(I22:I22)+I19 -> -668.4 | J23: =SUM(J22:J22)+J19 -> 4101.1 | K23: =SUM(K22:K22)+K19 -> -558.2 | L23: =SUM(L22:L22)+L19 -> -576.2 | M23: =SUM(M22:M22)+M19 -> -519.4 | N23: =SUM(N22:N22)+N19 -> 4229.8 | ... P23: =SUM(P22:P22)+P19 -> -647.1 | R23: =SUM(R22:R22)+R19 -> 2174 | S23: =SUM(S22:S22)+S19 -> 2219.2 | T23: =SUM(T22:T22)+T19 -> 2298.3 | U23: =SUM(U22:U22)+U19 -> 2447.3 | V23: =SUM(V22:V22)+V19 -> 2576 | W23: =SUM(W22:W22)+W19 -> 2576.4 | X23: =SUM(X22:X22)+X19 -> 2505.5 | Z23: =SUM(X23/T23)-1 -> 0.090153592
B24: EBT Margin (%) | C24: =C23/C11 -> 0.16434472 | D24: =D23/D11 -> 0.22611498 | E24: =E23/E11 -> 0.2432943 | G24: =G23/G11 -> -0.61035808 | H24: =H23/H11 -> -0.61374918 | I24: =I23/I11 -> -0.56234225 | J24: =J23/J11 -> 0.64340064 | K24: =K23/K11 -> -0.46719116 | L24: =L23/L11 -> -0.46587969 | M24: =M23/M11 -> -0.37840594 | N24: =N23/N11 -> 0.62351484 | ... P24: =P23/P11 -> -0.48115101 | R24: =R23/R11 -> 0.22601102 | S24: =S23/S11 -> 0.22586818 | T24: =T23/T11 -> 0.22996108 | U24: =U23/U11 -> 0.2404429 | V24: =V23/V11 -> 0.2432943 | W24: =W23/W11 -> 0.23952252 | X24: =X23/X11 -> 0.23061347 | Z24: =SUM(X24-T24)*1000 -> 0.65238806
B26: Income tax expense | C26: -478 | D26: -626 | E26: -761 | G26: -119 | H26: -145 | I26: -99 | J26: =SUM(D26-SUM(G26:I26)) -> -263 | K26: -135 | L26: -165 | M26: -153 | N26: =SUM(E26-SUM(K26:M26)) -> -308 | O26: -136 | P26: -161 | R26: =SUM(G26:J26) -> -626 | S26: =SUM(H26:K26) -> -642 | T26: =SUM(I26:L26) -> -662 | U26: =SUM(J26:M26) -> -716 | V26: =SUM(K26:N26) -> -761 | W26: =SUM(L26:O26) -> -762 | X26: =SUM(M26:P26) -> -758 | Z26: =SUM(X26/T26)-1 -> 0.14501511
B27: Net loss | C27: =SUM(C23+SUM(C26:C26)) -> 855 | D27: =SUM(D23+SUM(D26:D26)) -> 1549 | E27: =SUM(E23+SUM(E26:E26)) -> 1815 | G27: =SUM(G23+SUM(G26:G26)) -> -722.4 | H27: =SUM(H23+SUM(H26:H26)) -> -800.3 | I27: =SUM(I23+SUM(I26:I26)) -> -767.4 | J27: =SUM(J23+SUM(J26:J26)) -> 3838.1 | K27: =SUM(K23+SUM(K26:K26)) -> -693.2 | L27: =SUM(L23+SUM(L26:L26)) -> -741.2 | M27: =SUM(M23+SUM(M26:M26)) -> -672.4 | N27: =SUM(N23+SUM(N26:N26)) -> 3921.8 | ... P27: =SUM(P23+SUM(P26:P26)) -> -808.1 | R27: =SUM(R23+SUM(R26:R26)) -> 1548 | S27: =SUM(S23+SUM(S26:S26)) -> 1577.2 | T27: =SUM(T23+SUM(T26:T26)) -> 1636.3 | U27: =SUM(U23+SUM(U26:U26)) -> 1731.3 | V27: =SUM(V23+SUM(V26:V26)) -> 1815 | W27: =SUM(W23+SUM(W26:W26)) -> 1814.4 | X27: =SUM(X23+SUM(X26:X26)) -> 1747.5 | Z27: =SUM(X27/T27)-1 -> 0.067958198
B28: Net Margin (%) | C28: =C27/C11 -> 0.1054124 | D28: =D27/D11 -> 0.16103545 | E28: =E27/E11 -> 0.17142048 | G28: =G27/G11 -> -0.73073033 | H28: =H27/H11 -> -0.74955512 | I28: =I27/I11 -> -0.64563352 | J28: =J27/J11 -> 0.60213991 | K28: =K27/K11 -> -0.58018078 | L28: =L27/L11 -> -0.59928849 | M28: =M27/M11 -> -0.48987323 | N28: =N27/N11 -> 0.57811256 | ... P28: =P27/P11 -> -0.60086252 | R28: =R27/R11 -> 0.16093149 | S28: =S27/S11 -> 0.16052599 | T28: =T27/T11 -> 0.16372332 | U28: =U27/U11 -> 0.17009717 | V28: =V27/V11 -> 0.17142048 | W28: =W27/W11 -> 0.16868097 | X28: =X27/X11 -> 0.16084495 | Z28: =SUM(X28-T28)*1000 -> -2.8783685
B30: Basic shares | J30: =D30 -> 0 | N30: =E30 -> 0 | R30: =J30 -> 0 | S30: =K30 -> 0 | T30: =L30 -> 0 | U30: =M30 -> 0 | V30: =N30 -> 0 | W30: =O30 -> 0 | X30: =P30 -> 0 | Z30: =SUM(X30/T30)-1 -> #DIV/0!
B31: Basic EPS | C31: =C27/C30 -> #DIV/0! | D31: =D27/D30 -> #DIV/0! | E31: =E27/E30 -> #DIV/0! | G31: =G27/G30 -> #DIV/0! | H31: =H27/H30 -> #DIV/0! | I31: =I27/I30 -> #DIV/0! | J31: =J27/J30 -> #DIV/0! | K31: =K27/K30 -> #DIV/0! | L31: =L27/L30 -> #DIV/0! | M31: =M27/M30 -> #DIV/0! | N31: =N27/N30 -> #DIV/0! | ... P31: =P27/P30 -> #DIV/0! | R31: =R27/R30 -> #DIV/0! | S31: =S27/S30 -> #DIV/0! | T31: =T27/T30 -> #DIV/0! | U31: =U27/U30 -> #DIV/0! | V31: =V27/V30 -> #DIV/0! | W31: =W27/W30 -> #DIV/0! | X31: =X27/X30 -> #DIV/0! | Z31: =SUM(X31/T31)-1 -> #DIV/0!
B33: Fully Diluted Shares | J33: =D33 -> 0 | N33: =E33 -> 0 | R33: =J33 -> 0 | S33: =K33 -> 0 | T33: =L33 -> 0 | U33: =M33 -> 0 | V33: =N33 -> 0 | W33: =O33 -> 0 | X33: =P33 -> 0 | Z33: =SUM(X33/T33)-1 -> #DIV/0!
B34: Diluted EPS | C34: =C27/C33 -> #DIV/0! | D34: =D27/D33 -> #DIV/0! | E34: =E27/E33 -> #DIV/0! | G34: =G27/G33 -> #DIV/0! | H34: =H27/H33 -> #DIV/0! | I34: =I27/I33 -> #DIV/0! | J34: =J27/J33 -> #DIV/0! | K34: =K27/K33 -> #DIV/0! | L34: =L27/L33 -> #DIV/0! | M34: =M27/M33 -> #DIV/0! | N34: =N27/N33 -> #DIV/0! | ... P34: =P27/P33 -> #DIV/0! | R34: =R27/R33 -> #DIV/0! | S34: =S27/S33 -> #DIV/0! | T34: =T27/T33 -> #DIV/0! | U34: =U27/U33 -> #DIV/0! | V34: =V27/V33 -> #DIV/0! | W34: =W27/W33 -> #DIV/0! | X34: =X27/X33 -> #DIV/0! | Z34: =SUM(X34/T34)-1 -> #DIV/0!
A36: X | B36: Balance Sheet | C36: FYE | M36: Quarterly | T36: LTM | Z36: Variance
B37: =B7 -> Fiscal Period | C37: =C7 -> 2022 | D37: =D7 -> 2023 | E37: =E7 -> 2024 | G37: =G7 -> 1Q23 | H37: =H7 -> 2Q23 | I37: =I7 -> 3Q23 | J37: =J7 -> 4Q23 | K37: =K7 -> 1Q24 | L37: =L7 -> 2Q24 | M37: =M7 -> 3Q24 | N37: =N7 -> 4Q24 | ... P37: =P7 -> 2Q25 | R37: =R7 -> 4Q23 | S37: =S7 -> 1Q24 | T37: =T7 -> 2Q24 | U37: =U7 -> 3Q24 | V37: =V7 -> 4Q24 | W37: =W7 -> 1Q25 | X37: =X7 -> 2Q25
B38: =B8 -> Fiscal Period End Date | C38: =C8 -> XXX | D38: =D8 -> XXX | E38: =E8 -> XXX | G38: =G8 -> XXX | H38: =H8 -> XXX | I38: =I8 -> XXX | J38: =J8 -> XXX | K38: =K8 -> XXX | L38: =L8 -> XXX | M38: =M8 -> XXX | N38: =N8 -> XXX | ... P38: =P8 -> XXX | R38: =R8 -> XXX | S38: =S8 -> XXX | T38: =T8 -> XXX | U38: =U8 -> XXX | V38: =V8 -> XXX | W38: =W8 -> XXX | X38: =X8 -> XXX
B40: Current Assets
B41: Cash and cash equivalents | C41: 1155 | D41: 2244 | E41: 1984 | G41: 951 | H41: 1108 | I41: 1091 | J41: =D41 -> 2244 | K41: 1901 | L41: 1610 | M41: 1188 | N41: =E41 -> 1984 | O41: 1325 | P41: 1156 | R41: =J41 -> 2244 | S41: =K41 -> 1901 | T41: =L41 -> 1610 | U41: =M41 -> 1188 | V41: =N41 -> 1984 | W41: =O41 -> 1325 | X41: =P41 -> 1156 | Z41: =SUM(X41/T41)-1 -> -0.28198758
B42: Accounts receivable, net | C42: 133 | D42: 125 | E42: 120 | G42: 107 | H42: 106 | I42: 107 | J42: =D42 -> 125 | K42: 126 | L42: 126 | M42: 143 | N42: =E42 -> 120 | O42: 141 | P42: 139 | R42: =J42 -> 125 | S42: =K42 -> 126 | T42: =L42 -> 126 | U42: =M42 -> 143 | V42: =N42 -> 120 | W42: =O42 -> 141 | X42: =P42 -> 139 | Z42: =SUM(X42/T42)-1 -> 0.1031746
B43: Inventories | C43: 1447 | D43: 1324 | E43: 1442 | G43: 1580 | H43: 1661 | I43: 1664 | J43: =D43 -> 1324 | K43: 1345 | L43: 1429 | M43: 1801 | N43: =E43 -> 1442 | O43: 1652 | P43: 1723 | R43: =J43 -> 1324 | S43: =K43 -> 1345 | T43: =L43 -> 1429 | U43: =M43 -> 1801 | V43: =N43 -> 1442 | W43: =O43 -> 1652 | X43: =P43 -> 1723 | Z43: =SUM(X43/T43)-1 -> 0.20573828
B44: Prepaid Taxes, current | C44: 186 | D44: 184 | E44: 182 | G44: 182 | H44: 225 | I44: 300 | J44: =D44 -> 184 | K44: 193 | L44: 211 | M44: 257 | N44: =E44 -> 182 | O44: 230 | P44: 323 | R44: =J44 -> 184 | S44: =K44 -> 193 | T44: =L44 -> 211 | U44: =M44 -> 257 | V44: =N44 -> 182 | W44: =O44 -> 230 | X44: =P44 -> 323 | Z44: =SUM(X44/T44)-1 -> 0.53080569
B45: Prepaid expenses and other current assets | C45: 239 | D45: 185 | E45: 251 | G45: 233 | H45: 225 | I45: 203 | J45: =D45 -> 185 | K45: 203 | L45: 195 | M45: 215 | N45: =E45 -> 251 | O45: 234 | P45: 188 | R45: =J45 -> 185 | S45: =K45 -> 203 | T45: =L45 -> 195 | U45: =M45 -> 215 | V45: =N45 -> 251 | W45: =O45 -> 234 | X45: =P45 -> 188 | Z45: =SUM(X45/T45)-1 -> -0.035897436
B46: Total Current Assets | C46: =SUM(C41:C45) -> 3160 | D46: =SUM(D41:D45) -> 4062 | E46: =SUM(E41:E45) -> 3979 | G46: =SUM(G41:G45) -> 3053 | H46: =SUM(H41:H45) -> 3325 | I46: =SUM(I41:I45) -> 3365 | J46: =SUM(J41:J45) -> 4062 | K46: =SUM(K41:K45) -> 3768 | L46: =SUM(L41:L45) -> 3571 | M46: =SUM(M41:M45) -> 3604 | N46: =SUM(N41:N45) -> 3979 | ... P46: =SUM(P41:P45) -> 3529 | R46: =SUM(R41:R45) -> 4062 | S46: =SUM(S41:S45) -> 3768 | T46: =SUM(T41:T45) -> 3571 | U46: =SUM(U41:U45) -> 3604 | V46: =SUM(V41:V45) -> 3979 | W46: =SUM(W41:W45) -> 3582 | X46: =SUM(X41:X45) -> 3529 | Z46: =SUM(X46/T46)-1 -> -0.011761411
B48: Non-Current Assets
B49: Property and equipment, net | C49: 1270 | D49: 1546 | E49: 1781 | G49: 1313 | H49: 1367 | I49: 1414 | J49: =D49 -> 1546 | K49: 1561 | L49: 1615 | M49: 1698 | N49: =E49 -> 1781 | O49: 1847 | P49: 1917 | R49: =J49 -> 1546 | S49: =K49 -> 1561 | T49: =L49 -> 1615 | U49: =M49 -> 1698 | V49: =N49 -> 1781 | W49: =O49 -> 1847 | X49: =P49 -> 1917 | Z49: =SUM(X49/T49)-1 -> 0.1869969
B50: Long-term Prepaid Leases | C50: 969 | D50: 1266 | E50: 1416 | G50: 993 | H50: 1079 | I50: 1049 | J50: =D50 -> 1266 | K50: 1264 | L50: 1303 | M50: 1361 | N50: =E50 -> 1416 | O50: 1549 | P50: 1605 | R50: =J50 -> 1266 | S50: =K50 -> 1264 | T50: =L50 -> 1303 | U50: =M50 -> 1361 | V50: =N50 -> 1416 | W50: =O50 -> 1549 | X50: =P50 -> 1605 | Z50: =SUM(X50/T50)-1 -> 0.23177283
B51: Goodwill | C51: 24 | D51: 24 | E51: 160 | G51: 24 | H51: 24 | I51: 24 | J51: =D51 -> 24 | K51: 24 | L51: 24 | M51: 164 | N51: =E51 -> 160 | O51: 167 | P51: 173 | R51: =J51 -> 24 | S51: =K51 -> 24 | T51: =L51 -> 24 | U51: =M51 -> 164 | V51: =N51 -> 160 | W51: =O51 -> 167 | X51: =P51 -> 173 | Z51: =SUM(X51/T51)-1 -> 6.2083333
B52: Intangible Assets | C52: 22 | D52: 0 | E52: 12 | G52: 20 | H52: 18 | I52: 0 | J52: =D52 -> 0 | K52: 0 | L52: 0 | M52: 14 | N52: =E52 -> 12 | O52: 11 | P52: 9 | R52: =J52 -> 0 | S52: =K52 -> 0 | T52: =L52 -> 0 | U52: =M52 -> 14 | V52: =N52 -> 12 | W52: =O52 -> 11 | X52: =P52 -> 9 | Z52: =SUM(X52/T52)-1 -> #DIV/0!
B53: Prepaid Taxes, non-current | C53: 6 | D53: 9 | E53: 17 | G53: 6 | H53: 6 | I53: 6 | J53: =D53 -> 9 | K53: 9 | L53: 9 | M53: 9 | N53: =E53 -> 17 | O53: 18 | P53: 21 | R53: =J53 -> 9 | S53: =K53 -> 9 | T53: =L53 -> 9 | U53: =M53 -> 9 | V53: =N53 -> 17 | W53: =O53 -> 18 | X53: =P53 -> 21
B54: Other Non-Current Assets | C54: 156 | D54: 187 | E54: 238 | G54: 162 | H54: 174 | I54: 165 | J54: =D54 -> 187 | K54: 202 | L54: 222 | M54: 233 | N54: =E54 -> 238 | O54: 256 | P54: 269 | R54: =J54 -> 187 | S54: =K54 -> 202 | T54: =L54 -> 222 | U54: =M54 -> 233 | V54: =N54 -> 238 | W54: =O54 -> 256 | X54: =P54 -> 269 | Z54: =SUM(X54/T54)-1 -> 0.21171171
B55: Total Assets | C55: =SUM(C49:C54)+C46 -> 5607 | D55: =SUM(D49:D54)+D46 -> 7094 | E55: =SUM(E49:E54)+E46 -> 7603 | G55: =SUM(G49:G54)+G46 -> 5571 | H55: =SUM(H49:H54)+H46 -> 5993 | I55: =SUM(I49:I54)+I46 -> 6023 | J55: =SUM(J49:J54)+J46 -> 7094 | K55: =SUM(K49:K54)+K46 -> 6828 | L55: =SUM(L49:L54)+L46 -> 6744 | M55: =SUM(M49:M54)+M46 -> 7083 | N55: =SUM(N49:N54)+N46 -> 7603 | ... P55: =SUM(P49:P54)+P46 -> 7523 | R55: =SUM(R49:R54)+R46 -> 7094 | S55: =SUM(S49:S54)+S46 -> 6828 | T55: =SUM(T49:T54)+T46 -> 6744 | U55: =SUM(U49:U54)+U46 -> 7083 | V55: =SUM(V49:V54)+V46 -> 7603 | W55: =SUM(W49:W54)+W46 -> 7430 | X55: =SUM(X49:X54)+X46 -> 7523 | Z55: =SUM(X55/T55)-1 -> 0.11551008
B57: Current Liabilities
B58: A/P | C58: 173 | D58: 348 | E58: 271 | G58: 287 | H58: 299 | I58: 309 | J58: =D58 -> 348 | K58: 262 | L58: 317 | M58: 386 | N58: =E58 -> 271 | O58: 304 | P58: 373 | R58: =J58 -> 348 | S58: =K58 -> 262 | T58: =L58 -> 317 | U58: =M58 -> 386 | V58: =N58 -> 271 | W58: =O58 -> 304 | X58: =P58 -> 373 | Z58: =SUM(X58/T58)-1 -> 0.17665615
B59: Accrued ST Liabilities | C59: 399 | D59: 349 | E59: 559 | G59: 343 | H59: 399 | I59: 393 | J59: =D59 -> 349 | K59: 374 | L59: 396 | M59: 562 | N59: =E59 -> 559 | O59: 507 | P59: 424 | R59: =J59 -> 349 | S59: =K59 -> 374 | T59: =L59 -> 396 | U59: =M59 -> 562 | V59: =N59 -> 559 | W59: =O59 -> 507 | X59: =P59 -> 424 | Z59: =SUM(X59/T59)-1 -> 0.070707071
B60: Accrued ST Comp. | C60: 248 | D60: 326 | E60: 205 | G60: 125 | H60: 192 | I60: 250 | J60: =D60 -> 326 | K60: 133 | L60: 175 | M60: 190 | N60: =E60 -> 205 | O60: 144 | P60: 149 | R60: =J60 -> 326 | S60: =K60 -> 133 | T60: =L60 -> 175 | U60: =M60 -> 190 | V60: =N60 -> 205 | W60: =O60 -> 144 | X60: =P60 -> 149
B61: ST Lease Liabilities | C61: 208 | D61: 249 | E61: 275 | G61: 211 | H61: 217 | I61: 217 | J61: =D61 -> 249 | K61: 254 | L61: 278 | M61: 290 | N61: =E61 -> 275 | O61: 282 | P61: 298 | R61: =J61 -> 249 | S61: =K61 -> 254 | T61: =L61 -> 278 | U61: =M61 -> 290 | V61: =N61 -> 275 | W61: =O61 -> 282 | X61: =P61 -> 298
B62: ST Taxes Payable | C62: 174 | D62: 12 | E62: 183 | G62: 30 | H62: 21 | I62: 27 | J62: =D62 -> 12 | K62: 53 | L62: 19 | M62: 97 | N62: =E62 -> 183 | O62: 31 | P62: 27 | R62: =J62 -> 12 | S62: =K62 -> 53 | T62: =L62 -> 19 | U62: =M62 -> 97 | V62: =N62 -> 183 | W62: =O62 -> 31 | X62: =P62 -> 27
B63: ST Gift Card Liabilities | C63: 251 | D63: 306 | E63: 308 | G63: 224 | H63: 216 | I63: 213 | J63: =D63 -> 306 | K63: 268 | L63: 251 | M63: 238 | N63: =E63 -> 308 | O63: 271 | P63: 252 | R63: =J63 -> 306 | S63: =K63 -> 268 | T63: =L63 -> 251 | U63: =M63 -> 238 | V63: =N63 -> 308 | W63: =O63 -> 271 | X63: =P63 -> 252
B64: Other ST Liabilities | C64: 38 | D64: 40 | E64: 38 | G64: 37 | H64: 42 | I64: 38 | J64: =D64 -> 40 | K64: 39 | L64: 32 | M64: 40 | N64: =E64 -> 38 | O64: 33 | P64: 34 | R64: =J64 -> 40 | S64: =K64 -> 39 | T64: =L64 -> 32 | U64: =M64 -> 40 | V64: =N64 -> 38 | W64: =O64 -> 33 | X64: =P64 -> 34 | Z64: =SUM(X64/T64)-1 -> 0.0625
B65: Total Current Liabilities | C65: =SUM(C58:C64) -> 1491 | D65: =SUM(D58:D64) -> 1630 | E65: =SUM(E58:E64) -> 1839 | G65: =SUM(G58:G64) -> 1257 | H65: =SUM(H58:H64) -> 1386 | I65: =SUM(I58:I64) -> 1447 | J65: =SUM(J58:J64) -> 1630 | K65: =SUM(K58:K64) -> 1383 | L65: =SUM(L58:L64) -> 1468 | M65: =SUM(M58:M64) -> 1803 | N65: =SUM(N58:N64) -> 1839 | ... P65: =SUM(P58:P64) -> 1557 | R65: =SUM(R58:R64) -> 1630 | S65: =SUM(S58:S64) -> 1383 | T65: =SUM(T58:T64) -> 1468 | U65: =SUM(U58:U64) -> 1803 | V65: =SUM(V58:V64) -> 1839 | W65: =SUM(W58:W64) -> 1572 | X65: =SUM(X58:X64) -> 1557 | Z65: =SUM(X65/T65)-1 -> 0.060626703
B67: Non-Current Liabilities
B68: LT Lease Liabilities | C68: 862 | D68: 1154 | E68: 1301 | G68: 889 | H68: 977 | I68: 951 | J68: =D68 -> 1154 | K68: 1148 | L68: 1181 | M68: 1224 | N68: =E68 -> 1301 | O68: 1425 | P68: 1465 | R68: =J68 -> 1154 | S68: =K68 -> 1148 | T68: =L68 -> 1181 | U68: =M68 -> 1224 | V68: =N68 -> 1301 | W68: =O68 -> 1425 | X68: =P68 -> 1465 | Z68: =SUM(X68/T68)-1 -> 0.24047417
B69: LT Income Taxes | C69: 84 | D69: 45 | E69: 98 | G69: 83 | H69: 71 | I69: 70 | J69: =D69 -> 45 | K69: 45 | L69: 29 | M69: 33 | N69: =E69 -> 98 | O69: 98 | P69: 62 | R69: =J69 -> 45 | S69: =K69 -> 45 | T69: =L69 -> 29 | U69: =M69 -> 33 | V69: =N69 -> 98 | W69: =O69 -> 98 | X69: =P69 -> 62 | Z69: =SUM(X69/T69)-1 -> 1.137931
B70: Other LT Liabilities | C70: 20 | D70: 30 | E70: 41 | G70: 23 | H70: 25 | I70: 28 | J70: =D70 -> 30 | K70: 32 | L70: 34 | M70: 37 | N70: =E70 -> 41 | O70: 45 | P70: 52 | R70: =J70 -> 30 | S70: =K70 -> 32 | T70: =L70 -> 34 | U70: =M70 -> 37 | V70: =N70 -> 41 | W70: =O70 -> 45 | X70: =P70 -> 52 | Z70: =SUM(X70/T70)-1 -> 0.52941176
B71: Total Liabilities | C71: =SUM(C68:C70)+C65 -> 2457 | D71: =SUM(D68:D70)+D65 -> 2859 | E71: =SUM(E68:E70)+E65 -> 3279 | G71: =SUM(G68:G70)+G65 -> 2252 | H71: =SUM(H68:H70)+H65 -> 2459 | I71: =SUM(I68:I70)+I65 -> 2496 | J71: =SUM(J68:J70)+J65 -> 2859 | K71: =SUM(K68:K70)+K65 -> 2608 | L71: =SUM(L68:L70)+L65 -> 2712 | M71: =SUM(M68:M70)+M65 -> 3097 | N71: =SUM(N68:N70)+N65 -> 3279 | ... P71: =SUM(P68:P70)+P65 -> 3136 | R71: =SUM(R68:R70)+R65 -> 2859 | S71: =SUM(S68:S70)+S65 -> 2608 | T71: =SUM(T68:T70)+T65 -> 2712 | U71: =SUM(U68:U70)+U65 -> 3097 | V71: =SUM(V68:V70)+V65 -> 3279 | W71: =SUM(W68:W70)+W65 -> 3140 | X71: =SUM(X68:X70)+X65 -> 3136 | Z71: =SUM(X71/T71)-1 -> 0.15634218
B73: XXX | C73: 3149 | D73: 4232 | E73: 4324 | G73: 3321 | H73: 3533 | I73: 3526 | J73: 4232 | K73: 4220 | L73: 4032 | M73: 3986 | N73: 4324 | O73: 4290 | P73: 4387 | R73: =J73 -> 4232 | S73: =K73 -> 4220 | T73: =L73 -> 4032 | U73: =M73 -> 3986 | V73: =N73 -> 4324 | W73: =O73 -> 4290 | X73: =P73 -> 4387 | Z73: =SUM(X73/T73)-1 -> 0.088045635
B74: XXX | J74: =D74 -> 0 | N74: =E74 -> 0 | R74: =J74 -> 0 | S74: =K74 -> 0 | T74: =L74 -> 0 | U74: =M74 -> 0 | V74: =N74 -> 0 | W74: =O74 -> 0 | X74: =P74 -> 0 | Z74: =SUM(X74/T74)-1 -> #DIV/0!
B75: XXX | J75: =D75 -> 0 | N75: =E75 -> 0 | R75: =J75 -> 0 | S75: =K75 -> 0 | T75: =L75 -> 0 | U75: =M75 -> 0 | V75: =N75 -> 0 | W75: =O75 -> 0 | X75: =P75 -> 0 | Z75: =SUM(X75/T75)-1 -> #DIV/0!
B76: XXX | J76: =D76 -> 0 | N76: =E76 -> 0 | R76: =J76 -> 0 | S76: =K76 -> 0 | T76: =L76 -> 0 | U76: =M76 -> 0 | V76: =N76 -> 0 | W76: =O76 -> 0 | X76: =P76 -> 0 | Z76: =SUM(X76/T76)-1 -> #DIV/0!
B77: XXX | J77: =D77 -> 0 | N77: =E77 -> 0 | R77: =J77 -> 0 | S77: =K77 -> 0 | T77: =L77 -> 0 | U77: =M77 -> 0 | V77: =N77 -> 0 | W77: =O77 -> 0 | X77: =P77 -> 0 | Z77: =SUM(X77/T77)-1 -> #DIV/0!
B78: Total stockholders' equity | C78: =SUM(C73:C77) -> 3149 | D78: =SUM(D73:D77) -> 4232 | E78: =SUM(E73:E77) -> 4324 | G78: =SUM(G73:G77) -> 3321 | H78: =SUM(H73:H77) -> 3533 | I78: =SUM(I73:I77) -> 3526 | J78: =SUM(J73:J77) -> 4232 | K78: =SUM(K73:K77) -> 4220 | L78: =SUM(L73:L77) -> 4032 | M78: =SUM(M73:M77) -> 3986 | N78: =SUM(N73:N77) -> 4324 | ... P78: =SUM(P73:P77) -> 4387 | R78: =SUM(R73:R77) -> 4232 | S78: =SUM(S73:S77) -> 4220 | T78: =SUM(T73:T77) -> 4032 | U78: =SUM(U73:U77) -> 3986 | V78: =SUM(V73:V77) -> 4324 | W78: =SUM(W73:W77) -> 4290 | X78: =SUM(X73:X77) -> 4387 | Z78: =SUM(X78/T78)-1 -> 0.088045635
B79: Total liabilities and stockholders' equity | C79: =SUM(C78+C71) -> 5606 | D79: =SUM(D78+D71) -> 7091 | E79: =SUM(E78+E71) -> 7603 | G79: =SUM(G78+G71) -> 5573 | H79: =SUM(H78+H71) -> 5992 | I79: =SUM(I78+I71) -> 6022 | J79: =SUM(J78+J71) -> 7091 | K79: =SUM(K78+K71) -> 6828 | L79: =SUM(L78+L71) -> 6744 | M79: =SUM(M78+M71) -> 7083 | N79: =SUM(N78+N71) -> 7603 | ... P79: =SUM(P78+P71) -> 7523 | R79: =SUM(R78+R71) -> 7091 | S79: =SUM(S78+S71) -> 6828 | T79: =SUM(T78+T71) -> 6744 | U79: =SUM(U78+U71) -> 7083 | V79: =SUM(V78+V71) -> 7603 | W79: =SUM(W78+W71) -> 7430 | X79: =SUM(X78+X71) -> 7523 | Z79: =SUM(X79/T79)-1 -> 0.11551008
B81: Balance Check | C81: =C79-C55 -> -1 | D81: =D79-D55 -> -3 | E81: =E79-E55 -> 0 | G81: =G79-G55 -> 2 | H81: =H79-H55 -> -1 | I81: =I79-I55 -> -1 | J81: =J79-J55 -> -3 | K81: =K79-K55 -> 0 | L81: =L79-L55 -> 0 | M81: =M79-M55 -> 0 | N81: =N79-N55 -> 0 | ... P81: =P79-P55 -> 0 | R81: =R79-R55 -> -3 | S81: =S79-S55 -> 0 | T81: =T79-T55 -> 0 | U81: =U79-U55 -> 0 | V81: =V79-V55 -> 0 | W81: =W79-W55 -> 0 | X81: =X79-X55 -> 0
A84: X | B84: Cash-Flows Statement | C84: FYE | M84: Quarterly | T84: LTM | Z84: Variance
B85: =B7 -> Fiscal Period | C85: =C7 -> 2022 | D85: =D7 -> 2023 | E85: =E7 -> 2024 | G85: =G7 -> 1Q23 | H85: =H7 -> 2Q23 | I85: =I7 -> 3Q23 | J85: =J7 -> 4Q23 | K85: =K7 -> 1Q24 | L85: =L7 -> 2Q24 | M85: =M7 -> 3Q24 | N85: =N7 -> 4Q24 | ... P85: =P7 -> 2Q25 | R85: =R7 -> 4Q23 | S85: =S7 -> 1Q24 | T85: =T7 -> 2Q24 | U85: =U7 -> 3Q24 | V85: =V7 -> 4Q24 | W85: =W7 -> 1Q25 | X85: =X7 -> 2Q25
B86: =B8 -> Fiscal Period End Date | C86: =C8 -> XXX | D86: =D8 -> XXX | E86: =E8 -> XXX | G86: =G8 -> XXX | H86: =H8 -> XXX | I86: =I8 -> XXX | J86: =J8 -> XXX | K86: =K8 -> XXX | L86: =L8 -> XXX | M86: =M8 -> XXX | N86: =N8 -> XXX | ... P86: =P8 -> XXX | R86: =R8 -> XXX | S86: =S8 -> XXX | T86: =T8 -> XXX | U86: =U8 -> XXX | V86: =V8 -> XXX | W86: =W8 -> XXX | X86: =X8 -> XXX
B88: Cash-Flows From Operating Activities
B89: Net income (loss) | C89: =C27 -> 855 | D89: =D27 -> 1549 | E89: =E27 -> 1815 | G89: =G27 -> -722.4 | H89: =H27 -> -800.3 | I89: =I27 -> -767.4 | J89: =J27 -> 3838.1 | K89: =K27 -> -693.2 | L89: =L27 -> -741.2 | M89: =M27 -> -672.4 | N89: =N27 -> 3921.8 | ... P89: =P27 -> -808.1 | R89: =R27 -> 1548 | S89: =S27 -> 1577.2 | T89: =T27 -> 1636.3 | U89: =U27 -> 1731.3 | V89: =V27 -> 1815 | W89: =W27 -> 1814.4 | X89: =X27 -> 1747.5 | Z89: =SUM(X89/T89)-1 -> 0.067958198
B91: Adjustments to reconcile net income:
B92: Depreciation and amortization | J92: =SUM(D92-SUM(G92:I92)) -> 0 | N92: =SUM(E92-SUM(K92:M92)) -> 0 | R92: =SUM(H92:K92) -> 0 | S92: =SUM(I92:L92) -> 0 | T92: =SUM(J92:M92) -> 0 | U92: =SUM(K92:N92) -> 0 | V92: =SUM(L92:O92) -> 0 | W92: =SUM(M92:P92) -> 0 | X92: =SUM(N92:P92) -> 0 | Z92: =SUM(X92/T92)-1 -> #DIV/0!
B93: XXX | J93: =SUM(D93-SUM(G93:I93)) -> 0 | N93: =SUM(E93-SUM(K93:M93)) -> 0 | R93: =SUM(H93:K93) -> 0 | S93: =SUM(I93:L93) -> 0 | T93: =SUM(J93:M93) -> 0 | U93: =SUM(K93:N93) -> 0 | V93: =SUM(L93:O93) -> 0 | W93: =SUM(M93:P93) -> 0 | X93: =SUM(N93:P93) -> 0 | Z93: =SUM(X93/T93)-1 -> #DIV/0!
B94: XXX | J94: =SUM(D94-SUM(G94:I94)) -> 0 | N94: =SUM(E94-SUM(K94:M94)) -> 0 | R94: =SUM(H94:K94) -> 0 | S94: =SUM(I94:L94) -> 0 | T94: =SUM(J94:M94) -> 0 | U94: =SUM(K94:N94) -> 0 | V94: =SUM(L94:O94) -> 0 | W94: =SUM(M94:P94) -> 0 | X94: =SUM(N94:P94) -> 0 | Z94: =SUM(X94/T94)-1 -> #DIV/0!
B95: XXX | J95: =SUM(D95-SUM(G95:I95)) -> 0 | N95: =SUM(E95-SUM(K95:M95)) -> 0 | R95: =SUM(H95:K95) -> 0 | S95: =SUM(I95:L95) -> 0 | T95: =SUM(J95:M95) -> 0 | U95: =SUM(K95:N95) -> 0 | V95: =SUM(L95:O95) -> 0 | W95: =SUM(M95:P95) -> 0 | X95: =SUM(N95:P95) -> 0 | Z95: =SUM(X95/T95)-1 -> #DIV/0!
B96: XXX | J96: =SUM(D96-SUM(G96:I96)) -> 0 | N96: =SUM(E96-SUM(K96:M96)) -> 0 | R96: =SUM(H96:K96) -> 0 | S96: =SUM(I96:L96) -> 0 | T96: =SUM(J96:M96) -> 0 | U96: =SUM(K96:N96) -> 0 | V96: =SUM(L96:O96) -> 0 | W96: =SUM(M96:P96) -> 0 | X96: =SUM(N96:P96) -> 0 | Z96: =SUM(X96/T96)-1 -> #DIV/0!
B97: XXX | J97: =SUM(D97-SUM(G97:I97)) -> 0 | N97: =SUM(E97-SUM(K97:M97)) -> 0 | R97: =SUM(H97:K97) -> 0 | S97: =SUM(I97:L97) -> 0 | T97: =SUM(J97:M97) -> 0 | U97: =SUM(K97:N97) -> 0 | V97: =SUM(L97:O97) -> 0 | W97: =SUM(M97:P97) -> 0 | X97: =SUM(N97:P97) -> 0 | Z97: =SUM(X97/T97)-1 -> #DIV/0!
B98: XXX | J98: =SUM(D98-SUM(G98:I98)) -> 0 | N98: =SUM(E98-SUM(K98:M98)) -> 0 | R98: =SUM(H98:K98) -> 0 | S98: =SUM(I98:L98) -> 0 | T98: =SUM(J98:M98) -> 0 | U98: =SUM(K98:N98) -> 0 | V98: =SUM(L98:O98) -> 0 | W98: =SUM(M98:P98) -> 0 | X98: =SUM(N98:P98) -> 0 | Z98: =SUM(X98/T98)-1 -> #DIV/0!
B99: XXX | J99: =SUM(D99-SUM(G99:I99)) -> 0 | N99: =SUM(E99-SUM(K99:M99)) -> 0 | R99: =SUM(H99:K99) -> 0 | S99: =SUM(I99:L99) -> 0 | T99: =SUM(J99:M99) -> 0 | U99: =SUM(K99:N99) -> 0 | V99: =SUM(L99:O99) -> 0 | W99: =SUM(M99:P99) -> 0 | X99: =SUM(N99:P99) -> 0 | Z99: =SUM(X99/T99)-1 -> #DIV/0!
B100: XXX | J100: =SUM(D100-SUM(G100:I100)) -> 0 | N100: =SUM(E100-SUM(K100:M100)) -> 0 | R100: =SUM(H100:K100) -> 0 | S100: =SUM(I100:L100) -> 0 | T100: =SUM(J100:M100) -> 0 | U100: =SUM(K100:N100) -> 0 | V100: =SUM(L100:O100) -> 0 | W100: =SUM(M100:P100) -> 0 | X100: =SUM(N100:P100) -> 0 | Z100: =SUM(X100/T100)-1 -> #DIV/0!
B102: Changes in assets and liabilities:
B103: Receivables | J103: =SUM(D103-SUM(G103:I103)) -> 0 | N103: =SUM(E103-SUM(K103:M103)) -> 0 | R103: =SUM(H103:K103) -> 0 | S103: =SUM(I103:L103) -> 0 | T103: =SUM(J103:M103) -> 0 | U103: =SUM(K103:N103) -> 0 | V103: =SUM(L103:O103) -> 0 | W103: =SUM(M103:P103) -> 0 | X103: =SUM(N103:P103) -> 0 | Z103: =SUM(X103/T103)-1 -> #DIV/0!
B104: XXX | J104: =SUM(D104-SUM(G104:I104)) -> 0 | N104: =SUM(E104-SUM(K104:M104)) -> 0 | R104: =SUM(H104:K104) -> 0 | S104: =SUM(I104:L104) -> 0 | T104: =SUM(J104:M104) -> 0 | U104: =SUM(K104:N104) -> 0 | V104: =SUM(L104:O104) -> 0 | W104: =SUM(M104:P104) -> 0 | X104: =SUM(N104:P104) -> 0 | Z104: =SUM(X104/T104)-1 -> #DIV/0!
B105: XXX | J105: =SUM(D105-SUM(G105:I105)) -> 0 | N105: =SUM(E105-SUM(K105:M105)) -> 0 | R105: =SUM(H105:K105) -> 0 | S105: =SUM(I105:L105) -> 0 | T105: =SUM(J105:M105) -> 0 | U105: =SUM(K105:N105) -> 0 | V105: =SUM(L105:O105) -> 0 | W105: =SUM(M105:P105) -> 0 | X105: =SUM(N105:P105) -> 0 | Z105: =SUM(X105/T105)-1 -> #DIV/0!
B106: XXX | J106: =SUM(D106-SUM(G106:I106)) -> 0 | N106: =SUM(E106-SUM(K106:M106)) -> 0 | R106: =SUM(H106:K106) -> 0 | S106: =SUM(I106:L106) -> 0 | T106: =SUM(J106:M106) -> 0 | U106: =SUM(K106:N106) -> 0 | V106: =SUM(L106:O106) -> 0 | W106: =SUM(M106:P106) -> 0 | X106: =SUM(N106:P106) -> 0 | Z106: =SUM(X106/T106)-1 -> #DIV/0!
B107: XXX | J107: =SUM(D107-SUM(G107:I107)) -> 0 | N107: =SUM(E107-SUM(K107:M107)) -> 0 | R107: =SUM(H107:K107) -> 0 | S107: =SUM(I107:L107) -> 0 | T107: =SUM(J107:M107) -> 0 | U107: =SUM(K107:N107) -> 0 | V107: =SUM(L107:O107) -> 0 | W107: =SUM(M107:P107) -> 0 | X107: =SUM(N107:P107) -> 0 | Z107: =SUM(X107/T107)-1 -> #DIV/0!
B108: XXX | J108: =SUM(D108-SUM(G108:I108)) -> 0 | N108: =SUM(E108-SUM(K108:M108)) -> 0 | R108: =SUM(H108:K108) -> 0 | S108: =SUM(I108:L108) -> 0 | T108: =SUM(J108:M108) -> 0 | U108: =SUM(K108:N108) -> 0 | V108: =SUM(L108:O108) -> 0 | W108: =SUM(M108:P108) -> 0 | X108: =SUM(N108:P108) -> 0 | Z108: =SUM(X108/T108)-1 -> #DIV/0!
B109: Net cash used in operating activities | C109: =SUM(C89:C108) -> 855 | D109: =SUM(D89:D108) -> 1549 | E109: =SUM(E89:E108) -> 1815 | G109: =SUM(G89:G108) -> -722.4 | H109: =SUM(H89:H108) -> -800.3 | I109: =SUM(I89:I108) -> -767.4 | J109: =SUM(J89:J108) -> 3838.1 | K109: =SUM(K89:K108) -> -693.2 | L109: =SUM(L89:L108) -> -741.2 | M109: =SUM(M89:M108) -> -672.4 | N109: =SUM(N89:N108) -> 3921.8 | ... P109: =SUM(P89:P108) -> -808.1 | R109: =SUM(R89:R108) -> 1548 | S109: =SUM(S89:S108) -> 1577.2 | T109: =SUM(T89:T108) -> 1636.3 | U109: =SUM(U89:U108) -> 1731.3 | V109: =SUM(V89:V108) -> 1815 | W109: =SUM(W89:W108) -> 1814.4 | X109: =SUM(X89:X108) -> 1747.5 | Z109: =SUM(X109/T109)-1 -> 0.067958198
B111: Cash flows from investing activities:
B112: Additions to property and equipment | J112: =SUM(D112-SUM(G112:I112)) -> 0 | N112: =SUM(E112-SUM(K112:M112)) -> 0 | R112: =SUM(H112:K112) -> 0 | S112: =SUM(I112:L112) -> 0 | T112: =SUM(J112:M112) -> 0 | U112: =SUM(K112:N112) -> 0 | V112: =SUM(L112:O112) -> 0 | W112: =SUM(M112:P112) -> 0 | X112: =SUM(N112:P112) -> 0 | Z112: =SUM(X112/T112)-1 -> #DIV/0!
B113: XXX | J113: =SUM(D113-SUM(G113:I113)) -> 0 | N113: =SUM(E113-SUM(K113:M113)) -> 0 | R113: =SUM(H113:K113) -> 0 | S113: =SUM(I113:L113) -> 0 | T113: =SUM(J113:M113) -> 0 | U113: =SUM(K113:N113) -> 0 | V113: =SUM(L113:O113) -> 0 | W113: =SUM(M113:P113) -> 0 | X113: =SUM(N113:P113) -> 0 | Z113: =SUM(X113/T113)-1 -> #DIV/0!
B114: XXX | J114: =SUM(D114-SUM(G114:I114)) -> 0 | N114: =SUM(E114-SUM(K114:M114)) -> 0 | R114: =SUM(H114:K114) -> 0 | S114: =SUM(I114:L114) -> 0 | T114: =SUM(J114:M114) -> 0 | U114: =SUM(K114:N114) -> 0 | V114: =SUM(L114:O114) -> 0 | W114: =SUM(M114:P114) -> 0 | X114: =SUM(N114:P114) -> 0 | Z114: =SUM(X114/T114)-1 -> #DIV/0!
B115: XXX | J115: =SUM(D115-SUM(G115:I115)) -> 0 | N115: =SUM(E115-SUM(K115:M115)) -> 0 | R115: =SUM(H115:K115) -> 0 | S115: =SUM(I115:L115) -> 0 | T115: =SUM(J115:M115) -> 0 | U115: =SUM(K115:N115) -> 0 | V115: =SUM(L115:O115) -> 0 | W115: =SUM(M115:P115) -> 0 | X115: =SUM(N115:P115) -> 0 | Z115: =SUM(X115/T115)-1 -> #DIV/0!
B116: XXX | J116: =SUM(D116-SUM(G116:I116)) -> 0 | N116: =SUM(E116-SUM(K116:M116)) -> 0 | R116: =SUM(H116:K116) -> 0 | S116: =SUM(I116:L116) -> 0 | T116: =SUM(J116:M116) -> 0 | U116: =SUM(K116:N116) -> 0 | V116: =SUM(L116:O116) -> 0 | W116: =SUM(M116:P116) -> 0 | X116: =SUM(N116:P116) -> 0 | Z116: =SUM(X116/T116)-1 -> #DIV/0!
B117: Net cash used in investing activities | C117: =SUM(C112:C116) -> 0 | D117: =SUM(D112:D116) -> 0 | E117: =SUM(E112:E116) -> 0 | G117: =SUM(G112:G116) -> 0 | H117: =SUM(H112:H116) -> 0 | I117: =SUM(I112:I116) -> 0 | J117: =SUM(J112:J116) -> 0 | K117: =SUM(K112:K116) -> 0 | L117: =SUM(L112:L116) -> 0 | M117: =SUM(M112:M116) -> 0 | N117: =SUM(N112:N116) -> 0 | ... P117: =SUM(P112:P116) -> 0 | R117: =SUM(R112:R116) -> 0 | S117: =SUM(S112:S116) -> 0 | T117: =SUM(T112:T116) -> 0 | U117: =SUM(U112:U116) -> 0 | V117: =SUM(V112:V116) -> 0 | W117: =SUM(W112:W116) -> 0 | X117: =SUM(X112:X116) -> 0 | Z117: =SUM(X117/T117)-1 -> #DIV/0!
B119: Cash flows from financing activities:
B120: Proceeds from Equity Issuances / (Repurchases) | J120: =SUM(D120-SUM(G120:I120)) -> 0 | N120: =SUM(E120-SUM(K120:M120)) -> 0 | R120: =SUM(H120:K120) -> 0 | S120: =SUM(I120:L120) -> 0 | T120: =SUM(J120:M120) -> 0 | U120: =SUM(K120:N120) -> 0 | V120: =SUM(L120:O120) -> 0 | W120: =SUM(M120:P120) -> 0 | X120: =SUM(N120:P120) -> 0 | Z120: =SUM(X120/T120)-1 -> #DIV/0!
B121: XXX | J121: =SUM(D121-SUM(G121:I121)) -> 0 | N121: =SUM(E121-SUM(K121:M121)) -> 0 | R121: =SUM(H121:K121) -> 0 | S121: =SUM(I121:L121) -> 0 | T121: =SUM(J121:M121) -> 0 | U121: =SUM(K121:N121) -> 0 | V121: =SUM(L121:O121) -> 0 | W121: =SUM(M121:P121) -> 0 | X121: =SUM(N121:P121) -> 0 | Z121: =SUM(X121/T121)-1 -> #DIV/0!
B122: XXX | J122: =SUM(D122-SUM(G122:I122)) -> 0 | N122: =SUM(E122-SUM(K122:M122)) -> 0 | R122: =SUM(H122:K122) -> 0 | S122: =SUM(I122:L122) -> 0 | T122: =SUM(J122:M122) -> 0 | U122: =SUM(K122:N122) -> 0 | V122: =SUM(L122:O122) -> 0 | W122: =SUM(M122:P122) -> 0 | X122: =SUM(N122:P122) -> 0 | Z122: =SUM(X122/T122)-1 -> #DIV/0!
B123: XXX | J123: =SUM(D123-SUM(G123:I123)) -> 0 | N123: =SUM(E123-SUM(K123:M123)) -> 0 | R123: =SUM(H123:K123) -> 0 | S123: =SUM(I123:L123) -> 0 | T123: =SUM(J123:M123) -> 0 | U123: =SUM(K123:N123) -> 0 | V123: =SUM(L123:O123) -> 0 | W123: =SUM(M123:P123) -> 0 | X123: =SUM(N123:P123) -> 0 | Z123: =SUM(X123/T123)-1 -> #DIV/0!
...

Sheet Revenue Drivers
B2: ='Historical Financials'!B2 -> Lululemon Athletica Inc (NASDAQ: LULU) | C2: FYE | M2: Quarterly | T2: LTM
B3: Segment Anaysis | C3: ='Historical Financials'!C7 -> 2022 | D3: ='Historical Financials'!D7 -> 2023 | E3: ='Historical Financials'!E7 -> 2024 | G3: ='Historical Financials'!G7 -> 1Q23 | H3: ='Historical Financials'!H7 -> 2Q23 | I3: ='Historical Financials'!I7 -> 3Q23 | J3: ='Historical Financials'!J7 -> 4Q23 | K3: ='Historical Financials'!K7 -> 1Q24 | L3: ='Historical Financials'!L7 -> 2Q24 | M3: ='Historical Financials'!M7 -> 3Q24 | N3: ='Historical Financials'!N7 -> 4Q24 | ... P3: ='Historical Financials'!P7 -> 2Q25 | R3: =J3 -> 4Q23 | S3: =K3 -> 1Q24 | T3: =L3 -> 2Q24 | U3: =M3 -> 3Q24 | V3: =N3 -> 4Q24 | W3: =O3 -> 1Q25 | X3: =P3 -> 2Q25
B4: ($ In Millions) | C4: ='Historical Financials'!C8 -> XXX | D4: ='Historical Financials'!D8 -> XXX | E4: ='Historical Financials'!E8 -> XXX | G4: ='Historical Financials'!G8 -> XXX | H4: ='Historical Financials'!H8 -> XXX | I4: ='Historical Financials'!I8 -> XXX | J4: ='Historical Financials'!J8 -> XXX | K4: ='Historical Financials'!K8 -> XXX | L4: ='Historical Financials'!L8 -> XXX | M4: ='Historical Financials'!M8 -> XXX | N4: ='Historical Financials'!N8 -> XXX | ... P4: ='Historical Financials'!P8 -> XXX | R4: =J4 -> XXX | S4: =K4 -> XXX | T4: =L4 -> XXX | U4: =M4 -> XXX | V4: =N4 -> XXX | W4: =O4 -> XXX | X4: =P4 -> XXX
A6: X | B6: Revenue by reportable segment
A8: X | B8: Revenue Segment Anaysis
B9: Women's Apparel | C9: 5260 | D9: 6147 | E9: 6693 | G9: 1309 | H9: 1396 | I9: 1434 | J9: =SUM(D9-SUM(G9:I9)) -> 2008 | K9: 1435 | L9: 1476 | M9: 1556 | N9: =SUM(E9-SUM(K9:M9)) -> 2226 | O9: 1535 | P9: 1547 | R9: =SUM(G9:J9) -> 6147 | S9: =SUM(H9:K9) -> 6273 | T9: =SUM(I9:L9) -> 6353 | U9: =SUM(J9:M9) -> 6475 | V9: =SUM(K9:N9) -> 6693 | W9: =SUM(L9:O9) -> 6793 | X9: =SUM(M9:P9) -> 6864
B10: Men's Apparel | C10: 1957 | D10: 2253 | E10: 2558 | G10: 438 | H10: 531 | I10: 505 | J10: =SUM(D10-SUM(G10:I10)) -> 779 | K10: 506 | L10: 588 | M10: 551 | N10: =SUM(E10-SUM(K10:M10)) -> 913 | O10: 545 | P10: 625 | R10: =SUM(G10:J10) -> 2253 | S10: =SUM(H10:K10) -> 2321 | T10: =SUM(I10:L10) -> 2378 | U10: =SUM(J10:M10) -> 2424 | V10: =SUM(K10:N10) -> 2558 | W10: =SUM(L10:O10) -> 2597 | X10: =SUM(M10:P10) -> 2634
B11: Acccessories & Other | C11: 894 | D11: 1219 | E11: 1337 | G11: 254 | H11: 282 | I11: 265 | J11: =SUM(D11-SUM(G11:I11)) -> 418 | K11: 268 | L11: 307 | M11: 290 | N11: =SUM(E11-SUM(K11:M11)) -> 472 | O11: 291 | P11: 353 | R11: =SUM(G11:J11) -> 1219 | S11: =SUM(H11:K11) -> 1233 | T11: =SUM(I11:L11) -> 1258 | U11: =SUM(J11:M11) -> 1283 | V11: =SUM(K11:N11) -> 1337 | W11: =SUM(L11:O11) -> 1360 | X11: =SUM(M11:P11) -> 1406
B12: Total Net Revenue | C12: =SUM(C9:C11) -> 8111 | D12: =SUM(D9:D11) -> 9619 | E12: =SUM(E9:E11) -> 10588 | G12: =SUM(G9:G11) -> 2001 | H12: =SUM(H9:H11) -> 2209 | I12: =SUM(I9:I11) -> 2204 | J12: =SUM(J9:J11) -> 3205 | K12: =SUM(K9:K11) -> 2209 | L12: =SUM(L9:L11) -> 2371 | M12: =SUM(M9:M11) -> 2397 | N12: =SUM(N9:N11) -> 3611 | ... P12: =SUM(P9:P11) -> 2525 | R12: =SUM(R9:R11) -> 9619 | S12: =SUM(S9:S11) -> 9827 | T12: =SUM(T9:T11) -> 9989 | U12: =SUM(U9:U11) -> 10182 | V12: =SUM(V9:V11) -> 10588 | W12: =SUM(W9:W11) -> 10750 | X12: =SUM(X9:X11) -> 10904
B13: Balance Check | C13: =+C12-'Historical Financials'!C11 -> 0 | D13: =+D12-'Historical Financials'!D11 -> 0 | E13: =+E12-'Historical Financials'!E11 -> 0 | G13: =+G12-'Historical Financials'!G11 -> 1012.4 | H13: =+H12-'Historical Financials'!H11 -> 1141.3 | I13: =+I12-'Historical Financials'!I11 -> 1015.4 | J13: =+J12-'Historical Financials'!J11 -> -3169.1 | K13: =+K12-'Historical Financials'!K11 -> 1014.2 | L13: =+L12-'Historical Financials'!L11 -> 1134.2 | M13: =+M12-'Historical Financials'!M11 -> 1024.4 | N13: =+N12-'Historical Financials'!N11 -> -3172.8 | ... P13: =+P12-'Historical Financials'!P11 -> 1180.1 | R13: =+R12-'Historical Financials'!R11 -> 0 | S13: =+S12-'Historical Financials'!S11 -> 1.8 | T13: =+T12-'Historical Financials'!T11 -> -5.3 | U13: =+U12-'Historical Financials'!U11 -> 3.7 | V13: =+V12-'Historical Financials'!V11 -> 0 | W13: =+W12-'Historical Financials'!W11 -> -6.4 | X13: =+X12-'Historical Financials'!X11 -> 39.5
B15: =B9&"(%)" -> Women's Apparel(%) | C15: =SUM(C9/C$12) -> 0.64850203 | D15: =SUM(D9/D$12) -> 0.63904772 | E15: =SUM(E9/E$12) -> 0.63213071 | G15: =SUM(G9/G$12) -> 0.65417291 | H15: =SUM(H9/H$12) -> 0.63196016 | I15: =SUM(I9/I$12) -> 0.65063521 | J15: =SUM(J9/J$12) -> 0.62652106 | K15: =SUM(K9/K$12) -> 0.64961521 | L15: =SUM(L9/L$12) -> 0.62252214 | M15: =SUM(M9/M$12) -> 0.64914476 | N15: =SUM(N9/N$12) -> 0.61644974 | ... P15: =SUM(P9/P$12) -> 0.61267327 | R15: =K15 -> 0.64961521 | S15: =L15 -> 0.62252214 | T15: =M15 -> 0.64914476 | U15: =N15 -> 0.61644974 | V15: =O15 -> 0.64740616 | W15: =P15 -> 0.61267327 | X15: =#REF! -> #REF!
B16: =B10&"(%)" -> Men's Apparel(%) | C16: =SUM(C10/C$12) -> 0.24127728 | D16: =SUM(D10/D$12) -> 0.23422393 | E16: =SUM(E10/E$12) -> 0.24159426 | G16: =SUM(G10/G$12) -> 0.21889055 | H16: =SUM(H10/H$12) -> 0.24038026 | I16: =SUM(I10/I$12) -> 0.22912886 | J16: =SUM(J10/J$12) -> 0.24305772 | K16: =SUM(K10/K$12) -> 0.22906292 | L16: =SUM(L10/L$12) -> 0.24799663 | M16: =SUM(M10/M$12) -> 0.22987067 | N16: =SUM(N10/N$12) -> 0.25283855 | ... P16: =SUM(P10/P$12) -> 0.24752475 | R16: =K16 -> 0.22906292 | S16: =L16 -> 0.24799663 | T16: =M16 -> 0.22987067 | U16: =N16 -> 0.25283855 | V16: =O16 -> 0.22986082 | W16: =P16 -> 0.24752475 | X16: =#REF! -> #REF!
B17: =B11&"(%)" -> Acccessories & Other(%) | C17: =SUM(C11/C$12) -> 0.11022069 | D17: =SUM(D11/D$12) -> 0.12672835 | E17: =SUM(E11/E$12) -> 0.12627503 | G17: =SUM(G11/G$12) -> 0.12693653 | H17: =SUM(H11/H$12) -> 0.12765957 | I17: =SUM(I11/I$12) -> 0.12023593 | J17: =SUM(J11/J$12) -> 0.13042122 | K17: =SUM(K11/K$12) -> 0.12132187 | L17: =SUM(L11/L$12) -> 0.12948123 | M17: =SUM(M11/M$12) -> 0.12098456 | N17: =SUM(N11/N$12) -> 0.13071171 | ... P17: =SUM(P11/P$12) -> 0.13980198 | R17: =K17 -> 0.12132187 | S17: =L17 -> 0.12948123 | T17: =M17 -> 0.12098456 | U17: =N17 -> 0.13071171 | V17: =O17 -> 0.12273302 | W17: =P17 -> 0.13980198 | X17: =#REF! -> #REF!
A19: X | B19: Revenue by Geography
A21: X | B21: Revenue by Geography
B22: U.S. Revenues | C22: 5654 | D22: 6346 | E22: 6483 | G22: 1314 | H22: 1425 | I22: 1424 | J22: =SUM(D22-SUM(G22:I22)) -> 2183 | K22: 1340 | L22: 1422 | M22: 1424 | N22: =SUM(E22-SUM(K22:M22)) -> 2297 | O22: 1363 | P22: 1415 | R22: =SUM(J22:M22) -> 6369 | S22: =SUM(K22:N22) -> 6483 | T22: =SUM(L22:O22) -> 6506 | U22: =SUM(M22:P22) -> 6499 | V22: =SUM(N22:P22) -> 5075 | W22: =SUM(O22:P22) -> 2778 | X22: =SUM(P22:P22) -> 1415
B23: Canada Revenues | C23: 1163 | D23: 1285 | E23: 1412 | G23: 253 | H23: 295 | I23: 309 | J23: =SUM(D23-SUM(G23:I23)) -> 428 | K23: 282 | L23: 319 | M23: 335 | N23: =SUM(E23-SUM(K23:M23)) -> 476 | O23: 293 | P23: 321 | R23: =SUM(J23:M23) -> 1364 | S23: =SUM(K23:N23) -> 1412 | T23: =SUM(L23:O23) -> 1423 | U23: =SUM(M23:P23) -> 1425 | V23: =SUM(N23:P23) -> 1090 | W23: =SUM(O23:P23) -> 614 | X23: =SUM(P23:P23) -> 321
B24: Mexico Revenues | C24: 0 | D24: 0 | E24: 33 | G24: 0 | H24: 0 | I24: 0 | J24: =SUM(D24-SUM(G24:I24)) -> 0 | K24: 0 | L24: 0 | M24: 11 | N24: =SUM(E24-SUM(K24:M24)) -> 22 | O24: 19 | P24: 22 | R24: =SUM(J24:M24) -> 11 | S24: =SUM(K24:N24) -> 33 | T24: =SUM(L24:O24) -> 52 | U24: =SUM(M24:P24) -> 74 | V24: =SUM(N24:P24) -> 63 | W24: =SUM(O24:P24) -> 41 | X24: =SUM(P24:P24) -> 22
B25: China Revenues | C25: 682 | D25: 1134 | E25: 1541 | G25: 250 | H25: 278 | I25: 267 | J25: =SUM(D25-SUM(G25:I25)) -> 339 | K25: 346 | L25: 356 | M25: 359 | N25: =SUM(E25-SUM(K25:M25)) -> 480 | O25: 412 | P25: 441 | R25: =SUM(J25:M25) -> 1400 | S25: =SUM(K25:N25) -> 1541 | T25: =SUM(L25:O25) -> 1607 | U25: =SUM(M25:P25) -> 1692 | V25: =SUM(N25:P25) -> 1333 | W25: =SUM(O25:P25) -> 853 | X25: =SUM(P25:P25) -> 441
B26: Other Revenues | C26: 611 | D26: 853 | E26: 1119 | G26: 183 | H26: 212 | I26: 205 | J26: =SUM(D26-SUM(G26:I26)) -> 253 | K26: 241 | L26: 273 | M26: 267 | N26: =SUM(E26-SUM(K26:M26)) -> 338 | O26: 284 | P26: 326 | R26: =SUM(J26:M26) -> 1034 | S26: =SUM(K26:N26) -> 1119 | T26: =SUM(L26:O26) -> 1162 | U26: =SUM(M26:P26) -> 1215 | V26: =SUM(N26:P26) -> 948 | W26: =SUM(O26:P26) -> 610 | X26: =SUM(P26:P26) -> 326
B27: Total Revenue | C27: =SUM(C22:C26) -> 8110 | D27: =SUM(D22:D26) -> 9618 | E27: =SUM(E22:E26) -> 10588 | G27: =SUM(G22:G26) -> 2000 | H27: =SUM(H22:H26) -> 2210 | I27: =SUM(I22:I26) -> 2205 | J27: =SUM(J22:J26) -> 3203 | K27: =SUM(K22:K26) -> 2209 | L27: =SUM(L22:L26) -> 2370 | M27: =SUM(M22:M26) -> 2396 | N27: =SUM(N22:N26) -> 3613 | ... P27: =SUM(P22:P26) -> 2525 | R27: =SUM(R22:R26) -> 10178 | S27: =SUM(S22:S26) -> 10588 | T27: =SUM(T22:T26) -> 10750 | U27: =SUM(U22:U26) -> 10905 | V27: =SUM(V22:V26) -> 8509 | W27: =SUM(W22:W26) -> 4896 | X27: =SUM(X22:X26) -> 2525
B28: Balance Check | C28: =+C27-C12 -> -1 | D28: =+D27-D12 -> -1 | E28: =+E27-E12 -> 0 | G28: =+G27-G12 -> -1 | H28: =+H27-H12 -> 1 | I28: =+I27-I12 -> 1 | J28: =+J27-J12 -> -2 | K28: =+K27-K12 -> 0 | L28: =+L27-L12 -> -1 | M28: =+M27-M12 -> -1 | N28: =+N27-N12 -> 2 | ... P28: =+P27-P12 -> 0 | R28: =+R27-R12 -> 559 | S28: =+S27-S12 -> 761 | T28: =+T27-T12 -> 761 | U28: =+U27-U12 -> 723 | V28: =+V27-V12 -> -2079 | W28: =+W27-W12 -> -5854 | X28: =+X27-X12 -> -8379
B30: =B22&"(%)" -> U.S. Revenues(%) | C30: =C22/C$27 -> 0.697164 | D30: =D22/D$27 -> 0.65980453 | E30: =E22/E$27 -> 0.61229694 | G30: =G22/G$27 -> 0.657 | H30: =H22/H$27 -> 0.64479638 | I30: =I22/I$27 -> 0.64580499 | J30: =J22/J$27 -> 0.68154855 | K30: =K22/K$27 -> 0.60660933 | L30: =L22/L$27 -> 0.6 | M30: =M22/M$27 -> 0.59432387 | N30: =N22/N$27 -> 0.63575976 | ... P30: =P22/P$27 -> 0.56039604 | R30: =R22/R$27 -> 0.62576145 | S30: =S22/S$27 -> 0.61229694 | T30: =T22/T$27 -> 0.6052093 | U30: =U22/U$27 -> 0.59596515 | V30: =V22/V$27 -> 0.59642731 | W30: =W22/W$27 -> 0.56740196 | X30: =X22/X$27 -> 0.56039604
B31: =B23&"(%)" -> Canada Revenues(%) | C31: =C23/C$27 -> 0.14340321 | D31: =D23/D$27 -> 0.13360366 | E31: =E23/E$27 -> 0.13335852 | G31: =G23/G$27 -> 0.1265 | H31: =H23/H$27 -> 0.13348416 | I31: =I23/I$27 -> 0.14013605 | J31: =J23/J$27 -> 0.13362473 | K31: =K23/K$27 -> 0.12765957 | L31: =L23/L$27 -> 0.13459916 | M31: =M23/M$27 -> 0.13981636 | N31: =N23/N$27 -> 0.13174647 | ... P31: =P23/P$27 -> 0.12712871 | R31: =R23/R$27 -> 0.13401454 | S31: =S23/S$27 -> 0.13335852 | T31: =T23/T$27 -> 0.13237209 | U31: =U23/U$27 -> 0.130674 | V31: =V23/V$27 -> 0.12809966 | W31: =W23/W$27 -> 0.1254085 | X31: =X23/X$27 -> 0.12712871
B32: =B24&"(%)" -> Mexico Revenues(%) | C32: =C24/C$27 -> 0 | D32: =D24/D$27 -> 0 | E32: =E24/E$27 -> 0.0031167359 | G32: =G24/G$27 -> 0 | H32: =H24/H$27 -> 0 | I32: =I24/I$27 -> 0 | J32: =J24/J$27 -> 0 | K32: =K24/K$27 -> 0 | L32: =L24/L$27 -> 0 | M32: =M24/M$27 -> 0.004590985 | N32: =N24/N$27 -> 0.0060891226 | ... P32: =P24/P$27 -> 0.0087128713 | R32: =R24/R$27 -> 0.0010807624 | S32: =S24/S$27 -> 0.0031167359 | T32: =T24/T$27 -> 0.0048372093 | U32: =U24/U$27 -> 0.006785878 | V32: =V24/V$27 -> 0.0074039253 | W32: =W24/W$27 -> 0.008374183 | X32: =X24/X$27 -> 0.0087128713
B33: =B25&"(%)" -> China Revenues(%) | C33: =C25/C$27 -> 0.084093711 | D33: =D25/D$27 -> 0.11790393 | E33: =E25/E$27 -> 0.14554212 | G33: =G25/G$27 -> 0.125 | H33: =H25/H$27 -> 0.12579186 | I33: =I25/I$27 -> 0.12108844 | J33: =J25/J$27 -> 0.10583828 | K33: =K25/K$27 -> 0.15663196 | L33: =L25/L$27 -> 0.15021097 | M33: =M25/M$27 -> 0.14983306 | N33: =N25/N$27 -> 0.13285358 | ... P33: =P25/P$27 -> 0.17465347 | R33: =R25/R$27 -> 0.13755158 | S33: =S25/S$27 -> 0.14554212 | T33: =T25/T$27 -> 0.14948837 | U33: =U25/U$27 -> 0.15515818 | V33: =V25/V$27 -> 0.15665766 | W33: =W25/W$27 -> 0.17422386 | X33: =X25/X$27 -> 0.17465347
B34: =B26&"(%)" -> Other Revenues(%) | C34: =C26/C$27 -> 0.075339088 | D34: =D26/D$27 -> 0.088687877 | E34: =E26/E$27 -> 0.10568568 | G34: =G26/G$27 -> 0.0915 | H34: =H26/H$27 -> 0.095927602 | I34: =I26/I$27 -> 0.092970522 | J34: =J26/J$27 -> 0.078988448 | K34: =K26/K$27 -> 0.10909914 | L34: =L26/L$27 -> 0.11518987 | M34: =M26/M$27 -> 0.11143573 | N34: =N26/N$27 -> 0.093551066 | ... P34: =P26/P$27 -> 0.12910891 | R34: =R26/R$27 -> 0.10159167 | S34: =S26/S$27 -> 0.10568568 | T34: =T26/T$27 -> 0.10809302 | U34: =U26/U$27 -> 0.11141678 | V34: =V26/V$27 -> 0.11141145 | W34: =W26/W$27 -> 0.1245915 | X34: =X26/X$27 -> 0.12910891

Sheet FCF
B2: ='Historical Financials'!B2 -> Lululemon Athletica Inc (NASDAQ: LULU) | D2: FYE | H2: Quarterly | R2: Quarterly | Z2: LTM | AA2: LTM | AG2: Variance
B3: FCF Analysis | C3: ='Historical Financials'!C7 -> 2022 | D3: ='Historical Financials'!D7 -> 2023 | E3: ='Historical Financials'!E7 -> 2024 | F3: ='Historical Financials'!#REF! -> #REF! | H3: ='Historical Financials'!G7 -> 1Q23 | I3: ='Historical Financials'!H7 -> 2Q23 | J3: ='Historical Financials'!I7 -> 3Q23 | K3: ='Historical Financials'!J7 -> 4Q23 | L3: ='Historical Financials'!K7 -> 1Q24 | M3: ='Historical Financials'!L7 -> 2Q24 | N3: ='Historical Financials'!M7 -> 3Q24 | O3: ='Historical Financials'!N7 -> 4Q24 | ... Q3: ='Historical Financials'!P7 -> 2Q25 | R3: ='Historical Financials'!#REF! -> #REF! | S3: ='Historical Financials'!#REF! -> #REF! | T3: ='Historical Financials'!#REF! -> #REF! | V3: =K3 -> 4Q23 | W3: =L3 -> 1Q24 | X3: =M3 -> 2Q24 | Y3: =N3 -> 3Q24 | Z3: =O3 -> 4Q24 | AA3: =P3 -> 1Q25 | AB3: =Q3 -> 2Q25 | AC3: =R3 -> #REF! | ... AE3: =T3 -> #REF!
B4: ($ In Millions) | C4: ='Historical Financials'!C8 -> XXX | D4: ='Historical Financials'!D8 -> XXX | E4: ='Historical Financials'!E8 -> XXX | F4: ='Historical Financials'!#REF! -> #REF! | H4: ='Historical Financials'!G8 -> XXX | I4: ='Historical Financials'!H8 -> XXX | J4: ='Historical Financials'!I8 -> XXX | K4: ='Historical Financials'!J8 -> XXX | L4: ='Historical Financials'!K8 -> XXX | M4: ='Historical Financials'!L8 -> XXX | N4: ='Historical Financials'!M8 -> XXX | O4: ='Historical Financials'!N8 -> XXX | ... Q4: ='Historical Financials'!P8 -> XXX | R4: ='Historical Financials'!#REF! -> #REF! | S4: ='Historical Financials'!#REF! -> #REF! | T4: ='Historical Financials'!#REF! -> #REF! | V4: =K4 -> XXX | W4: =L4 -> XXX | X4: =M4 -> XXX | Y4: =N4 -> XXX | Z4: =O4 -> XXX | AA4: =P4 -> XXX | AB4: =Q4 -> XXX | AC4: =R4 -> #REF! | ... AE4: =T4 -> #REF!
B6: XXX | V6: =SUM(H6:K6) -> 0 | W6: =SUM(I6:L6) -> 0 | X6: =SUM(J6:M6) -> 0 | Y6: =SUM(K6:N6) -> 0 | Z6: =SUM(L6:O6) -> 0 | AA6: =SUM(M6:P6) -> 0 | AB6: =SUM(N6:Q6) -> 0 | AC6: =SUM(O6:R6) -> 0 | ... AE6: =SUM(Q6:T6) -> 0 | AG6: =SUM(AE6/AA6)-1 -> #DIV/0!
B7: XXX | V7: =SUM(H7:K7) -> 0 | W7: =SUM(I7:L7) -> 0 | X7: =SUM(J7:M7) -> 0 | Y7: =SUM(K7:N7) -> 0 | Z7: =SUM(L7:O7) -> 0 | AA7: =SUM(M7:P7) -> 0 | AB7: =SUM(N7:Q7) -> 0 | AC7: =SUM(O7:R7) -> 0 | ... AE7: =SUM(Q7:T7) -> 0 | AG7: =SUM(AE7/AA7)-1 -> #DIV/0!
B8: XXX | V8: =SUM(H8:K8) -> 0 | W8: =SUM(I8:L8) -> 0 | X8: =SUM(J8:M8) -> 0 | Y8: =SUM(K8:N8) -> 0 | Z8: =SUM(L8:O8) -> 0 | AA8: =SUM(M8:P8) -> 0 | AB8: =SUM(N8:Q8) -> 0 | AC8: =SUM(O8:R8) -> 0 | ... AE8: =SUM(Q8:T8) -> 0 | AG8: =SUM(AE8/AA8)-1 -> #DIV/0!
B9: XXX | V9: =SUM(H9:K9) -> 0 | W9: =SUM(I9:L9) -> 0 | X9: =SUM(J9:M9) -> 0 | Y9: =SUM(K9:N9) -> 0 | Z9: =SUM(L9:O9) -> 0 | AA9: =SUM(M9:P9) -> 0 | AB9: =SUM(N9:Q9) -> 0 | AC9: =SUM(O9:R9) -> 0 | ... AE9: =SUM(Q9:T9) -> 0 | AG9: =SUM(AE9/AA9)-1 -> #DIV/0!
B10: XXX | V10: =SUM(H10:K10) -> 0 | W10: =SUM(I10:L10) -> 0 | X10: =SUM(J10:M10) -> 0 | Y10: =SUM(K10:N10) -> 0 | Z10: =SUM(L10:O10) -> 0 | AA10: =SUM(M10:P10) -> 0 | AB10: =SUM(N10:Q10) -> 0 | AC10: =SUM(O10:R10) -> 0 | ... AE10: =SUM(Q10:T10) -> 0 | AG10: =SUM(AE10/AA10)-1 -> #DIV/0!
B11: XXX | V11: =SUM(H11:K11) -> 0 | W11: =SUM(I11:L11) -> 0 | X11: =SUM(J11:M11) -> 0 | Y11: =SUM(K11:N11) -> 0 | Z11: =SUM(L11:O11) -> 0 | AA11: =SUM(M11:P11) -> 0 | AB11: =SUM(N11:Q11) -> 0 | AC11: =SUM(O11:R11) -> 0 | ... AE11: =SUM(Q11:T11) -> 0 | AG11: =SUM(AE11/AA11)-1 -> #DIV/0!
B12: Total Revenue | C12: =SUM(C6:C11) -> 0 | D12: =SUM(D6:D11) -> 0 | E12: =SUM(E6:E11) -> 0 | F12: =SUM(F6:F11) -> 0 | H12: =SUM(H6:H11) -> 0 | I12: =SUM(I6:I11) -> 0 | J12: =SUM(J6:J11) -> 0 | K12: =SUM(K6:K11) -> 0 | L12: =SUM(L6:L11) -> 0 | M12: =SUM(M6:M11) -> 0 | N12: =SUM(N6:N11) -> 0 | O12: =SUM(O6:O11) -> 0 | ... T12: =SUM(T6:T11) -> 0 | V12: =SUM(V6:V11) -> 0 | W12: =SUM(W6:W11) -> 0 | X12: =SUM(X6:X11) -> 0 | Y12: =SUM(Y6:Y11) -> 0 | Z12: =SUM(Z6:Z11) -> 0 | AA12: =SUM(AA6:AA11) -> 0 | AB12: =SUM(AB6:AB11) -> 0 | AC12: =SUM(AC6:AC11) -> 0 | ... AE12: =SUM(AE6:AE11) -> 0 | AG12: =SUM(AE12/AA12)-1 -> #DIV/0!
B13: Y/Y Growth (%) | C13: =SUM(C12/#REF!)-1 -> #REF! | D13: =SUM(D12/C12)-1 -> #DIV/0! | E13: =SUM(E12/D12)-1 -> #DIV/0! | F13: =SUM(F12/E12)-1 -> #DIV/0! | L13: =SUM(L12/H12)-1 -> #DIV/0! | M13: =SUM(M12/I12)-1 -> #DIV/0! | N13: =SUM(N12/J12)-1 -> #DIV/0! | O13: =SUM(O12/K12)-1 -> #DIV/0! | P13: =SUM(P12/L12)-1 -> #DIV/0! | Q13: =SUM(Q12/M12)-1 -> #DIV/0! | R13: =SUM(R12/N12)-1 -> #DIV/0! | S13: =SUM(S12/O12)-1 -> #DIV/0! | T13: =SUM(T12/P12)-1 -> #DIV/0! | Z13: =SUM(Z12/V12)-1 -> #DIV/0! | AA13: =SUM(AA12/W12)-1 -> #DIV/0! | AB13: =SUM(AB12/X12)-1 -> #DIV/0! | AC13: =SUM(AC12/Y12)-1 -> #DIV/0! | AD13: =SUM(AD12/Z12)-1 -> #DIV/0! | AE13: =SUM(AE12/AA12)-1 -> #DIV/0! | AG13: =SUM(AE13-AA13)*10000 -> #DIV/0!
B14: Q/Q Growth (%) | C14: N/A | D14: N/A | E14: N/A | F14: N/A | I14: =SUM(I12/H12)-1 -> #DIV/0! | J14: =SUM(J12/I12)-1 -> #DIV/0! | K14: =SUM(K12/J12)-1 -> #DIV/0! | L14: =SUM(L12/K12)-1 -> #DIV/0! | M14: =SUM(M12/L12)-1 -> #DIV/0! | N14: =SUM(N12/M12)-1 -> #DIV/0! | O14: =SUM(O12/N12)-1 -> #DIV/0! | P14: =SUM(P12/O12)-1 -> #DIV/0! | ... T14: =SUM(T12/S12)-1 -> #DIV/0! | V14: N/A | W14: N/A | X14: N/A | Y14: N/A | Z14: N/A | AA14: N/A | AB14: N/A | AC14: N/A | AD14: N/A | AE14: N/A
B16: (-) Cost of Sales | V16: =SUM(H16:K16) -> 0 | W16: =SUM(I16:L16) -> 0 | X16: =SUM(J16:M16) -> 0 | Y16: =SUM(K16:N16) -> 0 | Z16: =SUM(L16:O16) -> 0 | AA16: =SUM(M16:P16) -> 0 | AB16: =SUM(N16:Q16) -> 0 | AC16: =SUM(O16:R16) -> 0 | ... AE16: =SUM(Q16:T16) -> 0 | AG16: =SUM(AE16/AA16)-1 -> #DIV/0!
B17: Gross Profit | C17: =SUM(C12+SUM(C16:C16)) -> 0 | D17: =SUM(D12+SUM(D16:D16)) -> 0 | E17: =SUM(E12+SUM(E16:E16)) -> 0 | F17: =SUM(F12+SUM(F16:F16)) -> 0 | H17: =SUM(H12+SUM(H16:H16)) -> 0 | I17: =SUM(I12+SUM(I16:I16)) -> 0 | J17: =SUM(J12+SUM(J16:J16)) -> 0 | K17: =SUM(K12+SUM(K16:K16)) -> 0 | L17: =SUM(L12+SUM(L16:L16)) -> 0 | M17: =SUM(M12+SUM(M16:M16)) -> 0 | N17: =SUM(N12+SUM(N16:N16)) -> 0 | O17: =SUM(O12+SUM(O16:O16)) -> 0 | ... T17: =SUM(T12+SUM(T16:T16)) -> 0 | V17: =SUM(V12+SUM(V16:V16)) -> 0 | W17: =SUM(W12+SUM(W16:W16)) -> 0 | X17: =SUM(X12+SUM(X16:X16)) -> 0 | Y17: =SUM(Y12+SUM(Y16:Y16)) -> 0 | Z17: =SUM(Z12+SUM(Z16:Z16)) -> 0 | AA17: =SUM(AA12+SUM(AA16:AA16)) -> 0 | AB17: =SUM(AB12+SUM(AB16:AB16)) -> 0 | AC17: =SUM(AC12+SUM(AC16:AC16)) -> 0 | ... AE17: =SUM(AE12+SUM(AE16:AE16)) -> 0 | AG17: =SUM(AE17/AA17)-1 -> #DIV/0!
B18: Gross Margin (%) | C18: =C17/C12 -> #DIV/0! | D18: =D17/D12 -> #DIV/0! | E18: =E17/E12 -> #DIV/0! | F18: =F17/F12 -> #DIV/0! | H18: =H17/H12 -> #DIV/0! | I18: =I17/I12 -> #DIV/0! | J18: =J17/J12 -> #DIV/0! | K18: =K17/K12 -> #DIV/0! | L18: =L17/L12 -> #DIV/0! | M18: =M17/M12 -> #DIV/0! | N18: =N17/N12 -> #DIV/0! | O18: =O17/O12 -> #DIV/0! | ... T18: =T17/T12 -> #DIV/0! | V18: =V17/V12 -> #DIV/0! | W18: =W17/W12 -> #DIV/0! | X18: =X17/X12 -> #DIV/0! | Y18: =Y17/Y12 -> #DIV/0! | Z18: =Z17/Z12 -> #DIV/0! | AA18: =AA17/AA12 -> #DIV/0! | AB18: =AB17/AB12 -> #DIV/0! | AC18: =AC17/AC12 -> #DIV/0! | ... AE18: =AE17/AE12 -> #DIV/0! | AG18: =SUM(AE18-AA18)*10000 -> #DIV/0!
B20: (-) XXX | V20: =SUM(H20:K20) -> 0 | W20: =SUM(I20:L20) -> 0 | X20: =SUM(J20:M20) -> 0 | Y20: =SUM(K20:N20) -> 0 | Z20: =SUM(L20:O20) -> 0 | AA20: =SUM(M20:P20) -> 0 | AB20: =SUM(N20:Q20) -> 0 | AC20: =SUM(O20:R20) -> 0 | ... AE20: =SUM(Q20:T20) -> 0 | AG20: =SUM(AE20/AA20)-1 -> #DIV/0!
B21: (-) XXX | V21: =SUM(H21:K21) -> 0 | W21: =SUM(I21:L21) -> 0 | X21: =SUM(J21:M21) -> 0 | Y21: =SUM(K21:N21) -> 0 | Z21: =SUM(L21:O21) -> 0 | AA21: =SUM(M21:P21) -> 0 | AB21: =SUM(N21:Q21) -> 0 | AC21: =SUM(O21:R21) -> 0 | ... AE21: =SUM(Q21:T21) -> 0 | AG21: =SUM(AE21/AA21)-1 -> #DIV/0!
B22: (-) XXX | V22: =SUM(H22:K22) -> 0 | W22: =SUM(I22:L22) -> 0 | X22: =SUM(J22:M22) -> 0 | Y22: =SUM(K22:N22) -> 0 | Z22: =SUM(L22:O22) -> 0 | AA22: =SUM(M22:P22) -> 0 | AB22: =SUM(N22:Q22) -> 0 | AC22: =SUM(O22:R22) -> 0 | ... AE22: =SUM(Q22:T22) -> 0 | AG22: =SUM(AE22/AA22)-1 -> #DIV/0!
B23: (-) XXX | V23: =SUM(H23:K23) -> 0 | W23: =SUM(I23:L23) -> 0 | X23: =SUM(J23:M23) -> 0 | Y23: =SUM(K23:N23) -> 0 | Z23: =SUM(L23:O23) -> 0 | AA23: =SUM(M23:P23) -> 0 | AB23: =SUM(N23:Q23) -> 0 | AC23: =SUM(O23:R23) -> 0 | ... AE23: =SUM(Q23:T23) -> 0 | AG23: =SUM(AE23/AA23)-1 -> #DIV/0!
B24: (-) XXX | V24: =SUM(H24:K24) -> 0 | W24: =SUM(I24:L24) -> 0 | X24: =SUM(J24:M24) -> 0 | Y24: =SUM(K24:N24) -> 0 | Z24: =SUM(L24:O24) -> 0 | AA24: =SUM(M24:P24) -> 0 | AB24: =SUM(N24:Q24) -> 0 | AC24: =SUM(O24:R24) -> 0 | ... AE24: =SUM(Q24:T24) -> 0 | AG24: =SUM(AE24/AA24)-1 -> #DIV/0!
B25: Earning before Interest & Taxes (EBIT) | C25: =SUM(C17+SUM(C20:C24)) -> 0 | D25: =SUM(D17+SUM(D20:D24)) -> 0 | E25: =SUM(E17+SUM(E20:E24)) -> 0 | F25: =SUM(F17+SUM(F20:F24)) -> 0 | H25: =SUM(H17+SUM(H20:H24)) -> 0 | I25: =SUM(I17+SUM(I20:I24)) -> 0 | J25: =SUM(J17+SUM(J20:J24)) -> 0 | K25: =SUM(K17+SUM(K20:K24)) -> 0 | L25: =SUM(L17+SUM(L20:L24)) -> 0 | M25: =SUM(M17+SUM(M20:M24)) -> 0 | N25: =SUM(N17+SUM(N20:N24)) -> 0 | O25: =SUM(O17+SUM(O20:O24)) -> 0 | ... T25: =SUM(T17+SUM(T20:T24)) -> 0 | V25: =SUM(V17+SUM(V20:V24)) -> 0 | W25: =SUM(W17+SUM(W20:W24)) -> 0 | X25: =SUM(X17+SUM(X20:X24)) -> 0 | Y25: =SUM(Y17+SUM(Y20:Y24)) -> 0 | Z25: =SUM(Z17+SUM(Z20:Z24)) -> 0 | AA25: =SUM(AA17+SUM(AA20:AA24)) -> 0 | AB25: =SUM(AB17+SUM(AB20:AB24)) -> 0 | AC25: =SUM(AC17+SUM(AC20:AC24)) -> 0 | ... AE25: =SUM(AE17+SUM(AE20:AE24)) -> 0 | AG25: =SUM(AE25/AA25)-1 -> #DIV/0!
B26: Operating Margin (%) | C26: =C25/C12 -> #DIV/0! | D26: =D25/D12 -> #DIV/0! | E26: =E25/E12 -> #DIV/0! | F26: =F25/F12 -> #DIV/0! | H26: =H25/H12 -> #DIV/0! | I26: =I25/I12 -> #DIV/0! | J26: =J25/J12 -> #DIV/0! | K26: =K25/K12 -> #DIV/0! | L26: =L25/L12 -> #DIV/0! | M26: =M25/M12 -> #DIV/0! | N26: =N25/N12 -> #DIV/0! | O26: =O25/O12 -> #DIV/0! | ... T26: =T25/T12 -> #DIV/0! | V26: =V25/V12 -> #DIV/0! | W26: =W25/W12 -> #DIV/0! | X26: =X25/X12 -> #DIV/0! | Y26: =Y25/Y12 -> #DIV/0! | Z26: =Z25/Z12 -> #DIV/0! | AA26: =AA25/AA12 -> #DIV/0! | AB26: =AB25/AB12 -> #DIV/0! | AC26: =AC25/AC12 -> #DIV/0! | ... AE26: =AE25/AE12 -> #DIV/0! | AG26: =SUM(AE26-AA26)*10000 -> #DIV/0!
B28: (+) Depreciation and Amortization (D&A) | V28: =SUM(H28:K28) -> 0 | W28: =SUM(I28:L28) -> 0 | X28: =SUM(J28:M28) -> 0 | Y28: =SUM(K28:N28) -> 0 | Z28: =SUM(L28:O28) -> 0 | AA28: =SUM(M28:P28) -> 0 | AB28: =SUM(N28:Q28) -> 0 | AC28: =SUM(O28:R28) -> 0 | ... AE28: =SUM(Q28:T28) -> 0 | AG28: =SUM(AE28/AA28)-1 -> #DIV/0!
B29: EBITDA | C29: =SUM(C25+SUM(C28:C28)) -> 0 | D29: =SUM(D25+SUM(D28:D28)) -> 0 | E29: =SUM(E25+SUM(E28:E28)) -> 0 | F29: =SUM(F25+SUM(F28:F28)) -> 0 | H29: =SUM(H25+SUM(H28:H28)) -> 0 | I29: =SUM(I25+SUM(I28:I28)) -> 0 | J29: =SUM(J25+SUM(J28:J28)) -> 0 | K29: =SUM(K25+SUM(K28:K28)) -> 0 | L29: =SUM(L25+SUM(L28:L28)) -> 0 | M29: =SUM(M25+SUM(M28:M28)) -> 0 | N29: =SUM(N25+SUM(N28:N28)) -> 0 | O29: =SUM(O25+SUM(O28:O28)) -> 0 | ... T29: =SUM(T25+SUM(T28:T28)) -> 0 | V29: =SUM(V25+SUM(V28:V28)) -> 0 | W29: =SUM(W25+SUM(W28:W28)) -> 0 | X29: =SUM(X25+SUM(X28:X28)) -> 0 | Y29: =SUM(Y25+SUM(Y28:Y28)) -> 0 | Z29: =SUM(Z25+SUM(Z28:Z28)) -> 0 | AA29: =SUM(AA25+SUM(AA28:AA28)) -> 0 | AB29: =SUM(AB25+SUM(AB28:AB28)) -> 0 | AC29: =SUM(AC25+SUM(AC28:AC28)) -> 0 | ... AE29: =SUM(AE25+SUM(AE28:AE28)) -> 0 | AG29: =SUM(AE29/AA29)-1 -> #DIV/0!
B30: EBITDA Margin (%) | C30: =C29/C12 -> #DIV/0! | D30: =D29/D12 -> #DIV/0! | E30: =E29/E12 -> #DIV/0! | F30: =F29/F12 -> #DIV/0! | H30: =H29/H12 -> #DIV/0! | I30: =I29/I12 -> #DIV/0! | J30: =J29/J12 -> #DIV/0! | K30: =K29/K12 -> #DIV/0! | L30: =L29/L12 -> #DIV/0! | M30: =M29/M12 -> #DIV/0! | N30: =N29/N12 -> #DIV/0! | O30: =O29/O12 -> #DIV/0! | ... T30: =T29/T12 -> #DIV/0! | V30: =V29/V12 -> #DIV/0! | W30: =W29/W12 -> #DIV/0! | X30: =X29/X12 -> #DIV/0! | Y30: =Y29/Y12 -> #DIV/0! | Z30: =Z29/Z12 -> #DIV/0! | AA30: =AA29/AA12 -> #DIV/0! | AB30: =AB29/AB12 -> #DIV/0! | AC30: =AC29/AC12 -> #DIV/0! | ... AE30: =AE29/AE12 -> #DIV/0! | AG30: =SUM(AE30-AA30)*10000 -> #DIV/0!
B32: (+) Stock-Based Compensation (SBC) | V32: =SUM(H32:K32) -> 0 | W32: =SUM(I32:L32) -> 0 | X32: =SUM(J32:M32) -> 0 | Y32: =SUM(K32:N32) -> 0 | Z32: =SUM(L32:O32) -> 0 | AA32: =SUM(M32:P32) -> 0 | AB32: =SUM(N32:Q32) -> 0 | AC32: =SUM(O32:R32) -> 0 | ... AE32: =SUM(Q32:T32) -> 0 | AG32: =SUM(AE32/AA32)-1 -> #DIV/0!
B33: (+) XXX | V33: =SUM(H33:K33) -> 0 | W33: =SUM(I33:L33) -> 0 | X33: =SUM(J33:M33) -> 0 | Y33: =SUM(K33:N33) -> 0 | Z33: =SUM(L33:O33) -> 0 | AA33: =SUM(M33:P33) -> 0 | AB33: =SUM(N33:Q33) -> 0 | AC33: =SUM(O33:R33) -> 0 | ... AE33: =SUM(Q33:T33) -> 0 | AG33: =SUM(AE33/AA33)-1 -> #DIV/0!
B34: Adj. EBITDA | C34: =+SUM(C29+SUM(C32:C32)) -> 0 | D34: =+SUM(D29+SUM(D32:D32)) -> 0 | E34: =+SUM(E29+SUM(E32:E32)) -> 0 | F34: =+SUM(F29+SUM(F32:F32)) -> 0 | H34: =+SUM(H29+SUM(H32:H32)) -> 0 | I34: =+SUM(I29+SUM(I32:I32)) -> 0 | J34: =+SUM(J29+SUM(J32:J32)) -> 0 | K34: =+SUM(K29+SUM(K32:K32)) -> 0 | L34: =+SUM(L29+SUM(L32:L32)) -> 0 | M34: =+SUM(M29+SUM(M32:M32)) -> 0 | N34: =+SUM(N29+SUM(N32:N32)) -> 0 | O34: =+SUM(O29+SUM(O32:O32)) -> 0 | ... T34: =+SUM(T29+SUM(T32:T32)) -> 0 | V34: =+SUM(V29+SUM(V32:V32)) -> 0 | W34: =+SUM(W29+SUM(W32:W32)) -> 0 | X34: =+SUM(X29+SUM(X32:X32)) -> 0 | Y34: =+SUM(Y29+SUM(Y32:Y32)) -> 0 | Z34: =+SUM(Z29+SUM(Z32:Z32)) -> 0 | AA34: =+SUM(AA29+SUM(AA32:AA32)) -> 0 | AB34: =+SUM(AB29+SUM(AB32:AB32)) -> 0 | AC34: =+SUM(AC29+SUM(AC32:AC32)) -> 0 | ... AE34: =+SUM(AE29+SUM(AE32:AE32)) -> 0 | AG34: =SUM(AE34/AA34)-1 -> #DIV/0!
B35: Adj. EBITDA Margin (%) | C35: =C34/C12 -> #DIV/0! | D35: =D34/D12 -> #DIV/0! | E35: =E34/E12 -> #DIV/0! | F35: =F34/F12 -> #DIV/0! | H35: =H34/H12 -> #DIV/0! | I35: =I34/I12 -> #DIV/0! | J35: =J34/J12 -> #DIV/0! | K35: =K34/K12 -> #DIV/0! | L35: =L34/L12 -> #DIV/0! | M35: =M34/M12 -> #DIV/0! | N35: =N34/N12 -> #DIV/0! | O35: =O34/O12 -> #DIV/0! | ... T35: =T34/T12 -> #DIV/0! | V35: =V34/V12 -> #DIV/0! | W35: =W34/W12 -> #DIV/0! | X35: =X34/X12 -> #DIV/0! | Y35: =Y34/Y12 -> #DIV/0! | Z35: =Z34/Z12 -> #DIV/0! | AA35: =AA34/AA12 -> #DIV/0! | AB35: =AB34/AB12 -> #DIV/0! | AC35: =AC34/AC12 -> #DIV/0! | ... AE35: =AE34/AE12 -> #DIV/0! | AG35: =SUM(AE35-AA35)*10000 -> #DIV/0!
B37: (-) Capital Expenditures | V37: =SUM(H37:K37) -> 0 | W37: =SUM(I37:L37) -> 0 | X37: =SUM(J37:M37) -> 0 | Y37: =SUM(K37:N37) -> 0 | Z37: =SUM(L37:O37) -> 0 | AA37: =SUM(M37:P37) -> 0 | AB37: =SUM(N37:Q37) -> 0 | AC37: =SUM(O37:R37) -> 0 | ... AE37: =SUM(Q37:T37) -> 0 | AG37: =SUM(AE37/AA37)-1 -> #DIV/0!
B38: (-) Cash Taxes | V38: =SUM(H38:K38) -> 0 | W38: =SUM(I38:L38) -> 0 | X38: =SUM(J38:M38) -> 0 | Y38: =SUM(K38:N38) -> 0 | Z38: =SUM(L38:O38) -> 0 | AA38: =SUM(M38:P38) -> 0 | AB38: =SUM(N38:Q38) -> 0 | AC38: =SUM(O38:R38) -> 0 | ... AE38: =SUM(Q38:T38) -> 0 | AG38: =SUM(AE38/AA38)-1 -> #DIV/0!
B39: (-) Cash Interest | V39: =SUM(H39:K39) -> 0 | W39: =SUM(I39:L39) -> 0 | X39: =SUM(J39:M39) -> 0 | Y39: =SUM(K39:N39) -> 0 | Z39: =SUM(L39:O39) -> 0 | AA39: =SUM(M39:P39) -> 0 | AB39: =SUM(N39:Q39) -> 0 | AC39: =SUM(O39:R39) -> 0 | ... AE39: =SUM(Q39:T39) -> 0 | AG39: =SUM(AE39/AA39)-1 -> #DIV/0!
B40: (-) Mandatory Outflows | V40: =SUM(H40:K40) -> 0 | W40: =SUM(I40:L40) -> 0 | X40: =SUM(J40:M40) -> 0 | Y40: =SUM(K40:N40) -> 0 | Z40: =SUM(L40:O40) -> 0 | AA40: =SUM(M40:P40) -> 0 | AB40: =SUM(N40:Q40) -> 0 | AC40: =SUM(O40:R40) -> 0 | ... AE40: =SUM(Q40:T40) -> 0 | AG40: =SUM(AE40/AA40)-1 -> #DIV/0!
B41: (+/-) Changes in NWC | V41: =SUM(H41:K41) -> 0 | W41: =SUM(I41:L41) -> 0 | X41: =SUM(J41:M41) -> 0 | Y41: =SUM(K41:N41) -> 0 | Z41: =SUM(L41:O41) -> 0 | AA41: =SUM(M41:P41) -> 0 | AB41: =SUM(N41:Q41) -> 0 | AC41: =SUM(O41:R41) -> 0 | ... AE41: =SUM(Q41:T41) -> 0 | AG41: =SUM(AE41/AA41)-1 -> #DIV/0!
B42: Discretionary Cash-Flows | C42: =SUM(C34+SUM(C37:C41)) -> 0 | D42: =SUM(D34+SUM(D37:D41)) -> 0 | E42: =SUM(E34+SUM(E37:E41)) -> 0 | F42: =SUM(F34+SUM(F37:F41)) -> 0 | H42: =SUM(H34+SUM(H37:H41)) -> 0 | I42: =SUM(I34+SUM(I37:I41)) -> 0 | J42: =SUM(J34+SUM(J37:J41)) -> 0 | K42: =SUM(K34+SUM(K37:K41)) -> 0 | L42: =SUM(L34+SUM(L37:L41)) -> 0 | M42: =SUM(M34+SUM(M37:M41)) -> 0 | N42: =SUM(N34+SUM(N37:N41)) -> 0 | O42: =SUM(O34+SUM(O37:O41)) -> 0 | ... T42: =SUM(T34+SUM(T37:T41)) -> 0 | V42: =SUM(V34+SUM(V37:V41)) -> 0 | W42: =SUM(W34+SUM(W37:W41)) -> 0 | X42: =SUM(X34+SUM(X37:X41)) -> 0 | Y42: =SUM(Y34+SUM(Y37:Y41)) -> 0 | Z42: =SUM(Z34+SUM(Z37:Z41)) -> 0 | AA42: =SUM(AA34+SUM(AA37:AA41)) -> 0 | AB42: =SUM(AB34+SUM(AB37:AB41)) -> 0 | AC42: =SUM(AC34+SUM(AC37:AC41)) -> 0 | ... AE42: =SUM(AE34+SUM(AE37:AE41)) -> 0 | AG42: =SUM(AE42/AA42)-1 -> #DIV/0!
B44: (+/-) XXX | V44: =SUM(H44:K44) -> 0 | W44: =SUM(I44:L44) -> 0 | X44: =SUM(J44:M44) -> 0 | Y44: =SUM(K44:N44) -> 0 | Z44: =SUM(L44:O44) -> 0 | AA44: =SUM(M44:P44) -> 0 | AB44: =SUM(N44:Q44) -> 0 | AC44: =SUM(O44:R44) -> 0 | ... AE44: =SUM(Q44:T44) -> 0
B45: (+/-) XXX | V45: =SUM(H45:K45) -> 0 | W45: =SUM(I45:L45) -> 0 | X45: =SUM(J45:M45) -> 0 | Y45: =SUM(K45:N45) -> 0 | Z45: =SUM(L45:O45) -> 0 | AA45: =SUM(M45:P45) -> 0 | AB45: =SUM(N45:Q45) -> 0 | AC45: =SUM(O45:R45) -> 0 | ... AE45: =SUM(Q45:T45) -> 0
B46: (+/-) XXX | V46: =SUM(H46:K46) -> 0 | W46: =SUM(I46:L46) -> 0 | X46: =SUM(J46:M46) -> 0 | Y46: =SUM(K46:N46) -> 0 | Z46: =SUM(L46:O46) -> 0 | AA46: =SUM(M46:P46) -> 0 | AB46: =SUM(N46:Q46) -> 0 | AC46: =SUM(O46:R46) -> 0 | ... AE46: =SUM(Q46:T46) -> 0
B47: (+/-) XXX | V47: =SUM(H47:K47) -> 0 | W47: =SUM(I47:L47) -> 0 | X47: =SUM(J47:M47) -> 0 | Y47: =SUM(K47:N47) -> 0 | Z47: =SUM(L47:O47) -> 0 | AA47: =SUM(M47:P47) -> 0 | AB47: =SUM(N47:Q47) -> 0 | AC47: =SUM(O47:R47) -> 0 | ... AE47: =SUM(Q47:T47) -> 0
B48: (+/-) XXX | V48: =SUM(H48:K48) -> 0 | W48: =SUM(I48:L48) -> 0 | X48: =SUM(J48:M48) -> 0 | Y48: =SUM(K48:N48) -> 0 | Z48: =SUM(L48:O48) -> 0 | AA48: =SUM(M48:P48) -> 0 | AB48: =SUM(N48:Q48) -> 0 | AC48: =SUM(O48:R48) -> 0 | ... AE48: =SUM(Q48:T48) -> 0
B49: (+/-) Other | D49: =SUM(D54)-SUM(C54)-SUM(D42:D48) -> 0 | E49: =SUM(E54)-SUM(D54)-SUM(E42:E48) -> 0 | F49: =SUM(F54)-SUM(E54)-SUM(F42:F48) -> 0 | H49: =SUM(H54)-SUM(C54)-SUM(H42:H48) -> 0 | I49: =SUM(I54)-SUM(H54)-SUM(I42:I48) -> 0 | J49: =SUM(J54)-SUM(I54)-SUM(J42:J48) -> 0 | K49: =SUM(K54)-SUM(J54)-SUM(K42:K48) -> 2244 | L49: =SUM(L54)-SUM(K54)-SUM(L42:L48) -> -2244 | M49: =SUM(M54)-SUM(L54)-SUM(M42:M48) -> 0 | N49: =SUM(N54)-SUM(M54)-SUM(N42:N48) -> 0 | O49: =SUM(O54)-SUM(N54)-SUM(O42:O48) -> 1984 | P49: =SUM(P54)-SUM(O54)-SUM(P42:P48) -> -1984 | ... T49: =SUM(T54)-SUM(S54)-SUM(T42:T48) -> #REF! | V49: =SUM(H49:K49) -> 2244 | W49: =SUM(I49:L49) -> 0 | X49: =SUM(J49:M49) -> 0 | Y49: =SUM(K49:N49) -> 0 | Z49: =SUM(L49:O49) -> -260 | AA49: =SUM(M49:P49) -> 0 | AB49: =SUM(N49:Q49) -> 0 | AC49: =SUM(O49:R49) -> 0 | ... AE49: =SUM(Q49:T49) -> #REF!
B50: Free-Cash Flows | C50: =SUM(C42+SUM(C44:C49)) -> 0 | D50: =SUM(D42+SUM(D44:D49)) -> 0 | E50: =SUM(E42+SUM(E44:E49)) -> 0 | F50: =SUM(F42+SUM(F44:F49)) -> 0 | H50: =SUM(H42+SUM(H44:H49)) -> 0 | I50: =SUM(I42+SUM(I44:I49)) -> 0 | J50: =SUM(J42+SUM(J44:J49)) -> 0 | K50: =SUM(K42+SUM(K44:K49)) -> 2244 | L50: =SUM(L42+SUM(L44:L49)) -> -2244 | M50: =SUM(M42+SUM(M44:M49)) -> 0 | N50: =SUM(N42+SUM(N44:N49)) -> 0 | O50: =SUM(O42+SUM(O44:O49)) -> 1984 | ... T50: =SUM(T42+SUM(T44:T49)) -> #REF! | V50: =SUM(V42+SUM(V44:V49)) -> 2244 | W50: =SUM(W42+SUM(W44:W49)) -> 0 | X50: =SUM(X42+SUM(X44:X49)) -> 0 | Y50: =SUM(Y42+SUM(Y44:Y49)) -> 0 | Z50: =SUM(Z42+SUM(Z44:Z49)) -> -260 | AA50: =SUM(AA42+SUM(AA44:AA49)) -> 0 | AB50: =SUM(AB42+SUM(AB44:AB49)) -> 0 | AC50: =SUM(AC42+SUM(AC44:AC49)) -> 0 | ... AE50: =SUM(AE42+SUM(AE44:AE49)) -> #REF!
B52: Capitalization
B54: Cash & Cash Equivelants | K54: ='Historical Financials'!J41 -> 2244 | O54: ='Historical Financials'!N41 -> 1984 | S54: ='Historical Financials'!#REF! -> #REF! | V54: =K54 -> 2244 | W54: =L54 -> 0 | X54: =M54 -> 0 | Y54: =N54 -> 0 | Z54: =O54 -> 1984 | AA54: =P54 -> 0 | AB54: =Q54 -> 0 | AC54: =R54 -> 0 | ... AE54: =T54 -> 0
B55: XXX | K55: ='Historical Financials'!#REF! -> #REF! | O55: ='Historical Financials'!#REF! -> #REF! | S55: ='Historical Financials'!#REF! -> #REF! | V55: =K55 -> #REF! | W55: =L55 -> 0 | X55: =M55 -> 0 | Y55: =N55 -> 0 | Z55: =O55 -> #REF! | AA55: =P55 -> 0 | AB55: =Q55 -> 0 | AC55: =R55 -> 0 | ... AE55: =T55 -> 0
B56: XXX | K56: =D56 -> 0 | O56: =E56 -> 0 | S56: =F56 -> 0 | V56: =K56 -> 0 | W56: =L56 -> 0 | X56: =M56 -> 0 | Y56: =N56 -> 0 | Z56: =O56 -> 0 | AA56: =P56 -> 0 | AB56: =Q56 -> 0 | AC56: =R56 -> 0 | ... AE56: =T56 -> 0
B57: Total Liquidity | C57: =SUM(C54:C56) -> 0 | D57: =SUM(D54:D56) -> 0 | E57: =SUM(E54:E56) -> 0 | F57: =SUM(F54:F56) -> 0 | H57: =SUM(H54:H56) -> 0 | I57: =SUM(I54:I56) -> 0 | J57: =SUM(J54:J56) -> 0 | K57: =SUM(K54:K56) -> #REF! | L57: =SUM(L54:L56) -> 0 | M57: =SUM(M54:M56) -> 0 | N57: =SUM(N54:N56) -> 0 | O57: =SUM(O54:O56) -> #REF! | ... T57: =SUM(T54:T56) -> 0 | V57: =SUM(V54:V56) -> #REF! | W57: =SUM(W54:W56) -> 0 | X57: =SUM(X54:X56) -> 0 | Y57: =SUM(Y54:Y56) -> 0 | Z57: =SUM(Z54:Z56) -> #REF! | AA57: =SUM(AA54:AA56) -> 0 | AB57: =SUM(AB54:AB56) -> 0 | AC57: =SUM(AC54:AC56) -> 0 | ... AE57: =SUM(AE54:AE56) -> 0
B59: Balance Sheet Metrics:
B60: XXX | V60: =K60 -> 0 | W60: =L60 -> 0 | X60: =M60 -> 0 | Y60: =N60 -> 0 | Z60: =O60 -> 0 | AA60: =P60 -> 0 | AB60: =Q60 -> 0 | AC60: =R60 -> 0 | ... AE60: =T60 -> 0
B61: XXX | V61: =K61 -> 0 | W61: =L61 -> 0 | X61: =M61 -> 0 | Y61: =N61 -> 0 | Z61: =O61 -> 0 | AA61: =P61 -> 0 | AB61: =Q61 -> 0 | AC61: =R61 -> 0 | ... AE61: =T61 -> 0
B62: XXX | V62: =K62 -> 0 | W62: =L62 -> 0 | X62: =M62 -> 0 | Y62: =N62 -> 0 | Z62: =O62 -> 0 | AA62: =P62 -> 0 | AB62: =Q62 -> 0 | AC62: =R62 -> 0 | ... AE62: =T62 -> 0
B63: XXX | V63: =K63 -> 0 | W63: =L63 -> 0 | X63: =M63 -> 0 | Y63: =N63 -> 0 | Z63: =O63 -> 0 | AA63: =P63 -> 0 | AB63: =Q63 -> 0 | AC63: =R63 -> 0 | ... AE63: =T63 -> 0
B64: XXX | V64: =K64 -> 0 | W64: =L64 -> 0 | X64: =M64 -> 0 | Y64: =N64 -> 0 | Z64: =O64 -> 0 | AA64: =P64 -> 0 | AB64: =Q64 -> 0 | AC64: =R64 -> 0 | ... AE64: =T64 -> 0
B65: XXX | V65: =K65 -> 0 | W65: =L65 -> 0 | X65: =M65 -> 0 | Y65: =N65 -> 0 | Z65: =O65 -> 0 | AA65: =P65 -> 0 | AB65: =Q65 -> 0 | AC65: =R65 -> 0 | ... AE65: =T65 -> 0
B66: XXX | V66: =K66 -> 0 | W66: =L66 -> 0 | X66: =M66 -> 0 | Y66: =N66 -> 0 | Z66: =O66 -> 0 | AA66: =P66 -> 0 | AB66: =Q66 -> 0 | AC66: =R66 -> 0 | ... AE66: =T66 -> 0
B68: Summary Debt:
B69: CPLTD | V69: =K69 -> 0 | W69: =L69 -> 0 | X69: =M69 -> 0 | Y69: =N69 -> 0 | Z69: =O69 -> 0 | AA69: =P69 -> 0 | AB69: =Q69 -> 0 | AC69: =R69 -> 0 | ... AE69: =T69 -> 0
B70: LTD | V70: =K70 -> 0 | W70: =L70 -> 0 | X70: =M70 -> 0 | Y70: =N70 -> 0 | Z70: =O70 -> 0 | AA70: =P70 -> 0 | AB70: =Q70 -> 0 | AC70: =R70 -> 0 | ... AE70: =T70 -> 0
B72: XXX | K72: =D72 -> 0 | O72: =E72 -> 0 | S72: =F72 -> 0 | V72: =K72 -> 0 | W72: =L72 -> 0 | X72: =M72 -> 0 | Y72: =N72 -> 0 | Z72: =O72 -> 0 | AA72: =P72 -> 0 | AB72: =Q72 -> 0 | AC72: =R72 -> 0 | ... AE72: =T72 -> 0
B73: XXX | K73: =D73 -> 0 | O73: =E73 -> 0 | S73: =F73 -> 0 | V73: =K73 -> 0 | W73: =L73 -> 0 | X73: =M73 -> 0 | Y73: =N73 -> 0 | Z73: =O73 -> 0 | AA73: =P73 -> 0 | AB73: =Q73 -> 0 | AC73: =R73 -> 0 | ... AE73: =T73 -> 0
B74: XXX | K74: =D74 -> 0 | O74: =E74 -> 0 | S74: =F74 -> 0 | V74: =K74 -> 0 | W74: =L74 -> 0 | X74: =M74 -> 0 | Y74: =N74 -> 0 | Z74: =O74 -> 0 | AA74: =P74 -> 0 | AB74: =Q74 -> 0 | AC74: =R74 -> 0 | ... AE74: =T74 -> 0
B75: XXX | K75: ='Historical Financials'!#REF!+'Historical Financials'!#REF! -> #REF! | O75: ='Historical Financials'!#REF!+'Historical Financials'!#REF! -> #REF! | S75: ='Historical Financials'!#REF!+'Historical Financials'!#REF! -> #REF! | V75: =K75 -> #REF! | W75: =L75 -> 0 | X75: =M75 -> 0 | Y75: =N75 -> 0 | Z75: =O75 -> #REF! | AA75: =P75 -> 0 | AB75: =Q75 -> 0 | AC75: =R75 -> 0 | ... AE75: =T75 -> 0
B76: Total Debt | C76: =SUM(C72:C75) -> 0 | D76: =SUM(D72:D75) -> 0 | E76: =SUM(E72:E75) -> 0 | F76: =SUM(F72:F75) -> 0 | H76: =SUM(H72:H75) -> 0 | I76: =SUM(I72:I75) -> 0 | J76: =SUM(J72:J75) -> 0 | K76: =SUM(K72:K75) -> #REF! | L76: =SUM(L72:L75) -> 0 | M76: =SUM(M72:M75) -> 0 | N76: =SUM(N72:N75) -> 0 | O76: =SUM(O72:O75) -> #REF! | ... T76: =SUM(T72:T75) -> 0 | V76: =SUM(V72:V75) -> #REF! | W76: =SUM(W72:W75) -> 0 | X76: =SUM(X72:X75) -> 0 | Y76: =SUM(Y72:Y75) -> 0 | Z76: =SUM(Z72:Z75) -> #REF! | AA76: =SUM(AA72:AA75) -> 0 | AB76: =SUM(AB72:AB75) -> 0 | AC76: =SUM(AC72:AC75) -> 0 | ... AE76: =SUM(AE72:AE75) -> 0
B78: Total Shareholder Equity | V78: =K78 -> 0 | W78: =L78 -> 0 | X78: =M78 -> 0 | Y78: =N78 -> 0 | Z78: =O78 -> 0 | AA78: =P78 -> 0 | AB78: =Q78 -> 0 | AC78: =R78 -> 0 | ... AE78: =T78 -> 0
B79: Total Book Capitalization | C79: =SUM(C76:C78) -> 0 | D79: =SUM(D76:D78) -> 0 | E79: =SUM(E76:E78) -> 0 | F79: =SUM(F76:F78) -> 0 | H79: =SUM(H76:H78) -> 0 | I79: =SUM(I76:I78) -> 0 | J79: =SUM(J76:J78) -> 0 | K79: =SUM(K76:K78) -> #REF! | L79: =SUM(L76:L78) -> 0 | M79: =SUM(M76:M78) -> 0 | N79: =SUM(N76:N78) -> 0 | O79: =SUM(O76:O78) -> #REF! | ... T79: =SUM(T76:T78) -> 0 | V79: =SUM(V76:V78) -> #REF! | W79: =SUM(W76:W78) -> 0 | X79: =SUM(X76:X78) -> 0 | Y79: =SUM(Y76:Y78) -> 0 | Z79: =SUM(Z76:Z78) -> #REF! | AA79: =SUM(AA76:AA78) -> 0 | AB79: =SUM(AB76:AB78) -> 0 | AC79: =SUM(AC76:AC78) -> 0 | ... AE79: =SUM(AE76:AE78) -> 0
B81: Credit Metrics
B83: LTM Total Leverage | C83: =C76/C34 -> #DIV/0! | D83: =D76/D34 -> #DIV/0! | E83: =E76/E34 -> #DIV/0! | F83: =F76/F34 -> #DIV/0! | K83: =SUM(K76/SUM(H34:K34)) -> #REF! | L83: =SUM(L76/SUM(I34:L34)) -> #DIV/0! | M83: =SUM(M76/SUM(J34:M34)) -> #DIV/0! | N83: =SUM(N76/SUM(K34:N34)) -> #DIV/0! | O83: =SUM(O76/SUM(L34:O34)) -> #REF! | P83: =SUM(P76/SUM(M34:P34)) -> #DIV/0! | Q83: =SUM(Q76/SUM(N34:Q34)) -> #DIV/0! | R83: =SUM(R76/SUM(O34:R34)) -> #DIV/0! | ... T83: =SUM(T76/SUM(Q34:T34)) -> #DIV/0! | V83: =V76/V34 -> #REF! | W83: =W76/W34 -> #DIV/0! | X83: =X76/X34 -> #DIV/0! | Y83: =Y76/Y34 -> #DIV/0! | Z83: =Z76/Z34 -> #REF! | AA83: =AA76/AA34 -> #DIV/0! | AB83: =AB76/AB34 -> #DIV/0! | AC83: =AC76/AC34 -> #DIV/0! | ... AE83: =AE76/AE34 -> #DIV/0!
B84: LTM Net Leverage | C84: =SUM(C76-C54)/C34 -> #DIV/0! | D84: =SUM(D76-D54)/D34 -> #DIV/0! | E84: =SUM(E76-E54)/E34 -> #DIV/0! | F84: =SUM(F76-F54)/F34 -> #DIV/0! | K84: =SUM(K76-K54)/SUM(H34:K34) -> #REF! | L84: =SUM(L76-L54)/SUM(I34:L34) -> #DIV/0! | M84: =SUM(M76-M54)/SUM(J34:M34) -> #DIV/0! | N84: =SUM(N76-N54)/SUM(K34:N34) -> #DIV/0! | O84: =SUM(O76-O54)/SUM(L34:O34) -> #REF! | P84: =SUM(P76-P54)/SUM(M34:P34) -> #DIV/0! | Q84: =SUM(Q76-Q54)/SUM(N34:Q34) -> #DIV/0! | R84: =SUM(R76-R54)/SUM(O34:R34) -> #DIV/0! | ... T84: =SUM(T76-T54)/SUM(Q34:T34) -> #DIV/0! | V84: =SUM(V76-V54)/V34 -> #REF! | W84: =SUM(W76-W54)/W34 -> #DIV/0! | X84: =SUM(X76-X54)/X34 -> #DIV/0! | Y84: =SUM(Y76-Y54)/Y34 -> #DIV/0! | Z84: =SUM(Z76-Z54)/Z34 -> #REF! | AA84: =SUM(AA76-AA54)/AA34 -> #DIV/0! | AB84: =SUM(AB76-AB54)/AB34 -> #DIV/0! | AC84: =SUM(AC76-AC54)/AC34 -> #DIV/0! | ... AE84: =SUM(AE76-AE54)/AE34 -> #DIV/0!
B85: LTM Interest Coverage | C85: =C34/-C39 -> #DIV/0! | D85: =D34/-D39 -> #DIV/0! | E85: =E34/-E39 -> #DIV/0! | F85: =F34/-F39 -> #DIV/0! | K85: {=SUM(H34:K34)/SUM(-H39:K39)} -> #DIV/0! | L85: {=SUM(I34:L34)/SUM(-I39:L39)} -> #DIV/0! | M85: {=SUM(J34:M34)/SUM(-J39:M39)} -> #DIV/0! | N85: {=SUM(K34:N34)/SUM(-K39:N39)} -> #DIV/0! | O85: {=SUM(L34:O34)/SUM(-L39:O39)} -> #DIV/0! | P85: {=SUM(M34:P34)/SUM(-M39:P39)} -> #DIV/0! | Q85: {=SUM(N34:Q34)/SUM(-N39:Q39)} -> #DIV/0! | R85: {=SUM(O34:R34)/SUM(-O39:R39)} -> #DIV/0! | ... T85: {=SUM(Q34:T34)/SUM(-Q39:T39)} -> #DIV/0! | V85: =V34/-V39 -> #DIV/0! | W85: =W34/-W39 -> #DIV/0! | X85: =X34/-X39 -> #DIV/0! | Y85: =Y34/-Y39 -> #DIV/0! | Z85: =Z34/-Z39 -> #DIV/0! | AA85: =AA34/-AA39 -> #DIV/0! | AB85: =AB34/-AB39 -> #DIV/0! | AC85: =AC34/-AC39 -> #DIV/0! | ... AE85: =AE34/-AE39 -> #DIV/0!
B86: LTM Debt Service Coverage | C86: {=SUM(C34+C37)/SUM(-C38:C39)} -> #DIV/0! | D86: {=SUM(D34+D37)/SUM(-D38:D39)} -> #DIV/0! | E86: {=SUM(E34+E37)/SUM(-E38:E39)} -> #DIV/0! | F86: {=SUM(F34+F37)/SUM(-F38:F39)} -> #DIV/0! | K86: {=SUM(H34:K34+H37:K37)/SUM(-H38:K39)} -> #DIV/0! | L86: {=SUM(I34:L34+I37:L37)/SUM(-I38:L39)} -> #DIV/0! | M86: {=SUM(J34:M34+J37:M37)/SUM(-J38:M39)} -> #DIV/0! | N86: {=SUM(K34:N34+K37:N37)/SUM(-K38:N39)} -> #DIV/0! | O86: {=SUM(L34:O34+L37:O37)/SUM(-L38:O39)} -> #DIV/0! | P86: {=SUM(M34:P34+M37:P37)/SUM(-M38:P39)} -> #DIV/0! | Q86: {=SUM(N34:Q34+N37:Q37)/SUM(-N38:Q39)} -> #DIV/0! | R86: {=SUM(O34:R34+O37:R37)/SUM(-O38:R39)} -> #DIV/0! | ... T86: {=SUM(Q34:T34+Q37:T37)/SUM(-Q38:T39)} -> #DIV/0! | V86: {=SUM(V34+V37)/SUM(-V38:V39)} -> #DIV/0! | W86: {=SUM(W34+W37)/SUM(-W38:W39)} -> #DIV/0! | X86: {=SUM(X34+X37)/SUM(-X38:X39)} -> #DIV/0! | Y86: {=SUM(Y34+Y37)/SUM(-Y38:Y39)} -> #DIV/0! | Z86: {=SUM(Z34+Z37)/SUM(-Z38:Z39)} -> #DIV/0! | AA86: {=SUM(AA34+AA37)/SUM(-AA38:AA39)} -> #DIV/0! | AB86: {=SUM(AB34+AB37)/SUM(-AB38:AB39)} -> #DIV/0! | AC86: {=SUM(AC34+AC37)/SUM(-AC38:AC39)} -> #DIV/0! | ... AE86: {=SUM(AE34+AE37)/SUM(-AE38:AE39)} -> #DIV/0!
B87: LTM Fixed Charge Coverage | C87: {=SUM(C34)/SUM(-C37:C39)} -> #DIV/0! | D87: {=SUM(D34)/SUM(-D37:D39)} -> #DIV/0! | E87: {=SUM(E34)/SUM(-E37:E39)} -> #DIV/0! | F87: {=SUM(F34)/SUM(-F37:F39)} -> #DIV/0! | K87: {=SUM(H34:K34)/SUM(-H37:K39)} -> #DIV/0! | L87: {=SUM(I34:L34)/SUM(-I37:L39)} -> #DIV/0! | M87: {=SUM(J34:M34)/SUM(-J37:M39)} -> #DIV/0! | N87: {=SUM(K34:N34)/SUM(-K37:N39)} -> #DIV/0! | O87: {=SUM(L34:O34)/SUM(-L37:O39)} -> #DIV/0! | P87: {=SUM(M34:P34)/SUM(-M37:P39)} -> #DIV/0! | Q87: {=SUM(N34:Q34)/SUM(-N37:Q39)} -> #DIV/0! | R87: {=SUM(O34:R34)/SUM(-O37:R39)} -> #DIV/0! | ... T87: {=SUM(Q34:T34)/SUM(-Q37:T39)} -> #DIV/0! | V87: {=SUM(V34)/SUM(-V37:V39)} -> #DIV/0! | W87: {=SUM(W34)/SUM(-W37:W39)} -> #DIV/0! | X87: {=SUM(X34)/SUM(-X37:X39)} -> #DIV/0! | Y87: {=SUM(Y34)/SUM(-Y37:Y39)} -> #DIV/0! | Z87: {=SUM(Z34)/SUM(-Z37:Z39)} -> #DIV/0! | AA87: {=SUM(AA34)/SUM(-AA37:AA39)} -> #DIV/0! | AB87: {=SUM(AB34)/SUM(-AB37:AB39)} -> #DIV/0! | AC87: {=SUM(AC34)/SUM(-AC37:AC39)} -> #DIV/0! | ... AE87: {=SUM(AE34)/SUM(-AE37:AE39)} -> #DIV/0!
B88: Debt-to-Book Capitalization | C88: =C79/C76 -> #DIV/0! | D88: =D79/D76 -> #DIV/0! | E88: =E79/E76 -> #DIV/0! | F88: =F79/F76 -> #DIV/0! | K88: =K79/K76 -> #REF! | L88: =L79/L76 -> #DIV/0! | M88: =M79/M76 -> #DIV/0! | N88: =N79/N76 -> #DIV/0! | O88: =O79/O76 -> #REF! | P88: =P79/P76 -> #DIV/0! | Q88: =Q79/Q76 -> #DIV/0! | R88: =R79/R76 -> #DIV/0! | ... T88: =T79/T76 -> #DIV/0! | V88: =V79/V76 -> #REF! | W88: =W79/W76 -> #DIV/0! | X88: =X79/X76 -> #DIV/0! | Y88: =Y79/Y76 -> #DIV/0! | Z88: =Z79/Z76 -> #REF! | AA88: =AA79/AA76 -> #DIV/0! | AB88: =AB79/AB76 -> #DIV/0! | AC88: =AC79/AC76 -> #DIV/0! | ... AE88: =AE79/AE76 -> #DIV/0!
