Workbook

Sheet Historical Financials
B2: Ulta Beauty Inc. (NASDAQ: ULTA)
B3: Historical Financials
B4: $ in thousands except per share
A6: X | B6: Income Statement | C6: FYE | J6: Quarterly | T6: Quarterly | AE6: LTM | AK6: Variance
B7: Fiscal Period | C7: 2019 | D7: 2020 | E7: 2021 | F7: 2022 | G7: 2023 | H7: 2024 | J7: 1Q22 | K7: 2Q22 | L7: 3Q22 | M7: 4Q22 | N7: 1Q23 | O7: 2Q23 | P7: 3Q23 | Q7: 4Q23 | R7: 1Q24 | S7: 2Q24 | T7: 3Q24 | U7: 4Q24 | V7: 1Q25 | W7: 2Q25 | Y7: =M7 -> 4Q22 | Z7: =N7 -> 1Q23 | AA7: =O7 -> 2Q23 | AB7: =P7 -> 3Q23 | AC7: =Q7 -> 4Q23 | AD7: =R7 -> 1Q24 | AE7: =S7 -> 2Q24 | AF7: =T7 -> 3Q24 | ... AI7: =W7 -> 2Q25
B8: Fiscal Period End Date | C8: 43497 | D8: 43861 | E8: 44225 | F8: 44954 | G8: 45325 | H8: 45689 | J8: 44681 | K8: 44772 | L8: 44863 | M8: 44954 | N8: 45045 | O8: 45136 | P8: 45227 | Q8: 45325 | R8: 45416 | S8: 45507 | T8: 45598 | U8: 45689 | V8: 45780 | W8: 45871 | Y8: =M8 -> 44954 | Z8: =N8 -> 45045 | AA8: =O8 -> 45136 | AB8: =P8 -> 45227 | AC8: =Q8 -> 45325 | AD8: =R8 -> 45416 | AE8: =S8 -> 45507 | AF8: =T8 -> 45598 | ... AI8: =W8 -> 45871
B10: Consolidated Revenue | C10: 7398068 | D10: 6090433.5 | E10: 8630889 | F10: 10208580 | G10: 11207303 | H10: 11295654 | J10: 2345901 | K10: 2297113 | L10: 2338793 | M10: =SUM(F10-SUM(J10:L10)) -> 3226773 | N10: 2634263 | O10: 2529809 | P10: 2488933 | Q10: =SUM(G10-SUM(N10:P10)) -> 3554298 | R10: 2725848 | S10: 2552087 | T10: 2530100 | U10: =SUM(H10-SUM(R10:T10)) -> 3487619 | V10: 2848367 | W10: 2788469 | Y10: =SUM(J10:M10) -> 10208580 | Z10: =SUM(K10:N10) -> 10496942 | AA10: =SUM(L10:O10) -> 10729638 | AB10: =SUM(M10:P10) -> 10879778 | AC10: =SUM(N10:Q10) -> 11207303 | AD10: =SUM(O10:R10) -> 11298888 | AE10: =SUM(P10:S10) -> 11321166 | AF10: =SUM(Q10:T10) -> 11362333 | ... AI10: =SUM(T10:W10) -> 11654555 | AK10: =SUM(AI10/AE10)-1 -> 0.029448292
B11: Total Revenue | C11: =+SUM(C10:C10) -> 7398068 | D11: =+SUM(D10:D10) -> 6090433.5 | E11: =+SUM(E10:E10) -> 8630889 | F11: =+SUM(F10:F10) -> 10208580 | G11: =+SUM(G10:G10) -> 11207303 | H11: =+SUM(H10:H10) -> 11295654 | J11: =+SUM(J10:J10) -> 2345901 | K11: =+SUM(K10:K10) -> 2297113 | L11: =+SUM(L10:L10) -> 2338793 | M11: =+SUM(M10:M10) -> 3226773 | N11: =+SUM(N10:N10) -> 2634263 | O11: =+SUM(O10:O10) -> 2529809 | P11: =+SUM(P10:P10) -> 2488933 | Q11: =+SUM(Q10:Q10) -> 3554298 | ... W11: =+SUM(W10:W10) -> 2788469 | Y11: =+SUM(Y10:Y10) -> 10208580 | Z11: =+SUM(Z10:Z10) -> 10496942 | AA11: =+SUM(AA10:AA10) -> 10729638 | AB11: =+SUM(AB10:AB10) -> 10879778 | AC11: =+SUM(AC10:AC10) -> 11207303 | AD11: =+SUM(AD10:AD10) -> 11298888 | AE11: =+SUM(AE10:AE10) -> 11321166 | AF11: =+SUM(AF10:AF10) -> 11362333 | ... AI11: =+SUM(AI10:AI10) -> 11654555 | AK11: =SUM(AI11/AE11)-1 -> 0.029448292
B13: Cost of Sales | C13: -4717004 | D13: -4202794 | E13: -5262335 | F13: -6164070 | G13: -6826203 | H13: -6908401 | J13: -1404875 | K13: -1368949 | L13: -1375976 | M13: =SUM(F13-SUM(J13:L13)) -> -2014270 | N13: -1579406 | O13: -1536197 | P13: -1496866 | Q13: =SUM(G13-SUM(N13:P13)) -> -2213734 | R13: -1656068 | S13: -1573910 | T13: -1524456 | U13: =SUM(H13-SUM(R13:T13)) -> -2153967 | V13: -1734148 | W13: -1696773 | Y13: =SUM(K13:N13) -> -6338601 | Z13: =SUM(L13:O13) -> -6505849 | AA13: =SUM(M13:P13) -> -6626739 | AB13: =SUM(N13:Q13) -> -6826203 | AC13: =SUM(O13:R13) -> -6902865 | AD13: =SUM(P13:S13) -> -6940578 | AE13: =SUM(P13:S13) -> -6940578 | AF13: =SUM(Q13:T13) -> -6968168 | AG13: =SUM(R13:U13) -> -6908401 | AH13: =SUM(S13:V13) -> -6986481 | AI13: =SUM(T13:W13) -> -7109344 | AK13: =SUM(AI13/AE13)-1 -> 0.024315842
B14: Gross Profit | C14: =+SUM(C11+SUM(C13:C13)) -> 2681064 | D14: =+SUM(D11+SUM(D13:D13)) -> 1887639.5 | E14: =+SUM(E11+SUM(E13:E13)) -> 3368554 | F14: =+SUM(F11+SUM(F13:F13)) -> 4044510 | G14: =+SUM(G11+SUM(G13:G13)) -> 4381100 | H14: =+SUM(H11+SUM(H13:H13)) -> 4387253 | J14: =+SUM(J11+SUM(J13:J13)) -> 941026 | K14: =+SUM(K11+SUM(K13:K13)) -> 928164 | L14: =+SUM(L11+SUM(L13:L13)) -> 962817 | M14: =+SUM(M11+SUM(M13:M13)) -> 1212503 | N14: =+SUM(N11+SUM(N13:N13)) -> 1054857 | O14: =+SUM(O11+SUM(O13:O13)) -> 993612 | P14: =+SUM(P11+SUM(P13:P13)) -> 992067 | Q14: =+SUM(Q11+SUM(Q13:Q13)) -> 1340564 | ... W14: =+SUM(W11+SUM(W13:W13)) -> 1091696 | Y14: =+SUM(Y11+SUM(Y13:Y13)) -> 3869979 | Z14: =+SUM(Z11+SUM(Z13:Z13)) -> 3991093 | AA14: =+SUM(AA11+SUM(AA13:AA13)) -> 4102899 | AB14: =+SUM(AB11+SUM(AB13:AB13)) -> 4053575 | AC14: =+SUM(AC11+SUM(AC13:AC13)) -> 4304438 | AD14: =+SUM(AD11+SUM(AD13:AD13)) -> 4358310 | AE14: =+SUM(AE11+SUM(AE13:AE13)) -> 4380588 | AF14: =+SUM(AF11+SUM(AF13:AF13)) -> 4394165 | ... AI14: =+SUM(AI11+SUM(AI13:AI13)) -> 4545211 | AK14: =SUM(AI14/AE14)-1 -> 0.037580115
B15: Gross Margin (%) | C15: =C14/C11 -> 0.36240056 | D15: =D14/D11 -> 0.30993516 | E15: =E14/E11 -> 0.3902905 | F15: =F14/F11 -> 0.39618732 | G15: =G14/G11 -> 0.39091475 | H15: =H14/H11 -> 0.38840186 | J15: =J14/J11 -> 0.40113628 | K15: =K14/K11 -> 0.40405674 | L15: =L14/L11 -> 0.4116726 | M15: =M14/M11 -> 0.37576334 | N15: =N14/N11 -> 0.40043724 | O15: =O14/O11 -> 0.39276167 | P15: =P14/P11 -> 0.39859128 | Q15: =Q14/Q11 -> 0.37716702 | ... W15: =W14/W11 -> 0.39150372 | Y15: =Y14/Y11 -> 0.37909082 | Z15: =Z14/Z11 -> 0.38021483 | AA15: =AA14/AA11 -> 0.38238932 | AB15: =AB14/AB11 -> 0.37257883 | AC15: =AC14/AC11 -> 0.38407438 | AD15: =AD14/AD11 -> 0.38572911 | AE15: =AE14/AE11 -> 0.38693788 | AF15: =AF14/AF11 -> 0.38673088 | ... AI15: =AI14/AI11 -> 0.38999438 | AK15: =SUM(AI15-AE15)*1000 -> 3.0565016
B17: Selling, general and administrative expenses | C17: -1760716 | D17: -1583017 | E17: -2061545 | F17: -2395299 | G17: -2694561 | H17: -2808592 | J17: -500970 | K17: -534459 | L17: -597164 | M17: =SUM(F17-SUM(J17:L17)) -> -762706 | N17: -612129 | O17: -600692 | P17: -661380 | Q17: =SUM(G17-SUM(N17:P17)) -> -820360 | R17: -665913 | S17: -644821 | T17: -682259 | U17: =SUM(H17-SUM(R17:T17)) -> -815599 | V17: -710613 | W17: -741737 | Y17: =SUM(K17:N17) -> -2506458 | Z17: =SUM(L17:O17) -> -2572691 | AA17: =SUM(M17:P17) -> -2636907 | AB17: =SUM(N17:Q17) -> -2694561 | AC17: =SUM(O17:R17) -> -2748345 | AD17: =SUM(P17:S17) -> -2792474 | AE17: =SUM(P17:S17) -> -2792474 | AF17: =SUM(Q17:T17) -> -2813353 | AG17: =SUM(R17:U17) -> -2808592 | AH17: =SUM(S17:V17) -> -2853292 | AI17: =SUM(T17:W17) -> -2950208 | AK17: =SUM(AI17/AE17)-1 -> 0.056485396
B18: Pre-opening expenses | C18: -19254 | D18: -15000 | E18: -9517 | F18: -10601 | G18: -8510 | H18: -13689 | J18: -2348 | K18: -2277 | L18: -3797 | M18: =SUM(F18-SUM(J18:L18)) -> -2179 | N18: -658 | O18: -1278 | P18: -3460 | Q18: =SUM(G18-SUM(N18:P18)) -> -3114 | R18: -2919 | S18: -4155 | T18: -4883 | U18: =SUM(H18-SUM(R18:T18)) -> -1732 | V18: -1829 | W18: -5105 | Y18: =SUM(K18:N18) -> -8911 | Z18: =SUM(L18:O18) -> -7912 | AA18: =SUM(M18:P18) -> -7575 | AB18: =SUM(N18:Q18) -> -8510 | AC18: =SUM(O18:R18) -> -10771 | AD18: =SUM(P18:S18) -> -13648 | AE18: =SUM(P18:S18) -> -13648 | AF18: =SUM(Q18:T18) -> -15071 | AG18: =SUM(R18:U18) -> -13689 | AH18: =SUM(S18:V18) -> -12599 | AI18: =SUM(T18:W18) -> -13549 | AK18: =SUM(AI18/AE18)-1 -> -0.0072538101
B19: Impairment, restructuring and other costs | C19: 0 | D19: -114322 | E19: 0 | F19: 0 | G19: 0 | H19: 0 | J19: 0 | K19: 0 | L19: 0 | M19: =SUM(F19-SUM(J19:L19)) -> 0 | N19: 0 | O19: 0 | P19: 0 | Q19: =SUM(G19-SUM(N19:P19)) -> 0 | R19: 0 | S19: 0 | T19: 0 | U19: =SUM(H19-SUM(R19:T19)) -> 0 | V19: 0 | W19: 0 | Y19: =SUM(K19:N19) -> 0 | Z19: =SUM(L19:O19) -> 0 | AA19: =SUM(M19:P19) -> 0 | AB19: =SUM(N19:Q19) -> 0 | AC19: =SUM(O19:R19) -> 0 | AD19: =SUM(P19:S19) -> 0 | AE19: =SUM(P19:S19) -> 0 | AF19: =SUM(Q19:T19) -> 0 | AG19: =SUM(R19:U19) -> 0 | AH19: =SUM(S19:V19) -> 0 | AI19: =SUM(T19:W19) -> 0 | AK19: =SUM(AI19/AE19)-1 -> #DIV/0!
B20: Operating Profit | C20: =+SUM(C14+SUM(C17:C19)) -> 901094 | D20: =+SUM(D14+SUM(D17:D19)) -> 175300.47 | E20: =+SUM(E14+SUM(E17:E19)) -> 1297492 | F20: =+SUM(F14+SUM(F17:F19)) -> 1638610 | G20: =+SUM(G14+SUM(G17:G19)) -> 1678029 | H20: =+SUM(H14+SUM(H17:H19)) -> 1564972 | J20: =+SUM(J14+SUM(J17:J19)) -> 437708 | K20: =+SUM(K14+SUM(K17:K19)) -> 391428 | L20: =+SUM(L14+SUM(L17:L19)) -> 361856 | M20: =+SUM(M14+SUM(M17:M19)) -> 447618 | N20: =+SUM(N14+SUM(N17:N19)) -> 442070 | O20: =+SUM(O14+SUM(O17:O19)) -> 391642 | P20: =+SUM(P14+SUM(P17:P19)) -> 327227 | Q20: =+SUM(Q14+SUM(Q17:Q19)) -> 517090 | ... W20: =+SUM(W14+SUM(W17:W19)) -> 344854 | Y20: =+SUM(Y14+SUM(Y17:Y19)) -> 1354610 | Z20: =+SUM(Z14+SUM(Z17:Z19)) -> 1410490 | AA20: =+SUM(AA14+SUM(AA17:AA19)) -> 1458417 | AB20: =+SUM(AB14+SUM(AB17:AB19)) -> 1350504 | AC20: =+SUM(AC14+SUM(AC17:AC19)) -> 1545322 | AD20: =+SUM(AD14+SUM(AD17:AD19)) -> 1552188 | AE20: =+SUM(AE14+SUM(AE17:AE19)) -> 1574466 | AF20: =+SUM(AF14+SUM(AF17:AF19)) -> 1565741 | ... AI20: =+SUM(AI14+SUM(AI17:AI19)) -> 1581454 | AK20: =SUM(AI20/AE20)-1 -> 0.0044383302
B21: Operating Margin (%) | C21: =C20/C11 -> 0.12180126 | D21: =D20/D11 -> 0.028782922 | E21: =E20/E11 -> 0.15033121 | F21: =F20/F11 -> 0.16051302 | G21: =G20/G11 -> 0.14972639 | H21: =H20/H11 -> 0.13854638 | J21: =J20/J11 -> 0.18658417 | K21: =K20/K11 -> 0.17039998 | L21: =L20/L11 -> 0.15471912 | M21: =M20/M11 -> 0.13872002 | N21: =N20/N11 -> 0.16781544 | O21: =O20/O11 -> 0.1548109 | P21: =P20/P11 -> 0.1314728 | Q21: =Q20/Q11 -> 0.14548302 | ... W21: =W20/W11 -> 0.12367145 | Y21: =Y20/Y11 -> 0.13269328 | Z21: =Z20/Z11 -> 0.13437152 | AA21: =AA20/AA11 -> 0.13592416 | AB21: =AB20/AB11 -> 0.12412974 | AC21: =AC20/AC11 -> 0.13788527 | AD21: =AD20/AD11 -> 0.13737529 | AE21: =AE20/AE11 -> 0.13907278 | AF21: =AF20/AF11 -> 0.13780101 | ... AI21: =AI20/AI11 -> 0.13569407 | AK21: =SUM(AI21-AE21)*1000 -> -3.3787077
B23: Interest Income (Expense), net | C23: 5056 | D23: -5735 | E23: 1663 | F23: -4934 | G23: -17622 | H23: 15094 | J23: -401 | K23: 108 | L23: 849 | M23: =SUM(F23-SUM(J23:L23)) -> -5490 | N23: 7348 | O23: 4449 | P23: 2497 | Q23: =SUM(G23-SUM(N23:P23)) -> -31916 | R23: 6900 | S23: 4526 | T23: -1674 | U23: =SUM(H23-SUM(R23:T23)) -> 5342 | V23: 3547 | W23: 1413 | Y23: =SUM(K23:N23) -> 2815 | Z23: =SUM(L23:O23) -> 7156 | AA23: =SUM(M23:P23) -> 8804 | AB23: =SUM(N23:Q23) -> -17622 | AC23: =SUM(O23:R23) -> -18070 | AD23: =SUM(P23:S23) -> -17993 | AE23: =SUM(P23:S23) -> -17993 | AF23: =SUM(Q23:T23) -> -22164 | AG23: =SUM(R23:U23) -> 15094 | AH23: =SUM(S23:V23) -> 11741 | AI23: =SUM(T23:W23) -> 8628 | AK23: =SUM(AI23/AE23)-1 -> -1.4795198
B24: Earning Before Taxes | C24: =SUM(C20+SUM(C23:C23)) -> 906150 | D24: =SUM(D20+SUM(D23:D23)) -> 169565.47 | E24: =SUM(E20+SUM(E23:E23)) -> 1299155 | F24: =SUM(F20+SUM(F23:F23)) -> 1633676 | G24: =SUM(G20+SUM(G23:G23)) -> 1660407 | H24: =SUM(H20+SUM(H23:H23)) -> 1580066 | J24: =SUM(J20+SUM(J23:J23)) -> 437307 | K24: =SUM(K20+SUM(K23:K23)) -> 391536 | L24: =SUM(L20+SUM(L23:L23)) -> 362705 | M24: =SUM(M20+SUM(M23:M23)) -> 442128 | N24: =SUM(N20+SUM(N23:N23)) -> 449418 | O24: =SUM(O20+SUM(O23:O23)) -> 396091 | P24: =SUM(P20+SUM(P23:P23)) -> 329724 | Q24: =SUM(Q20+SUM(Q23:Q23)) -> 485174 | ... W24: =SUM(W20+SUM(W23:W23)) -> 346267 | Y24: =SUM(Y20+SUM(Y23:Y23)) -> 1357425 | Z24: =SUM(Z20+SUM(Z23:Z23)) -> 1417646 | AA24: =SUM(AA20+SUM(AA23:AA23)) -> 1467221 | AB24: =SUM(AB20+SUM(AB23:AB23)) -> 1332882 | AC24: =SUM(AC20+SUM(AC23:AC23)) -> 1527252 | AD24: =SUM(AD20+SUM(AD23:AD23)) -> 1534195 | AE24: =SUM(AE20+SUM(AE23:AE23)) -> 1556473 | AF24: =SUM(AF20+SUM(AF23:AF23)) -> 1543577 | ... AI24: =SUM(AI20+SUM(AI23:AI23)) -> 1590082 | AK24: =SUM(AI24/AE24)-1 -> 0.02159305
B25: EBT Margin (%) | C25: =C24/C11 -> 0.12248468 | D25: =D24/D11 -> 0.027841281 | E25: =E24/E11 -> 0.15052389 | F25: =F24/F11 -> 0.1600297 | G25: =G24/G11 -> 0.14815402 | H25: =H24/H11 -> 0.13988265 | J25: =J24/J11 -> 0.18641324 | K25: =K24/K11 -> 0.17044699 | L25: =L24/L11 -> 0.15508213 | M25: =M24/M11 -> 0.13701863 | N25: =N24/N11 -> 0.17060483 | O25: =O24/O11 -> 0.15656953 | P25: =P24/P11 -> 0.13247604 | Q25: =Q24/Q11 -> 0.13650347 | ... W25: =W24/W11 -> 0.12417818 | Y25: =Y24/Y11 -> 0.13296903 | Z25: =Z24/Z11 -> 0.13505324 | AA25: =AA24/AA11 -> 0.13674469 | AB25: =AB24/AB11 -> 0.12251004 | AC25: =AC24/AC11 -> 0.13627293 | AD25: =AD24/AD11 -> 0.13578283 | AE25: =AE24/AE11 -> 0.13748345 | AF25: =AF24/AF11 -> 0.13585036 | ... AI25: =AI24/AI11 -> 0.13643438 | AK25: =SUM(AI25-AE25)*1000 -> -1.0490723
B27: Income tax expense | C27: -200205 | D27: -55250 | E27: -309992 | F27: -401136 | G27: -404646 | H27: -378948 | J27: -105912 | K27: -95859 | L27: -88120 | M27: =SUM(F27-SUM(J27:L27)) -> -111245 | N27: -102367 | O27: -95989 | P27: -80241 | Q27: =SUM(G27-SUM(N27:P27)) -> -126049 | R27: -94735 | S27: -81171 | T27: -77997 | U27: =SUM(H27-SUM(R27:T27)) -> -125045 | V27: -99644 | W27: -84795 | Y27: =SUM(K27:N27) -> -397591 | Z27: =SUM(L27:O27) -> -397721 | AA27: =SUM(M27:P27) -> -389842 | AB27: =SUM(N27:Q27) -> -404646 | AC27: =SUM(O27:R27) -> -397014 | AD27: =SUM(P27:S27) -> -382196 | AE27: =SUM(P27:S27) -> -382196 | AF27: =SUM(Q27:T27) -> -379952 | AG27: =SUM(R27:U27) -> -378948 | AH27: =SUM(S27:V27) -> -383857 | AI27: =SUM(T27:W27) -> -387481 | AK27: =SUM(AI27/AE27)-1 -> 0.013827984
B28: Net loss | C28: =SUM(C24+C27) -> 705945 | D28: =SUM(D24+D27) -> 114315.47 | E28: =SUM(E24+E27) -> 989163 | F28: =SUM(F24+F27) -> 1232540 | G28: =SUM(G24+G27) -> 1255761 | H28: =SUM(H24+H27) -> 1201118 | J28: =SUM(J24+J27) -> 331395 | K28: =SUM(K24+K27) -> 295677 | L28: =SUM(L24+L27) -> 274585 | M28: =SUM(M24+M27) -> 330883 | N28: =SUM(N24+N27) -> 347051 | O28: =SUM(O24+O27) -> 300102 | P28: =SUM(P24+P27) -> 249483 | Q28: =SUM(Q24+Q27) -> 359125 | ... W28: =SUM(W24+W27) -> 261472 | Y28: =SUM(Y24+Y27) -> 959834 | Z28: =SUM(Z24+Z27) -> 1019925 | AA28: =SUM(AA24+AA27) -> 1077379 | AB28: =SUM(AB24+AB27) -> 928236 | AC28: =SUM(AC24+AC27) -> 1130238 | AD28: =SUM(AD24+AD27) -> 1151999 | AE28: =SUM(AE24+AE27) -> 1174277 | AF28: =SUM(AF24+AF27) -> 1163625 | ... AI28: =SUM(AI24+AI27) -> 1202601 | AK28: =SUM(AI28/AE28)-1 -> 0.024120374
B29: Net Margin (%) | C29: =C28/C11 -> 0.095422886 | D29: =D28/D11 -> 0.018769677 | E29: =E28/E11 -> 0.11460731 | F29: =F28/F11 -> 0.12073569 | G29: =G28/G11 -> 0.11204846 | H29: =H28/H11 -> 0.10633452 | J29: =J28/J11 -> 0.14126555 | K29: =K28/K11 -> 0.12871678 | L29: =L28/L11 -> 0.11740458 | M29: =M28/M11 -> 0.10254301 | N29: =N28/N11 -> 0.13174501 | O29: =O28/O11 -> 0.11862635 | P29: =P28/P11 -> 0.10023693 | Q29: =Q28/Q11 -> 0.10103964 | ... W29: =W28/W11 -> 0.093769018 | Y29: =Y28/Y11 -> 0.094022283 | Z29: =Z28/Z11 -> 0.097164012 | AA29: =AA28/AA11 -> 0.1004115 | AB29: =AB28/AB11 -> 0.08531755 | AC29: =AC28/AC11 -> 0.10084835 | AD29: =AD28/AD11 -> 0.10195685 | AE29: =AE28/AE11 -> 0.10372403 | AF29: =AF28/AF11 -> 0.10241075 | ... AI29: =AI28/AI11 -> 0.10318721 | AK29: =SUM(AI29-AE29)*1000 -> -0.53682459
B31: Basic shares | M31: =F31 -> 0 | Q31: =G31 -> 0 | U31: =H31 -> 0 | Y31: =M31 -> 0 | Z31: =N31 -> 0 | AA31: =O31 -> 0 | AB31: =P31 -> 0 | AC31: =Q31 -> 0 | AD31: =R31 -> 0 | AE31: =S31 -> 0 | AF31: =T31 -> 0 | ... AI31: =W31 -> 0 | AK31: =SUM(AI31/AE31)-1 -> #DIV/0!
B32: Basic EPS | C32: =C28/C31 -> #DIV/0! | D32: =D28/D31 -> #DIV/0! | E32: =E28/E31 -> #DIV/0! | F32: =F28/F31 -> #DIV/0! | G32: =G28/G31 -> #DIV/0! | H32: =H28/H31 -> #DIV/0! | J32: =J28/J31 -> #DIV/0! | K32: =K28/K31 -> #DIV/0! | L32: =L28/L31 -> #DIV/0! | M32: =M28/M31 -> #DIV/0! | N32: =N28/N31 -> #DIV/0! | O32: =O28/O31 -> #DIV/0! | P32: =P28/P31 -> #DIV/0! | Q32: =Q28/Q31 -> #DIV/0! | ... W32: =W28/W31 -> #DIV/0! | Y32: =Y28/Y31 -> #DIV/0! | Z32: =Z28/Z31 -> #DIV/0! | AA32: =AA28/AA31 -> #DIV/0! | AB32: =AB28/AB31 -> #DIV/0! | AC32: =AC28/AC31 -> #DIV/0! | AD32: =AD28/AD31 -> #DIV/0! | AE32: =AE28/AE31 -> #DIV/0! | AF32: =AF28/AF31 -> #DIV/0! | ... AI32: =AI28/AI31 -> #DIV/0! | AK32: =SUM(AI32/AE32)-1 -> #DIV/0!
B34: Fully Diluted Shares | M34: =F34 -> 0 | Q34: =G34 -> 0 | U34: =H34 -> 0 | Y34: =N34 -> 0 | Z34: =O34 -> 0 | AA34: =P34 -> 0 | AB34: =Q34 -> 0 | AC34: =R34 -> 0 | AD34: =S34 -> 0 | AE34: =S34 -> 0 | AF34: =T34 -> 0 | AG34: =U34 -> 0 | AH34: =V34 -> 0 | AI34: =W34 -> 0 | AK34: =SUM(AI34/AE34)-1 -> #DIV/0!
B35: Diluted EPS | C35: =C28/C34 -> #DIV/0! | D35: =D28/D34 -> #DIV/0! | E35: =E28/E34 -> #DIV/0! | F35: =F28/F34 -> #DIV/0! | G35: =G28/G34 -> #DIV/0! | H35: =H28/H34 -> #DIV/0! | J35: =J28/J34 -> #DIV/0! | K35: =K28/K34 -> #DIV/0! | L35: =L28/L34 -> #DIV/0! | M35: =M28/M34 -> #DIV/0! | N35: =N28/N34 -> #DIV/0! | O35: =O28/O34 -> #DIV/0! | P35: =P28/P34 -> #DIV/0! | Q35: =Q28/Q34 -> #DIV/0! | ... W35: =W28/W34 -> #DIV/0! | Y35: =Y28/Y34 -> #DIV/0! | Z35: =Z28/Z34 -> #DIV/0! | AA35: =AA28/AA34 -> #DIV/0! | AB35: =AB28/AB34 -> #DIV/0! | AC35: =AC28/AC34 -> #DIV/0! | AD35: =AD28/AD34 -> #DIV/0! | AE35: =AE28/AE34 -> #DIV/0! | AF35: =AF28/AF34 -> #DIV/0! | ... AI35: =AI28/AI34 -> #DIV/0! | AK35: =SUM(AI35/AE35)-1 -> #DIV/0!
A37: X | B37: Balance Sheet | C37: FYE | F37: FYE | J37: Quarterly | T37: Quarterly | AE37: LTM | AK37: Variance
B38: =B7 -> Fiscal Period | C38: =C7 -> 2019 | D38: =D7 -> 2020 | E38: =E7 -> 2021 | F38: =F7 -> 2022 | G38: =G7 -> 2023 | H38: =H7 -> 2024 | J38: =J7 -> 1Q22 | K38: =K7 -> 2Q22 | L38: =L7 -> 3Q22 | M38: =M7 -> 4Q22 | N38: =N7 -> 1Q23 | O38: =O7 -> 2Q23 | P38: =P7 -> 3Q23 | Q38: =Q7 -> 4Q23 | ... W38: =W7 -> 2Q25 | Y38: =Y7 -> 4Q22 | Z38: =Z7 -> 1Q23 | AA38: =AA7 -> 2Q23 | AB38: =AB7 -> 3Q23 | AC38: =AC7 -> 4Q23 | AD38: =AD7 -> 1Q24 | AE38: =AE7 -> 2Q24 | AF38: =AF7 -> 3Q24 | ... AI38: =AI7 -> 2Q25
B39: =B8 -> Fiscal Period End Date | C39: =C8 -> 43497 | D39: =D8 -> 43861 | E39: =E8 -> 44225 | F39: =F8 -> 44954 | G39: =G8 -> 45325 | H39: =H8 -> 45689 | J39: =J8 -> 44681 | K39: =K8 -> 44772 | L39: =L8 -> 44863 | M39: =M8 -> 44954 | N39: =N8 -> 45045 | O39: =O8 -> 45136 | P39: =P8 -> 45227 | Q39: =Q8 -> 45325 | ... W39: =W8 -> 45871 | Y39: =Y8 -> 44954 | Z39: =Z8 -> 45045 | AA39: =AA8 -> 45136 | AB39: =AB8 -> 45227 | AC39: =AC8 -> 45325 | AD39: =AD8 -> 45416 | AE39: =AE8 -> 45507 | AF39: =AF8 -> 45598 | ... AI39: =AI8 -> 45871
B41: Current Assets
B42: Cash and cash equivalents | C42: 409251 | D42: 1046051 | E42: 431560 | F42: 737877 | G42: 766594 | H42: 703201 | J42: 654486 | K42: 434226 | L42: 250628 | M42: =F42 -> 737877 | N42: 636449 | O42: 388627 | P42: 121811 | Q42: =G42 -> 766594 | R42: 524596 | S42: 413962 | T42: 177782 | U42: =H42 -> 703201 | V42: 454629 | W42: 242745 | Y42: =M42 -> 737877 | Z42: =N42 -> 636449 | AA42: =O42 -> 388627 | AB42: =P42 -> 121811 | AC42: =Q42 -> 766594 | AD42: =R42 -> 524596 | AE42: =S42 -> 413962 | AF42: =T42 -> 177782 | ... AI42: =W42 -> 242745 | AK42: =SUM(AI42/AE42)-1 -> -0.4136056
B43: Receivables, net | C43: 136168 | D43: 193109 | E43: 233682 | F43: 199422 | G43: 207939 | H43: 223334 | J43: 192754 | K43: 180514 | L43: 200304 | M43: =F43 -> 199422 | N43: 190282 | O43: 174444 | P43: 202868 | Q43: =G43 -> 207939 | R43: 203463 | S43: 200863 | T43: 213621 | U43: =H43 -> 223334 | V43: 225146 | W43: 224412 | AE43: =S43 -> 200863 | AF43: =T43 -> 213621 | AG43: =U43 -> 223334 | AH43: =V43 -> 225146 | AI43: =W43 -> 224412
B44: Merchandise inventories, net | C44: 1214329 | D44: 1168215 | E44: 1499218 | F44: 1603451 | G44: 1742136 | H44: 1968214 | J44: 1570552 | K44: 1666130 | L44: 2114669 | M44: =F44 -> 1603451 | N44: 1751235 | O44: 1815539 | P44: 2321306 | Q44: =G44 -> 1742136 | R44: 1906040 | S44: 1998286 | T44: 2365186 | U44: =H44 -> 1968214 | V44: 2121519 | W44: 2407051 | Y44: =M44 -> 1603451 | Z44: =N44 -> 1751235 | AA44: =O44 -> 1815539 | AB44: =P44 -> 2321306 | AC44: =Q44 -> 1742136 | AD44: =R44 -> 1906040 | AE44: =S44 -> 1998286 | AF44: =T44 -> 2365186 | ... AI44: =W44 -> 2407051 | AK44: =SUM(AI44/AE44)-1 -> 0.20455781
B45: Prepaid expenses and other current assets | C45: 138116 | D45: 107402 | E45: 110814 | F45: 130246 | G45: 115598 | H45: 129113 | J45: 114075 | K45: 123014 | L45: 137642 | M45: =F45 -> 130246 | N45: 108014 | O45: 110524 | P45: 117282 | Q45: =G45 -> 115598 | R45: 126529 | S45: 132023 | T45: 135514 | U45: =H45 -> 129113 | V45: 138396 | W45: 165963 | Y45: =M45 -> 130246 | Z45: =N45 -> 108014 | AA45: =O45 -> 110524 | AB45: =P45 -> 117282 | AC45: =Q45 -> 115598 | AD45: =R45 -> 126529 | AE45: =S45 -> 132023 | AF45: =T45 -> 135514 | ... AI45: =W45 -> 165963 | AK45: =SUM(AI45/AE45)-1 -> 0.25707642
B46: Prepaid income taxes | C46: 16997 | D46: 0 | E46: 5909 | F46: 38308 | G46: 4251 | H46: 4946 | J46: 0 | K46: 39029 | L46: 42572 | M46: =F46 -> 38308 | N46: 0 | O46: 30114 | P46: 28773 | Q46: =G46 -> 4251 | R46: 0 | S46: 53607 | T46: 62759 | U46: =H46 -> 4946 | V46: 0 | W46: 28877 | Y46: =M46 -> 38308 | Z46: =N46 -> 0 | AA46: =O46 -> 30114 | AB46: =P46 -> 28773 | AC46: =Q46 -> 4251 | AD46: =R46 -> 0 | AE46: =S46 -> 53607 | AF46: =T46 -> 62759 | ... AI46: =W46 -> 28877 | AK46: =SUM(AI46/AE46)-1 -> -0.46132035
B47: Total Current Assets | C47: =SUM(C42:C46) -> 1914861 | D47: =SUM(D42:D46) -> 2514777 | E47: =SUM(E42:E46) -> 2281183 | F47: =SUM(F42:F46) -> 2709304 | G47: =SUM(G42:G46) -> 2836518 | H47: =SUM(H42:H46) -> 3028808 | J47: =SUM(J42:J46) -> 2531867 | K47: =SUM(K42:K46) -> 2442913 | L47: =SUM(L42:L46) -> 2745815 | M47: =SUM(M42:M46) -> 2709304 | N47: =SUM(N42:N46) -> 2685980 | O47: =SUM(O42:O46) -> 2519248 | P47: =SUM(P42:P46) -> 2792040 | Q47: =SUM(Q42:Q46) -> 2836518 | ... W47: =SUM(W42:W46) -> 3069048 | Y47: =SUM(Y42:Y46) -> 2509882 | Z47: =SUM(Z42:Z46) -> 2495698 | AA47: =SUM(AA42:AA46) -> 2344804 | AB47: =SUM(AB42:AB46) -> 2589172 | AC47: =SUM(AC42:AC46) -> 2628579 | AD47: =SUM(AD42:AD46) -> 2557165 | AE47: =SUM(AE42:AE46) -> 2798741 | AF47: =SUM(AF42:AF46) -> 2954862 | ... AI47: =SUM(AI42:AI46) -> 3069048 | AK47: =SUM(AI47/AE47)-1 -> 0.096581642
B49: Non-Current Assets
B50: Property and equipment, net | C50: 1226029 | D50: 995795 | E50: 914476 | F50: 1009273 | G50: 1182335 | H50: 1239295 | J50: 909543 | K50: 912017 | L50: 967039 | M50: =F50 -> 1009273 | N50: 1019978 | O50: 1073144 | P50: 1117874 | Q50: =G50 -> 1182335 | R50: 1195658 | S50: 1225850 | T50: 1264419 | U50: =H50 -> 1239295 | V50: 1251287 | W50: 1332503 | Y50: =M50 -> 1009273 | Z50: =N50 -> 1019978 | AA50: =O50 -> 1073144 | AB50: =P50 -> 1117874 | AC50: =Q50 -> 1182335 | AD50: =R50 -> 1195658 | AE50: =S50 -> 1225850 | AF50: =T50 -> 1264419 | ... AI50: =W50 -> 1332503 | AK50: =SUM(AI50/AE50)-1 -> 0.087003304
B51: Operating lease assets | C51: 0 | D51: 1504614 | E51: 1482256 | F51: 1561263 | G51: 1574530 | H51: 1609870 | J51: 1488040 | K51: 1509246 | L51: 1556940 | M51: =F51 -> 1561263 | N51: 1559560 | O51: 1549146 | P51: 1578316 | Q51: =G51 -> 1574530 | R51: 1561767 | S51: 1599735 | T51: 1619055 | U51: =H51 -> 1609870 | V51: 1658834 | W51: 1682151 | Y51: =N51 -> 1559560 | Z51: =O51 -> 1549146 | AA51: =P51 -> 1578316 | AB51: =Q51 -> 1574530 | AC51: =R51 -> 1561767 | AD51: =S51 -> 1599735 | AE51: =S51 -> 1599735 | AF51: =T51 -> 1619055 | AG51: =U51 -> 1609870 | AH51: =V51 -> 1658834 | AI51: =W51 -> 1682151 | AK51: =SUM(AI51/AE51)-1 -> 0.051518533
B52: Goodwill | C52: 10870 | D52: 10870 | E52: 10870 | F52: 10870 | G52: 10870 | H52: 10870 | J52: 10870 | K52: 10870 | L52: 10870 | M52: =F52 -> 10870 | N52: 10870 | O52: 10870 | P52: 10870 | Q52: =G52 -> 10870 | R52: 10870 | S52: 10870 | T52: 10870 | U52: =H52 -> 10870 | V52: 10870 | W52: 392606 | Y52: =N52 -> 10870 | Z52: =O52 -> 10870 | AA52: =P52 -> 10870 | AB52: =Q52 -> 10870 | AC52: =R52 -> 10870 | AD52: =S52 -> 10870 | AE52: =S52 -> 10870 | AF52: =T52 -> 10870 | AG52: =U52 -> 10870 | AH52: =V52 -> 10870 | AI52: =W52 -> 392606 | AK52: =SUM(AI52/AE52)-1 -> 35.118307
B53: Other intangible assets, net | C53: 4317 | D53: 2465 | E53: 1538 | F53: 1312 | G53: 510 | H53: 204 | J53: 1307 | K53: 1075 | L53: 844 | M53: =F53 -> 1312 | N53: 1015 | O53: 718 | P53: 591 | Q53: =G53 -> 510 | R53: 434 | S53: 357 | T53: 281 | U53: =H53 -> 204 | V53: 0 | W53: 5466 | Y53: =N53 -> 1015 | Z53: =O53 -> 718 | AA53: =P53 -> 591 | AB53: =Q53 -> 510 | AC53: =R53 -> 434 | AD53: =S53 -> 357 | AE53: =S53 -> 357 | AF53: =T53 -> 281 | AG53: =U53 -> 204 | AH53: =V53 -> 0 | AI53: =W53 -> 5466 | AK53: =SUM(AI53/AE53)-1 -> 14.310924
B54: Deferred compensation plan assets | C54: 20511 | D54: 33223 | E54: 38409 | F54: 35382 | G54: 43516 | H54: 47951 | J54: 35978 | K54: 33393 | L54: 31529 | M54: =F54 -> 35382 | N54: 37002 | O54: 40087 | P54: 38371 | Q54: =G54 -> 43516 | R54: 45718 | S54: 46280 | T54: 48872 | U54: =H54 -> 47951 | V54: 47467 | W54: 50550 | Y54: =N54 -> 37002 | Z54: =O54 -> 40087 | AA54: =P54 -> 38371 | AB54: =Q54 -> 43516 | AC54: =R54 -> 45718 | AD54: =S54 -> 46280 | AE54: =S54 -> 46280 | AF54: =T54 -> 48872 | AG54: =U54 -> 47951 | AH54: =V54 -> 47467 | AI54: =W54 -> 50550 | AK54: =SUM(AI54/AE54)-1 -> 0.092264477
B55: Other long-term assets | C55: 14584 | D55: 28225 | E55: 35647 | F55: 43007 | G55: 58732 | H55: 64695 | J55: 34431 | K55: 36480 | L55: 18512 | M55: =F55 -> 43007 | N55: 61314 | O55: 55547 | P55: 56946 | Q55: =G55 -> 58732 | R55: 56864 | S55: 55575 | T55: 60127 | U55: =H55 -> 64695 | V55: 78541 | W55: 98324 | Y55: =N55 -> 61314 | Z55: =O55 -> 55547 | AA55: =P55 -> 56946 | AB55: =Q55 -> 58732 | AC55: =R55 -> 56864 | AD55: =S55 -> 55575 | AE55: =S55 -> 55575 | AF55: =T55 -> 60127 | AG55: =U55 -> 64695 | AH55: =V55 -> 78541 | AI55: =W55 -> 98324 | AK55: =SUM(AI55/AE55)-1 -> 0.76921278
B56: Total Assets | C56: =SUM(C50:C55)+C47 -> 3191172 | D56: =SUM(D50:D55)+D47 -> 5089969 | E56: =SUM(E50:E55)+E47 -> 4764379 | F56: =SUM(F50:F55)+F47 -> 5370411 | G56: =SUM(G50:G55)+G47 -> 5707011 | H56: =SUM(H50:H55)+H47 -> 6001693 | J56: =SUM(J50:J55)+J47 -> 5012036 | K56: =SUM(K50:K55)+K47 -> 4945994 | L56: =SUM(L50:L55)+L47 -> 5331549 | M56: =SUM(M50:M55)+M47 -> 5370411 | N56: =SUM(N50:N55)+N47 -> 5375719 | O56: =SUM(O50:O55)+O47 -> 5248760 | P56: =SUM(P50:P55)+P47 -> 5595008 | Q56: =SUM(Q50:Q55)+Q47 -> 5707011 | ... W56: =SUM(W50:W55)+W47 -> 6630648 | Y56: =SUM(Y50:Y55)+Y47 -> 5188916 | Z56: =SUM(Z50:Z55)+Z47 -> 5172044 | AA56: =SUM(AA50:AA55)+AA47 -> 5103042 | AB56: =SUM(AB50:AB55)+AB47 -> 5395204 | AC56: =SUM(AC50:AC55)+AC47 -> 5486567 | AD56: =SUM(AD50:AD55)+AD47 -> 5465640 | AE56: =SUM(AE50:AE55)+AE47 -> 5737408 | AF56: =SUM(AF50:AF55)+AF47 -> 5958486 | ... AI56: =SUM(AI50:AI55)+AI47 -> 6630648 | AK56: =SUM(AI56/AE56)-1 -> 0.15568703
B58: Current Liabilities
B59: Accounts payable | C59: 404016 | D59: 477052 | E59: 552730 | F59: 559527 | G59: 544001 | H59: 563761 | J59: 585500 | K59: 586851 | L59: 647117 | M59: =E59 -> 552730 | N59: 621272 | O59: 521315 | P59: 597373 | Q59: =G59 -> 544001 | R59: 463777 | S59: 566904 | T59: 593219 | U59: =H59 -> 563761 | V59: 537518 | W59: 708655 | Y59: =N59 -> 621272 | Z59: =O59 -> 521315 | AA59: =P59 -> 597373 | AB59: =Q59 -> 544001 | AC59: =R59 -> 463777 | AD59: =S59 -> 566904 | AE59: =S59 -> 566904 | AF59: =T59 -> 593219 | AG59: =U59 -> 563761 | AH59: =V59 -> 537518 | AI59: =W59 -> 708655 | AK59: =SUM(AI59/AE59)-1 -> 0.2500441
B60: Accrued liabilities | C60: 220666 | D60: 296334 | E60: 364797 | F60: 444278 | G60: 382468 | H60: 380241 | J60: 305000 | K60: 323939 | L60: 462773 | M60: =E60 -> 364797 | N60: 308583 | O60: 328247 | P60: 405443 | Q60: =G60 -> 382468 | R60: 332692 | S60: 348042 | T60: 333463 | U60: =H60 -> 380241 | V60: 346960 | W60: 460232 | Y60: =N60 -> 308583 | Z60: =O60 -> 328247 | AA60: =P60 -> 405443 | AB60: =Q60 -> 382468 | AC60: =R60 -> 332692 | AD60: =S60 -> 348042 | AE60: =S60 -> 348042 | AF60: =T60 -> 333463 | AG60: =U60 -> 380241 | AH60: =V60 -> 346960 | AI60: =W60 -> 460232 | AK60: =SUM(AI60/AE60)-1 -> 0.32234615
B61: Deferred revenue | C61: 199054 | D61: 274383 | E61: 353579 | F61: 394677 | G61: 436591 | H61: 500585 | J61: 324694 | K61: 316571 | L61: 312132 | M61: =E61 -> 353579 | N61: 357217 | O61: 354253 | P61: 350937 | Q61: =G61 -> 436591 | R61: 398729 | S61: 394987 | T61: 405040 | U61: =H61 -> 500585 | V61: 462843 | W61: 460232 | AE61: =S61 -> 394987 | AF61: =T61 -> 405040 | AG61: =U61 -> 500585 | AH61: =V61 -> 462843 | AI61: =W61 -> 460232 | AK61: =SUM(AI61/AE61)-1 -> 0.16518265
B62: Current operating lease liabilities | C62: 0 | D62: 253415 | E62: 274118 | F62: 283293 | G62: 283821 | H62: 288114 | J62: 276440 | K62: 274693 | L62: 275749 | M62: =E62 -> 274118 | N62: 288133 | O62: 287359 | P62: 287786 | Q62: =G62 -> 283821 | R62: 284815 | S62: 281301 | T62: 284985 | U62: =H62 -> 288114 | V62: 285764 | W62: 282593 | AE62: =S62 -> 281301 | AF62: =T62 -> 284985 | AG62: =U62 -> 288114 | AH62: =V62 -> 285764 | AI62: =W62 -> 282593 | AK62: =SUM(AI62/AE62)-1 -> 0.0045929449
B63: Accrued income taxes | C63: 0 | D63: 42529 | E63: 12786 | F63: 0 | G63: 11310 | H63: 46777 | J63: 108113 | K63: 0 | L63: 0 | M63: =E63 -> 12786 | N63: 58695 | O63: 0 | P63: 0 | Q63: =G63 -> 11310 | R63: 92711 | S63: 0 | T63: 0 | U63: =H63 -> 46777 | V63: 130765 | W63: 0 | Y63: =N63 -> 58695 | Z63: =O63 -> 0 | AA63: =P63 -> 0 | AB63: =Q63 -> 11310 | AC63: =R63 -> 92711 | AD63: =S63 -> 0 | AE63: =S63 -> 0 | AF63: =T63 -> 0 | AG63: =U63 -> 46777 | AH63: =V63 -> 130765 | AI63: =W63 -> 0 | AK63: =SUM(AI63/AE63)-1 -> #DIV/0!
B64: Short-term debt | C64: 0 | D64: 0 | E64: 0 | F64: 0 | G64: 0 | H64: 0 | J64: 0 | K64: 0 | L64: 0 | M64: =E64 -> 0 | N64: 0 | O64: 0 | P64: 195400 | Q64: =G64 -> 0 | R64: 0 | S64: 0 | T64: 199700 | U64: =H64 -> 0 | V64: 0 | W64: 289101 | Y64: =N64 -> 0 | Z64: =O64 -> 0 | AA64: =P64 -> 195400 | AB64: =Q64 -> 0 | AC64: =R64 -> 0 | AD64: =S64 -> 0 | AE64: =S64 -> 0 | AF64: =T64 -> 199700 | AG64: =U64 -> 0 | AH64: =V64 -> 0 | AI64: =W64 -> 289101 | AK64: =SUM(AI64/AE64)-1 -> #DIV/0!
B65: Total Current Liabilities | C65: =SUM(C59:C64) -> 823736 | D65: =SUM(D59:D64) -> 1343713 | E65: =SUM(E59:E64) -> 1558010 | F65: =SUM(F59:F64) -> 1681775 | G65: =SUM(G59:G64) -> 1658191 | H65: =SUM(H59:H64) -> 1779478 | J65: =SUM(J59:J64) -> 1599747 | K65: =SUM(K59:K64) -> 1502054 | L65: =SUM(L59:L64) -> 1697771 | M65: =SUM(M59:M64) -> 1558010 | N65: =SUM(N59:N64) -> 1633900 | O65: =SUM(O59:O64) -> 1491174 | P65: =SUM(P59:P64) -> 1836939 | Q65: =SUM(Q59:Q64) -> 1658191 | ... W65: =SUM(W59:W64) -> 2200813 | Y65: =SUM(Y59:Y64) -> 988550 | Z65: =SUM(Z59:Z64) -> 849562 | AA65: =SUM(AA59:AA64) -> 1198216 | AB65: =SUM(AB59:AB64) -> 937779 | AC65: =SUM(AC59:AC64) -> 889180 | AD65: =SUM(AD59:AD64) -> 914946 | AE65: =SUM(AE59:AE64) -> 1591234 | AF65: =SUM(AF59:AF64) -> 1816407 | ... AI65: =SUM(AI59:AI64) -> 2200813 | AK65: =SUM(AI65/AE65)-1 -> 0.38308571
B67: Non-Current Liabilities
B68: Non-current operating lease liabilities | C68: 0 | D68: 1643386 | E68: 1572638 | F68: 1619883 | G68: 1627271 | H68: 1635120 | J68: 1568356 | K68: 1582003 | L68: 1621252 | M68: =E68 -> 1572638 | N68: 1610256 | O68: 1593040 | P68: 1616747 | Q68: =G68 -> 1627271 | R68: 1607953 | S68: 1647698 | T68: 1656317 | U68: =H68 -> 1635120 | V68: 1689439 | W68: 1716133 | Y68: =N68 -> 1610256 | Z68: =O68 -> 1593040 | AA68: =P68 -> 1616747 | AB68: =Q68 -> 1627271 | AC68: =R68 -> 1607953 | AD68: =S68 -> 1647698 | AE68: =S68 -> 1647698 | AF68: =T68 -> 1656317 | AG68: =U68 -> 1635120 | AH68: =V68 -> 1689439 | AI68: =W68 -> 1716133 | AK68: =SUM(AI68/AE68)-1 -> 0.041533703
B69: Deferred income taxes | C69: 83864 | D69: 65359 | E69: 39693 | F69: 55346 | G69: 85921 | H69: 42593 | J69: 40702 | K69: 40029 | L69: 38627 | M69: =E69 -> 39693 | N69: 57490 | O69: 56012 | P69: 56874 | Q69: =G69 -> 85921 | R69: 89556 | S69: 88461 | T69: 91729 | U69: =H69 -> 42593 | V69: 46013 | W69: 49158 | Y69: =N69 -> 57490 | Z69: =O69 -> 56012 | AA69: =P69 -> 56874 | AB69: =Q69 -> 85921 | AC69: =R69 -> 89556 | AD69: =S69 -> 88461 | AE69: =S69 -> 88461 | AF69: =T69 -> 91729 | AG69: =U69 -> 42593 | AH69: =V69 -> 46013 | AI69: =W69 -> 49158 | AK69: =SUM(AI69/AE69)-1 -> -0.44429749
B70: Other long-term liabilities | C70: 455340 | D70: 41523 | E70: 62528 | F70: 58806 | G70: 61318 | H70: 56149 | J70: 57611 | K70: 52840 | L70: 51644 | M70: =E70 -> 62528 | N70: 56005 | O70: 56657 | P70: 55906 | Q70: =G70 -> 61318 | R70: 60963 | S70: 61855 | T70: 65024 | U70: =H70 -> 56149 | V70: 57084 | W70: 60729 | AE70: =S70 -> 61855 | AF70: =T70 -> 65024 | AG70: =U70 -> 56149 | AH70: =V70 -> 57084 | AI70: =W70 -> 60729 | AK70: =SUM(AI70/AE70)-1 -> -0.018203864
B71: Total Liabilities | C71: =SUM(C68:C70)+C65 -> 1362940 | D71: =SUM(D68:D70)+D65 -> 3093981 | E71: =SUM(E68:E70)+E65 -> 3232869 | F71: =SUM(F68:F70)+F65 -> 3415810 | G71: =SUM(G68:G70)+G65 -> 3432701 | H71: =SUM(H68:H70)+H65 -> 3513340 | J71: =SUM(J68:J70)+J65 -> 3266416 | K71: =SUM(K68:K70)+K65 -> 3176926 | L71: =SUM(L68:L70)+L65 -> 3409294 | M71: =SUM(M68:M70)+M65 -> 3232869 | N71: =SUM(N68:N70)+N65 -> 3357651 | O71: =SUM(O68:O70)+O65 -> 3196883 | P71: =SUM(P68:P70)+P65 -> 3566466 | Q71: =SUM(Q68:Q70)+Q65 -> 3432701 | ... W71: =SUM(W68:W70)+W65 -> 4026833 | Y71: =SUM(Y68:Y70)+Y65 -> 2656296 | Z71: =SUM(Z68:Z70)+Z65 -> 2498614 | AA71: =SUM(AA68:AA70)+AA65 -> 2871837 | AB71: =SUM(AB68:AB70)+AB65 -> 2650971 | AC71: =SUM(AC68:AC70)+AC65 -> 2586689 | AD71: =SUM(AD68:AD70)+AD65 -> 2651105 | AE71: =SUM(AE68:AE70)+AE65 -> 3389248 | AF71: =SUM(AF68:AF70)+AF65 -> 3629477 | ... AI71: =SUM(AI68:AI70)+AI65 -> 4026833 | AK71: =SUM(AI71/AE71)-1 -> 0.1881199
B73: Common stock | C73: 592 | D73: 569 | E73: 530 | F73: 511 | G73: 491 | H73: 468 | J73: 528 | K73: 521 | L73: 517 | M73: =E73 -> 530 | N73: 507 | O73: 501 | P73: 495 | Q73: =G73 -> 491 | R73: 487 | S73: 481 | T73: 474 | U73: =H73 -> 468 | V73: 459 | W73: 458 | Y73: =N73 -> 507 | Z73: =O73 -> 501 | AA73: =P73 -> 495 | AB73: =Q73 -> 491 | AC73: =R73 -> 487 | AD73: =S73 -> 481 | AE73: =S73 -> 481 | AF73: =T73 -> 474 | AG73: =U73 -> 468 | AH73: =V73 -> 459 | AI73: =W73 -> 458 | AK73: =SUM(AI73/AE73)-1 -> -0.047817048
B74: Treasury stock-common, at cost | C74: -24908 | D74: -37801 | E74: -53478 | F74: -60470 | G74: -83032 | H74: -106793 | J74: -58650 | K74: -59803 | L74: -60218 | M74: =E74 -> -53478 | N74: -82129 | O74: -82229 | P74: -82798 | Q74: =G74 -> -83032 | R74: -106315 | S74: -106491 | T74: -106598 | U74: =H74 -> -106793 | V74: -119704 | W74: -120031 | AE74: =S74 -> -106491 | AF74: =T74 -> -106598 | AG74: =U74 -> -106793 | AH74: =V74 -> -119704 | AI74: =W74 -> -120031 | AK74: =SUM(AI74/AE74)-1 -> 0.1271469
B75: Additional paid-in capital | C75: 738671 | D75: 847303 | E75: 934945 | F75: 1023997 | G75: 1075104 | H75: 1120769 | J75: 951802 | K75: 982339 | L75: 998816 | M75: =E75 -> 934945 | N75: 1040378 | O75: 1049679 | P75: 1058969 | Q75: =G75 -> 1075104 | R75: 1091822 | S75: 1099197 | T75: 1104952 | U75: =H75 -> 1120769 | V75: 1129309 | W75: 1151858 | AE75: =S75 -> 1099197 | AF75: =T75 -> 1104952 | AG75: =U75 -> 1120769 | AH75: =V75 -> 1129309 | AI75: =W75 -> 1151858 | AK75: =SUM(AI75/AE75)-1 -> 0.04790861
B76: Retained earnings | C76: 1105863 | D76: 1189422 | E76: 653376 | F76: 995773 | G76: 1286765 | H76: 1473909 | J76: 851940 | K76: 846011 | L76: 983140 | M76: =E76 -> 653376 | N76: 1059312 | O76: 1083926 | P76: 1051876 | Q76: =G76 -> 1286765 | R76: 1314749 | S76: 1354973 | T76: 1330181 | U76: =H76 -> 1473909 | V76: 1420239 | W76: 1571575 | Y76: =N76 -> 1059312 | Z76: =O76 -> 1083926 | AA76: =P76 -> 1051876 | AB76: =Q76 -> 1286765 | AC76: =R76 -> 1314749 | AD76: =S76 -> 1354973 | AE76: =S76 -> 1354973 | AF76: =T76 -> 1330181 | AG76: =U76 -> 1473909 | AH76: =V76 -> 1420239 | AI76: =W76 -> 1571575 | AK76: =SUM(AI76/AE76)-1 -> 0.15985706
B77: Total stockholders' equity | C77: =SUM(C73:C76) -> 1820218 | D77: =SUM(D73:D76) -> 1999493 | E77: =SUM(E73:E76) -> 1535373 | F77: =SUM(F73:F76) -> 1959811 | G77: =SUM(G73:G76) -> 2279328 | H77: =SUM(H73:H76) -> 2488353 | J77: =SUM(J73:J76) -> 1745620 | K77: =SUM(K73:K76) -> 1769068 | L77: =SUM(L73:L76) -> 1922255 | M77: =SUM(M73:M76) -> 1535373 | N77: =SUM(N73:N76) -> 2018068 | O77: =SUM(O73:O76) -> 2051877 | P77: =SUM(P73:P76) -> 2028542 | Q77: =SUM(Q73:Q76) -> 2279328 | ... W77: =SUM(W73:W76) -> 2603860 | Y77: =SUM(Y73:Y76) -> 1059819 | Z77: =SUM(Z73:Z76) -> 1084427 | AA77: =SUM(AA73:AA76) -> 1052371 | AB77: =SUM(AB73:AB76) -> 1287256 | AC77: =SUM(AC73:AC76) -> 1315236 | AD77: =SUM(AD73:AD76) -> 1355454 | AE77: =SUM(AE73:AE76) -> 2348160 | AF77: =SUM(AF73:AF76) -> 2329009 | ... AI77: =SUM(AI73:AI76) -> 2603860 | AK77: =SUM(AI77/AE77)-1 -> 0.10889377
B78: Total liabilities and stockholders' equity | C78: =SUM(C77+C71) -> 3183158 | D78: =SUM(D77+D71) -> 5093474 | E78: =SUM(E77+E71) -> 4768242 | F78: =SUM(F77+F71) -> 5375621 | G78: =SUM(G77+G71) -> 5712029 | H78: =SUM(H77+H71) -> 6001693 | J78: =SUM(J77+J71) -> 5012036 | K78: =SUM(K77+K71) -> 4945994 | L78: =SUM(L77+L71) -> 5331549 | M78: =SUM(M77+M71) -> 4768242 | N78: =SUM(N77+N71) -> 5375719 | O78: =SUM(O77+O71) -> 5248760 | P78: =SUM(P77+P71) -> 5595008 | Q78: =SUM(Q77+Q71) -> 5712029 | ... W78: =SUM(W77+W71) -> 6630693 | Y78: =SUM(Y77+Y71) -> 3716115 | Z78: =SUM(Z77+Z71) -> 3583041 | AA78: =SUM(AA77+AA71) -> 3924208 | AB78: =SUM(AB77+AB71) -> 3938227 | AC78: =SUM(AC77+AC71) -> 3901925 | AD78: =SUM(AD77+AD71) -> 4006559 | AE78: =SUM(AE77+AE71) -> 5737408 | AF78: =SUM(AF77+AF71) -> 5958486 | ... AI78: =SUM(AI77+AI71) -> 6630693 | AK78: =SUM(AI78/AE78)-1 -> 0.15569487
B80: Balance Check | C80: =C78-C56 -> -8014 | D80: =D78-D56 -> 3505 | E80: =E78-E56 -> 3863 | F80: =F78-F56 -> 5210 | G80: =G78-G56 -> 5018 | H80: =H78-H56 -> 0 | J80: =J78-J56 -> 0 | K80: =K78-K56 -> 0 | L80: =L78-L56 -> 0 | M80: =M78-M56 -> -602169 | N80: =N78-N56 -> 0 | O80: =O78-O56 -> 0 | P80: =P78-P56 -> 0 | Q80: =Q78-Q56 -> 5018 | ... W80: =W78-W56 -> 45 | Y80: =Y78-Y56 -> -1472801 | Z80: =Z78-Z56 -> -1589003 | AA80: =AA78-AA56 -> -1178834 | AB80: =AB78-AB56 -> -1456977 | AC80: =AC78-AC56 -> -1584642 | AD80: =AD78-AD56 -> -1459081 | AE80: =AE78-AE56 -> 0 | AF80: =AF78-AF56 -> 0 | ... AI80: =AI78-AI56 -> 45
B82: 1) Prepaid expenses and other current assets consists of: Prepaid expenses and other current assets + Forward contracts + Deferred offering costs.
A84: X | B84: Cash-Flows Statement | C84: FYE | F84: FYE | J84: Quarterly | T84: Quarterly | AE84: LTM | AK84: Variance
B85: =B7 -> Fiscal Period | C85: =C7 -> 2019 | D85: =D7 -> 2020 | E85: =E7 -> 2021 | F85: =F7 -> 2022 | G85: =G7 -> 2023 | H85: =H7 -> 2024 | J85: =J7 -> 1Q22 | K85: =K7 -> 2Q22 | L85: =L7 -> 3Q22 | M85: =M7 -> 4Q22 | N85: =N7 -> 1Q23 | O85: =O7 -> 2Q23 | P85: =P7 -> 3Q23 | Q85: =Q7 -> 4Q23 | ... W85: =W7 -> 2Q25 | Y85: =Y7 -> 4Q22 | Z85: =Z7 -> 1Q23 | AA85: =AA7 -> 2Q23 | AB85: =AB7 -> 3Q23 | AC85: =AC7 -> 4Q23 | AD85: =AD7 -> 1Q24 | AE85: =AE7 -> 2Q24 | AF85: =AF7 -> 3Q24 | ... AI85: =AI7 -> 2Q25
B86: =B8 -> Fiscal Period End Date | C86: =C8 -> 43497 | D86: =D8 -> 43861 | E86: =E8 -> 44225 | F86: =F8 -> 44954 | G86: =G8 -> 45325 | H86: =H8 -> 45689 | J86: =J8 -> 44681 | K86: =K8 -> 44772 | L86: =L8 -> 44863 | M86: =M8 -> 44954 | N86: =N8 -> 45045 | O86: =O8 -> 45136 | P86: =P8 -> 45227 | Q86: =Q8 -> 45325 | ... W86: =W8 -> 45871 | Y86: =Y8 -> 44954 | Z86: =Z8 -> 45045 | AA86: =AA8 -> 45136 | AB86: =AB8 -> 45227 | AC86: =AC8 -> 45325 | AD86: =AD8 -> 45416 | AE86: =AE8 -> 45507 | AF86: =AF8 -> 45598 | ... AI86: =AI8 -> 45871
B88: Cash-Flows From Operating Activities
B89: Net income (loss) | C89: =C28 -> 705945 | D89: =D28 -> 114315.47 | E89: =E28 -> 989163 | F89: =F28 -> 1232540 | G89: =G28 -> 1255761 | H89: =H28 -> 1201118 | J89: =J28 -> 331395 | K89: =K28 -> 295677 | L89: =L28 -> 274585 | M89: =M28 -> 330883 | N89: =N28 -> 347051 | O89: =O28 -> 300102 | P89: =P28 -> 249483 | Q89: =SUM(G89-SUM(N89:P89)) -> 359125 | R89: =R28 -> 313113 | S89: =S28 -> 252556 | T89: =T28 -> 238831 | U89: =SUM(H89-SUM(R89:T89)) -> 396618 | V89: =V28 -> 305680 | W89: =W28 -> 261472 | Y89: =SUM(K89:N89) -> 1248196 | Z89: =SUM(L89:O89) -> 1252621 | AA89: =SUM(M89:P89) -> 1227519 | AB89: =SUM(N89:Q89) -> 1255761 | AC89: =SUM(O89:R89) -> 1221823 | AD89: =SUM(P89:S89) -> 1174277 | AE89: =SUM(P89:S89) -> 1174277 | AF89: =SUM(Q89:T89) -> 1163625 | AG89: =SUM(R89:U89) -> 1201118 | AH89: =SUM(S89:V89) -> 1193685 | AI89: =SUM(T89:W89) -> 1202601 | AK89: =SUM(AI89/AE89)-1 -> 0.024120374
B91: Adjustments to reconcile net income:
B92: Depreciation and amortization | C92: 295599 | D92: 297772 | E92: 268460 | F92: 241372 | G92: 243840 | H92: 267042 | J92: 62839 | K92: =123721-J92 -> 60882 | L92: =182182-K92-J92 -> 58461 | M92: =SUM(F92-SUM(J92:L92)) -> 59190 | N92: 57949 | O92: =119862-N92 -> 61913 | P92: =181273-O92-N92 -> 61411 | Q92: =SUM(G92-SUM(N92:P92)) -> 62567 | R92: 64739 | S92: =130053-R92 -> 65314 | T92: =197075-S92-R92 -> 67022 | U92: =SUM(H92-SUM(R92:T92)) -> 69967 | V92: 72033 | W92: =143198-V92 -> 71165 | Y92: =SUM(K92:N92) -> 236482 | Z92: =SUM(L92:O92) -> 237513 | AA92: =SUM(M92:P92) -> 240463 | AB92: =SUM(N92:Q92) -> 243840 | AC92: =SUM(O92:R92) -> 250630 | AD92: =SUM(P92:S92) -> 254031 | AE92: =SUM(P92:S92) -> 254031 | AF92: =SUM(Q92:T92) -> 259642 | AG92: =SUM(R92:U92) -> 267042 | AH92: =SUM(S92:V92) -> 274336 | AI92: =SUM(T92:W92) -> 280187 | AK92: =SUM(AI92/AE92)-1 -> 0.10296381
B93: Non-cash lease expense | C93: 278820 | D93: 268071 | E93: 276229 | F93: 301912 | G93: 332754 | H93: 310636 | J93: 72192 | K93: =146251-J93 -> 74059 | L93: =222548-K93-J93 -> 76297 | M93: =SUM(F93-SUM(J93:L93)) -> 79364 | N93: 75478 | O93: =152867-N93 -> 77389 | P93: =232772-O93-N93 -> 79905 | Q93: =SUM(G93-SUM(N93:P93)) -> 99982 | R93: 77938 | S93: =163481-R93 -> 85543 | T93: =235950-S93-R93 -> 72469 | U93: =SUM(H93-SUM(R93:T93)) -> 74686 | V93: 91105 | W93: =183528-V93 -> 92423 | Y93: =SUM(K93:N93) -> 305198 | Z93: =SUM(L93:O93) -> 308528 | AA93: =SUM(M93:P93) -> 312136 | AB93: =SUM(N93:Q93) -> 332754 | AC93: =SUM(O93:R93) -> 335214 | AD93: =SUM(P93:S93) -> 343368 | AE93: =SUM(P93:S93) -> 343368 | AF93: =SUM(Q93:T93) -> 335932 | AG93: =SUM(R93:U93) -> 310636 | AH93: =SUM(S93:V93) -> 323803 | AI93: =SUM(T93:W93) -> 330683 | AK93: =SUM(AI93/AE93)-1 -> -0.036942872
B94: Deferred income taxes | C94: 5503 | D94: -24008 | E94: -25666 | F94: 15653 | G94: 30575 | H94: -43328 | J94: 1009 | K94: =336-J94 -> -673 | L94: =-1066-K94-J94 -> -1402 | M94: =SUM(F94-SUM(J94:L94)) -> 16719 | N94: 2144 | O94: =666-N94 -> -1478 | P94: =1528-O94-N94 -> 862 | Q94: =SUM(G94-SUM(N94:P94)) -> 29047 | R94: 3635 | S94: =2540-R94 -> -1095 | T94: =5808-S94-R94 -> 3268 | U94: =SUM(H94-SUM(R94:T94)) -> -49136 | V94: 3420 | W94: =2232-V94 -> -1188 | Y94: =SUM(K94:N94) -> 16788 | Z94: =SUM(L94:O94) -> 15983 | AA94: =SUM(M94:P94) -> 18247 | AB94: =SUM(N94:Q94) -> 30575 | AC94: =SUM(O94:R94) -> 32066 | AD94: =SUM(P94:S94) -> 32449 | AE94: =SUM(P94:S94) -> 32449 | AF94: =SUM(Q94:T94) -> 34855 | AG94: =SUM(R94:U94) -> -43328 | AH94: =SUM(S94:V94) -> -43543 | AI94: =SUM(T94:W94) -> -43636 | AK94: =SUM(AI94/AE94)-1 -> -2.3447564
B95: Stock-based compensation expense | C95: 25045 | D95: 27583 | E95: 47259 | F95: 43044 | G95: 48246 | H95: 42787 | J95: 10356 | K95: =22875-J95 -> 12519 | L95: =32554-K95-J95 -> 9679 | M95: =SUM(F95-SUM(J95:L95)) -> 10490 | N95: 9721 | O95: =21539-N95 -> 11818 | P95: =33477-O95-N95 -> 11938 | Q95: =SUM(G95-SUM(N95:P95)) -> 14769 | R95: 10082 | S95: =19272-R95 -> 9190 | T95: =27691-S95-R95 -> 8419 | U95: =SUM(H95-SUM(R95:T95)) -> 15096 | V95: 11418 | W95: =20338-V95 -> 8920 | Y95: =SUM(K95:N95) -> 42409 | Z95: =SUM(L95:O95) -> 41708 | AA95: =SUM(M95:P95) -> 43967 | AB95: =SUM(N95:Q95) -> 48246 | AC95: =SUM(O95:R95) -> 48607 | AD95: =SUM(P95:S95) -> 45979 | AE95: =SUM(P95:S95) -> 45979 | AF95: =SUM(Q95:T95) -> 42460 | AG95: =SUM(R95:U95) -> 42787 | AH95: =SUM(S95:V95) -> 44123 | AI95: =SUM(T95:W95) -> 43853 | AK95: =SUM(AI95/AE95)-1 -> -0.0462385
B96: Loss on disposal of property and equipment | C96: 5850 | D96: 6827 | E96: 5358 | F96: 6688 | G96: 11419 | H96: 11566 | J96: 1002 | K96: =2277-J96 -> 1275 | L96: =3892-K96-J96 -> 1615 | M96: =SUM(F96-SUM(J96:L96)) -> 2796 | N96: 1451 | O96: =3878-N96 -> 2427 | P96: =6310-O96-N96 -> 2432 | Q96: =SUM(G96-SUM(N96:P96)) -> 5109 | R96: 2975 | S96: =5204-R96 -> 2229 | T96: =7280-S96-R96 -> 2076 | U96: =SUM(H96-SUM(R96:T96)) -> 4286 | V96: 892 | W96: =4689-V96 -> 3797 | AE96: =SUM(P96:S96) -> 12745 | AF96: =SUM(Q96:T96) -> 12389 | AG96: =SUM(R96:U96) -> 11566 | AH96: =SUM(S96:V96) -> 9483 | AI96: =SUM(T96:W96) -> 11051 | AK96: =SUM(AI96/AE96)-1 -> -0.13291487
B97: Long-lived asset impairment charge | C97: 0 | D97: 72533 | E97: 0 | F97: 0 | G97: 0 | H97: 0 | J97: 0 | K97: 0 | L97: 0 | M97: =SUM(F97-SUM(J97:L97)) -> 0 | N97: 0 | O97: 0 | P97: 0 | Q97: =SUM(G97-SUM(N97:P97)) -> 0 | R97: 0 | S97: 0 | T97: 0 | U97: 0 | V97: 0 | W97: 0 | AE97: =SUM(P97:S97) -> 0 | AF97: =SUM(Q97:T97) -> 0 | AG97: =SUM(R97:U97) -> 0 | AH97: =SUM(S97:V97) -> 0 | AI97: =SUM(T97:W97) -> 0 | AK97: =SUM(AI97/AE97)-1 -> #DIV/0!
B98: Equity net loss of affiliate | C98: 0 | D98: 0 | E98: 0 | F98: 0 | G98: 0 | H98: 0 | J98: 0 | K98: 0 | L98: 0 | M98: 0 | N98: 0 | O98: 0 | P98: 0 | Q98: 0 | R98: 0 | S98: 0 | T98: 0 | U98: 0 | V98: 628 | W98: =1225-V98 -> 597 | AE98: =SUM(P98:S98) -> 0 | AF98: =SUM(Q98:T98) -> 0 | AG98: =SUM(R98:U98) -> 0 | AH98: =SUM(S98:V98) -> 628 | AI98: =SUM(T98:W98) -> 1225 | AK98: =SUM(AI98/AE98)-1 -> #DIV/0!
B100: Changes in assets and liabilities:
B101: Receivables | C101: -20637 | D101: -53772 | E101: -40573 | F101: 34260 | G101: -8517 | H101: -15395 | J101: 40928 | K101: =53168-J101 -> 12240 | L101: =33378-K101-J101 -> -19790 | M101: =SUM(F101-SUM(J101:L101)) -> 882 | N101: 9140 | O101: =24978-N101 -> 15838 | P101: =-3446-O101-N101 -> -28424 | Q101: =SUM(G101-SUM(N101:P101)) -> -5071 | R101: 4476 | S101: =7076-R101 -> 2600 | T101: =-5682-S101-R101 -> -12758 | U101: =SUM(H101-SUM(R101:T101)) -> -9713 | V101: -1812 | W101: =-198-V101 -> 1614 | Y101: =SUM(K101:N101) -> 2472 | Z101: =SUM(L101:O101) -> 6070 | AA101: =SUM(M101:P101) -> -2564 | AB101: =SUM(N101:Q101) -> -8517 | AC101: =SUM(O101:R101) -> -13181 | AD101: =SUM(P101:S101) -> -26419 | AE101: =SUM(P101:S101) -> -26419 | AF101: =SUM(Q101:T101) -> -10753 | AG101: =SUM(R101:U101) -> -15395 | AH101: =SUM(S101:V101) -> -21683 | AI101: =SUM(T101:W101) -> -22669 | AK101: =SUM(AI101/AE101)-1 -> -0.1419433
B102: Merchandise inventories | C102: -79372 | D102: 125486 | E102: -331003 | F102: -104233 | G102: -138685 | H102: -226078 | J102: -71334 | K102: =-166912-J102 -> -95578 | L102: =-615451-K102-J102 -> -448539 | M102: =SUM(F102-SUM(J102:L102)) -> 511218 | N102: -147784 | O102: =-212088-N102 -> -64304 | P102: =-717855-O102-N102 -> -505767 | Q102: =SUM(G102-SUM(N102:P102)) -> 579170 | R102: -163904 | S102: =-256150-R102 -> -92246 | T102: =-623050-S102-R102 -> -366900 | U102: =SUM(H102-SUM(R102:T102)) -> 396972 | V102: -153305 | W102: =-366091-V102 -> -212786 | Y102: =SUM(K102:N102) -> -180683 | Z102: =SUM(L102:O102) -> -149409 | AA102: =SUM(M102:P102) -> -206637 | AB102: =SUM(N102:Q102) -> -138685 | AC102: =SUM(O102:R102) -> -154805 | AD102: =SUM(P102:S102) -> -182747 | AE102: =SUM(P102:S102) -> -182747 | AF102: =SUM(Q102:T102) -> -43880 | AG102: =SUM(R102:U102) -> -226078 | AH102: =SUM(S102:V102) -> -215479 | AI102: =SUM(T102:W102) -> -336019 | AK102: =SUM(AI102/AE102)-1 -> 0.83871144
B103: Prepaid expenses and other current assets | C103: 9289 | D103: -4363 | E103: -3412 | F103: -19432 | G103: 14648 | H103: -13515 | J103: -3261 | K103: =-12200-J103 -> -8939 | L103: =-26828-K103-J103 -> -14628 | M103: =SUM(F103-SUM(J103:L103)) -> 7396 | N103: 22232 | O103: =19722-N103 -> -2510 | P103: =12964-O103-N103 -> -6758 | Q103: =SUM(G103-SUM(N103:P103)) -> 1684 | R103: -10931 | S103: =-16425-R103 -> -5494 | T103: =-19916-S103-R103 -> -3491 | U103: =SUM(H103-SUM(R103:T103)) -> 6401 | V103: -9283 | W103: =-21657-V103 -> -12374
B104: Income taxes | C104: 610 | D104: 58916 | E104: -35652 | F104: -45182 | G104: 45367 | H104: 34772 | J104: 101236 | K104: =-45906-J104 -> -147142 | L104: =-49446-K104-J104 -> -3540 | M104: =SUM(F104-SUM(J104:L104)) -> 4264 | N104: 97003 | O104: =8194-N104 -> -88809 | P104: =9535-O104-N104 -> 1341 | Q104: =SUM(G104-SUM(N104:P104)) -> 35832 | R104: 85652 | S104: =-60666-R104 -> -146318 | T104: =-69818-S104-R104 -> -9152 | U104: =SUM(H104-SUM(R104:T104)) -> 104590 | V104: 88934 | W104: =-70406-V104 -> -159340
B105: Accounts payable | C105: 9993 | D105: 62324 | E105: 66156 | F105: 8309 | G105: -20873 | H105: 30297 | J105: 42586 | K105: =40051-J105 -> -2535 | L105: =94214-K105-J105 -> 54163 | M105: =SUM(F105-SUM(J105:L105)) -> -85905 | N105: 62257 | O105: =-38752-N105 -> -101009 | P105: =41817-O105-N105 -> 80569 | Q105: =SUM(G105-SUM(N105:P105)) -> -62690 | R105: -74069 | S105: =29715-R105 -> 103784 | T105: =54210-S105-R105 -> 24495 | U105: =SUM(H105-SUM(R105:T105)) -> -23913 | V105: -24920 | W105: =98115-V105 -> 123035
B106: Accrued liabilities | C106: 28183 | D106: 58599 | E106: 58598 | F106: 48249 | G106: -62238 | H106: 6303 | J106: -57214 | K106: =-49364-J106 -> 7850 | L106: =64164-K106-J106 -> 113528 | M106: =SUM(F106-SUM(J106:L106)) -> -15915 | N106: -98515 | O106: =-102763-N106 -> -4248 | P106: =-34955-O106-N106 -> 67808 | Q106: =SUM(G106-SUM(N106:P106)) -> -27283 | R106: -43846 | S106: =-33634-R106 -> 10212 | T106: =-45777-S106-R106 -> -12143 | U106: =SUM(H106-SUM(R106:T106)) -> 52080 | V106: -32716 | W106: =-3881-V106 -> 28835 | Y106: =SUM(K106:N106) -> 6948 | Z106: =SUM(L106:O106) -> -5150 | AA106: =SUM(M106:P106) -> -50870 | AB106: =SUM(N106:Q106) -> -62238 | AC106: =SUM(O106:R106) -> -7569 | AD106: =SUM(P106:S106) -> 6891 | AE106: =SUM(P106:S106) -> 6891 | AF106: =SUM(Q106:T106) -> -73060 | AG106: =SUM(R106:U106) -> 6303 | AH106: =SUM(S106:V106) -> 17433 | AI106: =SUM(T106:W106) -> 36056 | AK106: =SUM(AI106/AE106)-1 -> 4.232332
B107: Deferred revenue | C107: 38481 | D107: 36848 | E107: 79196 | F107: 41098 | G107: 41914 | H107: 63994 | J107: -28885 | K107: =-37008-J107 -> -8123 | L107: =-41447-K107-J107 -> -4439 | M107: =SUM(F107-SUM(J107:L107)) -> 82545 | N107: -37460 | O107: =-40424-N107 -> -2964 | P107: =-43740-O107-N107 -> -3316 | Q107: =SUM(G107-SUM(N107:P107)) -> 85654 | R107: -37862 | S107: =-41604-R107 -> -3742 | T107: =-31551-S107-R107 -> 10053 | U107: =SUM(H107-SUM(R107:T107)) -> 95545 | V107: -37742 | W107: =-44418-V107 -> -6676 | Y107: =SUM(K107:N107) -> 32523 | Z107: =SUM(L107:O107) -> 37682 | AA107: =SUM(M107:P107) -> 38805 | AB107: =SUM(N107:Q107) -> 41914 | AC107: =SUM(O107:R107) -> 41512 | AD107: =SUM(P107:S107) -> 40734 | AE107: =SUM(P107:S107) -> 40734 | AF107: =SUM(Q107:T107) -> 54103 | AG107: =SUM(R107:U107) -> 63994 | AH107: =SUM(S107:V107) -> 64114 | AI107: =SUM(T107:W107) -> 61180 | AK107: =SUM(AI107/AE107)-1 -> 0.50193941
B108: Operating lease liabilities | C108: -256910 | D108: -297513 | E108: -303914 | F108: -324500 | G108: -338105 | H108: -333835 | J108: -79936 | K108: =-163302-J108 -> -83366 | L108: =-246988-K108-J108 -> -83686 | M108: =SUM(F108-SUM(J108:L108)) -> -77512 | N108: -78562 | O108: =-163527-N108 -> -84965 | P108: =-248469-O108-N108 -> -84942 | Q108: =SUM(G108-SUM(N108:P108)) -> -89636 | R108: -83500 | S108: =-170779-R108 -> -87279 | T108: =-250267-S108-R108 -> -79488 | U108: =SUM(H108-SUM(R108:T108)) -> -83568 | V108: -88100 | W108: =-180316-V108 -> -92216 | Y108: =SUM(K108:N108) -> -323126 | Z108: =SUM(L108:O108) -> -324725 | AA108: =SUM(M108:P108) -> -325981 | AB108: =SUM(N108:Q108) -> -338105 | AC108: =SUM(O108:R108) -> -343043 | AD108: =SUM(P108:S108) -> -345357 | AE108: =SUM(P108:S108) -> -345357 | AF108: =SUM(Q108:T108) -> -339903 | AG108: =SUM(R108:U108) -> -333835 | AH108: =SUM(S108:V108) -> -338435 | AI108: =SUM(T108:W108) -> -343372 | AK108: =SUM(AI108/AE108)-1 -> -0.0057476756
B109: Other assets and liabilities | C109: 54894 | D109: -783 | E109: 12392 | F109: -7731 | G109: -15084 | H109: 2241 | J109: 3390 | K109: =-392-J109 -> -3782 | L109: =20063-K109-J109 -> 20455 | M109: =SUM(F109-SUM(J109:L109)) -> -27794 | N109: -17204 | O109: =-12497-N109 -> 4707 | P109: =-9836-O109-N109 -> 2661 | Q109: =SUM(G109-SUM(N109:P109)) -> -5248 | R109: 10842 | S109: =15127-R109 -> 4285 | T109: =12240-S109-R109 -> -2887 | U109: =SUM(H109-SUM(R109:T109)) -> -9999 | V109: -5583 | W109: =-15742-V109 -> -10159 | Y109: =SUM(K109:N109) -> -28325 | Z109: =SUM(L109:O109) -> -19836 | AA109: =SUM(M109:P109) -> -37630 | AB109: =SUM(N109:Q109) -> -15084 | AC109: =SUM(O109:R109) -> 12962 | AD109: =SUM(P109:S109) -> 12540 | AE109: =SUM(P109:S109) -> 12540 | AF109: =SUM(Q109:T109) -> 6992 | AG109: =SUM(R109:U109) -> 2241 | AH109: =SUM(S109:V109) -> -14184 | AI109: =SUM(T109:W109) -> -28628 | AK109: =SUM(AI109/AE109)-1 -> -3.2829346
B110: Net cash used in operating activities | C110: =SUM(C89:C109) -> 1101293 | D110: =SUM(D89:D109) -> 748835.47 | E110: =SUM(E89:E109) -> 1062591 | F110: =SUM(F89:F109) -> 1472047 | G110: =SUM(G89:G109) -> 1441022 | H110: =SUM(H89:H109) -> 1338605 | J110: =SUM(J89:J109) -> 426303 | K110: =SUM(K89:K109) -> 114364 | L110: =SUM(L89:L109) -> 32759 | M110: =SUM(M89:M109) -> 898621 | N110: =SUM(N89:N109) -> 304901 | O110: =SUM(O89:O109) -> 123907 | P110: =SUM(P89:P109) -> -70797 | Q110: =SUM(Q89:Q109) -> 1083011 | ... W110: =SUM(W89:W109) -> 97119 | Y110: =SUM(Y89:Y109) -> 1358882 | Z110: =SUM(Z89:Z109) -> 1400985 | AA110: =SUM(AA89:AA109) -> 1257455 | AB110: =SUM(AB89:AB109) -> 1390461 | AC110: =SUM(AC89:AC109) -> 1424216 | AD110: =SUM(AD89:AD109) -> 1355746 | AE110: =SUM(AE89:AE109) -> 1368491 | AF110: =SUM(AF89:AF109) -> 1442402 | ... AI110: =SUM(AI89:AI109) -> 1192512 | AK110: =SUM(AI110/AE110)-1 -> -0.12859347
B112: Cash flows from investing activities:
B113: Capital expenditures | C113: -298534 | D113: -151866 | E113: -172187 | F113: -312126 | G113: -435267 | H113: -374458 | J113: -71076 | K113: =-120500-J113 -> -49424 | L113: =-203961-K113-J113 -> -83461 | M113: =SUM(F113-SUM(J113:L113)) -> -108165 | N113: -109766 | O113: =-204748-N113 -> -94982 | P113: =-311030-O113-N113 -> -106282 | Q113: =SUM(G113-SUM(N113:P113)) -> -124237 | R113: -91024 | S113: =-186301-R113 -> -95277 | T113: =-300536-S113-R113 -> -114235 | U113: =SUM(H113-SUM(R113:T113)) -> -73922 | V113: -79031 | W113: =-155988-V113 -> -76957 | Y113: =SUM(K113:N113) -> -350816 | Z113: =SUM(L113:O113) -> -396374 | AA113: =SUM(M113:P113) -> -419195 | AB113: =SUM(N113:Q113) -> -435267 | AC113: =SUM(O113:R113) -> -416525 | AD113: =SUM(P113:S113) -> -416820 | AE113: =SUM(P113:S113) -> -416820 | AF113: =SUM(Q113:T113) -> -424773 | AG113: =SUM(R113:U113) -> -374458 | AH113: =SUM(S113:V113) -> -362465 | AI113: =SUM(T113:W113) -> -344145 | AK113: =SUM(AI113/AE113)-1 -> -0.17435584
B114: Acquisitions, net of cash acquired | C114: 0 | D114: 0 | E114: 0 | F114: 0 | G114: 0 | H114: 0 | J114: 0 | K114: 0 | L114: 0 | M114: 0 | N114: 0 | O114: 0 | P114: 0 | Q114: 0 | R114: 0 | S114: 0 | T114: 0 | U114: 0 | V114: 0 | W114: =-386793-V114 -> -386793
B115: Other investments | C115: -172946 | D115: 103115 | E115: -4297 | F115: -2458 | G115: -6158 | H115: -8631 | J115: -797 | K115: =-1249-J115 -> -452 | L115: =-3068-K115-J115 -> -1819 | M115: =SUM(F115-SUM(J115:L115)) -> 610 | N115: -314 | O115: =-1687-N115 -> -1373 | P115: =-4870-O115-N115 -> -3183 | Q115: =SUM(G115-SUM(N115:P115)) -> -1288 | R115: -2563 | S115: =-5091-R115 -> -2528 | T115: =-6108-S115-R115 -> -1017 | U115: =SUM(H115-SUM(R115:T115)) -> -2523 | V115: -7346 | W115: =-17130-V115 -> -9784 | Y115: =SUM(K115:N115) -> -1975 | Z115: =SUM(L115:O115) -> -2896 | AA115: =SUM(M115:P115) -> -4260 | AB115: =SUM(N115:Q115) -> -6158 | AC115: =SUM(O115:R115) -> -8407 | AD115: =SUM(P115:S115) -> -9562 | AE115: =SUM(P115:S115) -> -9562 | AF115: =SUM(Q115:T115) -> -7396 | AG115: =SUM(R115:U115) -> -8631 | AH115: =SUM(S115:V115) -> -13414 | AI115: =SUM(T115:W115) -> -20670 | AK115: =SUM(AI115/AE115)-1 -> 1.1616817
B116: Net cash used in investing activities | C116: =SUM(C113:C115) -> -471480 | D116: =SUM(D113:D115) -> -48751 | E116: =SUM(E113:E115) -> -176484 | F116: =SUM(F113:F115) -> -314584 | G116: =SUM(G113:G115) -> -441425 | H116: =SUM(H113:H115) -> -383089 | J116: =SUM(J113:J115) -> -71873 | K116: =SUM(K113:K115) -> -49876 | L116: =SUM(L113:L115) -> -85280 | M116: =SUM(M113:M115) -> -107555 | N116: =SUM(N113:N115) -> -110080 | O116: =SUM(O113:O115) -> -96355 | P116: =SUM(P113:P115) -> -109465 | Q116: =SUM(Q113:Q115) -> -125525 | ... W116: =SUM(W113:W115) -> -473534 | Y116: =SUM(Y113:Y115) -> -352791 | Z116: =SUM(Z113:Z115) -> -399270 | AA116: =SUM(AA113:AA115) -> -423455 | AB116: =SUM(AB113:AB115) -> -441425 | AC116: =SUM(AC113:AC115) -> -424932 | AD116: =SUM(AD113:AD115) -> -426382 | AE116: =SUM(AE113:AE115) -> -426382 | AF116: =SUM(AF113:AF115) -> -432169 | ... AI116: =SUM(AI113:AI115) -> -364815 | AK116: =SUM(AI116/AE116)-1 -> -0.14439399
B118: Cash flows from financing activities:
B119: Borrowings from short-term debt | C119: 0 | D119: 0 | E119: 0 | F119: 0 | G119: 0 | H119: 0 | J119: 0 | K119: 0 | L119: 0 | M119: 0 | N119: 0 | O119: 0 | P119: 0 | Q119: 0 | R119: 0 | S119: 0 | T119: 0 | U119: 0 | V119: 0 | W119: =593641-V119 -> 593641 | AE119: =SUM(P119:S119) -> 0 | AF119: =SUM(Q119:T119) -> 0 | AG119: =SUM(R119:U119) -> 0 | AH119: =SUM(S119:V119) -> 0 | AI119: =SUM(T119:W119) -> 593641 | AK119: =SUM(AI119/AE119)-1 -> #DIV/0!
B120: Payments on short-term debt | C120: 0 | D120: 0 | E120: 0 | F120: 0 | G120: 0 | H120: 0 | J120: 0 | K120: 0 | L120: 0 | M120: 0 | N120: 0 | O120: 0 | P120: 0 | Q120: 0 | R120: 0 | S120: 0 | T120: 0 | U120: 0 | V120: 0 | W120: =-333100-V120 -> -333100 | AE120: =SUM(P120:S120) -> 0 | AF120: =SUM(Q120:T120) -> 0 | AG120: =SUM(R120:U120) -> 0 | AH120: =SUM(S120:V120) -> 0 | AI120: =SUM(T120:W120) -> -333100 | AK120: =SUM(AI120/AE120)-1 -> #DIV/0!
B121: Borrowings from credit facility | C121: 0 | D121: 0 | E121: 0 | F121: 0 | G121: 195400 | H121: 199700 | J121: 0 | K121: 0 | L121: 0 | M121: =SUM(F121-SUM(J121:L121)) -> 0 | N121: 0 | O121: 0 | P121: =195400-O121-N121 -> 195400 | Q121: 0 | R121: 0 | S121: 0 | T121: =199700-S121-R121 -> 199700 | U121: =SUM(H121-SUM(R121:T121)) -> 0 | V121: 0 | W121: 0
B122: Payments on credit facility | C122: 0 | D122: 0 | E122: 0 | F122: 0 | G122: -195400 | H122: -199700 | J122: 0 | K122: 0 | L122: 0 | M122: =SUM(F122-SUM(J122:L122)) -> 0 | N122: 0 | O122: 0 | P122: 0 | Q122: =SUM(G122-SUM(N122:P122)) -> -195400 | R122: 0 | S122: 0 | T122: 0 | U122: =SUM(H122-SUM(R122:T122)) -> -199700 | V122: 0 | W122: 0
B123: Proceeds from long-term debt | C123: 0 | D123: 800000 | E123: 0 | F123: 0 | G123: 0 | J123: 0 | K123: 0 | L123: 0 | M123: =SUM(F123-SUM(J123:L123)) -> 0 | N123: 0 | O123: 0 | P123: 0 | Q123: =SUM(G123-SUM(N123:P123)) -> 0 | R123: 0 | S123: 0 | T123: 0 | U123: =SUM(H123-SUM(R123:T123)) -> 0 | V123: 0 | W123: 0
...

Sheet Revenue Drivers
B2: Ulta Beauty Inc. (NASDAQ: ULTA) | C2: FYE | J2: Quarterly | R2: Quarterly | S2: Quarterly | Y2: LTM | AC2: LTM | AE2: LTM
B3: Segment Anaysis | C3: ='Historical Financials'!C7 -> 2019 | D3: ='Historical Financials'!D7 -> 2020 | E3: ='Historical Financials'!E7 -> 2021 | F3: ='Historical Financials'!F7 -> 2022 | G3: ='Historical Financials'!G7 -> 2023 | H3: ='Historical Financials'!H7 -> 2024 | J3: ='Historical Financials'!J7 -> 1Q22 | K3: ='Historical Financials'!K7 -> 2Q22 | L3: ='Historical Financials'!L7 -> 3Q22 | M3: ='Historical Financials'!M7 -> 4Q22 | N3: ='Historical Financials'!N7 -> 1Q23 | O3: ='Historical Financials'!O7 -> 2Q23 | P3: ='Historical Financials'!P7 -> 3Q23 | Q3: ='Historical Financials'!Q7 -> 4Q23 | ... W3: ='Historical Financials'!W7 -> 2Q25 | Y3: =N3 -> 1Q23 | Z3: =O3 -> 2Q23 | AA3: =P3 -> 3Q23 | AB3: =Q3 -> 4Q23 | AC3: =R3 -> 1Q24 | AD3: =S3 -> 2Q24 | AE3: =U3 -> 4Q24 | AF3: =V3 -> 1Q25 | AG3: =W3 -> 2Q25
B4: $ in thousands except per share | C4: ='Historical Financials'!C8 -> 43497 | D4: ='Historical Financials'!D8 -> 43861 | E4: ='Historical Financials'!E8 -> 44225 | F4: ='Historical Financials'!F8 -> 44954 | G4: ='Historical Financials'!G8 -> 45325 | H4: ='Historical Financials'!H8 -> 45689 | J4: ='Historical Financials'!J8 -> 44681 | K4: ='Historical Financials'!K8 -> 44772 | L4: ='Historical Financials'!L8 -> 44863 | M4: ='Historical Financials'!M8 -> 44954 | N4: ='Historical Financials'!N8 -> 45045 | O4: ='Historical Financials'!O8 -> 45136 | P4: ='Historical Financials'!P8 -> 45227 | Q4: ='Historical Financials'!Q8 -> 45325 | ... W4: ='Historical Financials'!W8 -> 45871 | Y4: =N4 -> 45045 | Z4: =O4 -> 45136 | AA4: =P4 -> 45227 | AB4: =Q4 -> 45325 | AC4: =R4 -> 45416 | AD4: =S4 -> 45507 | AE4: =U4 -> 45689 | AF4: =V4 -> 45780 | AG4: =W4 -> 45871
A6: X | B6: Revenue Segment Anaysis
B7: Cosmetics | C7: 3773014.7 | D7: 3075976.5 | E7: 3711282.3 | F7: 4287603.6 | G7: 4594994.2 | H7: 4405305.1 | J7: 1032196.4 | K7: 964787.46 | L7: 1029068.9 | M7: =SUM(F7-SUM(J7:L7)) -> 1261550.8 | N7: 1159075.7 | O7: 1011923.6 | P7: 1045351.9 | Q7: =SUM(G7-SUM(N7:P7)) -> 1378643 | R7: 1144856.2 | S7: 995313.93 | T7: 1037341 | U7: 1360171.4 | V7: 1139346.8 | W7: 1059618.2 | AE7: =SUM(R7:U7) -> 4537682.5 | AF7: =SUM(S7:V7) -> 4532173.1 | AG7: =SUM(T7:W7) -> 4596477.4
B8: Haircare products and styling tools | C8: 1405632.9 | D8: 1168871.1 | E8: 1726177.8 | F8: 2143801.8 | G8: 2129387.6 | H8: 2598000.4 | J8: 469180.2 | K8: 505364.86 | L8: 491146.53 | M8: =SUM(F8-SUM(J8:L8)) -> 678110.21 | N8: 474167.34 | O8: 531259.89 | P8: 472897.27 | Q8: =SUM(G8-SUM(N8:P8)) -> 651063.07 | R8: 517911.12 | S8: 510417.4 | T8: 506020 | U8: 802152.37 | V8: 712091.75 | W8: 697117.25 | AE8: =SUM(R8:U8) -> 2336500.9 | AF8: =SUM(S8:V8) -> 2530681.5 | AG8: =SUM(T8:W8) -> 2717381.4
B9: Skincare | C9: 854476.85 | D9: 710550.57 | E9: 1467251.1 | F9: 1735458.6 | G9: 2129387.6 | H9: 2146174.3 | J9: 422262.18 | K9: 390509.21 | L9: 374206.88 | M9: =SUM(F9-SUM(J9:L9)) -> 548480.33 | N9: 500509.97 | O9: 505961.8 | P9: 472897.27 | Q9: =SUM(G9-SUM(N9:P9)) -> 650018.53 | R9: 626945.04 | S9: 612500.88 | T9: 581923 | U9: 662647.61 | V9: 512706.06 | W9: 529809.11 | AE9: =SUM(R9:U9) -> 2484016.5 | AF9: =SUM(S9:V9) -> 2369777.5 | AG9: =SUM(T9:W9) -> 2287085.8
B10: Fragrance and bath | C10: 699117.43 | D10: 581359.56 | E10: 1208324.5 | F10: 1429201.2 | G10: 1681095.4 | H10: 1468435 | J10: 281508.12 | K10: 275653.56 | L10: 280655.16 | M10: =SUM(F10-SUM(J10:L10)) -> 591384.36 | N10: 316111.56 | O10: 303577.08 | P10: 323561.29 | Q10: =SUM(G10-SUM(N10:P10)) -> 737845.52 | R10: 272584.8 | S10: 280729.57 | T10: 253010 | U10: 453390.47 | V10: 313320.37 | W10: 334616.28 | AE10: =SUM(R10:U10) -> 1259714.8 | AF10: =SUM(S10:V10) -> 1300450.4 | AG10: =SUM(T10:W10) -> 1354337.1
B11: Services | C11: 369903.4 | D11: 307597.65 | E11: 258926.67 | F11: 306257.4 | G11: 336219.09 | H11: 451826.16 | J11: 70377.03 | K11: 91884.52 | L11: 93551.72 | M11: =SUM(F11-SUM(J11:L11)) -> 50444.13 | N11: 105370.52 | O11: 101192.36 | P11: 99557.32 | Q11: =SUM(G11-SUM(N11:P11)) -> 30098.89 | R11: 109033.92 | S11: 102083.48 | T11: 101204 | U11: 139504.76 | V11: 113934.68 | W11: 111538.76 | Y11: =SUM(K11:N11) -> 341250.89 | Z11: =SUM(L11:O11) -> 350558.73 | AA11: =SUM(M11:P11) -> 356564.33 | AB11: =SUM(N11:Q11) -> 336219.09 | AC11: =SUM(O11:R11) -> 339882.49 | AD11: =SUM(P11:S11) -> 340773.61 | AE11: =SUM(R11:U11) -> 451826.16 | AF11: =SUM(S11:V11) -> 456726.92 | AG11: =SUM(T11:W11) -> 466182.2
B12: Accessories and other | C12: 295922.72 | D12: 246078.12 | E12: 258926.67 | F12: 306257.4 | G12: 336219.09 | H12: 225913.08 | J12: 70377.03 | K12: 68913.39 | L12: 70163.79 | M12: =SUM(F12-SUM(J12:L12)) -> 96803.19 | N12: 79027.89 | O12: 75894.27 | P12: 74667.99 | Q12: =SUM(G12-SUM(N12:P12)) -> 106628.94 | R12: 54516.96 | S12: 51041.74 | T12: 50602 | U12: 69752.38 | V12: 56967.34 | W12: 55769.38 | Y12: =SUM(K12:N12) -> 314908.26 | Z12: =SUM(L12:O12) -> 321889.14 | AA12: =SUM(M12:P12) -> 326393.34 | AB12: =SUM(N12:Q12) -> 336219.09 | AC12: =SUM(O12:R12) -> 311708.16 | AD12: =SUM(P12:S12) -> 286855.63 | AE12: =SUM(R12:U12) -> 225913.08 | AF12: =SUM(S12:V12) -> 228363.46 | AG12: =SUM(T12:W12) -> 233091.1
B13: Total Net Revenue | C13: =SUM(C7:C12) -> 7398068 | D13: =SUM(D7:D12) -> 6090433.5 | E13: =SUM(E7:E12) -> 8630889 | F13: =SUM(F7:F12) -> 10208580 | G13: =SUM(G7:G12) -> 11207303 | H13: =SUM(H7:H12) -> 11295654 | J13: =SUM(J7:J12) -> 2345901 | K13: =SUM(K7:K12) -> 2297113 | L13: =SUM(L7:L12) -> 2338793 | M13: =SUM(M7:M12) -> 3226773 | N13: =SUM(N7:N12) -> 2634263 | O13: =SUM(O7:O12) -> 2529809 | P13: =SUM(P7:P12) -> 2488933 | Q13: =SUM(Q7:Q12) -> 3554298 | ... W13: =SUM(W7:W12) -> 2788469 | Y13: =SUM(Y11:Y12) -> 656159.15 | Z13: =SUM(Z11:Z12) -> 672447.87 | AA13: =SUM(AA11:AA12) -> 682957.67 | AB13: =SUM(AB11:AB12) -> 672438.18 | AC13: =SUM(AC11:AC12) -> 651590.65 | AD13: =SUM(AD11:AD12) -> 627629.24 | AE13: =SUM(AE11:AE12) -> 677739.24 | AF13: =SUM(AF11:AF12) -> 685090.38 | AG13: =SUM(AG11:AG12) -> 699273.3
B14: Balance Check | C14: =C13-'Historical Financials'!C11 -> 0 | D14: =D13-'Historical Financials'!D11 -> 0 | E14: =E13-'Historical Financials'!E11 -> 0 | F14: =F13-'Historical Financials'!F11 -> 0 | G14: =G13-'Historical Financials'!G11 -> 0 | H14: =H13-'Historical Financials'!H11 -> 0 | J14: =J13-'Historical Financials'!J11 -> 0 | K14: =K13-'Historical Financials'!K11 -> 0 | L14: =L13-'Historical Financials'!L11 -> 0 | M14: =M13-'Historical Financials'!M11 -> 0 | N14: =N13-'Historical Financials'!N11 -> 0 | O14: =O13-'Historical Financials'!O11 -> 0 | P14: =P13-'Historical Financials'!P11 -> 0 | Q14: =Q13-'Historical Financials'!Q11 -> 0 | ... W14: =W13-'Historical Financials'!W11 -> 0 | Y14: =Y13-'Historical Financials'!Y11 -> -9552420.8 | Z14: =Z13-'Historical Financials'!Z11 -> -9824494.1 | AA14: =AA13-'Historical Financials'!AA11 -> -10046680 | AB14: =AB13-'Historical Financials'!AB11 -> -10207340 | AC14: =AC13-'Historical Financials'!AC11 -> -10555712 | AD14: =AD13-'Historical Financials'!AD11 -> -10671259 | AE14: =AE13-'Historical Financials'!AF11 -> -10684594 | AF14: =AF13-'Historical Financials'!AG11 -> -10610564 | AG14: =AG13-'Historical Financials'!AH11 -> -10718900
A16: X | B16: Revenue by Channel
Y17: =SUM(K17:N17) -> 0 | Z17: =SUM(L17:O17) -> 0 | AA17: =SUM(M17:P17) -> 0 | AB17: =SUM(N17:Q17) -> 0 | AC17: =SUM(O17:R17) -> 0 | AD17: =SUM(P17:S17) -> 0 | AE17: =SUM(R17:U17) -> 0 | AF17: =SUM(S17:V17) -> 0 | AG17: =SUM(T17:W17) -> 0
Y18: =SUM(K18:N18) -> 0 | Z18: =SUM(L18:O18) -> 0 | AA18: =SUM(M18:P18) -> 0 | AB18: =SUM(N18:Q18) -> 0 | AC18: =SUM(O18:R18) -> 0 | AD18: =SUM(P18:S18) -> 0 | AE18: =SUM(R18:U18) -> 0 | AF18: =SUM(S18:V18) -> 0 | AG18: =SUM(T18:W18) -> 0
B19: Total Net U.S Revenue | C19: =SUM(C17:C18) -> 0 | D19: =SUM(D17:D18) -> 0 | E19: =SUM(E17:E18) -> 0 | F19: =SUM(F17:F18) -> 0 | G19: =SUM(G17:G18) -> 0 | H19: =SUM(H17:H18) -> 0 | R19: =SUM(R17:R18) -> 0 | S19: =SUM(S17:S18) -> 0 | T19: =SUM(T17:T18) -> 0 | U19: =SUM(U17:U18) -> 0 | V19: =SUM(V17:V18) -> 0 | W19: =SUM(W17:W18) -> 0 | Y19: =SUM(Y17:Y18) -> 0 | Z19: =SUM(Z17:Z18) -> 0 | AA19: =SUM(AA17:AA18) -> 0 | AB19: =SUM(AB17:AB18) -> 0 | AC19: =SUM(AC17:AC18) -> 0 | AD19: =SUM(AD17:AD18) -> 0 | AE19: =SUM(AE17:AE18) -> 0 | AF19: =SUM(AF17:AF18) -> 0 | AG19: =SUM(AG17:AG18) -> 0
B20: Balance Check | C20: =+C19-C13 -> -7398068 | D20: =+D19-D13 -> -6090433.5 | E20: =+E19-E13 -> -8630889 | F20: =+F19-F13 -> -10208580 | G20: =+G19-G13 -> -11207303 | H20: =+H19-H13 -> -11295654 | R20: =+R19-R13 -> -2725848 | S20: =+S19-S13 -> -2552087 | T20: =+T19-T13 -> -2530100 | U20: =+U19-U13 -> -3487619 | V20: =+V19-V13 -> -2848367 | W20: =+W19-W13 -> -2788469 | Y20: =Y19-'Historical Financials'!Y17 -> 2506458 | Z20: =Z19-'Historical Financials'!Z17 -> 2572691 | AA20: =AA19-'Historical Financials'!AA17 -> 2636907 | AB20: =AB19-'Historical Financials'!AB17 -> 2694561 | AC20: =AC19-'Historical Financials'!AC17 -> 2748345 | AD20: =AD19-'Historical Financials'!AD17 -> 2792474 | AE20: =+AE19-AE13 -> -677739.24 | AF20: =+AF19-AF13 -> -685090.38 | AG20: =+AG19-AG13 -> -699273.3

Sheet FCF
B2: Ulta Beauty Inc. (NASDAQ: ULTA) | D2: FYE | H2: Quarterly | Q2: Quarterly | R2: Quarterly | X2: LTM | AE2: LTM | AK2: Variance
B3: FCF Analysis | C3: ='Historical Financials'!#REF! -> #REF! | D3: ='Historical Financials'!F7 -> 2022 | E3: ='Historical Financials'!G7 -> 2023 | F3: ='Historical Financials'!H7 -> 2024 | H3: ='Historical Financials'!J7 -> 1Q22 | I3: ='Historical Financials'!K7 -> 2Q22 | J3: ='Historical Financials'!L7 -> 3Q22 | K3: ='Historical Financials'!M7 -> 4Q22 | L3: ='Historical Financials'!N7 -> 1Q23 | M3: ='Historical Financials'!O7 -> 2Q23 | N3: ='Historical Financials'!P7 -> 3Q23 | O3: ='Historical Financials'!Q7 -> 4Q23 | ... U3: ='Historical Financials'!W7 -> 2Q25 | V3: ='Historical Financials'!#REF! -> #REF! | X3: =K3 -> 4Q22 | Y3: =L3 -> 1Q23 | Z3: =M3 -> 2Q23 | AA3: =N3 -> 3Q23 | AB3: =O3 -> 4Q23 | AC3: =P3 -> 1Q24 | AD3: =Q3 -> 2Q24 | AE3: =R3 -> 3Q24 | ... AI3: =V3 -> #REF!
B4: $ in thousands except per share | C4: ='Historical Financials'!#REF! -> #REF! | D4: ='Historical Financials'!F8 -> 44954 | E4: ='Historical Financials'!G8 -> 45325 | F4: ='Historical Financials'!H8 -> 45689 | H4: ='Historical Financials'!J8 -> 44681 | I4: ='Historical Financials'!K8 -> 44772 | J4: ='Historical Financials'!L8 -> 44863 | K4: ='Historical Financials'!M8 -> 44954 | L4: ='Historical Financials'!N8 -> 45045 | M4: ='Historical Financials'!O8 -> 45136 | N4: ='Historical Financials'!P8 -> 45227 | O4: ='Historical Financials'!Q8 -> 45325 | ... U4: ='Historical Financials'!W8 -> 45871 | V4: ='Historical Financials'!#REF! -> #REF! | X4: =K4 -> 44954 | Y4: =L4 -> 45045 | Z4: =M4 -> 45136 | AA4: =N4 -> 45227 | AB4: =O4 -> 45325 | AC4: =P4 -> 45416 | AD4: =Q4 -> 45507 | AE4: =R4 -> 45598 | ... AI4: =V4 -> #REF!
P6: ='Revenue Drivers'!R11 -> 109033.92 | Q6: ='Revenue Drivers'!S11 -> 102083.48 | AC6: =SUM(M6:P6) -> 109033.92 | AD6: =SUM(N6:Q6) -> 211117.4 | AE6: =SUM(O6:R6) -> 211117.4 | AF6: =SUM(P6:S6) -> 211117.4 | AG6: =SUM(Q6:T6) -> 102083.48 | AH6: =SUM(R6:U6) -> 0 | AI6: =SUM(S6:V6) -> 0 | AK6: =SUM(AI6/AE6)-1 -> -1
P7: ='Revenue Drivers'!R12 -> 54516.96 | Q7: ='Revenue Drivers'!S12 -> 51041.74 | AC7: =SUM(M7:P7) -> 54516.96 | AD7: =SUM(N7:Q7) -> 105558.7 | AE7: =SUM(O7:R7) -> 105558.7 | AF7: =SUM(P7:S7) -> 105558.7 | AG7: =SUM(Q7:T7) -> 51041.74 | AH7: =SUM(R7:U7) -> 0 | AI7: =SUM(S7:V7) -> 0 | AK7: =SUM(AI7/AE7)-1 -> -1
B8: Total Revenue | C8: ='Historical Financials'!#REF! -> #REF! | D8: =SUM(D6:D7) -> 0 | E8: =SUM(E6:E7) -> 0 | F8: =SUM(F6:F7) -> 0 | H8: ='Historical Financials'!J11 -> 2345901 | I8: ='Historical Financials'!K11 -> 2297113 | J8: ='Historical Financials'!L11 -> 2338793 | K8: ='Historical Financials'!M11 -> 3226773 | L8: ='Historical Financials'!N11 -> 2634263 | M8: ='Historical Financials'!O11 -> 2529809 | N8: ='Historical Financials'!P11 -> 2488933 | O8: ='Historical Financials'!Q11 -> 3554298 | P8: =SUM(P6:P7) -> 163550.88 | Q8: =SUM(Q6:Q7) -> 153125.22 | R8: =SUM(R6:R7) -> 0 | S8: =SUM(S6:S7) -> 0 | T8: =SUM(T6:T7) -> 0 | U8: =SUM(U6:U7) -> 0 | V8: =SUM(V6:V7) -> 0 | X8: =SUM(H8:K8) -> 10208580 | Y8: =SUM(I8:L8) -> 10496942 | Z8: =SUM(J8:M8) -> 10729638 | AA8: =SUM(K8:N8) -> 10879778 | AB8: =SUM(L8:O8) -> 11207303 | AC8: =SUM(AC6:AC7) -> 163550.88 | AD8: =SUM(AD6:AD7) -> 316676.1 | AE8: =SUM(AE6:AE7) -> 316676.1 | AF8: =SUM(AF6:AF7) -> 316676.1 | AG8: =SUM(AG6:AG7) -> 153125.22 | AH8: =SUM(AH6:AH7) -> 0 | AI8: =SUM(AI6:AI7) -> 0 | AK8: =SUM(AI8/AE8)-1 -> -1
B9: Y/Y Growth (%) | D9: =SUM(D8/C8)-1 -> #REF! | E9: =SUM(E8/D8)-1 -> #DIV/0! | F9: =SUM(F8/E8)-1 -> #DIV/0! | M9: =SUM(M8/I8)-1 -> 0.10129933 | N9: =SUM(N8/J8)-1 -> 0.064195506 | O9: =SUM(O8/K8)-1 -> 0.10150234 | P9: =SUM(P8/L8)-1 -> -0.93791399 | Q9: =SUM(Q8/M8)-1 -> -0.93947163 | R9: =SUM(R8/N8)-1 -> -1 | S9: =SUM(S8/O8)-1 -> -1 | T9: =SUM(T8/P8)-1 -> -1 | ... V9: =SUM(V8/R8)-1 -> #DIV/0! | AB9: =SUM(AB8/X8)-1 -> 0.097831726 | AC9: =SUM(AC8/Y8)-1 -> -0.98441919 | AD9: =SUM(AD8/Z8)-1 -> -0.97048585 | AE9: =SUM(AE8/AA8)-1 -> -0.97089315 | AF9: =SUM(AF8/AB8)-1 -> -0.97174377 | AG9: =SUM(AG8/AC8)-1 -> -0.063745667 | AH9: =SUM(AH8/AD8)-1 -> -1 | AI9: =SUM(AI8/AE8)-1 -> -1 | AK9: =SUM(AI9-AE9)*10000 -> -291.06853
B10: Q/Q Growth (%) | C10: N/A | D10: N/A | E10: N/A | F10: N/A | J10: =SUM(J8/I8)-1 -> 0.018144514 | K10: =SUM(K8/J8)-1 -> 0.37967447 | L10: =SUM(L8/K8)-1 -> -0.18362308 | M10: =SUM(M8/L8)-1 -> -0.039652077 | N10: =SUM(N8/M8)-1 -> -0.016157742 | O10: =SUM(O8/N8)-1 -> 0.42804085 | P10: =SUM(P8/O8)-1 -> -0.95398504 | Q10: =SUM(Q8/P8)-1 -> -0.063745667 | ... V10: =SUM(V8/U8)-1 -> #DIV/0! | X10: N/A | Y10: N/A | Z10: N/A | AA10: N/A | AB10: N/A | AC10: N/A | AD10: N/A | AE10: N/A | AF10: N/A | AG10: N/A | AH10: N/A | AI10: N/A
B12: (-) Cost of Sales | C12: ='Historical Financials'!#REF! -> #REF! | H12: ='Historical Financials'!J13 -> -1404875 | I12: ='Historical Financials'!K13 -> -1368949 | J12: ='Historical Financials'!L13 -> -1375976 | K12: ='Historical Financials'!M13 -> -2014270 | L12: ='Historical Financials'!N13 -> -1579406 | M12: ='Historical Financials'!O13 -> -1536197 | N12: ='Historical Financials'!P13 -> -1496866 | O12: ='Historical Financials'!Q13 -> -2213734 | ... Q12: ='Historical Financials'!S13 -> -1573910 | X12: =SUM(G12:K12) -> -6164070 | Y12: =SUM(I12:L12) -> -6338601 | Z12: =SUM(J12:M12) -> -6505849 | AA12: =SUM(K12:N12) -> -6626739 | AB12: =SUM(L12:O12) -> -6826203 | AC12: =SUM(M12:P12) -> -6902865 | AD12: =SUM(N12:Q12) -> -6940578 | AE12: =SUM(O12:R12) -> -5443712 | AF12: =SUM(P12:S12) -> -3229978 | ... AI12: =SUM(S12:V12) -> 0 | AK12: =SUM(AI12/AE12)-1 -> -1
B13: Gross Profit | C13: =+C8+C12 -> #REF! | D13: =+D8+D12 -> 0 | E13: =+E8+E12 -> 0 | F13: =+F8+F12 -> 0 | H13: =+H8+H12 -> 941026 | I13: =+I8+I12 -> 928164 | J13: =+J8+J12 -> 962817 | K13: =+K8+K12 -> 1212503 | L13: =+L8+L12 -> 1054857 | M13: =+M8+M12 -> 993612 | N13: =+N8+N12 -> 992067 | O13: =+O8+O12 -> 1340564 | ... V13: =+V8+V12 -> 0 | X13: =+X8+X12 -> 4044510 | Y13: =+Y8+Y12 -> 4158341 | Z13: =+Z8+Z12 -> 4223789 | AA13: =+AA8+AA12 -> 4253039 | AB13: =+AB8+AB12 -> 4381100 | AC13: =+AC8+AC12 -> -6739314.1 | AD13: =+AD8+AD12 -> -6623901.9 | AE13: =+AE8+AE12 -> -5127035.9 | ... AI13: =+AI8+AI12 -> 0 | AK13: =SUM(AI13/AE13)-1 -> -1
B14: Gross Margin (%) | C14: =C13/C8 -> #REF! | D14: =D13/D8 -> #DIV/0! | E14: =E13/E8 -> #DIV/0! | F14: =F13/F8 -> #DIV/0! | H14: =H13/H8 -> 0.40113628 | I14: =I13/I8 -> 0.40405674 | J14: =J13/J8 -> 0.4116726 | K14: =K13/K8 -> 0.37576334 | L14: =L13/L8 -> 0.40043724 | M14: =M13/M8 -> 0.39276167 | N14: =N13/N8 -> 0.39859128 | O14: =O13/O8 -> 0.37716702 | ... V14: =V13/V8 -> #DIV/0! | X14: =X13/X8 -> 0.39618732 | Y14: =Y13/Y8 -> 0.39614785 | Z14: =Z13/Z8 -> 0.39365624 | AA14: =AA13/AA8 -> 0.3909123 | AB14: =AB13/AB8 -> 0.39091475 | AC14: =AC13/AC8 -> -41.206224 | AD14: =AD13/AD8 -> -20.916962 | AE14: =AE13/AE8 -> -16.190157 | ... AI14: =AI13/AI8 -> #DIV/0! | AK14: =SUM(AI14-AE14)*10000 -> #DIV/0!
B16: (-) Research and development | C16: ='Historical Financials'!#REF! -> #REF! | H16: ='Historical Financials'!J17 -> -500970 | I16: ='Historical Financials'!K17 -> -534459 | J16: ='Historical Financials'!L17 -> -597164 | K16: ='Historical Financials'!M17 -> -762706 | L16: ='Historical Financials'!N17 -> -612129 | M16: ='Historical Financials'!O17 -> -600692 | N16: ='Historical Financials'!P17 -> -661380 | O16: ='Historical Financials'!Q17 -> -820360 | ... Q16: ='Historical Financials'!S17 -> -644821 | X16: =SUM(G16:K16) -> -2395299 | Y16: =SUM(I16:L16) -> -2506458 | Z16: =SUM(J16:M16) -> -2572691 | AA16: =SUM(K16:N16) -> -2636907 | AB16: =SUM(L16:O16) -> -2694561 | AC16: =SUM(M16:P16) -> -2748345 | AD16: =SUM(N16:Q16) -> -2792474 | AE16: =SUM(O16:R16) -> -2131094 | AF16: =SUM(P16:S16) -> -1310734 | ... AI16: =SUM(S16:V16) -> 0 | AK16: =SUM(AI16/AE16)-1 -> -1
B17: (-) Sales and marketing | C17: ='Historical Financials'!#REF! -> #REF! | H17: ='Historical Financials'!J18 -> -2348 | I17: ='Historical Financials'!K18 -> -2277 | J17: ='Historical Financials'!L18 -> -3797 | K17: ='Historical Financials'!M18 -> -2179 | L17: ='Historical Financials'!N18 -> -658 | M17: ='Historical Financials'!O18 -> -1278 | N17: ='Historical Financials'!P18 -> -3460 | O17: ='Historical Financials'!Q18 -> -3114 | ... Q17: ='Historical Financials'!S18 -> -4155 | X17: =SUM(G17:K17) -> -10601 | Y17: =SUM(I17:L17) -> -8911 | Z17: =SUM(J17:M17) -> -7912 | AA17: =SUM(K17:N17) -> -7575 | AB17: =SUM(L17:O17) -> -8510 | AC17: =SUM(M17:P17) -> -10771 | AD17: =SUM(N17:Q17) -> -13648 | AE17: =SUM(O17:R17) -> -10188 | AF17: =SUM(P17:S17) -> -7074 | ... AI17: =SUM(S17:V17) -> 0 | AK17: =SUM(AI17/AE17)-1 -> -1
B18: (-) General and administrative | C18: ='Historical Financials'!#REF! -> #REF! | H18: ='Historical Financials'!#REF! -> #REF! | I18: ='Historical Financials'!#REF! -> #REF! | J18: ='Historical Financials'!#REF! -> #REF! | K18: ='Historical Financials'!#REF! -> #REF! | L18: ='Historical Financials'!#REF! -> #REF! | M18: ='Historical Financials'!#REF! -> #REF! | N18: ='Historical Financials'!#REF! -> #REF! | O18: ='Historical Financials'!#REF! -> #REF! | ... Q18: ='Historical Financials'!#REF! -> #REF! | X18: =SUM(G18:K18) -> #REF! | Y18: =SUM(I18:L18) -> #REF! | Z18: =SUM(J18:M18) -> #REF! | AA18: =SUM(K18:N18) -> #REF! | AB18: =SUM(L18:O18) -> #REF! | AC18: =SUM(M18:P18) -> #REF! | AD18: =SUM(N18:Q18) -> #REF! | AE18: =SUM(O18:R18) -> #REF! | AF18: =SUM(P18:S18) -> #REF! | ... AI18: =SUM(S18:V18) -> 0 | AK18: =SUM(AI18/AE18)-1 -> #REF!
B19: (-) Depreciation and amortization | C19: ='Historical Financials'!#REF! -> #REF! | H19: ='Historical Financials'!J19 -> 0 | I19: ='Historical Financials'!K19 -> 0 | J19: ='Historical Financials'!L19 -> 0 | K19: ='Historical Financials'!M19 -> 0 | L19: ='Historical Financials'!N19 -> 0 | M19: ='Historical Financials'!O19 -> 0 | N19: ='Historical Financials'!P19 -> 0 | O19: ='Historical Financials'!Q19 -> 0 | ... Q19: ='Historical Financials'!S19 -> 0 | X19: =SUM(G19:K19) -> 0 | Y19: =SUM(I19:L19) -> 0 | Z19: =SUM(J19:M19) -> 0 | AA19: =SUM(K19:N19) -> 0 | AB19: =SUM(L19:O19) -> 0 | AC19: =SUM(M19:P19) -> 0 | AD19: =SUM(N19:Q19) -> 0 | AE19: =SUM(O19:R19) -> 0 | AF19: =SUM(P19:S19) -> 0 | ... AI19: =SUM(S19:V19) -> 0 | AK19: =SUM(AI19/AE19)-1 -> #DIV/0!
B20: Earning before Interest & Taxes (EBIT) | C20: =SUM(C13+SUM(C16:C19)) -> #REF! | D20: =SUM(D13+SUM(D16:D19)) -> 0 | E20: =SUM(E13+SUM(E16:E19)) -> 0 | F20: =SUM(F13+SUM(F16:F19)) -> 0 | H20: =SUM(H13+SUM(H16:H19)) -> #REF! | I20: =SUM(I13+SUM(I16:I19)) -> #REF! | J20: =SUM(J13+SUM(J16:J19)) -> #REF! | K20: =SUM(K13+SUM(K16:K19)) -> #REF! | L20: =SUM(L13+SUM(L16:L19)) -> #REF! | M20: =SUM(M13+SUM(M16:M19)) -> #REF! | N20: =SUM(N13+SUM(N16:N19)) -> #REF! | O20: =SUM(O13+SUM(O16:O19)) -> #REF! | ... V20: =SUM(V13+SUM(V16:V19)) -> 0 | X20: =SUM(X13+SUM(X16:X19)) -> #REF! | Y20: =SUM(Y13+SUM(Y16:Y19)) -> #REF! | Z20: =SUM(Z13+SUM(Z16:Z19)) -> #REF! | AA20: =SUM(AA13+SUM(AA16:AA19)) -> #REF! | AB20: =SUM(AB13+SUM(AB16:AB19)) -> #REF! | AC20: =SUM(AC13+SUM(AC16:AC19)) -> #REF! | AD20: =SUM(AD13+SUM(AD16:AD19)) -> #REF! | AE20: =SUM(AE13+SUM(AE16:AE19)) -> #REF! | ... AI20: =SUM(AI13+SUM(AI16:AI19)) -> 0 | AK20: =SUM(AI20/AE20)-1 -> #REF!
B21: Operating Margin (%) | C21: =C20/C8 -> #REF! | D21: =D20/D8 -> #DIV/0! | E21: =E20/E8 -> #DIV/0! | F21: =F20/F8 -> #DIV/0! | H21: =H20/H8 -> #REF! | I21: =I20/I8 -> #REF! | J21: =J20/J8 -> #REF! | K21: =K20/K8 -> #REF! | L21: =L20/L8 -> #REF! | M21: =M20/M8 -> #REF! | N21: =N20/N8 -> #REF! | O21: =O20/O8 -> #REF! | ... V21: =V20/V8 -> #DIV/0! | X21: =X20/X8 -> #REF! | Y21: =Y20/Y8 -> #REF! | Z21: =Z20/Z8 -> #REF! | AA21: =AA20/AA8 -> #REF! | AB21: =AB20/AB8 -> #REF! | AC21: =AC20/AC8 -> #REF! | AD21: =AD20/AD8 -> #REF! | AE21: =AE20/AE8 -> #REF! | ... AI21: =AI20/AI8 -> #DIV/0! | AK21: =SUM(AI21-AE21)*10000 -> #DIV/0!
B23: (+) Depreciation and Amortization | C23: =-C19 -> #REF! | H23: =-H19 -> 0 | I23: =-I19 -> 0 | J23: =-J19 -> 0 | K23: =-K19 -> 0 | L23: =-L19 -> 0 | M23: =-M19 -> 0 | N23: =-N19 -> 0 | O23: =-O19 -> 0 | ... Q23: =-Q19 -> 0 | X23: =SUM(G23:K23) -> 0 | Y23: =SUM(I23:L23) -> 0 | Z23: =SUM(J23:M23) -> 0 | AA23: =SUM(K23:N23) -> 0 | AB23: =SUM(L23:O23) -> 0 | AC23: =SUM(M23:P23) -> 0 | AD23: =SUM(N23:Q23) -> 0 | AE23: =SUM(O23:R23) -> 0 | AF23: =SUM(P23:S23) -> 0 | ... AI23: =SUM(S23:V23) -> 0 | AK23: =SUM(AI23/AE23)-1 -> #DIV/0!
B24: EBITDA | C24: =SUM(C20+C23) -> #REF! | D24: =SUM(D20+D23) -> 0 | E24: =SUM(E20+E23) -> 0 | F24: =SUM(F20+F23) -> 0 | H24: =SUM(H20+H23) -> #REF! | I24: =SUM(I20+I23) -> #REF! | J24: =SUM(J20+J23) -> #REF! | K24: =SUM(K20+K23) -> #REF! | L24: =SUM(L20+L23) -> #REF! | M24: =SUM(M20+M23) -> #REF! | N24: =SUM(N20+N23) -> #REF! | O24: =SUM(O20+O23) -> #REF! | ... V24: =SUM(V20+V23) -> 0 | X24: =SUM(X20+X23) -> #REF! | Y24: =SUM(Y20+Y23) -> #REF! | Z24: =SUM(Z20+Z23) -> #REF! | AA24: =SUM(AA20+AA23) -> #REF! | AB24: =SUM(AB20+AB23) -> #REF! | AC24: =SUM(AC20+AC23) -> #REF! | AD24: =SUM(AD20+AD23) -> #REF! | AE24: =SUM(AE20+AE23) -> #REF! | ... AI24: =SUM(AI20+AI23) -> 0 | AK24: =SUM(AI24/AE24)-1 -> #REF!
B25: EBITDA Margin (%) | C25: =C24/C8 -> #REF! | D25: =D24/D8 -> #DIV/0! | E25: =E24/E8 -> #DIV/0! | F25: =F24/F8 -> #DIV/0! | H25: =H24/H8 -> #REF! | I25: =I24/I8 -> #REF! | J25: =J24/J8 -> #REF! | K25: =K24/K8 -> #REF! | L25: =L24/L8 -> #REF! | M25: =M24/M8 -> #REF! | N25: =N24/N8 -> #REF! | O25: =O24/O8 -> #REF! | ... V25: =V24/V8 -> #DIV/0! | X25: =X24/X8 -> #REF! | Y25: =Y24/Y8 -> #REF! | Z25: =Z24/Z8 -> #REF! | AA25: =AA24/AA8 -> #REF! | AB25: =AB24/AB8 -> #REF! | AC25: =AC24/AC8 -> #REF! | AD25: =AD24/AD8 -> #REF! | AE25: =AE24/AE8 -> #REF! | ... AI25: =AI24/AI8 -> #DIV/0! | AK25: =SUM(AI25-AE25)*10000 -> #DIV/0!
B27: (+) Share-based Compensation | C27: ='Historical Financials'!#REF! -> #REF! | H27: ='Historical Financials'!J93 -> 72192 | I27: ='Historical Financials'!K93 -> 74059 | J27: ='Historical Financials'!L93 -> 76297 | K27: ='Historical Financials'!M93 -> 79364 | L27: ='Historical Financials'!N93 -> 75478 | M27: ='Historical Financials'!O93 -> 77389 | N27: ='Historical Financials'!P93 -> 79905 | O27: ='Historical Financials'!Q93 -> 99982 | ... Q27: ='Historical Financials'!S93 -> 85543 | X27: =SUM(G27:K27) -> 301912 | Y27: =SUM(I27:L27) -> 305198 | Z27: =SUM(J27:M27) -> 308528 | AA27: =SUM(K27:N27) -> 312136 | AB27: =SUM(L27:O27) -> 332754 | AC27: =SUM(M27:P27) -> 335214 | AD27: =SUM(N27:Q27) -> 343368 | AE27: =SUM(O27:R27) -> 263463 | AF27: =SUM(P27:S27) -> 163481 | ... AI27: =SUM(S27:V27) -> 0 | AK27: =SUM(AI27/AE27)-1 -> -1
B28: Adj. EBITDA | C28: =+SUM(C24+SUM(C27:C27)) -> #REF! | D28: =+SUM(D24+SUM(D27:D27)) -> 0 | E28: =+SUM(E24+SUM(E27:E27)) -> 0 | F28: =+SUM(F24+SUM(F27:F27)) -> 0 | H28: =+SUM(H24+SUM(H27:H27)) -> #REF! | I28: =+SUM(I24+SUM(I27:I27)) -> #REF! | J28: =+SUM(J24+SUM(J27:J27)) -> #REF! | K28: =+SUM(K24+SUM(K27:K27)) -> #REF! | L28: =+SUM(L24+SUM(L27:L27)) -> #REF! | M28: =+SUM(M24+SUM(M27:M27)) -> #REF! | N28: =+SUM(N24+SUM(N27:N27)) -> #REF! | O28: =+SUM(O24+SUM(O27:O27)) -> #REF! | ... V28: =+SUM(V24+SUM(V27:V27)) -> 0 | X28: =+SUM(X24+SUM(X27:X27)) -> #REF! | Y28: =+SUM(Y24+SUM(Y27:Y27)) -> #REF! | Z28: =+SUM(Z24+SUM(Z27:Z27)) -> #REF! | AA28: =+SUM(AA24+SUM(AA27:AA27)) -> #REF! | AB28: =+SUM(AB24+SUM(AB27:AB27)) -> #REF! | AC28: =+SUM(AC24+SUM(AC27:AC27)) -> #REF! | AD28: =+SUM(AD24+SUM(AD27:AD27)) -> #REF! | AE28: =+SUM(AE24+SUM(AE27:AE27)) -> #REF! | ... AI28: =+SUM(AI24+SUM(AI27:AI27)) -> 0 | AK28: =SUM(AI28/AE28)-1 -> #REF!
B29: Adj. EBITDA Margin (%) | C29: =C28/C8 -> #REF! | D29: =D28/D8 -> #DIV/0! | E29: =E28/E8 -> #DIV/0! | F29: =F28/F8 -> #DIV/0! | H29: =H28/H8 -> #REF! | I29: =I28/I8 -> #REF! | J29: =J28/J8 -> #REF! | K29: =K28/K8 -> #REF! | L29: =L28/L8 -> #REF! | M29: =M28/M8 -> #REF! | N29: =N28/N8 -> #REF! | O29: =O28/O8 -> #REF! | ... V29: =V28/V8 -> #DIV/0! | X29: =X28/X8 -> #REF! | Y29: =Y28/Y8 -> #REF! | Z29: =Z28/Z8 -> #REF! | AA29: =AA28/AA8 -> #REF! | AB29: =AB28/AB8 -> #REF! | AC29: =AC28/AC8 -> #REF! | AD29: =AD28/AD8 -> #REF! | AE29: =AE28/AE8 -> #REF! | ... AI29: =AI28/AI8 -> #DIV/0! | AK29: =SUM(AI29-AE29)*10000 -> #DIV/0!
B31: (-) Capital Expenditures | C31: =SUM('Historical Financials'!#REF!+'Historical Financials'!#REF!) -> #REF! | H31: =SUM('Historical Financials'!J113+'Historical Financials'!J115) -> -71873 | I31: =SUM('Historical Financials'!K113+'Historical Financials'!K115) -> -49876 | J31: =SUM('Historical Financials'!L113+'Historical Financials'!L115) -> -85280 | K31: =SUM('Historical Financials'!M113+'Historical Financials'!M115) -> -107555 | L31: =SUM('Historical Financials'!N113+'Historical Financials'!N115) -> -110080 | M31: =SUM('Historical Financials'!O113+'Historical Financials'!O115) -> -96355 | N31: =SUM('Historical Financials'!P113+'Historical Financials'!P115) -> -109465 | O31: =SUM('Historical Financials'!Q113+'Historical Financials'!Q115) -> -125525 | ... Q31: =SUM('Historical Financials'!S113+'Historical Financials'!S115) -> -97805 | X31: =SUM(G31:K31) -> -314584 | Y31: =SUM(I31:L31) -> -352791 | Z31: =SUM(J31:M31) -> -399270 | AA31: =SUM(K31:N31) -> -423455 | AB31: =SUM(L31:O31) -> -441425 | AC31: =SUM(M31:P31) -> -424932 | AD31: =SUM(N31:Q31) -> -426382 | AE31: =SUM(O31:R31) -> -316917 | AF31: =SUM(P31:S31) -> -191392 | ... AI31: =SUM(S31:V31) -> 0 | AK31: =SUM(AI31/AE31)-1 -> -1
B32: (-) Cash Taxes | C32: ='Historical Financials'!#REF! -> #REF! | H32: ='Historical Financials'!J27 -> -105912 | I32: ='Historical Financials'!K27 -> -95859 | J32: ='Historical Financials'!L27 -> -88120 | K32: ='Historical Financials'!M27 -> -111245 | L32: ='Historical Financials'!N27 -> -102367 | M32: ='Historical Financials'!O27 -> -95989 | N32: ='Historical Financials'!P27 -> -80241 | O32: ='Historical Financials'!Q27 -> -126049 | ... Q32: ='Historical Financials'!S27 -> -81171 | X32: =SUM(G32:K32) -> -401136 | Y32: =SUM(I32:L32) -> -397591 | Z32: =SUM(J32:M32) -> -397721 | AA32: =SUM(K32:N32) -> -389842 | AB32: =SUM(L32:O32) -> -404646 | AC32: =SUM(M32:P32) -> -397014 | AD32: =SUM(N32:Q32) -> -382196 | AE32: =SUM(O32:R32) -> -301955 | AF32: =SUM(P32:S32) -> -175906 | ... AI32: =SUM(S32:V32) -> 0 | AK32: =SUM(AI32/AE32)-1 -> -1
B33: (-) Cash Interest | C33: 0 | H33: 0 | I33: 0 | J33: 0 | K33: =D33 -> 0 | L33: 0 | M33: 0 | N33: 0 | O33: =E33 -> 0 | P33: 0 | Q33: 0 | X33: =SUM(G33:K33) -> 0 | Y33: =SUM(I33:L33) -> 0 | Z33: =SUM(J33:M33) -> 0 | AA33: =SUM(K33:N33) -> 0 | AB33: =SUM(L33:O33) -> 0 | AC33: =SUM(M33:P33) -> 0 | AD33: =SUM(N33:Q33) -> 0 | AE33: =SUM(O33:R33) -> 0 | AF33: =SUM(P33:S33) -> 0 | ... AI33: =SUM(S33:V33) -> 0 | AK33: =SUM(AI33/AE33)-1 -> #DIV/0!
B34: (+/-) Changes in NWC | C34: =SUM('Historical Financials'!#REF!) -> #REF! | H34: =SUM('Historical Financials'!J101:J109) -> -52490 | I34: =SUM('Historical Financials'!K101:K109) -> -329375 | J34: =SUM('Historical Financials'!L101:L109) -> -386476 | K34: =SUM('Historical Financials'!M101:M109) -> 399179 | L34: =SUM('Historical Financials'!N101:N109) -> -188893 | M34: =SUM('Historical Financials'!O101:O109) -> -328264 | N34: =SUM('Historical Financials'!P101:P109) -> -476828 | O34: =SUM('Historical Financials'!Q101:Q109) -> 512412 | ... Q34: =SUM('Historical Financials'!S101:S109) -> -214198 | X34: =SUM(G34:K34) -> -369162 | Y34: =SUM(I34:L34) -> -505565 | Z34: =SUM(J34:M34) -> -504454 | AA34: =SUM(K34:N34) -> -594806 | AB34: =SUM(L34:O34) -> -481573 | AC34: =SUM(M34:P34) -> -605822 | AD34: =SUM(N34:Q34) -> -491756 | AE34: =SUM(O34:R34) -> -14928 | AF34: =SUM(P34:S34) -> -527340 | ... AI34: =SUM(S34:V34) -> 0 | AK34: =SUM(AI34/AE34)-1 -> -1
B35: Discretionary Cash-Flows | C35: =SUM(C28+SUM(C31:C34)) -> #REF! | D35: =SUM(D28+SUM(D31:D34)) -> 0 | E35: =SUM(E28+SUM(E31:E34)) -> 0 | F35: =SUM(F28+SUM(F31:F34)) -> 0 | H35: =SUM(H28+SUM(H31:H34)) -> #REF! | I35: =SUM(I28+SUM(I31:I34)) -> #REF! | J35: =SUM(J28+SUM(J31:J34)) -> #REF! | K35: =SUM(K28+SUM(K31:K34)) -> #REF! | L35: =SUM(L28+SUM(L31:L34)) -> #REF! | M35: =SUM(M28+SUM(M31:M34)) -> #REF! | N35: =SUM(N28+SUM(N31:N34)) -> #REF! | O35: =SUM(O28+SUM(O31:O34)) -> #REF! | ... V35: =SUM(V28+SUM(V31:V34)) -> 0 | X35: =SUM(X28+SUM(X31:X34)) -> #REF! | Y35: =SUM(Y28+SUM(Y31:Y34)) -> #REF! | Z35: =SUM(Z28+SUM(Z31:Z34)) -> #REF! | AA35: =SUM(AA28+SUM(AA31:AA34)) -> #REF! | AB35: =SUM(AB28+SUM(AB31:AB34)) -> #REF! | AC35: =SUM(AC28+SUM(AC31:AC34)) -> #REF! | AD35: =SUM(AD28+SUM(AD31:AD34)) -> #REF! | AE35: =SUM(AE28+SUM(AE31:AE34)) -> #REF! | ... AI35: =SUM(AI28+SUM(AI31:AI34)) -> 0 | AK35: =SUM(AI35/AE35)-1 -> #REF!
B37: (+/-) Proceeds / (Purchases) of Equity, net | C37: ='Historical Financials'!#REF! -> #REF! | H37: ='Historical Financials'!#REF! -> #REF! | I37: ='Historical Financials'!#REF! -> #REF! | J37: ='Historical Financials'!#REF! -> #REF! | K37: ='Historical Financials'!#REF! -> #REF! | L37: ='Historical Financials'!#REF! -> #REF! | M37: ='Historical Financials'!#REF! -> #REF! | N37: ='Historical Financials'!#REF! -> #REF! | O37: ='Historical Financials'!#REF! -> #REF! | ... Q37: ='Historical Financials'!#REF! -> #REF! | X37: =SUM(G37:K37) -> #REF! | Y37: =SUM(I37:L37) -> #REF! | Z37: =SUM(J37:M37) -> #REF! | AA37: =SUM(K37:N37) -> #REF! | AB37: =SUM(L37:O37) -> #REF! | AC37: =SUM(M37:P37) -> #REF! | AD37: =SUM(N37:Q37) -> #REF! | AE37: =SUM(O37:R37) -> #REF! | AF37: =SUM(P37:S37) -> #REF! | ... AI37: =SUM(S37:V37) -> 0
B38: (+/-) Maturities / (Purchases) of available-for-sale securities | C38: =SUM('Historical Financials'!#REF!) -> #REF! | H38: =SUM('Historical Financials'!#REF!) -> #REF! | I38: =SUM('Historical Financials'!#REF!) -> #REF! | J38: =SUM('Historical Financials'!#REF!) -> #REF! | K38: =SUM('Historical Financials'!#REF!) -> #REF! | L38: =SUM('Historical Financials'!#REF!) -> #REF! | M38: =SUM('Historical Financials'!#REF!) -> #REF! | N38: =SUM('Historical Financials'!#REF!) -> #REF! | O38: =SUM('Historical Financials'!#REF!) -> #REF! | ... Q38: =SUM('Historical Financials'!#REF!) -> #REF! | X38: =SUM(G38:K38) -> #REF! | Y38: =SUM(I38:L38) -> #REF! | Z38: =SUM(J38:M38) -> #REF! | AA38: =SUM(K38:N38) -> #REF! | AB38: =SUM(L38:O38) -> #REF! | AC38: =SUM(M38:P38) -> #REF! | AD38: =SUM(N38:Q38) -> #REF! | AE38: =SUM(O38:R38) -> #REF! | AF38: =SUM(P38:S38) -> #REF! | ... AI38: =SUM(S38:V38) -> 0
B39: (+/-) Divestitures / (Acquisitions) | C39: ='Historical Financials'!#REF! -> #REF! | H39: ='Historical Financials'!#REF! -> #REF! | I39: ='Historical Financials'!#REF! -> #REF! | J39: ='Historical Financials'!#REF! -> #REF! | K39: ='Historical Financials'!#REF! -> #REF! | L39: ='Historical Financials'!#REF! -> #REF! | M39: ='Historical Financials'!#REF! -> #REF! | N39: ='Historical Financials'!#REF! -> #REF! | O39: ='Historical Financials'!#REF! -> #REF! | ... Q39: ='Historical Financials'!#REF! -> #REF! | X39: =SUM(G39:K39) -> #REF! | Y39: =SUM(I39:L39) -> #REF! | Z39: =SUM(J39:M39) -> #REF! | AA39: =SUM(K39:N39) -> #REF! | AB39: =SUM(L39:O39) -> #REF! | AC39: =SUM(M39:P39) -> #REF! | AD39: =SUM(N39:Q39) -> #REF! | AE39: =SUM(O39:R39) -> #REF! | AF39: =SUM(P39:S39) -> #REF! | ... AI39: =SUM(S39:V39) -> 0
B40: (+/-) Other Investing Activities | C40: ='Historical Financials'!#REF! -> #REF! | H40: ='Historical Financials'!#REF! -> #REF! | I40: ='Historical Financials'!#REF! -> #REF! | J40: ='Historical Financials'!#REF! -> #REF! | K40: ='Historical Financials'!#REF! -> #REF! | L40: ='Historical Financials'!#REF! -> #REF! | M40: ='Historical Financials'!#REF! -> #REF! | N40: ='Historical Financials'!#REF! -> #REF! | O40: ='Historical Financials'!#REF! -> #REF! | ... Q40: ='Historical Financials'!#REF! -> #REF! | X40: =SUM(G40:K40) -> #REF! | Y40: =SUM(I40:L40) -> #REF! | Z40: =SUM(J40:M40) -> #REF! | AA40: =SUM(K40:N40) -> #REF! | AB40: =SUM(L40:O40) -> #REF! | AC40: =SUM(M40:P40) -> #REF! | AD40: =SUM(N40:Q40) -> #REF! | AE40: =SUM(O40:R40) -> #REF! | AF40: =SUM(P40:S40) -> #REF! | ... AI40: =SUM(S40:V40) -> 0
B41: (+/-) Other Financing Activities | C41: ='Historical Financials'!#REF! -> #REF! | H41: ='Historical Financials'!#REF! -> #REF! | I41: ='Historical Financials'!#REF! -> #REF! | J41: ='Historical Financials'!#REF! -> #REF! | K41: ='Historical Financials'!#REF! -> #REF! | L41: ='Historical Financials'!#REF! -> #REF! | M41: ='Historical Financials'!#REF! -> #REF! | N41: ='Historical Financials'!#REF! -> #REF! | O41: ='Historical Financials'!#REF! -> #REF! | ... Q41: ='Historical Financials'!#REF! -> #REF! | X41: =SUM(G41:K41) -> #REF! | Y41: =SUM(I41:L41) -> #REF! | Z41: =SUM(J41:M41) -> #REF! | AA41: =SUM(K41:N41) -> #REF! | AB41: =SUM(L41:O41) -> #REF! | AC41: =SUM(M41:P41) -> #REF! | AD41: =SUM(N41:Q41) -> #REF! | AE41: =SUM(O41:R41) -> #REF! | AF41: =SUM(P41:S41) -> #REF! | ... AI41: =SUM(S41:V41) -> 0
B42: (+/-) Other Operating Activities | C42: ='Historical Financials'!#REF! -> #REF! | H42: ='Historical Financials'!#REF! -> #REF! | I42: ='Historical Financials'!#REF! -> #REF! | J42: ='Historical Financials'!#REF! -> #REF! | K42: ='Historical Financials'!#REF! -> #REF! | L42: ='Historical Financials'!#REF! -> #REF! | M42: ='Historical Financials'!#REF! -> #REF! | N42: ='Historical Financials'!#REF! -> #REF! | O42: ='Historical Financials'!#REF! -> #REF! | ... Q42: ='Historical Financials'!#REF! -> #REF! | X42: =SUM(G42:K42) -> #REF! | Y42: =SUM(I42:L42) -> #REF! | Z42: =SUM(J42:M42) -> #REF! | AA42: =SUM(K42:N42) -> #REF! | AB42: =SUM(L42:O42) -> #REF! | AC42: =SUM(M42:P42) -> #REF! | AD42: =SUM(N42:Q42) -> #REF! | AE42: =SUM(O42:R42) -> #REF! | AF42: =SUM(P42:S42) -> #REF! | ... AI42: =SUM(S42:V42) -> 0
B43: (+/-) Other | H43: =SUM(H48:H49)-SUM(C48:C49)-SUM(H35:H42) -> #REF! | I43: =SUM(I48:I49)-SUM(H48:H49)-SUM(I35:I42) -> #REF! | J43: =SUM(J48:J49)-SUM(I48:I49)-SUM(J35:J42) -> #REF! | K43: =SUM(K48:K49)-SUM(J48:J49)-SUM(K35:K42) -> #REF! | L43: =SUM(L48:L49)-SUM(K48:K49)-SUM(L35:L42) -> #REF! | M43: =SUM(M48:M49)-SUM(L48:L49)-SUM(M35:M42) -> #REF! | N43: =SUM(N48:N49)-SUM(M48:M49)-SUM(N35:N42) -> #REF! | O43: =SUM(O48:O49)-SUM(N48:N49)-SUM(O35:O42) -> #REF! | P43: =SUM(P48:P49)-SUM(O48:O49)-SUM(P35:P42) -> #REF! | Q43: =SUM(Q48:Q49)-SUM(P48:P49)-SUM(Q35:Q42) -> #REF! | X43: =SUM(G43:K43) -> #REF! | Y43: =SUM(I43:L43) -> #REF! | Z43: =SUM(J43:M43) -> #REF! | AA43: =SUM(K43:N43) -> #REF! | AB43: =SUM(L43:O43) -> #REF! | AC43: =SUM(M43:P43) -> #REF! | AD43: =SUM(N43:Q43) -> #REF! | AE43: =SUM(O43:R43) -> #REF! | AF43: =SUM(P43:S43) -> #REF! | ... AI43: =SUM(S43:V43) -> 0
B44: Free-Cash Flows | C44: =SUM(C35+SUM(C37:C43)) -> #REF! | D44: =SUM(D35+SUM(D37:D43)) -> 0 | E44: =SUM(E35+SUM(E37:E43)) -> 0 | F44: =SUM(F35+SUM(F37:F43)) -> 0 | H44: =SUM(H35+SUM(H37:H43)) -> #REF! | I44: =SUM(I35+SUM(I37:I43)) -> #REF! | J44: =SUM(J35+SUM(J37:J43)) -> #REF! | K44: =SUM(K35+SUM(K37:K43)) -> #REF! | L44: =SUM(L35+SUM(L37:L43)) -> #REF! | M44: =SUM(M35+SUM(M37:M43)) -> #REF! | N44: =SUM(N35+SUM(N37:N43)) -> #REF! | O44: =SUM(O35+SUM(O37:O43)) -> #REF! | ... V44: =SUM(V35+SUM(V37:V43)) -> 0 | X44: =SUM(X35+SUM(X37:X43)) -> #REF! | Y44: =SUM(Y35+SUM(Y37:Y43)) -> #REF! | Z44: =SUM(Z35+SUM(Z37:Z43)) -> #REF! | AA44: =SUM(AA35+SUM(AA37:AA43)) -> #REF! | AB44: =SUM(AB35+SUM(AB37:AB43)) -> #REF! | AC44: =SUM(AC35+SUM(AC37:AC43)) -> #REF! | AD44: =SUM(AD35+SUM(AD37:AD43)) -> #REF! | AE44: =SUM(AE35+SUM(AE37:AE43)) -> #REF! | ... AI44: =SUM(AI35+SUM(AI37:AI43)) -> 0
B46: Capitalization
B48: Cash & Cash Equivelants | C48: ='Historical Financials'!#REF! -> #REF! | H48: ='Historical Financials'!J42 -> 654486 | I48: ='Historical Financials'!K42 -> 434226 | J48: ='Historical Financials'!L42 -> 250628 | K48: ='Historical Financials'!M42 -> 737877 | L48: ='Historical Financials'!N42 -> 636449 | M48: ='Historical Financials'!O42 -> 388627 | N48: ='Historical Financials'!P42 -> 121811 | O48: ='Historical Financials'!Q42 -> 766594 | ... Q48: ='Historical Financials'!S42 -> 413962 | X48: =K48 -> 737877 | Y48: =L48 -> 636449 | Z48: =M48 -> 388627 | AA48: =N48 -> 121811 | AB48: =O48 -> 766594 | AC48: =P48 -> 524596 | AD48: =Q48 -> 413962 | AE48: =R48 -> 0 | ... AI48: =V48 -> 0
B49: Restricted Cash | C49: ='Historical Financials'!#REF! -> #REF! | H49: ='Historical Financials'!J46 -> 0 | I49: ='Historical Financials'!K46 -> 39029 | J49: ='Historical Financials'!L46 -> 42572 | K49: ='Historical Financials'!M46 -> 38308 | L49: ='Historical Financials'!N46 -> 0 | M49: ='Historical Financials'!O46 -> 30114 | N49: ='Historical Financials'!P46 -> 28773 | O49: ='Historical Financials'!Q46 -> 4251 | ... Q49: ='Historical Financials'!S46 -> 53607 | X49: =K49 -> 38308 | Y49: =L49 -> 0 | Z49: =M49 -> 30114 | AA49: =N49 -> 28773 | AB49: =O49 -> 4251 | AC49: =P49 -> 0 | AD49: =Q49 -> 53607 | AE49: =R49 -> 0 | ... AI49: =V49 -> 0
B50: Short-term Investments | C50: ='Historical Financials'!#REF! -> #REF! | H50: ='Historical Financials'!#REF! -> #REF! | I50: ='Historical Financials'!#REF! -> #REF! | J50: ='Historical Financials'!#REF! -> #REF! | K50: ='Historical Financials'!#REF! -> #REF! | L50: ='Historical Financials'!#REF! -> #REF! | M50: ='Historical Financials'!#REF! -> #REF! | N50: ='Historical Financials'!#REF! -> #REF! | O50: ='Historical Financials'!#REF! -> #REF! | ... Q50: ='Historical Financials'!#REF! -> #REF! | X50: =K50 -> #REF! | Y50: =L50 -> #REF! | Z50: =M50 -> #REF! | AA50: =N50 -> #REF! | AB50: =O50 -> #REF! | AC50: =P50 -> #REF! | AD50: =Q50 -> #REF! | AE50: =R50 -> 0 | ... AI50: =V50 -> 0
B51: Long-term Investments | C51: ='Historical Financials'!#REF! -> #REF! | H51: ='Historical Financials'!J50 -> 909543 | I51: ='Historical Financials'!K50 -> 912017 | J51: ='Historical Financials'!L50 -> 967039 | K51: ='Historical Financials'!M50 -> 1009273 | L51: ='Historical Financials'!N50 -> 1019978 | M51: ='Historical Financials'!O50 -> 1073144 | N51: ='Historical Financials'!P50 -> 1117874 | O51: ='Historical Financials'!Q50 -> 1182335 | ... Q51: ='Historical Financials'!S50 -> 1225850 | X51: =K51 -> 1009273 | Y51: =L51 -> 1019978 | Z51: =M51 -> 1073144 | AA51: =N51 -> 1117874 | AB51: =O51 -> 1182335 | AC51: =P51 -> 1195658 | AD51: =Q51 -> 1225850 | AE51: =R51 -> 0 | ... AI51: =V51 -> 0
B52: Total Liquidity | C52: =SUM(C48:C51) -> #REF! | D52: =SUM(D48:D51) -> 0 | E52: =SUM(E48:E51) -> 0 | F52: =SUM(F48:F51) -> 0 | H52: =SUM(H48:H51) -> #REF! | I52: =SUM(I48:I51) -> #REF! | J52: =SUM(J48:J51) -> #REF! | K52: =SUM(K48:K51) -> #REF! | L52: =SUM(L48:L51) -> #REF! | M52: =SUM(M48:M51) -> #REF! | N52: =SUM(N48:N51) -> #REF! | O52: =SUM(O48:O51) -> #REF! | ... V52: =SUM(V48:V51) -> 0 | X52: =SUM(X48:X51) -> #REF! | Y52: =SUM(Y48:Y51) -> #REF! | Z52: =SUM(Z48:Z51) -> #REF! | AA52: =SUM(AA48:AA51) -> #REF! | AB52: =SUM(AB48:AB51) -> #REF! | AC52: =SUM(AC48:AC51) -> #REF! | AD52: =SUM(AD48:AD51) -> #REF! | AE52: =SUM(AE48:AE51) -> 0 | ... AI52: =SUM(AI48:AI51) -> 0
B54: Balance Sheet Metrics:
B55: Accounts Receivable | C55: ='Historical Financials'!#REF! -> #REF! | H55: ='Historical Financials'!#REF! -> #REF! | I55: ='Historical Financials'!#REF! -> #REF! | J55: ='Historical Financials'!#REF! -> #REF! | K55: ='Historical Financials'!#REF! -> #REF! | L55: ='Historical Financials'!#REF! -> #REF! | M55: ='Historical Financials'!#REF! -> #REF! | N55: ='Historical Financials'!#REF! -> #REF! | O55: ='Historical Financials'!#REF! -> #REF! | ... Q55: ='Historical Financials'!#REF! -> #REF! | X55: =K55 -> #REF! | Y55: =L55 -> #REF! | Z55: =M55 -> #REF! | AA55: =N55 -> #REF! | AB55: =O55 -> #REF! | AC55: =P55 -> #REF! | AD55: =Q55 -> #REF! | AE55: =R55 -> 0 | ... AI55: =V55 -> 0
B56: Accounts Payable | C56: ='Historical Financials'!#REF! -> #REF! | H56: ='Historical Financials'!J59 -> 585500 | I56: ='Historical Financials'!K59 -> 586851 | J56: ='Historical Financials'!L59 -> 647117 | K56: ='Historical Financials'!M59 -> 552730 | L56: ='Historical Financials'!N59 -> 621272 | M56: ='Historical Financials'!O59 -> 521315 | N56: ='Historical Financials'!P59 -> 597373 | O56: ='Historical Financials'!Q59 -> 544001 | ... Q56: ='Historical Financials'!S59 -> 566904 | X56: =K56 -> 552730 | Y56: =L56 -> 621272 | Z56: =M56 -> 521315 | AA56: =N56 -> 597373 | AB56: =O56 -> 544001 | AC56: =P56 -> 463777 | AD56: =Q56 -> 566904 | AE56: =R56 -> 0 | ... AI56: =V56 -> 0
B57: Unearned Revenue, Current | C57: ='Historical Financials'!#REF! -> #REF! | H57: ='Historical Financials'!J64 -> 0 | I57: ='Historical Financials'!K64 -> 0 | J57: ='Historical Financials'!L64 -> 0 | K57: ='Historical Financials'!M64 -> 0 | L57: ='Historical Financials'!N64 -> 0 | M57: ='Historical Financials'!O64 -> 0 | N57: ='Historical Financials'!P64 -> 195400 | O57: ='Historical Financials'!Q64 -> 0 | ... Q57: ='Historical Financials'!S64 -> 0 | X57: =K57 -> 0 | Y57: =L57 -> 0 | Z57: =M57 -> 0 | AA57: =N57 -> 195400 | AB57: =O57 -> 0 | AC57: =P57 -> 0 | AD57: =Q57 -> 0 | AE57: =R57 -> 0 | ... AI57: =V57 -> 0
B58: Unearned Revenue, Non-Current | C58: ='Historical Financials'!#REF! -> #REF! | H58: ='Historical Financials'!#REF! -> #REF! | I58: ='Historical Financials'!#REF! -> #REF! | J58: ='Historical Financials'!#REF! -> #REF! | K58: ='Historical Financials'!#REF! -> #REF! | L58: ='Historical Financials'!#REF! -> #REF! | M58: ='Historical Financials'!#REF! -> #REF! | N58: ='Historical Financials'!#REF! -> #REF! | O58: ='Historical Financials'!#REF! -> #REF! | ... Q58: ='Historical Financials'!#REF! -> #REF! | X58: =K58 -> #REF! | Y58: =L58 -> #REF! | Z58: =M58 -> #REF! | AA58: =N58 -> #REF! | AB58: =O58 -> #REF! | AC58: =P58 -> #REF! | AD58: =Q58 -> #REF! | AE58: =R58 -> 0 | ... AI58: =V58 -> 0
B59: Property Plant, and Equiptment | C59: ='Historical Financials'!#REF! -> #REF! | H59: ='Historical Financials'!J52 -> 10870 | I59: ='Historical Financials'!K52 -> 10870 | J59: ='Historical Financials'!L52 -> 10870 | K59: ='Historical Financials'!M52 -> 10870 | L59: ='Historical Financials'!N52 -> 10870 | M59: ='Historical Financials'!O52 -> 10870 | N59: ='Historical Financials'!P52 -> 10870 | O59: ='Historical Financials'!Q52 -> 10870 | ... Q59: ='Historical Financials'!S52 -> 10870 | X59: =K59 -> 10870 | Y59: =L59 -> 10870 | Z59: =M59 -> 10870 | AA59: =N59 -> 10870 | AB59: =O59 -> 10870 | AC59: =P59 -> 10870 | AD59: =Q59 -> 10870 | AE59: =R59 -> 0 | ... AI59: =V59 -> 0
B60: Current Liabilities | C60: ='Historical Financials'!#REF! -> #REF! | H60: ='Historical Financials'!J65 -> 1599747 | I60: ='Historical Financials'!K65 -> 1502054 | J60: ='Historical Financials'!L65 -> 1697771 | K60: ='Historical Financials'!M65 -> 1558010 | L60: ='Historical Financials'!N65 -> 1633900 | M60: ='Historical Financials'!O65 -> 1491174 | N60: ='Historical Financials'!P65 -> 1836939 | O60: ='Historical Financials'!Q65 -> 1658191 | ... Q60: ='Historical Financials'!S65 -> 1591234 | X60: =K60 -> 1558010 | Y60: =L60 -> 1633900 | Z60: =M60 -> 1491174 | AA60: =N60 -> 1836939 | AB60: =O60 -> 1658191 | AC60: =P60 -> 1572724 | AD60: =Q60 -> 1591234 | AE60: =R60 -> 0 | ... AI60: =V60 -> 0
B61: Total Liabilities | C61: ='Historical Financials'!#REF! -> #REF! | H61: ='Historical Financials'!J71 -> 3266416 | I61: ='Historical Financials'!K71 -> 3176926 | J61: ='Historical Financials'!L71 -> 3409294 | K61: ='Historical Financials'!M71 -> 3232869 | L61: ='Historical Financials'!N71 -> 3357651 | M61: ='Historical Financials'!O71 -> 3196883 | N61: ='Historical Financials'!P71 -> 3566466 | O61: ='Historical Financials'!Q71 -> 3432701 | ... Q61: ='Historical Financials'!S71 -> 3389248 | X61: =K61 -> 3232869 | Y61: =L61 -> 3357651 | Z61: =M61 -> 3196883 | AA61: =N61 -> 3566466 | AB61: =O61 -> 3432701 | AC61: =P61 -> 3331196 | AD61: =Q61 -> 3389248 | AE61: =R61 -> 0 | ... AI61: =V61 -> 0
B63: Consolidated Debt | C63: 0 | H63: 0 | I63: 0 | J63: 0 | K63: =D63 -> 0 | L63: 0 | M63: 0 | N63: 0 | O63: =E63 -> 0 | P63: 0 | Q63: 0 | X63: =K63 -> 0 | Y63: =L63 -> 0 | Z63: =M63 -> 0 | AA63: =N63 -> 0 | AB63: =O63 -> 0 | AC63: =P63 -> 0 | AD63: =Q63 -> 0 | AE63: =R63 -> 0 | ... AI63: =V63 -> 0
B64: Total Debt | C64: =SUM(C63:C63) -> 0 | D64: =SUM(D63:D63) -> 0 | E64: =SUM(E63:E63) -> 0 | F64: =SUM(F63:F63) -> 0 | H64: =SUM(H63:H63) -> 0 | I64: =SUM(I63:I63) -> 0 | J64: =SUM(J63:J63) -> 0 | K64: =SUM(K63:K63) -> 0 | L64: =SUM(L63:L63) -> 0 | M64: =SUM(M63:M63) -> 0 | N64: =SUM(N63:N63) -> 0 | O64: =SUM(O63:O63) -> 0 | ... V64: =SUM(V63:V63) -> 0 | X64: =SUM(X63:X63) -> 0 | Y64: =SUM(Y63:Y63) -> 0 | Z64: =SUM(Z63:Z63) -> 0 | AA64: =SUM(AA63:AA63) -> 0 | AB64: =SUM(AB63:AB63) -> 0 | AC64: =SUM(AC63:AC63) -> 0 | AD64: =SUM(AD63:AD63) -> 0 | AE64: =SUM(AE63:AE63) -> 0 | ... AI64: =SUM(AI63:AI63) -> 0
B66: Total Shareholder Equity | C66: ='Historical Financials'!#REF! -> #REF! | H66: ='Historical Financials'!J77 -> 1745620 | I66: ='Historical Financials'!K77 -> 1769068 | J66: ='Historical Financials'!L77 -> 1922255 | K66: ='Historical Financials'!M77 -> 1535373 | L66: ='Historical Financials'!N77 -> 2018068 | M66: ='Historical Financials'!O77 -> 2051877 | N66: ='Historical Financials'!P77 -> 2028542 | O66: ='Historical Financials'!Q77 -> 2279328 | ... Q66: ='Historical Financials'!S77 -> 2348160 | X66: =K66 -> 1535373 | Y66: =L66 -> 2018068 | Z66: =M66 -> 2051877 | AA66: =N66 -> 2028542 | AB66: =O66 -> 2279328 | AC66: =P66 -> 2300743 | AD66: =Q66 -> 2348160 | AE66: =R66 -> 0 | ... AI66: =V66 -> 0
B67: Total Book Capitalization | C67: =SUM(C64:C66) -> #REF! | D67: =SUM(D64:D66) -> 0 | E67: =SUM(E64:E66) -> 0 | F67: =SUM(F64:F66) -> 0 | H67: =SUM(H64:H66) -> 1745620 | I67: =SUM(I64:I66) -> 1769068 | J67: =SUM(J64:J66) -> 1922255 | K67: =SUM(K64:K66) -> 1535373 | L67: =SUM(L64:L66) -> 2018068 | M67: =SUM(M64:M66) -> 2051877 | N67: =SUM(N64:N66) -> 2028542 | O67: =SUM(O64:O66) -> 2279328 | ... V67: =SUM(V64:V66) -> 0 | X67: =SUM(X64:X66) -> 1535373 | Y67: =SUM(Y64:Y66) -> 2018068 | Z67: =SUM(Z64:Z66) -> 2051877 | AA67: =SUM(AA64:AA66) -> 2028542 | AB67: =SUM(AB64:AB66) -> 2279328 | AC67: =SUM(AC64:AC66) -> 2300743 | AD67: =SUM(AD64:AD66) -> 2348160 | AE67: =SUM(AE64:AE66) -> 0 | ... AI67: =SUM(AI64:AI66) -> 0
B69: Credit Metrics
B71: Total Leverage | C71: NM | L71: NM | M71: NM | N71: NM | O71: NM | P71: NM | Q71: NM | X71: NM | Y71: NM | Z71: NM | AA71: NM | AB71: NM | AC71: NM | AD71: NM
B72: Net Leverage (C&CE) | C72: NM | L72: NM | M72: NM | N72: NM | O72: NM | P72: NM | Q72: NM | X72: NM | Y72: NM | Z72: NM | AA72: NM | AB72: NM | AC72: NM | AD72: NM
B73: Interest Coverage | C73: NM | L73: NM | M73: NM | N73: NM | O73: NM | P73: NM | Q73: NM | X73: NM | Y73: NM | Z73: NM | AA73: NM | AB73: NM | AC73: NM | AD73: NM
B74: Debt Service Coverage | C74: NM | L74: NM | M74: NM | N74: NM | O74: NM | P74: NM | Q74: NM | X74: NM | Y74: NM | Z74: NM | AA74: NM | AB74: NM | AC74: NM | AD74: NM
B75: Fixed Charge Coverage | C75: NM | L75: NM | M75: NM | N75: NM | O75: NM | P75: NM | Q75: NM | X75: NM | Y75: NM | Z75: NM | AA75: NM | AB75: NM | AC75: NM | AD75: NM
A76: ` | B76: Debt-to-Book Capitalization | C76: NM | L76: NM | M76: NM | N76: NM | O76: NM | P76: NM | Q76: NM | X76: NM | Y76: NM | Z76: NM | AA76: NM | AB76: NM | AC76: NM | AD76: NM
