Workbook

Sheet Historical Financials
B2: Anavex Life Sciences Corp. (AVXL)
B3: Historical Financials
B4: $ in thousands except per share
A6: X | B6: Income Statement | C6: FYE | H6: Quarterly | R6: Quarterly | AC6: LTM | AI6: Variance
B7: Fiscal Period | C7: 2021 | D7: 2022 | E7: 2023 | F7: 2024 | H7: 1Q22 | I7: 2Q22 | J7: 3Q22 | K7: 4Q22 | L7: 1Q23 | M7: 2Q23 | N7: 3Q23 | O7: 4Q23 | P7: 1Q24 | Q7: 2Q24 | R7: 3Q24 | S7: 4Q24 | T7: 1Q25 | U7: 2Q25 | W7: =K7 -> 4Q22 | X7: =L7 -> 1Q23 | Y7: =M7 -> 2Q23 | Z7: =N7 -> 3Q23 | AA7: =O7 -> 4Q23 | AB7: =P7 -> 1Q24 | AC7: =Q7 -> 2Q24 | AD7: =R7 -> 3Q24 | ... AG7: =U7 -> 2Q25
B8: Fiscal Period End Date | C8: 44561 | D8: 44926 | E8: 45291 | F8: 45657 | H8: 44651 | I8: 44742 | J8: 44834 | K8: 44926 | L8: 45016 | M8: 45107 | N8: 45199 | O8: 45291 | P8: 45382 | Q8: 45473 | R8: 45565 | S8: 45657 | T8: 45747 | U8: 45838 | W8: =K8 -> 44926 | X8: =L8 -> 45016 | Y8: =M8 -> 45107 | Z8: =N8 -> 45199 | AA8: =O8 -> 45291 | AB8: =P8 -> 45382 | AC8: =Q8 -> 45473 | AD8: =R8 -> 45565 | ... AG8: =U8 -> 45838
B10: Consolidated Revenue | C10: 0 | D10: 0 | E10: 0 | F10: 0 | H10: 0 | I10: 0 | J10: 0 | K10: =SUM(D10-SUM(H10:J10)) -> 0 | L10: 0 | M10: 0 | N10: 0 | O10: =SUM(E10-SUM(L10:N10)) -> 0 | P10: 0 | Q10: 0 | R10: 0 | S10: =SUM(F10-SUM(P10:R10)) -> 0 | W10: =SUM(H10:K10) -> 0 | X10: =SUM(I10:L10) -> 0 | Y10: =SUM(J10:M10) -> 0 | Z10: =SUM(K10:N10) -> 0 | AA10: =SUM(L10:O10) -> 0 | AB10: =SUM(M10:P10) -> 0 | AC10: =SUM(N10:Q10) -> 0 | AD10: =SUM(O10:R10) -> 0 | ... AG10: =SUM(R10:U10) -> 0 | AI10: =SUM(AG10/AC10)-1 -> #DIV/0!
B11: Total Revenue | C11: =+SUM(C10:C10) -> 0 | D11: =+SUM(D10:D10) -> 0 | E11: =+SUM(E10:E10) -> 0 | F11: =+SUM(F10:F10) -> 0 | H11: =+SUM(H10:H10) -> 0 | I11: =+SUM(I10:I10) -> 0 | J11: =+SUM(J10:J10) -> 0 | K11: =+SUM(K10:K10) -> 0 | L11: =+SUM(L10:L10) -> 0 | M11: =+SUM(M10:M10) -> 0 | N11: =+SUM(N10:N10) -> 0 | O11: =+SUM(O10:O10) -> 0 | ... U11: =+SUM(U10:U10) -> 0 | W11: =+SUM(W10:W10) -> 0 | X11: =+SUM(X10:X10) -> 0 | Y11: =+SUM(Y10:Y10) -> 0 | Z11: =+SUM(Z10:Z10) -> 0 | AA11: =+SUM(AA10:AA10) -> 0 | AB11: =+SUM(AB10:AB10) -> 0 | AC11: =+SUM(AC10:AC10) -> 0 | AD11: =+SUM(AD10:AD10) -> 0 | ... AG11: =+SUM(AG10:AG10) -> 0 | AI11: =SUM(AG11/AC11)-1 -> #DIV/0!
B13: Cost of Sales | C13: 0 | D13: 0 | E13: 0 | F13: 0 | K13: =SUM(D13-SUM(H13:J13)) -> 0 | O13: =SUM(E13-SUM(L13:N13)) -> 0 | S13: =SUM(F13-SUM(P13:R13)) -> 0 | W13: =SUM(I13:L13) -> 0 | X13: =SUM(J13:M13) -> 0 | Y13: =SUM(K13:N13) -> 0 | Z13: =SUM(L13:O13) -> 0 | AA13: =SUM(M13:P13) -> 0 | AB13: =SUM(N13:Q13) -> 0 | AC13: =SUM(N13:Q13) -> 0 | AD13: =SUM(O13:R13) -> 0 | AE13: =SUM(P13:S13) -> 0 | AF13: =SUM(Q13:T13) -> 0 | AG13: =SUM(R13:U13) -> 0 | AI13: =SUM(AG13/AC13)-1 -> #DIV/0!
B14: Gross Profit | C14: =+SUM(C11+SUM(C13:C13)) -> 0 | D14: =+SUM(D11+SUM(D13:D13)) -> 0 | E14: =+SUM(E11+SUM(E13:E13)) -> 0 | F14: =+SUM(F11+SUM(F13:F13)) -> 0 | H14: =+SUM(H11+SUM(H13:H13)) -> 0 | I14: =+SUM(I11+SUM(I13:I13)) -> 0 | J14: =+SUM(J11+SUM(J13:J13)) -> 0 | K14: =+SUM(K11+SUM(K13:K13)) -> 0 | L14: =+SUM(L11+SUM(L13:L13)) -> 0 | M14: =+SUM(M11+SUM(M13:M13)) -> 0 | N14: =+SUM(N11+SUM(N13:N13)) -> 0 | O14: =+SUM(O11+SUM(O13:O13)) -> 0 | ... U14: =+SUM(U11+SUM(U13:U13)) -> 0 | W14: =+SUM(W11+SUM(W13:W13)) -> 0 | X14: =+SUM(X11+SUM(X13:X13)) -> 0 | Y14: =+SUM(Y11+SUM(Y13:Y13)) -> 0 | Z14: =+SUM(Z11+SUM(Z13:Z13)) -> 0 | AA14: =+SUM(AA11+SUM(AA13:AA13)) -> 0 | AB14: =+SUM(AB11+SUM(AB13:AB13)) -> 0 | AC14: =+SUM(AC11+SUM(AC13:AC13)) -> 0 | AD14: =+SUM(AD11+SUM(AD13:AD13)) -> 0 | ... AG14: =+SUM(AG11+SUM(AG13:AG13)) -> 0 | AI14: =SUM(AG14/AC14)-1 -> #DIV/0!
B15: Gross Margin (%) | C15: =C14/C11 -> #DIV/0! | D15: =D14/D11 -> #DIV/0! | E15: =E14/E11 -> #DIV/0! | F15: =F14/F11 -> #DIV/0! | H15: =H14/H11 -> #DIV/0! | I15: =I14/I11 -> #DIV/0! | J15: =J14/J11 -> #DIV/0! | K15: =K14/K11 -> #DIV/0! | L15: =L14/L11 -> #DIV/0! | M15: =M14/M11 -> #DIV/0! | N15: =N14/N11 -> #DIV/0! | O15: =O14/O11 -> #DIV/0! | ... U15: =U14/U11 -> #DIV/0! | W15: =W14/W11 -> #DIV/0! | X15: =X14/X11 -> #DIV/0! | Y15: =Y14/Y11 -> #DIV/0! | Z15: =Z14/Z11 -> #DIV/0! | AA15: =AA14/AA11 -> #DIV/0! | AB15: =AB14/AB11 -> #DIV/0! | AC15: =AC14/AC11 -> #DIV/0! | AD15: =AD14/AD11 -> #DIV/0! | ... AG15: =AG14/AG11 -> #DIV/0! | AI15: =SUM(AG15-AC15)*1000 -> #DIV/0!
B17: General and administrative | C17: -9018 | D17: -13070 | E17: -12039 | F17: -11039 | H17: -3066.951 | I17: -2915.158 | J17: -3185.451 | K17: =SUM(D17-SUM(H17:J17)) -> -3902.44 | L17: -3317.036 | M17: -2882.568 | N17: -3247.843 | O17: =SUM(E17-SUM(L17:N17)) -> -2591.553 | P17: -2609 | Q17: -2790 | R17: -2859 | S17: =SUM(F17-SUM(P17:R17)) -> -2781 | W17: =SUM(I17:L17) -> -13320.085 | X17: =SUM(J17:M17) -> -13287.495 | Y17: =SUM(K17:N17) -> -13349.887 | Z17: =SUM(L17:O17) -> -12039 | AA17: =SUM(M17:P17) -> -11330.964 | AB17: =SUM(N17:Q17) -> -11238.396 | AC17: =SUM(N17:Q17) -> -11238.396 | AD17: =SUM(O17:R17) -> -10849.553 | AE17: =SUM(P17:S17) -> -11039 | AF17: =SUM(Q17:T17) -> -8430 | AG17: =SUM(R17:U17) -> -5640 | AI17: =SUM(AG17/AC17)-1 -> -0.49814902
B18: Research and development | C18: -32984 | D18: -37916 | E18: -43717 | F18: -41838 | H18: -8656.439 | I18: -8604.589 | J18: -9273.269 | K18: =SUM(D18-SUM(H18:J18)) -> -11381.703 | L18: -12066.919 | M18: -11306.591 | N18: -10282.854 | O18: =SUM(E18-SUM(L18:N18)) -> -10060.636 | P18: -8684 | Q18: -9729 | R18: -11870 | S18: =SUM(F18-SUM(P18:R18)) -> -11555 | W18: =SUM(I18:L18) -> -41326.48 | X18: =SUM(J18:M18) -> -44028.482 | Y18: =SUM(K18:N18) -> -45038.067 | Z18: =SUM(L18:O18) -> -43717 | AA18: =SUM(M18:P18) -> -40334.081 | AB18: =SUM(N18:Q18) -> -38756.49 | AC18: =SUM(N18:Q18) -> -38756.49 | AD18: =SUM(O18:R18) -> -40343.636 | AE18: =SUM(P18:S18) -> -41838 | AF18: =SUM(Q18:T18) -> -33154 | AG18: =SUM(R18:U18) -> -23425 | AI18: =SUM(AG18/AC18)-1 -> -0.3955851
B19: Operating Profit | C19: =+SUM(C14+SUM(C17:C18)) -> -42002 | D19: =+SUM(D14+SUM(D17:D18)) -> -50986 | E19: =+SUM(E14+SUM(E17:E18)) -> -55756 | F19: =+SUM(F14+SUM(F17:F18)) -> -52877 | H19: =+SUM(H14+SUM(H17:H18)) -> -11723.39 | I19: =+SUM(I14+SUM(I17:I18)) -> -11519.747 | J19: =+SUM(J14+SUM(J17:J18)) -> -12458.72 | K19: =+SUM(K14+SUM(K17:K18)) -> -15284.143 | L19: =+SUM(L14+SUM(L17:L18)) -> -15383.955 | M19: =+SUM(M14+SUM(M17:M18)) -> -14189.159 | N19: =+SUM(N14+SUM(N17:N18)) -> -13530.697 | O19: =+SUM(O14+SUM(O17:O18)) -> -12652.189 | ... U19: =+SUM(U14+SUM(U17:U18)) -> 0 | W19: =+SUM(W14+SUM(W17:W18)) -> -54646.565 | X19: =+SUM(X14+SUM(X17:X18)) -> -57315.977 | Y19: =+SUM(Y14+SUM(Y17:Y18)) -> -58387.954 | Z19: =+SUM(Z14+SUM(Z17:Z18)) -> -55756 | AA19: =+SUM(AA14+SUM(AA17:AA18)) -> -51665.045 | AB19: =+SUM(AB14+SUM(AB17:AB18)) -> -49994.886 | AC19: =+SUM(AC14+SUM(AC17:AC18)) -> -49994.886 | AD19: =+SUM(AD14+SUM(AD17:AD18)) -> -51193.189 | ... AG19: =+SUM(AG14+SUM(AG17:AG18)) -> -29065 | AI19: =SUM(AG19/AC19)-1 -> -0.41864054
B20: Operating Margin (%) | C20: =C19/C11 -> #DIV/0! | D20: =D19/D11 -> #DIV/0! | E20: =E19/E11 -> #DIV/0! | F20: =F19/F11 -> #DIV/0! | H20: =H19/H11 -> #DIV/0! | I20: =I19/I11 -> #DIV/0! | J20: =J19/J11 -> #DIV/0! | K20: =K19/K11 -> #DIV/0! | L20: =L19/L11 -> #DIV/0! | M20: =M19/M11 -> #DIV/0! | N20: =N19/N11 -> #DIV/0! | O20: =O19/O11 -> #DIV/0! | ... U20: =U19/U11 -> #DIV/0! | W20: =W19/W11 -> #DIV/0! | X20: =X19/X11 -> #DIV/0! | Y20: =Y19/Y11 -> #DIV/0! | Z20: =Z19/Z11 -> #DIV/0! | AA20: =AA19/AA11 -> #DIV/0! | AB20: =AB19/AB11 -> #DIV/0! | AC20: =AC19/AC11 -> #DIV/0! | AD20: =AD19/AD11 -> #DIV/0! | ... AG20: =AG19/AG11 -> #DIV/0! | AI20: =SUM(AG20-AC20)*1000 -> #DIV/0!
B22: Grant income | C22: 54 | E22: 25 | F22: 75 | K22: =SUM(D22-SUM(H22:J22)) -> 0 | L22: 25 | O22: =SUM(E22-SUM(L22:N22)) -> 0 | Q22: 0 | R22: 0 | S22: =SUM(F22-SUM(P22:R22)) -> 75 | W22: =SUM(I22:L22) -> 25 | X22: =SUM(J22:M22) -> 25 | Y22: =SUM(K22:N22) -> 25 | Z22: =SUM(L22:O22) -> 25 | AA22: =SUM(M22:P22) -> 0 | AB22: =SUM(N22:Q22) -> 0 | AC22: =SUM(N22:Q22) -> 0 | AD22: =SUM(O22:R22) -> 0 | AE22: =SUM(P22:S22) -> 75 | AF22: =SUM(Q22:T22) -> 75 | AG22: =SUM(R22:U22) -> 75 | AI22: =SUM(AG22/AC22)-1 -> #DIV/0!
B23: Research and development incentive income | C23: 4547 | D23: 3323 | E23: 2718 | F23: 2291 | H23: 810.73 | I23: 835.513 | J23: 682.432 | K23: =SUM(D23-SUM(H23:J23)) -> 994.325 | L23: 733.59 | M23: 749.681 | N23: 564.842 | O23: =SUM(E23-SUM(L23:N23)) -> 669.887 | P23: 592 | Q23: 472 | R23: 526 | S23: =SUM(F23-SUM(P23:R23)) -> 701 | AC23: =SUM(N23:Q23) -> 2298.729 | AD23: =SUM(O23:R23) -> 2259.887 | AE23: =SUM(P23:S23) -> 2291 | AF23: =SUM(Q23:T23) -> 1699 | AG23: =SUM(R23:U23) -> 1227 | AI23: =SUM(AG23/AC23)-1 -> -0.46622677
B24: Interest income (expense), net | C24: 26 | D24: 947 | E24: 6519 | F24: 7320 | H24: 4.91 | I24: 7.578 | J24: 229.917 | K24: =SUM(D24-SUM(H24:J24)) -> 704.595 | L24: 1267.618 | M24: 1465.221 | N24: 1827.945 | O24: =SUM(E24-SUM(L24:N24)) -> 1958.216 | P24: 2008 | Q24: 1756 | R24: 1796 | S24: =SUM(F24-SUM(P24:R24)) -> 1760 | AC24: =SUM(N24:Q24) -> 7550.161 | AD24: =SUM(O24:R24) -> 7518.216 | AE24: =SUM(P24:S24) -> 7320 | AF24: =SUM(Q24:T24) -> 5312 | AG24: =SUM(R24:U24) -> 3556 | AI24: =SUM(AG24/AC24)-1 -> -0.52901667
B25: Other financing expense | E25: -964 | F25: 0 | K25: =SUM(D25-SUM(H25:J25)) -> 0 | M25: -964.344 | O25: =SUM(E25-SUM(L25:N25)) -> 0.344 | P25: 0 | Q25: 0 | R25: 0 | S25: =SUM(F25-SUM(P25:R25)) -> 0 | AC25: =SUM(N25:Q25) -> 0.344 | AD25: =SUM(O25:R25) -> 0.344 | AE25: =SUM(P25:S25) -> 0 | AF25: =SUM(Q25:T25) -> 0 | AG25: =SUM(R25:U25) -> 0 | AI25: =SUM(AG25/AC25)-1 -> -1
B26: Foreign exchange gain (loss) | C26: -266 | D26: -904 | E26: -40 | F26: 189 | H26: 55.363 | I26: 268.645 | J26: -732.549 | K26: =SUM(D26-SUM(H26:J26)) -> -495.459 | L26: 365.983 | M26: -118.678 | N26: -101.066 | O26: =SUM(E26-SUM(L26:N26)) -> -186.239 | P26: 156 | Q26: -150 | R26: 67 | S26: =SUM(F26-SUM(P26:R26)) -> 116 | W26: =SUM(I26:L26) -> -593.38 | X26: =SUM(J26:M26) -> -980.703 | Y26: =SUM(K26:N26) -> -349.22 | Z26: =SUM(L26:O26) -> -40 | AA26: =SUM(M26:P26) -> -249.983 | AB26: =SUM(N26:Q26) -> -281.305 | AC26: =SUM(N26:Q26) -> -281.305 | AD26: =SUM(O26:R26) -> -113.239 | AE26: =SUM(P26:S26) -> 189 | AF26: =SUM(Q26:T26) -> 33 | AG26: =SUM(R26:U26) -> 183 | AI26: =SUM(AG26/AC26)-1 -> -1.6505395
B27: Gain on settlement of accounts payable | K27: =SUM(D27-SUM(H27:J27)) -> 0 | O27: =SUM(E27-SUM(L27:N27)) -> 0 | R27: 59 | S27: =SUM(F27-SUM(P27:R27)) -> -59 | W27: =SUM(I27:L27) -> 0 | X27: =SUM(J27:M27) -> 0 | Y27: =SUM(K27:N27) -> 0 | Z27: =SUM(L27:O27) -> 0 | AA27: =SUM(M27:P27) -> 0 | AB27: =SUM(N27:Q27) -> 0 | AC27: =SUM(N27:Q27) -> 0 | AD27: =SUM(O27:R27) -> 59 | AE27: =SUM(P27:S27) -> 0 | AF27: =SUM(Q27:T27) -> 0 | AG27: =SUM(R27:U27) -> 0 | AI27: =SUM(AG27/AC27)-1 -> #DIV/0!
B28: Earning Before Taxes | C28: =SUM(C19+SUM(C22:C27)) -> -37641 | D28: =SUM(D19+SUM(D22:D27)) -> -47620 | E28: =SUM(E19+SUM(E22:E27)) -> -47498 | F28: =SUM(F19+SUM(F22:F27)) -> -43002 | H28: =SUM(H19+SUM(H22:H27)) -> -10852.387 | I28: =SUM(I19+SUM(I22:I27)) -> -10408.011 | J28: =SUM(J19+SUM(J22:J27)) -> -12278.92 | K28: =SUM(K19+SUM(K22:K27)) -> -14080.682 | L28: =SUM(L19+SUM(L22:L27)) -> -12991.764 | M28: =SUM(M19+SUM(M22:M27)) -> -13057.279 | N28: =SUM(N19+SUM(N22:N27)) -> -11238.976 | O28: =SUM(O19+SUM(O22:O27)) -> -10209.981 | ... U28: =SUM(U19+SUM(U22:U27)) -> 0 | W28: =SUM(W19+SUM(W22:W27)) -> -55214.945 | X28: =SUM(X19+SUM(X22:X27)) -> -58271.68 | Y28: =SUM(Y19+SUM(Y22:Y27)) -> -58712.174 | Z28: =SUM(Z19+SUM(Z22:Z27)) -> -55771 | AA28: =SUM(AA19+SUM(AA22:AA27)) -> -51915.028 | AB28: =SUM(AB19+SUM(AB22:AB27)) -> -50276.191 | AC28: =SUM(AC19+SUM(AC22:AC27)) -> -40426.957 | AD28: =SUM(AD19+SUM(AD22:AD27)) -> -41468.981 | ... AG28: =SUM(AG19+SUM(AG22:AG27)) -> -24024 | AI28: =SUM(AG28/AC28)-1 -> -0.40574305
B29: EBT Margin (%) | C29: =C28/C11 -> #DIV/0! | D29: =D28/D11 -> #DIV/0! | E29: =E28/E11 -> #DIV/0! | F29: =F28/F11 -> #DIV/0! | H29: =H28/H11 -> #DIV/0! | I29: =I28/I11 -> #DIV/0! | J29: =J28/J11 -> #DIV/0! | K29: =K28/K11 -> #DIV/0! | L29: =L28/L11 -> #DIV/0! | M29: =M28/M11 -> #DIV/0! | N29: =N28/N11 -> #DIV/0! | O29: =O28/O11 -> #DIV/0! | ... U29: =U28/U11 -> #DIV/0! | W29: =W28/W11 -> #DIV/0! | X29: =X28/X11 -> #DIV/0! | Y29: =Y28/Y11 -> #DIV/0! | Z29: =Z28/Z11 -> #DIV/0! | AA29: =AA28/AA11 -> #DIV/0! | AB29: =AB28/AB11 -> #DIV/0! | AC29: =AC28/AC11 -> #DIV/0! | AD29: =AD28/AD11 -> #DIV/0! | ... AG29: =AG28/AG11 -> #DIV/0! | AI29: =SUM(AG29-AC29)*1000 -> #DIV/0!
B31: Provision for taxes | C31: -268 | D31: -358 | E31: -7 | F31: 0 | H31: -29.98 | I31: -29.8 | J31: -88.421 | K31: =SUM(D31-SUM(H31:J31)) -> -209.799 | L31: 20.046 | M31: -50 | N31: -41 | O31: =SUM(E31-SUM(L31:N31)) -> 63.954 | P31: -85 | Q31: -105 | R31: 67 | S31: =SUM(F31-SUM(P31:R31)) -> 123 | T31: 0 | W31: =SUM(I31:L31) -> -307.974 | X31: =SUM(J31:M31) -> -328.174 | Y31: =SUM(K31:N31) -> -280.753 | Z31: =SUM(L31:O31) -> -7 | AA31: =SUM(M31:P31) -> -112.046 | AB31: =SUM(N31:Q31) -> -167.046 | AC31: =SUM(N31:Q31) -> -167.046 | AD31: =SUM(O31:R31) -> -59.046 | AE31: =SUM(P31:S31) -> 0 | AF31: =SUM(Q31:T31) -> 85 | AG31: =SUM(R31:U31) -> 190 | AI31: =SUM(AG31/AC31)-1 -> -2.1374113
B32: Net loss | C32: =SUM(C28+C31) -> -37909 | D32: =SUM(D28+D31) -> -47978 | E32: =SUM(E28+E31) -> -47505 | F32: =SUM(F28+F31) -> -43002 | H32: =SUM(H28+H31) -> -10882.367 | I32: =SUM(I28+I31) -> -10437.811 | J32: =SUM(J28+J31) -> -12367.341 | K32: =SUM(K28+K31) -> -14290.481 | L32: =SUM(L28+L31) -> -12971.718 | M32: =SUM(M28+M31) -> -13107.279 | N32: =SUM(N28+N31) -> -11279.976 | O32: =SUM(O28+O31) -> -10146.027 | ... U32: =SUM(U28+U31) -> 0 | W32: =SUM(W28+W31) -> -55522.919 | X32: =SUM(X28+X31) -> -58599.854 | Y32: =SUM(Y28+Y31) -> -58992.927 | Z32: =SUM(Z28+Z31) -> -55778 | AA32: =SUM(AA28+AA31) -> -52027.074 | AB32: =SUM(AB28+AB31) -> -50443.237 | AC32: =SUM(AC28+AC31) -> -40594.003 | AD32: =SUM(AD28+AD31) -> -41528.027 | ... AG32: =SUM(AG28+AG31) -> -23834 | AI32: =SUM(AG32/AC32)-1 -> -0.41286894
B33: Net Margin (%) | C33: =C32/C11 -> #DIV/0! | D33: =D32/D11 -> #DIV/0! | E33: =E32/E11 -> #DIV/0! | F33: =F32/F11 -> #DIV/0! | H33: =H32/H11 -> #DIV/0! | I33: =I32/I11 -> #DIV/0! | J33: =J32/J11 -> #DIV/0! | K33: =K32/K11 -> #DIV/0! | L33: =L32/L11 -> #DIV/0! | M33: =M32/M11 -> #DIV/0! | N33: =N32/N11 -> #DIV/0! | O33: =O32/O11 -> #DIV/0! | ... U33: =U32/U11 -> #DIV/0! | W33: =W32/W11 -> #DIV/0! | X33: =X32/X11 -> #DIV/0! | Y33: =Y32/Y11 -> #DIV/0! | Z33: =Z32/Z11 -> #DIV/0! | AA33: =AA32/AA11 -> #DIV/0! | AB33: =AB32/AB11 -> #DIV/0! | AC33: =AC32/AC11 -> #DIV/0! | AD33: =AD32/AD11 -> #DIV/0! | ... AG33: =AG32/AG11 -> #DIV/0! | AI33: =SUM(AG33-AC33)*1000 -> #DIV/0!
B35: Basic shares | K35: =D35 -> 0 | O35: =E35 -> 0 | S35: =F35 -> 0 | W35: =K35 -> 0 | X35: =L35 -> 0 | Y35: =M35 -> 0 | Z35: =N35 -> 0 | AA35: =O35 -> 0 | AB35: =P35 -> 0 | AC35: =Q35 -> 0 | AD35: =R35 -> 0 | ... AG35: =U35 -> 0 | AI35: =SUM(AG35/AC35)-1 -> #DIV/0!
B36: Basic EPS | C36: =C32/C35 -> #DIV/0! | D36: =D32/D35 -> #DIV/0! | E36: =E32/E35 -> #DIV/0! | F36: =F32/F35 -> #DIV/0! | H36: =H32/H35 -> #DIV/0! | I36: =I32/I35 -> #DIV/0! | J36: =J32/J35 -> #DIV/0! | K36: =K32/K35 -> #DIV/0! | L36: =L32/L35 -> #DIV/0! | M36: =M32/M35 -> #DIV/0! | N36: =N32/N35 -> #DIV/0! | O36: =O32/O35 -> #DIV/0! | ... U36: =U32/U35 -> #DIV/0! | W36: =W32/W35 -> #DIV/0! | X36: =X32/X35 -> #DIV/0! | Y36: =Y32/Y35 -> #DIV/0! | Z36: =Z32/Z35 -> #DIV/0! | AA36: =AA32/AA35 -> #DIV/0! | AB36: =AB32/AB35 -> #DIV/0! | AC36: =AC32/AC35 -> #DIV/0! | AD36: =AD32/AD35 -> #DIV/0! | ... AG36: =AG32/AG35 -> #DIV/0! | AI36: =SUM(AG36/AC36)-1 -> #DIV/0!
B38: Fully Diluted Shares | E38: 79787.596 | F38: 83468.049 | H38: 75997.738 | I38: 76248.603 | J38: 77442.236 | K38: =D38 -> 0 | M38: 78304.363 | N38: 80875.235 | O38: =E38 -> 79787.596 | Q38: 82464.226 | R38: 84535.328 | S38: =F38 -> 83468.049 | W38: =L38 -> 0 | X38: =M38 -> 78304.363 | Y38: =N38 -> 80875.235 | Z38: =O38 -> 79787.596 | AA38: =P38 -> 0 | AB38: =Q38 -> 82464.226 | AC38: =Q38 -> 82464.226 | AD38: =R38 -> 84535.328 | AE38: =S38 -> 83468.049 | AF38: =T38 -> 0 | AG38: =U38 -> 0 | AI38: =SUM(AG38/AC38)-1 -> -1
B39: Diluted EPS | C39: =C32/C38 -> #DIV/0! | D39: =D32/D38 -> #DIV/0! | E39: =E32/E38 -> -0.5953933 | F39: =F32/F38 -> -0.51519115 | H39: =H32/H38 -> -0.1431933 | I39: =I32/I38 -> -0.13689183 | J39: =J32/J38 -> -0.15969762 | K39: =K32/K38 -> #DIV/0! | L39: =L32/L38 -> #DIV/0! | M39: =M32/M38 -> -0.16738887 | N39: =N32/N38 -> -0.1394738 | O39: =O32/O38 -> -0.12716296 | ... U39: =U32/U38 -> #DIV/0! | W39: =W32/W38 -> #DIV/0! | X39: =X32/X38 -> -0.74836001 | Y39: =Y32/Y38 -> -0.72943129 | Z39: =Z32/Z38 -> -0.6990811 | AA39: =AA32/AA38 -> #DIV/0! | AB39: =AB32/AB38 -> -0.61169842 | AC39: =AC32/AC38 -> -0.49226198 | AD39: =AD32/AD38 -> -0.49125056 | ... AG39: =AG32/AG38 -> #DIV/0! | AI39: =SUM(AG39/AC39)-1 -> #DIV/0!
A41: X | B41: Balance Sheet | C41: FYE | D41: FYE | H41: Quarterly | R41: Quarterly | AC41: LTM | AI41: Variance
B42: =B7 -> Fiscal Period | C42: =C7 -> 2021 | D42: =D7 -> 2022 | E42: =E7 -> 2023 | F42: =F7 -> 2024 | H42: =H7 -> 1Q22 | I42: =I7 -> 2Q22 | J42: =J7 -> 3Q22 | K42: =K7 -> 4Q22 | L42: =L7 -> 1Q23 | M42: =M7 -> 2Q23 | N42: =N7 -> 3Q23 | O42: =O7 -> 4Q23 | ... U42: =U7 -> 2Q25 | W42: =W7 -> 4Q22 | X42: =X7 -> 1Q23 | Y42: =Y7 -> 2Q23 | Z42: =Z7 -> 3Q23 | AA42: =AA7 -> 4Q23 | AB42: =AB7 -> 1Q24 | AC42: =AC7 -> 2Q24 | AD42: =AD7 -> 3Q24 | ... AG42: =AG7 -> 2Q25
B43: =B8 -> Fiscal Period End Date | C43: =C8 -> 44561 | D43: =D8 -> 44926 | E43: =E8 -> 45291 | F43: =F8 -> 45657 | H43: =H8 -> 44651 | I43: =I8 -> 44742 | J43: =J8 -> 44834 | K43: =K8 -> 44926 | L43: =L8 -> 45016 | M43: =M8 -> 45107 | N43: =N8 -> 45199 | O43: =O8 -> 45291 | ... U43: =U8 -> 45838 | W43: =W8 -> 44926 | X43: =X8 -> 45016 | Y43: =Y8 -> 45107 | Z43: =Z8 -> 45199 | AA43: =AA8 -> 45291 | AB43: =AB8 -> 45382 | AC43: =AC8 -> 45473 | AD43: =AD8 -> 45565 | ... AG43: =AG8 -> 45838
B45: Total Assets
B46: Cash and cash equivalents | C46: 152107.74 | D46: 149158 | E46: 151024 | F46: 132187 | H46: 151146.36 | I46: 153342.56 | J46: 153199.35 | K46: =D46 -> 149158 | L46: 143621.85 | M46: 153466.96 | N46: 154817.16 | O46: =E46 -> 151024 | P46: 143765 | Q46: 139386 | R46: 138756 | S46: =F46 -> 132187 | W46: =K46 -> 149158 | X46: =L46 -> 143621.85 | Y46: =M46 -> 153466.96 | Z46: =N46 -> 154817.16 | AA46: =O46 -> 151024 | AB46: =P46 -> 143765 | AC46: =Q46 -> 139386 | AD46: =R46 -> 138756 | ... AG46: =U46 -> 0 | AI46: =SUM(AG46/AC46)-1 -> -1
B47: Incentive and tax receivables | C47: 9136.831 | D47: 3193 | E47: 2709 | F47: 2449 | H47: 5372.153 | I47: 6468.987 | J47: 6559.829 | K47: =D47 -> 3193 | L47: 4094.431 | M47: 4737.661 | N47: 2165.127 | O47: =E47 -> 2709 | P47: 3549 | Q47: 3785 | R47: 1720 | S47: =F47 -> 2449 | W47: =K47 -> 3193 | X47: =L47 -> 4094.431 | Y47: =M47 -> 4737.661 | Z47: =N47 -> 2165.127 | AA47: =O47 -> 2709 | AB47: =P47 -> 3549 | AC47: =Q47 -> 3785 | AD47: =R47 -> 1720 | ... AG47: =U47 -> 0 | AI47: =SUM(AG47/AC47)-1 -> -1
B48: Prepaid expenses and other current assets | C48: 371.914 | D48: 354 | E48: 653 | F48: 931 | H48: 377.86 | I48: 464.605 | J48: 461.963 | K48: =D48 -> 354 | L48: 655.643 | M48: 981.774 | N48: 827.572 | O48: =E48 -> 653 | P48: 756 | Q48: 1345 | R48: 1059 | S48: =F48 -> 931 | W48: =K48 -> 354 | X48: =L48 -> 655.643 | Y48: =M48 -> 981.774 | Z48: =N48 -> 827.572 | AA48: =O48 -> 653 | AB48: =P48 -> 756 | AC48: =Q48 -> 1345 | AD48: =R48 -> 1059 | ... AG48: =U48 -> 0 | AI48: =SUM(AG48/AC48)-1 -> -1
B49: Total Assets | C49: =SUM(C46:C48) -> 161616.49 | D49: =SUM(D46:D48) -> 152705 | E49: =SUM(E46:E48) -> 154386 | F49: =SUM(F46:F48) -> 135567 | H49: =SUM(H46:H48) -> 156896.37 | I49: =SUM(I46:I48) -> 160276.15 | J49: =SUM(J46:J48) -> 160221.14 | K49: =SUM(K46:K48) -> 152705 | L49: =SUM(L46:L48) -> 148371.92 | M49: =SUM(M46:M48) -> 159186.4 | N49: =SUM(N46:N48) -> 157809.86 | O49: =SUM(O46:O48) -> 154386 | ... U49: =SUM(U46:U48) -> 0 | W49: =SUM(W46:W48) -> 152705 | X49: =SUM(X46:X48) -> 148371.92 | Y49: =SUM(Y46:Y48) -> 159186.4 | Z49: =SUM(Z46:Z48) -> 157809.86 | AA49: =SUM(AA46:AA48) -> 154386 | AB49: =SUM(AB46:AB48) -> 148070 | AC49: =SUM(AC46:AC48) -> 144516 | AD49: =SUM(AD46:AD48) -> 141535 | ... AG49: =SUM(AG46:AG48) -> 0 | AI49: =SUM(AG49/AC49)-1 -> -1
B51: Total Liabilities
B52: Accounts payable | C52: 4739.781 | D52: 3825 | E52: 4322 | F52: 9627 | H52: 4634.791 | I52: 2631.888 | J52: 3126.892 | K52: =D52 -> 3825 | L52: 5288.261 | M52: 6281.742 | N52: 4152.846 | O52: =E52 -> 4322 | P52: 4292 | Q52: 3726 | R52: 3503 | S52: =F52 -> 9627 | W52: =K52 -> 3825 | X52: =L52 -> 5288.261 | Y52: =M52 -> 6281.742 | Z52: =N52 -> 4152.846 | AA52: =O52 -> 4322 | AB52: =P52 -> 4292 | AC52: =Q52 -> 3726 | AD52: =R52 -> 3503 | ... AG52: =U52 -> 0 | AI52: =SUM(AG52/AC52)-1 -> -1
B53: Accrued liabilities | C53: 5614.774 | D53: 5945 | E53: 7295 | F53: 4835 | H53: 5450.04 | I53: 4995.388 | J53: 5913.821 | K53: =D53 -> 5945 | L53: 7042.822 | M53: 6822.838 | N53: 5985.658 | O53: =E53 -> 7295 | P53: 7286 | Q53: 4915 | R53: 7334 | S53: =F53 -> 4835 | W53: =L53 -> 7042.822 | X53: =M53 -> 6822.838 | Y53: =N53 -> 5985.658 | Z53: =O53 -> 7295 | AA53: =P53 -> 7286 | AB53: =Q53 -> 4915 | AC53: =Q53 -> 4915 | AD53: =R53 -> 7334 | AE53: =S53 -> 4835 | AF53: =T53 -> 0 | AG53: =U53 -> 0 | AI53: =SUM(AG53/AC53)-1 -> -1
B54: Deferred grant income | C54: 443.831 | D54: 444 | E54: 917 | F54: 842 | H54: 443.831 | I54: 443.831 | J54: 443.831 | K54: =D54 -> 444 | L54: 916.763 | M54: 916.763 | N54: 916.763 | O54: =E54 -> 917 | P54: 917 | Q54: 917 | R54: 917 | S54: =F54 -> 842 | W54: =L54 -> 916.763 | X54: =M54 -> 916.763 | Y54: =N54 -> 916.763 | Z54: =O54 -> 917 | AA54: =P54 -> 917 | AB54: =Q54 -> 917 | AC54: =Q54 -> 917 | AD54: =R54 -> 917 | AE54: =S54 -> 842 | AF54: =T54 -> 0 | AG54: =U54 -> 0 | AI54: =SUM(AG54/AC54)-1 -> -1
B55: Total Liabilities | C55: =SUM(C52:C54) -> 10798.386 | D55: =SUM(D52:D54)+D49 -> 162919 | E55: =SUM(E52:E54)+E49 -> 166920 | F55: =SUM(F52:F54) -> 15304 | H55: =SUM(H52:H54) -> 10528.662 | I55: =SUM(I52:I54) -> 8071.107 | J55: =SUM(J52:J54) -> 9484.544 | K55: =SUM(K52:K54) -> 10214 | L55: =SUM(L52:L54) -> 13247.846 | M55: =SUM(M52:M54) -> 14021.343 | N55: =SUM(N52:N54) -> 11055.267 | O55: =SUM(O52:O54) -> 12534 | ... U55: =SUM(U52:U54) -> 0 | W55: =SUM(W52:W54)+W49 -> 164489.58 | X55: =SUM(X52:X54)+X49 -> 161399.78 | Y55: =SUM(Y52:Y54)+Y49 -> 172370.56 | Z55: =SUM(Z52:Z54)+Z49 -> 170174.71 | AA55: =SUM(AA52:AA54)+AA49 -> 166911 | AB55: =SUM(AB52:AB54)+AB49 -> 158194 | AC55: =SUM(AC52:AC54)+AC49 -> 154074 | AD55: =SUM(AD52:AD54)+AD49 -> 153289 | ... AG55: =SUM(AG52:AG54)+AG49 -> 0 | AI55: =SUM(AG55/AC55)-1 -> -1
B57: Preferred stock | C57: 0 | D57: 0 | E57: 0 | F57: 0 | H57: 0 | J57: 0 | K57: =D57 -> 0 | L57: 0 | M57: 0 | N57: 0 | O57: =E57 -> 0 | P57: 0 | Q57: 0 | R57: 0 | S57: =F57 -> 0 | W57: =L57 -> 0 | X57: =M57 -> 0 | Y57: =N57 -> 0 | Z57: =O57 -> 0 | AA57: =P57 -> 0 | AB57: =Q57 -> 0 | AC57: =Q57 -> 0 | AD57: =R57 -> 0 | AE57: =S57 -> 0 | AF57: =T57 -> 0 | AG57: =U57 -> 0 | AI57: =SUM(AG57/AC57)-1 -> #DIV/0!
B58: Common stock | C58: 75.92 | D58: 78 | E58: 82 | F58: 85 | H58: 76.156 | I58: 77.163 | J58: 77.944 | K58: =D58 -> 78 | L58: 78.033 | M58: 80.236 | N58: 81391 | O58: =E58 -> 82 | P58: 82 | Q58: 84 | R58: 85 | S58: =F58 -> 85 | AC58: =Q58 -> 84 | AD58: =R58 -> 85 | AE58: =S58 -> 85 | AF58: =T58 -> 0 | AG58: =U58 -> 0 | AI58: =SUM(AG58/AC58)-1 -> -1
B59: Share proceeds receivable | I59: -403.696 | K59: =D59 -> 0 | O59: =E59 -> 0 | P59: 0 | Q59: -234 | R59: -89 | S59: =F59 -> 0 | AC59: =Q59 -> -234 | AD59: =R59 -> -89 | AE59: =S59 -> 0 | AF59: =T59 -> 0 | AG59: =U59 -> 0 | AI59: =SUM(AG59/AC59)-1 -> -1
B60: Additional paid-in capital | C60: 348328.05 | D60: 387977 | E60: 434839 | F60: 456249 | H60: 354759.78 | I60: 371437.62 | J60: 381932.04 | K60: =D60 -> 387977 | L60: 393581.54 | M60: 416727.6 | N60: 429595.96 | O60: =E60 -> 434839 | P60: 437184 | Q60: 447345 | R60: 454236 | S60: =F60 -> 456249 | W60: =L60 -> 393581.54 | X60: =M60 -> 416727.6 | Y60: =N60 -> 429595.96 | Z60: =O60 -> 434839 | AA60: =P60 -> 437184 | AB60: =Q60 -> 447345 | AC60: =Q60 -> 447345 | AD60: =R60 -> 454236 | AE60: =S60 -> 456249 | AF60: =T60 -> 0 | AG60: =U60 -> 0 | AI60: =SUM(AG60/AC60)-1 -> -1
B61: Accumulated deficit | C61: -197585.86 | D61: -245564 | E61: -293069 | F61: -336071 | H61: -208468.23 | I61: -218906.04 | J61: -231273.38 | K61: =D61 -> -245564 | L61: -258535.5 | M61: -271642.78 | N61: -282922.76 | O61: =E61 -> -293069 | P61: -301691 | Q61: -312237 | R61: -324451 | S61: =F61 -> -336071 | W61: =L61 -> -258535.5 | X61: =M61 -> -271642.78 | Y61: =N61 -> -282922.76 | Z61: =O61 -> -293069 | AA61: =P61 -> -301691 | AB61: =Q61 -> -312237 | AC61: =Q61 -> -312237 | AD61: =R61 -> -324451 | AE61: =S61 -> -336071 | AF61: =T61 -> 0 | AG61: =U61 -> 0 | AI61: =SUM(AG61/AC61)-1 -> -1
B62: Total stockholders' equity | C62: =SUM(C57:C61) -> 150818.1 | D62: =SUM(D57:D61) -> 142491 | E62: =SUM(E57:E61) -> 141852 | F62: =SUM(F57:F61) -> 120263 | H62: =SUM(H57:H61) -> 146367.71 | I62: =SUM(I57:I61) -> 152205.04 | J62: =SUM(J57:J61) -> 150736.6 | K62: =SUM(K57:K61) -> 142491 | L62: =SUM(L57:L61) -> 135124.08 | M62: =SUM(M57:M61) -> 145165.05 | N62: =SUM(N57:N61) -> 228064.21 | O62: =SUM(O57:O61) -> 141852 | ... U62: =SUM(U57:U61) -> 0 | W62: =SUM(W57:W61) -> 135046.04 | X62: =SUM(X57:X61) -> 145084.82 | Y62: =SUM(Y57:Y61) -> 146673.21 | Z62: =SUM(Z57:Z61) -> 141770 | AA62: =SUM(AA57:AA61) -> 135493 | AB62: =SUM(AB57:AB61) -> 135108 | AC62: =SUM(AC57:AC61) -> 134958 | AD62: =SUM(AD57:AD61) -> 129781 | ... AG62: =SUM(AG57:AG61) -> 0 | AI62: =SUM(AG62/AC62)-1 -> -1
B63: Total liabilities and stockholders' equity | C63: =SUM(C62+C55) -> 161616.49 | D63: =SUM(D62+D55) -> 305410 | E63: =SUM(E62+E55) -> 308772 | F63: =SUM(F62+F55) -> 135567 | H63: =SUM(H62+H55) -> 156896.37 | I63: =SUM(I62+I55) -> 160276.15 | J63: =SUM(J62+J55) -> 160221.14 | K63: =SUM(K62+K55) -> 152705 | L63: =SUM(L62+L55) -> 148371.92 | M63: =SUM(M62+M55) -> 159186.4 | N63: =SUM(N62+N55) -> 239119.47 | O63: =SUM(O62+O55) -> 154386 | ... U63: =SUM(U62+U55) -> 0 | W63: =SUM(W62+#REF!) -> #REF! | X63: =SUM(X62+#REF!) -> #REF! | Y63: =SUM(Y62+#REF!) -> #REF! | Z63: =SUM(Z62+#REF!) -> #REF! | AA63: =SUM(AA62+#REF!) -> #REF! | AB63: =SUM(AB62+#REF!) -> #REF! | AC63: =SUM(AC62+#REF!) -> #REF! | AD63: =SUM(AD62+#REF!) -> #REF! | ... AG63: =SUM(AG62+#REF!) -> #REF! | AI63: =SUM(AG63/AC63)-1 -> #REF!
B65: Balance Check | C65: =C63-C49 -> 0 | D65: =D63-D49 -> 152705 | E65: =E63-E49 -> 154386 | F65: =F63-F49 -> 0 | H65: =H63-H49 -> 0 | I65: =I63-I49 -> 0 | J65: =J63-J49 -> 0 | K65: =K63-K49 -> 0 | L65: =L63-L49 -> 0 | M65: =M63-M49 -> 0 | N65: =N63-N49 -> 81309.609 | O65: =O63-O49 -> 0 | ... U65: =U63-U49 -> 0 | W65: =W63-W55 -> #REF! | X65: =X63-X55 -> #REF! | Y65: =Y63-Y55 -> #REF! | Z65: =Z63-Z55 -> #REF! | AA65: =AA63-AA55 -> #REF! | AB65: =AB63-AB55 -> #REF! | AC65: =AC63-AC55 -> #REF! | AD65: =AD63-AD55 -> #REF! | ... AG65: =AG63-AG55 -> #REF!
B67: 1) Prepaid expenses and other current assets consists of: Prepaid expenses and other current assets + Forward contracts + Deferred offering costs.
A69: X | B69: Cash-Flows Statement | C69: FYE | D69: FYE | H69: Quarterly | R69: Quarterly | AC69: LTM | AI69: Variance
B70: =B7 -> Fiscal Period | C70: =C7 -> 2021 | D70: =D7 -> 2022 | E70: =E7 -> 2023 | F70: =F7 -> 2024 | H70: =H7 -> 1Q22 | I70: =I7 -> 2Q22 | J70: =J7 -> 3Q22 | K70: =K7 -> 4Q22 | L70: =L7 -> 1Q23 | M70: =M7 -> 2Q23 | N70: =N7 -> 3Q23 | O70: =O7 -> 4Q23 | ... U70: =U7 -> 2Q25 | W70: =W7 -> 4Q22 | X70: =X7 -> 1Q23 | Y70: =Y7 -> 2Q23 | Z70: =Z7 -> 3Q23 | AA70: =AA7 -> 4Q23 | AB70: =AB7 -> 1Q24 | AC70: =AC7 -> 2Q24 | AD70: =AD7 -> 3Q24 | ... AG70: =AG7 -> 2Q25
B71: =B8 -> Fiscal Period End Date | C71: =C8 -> 44561 | D71: =D8 -> 44926 | E71: =E8 -> 45291 | F71: =F8 -> 45657 | H71: =H8 -> 44651 | I71: =I8 -> 44742 | J71: =J8 -> 44834 | K71: =K8 -> 44926 | L71: =L8 -> 45016 | M71: =M8 -> 45107 | N71: =N8 -> 45199 | O71: =O8 -> 45291 | ... U71: =U8 -> 45838 | W71: =W8 -> 44926 | X71: =X8 -> 45016 | Y71: =Y8 -> 45107 | Z71: =Z8 -> 45199 | AA71: =AA8 -> 45291 | AB71: =AB8 -> 45382 | AC71: =AC8 -> 45473 | AD71: =AD8 -> 45565 | ... AG71: =AG8 -> 45838
B73: Cash-Flows From Operating Activities
B74: Net income (loss) | C74: =C32 -> -37909 | D74: =D32 -> -47978 | E74: =E32 -> -47505 | F74: =F32 -> -43002 | H74: =H32 -> -10882.367 | I74: =I32 -> -10437.811 | J74: =J32 -> -12367.341 | K74: =K32 -> -14290.481 | L74: =L32 -> -12971.718 | M74: =M32 -> -13107.279 | N74: =N32 -> -11279.976 | O74: =SUM(E74-SUM(L74:N74)) -> -10146.027 | P74: =P32 -> -8622 | Q74: =Q32 -> -10546 | R74: =R32 -> -12214 | S74: =SUM(F74-SUM(P74:R74)) -> -11620 | T74: =T32 -> 0 | U74: =U32 -> 0 | W74: =SUM(I74:L74) -> -50067.351 | X74: =SUM(J74:M74) -> -52736.819 | Y74: =SUM(K74:N74) -> -51649.454 | Z74: =SUM(L74:O74) -> -47505 | AA74: =SUM(M74:P74) -> -43155.282 | AB74: =SUM(N74:Q74) -> -40594.003 | AC74: =SUM(N74:Q74) -> -40594.003 | AD74: =SUM(O74:R74) -> -41528.027 | AE74: =SUM(P74:S74) -> -43002 | AF74: =SUM(Q74:T74) -> -34380 | AG74: =SUM(R74:U74) -> -23834 | AI74: =SUM(AG74/AC74)-1 -> -0.41286894
B76: Adjustments to reconcile net income:
B77: Non-cash financing related charges | E77: 845 | F77: 0 | K77: =SUM(D77-SUM(H77:J77)) -> 0 | L77: 0 | M77: =844.5-L77 -> 844.5 | N77: =844.5-M77-L77 -> 0 | O77: =SUM(E77-SUM(L77:N77)) -> 0.5 | Q77: 0 | R77: 0 | S77: =SUM(F77-SUM(P77:R77)) -> 0 | W77: =SUM(I77:L77) -> 0 | X77: =SUM(J77:M77) -> 844.5 | Y77: =SUM(K77:N77) -> 844.5 | Z77: =SUM(L77:O77) -> 845 | AA77: =SUM(M77:P77) -> 845 | AB77: =SUM(N77:Q77) -> 0.5 | AC77: =SUM(N77:Q77) -> 0.5 | AD77: =SUM(O77:R77) -> 0.5 | AE77: =SUM(P77:S77) -> 0 | AF77: =SUM(Q77:T77) -> 0 | AG77: =SUM(R77:U77) -> 0 | AI77: =SUM(AG77/AC77)-1 -> -1
B78: Gain on settlement of accounts payable | K78: =SUM(D78-SUM(H78:J78)) -> 0 | O78: =SUM(E78-SUM(L78:N78)) -> 0 | R78: =-59-Q78-P704 -> -59 | S78: =SUM(F78-SUM(P78:R78)) -> 59 | W78: =SUM(I78:L78) -> 0 | X78: =SUM(J78:M78) -> 0 | Y78: =SUM(K78:N78) -> 0 | Z78: =SUM(L78:O78) -> 0 | AA78: =SUM(M78:P78) -> 0 | AB78: =SUM(N78:Q78) -> 0 | AC78: =SUM(N78:Q78) -> 0 | AD78: =SUM(O78:R78) -> -59 | AE78: =SUM(P78:S78) -> 0 | AF78: =SUM(Q78:T78) -> 0 | AG78: =SUM(R78:U78) -> 0 | AI78: =SUM(AG78/AC78)-1 -> #DIV/0!
B79: Share-based compensation | C79: 8231 | D79: 18379 | E79: 16370 | F79: 9438 | H79: 3908.771 | I79: =8348.23-H79 -> 4439.459 | J79: =12336.844-I79-H79 -> 3988.614 | K79: =SUM(D79-SUM(H79:J79)) -> 6042.156 | L79: 5346.508 | M79: =9316.572-L79 -> 3970.064 | N79: =13183.353-M79-L79 -> 3866.781 | O79: =SUM(E79-SUM(L79:N79)) -> 3186.647 | P79: 2286 | Q79: =4938-P79 -> 2652 | R79: =7425-Q79-P79 -> 2487 | S79: =SUM(F79-SUM(P79:R79)) -> 2013 | W79: =SUM(I79:L79) -> 19816.737 | X79: =SUM(J79:M79) -> 19347.342 | Y79: =SUM(K79:N79) -> 19225.509 | Z79: =SUM(L79:O79) -> 16370 | AA79: =SUM(M79:P79) -> 13309.492 | AB79: =SUM(N79:Q79) -> 11991.428 | AC79: =SUM(N79:Q79) -> 11991.428 | AD79: =SUM(O79:R79) -> 10611.647 | AE79: =SUM(P79:S79) -> 9438 | AF79: =SUM(Q79:T79) -> 7152 | AG79: =SUM(R79:U79) -> 4500 | AI79: =SUM(AG79/AC79)-1 -> -0.62473193
B81: Changes in assets and liabilities:
B82: Incentive and tax receivables | C82: -4287 | D82: 5944 | E82: 484 | F82: 260 | H82: 3764.678 | I82: =2667.844-H82 -> -1096.834 | J82: =2577.002-I82-H82 -> -90.842 | K82: =SUM(D82-SUM(H82:J82)) -> 3366.998 | L82: -901.851 | M82: =-1545.081-L82 -> -643.23 | N82: =102.7453-M82-L82 -> 1647.8263 | O82: =SUM(E82-SUM(L82:N82)) -> 381.2547 | P82: -840 | Q82: =-1076-P82 -> -236 | R82: =989-Q82-P82 -> 2065 | S82: =SUM(F82-SUM(P82:R82)) -> -729 | W82: =SUM(I82:L82) -> 1277.471 | X82: =SUM(J82:M82) -> 1731.075 | Y82: =SUM(K82:N82) -> 3469.7433 | Z82: =SUM(L82:O82) -> 484 | AA82: =SUM(M82:P82) -> 545.851 | AB82: =SUM(N82:Q82) -> 953.081 | AC82: =SUM(N82:Q82) -> 953.081 | AD82: =SUM(O82:R82) -> 1370.2547 | AE82: =SUM(P82:S82) -> 260 | AF82: =SUM(Q82:T82) -> 1100 | AG82: =SUM(R82:U82) -> 1336 | AI82: =SUM(AG82/AC82)-1 -> 0.40176963
B83: Prepaid expenses and deposits | C83: 88 | D83: 1 | E83: -299 | F83: -278 | H83: -22.311 | I83: =-109.056-H83 -> -86.745 | J83: =-106.414-I83-H83 -> 2.642 | K83: =SUM(D83-SUM(H83:J83)) -> 107.414 | L83: -301.481 | M83: =-627.612-L83 -> -326.131 | N83: =-473.41-M83-L83 -> 154.202 | O83: =SUM(E83-SUM(L83:N83)) -> 174.41 | P83: -103 | Q83: =-692-P83 -> -589 | R83: =-406-Q83-P83 -> 286 | S83: =SUM(F83-SUM(P83:R83)) -> 128 | W83: =SUM(I83:L83) -> -278.17 | X83: =SUM(J83:M83) -> -517.556 | Y83: =SUM(K83:N83) -> -365.996 | Z83: =SUM(L83:O83) -> -299 | AA83: =SUM(M83:P83) -> -100.519 | AB83: =SUM(N83:Q83) -> -363.388 | AC83: =SUM(N83:Q83) -> -363.388 | AD83: =SUM(O83:R83) -> -231.59 | AE83: =SUM(P83:S83) -> -278 | AF83: =SUM(Q83:T83) -> -175 | AG83: =SUM(R83:U83) -> 414 | AI83: =SUM(AG83/AC83)-1 -> -2.1392781
B84: Accounts payable | C84: 751 | D84: -914 | E84: 497 | F84: 5305 | H84: -104.992 | I84: =-2107.893-H84 -> -2002.901 | J84: =-1612.889-I84-H84 -> 495.004 | K84: =SUM(D84-SUM(H84:J84)) -> 698.889 | L84: 1463.484 | M84: =2456.965-L84 -> 993.481 | N84: =328.069-M84-L84 -> -2128.896 | O84: =SUM(E84-SUM(L84:N84)) -> 168.931 | P84: -30 | Q84: =-596-P84 -> -566 | R84: =-760-Q84-P84 -> -164 | S84: =SUM(F84-SUM(P84:R84)) -> 6065 | W84: =SUM(I84:L84) -> 654.476 | X84: =SUM(J84:M84) -> 3650.858 | Y84: =SUM(K84:N84) -> 1026.958 | Z84: =SUM(L84:O84) -> 497 | AA84: =SUM(M84:P84) -> -996.484 | AB84: =SUM(N84:Q84) -> -2555.965 | AC84: =SUM(N84:Q84) -> -2555.965 | AD84: =SUM(O84:R84) -> -591.069 | AE84: =SUM(P84:S84) -> 5305 | AF84: =SUM(Q84:T84) -> 5335 | AG84: =SUM(R84:U84) -> 5901 | AI84: =SUM(AG84/AC84)-1 -> -3.3087171
B85: Accrued liabilities | C85: 2298 | D85: 330 | E85: 1350 | F85: -2460 | H85: -164.734 | I85: =-619.386-H85 -> -454.652 | J85: =299.047-I85-H85 -> 918.433 | K85: =SUM(D85-SUM(H85:J85)) -> 30.953 | L85: 1097.869 | M85: =877.885-L85 -> -219.984 | N85: =40.705-M85-L85 -> -837.18 | O85: =SUM(E85-SUM(L85:N85)) -> 1309.295 | P85: -9 | Q85: =-2380-P85 -> -2371 | R85: =39-Q85-P85 -> 2419 | S85: =SUM(F85-SUM(P85:R85)) -> -2499 | W85: =SUM(I85:L85) -> 1592.603 | X85: =SUM(J85:M85) -> 1827.271 | Y85: =SUM(K85:N85) -> 71.658 | Z85: =SUM(L85:O85) -> 1350 | AA85: =SUM(M85:P85) -> 243.131 | AB85: =SUM(N85:Q85) -> -1907.885 | AC85: =SUM(N85:Q85) -> -1907.885 | AD85: =SUM(O85:R85) -> 1348.295 | AE85: =SUM(P85:S85) -> -2460 | AF85: =SUM(Q85:T85) -> -2451 | AG85: =SUM(R85:U85) -> -80 | AI85: =SUM(AG85/AC85)-1 -> -0.95806875
B86: Deferred grant income | C86: 444 | D86: 0 | E86: 473 | F86: -75 | K86: =SUM(D86-SUM(H86:J86)) -> 0 | L86: 472.932 | M86: =472.932-L86 -> 0 | N86: =472.932-M86-L86 -> 0 | O86: =SUM(E86-SUM(L86:N86)) -> 0.068 | Q86: 0 | R86: 0 | S86: =SUM(F86-SUM(P86:R86)) -> -75 | W86: =SUM(I86:L86) -> 472.932 | X86: =SUM(J86:M86) -> 472.932 | Y86: =SUM(K86:N86) -> 472.932 | Z86: =SUM(L86:O86) -> 473 | AA86: =SUM(M86:P86) -> 0.068 | AB86: =SUM(N86:Q86) -> 0.068 | AC86: =SUM(N86:Q86) -> 0.068 | AD86: =SUM(O86:R86) -> 0.068 | AE86: =SUM(P86:S86) -> -75 | AF86: =SUM(Q86:T86) -> -75 | AG86: =SUM(R86:U86) -> -75 | AI86: =SUM(AG86/AC86)-1 -> -1103.9412
B87: Net cash used in operating activities | C87: =SUM(C74:C86) -> -30384 | D87: =SUM(D74:D86) -> -24238 | E87: =SUM(E74:E86) -> -27785 | F87: =SUM(F74:F86) -> -30812 | H87: =SUM(H74:H86) -> -3500.955 | I87: =SUM(I74:I86) -> -9639.484 | J87: =SUM(J74:J86) -> -7053.49 | K87: =SUM(K74:K86) -> -4044.071 | L87: =SUM(L74:L86) -> -5794.257 | M87: =SUM(M74:M86) -> -8488.579 | N87: =SUM(N74:N86) -> -8577.2427 | O87: =SUM(O74:O86) -> -4924.9213 | ... U87: =SUM(U74:U86) -> 0 | W87: =SUM(W74:W86) -> -26531.302 | X87: =SUM(X74:X86) -> -25380.397 | Y87: =SUM(Y74:Y86) -> -26904.15 | Z87: =SUM(Z74:Z86) -> -27785 | AA87: =SUM(AA74:AA86) -> -29308.743 | AB87: =SUM(AB74:AB86) -> -32476.164 | AC87: =SUM(AC74:AC86) -> -32476.164 | AD87: =SUM(AD74:AD86) -> -29078.921 | ... AG87: =SUM(AG74:AG86) -> -11838 | AI87: =SUM(AG87/AC87)-1 -> -0.63548651
B89: Cash flows from investing activities:
B90: Net cash used in investing activities | C90: =+C89 -> 0 | D90: =+D89 -> 0 | E90: =+E89 -> 0 | F90: =+F89 -> 0 | H90: =+H89 -> 0 | I90: =+I89 -> 0 | J90: =+J89 -> 0 | K90: =+K89 -> 0 | L90: =+L89 -> 0 | M90: =+M89 -> 0 | N90: =+N89 -> 0 | O90: =+O89 -> 0 | ... U90: =+U89 -> 0 | W90: =SUM(#REF!) -> #REF! | X90: =SUM(#REF!) -> #REF! | Y90: =SUM(#REF!) -> #REF! | Z90: =SUM(#REF!) -> #REF! | AA90: =SUM(#REF!) -> #REF! | AB90: =SUM(#REF!) -> #REF! | AC90: =+AC89 -> 0 | AD90: =+AD89 -> 0 | AE90: =+AE89 -> 0 | AF90: =+AF89 -> 0 | AG90: =+AG89 -> 0 | AI90: =SUM(AG90/AC90)-1 -> #DIV/0!
B92: Cash flows from financing activities:
B93: Issuance of common shares | C93: 153219 | D93: 20985 | E93: 27875 | F93: 11284 | H93: 2312.785 | I93: =14399.768-H93 -> 12086.983 | J93: =20982.148-I93-H93 -> 6582.38 | K93: =SUM(D93-SUM(H93:J93)) -> 2.852 | L93: 0 | M93: 18152.5 | N93: =26687.017-M93 -> 8534.517 | O93: =SUM(E93-SUM(L93:N93)) -> 1187.983 | P93: 0 | Q93: =7178-P93 -> 7178 | R93: =11284-Q93 -> 4106 | S93: =SUM(F93-SUM(P93:R93)) -> 0 | AC93: =SUM(N93:Q93) -> 16900.5 | AD93: =SUM(O93:R93) -> 12471.983 | AE93: =SUM(P93:S93) -> 11284 | AF93: =SUM(Q93:T93) -> 11284 | AG93: =SUM(R93:U93) -> 4106 | AI93: =SUM(AG93/AC93)-1 -> -0.75704861
B94: Share issue costs | C94: -5551 | D94: -707 | H94: -146.717 | I94: =-521.441-H94 -> -374.724 | J94: =-706.802-I94-H94 -> -185.361 | K94: =SUM(D94-SUM(H94:J94)) -> -0.198 | O94: =SUM(E94-SUM(L94:N94)) -> 0 | P94: 0 | S94: =SUM(F94-SUM(P94:R94)) -> 0 | AC94: =SUM(N94:Q94) -> 0 | AD94: =SUM(O94:R94) -> 0 | AE94: =SUM(P94:S94) -> 0 | AF94: =SUM(Q94:T94) -> 0 | AG94: =SUM(R94:U94) -> 0 | AI94: =SUM(AG94/AC94)-1 -> #DIV/0!
B95: Proceeds from exercise of warrants | C95: 1467 | D95: 0 | K95: =SUM(D95-SUM(H95:J95)) -> 0 | O95: =SUM(E95-SUM(L95:N95)) -> 0 | P95: 0 | S95: =SUM(F95-SUM(P95:R95)) -> 0 | W95: =SUM(I95:L95) -> 0 | X95: =SUM(J95:M95) -> 0 | Y95: =SUM(K95:N95) -> 0 | Z95: =SUM(L95:O95) -> 0 | AA95: =SUM(M95:P95) -> 0 | AB95: =SUM(N95:Q95) -> 0 | AC95: =SUM(N95:Q95) -> 0 | AD95: =SUM(O95:R95) -> 0 | AE95: =SUM(P95:S95) -> 0 | AF95: =SUM(Q95:T95) -> 0 | AG95: =SUM(R95:U95) -> 0 | AI95: =SUM(AG95/AC95)-1 -> #DIV/0!
B96: Proceeds from exercise of stock options | C96: 4108 | D96: 1010 | E96: 1776 | F96: 691 | H96: 373.497 | I96: =496.923-H96 -> 123.426 | J96: =1010.19-I96-H96 -> 513.267 | K96: =SUM(D96-SUM(H96:J96)) -> -0.19 | L96: 258.244 | M96: =439.437-L96 -> 181.193 | N96: =907.657-M96-L96 -> 468.22 | O96: =SUM(E96-SUM(L96:N96)) -> 868.343 | P96: 59 | Q96: =158-P96 -> 99 | R96: =602-Q96 -> 503 | S96: =SUM(F96-SUM(P96:R96)) -> 30 | AC96: =SUM(N96:Q96) -> 1494.563 | AD96: =SUM(O96:R96) -> 1529.343 | AE96: =SUM(P96:S96) -> 691 | AF96: =SUM(Q96:T96) -> 632 | AG96: =SUM(R96:U96) -> 533 | AI96: =SUM(AG96/AC96)-1 -> -0.64337402
B97: Net cash provided by financing activities | C97: =SUM(C93:C96) -> 153243 | D97: =SUM(D93:D96) -> 21288 | E97: =SUM(E93:E96) -> 29651 | F97: =SUM(F93:F96) -> 11975 | H97: =SUM(H93:H96) -> 2539.565 | I97: =SUM(I93:I96) -> 11835.685 | J97: =SUM(J93:J96) -> 6910.286 | K97: =SUM(K93:K96) -> 2.464 | L97: =SUM(L93:L96) -> 258.244 | M97: =SUM(M93:M96) -> 18333.693 | N97: =SUM(N93:N96) -> 9002.737 | O97: =SUM(O93:O96) -> 2056.326 | ... U97: =SUM(U93:U96) -> 0 | W97: =SUM(W93:W96) -> 0 | X97: =SUM(X93:X96) -> 0 | Y97: =SUM(Y93:Y96) -> 0 | Z97: =SUM(Z93:Z96) -> 0 | AA97: =SUM(AA93:AA96) -> 0 | AB97: =SUM(AB93:AB96) -> 0 | AC97: =SUM(AC93:AC96) -> 18395.063 | AD97: =SUM(AD93:AD96) -> 14001.326 | ... AG97: =SUM(AG93:AG96) -> 4639 | AI97: =SUM(AG97/AC97)-1 -> -0.74781277
B100: Cash BOP | E100: =D106 -> -2950 | F100: =E106 -> -1084 | I100: =H106 -> -961.39 | J100: =I106 -> 1234.811 | K100: =J106 -> 1091.607 | L100: =K106 -> -2950 | M100: =L106 -> -8486.013 | N100: =M106 -> 1359.101 | O100: =N106 -> 1784.5953 | P100: =O106 -> -1084 | ... U100: =T106 -> -19921 | W100: =H106 -> -961.39 | X100: =I106 -> 1234.811 | Y100: =J106 -> 1091.607 | Z100: =K106 -> -2950 | AA100: =L106 -> -8486.013 | AB100: =M106 -> 1359.101 | AC100: =N106 -> 1784.5953 | AD100: =O106 -> -1084 | ... AG100: =R106 -> -13293
B101: BOP Restricted Cash Adjustments (Changes in FX; Restricted Cash) | E101: 0 | F101: 0 | I101: 0 | J101: 0 | K101: 0 | L101: 0 | M101: 0 | N101: 0 | O101: 0 | P101: 0 | Q101: 0 | R101: 0 | S101: 0 | T101: 0 | U101: 0 | W101: =SUM(I101:L101) -> 0 | X101: =SUM(J101:M101) -> 0 | Y101: =SUM(K101:N101) -> 0 | Z101: =SUM(L101:O101) -> 0 | AA101: =SUM(M101:P101) -> 0 | AB101: =SUM(N101:Q101) -> 0 | AC101: =SUM(O101:R101) -> 0 | AD101: =SUM(P101:S101) -> 0 | ... AF101: =SUM(R101:U101) -> 0 | AG101: =SUM(S101:U101) -> 0
B102: Adjusted Cash Position BOP | C102: =SUM(C100:C101) -> 0 | D102: =SUM(D100:D101) -> 0 | E102: =SUM(E100:E101) -> -2950 | F102: =SUM(F100:F101) -> -1084 | H102: =SUM(H100:H101) -> 0 | I102: =SUM(I100:I101) -> -961.39 | J102: =SUM(J100:J101) -> 1234.811 | K102: =SUM(K100:K101) -> 1091.607 | L102: =SUM(L100:L101) -> -2950 | M102: =SUM(M100:M101) -> -8486.013 | N102: =SUM(N100:N101) -> 1359.101 | O102: =SUM(O100:O101) -> 1784.5953 | ... U102: =SUM(U100:U101) -> -19921 | W102: =SUM(W100:W101) -> -961.39 | X102: =SUM(X100:X101) -> 1234.811 | Y102: =SUM(Y100:Y101) -> 1091.607 | Z102: =SUM(Z100:Z101) -> -2950 | AA102: =SUM(AA100:AA101) -> -8486.013 | AB102: =SUM(AB100:AB101) -> 1359.101 | AC102: =SUM(AC100:AC101) -> 1784.5953 | AD102: =SUM(AD100:AD101) -> -1084 | ... AG102: =SUM(AG100:AG101) -> -13293
B104: EOP Restricted Cash Adjustments (Changes in FX; Restricted Cash) | K104: =D104 -> 0 | O104: =E104 -> 0 | S104: =F104 -> 0 | W104: =SUM(I104:L104) -> 0 | X104: =SUM(J104:M104) -> 0 | Y104: =SUM(K104:N104) -> 0 | Z104: =SUM(L104:O104) -> 0 | AA104: =SUM(M104:P104) -> 0 | AB104: =SUM(N104:Q104) -> 0 | AC104: =SUM(O104:R104) -> 0 | AD104: =SUM(P104:S104) -> 0 | ... AF104: =SUM(R104:U104) -> 0 | AG104: =SUM(S104:U104) -> 0
B105: Net Change in Cash | C105: =+C97+C90+C87 -> 122859 | D105: =+D97+D90+D87 -> -2950 | E105: =+E97+E90+E87 -> 1866 | F105: =+F97+F90+F87 -> -18837 | H105: =+H97+H90+H87 -> -961.39 | I105: =+I97+I90+I87 -> 2196.201 | J105: =+J97+J90+J87 -> -143.204 | K105: =+K97+K90+K87 -> -4041.607 | L105: =+L97+L90+L87 -> -5536.013 | M105: =+M97+M90+M87 -> 9845.114 | N105: =+N97+N90+N87 -> 425.4943 | O105: =+O97+O90+O87 -> -2868.5953 | ... U105: =+U97+U90+U87 -> 0 | W105: =SUM(I105:L105) -> -7524.623 | X105: =SUM(J105:M105) -> 124.29 | Y105: =SUM(K105:N105) -> 692.9883 | Z105: =SUM(L105:O105) -> 1866 | AA105: =SUM(M105:P105) -> 143.013 | AB105: =SUM(N105:Q105) -> -14081.101 | AC105: =SUM(O105:R105) -> -15077.595 | AD105: =SUM(P105:S105) -> -18837 | ... AF105: =SUM(R105:U105) -> -7199 | AG105: =SUM(S105:U105) -> -6628
B106: Adjusted Cash Position EOP | C106: =SUM(C102:C105) -> 122859 | D106: =SUM(D102:D105) -> -2950 | E106: =SUM(E102:E105) -> -1084 | F106: =SUM(F102:F105) -> -19921 | H106: =SUM(H102:H105) -> -961.39 | I106: =SUM(I102:I105) -> 1234.811 | J106: =SUM(J102:J105) -> 1091.607 | K106: =SUM(K102:K105) -> -2950 | L106: =SUM(L102:L105) -> -8486.013 | M106: =SUM(M102:M105) -> 1359.101 | N106: =SUM(N102:N105) -> 1784.5953 | O106: =SUM(O102:O105) -> -1084 | ... U106: =SUM(U102:U105) -> -19921 | W106: =SUM(W102:W105) -> -8486.013 | X106: =SUM(X102:X105) -> 1359.101 | Y106: =SUM(Y102:Y105) -> 1784.5953 | Z106: =SUM(Z102:Z105) -> -1084 | AA106: =SUM(AA102:AA105) -> -8343 | AB106: =SUM(AB102:AB105) -> -12722 | AC106: =SUM(AC102:AC105) -> -13293 | AD106: =SUM(AD102:AD105) -> -19921 | ... AG106: =SUM(AG102:AG105) -> -19921
B108: Balance Check | C108: =C106-C46 -> -29248.745 | D108: =D106-D46 -> -152108 | E108: =E106-E46 -> -152108 | F108: =F106-F46 -> -152108 | H108: =H106-H46 -> -152107.74 | I108: =I106-I46 -> -152107.74 | J108: =J106-J46 -> -152107.75 | K108: =K106-K46 -> -152108 | L108: =L106-L46 -> -152107.86 | M108: =M106-M46 -> -152107.86 | N108: =N106-N46 -> -153032.57 | O108: =O106-O46 -> -152108 | ... U108: =U106-U46 -> -19921 | W108: =W106-W46 -> -157644.01 | X108: =X106-X46 -> -142262.75 | Y108: =Y106-Y46 -> -151682.37 | Z108: =Z106-Z46 -> -155901.16 | AA108: =AA106-AA46 -> -159367 | AB108: =AB106-AB46 -> -156487 | AC108: =AC106-AC46 -> -152679 | AD108: =AD106-AD46 -> -158677 | ... AG108: =AG106-AG46 -> -19921
B111: Supplemental disclosures of other cash flow information:
B112: Cash paid for interest | C112: 140 | D112: 327 | E112: 136 | F112: 300 | I112: 141.374 | J112: =141.374-I112 -> 0 | K112: =SUM(D112-SUM(H112:J112)) -> 185.626 | L112: 50.077 | M112: =139.577-L112 -> 89.5 | N112: =208.577-M112-L112 -> 69 | O112: =SUM(E112-SUM(L112:N112)) -> -72.577 | P112: 47 | Q112: =220-P112 -> 173 | R112: =220-Q112-P112 -> 0 | S112: =SUM(F112-SUM(P112:R112)) -> 80
B114: 1) Other, net consists of:Other + Non-cash research and development arrangements+ Deferred income taxes.
B115: 2) Other Investing consists of: Other Investing + Intangible asset acquisition costs.

Sheet Revenue Drivers
B2: Anavex Life Sciences Corp. (AVXL) | H2: Quarterly | P2: Quarterly | Q2: Quarterly | W2: LTM | AA2: LTM | AC2: LTM
B3: Segment Anaysis | C3: ='Historical Financials'!#REF! -> #REF! | D3: ='Historical Financials'!D7 -> 2022 | E3: ='Historical Financials'!E7 -> 2023 | F3: ='Historical Financials'!F7 -> 2024 | H3: ='Historical Financials'!H7 -> 1Q22 | I3: ='Historical Financials'!I7 -> 2Q22 | J3: ='Historical Financials'!J7 -> 3Q22 | K3: ='Historical Financials'!K7 -> 4Q22 | L3: ='Historical Financials'!L7 -> 1Q23 | M3: ='Historical Financials'!M7 -> 2Q23 | N3: ='Historical Financials'!N7 -> 3Q23 | O3: ='Historical Financials'!O7 -> 4Q23 | ... U3: ='Historical Financials'!U7 -> 2Q25 | W3: =L3 -> 1Q23 | X3: =M3 -> 2Q23 | Y3: =N3 -> 3Q23 | Z3: =O3 -> 4Q23 | AA3: =P3 -> 1Q24 | AB3: =Q3 -> 2Q24 | AC3: =S3 -> 4Q24 | AD3: =T3 -> 1Q25 | AE3: =U3 -> 2Q25 | AF3: =#REF! -> #REF!
B4: $ in thousands except per share | C4: ='Historical Financials'!#REF! -> #REF! | D4: ='Historical Financials'!D8 -> 44926 | E4: ='Historical Financials'!E8 -> 45291 | F4: ='Historical Financials'!F8 -> 45657 | H4: ='Historical Financials'!H8 -> 44651 | I4: ='Historical Financials'!I8 -> 44742 | J4: ='Historical Financials'!J8 -> 44834 | K4: ='Historical Financials'!K8 -> 44926 | L4: ='Historical Financials'!L8 -> 45016 | M4: ='Historical Financials'!M8 -> 45107 | N4: ='Historical Financials'!N8 -> 45199 | O4: ='Historical Financials'!O8 -> 45291 | ... U4: ='Historical Financials'!U8 -> 45838 | W4: =L4 -> 45016 | X4: =M4 -> 45107 | Y4: =N4 -> 45199 | Z4: =O4 -> 45291 | AA4: =P4 -> 45382 | AB4: =Q4 -> 45473 | AC4: =S4 -> 45657 | AD4: =T4 -> 45747 | AE4: =U4 -> 45838 | AF4: =#REF! -> #REF!
A6: X | B6: Net Revenues by Channel
W7: =SUM(I7:L7) -> 0 | X7: =SUM(J7:M7) -> 0 | Y7: =SUM(K7:N7) -> 0 | Z7: =SUM(L7:O7) -> 0 | AA7: =SUM(M7:P7) -> 0 | AB7: =SUM(N7:Q7) -> 0 | AC7: =SUM(P7:S7) -> 0 | AD7: =SUM(Q7:T7) -> 0 | AE7: =SUM(R7:U7) -> 0 | AF7: =SUM(S7:U7) -> 0
W8: =SUM(I8:L8) -> 0 | X8: =SUM(J8:M8) -> 0 | Y8: =SUM(K8:N8) -> 0 | Z8: =SUM(L8:O8) -> 0 | AA8: =SUM(M8:P8) -> 0 | AB8: =SUM(N8:Q8) -> 0 | AC8: =SUM(P8:S8) -> 0 | AD8: =SUM(Q8:T8) -> 0 | AE8: =SUM(R8:U8) -> 0 | AF8: =SUM(S8:U8) -> 0
B9: Total Net Revenue | D9: =SUM(D7:D8) -> 0 | E9: =SUM(E7:E8) -> 0 | F9: =SUM(F7:F8) -> 0 | P9: =SUM(P7:P8) -> 0 | Q9: =SUM(Q7:Q8) -> 0 | R9: =SUM(R7:R8) -> 0 | S9: =SUM(S7:S8) -> 0 | T9: =SUM(T7:T8) -> 0 | U9: =SUM(U7:U8) -> 0 | W9: =SUM(W7:W8) -> 0 | X9: =SUM(X7:X8) -> 0 | Y9: =SUM(Y7:Y8) -> 0 | Z9: =SUM(Z7:Z8) -> 0 | AA9: =SUM(AA7:AA8) -> 0 | AB9: =SUM(AB7:AB8) -> 0 | AC9: =SUM(AC7:AC8) -> 0 | AD9: =SUM(AD7:AD8) -> 0 | ... AF9: =SUM(AF7:AF8) -> 0
B10: Balance Check | D10: =+D9-'Historical Financials'!D11 -> 0 | E10: =+E9-'Historical Financials'!E11 -> 0 | F10: =+F9-'Historical Financials'!F11 -> 0 | P10: =+P9-'Historical Financials'!P11 -> 0 | Q10: =+Q9-'Historical Financials'!Q11 -> 0 | R10: =+R9-'Historical Financials'!R11 -> 0 | S10: =+S9-'Historical Financials'!S11 -> 0 | T10: =+T9-'Historical Financials'!T11 -> 0 | U10: =+U9-'Historical Financials'!U11 -> 0 | W10: =W9-'Historical Financials'!W11 -> 0 | X10: =X9-'Historical Financials'!X11 -> 0 | Y10: =Y9-'Historical Financials'!Y11 -> 0 | Z10: =Z9-'Historical Financials'!Z11 -> 0 | AA10: =AA9-'Historical Financials'!AA11 -> 0 | AB10: =AB9-'Historical Financials'!AB11 -> 0 | AC10: =AC9-'Historical Financials'!AD11 -> 0 | AD10: =AD9-'Historical Financials'!AE11 -> 0 | AE10: =AE9-'Historical Financials'!AF11 -> 0 | AF10: =AF9-'Historical Financials'!AG11 -> 0
A12: X | B12: Revenue by Channel
W13: =SUM(I13:L13) -> 0 | X13: =SUM(J13:M13) -> 0 | Y13: =SUM(K13:N13) -> 0 | Z13: =SUM(L13:O13) -> 0 | AA13: =SUM(M13:P13) -> 0 | AB13: =SUM(N13:Q13) -> 0 | AC13: =SUM(P13:S13) -> 0 | AD13: =SUM(Q13:T13) -> 0 | AE13: =SUM(R13:U13) -> 0 | AF13: =SUM(S13:U13) -> 0
W14: =SUM(I14:L14) -> 0 | X14: =SUM(J14:M14) -> 0 | Y14: =SUM(K14:N14) -> 0 | Z14: =SUM(L14:O14) -> 0 | AA14: =SUM(M14:P14) -> 0 | AB14: =SUM(N14:Q14) -> 0 | AC14: =SUM(P14:S14) -> 0 | AD14: =SUM(Q14:T14) -> 0 | AE14: =SUM(R14:U14) -> 0 | AF14: =SUM(S14:U14) -> 0
B15: Total Net U.S Revenue | D15: =SUM(D13:D14) -> 0 | E15: =SUM(E13:E14) -> 0 | F15: =SUM(F13:F14) -> 0 | P15: =SUM(P13:P14) -> 0 | Q15: =SUM(Q13:Q14) -> 0 | R15: =SUM(R13:R14) -> 0 | S15: =SUM(S13:S14) -> 0 | T15: =SUM(T13:T14) -> 0 | U15: =SUM(U13:U14) -> 0 | W15: =SUM(W13:W14) -> 0 | X15: =SUM(X13:X14) -> 0 | Y15: =SUM(Y13:Y14) -> 0 | Z15: =SUM(Z13:Z14) -> 0 | AA15: =SUM(AA13:AA14) -> 0 | AB15: =SUM(AB13:AB14) -> 0 | AC15: =SUM(AC13:AC14) -> 0 | AD15: =SUM(AD13:AD14) -> 0 | ... AF15: =SUM(AF13:AF14) -> 0
B16: Balance Check | D16: =+D15-D9 -> 0 | E16: =+E15-E9 -> 0 | F16: =+F15-F9 -> 0 | P16: =+P15-P9 -> 0 | Q16: =+Q15-Q9 -> 0 | R16: =+R15-R9 -> 0 | S16: =+S15-S9 -> 0 | T16: =+T15-T9 -> 0 | U16: =+U15-U9 -> 0 | W16: =W15-'Historical Financials'!W17 -> 13320.085 | X16: =X15-'Historical Financials'!X17 -> 13287.495 | Y16: =Y15-'Historical Financials'!Y17 -> 13349.887 | Z16: =Z15-'Historical Financials'!Z17 -> 12039 | AA16: =AA15-'Historical Financials'!AA17 -> 11330.964 | AB16: =AB15-'Historical Financials'!AB17 -> 11238.396 | AC16: =+AC15-AC9 -> 0 | AD16: =+AD15-AD9 -> 0 | AE16: =+AE15-AE9 -> 0 | AF16: =+AF15-AF9 -> 0

Sheet FCF
B2: Anavex Life Sciences Corp. (AVXL) | D2: FYE | H2: Quarterly | Q2: Quarterly | R2: Quarterly | X2: LTM | AE2: LTM | AK2: Variance
B3: FCF Analysis | C3: ='Historical Financials'!#REF! -> #REF! | D3: ='Historical Financials'!D7 -> 2022 | E3: ='Historical Financials'!E7 -> 2023 | F3: ='Historical Financials'!F7 -> 2024 | H3: ='Historical Financials'!H7 -> 1Q22 | I3: ='Historical Financials'!I7 -> 2Q22 | J3: ='Historical Financials'!J7 -> 3Q22 | K3: ='Historical Financials'!K7 -> 4Q22 | L3: ='Historical Financials'!L7 -> 1Q23 | M3: ='Historical Financials'!M7 -> 2Q23 | N3: ='Historical Financials'!N7 -> 3Q23 | O3: ='Historical Financials'!O7 -> 4Q23 | ... U3: ='Historical Financials'!U7 -> 2Q25 | V3: ='Historical Financials'!#REF! -> #REF! | X3: =K3 -> 4Q22 | Y3: =L3 -> 1Q23 | Z3: =M3 -> 2Q23 | AA3: =N3 -> 3Q23 | AB3: =O3 -> 4Q23 | AC3: =P3 -> 1Q24 | AD3: =Q3 -> 2Q24 | AE3: =R3 -> 3Q24 | ... AI3: =V3 -> #REF!
B4: $ in thousands except per share | C4: ='Historical Financials'!#REF! -> #REF! | D4: ='Historical Financials'!D8 -> 44926 | E4: ='Historical Financials'!E8 -> 45291 | F4: ='Historical Financials'!F8 -> 45657 | H4: ='Historical Financials'!H8 -> 44651 | I4: ='Historical Financials'!I8 -> 44742 | J4: ='Historical Financials'!J8 -> 44834 | K4: ='Historical Financials'!K8 -> 44926 | L4: ='Historical Financials'!L8 -> 45016 | M4: ='Historical Financials'!M8 -> 45107 | N4: ='Historical Financials'!N8 -> 45199 | O4: ='Historical Financials'!O8 -> 45291 | ... U4: ='Historical Financials'!U8 -> 45838 | V4: ='Historical Financials'!#REF! -> #REF! | X4: =K4 -> 44926 | Y4: =L4 -> 45016 | Z4: =M4 -> 45107 | AA4: =N4 -> 45199 | AB4: =O4 -> 45291 | AC4: =P4 -> 45382 | AD4: =Q4 -> 45473 | AE4: =R4 -> 45565 | ... AI4: =V4 -> #REF!
P6: ='Revenue Drivers'!P7 -> 0 | Q6: ='Revenue Drivers'!Q7 -> 0 | AC6: =SUM(M6:P6) -> 0 | AD6: =SUM(N6:Q6) -> 0 | AE6: =SUM(O6:R6) -> 0 | AF6: =SUM(P6:S6) -> 0 | AG6: =SUM(Q6:T6) -> 0 | AH6: =SUM(R6:U6) -> 0 | AI6: =SUM(S6:V6) -> 0 | AK6: =SUM(AI6/AE6)-1 -> #DIV/0!
P7: ='Revenue Drivers'!P8 -> 0 | Q7: ='Revenue Drivers'!Q8 -> 0 | AC7: =SUM(M7:P7) -> 0 | AD7: =SUM(N7:Q7) -> 0 | AE7: =SUM(O7:R7) -> 0 | AF7: =SUM(P7:S7) -> 0 | AG7: =SUM(Q7:T7) -> 0 | AH7: =SUM(R7:U7) -> 0 | AI7: =SUM(S7:V7) -> 0 | AK7: =SUM(AI7/AE7)-1 -> #DIV/0!
B8: Total Revenue | C8: ='Historical Financials'!#REF! -> #REF! | D8: =SUM(D6:D7) -> 0 | E8: =SUM(E6:E7) -> 0 | F8: =SUM(F6:F7) -> 0 | H8: ='Historical Financials'!H11 -> 0 | I8: ='Historical Financials'!I11 -> 0 | J8: ='Historical Financials'!J11 -> 0 | K8: ='Historical Financials'!K11 -> 0 | L8: ='Historical Financials'!L11 -> 0 | M8: ='Historical Financials'!M11 -> 0 | N8: ='Historical Financials'!N11 -> 0 | O8: ='Historical Financials'!O11 -> 0 | P8: =SUM(P6:P7) -> 0 | Q8: =SUM(Q6:Q7) -> 0 | R8: =SUM(R6:R7) -> 0 | S8: =SUM(S6:S7) -> 0 | T8: =SUM(T6:T7) -> 0 | U8: =SUM(U6:U7) -> 0 | V8: =SUM(V6:V7) -> 0 | X8: =SUM(H8:K8) -> 0 | Y8: =SUM(I8:L8) -> 0 | Z8: =SUM(J8:M8) -> 0 | AA8: =SUM(K8:N8) -> 0 | AB8: =SUM(L8:O8) -> 0 | AC8: =SUM(AC6:AC7) -> 0 | AD8: =SUM(AD6:AD7) -> 0 | AE8: =SUM(AE6:AE7) -> 0 | AF8: =SUM(AF6:AF7) -> 0 | AG8: =SUM(AG6:AG7) -> 0 | AH8: =SUM(AH6:AH7) -> 0 | AI8: =SUM(AI6:AI7) -> 0 | AK8: =SUM(AI8/AE8)-1 -> #DIV/0!
B9: Y/Y Growth (%) | D9: =SUM(D8/C8)-1 -> #REF! | E9: =SUM(E8/D8)-1 -> #DIV/0! | F9: =SUM(F8/E8)-1 -> #DIV/0! | M9: =SUM(M8/I8)-1 -> #DIV/0! | N9: =SUM(N8/J8)-1 -> #DIV/0! | O9: =SUM(O8/K8)-1 -> #DIV/0! | P9: =SUM(P8/L8)-1 -> #DIV/0! | Q9: =SUM(Q8/M8)-1 -> #DIV/0! | R9: =SUM(R8/N8)-1 -> #DIV/0! | S9: =SUM(S8/O8)-1 -> #DIV/0! | T9: =SUM(T8/P8)-1 -> #DIV/0! | ... V9: =SUM(V8/R8)-1 -> #DIV/0! | AB9: =SUM(AB8/X8)-1 -> #DIV/0! | AC9: =SUM(AC8/Y8)-1 -> #DIV/0! | AD9: =SUM(AD8/Z8)-1 -> #DIV/0! | AE9: =SUM(AE8/AA8)-1 -> #DIV/0! | AF9: =SUM(AF8/AB8)-1 -> #DIV/0! | AG9: =SUM(AG8/AC8)-1 -> #DIV/0! | AH9: =SUM(AH8/AD8)-1 -> #DIV/0! | AI9: =SUM(AI8/AE8)-1 -> #DIV/0! | AK9: =SUM(AI9-AE9)*10000 -> #DIV/0!
B10: Q/Q Growth (%) | C10: N/A | D10: N/A | E10: N/A | F10: N/A | J10: =SUM(J8/I8)-1 -> #DIV/0! | K10: =SUM(K8/J8)-1 -> #DIV/0! | L10: =SUM(L8/K8)-1 -> #DIV/0! | M10: =SUM(M8/L8)-1 -> #DIV/0! | N10: =SUM(N8/M8)-1 -> #DIV/0! | O10: =SUM(O8/N8)-1 -> #DIV/0! | P10: =SUM(P8/O8)-1 -> #DIV/0! | Q10: =SUM(Q8/P8)-1 -> #DIV/0! | ... V10: =SUM(V8/U8)-1 -> #DIV/0! | X10: N/A | Y10: N/A | Z10: N/A | AA10: N/A | AB10: N/A | AC10: N/A | AD10: N/A | AE10: N/A | AF10: N/A | AG10: N/A | AH10: N/A | AI10: N/A
B12: (-) Cost of Sales | C12: ='Historical Financials'!#REF! -> #REF! | H12: ='Historical Financials'!H13 -> 0 | I12: ='Historical Financials'!I13 -> 0 | J12: ='Historical Financials'!J13 -> 0 | K12: ='Historical Financials'!K13 -> 0 | L12: ='Historical Financials'!L13 -> 0 | M12: ='Historical Financials'!M13 -> 0 | N12: ='Historical Financials'!N13 -> 0 | O12: ='Historical Financials'!O13 -> 0 | ... Q12: ='Historical Financials'!Q13 -> 0 | X12: =SUM(G12:K12) -> 0 | Y12: =SUM(I12:L12) -> 0 | Z12: =SUM(J12:M12) -> 0 | AA12: =SUM(K12:N12) -> 0 | AB12: =SUM(L12:O12) -> 0 | AC12: =SUM(M12:P12) -> 0 | AD12: =SUM(N12:Q12) -> 0 | AE12: =SUM(O12:R12) -> 0 | AF12: =SUM(P12:S12) -> 0 | ... AI12: =SUM(S12:V12) -> 0 | AK12: =SUM(AI12/AE12)-1 -> #DIV/0!
B13: Gross Profit | C13: =+C8+C12 -> #REF! | D13: =+D8+D12 -> 0 | E13: =+E8+E12 -> 0 | F13: =+F8+F12 -> 0 | H13: =+H8+H12 -> 0 | I13: =+I8+I12 -> 0 | J13: =+J8+J12 -> 0 | K13: =+K8+K12 -> 0 | L13: =+L8+L12 -> 0 | M13: =+M8+M12 -> 0 | N13: =+N8+N12 -> 0 | O13: =+O8+O12 -> 0 | ... V13: =+V8+V12 -> 0 | X13: =+X8+X12 -> 0 | Y13: =+Y8+Y12 -> 0 | Z13: =+Z8+Z12 -> 0 | AA13: =+AA8+AA12 -> 0 | AB13: =+AB8+AB12 -> 0 | AC13: =+AC8+AC12 -> 0 | AD13: =+AD8+AD12 -> 0 | AE13: =+AE8+AE12 -> 0 | ... AI13: =+AI8+AI12 -> 0 | AK13: =SUM(AI13/AE13)-1 -> #DIV/0!
B14: Gross Margin (%) | C14: =C13/C8 -> #REF! | D14: =D13/D8 -> #DIV/0! | E14: =E13/E8 -> #DIV/0! | F14: =F13/F8 -> #DIV/0! | H14: =H13/H8 -> #DIV/0! | I14: =I13/I8 -> #DIV/0! | J14: =J13/J8 -> #DIV/0! | K14: =K13/K8 -> #DIV/0! | L14: =L13/L8 -> #DIV/0! | M14: =M13/M8 -> #DIV/0! | N14: =N13/N8 -> #DIV/0! | O14: =O13/O8 -> #DIV/0! | ... V14: =V13/V8 -> #DIV/0! | X14: =X13/X8 -> #DIV/0! | Y14: =Y13/Y8 -> #DIV/0! | Z14: =Z13/Z8 -> #DIV/0! | AA14: =AA13/AA8 -> #DIV/0! | AB14: =AB13/AB8 -> #DIV/0! | AC14: =AC13/AC8 -> #DIV/0! | AD14: =AD13/AD8 -> #DIV/0! | AE14: =AE13/AE8 -> #DIV/0! | ... AI14: =AI13/AI8 -> #DIV/0! | AK14: =SUM(AI14-AE14)*10000 -> #DIV/0!
B16: (-) Research and development | C16: ='Historical Financials'!#REF! -> #REF! | H16: ='Historical Financials'!H17 -> -3066.951 | I16: ='Historical Financials'!I17 -> -2915.158 | J16: ='Historical Financials'!J17 -> -3185.451 | K16: ='Historical Financials'!K17 -> -3902.44 | L16: ='Historical Financials'!L17 -> -3317.036 | M16: ='Historical Financials'!M17 -> -2882.568 | N16: ='Historical Financials'!N17 -> -3247.843 | O16: ='Historical Financials'!O17 -> -2591.553 | ... Q16: ='Historical Financials'!Q17 -> -2790 | X16: =SUM(G16:K16) -> -13070 | Y16: =SUM(I16:L16) -> -13320.085 | Z16: =SUM(J16:M16) -> -13287.495 | AA16: =SUM(K16:N16) -> -13349.887 | AB16: =SUM(L16:O16) -> -12039 | AC16: =SUM(M16:P16) -> -11330.964 | AD16: =SUM(N16:Q16) -> -11238.396 | AE16: =SUM(O16:R16) -> -7990.553 | AF16: =SUM(P16:S16) -> -5399 | ... AI16: =SUM(S16:V16) -> 0 | AK16: =SUM(AI16/AE16)-1 -> -1
B17: (-) Sales and marketing | C17: ='Historical Financials'!#REF! -> #REF! | H17: ='Historical Financials'!H18 -> -8656.439 | I17: ='Historical Financials'!I18 -> -8604.589 | J17: ='Historical Financials'!J18 -> -9273.269 | K17: ='Historical Financials'!K18 -> -11381.703 | L17: ='Historical Financials'!L18 -> -12066.919 | M17: ='Historical Financials'!M18 -> -11306.591 | N17: ='Historical Financials'!N18 -> -10282.854 | O17: ='Historical Financials'!O18 -> -10060.636 | ... Q17: ='Historical Financials'!Q18 -> -9729 | X17: =SUM(G17:K17) -> -37916 | Y17: =SUM(I17:L17) -> -41326.48 | Z17: =SUM(J17:M17) -> -44028.482 | AA17: =SUM(K17:N17) -> -45038.067 | AB17: =SUM(L17:O17) -> -43717 | AC17: =SUM(M17:P17) -> -40334.081 | AD17: =SUM(N17:Q17) -> -38756.49 | AE17: =SUM(O17:R17) -> -28473.636 | AF17: =SUM(P17:S17) -> -18413 | ... AI17: =SUM(S17:V17) -> 0 | AK17: =SUM(AI17/AE17)-1 -> -1
B18: (-) General and administrative | C18: ='Historical Financials'!#REF! -> #REF! | H18: ='Historical Financials'!#REF! -> #REF! | I18: ='Historical Financials'!#REF! -> #REF! | J18: ='Historical Financials'!#REF! -> #REF! | K18: ='Historical Financials'!#REF! -> #REF! | L18: ='Historical Financials'!#REF! -> #REF! | M18: ='Historical Financials'!#REF! -> #REF! | N18: ='Historical Financials'!#REF! -> #REF! | O18: ='Historical Financials'!#REF! -> #REF! | ... Q18: ='Historical Financials'!#REF! -> #REF! | X18: =SUM(G18:K18) -> #REF! | Y18: =SUM(I18:L18) -> #REF! | Z18: =SUM(J18:M18) -> #REF! | AA18: =SUM(K18:N18) -> #REF! | AB18: =SUM(L18:O18) -> #REF! | AC18: =SUM(M18:P18) -> #REF! | AD18: =SUM(N18:Q18) -> #REF! | AE18: =SUM(O18:R18) -> #REF! | AF18: =SUM(P18:S18) -> #REF! | ... AI18: =SUM(S18:V18) -> 0 | AK18: =SUM(AI18/AE18)-1 -> #REF!
B19: (-) Depreciation and amortization | C19: ='Historical Financials'!#REF! -> #REF! | H19: ='Historical Financials'!#REF! -> #REF! | I19: ='Historical Financials'!#REF! -> #REF! | J19: ='Historical Financials'!#REF! -> #REF! | K19: ='Historical Financials'!#REF! -> #REF! | L19: ='Historical Financials'!#REF! -> #REF! | M19: ='Historical Financials'!#REF! -> #REF! | N19: ='Historical Financials'!#REF! -> #REF! | O19: ='Historical Financials'!#REF! -> #REF! | ... Q19: ='Historical Financials'!#REF! -> #REF! | X19: =SUM(G19:K19) -> #REF! | Y19: =SUM(I19:L19) -> #REF! | Z19: =SUM(J19:M19) -> #REF! | AA19: =SUM(K19:N19) -> #REF! | AB19: =SUM(L19:O19) -> #REF! | AC19: =SUM(M19:P19) -> #REF! | AD19: =SUM(N19:Q19) -> #REF! | AE19: =SUM(O19:R19) -> #REF! | AF19: =SUM(P19:S19) -> #REF! | ... AI19: =SUM(S19:V19) -> 0 | AK19: =SUM(AI19/AE19)-1 -> #REF!
B20: Earning before Interest & Taxes (EBIT) | C20: =SUM(C13+SUM(C16:C19)) -> #REF! | D20: =SUM(D13+SUM(D16:D19)) -> 0 | E20: =SUM(E13+SUM(E16:E19)) -> 0 | F20: =SUM(F13+SUM(F16:F19)) -> 0 | H20: =SUM(H13+SUM(H16:H19)) -> #REF! | I20: =SUM(I13+SUM(I16:I19)) -> #REF! | J20: =SUM(J13+SUM(J16:J19)) -> #REF! | K20: =SUM(K13+SUM(K16:K19)) -> #REF! | L20: =SUM(L13+SUM(L16:L19)) -> #REF! | M20: =SUM(M13+SUM(M16:M19)) -> #REF! | N20: =SUM(N13+SUM(N16:N19)) -> #REF! | O20: =SUM(O13+SUM(O16:O19)) -> #REF! | ... V20: =SUM(V13+SUM(V16:V19)) -> 0 | X20: =SUM(X13+SUM(X16:X19)) -> #REF! | Y20: =SUM(Y13+SUM(Y16:Y19)) -> #REF! | Z20: =SUM(Z13+SUM(Z16:Z19)) -> #REF! | AA20: =SUM(AA13+SUM(AA16:AA19)) -> #REF! | AB20: =SUM(AB13+SUM(AB16:AB19)) -> #REF! | AC20: =SUM(AC13+SUM(AC16:AC19)) -> #REF! | AD20: =SUM(AD13+SUM(AD16:AD19)) -> #REF! | AE20: =SUM(AE13+SUM(AE16:AE19)) -> #REF! | ... AI20: =SUM(AI13+SUM(AI16:AI19)) -> 0 | AK20: =SUM(AI20/AE20)-1 -> #REF!
B21: Operating Margin (%) | C21: =C20/C8 -> #REF! | D21: =D20/D8 -> #DIV/0! | E21: =E20/E8 -> #DIV/0! | F21: =F20/F8 -> #DIV/0! | H21: =H20/H8 -> #REF! | I21: =I20/I8 -> #REF! | J21: =J20/J8 -> #REF! | K21: =K20/K8 -> #REF! | L21: =L20/L8 -> #REF! | M21: =M20/M8 -> #REF! | N21: =N20/N8 -> #REF! | O21: =O20/O8 -> #REF! | ... V21: =V20/V8 -> #DIV/0! | X21: =X20/X8 -> #REF! | Y21: =Y20/Y8 -> #REF! | Z21: =Z20/Z8 -> #REF! | AA21: =AA20/AA8 -> #REF! | AB21: =AB20/AB8 -> #REF! | AC21: =AC20/AC8 -> #REF! | AD21: =AD20/AD8 -> #REF! | AE21: =AE20/AE8 -> #REF! | ... AI21: =AI20/AI8 -> #DIV/0! | AK21: =SUM(AI21-AE21)*10000 -> #DIV/0!
B23: (+) Depreciation and Amortization | C23: =-C19 -> #REF! | H23: =-H19 -> #REF! | I23: =-I19 -> #REF! | J23: =-J19 -> #REF! | K23: =-K19 -> #REF! | L23: =-L19 -> #REF! | M23: =-M19 -> #REF! | N23: =-N19 -> #REF! | O23: =-O19 -> #REF! | ... Q23: =-Q19 -> #REF! | X23: =SUM(G23:K23) -> #REF! | Y23: =SUM(I23:L23) -> #REF! | Z23: =SUM(J23:M23) -> #REF! | AA23: =SUM(K23:N23) -> #REF! | AB23: =SUM(L23:O23) -> #REF! | AC23: =SUM(M23:P23) -> #REF! | AD23: =SUM(N23:Q23) -> #REF! | AE23: =SUM(O23:R23) -> #REF! | AF23: =SUM(P23:S23) -> #REF! | ... AI23: =SUM(S23:V23) -> 0 | AK23: =SUM(AI23/AE23)-1 -> #REF!
B24: EBITDA | C24: =SUM(C20+C23) -> #REF! | D24: =SUM(D20+D23) -> 0 | E24: =SUM(E20+E23) -> 0 | F24: =SUM(F20+F23) -> 0 | H24: =SUM(H20+H23) -> #REF! | I24: =SUM(I20+I23) -> #REF! | J24: =SUM(J20+J23) -> #REF! | K24: =SUM(K20+K23) -> #REF! | L24: =SUM(L20+L23) -> #REF! | M24: =SUM(M20+M23) -> #REF! | N24: =SUM(N20+N23) -> #REF! | O24: =SUM(O20+O23) -> #REF! | ... V24: =SUM(V20+V23) -> 0 | X24: =SUM(X20+X23) -> #REF! | Y24: =SUM(Y20+Y23) -> #REF! | Z24: =SUM(Z20+Z23) -> #REF! | AA24: =SUM(AA20+AA23) -> #REF! | AB24: =SUM(AB20+AB23) -> #REF! | AC24: =SUM(AC20+AC23) -> #REF! | AD24: =SUM(AD20+AD23) -> #REF! | AE24: =SUM(AE20+AE23) -> #REF! | ... AI24: =SUM(AI20+AI23) -> 0 | AK24: =SUM(AI24/AE24)-1 -> #REF!
B25: EBITDA Margin (%) | C25: =C24/C8 -> #REF! | D25: =D24/D8 -> #DIV/0! | E25: =E24/E8 -> #DIV/0! | F25: =F24/F8 -> #DIV/0! | H25: =H24/H8 -> #REF! | I25: =I24/I8 -> #REF! | J25: =J24/J8 -> #REF! | K25: =K24/K8 -> #REF! | L25: =L24/L8 -> #REF! | M25: =M24/M8 -> #REF! | N25: =N24/N8 -> #REF! | O25: =O24/O8 -> #REF! | ... V25: =V24/V8 -> #DIV/0! | X25: =X24/X8 -> #REF! | Y25: =Y24/Y8 -> #REF! | Z25: =Z24/Z8 -> #REF! | AA25: =AA24/AA8 -> #REF! | AB25: =AB24/AB8 -> #REF! | AC25: =AC24/AC8 -> #REF! | AD25: =AD24/AD8 -> #REF! | AE25: =AE24/AE8 -> #REF! | ... AI25: =AI24/AI8 -> #DIV/0! | AK25: =SUM(AI25-AE25)*10000 -> #DIV/0!
B27: (+) Share-based Compensation | C27: ='Historical Financials'!#REF! -> #REF! | H27: ='Historical Financials'!H78 -> 0 | I27: ='Historical Financials'!I78 -> 0 | J27: ='Historical Financials'!J78 -> 0 | K27: ='Historical Financials'!K78 -> 0 | L27: ='Historical Financials'!L78 -> 0 | M27: ='Historical Financials'!M78 -> 0 | N27: ='Historical Financials'!N78 -> 0 | O27: ='Historical Financials'!O78 -> 0 | ... Q27: ='Historical Financials'!Q78 -> 0 | X27: =SUM(G27:K27) -> 0 | Y27: =SUM(I27:L27) -> 0 | Z27: =SUM(J27:M27) -> 0 | AA27: =SUM(K27:N27) -> 0 | AB27: =SUM(L27:O27) -> 0 | AC27: =SUM(M27:P27) -> 0 | AD27: =SUM(N27:Q27) -> 0 | AE27: =SUM(O27:R27) -> 0 | AF27: =SUM(P27:S27) -> 0 | ... AI27: =SUM(S27:V27) -> 0 | AK27: =SUM(AI27/AE27)-1 -> #DIV/0!
B28: Adj. EBITDA | C28: =+SUM(C24+SUM(C27:C27)) -> #REF! | D28: =+SUM(D24+SUM(D27:D27)) -> 0 | E28: =+SUM(E24+SUM(E27:E27)) -> 0 | F28: =+SUM(F24+SUM(F27:F27)) -> 0 | H28: =+SUM(H24+SUM(H27:H27)) -> #REF! | I28: =+SUM(I24+SUM(I27:I27)) -> #REF! | J28: =+SUM(J24+SUM(J27:J27)) -> #REF! | K28: =+SUM(K24+SUM(K27:K27)) -> #REF! | L28: =+SUM(L24+SUM(L27:L27)) -> #REF! | M28: =+SUM(M24+SUM(M27:M27)) -> #REF! | N28: =+SUM(N24+SUM(N27:N27)) -> #REF! | O28: =+SUM(O24+SUM(O27:O27)) -> #REF! | ... V28: =+SUM(V24+SUM(V27:V27)) -> 0 | X28: =+SUM(X24+SUM(X27:X27)) -> #REF! | Y28: =+SUM(Y24+SUM(Y27:Y27)) -> #REF! | Z28: =+SUM(Z24+SUM(Z27:Z27)) -> #REF! | AA28: =+SUM(AA24+SUM(AA27:AA27)) -> #REF! | AB28: =+SUM(AB24+SUM(AB27:AB27)) -> #REF! | AC28: =+SUM(AC24+SUM(AC27:AC27)) -> #REF! | AD28: =+SUM(AD24+SUM(AD27:AD27)) -> #REF! | AE28: =+SUM(AE24+SUM(AE27:AE27)) -> #REF! | ... AI28: =+SUM(AI24+SUM(AI27:AI27)) -> 0 | AK28: =SUM(AI28/AE28)-1 -> #REF!
B29: Adj. EBITDA Margin (%) | C29: =C28/C8 -> #REF! | D29: =D28/D8 -> #DIV/0! | E29: =E28/E8 -> #DIV/0! | F29: =F28/F8 -> #DIV/0! | H29: =H28/H8 -> #REF! | I29: =I28/I8 -> #REF! | J29: =J28/J8 -> #REF! | K29: =K28/K8 -> #REF! | L29: =L28/L8 -> #REF! | M29: =M28/M8 -> #REF! | N29: =N28/N8 -> #REF! | O29: =O28/O8 -> #REF! | ... V29: =V28/V8 -> #DIV/0! | X29: =X28/X8 -> #REF! | Y29: =Y28/Y8 -> #REF! | Z29: =Z28/Z8 -> #REF! | AA29: =AA28/AA8 -> #REF! | AB29: =AB28/AB8 -> #REF! | AC29: =AC28/AC8 -> #REF! | AD29: =AD28/AD8 -> #REF! | AE29: =AE28/AE8 -> #REF! | ... AI29: =AI28/AI8 -> #DIV/0! | AK29: =SUM(AI29-AE29)*10000 -> #DIV/0!
B31: (-) Capital Expenditures | C31: =SUM('Historical Financials'!#REF!+'Historical Financials'!#REF!) -> #REF! | H31: =SUM('Historical Financials'!#REF!+'Historical Financials'!#REF!) -> #REF! | I31: =SUM('Historical Financials'!#REF!+'Historical Financials'!#REF!) -> #REF! | J31: =SUM('Historical Financials'!#REF!+'Historical Financials'!#REF!) -> #REF! | K31: =SUM('Historical Financials'!#REF!+'Historical Financials'!#REF!) -> #REF! | L31: =SUM('Historical Financials'!#REF!+'Historical Financials'!#REF!) -> #REF! | M31: =SUM('Historical Financials'!#REF!+'Historical Financials'!#REF!) -> #REF! | N31: =SUM('Historical Financials'!#REF!+'Historical Financials'!#REF!) -> #REF! | O31: =SUM('Historical Financials'!#REF!+'Historical Financials'!#REF!) -> #REF! | ... Q31: =SUM('Historical Financials'!#REF!+'Historical Financials'!#REF!) -> #REF! | X31: =SUM(G31:K31) -> #REF! | Y31: =SUM(I31:L31) -> #REF! | Z31: =SUM(J31:M31) -> #REF! | AA31: =SUM(K31:N31) -> #REF! | AB31: =SUM(L31:O31) -> #REF! | AC31: =SUM(M31:P31) -> #REF! | AD31: =SUM(N31:Q31) -> #REF! | AE31: =SUM(O31:R31) -> #REF! | AF31: =SUM(P31:S31) -> #REF! | ... AI31: =SUM(S31:V31) -> 0 | AK31: =SUM(AI31/AE31)-1 -> #REF!
B32: (-) Cash Taxes | C32: ='Historical Financials'!#REF! -> #REF! | H32: ='Historical Financials'!H31 -> -29.98 | I32: ='Historical Financials'!I31 -> -29.8 | J32: ='Historical Financials'!J31 -> -88.421 | K32: ='Historical Financials'!K31 -> -209.799 | L32: ='Historical Financials'!L31 -> 20.046 | M32: ='Historical Financials'!M31 -> -50 | N32: ='Historical Financials'!N31 -> -41 | O32: ='Historical Financials'!O31 -> 63.954 | ... Q32: ='Historical Financials'!Q31 -> -105 | X32: =SUM(G32:K32) -> -358 | Y32: =SUM(I32:L32) -> -307.974 | Z32: =SUM(J32:M32) -> -328.174 | AA32: =SUM(K32:N32) -> -280.753 | AB32: =SUM(L32:O32) -> -7 | AC32: =SUM(M32:P32) -> -112.046 | AD32: =SUM(N32:Q32) -> -167.046 | AE32: =SUM(O32:R32) -> -126.046 | AF32: =SUM(P32:S32) -> -190 | ... AI32: =SUM(S32:V32) -> 0 | AK32: =SUM(AI32/AE32)-1 -> -1
B33: (-) Cash Interest | C33: 0 | H33: 0 | I33: 0 | J33: 0 | K33: =D33 -> 0 | L33: 0 | M33: 0 | N33: 0 | O33: =E33 -> 0 | P33: 0 | Q33: 0 | X33: =SUM(G33:K33) -> 0 | Y33: =SUM(I33:L33) -> 0 | Z33: =SUM(J33:M33) -> 0 | AA33: =SUM(K33:N33) -> 0 | AB33: =SUM(L33:O33) -> 0 | AC33: =SUM(M33:P33) -> 0 | AD33: =SUM(N33:Q33) -> 0 | AE33: =SUM(O33:R33) -> 0 | AF33: =SUM(P33:S33) -> 0 | ... AI33: =SUM(S33:V33) -> 0 | AK33: =SUM(AI33/AE33)-1 -> #DIV/0!
B34: (+/-) Changes in NWC | C34: =SUM('Historical Financials'!#REF!) -> #REF! | H34: =SUM('Historical Financials'!H82:H86) -> 3472.641 | I34: =SUM('Historical Financials'!I82:I86) -> -3641.132 | J34: =SUM('Historical Financials'!J82:J86) -> 1325.237 | K34: =SUM('Historical Financials'!K82:K86) -> 4204.254 | L34: =SUM('Historical Financials'!L82:L86) -> 1830.953 | M34: =SUM('Historical Financials'!M82:M86) -> -195.864 | N34: =SUM('Historical Financials'!N82:N86) -> -1164.0477 | O34: =SUM('Historical Financials'!O82:O86) -> 2033.9587 | ... Q34: =SUM('Historical Financials'!Q82:Q86) -> -3762 | X34: =SUM(G34:K34) -> 5361 | Y34: =SUM(I34:L34) -> 3719.312 | Z34: =SUM(J34:M34) -> 7164.58 | AA34: =SUM(K34:N34) -> 4675.2953 | AB34: =SUM(L34:O34) -> 2505 | AC34: =SUM(M34:P34) -> -307.953 | AD34: =SUM(N34:Q34) -> -3874.089 | AE34: =SUM(O34:R34) -> -2710.0413 | AF34: =SUM(P34:S34) -> -4744 | ... AI34: =SUM(S34:V34) -> 0 | AK34: =SUM(AI34/AE34)-1 -> -1
B35: Discretionary Cash-Flows | C35: =SUM(C28+SUM(C31:C34)) -> #REF! | D35: =SUM(D28+SUM(D31:D34)) -> 0 | E35: =SUM(E28+SUM(E31:E34)) -> 0 | F35: =SUM(F28+SUM(F31:F34)) -> 0 | H35: =SUM(H28+SUM(H31:H34)) -> #REF! | I35: =SUM(I28+SUM(I31:I34)) -> #REF! | J35: =SUM(J28+SUM(J31:J34)) -> #REF! | K35: =SUM(K28+SUM(K31:K34)) -> #REF! | L35: =SUM(L28+SUM(L31:L34)) -> #REF! | M35: =SUM(M28+SUM(M31:M34)) -> #REF! | N35: =SUM(N28+SUM(N31:N34)) -> #REF! | O35: =SUM(O28+SUM(O31:O34)) -> #REF! | ... V35: =SUM(V28+SUM(V31:V34)) -> 0 | X35: =SUM(X28+SUM(X31:X34)) -> #REF! | Y35: =SUM(Y28+SUM(Y31:Y34)) -> #REF! | Z35: =SUM(Z28+SUM(Z31:Z34)) -> #REF! | AA35: =SUM(AA28+SUM(AA31:AA34)) -> #REF! | AB35: =SUM(AB28+SUM(AB31:AB34)) -> #REF! | AC35: =SUM(AC28+SUM(AC31:AC34)) -> #REF! | AD35: =SUM(AD28+SUM(AD31:AD34)) -> #REF! | AE35: =SUM(AE28+SUM(AE31:AE34)) -> #REF! | ... AI35: =SUM(AI28+SUM(AI31:AI34)) -> 0 | AK35: =SUM(AI35/AE35)-1 -> #REF!
B37: (+/-) Proceeds / (Purchases) of Equity, net | C37: ='Historical Financials'!#REF! -> #REF! | H37: ='Historical Financials'!#REF! -> #REF! | I37: ='Historical Financials'!#REF! -> #REF! | J37: ='Historical Financials'!#REF! -> #REF! | K37: ='Historical Financials'!#REF! -> #REF! | L37: ='Historical Financials'!#REF! -> #REF! | M37: ='Historical Financials'!#REF! -> #REF! | N37: ='Historical Financials'!#REF! -> #REF! | O37: ='Historical Financials'!#REF! -> #REF! | ... Q37: ='Historical Financials'!#REF! -> #REF! | X37: =SUM(G37:K37) -> #REF! | Y37: =SUM(I37:L37) -> #REF! | Z37: =SUM(J37:M37) -> #REF! | AA37: =SUM(K37:N37) -> #REF! | AB37: =SUM(L37:O37) -> #REF! | AC37: =SUM(M37:P37) -> #REF! | AD37: =SUM(N37:Q37) -> #REF! | AE37: =SUM(O37:R37) -> #REF! | AF37: =SUM(P37:S37) -> #REF! | ... AI37: =SUM(S37:V37) -> 0
B38: (+/-) Maturities / (Purchases) of available-for-sale securities | C38: =SUM('Historical Financials'!#REF!) -> #REF! | H38: =SUM('Historical Financials'!#REF!) -> #REF! | I38: =SUM('Historical Financials'!#REF!) -> #REF! | J38: =SUM('Historical Financials'!#REF!) -> #REF! | K38: =SUM('Historical Financials'!#REF!) -> #REF! | L38: =SUM('Historical Financials'!#REF!) -> #REF! | M38: =SUM('Historical Financials'!#REF!) -> #REF! | N38: =SUM('Historical Financials'!#REF!) -> #REF! | O38: =SUM('Historical Financials'!#REF!) -> #REF! | ... Q38: =SUM('Historical Financials'!#REF!) -> #REF! | X38: =SUM(G38:K38) -> #REF! | Y38: =SUM(I38:L38) -> #REF! | Z38: =SUM(J38:M38) -> #REF! | AA38: =SUM(K38:N38) -> #REF! | AB38: =SUM(L38:O38) -> #REF! | AC38: =SUM(M38:P38) -> #REF! | AD38: =SUM(N38:Q38) -> #REF! | AE38: =SUM(O38:R38) -> #REF! | AF38: =SUM(P38:S38) -> #REF! | ... AI38: =SUM(S38:V38) -> 0
B39: (+/-) Divestitures / (Acquisitions) | C39: ='Historical Financials'!#REF! -> #REF! | H39: ='Historical Financials'!#REF! -> #REF! | I39: ='Historical Financials'!#REF! -> #REF! | J39: ='Historical Financials'!#REF! -> #REF! | K39: ='Historical Financials'!#REF! -> #REF! | L39: ='Historical Financials'!#REF! -> #REF! | M39: ='Historical Financials'!#REF! -> #REF! | N39: ='Historical Financials'!#REF! -> #REF! | O39: ='Historical Financials'!#REF! -> #REF! | ... Q39: ='Historical Financials'!#REF! -> #REF! | X39: =SUM(G39:K39) -> #REF! | Y39: =SUM(I39:L39) -> #REF! | Z39: =SUM(J39:M39) -> #REF! | AA39: =SUM(K39:N39) -> #REF! | AB39: =SUM(L39:O39) -> #REF! | AC39: =SUM(M39:P39) -> #REF! | AD39: =SUM(N39:Q39) -> #REF! | AE39: =SUM(O39:R39) -> #REF! | AF39: =SUM(P39:S39) -> #REF! | ... AI39: =SUM(S39:V39) -> 0
B40: (+/-) Other Investing Activities | C40: ='Historical Financials'!#REF! -> #REF! | H40: ='Historical Financials'!#REF! -> #REF! | I40: ='Historical Financials'!#REF! -> #REF! | J40: ='Historical Financials'!#REF! -> #REF! | K40: ='Historical Financials'!#REF! -> #REF! | L40: ='Historical Financials'!#REF! -> #REF! | M40: ='Historical Financials'!#REF! -> #REF! | N40: ='Historical Financials'!#REF! -> #REF! | O40: ='Historical Financials'!#REF! -> #REF! | ... Q40: ='Historical Financials'!#REF! -> #REF! | X40: =SUM(G40:K40) -> #REF! | Y40: =SUM(I40:L40) -> #REF! | Z40: =SUM(J40:M40) -> #REF! | AA40: =SUM(K40:N40) -> #REF! | AB40: =SUM(L40:O40) -> #REF! | AC40: =SUM(M40:P40) -> #REF! | AD40: =SUM(N40:Q40) -> #REF! | AE40: =SUM(O40:R40) -> #REF! | AF40: =SUM(P40:S40) -> #REF! | ... AI40: =SUM(S40:V40) -> 0
B41: (+/-) Other Financing Activities | C41: ='Historical Financials'!#REF! -> #REF! | H41: ='Historical Financials'!#REF! -> #REF! | I41: ='Historical Financials'!#REF! -> #REF! | J41: ='Historical Financials'!#REF! -> #REF! | K41: ='Historical Financials'!#REF! -> #REF! | L41: ='Historical Financials'!#REF! -> #REF! | M41: ='Historical Financials'!#REF! -> #REF! | N41: ='Historical Financials'!#REF! -> #REF! | O41: ='Historical Financials'!#REF! -> #REF! | ... Q41: ='Historical Financials'!#REF! -> #REF! | X41: =SUM(G41:K41) -> #REF! | Y41: =SUM(I41:L41) -> #REF! | Z41: =SUM(J41:M41) -> #REF! | AA41: =SUM(K41:N41) -> #REF! | AB41: =SUM(L41:O41) -> #REF! | AC41: =SUM(M41:P41) -> #REF! | AD41: =SUM(N41:Q41) -> #REF! | AE41: =SUM(O41:R41) -> #REF! | AF41: =SUM(P41:S41) -> #REF! | ... AI41: =SUM(S41:V41) -> 0
B42: (+/-) Other Operating Activities | C42: ='Historical Financials'!#REF! -> #REF! | H42: ='Historical Financials'!#REF! -> #REF! | I42: ='Historical Financials'!#REF! -> #REF! | J42: ='Historical Financials'!#REF! -> #REF! | K42: ='Historical Financials'!#REF! -> #REF! | L42: ='Historical Financials'!#REF! -> #REF! | M42: ='Historical Financials'!#REF! -> #REF! | N42: ='Historical Financials'!#REF! -> #REF! | O42: ='Historical Financials'!#REF! -> #REF! | ... Q42: ='Historical Financials'!#REF! -> #REF! | X42: =SUM(G42:K42) -> #REF! | Y42: =SUM(I42:L42) -> #REF! | Z42: =SUM(J42:M42) -> #REF! | AA42: =SUM(K42:N42) -> #REF! | AB42: =SUM(L42:O42) -> #REF! | AC42: =SUM(M42:P42) -> #REF! | AD42: =SUM(N42:Q42) -> #REF! | AE42: =SUM(O42:R42) -> #REF! | AF42: =SUM(P42:S42) -> #REF! | ... AI42: =SUM(S42:V42) -> 0
B43: (+/-) Other | H43: =SUM(H48:H49)-SUM(C48:C49)-SUM(H35:H42) -> #REF! | I43: =SUM(I48:I49)-SUM(H48:H49)-SUM(I35:I42) -> #REF! | J43: =SUM(J48:J49)-SUM(I48:I49)-SUM(J35:J42) -> #REF! | K43: =SUM(K48:K49)-SUM(J48:J49)-SUM(K35:K42) -> #REF! | L43: =SUM(L48:L49)-SUM(K48:K49)-SUM(L35:L42) -> #REF! | M43: =SUM(M48:M49)-SUM(L48:L49)-SUM(M35:M42) -> #REF! | N43: =SUM(N48:N49)-SUM(M48:M49)-SUM(N35:N42) -> #REF! | O43: =SUM(O48:O49)-SUM(N48:N49)-SUM(O35:O42) -> #REF! | P43: =SUM(P48:P49)-SUM(O48:O49)-SUM(P35:P42) -> #REF! | Q43: =SUM(Q48:Q49)-SUM(P48:P49)-SUM(Q35:Q42) -> #REF! | X43: =SUM(G43:K43) -> #REF! | Y43: =SUM(I43:L43) -> #REF! | Z43: =SUM(J43:M43) -> #REF! | AA43: =SUM(K43:N43) -> #REF! | AB43: =SUM(L43:O43) -> #REF! | AC43: =SUM(M43:P43) -> #REF! | AD43: =SUM(N43:Q43) -> #REF! | AE43: =SUM(O43:R43) -> #REF! | AF43: =SUM(P43:S43) -> #REF! | ... AI43: =SUM(S43:V43) -> 0
B44: Free-Cash Flows | C44: =SUM(C35+SUM(C37:C43)) -> #REF! | D44: =SUM(D35+SUM(D37:D43)) -> 0 | E44: =SUM(E35+SUM(E37:E43)) -> 0 | F44: =SUM(F35+SUM(F37:F43)) -> 0 | H44: =SUM(H35+SUM(H37:H43)) -> #REF! | I44: =SUM(I35+SUM(I37:I43)) -> #REF! | J44: =SUM(J35+SUM(J37:J43)) -> #REF! | K44: =SUM(K35+SUM(K37:K43)) -> #REF! | L44: =SUM(L35+SUM(L37:L43)) -> #REF! | M44: =SUM(M35+SUM(M37:M43)) -> #REF! | N44: =SUM(N35+SUM(N37:N43)) -> #REF! | O44: =SUM(O35+SUM(O37:O43)) -> #REF! | ... V44: =SUM(V35+SUM(V37:V43)) -> 0 | X44: =SUM(X35+SUM(X37:X43)) -> #REF! | Y44: =SUM(Y35+SUM(Y37:Y43)) -> #REF! | Z44: =SUM(Z35+SUM(Z37:Z43)) -> #REF! | AA44: =SUM(AA35+SUM(AA37:AA43)) -> #REF! | AB44: =SUM(AB35+SUM(AB37:AB43)) -> #REF! | AC44: =SUM(AC35+SUM(AC37:AC43)) -> #REF! | AD44: =SUM(AD35+SUM(AD37:AD43)) -> #REF! | AE44: =SUM(AE35+SUM(AE37:AE43)) -> #REF! | ... AI44: =SUM(AI35+SUM(AI37:AI43)) -> 0
B46: Capitalization
B48: Cash & Cash Equivelants | C48: ='Historical Financials'!#REF! -> #REF! | H48: ='Historical Financials'!H46 -> 151146.36 | I48: ='Historical Financials'!I46 -> 153342.56 | J48: ='Historical Financials'!J46 -> 153199.35 | K48: ='Historical Financials'!K46 -> 149158 | L48: ='Historical Financials'!L46 -> 143621.85 | M48: ='Historical Financials'!M46 -> 153466.96 | N48: ='Historical Financials'!N46 -> 154817.16 | O48: ='Historical Financials'!O46 -> 151024 | ... Q48: ='Historical Financials'!Q46 -> 139386 | X48: =K48 -> 149158 | Y48: =L48 -> 143621.85 | Z48: =M48 -> 153466.96 | AA48: =N48 -> 154817.16 | AB48: =O48 -> 151024 | AC48: =P48 -> 143765 | AD48: =Q48 -> 139386 | AE48: =R48 -> 0 | ... AI48: =V48 -> 0
B49: Restricted Cash | C49: ='Historical Financials'!#REF! -> #REF! | H49: ='Historical Financials'!#REF! -> #REF! | I49: ='Historical Financials'!#REF! -> #REF! | J49: ='Historical Financials'!#REF! -> #REF! | K49: ='Historical Financials'!#REF! -> #REF! | L49: ='Historical Financials'!#REF! -> #REF! | M49: ='Historical Financials'!#REF! -> #REF! | N49: ='Historical Financials'!#REF! -> #REF! | O49: ='Historical Financials'!#REF! -> #REF! | ... Q49: ='Historical Financials'!#REF! -> #REF! | X49: =K49 -> #REF! | Y49: =L49 -> #REF! | Z49: =M49 -> #REF! | AA49: =N49 -> #REF! | AB49: =O49 -> #REF! | AC49: =P49 -> #REF! | AD49: =Q49 -> #REF! | AE49: =R49 -> 0 | ... AI49: =V49 -> 0
B50: Short-term Investments | C50: ='Historical Financials'!#REF! -> #REF! | H50: ='Historical Financials'!#REF! -> #REF! | I50: ='Historical Financials'!#REF! -> #REF! | J50: ='Historical Financials'!#REF! -> #REF! | K50: ='Historical Financials'!#REF! -> #REF! | L50: ='Historical Financials'!#REF! -> #REF! | M50: ='Historical Financials'!#REF! -> #REF! | N50: ='Historical Financials'!#REF! -> #REF! | O50: ='Historical Financials'!#REF! -> #REF! | ... Q50: ='Historical Financials'!#REF! -> #REF! | X50: =K50 -> #REF! | Y50: =L50 -> #REF! | Z50: =M50 -> #REF! | AA50: =N50 -> #REF! | AB50: =O50 -> #REF! | AC50: =P50 -> #REF! | AD50: =Q50 -> #REF! | AE50: =R50 -> 0 | ... AI50: =V50 -> 0
B51: Long-term Investments | C51: ='Historical Financials'!#REF! -> #REF! | H51: ='Historical Financials'!H52 -> 4634.791 | I51: ='Historical Financials'!I52 -> 2631.888 | J51: ='Historical Financials'!J52 -> 3126.892 | K51: ='Historical Financials'!K52 -> 3825 | L51: ='Historical Financials'!L52 -> 5288.261 | M51: ='Historical Financials'!M52 -> 6281.742 | N51: ='Historical Financials'!N52 -> 4152.846 | O51: ='Historical Financials'!O52 -> 4322 | ... Q51: ='Historical Financials'!Q52 -> 3726 | X51: =K51 -> 3825 | Y51: =L51 -> 5288.261 | Z51: =M51 -> 6281.742 | AA51: =N51 -> 4152.846 | AB51: =O51 -> 4322 | AC51: =P51 -> 4292 | AD51: =Q51 -> 3726 | AE51: =R51 -> 0 | ... AI51: =V51 -> 0
B52: Total Liquidity | C52: =SUM(C48:C51) -> #REF! | D52: =SUM(D48:D51) -> 0 | E52: =SUM(E48:E51) -> 0 | F52: =SUM(F48:F51) -> 0 | H52: =SUM(H48:H51) -> #REF! | I52: =SUM(I48:I51) -> #REF! | J52: =SUM(J48:J51) -> #REF! | K52: =SUM(K48:K51) -> #REF! | L52: =SUM(L48:L51) -> #REF! | M52: =SUM(M48:M51) -> #REF! | N52: =SUM(N48:N51) -> #REF! | O52: =SUM(O48:O51) -> #REF! | ... V52: =SUM(V48:V51) -> 0 | X52: =SUM(X48:X51) -> #REF! | Y52: =SUM(Y48:Y51) -> #REF! | Z52: =SUM(Z48:Z51) -> #REF! | AA52: =SUM(AA48:AA51) -> #REF! | AB52: =SUM(AB48:AB51) -> #REF! | AC52: =SUM(AC48:AC51) -> #REF! | AD52: =SUM(AD48:AD51) -> #REF! | AE52: =SUM(AE48:AE51) -> 0 | ... AI52: =SUM(AI48:AI51) -> 0
B54: Balance Sheet Metrics:
B55: Accounts Receivable | C55: ='Historical Financials'!#REF! -> #REF! | H55: ='Historical Financials'!#REF! -> #REF! | I55: ='Historical Financials'!#REF! -> #REF! | J55: ='Historical Financials'!#REF! -> #REF! | K55: ='Historical Financials'!#REF! -> #REF! | L55: ='Historical Financials'!#REF! -> #REF! | M55: ='Historical Financials'!#REF! -> #REF! | N55: ='Historical Financials'!#REF! -> #REF! | O55: ='Historical Financials'!#REF! -> #REF! | ... Q55: ='Historical Financials'!#REF! -> #REF! | X55: =K55 -> #REF! | Y55: =L55 -> #REF! | Z55: =M55 -> #REF! | AA55: =N55 -> #REF! | AB55: =O55 -> #REF! | AC55: =P55 -> #REF! | AD55: =Q55 -> #REF! | AE55: =R55 -> 0 | ... AI55: =V55 -> 0
B56: Accounts Payable | C56: ='Historical Financials'!#REF! -> #REF! | H56: ='Historical Financials'!#REF! -> #REF! | I56: ='Historical Financials'!#REF! -> #REF! | J56: ='Historical Financials'!#REF! -> #REF! | K56: ='Historical Financials'!#REF! -> #REF! | L56: ='Historical Financials'!#REF! -> #REF! | M56: ='Historical Financials'!#REF! -> #REF! | N56: ='Historical Financials'!#REF! -> #REF! | O56: ='Historical Financials'!#REF! -> #REF! | ... Q56: ='Historical Financials'!#REF! -> #REF! | X56: =K56 -> #REF! | Y56: =L56 -> #REF! | Z56: =M56 -> #REF! | AA56: =N56 -> #REF! | AB56: =O56 -> #REF! | AC56: =P56 -> #REF! | AD56: =Q56 -> #REF! | AE56: =R56 -> 0 | ... AI56: =V56 -> 0
B57: Unearned Revenue, Current | C57: ='Historical Financials'!#REF! -> #REF! | H57: ='Historical Financials'!#REF! -> #REF! | I57: ='Historical Financials'!#REF! -> #REF! | J57: ='Historical Financials'!#REF! -> #REF! | K57: ='Historical Financials'!#REF! -> #REF! | L57: ='Historical Financials'!#REF! -> #REF! | M57: ='Historical Financials'!#REF! -> #REF! | N57: ='Historical Financials'!#REF! -> #REF! | O57: ='Historical Financials'!#REF! -> #REF! | ... Q57: ='Historical Financials'!#REF! -> #REF! | X57: =K57 -> #REF! | Y57: =L57 -> #REF! | Z57: =M57 -> #REF! | AA57: =N57 -> #REF! | AB57: =O57 -> #REF! | AC57: =P57 -> #REF! | AD57: =Q57 -> #REF! | AE57: =R57 -> 0 | ... AI57: =V57 -> 0
B58: Unearned Revenue, Non-Current | C58: ='Historical Financials'!#REF! -> #REF! | H58: ='Historical Financials'!#REF! -> #REF! | I58: ='Historical Financials'!#REF! -> #REF! | J58: ='Historical Financials'!#REF! -> #REF! | K58: ='Historical Financials'!#REF! -> #REF! | L58: ='Historical Financials'!#REF! -> #REF! | M58: ='Historical Financials'!#REF! -> #REF! | N58: ='Historical Financials'!#REF! -> #REF! | O58: ='Historical Financials'!#REF! -> #REF! | ... Q58: ='Historical Financials'!#REF! -> #REF! | X58: =K58 -> #REF! | Y58: =L58 -> #REF! | Z58: =M58 -> #REF! | AA58: =N58 -> #REF! | AB58: =O58 -> #REF! | AC58: =P58 -> #REF! | AD58: =Q58 -> #REF! | AE58: =R58 -> 0 | ... AI58: =V58 -> 0
B59: Property Plant, and Equiptment | C59: ='Historical Financials'!#REF! -> #REF! | H59: ='Historical Financials'!H54 -> 443.831 | I59: ='Historical Financials'!I54 -> 443.831 | J59: ='Historical Financials'!J54 -> 443.831 | K59: ='Historical Financials'!K54 -> 444 | L59: ='Historical Financials'!L54 -> 916.763 | M59: ='Historical Financials'!M54 -> 916.763 | N59: ='Historical Financials'!N54 -> 916.763 | O59: ='Historical Financials'!O54 -> 917 | ... Q59: ='Historical Financials'!Q54 -> 917 | X59: =K59 -> 444 | Y59: =L59 -> 916.763 | Z59: =M59 -> 916.763 | AA59: =N59 -> 916.763 | AB59: =O59 -> 917 | AC59: =P59 -> 917 | AD59: =Q59 -> 917 | AE59: =R59 -> 0 | ... AI59: =V59 -> 0
B60: Current Liabilities | C60: ='Historical Financials'!#REF! -> #REF! | H60: ='Historical Financials'!#REF! -> #REF! | I60: ='Historical Financials'!#REF! -> #REF! | J60: ='Historical Financials'!#REF! -> #REF! | K60: ='Historical Financials'!#REF! -> #REF! | L60: ='Historical Financials'!#REF! -> #REF! | M60: ='Historical Financials'!#REF! -> #REF! | N60: ='Historical Financials'!#REF! -> #REF! | O60: ='Historical Financials'!#REF! -> #REF! | ... Q60: ='Historical Financials'!#REF! -> #REF! | X60: =K60 -> #REF! | Y60: =L60 -> #REF! | Z60: =M60 -> #REF! | AA60: =N60 -> #REF! | AB60: =O60 -> #REF! | AC60: =P60 -> #REF! | AD60: =Q60 -> #REF! | AE60: =R60 -> 0 | ... AI60: =V60 -> 0
B61: Total Liabilities | C61: ='Historical Financials'!#REF! -> #REF! | H61: ='Historical Financials'!#REF! -> #REF! | I61: ='Historical Financials'!#REF! -> #REF! | J61: ='Historical Financials'!#REF! -> #REF! | K61: ='Historical Financials'!#REF! -> #REF! | L61: ='Historical Financials'!#REF! -> #REF! | M61: ='Historical Financials'!#REF! -> #REF! | N61: ='Historical Financials'!#REF! -> #REF! | O61: ='Historical Financials'!#REF! -> #REF! | ... Q61: ='Historical Financials'!#REF! -> #REF! | X61: =K61 -> #REF! | Y61: =L61 -> #REF! | Z61: =M61 -> #REF! | AA61: =N61 -> #REF! | AB61: =O61 -> #REF! | AC61: =P61 -> #REF! | AD61: =Q61 -> #REF! | AE61: =R61 -> 0 | ... AI61: =V61 -> 0
B63: Consolidated Debt | C63: 0 | H63: 0 | I63: 0 | J63: 0 | K63: =D63 -> 0 | L63: 0 | M63: 0 | N63: 0 | O63: =E63 -> 0 | P63: 0 | Q63: 0 | X63: =K63 -> 0 | Y63: =L63 -> 0 | Z63: =M63 -> 0 | AA63: =N63 -> 0 | AB63: =O63 -> 0 | AC63: =P63 -> 0 | AD63: =Q63 -> 0 | AE63: =R63 -> 0 | ... AI63: =V63 -> 0
B64: Total Debt | C64: =SUM(C63:C63) -> 0 | D64: =SUM(D63:D63) -> 0 | E64: =SUM(E63:E63) -> 0 | F64: =SUM(F63:F63) -> 0 | H64: =SUM(H63:H63) -> 0 | I64: =SUM(I63:I63) -> 0 | J64: =SUM(J63:J63) -> 0 | K64: =SUM(K63:K63) -> 0 | L64: =SUM(L63:L63) -> 0 | M64: =SUM(M63:M63) -> 0 | N64: =SUM(N63:N63) -> 0 | O64: =SUM(O63:O63) -> 0 | ... V64: =SUM(V63:V63) -> 0 | X64: =SUM(X63:X63) -> 0 | Y64: =SUM(Y63:Y63) -> 0 | Z64: =SUM(Z63:Z63) -> 0 | AA64: =SUM(AA63:AA63) -> 0 | AB64: =SUM(AB63:AB63) -> 0 | AC64: =SUM(AC63:AC63) -> 0 | AD64: =SUM(AD63:AD63) -> 0 | AE64: =SUM(AE63:AE63) -> 0 | ... AI64: =SUM(AI63:AI63) -> 0
B66: Total Shareholder Equity | C66: ='Historical Financials'!#REF! -> #REF! | H66: ='Historical Financials'!H62 -> 146367.71 | I66: ='Historical Financials'!I62 -> 152205.04 | J66: ='Historical Financials'!J62 -> 150736.6 | K66: ='Historical Financials'!K62 -> 142491 | L66: ='Historical Financials'!L62 -> 135124.08 | M66: ='Historical Financials'!M62 -> 145165.05 | N66: ='Historical Financials'!N62 -> 228064.21 | O66: ='Historical Financials'!O62 -> 141852 | ... Q66: ='Historical Financials'!Q62 -> 134958 | X66: =K66 -> 142491 | Y66: =L66 -> 135124.08 | Z66: =M66 -> 145165.05 | AA66: =N66 -> 228064.21 | AB66: =O66 -> 141852 | AC66: =P66 -> 135575 | AD66: =Q66 -> 134958 | AE66: =R66 -> 0 | ... AI66: =V66 -> 0
B67: Total Book Capitalization | C67: =SUM(C64:C66) -> #REF! | D67: =SUM(D64:D66) -> 0 | E67: =SUM(E64:E66) -> 0 | F67: =SUM(F64:F66) -> 0 | H67: =SUM(H64:H66) -> 146367.71 | I67: =SUM(I64:I66) -> 152205.04 | J67: =SUM(J64:J66) -> 150736.6 | K67: =SUM(K64:K66) -> 142491 | L67: =SUM(L64:L66) -> 135124.08 | M67: =SUM(M64:M66) -> 145165.05 | N67: =SUM(N64:N66) -> 228064.21 | O67: =SUM(O64:O66) -> 141852 | ... V67: =SUM(V64:V66) -> 0 | X67: =SUM(X64:X66) -> 142491 | Y67: =SUM(Y64:Y66) -> 135124.08 | Z67: =SUM(Z64:Z66) -> 145165.05 | AA67: =SUM(AA64:AA66) -> 228064.21 | AB67: =SUM(AB64:AB66) -> 141852 | AC67: =SUM(AC64:AC66) -> 135575 | AD67: =SUM(AD64:AD66) -> 134958 | AE67: =SUM(AE64:AE66) -> 0 | ... AI67: =SUM(AI64:AI66) -> 0
B69: Credit Metrics
B71: Total Leverage | C71: NM | L71: NM | M71: NM | N71: NM | O71: NM | P71: NM | Q71: NM | X71: NM | Y71: NM | Z71: NM | AA71: NM | AB71: NM | AC71: NM | AD71: NM
B72: Net Leverage (C&CE) | C72: NM | L72: NM | M72: NM | N72: NM | O72: NM | P72: NM | Q72: NM | X72: NM | Y72: NM | Z72: NM | AA72: NM | AB72: NM | AC72: NM | AD72: NM
B73: Interest Coverage | C73: NM | L73: NM | M73: NM | N73: NM | O73: NM | P73: NM | Q73: NM | X73: NM | Y73: NM | Z73: NM | AA73: NM | AB73: NM | AC73: NM | AD73: NM
B74: Debt Service Coverage | C74: NM | L74: NM | M74: NM | N74: NM | O74: NM | P74: NM | Q74: NM | X74: NM | Y74: NM | Z74: NM | AA74: NM | AB74: NM | AC74: NM | AD74: NM
B75: Fixed Charge Coverage | C75: NM | L75: NM | M75: NM | N75: NM | O75: NM | P75: NM | Q75: NM | X75: NM | Y75: NM | Z75: NM | AA75: NM | AB75: NM | AC75: NM | AD75: NM
B76: Debt-to-Book Capitalization | C76: NM | L76: NM | M76: NM | N76: NM | O76: NM | P76: NM | Q76: NM | X76: NM | Y76: NM | Z76: NM | AA76: NM | AB76: NM | AC76: NM | AD76: NM
