Workbook

Sheet Historical Financials
B2: Ulta Beauty Inc. (NASDAQ: ULTA)
B3: Historical Financials
B4: $ in thousands except per share
A6: X | B6: Income Statement | C6: FYE | F6: FYE | J6: Quarterly | T6: Quarterly | AF6: LTM | AG6: LTM | AM6: Variance
B7: Fiscal Period | C7: 2019 | D7: 2020 | E7: 2021 | F7: 2022 | G7: 2023 | H7: 2024 | J7: 1Q22 | K7: 2Q22 | L7: 3Q22 | M7: 4Q22 | N7: 1Q23 | O7: 2Q23 | P7: 3Q23 | Q7: 4Q23 | R7: 1Q24 | S7: 2Q24 | T7: 3Q24 | U7: 4Q24 | V7: 1Q25 | W7: 2Q25 | X7: 3Q25 | Z7: =M7 -> 4Q22 | AA7: =N7 -> 1Q23 | AB7: =O7 -> 2Q23 | AC7: =P7 -> 3Q23 | AD7: =Q7 -> 4Q23 | AE7: =R7 -> 1Q24 | AF7: =S7 -> 2Q24 | AG7: =T7 -> 3Q24 | ... AK7: =X7 -> 3Q25
B8: Fiscal Period End Date | C8: 43862 | D8: 44226 | E8: 44590 | F8: 44954 | G8: 45325 | H8: 45689 | J8: 44681 | K8: 44772 | L8: 44863 | M8: 44954 | N8: 45045 | O8: 45136 | P8: 45227 | Q8: 45325 | R8: 45416 | S8: 45507 | T8: 45598 | U8: 45689 | V8: 45780 | W8: 45871 | X8: 45962 | Z8: =M8 -> 44954 | AA8: =N8 -> 45045 | AB8: =O8 -> 45136 | AC8: =P8 -> 45227 | AD8: =Q8 -> 45325 | AE8: =R8 -> 45416 | AF8: =S8 -> 45507 | AG8: =T8 -> 45598 | ... AK8: =X8 -> 45962
B10: Consolidated Revenue | C10: 7398068 | D10: 6151953 | E10: 8630889 | F10: 10208580 | G10: 11207303 | H10: 11295654 | J10: 2345901 | K10: 2297113 | L10: 2338793 | M10: =SUM(F10-SUM(J10:L10)) -> 3226773 | N10: 2634263 | O10: 2529809 | P10: 2488933 | Q10: =SUM(G10-SUM(N10:P10)) -> 3554298 | R10: 2725848 | S10: 2552087 | T10: 2530100 | U10: =SUM(H10-SUM(R10:T10)) -> 3487619 | V10: 2848367 | W10: 2788469 | X10: 2857623 | Z10: =SUM(J10:M10) -> 10208580 | AA10: =SUM(K10:N10) -> 10496942 | AB10: =SUM(L10:O10) -> 10729638 | AC10: =SUM(M10:P10) -> 10879778 | AD10: =SUM(N10:Q10) -> 11207303 | AE10: =SUM(O10:R10) -> 11298888 | AF10: =SUM(P10:S10) -> 11321166 | AG10: =SUM(Q10:T10) -> 11362333 | ... AK10: =SUM(U10:X10) -> 11982078 | AM10: =SUM(AJ10/AF10)-1 -> 0.029448292
B11: Total Revenue | C11: =+SUM(C10:C10) -> 7398068 | D11: =+SUM(D10:D10) -> 6151953 | E11: =+SUM(E10:E10) -> 8630889 | F11: =+SUM(F10:F10) -> 10208580 | G11: =+SUM(G10:G10) -> 11207303 | H11: =+SUM(H10:H10) -> 11295654 | J11: =+SUM(J10:J10) -> 2345901 | K11: =+SUM(K10:K10) -> 2297113 | L11: =+SUM(L10:L10) -> 2338793 | M11: =+SUM(M10:M10) -> 3226773 | N11: =+SUM(N10:N10) -> 2634263 | O11: =+SUM(O10:O10) -> 2529809 | P11: =+SUM(P10:P10) -> 2488933 | Q11: =+SUM(Q10:Q10) -> 3554298 | ... X11: =+SUM(X10:X10) -> 2857623 | Z11: =+SUM(Z10:Z10) -> 10208580 | AA11: =+SUM(AA10:AA10) -> 10496942 | AB11: =+SUM(AB10:AB10) -> 10729638 | AC11: =+SUM(AC10:AC10) -> 10879778 | AD11: =+SUM(AD10:AD10) -> 11207303 | AE11: =+SUM(AE10:AE10) -> 11298888 | AF11: =+SUM(AF10:AF10) -> 11321166 | AG11: =+SUM(AG10:AG10) -> 11362333 | ... AK11: =+SUM(AK10:AK10) -> 11982078 | AM11: =SUM(AJ11/AF11)-1 -> 0.029448292
B13: Cost of Sales | C13: -4717004 | D13: -4202794 | E13: -5262335 | F13: -6164070 | G13: -6826203 | H13: -6908401 | J13: -1404875 | K13: -1368949 | L13: -1375976 | M13: =SUM(F13-SUM(J13:L13)) -> -2014270 | N13: -1579406 | O13: -1536197 | P13: -1496866 | Q13: =SUM(G13-SUM(N13:P13)) -> -2213734 | R13: -1656068 | S13: -1573910 | T13: -1524456 | U13: =SUM(H13-SUM(R13:T13)) -> -2153967 | V13: -1734148 | W13: -1696773 | X13: -1701958 | Z13: =SUM(K13:N13) -> -6338601 | AA13: =SUM(L13:O13) -> -6505849 | AB13: =SUM(M13:P13) -> -6626739 | AC13: =SUM(N13:Q13) -> -6826203 | AD13: =SUM(O13:R13) -> -6902865 | AE13: =SUM(P13:S13) -> -6940578 | AF13: =SUM(P13:S13) -> -6940578 | AG13: =SUM(Q13:T13) -> -6968168 | AH13: =SUM(R13:U13) -> -6908401 | AI13: =SUM(S13:V13) -> -6986481 | AJ13: =SUM(T13:W13) -> -7109344 | AK13: =SUM(U13:X13) -> -7286846 | AM13: =SUM(AJ13/AF13)-1 -> 0.024315842
B14: Gross Profit | C14: =+SUM(C11+SUM(C13:C13)) -> 2681064 | D14: =+SUM(D11+SUM(D13:D13)) -> 1949159 | E14: =+SUM(E11+SUM(E13:E13)) -> 3368554 | F14: =+SUM(F11+SUM(F13:F13)) -> 4044510 | G14: =+SUM(G11+SUM(G13:G13)) -> 4381100 | H14: =+SUM(H11+SUM(H13:H13)) -> 4387253 | J14: =+SUM(J11+SUM(J13:J13)) -> 941026 | K14: =+SUM(K11+SUM(K13:K13)) -> 928164 | L14: =+SUM(L11+SUM(L13:L13)) -> 962817 | M14: =+SUM(M11+SUM(M13:M13)) -> 1212503 | N14: =+SUM(N11+SUM(N13:N13)) -> 1054857 | O14: =+SUM(O11+SUM(O13:O13)) -> 993612 | P14: =+SUM(P11+SUM(P13:P13)) -> 992067 | Q14: =+SUM(Q11+SUM(Q13:Q13)) -> 1340564 | ... X14: =+SUM(X11+SUM(X13:X13)) -> 1155665 | Z14: =+SUM(Z11+SUM(Z13:Z13)) -> 3869979 | AA14: =+SUM(AA11+SUM(AA13:AA13)) -> 3991093 | AB14: =+SUM(AB11+SUM(AB13:AB13)) -> 4102899 | AC14: =+SUM(AC11+SUM(AC13:AC13)) -> 4053575 | AD14: =+SUM(AD11+SUM(AD13:AD13)) -> 4304438 | AE14: =+SUM(AE11+SUM(AE13:AE13)) -> 4358310 | AF14: =+SUM(AF11+SUM(AF13:AF13)) -> 4380588 | AG14: =+SUM(AG11+SUM(AG13:AG13)) -> 4394165 | ... AK14: =+SUM(AK11+SUM(AK13:AK13)) -> 4695232 | AM14: =SUM(AJ14/AF14)-1 -> 0.037580115
B15: Gross Margin (%) | C15: =C14/C11 -> 0.36240056 | D15: =D14/D11 -> 0.31683581 | E15: =E14/E11 -> 0.3902905 | F15: =F14/F11 -> 0.39618732 | G15: =G14/G11 -> 0.39091475 | H15: =H14/H11 -> 0.38840186 | J15: =J14/J11 -> 0.40113628 | K15: =K14/K11 -> 0.40405674 | L15: =L14/L11 -> 0.4116726 | M15: =M14/M11 -> 0.37576334 | N15: =N14/N11 -> 0.40043724 | O15: =O14/O11 -> 0.39276167 | P15: =P14/P11 -> 0.39859128 | Q15: =Q14/Q11 -> 0.37716702 | ... X15: =X14/X11 -> 0.40441479 | Z15: =Z14/Z11 -> 0.37909082 | AA15: =AA14/AA11 -> 0.38021483 | AB15: =AB14/AB11 -> 0.38238932 | AC15: =AC14/AC11 -> 0.37257883 | AD15: =AD14/AD11 -> 0.38407438 | AE15: =AE14/AE11 -> 0.38572911 | AF15: =AF14/AF11 -> 0.38693788 | AG15: =AG14/AG11 -> 0.38673088 | ... AK15: =AK14/AK11 -> 0.39185457 | AM15: =SUM(AJ15-AF15)*1000 -> 3.0565016
B17: Selling, general and administrative expenses | C17: -1760716 | D17: -1583017 | E17: -2061545 | F17: -2395299 | G17: -2694561 | H17: -2808592 | J17: -500970 | K17: -534459 | L17: -597164 | M17: =SUM(F17-SUM(J17:L17)) -> -762706 | N17: -612129 | O17: -600692 | P17: -661380 | Q17: =SUM(G17-SUM(N17:P17)) -> -820360 | R17: -665913 | S17: -644821 | T17: -682259 | U17: =SUM(H17-SUM(R17:T17)) -> -815599 | V17: -710613 | W17: -741737 | X17: -840920 | Z17: =SUM(K17:N17) -> -2506458 | AA17: =SUM(L17:O17) -> -2572691 | AB17: =SUM(M17:P17) -> -2636907 | AC17: =SUM(N17:Q17) -> -2694561 | AD17: =SUM(O17:R17) -> -2748345 | AE17: =SUM(P17:S17) -> -2792474 | AF17: =SUM(P17:S17) -> -2792474 | AG17: =SUM(Q17:T17) -> -2813353 | AH17: =SUM(R17:U17) -> -2808592 | AI17: =SUM(S17:V17) -> -2853292 | AJ17: =SUM(T17:W17) -> -2950208 | AK17: =SUM(U17:X17) -> -3108869 | AM17: =SUM(AJ17/AF17)-1 -> 0.056485396
B18: Pre-opening expenses | C18: -19254 | D18: -15000 | E18: -9517 | F18: -10601 | G18: -8510 | H18: -13689 | J18: -2348 | K18: -2277 | L18: -3797 | M18: =SUM(F18-SUM(J18:L18)) -> -2179 | N18: -658 | O18: -1278 | P18: -3460 | Q18: =SUM(G18-SUM(N18:P18)) -> -3114 | R18: -2919 | S18: -4155 | T18: -4883 | U18: =SUM(H18-SUM(R18:T18)) -> -1732 | V18: -1829 | W18: -5105 | X18: -5326 | Z18: =SUM(K18:N18) -> -8911 | AA18: =SUM(L18:O18) -> -7912 | AB18: =SUM(M18:P18) -> -7575 | AC18: =SUM(N18:Q18) -> -8510 | AD18: =SUM(O18:R18) -> -10771 | AE18: =SUM(P18:S18) -> -13648 | AF18: =SUM(P18:S18) -> -13648 | AG18: =SUM(Q18:T18) -> -15071 | AH18: =SUM(R18:U18) -> -13689 | AI18: =SUM(S18:V18) -> -12599 | AJ18: =SUM(T18:W18) -> -13549 | AK18: =SUM(U18:X18) -> -13992 | AM18: =SUM(AJ18/AF18)-1 -> -0.0072538101
B19: Impairment, restructuring and other costs | C19: 0 | D19: -114322 | E19: 0 | F19: 0 | G19: 0 | H19: 0 | J19: 0 | K19: 0 | L19: 0 | M19: =SUM(F19-SUM(J19:L19)) -> 0 | N19: 0 | O19: 0 | P19: 0 | Q19: =SUM(G19-SUM(N19:P19)) -> 0 | R19: 0 | S19: 0 | T19: 0 | U19: =SUM(H19-SUM(R19:T19)) -> 0 | V19: 0 | W19: 0 | X19: 0 | Z19: =SUM(K19:N19) -> 0 | AA19: =SUM(L19:O19) -> 0 | AB19: =SUM(M19:P19) -> 0 | AC19: =SUM(N19:Q19) -> 0 | AD19: =SUM(O19:R19) -> 0 | AE19: =SUM(P19:S19) -> 0 | AF19: =SUM(P19:S19) -> 0 | AG19: =SUM(Q19:T19) -> 0 | AH19: =SUM(R19:U19) -> 0 | AI19: =SUM(S19:V19) -> 0 | AJ19: =SUM(T19:W19) -> 0 | AK19: =SUM(U19:X19) -> 0 | AM19: =SUM(AJ19/AF19)-1 -> #DIV/0!
B20: Operating Profit | C20: =+SUM(C14+SUM(C17:C19)) -> 901094 | D20: =+SUM(D14+SUM(D17:D19)) -> 236820 | E20: =+SUM(E14+SUM(E17:E19)) -> 1297492 | F20: =+SUM(F14+SUM(F17:F19)) -> 1638610 | G20: =+SUM(G14+SUM(G17:G19)) -> 1678029 | H20: =+SUM(H14+SUM(H17:H19)) -> 1564972 | J20: =+SUM(J14+SUM(J17:J19)) -> 437708 | K20: =+SUM(K14+SUM(K17:K19)) -> 391428 | L20: =+SUM(L14+SUM(L17:L19)) -> 361856 | M20: =+SUM(M14+SUM(M17:M19)) -> 447618 | N20: =+SUM(N14+SUM(N17:N19)) -> 442070 | O20: =+SUM(O14+SUM(O17:O19)) -> 391642 | P20: =+SUM(P14+SUM(P17:P19)) -> 327227 | Q20: =+SUM(Q14+SUM(Q17:Q19)) -> 517090 | ... X20: =+SUM(X14+SUM(X17:X19)) -> 309419 | Z20: =+SUM(Z14+SUM(Z17:Z19)) -> 1354610 | AA20: =+SUM(AA14+SUM(AA17:AA19)) -> 1410490 | AB20: =+SUM(AB14+SUM(AB17:AB19)) -> 1458417 | AC20: =+SUM(AC14+SUM(AC17:AC19)) -> 1350504 | AD20: =+SUM(AD14+SUM(AD17:AD19)) -> 1545322 | AE20: =+SUM(AE14+SUM(AE17:AE19)) -> 1552188 | AF20: =+SUM(AF14+SUM(AF17:AF19)) -> 1574466 | AG20: =+SUM(AG14+SUM(AG17:AG19)) -> 1565741 | ... AK20: =+SUM(AK14+SUM(AK17:AK19)) -> 1572371 | AM20: =SUM(AJ20/AF20)-1 -> 0.0044383302
B21: Operating Margin (%) | C21: =C20/C11 -> 0.12180126 | D21: =D20/D11 -> 0.038495093 | E21: =E20/E11 -> 0.15033121 | F21: =F20/F11 -> 0.16051302 | G21: =G20/G11 -> 0.14972639 | H21: =H20/H11 -> 0.13854638 | J21: =J20/J11 -> 0.18658417 | K21: =K20/K11 -> 0.17039998 | L21: =L20/L11 -> 0.15471912 | M21: =M20/M11 -> 0.13872002 | N21: =N20/N11 -> 0.16781544 | O21: =O20/O11 -> 0.1548109 | P21: =P20/P11 -> 0.1314728 | Q21: =Q20/Q11 -> 0.14548302 | ... X21: =X20/X11 -> 0.10827845 | Z21: =Z20/Z11 -> 0.13269328 | AA21: =AA20/AA11 -> 0.13437152 | AB21: =AB20/AB11 -> 0.13592416 | AC21: =AC20/AC11 -> 0.12412974 | AD21: =AD20/AD11 -> 0.13788527 | AE21: =AE20/AE11 -> 0.13737529 | AF21: =AF20/AF11 -> 0.13907278 | AG21: =AG20/AG11 -> 0.13780101 | ... AK21: =AK20/AK11 -> 0.1312269 | AM21: =SUM(AJ21-AF21)*1000 -> -3.3787077
B23: Interest Income (Expense), net | C23: 5056 | D23: -5735 | E23: -1663 | F23: 4934 | G23: 17622 | H23: 15094 | J23: -401 | K23: 108 | L23: 849 | M23: =SUM(F23-SUM(J23:L23)) -> 4378 | N23: 7348 | O23: 4449 | P23: 2497 | Q23: =SUM(G23-SUM(N23:P23)) -> 3328 | R23: 6900 | S23: 4526 | T23: 1674 | U23: =SUM(H23-SUM(R23:T23)) -> 1994 | V23: 3547 | W23: 1413 | X23: -4123 | Z23: =SUM(K23:N23) -> 12683 | AA23: =SUM(L23:O23) -> 17024 | AB23: =SUM(M23:P23) -> 18672 | AC23: =SUM(N23:Q23) -> 17622 | AD23: =SUM(O23:R23) -> 17174 | AE23: =SUM(P23:S23) -> 17251 | AF23: =SUM(P23:S23) -> 17251 | AG23: =SUM(Q23:T23) -> 16428 | AH23: =SUM(R23:U23) -> 15094 | AI23: =SUM(S23:V23) -> 11741 | AJ23: =SUM(T23:W23) -> 8628 | AK23: =SUM(U23:X23) -> 2831 | AM23: =SUM(AJ23/AF23)-1 -> -0.49985508
B24: Earning Before Taxes | C24: =SUM(C20+SUM(C23:C23)) -> 906150 | D24: =SUM(D20+SUM(D23:D23)) -> 231085 | E24: =SUM(E20+SUM(E23:E23)) -> 1295829 | F24: =SUM(F20+SUM(F23:F23)) -> 1643544 | G24: =SUM(G20+SUM(G23:G23)) -> 1695651 | H24: =SUM(H20+SUM(H23:H23)) -> 1580066 | J24: =SUM(J20+SUM(J23:J23)) -> 437307 | K24: =SUM(K20+SUM(K23:K23)) -> 391536 | L24: =SUM(L20+SUM(L23:L23)) -> 362705 | M24: =SUM(M20+SUM(M23:M23)) -> 451996 | N24: =SUM(N20+SUM(N23:N23)) -> 449418 | O24: =SUM(O20+SUM(O23:O23)) -> 396091 | P24: =SUM(P20+SUM(P23:P23)) -> 329724 | Q24: =SUM(Q20+SUM(Q23:Q23)) -> 520418 | ... X24: =SUM(X20+SUM(X23:X23)) -> 305296 | Z24: =SUM(Z20+SUM(Z23:Z23)) -> 1367293 | AA24: =SUM(AA20+SUM(AA23:AA23)) -> 1427514 | AB24: =SUM(AB20+SUM(AB23:AB23)) -> 1477089 | AC24: =SUM(AC20+SUM(AC23:AC23)) -> 1368126 | AD24: =SUM(AD20+SUM(AD23:AD23)) -> 1562496 | AE24: =SUM(AE20+SUM(AE23:AE23)) -> 1569439 | AF24: =SUM(AF20+SUM(AF23:AF23)) -> 1591717 | AG24: =SUM(AG20+SUM(AG23:AG23)) -> 1582169 | ... AK24: =SUM(AK20+SUM(AK23:AK23)) -> 1575202 | AM24: =SUM(AJ24/AF24)-1 -> -0.0010271926
B25: EBT Margin (%) | C25: =C24/C11 -> 0.12248468 | D25: =D24/D11 -> 0.037562868 | E25: =E24/E11 -> 0.15013853 | F25: =F24/F11 -> 0.16099634 | G25: =G24/G11 -> 0.15129876 | H25: =H24/H11 -> 0.13988265 | J25: =J24/J11 -> 0.18641324 | K25: =K24/K11 -> 0.17044699 | L25: =L24/L11 -> 0.15508213 | M25: =M24/M11 -> 0.14007679 | N25: =N24/N11 -> 0.17060483 | O25: =O24/O11 -> 0.15656953 | P25: =P24/P11 -> 0.13247604 | Q25: =Q24/Q11 -> 0.14641935 | ... X25: =X24/X11 -> 0.10683565 | Z25: =Z24/Z11 -> 0.13393567 | AA25: =AA24/AA11 -> 0.13599332 | AB25: =AB24/AB11 -> 0.13766438 | AC25: =AC24/AC11 -> 0.12574944 | AD25: =AD24/AD11 -> 0.13941766 | AE25: =AE24/AE11 -> 0.13890208 | AF25: =AF24/AF11 -> 0.14059656 | AG25: =AG24/AG11 -> 0.13924684 | ... AK25: =AK24/AK11 -> 0.13146317 | AM25: =SUM(AJ25-AF25)*1000 -> -4.1621792
B27: Income tax expense | C27: -200205 | D27: -55250 | E27: -309992 | F27: -401136 | G27: -404646 | H27: -378948 | J27: -105912 | K27: -95859 | L27: -88120 | M27: =SUM(F27-SUM(J27:L27)) -> -111245 | N27: -102367 | O27: -95989 | P27: -80241 | Q27: =SUM(G27-SUM(N27:P27)) -> -126049 | R27: -94735 | S27: -81171 | T27: -77997 | U27: =SUM(H27-SUM(R27:T27)) -> -125045 | V27: -99644 | W27: -84795 | X27: -73436 | Z27: =SUM(K27:N27) -> -397591 | AA27: =SUM(L27:O27) -> -397721 | AB27: =SUM(M27:P27) -> -389842 | AC27: =SUM(N27:Q27) -> -404646 | AD27: =SUM(O27:R27) -> -397014 | AE27: =SUM(P27:S27) -> -382196 | AF27: =SUM(P27:S27) -> -382196 | AG27: =SUM(Q27:T27) -> -379952 | AH27: =SUM(R27:U27) -> -378948 | AI27: =SUM(S27:V27) -> -383857 | AJ27: =SUM(T27:W27) -> -387481 | AK27: =SUM(U27:X27) -> -382920 | AM27: =SUM(AJ27/AF27)-1 -> 0.013827984
B28: Income before equity net loss of affiliate | C28: =SUM(C24+C27) -> 705945 | D28: =SUM(D24+D27) -> 175835 | E28: =SUM(E24+E27) -> 985837 | F28: =SUM(F24+F27) -> 1242408 | G28: =SUM(G24+G27) -> 1291005 | H28: =SUM(H24+H27) -> 1201118 | J28: =SUM(J24+J27) -> 331395 | K28: =SUM(K24+K27) -> 295677 | L28: =SUM(L24+L27) -> 274585 | M28: =SUM(M24+M27) -> 340751 | N28: =SUM(N24+N27) -> 347051 | O28: =SUM(O24+O27) -> 300102 | P28: =SUM(P24+P27) -> 249483 | Q28: =SUM(Q24+Q27) -> 394369 | ... X28: =SUM(X24+X27) -> 231860 | Z28: =SUM(Z24+Z27) -> 969702 | AA28: =SUM(AA24+AA27) -> 1029793 | AB28: =SUM(AB24+AB27) -> 1087247 | AC28: =SUM(AC24+AC27) -> 963480 | AD28: =SUM(AD24+AD27) -> 1165482 | AE28: =SUM(AE24+AE27) -> 1187243 | AF28: =SUM(AF24+AF27) -> 1209521 | AG28: =SUM(AG24+AG27) -> 1202217 | ... AK28: =SUM(AK24+AK27) -> 1192282 | AM28: =SUM(AJ28/AF28)-1 -> -0.0057212731
B30: Equity net loss of affiliate | C30: 0 | D30: 0 | E30: 0 | F30: 0 | G30: 0 | H30: 0 | J30: 0 | K30: 0 | L30: 0 | M30: =SUM(F30-SUM(J30:L30)) -> 0 | N30: 0 | O30: 0 | P30: 0 | Q30: =SUM(G30-SUM(N30:P30)) -> 0 | R30: 0 | S30: 0 | T30: 0 | U30: =SUM(H30-SUM(R30:T30)) -> 0 | V30: -628 | W30: -597 | X30: -985 | Z30: =SUM(K30:N30) -> 0 | AA30: =SUM(L30:O30) -> 0 | AB30: =SUM(M30:P30) -> 0 | AC30: =SUM(N30:Q30) -> 0 | AD30: =SUM(O30:R30) -> 0 | AE30: =SUM(P30:S30) -> 0 | AF30: =SUM(P30:S30) -> 0 | AG30: =SUM(Q30:T30) -> 0 | AH30: =SUM(R30:U30) -> 0 | AI30: =SUM(S30:V30) -> -628 | AJ30: =SUM(T30:W30) -> -1225 | AK30: =SUM(U30:X30) -> -2210 | AM30: =SUM(AJ30/AF30)-1 -> #DIV/0!
B31: Net Income | C31: =SUM(C28+C30) -> 705945 | D31: =SUM(D28+D30) -> 175835 | E31: =SUM(E28+E30) -> 985837 | F31: =SUM(F28+F30) -> 1242408 | G31: =SUM(G28+G30) -> 1291005 | H31: =SUM(H28+H30) -> 1201118 | J31: =SUM(J28+J30) -> 331395 | K31: =SUM(K28+K30) -> 295677 | L31: =SUM(L28+L30) -> 274585 | M31: =SUM(M28+M30) -> 340751 | N31: =SUM(N28+N30) -> 347051 | O31: =SUM(O28+O30) -> 300102 | P31: =SUM(P28+P30) -> 249483 | Q31: =SUM(Q28+Q30) -> 394369 | ... X31: =SUM(X28+X30) -> 230875 | Z31: =SUM(Z28+Z30) -> 969702 | AA31: =SUM(AA28+AA30) -> 1029793 | AB31: =SUM(AB28+AB30) -> 1087247 | AC31: =SUM(AC28+AC30) -> 963480 | AD31: =SUM(AD28+AD30) -> 1165482 | AE31: =SUM(AE28+AE30) -> 1187243 | AF31: =SUM(AF28+AF30) -> 1209521 | AG31: =SUM(AG28+AG30) -> 1202217 | ... AK31: =SUM(AK28+AK30) -> 1190072 | AM31: =SUM(AJ31/AF31)-1 -> -0.0067340708
B32: Margin (%) | C32: =C31/C11 -> 0.095422886 | D32: =D31/D11 -> 0.02858198 | E32: =E31/E11 -> 0.11422195 | F32: =F31/F11 -> 0.12170233 | G32: =G31/G11 -> 0.11519319 | H32: =H31/H11 -> 0.10633452 | J32: =J31/J11 -> 0.14126555 | K32: =K31/K11 -> 0.12871678 | L32: =L31/L11 -> 0.11740458 | M32: =M31/M11 -> 0.10560117 | N32: =N31/N11 -> 0.13174501 | O32: =O31/O11 -> 0.11862635 | P32: =P31/P11 -> 0.10023693 | Q32: =Q31/Q11 -> 0.11095552 | ... X32: =X31/X11 -> 0.080792673 | Z32: =Z31/Z11 -> 0.094988921 | AA32: =AA31/AA11 -> 0.098104095 | AB32: =AB31/AB11 -> 0.10133119 | AC32: =AC31/AC11 -> 0.088556954 | AD32: =AD31/AD11 -> 0.10399308 | AE32: =AE31/AE11 -> 0.10507609 | AF32: =AF31/AF11 -> 0.10683714 | AG32: =AG31/AG11 -> 0.10580723 | ... AK32: =AK31/AK11 -> 0.099321003 | AM32: =SUM(AJ32-AF32)*1000 -> -3.7550406
B34: Basic shares | C34: 57840 | D34: 56351 | E34: 54482 | F34: 51403 | G34: 49304 | H34: 47207 | J34: 52250 | K34: 51607 | L34: 51131 | M34: =F34 -> 51403 | N34: 50153 | O34: 49617 | P34: 49007 | Q34: =G34 -> 49304 | R34: 48125 | S34: 47505 | T34: 46928 | U34: =H34 -> 47207 | V34: 45362 | W34: 44955 | X34: 44731 | Z34: =M34 -> 51403 | AA34: =N34 -> 50153 | AB34: =O34 -> 49617 | AC34: =P34 -> 49007 | AD34: =Q34 -> 49304 | AE34: =R34 -> 48125 | AF34: =S34 -> 47505 | AG34: =T34 -> 46928 | ... AK34: =X34 -> 44731 | AM34: =SUM(AJ34/AF34)-1 -> -0.05367856
B35: Basic EPS | C35: =C31/C34 -> 12.205135 | D35: =D31/D34 -> 3.1203528 | E35: =E31/E34 -> 18.094729 | F35: =F31/F34 -> 24.169951 | G35: =G31/G34 -> 26.184589 | H35: =H31/H34 -> 25.443642 | J35: =J31/J34 -> 6.342488 | K35: =K31/K34 -> 5.7293972 | L35: =L31/L34 -> 5.3702255 | M35: =M31/M34 -> 6.62901 | N35: =N31/N34 -> 6.9198453 | O35: =O31/O34 -> 6.0483705 | P35: =P31/P34 -> 5.0907625 | Q35: =Q31/Q34 -> 7.9987222 | ... X35: =X31/X34 -> 5.1614093 | Z35: =Z31/Z34 -> 18.864697 | AA35: =AA31/AA34 -> 20.533029 | AB35: =AB31/AB34 -> 21.912792 | AC35: =AC31/AC34 -> 19.660049 | AD35: =AD31/AD34 -> 23.638691 | AE35: =AE31/AE34 -> 24.669984 | AF35: =AF31/AF34 -> 25.46092 | AG35: =AG31/AG34 -> 25.61833 | ... AK35: =AK31/AK34 -> 26.605084 | AM35: =SUM(AJ35/AF35)-1 -> 0.04960734
B37: Fully Diluted Shares | C37: 58105 | D37: 56558 | E37: 54841 | F37: 51738 | G37: 49596 | H37: 47404 | J37: 52582 | K37: 51900 | L37: 51418 | M37: =F37 -> 51738 | N37: 50469 | O37: 49849 | P37: 49226 | Q37: =G37 -> 49596 | R37: 48381 | S37: 47667 | T37: 47092 | U37: =H37 -> 47404 | V37: 45508 | W37: 45112 | X37: 44895 | Z37: =N37 -> 50469 | AA37: =O37 -> 49849 | AB37: =P37 -> 49226 | AC37: =Q37 -> 49596 | AD37: =R37 -> 48381 | AE37: =S37 -> 47667 | AF37: =S37 -> 47667 | AG37: =T37 -> 47092 | AH37: =U37 -> 47404 | AI37: =V37 -> 45508 | AJ37: =W37 -> 45112 | AK37: =X37 -> 44895 | AM37: =SUM(AJ37/AF37)-1 -> -0.053601024
B38: Diluted EPS | C38: =C31/C37 -> 12.149471 | D38: =D31/D37 -> 3.1089324 | E38: =E31/E37 -> 17.976277 | F38: =F31/F37 -> 24.013452 | G38: =G31/G37 -> 26.030426 | H38: =H31/H37 -> 25.337904 | J38: =J31/J37 -> 6.3024419 | K38: =K31/K37 -> 5.697052 | L38: =L31/L37 -> 5.3402505 | M38: =M31/M37 -> 6.5860876 | N38: =N31/N37 -> 6.8765183 | O38: =O31/O37 -> 6.0202211 | P38: =P31/P37 -> 5.0681144 | Q38: =Q31/Q37 -> 7.9516292 | ... X38: =X31/X37 -> 5.1425549 | Z38: =Z31/Z37 -> 19.213814 | AA38: =AA31/AA37 -> 20.658248 | AB38: =AB31/AB37 -> 22.086844 | AC38: =AC31/AC37 -> 19.426567 | AD38: =AD31/AD37 -> 24.089663 | AE38: =AE31/AE37 -> 24.907022 | AF38: =AF31/AF37 -> 25.374389 | AG38: =AG31/AG37 -> 25.529113 | ... AK38: =AK31/AK37 -> 26.507896 | AM38: =SUM(AJ38/AF38)-1 -> 0.049521348
A40: X | B40: Balance Sheet | C40: FYE | F40: FYE | J40: Quarterly | T40: Quarterly | AF40: LTM | AM40: Variance
B41: =B7 -> Fiscal Period | C41: =C7 -> 2019 | D41: =D7 -> 2020 | E41: =E7 -> 2021 | F41: =F7 -> 2022 | G41: =G7 -> 2023 | H41: =H7 -> 2024 | J41: =J7 -> 1Q22 | K41: =K7 -> 2Q22 | L41: =L7 -> 3Q22 | M41: =M7 -> 4Q22 | N41: =N7 -> 1Q23 | O41: =O7 -> 2Q23 | P41: =P7 -> 3Q23 | Q41: =Q7 -> 4Q23 | ... X41: =X7 -> 3Q25 | Z41: =Z7 -> 4Q22 | AA41: =AA7 -> 1Q23 | AB41: =AB7 -> 2Q23 | AC41: =AC7 -> 3Q23 | AD41: =AD7 -> 4Q23 | AE41: =AE7 -> 1Q24 | AF41: =AF7 -> 2Q24 | AG41: =AG7 -> 3Q24 | ... AK41: =AK7 -> 3Q25
B42: =B8 -> Fiscal Period End Date | C42: =C8 -> 43862 | D42: =D8 -> 44226 | E42: =E8 -> 44590 | F42: =F8 -> 44954 | G42: =G8 -> 45325 | H42: =H8 -> 45689 | J42: =J8 -> 44681 | K42: =K8 -> 44772 | L42: =L8 -> 44863 | M42: =M8 -> 44954 | N42: =N8 -> 45045 | O42: =O8 -> 45136 | P42: =P8 -> 45227 | Q42: =Q8 -> 45325 | ... X42: =X8 -> 45962 | Z42: =Z8 -> 44954 | AA42: =AA8 -> 45045 | AB42: =AB8 -> 45136 | AC42: =AC8 -> 45227 | AD42: =AD8 -> 45325 | AE42: =AE8 -> 45416 | AF42: =AF8 -> 45507 | AG42: =AG8 -> 45598 | ... AK42: =AK8 -> 45962
B44: Current Assets
B45: Cash and cash equivalents | C45: 392325 | D45: 1046051 | E45: 431560 | F45: 737877 | G45: 766594 | H45: 703201 | J45: 654486 | K45: 434226 | L45: 250628 | M45: =F45 -> 737877 | N45: 636449 | O45: 388627 | P45: 121811 | Q45: =G45 -> 766594 | R45: 524596 | S45: 413962 | T45: 177782 | U45: =H45 -> 703201 | V45: 454629 | W45: 242745 | X45: 204921 | Z45: =M45 -> 737877 | AA45: =N45 -> 636449 | AB45: =O45 -> 388627 | AC45: =P45 -> 121811 | AD45: =Q45 -> 766594 | AE45: =R45 -> 524596 | AF45: =S45 -> 413962 | AG45: =T45 -> 177782 | ... AK45: =X45 -> 204921 | AM45: =SUM(AJ45/AF45)-1 -> -0.4136056
B46: Receivables, net | C46: 139337 | D46: 193109 | E46: 233682 | F46: 199422 | G46: 207939 | H46: 223334 | J46: 192754 | K46: 180514 | L46: 200304 | M46: =F46 -> 199422 | N46: 190282 | O46: 174444 | P46: 202868 | Q46: =G46 -> 207939 | R46: 203463 | S46: 200863 | T46: 213621 | U46: =H46 -> 223334 | V46: 225146 | W46: 224412 | X46: 237352 | Z46: =M46 -> 199422 | AA46: =N46 -> 190282 | AB46: =O46 -> 174444 | AC46: =P46 -> 202868 | AD46: =Q46 -> 207939 | AE46: =R46 -> 203463 | AF46: =S46 -> 200863 | AG46: =T46 -> 213621 | ... AK46: =X46 -> 237352 | AM46: =SUM(AJ46/AF46)-1 -> 0.11723911
B47: Merchandise inventories, net | C47: 1293701 | D47: 1168215 | E47: 1499218 | F47: 1603451 | G47: 1742136 | H47: 1968214 | J47: 1570552 | K47: 1666130 | L47: 2114669 | M47: =F47 -> 1603451 | N47: 1751235 | O47: 1815539 | P47: 2321306 | Q47: =G47 -> 1742136 | R47: 1906040 | S47: 1998286 | T47: 2365186 | U47: =H47 -> 1968214 | V47: 2121519 | W47: 2407051 | X47: 2743639 | Z47: =M47 -> 1603451 | AA47: =N47 -> 1751235 | AB47: =O47 -> 1815539 | AC47: =P47 -> 2321306 | AD47: =Q47 -> 1742136 | AE47: =R47 -> 1906040 | AF47: =S47 -> 1998286 | AG47: =T47 -> 2365186 | ... AK47: =X47 -> 2743639 | AM47: =SUM(AJ47/AF47)-1 -> 0.20455781
B48: Prepaid expenses and other current assets | C48: =103567+16387+110000 -> 229954 | D48: 107402 | E48: =110814+5909 -> 116723 | F48: =130246+38308 -> 168554 | G48: =115598+4251 -> 119849 | H48: =129113+4946 -> 134059 | J48: 114075 | K48: =123014+39029 -> 162043 | L48: =137642+42572 -> 180214 | M48: =F48 -> 168554 | N48: 108014 | O48: =110524+30114 -> 140638 | P48: =117282+28773 -> 146055 | Q48: =G48 -> 119849 | R48: 126529 | S48: =132023+53607 -> 185630 | T48: =135514+62759 -> 198273 | U48: =H48 -> 134059 | V48: 138396 | W48: =165963+28877 -> 194840 | X48: =158394+26465 -> 184859 | Z48: =M48 -> 168554 | AA48: =N48 -> 108014 | AB48: =O48 -> 140638 | AC48: =P48 -> 146055 | AD48: =Q48 -> 119849 | AE48: =R48 -> 126529 | AF48: =S48 -> 185630 | AG48: =T48 -> 198273 | ... AK48: =X48 -> 184859 | AM48: =SUM(AJ48/AF48)-1 -> 0.049614825
B49: Total Current Assets | C49: =SUM(C45:C48) -> 2055317 | D49: =SUM(D45:D48) -> 2514777 | E49: =SUM(E45:E48) -> 2281183 | F49: =SUM(F45:F48) -> 2709304 | G49: =SUM(G45:G48) -> 2836518 | H49: =SUM(H45:H48) -> 3028808 | J49: =SUM(J45:J48) -> 2531867 | K49: =SUM(K45:K48) -> 2442913 | L49: =SUM(L45:L48) -> 2745815 | M49: =SUM(M45:M48) -> 2709304 | N49: =SUM(N45:N48) -> 2685980 | O49: =SUM(O45:O48) -> 2519248 | P49: =SUM(P45:P48) -> 2792040 | Q49: =SUM(Q45:Q48) -> 2836518 | ... X49: =SUM(X45:X48) -> 3370771 | Z49: =SUM(Z45:Z48) -> 2709304 | AA49: =SUM(AA45:AA48) -> 2685980 | AB49: =SUM(AB45:AB48) -> 2519248 | AC49: =SUM(AC45:AC48) -> 2792040 | AD49: =SUM(AD45:AD48) -> 2836518 | AE49: =SUM(AE45:AE48) -> 2760628 | AF49: =SUM(AF45:AF48) -> 2798741 | AG49: =SUM(AG45:AG48) -> 2954862 | ... AK49: =SUM(AK45:AK48) -> 3370771 | AM49: =SUM(AJ49/AF49)-1 -> 0.096581642
B51: Non-Current Assets
B52: Property and equipment, net | C52: 1205524 | D52: 995795 | E52: 914476 | F52: 1009273 | G52: 1182335 | H52: 1239295 | J52: 909543 | K52: 912017 | L52: 967039 | M52: =F52 -> 1009273 | N52: 1019978 | O52: 1073144 | P52: 1117874 | Q52: =G52 -> 1182335 | R52: 1195658 | S52: 1225850 | T52: 1264419 | U52: =H52 -> 1239295 | V52: 1251287 | W52: 1332503 | X52: 1366504 | Z52: =M52 -> 1009273 | AA52: =N52 -> 1019978 | AB52: =O52 -> 1073144 | AC52: =P52 -> 1117874 | AD52: =Q52 -> 1182335 | AE52: =R52 -> 1195658 | AF52: =S52 -> 1225850 | AG52: =T52 -> 1264419 | ... AK52: =X52 -> 1366504 | AM52: =SUM(AJ52/AF52)-1 -> 0.087003304
B53: Operating lease assets | C53: 1537565 | D53: 1504614 | E53: 1482256 | F53: 1561263 | G53: 1574530 | H53: 1609870 | J53: 1488040 | K53: 1509246 | L53: 1556940 | M53: =F53 -> 1561263 | N53: 1559560 | O53: 1549146 | P53: 1578316 | Q53: =G53 -> 1574530 | R53: 1561767 | S53: 1599735 | T53: 1619055 | U53: =H53 -> 1609870 | V53: 1658834 | W53: 1682151 | X53: 1710804 | Z53: =M53 -> 1561263 | AA53: =N53 -> 1559560 | AB53: =O53 -> 1549146 | AC53: =P53 -> 1578316 | AD53: =Q53 -> 1574530 | AE53: =R53 -> 1561767 | AF53: =S53 -> 1599735 | AG53: =T53 -> 1619055 | ... AK53: =X53 -> 1710804 | AM53: =SUM(AJ53/AF53)-1 -> 0.051518533
B54: Goodwill | C54: 10870 | D54: 10870 | E54: 10870 | F54: 10870 | G54: 10870 | H54: 10870 | J54: 10870 | K54: 10870 | L54: 10870 | M54: =F54 -> 10870 | N54: 10870 | O54: 10870 | P54: 10870 | Q54: =G54 -> 10870 | R54: 10870 | S54: 10870 | T54: 10870 | U54: =H54 -> 10870 | V54: 10870 | W54: 392606 | X54: 392606 | Z54: =M54 -> 10870 | AA54: =N54 -> 10870 | AB54: =O54 -> 10870 | AC54: =P54 -> 10870 | AD54: =Q54 -> 10870 | AE54: =R54 -> 10870 | AF54: =S54 -> 10870 | AG54: =T54 -> 10870 | ... AK54: =X54 -> 392606 | AM54: =SUM(AJ54/AF54)-1 -> 35.118307
B55: Other intangible assets, net | C55: 3391 | D55: 2465 | E55: 1538 | F55: 1312 | G55: 510 | H55: 204 | J55: 1307 | K55: 1075 | L55: 844 | M55: =F55 -> 1312 | N55: 1015 | O55: 718 | P55: 591 | Q55: =G55 -> 510 | R55: 434 | S55: 357 | T55: 281 | U55: =H55 -> 204 | V55: 0 | W55: 5466 | X55: 6089 | Z55: =M55 -> 1312 | AA55: =N55 -> 1015 | AB55: =O55 -> 718 | AC55: =P55 -> 591 | AD55: =Q55 -> 510 | AE55: =R55 -> 434 | AF55: =S55 -> 357 | AG55: =T55 -> 281 | ... AK55: =X55 -> 6089 | AM55: =SUM(AJ55/AF55)-1 -> 14.310924
B56: Deferred compensation plan assets | C56: 27849 | D56: 33223 | E56: 38409 | F56: 35382 | G56: 43516 | H56: 47951 | J56: 35978 | K56: 33393 | L56: 31529 | M56: =F56 -> 35382 | N56: 37002 | O56: 40087 | P56: 38371 | Q56: =G56 -> 43516 | R56: 45718 | S56: 46280 | T56: 48872 | U56: =H56 -> 47951 | V56: 47467 | W56: 50550 | X56: 52684 | Z56: =M56 -> 35382 | AA56: =N56 -> 37002 | AB56: =O56 -> 40087 | AC56: =P56 -> 38371 | AD56: =Q56 -> 43516 | AE56: =R56 -> 45718 | AF56: =S56 -> 46280 | AG56: =T56 -> 48872 | ... AK56: =X56 -> 52684 | AM56: =SUM(AJ56/AF56)-1 -> 0.092264477
B57: Other long-term assets | C57: 23356 | D57: 28225 | E57: 35647 | F57: 43007 | G57: 58732 | H57: 64695 | J57: 34431 | K57: 36480 | L57: 18512 | M57: =F57 -> 43007 | N57: 61314 | O57: 55547 | P57: 56946 | Q57: =G57 -> 58732 | R57: 56864 | S57: 55575 | T57: 60127 | U57: =H57 -> 64695 | V57: 78541 | W57: 98324 | X57: 112834 | Z57: =M57 -> 43007 | AA57: =N57 -> 61314 | AB57: =O57 -> 55547 | AC57: =P57 -> 56946 | AD57: =Q57 -> 58732 | AE57: =R57 -> 56864 | AF57: =S57 -> 55575 | AG57: =T57 -> 60127 | ... AK57: =X57 -> 112834 | AM57: =SUM(AJ57/AF57)-1 -> 0.76921278
B58: Total Assets | C58: =SUM(C52:C57)+C49 -> 4863872 | D58: =SUM(D52:D57)+D49 -> 5089969 | E58: =SUM(E52:E57)+E49 -> 4764379 | F58: =SUM(F52:F57)+F49 -> 5370411 | G58: =SUM(G52:G57)+G49 -> 5707011 | H58: =SUM(H52:H57)+H49 -> 6001693 | J58: =SUM(J52:J57)+J49 -> 5012036 | K58: =SUM(K52:K57)+K49 -> 4945994 | L58: =SUM(L52:L57)+L49 -> 5331549 | M58: =SUM(M52:M57)+M49 -> 5370411 | N58: =SUM(N52:N57)+N49 -> 5375719 | O58: =SUM(O52:O57)+O49 -> 5248760 | P58: =SUM(P52:P57)+P49 -> 5595008 | Q58: =SUM(Q52:Q57)+Q49 -> 5707011 | ... X58: =SUM(X52:X57)+X49 -> 7012292 | Z58: =SUM(Z52:Z57)+Z49 -> 5370411 | AA58: =SUM(AA52:AA57)+AA49 -> 5375719 | AB58: =SUM(AB52:AB57)+AB49 -> 5248760 | AC58: =SUM(AC52:AC57)+AC49 -> 5595008 | AD58: =SUM(AD52:AD57)+AD49 -> 5707011 | AE58: =SUM(AE52:AE57)+AE49 -> 5631939 | AF58: =SUM(AF52:AF57)+AF49 -> 5737408 | AG58: =SUM(AG52:AG57)+AG49 -> 5958486 | ... AK58: =SUM(AK52:AK57)+AK49 -> 7012292 | AM58: =SUM(AJ58/AF58)-1 -> 0.15568703
B60: Current Liabilities
B61: Accounts payable | C61: 414009 | D61: 477052 | E61: 552730 | F61: 559527 | G61: 544001 | H61: 563761 | J61: 585500 | K61: 586851 | L61: 647117 | M61: =F61 -> 559527 | N61: 621272 | O61: 521315 | P61: 597373 | Q61: =G61 -> 544001 | R61: 463777 | S61: 566904 | T61: 593219 | U61: =H61 -> 563761 | V61: 537518 | W61: 708655 | X61: 759001 | Z61: =M61 -> 559527 | AA61: =N61 -> 621272 | AB61: =O61 -> 521315 | AC61: =P61 -> 597373 | AD61: =Q61 -> 544001 | AE61: =R61 -> 463777 | AF61: =S61 -> 566904 | AG61: =T61 -> 593219 | ... AK61: =X61 -> 759001 | AM61: =SUM(AJ61/AF61)-1 -> 0.2500441
B62: Deferred revenue | C62: 237535 | D62: 274383 | E62: 353579 | F62: 394677 | G62: 436591 | H62: 500585 | J62: 324694 | K62: 316571 | L62: 312132 | M62: =F62 -> 394677 | N62: 357217 | O62: 354253 | P62: 350937 | Q62: =G62 -> 436591 | R62: 398729 | S62: 394987 | T62: 405040 | U62: =H62 -> 500585 | V62: 462843 | W62: 460187 | X62: 462964 | Z62: =M62 -> 394677 | AA62: =N62 -> 357217 | AB62: =O62 -> 354253 | AC62: =P62 -> 350937 | AD62: =Q62 -> 436591 | AE62: =R62 -> 398729 | AF62: =S62 -> 394987 | AG62: =T62 -> 405040 | ... AK62: =X62 -> 462964 | AM62: =SUM(AJ62/AF62)-1 -> 0.16506872
B63: Current operating lease liabilities | C63: 239629 | D63: 253415 | E63: 274118 | F63: 283293 | G63: 283821 | H63: 288114 | J63: 276440 | K63: 274693 | L63: 275749 | M63: =F63 -> 283293 | N63: 288133 | O63: 287359 | P63: 287786 | Q63: =G63 -> 283821 | R63: 284815 | S63: 281301 | T63: 284985 | U63: =H63 -> 288114 | V63: 285764 | W63: 282593 | X63: 290716 | Z63: =M63 -> 283293 | AA63: =N63 -> 288133 | AB63: =O63 -> 287359 | AC63: =P63 -> 287786 | AD63: =Q63 -> 283821 | AE63: =R63 -> 284815 | AF63: =S63 -> 281301 | AG63: =T63 -> 284985 | ... AK63: =X63 -> 290716 | AM63: =SUM(AJ63/AF63)-1 -> 0.0045929449
B64: Accruals & Other Current Liabilities | C64: 246088 | D64: =296334+42529 -> 338863 | E64: =364797+12786 -> 377583 | F64: 444278 | G64: =382468+11310 -> 393778 | H64: =380241+46777 -> 427018 | J64: =305000+108113 -> 413113 | K64: 323939 | L64: 462773 | M64: =F64 -> 444278 | N64: =308583+58695 -> 367278 | O64: 328247 | P64: 405443 | Q64: =G64 -> 393778 | R64: =332692+92711 -> 425403 | S64: 348042 | T64: 333463 | U64: =H64 -> 427018 | V64: =346960+130765 -> 477725 | W64: 460232 | X64: 473949 | Z64: =M64 -> 444278 | AA64: =N64 -> 367278 | AB64: =O64 -> 328247 | AC64: =P64 -> 405443 | AD64: =Q64 -> 393778 | AE64: =R64 -> 425403 | AF64: =S64 -> 348042 | AG64: =T64 -> 333463 | ... AK64: =X64 -> 473949 | AM64: =SUM(AJ64/AF64)-1 -> 0.32234615
B65: Short-term debt | C65: 0 | D65: 0 | E65: 0 | F65: 0 | G65: 0 | H65: 0 | J65: 0 | K65: 0 | L65: 0 | M65: =F65 -> 0 | N65: 0 | O65: 0 | P65: 195400 | Q65: =G65 -> 0 | R65: 0 | S65: 0 | T65: 199700 | U65: =H65 -> 0 | V65: 0 | W65: 289101 | X65: 551721 | Z65: =M65 -> 0 | AA65: =N65 -> 0 | AB65: =O65 -> 0 | AC65: =P65 -> 195400 | AD65: =Q65 -> 0 | AE65: =R65 -> 0 | AF65: =S65 -> 0 | AG65: =T65 -> 199700 | ... AK65: =X65 -> 551721 | AM65: =SUM(AJ65/AF65)-1 -> #DIV/0!
B66: Total Current Liabilities | C66: =SUM(C61:C65) -> 1137261 | D66: =SUM(D61:D65) -> 1343713 | E66: =SUM(E61:E65) -> 1558010 | F66: =SUM(F61:F65) -> 1681775 | G66: =SUM(G61:G65) -> 1658191 | H66: =SUM(H61:H65) -> 1779478 | J66: =SUM(J61:J65) -> 1599747 | K66: =SUM(K61:K65) -> 1502054 | L66: =SUM(L61:L65) -> 1697771 | M66: =SUM(M61:M65) -> 1681775 | N66: =SUM(N61:N65) -> 1633900 | O66: =SUM(O61:O65) -> 1491174 | P66: =SUM(P61:P65) -> 1836939 | Q66: =SUM(Q61:Q65) -> 1658191 | ... X66: =SUM(X61:X65) -> 2538351 | Z66: =SUM(Z61:Z65) -> 1681775 | AA66: =SUM(AA61:AA65) -> 1633900 | AB66: =SUM(AB61:AB65) -> 1491174 | AC66: =SUM(AC61:AC65) -> 1836939 | AD66: =SUM(AD61:AD65) -> 1658191 | AE66: =SUM(AE61:AE65) -> 1572724 | AF66: =SUM(AF61:AF65) -> 1591234 | AG66: =SUM(AG61:AG65) -> 1816407 | ... AK66: =SUM(AK61:AK65) -> 2538351 | AM66: =SUM(AJ66/AF66)-1 -> 0.38305743
B68: Non-Current Liabilities
B69: Non-current operating lease liabilities | C69: 1698718 | D69: 1643386 | E69: 1572638 | F69: 1619883 | G69: 1627271 | H69: 1635120 | J69: 1568356 | K69: 1582003 | L69: 1621252 | M69: =F69 -> 1619883 | N69: 1610256 | O69: 1593040 | P69: 1616747 | Q69: =G69 -> 1627271 | R69: 1607953 | S69: 1647698 | T69: 1656317 | U69: =H69 -> 1635120 | V69: 1689439 | W69: 1716133 | X69: 1732219 | Z69: =M69 -> 1619883 | AA69: =N69 -> 1610256 | AB69: =O69 -> 1593040 | AC69: =P69 -> 1616747 | AD69: =Q69 -> 1627271 | AE69: =R69 -> 1607953 | AF69: =S69 -> 1647698 | AG69: =T69 -> 1656317 | ... AK69: =X69 -> 1732219 | AM69: =SUM(AJ69/AF69)-1 -> 0.041533703
B70: Deferred income taxes | C70: 89367 | D70: 65359 | E70: 39693 | F70: 55346 | G70: 85921 | H70: 42593 | J70: 40702 | K70: 40029 | L70: 38627 | M70: =F70 -> 55346 | N70: 57490 | O70: 56012 | P70: 56874 | Q70: =G70 -> 85921 | R70: 89556 | S70: 88461 | T70: 91729 | U70: =H70 -> 42593 | V70: 46013 | W70: 49158 | X70: 45312 | Z70: =M70 -> 55346 | AA70: =N70 -> 57490 | AB70: =O70 -> 56012 | AC70: =P70 -> 56874 | AD70: =Q70 -> 85921 | AE70: =R70 -> 89556 | AF70: =S70 -> 88461 | AG70: =T70 -> 91729 | ... AK70: =X70 -> 45312 | AM70: =SUM(AJ70/AF70)-1 -> -0.44429749
B71: Other long-term liabilities | C71: 36432 | D71: 37962 | E71: 58665 | F71: 53596 | G71: 56300 | H71: 56149 | J71: 57611 | K71: 52840 | L71: 51644 | M71: =F71 -> 53596 | N71: 56005 | O71: 56657 | P71: 55906 | Q71: =G71 -> 56300 | R71: 60963 | S71: 61855 | T71: 65024 | U71: =H71 -> 56149 | V71: 57084 | W71: 60729 | X71: 63396 | Z71: =M71 -> 53596 | AA71: =N71 -> 56005 | AB71: =O71 -> 56657 | AC71: =P71 -> 55906 | AD71: =Q71 -> 56300 | AE71: =R71 -> 60963 | AF71: =S71 -> 61855 | AG71: =T71 -> 65024 | ... AK71: =X71 -> 63396 | AM71: =SUM(AJ71/AF71)-1 -> -0.018203864
B72: Total Liabilities | C72: =SUM(C69:C71)+C66 -> 2961778 | D72: =SUM(D69:D71)+D66 -> 3090420 | E72: =SUM(E69:E71)+E66 -> 3229006 | F72: =SUM(F69:F71)+F66 -> 3410600 | G72: =SUM(G69:G71)+G66 -> 3427683 | H72: =SUM(H69:H71)+H66 -> 3513340 | J72: =SUM(J69:J71)+J66 -> 3266416 | K72: =SUM(K69:K71)+K66 -> 3176926 | L72: =SUM(L69:L71)+L66 -> 3409294 | M72: =SUM(M69:M71)+M66 -> 3410600 | N72: =SUM(N69:N71)+N66 -> 3357651 | O72: =SUM(O69:O71)+O66 -> 3196883 | P72: =SUM(P69:P71)+P66 -> 3566466 | Q72: =SUM(Q69:Q71)+Q66 -> 3427683 | ... X72: =SUM(X69:X71)+X66 -> 4379278 | Z72: =SUM(Z69:Z71)+Z66 -> 3410600 | AA72: =SUM(AA69:AA71)+AA66 -> 3357651 | AB72: =SUM(AB69:AB71)+AB66 -> 3196883 | AC72: =SUM(AC69:AC71)+AC66 -> 3566466 | AD72: =SUM(AD69:AD71)+AD66 -> 3427683 | AE72: =SUM(AE69:AE71)+AE66 -> 3331196 | AF72: =SUM(AF69:AF71)+AF66 -> 3389248 | AG72: =SUM(AG69:AG71)+AG66 -> 3629477 | ... AK72: =SUM(AK69:AK71)+AK66 -> 4379278 | AM72: =SUM(AJ72/AF72)-1 -> 0.18810662
B74: Common Stock | C74: 573 | D74: 569 | E74: 530 | F74: 511 | G74: 491 | H74: 468 | J74: 528 | K74: 521 | L74: 517 | M74: =F74 -> 511 | N74: 507 | O74: 501 | P74: 495 | Q74: =G74 -> 491 | R74: 487 | S74: 481 | T74: 474 | U74: =H74 -> 468 | V74: 459 | W74: 458 | X74: 454 | Z74: =M74 -> 511 | AA74: =N74 -> 507 | AB74: =O74 -> 501 | AC74: =P74 -> 495 | AD74: =Q74 -> 491 | AE74: =R74 -> 487 | AF74: =S74 -> 481 | AG74: =T74 -> 474 | ... AK74: =X74 -> 454 | AM74: =SUM(AJ74/AF74)-1 -> -0.047817048
B75: Treasury Stock | C75: -34448 | D75: -37801 | E75: -53478 | F75: -60470 | G75: -83032 | H75: -106793 | J75: -58650 | K75: -59803 | L75: -60218 | M75: =F75 -> -60470 | N75: -82129 | O75: -82229 | P75: -82798 | Q75: =G75 -> -83032 | R75: -106315 | S75: -106491 | T75: -106598 | U75: =H75 -> -106793 | V75: -119704 | W75: -120031 | X75: -120298 | Z75: =M75 -> -60470 | AA75: =N75 -> -82129 | AB75: =O75 -> -82229 | AC75: =P75 -> -82798 | AD75: =Q75 -> -83032 | AE75: =R75 -> -106315 | AF75: =S75 -> -106491 | AG75: =T75 -> -106598 | ... AK75: =X75 -> -120298 | AM75: =SUM(AJ75/AF75)-1 -> 0.1271469
B76: Additional paid-in capital | C76: 807492 | D76: 847303 | E76: 934945 | F76: 1023997 | G76: 1075104 | H76: 1120769 | J76: 951802 | K76: 982339 | L76: 998816 | M76: =F76 -> 1023997 | N76: 1040378 | O76: 1049679 | P76: 1058969 | Q76: =G76 -> 1075104 | R76: 1091822 | S76: 1099197 | T76: 1104952 | U76: =H76 -> 1120769 | V76: 1129309 | W76: 1151858 | X76: 1175122 | Z76: =M76 -> 1023997 | AA76: =N76 -> 1040378 | AB76: =O76 -> 1049679 | AC76: =P76 -> 1058969 | AD76: =Q76 -> 1075104 | AE76: =R76 -> 1091822 | AF76: =S76 -> 1099197 | AG76: =T76 -> 1104952 | ... AK76: =X76 -> 1175122 | AM76: =SUM(AJ76/AF76)-1 -> 0.04790861
B77: Accumulated OCI | C77: 0 | D77: 56 | E77: 0 | F77: 0 | J77: 0 | K77: 0 | L77: 0 | M77: =F77 -> 0 | N77: 0 | O77: 0 | P77: 0 | Q77: =G77 -> 0 | R77: 0 | S77: 0 | T77: 0 | U77: =H77 -> 0 | V77: 0 | W77: 0 | X77: 0 | Z77: =M77 -> 0 | AA77: =N77 -> 0 | AB77: =O77 -> 0 | AC77: =P77 -> 0 | AD77: =Q77 -> 0 | AE77: =R77 -> 0 | AF77: =S77 -> 0 | AG77: =T77 -> 0 | ... AK77: =X77 -> 0
B78: Retained earnings | C78: 1128477 | D78: 1189422 | E78: 653376 | F78: 995773 | G78: 1286765 | H78: 1473909 | J78: 851940 | K78: 846011 | L78: 983140 | M78: =F78 -> 995773 | N78: 1059312 | O78: 1083926 | P78: 1051876 | Q78: =G78 -> 1286765 | R78: 1314749 | S78: 1354973 | T78: 1330181 | U78: =H78 -> 1473909 | V78: 1420239 | W78: 1571575 | X78: 1577736 | Z78: =M78 -> 995773 | AA78: =N78 -> 1059312 | AB78: =O78 -> 1083926 | AC78: =P78 -> 1051876 | AD78: =Q78 -> 1286765 | AE78: =R78 -> 1314749 | AF78: =S78 -> 1354973 | AG78: =T78 -> 1330181 | ... AK78: =X78 -> 1577736 | AM78: =SUM(AJ78/AF78)-1 -> 0.15985706
B79: Total stockholders' equity | C79: =SUM(C74:C78) -> 1902094 | D79: =SUM(D74:D78) -> 1999549 | E79: =SUM(E74:E78) -> 1535373 | F79: =SUM(F74:F78) -> 1959811 | G79: =SUM(G74:G78) -> 2279328 | H79: =SUM(H74:H78) -> 2488353 | J79: =SUM(J74:J78) -> 1745620 | K79: =SUM(K74:K78) -> 1769068 | L79: =SUM(L74:L78) -> 1922255 | M79: =SUM(M74:M78) -> 1959811 | N79: =SUM(N74:N78) -> 2018068 | O79: =SUM(O74:O78) -> 2051877 | P79: =SUM(P74:P78) -> 2028542 | Q79: =SUM(Q74:Q78) -> 2279328 | ... X79: =SUM(X74:X78) -> 2633014 | Z79: =SUM(Z74:Z78) -> 1959811 | AA79: =SUM(AA74:AA78) -> 2018068 | AB79: =SUM(AB74:AB78) -> 2051877 | AC79: =SUM(AC74:AC78) -> 2028542 | AD79: =SUM(AD74:AD78) -> 2279328 | AE79: =SUM(AE74:AE78) -> 2300743 | AF79: =SUM(AF74:AF78) -> 2348160 | AG79: =SUM(AG74:AG78) -> 2329009 | ... AK79: =SUM(AK74:AK78) -> 2633014 | AM79: =SUM(AJ79/AF79)-1 -> 0.10889377
B80: Total liabilities and stockholders' equity | C80: =SUM(C79+C72) -> 4863872 | D80: =SUM(D79+D72) -> 5089969 | E80: =SUM(E79+E72) -> 4764379 | F80: =SUM(F79+F72) -> 5370411 | G80: =SUM(G79+G72) -> 5707011 | H80: =SUM(H79+H72) -> 6001693 | J80: =SUM(J79+J72) -> 5012036 | K80: =SUM(K79+K72) -> 4945994 | L80: =SUM(L79+L72) -> 5331549 | M80: =SUM(M79+M72) -> 5370411 | N80: =SUM(N79+N72) -> 5375719 | O80: =SUM(O79+O72) -> 5248760 | P80: =SUM(P79+P72) -> 5595008 | Q80: =SUM(Q79+Q72) -> 5707011 | ... X80: =SUM(X79+X72) -> 7012292 | Z80: =SUM(Z79+Z72) -> 5370411 | AA80: =SUM(AA79+AA72) -> 5375719 | AB80: =SUM(AB79+AB72) -> 5248760 | AC80: =SUM(AC79+AC72) -> 5595008 | AD80: =SUM(AD79+AD72) -> 5707011 | AE80: =SUM(AE79+AE72) -> 5631939 | AF80: =SUM(AF79+AF72) -> 5737408 | AG80: =SUM(AG79+AG72) -> 5958486 | ... AK80: =SUM(AK79+AK72) -> 7012292 | AM80: =SUM(AJ80/AF80)-1 -> 0.15568703
B82: Balance Check | C82: =C80-C58 -> 0 | D82: =D80-D58 -> 0 | E82: =E80-E58 -> 0 | F82: =F80-F58 -> 0 | G82: =G80-G58 -> 0 | H82: =H80-H58 -> 0 | J82: =J80-J58 -> 0 | K82: =K80-K58 -> 0 | L82: =L80-L58 -> 0 | M82: =M80-M58 -> 0 | N82: =N80-N58 -> 0 | O82: =O80-O58 -> 0 | P82: =P80-P58 -> 0 | Q82: =Q80-Q58 -> 0 | ... X82: =X80-X58 -> 0 | Z82: =Z80-Z58 -> 0 | AA82: =AA80-AA58 -> 0 | AB82: =AB80-AB58 -> 0 | AC82: =AC80-AC58 -> 0 | AD82: =AD80-AD58 -> 0 | AE82: =AE80-AE58 -> 0 | AF82: =AF80-AF58 -> 0 | AG82: =AG80-AG58 -> 0 | ... AK82: =AK80-AK58 -> 0
B84: 1) Prepaid expenses and other current assets consists of: Prepaid expenses and other current assets + Forward contracts + Deferred offering costs.
A86: X | B86: Cash-Flows Statement | C86: FYE | F86: FYE | J86: Quarterly | T86: Quarterly | AF86: LTM | AM86: Variance
B87: =B7 -> Fiscal Period | C87: =C7 -> 2019 | D87: =D7 -> 2020 | E87: =E7 -> 2021 | F87: =F7 -> 2022 | G87: =G7 -> 2023 | H87: =H7 -> 2024 | J87: =J7 -> 1Q22 | K87: =K7 -> 2Q22 | L87: =L7 -> 3Q22 | M87: =M7 -> 4Q22 | N87: =N7 -> 1Q23 | O87: =O7 -> 2Q23 | P87: =P7 -> 3Q23 | Q87: =Q7 -> 4Q23 | ... X87: =X7 -> 3Q25 | Z87: =Z7 -> 4Q22 | AA87: =AA7 -> 1Q23 | AB87: =AB7 -> 2Q23 | AC87: =AC7 -> 3Q23 | AD87: =AD7 -> 4Q23 | AE87: =AE7 -> 1Q24 | AF87: =AF7 -> 2Q24 | AG87: =AG7 -> 3Q24 | ... AK87: =AK7 -> 3Q25
B88: =B8 -> Fiscal Period End Date | C88: =C8 -> 43862 | D88: =D8 -> 44226 | E88: =E8 -> 44590 | F88: =F8 -> 44954 | G88: =G8 -> 45325 | H88: =H8 -> 45689 | J88: =J8 -> 44681 | K88: =K8 -> 44772 | L88: =L8 -> 44863 | M88: =M8 -> 44954 | N88: =N8 -> 45045 | O88: =O8 -> 45136 | P88: =P8 -> 45227 | Q88: =Q8 -> 45325 | ... X88: =X8 -> 45962 | Z88: =Z8 -> 44954 | AA88: =AA8 -> 45045 | AB88: =AB8 -> 45136 | AC88: =AC8 -> 45227 | AD88: =AD8 -> 45325 | AE88: =AE8 -> 45416 | AF88: =AF8 -> 45507 | AG88: =AG8 -> 45598 | ... AK88: =AK8 -> 45962
B90: Cash-Flows From Operating Activities
B91: Net income (loss) | C91: =C31 -> 705945 | D91: =D31 -> 175835 | E91: =E31 -> 985837 | F91: =F31 -> 1242408 | G91: =G31 -> 1291005 | H91: =H31 -> 1201118 | J91: =J31 -> 331395 | K91: =K31 -> 295677 | L91: =L31 -> 274585 | M91: =M31 -> 340751 | N91: =N31 -> 347051 | O91: =O31 -> 300102 | P91: =P31 -> 249483 | Q91: =Q31 -> 394369 | ... X91: =X31 -> 230875 | Z91: =SUM(K91:N91) -> 1258064 | AA91: =SUM(L91:O91) -> 1262489 | AB91: =SUM(M91:P91) -> 1237387 | AC91: =SUM(N91:Q91) -> 1291005 | AD91: =SUM(O91:R91) -> 1257067 | AE91: =SUM(P91:S91) -> 1209521 | AF91: =SUM(P91:S91) -> 1209521 | AG91: =SUM(Q91:T91) -> 1202217 | AH91: =SUM(R91:U91) -> 1201118 | AI91: =SUM(S91:V91) -> 1193057 | AJ91: =SUM(T91:W91) -> 1201376 | AK91: =SUM(U91:X91) -> 1190072 | AM91: =SUM(AJ91/AF91)-1 -> -0.0067340708
B93: Adjustments to reconcile net income:
B94: Depreciation and amortization | C94: 295599 | D94: 297772 | E94: 268460 | F94: 241372 | G94: 243840 | H94: 267042 | J94: 62839 | K94: =123721-J94 -> 60882 | L94: =182182-K94-J94 -> 58461 | M94: =SUM(F94-SUM(J94:L94)) -> 59190 | N94: 57949 | O94: =119862-N94 -> 61913 | P94: =181273-O94-N94 -> 61411 | Q94: =SUM(G94-SUM(N94:P94)) -> 62567 | R94: 64739 | S94: =130053-R94 -> 65314 | T94: =197075-S94-R94 -> 67022 | U94: =SUM(H94-SUM(R94:T94)) -> 69967 | V94: 72033 | W94: =143198-V94 -> 71165 | X94: =218985-W94-V94 -> 75787 | Z94: =SUM(J94:M94) -> 241372 | AA94: =SUM(K94:N94) -> 236482 | AB94: =SUM(L94:O94) -> 237513 | AC94: =SUM(M94:P94) -> 240463 | AD94: =SUM(N94:Q94) -> 243840 | AE94: =SUM(O94:R94) -> 250630 | AF94: =SUM(P94:S94) -> 254031 | AG94: =SUM(Q94:T94) -> 259642 | ... AK94: =SUM(U94:X94) -> 288952 | AM94: =SUM(AJ94/AF94)-1 -> 0.10296381
B95: Non-cash lease expense | C95: 278820 | D95: 268071 | E95: 276229 | F95: 301912 | G95: 332754 | H95: 310636 | J95: 72192 | K95: =146251-J95 -> 74059 | L95: =222548-K95-J95 -> 76297 | M95: =SUM(F95-SUM(J95:L95)) -> 79364 | N95: 75478 | O95: =152867-N95 -> 77389 | P95: =232772-O95-N95 -> 79905 | Q95: =SUM(G95-SUM(N95:P95)) -> 99982 | R95: 77938 | S95: =163481-R95 -> 85543 | T95: =235950-S95-R95 -> 72469 | U95: =SUM(H95-SUM(R95:T95)) -> 74686 | V95: 91105 | W95: =183528-V95 -> 92423 | X95: =260632-W95-V95 -> 77104 | Z95: =SUM(J95:M95) -> 301912 | AA95: =SUM(K95:N95) -> 305198 | AB95: =SUM(L95:O95) -> 308528 | AC95: =SUM(M95:P95) -> 312136 | AD95: =SUM(N95:Q95) -> 332754 | AE95: =SUM(O95:R95) -> 335214 | AF95: =SUM(P95:S95) -> 343368 | AG95: =SUM(Q95:T95) -> 335932 | ... AK95: =SUM(U95:X95) -> 335318 | AM95: =SUM(AJ95/AF95)-1 -> -0.036942872
B96: Deferred income taxes | C96: 5503 | D96: -24008 | E96: -25666 | F96: 15653 | G96: 30575 | H96: -43328 | J96: 1009 | K96: =336-J96 -> -673 | L96: =-1066-K96-J96 -> -1402 | M96: =SUM(F96-SUM(J96:L96)) -> 16719 | N96: 2144 | O96: =666-N96 -> -1478 | P96: =1528-O96-N96 -> 862 | Q96: =SUM(G96-SUM(N96:P96)) -> 29047 | R96: 3635 | S96: =2540-R96 -> -1095 | T96: =5808-S96-R96 -> 3268 | U96: =SUM(H96-SUM(R96:T96)) -> -49136 | V96: 3420 | W96: =2232-V96 -> -1188 | X96: =-1613-W96-V96 -> -3845 | Z96: =SUM(J96:M96) -> 15653 | AA96: =SUM(K96:N96) -> 16788 | AB96: =SUM(L96:O96) -> 15983 | AC96: =SUM(M96:P96) -> 18247 | AD96: =SUM(N96:Q96) -> 30575 | AE96: =SUM(O96:R96) -> 32066 | AF96: =SUM(P96:S96) -> 32449 | AG96: =SUM(Q96:T96) -> 34855 | ... AK96: =SUM(U96:X96) -> -50749 | AM96: =SUM(AJ96/AF96)-1 -> -2.3447564
B97: Stock-based compensation expense | C97: 25045 | D97: 27583 | E97: 47259 | F97: 43044 | G97: 48246 | H97: 42787 | J97: 10356 | K97: =22875-J97 -> 12519 | L97: =32554-K97-J97 -> 9679 | M97: =SUM(F97-SUM(J97:L97)) -> 10490 | N97: 9721 | O97: =21539-N97 -> 11818 | P97: =33477-O97-N97 -> 11938 | Q97: =SUM(G97-SUM(N97:P97)) -> 14769 | R97: 10082 | S97: =19272-R97 -> 9190 | T97: =27691-S97-R97 -> 8419 | U97: =SUM(H97-SUM(R97:T97)) -> 15096 | V97: 11418 | W97: =20338-V97 -> 8920 | X97: =30324-W97-V97 -> 9986 | Z97: =SUM(J97:M97) -> 43044 | AA97: =SUM(K97:N97) -> 42409 | AB97: =SUM(L97:O97) -> 41708 | AC97: =SUM(M97:P97) -> 43967 | AD97: =SUM(N97:Q97) -> 48246 | AE97: =SUM(O97:R97) -> 48607 | AF97: =SUM(P97:S97) -> 45979 | AG97: =SUM(Q97:T97) -> 42460 | ... AK97: =SUM(U97:X97) -> 45420 | AM97: =SUM(AJ97/AF97)-1 -> -0.0462385
B98: Loss on disposal of property and equipment | C98: 5850 | D98: 6827 | E98: 5358 | F98: 6688 | G98: 11419 | H98: 11566 | J98: 1002 | K98: =2277-J98 -> 1275 | L98: =3892-K98-J98 -> 1615 | M98: =SUM(F98-SUM(J98:L98)) -> 2796 | N98: 1451 | O98: =3878-N98 -> 2427 | P98: =6310-O98-N98 -> 2432 | Q98: =SUM(G98-SUM(N98:P98)) -> 5109 | R98: 2975 | S98: =5204-R98 -> 2229 | T98: =7280-S98-R98 -> 2076 | U98: =SUM(H98-SUM(R98:T98)) -> 4286 | V98: 892 | W98: =4689-V98 -> 3797 | X98: =7398-W98-V98 -> 2709 | Z98: =SUM(J98:M98) -> 6688 | AA98: =SUM(K98:N98) -> 7137 | AB98: =SUM(L98:O98) -> 8289 | AC98: =SUM(M98:P98) -> 9106 | AD98: =SUM(N98:Q98) -> 11419 | AE98: =SUM(O98:R98) -> 12943 | AF98: =SUM(P98:S98) -> 12745 | AG98: =SUM(Q98:T98) -> 12389 | ... AK98: =SUM(U98:X98) -> 11684 | AM98: =SUM(AJ98/AF98)-1 -> -0.13291487
B99: Long-lived asset impairment charge | C99: 0 | D99: 72533 | E99: 0 | F99: 0 | G99: 0 | H99: 0 | J99: 0 | K99: 0 | L99: 0 | M99: =SUM(F99-SUM(J99:L99)) -> 0 | N99: 0 | O99: 0 | P99: 0 | Q99: =SUM(G99-SUM(N99:P99)) -> 0 | R99: 0 | S99: 0 | T99: 0 | U99: =SUM(H99-SUM(R99:T99)) -> 0 | V99: 0 | W99: 0 | X99: 0 | Z99: =SUM(J99:M99) -> 0 | AA99: =SUM(K99:N99) -> 0 | AB99: =SUM(L99:O99) -> 0 | AC99: =SUM(M99:P99) -> 0 | AD99: =SUM(N99:Q99) -> 0 | AE99: =SUM(O99:R99) -> 0 | AF99: =SUM(P99:S99) -> 0 | AG99: =SUM(Q99:T99) -> 0 | ... AK99: =SUM(U99:X99) -> 0 | AM99: =SUM(AJ99/AF99)-1 -> #DIV/0!
B100: Equity net loss of affiliate | C100: 0 | D100: 0 | E100: 0 | F100: 0 | G100: 0 | H100: 0 | J100: 0 | K100: 0 | L100: 0 | M100: =SUM(F100-SUM(J100:L100)) -> 0 | N100: 0 | O100: 0 | P100: 0 | Q100: =SUM(G100-SUM(N100:P100)) -> 0 | R100: 0 | S100: 0 | T100: 0 | U100: =SUM(H100-SUM(R100:T100)) -> 0 | V100: 628 | W100: =1225-V100 -> 597 | X100: =2210-W100-V100 -> 985 | Z100: =SUM(J100:M100) -> 0 | AA100: =SUM(K100:N100) -> 0 | AB100: =SUM(L100:O100) -> 0 | AC100: =SUM(M100:P100) -> 0 | AD100: =SUM(N100:Q100) -> 0 | AE100: =SUM(O100:R100) -> 0 | AF100: =SUM(P100:S100) -> 0 | AG100: =SUM(Q100:T100) -> 0 | ... AK100: =SUM(U100:X100) -> 2210 | AM100: =SUM(AJ100/AF100)-1 -> #DIV/0!
B102: Changes in assets and liabilities:
B103: Receivables | C103: -20637 | D103: -53772 | E103: -40573 | F103: 34260 | G103: -8517 | H103: -15395 | J103: 40928 | K103: =53168-J103 -> 12240 | L103: =33378-K103-J103 -> -19790 | M103: =SUM(F103-SUM(J103:L103)) -> 882 | N103: 9140 | O103: =24978-N103 -> 15838 | P103: =-3446-O103-N103 -> -28424 | Q103: =SUM(G103-SUM(N103:P103)) -> -5071 | R103: 4476 | S103: =7076-R103 -> 2600 | T103: =-5682-S103-R103 -> -12758 | U103: =SUM(H103-SUM(R103:T103)) -> -9713 | V103: -1812 | W103: =-198-V103 -> 1614 | X103: =-13138-W103-V103 -> -12940 | Z103: =SUM(J103:M103) -> 34260 | AA103: =SUM(K103:N103) -> 2472 | AB103: =SUM(L103:O103) -> 6070 | AC103: =SUM(M103:P103) -> -2564 | AD103: =SUM(N103:Q103) -> -8517 | AE103: =SUM(O103:R103) -> -13181 | AF103: =SUM(P103:S103) -> -26419 | AG103: =SUM(Q103:T103) -> -10753 | ... AK103: =SUM(U103:X103) -> -22851 | AM103: =SUM(AJ103/AF103)-1 -> -0.1419433
B104: Merchandise inventories | C104: -79372 | D104: 125486 | E104: -331003 | F104: -104233 | G104: -138685 | H104: -226078 | J104: -71334 | K104: =-166912-J104 -> -95578 | L104: =-615451-K104-J104 -> -448539 | M104: =SUM(F104-SUM(J104:L104)) -> 511218 | N104: -147784 | O104: =-212088-N104 -> -64304 | P104: =-717855-O104-N104 -> -505767 | Q104: =SUM(G104-SUM(N104:P104)) -> 579170 | R104: -163904 | S104: =-256150-R104 -> -92246 | T104: =-623050-S104-R104 -> -366900 | U104: =SUM(H104-SUM(R104:T104)) -> 396972 | V104: -153305 | W104: =-366091-V104 -> -212786 | X104: =-702678-W104-V104 -> -336587 | Z104: =SUM(J104:M104) -> -104233 | AA104: =SUM(K104:N104) -> -180683 | AB104: =SUM(L104:O104) -> -149409 | AC104: =SUM(M104:P104) -> -206637 | AD104: =SUM(N104:Q104) -> -138685 | AE104: =SUM(O104:R104) -> -154805 | AF104: =SUM(P104:S104) -> -182747 | AG104: =SUM(Q104:T104) -> -43880 | ... AK104: =SUM(U104:X104) -> -305706 | AM104: =SUM(AJ104/AF104)-1 -> 0.83871144
B105: Prepaid expenses and other current assets | C105: 9289 | D105: -4363 | E105: -3412 | F105: -19432 | G105: 14648 | H105: -13515 | J105: -3261 | K105: =-12200-J105 -> -8939 | L105: =-26828-K105-J105 -> -14628 | M105: =SUM(F105-SUM(J105:L105)) -> 7396 | N105: 22232 | O105: =19722-N105 -> -2510 | P105: =12964-O105-N105 -> -6758 | Q105: =SUM(G105-SUM(N105:P105)) -> 1684 | R105: -10931 | S105: =-16425-R105 -> -5494 | T105: =-19916-S105-R105 -> -3491 | U105: =SUM(H105-SUM(R105:T105)) -> 6401 | V105: -9283 | W105: =-21657-V105 -> -12374 | X105: =-14088-W105-V105 -> 7569 | Z105: =SUM(J105:M105) -> -19432 | AA105: =SUM(K105:N105) -> 6061 | AB105: =SUM(L105:O105) -> 12490 | AC105: =SUM(M105:P105) -> 20360 | AD105: =SUM(N105:Q105) -> 14648 | AE105: =SUM(O105:R105) -> -18515 | AF105: =SUM(P105:S105) -> -21499 | AG105: =SUM(Q105:T105) -> -18232 | ... AK105: =SUM(U105:X105) -> -7687 | AM105: =SUM(AJ105/AF105)-1 -> -0.12800595
B106: Income taxes | C106: 610 | D106: 58916 | E106: -35652 | F106: -45182 | G106: 45367 | H106: 34772 | J106: 101236 | K106: =-45906-J106 -> -147142 | L106: =-49446-K106-J106 -> -3540 | M106: =SUM(F106-SUM(J106:L106)) -> 4264 | N106: 97003 | O106: =8194-N106 -> -88809 | P106: =9535-O106-N106 -> 1341 | Q106: =SUM(G106-SUM(N106:P106)) -> 35832 | R106: 85652 | S106: =-60666-R106 -> -146318 | T106: =-69818-S106-R106 -> -9152 | U106: =SUM(H106-SUM(R106:T106)) -> 104590 | V106: 88934 | W106: =-70406-V106 -> -159340 | X106: =-67994-W106-V106 -> 2412 | Z106: =SUM(J106:M106) -> -45182 | AA106: =SUM(K106:N106) -> -49415 | AB106: =SUM(L106:O106) -> 8918 | AC106: =SUM(M106:P106) -> 13799 | AD106: =SUM(N106:Q106) -> 45367 | AE106: =SUM(O106:R106) -> 34016 | AF106: =SUM(P106:S106) -> -23493 | AG106: =SUM(Q106:T106) -> -33986 | ... AK106: =SUM(U106:X106) -> 36596 | AM106: =SUM(AJ106/AF106)-1 -> -2.0655089
B107: Accounts payable | C107: 9993 | D107: 62324 | E107: 66156 | F107: 8309 | G107: -20873 | H107: 30297 | J107: 42586 | K107: =40051-J107 -> -2535 | L107: =94214-K107-J107 -> 54163 | M107: =SUM(F107-SUM(J107:L107)) -> -85905 | N107: 62257 | O107: =-38752-N107 -> -101009 | P107: =41817-O107-N107 -> 80569 | Q107: =SUM(G107-SUM(N107:P107)) -> -62690 | R107: -74069 | S107: =29715-R107 -> 103784 | T107: =54210-S107-R107 -> 24495 | U107: =SUM(H107-SUM(R107:T107)) -> -23913 | V107: -24920 | W107: =98115-V107 -> 123035 | X107: =123911-W107-V107 -> 25796 | Z107: =SUM(J107:M107) -> 8309 | AA107: =SUM(K107:N107) -> 27980 | AB107: =SUM(L107:O107) -> -70494 | AC107: =SUM(M107:P107) -> -44088 | AD107: =SUM(N107:Q107) -> -20873 | AE107: =SUM(O107:R107) -> -157199 | AF107: =SUM(P107:S107) -> 47594 | AG107: =SUM(Q107:T107) -> -8480 | ... AK107: =SUM(U107:X107) -> 99998 | AM107: =SUM(AJ107/AF107)-1 -> 1.0737278
B108: Accrued liabilities | C108: 28183 | D108: 58599 | E108: 58598 | F108: 48249 | G108: -62238 | H108: 6303 | J108: -57214 | K108: =-49364-J108 -> 7850 | L108: =64164-K108-J108 -> 113528 | M108: =SUM(F108-SUM(J108:L108)) -> -15915 | N108: -98515 | O108: =-102763-N108 -> -4248 | P108: =-34955-O108-N108 -> 67808 | Q108: =SUM(G108-SUM(N108:P108)) -> -27283 | R108: -43846 | S108: =-33634-R108 -> 10212 | T108: =-45777-S108-R108 -> -12143 | U108: =SUM(H108-SUM(R108:T108)) -> 52080 | V108: -32716 | W108: =-3881-V108 -> 28835 | X108: =6567-W108-V108 -> 10448 | Z108: =SUM(J108:M108) -> 48249 | AA108: =SUM(K108:N108) -> 6948 | AB108: =SUM(L108:O108) -> -5150 | AC108: =SUM(M108:P108) -> -50870 | AD108: =SUM(N108:Q108) -> -62238 | AE108: =SUM(O108:R108) -> -7569 | AF108: =SUM(P108:S108) -> 6891 | AG108: =SUM(Q108:T108) -> -73060 | ... AK108: =SUM(U108:X108) -> 58647 | AM108: =SUM(AJ108/AF108)-1 -> 4.232332
B109: Deferred revenue | C109: 38481 | D109: 36848 | E109: 79196 | F109: 41098 | G109: 41914 | H109: 63994 | J109: -28885 | K109: =-37008-J109 -> -8123 | L109: =-41447-K109-J109 -> -4439 | M109: =SUM(F109-SUM(J109:L109)) -> 82545 | N109: -37460 | O109: =-40424-N109 -> -2964 | P109: =-43740-O109-N109 -> -3316 | Q109: =SUM(G109-SUM(N109:P109)) -> 85654 | R109: -37862 | S109: =-41604-R109 -> -3742 | T109: =-31551-S109-R109 -> 10053 | U109: =SUM(H109-SUM(R109:T109)) -> 95545 | V109: -37742 | W109: =-44418-V109 -> -6676 | X109: =-41642-W109-V109 -> 2776 | Z109: =SUM(J109:M109) -> 41098 | AA109: =SUM(K109:N109) -> 32523 | AB109: =SUM(L109:O109) -> 37682 | AC109: =SUM(M109:P109) -> 38805 | AD109: =SUM(N109:Q109) -> 41914 | AE109: =SUM(O109:R109) -> 41512 | AF109: =SUM(P109:S109) -> 40734 | AG109: =SUM(Q109:T109) -> 54103 | ... AK109: =SUM(U109:X109) -> 53903 | AM109: =SUM(AJ109/AF109)-1 -> 0.50193941
B110: Operating lease liabilities | C110: -256910 | D110: -297513 | E110: -303914 | F110: -324500 | G110: -338105 | H110: -333835 | J110: -79936 | K110: =-163302-J110 -> -83366 | L110: =-246988-K110-J110 -> -83686 | M110: =SUM(F110-SUM(J110:L110)) -> -77512 | N110: -78562 | O110: =-163527-N110 -> -84965 | P110: =-248469-O110-N110 -> -84942 | Q110: =SUM(G110-SUM(N110:P110)) -> -89636 | R110: -83500 | S110: =-170779-R110 -> -87279 | T110: =-250267-S110-R110 -> -79488 | U110: =SUM(H110-SUM(R110:T110)) -> -83568 | V110: -88100 | W110: =-180316-V110 -> -92216 | X110: =-261864-W110-V110 -> -81548 | Z110: =SUM(J110:M110) -> -324500 | AA110: =SUM(K110:N110) -> -323126 | AB110: =SUM(L110:O110) -> -324725 | AC110: =SUM(M110:P110) -> -325981 | AD110: =SUM(N110:Q110) -> -338105 | AE110: =SUM(O110:R110) -> -343043 | AF110: =SUM(P110:S110) -> -345357 | AG110: =SUM(Q110:T110) -> -339903 | ... AK110: =SUM(U110:X110) -> -345432 | AM110: =SUM(AJ110/AF110)-1 -> -0.0057476756
B111: Other assets and liabilities | C111: 54894 | D111: -783 | E111: 12392 | F111: -7731 | G111: -15084 | H111: 2241 | J111: 3390 | K111: =-392-J111 -> -3782 | L111: =20063-K111-J111 -> 20455 | M111: =SUM(F111-SUM(J111:L111)) -> -27794 | N111: -17204 | O111: =-12497-N111 -> 4707 | P111: =-9836-O111-N111 -> 2661 | Q111: =SUM(G111-SUM(N111:P111)) -> -5248 | R111: 10842 | S111: =15127-R111 -> 4285 | T111: =12240-S111-R111 -> -2887 | U111: =SUM(H111-SUM(R111:T111)) -> -9999 | V111: -5583 | W111: =-15742-V111 -> -10159 | X111: =-21628-W111-V111 -> -5886 | Z111: =SUM(J111:M111) -> -7731 | AA111: =SUM(K111:N111) -> -28325 | AB111: =SUM(L111:O111) -> -19836 | AC111: =SUM(M111:P111) -> -37630 | AD111: =SUM(N111:Q111) -> -15084 | AE111: =SUM(O111:R111) -> 12962 | AF111: =SUM(P111:S111) -> 12540 | AG111: =SUM(Q111:T111) -> 6992 | ... AK111: =SUM(U111:X111) -> -31627 | AM111: =SUM(AJ111/AF111)-1 -> -3.2829346
B112: Net cash used in operating activities | C112: =SUM(C91:C111) -> 1101293 | D112: =SUM(D91:D111) -> 810355 | E112: =SUM(E91:E111) -> 1059265 | F112: =SUM(F91:F111) -> 1481915 | G112: =SUM(G91:G111) -> 1476266 | H112: =SUM(H91:H111) -> 1338605 | J112: =SUM(J91:J111) -> 426303 | K112: =SUM(K91:K111) -> 114364 | L112: =SUM(L91:L111) -> 32759 | M112: =SUM(M91:M111) -> 908489 | N112: =SUM(N91:N111) -> 304901 | O112: =SUM(O91:O111) -> 123907 | P112: =SUM(P91:P111) -> -70797 | Q112: =SUM(Q91:Q111) -> 1118255 | ... X112: =SUM(X91:X111) -> 5641 | Z112: =SUM(Z91:Z111) -> 1497571 | AA112: =SUM(AA91:AA111) -> 1364938 | AB112: =SUM(AB91:AB111) -> 1344954 | AC112: =SUM(AC91:AC111) -> 1320118 | AD112: =SUM(AD91:AD111) -> 1442328 | AE112: =SUM(AE91:AE111) -> 1283159 | AF112: =SUM(AF91:AF111) -> 1406337 | AG112: =SUM(AG91:AG111) -> 1420296 | ... AK112: =SUM(AK91:AK111) -> 1358748 | AM112: =SUM(AJ112/AF112)-1 -> -0.078265736
B114: Cash flows from investing activities:
B115: Capital expenditures | C115: -298534 | D115: -151866 | E115: -172187 | F115: -312126 | G115: -435267 | H115: -374458 | J115: -71076 | K115: =-120500-J115 -> -49424 | L115: =-203961-K115-J115 -> -83461 | M115: =SUM(F115-SUM(J115:L115)) -> -108165 | N115: -109766 | O115: =-204748-N115 -> -94982 | P115: =-311030-O115-N115 -> -106282 | Q115: =SUM(G115-SUM(N115:P115)) -> -124237 | R115: -91024 | S115: =-186301-R115 -> -95277 | T115: =-300536-S115-R115 -> -114235 | U115: =SUM(H115-SUM(R115:T115)) -> -73922 | V115: -79031 | W115: =-155988-V115 -> -76957 | X115: =-243262-W115-V115 -> -87274 | Z115: =SUM(J115:M115) -> -312126 | AA115: =SUM(K115:N115) -> -350816 | AB115: =SUM(L115:O115) -> -396374 | AC115: =SUM(M115:P115) -> -419195 | AD115: =SUM(N115:Q115) -> -435267 | AE115: =SUM(O115:R115) -> -416525 | AF115: =SUM(P115:S115) -> -416820 | AG115: =SUM(Q115:T115) -> -424773 | ... AK115: =SUM(U115:X115) -> -317184 | AM115: =SUM(AJ115/AF115)-1 -> -0.17435584
B116: Acquisitions, net of cash acquired | C116: 0 | D116: 0 | E116: 0 | F116: 0 | G116: 0 | H116: 0 | J116: 0 | K116: 0 | L116: 0 | M116: =SUM(F116-SUM(J116:L116)) -> 0 | N116: 0 | O116: 0 | P116: 0 | Q116: =SUM(G116-SUM(N116:P116)) -> 0 | R116: 0 | S116: 0 | T116: 0 | U116: =SUM(H116-SUM(R116:T116)) -> 0 | V116: 0 | W116: =-386793-V116 -> -386793 | X116: =-386793-W116-V116 -> 0 | Z116: =SUM(J116:M116) -> 0 | AA116: =SUM(K116:N116) -> 0 | AB116: =SUM(L116:O116) -> 0 | AC116: =SUM(M116:P116) -> 0 | AD116: =SUM(N116:Q116) -> 0 | AE116: =SUM(O116:R116) -> 0 | AF116: =SUM(P116:S116) -> 0 | AG116: =SUM(Q116:T116) -> 0 | ... AK116: =SUM(U116:X116) -> -386793 | AM116: =SUM(AJ116/AF116)-1 -> #DIV/0!
B117: Other investments | C117: -172946 | D117: 103115 | E117: -4297 | F117: -2458 | G117: -6158 | H117: -8631 | J117: -797 | K117: =-1249-J117 -> -452 | L117: =-3068-K117-J117 -> -1819 | M117: =SUM(F117-SUM(J117:L117)) -> 610 | N117: -314 | O117: =-1687-N117 -> -1373 | P117: =-4870-O117-N117 -> -3183 | Q117: =SUM(G117-SUM(N117:P117)) -> -1288 | R117: -2563 | S117: =-5091-R117 -> -2528 | T117: =-6108-S117-R117 -> -1017 | U117: =SUM(H117-SUM(R117:T117)) -> -2523 | V117: -7346 | W117: =-17130-V117 -> -9784 | X117: =-25445-W117-V117 -> -8315 | Z117: =SUM(J117:M117) -> -2458 | AA117: =SUM(K117:N117) -> -1975 | AB117: =SUM(L117:O117) -> -2896 | AC117: =SUM(M117:P117) -> -4260 | AD117: =SUM(N117:Q117) -> -6158 | AE117: =SUM(O117:R117) -> -8407 | AF117: =SUM(P117:S117) -> -9562 | AG117: =SUM(Q117:T117) -> -7396 | ... AK117: =SUM(U117:X117) -> -27968 | AM117: =SUM(AJ117/AF117)-1 -> 1.1616817
B118: Net cash used in investing activities | C118: =SUM(C115:C117) -> -471480 | D118: =SUM(D115:D117) -> -48751 | E118: =SUM(E115:E117) -> -176484 | F118: =SUM(F115:F117) -> -314584 | G118: =SUM(G115:G117) -> -441425 | H118: =SUM(H115:H117) -> -383089 | J118: =SUM(J115:J117) -> -71873 | K118: =SUM(K115:K117) -> -49876 | L118: =SUM(L115:L117) -> -85280 | M118: =SUM(M115:M117) -> -107555 | N118: =SUM(N115:N117) -> -110080 | O118: =SUM(O115:O117) -> -96355 | P118: =SUM(P115:P117) -> -109465 | Q118: =SUM(Q115:Q117) -> -125525 | ... X118: =SUM(X115:X117) -> -95589 | Z118: =SUM(Z115:Z117) -> -314584 | AA118: =SUM(AA115:AA117) -> -352791 | AB118: =SUM(AB115:AB117) -> -399270 | AC118: =SUM(AC115:AC117) -> -423455 | AD118: =SUM(AD115:AD117) -> -441425 | AE118: =SUM(AE115:AE117) -> -424932 | AF118: =SUM(AF115:AF117) -> -426382 | AG118: =SUM(AG115:AG117) -> -432169 | ... AK118: =SUM(AK115:AK117) -> -731945 | AM118: =SUM(AJ118/AF118)-1 -> 0.76275734
B120: Cash flows from financing activities:
B121: Proceeds from Debt Issuances / (Repayment) | C121: 0 | D121: =800000-800000 -> 0 | E121: 0 | F121: 0 | G121: =195400-195400 -> 0 | H121: =199700-199700 -> 0 | J121: 0 | K121: 0 | L121: 0 | M121: =SUM(F121-SUM(J121:L121)) -> 0 | N121: 0 | O121: 0 | P121: =195400-O121-N121 -> 195400 | Q121: =SUM(G121-SUM(N121:P121)) -> -195400 | R121: 0 | S121: 0 | T121: =199700-S121-R121 -> 199700 | U121: =SUM(H121-SUM(R121:T121)) -> -199700 | V121: 0 | W121: =-333100+593641-V121 -> 260541 | X121: =1641844-1118683-W121-V121 -> 262620 | Z121: =SUM(J121:M121) -> 0 | AA121: =SUM(K121:N121) -> 0 | AB121: =SUM(L121:O121) -> 0 | AC121: =SUM(M121:P121) -> 195400 | AD121: =SUM(N121:Q121) -> 0 | AE121: =SUM(O121:R121) -> 0 | AF121: =SUM(P121:S121) -> 0 | AG121: =SUM(Q121:T121) -> 4300 | ... AK121: =SUM(U121:X121) -> 323461 | AM121: =SUM(AJ121/AF121)-1 -> #DIV/0!
B122: Repurchase of common shares | C122: -680979 | D122: -114895 | E122: -1521925 | F122: -900033 | G122: -995738 | H122: -1003328 | J122: -132834 | K122: =-434448-J122 -> -301614 | L122: =-571908-K122-J122 -> -137460 | M122: =SUM(F122-SUM(J122:L122)) -> -328125 | N122: -283517 | O122: =-559011-N122 -> -275494 | P122: =-840551-O122-N122 -> -281540 | Q122: =SUM(G122-SUM(N122:P122)) -> -155187 | R122: -289431 | S122: =-501768-R122 -> -212337 | T122: =-765384-S122-R122 -> -263616 | U122: =SUM(H122-SUM(R122:T122)) -> -237944 | V122: -369786 | W122: =-479242-V122 -> -109456 | X122: =-703960-W122-V122 -> -224718 | Z122: =SUM(J122:M122) -> -900033 | AA122: =SUM(K122:N122) -> -1050716 | AB122: =SUM(L122:O122) -> -1024596 | AC122: =SUM(M122:P122) -> -1168676 | AD122: =SUM(N122:Q122) -> -995738 | AE122: =SUM(O122:R122) -> -1001652 | AF122: =SUM(P122:S122) -> -938495 | AG122: =SUM(Q122:T122) -> -920571 | ... AK122: =SUM(U122:X122) -> -941904 | AM122: =SUM(AJ122/AF122)-1 -> 0.045079622
B123: Debt issuance costs | C123: 0 | D123: -1915 | E123: 0 | F123: 0 | G123: 0 | H123: -4159 | J123: 0 | K123: 0 | L123: 0 | M123: =SUM(F123-SUM(J123:L123)) -> 0 | N123: 0 | O123: 0 | P123: 0 | Q123: =SUM(G123-SUM(N123:P123)) -> 0 | R123: -3950 | S123: =-4088-R123 -> -138 | T123: =-4159-S123-R123 -> -71 | U123: =SUM(H123-SUM(R123:T123)) -> 0 | V123: 0 | W123: 0 | X123: =-763-W123-V123 -> -763 | Z123: =SUM(J123:M123) -> 0 | AA123: =SUM(K123:N123) -> 0 | AB123: =SUM(L123:O123) -> 0 | AC123: =SUM(M123:P123) -> 0 | AD123: =SUM(N123:Q123) -> 0 | AE123: =SUM(O123:R123) -> -3950 | AF123: =SUM(P123:S123) -> -4088 | AG123: =SUM(Q123:T123) -> -4159 | ... AK123: =SUM(U123:X123) -> -763 | AM123: =SUM(AJ123/AF123)-1 -> -0.98263209
B124: Stock options exercised | C124: 43780 | D124: 12229 | E124: 40386 | F124: 46011 | G124: 12176 | H124: 12339 | J124: 6502 | K124: =24521-J124 -> 18019 | L124: =31319-K124-J124 -> 6798 | M124: =SUM(F124-SUM(J124:L124)) -> 14692 | N124: 8927 | O124: =9147-N124 -> 220 | P124: =9302-O124-N124 -> 155 | Q124: =SUM(G124-SUM(N124:P124)) -> 2874 | R124: 8913 | S124: =9196-R124 -> 283 | T124: =9200-S124-R124 -> 4 | U124: =SUM(H124-SUM(R124:T124)) -> 3139 | V124: 481 | W124: =14851-V124 -> 14370 | X124: =30103-W124-V124 -> 15252 | Z124: =SUM(J124:M124) -> 46011 | AA124: =SUM(K124:N124) -> 48436 | AB124: =SUM(L124:O124) -> 30637 | AC124: =SUM(M124:P124) -> 23994 | AD124: =SUM(N124:Q124) -> 12176 | AE124: =SUM(O124:R124) -> 12162 | AF124: =SUM(P124:S124) -> 12225 | AG124: =SUM(Q124:T124) -> 12074 | ... AK124: =SUM(U124:X124) -> 33242 | AM124: =SUM(AJ124/AF124)-1 -> 0.47190184
...

Sheet Revenue Drivers
B2: Ulta Beauty Inc. (NASDAQ: ULTA) | C2: FYE | F2: FYE | J2: Quarterly | T2: Quarterly | AE2: LTM
B3: Segment Anaysis | C3: ='Historical Financials'!C7 -> 2019 | D3: ='Historical Financials'!D7 -> 2020 | E3: ='Historical Financials'!E7 -> 2021 | F3: ='Historical Financials'!F7 -> 2022 | G3: ='Historical Financials'!G7 -> 2023 | H3: ='Historical Financials'!H7 -> 2024 | J3: ='Historical Financials'!J7 -> 1Q22 | K3: ='Historical Financials'!K7 -> 2Q22 | L3: ='Historical Financials'!L7 -> 3Q22 | M3: ='Historical Financials'!M7 -> 4Q22 | N3: ='Historical Financials'!N7 -> 1Q23 | O3: ='Historical Financials'!O7 -> 2Q23 | P3: ='Historical Financials'!P7 -> 3Q23 | Q3: ='Historical Financials'!Q7 -> 4Q23 | ... X3: ='Historical Financials'!X7 -> 3Q25 | Z3: =O3 -> 2Q23 | AA3: =P3 -> 3Q23 | AB3: =Q3 -> 4Q23 | AC3: =R3 -> 1Q24 | AD3: =S3 -> 2Q24 | AE3: =T3 -> 3Q24 | AF3: =U3 -> 4Q24 | AG3: =V3 -> 1Q25 | ... AI3: =X3 -> 3Q25
B4: ($ In Thousands) | C4: ='Historical Financials'!C8 -> 43862 | D4: ='Historical Financials'!D8 -> 44226 | E4: ='Historical Financials'!E8 -> 44590 | F4: ='Historical Financials'!F8 -> 44954 | G4: ='Historical Financials'!G8 -> 45325 | H4: ='Historical Financials'!H8 -> 45689 | J4: ='Historical Financials'!J8 -> 44681 | K4: ='Historical Financials'!K8 -> 44772 | L4: ='Historical Financials'!L8 -> 44863 | M4: ='Historical Financials'!M8 -> 44954 | N4: ='Historical Financials'!N8 -> 45045 | O4: ='Historical Financials'!O8 -> 45136 | P4: ='Historical Financials'!P8 -> 45227 | Q4: ='Historical Financials'!Q8 -> 45325 | ... X4: ='Historical Financials'!X8 -> 45962 | Z4: =O4 -> 45136 | AA4: =P4 -> 45227 | AB4: =Q4 -> 45325 | AC4: =R4 -> 45416 | AD4: =S4 -> 45507 | AE4: =T4 -> 45598 | AF4: =U4 -> 45689 | AG4: =V4 -> 45780 | ... AI4: =X4 -> 45962
A6: X | B6: Revenue Segment Anaysis
B7: Cosmetics | C7: =C16*'Historical Financials'!$C$10 -> 3773014.7 | D7: =D16*'Historical Financials'!$D$10 -> 2768378.9 | E7: =E16*'Historical Financials'!$E$10 -> 3711282.3 | F7: =F16*'Historical Financials'!$F$10 -> 4287603.6 | G7: =G16*'Historical Financials'!$G$10 -> 4594994.2 | H7: =H16*'Historical Financials'!$H$10 -> 4405305.1 | J7: =J16*'Historical Financials'!$J$10 -> 1032196.4 | K7: =K16*'Historical Financials'!$K$10 -> 964787.46 | L7: =L16*'Historical Financials'!$L$10 -> 1029068.9 | M7: =M16*'Historical Financials'!$M$10 -> 1355244.7 | N7: =N16*'Historical Financials'!$N$10 -> 1159075.7 | O7: =O16*'Historical Financials'!$O$10 -> 1011923.6 | P7: =P16*'Historical Financials'!$P$10 -> 1045351.9 | Q7: =Q16*'Historical Financials'!$Q$10 -> 1457262.2 | R7: =R16*'Historical Financials'!$R$10 -> 1144856.2 | S7: =S16*'Historical Financials'!$S$10 -> 995313.93 | T7: =T16*'Historical Financials'!$T$10 -> 1037341 | U7: =U16*'Historical Financials'!$U$10 -> 1360171.4 | V7: =V16*'Historical Financials'!$V$10 -> 1139346.8 | W7: =W16*'Historical Financials'!$W$10 -> 1059618.2 | X7: =X16*'Historical Financials'!$X$10 -> 1171625.4 | Z7: =SUM(L7:O7) -> 4555312.9 | AA7: =SUM(M7:P7) -> 4571595.8 | AB7: =SUM(N7:Q7) -> 4673613.4 | AC7: =SUM(O7:R7) -> 4659393.8 | AD7: =SUM(P7:S7) -> 4642784.1 | AE7: =SUM(Q7:T7) -> 4634773.3 | AF7: =SUM(R7:U7) -> 4537682.5 | AG7: =SUM(S7:V7) -> 4532173.1 | ... AI7: =SUM(U7:X7) -> 4730761.9
B8: Haircare products and styling tools | C8: =C17*'Historical Financials'!$C$10 -> 1331652.2 | D8: =D17*'Historical Financials'!$D$10 -> 1230390.6 | E8: =E17*'Historical Financials'!$E$10 -> 1726177.8 | F8: =F17*'Historical Financials'!$F$10 -> 2143801.8 | G8: =G17*'Historical Financials'!$G$10 -> 2129387.6 | H8: =H17*'Historical Financials'!$H$10 -> 2598000.4 | J8: =J17*'Historical Financials'!$J$10 -> 469180.2 | K8: =K17*'Historical Financials'!$K$10 -> 505364.86 | L8: =L17*'Historical Financials'!$L$10 -> 491146.53 | M8: =M17*'Historical Financials'!$M$10 -> 677622.33 | N8: =N17*'Historical Financials'!$N$10 -> 474167.34 | O8: =O17*'Historical Financials'!$O$10 -> 531259.89 | P8: =P17*'Historical Financials'!$P$10 -> 472897.27 | Q8: =Q17*'Historical Financials'!$Q$10 -> 675316.62 | R8: =R17*'Historical Financials'!$R$10 -> 517911.12 | S8: =S17*'Historical Financials'!$S$10 -> 510417.4 | T8: =T17*'Historical Financials'!$T$10 -> 506020 | U8: =U17*'Historical Financials'!$U$10 -> 802152.37 | V8: =V17*'Historical Financials'!$V$10 -> 712091.75 | W8: =W17*'Historical Financials'!$W$10 -> 697117.25 | X8: =X17*'Historical Financials'!$X$10 -> 542948.37 | Z8: =SUM(L8:O8) -> 2174196.1 | AA8: =SUM(M8:P8) -> 2155946.8 | AB8: =SUM(N8:Q8) -> 2153641.1 | AC8: =SUM(O8:R8) -> 2197384.9 | AD8: =SUM(P8:S8) -> 2176542.4 | AE8: =SUM(Q8:T8) -> 2209665.1 | AF8: =SUM(R8:U8) -> 2336500.9 | AG8: =SUM(S8:V8) -> 2530681.5 | ... AI8: =SUM(U8:X8) -> 2754309.7
B9: Skincare | C9: =C18*'Historical Financials'!$C$10 -> 1035729.5 | D9: =D18*'Historical Financials'!$D$10 -> 984312.48 | E9: =E18*'Historical Financials'!$E$10 -> 1467251.1 | F9: =F18*'Historical Financials'!$F$10 -> 1735458.6 | G9: =G18*'Historical Financials'!$G$10 -> 2129387.6 | H9: =H18*'Historical Financials'!$H$10 -> 2146174.3 | J9: =J18*'Historical Financials'!$J$10 -> 422262.18 | K9: =K18*'Historical Financials'!$K$10 -> 390509.21 | L9: =L18*'Historical Financials'!$L$10 -> 374206.88 | M9: =M18*'Historical Financials'!$M$10 -> 548551.41 | N9: =N18*'Historical Financials'!$N$10 -> 500509.97 | O9: =O18*'Historical Financials'!$O$10 -> 505961.8 | P9: =P18*'Historical Financials'!$P$10 -> 472897.27 | Q9: =Q18*'Historical Financials'!$Q$10 -> 675316.62 | R9: =R18*'Historical Financials'!$R$10 -> 626945.04 | S9: =S18*'Historical Financials'!$S$10 -> 612500.88 | T9: =T18*'Historical Financials'!$T$10 -> 581923 | U9: =U18*'Historical Financials'!$U$10 -> 662647.61 | V9: =V18*'Historical Financials'!$V$10 -> 512706.06 | W9: =W18*'Historical Financials'!$W$10 -> 529809.11 | X9: =X18*'Historical Financials'!$X$10 -> 685829.52 | Z9: =SUM(L9:O9) -> 1929230.1 | AA9: =SUM(M9:P9) -> 2027920.5 | AB9: =SUM(N9:Q9) -> 2154685.7 | AC9: =SUM(O9:R9) -> 2281120.7 | AD9: =SUM(P9:S9) -> 2387659.8 | AE9: =SUM(Q9:T9) -> 2496685.5 | AF9: =SUM(R9:U9) -> 2484016.5 | AG9: =SUM(S9:V9) -> 2369777.5 | ... AI9: =SUM(U9:X9) -> 2390992.3
B10: Fragrance and bath | C10: =C19*'Historical Financials'!$C$10 -> 665826.12 | D10: =D19*'Historical Financials'!$D$10 -> 738234.36 | E10: =E19*'Historical Financials'!$E$10 -> 1208324.5 | F10: =F19*'Historical Financials'!$F$10 -> 1429201.2 | G10: =G19*'Historical Financials'!$G$10 -> 1681095.4 | H10: =H19*'Historical Financials'!$H$10 -> 1468435 | J10: =J19*'Historical Financials'!$J$10 -> 281508.12 | K10: =K19*'Historical Financials'!$K$10 -> 275653.56 | L10: =L19*'Historical Financials'!$L$10 -> 280655.16 | M10: =M19*'Historical Financials'!$M$10 -> 451748.22 | N10: =N19*'Historical Financials'!$N$10 -> 316111.56 | O10: =O19*'Historical Financials'!$O$10 -> 303577.08 | P10: =P19*'Historical Financials'!$P$10 -> 323561.29 | Q10: =Q19*'Historical Financials'!$Q$10 -> 533144.7 | R10: =R19*'Historical Financials'!$R$10 -> 272584.8 | S10: =S19*'Historical Financials'!$S$10 -> 280729.57 | T10: =T19*'Historical Financials'!$T$10 -> 253010 | U10: =U19*'Historical Financials'!$U$10 -> 453390.47 | V10: =V19*'Historical Financials'!$V$10 -> 313320.37 | W10: =W19*'Historical Financials'!$W$10 -> 334616.28 | X10: =X19*'Historical Financials'!$X$10 -> 314338.53 | Z10: =SUM(L10:O10) -> 1352092 | AA10: =SUM(M10:P10) -> 1394998.2 | AB10: =SUM(N10:Q10) -> 1476394.6 | AC10: =SUM(O10:R10) -> 1432867.9 | AD10: =SUM(P10:S10) -> 1410020.4 | AE10: =SUM(Q10:T10) -> 1339469.1 | AF10: =SUM(R10:U10) -> 1259714.8 | AG10: =SUM(S10:V10) -> 1300450.4 | ... AI10: =SUM(U10:X10) -> 1415665.7
B11: Services | C11: =C20*'Historical Financials'!$C$10 -> 369903.4 | D11: =D20*'Historical Financials'!$D$10 -> 184558.59 | E11: =E20*'Historical Financials'!$E$10 -> 258926.67 | F11: =F20*'Historical Financials'!$F$10 -> 306257.4 | G11: =G20*'Historical Financials'!$G$10 -> 336219.09 | H11: =H20*'Historical Financials'!$H$10 -> 451826.16 | J11: =J20*'Historical Financials'!$J$10 -> 70377.03 | K11: =K20*'Historical Financials'!$K$10 -> 91884.52 | L11: =L20*'Historical Financials'!$L$10 -> 93551.72 | M11: =M20*'Historical Financials'!$M$10 -> 96803.19 | N11: =N20*'Historical Financials'!$N$10 -> 105370.52 | O11: =O20*'Historical Financials'!$O$10 -> 101192.36 | P11: =P20*'Historical Financials'!$P$10 -> 99557.32 | Q11: =Q20*'Historical Financials'!$Q$10 -> 106628.94 | R11: =R20*'Historical Financials'!$R$10 -> 109033.92 | S11: =S20*'Historical Financials'!$S$10 -> 102083.48 | T11: =T20*'Historical Financials'!$T$10 -> 101204 | U11: =U20*'Historical Financials'!$U$10 -> 139504.76 | V11: =V20*'Historical Financials'!$V$10 -> 113934.68 | W11: =W20*'Historical Financials'!$W$10 -> 111538.76 | X11: =X20*'Historical Financials'!$X$10 -> 85728.69 | Z11: =SUM(L11:O11) -> 396917.79 | AA11: =SUM(M11:P11) -> 402923.39 | AB11: =SUM(N11:Q11) -> 412749.14 | AC11: =SUM(O11:R11) -> 416412.54 | AD11: =SUM(P11:S11) -> 417303.66 | AE11: =SUM(Q11:T11) -> 418950.34 | AF11: =SUM(R11:U11) -> 451826.16 | AG11: =SUM(S11:V11) -> 456726.92 | ... AI11: =SUM(U11:X11) -> 450706.89
B12: Accessories and other | C12: =C21*'Historical Financials'!$C$10 -> 221942.04 | D12: =D21*'Historical Financials'!$D$10 -> 246078.12 | E12: =E21*'Historical Financials'!$E$10 -> 258926.67 | F12: =F21*'Historical Financials'!$F$10 -> 306257.4 | G12: =G21*'Historical Financials'!$G$10 -> 336219.09 | H12: =H21*'Historical Financials'!$H$10 -> 225913.08 | J12: =J21*'Historical Financials'!$J$10 -> 70377.03 | K12: =K21*'Historical Financials'!$K$10 -> 68913.39 | L12: =L21*'Historical Financials'!$L$10 -> 70163.79 | M12: =M21*'Historical Financials'!$M$10 -> 96803.19 | N12: =N21*'Historical Financials'!$N$10 -> 79027.89 | O12: =O21*'Historical Financials'!$O$10 -> 75894.27 | P12: =P21*'Historical Financials'!$P$10 -> 74667.99 | Q12: =Q21*'Historical Financials'!$Q$10 -> 106628.94 | R12: =R21*'Historical Financials'!$R$10 -> 54516.96 | S12: =S21*'Historical Financials'!$S$10 -> 51041.74 | T12: =T21*'Historical Financials'!$T$10 -> 50602 | U12: =U21*'Historical Financials'!$U$10 -> 69752.38 | V12: =V21*'Historical Financials'!$V$10 -> 56967.34 | W12: =W21*'Historical Financials'!$W$10 -> 55769.38 | X12: =X21*'Historical Financials'!$X$10 -> 57152.46 | Z12: =SUM(L12:O12) -> 321889.14 | AA12: =SUM(M12:P12) -> 326393.34 | AB12: =SUM(N12:Q12) -> 336219.09 | AC12: =SUM(O12:R12) -> 311708.16 | AD12: =SUM(P12:S12) -> 286855.63 | AE12: =SUM(Q12:T12) -> 262789.64 | AF12: =SUM(R12:U12) -> 225913.08 | AG12: =SUM(S12:V12) -> 228363.46 | ... AI12: =SUM(U12:X12) -> 239641.56
B13: Total Net Revenue | C13: =SUM(C7:C12) -> 7398068 | D13: =SUM(D7:D12) -> 6151953 | E13: =SUM(E7:E12) -> 8630889 | F13: =SUM(F7:F12) -> 10208580 | G13: =SUM(G7:G12) -> 11207303 | H13: =SUM(H7:H12) -> 11295654 | J13: =SUM(J7:J12) -> 2345901 | K13: =SUM(K7:K12) -> 2297113 | L13: =SUM(L7:L12) -> 2338793 | M13: =SUM(M7:M12) -> 3226773 | N13: =SUM(N7:N12) -> 2634263 | O13: =SUM(O7:O12) -> 2529809 | P13: =SUM(P7:P12) -> 2488933 | Q13: =SUM(Q7:Q12) -> 3554298 | ... X13: =SUM(X7:X12) -> 2857623 | Z13: =SUM(Z7:Z12) -> 10729638 | AA13: =SUM(AA7:AA12) -> 10879778 | AB13: =SUM(AB7:AB12) -> 11207303 | AC13: =SUM(AC7:AC12) -> 11298888 | AD13: =SUM(AD7:AD12) -> 11321166 | AE13: =SUM(AE7:AE12) -> 11362333 | AF13: =SUM(AF7:AF12) -> 11295654 | AG13: =SUM(AG7:AG12) -> 11418173 | ... AI13: =SUM(AI7:AI12) -> 11982078
B14: Balance Check | C14: =C13-'Historical Financials'!C11 -> 0 | D14: =D13-'Historical Financials'!D11 -> 0 | E14: =E13-'Historical Financials'!E11 -> 0 | F14: =F13-'Historical Financials'!F11 -> 0 | G14: =G13-'Historical Financials'!G11 -> 0 | H14: =H13-'Historical Financials'!H11 -> 0 | J14: =J13-'Historical Financials'!J11 -> 0 | K14: =K13-'Historical Financials'!K11 -> 0 | L14: =L13-'Historical Financials'!L11 -> 0 | M14: =M13-'Historical Financials'!M11 -> 0 | N14: =N13-'Historical Financials'!N11 -> 0 | O14: =O13-'Historical Financials'!O11 -> 0 | P14: =P13-'Historical Financials'!P11 -> 0 | Q14: =Q13-'Historical Financials'!Q11 -> 0 | ... X14: =X13-'Historical Financials'!X11 -> 0 | Z14: =Z13-'Historical Financials'!AB11 -> 0 | AA14: =AA13-'Historical Financials'!AC11 -> 0 | AB14: =AB13-'Historical Financials'!AD11 -> 0 | AC14: =AC13-'Historical Financials'!AE11 -> 0 | AD14: =AD13-'Historical Financials'!AF11 -> 0 | AE14: =AE13-'Historical Financials'!AG11 -> 0 | AF14: =AF13-'Historical Financials'!AH11 -> 0 | AG14: =AG13-'Historical Financials'!AI11 -> 0 | ... AI14: =AI13-'Historical Financials'!AK11 -> 0
B16: =B7&"(%)" -> Cosmetics(%) | C16: 0.51 | D16: 0.45 | E16: 0.43 | F16: 0.42 | G16: 0.41 | H16: 0.39 | J16: 0.44 | K16: 0.42 | L16: 0.44 | M16: =F16 -> 0.42 | N16: 0.44 | O16: 0.4 | P16: 0.42 | Q16: =G16 -> 0.41 | R16: 0.42 | S16: 0.39 | T16: 0.41 | U16: =H16 -> 0.39 | V16: 0.4 | W16: 0.38 | X16: 0.41 | Z16: =O16 -> 0.4 | AA16: =P16 -> 0.42 | AB16: =Q16 -> 0.41 | AC16: =R16 -> 0.42 | AD16: =S16 -> 0.39 | AE16: =T16 -> 0.41 | AF16: =U16 -> 0.39 | AG16: =V16 -> 0.4 | ... AI16: =X16 -> 0.41
B17: =B8&"(%)" -> Haircare products and styling tools(%) | C17: 0.18 | D17: 0.2 | E17: 0.2 | F17: 0.21 | G17: 0.19 | H17: 0.23 | J17: 0.2 | K17: 0.22 | L17: 0.21 | M17: =F17 -> 0.21 | N17: 0.18 | O17: 0.21 | P17: 0.19 | Q17: =G17 -> 0.19 | R17: 0.19 | S17: 0.2 | T17: 0.2 | U17: =H17 -> 0.23 | V17: 0.25 | W17: 0.25 | X17: 0.19 | Z17: =O17 -> 0.21 | AA17: =P17 -> 0.19 | AB17: =Q17 -> 0.19 | AC17: =R17 -> 0.19 | AD17: =S17 -> 0.2 | AE17: =T17 -> 0.2 | AF17: =U17 -> 0.23 | AG17: =V17 -> 0.25 | ... AI17: =X17 -> 0.19
B18: =B9&"(%)" -> Skincare(%) | C18: 0.14 | D18: 0.16 | E18: 0.17 | F18: 0.17 | G18: 0.19 | H18: 0.19 | J18: 0.18 | K18: 0.17 | L18: 0.16 | M18: =F18 -> 0.17 | N18: 0.19 | O18: 0.2 | P18: 0.19 | Q18: =G18 -> 0.19 | R18: 0.23 | S18: 0.24 | T18: 0.23 | U18: =H18 -> 0.19 | V18: 0.18 | W18: 0.19 | X18: 0.24 | Z18: =O18 -> 0.2 | AA18: =P18 -> 0.19 | AB18: =Q18 -> 0.19 | AC18: =R18 -> 0.23 | AD18: =S18 -> 0.24 | AE18: =T18 -> 0.23 | AF18: =U18 -> 0.19 | AG18: =V18 -> 0.18 | ... AI18: =X18 -> 0.24
B19: =B10&"(%)" -> Fragrance and bath(%) | C19: 0.09 | D19: 0.12 | E19: 0.14 | F19: 0.14 | G19: 0.15 | H19: 0.13 | J19: 0.12 | K19: 0.12 | L19: 0.12 | M19: =F19 -> 0.14 | N19: 0.12 | O19: 0.12 | P19: 0.13 | Q19: =G19 -> 0.15 | R19: 0.1 | S19: 0.11 | T19: 0.1 | U19: =H19 -> 0.13 | V19: 0.11 | W19: 0.12 | X19: 0.11 | Z19: =O19 -> 0.12 | AA19: =P19 -> 0.13 | AB19: =Q19 -> 0.15 | AC19: =R19 -> 0.1 | AD19: =S19 -> 0.11 | AE19: =T19 -> 0.1 | AF19: =U19 -> 0.13 | AG19: =V19 -> 0.11 | ... AI19: =X19 -> 0.11
B20: =B11&"(%)" -> Services(%) | C20: 0.05 | D20: 0.03 | E20: 0.03 | F20: 0.03 | G20: 0.03 | H20: 0.04 | J20: 0.03 | K20: 0.04 | L20: 0.04 | M20: =F20 -> 0.03 | N20: 0.04 | O20: 0.04 | P20: 0.04 | Q20: =G20 -> 0.03 | R20: 0.04 | S20: 0.04 | T20: 0.04 | U20: =H20 -> 0.04 | V20: 0.04 | W20: 0.04 | X20: 0.03 | Z20: =O20 -> 0.04 | AA20: =P20 -> 0.04 | AB20: =Q20 -> 0.03 | AC20: =R20 -> 0.04 | AD20: =S20 -> 0.04 | AE20: =T20 -> 0.04 | AF20: =U20 -> 0.04 | AG20: =V20 -> 0.04 | ... AI20: =X20 -> 0.03
B21: =B12&"(%)" -> Accessories and other(%) | C21: 0.03 | D21: 0.04 | E21: 0.03 | F21: 0.03 | G21: 0.03 | H21: 0.02 | J21: 0.03 | K21: 0.03 | L21: 0.03 | M21: =F21 -> 0.03 | N21: 0.03 | O21: 0.03 | P21: 0.03 | Q21: =G21 -> 0.03 | R21: 0.02 | S21: 0.02 | T21: 0.02 | U21: =H21 -> 0.02 | V21: 0.02 | W21: 0.02 | X21: 0.02 | Z21: =O21 -> 0.03 | AA21: =P21 -> 0.03 | AB21: =Q21 -> 0.03 | AC21: =R21 -> 0.02 | AD21: =S21 -> 0.02 | AE21: =T21 -> 0.02 | AF21: =U21 -> 0.02 | AG21: =V21 -> 0.02 | ... AI21: =X21 -> 0.02

Sheet FCF
B2: ='Historical Financials'!B2 -> Ulta Beauty Inc. (NASDAQ: ULTA) | C2: FYE | F2: FYE | J2: Quarterly | N2: Quarterly | T2: Quarterly | Z2: LTM | AG2: LTM | AM2: Variance
B3: FCF Analysis | C3: ='Historical Financials'!C7 -> 2019 | D3: ='Historical Financials'!D7 -> 2020 | E3: ='Historical Financials'!E7 -> 2021 | F3: ='Historical Financials'!F7 -> 2022 | G3: ='Historical Financials'!G7 -> 2023 | H3: ='Historical Financials'!H7 -> 2024 | J3: ='Historical Financials'!J7 -> 1Q22 | K3: ='Historical Financials'!K7 -> 2Q22 | L3: ='Historical Financials'!L7 -> 3Q22 | M3: ='Historical Financials'!M7 -> 4Q22 | N3: ='Historical Financials'!N7 -> 1Q23 | O3: ='Historical Financials'!O7 -> 2Q23 | P3: ='Historical Financials'!P7 -> 3Q23 | Q3: ='Historical Financials'!Q7 -> 4Q23 | ... X3: ='Historical Financials'!X7 -> 3Q25 | Z3: =M3 -> 4Q22 | AA3: =N3 -> 1Q23 | AB3: =O3 -> 2Q23 | AC3: =P3 -> 3Q23 | AD3: =Q3 -> 4Q23 | AE3: =R3 -> 1Q24 | AF3: =S3 -> 2Q24 | AG3: =T3 -> 3Q24 | ... AK3: =X3 -> 3Q25
B4: ($ In Millions) | C4: ='Historical Financials'!C8 -> 43862 | D4: ='Historical Financials'!D8 -> 44226 | E4: ='Historical Financials'!E8 -> 44590 | F4: ='Historical Financials'!F8 -> 44954 | G4: ='Historical Financials'!G8 -> 45325 | H4: ='Historical Financials'!H8 -> 45689 | J4: ='Historical Financials'!J8 -> 44681 | K4: ='Historical Financials'!K8 -> 44772 | L4: ='Historical Financials'!L8 -> 44863 | M4: ='Historical Financials'!M8 -> 44954 | N4: ='Historical Financials'!N8 -> 45045 | O4: ='Historical Financials'!O8 -> 45136 | P4: ='Historical Financials'!P8 -> 45227 | Q4: ='Historical Financials'!Q8 -> 45325 | ... X4: ='Historical Financials'!X8 -> 45962 | Z4: =M4 -> 44954 | AA4: =N4 -> 45045 | AB4: =O4 -> 45136 | AC4: =P4 -> 45227 | AD4: =Q4 -> 45325 | AE4: =R4 -> 45416 | AF4: =S4 -> 45507 | AG4: =T4 -> 45598 | ... AK4: =X4 -> 45962
B6: ='Revenue Drivers'!B7 -> Cosmetics | C6: ='Revenue Drivers'!C7/1000 -> 3773.0147 | D6: ='Revenue Drivers'!D7/1000 -> 2768.3789 | E6: ='Revenue Drivers'!E7/1000 -> 3711.2823 | F6: ='Revenue Drivers'!F7/1000 -> 4287.6036 | G6: ='Revenue Drivers'!G7/1000 -> 4594.9942 | H6: ='Revenue Drivers'!H7/1000 -> 4405.3051 | J6: ='Revenue Drivers'!J7/1000 -> 1032.1964 | K6: ='Revenue Drivers'!K7/1000 -> 964.78746 | L6: ='Revenue Drivers'!L7/1000 -> 1029.0689 | M6: ='Revenue Drivers'!M7/1000 -> 1355.2447 | N6: ='Revenue Drivers'!N7/1000 -> 1159.0757 | O6: ='Revenue Drivers'!O7/1000 -> 1011.9236 | P6: ='Revenue Drivers'!P7/1000 -> 1045.3519 | Q6: ='Revenue Drivers'!Q7/1000 -> 1457.2622 | ... X6: ='Revenue Drivers'!X7/1000 -> 1171.6254 | Z6: =SUM(J6:M6) -> 4381.2975 | AA6: =SUM(K6:N6) -> 4508.1768 | AB6: =SUM(L6:O6) -> 4555.3129 | AC6: =SUM(M6:P6) -> 4571.5958 | AD6: =SUM(N6:Q6) -> 4673.6134 | AE6: =SUM(O6:R6) -> 4659.3938 | AF6: =SUM(P6:S6) -> 4642.7841 | AG6: =SUM(Q6:T6) -> 4634.7733 | ... AK6: =SUM(U6:X6) -> 4730.7619 | AM6: =SUM(AK6/AG6)-1 -> 0.020710526
B7: ='Revenue Drivers'!B8 -> Haircare products and styling tools | C7: ='Revenue Drivers'!C8/1000 -> 1331.6522 | D7: ='Revenue Drivers'!D8/1000 -> 1230.3906 | E7: ='Revenue Drivers'!E8/1000 -> 1726.1778 | F7: ='Revenue Drivers'!F8/1000 -> 2143.8018 | G7: ='Revenue Drivers'!G8/1000 -> 2129.3876 | H7: ='Revenue Drivers'!H8/1000 -> 2598.0004 | J7: ='Revenue Drivers'!J8/1000 -> 469.1802 | K7: ='Revenue Drivers'!K8/1000 -> 505.36486 | L7: ='Revenue Drivers'!L8/1000 -> 491.14653 | M7: ='Revenue Drivers'!M8/1000 -> 677.62233 | N7: ='Revenue Drivers'!N8/1000 -> 474.16734 | O7: ='Revenue Drivers'!O8/1000 -> 531.25989 | P7: ='Revenue Drivers'!P8/1000 -> 472.89727 | Q7: ='Revenue Drivers'!Q8/1000 -> 675.31662 | ... X7: ='Revenue Drivers'!X8/1000 -> 542.94837 | Z7: =SUM(J7:M7) -> 2143.3139 | AA7: =SUM(K7:N7) -> 2148.3011 | AB7: =SUM(L7:O7) -> 2174.1961 | AC7: =SUM(M7:P7) -> 2155.9468 | AD7: =SUM(N7:Q7) -> 2153.6411 | AE7: =SUM(O7:R7) -> 2197.3849 | AF7: =SUM(P7:S7) -> 2176.5424 | AG7: =SUM(Q7:T7) -> 2209.6651 | ... AK7: =SUM(U7:X7) -> 2754.3097 | AM7: =SUM(AK7/AG7)-1 -> 0.24648287
B8: ='Revenue Drivers'!B9 -> Skincare | C8: ='Revenue Drivers'!C9/1000 -> 1035.7295 | D8: ='Revenue Drivers'!D9/1000 -> 984.31248 | E8: ='Revenue Drivers'!E9/1000 -> 1467.2511 | F8: ='Revenue Drivers'!F9/1000 -> 1735.4586 | G8: ='Revenue Drivers'!G9/1000 -> 2129.3876 | H8: ='Revenue Drivers'!H9/1000 -> 2146.1743 | J8: ='Revenue Drivers'!J9/1000 -> 422.26218 | K8: ='Revenue Drivers'!K9/1000 -> 390.50921 | L8: ='Revenue Drivers'!L9/1000 -> 374.20688 | M8: ='Revenue Drivers'!M9/1000 -> 548.55141 | N8: ='Revenue Drivers'!N9/1000 -> 500.50997 | O8: ='Revenue Drivers'!O9/1000 -> 505.9618 | P8: ='Revenue Drivers'!P9/1000 -> 472.89727 | Q8: ='Revenue Drivers'!Q9/1000 -> 675.31662 | ... X8: ='Revenue Drivers'!X9/1000 -> 685.82952 | Z8: =SUM(J8:M8) -> 1735.5297 | AA8: =SUM(K8:N8) -> 1813.7775 | AB8: =SUM(L8:O8) -> 1929.2301 | AC8: =SUM(M8:P8) -> 2027.9205 | AD8: =SUM(N8:Q8) -> 2154.6857 | AE8: =SUM(O8:R8) -> 2281.1207 | AF8: =SUM(P8:S8) -> 2387.6598 | AG8: =SUM(Q8:T8) -> 2496.6855 | ... AK8: =SUM(U8:X8) -> 2390.9923 | AM8: =SUM(AK8/AG8)-1 -> -0.042333421
B9: ='Revenue Drivers'!B10 -> Fragrance and bath | C9: ='Revenue Drivers'!C10/1000 -> 665.82612 | D9: ='Revenue Drivers'!D10/1000 -> 738.23436 | E9: ='Revenue Drivers'!E10/1000 -> 1208.3245 | F9: ='Revenue Drivers'!F10/1000 -> 1429.2012 | G9: ='Revenue Drivers'!G10/1000 -> 1681.0954 | H9: ='Revenue Drivers'!H10/1000 -> 1468.435 | J9: ='Revenue Drivers'!J10/1000 -> 281.50812 | K9: ='Revenue Drivers'!K10/1000 -> 275.65356 | L9: ='Revenue Drivers'!L10/1000 -> 280.65516 | M9: ='Revenue Drivers'!M10/1000 -> 451.74822 | N9: ='Revenue Drivers'!N10/1000 -> 316.11156 | O9: ='Revenue Drivers'!O10/1000 -> 303.57708 | P9: ='Revenue Drivers'!P10/1000 -> 323.56129 | Q9: ='Revenue Drivers'!Q10/1000 -> 533.1447 | ... X9: ='Revenue Drivers'!X10/1000 -> 314.33853 | Z9: =SUM(J9:M9) -> 1289.5651 | AA9: =SUM(K9:N9) -> 1324.1685 | AB9: =SUM(L9:O9) -> 1352.092 | AC9: =SUM(M9:P9) -> 1394.9982 | AD9: =SUM(N9:Q9) -> 1476.3946 | AE9: =SUM(O9:R9) -> 1432.8679 | AF9: =SUM(P9:S9) -> 1410.0204 | AG9: =SUM(Q9:T9) -> 1339.4691 | ... AK9: =SUM(U9:X9) -> 1415.6656 | AM9: =SUM(AK9/AG9)-1 -> 0.056885658
B10: ='Revenue Drivers'!B11 -> Services | C10: ='Revenue Drivers'!C11/1000 -> 369.9034 | D10: ='Revenue Drivers'!D11/1000 -> 184.55859 | E10: ='Revenue Drivers'!E11/1000 -> 258.92667 | F10: ='Revenue Drivers'!F11/1000 -> 306.2574 | G10: ='Revenue Drivers'!G11/1000 -> 336.21909 | H10: ='Revenue Drivers'!H11/1000 -> 451.82616 | J10: ='Revenue Drivers'!J11/1000 -> 70.37703 | K10: ='Revenue Drivers'!K11/1000 -> 91.88452 | L10: ='Revenue Drivers'!L11/1000 -> 93.55172 | M10: ='Revenue Drivers'!M11/1000 -> 96.80319 | N10: ='Revenue Drivers'!N11/1000 -> 105.37052 | O10: ='Revenue Drivers'!O11/1000 -> 101.19236 | P10: ='Revenue Drivers'!P11/1000 -> 99.55732 | Q10: ='Revenue Drivers'!Q11/1000 -> 106.62894 | ... X10: ='Revenue Drivers'!X11/1000 -> 85.72869 | Z10: =SUM(J10:M10) -> 352.61646 | AA10: =SUM(K10:N10) -> 387.60995 | AB10: =SUM(L10:O10) -> 396.91779 | AC10: =SUM(M10:P10) -> 402.92339 | AD10: =SUM(N10:Q10) -> 412.74914 | AE10: =SUM(O10:R10) -> 416.41254 | AF10: =SUM(P10:S10) -> 417.30366 | AG10: =SUM(Q10:T10) -> 418.95034 | ... AK10: =SUM(U10:X10) -> 450.70689 | AM10: =SUM(AK10/AG10)-1 -> 0.075800273
B11: ='Revenue Drivers'!B12 -> Accessories and other | C11: ='Revenue Drivers'!C12/1000 -> 221.94204 | D11: ='Revenue Drivers'!D12/1000 -> 246.07812 | E11: ='Revenue Drivers'!E12/1000 -> 258.92667 | F11: ='Revenue Drivers'!F12/1000 -> 306.2574 | G11: ='Revenue Drivers'!G12/1000 -> 336.21909 | H11: ='Revenue Drivers'!H12/1000 -> 225.91308 | J11: ='Revenue Drivers'!J12/1000 -> 70.37703 | K11: ='Revenue Drivers'!K12/1000 -> 68.91339 | L11: ='Revenue Drivers'!L12/1000 -> 70.16379 | M11: ='Revenue Drivers'!M12/1000 -> 96.80319 | N11: ='Revenue Drivers'!N12/1000 -> 79.02789 | O11: ='Revenue Drivers'!O12/1000 -> 75.89427 | P11: ='Revenue Drivers'!P12/1000 -> 74.66799 | Q11: ='Revenue Drivers'!Q12/1000 -> 106.62894 | ... X11: ='Revenue Drivers'!X12/1000 -> 57.15246 | Z11: =SUM(J11:M11) -> 306.2574 | AA11: =SUM(K11:N11) -> 314.90826 | AB11: =SUM(L11:O11) -> 321.88914 | AC11: =SUM(M11:P11) -> 326.39334 | AD11: =SUM(N11:Q11) -> 336.21909 | AE11: =SUM(O11:R11) -> 311.70816 | AF11: =SUM(P11:S11) -> 286.85563 | AG11: =SUM(Q11:T11) -> 262.78964 | ... AK11: =SUM(U11:X11) -> 239.64156 | AM11: =SUM(AK11/AG11)-1 -> -0.088085969
B12: Total Revenue | C12: =SUM(C6:C11) -> 7398.068 | D12: =SUM(D6:D11) -> 6151.953 | E12: =SUM(E6:E11) -> 8630.889 | F12: =SUM(F6:F11) -> 10208.58 | G12: =SUM(G6:G11) -> 11207.303 | H12: =SUM(H6:H11) -> 11295.654 | J12: =SUM(J6:J11) -> 2345.901 | K12: =SUM(K6:K11) -> 2297.113 | L12: =SUM(L6:L11) -> 2338.793 | M12: =SUM(M6:M11) -> 3226.773 | N12: =SUM(N6:N11) -> 2634.263 | O12: =SUM(O6:O11) -> 2529.809 | P12: =SUM(P6:P11) -> 2488.933 | Q12: =SUM(Q6:Q11) -> 3554.298 | ... X12: =SUM(X6:X11) -> 2857.623 | Z12: =SUM(Z6:Z11) -> 10208.58 | AA12: =SUM(AA6:AA11) -> 10496.942 | AB12: =SUM(AB6:AB11) -> 10729.638 | AC12: =SUM(AC6:AC11) -> 10879.778 | AD12: =SUM(AD6:AD11) -> 11207.303 | AE12: =SUM(AE6:AE11) -> 11298.888 | AF12: =SUM(AF6:AF11) -> 11321.166 | AG12: =SUM(AG6:AG11) -> 11362.333 | ... AK12: =SUM(AK6:AK11) -> 11982.078 | AM12: =SUM(AK12/AG12)-1 -> 0.054543816
B13: Y/Y Growth (%) | D13: =SUM(D12/C12)-1 -> -0.16843789 | E13: =SUM(E12/D12)-1 -> 0.40295106 | F13: =SUM(F12/E12)-1 -> 0.18279589 | G13: =SUM(G12/F12)-1 -> 0.097831726 | H13: =SUM(H12/G12)-1 -> 0.0078833418 | N13: =SUM(N12/J12)-1 -> 0.12292164 | O13: =SUM(O12/K12)-1 -> 0.10129933 | P13: =SUM(P12/L12)-1 -> 0.064195506 | Q13: =SUM(Q12/M12)-1 -> 0.10150234 | R13: =SUM(R12/N12)-1 -> 0.03476684 | S13: =SUM(S12/O12)-1 -> 0.0088061984 | T13: =SUM(T12/P12)-1 -> 0.016540019 | U13: =SUM(U12/Q12)-1 -> -0.018760104 | ... X13: =SUM(X12/T12)-1 -> 0.12945061 | Z13: =SUM(Z12/W12)-1 -> 2.6609982 | AA13: =SUM(AA12/X12)-1 -> 2.6733124 | AB13: =SUM(AB12/Y12)-1 -> #DIV/0! | AC13: =SUM(AC12/#REF!)-1 -> #REF! | AD13: =SUM(AD12/Z12)-1 -> 0.097831726 | AE13: =SUM(AE12/AA12)-1 -> 0.07639806 | AF13: =SUM(AF12/AB12)-1 -> 0.055130285 | AG13: =SUM(AG12/AC12)-1 -> 0.044353387 | AH13: =SUM(AH12/AD12)-1 -> 0.0078833418 | AI13: =SUM(AI12/AE12)-1 -> 0.010557234 | AJ13: =SUM(AJ12/AF12)-1 -> 0.029448292 | AK13: =SUM(AK12/AG12)-1 -> 0.054543816 | AM13: =SUM(AK13-AG13)*10000 -> 101.90429
B14: Q/Q Growth (%) | C14: N/A | D14: N/A | E14: N/A | F14: N/A | G14: N/A | H14: N/A | K14: =SUM(K12/J12)-1 -> -0.020797127 | L14: =SUM(L12/K12)-1 -> 0.018144514 | M14: =SUM(M12/L12)-1 -> 0.37967447 | N14: =SUM(N12/M12)-1 -> -0.18362308 | O14: =SUM(O12/N12)-1 -> -0.039652077 | P14: =SUM(P12/O12)-1 -> -0.016157742 | Q14: =SUM(Q12/P12)-1 -> 0.42804085 | R14: =SUM(R12/Q12)-1 -> -0.233084 | ... X14: =SUM(X12/W12)-1 -> 0.024799989 | Z14: N/A | AA14: N/A | AB14: N/A | AC14: N/A | AD14: N/A | AE14: N/A | AF14: N/A | AG14: N/A | AH14: N/A | AI14: N/A | AJ14: N/A | AK14: N/A
B16: (-) Cost of Revenues | C16: ='Historical Financials'!C13/1000 -> -4717.004 | D16: ='Historical Financials'!D13/1000 -> -4202.794 | E16: ='Historical Financials'!E13/1000 -> -5262.335 | F16: ='Historical Financials'!F13/1000 -> -6164.07 | G16: ='Historical Financials'!G13/1000 -> -6826.203 | H16: ='Historical Financials'!H13/1000 -> -6908.401 | J16: ='Historical Financials'!J13/1000 -> -1404.875 | K16: ='Historical Financials'!K13/1000 -> -1368.949 | L16: ='Historical Financials'!L13/1000 -> -1375.976 | M16: ='Historical Financials'!M13/1000 -> -2014.27 | N16: ='Historical Financials'!N13/1000 -> -1579.406 | O16: ='Historical Financials'!O13/1000 -> -1536.197 | P16: ='Historical Financials'!P13/1000 -> -1496.866 | Q16: ='Historical Financials'!Q13/1000 -> -2213.734 | ... X16: ='Historical Financials'!X13/1000 -> -1701.958 | Z16: =SUM(J16:M16) -> -6164.07 | AA16: =SUM(K16:N16) -> -6338.601 | AB16: =SUM(L16:O16) -> -6505.849 | AC16: =SUM(M16:P16) -> -6626.739 | AD16: =SUM(N16:Q16) -> -6826.203 | AE16: =SUM(O16:R16) -> -6902.865 | AF16: =SUM(P16:S16) -> -6940.578 | AG16: =SUM(Q16:T16) -> -6968.168 | ... AK16: =SUM(U16:X16) -> -7286.846 | AM16: =SUM(AK16/AG16)-1 -> 0.045733398
B17: Gross Profit | C17: =SUM(C12+SUM(C16:C16)) -> 2681.064 | D17: =SUM(D12+SUM(D16:D16)) -> 1949.159 | E17: =SUM(E12+SUM(E16:E16)) -> 3368.554 | F17: =SUM(F12+SUM(F16:F16)) -> 4044.51 | G17: =SUM(G12+SUM(G16:G16)) -> 4381.1 | H17: =SUM(H12+SUM(H16:H16)) -> 4387.253 | J17: =SUM(J12+SUM(J16:J16)) -> 941.026 | K17: =SUM(K12+SUM(K16:K16)) -> 928.164 | L17: =SUM(L12+SUM(L16:L16)) -> 962.817 | M17: =SUM(M12+SUM(M16:M16)) -> 1212.503 | N17: =SUM(N12+SUM(N16:N16)) -> 1054.857 | O17: =SUM(O12+SUM(O16:O16)) -> 993.612 | P17: =SUM(P12+SUM(P16:P16)) -> 992.067 | Q17: =SUM(Q12+SUM(Q16:Q16)) -> 1340.564 | ... X17: =SUM(X12+SUM(X16:X16)) -> 1155.665 | Z17: =SUM(Z12+SUM(Z16:Z16)) -> 4044.51 | AA17: =SUM(AA12+SUM(AA16:AA16)) -> 4158.341 | AB17: =SUM(AB12+SUM(AB16:AB16)) -> 4223.789 | AC17: =SUM(AC12+SUM(AC16:AC16)) -> 4253.039 | AD17: =SUM(AD12+SUM(AD16:AD16)) -> 4381.1 | AE17: =SUM(AE12+SUM(AE16:AE16)) -> 4396.023 | AF17: =SUM(AF12+SUM(AF16:AF16)) -> 4380.588 | AG17: =SUM(AG12+SUM(AG16:AG16)) -> 4394.165 | ... AK17: =SUM(AK12+SUM(AK16:AK16)) -> 4695.232 | AM17: =SUM(AK17/AG17)-1 -> 0.068515179
B18: Gross Margin (%) | C18: =C17/C12 -> 0.36240056 | D18: =D17/D12 -> 0.31683581 | E18: =E17/E12 -> 0.3902905 | F18: =F17/F12 -> 0.39618732 | G18: =G17/G12 -> 0.39091475 | H18: =H17/H12 -> 0.38840186 | J18: =J17/J12 -> 0.40113628 | K18: =K17/K12 -> 0.40405674 | L18: =L17/L12 -> 0.4116726 | M18: =M17/M12 -> 0.37576334 | N18: =N17/N12 -> 0.40043724 | O18: =O17/O12 -> 0.39276167 | P18: =P17/P12 -> 0.39859128 | Q18: =Q17/Q12 -> 0.37716702 | ... X18: =X17/X12 -> 0.40441479 | Z18: =Z17/Z12 -> 0.39618732 | AA18: =AA17/AA12 -> 0.39614785 | AB18: =AB17/AB12 -> 0.39365624 | AC18: =AC17/AC12 -> 0.3909123 | AD18: =AD17/AD12 -> 0.39091475 | AE18: =AE17/AE12 -> 0.38906687 | AF18: =AF17/AF12 -> 0.38693788 | AG18: =AG17/AG12 -> 0.38673088 | ... AK18: =AK17/AK12 -> 0.39185457 | AM18: =SUM(AK18-AG18)*10000 -> 51.236916
B20: (-) Selling, general and administrative expenses | C20: ='Historical Financials'!C17/1000 -> -1760.716 | D20: ='Historical Financials'!D17/1000 -> -1583.017 | E20: ='Historical Financials'!E17/1000 -> -2061.545 | F20: ='Historical Financials'!F17/1000 -> -2395.299 | G20: ='Historical Financials'!G17/1000 -> -2694.561 | H20: ='Historical Financials'!H17/1000 -> -2808.592 | J20: ='Historical Financials'!J17/1000 -> -500.97 | K20: ='Historical Financials'!K17/1000 -> -534.459 | L20: ='Historical Financials'!L17/1000 -> -597.164 | M20: ='Historical Financials'!M17/1000 -> -762.706 | N20: ='Historical Financials'!N17/1000 -> -612.129 | O20: ='Historical Financials'!O17/1000 -> -600.692 | P20: ='Historical Financials'!P17/1000 -> -661.38 | Q20: ='Historical Financials'!Q17/1000 -> -820.36 | ... X20: ='Historical Financials'!X17/1000 -> -840.92 | Z20: =SUM(J20:M20) -> -2395.299 | AA20: =SUM(K20:N20) -> -2506.458 | AB20: =SUM(L20:O20) -> -2572.691 | AC20: =SUM(M20:P20) -> -2636.907 | AD20: =SUM(N20:Q20) -> -2694.561 | AE20: =SUM(O20:R20) -> -2748.345 | AF20: =SUM(P20:S20) -> -2792.474 | AG20: =SUM(Q20:T20) -> -2813.353 | ... AK20: =SUM(U20:X20) -> -3108.869 | AM20: =SUM(AK20/AG20)-1 -> 0.1050405
B21: (-) Pre-opening expenses | C21: ='Historical Financials'!C18/1000 -> -19.254 | D21: ='Historical Financials'!D18/1000 -> -15 | E21: ='Historical Financials'!E18/1000 -> -9.517 | F21: ='Historical Financials'!F18/1000 -> -10.601 | G21: ='Historical Financials'!G18/1000 -> -8.51 | H21: ='Historical Financials'!H18/1000 -> -13.689 | J21: ='Historical Financials'!J18/1000 -> -2.348 | K21: ='Historical Financials'!K18/1000 -> -2.277 | L21: ='Historical Financials'!L18/1000 -> -3.797 | M21: ='Historical Financials'!M18/1000 -> -2.179 | N21: ='Historical Financials'!N18/1000 -> -0.658 | O21: ='Historical Financials'!O18/1000 -> -1.278 | P21: ='Historical Financials'!P18/1000 -> -3.46 | Q21: ='Historical Financials'!Q18/1000 -> -3.114 | ... X21: ='Historical Financials'!X18/1000 -> -5.326 | Z21: =SUM(J21:M21) -> -10.601 | AA21: =SUM(K21:N21) -> -8.911 | AB21: =SUM(L21:O21) -> -7.912 | AC21: =SUM(M21:P21) -> -7.575 | AD21: =SUM(N21:Q21) -> -8.51 | AE21: =SUM(O21:R21) -> -10.771 | AF21: =SUM(P21:S21) -> -13.648 | AG21: =SUM(Q21:T21) -> -15.071 | ... AK21: =SUM(U21:X21) -> -13.992
B22: (-) Impairment, restructuring and other costs | C22: ='Historical Financials'!C19/1000 -> 0 | D22: ='Historical Financials'!D19/1000 -> -114.322 | E22: ='Historical Financials'!E19/1000 -> 0 | F22: ='Historical Financials'!F19/1000 -> 0 | G22: ='Historical Financials'!G19/1000 -> 0 | H22: ='Historical Financials'!H19/1000 -> 0 | J22: ='Historical Financials'!J19/1000 -> 0 | K22: ='Historical Financials'!K19/1000 -> 0 | L22: ='Historical Financials'!L19/1000 -> 0 | M22: ='Historical Financials'!M19/1000 -> 0 | N22: ='Historical Financials'!N19/1000 -> 0 | O22: ='Historical Financials'!O19/1000 -> 0 | P22: ='Historical Financials'!P19/1000 -> 0 | Q22: ='Historical Financials'!Q19/1000 -> 0 | ... X22: ='Historical Financials'!X19/1000 -> 0 | Z22: =SUM(J22:M22) -> 0 | AA22: =SUM(K22:N22) -> 0 | AB22: =SUM(L22:O22) -> 0 | AC22: =SUM(M22:P22) -> 0 | AD22: =SUM(N22:Q22) -> 0 | AE22: =SUM(O22:R22) -> 0 | AF22: =SUM(P22:S22) -> 0 | AG22: =SUM(Q22:T22) -> 0 | ... AK22: =SUM(U22:X22) -> 0 | AM22: =SUM(AK22/AG22)-1 -> #DIV/0!
B23: Earning before Interest & Taxes (EBIT) | C23: =SUM(C17+SUM(C20:C22)) -> 901.094 | D23: =SUM(D17+SUM(D20:D22)) -> 236.82 | E23: =SUM(E17+SUM(E20:E22)) -> 1297.492 | F23: =SUM(F17+SUM(F20:F22)) -> 1638.61 | G23: =SUM(G17+SUM(G20:G22)) -> 1678.029 | H23: =SUM(H17+SUM(H20:H22)) -> 1564.972 | J23: =SUM(J17+SUM(J20:J22)) -> 437.708 | K23: =SUM(K17+SUM(K20:K22)) -> 391.428 | L23: =SUM(L17+SUM(L20:L22)) -> 361.856 | M23: =SUM(M17+SUM(M20:M22)) -> 447.618 | N23: =SUM(N17+SUM(N20:N22)) -> 442.07 | O23: =SUM(O17+SUM(O20:O22)) -> 391.642 | P23: =SUM(P17+SUM(P20:P22)) -> 327.227 | Q23: =SUM(Q17+SUM(Q20:Q22)) -> 517.09 | ... X23: =SUM(X17+SUM(X20:X22)) -> 309.419 | Z23: =SUM(Z17+SUM(Z20:Z22)) -> 1638.61 | AA23: =SUM(AA17+SUM(AA20:AA22)) -> 1642.972 | AB23: =SUM(AB17+SUM(AB20:AB22)) -> 1643.186 | AC23: =SUM(AC17+SUM(AC20:AC22)) -> 1608.557 | AD23: =SUM(AD17+SUM(AD20:AD22)) -> 1678.029 | AE23: =SUM(AE17+SUM(AE20:AE22)) -> 1636.907 | AF23: =SUM(AF17+SUM(AF20:AF22)) -> 1574.466 | AG23: =SUM(AG17+SUM(AG20:AG22)) -> 1565.741 | ... AK23: =SUM(AK17+SUM(AK20:AK22)) -> 1572.371 | AM23: =SUM(AK23/AG23)-1 -> 0.0042344168
B24: Operating Margin (%) | C24: =C23/C12 -> 0.12180126 | D24: =D23/D12 -> 0.038495093 | E24: =E23/E12 -> 0.15033121 | F24: =F23/F12 -> 0.16051302 | G24: =G23/G12 -> 0.14972639 | H24: =H23/H12 -> 0.13854638 | J24: =J23/J12 -> 0.18658417 | K24: =K23/K12 -> 0.17039998 | L24: =L23/L12 -> 0.15471912 | M24: =M23/M12 -> 0.13872002 | N24: =N23/N12 -> 0.16781544 | O24: =O23/O12 -> 0.1548109 | P24: =P23/P12 -> 0.1314728 | Q24: =Q23/Q12 -> 0.14548302 | ... X24: =X23/X12 -> 0.10827845 | Z24: =Z23/Z12 -> 0.16051302 | AA24: =AA23/AA12 -> 0.15651911 | AB24: =AB23/AB12 -> 0.15314459 | AC24: =AC23/AC12 -> 0.14784833 | AD24: =AD23/AD12 -> 0.14972639 | AE24: =AE23/AE12 -> 0.14487328 | AF24: =AF23/AF12 -> 0.13907278 | AG24: =AG23/AG12 -> 0.13780101 | ... AK24: =AK23/AK12 -> 0.1312269 | AM24: =SUM(AK24-AG24)*10000 -> -65.741092
B26: (+) Depreciation and Amortization | C26: ='Historical Financials'!C94/1000 -> 295.599 | D26: ='Historical Financials'!D94/1000 -> 297.772 | E26: ='Historical Financials'!E94/1000 -> 268.46 | F26: ='Historical Financials'!F94/1000 -> 241.372 | G26: ='Historical Financials'!G94/1000 -> 243.84 | H26: ='Historical Financials'!H94/1000 -> 267.042 | J26: ='Historical Financials'!J94/1000 -> 62.839 | K26: ='Historical Financials'!K94/1000 -> 60.882 | L26: ='Historical Financials'!L94/1000 -> 58.461 | M26: ='Historical Financials'!M94/1000 -> 59.19 | N26: ='Historical Financials'!N94/1000 -> 57.949 | O26: ='Historical Financials'!O94/1000 -> 61.913 | P26: ='Historical Financials'!P94/1000 -> 61.411 | Q26: ='Historical Financials'!Q94/1000 -> 62.567 | ... X26: ='Historical Financials'!X94/1000 -> 75.787 | Z26: =SUM(J26:M26) -> 241.372 | AA26: =SUM(K26:N26) -> 236.482 | AB26: =SUM(L26:O26) -> 237.513 | AC26: =SUM(M26:P26) -> 240.463 | AD26: =SUM(N26:Q26) -> 243.84 | AE26: =SUM(O26:R26) -> 250.63 | AF26: =SUM(P26:S26) -> 254.031 | AG26: =SUM(Q26:T26) -> 259.642 | ... AK26: =SUM(U26:X26) -> 288.952 | AM26: =SUM(AK26/AG26)-1 -> 0.1128862
B27: EBITDA | C27: =SUM(C23+SUM(C26:C26)) -> 1196.693 | D27: =SUM(D23+SUM(D26:D26)) -> 534.592 | E27: =SUM(E23+SUM(E26:E26)) -> 1565.952 | F27: =SUM(F23+SUM(F26:F26)) -> 1879.982 | G27: =SUM(G23+SUM(G26:G26)) -> 1921.869 | H27: =SUM(H23+SUM(H26:H26)) -> 1832.014 | J27: =SUM(J23+SUM(J26:J26)) -> 500.547 | K27: =SUM(K23+SUM(K26:K26)) -> 452.31 | L27: =SUM(L23+SUM(L26:L26)) -> 420.317 | M27: =SUM(M23+SUM(M26:M26)) -> 506.808 | N27: =SUM(N23+SUM(N26:N26)) -> 500.019 | O27: =SUM(O23+SUM(O26:O26)) -> 453.555 | P27: =SUM(P23+SUM(P26:P26)) -> 388.638 | Q27: =SUM(Q23+SUM(Q26:Q26)) -> 579.657 | ... X27: =SUM(X23+SUM(X26:X26)) -> 385.206 | Z27: =SUM(Z23+SUM(Z26:Z26)) -> 1879.982 | AA27: =SUM(AA23+SUM(AA26:AA26)) -> 1879.454 | AB27: =SUM(AB23+SUM(AB26:AB26)) -> 1880.699 | AC27: =SUM(AC23+SUM(AC26:AC26)) -> 1849.02 | AD27: =SUM(AD23+SUM(AD26:AD26)) -> 1921.869 | AE27: =SUM(AE23+SUM(AE26:AE26)) -> 1887.537 | AF27: =SUM(AF23+SUM(AF26:AF26)) -> 1828.497 | AG27: =SUM(AG23+SUM(AG26:AG26)) -> 1825.383 | ... AK27: =SUM(AK23+SUM(AK26:AK26)) -> 1861.323 | AM27: =SUM(AK27/AG27)-1 -> 0.019689019
B28: EBITDA Margin (%) | C28: =C27/C12 -> 0.1617575 | D28: =D27/D12 -> 0.086897933 | E28: =E27/E12 -> 0.18143577 | F28: =F27/F12 -> 0.18415705 | G28: =G27/G12 -> 0.17148363 | H28: =H27/H12 -> 0.16218751 | J28: =J27/J12 -> 0.2133709 | K28: =K27/K12 -> 0.19690368 | L28: =L27/L12 -> 0.17971535 | M28: =M27/M12 -> 0.15706342 | N28: =N27/N12 -> 0.18981362 | O28: =O27/O12 -> 0.17928429 | P28: =P27/P12 -> 0.15614643 | Q28: =Q27/Q12 -> 0.16308621 | ... X28: =X27/X12 -> 0.13479945 | Z28: =Z27/Z12 -> 0.18415705 | AA28: =AA27/AA12 -> 0.17904776 | AB28: =AB27/AB12 -> 0.17528075 | AC28: =AC27/AC12 -> 0.16995016 | AD28: =AD27/AD12 -> 0.17148363 | AE28: =AE27/AE12 -> 0.16705511 | AF28: =AF27/AF12 -> 0.16151137 | AG28: =AG27/AG12 -> 0.16065213 | ... AK28: =AK27/AK12 -> 0.15534225 | AM28: =SUM(AK28-AG28)*10000 -> -53.098765
B30: (+) Share-Based Compensation (SBC) | C30: ='Historical Financials'!C97/1000 -> 25.045 | D30: ='Historical Financials'!D97/1000 -> 27.583 | E30: ='Historical Financials'!E97/1000 -> 47.259 | F30: ='Historical Financials'!F97/1000 -> 43.044 | G30: ='Historical Financials'!G97/1000 -> 48.246 | H30: ='Historical Financials'!H97/1000 -> 42.787 | J30: ='Historical Financials'!J97/1000 -> 10.356 | K30: ='Historical Financials'!K97/1000 -> 12.519 | L30: ='Historical Financials'!L97/1000 -> 9.679 | M30: ='Historical Financials'!M97/1000 -> 10.49 | N30: ='Historical Financials'!N97/1000 -> 9.721 | O30: ='Historical Financials'!O97/1000 -> 11.818 | P30: ='Historical Financials'!P97/1000 -> 11.938 | Q30: ='Historical Financials'!Q97/1000 -> 14.769 | ... X30: ='Historical Financials'!X97/1000 -> 9.986 | Z30: =SUM(J30:M30) -> 43.044 | AA30: =SUM(K30:N30) -> 42.409 | AB30: =SUM(L30:O30) -> 41.708 | AC30: =SUM(M30:P30) -> 43.967 | AD30: =SUM(N30:Q30) -> 48.246 | AE30: =SUM(O30:R30) -> 48.607 | AF30: =SUM(P30:S30) -> 45.979 | AG30: =SUM(Q30:T30) -> 42.46 | ... AK30: =SUM(U30:X30) -> 45.42 | AM30: =SUM(AK30/AG30)-1 -> 0.069712671
B31: (+) Impairment, restructuring and other costs | C31: =-C22 -> 0 | D31: =-D22 -> 114.322 | E31: =-E22 -> 0 | F31: =-F22 -> 0 | G31: =-G22 -> 0 | H31: =-H22 -> 0 | J31: =-J22 -> 0 | K31: =-K22 -> 0 | L31: =-L22 -> 0 | M31: =-M22 -> 0 | N31: =-N22 -> 0 | O31: =-O22 -> 0 | P31: =-P22 -> 0 | Q31: =-Q22 -> 0 | ... X31: =-X22 -> 0 | Z31: =SUM(J31:M31) -> 0 | AA31: =SUM(K31:N31) -> 0 | AB31: =SUM(L31:O31) -> 0 | AC31: =SUM(M31:P31) -> 0 | AD31: =SUM(N31:Q31) -> 0 | AE31: =SUM(O31:R31) -> 0 | AF31: =SUM(P31:S31) -> 0 | AG31: =SUM(Q31:T31) -> 0 | ... AK31: =SUM(U31:X31) -> 0 | AM31: =SUM(AK31/AG31)-1 -> #DIV/0!
B32: Adj. EBITDA | C32: =SUM(C27+SUM(C30:C31)) -> 1221.738 | D32: =SUM(D27+SUM(D30:D31)) -> 676.497 | E32: =SUM(E27+SUM(E30:E31)) -> 1613.211 | F32: =SUM(F27+SUM(F30:F31)) -> 1923.026 | G32: =SUM(G27+SUM(G30:G31)) -> 1970.115 | H32: =SUM(H27+SUM(H30:H31)) -> 1874.801 | J32: =SUM(J27+SUM(J30:J31)) -> 510.903 | K32: =SUM(K27+SUM(K30:K31)) -> 464.829 | L32: =SUM(L27+SUM(L30:L31)) -> 429.996 | M32: =SUM(M27+SUM(M30:M31)) -> 517.298 | N32: =SUM(N27+SUM(N30:N31)) -> 509.74 | O32: =SUM(O27+SUM(O30:O31)) -> 465.373 | P32: =SUM(P27+SUM(P30:P31)) -> 400.576 | Q32: =SUM(Q27+SUM(Q30:Q31)) -> 594.426 | ... X32: =SUM(X27+SUM(X30:X31)) -> 395.192 | Z32: =SUM(Z27+SUM(Z30:Z31)) -> 1923.026 | AA32: =SUM(AA27+SUM(AA30:AA31)) -> 1921.863 | AB32: =SUM(AB27+SUM(AB30:AB31)) -> 1922.407 | AC32: =SUM(AC27+SUM(AC30:AC31)) -> 1892.987 | AD32: =SUM(AD27+SUM(AD30:AD31)) -> 1970.115 | AE32: =SUM(AE27+SUM(AE30:AE31)) -> 1936.144 | AF32: =SUM(AF27+SUM(AF30:AF31)) -> 1874.476 | AG32: =SUM(AG27+SUM(AG30:AG31)) -> 1867.843 | ... AK32: =SUM(AK27+SUM(AK30:AK31)) -> 1906.743 | AM32: =SUM(AK32/AG32)-1 -> 0.020826162
B33: Adj. EBITDA Margin (%) | C33: =C32/C12 -> 0.16514285 | D33: =D32/D12 -> 0.10996459 | E33: =E32/E12 -> 0.18691134 | F33: =F32/F12 -> 0.18837351 | G33: =G32/G12 -> 0.1757885 | H33: =H32/H12 -> 0.16597543 | J33: =J32/J12 -> 0.21778541 | K33: =K32/K12 -> 0.20235356 | L33: =L32/L12 -> 0.18385381 | M33: =M32/M12 -> 0.16031435 | N33: =N32/N12 -> 0.19350384 | O33: =O32/O12 -> 0.18395578 | P33: =P32/P12 -> 0.16094286 | Q33: =Q32/Q12 -> 0.16724146 | ... X33: =X32/X12 -> 0.13829396 | Z33: =Z32/Z12 -> 0.18837351 | AA33: =AA32/AA12 -> 0.18308789 | AB33: =AB32/AB12 -> 0.17916793 | AC33: =AC32/AC12 -> 0.17399133 | AD33: =AD32/AD12 -> 0.1757885 | AE33: =AE32/AE12 -> 0.17135704 | AF33: =AF32/AF12 -> 0.1655727 | AG33: =AG32/AG12 -> 0.16438904 | ... AK33: =AK32/AK12 -> 0.15913292 | AM33: =SUM(AK33-AG33)*10000 -> -52.561238
B35: (-) Capital Expenditures | C35: ='Historical Financials'!C115/1000 -> -298.534 | D35: ='Historical Financials'!D115/1000 -> -151.866 | E35: ='Historical Financials'!E115/1000 -> -172.187 | F35: ='Historical Financials'!F115/1000 -> -312.126 | G35: ='Historical Financials'!G115/1000 -> -435.267 | H35: ='Historical Financials'!H115/1000 -> -374.458 | J35: ='Historical Financials'!J115/1000 -> -71.076 | K35: ='Historical Financials'!K115/1000 -> -49.424 | L35: ='Historical Financials'!L115/1000 -> -83.461 | M35: ='Historical Financials'!M115/1000 -> -108.165 | N35: ='Historical Financials'!N115/1000 -> -109.766 | O35: ='Historical Financials'!O115/1000 -> -94.982 | P35: ='Historical Financials'!P115/1000 -> -106.282 | Q35: ='Historical Financials'!Q115/1000 -> -124.237 | ... X35: ='Historical Financials'!X115/1000 -> -87.274 | Z35: =SUM(J35:M35) -> -312.126 | AA35: =SUM(K35:N35) -> -350.816 | AB35: =SUM(L35:O35) -> -396.374 | AC35: =SUM(M35:P35) -> -419.195 | AD35: =SUM(N35:Q35) -> -435.267 | AE35: =SUM(O35:R35) -> -416.525 | AF35: =SUM(P35:S35) -> -416.82 | AG35: =SUM(Q35:T35) -> -424.773 | ... AK35: =SUM(U35:X35) -> -317.184 | AM35: =SUM(AK35/AG35)-1 -> -0.25328587
B36: (-) Cash Taxes | C36: =-'Historical Financials'!C142/1000 -> -133.861 | D36: =-'Historical Financials'!D142/1000 -> -19.454 | E36: =-'Historical Financials'!E142/1000 -> -370.646 | F36: =-'Historical Financials'!F142/1000 -> -429.846 | G36: =-'Historical Financials'!G142/1000 -> -328.215 | H36: =-'Historical Financials'!H142/1000 -> -386.059 | J36: =-'Historical Financials'!J142/1000 -> -0.524 | K36: =-'Historical Financials'!K142/1000 -> -246.117 | L36: =-'Historical Financials'!L142/1000 -> -92.649 | M36: =-'Historical Financials'!M142/1000 -> -90.556 | N36: =-'Historical Financials'!N142/1000 -> -2.818 | O36: =-'Historical Financials'!O142/1000 -> -186.348 | P36: =-'Historical Financials'!P142/1000 -> -77.636 | Q36: =-'Historical Financials'!Q142/1000 -> -61.413 | ... X36: =-'Historical Financials'!X142/1000 -> -74.347 | Z36: =SUM(J36:M36) -> -429.846 | AA36: =SUM(K36:N36) -> -432.14 | AB36: =SUM(L36:O36) -> -372.371 | AC36: =SUM(M36:P36) -> -357.358 | AD36: =SUM(N36:Q36) -> -328.215 | AE36: =SUM(O36:R36) -> -330.454 | AF36: =SUM(P36:S36) -> -372.298 | AG36: =SUM(Q36:T36) -> -378.203 | ... AK36: =SUM(U36:X36) -> -395.629 | AM36: =SUM(AK36/AG36)-1 -> 0.046075785
B37: (-) Cash Interest | C37: =-'Historical Financials'!C141/1000 -> 0 | D37: =-'Historical Financials'!D141/1000 -> -6.987 | E37: =-'Historical Financials'!E141/1000 -> -2.132 | F37: =-'Historical Financials'!F141/1000 -> -2.138 | G37: =-'Historical Financials'!G141/1000 -> -3.327 | H37: =-'Historical Financials'!H141/1000 -> -4.159 | J37: =-'Historical Financials'!J141/1000 -> 0 | K37: =-'Historical Financials'!K141/1000 -> -1.057 | L37: =-'Historical Financials'!L141/1000 -> -0.541 | M37: =-'Historical Financials'!M141/1000 -> -0.54 | N37: =-'Historical Financials'!N141/1000 -> 0 | O37: =-'Historical Financials'!O141/1000 -> 0 | P37: =-'Historical Financials'!P141/1000 -> 0 | Q37: =-'Historical Financials'!Q141/1000 -> -3.327 | ... X37: =-'Historical Financials'!X141/1000 -> 0 | Z37: =SUM(J37:M37) -> -2.138 | AA37: =SUM(K37:N37) -> -2.138 | AB37: =SUM(L37:O37) -> -1.081 | AC37: =SUM(M37:P37) -> -0.54 | AD37: =SUM(N37:Q37) -> -3.327 | AE37: =SUM(O37:R37) -> -3.327 | AF37: =SUM(P37:S37) -> -3.327 | AG37: =SUM(Q37:T37) -> -3.327 | ... AK37: =SUM(U37:X37) -> -4.159 | AM37: =SUM(AK37/AG37)-1 -> 0.25007514
B38: (+/-) Changes in NWC | C38: =SUM('Historical Financials'!C103:C111)/1000 -> -215.469 | D38: =SUM('Historical Financials'!D103:D111)/1000 -> -14.258 | E38: =SUM('Historical Financials'!E103:E111)/1000 -> -498.212 | F38: =SUM('Historical Financials'!F103:F111)/1000 -> -369.162 | G38: =SUM('Historical Financials'!G103:G111)/1000 -> -481.573 | H38: =SUM('Historical Financials'!H103:H111)/1000 -> -451.216 | J38: =SUM('Historical Financials'!J103:J111)/1000 -> -52.49 | K38: =SUM('Historical Financials'!K103:K111)/1000 -> -329.375 | L38: =SUM('Historical Financials'!L103:L111)/1000 -> -386.476 | M38: =SUM('Historical Financials'!M103:M111)/1000 -> 399.179 | N38: =SUM('Historical Financials'!N103:N111)/1000 -> -188.893 | O38: =SUM('Historical Financials'!O103:O111)/1000 -> -328.264 | P38: =SUM('Historical Financials'!P103:P111)/1000 -> -476.828 | Q38: =SUM('Historical Financials'!Q103:Q111)/1000 -> 512.412 | ... X38: =SUM('Historical Financials'!X103:X111)/1000 -> -387.96 | Z38: =SUM(J38:M38) -> -369.162 | AA38: =SUM(K38:N38) -> -505.565 | AB38: =SUM(L38:O38) -> -504.454 | AC38: =SUM(M38:P38) -> -594.806 | AD38: =SUM(N38:Q38) -> -481.573 | AE38: =SUM(O38:R38) -> -605.822 | AF38: =SUM(P38:S38) -> -491.756 | AG38: =SUM(Q38:T38) -> -467.199 | ... AK38: =SUM(U38:X38) -> -464.159 | AM38: =SUM(AK38/AG38)-1 -> -0.0065068632
B39: Discretionary Cash-Flows | C39: =SUM(C32+SUM(C35:C38)) -> 573.874 | D39: =SUM(D32+SUM(D35:D38)) -> 483.932 | E39: =SUM(E32+SUM(E35:E38)) -> 570.034 | F39: =SUM(F32+SUM(F35:F38)) -> 809.754 | G39: =SUM(G32+SUM(G35:G38)) -> 721.733 | H39: =SUM(H32+SUM(H35:H38)) -> 658.909 | J39: =SUM(J32+SUM(J35:J38)) -> 386.813 | K39: =SUM(K32+SUM(K35:K38)) -> -161.144 | L39: =SUM(L32+SUM(L35:L38)) -> -133.131 | M39: =SUM(M32+SUM(M35:M38)) -> 717.216 | N39: =SUM(N32+SUM(N35:N38)) -> 208.263 | O39: =SUM(O32+SUM(O35:O38)) -> -144.221 | P39: =SUM(P32+SUM(P35:P38)) -> -260.17 | Q39: =SUM(Q32+SUM(Q35:Q38)) -> 917.861 | ... X39: =SUM(X32+SUM(X35:X38)) -> -154.389 | Z39: =SUM(Z32+SUM(Z35:Z38)) -> 809.754 | AA39: =SUM(AA32+SUM(AA35:AA38)) -> 631.204 | AB39: =SUM(AB32+SUM(AB35:AB38)) -> 648.127 | AC39: =SUM(AC32+SUM(AC35:AC38)) -> 521.088 | AD39: =SUM(AD32+SUM(AD35:AD38)) -> 721.733 | AE39: =SUM(AE32+SUM(AE35:AE38)) -> 580.016 | AF39: =SUM(AF32+SUM(AF35:AF38)) -> 590.275 | AG39: =SUM(AG32+SUM(AG35:AG38)) -> 594.341 | ... AK39: =SUM(AK32+SUM(AK35:AK38)) -> 725.612 | AM39: =SUM(AK39/AG39)-1 -> 0.22086815
B41: (+/-) Divestiture / Acquisitions | C41: =SUM('Historical Financials'!C116:C117)/1000 -> -172.946 | D41: =SUM('Historical Financials'!D116:D117)/1000 -> 103.115 | E41: =SUM('Historical Financials'!E116:E117)/1000 -> -4.297 | F41: =SUM('Historical Financials'!F116:F117)/1000 -> -2.458 | G41: =SUM('Historical Financials'!G116:G117)/1000 -> -6.158 | H41: =SUM('Historical Financials'!H116:H117)/1000 -> -8.631 | J41: =SUM('Historical Financials'!J116:J117)/1000 -> -0.797 | K41: =SUM('Historical Financials'!K116:K117)/1000 -> -0.452 | L41: =SUM('Historical Financials'!L116:L117)/1000 -> -1.819 | M41: =SUM('Historical Financials'!M116:M117)/1000 -> 0.61 | N41: =SUM('Historical Financials'!N116:N117)/1000 -> -0.314 | O41: =SUM('Historical Financials'!O116:O117)/1000 -> -1.373 | P41: =SUM('Historical Financials'!P116:P117)/1000 -> -3.183 | Q41: =SUM('Historical Financials'!Q116:Q117)/1000 -> -1.288 | ... X41: =SUM('Historical Financials'!X116:X117)/1000 -> -8.315 | Z41: =SUM(J41:M41) -> -2.458 | AA41: =SUM(K41:N41) -> -1.975 | AB41: =SUM(L41:O41) -> -2.896 | AC41: =SUM(M41:P41) -> -4.26 | AD41: =SUM(N41:Q41) -> -6.158 | AE41: =SUM(O41:R41) -> -8.407 | AF41: =SUM(P41:S41) -> -9.562 | AG41: =SUM(Q41:T41) -> -7.396 | ... AK41: =SUM(U41:X41) -> -414.761
B42: (-) 'Proceeds from Debt Issuances / (Repayment) | C42: ='Historical Financials'!C121/1000 -> 0 | D42: ='Historical Financials'!D121/1000 -> 0 | E42: ='Historical Financials'!E121/1000 -> 0 | F42: ='Historical Financials'!F121/1000 -> 0 | G42: ='Historical Financials'!G121/1000 -> 0 | H42: ='Historical Financials'!H121/1000 -> 0 | J42: ='Historical Financials'!J121/1000 -> 0 | K42: ='Historical Financials'!K121/1000 -> 0 | L42: ='Historical Financials'!L121/1000 -> 0 | M42: ='Historical Financials'!M121/1000 -> 0 | N42: ='Historical Financials'!N121/1000 -> 0 | O42: ='Historical Financials'!O121/1000 -> 0 | P42: ='Historical Financials'!P121/1000 -> 195.4 | Q42: ='Historical Financials'!Q121/1000 -> -195.4 | ... X42: ='Historical Financials'!X121/1000 -> 262.62 | Z42: =SUM(J42:M42) -> 0 | AA42: =SUM(K42:N42) -> 0 | AB42: =SUM(L42:O42) -> 0 | AC42: =SUM(M42:P42) -> 195.4 | AD42: =SUM(N42:Q42) -> 0 | AE42: =SUM(O42:R42) -> 0 | AF42: =SUM(P42:S42) -> 0 | AG42: =SUM(Q42:T42) -> 4.3 | ... AK42: =SUM(U42:X42) -> 323.461
B43: (-) Share Repurchases | C43: ='Historical Financials'!C122/1000 -> -680.979 | D43: ='Historical Financials'!D122/1000 -> -114.895 | E43: ='Historical Financials'!E122/1000 -> -1521.925 | F43: ='Historical Financials'!F122/1000 -> -900.033 | G43: ='Historical Financials'!G122/1000 -> -995.738 | H43: ='Historical Financials'!H122/1000 -> -1003.328 | J43: ='Historical Financials'!J122/1000 -> -132.834 | K43: ='Historical Financials'!K122/1000 -> -301.614 | L43: ='Historical Financials'!L122/1000 -> -137.46 | M43: ='Historical Financials'!M122/1000 -> -328.125 | N43: ='Historical Financials'!N122/1000 -> -283.517 | O43: ='Historical Financials'!O122/1000 -> -275.494 | P43: ='Historical Financials'!P122/1000 -> -281.54 | Q43: ='Historical Financials'!Q122/1000 -> -155.187 | ... X43: ='Historical Financials'!X122/1000 -> -224.718 | Z43: =SUM(J43:M43) -> -900.033 | AA43: =SUM(K43:N43) -> -1050.716 | AB43: =SUM(L43:O43) -> -1024.596 | AC43: =SUM(M43:P43) -> -1168.676 | AD43: =SUM(N43:Q43) -> -995.738 | AE43: =SUM(O43:R43) -> -1001.652 | AF43: =SUM(P43:S43) -> -938.495 | AG43: =SUM(Q43:T43) -> -920.571 | ... AK43: =SUM(U43:X43) -> -941.904
B44: (+) Stock options exercised | C44: ='Historical Financials'!C124/1000 -> 43.78 | D44: ='Historical Financials'!D124/1000 -> 12.229 | E44: ='Historical Financials'!E124/1000 -> 40.386 | F44: ='Historical Financials'!F124/1000 -> 46.011 | G44: ='Historical Financials'!G124/1000 -> 12.176 | H44: ='Historical Financials'!H124/1000 -> 12.339 | J44: ='Historical Financials'!J124/1000 -> 6.502 | K44: ='Historical Financials'!K124/1000 -> 18.019 | L44: ='Historical Financials'!L124/1000 -> 6.798 | M44: ='Historical Financials'!M124/1000 -> 14.692 | N44: ='Historical Financials'!N124/1000 -> 8.927 | O44: ='Historical Financials'!O124/1000 -> 0.22 | P44: ='Historical Financials'!P124/1000 -> 0.155 | Q44: ='Historical Financials'!Q124/1000 -> 2.874 | ... X44: ='Historical Financials'!X124/1000 -> 15.252 | Z44: =SUM(J44:M44) -> 46.011 | AA44: =SUM(K44:N44) -> 48.436 | AB44: =SUM(L44:O44) -> 30.637 | AC44: =SUM(M44:P44) -> 23.994 | AD44: =SUM(N44:Q44) -> 12.176 | AE44: =SUM(O44:R44) -> 12.162 | AF44: =SUM(P44:S44) -> 12.225 | AG44: =SUM(Q44:T44) -> 12.074 | ... AK44: =SUM(U44:X44) -> 33.242
B45: (-) Purchase of treasury shares | C45: ='Historical Financials'!C125/1000 -> -9.54 | D45: ='Historical Financials'!D125/1000 -> -3.353 | E45: ='Historical Financials'!E125/1000 -> -15.677 | F45: ='Historical Financials'!F125/1000 -> -6.992 | G45: ='Historical Financials'!G125/1000 -> -22.562 | H45: ='Historical Financials'!H125/1000 -> -23.761 | J45: ='Historical Financials'!J125/1000 -> -5.172 | K45: ='Historical Financials'!K125/1000 -> -1.153 | L45: ='Historical Financials'!L125/1000 -> -0.415 | M45: ='Historical Financials'!M125/1000 -> -0.252 | N45: ='Historical Financials'!N125/1000 -> -21.659 | O45: ='Historical Financials'!O125/1000 -> -0.1 | P45: ='Historical Financials'!P125/1000 -> -0.569 | Q45: ='Historical Financials'!Q125/1000 -> -0.234 | ... X45: ='Historical Financials'!X125/1000 -> -0.267 | Z45: =SUM(J45:M45) -> -6.992 | AA45: =SUM(K45:N45) -> -23.479 | AB45: =SUM(L45:O45) -> -22.426 | AC45: =SUM(M45:P45) -> -22.58 | AD45: =SUM(N45:Q45) -> -22.562 | AE45: =SUM(O45:R45) -> -24.186 | AF45: =SUM(P45:S45) -> -24.262 | AG45: =SUM(Q45:T45) -> -23.8 | ... AK45: =SUM(U45:X45) -> -13.7
B46: (+/-) Other | D46: =SUM(D51-C51)-SUM(D39:D45) -> 172.698 | E46: =SUM(E51-D51)-SUM(E39:E45) -> 316.988 | F46: =SUM(F51-E51)-SUM(F39:F45) -> 360.035 | G46: =SUM(G51-F51)-SUM(G39:G45) -> 319.266 | H46: =SUM(H51-G51)-SUM(H39:H45) -> 301.079 | K46: =SUM(K51-J51)-SUM(K39:K45) -> 226.084 | L46: =SUM(L51-K51)-SUM(L39:L45) -> 82.429 | M46: =SUM(M51-L51)-SUM(M39:M45) -> 83.108 | N46: =SUM(N51-M51)-SUM(N39:N45) -> -13.128 | O46: =SUM(O51-N51)-SUM(O39:O45) -> 173.146 | P46: =SUM(P51-O51)-SUM(P39:P45) -> 83.091 | Q46: =SUM(Q51-P51)-SUM(Q39:Q45) -> 76.157 | R46: =SUM(R51-Q51)-SUM(R39:R45) -> -2.18 | ... X46: =SUM(X51-W51)-SUM(X39:X45) -> 71.993 | Z46: =SUM(J46:M46) -> 391.621 | AA46: =SUM(K46:N46) -> 378.493 | AB46: =SUM(L46:O46) -> 325.555 | AC46: =SUM(M46:P46) -> 326.217 | AD46: =SUM(N46:Q46) -> 319.266 | AE46: =SUM(O46:R46) -> 330.214 | AF46: =SUM(P46:S46) -> 395.154 | AG46: =SUM(Q46:T46) -> 397.023 | ... AK46: =SUM(U46:X46) -> 315.189
B47: Free-Cash Flows | C47: =SUM(C39+SUM(C41:C46)) -> -245.811 | D47: =SUM(D39+SUM(D41:D46)) -> 653.726 | E47: =SUM(E39+SUM(E41:E46)) -> -614.491 | F47: =SUM(F39+SUM(F41:F46)) -> 306.317 | G47: =SUM(G39+SUM(G41:G46)) -> 28.717 | H47: =SUM(H39+SUM(H41:H46)) -> -63.393 | J47: =SUM(J39+SUM(J41:J46)) -> 254.512 | K47: =SUM(K39+SUM(K41:K46)) -> -220.26 | L47: =SUM(L39+SUM(L41:L46)) -> -183.598 | M47: =SUM(M39+SUM(M41:M46)) -> 487.249 | N47: =SUM(N39+SUM(N41:N46)) -> -101.428 | O47: =SUM(O39+SUM(O41:O46)) -> -247.822 | P47: =SUM(P39+SUM(P41:P46)) -> -266.816 | Q47: =SUM(Q39+SUM(Q41:Q46)) -> 644.783 | ... X47: =SUM(X39+SUM(X41:X46)) -> -37.824 | Z47: =SUM(Z39+SUM(Z41:Z46)) -> 337.903 | AA47: =SUM(AA39+SUM(AA41:AA46)) -> -18.037 | AB47: =SUM(AB39+SUM(AB41:AB46)) -> -45.599 | AC47: =SUM(AC39+SUM(AC41:AC46)) -> -128.817 | AD47: =SUM(AD39+SUM(AD41:AD46)) -> 28.717 | AE47: =SUM(AE39+SUM(AE41:AE46)) -> -111.853 | AF47: =SUM(AF39+SUM(AF41:AF46)) -> 25.335 | AG47: =SUM(AG39+SUM(AG41:AG46)) -> 55.971 | ... AK47: =SUM(AK39+SUM(AK41:AK46)) -> 27.139
B49: Capitalization
B51: Cash & Cash Equivelants | C51: ='Historical Financials'!C45/1000 -> 392.325 | D51: ='Historical Financials'!D45/1000 -> 1046.051 | E51: ='Historical Financials'!E45/1000 -> 431.56 | F51: ='Historical Financials'!F45/1000 -> 737.877 | G51: ='Historical Financials'!G45/1000 -> 766.594 | H51: ='Historical Financials'!H45/1000 -> 703.201 | J51: ='Historical Financials'!J45/1000 -> 654.486 | K51: ='Historical Financials'!K45/1000 -> 434.226 | L51: ='Historical Financials'!L45/1000 -> 250.628 | M51: ='Historical Financials'!M45/1000 -> 737.877 | N51: ='Historical Financials'!N45/1000 -> 636.449 | O51: ='Historical Financials'!O45/1000 -> 388.627 | P51: ='Historical Financials'!P45/1000 -> 121.811 | Q51: ='Historical Financials'!Q45/1000 -> 766.594 | ... X51: ='Historical Financials'!X45/1000 -> 204.921 | Z51: =M51 -> 737.877 | AA51: =N51 -> 636.449 | AB51: =O51 -> 388.627 | AC51: =P51 -> 121.811 | AD51: =Q51 -> 766.594 | AE51: =R51 -> 524.596 | AF51: =S51 -> 413.962 | AG51: =T51 -> 177.782 | ... AK51: =X51 -> 204.921
B52: $1,000MM Revolving Credit Facility | C52: =400-C70 -> 400 | D52: =1000-D70 -> 1000 | E52: =1000-E70 -> 1000 | F52: =1000-F70 -> 1000 | G52: =800-G70 -> 800 | H52: =800-H70 -> 800 | J52: =1000-J70 -> 1000 | K52: =1000-K70 -> 1000 | L52: =1000-L70 -> 1000 | M52: =F52 -> 1000 | N52: =1000-N70 -> 1000 | O52: =1000-O70 -> 1000 | P52: =1000-P70 -> 804.6 | Q52: =G52 -> 800 | R52: =800-R70 -> 800 | S52: =800-S70 -> 800 | T52: =800-T70 -> 600.3 | U52: =H52 -> 800 | V52: =800-V70 -> 800 | W52: =800-W70 -> 562.3 | X52: =800-X70 -> 311.7 | Z52: =M52 -> 1000 | AA52: =N52 -> 1000 | AB52: =O52 -> 1000 | AC52: =P52 -> 804.6 | AD52: =Q52 -> 800 | AE52: =R52 -> 800 | AF52: =S52 -> 800 | AG52: =T52 -> 600.3 | ... AK52: =X52 -> 311.7
B53: £50MM Space NK RCF (+£10MM Accordion / 1.285 FX Adj.) | C53: 0 | D53: 0 | E53: 0 | F53: 0 | G53: 0 | H53: 0 | J53: 0 | K53: 0 | L53: 0 | M53: =F53 -> 0 | N53: 0 | O53: 0 | P53: 0 | Q53: =G53 -> 0 | R53: 0 | S53: 0 | T53: 0 | U53: =H53 -> 0 | V53: 0 | W53: =64.3-W71 -> 12.899 | X53: =64.3-X71 -> 0.879 | Z53: =M53 -> 0 | AA53: =N53 -> 0 | AB53: =O53 -> 0 | AC53: =P53 -> 0 | AD53: =Q53 -> 0 | AE53: =R53 -> 0 | AF53: =S53 -> 0 | AG53: =T53 -> 0 | ... AK53: =X53 -> 0.879
B54: Total Liquidity | C54: =SUM(C51:C53) -> 792.325 | D54: =SUM(D51:D53) -> 2046.051 | E54: =SUM(E51:E53) -> 1431.56 | F54: =SUM(F51:F53) -> 1737.877 | G54: =SUM(G51:G53) -> 1566.594 | H54: =SUM(H51:H53) -> 1503.201 | J54: =SUM(J51:J53) -> 1654.486 | K54: =SUM(K51:K53) -> 1434.226 | L54: =SUM(L51:L53) -> 1250.628 | M54: =SUM(M51:M53) -> 1737.877 | N54: =SUM(N51:N53) -> 1636.449 | O54: =SUM(O51:O53) -> 1388.627 | P54: =SUM(P51:P53) -> 926.411 | Q54: =SUM(Q51:Q53) -> 1566.594 | ... X54: =SUM(X51:X53) -> 517.5 | Z54: =SUM(Z51:Z53) -> 1737.877 | AA54: =SUM(AA51:AA53) -> 1636.449 | AB54: =SUM(AB51:AB53) -> 1388.627 | AC54: =SUM(AC51:AC53) -> 926.411 | AD54: =SUM(AD51:AD53) -> 1566.594 | AE54: =SUM(AE51:AE53) -> 1324.596 | AF54: =SUM(AF51:AF53) -> 1213.962 | AG54: =SUM(AG51:AG53) -> 778.082 | ... AK54: =SUM(AK51:AK53) -> 517.5
B55: L/C Avaliability ($50MM) | C55: 20 | D55: 50 | E55: 50 | F55: 50 | G55: 50 | H55: 50 | J55: 50 | K55: 50 | L55: 50 | M55: 50 | N55: 50 | O55: 50 | P55: 50 | Q55: 50 | R55: 50 | S55: 50 | T55: 50 | U55: =H55 -> 50 | V55: 50 | W55: 50 | X55: 50 | Z55: =M55 -> 50 | AA55: =N55 -> 50 | AB55: =O55 -> 50 | AC55: =P55 -> 50 | AD55: =Q55 -> 50 | AE55: =R55 -> 50 | AF55: =S55 -> 50 | AG55: =T55 -> 50 | ... AK55: =X55 -> 50
B57: Balance Sheet Metrics:
B58: Accounts Receivables | C58: ='Historical Financials'!C46/1000 -> 139.337 | D58: ='Historical Financials'!D46/1000 -> 193.109 | E58: ='Historical Financials'!E46/1000 -> 233.682 | F58: ='Historical Financials'!F46/1000 -> 199.422 | G58: ='Historical Financials'!G46/1000 -> 207.939 | H58: ='Historical Financials'!H46/1000 -> 223.334 | J58: ='Historical Financials'!J46/1000 -> 192.754 | K58: ='Historical Financials'!K46/1000 -> 180.514 | L58: ='Historical Financials'!L46/1000 -> 200.304 | M58: ='Historical Financials'!M46/1000 -> 199.422 | N58: ='Historical Financials'!N46/1000 -> 190.282 | O58: ='Historical Financials'!O46/1000 -> 174.444 | P58: ='Historical Financials'!P46/1000 -> 202.868 | Q58: ='Historical Financials'!Q46/1000 -> 207.939 | ... X58: ='Historical Financials'!X46/1000 -> 237.352 | Z58: =M58 -> 199.422 | AA58: =N58 -> 190.282 | AB58: =O58 -> 174.444 | AC58: =P58 -> 202.868 | AD58: =Q58 -> 207.939 | AE58: =R58 -> 203.463 | AF58: =S58 -> 200.863 | AG58: =T58 -> 213.621 | ... AK58: =X58 -> 237.352
B59: Merchandise inventories, net | C59: ='Historical Financials'!C47/1000 -> 1293.701 | D59: ='Historical Financials'!D47/1000 -> 1168.215 | E59: ='Historical Financials'!E47/1000 -> 1499.218 | F59: ='Historical Financials'!F47/1000 -> 1603.451 | G59: ='Historical Financials'!G47/1000 -> 1742.136 | H59: ='Historical Financials'!H47/1000 -> 1968.214 | J59: ='Historical Financials'!J47/1000 -> 1570.552 | K59: ='Historical Financials'!K47/1000 -> 1666.13 | L59: ='Historical Financials'!L47/1000 -> 2114.669 | M59: ='Historical Financials'!M47/1000 -> 1603.451 | N59: ='Historical Financials'!N47/1000 -> 1751.235 | O59: ='Historical Financials'!O47/1000 -> 1815.539 | P59: ='Historical Financials'!P47/1000 -> 2321.306 | Q59: ='Historical Financials'!Q47/1000 -> 1742.136 | ... X59: ='Historical Financials'!X47/1000 -> 2743.639 | Z59: =M59 -> 1603.451 | AA59: =N59 -> 1751.235 | AB59: =O59 -> 1815.539 | AC59: =P59 -> 2321.306 | AD59: =Q59 -> 1742.136 | AE59: =R59 -> 1906.04 | AF59: =S59 -> 1998.286 | AG59: =T59 -> 2365.186 | ... AK59: =X59 -> 2743.639
B60: Property and Equipment | C60: ='Historical Financials'!C52/1000 -> 1205.524 | D60: ='Historical Financials'!D52/1000 -> 995.795 | E60: ='Historical Financials'!E52/1000 -> 914.476 | F60: ='Historical Financials'!F52/1000 -> 1009.273 | G60: ='Historical Financials'!G52/1000 -> 1182.335 | H60: ='Historical Financials'!H52/1000 -> 1239.295 | J60: ='Historical Financials'!J52/1000 -> 909.543 | K60: ='Historical Financials'!K52/1000 -> 912.017 | L60: ='Historical Financials'!L52/1000 -> 967.039 | M60: ='Historical Financials'!M52/1000 -> 1009.273 | N60: ='Historical Financials'!N52/1000 -> 1019.978 | O60: ='Historical Financials'!O52/1000 -> 1073.144 | P60: ='Historical Financials'!P52/1000 -> 1117.874 | Q60: ='Historical Financials'!Q52/1000 -> 1182.335 | ... X60: ='Historical Financials'!X52/1000 -> 1366.504 | Z60: =M60 -> 1009.273 | AA60: =N60 -> 1019.978 | AB60: =O60 -> 1073.144 | AC60: =P60 -> 1117.874 | AD60: =Q60 -> 1182.335 | AE60: =R60 -> 1195.658 | AF60: =S60 -> 1225.85 | AG60: =T60 -> 1264.419 | ... AK60: =X60 -> 1366.504
B61: Accounts Payable | C61: ='Historical Financials'!C61/1000 -> 414.009 | D61: ='Historical Financials'!D61/1000 -> 477.052 | E61: ='Historical Financials'!E61/1000 -> 552.73 | F61: ='Historical Financials'!F61/1000 -> 559.527 | G61: ='Historical Financials'!G61/1000 -> 544.001 | H61: ='Historical Financials'!H61/1000 -> 563.761 | J61: ='Historical Financials'!J61/1000 -> 585.5 | K61: ='Historical Financials'!K61/1000 -> 586.851 | L61: ='Historical Financials'!L61/1000 -> 647.117 | M61: ='Historical Financials'!M61/1000 -> 559.527 | N61: ='Historical Financials'!N61/1000 -> 621.272 | O61: ='Historical Financials'!O61/1000 -> 521.315 | P61: ='Historical Financials'!P61/1000 -> 597.373 | Q61: ='Historical Financials'!Q61/1000 -> 544.001 | ... X61: ='Historical Financials'!X61/1000 -> 759.001 | Z61: =M61 -> 559.527 | AA61: =N61 -> 621.272 | AB61: =O61 -> 521.315 | AC61: =P61 -> 597.373 | AD61: =Q61 -> 544.001 | AE61: =R61 -> 463.777 | AF61: =S61 -> 566.904 | AG61: =T61 -> 593.219 | ... AK61: =X61 -> 759.001
B62: Deferred Revenue | C62: ='Historical Financials'!C62/1000 -> 237.535 | D62: ='Historical Financials'!D62/1000 -> 274.383 | E62: ='Historical Financials'!E62/1000 -> 353.579 | F62: ='Historical Financials'!F62/1000 -> 394.677 | G62: ='Historical Financials'!G62/1000 -> 436.591 | H62: ='Historical Financials'!H62/1000 -> 500.585 | J62: ='Historical Financials'!J62/1000 -> 324.694 | K62: ='Historical Financials'!K62/1000 -> 316.571 | L62: ='Historical Financials'!L62/1000 -> 312.132 | M62: ='Historical Financials'!M62/1000 -> 394.677 | N62: ='Historical Financials'!N62/1000 -> 357.217 | O62: ='Historical Financials'!O62/1000 -> 354.253 | P62: ='Historical Financials'!P62/1000 -> 350.937 | Q62: ='Historical Financials'!Q62/1000 -> 436.591 | ... X62: ='Historical Financials'!X62/1000 -> 462.964 | Z62: =M62 -> 394.677 | AA62: =N62 -> 357.217 | AB62: =O62 -> 354.253 | AC62: =P62 -> 350.937 | AD62: =Q62 -> 436.591 | AE62: =R62 -> 398.729 | AF62: =S62 -> 394.987 | AG62: =T62 -> 405.04 | ... AK62: =X62 -> 462.964
B63: Current Liabilities | C63: ='Historical Financials'!C66/1000 -> 1137.261 | D63: ='Historical Financials'!D66/1000 -> 1343.713 | E63: ='Historical Financials'!E66/1000 -> 1558.01 | F63: ='Historical Financials'!F66/1000 -> 1681.775 | G63: ='Historical Financials'!G66/1000 -> 1658.191 | H63: ='Historical Financials'!H66/1000 -> 1779.478 | J63: ='Historical Financials'!J66/1000 -> 1599.747 | K63: ='Historical Financials'!K66/1000 -> 1502.054 | L63: ='Historical Financials'!L66/1000 -> 1697.771 | M63: ='Historical Financials'!M66/1000 -> 1681.775 | N63: ='Historical Financials'!N66/1000 -> 1633.9 | O63: ='Historical Financials'!O66/1000 -> 1491.174 | P63: ='Historical Financials'!P66/1000 -> 1836.939 | Q63: ='Historical Financials'!Q66/1000 -> 1658.191 | ... X63: ='Historical Financials'!X66/1000 -> 2538.351 | Z63: =M63 -> 1681.775 | AA63: =N63 -> 1633.9 | AB63: =O63 -> 1491.174 | AC63: =P63 -> 1836.939 | AD63: =Q63 -> 1658.191 | AE63: =R63 -> 1572.724 | AF63: =S63 -> 1591.234 | AG63: =T63 -> 1816.407 | ... AK63: =X63 -> 2538.351
B64: Total Liabilities | C64: ='Historical Financials'!C72/1000 -> 2961.778 | D64: ='Historical Financials'!D72/1000 -> 3090.42 | E64: ='Historical Financials'!E72/1000 -> 3229.006 | F64: ='Historical Financials'!F72/1000 -> 3410.6 | G64: ='Historical Financials'!G72/1000 -> 3427.683 | H64: ='Historical Financials'!H72/1000 -> 3513.34 | J64: ='Historical Financials'!J72/1000 -> 3266.416 | K64: ='Historical Financials'!K72/1000 -> 3176.926 | L64: ='Historical Financials'!L72/1000 -> 3409.294 | M64: ='Historical Financials'!M72/1000 -> 3410.6 | N64: ='Historical Financials'!N72/1000 -> 3357.651 | O64: ='Historical Financials'!O72/1000 -> 3196.883 | P64: ='Historical Financials'!P72/1000 -> 3566.466 | Q64: ='Historical Financials'!Q72/1000 -> 3427.683 | ... X64: ='Historical Financials'!X72/1000 -> 4379.278 | Z64: =M64 -> 3410.6 | AA64: =N64 -> 3357.651 | AB64: =O64 -> 3196.883 | AC64: =P64 -> 3566.466 | AD64: =Q64 -> 3427.683 | AE64: =R64 -> 3331.196 | AF64: =S64 -> 3389.248 | AG64: =T64 -> 3629.477 | ... AK64: =X64 -> 4379.278
B66: Summary Debt:
B67: CPLTD | C67: ='Historical Financials'!C65/1000 -> 0 | D67: ='Historical Financials'!D65/1000 -> 0 | E67: ='Historical Financials'!E65/1000 -> 0 | F67: ='Historical Financials'!F65/1000 -> 0 | G67: ='Historical Financials'!G65/1000 -> 0 | H67: ='Historical Financials'!H65/1000 -> 0 | J67: ='Historical Financials'!J65/1000 -> 0 | K67: ='Historical Financials'!K65/1000 -> 0 | L67: ='Historical Financials'!L65/1000 -> 0 | M67: ='Historical Financials'!M65/1000 -> 0 | N67: ='Historical Financials'!N65/1000 -> 0 | O67: ='Historical Financials'!O65/1000 -> 0 | P67: ='Historical Financials'!P65/1000 -> 195.4 | Q67: ='Historical Financials'!Q65/1000 -> 0 | ... X67: ='Historical Financials'!X65/1000 -> 551.721 | Z67: =M67 -> 0 | AA67: =N67 -> 0 | AB67: =O67 -> 0 | AC67: =P67 -> 195.4 | AD67: =Q67 -> 0 | AE67: =R67 -> 0 | AF67: =S67 -> 0 | AG67: =T67 -> 199.7 | ... AK67: =X67 -> 551.721
B68: LTD | C68: 0 | D68: 0 | E68: 0 | F68: 0 | G68: 0 | H68: 0 | J68: 0 | K68: 0 | L68: 0 | M68: 0 | N68: 0 | O68: 0 | P68: 0 | Q68: 0 | R68: 0 | S68: 0 | T68: 0 | U68: 0 | V68: 0 | W68: 0 | X68: 0 | Z68: =M68 -> 0 | AA68: =N68 -> 0 | AB68: =O68 -> 0 | AC68: =P68 -> 0 | AD68: =Q68 -> 0 | AE68: =R68 -> 0 | AF68: =S68 -> 0 | AG68: =T68 -> 0 | ... AK68: =X68 -> 0
B70: $800MM Revolving Credit Facility | C70: 0 | D70: 0 | E70: 0 | F70: 0 | G70: 0 | H70: 0 | J70: 0 | K70: 0 | L70: 0 | M70: =F70 -> 0 | N70: 0 | O70: 0 | P70: 195.4 | Q70: =G70 -> 0 | R70: 0 | S70: 0 | T70: 199.7 | U70: =H70 -> 0 | V70: 0 | W70: 237.7 | X70: 488.3 | Z70: =M70 -> 0 | AA70: =N70 -> 0 | AB70: =O70 -> 0 | AC70: =P70 -> 195.4 | AD70: =Q70 -> 0 | AE70: =R70 -> 0 | AF70: =S70 -> 0 | AG70: =T70 -> 199.7 | ... AK70: =X70 -> 488.3
B71: £50MM Space NK RCF (+£10MM Accordion / 1.285 FX Adj.) | C71: 0 | D71: 0 | E71: 0 | F71: 0 | G71: 0 | H71: 0 | J71: 0 | K71: 0 | L71: 0 | M71: =F71 -> 0 | N71: 0 | O71: 0 | P71: 0 | Q71: =G71 -> 0 | R71: 0 | S71: 0 | T71: 0 | U71: =H71 -> 0 | V71: 0 | W71: 51.401 | X71: 63.421 | Z71: =M71 -> 0 | AA71: =N71 -> 0 | AB71: =O71 -> 0 | AC71: =P71 -> 0 | AD71: =Q71 -> 0 | AE71: =R71 -> 0 | AF71: =S71 -> 0 | AG71: =T71 -> 0 | ... AK71: =X71 -> 63.421
B72: Total Debt | C72: =SUM(C70:C71) -> 0 | D72: =SUM(D70:D71) -> 0 | E72: =SUM(E70:E71) -> 0 | F72: =SUM(F70:F71) -> 0 | G72: =SUM(G70:G71) -> 0 | H72: =SUM(H70:H71) -> 0 | J72: =SUM(J70:J71) -> 0 | K72: =SUM(K70:K71) -> 0 | L72: =SUM(L70:L71) -> 0 | M72: =SUM(M70:M71) -> 0 | N72: =SUM(N70:N71) -> 0 | O72: =SUM(O70:O71) -> 0 | P72: =SUM(P70:P71) -> 195.4 | Q72: =SUM(Q70:Q71) -> 0 | ... X72: =SUM(X70:X71) -> 551.721 | Z72: =SUM(Z70:Z71) -> 0 | AA72: =SUM(AA70:AA71) -> 0 | AB72: =SUM(AB70:AB71) -> 0 | AC72: =SUM(AC70:AC71) -> 195.4 | AD72: =SUM(AD70:AD71) -> 0 | AE72: =SUM(AE70:AE71) -> 0 | AF72: =SUM(AF70:AF71) -> 0 | AG72: =SUM(AG70:AG71) -> 199.7 | ... AK72: =SUM(AK70:AK71) -> 551.721
B74: Total Shareholder Equity | C74: ='Historical Financials'!C79/1000 -> 1902.094 | D74: ='Historical Financials'!D79/1000 -> 1999.549 | E74: ='Historical Financials'!E79/1000 -> 1535.373 | F74: ='Historical Financials'!F79/1000 -> 1959.811 | G74: ='Historical Financials'!G79/1000 -> 2279.328 | H74: ='Historical Financials'!H79/1000 -> 2488.353 | I74: ='Historical Financials'!I79/1000 -> 0 | J74: ='Historical Financials'!J79/1000 -> 1745.62 | ... X74: ='Historical Financials'!X79/1000 -> 2633.014 | Z74: =M74 -> 1959.811 | AA74: =N74 -> 2018.068 | AB74: =O74 -> 2051.877 | AC74: =P74 -> 2028.542 | AD74: =Q74 -> 2279.328 | AE74: =R74 -> 2300.743 | AF74: =S74 -> 2348.16 | AG74: =T74 -> 2329.009 | ... AK74: =X74 -> 2633.014
B75: Total Book Capitalization | C75: =SUM(C72:C74) -> 1902.094 | D75: =SUM(D72:D74) -> 1999.549 | E75: =SUM(E72:E74) -> 1535.373 | F75: =SUM(F72:F74) -> 1959.811 | G75: =SUM(G72:G74) -> 2279.328 | H75: =SUM(H72:H74) -> 2488.353 | J75: =SUM(J72:J74) -> 1745.62 | K75: =SUM(K72:K74) -> 1769.068 | L75: =SUM(L72:L74) -> 1922.255 | M75: =SUM(M72:M74) -> 1959.811 | N75: =SUM(N72:N74) -> 2018.068 | O75: =SUM(O72:O74) -> 2051.877 | P75: =SUM(P72:P74) -> 2223.942 | Q75: =SUM(Q72:Q74) -> 2279.328 | ... X75: =SUM(X72:X74) -> 3184.735 | Z75: =SUM(Z72:Z74) -> 1959.811 | AA75: =SUM(AA72:AA74) -> 2018.068 | AB75: =SUM(AB72:AB74) -> 2051.877 | AC75: =SUM(AC72:AC74) -> 2223.942 | AD75: =SUM(AD72:AD74) -> 2279.328 | AE75: =SUM(AE72:AE74) -> 2300.743 | AF75: =SUM(AF72:AF74) -> 2348.16 | AG75: =SUM(AG72:AG74) -> 2528.709 | ... AK75: =SUM(AK72:AK74) -> 3184.735
B77: Credit Metrics
B79: LTM Total Leverage | C79: =C72/C32 -> 0 | D79: =D72/D32 -> 0 | E79: =E72/E32 -> 0 | F79: =F72/F32 -> 0 | G79: =G72/G32 -> 0 | H79: =H72/H32 -> 0 | M79: =SUM(M72/SUM(J32:M32)) -> 0 | N79: =SUM(N72/SUM(K32:N32)) -> 0 | O79: =SUM(O72/SUM(L32:O32)) -> 0 | P79: =SUM(P72/SUM(M32:P32)) -> 0.10322311 | Q79: =SUM(Q72/SUM(N32:Q32)) -> 0 | R79: =SUM(R72/SUM(O32:R32)) -> 0 | S79: =SUM(S72/SUM(P32:S32)) -> 0 | T79: =SUM(T72/SUM(Q32:T32)) -> 0.10691477 | ... X79: =SUM(X72/SUM(U32:X32)) -> 0.28935258 | Z79: =Z72/Z32 -> 0 | AA79: =AA72/AA32 -> 0 | AB79: =AB72/AB32 -> 0 | AC79: =AC72/AC32 -> 0.10322311 | AD79: =AD72/AD32 -> 0 | AE79: =AE72/AE32 -> 0 | AF79: =AF72/AF32 -> 0 | AG79: =AG72/AG32 -> 0.10691477 | ... AK79: =AK72/AK32 -> 0.28935258
B80: LTM Net Leverage | C80: =SUM(C72-C51)/C32 -> -0.3211204 | D80: =SUM(D72-D51)/D32 -> -1.5462759 | E80: =SUM(E72-E51)/E32 -> -0.26751615 | F80: =SUM(F72-F51)/F32 -> -0.3837062 | G80: =SUM(G72-G51)/G32 -> -0.3891113 | H80: =SUM(H72-H51)/H32 -> -0.37508034 | M80: =SUM(M72-M51)/SUM(J32:M32) -> -0.3837062 | N80: =SUM(N72-N51)/SUM(K32:N32) -> -0.33116252 | O80: =SUM(O72-O51)/SUM(L32:O32) -> -0.20215646 | P80: =SUM(P72-P51)/SUM(M32:P32) -> 0.038874541 | Q80: =SUM(Q72-Q51)/SUM(N32:Q32) -> -0.3891113 | R80: =SUM(R72-R51)/SUM(O32:R32) -> -0.27094886 | S80: =SUM(S72-S51)/SUM(P32:S32) -> -0.22084145 | T80: =SUM(T72-T51)/SUM(Q32:T32) -> 0.011734391 | ... X80: =SUM(X72-X51)/SUM(U32:X32) -> 0.18188083 | Z80: =SUM(Z72-Z51)/Z32 -> -0.3837062 | AA80: =SUM(AA72-AA51)/AA32 -> -0.33116252 | AB80: =SUM(AB72-AB51)/AB32 -> -0.20215646 | AC80: =SUM(AC72-AC51)/AC32 -> 0.038874541 | AD80: =SUM(AD72-AD51)/AD32 -> -0.3891113 | AE80: =SUM(AE72-AE51)/AE32 -> -0.27094886 | AF80: =SUM(AF72-AF51)/AF32 -> -0.22084145 | AG80: =SUM(AG72-AG51)/AG32 -> 0.011734391 | ... AK80: =SUM(AK72-AK51)/AK32 -> 0.18188083
B81: LTM Interest Coverage | C81: =C32/-C37 -> #DIV/0! | D81: =D32/-D37 -> 96.822241 | E81: =E32/-E37 -> 756.66557 | F81: =F32/-F37 -> 899.45089 | G81: =G32/-G37 -> 592.1596 | H81: =H32/-H37 -> 450.78168 | M81: {=SUM(J32:M32)/SUM(-J37:M37)} -> 899.45089 | N81: {=SUM(K32:N32)/SUM(-K37:N37)} -> 898.90692 | O81: {=SUM(L32:O32)/SUM(-L37:O37)} -> 1778.3599 | P81: {=SUM(M32:P32)/SUM(-M37:P37)} -> 3505.5315 | Q81: {=SUM(N32:Q32)/SUM(-N37:Q37)} -> 592.1596 | R81: {=SUM(O32:R32)/SUM(-O37:R37)} -> 581.9489 | S81: {=SUM(P32:S32)/SUM(-P37:S37)} -> 563.41329 | T81: {=SUM(Q32:T32)/SUM(-Q37:T37)} -> 561.4196 | ... X81: {=SUM(U32:X32)/SUM(-U37:X37)} -> 458.46189 | Z81: =Z32/-Z37 -> 899.45089 | AA81: =AA32/-AA37 -> 898.90692 | AB81: =AB32/-AB37 -> 1778.3599 | AC81: =AC32/-AC37 -> 3505.5315 | AD81: =AD32/-AD37 -> 592.1596 | AE81: =AE32/-AE37 -> 581.9489 | AF81: =AF32/-AF37 -> 563.41329 | AG81: =AG32/-AG37 -> 561.4196 | ... AK81: =AK32/-AK37 -> 458.46189
B82: LTM Debt Service Coverage | C82: {=SUM(C32+C35)/SUM(-C36:C37)} -> 6.8967362 | D82: {=SUM(D32+D35)/SUM(-D36:D37)} -> 19.841572 | E82: {=SUM(E32+E35)/SUM(-E36:E37)} -> 3.8656358 | F82: {=SUM(F32+F35)/SUM(-F36:F37)} -> 3.7290733 | G82: {=SUM(G32+G35)/SUM(-G36:G37)} -> 4.6294225 | H82: {=SUM(H32+H35)/SUM(-H36:H37)} -> 3.8448841 | M82: {=SUM(J32:M32+J35:M35)/SUM(-J36:M37)} -> 3.7290733 | N82: {=SUM(K32:N32+K35:N35)/SUM(-K36:N37)} -> 3.6176067 | O82: {=SUM(L32:O32+L35:O35)/SUM(-L36:O37)} -> 4.0862895 | P82: {=SUM(M32:P32+M35:P35)/SUM(-M36:P37)} -> 4.1179107 | Q82: {=SUM(N32:Q32+N35:Q35)/SUM(-N36:Q37)} -> 4.6294225 | R82: {=SUM(O32:R32+O35:R35)/SUM(-O36:R37)} -> 4.5527427 | S82: {=SUM(P32:S32+P35:S35)/SUM(-P36:S37)} -> 3.880615 | T82: {=SUM(Q32:T32+Q35:T35)/SUM(-Q36:T37)} -> 3.7823238 | ... X82: {=SUM(U32:X32+U35:X35)/SUM(-U36:X37)} -> 3.9760048 | Z82: {=SUM(Z32+Z35)/SUM(-Z36:Z37)} -> 3.7290733 | AA82: {=SUM(AA32+AA35)/SUM(-AA36:AA37)} -> 3.6176067 | AB82: {=SUM(AB32+AB35)/SUM(-AB36:AB37)} -> 4.0862895 | AC82: {=SUM(AC32+AC35)/SUM(-AC36:AC37)} -> 4.1179107 | AD82: {=SUM(AD32+AD35)/SUM(-AD36:AD37)} -> 4.6294225 | AE82: {=SUM(AE32+AE35)/SUM(-AE36:AE37)} -> 4.5527427 | AF82: {=SUM(AF32+AF35)/SUM(-AF36:AF37)} -> 3.880615 | AG82: {=SUM(AG32+AG35)/SUM(-AG36:AG37)} -> 3.7823238 | ... AK82: {=SUM(AK32+AK35)/SUM(-AK36:AK37)} -> 3.9760048
B83: LTM Fixed Charge Coverage | C83: {=SUM(C32)/SUM(-C35:C37)} -> 2.8255137 | D83: {=SUM(D32)/SUM(-D35:D37)} -> 3.7940014 | E83: {=SUM(E32)/SUM(-E35:E37)} -> 2.9602103 | F83: {=SUM(F32)/SUM(-F35:F37)} -> 2.5843303 | G83: {=SUM(G32)/SUM(-G35:G37)} -> 2.5692382 | H83: {=SUM(H32)/SUM(-H35:H37)} -> 2.4517587 | M83: {=SUM(J32:M32)/SUM(-J35:M37)} -> 2.5843303 | N83: {=SUM(K32:N32)/SUM(-K35:N37)} -> 2.44794 | O83: {=SUM(L32:O32)/SUM(-L35:O37)} -> 2.4971968 | P83: {=SUM(M32:P32)/SUM(-M35:P37)} -> 2.4359851 | Q83: {=SUM(N32:Q32)/SUM(-N35:Q37)} -> 2.5692382 | R83: {=SUM(O32:R32)/SUM(-O35:R37)} -> 2.5804725 | S83: {=SUM(P32:S32)/SUM(-P35:S37)} -> 2.3654336 | T83: {=SUM(Q32:T32)/SUM(-Q35:T37)} -> 2.3165522 | ... X83: {=SUM(U32:X32)/SUM(-U35:X37)} -> 2.6594386 | Z83: {=SUM(Z32)/SUM(-Z35:Z37)} -> 2.5843303 | AA83: {=SUM(AA32)/SUM(-AA35:AA37)} -> 2.44794 | AB83: {=SUM(AB32)/SUM(-AB35:AB37)} -> 2.4971968 | AC83: {=SUM(AC32)/SUM(-AC35:AC37)} -> 2.4359851 | AD83: {=SUM(AD32)/SUM(-AD35:AD37)} -> 2.5692382 | AE83: {=SUM(AE32)/SUM(-AE35:AE37)} -> 2.5804725 | AF83: {=SUM(AF32)/SUM(-AF35:AF37)} -> 2.3654336 | AG83: {=SUM(AG32)/SUM(-AG35:AG37)} -> 2.3165522 | ... AK83: {=SUM(AK32)/SUM(-AK35:AK37)} -> 2.6594386
B84: Debt-to-Book Capitalization | C84: =C75/C72 -> #DIV/0! | D84: =D75/D72 -> #DIV/0! | E84: =E75/E72 -> #DIV/0! | F84: =F75/F72 -> #DIV/0! | G84: =G75/G72 -> #DIV/0! | H84: =H75/H72 -> #DIV/0! | M84: =M75/M72 -> #DIV/0! | N84: =N75/N72 -> #DIV/0! | O84: =O75/O72 -> #DIV/0! | P84: =P75/P72 -> 11.381484 | Q84: =Q75/Q72 -> #DIV/0! | R84: =R75/R72 -> #DIV/0! | S84: =S75/S72 -> #DIV/0! | T84: =T75/T72 -> 12.662539 | ... X84: =X75/X72 -> 5.772365 | Z84: =Z75/Z72 -> #DIV/0! | AA84: =AA75/AA72 -> #DIV/0! | AB84: =AB75/AB72 -> #DIV/0! | AC84: =AC75/AC72 -> 11.381484 | AD84: =AD75/AD72 -> #DIV/0! | AE84: =AE75/AE72 -> #DIV/0! | AF84: =AF75/AF72 -> #DIV/0! | AG84: =AG75/AG72 -> 12.662539 | ... AK84: =AK75/AK72 -> 5.772365
