Workbook

Sheet Historical Financials
B2: Starbucks Corp (NASDAQ: SBUX)
B3: Historical Financials
B4: ($ In Millions, except EPS)
A6: X | B6: Income Statement | C6: FYE | D6: FYE | H6: Quarterly | N6: Quarterly | AA6: LTM | AG6: Variance
B7: Fiscal Period | C7: 2022 | D7: 2023 | E7: 2024 | F7: 2025 | H7: 1Q23 | I7: 2Q23 | J7: 3Q23 | K7: 4Q23 | L7: 1Q24 | M7: 2Q24 | N7: 3Q24 | O7: 4Q24 | P7: 1Q25 | Q7: 2Q25 | R7: 3Q25 | S7: 4Q25 | T7: 1Q26 | V7: =K7 -> 4Q23 | W7: =L7 -> 1Q24 | X7: =M7 -> 2Q24 | Y7: =N7 -> 3Q24 | Z7: =O7 -> 4Q24 | AA7: =P7 -> 1Q25 | AB7: =Q7 -> 2Q25 | AC7: =R7 -> 3Q25 | ... AE7: =T7 -> 1Q26
B8: Fiscal Period End Date | C8: 44836 | D8: 45200 | E8: 45564 | H8: XXX | I8: XXX | J8: XXX | K8: =D8 -> 45200 | L8: XXX | M8: XXX | N8: XXX | O8: =E8 -> 45564 | P8: XXX | Q8: XXX | R8: XXX | S8: =F8 -> 0 | T8: XXX | V8: =K8 -> 45200 | W8: =L8 -> XXX | X8: =M8 -> XXX | Y8: =N8 -> XXX | Z8: =O8 -> 45564 | AA8: =P8 -> XXX | AB8: =Q8 -> XXX | AC8: =R8 -> XXX | ... AE8: =T8 -> XXX
B10: Consolidated Revenue | C10: 32250.3 | D10: 35975.6 | E10: 36176.2 | K10: =SUM(D10-SUM(H10:J10)) -> 35975.6 | O10: =SUM(E10-SUM(L10:N10)) -> 36176.2 | S10: =SUM(F10-SUM(P10:R10)) -> 0 | V10: =SUM(H10:K10) -> 35975.6 | W10: =SUM(I10:L10) -> 35975.6 | X10: =SUM(J10:M10) -> 35975.6 | Y10: =SUM(K10:N10) -> 35975.6 | Z10: =SUM(L10:O10) -> 36176.2 | AA10: =SUM(M10:P10) -> 36176.2 | AB10: =SUM(N10:Q10) -> 36176.2 | AC10: =SUM(O10:R10) -> 36176.2 | ... AE10: =SUM(Q10:T10) -> 0 | AG10: =SUM(AE10/AA10)-1 -> -1
B11: Total Revenue | C11: =+SUM(C10:C10) -> 32250.3 | D11: =+SUM(D10:D10) -> 35975.6 | E11: =+SUM(E10:E10) -> 36176.2 | F11: =+SUM(F10:F10) -> 0 | H11: =+SUM(H10:H10) -> 0 | I11: =+SUM(I10:I10) -> 0 | J11: =+SUM(J10:J10) -> 0 | K11: =+SUM(K10:K10) -> 35975.6 | L11: =+SUM(L10:L10) -> 0 | M11: =+SUM(M10:M10) -> 0 | N11: =+SUM(N10:N10) -> 0 | O11: =+SUM(O10:O10) -> 36176.2 | ... T11: =+SUM(T10:T10) -> 0 | V11: =+SUM(V10:V10) -> 35975.6 | W11: =+SUM(W10:W10) -> 35975.6 | X11: =+SUM(X10:X10) -> 35975.6 | Y11: =+SUM(Y10:Y10) -> 35975.6 | Z11: =+SUM(Z10:Z10) -> 36176.2 | AA11: =+SUM(AA10:AA10) -> 36176.2 | AB11: =+SUM(AB10:AB10) -> 36176.2 | AC11: =+SUM(AC10:AC10) -> 36176.2 | ... AE11: =+SUM(AE10:AE10) -> 0 | AG11: =SUM(AE11/AA11)-1 -> -1
B14: Product and Distribution Costs | C14: -10317.4 | D14: -11409.1 | E14: -11180.6 | K14: =SUM(D14-SUM(H14:J14)) -> -11409.1 | O14: =SUM(E14-SUM(L14:N14)) -> -11180.6 | S14: =SUM(F14-SUM(P14:R14)) -> 0 | V14: =SUM(H14:K14) -> -11409.1 | W14: =SUM(I14:L14) -> -11409.1 | X14: =SUM(J14:M14) -> -11409.1 | Y14: =SUM(K14:N14) -> -11409.1 | Z14: =SUM(L14:O14) -> -11180.6 | AA14: =SUM(M14:P14) -> -11180.6 | AB14: =SUM(N14:Q14) -> -11180.6 | AC14: =SUM(O14:R14) -> -11180.6 | ... AE14: =SUM(Q14:T14) -> 0 | AG14: =SUM(AE14/AA14)-1 -> -1
B15: Store Operating Expenses | C15: -13561.8 | D15: -14720.3 | E15: -15286.5 | K15: =SUM(D15-SUM(H15:J15)) -> -14720.3 | O15: =SUM(E15-SUM(L15:N15)) -> -15286.5 | S15: =SUM(F15-SUM(P15:R15)) -> 0 | V15: =SUM(H15:K15) -> -14720.3 | W15: =SUM(I15:L15) -> -14720.3 | X15: =SUM(J15:M15) -> -14720.3 | Y15: =SUM(K15:N15) -> -14720.3 | Z15: =SUM(L15:O15) -> -15286.5 | AA15: =SUM(M15:P15) -> -15286.5 | AB15: =SUM(N15:Q15) -> -15286.5 | AC15: =SUM(O15:R15) -> -15286.5 | ... AE15: =SUM(Q15:T15) -> 0 | AG15: =SUM(AE15/AA15)-1 -> -1
B16: Other Operating Expenses | C16: -461.5 | D16: -539.4 | E16: -565.6 | K16: =SUM(D16-SUM(H16:J16)) -> -539.4 | O16: =SUM(E16-SUM(L16:N16)) -> -565.6 | S16: =SUM(F16-SUM(P16:R16)) -> 0 | V16: =SUM(H16:K16) -> -539.4 | W16: =SUM(I16:L16) -> -539.4 | X16: =SUM(J16:M16) -> -539.4 | Y16: =SUM(K16:N16) -> -539.4 | Z16: =SUM(L16:O16) -> -565.6 | AA16: =SUM(M16:P16) -> -565.6 | AB16: =SUM(N16:Q16) -> -565.6 | AC16: =SUM(O16:R16) -> -565.6 | ... AE16: =SUM(Q16:T16) -> 0 | AG16: =SUM(AE16/AA16)-1 -> -1
B17: Depreciation and Amortization | C17: -1447.9 | D17: -1362.6 | E17: -1512.6 | K17: =SUM(D17-SUM(H17:J17)) -> -1362.6 | O17: =SUM(E17-SUM(L17:N17)) -> -1512.6 | S17: =SUM(F17-SUM(P17:R17)) -> 0 | V17: =SUM(H17:K17) -> -1362.6 | W17: =SUM(I17:L17) -> -1362.6 | X17: =SUM(J17:M17) -> -1362.6 | Y17: =SUM(K17:N17) -> -1362.6 | Z17: =SUM(L17:O17) -> -1512.6 | AA17: =SUM(M17:P17) -> -1512.6 | AB17: =SUM(N17:Q17) -> -1512.6 | AC17: =SUM(O17:R17) -> -1512.6 | ... AE17: =SUM(Q17:T17) -> 0 | AG17: =SUM(AE17/AA17)-1 -> -1
B18: G&A | C18: -2032 | D18: -2441.3 | E18: -2523.3 | K18: =SUM(D18-SUM(H18:J18)) -> -2441.3 | O18: =SUM(E18-SUM(L18:N18)) -> -2523.3 | S18: =SUM(F18-SUM(P18:R18)) -> 0 | V18: =SUM(H18:K18) -> -2441.3 | W18: =SUM(I18:L18) -> -2441.3 | X18: =SUM(J18:M18) -> -2441.3 | Y18: =SUM(K18:N18) -> -2441.3 | Z18: =SUM(L18:O18) -> -2523.3 | AA18: =SUM(M18:P18) -> -2523.3 | AB18: =SUM(N18:Q18) -> -2523.3 | AC18: =SUM(O18:R18) -> -2523.3 | ... AE18: =SUM(Q18:T18) -> 0 | AG18: =SUM(AE18/AA18)-1 -> -1
B19: Restructuring and Impairments | C19: -46 | D19: -21.8 | E19: 0 | K19: =SUM(D19-SUM(H19:J19)) -> -21.8 | O19: =SUM(E19-SUM(L19:N19)) -> 0 | S19: =SUM(F19-SUM(P19:R19)) -> 0 | V19: =SUM(H19:K19) -> -21.8 | W19: =SUM(I19:L19) -> -21.8 | X19: =SUM(J19:M19) -> -21.8 | Y19: =SUM(K19:N19) -> -21.8 | Z19: =SUM(L19:O19) -> 0 | AA19: =SUM(M19:P19) -> 0 | AB19: =SUM(N19:Q19) -> 0 | AC19: =SUM(O19:R19) -> 0 | ... AE19: =SUM(Q19:T19) -> 0 | AG19: =SUM(AE19/AA19)-1 -> #DIV/0!
B20: Income From Equity Investees | C20: 234.1 | D20: 298.4 | E20: 301.2 | K20: =SUM(D20-SUM(H20:J20)) -> 298.4 | O20: =SUM(E20-SUM(L20:N20)) -> 301.2 | S20: =SUM(F20-SUM(P20:R20)) -> 0 | V20: =SUM(H20:K20) -> 298.4 | W20: =SUM(I20:L20) -> 298.4 | X20: =SUM(J20:M20) -> 298.4 | Y20: =SUM(K20:N20) -> 298.4 | Z20: =SUM(L20:O20) -> 301.2 | AA20: =SUM(M20:P20) -> 301.2 | AB20: =SUM(N20:Q20) -> 301.2 | AC20: =SUM(O20:R20) -> 301.2 | ... AE20: =SUM(Q20:T20) -> 0
B21: Gains From Sale of Assets | C21: 0 | D21: 91.3 | E21: 0 | K21: =SUM(D21-SUM(H21:J21)) -> 91.3 | O21: =SUM(E21-SUM(L21:N21)) -> 0 | S21: =SUM(F21-SUM(P21:R21)) -> 0 | V21: =SUM(H21:K21) -> 91.3 | W21: =SUM(I21:L21) -> 91.3 | X21: =SUM(J21:M21) -> 91.3 | Y21: =SUM(K21:N21) -> 91.3 | Z21: =SUM(L21:O21) -> 0 | AA21: =SUM(M21:P21) -> 0 | AB21: =SUM(N21:Q21) -> 0 | AC21: =SUM(O21:R21) -> 0 | ... AE21: =SUM(Q21:T21) -> 0
B22: Operating Profit | C22: =+SUM(C11+SUM(C14:C21)) -> 4617.8 | D22: =+SUM(D11+SUM(D14:D21)) -> 5870.8 | E22: =+SUM(E11+SUM(E14:E21)) -> 5408.8 | F22: =+SUM(F11+SUM(F14:F21)) -> 0 | H22: =+SUM(H11+SUM(H14:H21)) -> 0 | I22: =+SUM(I11+SUM(I14:I21)) -> 0 | J22: =+SUM(J11+SUM(J14:J21)) -> 0 | K22: =+SUM(K11+SUM(K14:K21)) -> 5870.8 | L22: =+SUM(L11+SUM(L14:L21)) -> 0 | M22: =+SUM(M11+SUM(M14:M21)) -> 0 | N22: =+SUM(N11+SUM(N14:N21)) -> 0 | O22: =+SUM(O11+SUM(O14:O21)) -> 5408.8 | ... T22: =+SUM(T11+SUM(T14:T21)) -> 0 | V22: =+SUM(V11+SUM(V14:V21)) -> 5870.8 | W22: =+SUM(W11+SUM(W14:W21)) -> 5870.8 | X22: =+SUM(X11+SUM(X14:X21)) -> 5870.8 | Y22: =+SUM(Y11+SUM(Y14:Y21)) -> 5870.8 | Z22: =+SUM(Z11+SUM(Z14:Z21)) -> 5408.8 | AA22: =+SUM(AA11+SUM(AA14:AA21)) -> 5408.8 | AB22: =+SUM(AB11+SUM(AB14:AB21)) -> 5408.8 | AC22: =+SUM(AC11+SUM(AC14:AC21)) -> 5408.8 | ... AE22: =+SUM(AE11+SUM(AE14:AE21)) -> 0 | AG22: =SUM(AE22/AA22)-1 -> -1
B23: Operating Margin (%) | C23: =C22/C11 -> 0.14318626 | D23: =D22/D11 -> 0.16318838 | E23: =E22/E11 -> 0.14951266 | F23: =F22/F11 -> #DIV/0! | H23: =H22/H11 -> #DIV/0! | I23: =I22/I11 -> #DIV/0! | J23: =J22/J11 -> #DIV/0! | K23: =K22/K11 -> 0.16318838 | L23: =L22/L11 -> #DIV/0! | M23: =M22/M11 -> #DIV/0! | N23: =N22/N11 -> #DIV/0! | O23: =O22/O11 -> 0.14951266 | ... T23: =T22/T11 -> #DIV/0! | V23: =V22/V11 -> 0.16318838 | W23: =W22/W11 -> 0.16318838 | X23: =X22/X11 -> 0.16318838 | Y23: =Y22/Y11 -> 0.16318838 | Z23: =Z22/Z11 -> 0.14951266 | AA23: =AA22/AA11 -> 0.14951266 | AB23: =AB22/AB11 -> 0.14951266 | AC23: =AC22/AC11 -> 0.14951266 | ... AE23: =AE22/AE11 -> #DIV/0! | AG23: =SUM(AE23-AA23)*1000 -> #DIV/0!
B25: Interest Income and Other Net | C25: 97 | D25: 81.2 | E25: 122.8 | K25: =SUM(D25-SUM(H25:J25)) -> 81.2 | O25: =SUM(E25-SUM(L25:N25)) -> 122.8 | S25: =SUM(F25-SUM(P25:R25)) -> 0 | V25: =SUM(H25:K25) -> 81.2 | W25: =SUM(I25:L25) -> 81.2 | X25: =SUM(J25:M25) -> 81.2 | Y25: =SUM(K25:N25) -> 81.2 | Z25: =SUM(L25:O25) -> 122.8 | AA25: =SUM(M25:P25) -> 122.8 | AB25: =SUM(N25:Q25) -> 122.8 | AC25: =SUM(O25:R25) -> 122.8 | ... AE25: =SUM(Q25:T25) -> 0 | AG25: =SUM(AE25/AA25)-1 -> -1
B26: Interest Expense | C26: -482.9 | D26: -550.1 | E26: -562 | K26: =SUM(D26-SUM(H26:J26)) -> -550.1 | O26: =SUM(E26-SUM(L26:N26)) -> -562 | S26: =SUM(F26-SUM(P26:R26)) -> 0 | V26: =SUM(H26:K26) -> -550.1 | W26: =SUM(I26:L26) -> -550.1 | X26: =SUM(J26:M26) -> -550.1 | Y26: =SUM(K26:N26) -> -550.1 | Z26: =SUM(L26:O26) -> -562 | AA26: =SUM(M26:P26) -> -562 | AB26: =SUM(N26:Q26) -> -562 | AC26: =SUM(O26:R26) -> -562 | ... AE26: =SUM(Q26:T26) -> 0 | AG26: =SUM(AE26/AA26)-1 -> -1
B27: Earnings before Taxes | C27: =SUM(C25:C26)+C22 -> 4231.9 | D27: =SUM(D25:D26)+D22 -> 5401.9 | E27: =SUM(E25:E26)+E22 -> 4969.6 | F27: =SUM(F25:F26)+F22 -> 0 | H27: =SUM(H25:H26)+H22 -> 0 | I27: =SUM(I25:I26)+I22 -> 0 | J27: =SUM(J25:J26)+J22 -> 0 | K27: =SUM(K25:K26)+K22 -> 5401.9 | L27: =SUM(L25:L26)+L22 -> 0 | M27: =SUM(M25:M26)+M22 -> 0 | N27: =SUM(N25:N26)+N22 -> 0 | O27: =SUM(O25:O26)+O22 -> 4969.6 | ... T27: =SUM(T25:T26)+T22 -> 0 | V27: =SUM(V25:V26)+V22 -> 5401.9 | W27: =SUM(W25:W26)+W22 -> 5401.9 | X27: =SUM(X25:X26)+X22 -> 5401.9 | Y27: =SUM(Y25:Y26)+Y22 -> 5401.9 | Z27: =SUM(Z25:Z26)+Z22 -> 4969.6 | AA27: =SUM(AA25:AA26)+AA22 -> 4969.6 | AB27: =SUM(AB25:AB26)+AB22 -> 4969.6 | AC27: =SUM(AC25:AC26)+AC22 -> 4969.6 | ... AE27: =SUM(AE25:AE26)+AE22 -> 0 | AG27: =SUM(AE27/AA27)-1 -> -1
B28: EBT Margin (%) | C28: =C27/C11 -> 0.13122048 | D28: =D27/D11 -> 0.15015455 | E28: =E27/E11 -> 0.13737208 | F28: =F27/F11 -> #DIV/0! | H28: =H27/H11 -> #DIV/0! | I28: =I27/I11 -> #DIV/0! | J28: =J27/J11 -> #DIV/0! | K28: =K27/K11 -> 0.15015455 | L28: =L27/L11 -> #DIV/0! | M28: =M27/M11 -> #DIV/0! | N28: =N27/N11 -> #DIV/0! | O28: =O27/O11 -> 0.13737208 | ... T28: =T27/T11 -> #DIV/0! | V28: =V27/V11 -> 0.15015455 | W28: =W27/W11 -> 0.15015455 | X28: =X27/X11 -> 0.15015455 | Y28: =Y27/Y11 -> 0.15015455 | Z28: =Z27/Z11 -> 0.13737208 | AA28: =AA27/AA11 -> 0.13737208 | AB28: =AB27/AB11 -> 0.13737208 | AC28: =AC27/AC11 -> 0.13737208 | ... AE28: =AE27/AE11 -> #DIV/0! | AG28: =SUM(AE28-AA28)*1000 -> #DIV/0!
B30: Income tax expense | C30: -948.5 | D30: -1277.2 | E30: -1207.3 | K30: =SUM(D30-SUM(H30:J30)) -> -1277.2 | O30: =SUM(E30-SUM(L30:N30)) -> -1207.3 | S30: =SUM(F30-SUM(P30:R30)) -> 0 | V30: =SUM(H30:K30) -> -1277.2 | W30: =SUM(I30:L30) -> -1277.2 | X30: =SUM(J30:M30) -> -1277.2 | Y30: =SUM(K30:N30) -> -1277.2 | Z30: =SUM(L30:O30) -> -1207.3 | AA30: =SUM(M30:P30) -> -1207.3 | AB30: =SUM(N30:Q30) -> -1207.3 | AC30: =SUM(O30:R30) -> -1207.3 | ... AE30: =SUM(Q30:T30) -> 0 | AG30: =SUM(AE30/AA30)-1 -> -1
B31: Net earnings including noncontrolling interests | C31: =SUM(C27+SUM(C30:C30)) -> 3283.4 | D31: =SUM(D27+SUM(D30:D30)) -> 4124.7 | E31: =SUM(E27+SUM(E30:E30)) -> 3762.3 | F31: =SUM(F27+SUM(F30:F30)) -> 0 | H31: =SUM(H27+SUM(H30:H30)) -> 0 | I31: =SUM(I27+SUM(I30:I30)) -> 0 | J31: =SUM(J27+SUM(J30:J30)) -> 0 | K31: =SUM(K27+SUM(K30:K30)) -> 4124.7 | L31: =SUM(L27+SUM(L30:L30)) -> 0 | M31: =SUM(M27+SUM(M30:M30)) -> 0 | N31: =SUM(N27+SUM(N30:N30)) -> 0 | O31: =SUM(O27+SUM(O30:O30)) -> 3762.3 | ... T31: =SUM(T27+SUM(T30:T30)) -> 0 | V31: =SUM(V27+SUM(V30:V30)) -> 4124.7 | W31: =SUM(W27+SUM(W30:W30)) -> 4124.7 | X31: =SUM(X27+SUM(X30:X30)) -> 4124.7 | Y31: =SUM(Y27+SUM(Y30:Y30)) -> 4124.7 | Z31: =SUM(Z27+SUM(Z30:Z30)) -> 3762.3 | AA31: =SUM(AA27+SUM(AA30:AA30)) -> 3762.3 | AB31: =SUM(AB27+SUM(AB30:AB30)) -> 3762.3 | AC31: =SUM(AC27+SUM(AC30:AC30)) -> 3762.3 | ... AE31: =SUM(AE27+SUM(AE30:AE30)) -> 0 | AG31: =SUM(AE31/AA31)-1 -> -1
B33: Net earnings attributable to noncontrolling interests | C33: 1.8 | D33: 0.2 | E33: 1.4 | K33: =SUM(D33-SUM(H33:J33)) -> 0.2 | O33: =SUM(E33-SUM(L33:N33)) -> 1.4 | S33: =SUM(F33-SUM(P33:R33)) -> 0 | V33: =SUM(H33:K33) -> 0.2 | W33: =SUM(I33:L33) -> 0.2 | X33: =SUM(J33:M33) -> 0.2 | Y33: =SUM(K33:N33) -> 0.2 | Z33: =SUM(L33:O33) -> 1.4 | AA33: =SUM(M33:P33) -> 1.4 | AB33: =SUM(N33:Q33) -> 1.4 | AC33: =SUM(O33:R33) -> 1.4 | ... AE33: =SUM(Q33:T33) -> 0 | AG33: =SUM(AE33/AA33)-1 -> -1
B34: Net earnings attributable to Starbucks | C34: =SUM(C31+SUM(C33:C33)) -> 3285.2 | D34: =SUM(D31+SUM(D33:D33)) -> 4124.9 | E34: =SUM(E31+SUM(E33:E33)) -> 3763.7 | F34: =SUM(F31+SUM(F33:F33)) -> 0 | H34: =SUM(H31+SUM(H33:H33)) -> 0 | I34: =SUM(I31+SUM(I33:I33)) -> 0 | J34: =SUM(J31+SUM(J33:J33)) -> 0 | K34: =SUM(K31+SUM(K33:K33)) -> 4124.9 | L34: =SUM(L31+SUM(L33:L33)) -> 0 | M34: =SUM(M31+SUM(M33:M33)) -> 0 | N34: =SUM(N31+SUM(N33:N33)) -> 0 | O34: =SUM(O31+SUM(O33:O33)) -> 3763.7 | ... T34: =SUM(T31+SUM(T33:T33)) -> 0 | V34: =SUM(V31+SUM(V33:V33)) -> 4124.9 | W34: =SUM(W31+SUM(W33:W33)) -> 4124.9 | X34: =SUM(X31+SUM(X33:X33)) -> 4124.9 | Y34: =SUM(Y31+SUM(Y33:Y33)) -> 4124.9 | Z34: =SUM(Z31+SUM(Z33:Z33)) -> 3763.7 | AA34: =SUM(AA31+SUM(AA33:AA33)) -> 3763.7 | AB34: =SUM(AB31+SUM(AB33:AB33)) -> 3763.7 | AC34: =SUM(AC31+SUM(AC33:AC33)) -> 3763.7 | ... AE34: =SUM(AE31+SUM(AE33:AE33)) -> 0 | AG34: =SUM(AE34/AA34)-1 -> -1
B35: Net Margin (%) | C35: =C34/C15 -> -0.24223923 | D35: =D34/D15 -> -0.28021847 | E35: =E34/E15 -> -0.24621071 | F35: =F34/F15 -> #DIV/0! | H35: =H34/H15 -> #DIV/0! | I35: =I34/I15 -> #DIV/0! | J35: =J34/J15 -> #DIV/0! | K35: =K34/K15 -> -0.28021847 | L35: =L34/L15 -> #DIV/0! | M35: =M34/M15 -> #DIV/0! | N35: =N34/N15 -> #DIV/0! | O35: =O34/O15 -> -0.24621071 | ... T35: =T34/T15 -> #DIV/0! | V35: =V34/V15 -> -0.28021847 | W35: =W34/W15 -> -0.28021847 | X35: =X34/X15 -> -0.28021847 | Y35: =Y34/Y15 -> -0.28021847 | Z35: =Z34/Z15 -> -0.24621071 | AA35: =AA34/AA15 -> -0.24621071 | AB35: =AB34/AB15 -> -0.24621071 | AC35: =AC34/AC15 -> -0.24621071 | ... AE35: =AE34/AE15 -> #DIV/0! | AG35: =SUM(AE35-AA35)*1000 -> #DIV/0!
B37: Basic shares | C37: 1153.3 | D37: 1146.8 | E37: 1133.8 | K37: =D37 -> 1146.8 | O37: =E37 -> 1133.8 | S37: =F37 -> 0 | V37: =K37 -> 1146.8 | W37: =L37 -> 0 | X37: =M37 -> 0 | Y37: =N37 -> 0 | Z37: =O37 -> 1133.8 | AA37: =P37 -> 0 | AB37: =Q37 -> 0 | AC37: =R37 -> 0 | ... AE37: =T37 -> 0 | AG37: =SUM(AE37/AA37)-1 -> #DIV/0!
B38: Basic EPS | C38: =C34/C37 -> 2.8485216 | D38: =D34/D37 -> 3.5968783 | E38: =E34/E37 -> 3.3195449 | F38: =F34/F37 -> #DIV/0! | H38: =H34/H37 -> #DIV/0! | I38: =I34/I37 -> #DIV/0! | J38: =J34/J37 -> #DIV/0! | K38: =K34/K37 -> 3.5968783 | L38: =L34/L37 -> #DIV/0! | M38: =M34/M37 -> #DIV/0! | N38: =N34/N37 -> #DIV/0! | O38: =O34/O37 -> 3.3195449 | ... T38: =T34/T37 -> #DIV/0! | V38: =V34/V37 -> 3.5968783 | W38: =W34/W37 -> #DIV/0! | X38: =X34/X37 -> #DIV/0! | Y38: =Y34/Y37 -> #DIV/0! | Z38: =Z34/Z37 -> 3.3195449 | AA38: =AA34/AA37 -> #DIV/0! | AB38: =AB34/AB37 -> #DIV/0! | AC38: =AC34/AC37 -> #DIV/0! | ... AE38: =AE34/AE37 -> #DIV/0! | AG38: =SUM(AE38/AA38)-1 -> #DIV/0!
B40: Fully Diluted Shares | C40: 1158.5 | D40: 1151.3 | E40: 1137.3 | K40: =D40 -> 1151.3 | O40: =E40 -> 1137.3 | S40: =F40 -> 0 | V40: =K40 -> 1151.3 | W40: =L40 -> 0 | X40: =M40 -> 0 | Y40: =N40 -> 0 | Z40: =O40 -> 1137.3 | AA40: =P40 -> 0 | AB40: =Q40 -> 0 | AC40: =R40 -> 0 | ... AE40: =T40 -> 0 | AG40: =SUM(AE40/AA40)-1 -> #DIV/0!
B41: Diluted EPS | C41: =C34/C40 -> 2.8357359 | D41: =D34/D40 -> 3.5828194 | E41: =E34/E40 -> 3.3093291 | F41: =F34/F40 -> #DIV/0! | H41: =H34/H40 -> #DIV/0! | I41: =I34/I40 -> #DIV/0! | J41: =J34/J40 -> #DIV/0! | K41: =K34/K40 -> 3.5828194 | L41: =L34/L40 -> #DIV/0! | M41: =M34/M40 -> #DIV/0! | N41: =N34/N40 -> #DIV/0! | O41: =O34/O40 -> 3.3093291 | ... T41: =T34/T40 -> #DIV/0! | V41: =V34/V40 -> 3.5828194 | W41: =W34/W40 -> #DIV/0! | X41: =X34/X40 -> #DIV/0! | Y41: =Y34/Y40 -> #DIV/0! | Z41: =Z34/Z40 -> 3.3093291 | AA41: =AA34/AA40 -> #DIV/0! | AB41: =AB34/AB40 -> #DIV/0! | AC41: =AC34/AC40 -> #DIV/0! | ... AE41: =AE34/AE40 -> #DIV/0! | AG41: =SUM(AE41/AA41)-1 -> #DIV/0!
A43: X | B43: Balance Sheet | N43: Quarterly | AA43: LTM | AG43: Variance
B44: =B7 -> Fiscal Period | C44: =C7 -> 2022 | D44: =D7 -> 2023 | E44: =E7 -> 2024 | F44: =F7 -> 2025 | H44: =H7 -> 1Q23 | I44: =I7 -> 2Q23 | J44: =J7 -> 3Q23 | K44: =K7 -> 4Q23 | L44: =L7 -> 1Q24 | M44: =M7 -> 2Q24 | N44: =N7 -> 3Q24 | O44: =O7 -> 4Q24 | ... T44: =T7 -> 1Q26 | V44: =V7 -> 4Q23 | W44: =W7 -> 1Q24 | X44: =X7 -> 2Q24 | Y44: =Y7 -> 3Q24 | Z44: =Z7 -> 4Q24 | AA44: =AA7 -> 1Q25 | AB44: =AB7 -> 2Q25 | AC44: =AC7 -> 3Q25 | ... AE44: =AE7 -> 1Q26
B45: =B8 -> Fiscal Period End Date | C45: =C8 -> 44836 | D45: =D8 -> 45200 | E45: =E8 -> 45564 | F45: =F8 -> 0 | H45: =H8 -> XXX | I45: =I8 -> XXX | J45: =J8 -> XXX | K45: =K8 -> 45200 | L45: =L8 -> XXX | M45: =M8 -> XXX | N45: =N8 -> XXX | O45: =O8 -> 45564 | ... T45: =T8 -> XXX | V45: =V8 -> 45200 | W45: =W8 -> XXX | X45: =X8 -> XXX | Y45: =Y8 -> XXX | Z45: =Z8 -> 45564 | AA45: =AA8 -> XXX | AB45: =AB8 -> XXX | AC45: =AC8 -> XXX | ... AE45: =AE8 -> XXX
B47: Current Assets
B48: Cash and cash equivalents | C48: 2818.4 | D48: 3551.5 | E48: 3286.2 | K48: =D48 -> 3551.5 | O48: =E48 -> 3286.2 | S48: =F48 -> 0 | V48: =K48 -> 3551.5 | W48: =L48 -> 0 | X48: =M48 -> 0 | Y48: =N48 -> 0 | Z48: =O48 -> 3286.2 | AA48: =P48 -> 0 | AB48: =Q48 -> 0 | AC48: =R48 -> 0 | ... AE48: =T48 -> 0 | AG48: =SUM(AE48/AA48)-1 -> #DIV/0!
B49: Short-term investments | C49: 364.5 | D49: 401.5 | E49: 257 | K49: =D49 -> 401.5 | O49: =E49 -> 257 | S49: =F49 -> 0 | V49: =K49 -> 401.5 | W49: =L49 -> 0 | X49: =M49 -> 0 | Y49: =N49 -> 0 | Z49: =O49 -> 257 | AA49: =P49 -> 0 | AB49: =Q49 -> 0 | AC49: =R49 -> 0 | ... AE49: =T49 -> 0 | AG49: =SUM(AE49/AA49)-1 -> #DIV/0!
B50: Accounts receivable, net | C50: 1175.5 | D50: 1184.1 | E50: 1213.8 | K50: =D50 -> 1184.1 | O50: =E50 -> 1213.8 | S50: =F50 -> 0 | V50: =K50 -> 1184.1 | W50: =L50 -> 0 | X50: =M50 -> 0 | Y50: =N50 -> 0 | Z50: =O50 -> 1213.8 | AA50: =P50 -> 0 | AB50: =Q50 -> 0 | AC50: =R50 -> 0 | ... AE50: =T50 -> 0 | AG50: =SUM(AE50/AA50)-1 -> #DIV/0!
B51: Inventories | C51: 2176.6 | D51: 1806.4 | E51: 1777.3 | K51: =D51 -> 1806.4 | O51: =E51 -> 1777.3 | S51: =F51 -> 0 | V51: =K51 -> 1806.4 | W51: =L51 -> 0 | X51: =M51 -> 0 | Y51: =N51 -> 0 | Z51: =O51 -> 1777.3 | AA51: =P51 -> 0 | AB51: =Q51 -> 0 | AC51: =R51 -> 0 | ... AE51: =T51 -> 0 | AG51: =SUM(AE51/AA51)-1 -> #DIV/0!
B52: Prepaid expenses and other current assets | C52: 483.7 | D52: 359.9 | E52: 313.1 | K52: =D52 -> 359.9 | O52: =E52 -> 313.1 | S52: =F52 -> 0 | V52: =K52 -> 359.9 | W52: =L52 -> 0 | X52: =M52 -> 0 | Y52: =N52 -> 0 | Z52: =O52 -> 313.1 | AA52: =P52 -> 0 | AB52: =Q52 -> 0 | AC52: =R52 -> 0 | ... AE52: =T52 -> 0 | AG52: =SUM(AE52/AA52)-1 -> #DIV/0!
B53: Total Current Assets | C53: =SUM(C48:C52) -> 7018.7 | D53: =SUM(D48:D52) -> 7303.4 | E53: =SUM(E48:E52) -> 6847.4 | F53: =SUM(F48:F52) -> 0 | H53: =SUM(H48:H52) -> 0 | I53: =SUM(I48:I52) -> 0 | J53: =SUM(J48:J52) -> 0 | K53: =SUM(K48:K52) -> 7303.4 | L53: =SUM(L48:L52) -> 0 | M53: =SUM(M48:M52) -> 0 | N53: =SUM(N48:N52) -> 0 | O53: =SUM(O48:O52) -> 6847.4 | ... T53: =SUM(T48:T52) -> 0 | V53: =SUM(V48:V52) -> 7303.4 | W53: =SUM(W48:W52) -> 0 | X53: =SUM(X48:X52) -> 0 | Y53: =SUM(Y48:Y52) -> 0 | Z53: =SUM(Z48:Z52) -> 6847.4 | AA53: =SUM(AA48:AA52) -> 0 | AB53: =SUM(AB48:AB52) -> 0 | AC53: =SUM(AC48:AC52) -> 0 | ... AE53: =SUM(AE48:AE52) -> 0 | AG53: =SUM(AE53/AA53)-1 -> #DIV/0!
B55: Non-Current Assets
B56: Long-term investments | C56: 279.1 | D56: 247.4 | E56: 276 | K56: =D56 -> 247.4 | O56: =E56 -> 276 | S56: =F56 -> 0 | V56: =K56 -> 247.4 | W56: =L56 -> 0 | X56: =M56 -> 0 | Y56: =N56 -> 0 | Z56: =O56 -> 276 | AA56: =P56 -> 0 | AB56: =Q56 -> 0 | AC56: =R56 -> 0 | ... AE56: =T56 -> 0 | AG56: =SUM(AE56/AA56)-1 -> #DIV/0!
B57: Equity Investments | C57: 311.2 | D57: 439.9 | E57: 463.9 | K57: =D57 -> 439.9 | O57: =E57 -> 463.9 | S57: =F57 -> 0 | V57: =K57 -> 439.9 | W57: =L57 -> 0 | X57: =M57 -> 0 | Y57: =N57 -> 0 | Z57: =O57 -> 463.9 | AA57: =P57 -> 0 | AB57: =Q57 -> 0 | AC57: =R57 -> 0 | ... AE57: =T57 -> 0 | AG57: =SUM(AE57/AA57)-1 -> #DIV/0!
B58: PP&E, net | C58: 6560.5 | D58: 7387.1 | E58: 8665.5 | K58: =D58 -> 7387.1 | O58: =E58 -> 8665.5 | S58: =F58 -> 0 | V58: =K58 -> 7387.1 | W58: =L58 -> 0 | X58: =M58 -> 0 | Y58: =N58 -> 0 | Z58: =O58 -> 8665.5 | AA58: =P58 -> 0 | AB58: =Q58 -> 0 | AC58: =R58 -> 0 | ... AE58: =T58 -> 0 | AG58: =SUM(AE58/AA58)-1 -> #DIV/0!
B59: Operating lease, ROU asset | C59: 8015.6 | D59: 8412.6 | E59: 9286.2 | K59: =D59 -> 8412.6 | O59: =E59 -> 9286.2 | S59: =F59 -> 0 | V59: =K59 -> 8412.6 | W59: =L59 -> 0 | X59: =M59 -> 0 | Y59: =N59 -> 0 | Z59: =O59 -> 9286.2 | AA59: =P59 -> 0 | AB59: =Q59 -> 0 | AC59: =R59 -> 0 | ... AE59: =T59 -> 0 | AG59: =SUM(AE59/AA59)-1 -> #DIV/0!
B60: Deferred income taxes, net | C60: 1799.7 | D60: 1769.8 | E60: 1766.7 | K60: =D60 -> 1769.8 | O60: =E60 -> 1766.7 | S60: =F60 -> 0 | V60: =K60 -> 1769.8 | W60: =L60 -> 0 | X60: =M60 -> 0 | Y60: =N60 -> 0 | Z60: =O60 -> 1766.7 | AA60: =P60 -> 0 | AB60: =Q60 -> 0 | AC60: =R60 -> 0 | ... AE60: =T60 -> 0 | AG60: =SUM(AE60/AA60)-1 -> #DIV/0!
B61: Other long-term assets | C61: 554.2 | D61: 546.5 | E61: 617 | K61: =D61 -> 546.5 | O61: =E61 -> 617 | S61: =F61 -> 0 | V61: =K61 -> 546.5 | W61: =L61 -> 0 | X61: =M61 -> 0 | Y61: =N61 -> 0 | Z61: =O61 -> 617 | AA61: =P61 -> 0 | AB61: =Q61 -> 0 | AC61: =R61 -> 0 | ... AE61: =T61 -> 0 | AG61: =SUM(AE61/AA61)-1 -> #DIV/0!
B62: Other intangible assets | C62: 155.9 | D62: 120.5 | E62: 100.9 | K62: =D62 -> 120.5 | O62: =E62 -> 100.9 | S62: =F62 -> 0 | V62: =K62 -> 120.5 | W62: =L62 -> 0 | X62: =M62 -> 0 | Y62: =N62 -> 0 | Z62: =O62 -> 100.9 | AA62: =P62 -> 0 | AB62: =Q62 -> 0 | AC62: =R62 -> 0 | ... AE62: =T62 -> 0 | AG62: =SUM(AE62/AA62)-1 -> #DIV/0!
B63: Goodwill | C63: 3283.5 | D63: 3218.3 | E63: 3315.7 | K63: =D63 -> 3218.3 | O63: =E63 -> 3315.7 | S63: =F63 -> 0 | V63: =K63 -> 3218.3 | W63: =L63 -> 0 | X63: =M63 -> 0 | Y63: =N63 -> 0 | Z63: =O63 -> 3315.7 | AA63: =P63 -> 0 | AB63: =Q63 -> 0 | AC63: =R63 -> 0 | ... AE63: =T63 -> 0 | AG63: =SUM(AE63/AA63)-1 -> #DIV/0!
B64: Total Assets | C64: =SUM(C56:C63)+C53 -> 27978.4 | D64: =SUM(D56:D63)+D53 -> 29445.5 | E64: =SUM(E56:E63)+E53 -> 31339.3 | F64: =SUM(F56:F63)+F53 -> 0 | H64: =SUM(H56:H63)+H53 -> 0 | I64: =SUM(I56:I63)+I53 -> 0 | J64: =SUM(J56:J63)+J53 -> 0 | K64: =SUM(K56:K63)+K53 -> 29445.5 | L64: =SUM(L56:L63)+L53 -> 0 | M64: =SUM(M56:M63)+M53 -> 0 | N64: =SUM(N56:N63)+N53 -> 0 | O64: =SUM(O56:O63)+O53 -> 31339.3 | ... T64: =SUM(T56:T63)+T53 -> 0 | V64: =SUM(V56:V63)+V53 -> 29445.5 | W64: =SUM(W56:W63)+W53 -> 0 | X64: =SUM(X56:X63)+X53 -> 0 | Y64: =SUM(Y56:Y63)+Y53 -> 0 | Z64: =SUM(Z56:Z63)+Z53 -> 31339.3 | AA64: =SUM(AA56:AA63)+AA53 -> 0 | AB64: =SUM(AB56:AB63)+AB53 -> 0 | AC64: =SUM(AC56:AC63)+AC53 -> 0 | ... AE64: =SUM(AE56:AE63)+AE53 -> 0 | AG64: =SUM(AE64/AA64)-1 -> #DIV/0!
B66: Current Liabilities
B67: Accounts payable | C67: 1441.4 | D67: 1544.3 | E67: 1595.5 | K67: =D67 -> 1544.3 | O67: =E67 -> 1595.5 | S67: =F67 -> 0 | V67: =K67 -> 1544.3 | W67: =L67 -> 0 | X67: =M67 -> 0 | Y67: =N67 -> 0 | Z67: =O67 -> 1595.5 | AA67: =P67 -> 0 | AB67: =Q67 -> 0 | AC67: =R67 -> 0 | ... AE67: =T67 -> 0 | AG67: =SUM(AE67/AA67)-1 -> #DIV/0!
B68: Accrued payroll and benefits | C68: 761.7 | D68: 828.3 | E68: 786.6 | K68: =D68 -> 828.3 | O68: =E68 -> 786.6 | S68: =F68 -> 0 | V68: =K68 -> 828.3 | W68: =L68 -> 0 | X68: =M68 -> 0 | Y68: =N68 -> 0 | Z68: =O68 -> 786.6 | AA68: =P68 -> 0 | AB68: =Q68 -> 0 | AC68: =R68 -> 0 | ... AE68: =T68 -> 0 | AG68: =SUM(AE68/AA68)-1 -> #DIV/0!
B69: Accrued Liabilities | C69: 2137.1 | D69: 2145.1 | E69: 2194.7 | K69: =D69 -> 2145.1 | O69: =E69 -> 2194.7 | S69: =F69 -> 0 | V69: =K69 -> 2145.1 | W69: =L69 -> 0 | X69: =M69 -> 0 | Y69: =N69 -> 0 | Z69: =O69 -> 2194.7 | AA69: =P69 -> 0 | AB69: =Q69 -> 0 | AC69: =R69 -> 0 | ... AE69: =T69 -> 0 | AG69: =SUM(AE69/AA69)-1 -> #DIV/0!
B70: Current portion of operating lease liability | C70: 1245.7 | D70: 1275.3 | E70: 1463.1 | K70: =D70 -> 1275.3 | O70: =E70 -> 1463.1 | S70: =F70 -> 0 | V70: =K70 -> 1275.3 | W70: =L70 -> 0 | X70: =M70 -> 0 | Y70: =N70 -> 0 | Z70: =O70 -> 1463.1 | AA70: =P70 -> 0 | AB70: =Q70 -> 0 | AC70: =R70 -> 0 | ... AE70: =T70 -> 0 | AG70: =SUM(AE70/AA70)-1 -> #DIV/0!
B71: Deferred revenue, current | C71: 1641.9 | D71: 1700.2 | E71: 1781.2 | K71: =D71 -> 1700.2 | O71: =E71 -> 1781.2 | S71: =F71 -> 0 | V71: =K71 -> 1700.2 | W71: =L71 -> 0 | X71: =M71 -> 0 | Y71: =N71 -> 0 | Z71: =O71 -> 1781.2 | AA71: =P71 -> 0 | AB71: =Q71 -> 0 | AC71: =R71 -> 0 | ... AE71: =T71 -> 0 | AG71: =SUM(AE71/AA71)-1 -> #DIV/0!
B72: Short-term debt | C72: 175 | D72: 33.5 | E72: 0 | K72: =D72 -> 33.5 | O72: =E72 -> 0 | S72: =F72 -> 0 | V72: =K72 -> 33.5 | W72: =L72 -> 0 | X72: =M72 -> 0 | Y72: =N72 -> 0 | Z72: =O72 -> 0 | AA72: =P72 -> 0 | AB72: =Q72 -> 0 | AC72: =R72 -> 0 | ... AE72: =T72 -> 0
B73: Current portion of long-term debt | C73: 1749 | D73: 1818.6 | E73: 1248.9 | K73: =D73 -> 1818.6 | O73: =E73 -> 1248.9 | S73: =F73 -> 0 | V73: =K73 -> 1818.6 | W73: =L73 -> 0 | X73: =M73 -> 0 | Y73: =N73 -> 0 | Z73: =O73 -> 1248.9 | AA73: =P73 -> 0 | AB73: =Q73 -> 0 | AC73: =R73 -> 0 | ... AE73: =T73 -> 0 | AG73: =SUM(AE73/AA73)-1 -> #DIV/0!
B74: Total Current Liabilities | C74: =SUM(C67:C73) -> 9151.8 | D74: =SUM(D67:D73) -> 9345.3 | E74: =SUM(E67:E73) -> 9070 | F74: =SUM(F67:F73) -> 0 | H74: =SUM(H67:H73) -> 0 | I74: =SUM(I67:I73) -> 0 | J74: =SUM(J67:J73) -> 0 | K74: =SUM(K67:K73) -> 9345.3 | L74: =SUM(L67:L73) -> 0 | M74: =SUM(M67:M73) -> 0 | N74: =SUM(N67:N73) -> 0 | O74: =SUM(O67:O73) -> 9070 | ... T74: =SUM(T67:T73) -> 0 | V74: =SUM(V67:V73) -> 9345.3 | W74: =SUM(W67:W73) -> 0 | X74: =SUM(X67:X73) -> 0 | Y74: =SUM(Y67:Y73) -> 0 | Z74: =SUM(Z67:Z73) -> 9070 | AA74: =SUM(AA67:AA73) -> 0 | AB74: =SUM(AB67:AB73) -> 0 | AC74: =SUM(AC67:AC73) -> 0 | ... AE74: =SUM(AE67:AE73) -> 0 | AG74: =SUM(AE74/AA74)-1 -> #DIV/0!
B76: Non-Current Liabilities
B77: Long-term debt | C77: 13119.9 | D77: 13547.6 | E77: 14319.5 | K77: =D77 -> 13547.6 | O77: =E77 -> 14319.5 | S77: =F77 -> 0 | V77: =K77 -> 13547.6 | W77: =L77 -> 0 | X77: =M77 -> 0 | Y77: =N77 -> 0 | Z77: =O77 -> 14319.5 | AA77: =P77 -> 0 | AB77: =Q77 -> 0 | AC77: =R77 -> 0 | ... AE77: =T77 -> 0 | AG77: =SUM(AE77/AA77)-1 -> #DIV/0!
B78: Operating lease liability | C78: 7515.2 | D78: 7924.8 | E78: 8771.6 | K78: =D78 -> 7924.8 | O78: =E78 -> 8771.6 | S78: =F78 -> 0 | V78: =K78 -> 7924.8 | W78: =L78 -> 0 | X78: =M78 -> 0 | Y78: =N78 -> 0 | Z78: =O78 -> 8771.6 | AA78: =P78 -> 0 | AB78: =Q78 -> 0 | AC78: =R78 -> 0 | ... AE78: =T78 -> 0 | AG78: =SUM(AE78/AA78)-1 -> #DIV/0!
B79: Deferred revenue | C79: 6279.7 | D79: 6101.8 | E79: 5963.6 | K79: =D79 -> 6101.8 | O79: =E79 -> 5963.6 | S79: =F79 -> 0 | V79: =K79 -> 6101.8 | W79: =L79 -> 0 | X79: =M79 -> 0 | Y79: =N79 -> 0 | Z79: =O79 -> 5963.6 | AA79: =P79 -> 0 | AB79: =Q79 -> 0 | AC79: =R79 -> 0 | ... AE79: =T79 -> 0 | AG79: =SUM(AE79/AA79)-1 -> #DIV/0!
B80: Other long-term liabilities | C80: 610.5 | D80: 513.8 | E80: 656.2 | K80: =D80 -> 513.8 | O80: =E80 -> 656.2 | S80: =F80 -> 0 | V80: =K80 -> 513.8 | W80: =L80 -> 0 | X80: =M80 -> 0 | Y80: =N80 -> 0 | Z80: =O80 -> 656.2 | AA80: =P80 -> 0 | AB80: =Q80 -> 0 | AC80: =R80 -> 0 | ... AE80: =T80 -> 0 | AG80: =SUM(AE80/AA80)-1 -> #DIV/0!
B81: Total Liabilities | C81: =SUM(C77:C80)+C74 -> 36677.1 | D81: =SUM(D77:D80)+D74 -> 37433.3 | E81: =SUM(E77:E80)+E74 -> 38780.9 | F81: =SUM(F77:F80)+F74 -> 0 | H81: =SUM(H77:H80)+H74 -> 0 | I81: =SUM(I77:I80)+I74 -> 0 | J81: =SUM(J77:J80)+J74 -> 0 | K81: =SUM(K77:K80)+K74 -> 37433.3 | L81: =SUM(L77:L80)+L74 -> 0 | M81: =SUM(M77:M80)+M74 -> 0 | N81: =SUM(N77:N80)+N74 -> 0 | O81: =SUM(O77:O80)+O74 -> 38780.9 | ... T81: =SUM(T77:T80)+T74 -> 0 | V81: =SUM(V77:V80)+V74 -> 37433.3 | W81: =SUM(W77:W80)+W74 -> 0 | X81: =SUM(X77:X80)+X74 -> 0 | Y81: =SUM(Y77:Y80)+Y74 -> 0 | Z81: =SUM(Z77:Z80)+Z74 -> 38780.9 | AA81: =SUM(AA77:AA80)+AA74 -> 0 | AB81: =SUM(AB77:AB80)+AB74 -> 0 | AC81: =SUM(AC77:AC80)+AC74 -> 0 | ... AE81: =SUM(AE77:AE80)+AE74 -> 0 | AG81: =SUM(AE81/AA81)-1 -> #DIV/0!
B83: Common Stock | C83: 1.1 | D83: 1.1 | E83: 1.1 | K83: =D83 -> 1.1 | O83: =E83 -> 1.1 | S83: =F83 -> 0 | V83: =K83 -> 1.1 | W83: =L83 -> 0 | X83: =M83 -> 0 | Y83: =N83 -> 0 | Z83: =O83 -> 1.1 | AA83: =P83 -> 0 | AB83: =Q83 -> 0 | AC83: =R83 -> 0 | ... AE83: =T83 -> 0 | AG83: =SUM(AE83/AA83)-1 -> #DIV/0!
B84: Additional paid-in capital | C84: 205.3 | D84: 38.1 | E84: 322.6 | K84: =D84 -> 38.1 | O84: =E84 -> 322.6 | S84: =F84 -> 0 | V84: =K84 -> 38.1 | W84: =L84 -> 0 | X84: =M84 -> 0 | Y84: =N84 -> 0 | Z84: =O84 -> 322.6 | AA84: =P84 -> 0 | AB84: =Q84 -> 0 | AC84: =R84 -> 0 | ... AE84: =T84 -> 0 | AG84: =SUM(AE84/AA84)-1 -> #DIV/0!
B85: Retained Deficit | C85: -8449.8 | D85: -7255.8 | E85: -7343.8 | K85: =D85 -> -7255.8 | O85: =E85 -> -7343.8 | S85: =F85 -> 0 | V85: =K85 -> -7255.8 | W85: =L85 -> 0 | X85: =M85 -> 0 | Y85: =N85 -> 0 | Z85: =O85 -> -7343.8 | AA85: =P85 -> 0 | AB85: =Q85 -> 0 | AC85: =R85 -> 0 | ... AE85: =T85 -> 0 | AG85: =SUM(AE85/AA85)-1 -> #DIV/0!
B86: Accumulated other comprehensive income/(loss) | C86: -463.2 | D86: -778.2 | E86: -428.8 | K86: =D86 -> -778.2 | O86: =E86 -> -428.8 | S86: =F86 -> 0 | V86: =K86 -> -778.2 | W86: =L86 -> 0 | X86: =M86 -> 0 | Y86: =N86 -> 0 | Z86: =O86 -> -428.8 | AA86: =P86 -> 0 | AB86: =Q86 -> 0 | AC86: =R86 -> 0 | ... AE86: =T86 -> 0 | AG86: =SUM(AE86/AA86)-1 -> #DIV/0!
B87: Noncontrolling Interests | C87: 7.9 | D87: 7 | E87: 7.3 | K87: =D87 -> 7 | O87: =E87 -> 7.3 | S87: =F87 -> 0 | V87: =K87 -> 7 | W87: =L87 -> 0 | X87: =M87 -> 0 | Y87: =N87 -> 0 | Z87: =O87 -> 7.3 | AA87: =P87 -> 0 | AB87: =Q87 -> 0 | AC87: =R87 -> 0 | ... AE87: =T87 -> 0 | AG87: =SUM(AE87/AA87)-1 -> #DIV/0!
B88: Total stockholders' equity | C88: =SUM(C83:C87) -> -8698.7 | D88: =SUM(D83:D87) -> -7987.8 | E88: =SUM(E83:E87) -> -7441.6 | F88: =SUM(F83:F87) -> 0 | H88: =SUM(H83:H87) -> 0 | I88: =SUM(I83:I87) -> 0 | J88: =SUM(J83:J87) -> 0 | K88: =SUM(K83:K87) -> -7987.8 | L88: =SUM(L83:L87) -> 0 | M88: =SUM(M83:M87) -> 0 | N88: =SUM(N83:N87) -> 0 | O88: =SUM(O83:O87) -> -7441.6 | ... T88: =SUM(T83:T87) -> 0 | V88: =SUM(V83:V87) -> -7987.8 | W88: =SUM(W83:W87) -> 0 | X88: =SUM(X83:X87) -> 0 | Y88: =SUM(Y83:Y87) -> 0 | Z88: =SUM(Z83:Z87) -> -7441.6 | AA88: =SUM(AA83:AA87) -> 0 | AB88: =SUM(AB83:AB87) -> 0 | AC88: =SUM(AC83:AC87) -> 0 | ... AE88: =SUM(AE83:AE87) -> 0 | AG88: =SUM(AE88/AA88)-1 -> #DIV/0!
B89: Total liabilities and stockholders' equity | C89: =SUM(C88+C81) -> 27978.4 | D89: =SUM(D88+D81) -> 29445.5 | E89: =SUM(E88+E81) -> 31339.3 | F89: =SUM(F88+F81) -> 0 | H89: =SUM(H88+H81) -> 0 | I89: =SUM(I88+I81) -> 0 | J89: =SUM(J88+J81) -> 0 | K89: =SUM(K88+K81) -> 29445.5 | L89: =SUM(L88+L81) -> 0 | M89: =SUM(M88+M81) -> 0 | N89: =SUM(N88+N81) -> 0 | O89: =SUM(O88+O81) -> 31339.3 | ... T89: =SUM(T88+T81) -> 0 | V89: =SUM(V88+V81) -> 29445.5 | W89: =SUM(W88+W81) -> 0 | X89: =SUM(X88+X81) -> 0 | Y89: =SUM(Y88+Y81) -> 0 | Z89: =SUM(Z88+Z81) -> 31339.3 | AA89: =SUM(AA88+AA81) -> 0 | AB89: =SUM(AB88+AB81) -> 0 | AC89: =SUM(AC88+AC81) -> 0 | ... AE89: =SUM(AE88+AE81) -> 0 | AG89: =SUM(AE89/AA89)-1 -> #DIV/0!
B91: Balance Check | C91: =C89-C64 -> 0 | D91: =D89-D64 -> 0 | E91: =E89-E64 -> 0 | F91: =F89-F64 -> 0 | H91: =H89-H64 -> 0 | I91: =I89-I64 -> 0 | J91: =J89-J64 -> 0 | K91: =K89-K64 -> 0 | L91: =L89-L64 -> 0 | M91: =M89-M64 -> 0 | N91: =N89-N64 -> 0 | O91: =O89-O64 -> 0 | ... T91: =T89-T64 -> 0 | V91: =V89-V64 -> 0 | W91: =W89-W64 -> 0 | X91: =X89-X64 -> 0 | Y91: =Y89-Y64 -> 0 | Z91: =Z89-Z64 -> 0 | AA91: =AA89-AA64 -> 0 | AB91: =AB89-AB64 -> 0 | AC91: =AC89-AC64 -> 0 | ... AE91: =AE89-AE64 -> 0
A94: X | B94: Cash-Flows Statement | N94: Quarterly | AA94: LTM | AG94: Variance
B95: =B7 -> Fiscal Period | C95: =C7 -> 2022 | D95: =D7 -> 2023 | E95: =E7 -> 2024 | F95: =F7 -> 2025 | H95: =H7 -> 1Q23 | I95: =I7 -> 2Q23 | J95: =J7 -> 3Q23 | K95: =K7 -> 4Q23 | L95: =L7 -> 1Q24 | M95: =M7 -> 2Q24 | N95: =N7 -> 3Q24 | O95: =O7 -> 4Q24 | ... T95: =T7 -> 1Q26 | V95: =V7 -> 4Q23 | W95: =W7 -> 1Q24 | X95: =X7 -> 2Q24 | Y95: =Y7 -> 3Q24 | Z95: =Z7 -> 4Q24 | AA95: =AA7 -> 1Q25 | AB95: =AB7 -> 2Q25 | AC95: =AC7 -> 3Q25 | ... AE95: =AE7 -> 1Q26
B96: =B8 -> Fiscal Period End Date | C96: =C8 -> 44836 | D96: =D8 -> 45200 | E96: =E8 -> 45564 | F96: =F8 -> 0 | H96: =H8 -> XXX | I96: =I8 -> XXX | J96: =J8 -> XXX | K96: =K8 -> 45200 | L96: =L8 -> XXX | M96: =M8 -> XXX | N96: =N8 -> XXX | O96: =O8 -> 45564 | ... T96: =T8 -> XXX | V96: =V8 -> 45200 | W96: =W8 -> XXX | X96: =X8 -> XXX | Y96: =Y8 -> XXX | Z96: =Z8 -> 45564 | AA96: =AA8 -> XXX | AB96: =AB8 -> XXX | AC96: =AC8 -> XXX | ... AE96: =AE8 -> XXX
B98: Cash-Flows From Operating Activities
B99: Net income (loss) | C99: =C31 -> 3283.4 | D99: =D31 -> 4124.7 | E99: =E31 -> 3762.3 | F99: =F31 -> 0 | H99: =H31 -> 0 | I99: =I31 -> 0 | J99: =J31 -> 0 | K99: =K31 -> 4124.7 | L99: =L31 -> 0 | M99: =M31 -> 0 | N99: =N31 -> 0 | O99: =O31 -> 3762.3 | ... T99: =T31 -> 0 | V99: =V31 -> 4124.7 | W99: =W31 -> 4124.7 | X99: =X31 -> 4124.7 | Y99: =Y31 -> 4124.7 | Z99: =Z31 -> 3762.3 | AA99: =AA31 -> 3762.3 | AB99: =AB31 -> 3762.3 | AC99: =AC31 -> 3762.3 | ... AE99: =AE31 -> 0 | AG99: =SUM(AE99/AA99)-1 -> -1
B101: Adjustments to reconcile net income:
B102: Depreciation and Amortization | C102: 1529.4 | D102: 1450.3 | E102: 1592.4 | K102: =SUM(D102-SUM(H102:J102)) -> 1450.3 | O102: =SUM(E102-SUM(L102:N102)) -> 1592.4 | S102: =SUM(F102-SUM(P102:R102)) -> 0 | V102: =SUM(H102:K102) -> 1450.3 | W102: =SUM(I102:L102) -> 1450.3 | X102: =SUM(J102:M102) -> 1450.3 | Y102: =SUM(K102:N102) -> 1450.3 | Z102: =SUM(L102:O102) -> 1592.4 | AA102: =SUM(M102:P102) -> 1592.4 | AB102: =SUM(N102:Q102) -> 1592.4 | AC102: =SUM(O102:R102) -> 1592.4 | ... AE102: =SUM(Q102:T102) -> 0 | AG102: =SUM(AE102/AA102)-1 -> -1
B103: Income from equity investees | C103: -268.7 | D103: -301.8 | E103: -306.4 | K103: =SUM(D103-SUM(H103:J103)) -> -301.8 | O103: =SUM(E103-SUM(L103:N103)) -> -306.4 | S103: =SUM(F103-SUM(P103:R103)) -> 0 | V103: =SUM(H103:K103) -> -301.8 | W103: =SUM(I103:L103) -> -301.8 | X103: =SUM(J103:M103) -> -301.8 | Y103: =SUM(K103:N103) -> -301.8 | Z103: =SUM(L103:O103) -> -306.4 | AA103: =SUM(M103:P103) -> -306.4 | AB103: =SUM(N103:Q103) -> -306.4 | AC103: =SUM(O103:R103) -> -306.4 | ... AE103: =SUM(Q103:T103) -> 0 | AG103: =SUM(AE103/AA103)-1 -> -1
B104: Distributions from equity investees | C104: 231.2 | D104: 222.8 | E104: 333.3 | K104: =SUM(D104-SUM(H104:J104)) -> 222.8 | O104: =SUM(E104-SUM(L104:N104)) -> 333.3 | S104: =SUM(F104-SUM(P104:R104)) -> 0 | V104: =SUM(H104:K104) -> 222.8 | W104: =SUM(I104:L104) -> 222.8 | X104: =SUM(J104:M104) -> 222.8 | Y104: =SUM(K104:N104) -> 222.8 | Z104: =SUM(L104:O104) -> 333.3 | AA104: =SUM(M104:P104) -> 333.3 | AB104: =SUM(N104:Q104) -> 333.3 | AC104: =SUM(O104:R104) -> 333.3 | ... AE104: =SUM(Q104:T104) -> 0 | AG104: =SUM(AE104/AA104)-1 -> -1
B105: Gain on sale of assets | C105: 0 | D105: -91.3 | E105: 0 | K105: =SUM(D105-SUM(H105:J105)) -> -91.3 | O105: =SUM(E105-SUM(L105:N105)) -> 0 | S105: =SUM(F105-SUM(P105:R105)) -> 0 | V105: =SUM(H105:K105) -> -91.3 | W105: =SUM(I105:L105) -> -91.3 | X105: =SUM(J105:M105) -> -91.3 | Y105: =SUM(K105:N105) -> -91.3 | Z105: =SUM(L105:O105) -> 0 | AA105: =SUM(M105:P105) -> 0 | AB105: =SUM(N105:Q105) -> 0 | AC105: =SUM(O105:R105) -> 0 | ... AE105: =SUM(Q105:T105) -> 0 | AG105: =SUM(AE105/AA105)-1 -> #DIV/0!
B106: Stock-based compensation | C106: 271. 5 | D106: 302.7 | E106: 308.3 | K106: =SUM(D106-SUM(H106:J106)) -> 302.7 | O106: =SUM(E106-SUM(L106:N106)) -> 308.3 | S106: =SUM(F106-SUM(P106:R106)) -> 0 | V106: =SUM(H106:K106) -> 302.7 | W106: =SUM(I106:L106) -> 302.7 | X106: =SUM(J106:M106) -> 302.7 | Y106: =SUM(K106:N106) -> 302.7 | Z106: =SUM(L106:O106) -> 308.3 | AA106: =SUM(M106:P106) -> 308.3 | AB106: =SUM(N106:Q106) -> 308.3 | AC106: =SUM(O106:R106) -> 308.3 | ... AE106: =SUM(Q106:T106) -> 0 | AG106: =SUM(AE106/AA106)-1 -> -1
B107: Non-cash lease costs | C107: 1497.7 | D107: 1365.9 | E107: 1314.9 | K107: =SUM(D107-SUM(H107:J107)) -> 1365.9 | O107: =SUM(E107-SUM(L107:N107)) -> 1314.9 | S107: =SUM(F107-SUM(P107:R107)) -> 0 | V107: =SUM(H107:K107) -> 1365.9 | W107: =SUM(I107:L107) -> 1365.9 | X107: =SUM(J107:M107) -> 1365.9 | Y107: =SUM(K107:N107) -> 1365.9 | Z107: =SUM(L107:O107) -> 1314.9 | AA107: =SUM(M107:P107) -> 1314.9 | AB107: =SUM(N107:Q107) -> 1314.9 | AC107: =SUM(O107:R107) -> 1314.9 | ... AE107: =SUM(Q107:T107) -> 0 | AG107: =SUM(AE107/AA107)-1 -> -1
B108: Loss on retirement and impairment assets | C108: 91.4 | D108: 101.4 | E108: 121.5 | K108: =SUM(D108-SUM(H108:J108)) -> 101.4 | O108: =SUM(E108-SUM(L108:N108)) -> 121.5 | S108: =SUM(F108-SUM(P108:R108)) -> 0 | V108: =SUM(H108:K108) -> 101.4 | W108: =SUM(I108:L108) -> 101.4 | X108: =SUM(J108:M108) -> 101.4 | Y108: =SUM(K108:N108) -> 101.4 | Z108: =SUM(L108:O108) -> 121.5 | AA108: =SUM(M108:P108) -> 121.5 | AB108: =SUM(N108:Q108) -> 121.5 | AC108: =SUM(O108:R108) -> 121.5 | ... AE108: =SUM(Q108:T108) -> 0 | AG108: =SUM(AE108/AA108)-1 -> -1
B109: Other | C109: -67.8 | D109: 26.8 | E109: 31.9 | K109: =SUM(D109-SUM(H109:J109)) -> 26.8 | O109: =SUM(E109-SUM(L109:N109)) -> 31.9 | S109: =SUM(F109-SUM(P109:R109)) -> 0 | V109: =SUM(H109:K109) -> 26.8 | W109: =SUM(I109:L109) -> 26.8 | X109: =SUM(J109:M109) -> 26.8 | Y109: =SUM(K109:N109) -> 26.8 | Z109: =SUM(L109:O109) -> 31.9 | AA109: =SUM(M109:P109) -> 31.9 | AB109: =SUM(N109:Q109) -> 31.9 | AC109: =SUM(O109:R109) -> 31.9 | ... AE109: =SUM(Q109:T109) -> 0 | AG109: =SUM(AE109/AA109)-1 -> -1
B111: Changes in assets and liabilities:
B112: Accounts Receivable | C112: -326.1 | D112: -4.1 | E112: 18.4 | K112: =SUM(D112-SUM(H112:J112)) -> -4.1 | O112: =SUM(E112-SUM(L112:N112)) -> 18.4 | S112: =SUM(F112-SUM(P112:R112)) -> 0 | V112: =SUM(H112:K112) -> -4.1 | W112: =SUM(I112:L112) -> -4.1 | X112: =SUM(J112:M112) -> -4.1 | Y112: =SUM(K112:N112) -> -4.1 | Z112: =SUM(L112:O112) -> 18.4 | AA112: =SUM(M112:P112) -> 18.4 | AB112: =SUM(N112:Q112) -> 18.4 | AC112: =SUM(O112:R112) -> 18.4 | ... AE112: =SUM(Q112:T112) -> 0 | AG112: =SUM(AE112/AA112)-1 -> -1
B113: Investories | C113: -641 | D113: 366.4 | E113: 42.8 | K113: =SUM(D113-SUM(H113:J113)) -> 366.4 | O113: =SUM(E113-SUM(L113:N113)) -> 42.8 | S113: =SUM(F113-SUM(P113:R113)) -> 0 | V113: =SUM(H113:K113) -> 366.4 | W113: =SUM(I113:L113) -> 366.4 | X113: =SUM(J113:M113) -> 366.4 | Y113: =SUM(K113:N113) -> 366.4 | Z113: =SUM(L113:O113) -> 42.8 | AA113: =SUM(M113:P113) -> 42.8 | AB113: =SUM(N113:Q113) -> 42.8 | AC113: =SUM(O113:R113) -> 42.8 | ... AE113: =SUM(Q113:T113) -> 0 | AG113: =SUM(AE113/AA113)-1 -> -1
B114: Income Taxes Payable | C114: -149.6 | D114: 52.5 | E114: -61.9 | K114: =SUM(D114-SUM(H114:J114)) -> 52.5 | O114: =SUM(E114-SUM(L114:N114)) -> -61.9 | S114: =SUM(F114-SUM(P114:R114)) -> 0 | V114: =SUM(H114:K114) -> 52.5 | W114: =SUM(I114:L114) -> 52.5 | X114: =SUM(J114:M114) -> 52.5 | Y114: =SUM(K114:N114) -> 52.5 | Z114: =SUM(L114:O114) -> -61.9 | AA114: =SUM(M114:P114) -> -61.9 | AB114: =SUM(N114:Q114) -> -61.9 | AC114: =SUM(O114:R114) -> -61.9 | ... AE114: =SUM(Q114:T114) -> 0 | AG114: =SUM(AE114/AA114)-1 -> -1
B115: Accounts Payable | C115: 345.5 | D115: 100.1 | E115: 28 | K115: =SUM(D115-SUM(H115:J115)) -> 100.1 | O115: =SUM(E115-SUM(L115:N115)) -> 28 | S115: =SUM(F115-SUM(P115:R115)) -> 0 | V115: =SUM(H115:K115) -> 100.1 | W115: =SUM(I115:L115) -> 100.1 | X115: =SUM(J115:M115) -> 100.1 | Y115: =SUM(K115:N115) -> 100.1 | Z115: =SUM(L115:O115) -> 28 | AA115: =SUM(M115:P115) -> 28 | AB115: =SUM(N115:Q115) -> 28 | AC115: =SUM(O115:R115) -> 28 | ... AE115: =SUM(Q115:T115) -> 0 | AG115: =SUM(AE115/AA115)-1 -> -1
B116: Deferred Revenue | C116: -75.8 | D116: -110.8 | E116: -72.2 | K116: =SUM(D116-SUM(H116:J116)) -> -110.8 | O116: =SUM(E116-SUM(L116:N116)) -> -72.2 | S116: =SUM(F116-SUM(P116:R116)) -> 0 | V116: =SUM(H116:K116) -> -110.8 | W116: =SUM(I116:L116) -> -110.8 | X116: =SUM(J116:M116) -> -110.8 | Y116: =SUM(K116:N116) -> -110.8 | Z116: =SUM(L116:O116) -> -72.2 | AA116: =SUM(M116:P116) -> -72.2 | AB116: =SUM(N116:Q116) -> -72.2 | AC116: =SUM(O116:R116) -> -72.2 | ... AE116: =SUM(Q116:T116) -> 0 | AG116: =SUM(AE116/AA116)-1 -> -1
B117: Operating Lease Liability | C117: -1625.6 | D117: -1443.8 | E117: -1294.9 | K117: =SUM(D117-SUM(H117:J117)) -> -1443.8 | O117: =SUM(E117-SUM(L117:N117)) -> -1294.9 | S117: =SUM(F117-SUM(P117:R117)) -> 0 | V117: =SUM(H117:K117) -> -1443.8 | W117: =SUM(I117:L117) -> -1443.8 | X117: =SUM(J117:M117) -> -1443.8 | Y117: =SUM(K117:N117) -> -1443.8 | Z117: =SUM(L117:O117) -> -1294.9 | AA117: =SUM(M117:P117) -> -1294.9 | AB117: =SUM(N117:Q117) -> -1294.9 | AC117: =SUM(O117:R117) -> -1294.9 | ... AE117: =SUM(Q117:T117) -> 0 | AG117: =SUM(AE117/AA117)-1 -> -1
B118: Other Operating assets and liabilities | C118: 339.6 | D118: -93.7 | E118: 291 | K118: =SUM(D118-SUM(H118:J118)) -> -93.7 | O118: =SUM(E118-SUM(L118:N118)) -> 291 | S118: =SUM(F118-SUM(P118:R118)) -> 0 | V118: =SUM(H118:K118) -> -93.7 | W118: =SUM(I118:L118) -> -93.7 | X118: =SUM(J118:M118) -> -93.7 | Y118: =SUM(K118:N118) -> -93.7 | Z118: =SUM(L118:O118) -> 291 | AA118: =SUM(M118:P118) -> 291 | AB118: =SUM(N118:Q118) -> 291 | AC118: =SUM(O118:R118) -> 291 | ... AE118: =SUM(Q118:T118) -> 0 | AG118: =SUM(AE118/AA118)-1 -> -1
B119: Net cash used in operating activities | C119: =SUM(C99:C118) -> 4163.6 | D119: =SUM(D99:D118) -> 6068.1 | E119: =SUM(E99:E118) -> 6109.4 | F119: =SUM(F99:F118) -> 0 | H119: =SUM(H99:H118) -> 0 | I119: =SUM(I99:I118) -> 0 | J119: =SUM(J99:J118) -> 0 | K119: =SUM(K99:K118) -> 6068.1 | L119: =SUM(L99:L118) -> 0 | M119: =SUM(M99:M118) -> 0 | N119: =SUM(N99:N118) -> 0 | O119: =SUM(O99:O118) -> 6109.4 | ... T119: =SUM(T99:T118) -> 0 | V119: =SUM(V99:V118) -> 6068.1 | W119: =SUM(W99:W118) -> 6068.1 | X119: =SUM(X99:X118) -> 6068.1 | Y119: =SUM(Y99:Y118) -> 6068.1 | Z119: =SUM(Z99:Z118) -> 6109.4 | AA119: =SUM(AA99:AA118) -> 6109.4 | AB119: =SUM(AB99:AB118) -> 6109.4 | AC119: =SUM(AC99:AC118) -> 6109.4 | ... AE119: =SUM(AE99:AE118) -> 0 | AG119: =SUM(AE119/AA119)-1 -> -1
B121: Cash flows from investing activities:
B122: Purchase of investments | C122: -377.9 | D122: -610.5 | E122: -627.5 | K122: =SUM(D122-SUM(H122:J122)) -> -610.5 | O122: =SUM(E122-SUM(L122:N122)) -> -627.5 | S122: =SUM(F122-SUM(P122:R122)) -> 0 | V122: =SUM(H122:K122) -> -610.5 | W122: =SUM(I122:L122) -> -610.5 | X122: =SUM(J122:M122) -> -610.5 | Y122: =SUM(K122:N122) -> -610.5 | Z122: =SUM(L122:O122) -> -627.5 | AA122: =SUM(M122:P122) -> -627.5 | AB122: =SUM(N122:Q122) -> -627.5 | AC122: =SUM(O122:R122) -> -627.5 | ... AE122: =SUM(Q122:T122) -> 0 | AG122: =SUM(AE122/AA122)-1 -> -1
B123: Sale of investments | C123: 72.6 | D123: 2.5 | E123: 10.3 | K123: =SUM(D123-SUM(H123:J123)) -> 2.5 | O123: =SUM(E123-SUM(L123:N123)) -> 10.3 | S123: =SUM(F123-SUM(P123:R123)) -> 0 | V123: =SUM(H123:K123) -> 2.5 | W123: =SUM(I123:L123) -> 2.5 | X123: =SUM(J123:M123) -> 2.5 | Y123: =SUM(K123:N123) -> 2.5 | Z123: =SUM(L123:O123) -> 10.3 | AA123: =SUM(M123:P123) -> 10.3 | AB123: =SUM(N123:Q123) -> 10.3 | AC123: =SUM(O123:R123) -> 10.3 | ... AE123: =SUM(Q123:T123) -> 0 | AG123: =SUM(AE123/AA123)-1 -> -1
...

Sheet Revenue Drivers
B2: ='Historical Financials'!B2 -> Starbucks Corp (NASDAQ: SBUX) | N2: Quarterly | AA2: LTM
B3: Segment Anaysis | C3: ='Historical Financials'!C7 -> 2022 | D3: ='Historical Financials'!D7 -> 2023 | E3: ='Historical Financials'!E7 -> 2024 | F3: ='Historical Financials'!F7 -> 2025 | H3: ='Historical Financials'!H7 -> 1Q23 | I3: ='Historical Financials'!I7 -> 2Q23 | J3: ='Historical Financials'!J7 -> 3Q23 | K3: ='Historical Financials'!K7 -> 4Q23 | L3: ='Historical Financials'!L7 -> 1Q24 | M3: ='Historical Financials'!M7 -> 2Q24 | N3: ='Historical Financials'!N7 -> 3Q24 | O3: ='Historical Financials'!O7 -> 4Q24 | ... T3: ='Historical Financials'!T7 -> 1Q26 | V3: =K3 -> 4Q23 | W3: =L3 -> 1Q24 | X3: =M3 -> 2Q24 | Y3: =N3 -> 3Q24 | Z3: =O3 -> 4Q24 | AA3: =P3 -> 1Q25 | AB3: =Q3 -> 2Q25 | AC3: =R3 -> 3Q25 | ... AE3: =T3 -> 1Q26
B4: ($ In Millions) | C4: ='Historical Financials'!C8 -> 44836 | D4: ='Historical Financials'!D8 -> 45200 | E4: ='Historical Financials'!E8 -> 45564 | F4: ='Historical Financials'!F8 -> 0 | H4: ='Historical Financials'!H8 -> XXX | I4: ='Historical Financials'!I8 -> XXX | J4: ='Historical Financials'!J8 -> XXX | K4: ='Historical Financials'!K8 -> 45200 | L4: ='Historical Financials'!L8 -> XXX | M4: ='Historical Financials'!M8 -> XXX | N4: ='Historical Financials'!N8 -> XXX | O4: ='Historical Financials'!O8 -> 45564 | ... T4: ='Historical Financials'!T8 -> XXX | V4: =K4 -> 45200 | W4: =L4 -> XXX | X4: =M4 -> XXX | Y4: =N4 -> XXX | Z4: =O4 -> 45564 | AA4: =P4 -> XXX | AB4: =Q4 -> XXX | AC4: =R4 -> XXX | ... AE4: =T4 -> XXX
A6: X | B6: Revenue by reportable segment
A8: X | B8: Revenue Segment Anaysis
B9: Company Operated Stores | C9: 26576.1 | D9: 29462.3 | E9: 29765.9 | K9: =SUM(D9-SUM(H9:J9)) -> 29462.3 | O9: =SUM(E9-SUM(L9:N9)) -> 29765.9 | S9: =SUM(F9-SUM(P9:R9)) -> 0 | V9: =SUM(H9:K9) -> 29462.3 | W9: =SUM(I9:L9) -> 29462.3 | X9: =SUM(J9:M9) -> 29462.3 | Y9: =SUM(K9:N9) -> 29462.3 | Z9: =SUM(L9:O9) -> 29765.9 | AA9: =SUM(M9:P9) -> 29765.9 | AB9: =SUM(N9:Q9) -> 29765.9 | AC9: =SUM(O9:R9) -> 29765.9 | ... AE9: =SUM(Q9:T9) -> 0
B10: Licensed Stores | C10: 3655.5 | D10: 4512.7 | E10: 4505.1 | K10: =SUM(D10-SUM(H10:J10)) -> 4512.7 | O10: =SUM(E10-SUM(L10:N10)) -> 4505.1 | S10: =SUM(F10-SUM(P10:R10)) -> 0 | V10: =SUM(H10:K10) -> 4512.7 | W10: =SUM(I10:L10) -> 4512.7 | X10: =SUM(J10:M10) -> 4512.7 | Y10: =SUM(K10:N10) -> 4512.7 | Z10: =SUM(L10:O10) -> 4505.1 | AA10: =SUM(M10:P10) -> 4505.1 | AB10: =SUM(N10:Q10) -> 4505.1 | AC10: =SUM(O10:R10) -> 4505.1 | ... AE10: =SUM(Q10:T10) -> 0
B11: Other | C11: 2018.7 | D11: 2000.6 | E11: 1905.2 | K11: =SUM(D11-SUM(H11:J11)) -> 2000.6 | O11: =SUM(E11-SUM(L11:N11)) -> 1905.2 | S11: =SUM(F11-SUM(P11:R11)) -> 0 | V11: =SUM(H11:K11) -> 2000.6 | W11: =SUM(I11:L11) -> 2000.6 | X11: =SUM(J11:M11) -> 2000.6 | Y11: =SUM(K11:N11) -> 2000.6 | Z11: =SUM(L11:O11) -> 1905.2 | AA11: =SUM(M11:P11) -> 1905.2 | AB11: =SUM(N11:Q11) -> 1905.2 | AC11: =SUM(O11:R11) -> 1905.2 | ... AE11: =SUM(Q11:T11) -> 0
B12: Total Net Revenue | C12: =SUM(C9:C11) -> 32250.3 | D12: =SUM(D9:D11) -> 35975.6 | E12: =SUM(E9:E11) -> 36176.2 | F12: =SUM(F9:F11) -> 0 | H12: =SUM(H9:H11) -> 0 | I12: =SUM(I9:I11) -> 0 | J12: =SUM(J9:J11) -> 0 | K12: =SUM(K9:K11) -> 35975.6 | L12: =SUM(L9:L11) -> 0 | M12: =SUM(M9:M11) -> 0 | N12: =SUM(N9:N11) -> 0 | O12: =SUM(O9:O11) -> 36176.2 | ... T12: =SUM(T9:T11) -> 0 | V12: =SUM(V9:V11) -> 35975.6 | W12: =SUM(W9:W11) -> 35975.6 | X12: =SUM(X9:X11) -> 35975.6 | Y12: =SUM(Y9:Y11) -> 35975.6 | Z12: =SUM(Z9:Z11) -> 36176.2 | AA12: =SUM(AA9:AA11) -> 36176.2 | AB12: =SUM(AB9:AB11) -> 36176.2 | AC12: =SUM(AC9:AC11) -> 36176.2 | ... AE12: =SUM(AE9:AE11) -> 0
B13: Balance Check | C13: =+C12-'Historical Financials'!C11 -> 0 | D13: =+D12-'Historical Financials'!D11 -> 0 | E13: =+E12-'Historical Financials'!E11 -> 0 | F13: =+F12-'Historical Financials'!F11 -> 0 | H13: =+H12-'Historical Financials'!H11 -> 0 | I13: =+I12-'Historical Financials'!I11 -> 0 | J13: =+J12-'Historical Financials'!J11 -> 0 | K13: =+K12-'Historical Financials'!K11 -> 0 | L13: =+L12-'Historical Financials'!L11 -> 0 | M13: =+M12-'Historical Financials'!M11 -> 0 | N13: =+N12-'Historical Financials'!N11 -> 0 | O13: =+O12-'Historical Financials'!O11 -> 0 | ... T13: =+T12-'Historical Financials'!T11 -> 0 | V13: =+V12-'Historical Financials'!V11 -> 0 | W13: =+W12-'Historical Financials'!W11 -> 0 | X13: =+X12-'Historical Financials'!X11 -> 0 | Y13: =+Y12-'Historical Financials'!Y11 -> 0 | Z13: =+Z12-'Historical Financials'!Z11 -> 0 | AA13: =+AA12-'Historical Financials'!AA11 -> 0 | AB13: =+AB12-'Historical Financials'!AB11 -> 0 | AC13: =+AC12-'Historical Financials'!AC11 -> 0 | ... AE13: =+AE12-'Historical Financials'!AE11 -> 0
B15: =B9&"(%)" -> Company Operated Stores(%) | C15: =SUM(C9/C$12) -> 0.82405745 | D15: =SUM(D9/D$12) -> 0.81895229 | E15: =SUM(E9/E$12) -> 0.82280339 | F15: =SUM(F9/F$12) -> #DIV/0! | H15: =SUM(H9/H$12) -> #DIV/0! | I15: =SUM(I9/I$12) -> #DIV/0! | J15: =SUM(J9/J$12) -> #DIV/0! | K15: =SUM(K9/K$12) -> 0.81895229 | L15: =SUM(L9/L$12) -> #DIV/0! | M15: =SUM(M9/M$12) -> #DIV/0! | N15: =SUM(N9/N$12) -> #DIV/0! | O15: =SUM(O9/O$12) -> 0.82280339 | ... T15: =SUM(T9/T$12) -> #DIV/0! | V15: =I15 -> #DIV/0! | W15: =J15 -> #DIV/0! | X15: =K15 -> 0.81895229 | Y15: =L15 -> #DIV/0! | Z15: =M15 -> #DIV/0! | AA15: =N15 -> #DIV/0! | AB15: =O15 -> 0.82280339 | AC15: =P15 -> #DIV/0! | ... AE15: =R15 -> #DIV/0!
B16: =B10&"(%)" -> Licensed Stores(%) | C16: =SUM(C10/C$12) -> 0.11334778 | D16: =SUM(D10/D$12) -> 0.1254378 | E16: =SUM(E10/E$12) -> 0.12453215 | F16: =SUM(F10/F$12) -> #DIV/0! | H16: =SUM(H10/H$12) -> #DIV/0! | I16: =SUM(I10/I$12) -> #DIV/0! | J16: =SUM(J10/J$12) -> #DIV/0! | K16: =SUM(K10/K$12) -> 0.1254378 | L16: =SUM(L10/L$12) -> #DIV/0! | M16: =SUM(M10/M$12) -> #DIV/0! | N16: =SUM(N10/N$12) -> #DIV/0! | O16: =SUM(O10/O$12) -> 0.12453215 | ... T16: =SUM(T10/T$12) -> #DIV/0! | V16: =I16 -> #DIV/0! | W16: =J16 -> #DIV/0! | X16: =K16 -> 0.1254378 | Y16: =L16 -> #DIV/0! | Z16: =M16 -> #DIV/0! | AA16: =N16 -> #DIV/0! | AB16: =O16 -> 0.12453215 | AC16: =P16 -> #DIV/0! | ... AE16: =R16 -> #DIV/0!
B17: =B11&"(%)" -> Other(%) | C17: =SUM(C11/C$12) -> 0.062594767 | D17: =SUM(D11/D$12) -> 0.055609913 | E17: =SUM(E11/E$12) -> 0.052664459 | F17: =SUM(F11/F$12) -> #DIV/0! | H17: =SUM(H11/H$12) -> #DIV/0! | I17: =SUM(I11/I$12) -> #DIV/0! | J17: =SUM(J11/J$12) -> #DIV/0! | K17: =SUM(K11/K$12) -> 0.055609913 | L17: =SUM(L11/L$12) -> #DIV/0! | M17: =SUM(M11/M$12) -> #DIV/0! | N17: =SUM(N11/N$12) -> #DIV/0! | O17: =SUM(O11/O$12) -> 0.052664459 | ... T17: =SUM(T11/T$12) -> #DIV/0! | V17: =I17 -> #DIV/0! | W17: =J17 -> #DIV/0! | X17: =K17 -> 0.055609913 | Y17: =L17 -> #DIV/0! | Z17: =M17 -> #DIV/0! | AA17: =N17 -> #DIV/0! | AB17: =O17 -> 0.052664459 | AC17: =P17 -> #DIV/0! | ... AE17: =R17 -> #DIV/0!
A19: X | B19: Revenue by product category
A21: X | B21: Revenue by XXX
B22: XXX | K22: =SUM(D22-SUM(H22:J22)) -> 0 | O22: =SUM(E22-SUM(L22:N22)) -> 0 | S22: =SUM(F22-SUM(P22:R22)) -> 0 | V22: =SUM(H22:K22) -> 0 | W22: =SUM(I22:L22) -> 0 | X22: =SUM(J22:M22) -> 0 | Y22: =SUM(K22:N22) -> 0 | Z22: =SUM(L22:O22) -> 0 | AA22: =SUM(M22:P22) -> 0 | AB22: =SUM(N22:Q22) -> 0 | AC22: =SUM(O22:R22) -> 0 | ... AE22: =SUM(Q22:T22) -> 0
B23: XXX | K23: =SUM(D23-SUM(H23:J23)) -> 0 | O23: =SUM(E23-SUM(L23:N23)) -> 0 | S23: =SUM(F23-SUM(P23:R23)) -> 0 | V23: =SUM(H23:K23) -> 0 | W23: =SUM(I23:L23) -> 0 | X23: =SUM(J23:M23) -> 0 | Y23: =SUM(K23:N23) -> 0 | Z23: =SUM(L23:O23) -> 0 | AA23: =SUM(M23:P23) -> 0 | AB23: =SUM(N23:Q23) -> 0 | AC23: =SUM(O23:R23) -> 0 | ... AE23: =SUM(Q23:T23) -> 0
B24: XXX | K24: =SUM(D24-SUM(H24:J24)) -> 0 | O24: =SUM(E24-SUM(L24:N24)) -> 0 | S24: =SUM(F24-SUM(P24:R24)) -> 0 | V24: =SUM(H24:K24) -> 0 | W24: =SUM(I24:L24) -> 0 | X24: =SUM(J24:M24) -> 0 | Y24: =SUM(K24:N24) -> 0 | Z24: =SUM(L24:O24) -> 0 | AA24: =SUM(M24:P24) -> 0 | AB24: =SUM(N24:Q24) -> 0 | AC24: =SUM(O24:R24) -> 0 | ... AE24: =SUM(Q24:T24) -> 0
B25: XXX | K25: =SUM(D25-SUM(H25:J25)) -> 0 | O25: =SUM(E25-SUM(L25:N25)) -> 0 | S25: =SUM(F25-SUM(P25:R25)) -> 0 | V25: =SUM(H25:K25) -> 0 | W25: =SUM(I25:L25) -> 0 | X25: =SUM(J25:M25) -> 0 | Y25: =SUM(K25:N25) -> 0 | Z25: =SUM(L25:O25) -> 0 | AA25: =SUM(M25:P25) -> 0 | AB25: =SUM(N25:Q25) -> 0 | AC25: =SUM(O25:R25) -> 0 | ... AE25: =SUM(Q25:T25) -> 0
B26: XXX | K26: =SUM(D26-SUM(H26:J26)) -> 0 | O26: =SUM(E26-SUM(L26:N26)) -> 0 | S26: =SUM(F26-SUM(P26:R26)) -> 0 | V26: =SUM(H26:K26) -> 0 | W26: =SUM(I26:L26) -> 0 | X26: =SUM(J26:M26) -> 0 | Y26: =SUM(K26:N26) -> 0 | Z26: =SUM(L26:O26) -> 0 | AA26: =SUM(M26:P26) -> 0 | AB26: =SUM(N26:Q26) -> 0 | AC26: =SUM(O26:R26) -> 0 | ... AE26: =SUM(Q26:T26) -> 0
B27: XXX | K27: =SUM(D27-SUM(H27:J27)) -> 0 | O27: =SUM(E27-SUM(L27:N27)) -> 0 | S27: =SUM(F27-SUM(P27:R27)) -> 0 | V27: =SUM(H27:K27) -> 0 | W27: =SUM(I27:L27) -> 0 | X27: =SUM(J27:M27) -> 0 | Y27: =SUM(K27:N27) -> 0 | Z27: =SUM(L27:O27) -> 0 | AA27: =SUM(M27:P27) -> 0 | AB27: =SUM(N27:Q27) -> 0 | AC27: =SUM(O27:R27) -> 0 | ... AE27: =SUM(Q27:T27) -> 0
B28: Total Revenue | C28: =SUM(C22:C27) -> 0 | D28: =SUM(D22:D27) -> 0 | E28: =SUM(E22:E27) -> 0 | F28: =SUM(F22:F27) -> 0 | H28: =SUM(H22:H27) -> 0 | I28: =SUM(I22:I27) -> 0 | J28: =SUM(J22:J27) -> 0 | K28: =SUM(K22:K27) -> 0 | L28: =SUM(L22:L27) -> 0 | M28: =SUM(M22:M27) -> 0 | N28: =SUM(N22:N27) -> 0 | O28: =SUM(O22:O27) -> 0 | ... T28: =SUM(T22:T27) -> 0 | V28: =SUM(V22:V27) -> 0 | W28: =SUM(W22:W27) -> 0 | X28: =SUM(X22:X27) -> 0 | Y28: =SUM(Y22:Y27) -> 0 | Z28: =SUM(Z22:Z27) -> 0 | AA28: =SUM(AA22:AA27) -> 0 | AB28: =SUM(AB22:AB27) -> 0 | AC28: =SUM(AC22:AC27) -> 0 | ... AE28: =SUM(AE22:AE27) -> 0
B29: Balance Check | C29: =+C28-C12 -> -32250.3 | D29: =+D28-D12 -> -35975.6 | E29: =+E28-E12 -> -36176.2 | F29: =+F28-F12 -> 0 | H29: =+H28-H12 -> 0 | I29: =+I28-I12 -> 0 | J29: =+J28-J12 -> 0 | K29: =+K28-K12 -> -35975.6 | L29: =+L28-L12 -> 0 | M29: =+M28-M12 -> 0 | N29: =+N28-N12 -> 0 | O29: =+O28-O12 -> -36176.2 | ... T29: =+T28-T12 -> 0 | V29: =+V28-V12 -> -35975.6 | W29: =+W28-W12 -> -35975.6 | X29: =+X28-X12 -> -35975.6 | Y29: =+Y28-Y12 -> -35975.6 | Z29: =+Z28-Z12 -> -36176.2 | AA29: =+AA28-AA12 -> -36176.2 | AB29: =+AB28-AB12 -> -36176.2 | AC29: =+AC28-AC12 -> -36176.2 | ... AE29: =+AE28-AE12 -> 0
B31: =B22&"(%)" -> XXX(%) | C31: =C22/C$28 -> #DIV/0! | D31: =D22/D$28 -> #DIV/0! | E31: =E22/E$28 -> #DIV/0! | F31: =F22/F$28 -> #DIV/0! | H31: =H22/H$28 -> #DIV/0! | I31: =I22/I$28 -> #DIV/0! | J31: =J22/J$28 -> #DIV/0! | K31: =K22/K$28 -> #DIV/0! | L31: =L22/L$28 -> #DIV/0! | M31: =M22/M$28 -> #DIV/0! | N31: =N22/N$28 -> #DIV/0! | O31: =O22/O$28 -> #DIV/0! | ... T31: =T22/T$28 -> #DIV/0! | V31: =V22/V$28 -> #DIV/0! | W31: =W22/W$28 -> #DIV/0! | X31: =X22/X$28 -> #DIV/0! | Y31: =Y22/Y$28 -> #DIV/0! | Z31: =Z22/Z$28 -> #DIV/0! | AA31: =AA22/AA$28 -> #DIV/0! | AB31: =AB22/AB$28 -> #DIV/0! | AC31: =AC22/AC$28 -> #DIV/0! | ... AE31: =AE22/AE$28 -> #DIV/0!
B32: =B23&"(%)" -> XXX(%) | C32: =C23/C$28 -> #DIV/0! | D32: =D23/D$28 -> #DIV/0! | E32: =E23/E$28 -> #DIV/0! | F32: =F23/F$28 -> #DIV/0! | H32: =H23/H$28 -> #DIV/0! | I32: =I23/I$28 -> #DIV/0! | J32: =J23/J$28 -> #DIV/0! | K32: =K23/K$28 -> #DIV/0! | L32: =L23/L$28 -> #DIV/0! | M32: =M23/M$28 -> #DIV/0! | N32: =N23/N$28 -> #DIV/0! | O32: =O23/O$28 -> #DIV/0! | ... T32: =T23/T$28 -> #DIV/0! | V32: =V23/V$28 -> #DIV/0! | W32: =W23/W$28 -> #DIV/0! | X32: =X23/X$28 -> #DIV/0! | Y32: =Y23/Y$28 -> #DIV/0! | Z32: =Z23/Z$28 -> #DIV/0! | AA32: =AA23/AA$28 -> #DIV/0! | AB32: =AB23/AB$28 -> #DIV/0! | AC32: =AC23/AC$28 -> #DIV/0! | ... AE32: =AE23/AE$28 -> #DIV/0!
B33: =B24&"(%)" -> XXX(%) | C33: =C24/C$28 -> #DIV/0! | D33: =D24/D$28 -> #DIV/0! | E33: =E24/E$28 -> #DIV/0! | F33: =F24/F$28 -> #DIV/0! | H33: =H24/H$28 -> #DIV/0! | I33: =I24/I$28 -> #DIV/0! | J33: =J24/J$28 -> #DIV/0! | K33: =K24/K$28 -> #DIV/0! | L33: =L24/L$28 -> #DIV/0! | M33: =M24/M$28 -> #DIV/0! | N33: =N24/N$28 -> #DIV/0! | O33: =O24/O$28 -> #DIV/0! | ... T33: =T24/T$28 -> #DIV/0! | V33: =V24/V$28 -> #DIV/0! | W33: =W24/W$28 -> #DIV/0! | X33: =X24/X$28 -> #DIV/0! | Y33: =Y24/Y$28 -> #DIV/0! | Z33: =Z24/Z$28 -> #DIV/0! | AA33: =AA24/AA$28 -> #DIV/0! | AB33: =AB24/AB$28 -> #DIV/0! | AC33: =AC24/AC$28 -> #DIV/0! | ... AE33: =AE24/AE$28 -> #DIV/0!
B34: =B25&"(%)" -> XXX(%) | C34: =C25/C$28 -> #DIV/0! | D34: =D25/D$28 -> #DIV/0! | E34: =E25/E$28 -> #DIV/0! | F34: =F25/F$28 -> #DIV/0! | H34: =H25/H$28 -> #DIV/0! | I34: =I25/I$28 -> #DIV/0! | J34: =J25/J$28 -> #DIV/0! | K34: =K25/K$28 -> #DIV/0! | L34: =L25/L$28 -> #DIV/0! | M34: =M25/M$28 -> #DIV/0! | N34: =N25/N$28 -> #DIV/0! | O34: =O25/O$28 -> #DIV/0! | ... T34: =T25/T$28 -> #DIV/0! | V34: =V25/V$28 -> #DIV/0! | W34: =W25/W$28 -> #DIV/0! | X34: =X25/X$28 -> #DIV/0! | Y34: =Y25/Y$28 -> #DIV/0! | Z34: =Z25/Z$28 -> #DIV/0! | AA34: =AA25/AA$28 -> #DIV/0! | AB34: =AB25/AB$28 -> #DIV/0! | AC34: =AC25/AC$28 -> #DIV/0! | ... AE34: =AE25/AE$28 -> #DIV/0!
B35: =B26&"(%)" -> XXX(%) | C35: =C26/C$28 -> #DIV/0! | D35: =D26/D$28 -> #DIV/0! | E35: =E26/E$28 -> #DIV/0! | F35: =F26/F$28 -> #DIV/0! | H35: =H26/H$28 -> #DIV/0! | I35: =I26/I$28 -> #DIV/0! | J35: =J26/J$28 -> #DIV/0! | K35: =K26/K$28 -> #DIV/0! | L35: =L26/L$28 -> #DIV/0! | M35: =M26/M$28 -> #DIV/0! | N35: =N26/N$28 -> #DIV/0! | O35: =O26/O$28 -> #DIV/0! | ... T35: =T26/T$28 -> #DIV/0! | V35: =V26/V$28 -> #DIV/0! | W35: =W26/W$28 -> #DIV/0! | X35: =X26/X$28 -> #DIV/0! | Y35: =Y26/Y$28 -> #DIV/0! | Z35: =Z26/Z$28 -> #DIV/0! | AA35: =AA26/AA$28 -> #DIV/0! | AB35: =AB26/AB$28 -> #DIV/0! | AC35: =AC26/AC$28 -> #DIV/0! | ... AE35: =AE26/AE$28 -> #DIV/0!
B36: =B27&"(%)" -> XXX(%) | C36: =C27/C$28 -> #DIV/0! | D36: =D27/D$28 -> #DIV/0! | E36: =E27/E$28 -> #DIV/0! | F36: =F27/F$28 -> #DIV/0! | H36: =H27/H$28 -> #DIV/0! | I36: =I27/I$28 -> #DIV/0! | J36: =J27/J$28 -> #DIV/0! | K36: =K27/K$28 -> #DIV/0! | L36: =L27/L$28 -> #DIV/0! | M36: =M27/M$28 -> #DIV/0! | N36: =N27/N$28 -> #DIV/0! | O36: =O27/O$28 -> #DIV/0! | ... T36: =T27/T$28 -> #DIV/0! | V36: =V27/V$28 -> #DIV/0! | W36: =W27/W$28 -> #DIV/0! | X36: =X27/X$28 -> #DIV/0! | Y36: =Y27/Y$28 -> #DIV/0! | Z36: =Z27/Z$28 -> #DIV/0! | AA36: =AA27/AA$28 -> #DIV/0! | AB36: =AB27/AB$28 -> #DIV/0! | AC36: =AC27/AC$28 -> #DIV/0! | ... AE36: =AE27/AE$28 -> #DIV/0!

Sheet FCF
B2: ='Historical Financials'!B2 -> Starbucks Corp (NASDAQ: SBUX) | D2: FYE | H2: Quarterly | R2: Quarterly | Z2: LTM | AA2: LTM | AG2: Variance
B3: FCF Analysis | C3: ='Historical Financials'!#REF! -> #REF! | D3: ='Historical Financials'!D7 -> 2023 | E3: ='Historical Financials'!E7 -> 2024 | F3: ='Historical Financials'!F7 -> 2025 | H3: ='Historical Financials'!H7 -> 1Q23 | I3: ='Historical Financials'!I7 -> 2Q23 | J3: ='Historical Financials'!J7 -> 3Q23 | K3: ='Historical Financials'!K7 -> 4Q23 | L3: ='Historical Financials'!L7 -> 1Q24 | M3: ='Historical Financials'!M7 -> 2Q24 | N3: ='Historical Financials'!N7 -> 3Q24 | O3: ='Historical Financials'!O7 -> 4Q24 | ... T3: ='Historical Financials'!T7 -> 1Q26 | V3: =K3 -> 4Q23 | W3: =L3 -> 1Q24 | X3: =M3 -> 2Q24 | Y3: =N3 -> 3Q24 | Z3: =O3 -> 4Q24 | AA3: =P3 -> 1Q25 | AB3: =Q3 -> 2Q25 | AC3: =R3 -> 3Q25 | ... AE3: =T3 -> 1Q26
B4: ($ In Millions) | C4: ='Historical Financials'!#REF! -> #REF! | D4: ='Historical Financials'!D8 -> 45200 | E4: ='Historical Financials'!E8 -> 45564 | F4: ='Historical Financials'!F8 -> 0 | H4: ='Historical Financials'!H8 -> XXX | I4: ='Historical Financials'!I8 -> XXX | J4: ='Historical Financials'!J8 -> XXX | K4: ='Historical Financials'!K8 -> 45200 | L4: ='Historical Financials'!L8 -> XXX | M4: ='Historical Financials'!M8 -> XXX | N4: ='Historical Financials'!N8 -> XXX | O4: ='Historical Financials'!O8 -> 45564 | ... T4: ='Historical Financials'!T8 -> XXX | V4: =K4 -> 45200 | W4: =L4 -> XXX | X4: =M4 -> XXX | Y4: =N4 -> XXX | Z4: =O4 -> 45564 | AA4: =P4 -> XXX | AB4: =Q4 -> XXX | AC4: =R4 -> XXX | ... AE4: =T4 -> XXX
B6: XXX | V6: =SUM(H6:K6) -> 0 | W6: =SUM(I6:L6) -> 0 | X6: =SUM(J6:M6) -> 0 | Y6: =SUM(K6:N6) -> 0 | Z6: =SUM(L6:O6) -> 0 | AA6: =SUM(M6:P6) -> 0 | AB6: =SUM(N6:Q6) -> 0 | AC6: =SUM(O6:R6) -> 0 | ... AE6: =SUM(Q6:T6) -> 0 | AG6: =SUM(AE6/AA6)-1 -> #DIV/0!
B7: XXX | V7: =SUM(H7:K7) -> 0 | W7: =SUM(I7:L7) -> 0 | X7: =SUM(J7:M7) -> 0 | Y7: =SUM(K7:N7) -> 0 | Z7: =SUM(L7:O7) -> 0 | AA7: =SUM(M7:P7) -> 0 | AB7: =SUM(N7:Q7) -> 0 | AC7: =SUM(O7:R7) -> 0 | ... AE7: =SUM(Q7:T7) -> 0 | AG7: =SUM(AE7/AA7)-1 -> #DIV/0!
B8: XXX | V8: =SUM(H8:K8) -> 0 | W8: =SUM(I8:L8) -> 0 | X8: =SUM(J8:M8) -> 0 | Y8: =SUM(K8:N8) -> 0 | Z8: =SUM(L8:O8) -> 0 | AA8: =SUM(M8:P8) -> 0 | AB8: =SUM(N8:Q8) -> 0 | AC8: =SUM(O8:R8) -> 0 | ... AE8: =SUM(Q8:T8) -> 0 | AG8: =SUM(AE8/AA8)-1 -> #DIV/0!
B9: XXX | V9: =SUM(H9:K9) -> 0 | W9: =SUM(I9:L9) -> 0 | X9: =SUM(J9:M9) -> 0 | Y9: =SUM(K9:N9) -> 0 | Z9: =SUM(L9:O9) -> 0 | AA9: =SUM(M9:P9) -> 0 | AB9: =SUM(N9:Q9) -> 0 | AC9: =SUM(O9:R9) -> 0 | ... AE9: =SUM(Q9:T9) -> 0 | AG9: =SUM(AE9/AA9)-1 -> #DIV/0!
B10: XXX | V10: =SUM(H10:K10) -> 0 | W10: =SUM(I10:L10) -> 0 | X10: =SUM(J10:M10) -> 0 | Y10: =SUM(K10:N10) -> 0 | Z10: =SUM(L10:O10) -> 0 | AA10: =SUM(M10:P10) -> 0 | AB10: =SUM(N10:Q10) -> 0 | AC10: =SUM(O10:R10) -> 0 | ... AE10: =SUM(Q10:T10) -> 0 | AG10: =SUM(AE10/AA10)-1 -> #DIV/0!
B11: XXX | V11: =SUM(H11:K11) -> 0 | W11: =SUM(I11:L11) -> 0 | X11: =SUM(J11:M11) -> 0 | Y11: =SUM(K11:N11) -> 0 | Z11: =SUM(L11:O11) -> 0 | AA11: =SUM(M11:P11) -> 0 | AB11: =SUM(N11:Q11) -> 0 | AC11: =SUM(O11:R11) -> 0 | ... AE11: =SUM(Q11:T11) -> 0 | AG11: =SUM(AE11/AA11)-1 -> #DIV/0!
B12: Total Revenue | C12: =SUM(C6:C11) -> 0 | D12: =SUM(D6:D11) -> 0 | E12: =SUM(E6:E11) -> 0 | F12: =SUM(F6:F11) -> 0 | H12: =SUM(H6:H11) -> 0 | I12: =SUM(I6:I11) -> 0 | J12: =SUM(J6:J11) -> 0 | K12: =SUM(K6:K11) -> 0 | L12: =SUM(L6:L11) -> 0 | M12: =SUM(M6:M11) -> 0 | N12: =SUM(N6:N11) -> 0 | O12: =SUM(O6:O11) -> 0 | ... T12: =SUM(T6:T11) -> 0 | V12: =SUM(V6:V11) -> 0 | W12: =SUM(W6:W11) -> 0 | X12: =SUM(X6:X11) -> 0 | Y12: =SUM(Y6:Y11) -> 0 | Z12: =SUM(Z6:Z11) -> 0 | AA12: =SUM(AA6:AA11) -> 0 | AB12: =SUM(AB6:AB11) -> 0 | AC12: =SUM(AC6:AC11) -> 0 | ... AE12: =SUM(AE6:AE11) -> 0 | AG12: =SUM(AE12/AA12)-1 -> #DIV/0!
B13: Y/Y Growth (%) | C13: =SUM(C12/#REF!)-1 -> #REF! | D13: =SUM(D12/C12)-1 -> #DIV/0! | E13: =SUM(E12/D12)-1 -> #DIV/0! | F13: =SUM(F12/E12)-1 -> #DIV/0! | L13: =SUM(L12/H12)-1 -> #DIV/0! | M13: =SUM(M12/I12)-1 -> #DIV/0! | N13: =SUM(N12/J12)-1 -> #DIV/0! | O13: =SUM(O12/K12)-1 -> #DIV/0! | P13: =SUM(P12/L12)-1 -> #DIV/0! | Q13: =SUM(Q12/M12)-1 -> #DIV/0! | R13: =SUM(R12/N12)-1 -> #DIV/0! | S13: =SUM(S12/O12)-1 -> #DIV/0! | T13: =SUM(T12/P12)-1 -> #DIV/0! | Z13: =SUM(Z12/V12)-1 -> #DIV/0! | AA13: =SUM(AA12/W12)-1 -> #DIV/0! | AB13: =SUM(AB12/X12)-1 -> #DIV/0! | AC13: =SUM(AC12/Y12)-1 -> #DIV/0! | AD13: =SUM(AD12/Z12)-1 -> #DIV/0! | AE13: =SUM(AE12/AA12)-1 -> #DIV/0! | AG13: =SUM(AE13-AA13)*10000 -> #DIV/0!
B14: Q/Q Growth (%) | C14: N/A | D14: N/A | E14: N/A | F14: N/A | I14: =SUM(I12/H12)-1 -> #DIV/0! | J14: =SUM(J12/I12)-1 -> #DIV/0! | K14: =SUM(K12/J12)-1 -> #DIV/0! | L14: =SUM(L12/K12)-1 -> #DIV/0! | M14: =SUM(M12/L12)-1 -> #DIV/0! | N14: =SUM(N12/M12)-1 -> #DIV/0! | O14: =SUM(O12/N12)-1 -> #DIV/0! | P14: =SUM(P12/O12)-1 -> #DIV/0! | ... T14: =SUM(T12/S12)-1 -> #DIV/0! | V14: N/A | W14: N/A | X14: N/A | Y14: N/A | Z14: N/A | AA14: N/A | AB14: N/A | AC14: N/A | AD14: N/A | AE14: N/A
B16: (-) Cost of Sales | V16: =SUM(H16:K16) -> 0 | W16: =SUM(I16:L16) -> 0 | X16: =SUM(J16:M16) -> 0 | Y16: =SUM(K16:N16) -> 0 | Z16: =SUM(L16:O16) -> 0 | AA16: =SUM(M16:P16) -> 0 | AB16: =SUM(N16:Q16) -> 0 | AC16: =SUM(O16:R16) -> 0 | ... AE16: =SUM(Q16:T16) -> 0 | AG16: =SUM(AE16/AA16)-1 -> #DIV/0!
B17: Gross Profit | C17: =SUM(C12+SUM(C16:C16)) -> 0 | D17: =SUM(D12+SUM(D16:D16)) -> 0 | E17: =SUM(E12+SUM(E16:E16)) -> 0 | F17: =SUM(F12+SUM(F16:F16)) -> 0 | H17: =SUM(H12+SUM(H16:H16)) -> 0 | I17: =SUM(I12+SUM(I16:I16)) -> 0 | J17: =SUM(J12+SUM(J16:J16)) -> 0 | K17: =SUM(K12+SUM(K16:K16)) -> 0 | L17: =SUM(L12+SUM(L16:L16)) -> 0 | M17: =SUM(M12+SUM(M16:M16)) -> 0 | N17: =SUM(N12+SUM(N16:N16)) -> 0 | O17: =SUM(O12+SUM(O16:O16)) -> 0 | ... T17: =SUM(T12+SUM(T16:T16)) -> 0 | V17: =SUM(V12+SUM(V16:V16)) -> 0 | W17: =SUM(W12+SUM(W16:W16)) -> 0 | X17: =SUM(X12+SUM(X16:X16)) -> 0 | Y17: =SUM(Y12+SUM(Y16:Y16)) -> 0 | Z17: =SUM(Z12+SUM(Z16:Z16)) -> 0 | AA17: =SUM(AA12+SUM(AA16:AA16)) -> 0 | AB17: =SUM(AB12+SUM(AB16:AB16)) -> 0 | AC17: =SUM(AC12+SUM(AC16:AC16)) -> 0 | ... AE17: =SUM(AE12+SUM(AE16:AE16)) -> 0 | AG17: =SUM(AE17/AA17)-1 -> #DIV/0!
B18: Gross Margin (%) | C18: =C17/C12 -> #DIV/0! | D18: =D17/D12 -> #DIV/0! | E18: =E17/E12 -> #DIV/0! | F18: =F17/F12 -> #DIV/0! | H18: =H17/H12 -> #DIV/0! | I18: =I17/I12 -> #DIV/0! | J18: =J17/J12 -> #DIV/0! | K18: =K17/K12 -> #DIV/0! | L18: =L17/L12 -> #DIV/0! | M18: =M17/M12 -> #DIV/0! | N18: =N17/N12 -> #DIV/0! | O18: =O17/O12 -> #DIV/0! | ... T18: =T17/T12 -> #DIV/0! | V18: =V17/V12 -> #DIV/0! | W18: =W17/W12 -> #DIV/0! | X18: =X17/X12 -> #DIV/0! | Y18: =Y17/Y12 -> #DIV/0! | Z18: =Z17/Z12 -> #DIV/0! | AA18: =AA17/AA12 -> #DIV/0! | AB18: =AB17/AB12 -> #DIV/0! | AC18: =AC17/AC12 -> #DIV/0! | ... AE18: =AE17/AE12 -> #DIV/0! | AG18: =SUM(AE18-AA18)*10000 -> #DIV/0!
B20: (-) XXX | V20: =SUM(H20:K20) -> 0 | W20: =SUM(I20:L20) -> 0 | X20: =SUM(J20:M20) -> 0 | Y20: =SUM(K20:N20) -> 0 | Z20: =SUM(L20:O20) -> 0 | AA20: =SUM(M20:P20) -> 0 | AB20: =SUM(N20:Q20) -> 0 | AC20: =SUM(O20:R20) -> 0 | ... AE20: =SUM(Q20:T20) -> 0 | AG20: =SUM(AE20/AA20)-1 -> #DIV/0!
B21: (-) XXX | V21: =SUM(H21:K21) -> 0 | W21: =SUM(I21:L21) -> 0 | X21: =SUM(J21:M21) -> 0 | Y21: =SUM(K21:N21) -> 0 | Z21: =SUM(L21:O21) -> 0 | AA21: =SUM(M21:P21) -> 0 | AB21: =SUM(N21:Q21) -> 0 | AC21: =SUM(O21:R21) -> 0 | ... AE21: =SUM(Q21:T21) -> 0 | AG21: =SUM(AE21/AA21)-1 -> #DIV/0!
B22: (-) XXX | V22: =SUM(H22:K22) -> 0 | W22: =SUM(I22:L22) -> 0 | X22: =SUM(J22:M22) -> 0 | Y22: =SUM(K22:N22) -> 0 | Z22: =SUM(L22:O22) -> 0 | AA22: =SUM(M22:P22) -> 0 | AB22: =SUM(N22:Q22) -> 0 | AC22: =SUM(O22:R22) -> 0 | ... AE22: =SUM(Q22:T22) -> 0 | AG22: =SUM(AE22/AA22)-1 -> #DIV/0!
B23: (-) XXX | V23: =SUM(H23:K23) -> 0 | W23: =SUM(I23:L23) -> 0 | X23: =SUM(J23:M23) -> 0 | Y23: =SUM(K23:N23) -> 0 | Z23: =SUM(L23:O23) -> 0 | AA23: =SUM(M23:P23) -> 0 | AB23: =SUM(N23:Q23) -> 0 | AC23: =SUM(O23:R23) -> 0 | ... AE23: =SUM(Q23:T23) -> 0 | AG23: =SUM(AE23/AA23)-1 -> #DIV/0!
B24: (-) XXX | V24: =SUM(H24:K24) -> 0 | W24: =SUM(I24:L24) -> 0 | X24: =SUM(J24:M24) -> 0 | Y24: =SUM(K24:N24) -> 0 | Z24: =SUM(L24:O24) -> 0 | AA24: =SUM(M24:P24) -> 0 | AB24: =SUM(N24:Q24) -> 0 | AC24: =SUM(O24:R24) -> 0 | ... AE24: =SUM(Q24:T24) -> 0 | AG24: =SUM(AE24/AA24)-1 -> #DIV/0!
B25: Earning before Interest & Taxes (EBIT) | C25: =SUM(C17+SUM(C20:C24)) -> 0 | D25: =SUM(D17+SUM(D20:D24)) -> 0 | E25: =SUM(E17+SUM(E20:E24)) -> 0 | F25: =SUM(F17+SUM(F20:F24)) -> 0 | H25: =SUM(H17+SUM(H20:H24)) -> 0 | I25: =SUM(I17+SUM(I20:I24)) -> 0 | J25: =SUM(J17+SUM(J20:J24)) -> 0 | K25: =SUM(K17+SUM(K20:K24)) -> 0 | L25: =SUM(L17+SUM(L20:L24)) -> 0 | M25: =SUM(M17+SUM(M20:M24)) -> 0 | N25: =SUM(N17+SUM(N20:N24)) -> 0 | O25: =SUM(O17+SUM(O20:O24)) -> 0 | ... T25: =SUM(T17+SUM(T20:T24)) -> 0 | V25: =SUM(V17+SUM(V20:V24)) -> 0 | W25: =SUM(W17+SUM(W20:W24)) -> 0 | X25: =SUM(X17+SUM(X20:X24)) -> 0 | Y25: =SUM(Y17+SUM(Y20:Y24)) -> 0 | Z25: =SUM(Z17+SUM(Z20:Z24)) -> 0 | AA25: =SUM(AA17+SUM(AA20:AA24)) -> 0 | AB25: =SUM(AB17+SUM(AB20:AB24)) -> 0 | AC25: =SUM(AC17+SUM(AC20:AC24)) -> 0 | ... AE25: =SUM(AE17+SUM(AE20:AE24)) -> 0 | AG25: =SUM(AE25/AA25)-1 -> #DIV/0!
B26: Operating Margin (%) | C26: =C25/C12 -> #DIV/0! | D26: =D25/D12 -> #DIV/0! | E26: =E25/E12 -> #DIV/0! | F26: =F25/F12 -> #DIV/0! | H26: =H25/H12 -> #DIV/0! | I26: =I25/I12 -> #DIV/0! | J26: =J25/J12 -> #DIV/0! | K26: =K25/K12 -> #DIV/0! | L26: =L25/L12 -> #DIV/0! | M26: =M25/M12 -> #DIV/0! | N26: =N25/N12 -> #DIV/0! | O26: =O25/O12 -> #DIV/0! | ... T26: =T25/T12 -> #DIV/0! | V26: =V25/V12 -> #DIV/0! | W26: =W25/W12 -> #DIV/0! | X26: =X25/X12 -> #DIV/0! | Y26: =Y25/Y12 -> #DIV/0! | Z26: =Z25/Z12 -> #DIV/0! | AA26: =AA25/AA12 -> #DIV/0! | AB26: =AB25/AB12 -> #DIV/0! | AC26: =AC25/AC12 -> #DIV/0! | ... AE26: =AE25/AE12 -> #DIV/0! | AG26: =SUM(AE26-AA26)*10000 -> #DIV/0!
B28: (+) Depreciation and Amortization (D&A) | V28: =SUM(H28:K28) -> 0 | W28: =SUM(I28:L28) -> 0 | X28: =SUM(J28:M28) -> 0 | Y28: =SUM(K28:N28) -> 0 | Z28: =SUM(L28:O28) -> 0 | AA28: =SUM(M28:P28) -> 0 | AB28: =SUM(N28:Q28) -> 0 | AC28: =SUM(O28:R28) -> 0 | ... AE28: =SUM(Q28:T28) -> 0 | AG28: =SUM(AE28/AA28)-1 -> #DIV/0!
B29: EBITDA | C29: =SUM(C25+SUM(C28:C28)) -> 0 | D29: =SUM(D25+SUM(D28:D28)) -> 0 | E29: =SUM(E25+SUM(E28:E28)) -> 0 | F29: =SUM(F25+SUM(F28:F28)) -> 0 | H29: =SUM(H25+SUM(H28:H28)) -> 0 | I29: =SUM(I25+SUM(I28:I28)) -> 0 | J29: =SUM(J25+SUM(J28:J28)) -> 0 | K29: =SUM(K25+SUM(K28:K28)) -> 0 | L29: =SUM(L25+SUM(L28:L28)) -> 0 | M29: =SUM(M25+SUM(M28:M28)) -> 0 | N29: =SUM(N25+SUM(N28:N28)) -> 0 | O29: =SUM(O25+SUM(O28:O28)) -> 0 | ... T29: =SUM(T25+SUM(T28:T28)) -> 0 | V29: =SUM(V25+SUM(V28:V28)) -> 0 | W29: =SUM(W25+SUM(W28:W28)) -> 0 | X29: =SUM(X25+SUM(X28:X28)) -> 0 | Y29: =SUM(Y25+SUM(Y28:Y28)) -> 0 | Z29: =SUM(Z25+SUM(Z28:Z28)) -> 0 | AA29: =SUM(AA25+SUM(AA28:AA28)) -> 0 | AB29: =SUM(AB25+SUM(AB28:AB28)) -> 0 | AC29: =SUM(AC25+SUM(AC28:AC28)) -> 0 | ... AE29: =SUM(AE25+SUM(AE28:AE28)) -> 0 | AG29: =SUM(AE29/AA29)-1 -> #DIV/0!
B30: EBITDA Margin (%) | C30: =C29/C12 -> #DIV/0! | D30: =D29/D12 -> #DIV/0! | E30: =E29/E12 -> #DIV/0! | F30: =F29/F12 -> #DIV/0! | H30: =H29/H12 -> #DIV/0! | I30: =I29/I12 -> #DIV/0! | J30: =J29/J12 -> #DIV/0! | K30: =K29/K12 -> #DIV/0! | L30: =L29/L12 -> #DIV/0! | M30: =M29/M12 -> #DIV/0! | N30: =N29/N12 -> #DIV/0! | O30: =O29/O12 -> #DIV/0! | ... T30: =T29/T12 -> #DIV/0! | V30: =V29/V12 -> #DIV/0! | W30: =W29/W12 -> #DIV/0! | X30: =X29/X12 -> #DIV/0! | Y30: =Y29/Y12 -> #DIV/0! | Z30: =Z29/Z12 -> #DIV/0! | AA30: =AA29/AA12 -> #DIV/0! | AB30: =AB29/AB12 -> #DIV/0! | AC30: =AC29/AC12 -> #DIV/0! | ... AE30: =AE29/AE12 -> #DIV/0! | AG30: =SUM(AE30-AA30)*10000 -> #DIV/0!
B32: (+) Stock-Based Compensation (SBC) | V32: =SUM(H32:K32) -> 0 | W32: =SUM(I32:L32) -> 0 | X32: =SUM(J32:M32) -> 0 | Y32: =SUM(K32:N32) -> 0 | Z32: =SUM(L32:O32) -> 0 | AA32: =SUM(M32:P32) -> 0 | AB32: =SUM(N32:Q32) -> 0 | AC32: =SUM(O32:R32) -> 0 | ... AE32: =SUM(Q32:T32) -> 0 | AG32: =SUM(AE32/AA32)-1 -> #DIV/0!
B33: (+) XXX | V33: =SUM(H33:K33) -> 0 | W33: =SUM(I33:L33) -> 0 | X33: =SUM(J33:M33) -> 0 | Y33: =SUM(K33:N33) -> 0 | Z33: =SUM(L33:O33) -> 0 | AA33: =SUM(M33:P33) -> 0 | AB33: =SUM(N33:Q33) -> 0 | AC33: =SUM(O33:R33) -> 0 | ... AE33: =SUM(Q33:T33) -> 0 | AG33: =SUM(AE33/AA33)-1 -> #DIV/0!
B34: Adj. EBITDA | C34: =+SUM(C29+SUM(C32:C32)) -> 0 | D34: =+SUM(D29+SUM(D32:D32)) -> 0 | E34: =+SUM(E29+SUM(E32:E32)) -> 0 | F34: =+SUM(F29+SUM(F32:F32)) -> 0 | H34: =+SUM(H29+SUM(H32:H32)) -> 0 | I34: =+SUM(I29+SUM(I32:I32)) -> 0 | J34: =+SUM(J29+SUM(J32:J32)) -> 0 | K34: =+SUM(K29+SUM(K32:K32)) -> 0 | L34: =+SUM(L29+SUM(L32:L32)) -> 0 | M34: =+SUM(M29+SUM(M32:M32)) -> 0 | N34: =+SUM(N29+SUM(N32:N32)) -> 0 | O34: =+SUM(O29+SUM(O32:O32)) -> 0 | ... T34: =+SUM(T29+SUM(T32:T32)) -> 0 | V34: =+SUM(V29+SUM(V32:V32)) -> 0 | W34: =+SUM(W29+SUM(W32:W32)) -> 0 | X34: =+SUM(X29+SUM(X32:X32)) -> 0 | Y34: =+SUM(Y29+SUM(Y32:Y32)) -> 0 | Z34: =+SUM(Z29+SUM(Z32:Z32)) -> 0 | AA34: =+SUM(AA29+SUM(AA32:AA32)) -> 0 | AB34: =+SUM(AB29+SUM(AB32:AB32)) -> 0 | AC34: =+SUM(AC29+SUM(AC32:AC32)) -> 0 | ... AE34: =+SUM(AE29+SUM(AE32:AE32)) -> 0 | AG34: =SUM(AE34/AA34)-1 -> #DIV/0!
B35: Adj. EBITDA Margin (%) | C35: =C34/C12 -> #DIV/0! | D35: =D34/D12 -> #DIV/0! | E35: =E34/E12 -> #DIV/0! | F35: =F34/F12 -> #DIV/0! | H35: =H34/H12 -> #DIV/0! | I35: =I34/I12 -> #DIV/0! | J35: =J34/J12 -> #DIV/0! | K35: =K34/K12 -> #DIV/0! | L35: =L34/L12 -> #DIV/0! | M35: =M34/M12 -> #DIV/0! | N35: =N34/N12 -> #DIV/0! | O35: =O34/O12 -> #DIV/0! | ... T35: =T34/T12 -> #DIV/0! | V35: =V34/V12 -> #DIV/0! | W35: =W34/W12 -> #DIV/0! | X35: =X34/X12 -> #DIV/0! | Y35: =Y34/Y12 -> #DIV/0! | Z35: =Z34/Z12 -> #DIV/0! | AA35: =AA34/AA12 -> #DIV/0! | AB35: =AB34/AB12 -> #DIV/0! | AC35: =AC34/AC12 -> #DIV/0! | ... AE35: =AE34/AE12 -> #DIV/0! | AG35: =SUM(AE35-AA35)*10000 -> #DIV/0!
B37: (-) Capital Expenditures | V37: =SUM(H37:K37) -> 0 | W37: =SUM(I37:L37) -> 0 | X37: =SUM(J37:M37) -> 0 | Y37: =SUM(K37:N37) -> 0 | Z37: =SUM(L37:O37) -> 0 | AA37: =SUM(M37:P37) -> 0 | AB37: =SUM(N37:Q37) -> 0 | AC37: =SUM(O37:R37) -> 0 | ... AE37: =SUM(Q37:T37) -> 0 | AG37: =SUM(AE37/AA37)-1 -> #DIV/0!
B38: (-) Cash Taxes | V38: =SUM(H38:K38) -> 0 | W38: =SUM(I38:L38) -> 0 | X38: =SUM(J38:M38) -> 0 | Y38: =SUM(K38:N38) -> 0 | Z38: =SUM(L38:O38) -> 0 | AA38: =SUM(M38:P38) -> 0 | AB38: =SUM(N38:Q38) -> 0 | AC38: =SUM(O38:R38) -> 0 | ... AE38: =SUM(Q38:T38) -> 0 | AG38: =SUM(AE38/AA38)-1 -> #DIV/0!
B39: (-) Cash Interest | V39: =SUM(H39:K39) -> 0 | W39: =SUM(I39:L39) -> 0 | X39: =SUM(J39:M39) -> 0 | Y39: =SUM(K39:N39) -> 0 | Z39: =SUM(L39:O39) -> 0 | AA39: =SUM(M39:P39) -> 0 | AB39: =SUM(N39:Q39) -> 0 | AC39: =SUM(O39:R39) -> 0 | ... AE39: =SUM(Q39:T39) -> 0 | AG39: =SUM(AE39/AA39)-1 -> #DIV/0!
B40: (-) Mandatory Outflows | V40: =SUM(H40:K40) -> 0 | W40: =SUM(I40:L40) -> 0 | X40: =SUM(J40:M40) -> 0 | Y40: =SUM(K40:N40) -> 0 | Z40: =SUM(L40:O40) -> 0 | AA40: =SUM(M40:P40) -> 0 | AB40: =SUM(N40:Q40) -> 0 | AC40: =SUM(O40:R40) -> 0 | ... AE40: =SUM(Q40:T40) -> 0 | AG40: =SUM(AE40/AA40)-1 -> #DIV/0!
B41: (+/-) Changes in NWC | V41: =SUM(H41:K41) -> 0 | W41: =SUM(I41:L41) -> 0 | X41: =SUM(J41:M41) -> 0 | Y41: =SUM(K41:N41) -> 0 | Z41: =SUM(L41:O41) -> 0 | AA41: =SUM(M41:P41) -> 0 | AB41: =SUM(N41:Q41) -> 0 | AC41: =SUM(O41:R41) -> 0 | ... AE41: =SUM(Q41:T41) -> 0 | AG41: =SUM(AE41/AA41)-1 -> #DIV/0!
B42: Discretionary Cash-Flows | C42: =SUM(C34+SUM(C37:C41)) -> 0 | D42: =SUM(D34+SUM(D37:D41)) -> 0 | E42: =SUM(E34+SUM(E37:E41)) -> 0 | F42: =SUM(F34+SUM(F37:F41)) -> 0 | H42: =SUM(H34+SUM(H37:H41)) -> 0 | I42: =SUM(I34+SUM(I37:I41)) -> 0 | J42: =SUM(J34+SUM(J37:J41)) -> 0 | K42: =SUM(K34+SUM(K37:K41)) -> 0 | L42: =SUM(L34+SUM(L37:L41)) -> 0 | M42: =SUM(M34+SUM(M37:M41)) -> 0 | N42: =SUM(N34+SUM(N37:N41)) -> 0 | O42: =SUM(O34+SUM(O37:O41)) -> 0 | ... T42: =SUM(T34+SUM(T37:T41)) -> 0 | V42: =SUM(V34+SUM(V37:V41)) -> 0 | W42: =SUM(W34+SUM(W37:W41)) -> 0 | X42: =SUM(X34+SUM(X37:X41)) -> 0 | Y42: =SUM(Y34+SUM(Y37:Y41)) -> 0 | Z42: =SUM(Z34+SUM(Z37:Z41)) -> 0 | AA42: =SUM(AA34+SUM(AA37:AA41)) -> 0 | AB42: =SUM(AB34+SUM(AB37:AB41)) -> 0 | AC42: =SUM(AC34+SUM(AC37:AC41)) -> 0 | ... AE42: =SUM(AE34+SUM(AE37:AE41)) -> 0 | AG42: =SUM(AE42/AA42)-1 -> #DIV/0!
B44: (+/-) XXX | V44: =SUM(H44:K44) -> 0 | W44: =SUM(I44:L44) -> 0 | X44: =SUM(J44:M44) -> 0 | Y44: =SUM(K44:N44) -> 0 | Z44: =SUM(L44:O44) -> 0 | AA44: =SUM(M44:P44) -> 0 | AB44: =SUM(N44:Q44) -> 0 | AC44: =SUM(O44:R44) -> 0 | ... AE44: =SUM(Q44:T44) -> 0
B45: (+/-) XXX | V45: =SUM(H45:K45) -> 0 | W45: =SUM(I45:L45) -> 0 | X45: =SUM(J45:M45) -> 0 | Y45: =SUM(K45:N45) -> 0 | Z45: =SUM(L45:O45) -> 0 | AA45: =SUM(M45:P45) -> 0 | AB45: =SUM(N45:Q45) -> 0 | AC45: =SUM(O45:R45) -> 0 | ... AE45: =SUM(Q45:T45) -> 0
B46: (+/-) XXX | V46: =SUM(H46:K46) -> 0 | W46: =SUM(I46:L46) -> 0 | X46: =SUM(J46:M46) -> 0 | Y46: =SUM(K46:N46) -> 0 | Z46: =SUM(L46:O46) -> 0 | AA46: =SUM(M46:P46) -> 0 | AB46: =SUM(N46:Q46) -> 0 | AC46: =SUM(O46:R46) -> 0 | ... AE46: =SUM(Q46:T46) -> 0
B47: (+/-) XXX | V47: =SUM(H47:K47) -> 0 | W47: =SUM(I47:L47) -> 0 | X47: =SUM(J47:M47) -> 0 | Y47: =SUM(K47:N47) -> 0 | Z47: =SUM(L47:O47) -> 0 | AA47: =SUM(M47:P47) -> 0 | AB47: =SUM(N47:Q47) -> 0 | AC47: =SUM(O47:R47) -> 0 | ... AE47: =SUM(Q47:T47) -> 0
B48: (+/-) XXX | V48: =SUM(H48:K48) -> 0 | W48: =SUM(I48:L48) -> 0 | X48: =SUM(J48:M48) -> 0 | Y48: =SUM(K48:N48) -> 0 | Z48: =SUM(L48:O48) -> 0 | AA48: =SUM(M48:P48) -> 0 | AB48: =SUM(N48:Q48) -> 0 | AC48: =SUM(O48:R48) -> 0 | ... AE48: =SUM(Q48:T48) -> 0
B49: (+/-) Other | D49: =SUM(D54)-SUM(C54)-SUM(D42:D48) -> 0 | E49: =SUM(E54)-SUM(D54)-SUM(E42:E48) -> 0 | F49: =SUM(F54)-SUM(E54)-SUM(F42:F48) -> 0 | H49: =SUM(H54)-SUM(C54)-SUM(H42:H48) -> 0 | I49: =SUM(I54)-SUM(H54)-SUM(I42:I48) -> 0 | J49: =SUM(J54)-SUM(I54)-SUM(J42:J48) -> 0 | K49: =SUM(K54)-SUM(J54)-SUM(K42:K48) -> 3551.5 | L49: =SUM(L54)-SUM(K54)-SUM(L42:L48) -> -3551.5 | M49: =SUM(M54)-SUM(L54)-SUM(M42:M48) -> 0 | N49: =SUM(N54)-SUM(M54)-SUM(N42:N48) -> 0 | O49: =SUM(O54)-SUM(N54)-SUM(O42:O48) -> 3286.2 | P49: =SUM(P54)-SUM(O54)-SUM(P42:P48) -> -3286.2 | ... T49: =SUM(T54)-SUM(S54)-SUM(T42:T48) -> 0 | V49: =SUM(H49:K49) -> 3551.5 | W49: =SUM(I49:L49) -> 0 | X49: =SUM(J49:M49) -> 0 | Y49: =SUM(K49:N49) -> 0 | Z49: =SUM(L49:O49) -> -265.3 | AA49: =SUM(M49:P49) -> 0 | AB49: =SUM(N49:Q49) -> 0 | AC49: =SUM(O49:R49) -> 0 | ... AE49: =SUM(Q49:T49) -> 0
B50: Free-Cash Flows | C50: =SUM(C42+SUM(C44:C49)) -> 0 | D50: =SUM(D42+SUM(D44:D49)) -> 0 | E50: =SUM(E42+SUM(E44:E49)) -> 0 | F50: =SUM(F42+SUM(F44:F49)) -> 0 | H50: =SUM(H42+SUM(H44:H49)) -> 0 | I50: =SUM(I42+SUM(I44:I49)) -> 0 | J50: =SUM(J42+SUM(J44:J49)) -> 0 | K50: =SUM(K42+SUM(K44:K49)) -> 3551.5 | L50: =SUM(L42+SUM(L44:L49)) -> -3551.5 | M50: =SUM(M42+SUM(M44:M49)) -> 0 | N50: =SUM(N42+SUM(N44:N49)) -> 0 | O50: =SUM(O42+SUM(O44:O49)) -> 3286.2 | ... T50: =SUM(T42+SUM(T44:T49)) -> 0 | V50: =SUM(V42+SUM(V44:V49)) -> 3551.5 | W50: =SUM(W42+SUM(W44:W49)) -> 0 | X50: =SUM(X42+SUM(X44:X49)) -> 0 | Y50: =SUM(Y42+SUM(Y44:Y49)) -> 0 | Z50: =SUM(Z42+SUM(Z44:Z49)) -> -265.3 | AA50: =SUM(AA42+SUM(AA44:AA49)) -> 0 | AB50: =SUM(AB42+SUM(AB44:AB49)) -> 0 | AC50: =SUM(AC42+SUM(AC44:AC49)) -> 0 | ... AE50: =SUM(AE42+SUM(AE44:AE49)) -> 0
B52: Capitalization
B54: Cash & Cash Equivelants | K54: ='Historical Financials'!K48 -> 3551.5 | O54: ='Historical Financials'!O48 -> 3286.2 | S54: ='Historical Financials'!S48 -> 0 | V54: =K54 -> 3551.5 | W54: =L54 -> 0 | X54: =M54 -> 0 | Y54: =N54 -> 0 | Z54: =O54 -> 3286.2 | AA54: =P54 -> 0 | AB54: =Q54 -> 0 | AC54: =R54 -> 0 | ... AE54: =T54 -> 0
B55: XXX | K55: ='Historical Financials'!K49 -> 401.5 | O55: ='Historical Financials'!O49 -> 257 | S55: ='Historical Financials'!S49 -> 0 | V55: =K55 -> 401.5 | W55: =L55 -> 0 | X55: =M55 -> 0 | Y55: =N55 -> 0 | Z55: =O55 -> 257 | AA55: =P55 -> 0 | AB55: =Q55 -> 0 | AC55: =R55 -> 0 | ... AE55: =T55 -> 0
B56: XXX | K56: =D56 -> 0 | O56: =E56 -> 0 | S56: =F56 -> 0 | V56: =K56 -> 0 | W56: =L56 -> 0 | X56: =M56 -> 0 | Y56: =N56 -> 0 | Z56: =O56 -> 0 | AA56: =P56 -> 0 | AB56: =Q56 -> 0 | AC56: =R56 -> 0 | ... AE56: =T56 -> 0
B57: Total Liquidity | C57: =SUM(C54:C56) -> 0 | D57: =SUM(D54:D56) -> 0 | E57: =SUM(E54:E56) -> 0 | F57: =SUM(F54:F56) -> 0 | H57: =SUM(H54:H56) -> 0 | I57: =SUM(I54:I56) -> 0 | J57: =SUM(J54:J56) -> 0 | K57: =SUM(K54:K56) -> 3953 | L57: =SUM(L54:L56) -> 0 | M57: =SUM(M54:M56) -> 0 | N57: =SUM(N54:N56) -> 0 | O57: =SUM(O54:O56) -> 3543.2 | ... T57: =SUM(T54:T56) -> 0 | V57: =SUM(V54:V56) -> 3953 | W57: =SUM(W54:W56) -> 0 | X57: =SUM(X54:X56) -> 0 | Y57: =SUM(Y54:Y56) -> 0 | Z57: =SUM(Z54:Z56) -> 3543.2 | AA57: =SUM(AA54:AA56) -> 0 | AB57: =SUM(AB54:AB56) -> 0 | AC57: =SUM(AC54:AC56) -> 0 | ... AE57: =SUM(AE54:AE56) -> 0
B59: Balance Sheet Metrics:
B60: XXX | V60: =K60 -> 0 | W60: =L60 -> 0 | X60: =M60 -> 0 | Y60: =N60 -> 0 | Z60: =O60 -> 0 | AA60: =P60 -> 0 | AB60: =Q60 -> 0 | AC60: =R60 -> 0 | ... AE60: =T60 -> 0
B61: XXX | V61: =K61 -> 0 | W61: =L61 -> 0 | X61: =M61 -> 0 | Y61: =N61 -> 0 | Z61: =O61 -> 0 | AA61: =P61 -> 0 | AB61: =Q61 -> 0 | AC61: =R61 -> 0 | ... AE61: =T61 -> 0
B62: XXX | V62: =K62 -> 0 | W62: =L62 -> 0 | X62: =M62 -> 0 | Y62: =N62 -> 0 | Z62: =O62 -> 0 | AA62: =P62 -> 0 | AB62: =Q62 -> 0 | AC62: =R62 -> 0 | ... AE62: =T62 -> 0
B63: XXX | V63: =K63 -> 0 | W63: =L63 -> 0 | X63: =M63 -> 0 | Y63: =N63 -> 0 | Z63: =O63 -> 0 | AA63: =P63 -> 0 | AB63: =Q63 -> 0 | AC63: =R63 -> 0 | ... AE63: =T63 -> 0
B64: XXX | V64: =K64 -> 0 | W64: =L64 -> 0 | X64: =M64 -> 0 | Y64: =N64 -> 0 | Z64: =O64 -> 0 | AA64: =P64 -> 0 | AB64: =Q64 -> 0 | AC64: =R64 -> 0 | ... AE64: =T64 -> 0
B65: XXX | V65: =K65 -> 0 | W65: =L65 -> 0 | X65: =M65 -> 0 | Y65: =N65 -> 0 | Z65: =O65 -> 0 | AA65: =P65 -> 0 | AB65: =Q65 -> 0 | AC65: =R65 -> 0 | ... AE65: =T65 -> 0
B66: XXX | V66: =K66 -> 0 | W66: =L66 -> 0 | X66: =M66 -> 0 | Y66: =N66 -> 0 | Z66: =O66 -> 0 | AA66: =P66 -> 0 | AB66: =Q66 -> 0 | AC66: =R66 -> 0 | ... AE66: =T66 -> 0
B68: Summary Debt:
B69: CPLTD | V69: =K69 -> 0 | W69: =L69 -> 0 | X69: =M69 -> 0 | Y69: =N69 -> 0 | Z69: =O69 -> 0 | AA69: =P69 -> 0 | AB69: =Q69 -> 0 | AC69: =R69 -> 0 | ... AE69: =T69 -> 0
B70: LTD | V70: =K70 -> 0 | W70: =L70 -> 0 | X70: =M70 -> 0 | Y70: =N70 -> 0 | Z70: =O70 -> 0 | AA70: =P70 -> 0 | AB70: =Q70 -> 0 | AC70: =R70 -> 0 | ... AE70: =T70 -> 0
B72: XXX | K72: =D72 -> 0 | O72: =E72 -> 0 | S72: =F72 -> 0 | V72: =K72 -> 0 | W72: =L72 -> 0 | X72: =M72 -> 0 | Y72: =N72 -> 0 | Z72: =O72 -> 0 | AA72: =P72 -> 0 | AB72: =Q72 -> 0 | AC72: =R72 -> 0 | ... AE72: =T72 -> 0
B73: XXX | K73: =D73 -> 0 | O73: =E73 -> 0 | S73: =F73 -> 0 | V73: =K73 -> 0 | W73: =L73 -> 0 | X73: =M73 -> 0 | Y73: =N73 -> 0 | Z73: =O73 -> 0 | AA73: =P73 -> 0 | AB73: =Q73 -> 0 | AC73: =R73 -> 0 | ... AE73: =T73 -> 0
B74: XXX | K74: =D74 -> 0 | O74: =E74 -> 0 | S74: =F74 -> 0 | V74: =K74 -> 0 | W74: =L74 -> 0 | X74: =M74 -> 0 | Y74: =N74 -> 0 | Z74: =O74 -> 0 | AA74: =P74 -> 0 | AB74: =Q74 -> 0 | AC74: =R74 -> 0 | ... AE74: =T74 -> 0
B75: XXX | K75: ='Historical Financials'!K72+'Historical Financials'!#REF! -> #REF! | O75: ='Historical Financials'!O72+'Historical Financials'!#REF! -> #REF! | S75: ='Historical Financials'!S72+'Historical Financials'!#REF! -> #REF! | V75: =K75 -> #REF! | W75: =L75 -> 0 | X75: =M75 -> 0 | Y75: =N75 -> 0 | Z75: =O75 -> #REF! | AA75: =P75 -> 0 | AB75: =Q75 -> 0 | AC75: =R75 -> 0 | ... AE75: =T75 -> 0
B76: Total Debt | C76: =SUM(C72:C75) -> 0 | D76: =SUM(D72:D75) -> 0 | E76: =SUM(E72:E75) -> 0 | F76: =SUM(F72:F75) -> 0 | H76: =SUM(H72:H75) -> 0 | I76: =SUM(I72:I75) -> 0 | J76: =SUM(J72:J75) -> 0 | K76: =SUM(K72:K75) -> #REF! | L76: =SUM(L72:L75) -> 0 | M76: =SUM(M72:M75) -> 0 | N76: =SUM(N72:N75) -> 0 | O76: =SUM(O72:O75) -> #REF! | ... T76: =SUM(T72:T75) -> 0 | V76: =SUM(V72:V75) -> #REF! | W76: =SUM(W72:W75) -> 0 | X76: =SUM(X72:X75) -> 0 | Y76: =SUM(Y72:Y75) -> 0 | Z76: =SUM(Z72:Z75) -> #REF! | AA76: =SUM(AA72:AA75) -> 0 | AB76: =SUM(AB72:AB75) -> 0 | AC76: =SUM(AC72:AC75) -> 0 | ... AE76: =SUM(AE72:AE75) -> 0
B78: Total Shareholder Equity | V78: =K78 -> 0 | W78: =L78 -> 0 | X78: =M78 -> 0 | Y78: =N78 -> 0 | Z78: =O78 -> 0 | AA78: =P78 -> 0 | AB78: =Q78 -> 0 | AC78: =R78 -> 0 | ... AE78: =T78 -> 0
B79: Total Book Capitalization | C79: =SUM(C76:C78) -> 0 | D79: =SUM(D76:D78) -> 0 | E79: =SUM(E76:E78) -> 0 | F79: =SUM(F76:F78) -> 0 | H79: =SUM(H76:H78) -> 0 | I79: =SUM(I76:I78) -> 0 | J79: =SUM(J76:J78) -> 0 | K79: =SUM(K76:K78) -> #REF! | L79: =SUM(L76:L78) -> 0 | M79: =SUM(M76:M78) -> 0 | N79: =SUM(N76:N78) -> 0 | O79: =SUM(O76:O78) -> #REF! | ... T79: =SUM(T76:T78) -> 0 | V79: =SUM(V76:V78) -> #REF! | W79: =SUM(W76:W78) -> 0 | X79: =SUM(X76:X78) -> 0 | Y79: =SUM(Y76:Y78) -> 0 | Z79: =SUM(Z76:Z78) -> #REF! | AA79: =SUM(AA76:AA78) -> 0 | AB79: =SUM(AB76:AB78) -> 0 | AC79: =SUM(AC76:AC78) -> 0 | ... AE79: =SUM(AE76:AE78) -> 0
B81: Credit Metrics
B83: LTM Total Leverage | C83: =C76/C34 -> #DIV/0! | D83: =D76/D34 -> #DIV/0! | E83: =E76/E34 -> #DIV/0! | F83: =F76/F34 -> #DIV/0! | K83: =SUM(K76/SUM(H34:K34)) -> #REF! | L83: =SUM(L76/SUM(I34:L34)) -> #DIV/0! | M83: =SUM(M76/SUM(J34:M34)) -> #DIV/0! | N83: =SUM(N76/SUM(K34:N34)) -> #DIV/0! | O83: =SUM(O76/SUM(L34:O34)) -> #REF! | P83: =SUM(P76/SUM(M34:P34)) -> #DIV/0! | Q83: =SUM(Q76/SUM(N34:Q34)) -> #DIV/0! | R83: =SUM(R76/SUM(O34:R34)) -> #DIV/0! | ... T83: =SUM(T76/SUM(Q34:T34)) -> #DIV/0! | V83: =V76/V34 -> #REF! | W83: =W76/W34 -> #DIV/0! | X83: =X76/X34 -> #DIV/0! | Y83: =Y76/Y34 -> #DIV/0! | Z83: =Z76/Z34 -> #REF! | AA83: =AA76/AA34 -> #DIV/0! | AB83: =AB76/AB34 -> #DIV/0! | AC83: =AC76/AC34 -> #DIV/0! | ... AE83: =AE76/AE34 -> #DIV/0!
B84: LTM Net Leverage | C84: =SUM(C76-C54)/C34 -> #DIV/0! | D84: =SUM(D76-D54)/D34 -> #DIV/0! | E84: =SUM(E76-E54)/E34 -> #DIV/0! | F84: =SUM(F76-F54)/F34 -> #DIV/0! | K84: =SUM(K76-K54)/SUM(H34:K34) -> #REF! | L84: =SUM(L76-L54)/SUM(I34:L34) -> #DIV/0! | M84: =SUM(M76-M54)/SUM(J34:M34) -> #DIV/0! | N84: =SUM(N76-N54)/SUM(K34:N34) -> #DIV/0! | O84: =SUM(O76-O54)/SUM(L34:O34) -> #REF! | P84: =SUM(P76-P54)/SUM(M34:P34) -> #DIV/0! | Q84: =SUM(Q76-Q54)/SUM(N34:Q34) -> #DIV/0! | R84: =SUM(R76-R54)/SUM(O34:R34) -> #DIV/0! | ... T84: =SUM(T76-T54)/SUM(Q34:T34) -> #DIV/0! | V84: =SUM(V76-V54)/V34 -> #REF! | W84: =SUM(W76-W54)/W34 -> #DIV/0! | X84: =SUM(X76-X54)/X34 -> #DIV/0! | Y84: =SUM(Y76-Y54)/Y34 -> #DIV/0! | Z84: =SUM(Z76-Z54)/Z34 -> #REF! | AA84: =SUM(AA76-AA54)/AA34 -> #DIV/0! | AB84: =SUM(AB76-AB54)/AB34 -> #DIV/0! | AC84: =SUM(AC76-AC54)/AC34 -> #DIV/0! | ... AE84: =SUM(AE76-AE54)/AE34 -> #DIV/0!
B85: LTM Interest Coverage | C85: =C34/-C39 -> #DIV/0! | D85: =D34/-D39 -> #DIV/0! | E85: =E34/-E39 -> #DIV/0! | F85: =F34/-F39 -> #DIV/0! | K85: {=SUM(H34:K34)/SUM(-H39:K39)} -> #DIV/0! | L85: {=SUM(I34:L34)/SUM(-I39:L39)} -> #DIV/0! | M85: {=SUM(J34:M34)/SUM(-J39:M39)} -> #DIV/0! | N85: {=SUM(K34:N34)/SUM(-K39:N39)} -> #DIV/0! | O85: {=SUM(L34:O34)/SUM(-L39:O39)} -> #DIV/0! | P85: {=SUM(M34:P34)/SUM(-M39:P39)} -> #DIV/0! | Q85: {=SUM(N34:Q34)/SUM(-N39:Q39)} -> #DIV/0! | R85: {=SUM(O34:R34)/SUM(-O39:R39)} -> #DIV/0! | ... T85: {=SUM(Q34:T34)/SUM(-Q39:T39)} -> #DIV/0! | V85: =V34/-V39 -> #DIV/0! | W85: =W34/-W39 -> #DIV/0! | X85: =X34/-X39 -> #DIV/0! | Y85: =Y34/-Y39 -> #DIV/0! | Z85: =Z34/-Z39 -> #DIV/0! | AA85: =AA34/-AA39 -> #DIV/0! | AB85: =AB34/-AB39 -> #DIV/0! | AC85: =AC34/-AC39 -> #DIV/0! | ... AE85: =AE34/-AE39 -> #DIV/0!
B86: LTM Debt Service Coverage | C86: {=SUM(C34+C37)/SUM(-C38:C39)} -> #DIV/0! | D86: {=SUM(D34+D37)/SUM(-D38:D39)} -> #DIV/0! | E86: {=SUM(E34+E37)/SUM(-E38:E39)} -> #DIV/0! | F86: {=SUM(F34+F37)/SUM(-F38:F39)} -> #DIV/0! | K86: {=SUM(H34:K34+H37:K37)/SUM(-H38:K39)} -> #DIV/0! | L86: {=SUM(I34:L34+I37:L37)/SUM(-I38:L39)} -> #DIV/0! | M86: {=SUM(J34:M34+J37:M37)/SUM(-J38:M39)} -> #DIV/0! | N86: {=SUM(K34:N34+K37:N37)/SUM(-K38:N39)} -> #DIV/0! | O86: {=SUM(L34:O34+L37:O37)/SUM(-L38:O39)} -> #DIV/0! | P86: {=SUM(M34:P34+M37:P37)/SUM(-M38:P39)} -> #DIV/0! | Q86: {=SUM(N34:Q34+N37:Q37)/SUM(-N38:Q39)} -> #DIV/0! | R86: {=SUM(O34:R34+O37:R37)/SUM(-O38:R39)} -> #DIV/0! | ... T86: {=SUM(Q34:T34+Q37:T37)/SUM(-Q38:T39)} -> #DIV/0! | V86: {=SUM(V34+V37)/SUM(-V38:V39)} -> #DIV/0! | W86: {=SUM(W34+W37)/SUM(-W38:W39)} -> #DIV/0! | X86: {=SUM(X34+X37)/SUM(-X38:X39)} -> #DIV/0! | Y86: {=SUM(Y34+Y37)/SUM(-Y38:Y39)} -> #DIV/0! | Z86: {=SUM(Z34+Z37)/SUM(-Z38:Z39)} -> #DIV/0! | AA86: {=SUM(AA34+AA37)/SUM(-AA38:AA39)} -> #DIV/0! | AB86: {=SUM(AB34+AB37)/SUM(-AB38:AB39)} -> #DIV/0! | AC86: {=SUM(AC34+AC37)/SUM(-AC38:AC39)} -> #DIV/0! | ... AE86: {=SUM(AE34+AE37)/SUM(-AE38:AE39)} -> #DIV/0!
B87: LTM Fixed Charge Coverage | C87: {=SUM(C34)/SUM(-C37:C39)} -> #DIV/0! | D87: {=SUM(D34)/SUM(-D37:D39)} -> #DIV/0! | E87: {=SUM(E34)/SUM(-E37:E39)} -> #DIV/0! | F87: {=SUM(F34)/SUM(-F37:F39)} -> #DIV/0! | K87: {=SUM(H34:K34)/SUM(-H37:K39)} -> #DIV/0! | L87: {=SUM(I34:L34)/SUM(-I37:L39)} -> #DIV/0! | M87: {=SUM(J34:M34)/SUM(-J37:M39)} -> #DIV/0! | N87: {=SUM(K34:N34)/SUM(-K37:N39)} -> #DIV/0! | O87: {=SUM(L34:O34)/SUM(-L37:O39)} -> #DIV/0! | P87: {=SUM(M34:P34)/SUM(-M37:P39)} -> #DIV/0! | Q87: {=SUM(N34:Q34)/SUM(-N37:Q39)} -> #DIV/0! | R87: {=SUM(O34:R34)/SUM(-O37:R39)} -> #DIV/0! | ... T87: {=SUM(Q34:T34)/SUM(-Q37:T39)} -> #DIV/0! | V87: {=SUM(V34)/SUM(-V37:V39)} -> #DIV/0! | W87: {=SUM(W34)/SUM(-W37:W39)} -> #DIV/0! | X87: {=SUM(X34)/SUM(-X37:X39)} -> #DIV/0! | Y87: {=SUM(Y34)/SUM(-Y37:Y39)} -> #DIV/0! | Z87: {=SUM(Z34)/SUM(-Z37:Z39)} -> #DIV/0! | AA87: {=SUM(AA34)/SUM(-AA37:AA39)} -> #DIV/0! | AB87: {=SUM(AB34)/SUM(-AB37:AB39)} -> #DIV/0! | AC87: {=SUM(AC34)/SUM(-AC37:AC39)} -> #DIV/0! | ... AE87: {=SUM(AE34)/SUM(-AE37:AE39)} -> #DIV/0!
B88: Debt-to-Book Capitalization | C88: =C79/C76 -> #DIV/0! | D88: =D79/D76 -> #DIV/0! | E88: =E79/E76 -> #DIV/0! | F88: =F79/F76 -> #DIV/0! | K88: =K79/K76 -> #REF! | L88: =L79/L76 -> #DIV/0! | M88: =M79/M76 -> #DIV/0! | N88: =N79/N76 -> #DIV/0! | O88: =O79/O76 -> #REF! | P88: =P79/P76 -> #DIV/0! | Q88: =Q79/Q76 -> #DIV/0! | R88: =R79/R76 -> #DIV/0! | ... T88: =T79/T76 -> #DIV/0! | V88: =V79/V76 -> #REF! | W88: =W79/W76 -> #DIV/0! | X88: =X79/X76 -> #DIV/0! | Y88: =Y79/Y76 -> #DIV/0! | Z88: =Z79/Z76 -> #REF! | AA88: =AA79/AA76 -> #DIV/0! | AB88: =AB79/AB76 -> #DIV/0! | AC88: =AC79/AC76 -> #DIV/0! | ... AE88: =AE79/AE76 -> #DIV/0!
