Workbook

Sheet Historical Financials
B2: Snap Inc (NASDAQ: SNAP)
B3: Historical Financials
B4: ($ In Millions, except EPS)
A6: X | B6: Income Statement | D6: FYE | G6: Quarterly | M6: Quarterly | V6: LTM | AB6: Variance
B7: Fiscal Period | C7: 2022 | D7: 2023 | E7: 2024 | G7: 1Q23 | H7: 2Q23 | I7: 3Q23 | J7: 4Q23 | K7: 1Q24 | L7: 2Q24 | M7: 3Q24 | N7: 4Q24 | O7: 1Q25 | P7: 2Q25 | Q7: 3Q25 | S7: =J7 -> 4Q23 | T7: =K7 -> 1Q24 | U7: =L7 -> 2Q24 | V7: =M7 -> 3Q24 | W7: =N7 -> 4Q24 | X7: =O7 -> 1Q25 | Y7: =P7 -> 2Q25 | Z7: =Q7 -> 3Q25
B8: Fiscal Period End Date | C8: 44926 | D8: 45291 | E8: 45657 | G8: 45016 | H8: 45107 | I8: 45199 | J8: =D8 -> 45291 | K8: 45382 | L8: 45473 | M8: 45565 | N8: =E8 -> 45657 | O8: 45747 | P8: 45838 | Q8: 45930 | S8: =J8 -> 45291 | T8: =K8 -> 45382 | U8: =L8 -> 45473 | V8: =M8 -> 45565 | W8: =N8 -> 45657 | X8: =O8 -> 45747 | Y8: =P8 -> 45838 | Z8: =Q8 -> 45930
B10: Consolidated Revenue | C10: 4601.8 | D10: 4606.2 | E10: 5361.5 | G10: 988.608 | H10: 1067.669 | I10: 1188.551 | J10: =SUM(D10-SUM(G10:I10)) -> 1361.372 | K10: 1194.773 | L10: 1236.768 | M10: 1372.574 | N10: =SUM(E10-SUM(K10:M10)) -> 1557.385 | O10: 1363.217 | P10: 1344.93 | Q10: 1506.839 | S10: =SUM(G10:J10) -> 4606.2 | T10: =SUM(H10:K10) -> 4812.365 | U10: =SUM(I10:L10) -> 4981.464 | V10: =SUM(J10:M10) -> 5165.487 | W10: =SUM(K10:N10) -> 5361.5 | X10: =SUM(L10:O10) -> 5529.944 | Y10: =SUM(M10:P10) -> 5638.106 | Z10: =SUM(N10:Q10) -> 5772.371 | AB10: =SUM(Z10/V10)-1 -> 0.11748824
B11: Total Revenue | C11: =+SUM(C10:C10) -> 4601.8 | D11: =+SUM(D10:D10) -> 4606.2 | E11: =+SUM(E10:E10) -> 5361.5 | G11: =+SUM(G10:G10) -> 988.608 | H11: =+SUM(H10:H10) -> 1067.669 | I11: =+SUM(I10:I10) -> 1188.551 | J11: =+SUM(J10:J10) -> 1361.372 | K11: =+SUM(K10:K10) -> 1194.773 | L11: =+SUM(L10:L10) -> 1236.768 | M11: =+SUM(M10:M10) -> 1372.574 | N11: =+SUM(N10:N10) -> 1557.385 | ... Q11: =+SUM(Q10:Q10) -> 1506.839 | S11: =+SUM(S10:S10) -> 4606.2 | T11: =+SUM(T10:T10) -> 4812.365 | U11: =+SUM(U10:U10) -> 4981.464 | V11: =+SUM(V10:V10) -> 5165.487 | W11: =+SUM(W10:W10) -> 5361.5 | X11: =+SUM(X10:X10) -> 5529.944 | Y11: =+SUM(Y10:Y10) -> 5638.106 | Z11: =+SUM(Z10:Z10) -> 5772.371 | AB11: =SUM(Z11/V11)-1 -> 0.11748824
B13: Cost of Sales | C13: -1815.4 | D13: -2114.2 | E13: -2474.2 | G13: -439.986 | H13: -496.874 | I13: -555.753 | J13: =SUM(D13-SUM(G13:I13)) -> -621.587 | K13: -574.749 | L13: -588.921 | M13: -638.907 | N13: =SUM(E13-SUM(K13:M13)) -> -671.623 | O13: -639.579 | P13: -653.333 | Q13: -674.22 | S13: =SUM(G13:J13) -> -2114.2 | T13: =SUM(H13:K13) -> -2248.963 | U13: =SUM(I13:L13) -> -2341.01 | V13: =SUM(J13:M13) -> -2424.164 | W13: =SUM(K13:N13) -> -2474.2 | X13: =SUM(L13:O13) -> -2539.03 | Y13: =SUM(M13:P13) -> -2603.442 | Z13: =SUM(N13:Q13) -> -2638.755 | AB13: =SUM(Z13/V13)-1 -> 0.088521651
B14: Gross Profit | C14: =+SUM(C11+SUM(C13:C13)) -> 2786.4 | D14: =+SUM(D11+SUM(D13:D13)) -> 2492 | E14: =+SUM(E11+SUM(E13:E13)) -> 2887.3 | G14: =+SUM(G11+SUM(G13:G13)) -> 548.622 | H14: =+SUM(H11+SUM(H13:H13)) -> 570.795 | I14: =+SUM(I11+SUM(I13:I13)) -> 632.798 | J14: =+SUM(J11+SUM(J13:J13)) -> 739.785 | K14: =+SUM(K11+SUM(K13:K13)) -> 620.024 | L14: =+SUM(L11+SUM(L13:L13)) -> 647.847 | M14: =+SUM(M11+SUM(M13:M13)) -> 733.667 | N14: =+SUM(N11+SUM(N13:N13)) -> 885.762 | ... Q14: =+SUM(Q11+SUM(Q13:Q13)) -> 832.619 | S14: =+SUM(S11+SUM(S13:S13)) -> 2492 | T14: =+SUM(T11+SUM(T13:T13)) -> 2563.402 | U14: =+SUM(U11+SUM(U13:U13)) -> 2640.454 | V14: =+SUM(V11+SUM(V13:V13)) -> 2741.323 | W14: =+SUM(W11+SUM(W13:W13)) -> 2887.3 | X14: =+SUM(X11+SUM(X13:X13)) -> 2990.914 | Y14: =+SUM(Y11+SUM(Y13:Y13)) -> 3034.664 | Z14: =+SUM(Z11+SUM(Z13:Z13)) -> 3133.616 | AB14: =SUM(Z14/V14)-1 -> 0.14310353
B15: Gross Margin (%) | C15: =C14/C11 -> 0.60550219 | D15: =D14/D11 -> 0.54100994 | E15: =E14/E11 -> 0.53852467 | G15: =G14/G11 -> 0.55494392 | H15: =H14/H11 -> 0.53461794 | I15: =I14/I11 -> 0.53241131 | J15: =J14/J11 -> 0.54341135 | K15: =K14/K11 -> 0.51894711 | L15: =L14/L11 -> 0.52382258 | M15: =M14/M11 -> 0.53451909 | N15: =N14/N11 -> 0.56874954 | ... Q15: =Q14/Q11 -> 0.55256003 | S15: =S14/S11 -> 0.54100994 | T15: =T14/T11 -> 0.5326699 | U15: =U14/U11 -> 0.53005582 | V15: =V14/V11 -> 0.53069982 | W15: =W14/W11 -> 0.53852467 | X15: =X14/X11 -> 0.54085792 | Y15: =Y14/Y11 -> 0.53824174 | Z15: =Z14/Z11 -> 0.54286462 | AB15: =SUM(Z15-V15)*1000 -> 12.164806
B17: Research and development | C17: -2109.8 | D17: -1910.9 | E17: -1691.7 | G17: -455.112 | H17: -477.663 | I17: -494.6 | J17: =SUM(D17-SUM(G17:I17)) -> -483.525 | K17: -449.759 | L17: -406.196 | M17: -412.791 | N17: =SUM(E17-SUM(K17:M17)) -> -422.954 | O17: -424.165 | P17: -443.325 | Q17: -453.418 | S17: =SUM(G17:J17) -> -1910.9 | T17: =SUM(H17:K17) -> -1905.547 | U17: =SUM(I17:L17) -> -1834.08 | V17: =SUM(J17:M17) -> -1752.271 | W17: =SUM(K17:N17) -> -1691.7 | X17: =SUM(L17:O17) -> -1666.106 | Y17: =SUM(M17:P17) -> -1703.235 | Z17: =SUM(N17:Q17) -> -1743.862 | AB17: =SUM(Z17/V17)-1 -> -0.0047989152
B18: Sales and Marketing | C18: -1118.8 | D18: -1122 | E18: -1063.7 | G18: -268.433 | H18: -280.597 | I18: -297.2 | J18: =SUM(D18-SUM(G18:I18)) -> -275.77 | K18: -276.034 | L18: -266.32 | M18: -273.107 | N18: =SUM(E18-SUM(K18:M18)) -> -248.239 | O18: -257.957 | P18: -257.853 | Q18: -256.215 | S18: =SUM(G18:J18) -> -1122 | T18: =SUM(H18:K18) -> -1129.601 | U18: =SUM(I18:L18) -> -1115.324 | V18: =SUM(J18:M18) -> -1091.231 | W18: =SUM(K18:N18) -> -1063.7 | X18: =SUM(L18:O18) -> -1045.623 | Y18: =SUM(M18:P18) -> -1037.156 | Z18: =SUM(N18:Q18) -> -1020.264 | AB18: =SUM(Z18/V18)-1 -> -0.065033893
B19: General and Administrative | C19: -953.3 | D19: -857.5 | E19: -919.1 | G19: -190.341 | H19: -216.874 | I19: -221.1 | J19: =SUM(D19-SUM(G19:I19)) -> -229.185 | K19: -227.463 | L19: -229.306 | M19: -220.979 | N19: =SUM(E19-SUM(K19:M19)) -> -241.352 | O19: -235.362 | P19: -250.095 | Q19: -251.348 | S19: =SUM(G19:J19) -> -857.5 | T19: =SUM(H19:K19) -> -894.622 | U19: =SUM(I19:L19) -> -907.054 | V19: =SUM(J19:M19) -> -906.933 | W19: =SUM(K19:N19) -> -919.1 | X19: =SUM(L19:O19) -> -926.999 | Y19: =SUM(M19:P19) -> -947.788 | Z19: =SUM(N19:Q19) -> -978.157 | AB19: =SUM(Z19/V19)-1 -> 0.078532813
B20: Operating Profit | C20: =+SUM(C14+SUM(C17:C19)) -> -1395.5 | D20: =+SUM(D14+SUM(D17:D19)) -> -1398.4 | E20: =+SUM(E14+SUM(E17:E19)) -> -787.2 | G20: =+SUM(G14+SUM(G17:G19)) -> -365.264 | H20: =+SUM(H14+SUM(H17:H19)) -> -404.339 | I20: =+SUM(I14+SUM(I17:I19)) -> -380.102 | J20: =+SUM(J14+SUM(J17:J19)) -> -248.695 | K20: =+SUM(K14+SUM(K17:K19)) -> -333.232 | L20: =+SUM(L14+SUM(L17:L19)) -> -253.975 | M20: =+SUM(M14+SUM(M17:M19)) -> -173.21 | N20: =+SUM(N14+SUM(N17:N19)) -> -26.783 | ... Q20: =+SUM(Q14+SUM(Q17:Q19)) -> -128.362 | S20: =+SUM(S14+SUM(S17:S19)) -> -1398.4 | T20: =+SUM(T14+SUM(T17:T19)) -> -1366.368 | U20: =+SUM(U14+SUM(U17:U19)) -> -1216.004 | V20: =+SUM(V14+SUM(V17:V19)) -> -1009.112 | W20: =+SUM(W14+SUM(W17:W19)) -> -787.2 | X20: =+SUM(X14+SUM(X17:X19)) -> -647.814 | Y20: =+SUM(Y14+SUM(Y17:Y19)) -> -653.515 | Z20: =+SUM(Z14+SUM(Z17:Z19)) -> -608.667 | AB20: =SUM(Z20/V20)-1 -> -0.39682909
B21: Operating Margin (%) | C21: =C20/C11 -> -0.3032509 | D21: =D20/D11 -> -0.30359081 | E21: =E20/E11 -> -0.14682458 | G21: =G20/G11 -> -0.36947304 | H21: =H20/H11 -> -0.37871194 | I21: =I20/I11 -> -0.31980285 | J21: =J20/J11 -> -0.18267968 | K21: =K20/K11 -> -0.27890821 | L21: =L20/L11 -> -0.20535379 | M21: =M20/M11 -> -0.12619356 | N21: =N20/N11 -> -0.017197417 | ... Q21: =Q20/Q11 -> -0.085186274 | S21: =S20/S11 -> -0.30359081 | T21: =T20/T11 -> -0.28392859 | U21: =U20/U11 -> -0.24410575 | V21: =V20/V11 -> -0.1953566 | W21: =W20/W11 -> -0.14682458 | X21: =X20/X11 -> -0.11714658 | Y21: =Y20/Y11 -> -0.11591038 | Z21: =Z20/Z11 -> -0.10544489 | AB21: =SUM(Z21-V21)*1000 -> 89.911719
B23: Interest Income | C23: 58.597 | D23: 168.394 | E23: 153.466 | G23: 37.948 | H23: 43.144 | I23: 43.839 | J23: =SUM(D23-SUM(G23:I23)) -> 43.463 | K23: 39.898 | L23: 36.462 | M23: 38.533 | N23: =SUM(E23-SUM(K23:M23)) -> 38.573 | O23: 37.018 | P23: 33.199 | Q23: 32.255 | S23: =SUM(G23:J23) -> 168.394 | T23: =SUM(H23:K23) -> 170.344 | U23: =SUM(I23:L23) -> 163.662 | V23: =SUM(J23:M23) -> 158.356 | W23: =SUM(K23:N23) -> 153.466 | X23: =SUM(L23:O23) -> 150.586 | Y23: =SUM(M23:P23) -> 147.323 | Z23: =SUM(N23:Q23) -> 141.045 | AB23: =SUM(Z23/V23)-1 -> -0.10931698
B24: Interest Expenses | C24: -21.459 | D24: -22.024 | E24: -21.552 | G24: -5.885 | H24: -5.343 | I24: -5.521 | J24: =SUM(D24-SUM(G24:I24)) -> -5.275 | K24: -4.743 | L24: -5.113 | M24: -5.883 | N24: =SUM(E24-SUM(K24:M24)) -> -5.813 | O24: -23.399 | P24: -27.607 | Q24: -34.494 | S24: =SUM(G24:J24) -> -22.024 | T24: =SUM(H24:K24) -> -20.882 | U24: =SUM(I24:L24) -> -20.652 | V24: =SUM(J24:M24) -> -21.014 | W24: =SUM(K24:N24) -> -21.552 | X24: =SUM(L24:O24) -> -40.208 | Y24: =SUM(M24:P24) -> -62.702 | Z24: =SUM(N24:Q24) -> -91.313 | AB24: =SUM(Z24/V24)-1 -> 3.3453412
B25: Other Income | C25: -42.529 | D25: -42.414 | E25: -16.846 | G25: 11.372 | H25: 1.323 | I25: -20.662 | J25: =SUM(D25-SUM(G25:I25)) -> -34.447 | K25: -0.081 | L25: -20.792 | M25: -4.355 | N25: =SUM(E25-SUM(K25:M25)) -> 8.382 | O25: 49.069 | P25: -0.823 | Q25: 27.57 | S25: =SUM(G25:J25) -> -42.414 | T25: =SUM(H25:K25) -> -53.867 | U25: =SUM(I25:L25) -> -75.982 | V25: =SUM(J25:M25) -> -59.675 | W25: =SUM(K25:N25) -> -16.846 | X25: =SUM(L25:O25) -> 32.304 | Y25: =SUM(M25:P25) -> 52.273 | Z25: =SUM(N25:Q25) -> 84.198 | AB25: =SUM(Z25/V25)-1 -> -2.4109426
B26: Earnings before Taxes | C26: =SUM(C23:C25)+C20 -> -1400.891 | D26: =SUM(D23:D25)+D20 -> -1294.444 | E26: =SUM(E23:E25)+E20 -> -672.132 | G26: =SUM(G23:G25)+G20 -> -321.829 | H26: =SUM(H23:H25)+H20 -> -365.215 | I26: =SUM(I23:I25)+I20 -> -362.446 | J26: =SUM(J23:J25)+J20 -> -244.954 | K26: =SUM(K23:K25)+K20 -> -298.158 | L26: =SUM(L23:L25)+L20 -> -243.418 | M26: =SUM(M23:M25)+M20 -> -144.915 | N26: =SUM(N23:N25)+N20 -> 14.359 | ... Q26: =SUM(Q23:Q25)+Q20 -> -103.031 | S26: =SUM(S23:S25)+S20 -> -1294.444 | T26: =SUM(T23:T25)+T20 -> -1270.773 | U26: =SUM(U23:U25)+U20 -> -1148.976 | V26: =SUM(V23:V25)+V20 -> -931.445 | W26: =SUM(W23:W25)+W20 -> -672.132 | X26: =SUM(X23:X25)+X20 -> -505.132 | Y26: =SUM(Y23:Y25)+Y20 -> -516.621 | Z26: =SUM(Z23:Z25)+Z20 -> -474.737 | AB26: =SUM(Z26/V26)-1 -> -0.49032203
B27: EBT Margin (%) | C27: =C26/C11 -> -0.3044224 | D27: =D26/D11 -> -0.2810221 | E27: =E26/E11 -> -0.12536268 | G27: =G26/G11 -> -0.32553752 | H27: =H26/H11 -> -0.34206763 | I27: =I26/I11 -> -0.30494779 | J27: =J26/J11 -> -0.17993172 | K27: =K26/K11 -> -0.24955201 | L27: =L26/L11 -> -0.19681783 | M27: =M26/M11 -> -0.10557901 | N27: =N26/N11 -> 0.0092199424 | ... Q27: =Q26/Q11 -> -0.068375586 | S27: =S26/S11 -> -0.2810221 | T27: =T26/T11 -> -0.26406413 | U27: =U26/U11 -> -0.23065027 | V27: =V26/V11 -> -0.18032085 | W27: =W26/W11 -> -0.12536268 | X27: =X26/X11 -> -0.091344867 | Y27: =Y26/Y11 -> -0.091630239 | Z27: =Z26/Z11 -> -0.082242981 | AB27: =SUM(Z27-V27)*1000 -> 98.077867
B29: Income tax expense | C29: -28.9 | D29: -28 | E29: -25.6 | G29: -6.845 | H29: -12.093 | I29: -5.8 | J29: =SUM(D29-SUM(G29:I29)) -> -3.262 | K29: -6.932 | L29: -5.202 | M29: -8.332 | N29: =SUM(E29-SUM(K29:M29)) -> -5.134 | O29: -8.429 | P29: -7.663 | Q29: -0.51 | S29: =SUM(G29:J29) -> -28 | T29: =SUM(H29:K29) -> -28.087 | U29: =SUM(I29:L29) -> -21.196 | V29: =SUM(J29:M29) -> -23.728 | W29: =SUM(K29:N29) -> -25.6 | X29: =SUM(L29:O29) -> -27.097 | Y29: =SUM(M29:P29) -> -29.558 | Z29: =SUM(N29:Q29) -> -21.736 | AB29: =SUM(Z29/V29)-1 -> -0.08395145
B30: Net loss | C30: =SUM(C26+SUM(C29:C29)) -> -1429.791 | D30: =SUM(D26+SUM(D29:D29)) -> -1322.444 | E30: =SUM(E26+SUM(E29:E29)) -> -697.732 | G30: =SUM(G26+SUM(G29:G29)) -> -328.674 | H30: =SUM(H26+SUM(H29:H29)) -> -377.308 | I30: =SUM(I26+SUM(I29:I29)) -> -368.246 | J30: =SUM(J26+SUM(J29:J29)) -> -248.216 | K30: =SUM(K26+SUM(K29:K29)) -> -305.09 | L30: =SUM(L26+SUM(L29:L29)) -> -248.62 | M30: =SUM(M26+SUM(M29:M29)) -> -153.247 | N30: =SUM(N26+SUM(N29:N29)) -> 9.225 | ... Q30: =SUM(Q26+SUM(Q29:Q29)) -> -103.541 | S30: =SUM(S26+SUM(S29:S29)) -> -1322.444 | T30: =SUM(T26+SUM(T29:T29)) -> -1298.86 | U30: =SUM(U26+SUM(U29:U29)) -> -1170.172 | V30: =SUM(V26+SUM(V29:V29)) -> -955.173 | W30: =SUM(W26+SUM(W29:W29)) -> -697.732 | X30: =SUM(X26+SUM(X29:X29)) -> -532.229 | Y30: =SUM(Y26+SUM(Y29:Y29)) -> -546.179 | Z30: =SUM(Z26+SUM(Z29:Z29)) -> -496.473 | AB30: =SUM(Z30/V30)-1 -> -0.48022714
B31: Net Margin (%) | C31: =C30/C11 -> -0.31070255 | D31: =D30/D11 -> -0.28710086 | E31: =E30/E11 -> -0.13013746 | G31: =G30/G11 -> -0.3324614 | H31: =H30/H11 -> -0.35339417 | I31: =I30/I11 -> -0.30982768 | J31: =J30/J11 -> -0.18232783 | K31: =K30/K11 -> -0.25535395 | L31: =L30/L11 -> -0.20102396 | M31: =M30/M11 -> -0.11164935 | N31: =N30/N11 -> 0.0059233908 | ... Q31: =Q30/Q11 -> -0.068714043 | S31: =S30/S11 -> -0.28710086 | T31: =T30/T11 -> -0.26990056 | U31: =U30/U11 -> -0.23490524 | V31: =V30/V11 -> -0.18491441 | W31: =W30/W11 -> -0.13013746 | X31: =X30/X11 -> -0.096244917 | Y31: =Y30/Y11 -> -0.09687278 | Z31: =Z30/Z11 -> -0.086008505 | AB31: =SUM(Z31-V31)*1000 -> 98.905909
B33: Basic shares | C33: 1608.304 | D33: 1612.504 | E33: 1659.147 | G33: 1581.37 | H33: 1603.172 | I33: 1625.917 | J33: =D33 -> 1612.504 | K33: 1647.387 | L33: 1644.736 | M33: 1663.011 | N33: =E33 -> 1659.147 | O33: 1696.353 | P33: 1674.854 | Q33: 1696.542 | S33: =J33 -> 1612.504 | T33: =K33 -> 1647.387 | U33: =L33 -> 1644.736 | V33: =M33 -> 1663.011 | W33: =N33 -> 1659.147 | X33: =O33 -> 1696.353 | Y33: =P33 -> 1674.854 | Z33: =Q33 -> 1696.542 | AB33: =SUM(Z33/V33)-1 -> 0.020162825
B34: Basic EPS | C34: =C30/C33 -> -0.88900544 | D34: =D30/D33 -> -0.82011828 | E34: =E30/E33 -> -0.42053658 | G34: =G30/G33 -> -0.2078413 | H34: =H30/H33 -> -0.23535092 | I34: =I30/I33 -> -0.22648512 | J34: =J30/J33 -> -0.15393202 | K34: =K30/K33 -> -0.18519631 | L34: =L30/L33 -> -0.15116104 | M34: =M30/M33 -> -0.092150323 | N34: =N30/N33 -> 0.005560086 | ... Q34: =Q30/Q33 -> -0.061030614 | S34: =S30/S33 -> -0.82011828 | T34: =T30/T33 -> -0.78843648 | U34: =U30/U33 -> -0.71146494 | V34: =V30/V33 -> -0.57436361 | W34: =W30/W33 -> -0.42053658 | X34: =X30/X33 -> -0.31374897 | Y34: =Y30/Y33 -> -0.32610544 | Z34: =Z30/Z33 -> -0.2926382 | AB34: =SUM(Z34/V34)-1 -> -0.4905001
B36: Fully Diluted Shares | C36: 1608.304 | D36: 1612.504 | E36: 1659.147 | G36: 1581.37 | H36: 1603.172 | I36: 1625.917 | J36: =D36 -> 1612.504 | K36: 1647.387 | L36: 1644.736 | M36: 1663.011 | N36: =E36 -> 1659.147 | O36: 1696.353 | P36: 1674.854 | Q36: 1696.542 | S36: =J36 -> 1612.504 | T36: =K36 -> 1647.387 | U36: =L36 -> 1644.736 | V36: =M36 -> 1663.011 | W36: =N36 -> 1659.147 | X36: =O36 -> 1696.353 | Y36: =P36 -> 1674.854 | Z36: =Q36 -> 1696.542 | AB36: =SUM(Z36/V36)-1 -> 0.020162825
B37: Diluted EPS | C37: =C30/C36 -> -0.88900544 | D37: =D30/D36 -> -0.82011828 | E37: =E30/E36 -> -0.42053658 | G37: =G30/G36 -> -0.2078413 | H37: =H30/H36 -> -0.23535092 | I37: =I30/I36 -> -0.22648512 | J37: =J30/J36 -> -0.15393202 | K37: =K30/K36 -> -0.18519631 | L37: =L30/L36 -> -0.15116104 | M37: =M30/M36 -> -0.092150323 | N37: =N30/N36 -> 0.005560086 | ... Q37: =Q30/Q36 -> -0.061030614 | S37: =S30/S36 -> -0.82011828 | T37: =T30/T36 -> -0.78843648 | U37: =U30/U36 -> -0.71146494 | V37: =V30/V36 -> -0.57436361 | W37: =W30/W36 -> -0.42053658 | X37: =X30/X36 -> -0.31374897 | Y37: =Y30/Y36 -> -0.32610544 | Z37: =Z30/Z36 -> -0.2926382 | AB37: =SUM(Z37/V37)-1 -> -0.4905001
A39: X | B39: Balance Sheet | C39: FYE | M39: Quarterly | V39: LTM | AB39: Variance
B40: =B7 -> Fiscal Period | C40: =C7 -> 2022 | D40: =D7 -> 2023 | E40: =E7 -> 2024 | G40: =G7 -> 1Q23 | H40: =H7 -> 2Q23 | I40: =I7 -> 3Q23 | J40: =J7 -> 4Q23 | K40: =K7 -> 1Q24 | L40: =L7 -> 2Q24 | M40: =M7 -> 3Q24 | N40: =N7 -> 4Q24 | ... Q40: =Q7 -> 3Q25 | S40: =S7 -> 4Q23 | T40: =T7 -> 1Q24 | U40: =U7 -> 2Q24 | V40: =V7 -> 3Q24 | W40: =W7 -> 4Q24 | X40: =X7 -> 1Q25 | Y40: =Y7 -> 2Q25 | Z40: =Z7 -> 3Q25
B41: =B8 -> Fiscal Period End Date | C41: =C8 -> 44926 | D41: =D8 -> 45291 | E41: =E8 -> 45657 | G41: =G8 -> 45016 | H41: =H8 -> 45107 | I41: =I8 -> 45199 | J41: =J8 -> 45291 | K41: =K8 -> 45382 | L41: =L8 -> 45473 | M41: =M8 -> 45565 | N41: =N8 -> 45657 | ... Q41: =Q8 -> 45930 | S41: =S8 -> 45291 | T41: =T8 -> 45382 | U41: =U8 -> 45473 | V41: =V8 -> 45565 | W41: =W8 -> 45657 | X41: =X8 -> 45747 | Y41: =Y8 -> 45838 | Z41: =Z8 -> 45930
B43: Current Assets
B44: Cash and cash equivalents | C44: 1423.121 | D44: 1780.4 | E44: 1046.5 | G44: 1578.52 | H44: 1228.62 | I44: 1199.36 | J44: =D44 -> 1780.4 | K44: 1060.39 | L44: 1060.55 | M44: 964.96 | N44: =E44 -> 1046.5 | O44: 911.227 | P44: 925.973 | Q44: 953.317 | S44: =J44 -> 1780.4 | T44: =K44 -> 1060.39 | U44: =L44 -> 1060.55 | V44: =M44 -> 964.96 | W44: =N44 -> 1046.5 | X44: =O44 -> 911.227 | Y44: =P44 -> 925.973 | Z44: =Q44 -> 953.317 | AB44: =SUM(Z44/V44)-1 -> -0.012065785
B45: Marketable Securities | C45: 2516 | D45: 1763.68 | E45: 2329.745 | G45: 2524.9 | H45: 2460.64 | I45: 2414.13 | J45: =D45 -> 1763.68 | K45: 1850.62 | L45: 2020.72 | M45: 2227 | N45: =E45 -> 2329.745 | O45: 2295.66 | P45: 1967 | Q45: 2040.06 | S45: =J45 -> 1763.68 | T45: =K45 -> 1850.62 | U45: =L45 -> 2020.72 | V45: =M45 -> 2227 | W45: =N45 -> 2329.745 | X45: =O45 -> 2295.66 | Y45: =P45 -> 1967 | Z45: =Q45 -> 2040.06 | AB45: =SUM(Z45/V45)-1 -> -0.083942524
B46: Accounts receivable, net | C46: 1183.09 | D46: 1278.176 | E46: 1348.472 | G46: 892.511 | H46: 996.08 | I46: 1116.51 | J46: =D46 -> 1278.176 | K46: 1108.35 | L46: 1141.849 | M46: 1195.7 | N46: =E46 -> 1348.472 | O46: 1157.61 | P46: 1164.87 | Q46: 1248.01 | S46: =J46 -> 1278.176 | T46: =K46 -> 1108.35 | U46: =L46 -> 1141.849 | V46: =M46 -> 1195.7 | W46: =N46 -> 1348.472 | X46: =O46 -> 1157.61 | Y46: =P46 -> 1164.87 | Z46: =Q46 -> 1248.01 | AB46: =SUM(Z46/V46)-1 -> 0.043748432
B47: Prepaid expenses and other current assets | C47: 134.43 | D47: 153.587 | E47: 182 | G47: 146.973 | H47: 154.17 | I47: 144.25 | J47: =D47 -> 153.587 | K47: 167.38 | L47: 198.07 | M47: 200.9 | N47: =E47 -> 182 | O47: 212.53 | P47: 226.25 | Q47: 235.099 | S47: =J47 -> 153.587 | T47: =K47 -> 167.38 | U47: =L47 -> 198.07 | V47: =M47 -> 200.9 | W47: =N47 -> 182 | X47: =O47 -> 212.53 | Y47: =P47 -> 226.25 | Z47: =Q47 -> 235.099 | AB47: =SUM(Z47/V47)-1 -> 0.17022897
B48: Total Current Assets | C48: =SUM(C44:C47) -> 5256.641 | D48: =SUM(D44:D47) -> 4975.843 | E48: =SUM(E44:E47) -> 4906.717 | G48: =SUM(G44:G47) -> 5142.904 | H48: =SUM(H44:H47) -> 4839.51 | I48: =SUM(I44:I47) -> 4874.25 | J48: =SUM(J44:J47) -> 4975.843 | K48: =SUM(K44:K47) -> 4186.74 | L48: =SUM(L44:L47) -> 4421.189 | M48: =SUM(M44:M47) -> 4588.56 | N48: =SUM(N44:N47) -> 4906.717 | ... Q48: =SUM(Q44:Q47) -> 4476.486 | S48: =SUM(S44:S47) -> 4975.843 | T48: =SUM(T44:T47) -> 4186.74 | U48: =SUM(U44:U47) -> 4421.189 | V48: =SUM(V44:V47) -> 4588.56 | W48: =SUM(W44:W47) -> 4906.717 | X48: =SUM(X44:X47) -> 4577.027 | Y48: =SUM(Y44:Y47) -> 4284.093 | Z48: =SUM(Z44:Z47) -> 4476.486 | AB48: =SUM(Z48/V48)-1 -> -0.024424656
B50: Non-Current Assets
B51: Property and equipment, net | C51: 271.77 | D51: 410.326 | E51: 489.09 | G51: 303.02 | H51: 330.01 | I51: 377.32 | J51: =D51 -> 410.326 | K51: 426.363 | L51: 444.485 | M51: 466.39 | N51: =E51 -> 489.09 | O51: 501.353 | P51: 544.226 | Q51: 557.418 | S51: =J51 -> 410.326 | T51: =K51 -> 426.363 | U51: =L51 -> 444.485 | V51: =M51 -> 466.39 | W51: =N51 -> 489.09 | X51: =O51 -> 501.353 | Y51: =P51 -> 544.226 | Z51: =Q51 -> 557.418 | AB51: =SUM(Z51/V51)-1 -> 0.19517571
B52: Long-term operating lease Assets | C52: 370.95 | D52: 516.86 | E52: 530.44 | G52: 355.06 | H52: 348.97 | I52: 344.68 | J52: =D52 -> 516.86 | K52: 511.1 | L52: 521.1 | M52: 516.959 | N52: =E52 -> 530.44 | O52: 528.27 | P52: 534.084 | Q52: 520.187 | S52: =J52 -> 516.86 | T52: =K52 -> 511.1 | U52: =L52 -> 521.1 | V52: =M52 -> 516.959 | W52: =N52 -> 530.44 | X52: =O52 -> 528.27 | Y52: =P52 -> 534.084 | Z52: =Q52 -> 520.187 | AB52: =SUM(Z52/V52)-1 -> 0.0062442089
B53: Intangible Assets | C53: 204.48 | D53: 146.3 | E53: 86.363 | G53: 186.72 | H53: 202.671 | I53: 183.86 | J53: =D53 -> 146.3 | K53: 127.658 | L53: 112.808 | M53: 98.92 | N53: =E53 -> 86.363 | O53: 74.822 | P53: 88.791 | Q53: 77.257 | S53: =J53 -> 146.3 | T53: =K53 -> 127.658 | U53: =L53 -> 112.808 | V53: =M53 -> 98.92 | W53: =N53 -> 86.363 | X53: =O53 -> 74.822 | Y53: =P53 -> 88.791 | Z53: =Q53 -> 77.257 | AB53: =SUM(Z53/V53)-1 -> -0.21899515
B54: Goodwill | C54: 1646.12 | D54: 1691.827 | E54: 1689.78 | G54: 1649.09 | H54: 1692.06 | I54: 1691.54 | J54: =D54 -> 1691.827 | K54: 1691.52 | L54: 1691.31 | M54: 1693.94 | N54: =E54 -> 1689.78 | O54: 1691.87 | P54: 1720.83 | Q54: 1720.586 | S54: =J54 -> 1691.827 | T54: =K54 -> 1691.52 | U54: =L54 -> 1691.31 | V54: =M54 -> 1693.94 | W54: =N54 -> 1689.78 | X54: =O54 -> 1691.87 | Y54: =P54 -> 1720.83 | Z54: =Q54 -> 1720.586 | AB54: =SUM(Z54/V54)-1 -> 0.015730191
B55: Other Non-Current Assets | C55: 279.56 | D55: 226.597 | E55: 233.91 | G55: 251.569 | H55: 252.973 | I55: 251.23 | J55: =D55 -> 226.597 | K55: 223.982 | L55: 229.131 | M55: 226.463 | N55: =E55 -> 233.91 | O55: 215.848 | P55: 226.88 | Q55: 226.015 | S55: =J55 -> 226.597 | T55: =K55 -> 223.982 | U55: =L55 -> 229.131 | V55: =M55 -> 226.463 | W55: =N55 -> 233.91 | X55: =O55 -> 215.848 | Y55: =P55 -> 226.88 | Z55: =Q55 -> 226.015 | AB55: =SUM(Z55/V55)-1 -> -0.0019782481
B56: Total Assets | C56: =SUM(C51:C55)+C48 -> 8029.521 | D56: =SUM(D51:D55)+D48 -> 7967.753 | E56: =SUM(E51:E55)+E48 -> 7936.3 | G56: =SUM(G51:G55)+G48 -> 7888.363 | H56: =SUM(H51:H55)+H48 -> 7666.194 | I56: =SUM(I51:I55)+I48 -> 7722.88 | J56: =SUM(J51:J55)+J48 -> 7967.753 | K56: =SUM(K51:K55)+K48 -> 7167.363 | L56: =SUM(L51:L55)+L48 -> 7420.023 | M56: =SUM(M51:M55)+M48 -> 7591.232 | N56: =SUM(N51:N55)+N48 -> 7936.3 | ... Q56: =SUM(Q51:Q55)+Q48 -> 7577.949 | S56: =SUM(S51:S55)+S48 -> 7967.753 | T56: =SUM(T51:T55)+T48 -> 7167.363 | U56: =SUM(U51:U55)+U48 -> 7420.023 | V56: =SUM(V51:V55)+V48 -> 7591.232 | W56: =SUM(W51:W55)+W48 -> 7936.3 | X56: =SUM(X51:X55)+X48 -> 7589.19 | Y56: =SUM(Y51:Y55)+Y48 -> 7398.904 | Z56: =SUM(Z51:Z55)+Z48 -> 7577.949 | AB56: =SUM(Z56/V56)-1 -> -0.0017497819
B58: Current Liabilities
B59: Accounts payable | C59: 181.774 | D59: 278.961 | E59: 173.197 | G59: 141.8 | H59: 163.604 | I59: 128.546 | J59: =D59 -> 278.961 | K59: 246.217 | L59: 179.586 | M59: 157.471 | N59: =E59 -> 173.197 | O59: 209.445 | P59: 116.85 | Q59: 153.683 | S59: =J59 -> 278.961 | T59: =K59 -> 246.217 | U59: =L59 -> 179.586 | V59: =M59 -> 157.471 | W59: =N59 -> 173.197 | X59: =O59 -> 209.445 | Y59: =P59 -> 116.85 | Z59: =Q59 -> 153.683 | AB59: =SUM(Z59/V59)-1 -> -0.024055223
B60: Current Operating Lease Liabilities | C60: 46.48 | D60: 49.321 | E60: 24.885 | G60: 50.787 | H60: 57.893 | I60: 62.11 | J60: =D60 -> 49.321 | K60: 36.649 | L60: 21.27 | M60: 21.311 | N60: =E60 -> 24.885 | O60: 22.501 | P60: 32.156 | Q60: 43.468 | S60: =J60 -> 49.321 | T60: =K60 -> 36.649 | U60: =L60 -> 21.27 | V60: =M60 -> 21.311 | W60: =N60 -> 24.885 | X60: =O60 -> 22.501 | Y60: =P60 -> 32.156 | Z60: =Q60 -> 43.468 | AB60: =SUM(Z60/V60)-1 -> 1.0396978
B61: Accrued liabilities | C61: 987.34 | D61: 805.836 | E61: 1009.254 | G61: 898.897 | H61: 716.16 | I61: 818.915 | J61: =D61 -> 805.836 | K61: 829.579 | L61: 875.119 | M61: 921.393 | N61: =E61 -> 1009.254 | O61: 796.258 | P61: 954.01 | Q61: 976.547 | S61: =J61 -> 805.836 | T61: =K61 -> 829.579 | U61: =L61 -> 875.119 | V61: =M61 -> 921.393 | W61: =N61 -> 1009.254 | X61: =O61 -> 796.258 | Y61: =P61 -> 954.01 | Z61: =Q61 -> 976.547 | AB61: =SUM(Z61/V61)-1 -> 0.059859365
B62: Current portion of long-term debt, net | C62: 0 | D62: 0 | E62: 36.212 | G62: 0 | H62: 0 | I62: 0 | J62: =D62 -> 0 | K62: 0 | L62: 36.17 | M62: 36.191 | N62: =E62 -> 36.212 | O62: 36.233 | P62: 0 | Q62: 46.951 | S62: =J62 -> 0 | T62: =K62 -> 0 | U62: =L62 -> 36.17 | V62: =M62 -> 36.191 | W62: =N62 -> 36.212 | X62: =O62 -> 36.233 | Y62: =P62 -> 0 | Z62: =Q62 -> 46.951 | AB62: =SUM(Z62/V62)-1 -> 0.29731149
B63: Total Current Liabilities | C63: =SUM(C59:C62) -> 1215.594 | D63: =SUM(D59:D62) -> 1134.118 | E63: =SUM(E59:E62) -> 1243.548 | G63: =SUM(G59:G62) -> 1091.484 | H63: =SUM(H59:H62) -> 937.657 | I63: =SUM(I59:I62) -> 1009.571 | J63: =SUM(J59:J62) -> 1134.118 | K63: =SUM(K59:K62) -> 1112.445 | L63: =SUM(L59:L62) -> 1112.145 | M63: =SUM(M59:M62) -> 1136.366 | N63: =SUM(N59:N62) -> 1243.548 | ... Q63: =SUM(Q59:Q62) -> 1220.649 | S63: =SUM(S59:S62) -> 1134.118 | T63: =SUM(T59:T62) -> 1112.445 | U63: =SUM(U59:U62) -> 1112.145 | V63: =SUM(V59:V62) -> 1136.366 | W63: =SUM(W59:W62) -> 1243.548 | X63: =SUM(X59:X62) -> 1064.437 | Y63: =SUM(Y59:Y62) -> 1103.016 | Z63: =SUM(Z59:Z62) -> 1220.649 | AB63: =SUM(Z63/V63)-1 -> 0.074168886
B65: Non-Current Liabilities
B66: Long-term debt, net of current portion | C66: 3742.52 | D66: 3749.4 | E66: 3607.7 | G66: 3744.23 | H66: 3745.956 | I66: 3747.677 | J66: 3749.4 | K66: 3301.466 | L66: 3602.56 | M66: 3605.137 | N66: 3607.7 | O66: 3576.692 | P66: 3575.97 | Q66: 3490.938 | S66: =J66 -> 3749.4 | T66: =K66 -> 3301.466 | U66: =L66 -> 3602.56 | V66: =M66 -> 3605.137 | W66: =N66 -> 3607.7 | X66: =O66 -> 3576.692 | Y66: =P66 -> 3575.97 | Z66: =Q66 -> 3490.938 | AB66: =SUM(Z66/V66)-1 -> -0.031676743
B67: Long-term operating lease liabilities | C67: 386.27 | D67: 546.279 | E67: 575.08 | G67: 368.526 | H67: 356.929 | I67: 346.508 | J67: 546.279 | K67: 553.741 | L67: 579.89 | M67: 577.912 | N67: 575.08 | O67: 575.427 | P67: 583.86 | Q67: 572.24 | S67: =J67 -> 546.279 | T67: =K67 -> 553.741 | U67: =L67 -> 579.89 | V67: =M67 -> 577.912 | W67: =N67 -> 575.08 | X67: =O67 -> 575.427 | Y67: =P67 -> 583.86 | Z67: =Q67 -> 572.24 | AB67: =SUM(Z67/V67)-1 -> -0.0098146431
B68: Other long-term liabilities | C68: 104.45 | D68: 123.849 | E68: 59.24 | G68: 105.703 | H68: 120.714 | I68: 126.127 | J68: 123.849 | K68: 68.401 | L68: 58.7 | M68: 61.927 | N68: 59.24 | O68: 61.309 | P68: 66.77 | Q68: 66.773 | S68: =J68 -> 123.849 | T68: =K68 -> 68.401 | U68: =L68 -> 58.7 | V68: =M68 -> 61.927 | W68: =N68 -> 59.24 | X68: =O68 -> 61.309 | Y68: =P68 -> 66.77 | Z68: =Q68 -> 66.773 | AB68: =SUM(Z68/V68)-1 -> 0.078253427
B69: Total Liabilities | C69: =SUM(C66:C68)+C63 -> 5448.834 | D69: =SUM(D66:D68)+D63 -> 5553.646 | E69: =SUM(E66:E68)+E63 -> 5485.568 | G69: =SUM(G66:G68)+G63 -> 5309.943 | H69: =SUM(H66:H68)+H63 -> 5161.256 | I69: =SUM(I66:I68)+I63 -> 5229.883 | J69: =SUM(J66:J68)+J63 -> 5553.646 | K69: =SUM(K66:K68)+K63 -> 5036.053 | L69: =SUM(L66:L68)+L63 -> 5353.295 | M69: =SUM(M66:M68)+M63 -> 5381.342 | N69: =SUM(N66:N68)+N63 -> 5485.568 | ... Q69: =SUM(Q66:Q68)+Q63 -> 5350.6 | S69: =SUM(S66:S68)+S63 -> 5553.646 | T69: =SUM(T66:T68)+T63 -> 5036.053 | U69: =SUM(U66:U68)+U63 -> 5353.295 | V69: =SUM(V66:V68)+V63 -> 5381.342 | W69: =SUM(W66:W68)+W63 -> 5485.568 | X69: =SUM(X66:X68)+X63 -> 5277.865 | Y69: =SUM(Y66:Y68)+Y63 -> 5329.616 | Z69: =SUM(Z66:Z68)+Z63 -> 5350.6 | AB69: =SUM(Z69/V69)-1 -> -0.0057127014
B71: Class A non-voting common stock | C71: 0.013 | D71: 0.014 | E71: 0.014 | G71: 0.013 | H71: 0.014 | I71: 0.014 | J71: =D71 -> 0.014 | K71: 0.014 | L71: 0.014 | M71: 0.014 | N71: =E71 -> 0.014 | O71: 0.014 | P71: 0.014 | Q71: 0.015 | S71: =J71 -> 0.014 | T71: =K71 -> 0.014 | U71: =L71 -> 0.014 | V71: =M71 -> 0.014 | W71: =N71 -> 0.014 | X71: =O71 -> 0.014 | Y71: =P71 -> 0.014 | Z71: =Q71 -> 0.015 | AB71: =SUM(Z71/V71)-1 -> 0.071428571
B72: Class B voting common stock | C72: 0 | D72: 0 | E72: 0 | G72: 0 | H72: 0 | I72: 0 | J72: =D72 -> 0 | K72: 0 | L72: 0 | M72: 0 | N72: =E72 -> 0 | O72: 0 | P72: 0 | Q72: 0 | S72: =J72 -> 0 | T72: =K72 -> 0 | U72: =L72 -> 0 | V72: =M72 -> 0 | W72: =N72 -> 0 | X72: =O72 -> 0 | Y72: =P72 -> 0 | Z72: =Q72 -> 0 | AB72: =SUM(Z72/V72)-1 -> #DIV/0!
B73: Class C voting common stock | C73: 0.002 | D73: 0.002 | E73: 0.002 | G73: 0.002 | H73: 0.002 | I73: 0.002 | J73: =D73 -> 0.002 | K73: 0.002 | L73: 0.002 | M73: 0.002 | N73: =E73 -> 0.002 | O73: 0.002 | P73: 0.002 | Q73: 0.002 | S73: =J73 -> 0.002 | T73: =K73 -> 0.002 | U73: =L73 -> 0.002 | V73: =M73 -> 0.002 | W73: =N73 -> 0.002 | X73: =O73 -> 0.002 | Y73: =P73 -> 0.002 | Z73: =Q73 -> 0.002 | AB73: =SUM(Z73/V73)-1 -> 0
B74: Treasury stock | C74: -500.514 | D74: -479.903 | E74: -460.62 | G74: -496.906 | H74: -492.5 | I74: -487.982 | J74: =D74 -> -479.903 | K74: -475.939 | L74: -470.999 | M74: -465.502 | N74: =E74 -> -460.62 | O74: -448.509 | P74: -444.573 | Q74: -440.476 | S74: =J74 -> -479.903 | T74: =K74 -> -475.939 | U74: =L74 -> -470.999 | V74: =M74 -> -465.502 | W74: =N74 -> -460.62 | X74: =O74 -> -448.509 | Y74: =P74 -> -444.573 | Z74: =Q74 -> -440.476 | AB74: =SUM(Z74/V74)-1 -> -0.053761316
B75: Additional paid-in capital | C75: 13309.828 | D75: 14613.404 | E75: 15644.132 | G75: 13620.326 | H75: 13934.244 | I75: 14287.664 | J75: =D75 -> 14613.404 | K75: 14873.261 | L75: 15126.248 | M75: 15391.284 | N75: =E75 -> 15644.132 | O75: 15879.359 | P75: 16127.309 | Q75: 16383.575 | S75: =J75 -> 14613.404 | T75: =K75 -> 14873.261 | U75: =L75 -> 15126.248 | V75: =M75 -> 15391.284 | W75: =N75 -> 15644.132 | X75: =O75 -> 15879.359 | Y75: =P75 -> 16127.309 | Z75: =Q75 -> 16383.575 | AB75: =SUM(Z75/V75)-1 -> 0.064470969
B76: Accumulated deficit | C76: -10214.657 | D76: -11726.536 | E76: -12735.461 | G76: -10543.331 | H76: -10920.639 | I76: -11288.895 | J76: =D76 -> -11726.536 | K76: -12266.74 | L76: -12591.315 | M76: -12744.562 | N76: =E76 -> -12735.461 | O76: -13132.148 | P76: -13638.191 | Q76: -13741.732 | S76: =J76 -> -11726.536 | T76: =K76 -> -12266.74 | U76: =L76 -> -12591.315 | V76: =M76 -> -12744.562 | W76: =N76 -> -12735.461 | X76: =O76 -> -13132.148 | Y76: =P76 -> -13638.191 | Z76: =Q76 -> -13741.732 | AB76: =SUM(Z76/V76)-1 -> 0.078242783
B77: Accumulated OCI | C77: -13.974 | D77: 7.131 | E77: 2.694 | G77: -1.664 | H77: -16.161 | I77: -17.782 | J77: =D77 -> 7.131 | K77: 0.75 | L77: 2.772 | M77: 28.839 | N77: =E77 -> 2.694 | O77: 12.617 | P77: 24.796 | Q77: 25.966 | S77: =J77 -> 7.131 | T77: =K77 -> 0.75 | U77: =L77 -> 2.772 | V77: =M77 -> 28.839 | W77: =N77 -> 2.694 | X77: =O77 -> 12.617 | Y77: =P77 -> 24.796 | Z77: =Q77 -> 25.966 | AB77: =SUM(Z77/V77)-1 -> -0.09962204
B78: Total stockholders' equity | C78: =SUM(C71:C77) -> 2580.698 | D78: =SUM(D71:D77) -> 2414.112 | E78: =SUM(E71:E77) -> 2450.761 | G78: =SUM(G71:G77) -> 2578.44 | H78: =SUM(H71:H77) -> 2504.96 | I78: =SUM(I71:I77) -> 2493.021 | J78: =SUM(J71:J77) -> 2414.112 | K78: =SUM(K71:K77) -> 2131.348 | L78: =SUM(L71:L77) -> 2066.722 | M78: =SUM(M71:M77) -> 2210.075 | N78: =SUM(N71:N77) -> 2450.761 | ... Q78: =SUM(Q71:Q77) -> 2227.35 | S78: =SUM(S71:S77) -> 2414.112 | T78: =SUM(T71:T77) -> 2131.348 | U78: =SUM(U71:U77) -> 2066.722 | V78: =SUM(V71:V77) -> 2210.075 | W78: =SUM(W71:W77) -> 2450.761 | X78: =SUM(X71:X77) -> 2311.335 | Y78: =SUM(Y71:Y77) -> 2069.357 | Z78: =SUM(Z71:Z77) -> 2227.35 | AB78: =SUM(Z78/V78)-1 -> 0.0078164768
B79: Total liabilities and stockholders' equity | C79: =SUM(C78+C69) -> 8029.532 | D79: =SUM(D78+D69) -> 7967.758 | E79: =SUM(E78+E69) -> 7936.329 | G79: =SUM(G78+G69) -> 7888.383 | H79: =SUM(H78+H69) -> 7666.216 | I79: =SUM(I78+I69) -> 7722.904 | J79: =SUM(J78+J69) -> 7967.758 | K79: =SUM(K78+K69) -> 7167.401 | L79: =SUM(L78+L69) -> 7420.017 | M79: =SUM(M78+M69) -> 7591.417 | N79: =SUM(N78+N69) -> 7936.329 | ... Q79: =SUM(Q78+Q69) -> 7577.95 | S79: =SUM(S78+S69) -> 7967.758 | T79: =SUM(T78+T69) -> 7167.401 | U79: =SUM(U78+U69) -> 7420.017 | V79: =SUM(V78+V69) -> 7591.417 | W79: =SUM(W78+W69) -> 7936.329 | X79: =SUM(X78+X69) -> 7589.2 | Y79: =SUM(Y78+Y69) -> 7398.973 | Z79: =SUM(Z78+Z69) -> 7577.95 | AB79: =SUM(Z79/V79)-1 -> -0.0017739771
B81: Balance Check | C81: =ROUND(C79-C56,0.1) -> 0 | D81: =ROUND(D79-D56,0.1) -> 0 | E81: =ROUND(E79-E56,0.1) -> 0 | G81: =ROUND(G79-G56,0.1) -> 0 | H81: =ROUND(H79-H56,0.1) -> 0 | I81: =ROUND(I79-I56,0.1) -> 0 | J81: =ROUND(J79-J56,0.1) -> 0 | K81: =ROUND(K79-K56,0.1) -> 0 | L81: =ROUND(L79-L56,0.1) -> 0 | M81: =ROUND(M79-M56,0.1) -> 0 | N81: =ROUND(N79-N56,0.1) -> 0 | ... Q81: =ROUND(Q79-Q56,0.1) -> 0 | S81: =ROUND(S79-S56,0.1) -> 0 | T81: =ROUND(T79-T56,0.1) -> 0 | U81: =ROUND(U79-U56,0.1) -> 0 | V81: =ROUND(V79-V56,0.1) -> 0 | W81: =ROUND(W79-W56,0.1) -> 0 | X81: =ROUND(X79-X56,0.1) -> 0 | Y81: =ROUND(Y79-Y56,0.1) -> 0 | Z81: =ROUND(Z79-Z56,0.1) -> 0
A84: X | B84: Cash-Flows Statement | C84: FYE | M84: Quarterly | V84: LTM | AB84: Variance
B85: =B7 -> Fiscal Period | C85: =C7 -> 2022 | D85: =D7 -> 2023 | E85: =E7 -> 2024 | G85: =G7 -> 1Q23 | H85: =H7 -> 2Q23 | I85: =I7 -> 3Q23 | J85: =J7 -> 4Q23 | K85: =K7 -> 1Q24 | L85: =L7 -> 2Q24 | M85: =M7 -> 3Q24 | N85: =N7 -> 4Q24 | ... Q85: =Q7 -> 3Q25 | S85: =S7 -> 4Q23 | T85: =T7 -> 1Q24 | U85: =U7 -> 2Q24 | V85: =V7 -> 3Q24 | W85: =W7 -> 4Q24 | X85: =X7 -> 1Q25 | Y85: =Y7 -> 2Q25 | Z85: =Z7 -> 3Q25
B86: =B8 -> Fiscal Period End Date | C86: =C8 -> 44926 | D86: =D8 -> 45291 | E86: =E8 -> 45657 | G86: =G8 -> 45016 | H86: =H8 -> 45107 | I86: =I8 -> 45199 | J86: =J8 -> 45291 | K86: =K8 -> 45382 | L86: =L8 -> 45473 | M86: =M8 -> 45565 | N86: =N8 -> 45657 | ... Q86: =Q8 -> 45930 | S86: =S8 -> 45291 | T86: =T8 -> 45382 | U86: =U8 -> 45473 | V86: =V8 -> 45565 | W86: =W8 -> 45657 | X86: =X8 -> 45747 | Y86: =Y8 -> 45838 | Z86: =Z8 -> 45930
B88: Cash-Flows From Operating Activities
B89: Net income (loss) | C89: =C30 -> -1429.791 | D89: =D30 -> -1322.444 | E89: =E30 -> -697.732 | G89: =G30 -> -328.674 | H89: =H30 -> -377.308 | I89: =I30 -> -368.246 | J89: =J30 -> -248.216 | K89: =K30 -> -305.09 | L89: =L30 -> -248.62 | M89: =M30 -> -153.247 | N89: =N30 -> 9.225 | ... Q89: =Q30 -> -103.541 | S89: =S30 -> -1322.444 | T89: =T30 -> -1298.86 | U89: =U30 -> -1170.172 | V89: =V30 -> -955.173 | W89: =W30 -> -697.732 | X89: =X30 -> -532.229 | Y89: =Y30 -> -546.179 | Z89: =Z30 -> -496.473 | AB89: =SUM(Z89/V89)-1 -> -0.48022714
B91: Adjustments to reconcile net income:
B92: Depreciation and amortization | C92: 202.173 | D92: 168.441 | E92: 158.074 | G92: 35.22 | H92: 39.688 | I92: 41.209 | J92: =SUM(D92-SUM(G92:I92)) -> 52.324 | K92: 41.713 | L92: 37.93 | M92: 38.85 | N92: =SUM(E92-SUM(K92:M92)) -> 39.581 | O92: 37.715 | P92: 40.023 | Q92: 42.514 | S92: =SUM(G92:J92) -> 168.441 | T92: =SUM(H92:K92) -> 174.934 | U92: =SUM(I92:L92) -> 173.176 | V92: =SUM(J92:M92) -> 170.817 | W92: =SUM(K92:N92) -> 158.074 | X92: =SUM(L92:O92) -> 154.076 | Y92: =SUM(M92:P92) -> 156.169 | Z92: =SUM(N92:Q92) -> 159.833 | AB92: =SUM(Z92/V92)-1 -> -0.064302733
B93: Stock-based compensation | C93: 1387.787 | D93: 1324.004 | E93: 1041.023 | G93: 314.931 | H93: 317.943 | I93: 357.933 | J93: =SUM(D93-SUM(G93:I93)) -> 333.197 | K93: 263.752 | L93: 259.311 | M93: 260.229 | N93: =SUM(E93-SUM(K93:M93)) -> 257.731 | O93: 247.338 | P93: 251.886 | Q93: 260.363 | S93: =SUM(G93:J93) -> 1324.004 | T93: =SUM(H93:K93) -> 1272.825 | U93: =SUM(I93:L93) -> 1214.193 | V93: =SUM(J93:M93) -> 1116.489 | W93: =SUM(K93:N93) -> 1041.023 | X93: =SUM(L93:O93) -> 1024.609 | Y93: =SUM(M93:P93) -> 1017.184 | Z93: =SUM(N93:Q93) -> 1017.318 | AB93: =SUM(Z93/V93)-1 -> -0.088823983
B94: Amortization of debt issuance costs | C94: 6.865 | D94: 7.361 | E94: 9.388 | G94: 1.836 | H94: 1.839 | I94: 1.842 | J94: =SUM(D94-SUM(G94:I94)) -> 1.844 | K94: 1.742 | L94: 2.208 | M94: 2.717 | N94: =SUM(E94-SUM(K94:M94)) -> 2.721 | O94: 7.642 | P94: -0.55 | Q94: 0.686 | S94: =SUM(G94:J94) -> 7.361 | T94: =SUM(H94:K94) -> 7.267 | U94: =SUM(I94:L94) -> 7.636 | V94: =SUM(J94:M94) -> 8.511 | W94: =SUM(K94:N94) -> 9.388 | X94: =SUM(L94:O94) -> 15.288 | Y94: =SUM(M94:P94) -> 12.53 | Z94: =SUM(N94:Q94) -> 10.499 | AB94: =SUM(Z94/V94)-1 -> 0.23358007
B95: Losses (gains) on debt and equity securities, net | C95: 36.838 | D95: 33.027 | E95: 8.46 | G95: -10.833 | H95: -4.434 | I95: 21.155 | J95: =SUM(D95-SUM(G95:I95)) -> 27.139 | K95: 8.968 | L95: 2.662 | M95: 0.536 | N95: =SUM(E95-SUM(K95:M95)) -> -3.706 | O95: 15.8 | P95: -1.208 | Q95: 1.182 | S95: =SUM(G95:J95) -> 33.027 | T95: =SUM(H95:K95) -> 52.828 | U95: =SUM(I95:L95) -> 59.924 | V95: =SUM(J95:M95) -> 39.305 | W95: =SUM(K95:N95) -> 8.46 | X95: =SUM(L95:O95) -> 15.292 | Y95: =SUM(M95:P95) -> 11.422 | Z95: =SUM(N95:Q95) -> 12.068 | AB95: =SUM(Z95/V95)-1 -> -0.69296527
B96: Gain on extinguishment of debt | C96: 0 | D96: 0 | E96: 0 | G96: 0 | H96: 0 | I96: 0 | J96: =SUM(D96-SUM(G96:I96)) -> 0 | K96: 0 | L96: 0 | M96: 0 | N96: =SUM(E96-SUM(K96:M96)) -> 0 | O96: -66.939 | P96: 0 | Q96: -29.795 | S96: =SUM(G96:J96) -> 0 | T96: =SUM(H96:K96) -> 0 | U96: =SUM(I96:L96) -> 0 | V96: =SUM(J96:M96) -> 0 | W96: =SUM(K96:N96) -> 0 | X96: =SUM(L96:O96) -> -66.939 | Y96: =SUM(M96:P96) -> -66.939 | Z96: =SUM(N96:Q96) -> -96.734 | AB96: =SUM(Z96/V96)-1 -> #DIV/0!
B97: Other | C97: 15.596 | D97: -26.958 | E97: -14.153 | G97: -10.396 | H97: -16.307 | I97: -4.395 | J97: =SUM(D97-SUM(G97:I97)) -> 4.14 | K97: -16.612 | L97: 10.583 | M97: 2.2 | N97: =SUM(E97-SUM(K97:M97)) -> -10.324 | O97: -0.805 | P97: 12.362 | Q97: 2.985 | S97: =SUM(G97:J97) -> -26.958 | T97: =SUM(H97:K97) -> -33.174 | U97: =SUM(I97:L97) -> -6.284 | V97: =SUM(J97:M97) -> 0.311 | W97: =SUM(K97:N97) -> -14.153 | X97: =SUM(L97:O97) -> 1.654 | Y97: =SUM(M97:P97) -> 3.433 | Z97: =SUM(N97:Q97) -> 4.218 | AB97: =SUM(Z97/V97)-1 -> 12.562701
G98: 0
B99: Changes in assets and liabilities:
B100: Accounts receivable, net of allowance | C100: -119.78 | D100: -98.127 | E100: -94.005 | G100: 288.373 | H100: -103.629 | I100: -128.972 | J100: =SUM(D100-SUM(G100:I100)) -> -153.899 | K100: 162.207 | L100: -36.916 | M100: -51.941 | N100: =SUM(E100-SUM(K100:M100)) -> -167.355 | O100: 194.216 | P100: -3.088 | Q100: -89.096 | S100: =SUM(G100:J100) -> -98.127 | T100: =SUM(H100:K100) -> -224.293 | U100: =SUM(I100:L100) -> -157.58 | V100: =SUM(J100:M100) -> -80.549 | W100: =SUM(K100:N100) -> -94.005 | X100: =SUM(L100:O100) -> -61.996 | Y100: =SUM(M100:P100) -> -28.168 | Z100: =SUM(N100:Q100) -> -65.323 | AB100: =SUM(Z100/V100)-1 -> -0.1890278
B101: Prepaid expenses and other current assets | C101: -40.917 | D101: -9.92 | E101: -36.544 | G101: -13.204 | H101: -1.098 | I101: -0.837 | J101: =SUM(D101-SUM(G101:I101)) -> 5.219 | K101: -13.629 | L101: -34.526 | M101: 11.914 | N101: =SUM(E101-SUM(K101:M101)) -> -0.303 | O101: -22.828 | P101: -7.058 | Q101: -16.313 | S101: =SUM(G101:J101) -> -9.92 | T101: =SUM(H101:K101) -> -10.345 | U101: =SUM(I101:L101) -> -43.773 | V101: =SUM(J101:M101) -> -31.022 | W101: =SUM(K101:N101) -> -36.544 | X101: =SUM(L101:O101) -> -45.743 | Y101: =SUM(M101:P101) -> -18.275 | Z101: =SUM(N101:Q101) -> -46.502 | AB101: =SUM(Z101/V101)-1 -> 0.49900071
B102: Operating lease right-of-use assets | C102: 71.441 | D102: 70.674 | E102: 54.127 | G102: 17.658 | H102: 17.817 | I102: 17.904 | J102: =SUM(D102-SUM(G102:I102)) -> 17.295 | K102: 13.575 | L102: 14.929 | M102: 12.731 | N102: =SUM(E102-SUM(K102:M102)) -> 12.892 | O102: 14.123 | P102: 13.797 | Q102: 14.909 | S102: =SUM(G102:J102) -> 70.674 | T102: =SUM(H102:K102) -> 66.591 | U102: =SUM(I102:L102) -> 63.703 | V102: =SUM(J102:M102) -> 58.53 | W102: =SUM(K102:N102) -> 54.127 | X102: =SUM(L102:O102) -> 54.675 | Y102: =SUM(M102:P102) -> 53.543 | Z102: =SUM(N102:Q102) -> 55.721 | AB102: =SUM(Z102/V102)-1 -> -0.047992482
B103: Other assets | C103: -0.504 | D103: 2.238 | E103: -9.952 | G103: 0.85 | H103: -1.275 | I103: -2.767 | J103: =SUM(D103-SUM(G103:I103)) -> 5.43 | K103: -5.142 | L103: -0.955 | M103: 3.09 | N103: =SUM(E103-SUM(K103:M103)) -> -6.945 | O103: 9.01 | P103: -2.117 | Q103: 0.161 | S103: =SUM(G103:J103) -> 2.238 | T103: =SUM(H103:K103) -> -3.754 | U103: =SUM(I103:L103) -> -3.434 | V103: =SUM(J103:M103) -> 2.423 | W103: =SUM(K103:N103) -> -9.952 | X103: =SUM(L103:O103) -> 4.2 | Y103: =SUM(M103:P103) -> 3.038 | Z103: =SUM(N103:Q103) -> 0.109 | AB103: =SUM(Z103/V103)-1 -> -0.95501444
B104: Accounts payable | C104: 46.492 | D104: 94.988 | E104: -100.728 | G104: -36.972 | H104: 8.426 | I104: -16.951 | J104: =SUM(D104-SUM(G104:I104)) -> 140.485 | K104: -34.089 | L104: -61.556 | M104: -16.642 | N104: =SUM(E104-SUM(K104:M104)) -> 11.559 | O104: 34.26 | P104: -94.203 | Q104: 38.125 | S104: =SUM(G104:J104) -> 94.988 | T104: =SUM(H104:K104) -> 97.871 | U104: =SUM(I104:L104) -> 27.889 | V104: =SUM(J104:M104) -> 28.198 | W104: =SUM(K104:N104) -> -100.728 | X104: =SUM(L104:O104) -> -32.379 | Y104: =SUM(M104:P104) -> -65.026 | Z104: =SUM(N104:Q104) -> -10.259 | AB104: =SUM(Z104/V104)-1 -> -1.3638201
B105: Accrued expenses and other current liabilities | C105: 71.706 | D105: 62.13 | E105: 150.391 | G105: -90.191 | H105: 52.981 | I105: 105.907 | J105: =SUM(D105-SUM(G105:I105)) -> -6.567 | K105: -18.381 | L105: 45.821 | M105: 19.331 | N105: =SUM(E105-SUM(K105:M105)) -> 103.62 | O105: -162.568 | P105: 147.695 | Q105: 23.926 | S105: =SUM(G105:J105) -> 62.13 | T105: =SUM(H105:K105) -> 133.94 | U105: =SUM(I105:L105) -> 126.78 | V105: =SUM(J105:M105) -> 40.204 | W105: =SUM(K105:N105) -> 150.391 | X105: =SUM(L105:O105) -> 6.204 | Y105: =SUM(M105:P105) -> 108.078 | Z105: =SUM(N105:Q105) -> 112.673 | AB105: =SUM(Z105/V105)-1 -> 1.8025321
B106: Operating lease liabilities | C106: -68.886 | D106: -68.007 | E106: -62.663 | G106: -18.55 | H106: -17.792 | I106: -16.181 | J106: =SUM(D106-SUM(G106:I106)) -> -15.484 | K106: -13.93 | L106: -13.94 | M106: -16.384 | N106: =SUM(E106-SUM(K106:M106)) -> -18.409 | O106: -16.993 | P106: -8.492 | Q106: 1.325 | S106: =SUM(G106:J106) -> -68.007 | T106: =SUM(H106:K106) -> -63.387 | U106: =SUM(I106:L106) -> -59.535 | V106: =SUM(J106:M106) -> -59.738 | W106: =SUM(K106:N106) -> -62.663 | X106: =SUM(L106:O106) -> -65.726 | Y106: =SUM(M106:P106) -> -60.278 | Z106: =SUM(N106:Q106) -> -42.569 | AB106: =SUM(Z106/V106)-1 -> -0.287405
B107: Other liabilities | C107: 5.456 | D107: 9.155 | E107: 7.918 | G107: 1.054 | H107: 1.213 | I107: 5.19 | J107: =SUM(D107-SUM(G107:I107)) -> 1.698 | K107: 3.268 | L107: 1.692 | M107: 2.488 | N107: =SUM(E107-SUM(K107:M107)) -> 0.47 | O107: 1.226 | P107: 2.017 | Q107: -0.943 | S107: =SUM(G107:J107) -> 9.155 | T107: =SUM(H107:K107) -> 11.369 | U107: =SUM(I107:L107) -> 11.848 | V107: =SUM(J107:M107) -> 9.146 | W107: =SUM(K107:N107) -> 7.918 | X107: =SUM(L107:O107) -> 5.876 | Y107: =SUM(M107:P107) -> 6.201 | Z107: =SUM(N107:Q107) -> 2.77 | AB107: =SUM(Z107/V107)-1 -> -0.69713536
B108: Net cash used in operating activities | C108: =SUM(C89:C107) -> 184.476 | D108: =SUM(D89:D107) -> 246.562 | E108: =SUM(E89:E107) -> 413.604 | G108: =SUM(G89:G107) -> 151.102 | H108: =SUM(H89:H107) -> -81.936 | I108: =SUM(I89:I107) -> 12.791 | J108: =SUM(J89:J107) -> 164.605 | K108: =SUM(K89:K107) -> 88.352 | L108: =SUM(L89:L107) -> -21.377 | M108: =SUM(M89:M107) -> 115.872 | N108: =SUM(N89:N107) -> 230.757 | ... Q108: =SUM(Q89:Q107) -> 146.488 | S108: =SUM(S89:S107) -> 246.562 | T108: =SUM(T89:T107) -> 183.812 | U108: =SUM(U89:U107) -> 244.371 | V108: =SUM(V89:V107) -> 347.452 | W108: =SUM(W89:W107) -> 413.604 | X108: =SUM(X89:X107) -> 476.862 | Y108: =SUM(Y89:Y107) -> 586.733 | Z108: =SUM(Z89:Z107) -> 617.349 | AB108: =SUM(Z108/V108)-1 -> 0.77678931
B110: Cash flows from investing activities:
B111: Purchases of property and equipment | C111: -129.306 | D111: -211.727 | E111: -194.826 | G111: -47.63 | H111: -36.943 | I111: -73.435 | J111: =SUM(D111-SUM(G111:I111)) -> -53.719 | K111: -50.448 | L111: -52.062 | M111: -44.041 | N111: =SUM(E111-SUM(K111:M111)) -> -48.275 | O111: -37.214 | P111: -64.701 | Q111: -53.044 | S111: =SUM(G111:J111) -> -211.727 | T111: =SUM(H111:K111) -> -214.545 | U111: =SUM(I111:L111) -> -229.664 | V111: =SUM(J111:M111) -> -200.27 | W111: =SUM(K111:N111) -> -194.826 | X111: =SUM(L111:O111) -> -181.592 | Y111: =SUM(M111:P111) -> -194.231 | Z111: =SUM(N111:Q111) -> -203.234 | AB111: =SUM(Z111/V111)-1 -> 0.01480002
B112: Purchases of strategic investments | C112: -26.346 | D112: -7.77 | E112: -2 | G112: -4.48 | H112: -3.29 | I112: 0 | J112: =SUM(D112-SUM(G112:I112)) -> 8.8817842e-16 | K112: 0 | L112: -2 | M112: 0 | N112: =SUM(E112-SUM(K112:M112)) -> 0 | O112: 0 | P112: -20 | Q112: 0 | S112: =SUM(G112:J112) -> -7.77 | T112: =SUM(H112:K112) -> -3.29 | U112: =SUM(I112:L112) -> -2 | V112: =SUM(J112:M112) -> -2 | W112: =SUM(K112:N112) -> -2 | X112: =SUM(L112:O112) -> -2 | Y112: =SUM(M112:P112) -> -20 | Z112: =SUM(N112:Q112) -> -20 | AB112: =SUM(Z112/V112)-1 -> 9
B113: Sales of strategic investments | C113: 63.276 | D113: 7.559 | E113: 1.755 | G113: 0 | H113: 0 | I113: 5.151 | J113: =SUM(D113-SUM(G113:I113)) -> 2.408 | K113: 0 | L113: 1.006 | M113: 0.557 | N113: =SUM(E113-SUM(K113:M113)) -> 0.192 | O113: 0 | P113: 0 | Q113: 11.05 | S113: =SUM(G113:J113) -> 7.559 | T113: =SUM(H113:K113) -> 7.559 | U113: =SUM(I113:L113) -> 8.565 | V113: =SUM(J113:M113) -> 3.971 | W113: =SUM(K113:N113) -> 1.755 | X113: =SUM(L113:O113) -> 1.755 | Y113: =SUM(M113:P113) -> 0.749 | Z113: =SUM(N113:Q113) -> 11.242 | AB113: =SUM(Z113/V113)-1 -> 1.8310249
B114: Cash paid for acquisitions, net of cash acquired | C114: -67.067 | D114: -50.254 | E114: 0 | G114: 0 | H114: -50.254 | I114: 0 | J114: =SUM(D114-SUM(G114:I114)) -> 0 | K114: 0 | L114: 0 | M114: 0 | N114: =SUM(E114-SUM(K114:M114)) -> 0 | O114: 0 | P114: -35.499 | Q114: 0 | S114: =SUM(G114:J114) -> -50.254 | T114: =SUM(H114:K114) -> -50.254 | U114: =SUM(I114:L114) -> 0 | V114: =SUM(J114:M114) -> 0 | W114: =SUM(K114:N114) -> 0 | X114: =SUM(L114:O114) -> 0 | Y114: =SUM(M114:P114) -> -35.499 | Z114: =SUM(N114:Q114) -> -35.499 | AB114: =SUM(Z114/V114)-1 -> #DIV/0!
B115: Purchases of marketable securities | C115: -3485.638 | D115: -2048.273 | E115: -2287.668 | G115: -874.053 | H115: -631.218 | I115: -537.046 | J115: =SUM(D115-SUM(G115:I115)) -> -5.956 | K115: -465.672 | L115: -774.852 | M115: -705.066 | N115: =SUM(E115-SUM(K115:M115)) -> -342.078 | O115: -235.799 | P115: -390.866 | Q115: -388.652 | S115: =SUM(G115:J115) -> -2048.273 | T115: =SUM(H115:K115) -> -1639.892 | U115: =SUM(I115:L115) -> -1783.526 | V115: =SUM(J115:M115) -> -1951.546 | W115: =SUM(K115:N115) -> -2287.668 | X115: =SUM(L115:O115) -> -2057.795 | Y115: =SUM(M115:P115) -> -1673.809 | Z115: =SUM(N115:Q115) -> -1357.395 | AB115: =SUM(Z115/V115)-1 -> -0.30445145
B116: Sales of marketable securities | C116: 75.716 | D116: 459.481 | E116: 354.311 | G116: 5.351 | H116: 85.922 | I116: 16.451 | J116: =SUM(D116-SUM(G116:I116)) -> 351.757 | K116: 0 | L116: 166.557 | M116: 187.754 | N116: =SUM(E116-SUM(K116:M116)) -> 0 | O116: 12.001 | P116: 425.157 | Q116: 102.53 | S116: =SUM(G116:J116) -> 459.481 | T116: =SUM(H116:K116) -> 454.13 | U116: =SUM(I116:L116) -> 534.765 | V116: =SUM(J116:M116) -> 706.068 | W116: =SUM(K116:N116) -> 354.311 | X116: =SUM(L116:O116) -> 366.312 | Y116: =SUM(M116:P116) -> 624.912 | Z116: =SUM(N116:Q116) -> 539.688 | AB116: =SUM(Z116/V116)-1 -> -0.23564303
B117: Maturities of marketable securities | C117: 2525.215 | D117: 2424.717 | E117: 1411.444 | G117: 924.323 | H117: 611.835 | I117: 557.579 | J117: =SUM(D117-SUM(G117:I117)) -> 330.98 | K117: 384.928 | L117: 447.153 | M117: 337.985 | N117: =SUM(E117-SUM(K117:M117)) -> 241.378 | O117: 263.766 | P117: 301.348 | Q117: 220.203 | S117: =SUM(G117:J117) -> 2424.717 | T117: =SUM(H117:K117) -> 1885.322 | U117: =SUM(I117:L117) -> 1720.64 | V117: =SUM(J117:M117) -> 1501.046 | W117: =SUM(K117:N117) -> 1411.444 | X117: =SUM(L117:O117) -> 1290.282 | Y117: =SUM(M117:P117) -> 1144.477 | Z117: =SUM(N117:Q117) -> 1026.695 | AB117: =SUM(Z117/V117)-1 -> -0.31601363
B118: Other | C118: -18.125 | D118: -2.779 | E118: -0.1 | G118: 2.327 | H118: -2.451 | I118: -0.308 | J118: =SUM(D118-SUM(G118:I118)) -> -2.347 | K118: 0.009 | L118: -0.1 | M118: 0 | N118: =SUM(E118-SUM(K118:M118)) -> -0.009 | O118: 0 | P118: 0 | Q118: 0 | S118: =SUM(G118:J118) -> -2.779 | T118: =SUM(H118:K118) -> -5.097 | U118: =SUM(I118:L118) -> -2.746 | V118: =SUM(J118:M118) -> -2.438 | W118: =SUM(K118:N118) -> -0.1 | X118: =SUM(L118:O118) -> -0.109 | Y118: =SUM(M118:P118) -> -0.009 | Z118: =SUM(N118:Q118) -> -0.009 | AB118: =SUM(Z118/V118)-1 -> -0.99630845
B119: Net cash used in investing activities | C119: =SUM(C111:C118) -> -1062.275 | D119: =SUM(D111:D118) -> 570.954 | E119: =SUM(E111:E118) -> -717.084 | G119: =SUM(G111:G118) -> 5.838 | H119: =SUM(H111:H118) -> -26.399 | I119: =SUM(I111:I118) -> -31.608 | J119: =SUM(J111:J118) -> 623.123 | K119: =SUM(K111:K118) -> -131.183 | L119: =SUM(L111:L118) -> -214.298 | M119: =SUM(M111:M118) -> -222.811 | N119: =SUM(N111:N118) -> -148.792 | ... Q119: =SUM(Q111:Q118) -> -107.913 | S119: =SUM(S111:S118) -> 570.954 | T119: =SUM(T111:T118) -> 433.933 | U119: =SUM(U111:U118) -> 246.034 | V119: =SUM(V111:V118) -> 54.831 | W119: =SUM(W111:W118) -> -717.084 | X119: =SUM(X111:X118) -> -583.147 | Y119: =SUM(Y111:Y118) -> -153.41 | Z119: =SUM(Z111:Z118) -> -38.512 | AB119: =SUM(Z119/V119)-1 -> -1.7023764
B121: Cash flows from financing activities:
B122: Proceeds from issuance of convertible notes, net of issuance costs | C122: 1483.5 | D122: 0 | E122: 740.35 | G122: 0 | H122: 0 | I122: 0 | J122: =SUM(D122-SUM(G122:I122)) -> 0 | K122: 0 | L122: 740.35 | M122: 0 | N122: =SUM(E122-SUM(K122:M122)) -> 0 | O122: 1473.083 | P122: 0 | Q122: 541.11 | S122: =SUM(G122:J122) -> 0 | T122: =SUM(H122:K122) -> 0 | U122: =SUM(I122:L122) -> 740.35 | V122: =SUM(J122:M122) -> 740.35 | W122: =SUM(K122:N122) -> 740.35 | X122: =SUM(L122:O122) -> 2213.433 | Y122: =SUM(M122:P122) -> 1473.083 | Z122: =SUM(N122:Q122) -> 2014.193 | AB122: =SUM(Z122/V122)-1 -> 1.7205957
...

Sheet Revenue Drivers
B2: ='Historical Financials'!B2 -> Snap Inc (NASDAQ: SNAP) | C2: FYE | N2: Quarterly | AA2: LTM
B3: Segment Anaysis | C3: ='Historical Financials'!C7 -> 2022 | D3: ='Historical Financials'!D7 -> 2023 | E3: ='Historical Financials'!E7 -> 2024 | F3: ='Historical Financials'!#REF! -> #REF! | H3: ='Historical Financials'!G7 -> 1Q23 | I3: ='Historical Financials'!H7 -> 2Q23 | J3: ='Historical Financials'!I7 -> 3Q23 | K3: ='Historical Financials'!J7 -> 4Q23 | L3: ='Historical Financials'!K7 -> 1Q24 | M3: ='Historical Financials'!L7 -> 2Q24 | N3: ='Historical Financials'!M7 -> 3Q24 | O3: ='Historical Financials'!N7 -> 4Q24 | ... R3: ='Historical Financials'!Q7 -> 3Q25 | S3: ='Historical Financials'!#REF! -> #REF! | T3: ='Historical Financials'!#REF! -> #REF! | V3: =K3 -> 4Q23 | W3: =L3 -> 1Q24 | X3: =M3 -> 2Q24 | Y3: =N3 -> 3Q24 | Z3: =O3 -> 4Q24 | AA3: =P3 -> 1Q25 | AB3: =Q3 -> 2Q25 | AC3: =R3 -> 3Q25 | ... AE3: =T3 -> #REF!
B4: ($ In Millions) | C4: ='Historical Financials'!C8 -> 44926 | D4: ='Historical Financials'!D8 -> 45291 | E4: ='Historical Financials'!E8 -> 45657 | F4: ='Historical Financials'!#REF! -> #REF! | H4: ='Historical Financials'!G8 -> 45016 | I4: ='Historical Financials'!H8 -> 45107 | J4: ='Historical Financials'!I8 -> 45199 | K4: ='Historical Financials'!J8 -> 45291 | L4: ='Historical Financials'!K8 -> 45382 | M4: ='Historical Financials'!L8 -> 45473 | N4: ='Historical Financials'!M8 -> 45565 | O4: ='Historical Financials'!N8 -> 45657 | ... R4: ='Historical Financials'!Q8 -> 45930 | S4: ='Historical Financials'!#REF! -> #REF! | T4: ='Historical Financials'!#REF! -> #REF! | V4: =K4 -> 45291 | W4: =L4 -> 45382 | X4: =M4 -> 45473 | Y4: =N4 -> 45565 | Z4: =O4 -> 45657 | AA4: =P4 -> 45747 | AB4: =Q4 -> 45838 | AC4: =R4 -> 45930 | ... AE4: =T4 -> #REF!
A6: X | B6: Revenue by reportable segment
A8: X | B8: Revenue Segment Anaysis
B9: XXX | K9: =SUM(D9-SUM(H9:J9)) -> 0 | O9: =SUM(E9-SUM(L9:N9)) -> 0 | S9: =SUM(F9-SUM(P9:R9)) -> 0 | V9: =SUM(H9:K9) -> 0 | W9: =SUM(I9:L9) -> 0 | X9: =SUM(J9:M9) -> 0 | Y9: =SUM(K9:N9) -> 0 | Z9: =SUM(L9:O9) -> 0 | AA9: =SUM(M9:P9) -> 0 | AB9: =SUM(N9:Q9) -> 0 | AC9: =SUM(O9:R9) -> 0 | ... AE9: =SUM(Q9:T9) -> 0
B10: XXX | K10: =SUM(D10-SUM(H10:J10)) -> 0 | O10: =SUM(E10-SUM(L10:N10)) -> 0 | S10: =SUM(F10-SUM(P10:R10)) -> 0 | V10: =SUM(H10:K10) -> 0 | W10: =SUM(I10:L10) -> 0 | X10: =SUM(J10:M10) -> 0 | Y10: =SUM(K10:N10) -> 0 | Z10: =SUM(L10:O10) -> 0 | AA10: =SUM(M10:P10) -> 0 | AB10: =SUM(N10:Q10) -> 0 | AC10: =SUM(O10:R10) -> 0 | ... AE10: =SUM(Q10:T10) -> 0
B11: Total Net Revenue | C11: =SUM(C9:C10) -> 0 | D11: =SUM(D9:D10) -> 0 | E11: =SUM(E9:E10) -> 0 | F11: =SUM(F9:F10) -> 0 | H11: =SUM(H9:H10) -> 0 | I11: =SUM(I9:I10) -> 0 | J11: =SUM(J9:J10) -> 0 | K11: =SUM(K9:K10) -> 0 | L11: =SUM(L9:L10) -> 0 | M11: =SUM(M9:M10) -> 0 | N11: =SUM(N9:N10) -> 0 | O11: =SUM(O9:O10) -> 0 | ... T11: =SUM(T9:T10) -> 0 | V11: =SUM(V9:V10) -> 0 | W11: =SUM(W9:W10) -> 0 | X11: =SUM(X9:X10) -> 0 | Y11: =SUM(Y9:Y10) -> 0 | Z11: =SUM(Z9:Z10) -> 0 | AA11: =SUM(AA9:AA10) -> 0 | AB11: =SUM(AB9:AB10) -> 0 | AC11: =SUM(AC9:AC10) -> 0 | ... AE11: =SUM(AE9:AE10) -> 0
B12: Balance Check | C12: =+C11-'Historical Financials'!C11 -> -4601.8 | D12: =+D11-'Historical Financials'!D11 -> -4606.2 | E12: =+E11-'Historical Financials'!E11 -> -5361.5 | F12: =+F11-'Historical Financials'!#REF! -> #REF! | H12: =+H11-'Historical Financials'!G11 -> -988.608 | I12: =+I11-'Historical Financials'!H11 -> -1067.669 | J12: =+J11-'Historical Financials'!I11 -> -1188.551 | K12: =+K11-'Historical Financials'!J11 -> -1361.372 | L12: =+L11-'Historical Financials'!K11 -> -1194.773 | M12: =+M11-'Historical Financials'!L11 -> -1236.768 | N12: =+N11-'Historical Financials'!M11 -> -1372.574 | O12: =+O11-'Historical Financials'!N11 -> -1557.385 | ... R12: =+R11-'Historical Financials'!Q11 -> -1506.839 | S12: =+S11-'Historical Financials'!#REF! -> #REF! | T12: =+T11-'Historical Financials'!#REF! -> #REF! | V12: =+V11-'Historical Financials'!#REF! -> #REF! | W12: =+W11-'Historical Financials'!#REF! -> #REF! | X12: =+X11-'Historical Financials'!S11 -> -4606.2 | Y12: =+Y11-'Historical Financials'!T11 -> -4812.365 | Z12: =+Z11-'Historical Financials'!U11 -> -4981.464 | AA12: =+AA11-'Historical Financials'!V11 -> -5165.487 | AB12: =+AB11-'Historical Financials'!W11 -> -5361.5 | AC12: =+AC11-'Historical Financials'!X11 -> -5529.944 | AD12: =+AD11-'Historical Financials'!Y11 -> -5638.106 | AE12: =+AE11-'Historical Financials'!Z11 -> -5772.371
B14: =B9&"(%)" -> XXX(%) | C14: =SUM(C9/C$11) -> #DIV/0! | D14: =SUM(D9/D$11) -> #DIV/0! | E14: =SUM(E9/E$11) -> #DIV/0! | F14: =SUM(F9/F$11) -> #DIV/0! | H14: =SUM(H9/H$11) -> #DIV/0! | I14: =SUM(I9/I$11) -> #DIV/0! | J14: =SUM(J9/J$11) -> #DIV/0! | K14: =SUM(K9/K$11) -> #DIV/0! | L14: =SUM(L9/L$11) -> #DIV/0! | M14: =SUM(M9/M$11) -> #DIV/0! | N14: =SUM(N9/N$11) -> #DIV/0! | O14: =SUM(O9/O$11) -> #DIV/0! | ... T14: =SUM(T9/T$11) -> #DIV/0! | V14: =I14 -> #DIV/0! | W14: =J14 -> #DIV/0! | X14: =K14 -> #DIV/0! | Y14: =L14 -> #DIV/0! | Z14: =M14 -> #DIV/0! | AA14: =N14 -> #DIV/0! | AB14: =O14 -> #DIV/0! | AC14: =P14 -> #DIV/0! | ... AE14: =R14 -> #DIV/0!
B15: =B10&"(%)" -> XXX(%) | C15: =SUM(C10/C$11) -> #DIV/0! | D15: =SUM(D10/D$11) -> #DIV/0! | E15: =SUM(E10/E$11) -> #DIV/0! | F15: =SUM(F10/F$11) -> #DIV/0! | H15: =SUM(H10/H$11) -> #DIV/0! | I15: =SUM(I10/I$11) -> #DIV/0! | J15: =SUM(J10/J$11) -> #DIV/0! | K15: =SUM(K10/K$11) -> #DIV/0! | L15: =SUM(L10/L$11) -> #DIV/0! | M15: =SUM(M10/M$11) -> #DIV/0! | N15: =SUM(N10/N$11) -> #DIV/0! | O15: =SUM(O10/O$11) -> #DIV/0! | ... T15: =SUM(T10/T$11) -> #DIV/0! | V15: =I15 -> #DIV/0! | W15: =J15 -> #DIV/0! | X15: =K15 -> #DIV/0! | Y15: =L15 -> #DIV/0! | Z15: =M15 -> #DIV/0! | AA15: =N15 -> #DIV/0! | AB15: =O15 -> #DIV/0! | AC15: =P15 -> #DIV/0! | ... AE15: =R15 -> #DIV/0!
A17: X | B17: Revenue by product category
A19: X | B19: Revenue by XXX
B20: XXX | K20: =SUM(D20-SUM(H20:J20)) -> 0 | O20: =SUM(E20-SUM(L20:N20)) -> 0 | S20: =SUM(F20-SUM(P20:R20)) -> 0 | V20: =SUM(H20:K20) -> 0 | W20: =SUM(I20:L20) -> 0 | X20: =SUM(J20:M20) -> 0 | Y20: =SUM(K20:N20) -> 0 | Z20: =SUM(L20:O20) -> 0 | AA20: =SUM(M20:P20) -> 0 | AB20: =SUM(N20:Q20) -> 0 | AC20: =SUM(O20:R20) -> 0 | ... AE20: =SUM(Q20:T20) -> 0
B21: XXX | K21: =SUM(D21-SUM(H21:J21)) -> 0 | O21: =SUM(E21-SUM(L21:N21)) -> 0 | S21: =SUM(F21-SUM(P21:R21)) -> 0 | V21: =SUM(H21:K21) -> 0 | W21: =SUM(I21:L21) -> 0 | X21: =SUM(J21:M21) -> 0 | Y21: =SUM(K21:N21) -> 0 | Z21: =SUM(L21:O21) -> 0 | AA21: =SUM(M21:P21) -> 0 | AB21: =SUM(N21:Q21) -> 0 | AC21: =SUM(O21:R21) -> 0 | ... AE21: =SUM(Q21:T21) -> 0
B22: XXX | K22: =SUM(D22-SUM(H22:J22)) -> 0 | O22: =SUM(E22-SUM(L22:N22)) -> 0 | S22: =SUM(F22-SUM(P22:R22)) -> 0 | V22: =SUM(H22:K22) -> 0 | W22: =SUM(I22:L22) -> 0 | X22: =SUM(J22:M22) -> 0 | Y22: =SUM(K22:N22) -> 0 | Z22: =SUM(L22:O22) -> 0 | AA22: =SUM(M22:P22) -> 0 | AB22: =SUM(N22:Q22) -> 0 | AC22: =SUM(O22:R22) -> 0 | ... AE22: =SUM(Q22:T22) -> 0
B23: XXX | K23: =SUM(D23-SUM(H23:J23)) -> 0 | O23: =SUM(E23-SUM(L23:N23)) -> 0 | S23: =SUM(F23-SUM(P23:R23)) -> 0 | V23: =SUM(H23:K23) -> 0 | W23: =SUM(I23:L23) -> 0 | X23: =SUM(J23:M23) -> 0 | Y23: =SUM(K23:N23) -> 0 | Z23: =SUM(L23:O23) -> 0 | AA23: =SUM(M23:P23) -> 0 | AB23: =SUM(N23:Q23) -> 0 | AC23: =SUM(O23:R23) -> 0 | ... AE23: =SUM(Q23:T23) -> 0
B24: XXX | K24: =SUM(D24-SUM(H24:J24)) -> 0 | O24: =SUM(E24-SUM(L24:N24)) -> 0 | S24: =SUM(F24-SUM(P24:R24)) -> 0 | V24: =SUM(H24:K24) -> 0 | W24: =SUM(I24:L24) -> 0 | X24: =SUM(J24:M24) -> 0 | Y24: =SUM(K24:N24) -> 0 | Z24: =SUM(L24:O24) -> 0 | AA24: =SUM(M24:P24) -> 0 | AB24: =SUM(N24:Q24) -> 0 | AC24: =SUM(O24:R24) -> 0 | ... AE24: =SUM(Q24:T24) -> 0
B25: XXX | K25: =SUM(D25-SUM(H25:J25)) -> 0 | O25: =SUM(E25-SUM(L25:N25)) -> 0 | S25: =SUM(F25-SUM(P25:R25)) -> 0 | V25: =SUM(H25:K25) -> 0 | W25: =SUM(I25:L25) -> 0 | X25: =SUM(J25:M25) -> 0 | Y25: =SUM(K25:N25) -> 0 | Z25: =SUM(L25:O25) -> 0 | AA25: =SUM(M25:P25) -> 0 | AB25: =SUM(N25:Q25) -> 0 | AC25: =SUM(O25:R25) -> 0 | ... AE25: =SUM(Q25:T25) -> 0
B26: Total Revenue | C26: =SUM(C20:C25) -> 0 | D26: =SUM(D20:D25) -> 0 | E26: =SUM(E20:E25) -> 0 | F26: =SUM(F20:F25) -> 0 | H26: =SUM(H20:H25) -> 0 | I26: =SUM(I20:I25) -> 0 | J26: =SUM(J20:J25) -> 0 | K26: =SUM(K20:K25) -> 0 | L26: =SUM(L20:L25) -> 0 | M26: =SUM(M20:M25) -> 0 | N26: =SUM(N20:N25) -> 0 | O26: =SUM(O20:O25) -> 0 | ... T26: =SUM(T20:T25) -> 0 | V26: =SUM(V20:V25) -> 0 | W26: =SUM(W20:W25) -> 0 | X26: =SUM(X20:X25) -> 0 | Y26: =SUM(Y20:Y25) -> 0 | Z26: =SUM(Z20:Z25) -> 0 | AA26: =SUM(AA20:AA25) -> 0 | AB26: =SUM(AB20:AB25) -> 0 | AC26: =SUM(AC20:AC25) -> 0 | ... AE26: =SUM(AE20:AE25) -> 0
B27: Balance Check | C27: =+C26-C11 -> 0 | D27: =+D26-D11 -> 0 | E27: =+E26-E11 -> 0 | F27: =+F26-F11 -> 0 | H27: =+H26-H11 -> 0 | I27: =+I26-I11 -> 0 | J27: =+J26-J11 -> 0 | K27: =+K26-K11 -> 0 | L27: =+L26-L11 -> 0 | M27: =+M26-M11 -> 0 | N27: =+N26-N11 -> 0 | O27: =+O26-O11 -> 0 | ... T27: =+T26-T11 -> 0 | V27: =+V26-V11 -> 0 | W27: =+W26-W11 -> 0 | X27: =+X26-X11 -> 0 | Y27: =+Y26-Y11 -> 0 | Z27: =+Z26-Z11 -> 0 | AA27: =+AA26-AA11 -> 0 | AB27: =+AB26-AB11 -> 0 | AC27: =+AC26-AC11 -> 0 | ... AE27: =+AE26-AE11 -> 0
B29: =B20&"(%)" -> XXX(%) | C29: =C20/C$26 -> #DIV/0! | D29: =D20/D$26 -> #DIV/0! | E29: =E20/E$26 -> #DIV/0! | F29: =F20/F$26 -> #DIV/0! | H29: =H20/H$26 -> #DIV/0! | I29: =I20/I$26 -> #DIV/0! | J29: =J20/J$26 -> #DIV/0! | K29: =K20/K$26 -> #DIV/0! | L29: =L20/L$26 -> #DIV/0! | M29: =M20/M$26 -> #DIV/0! | N29: =N20/N$26 -> #DIV/0! | O29: =O20/O$26 -> #DIV/0! | ... T29: =T20/T$26 -> #DIV/0! | V29: =V20/V$26 -> #DIV/0! | W29: =W20/W$26 -> #DIV/0! | X29: =X20/X$26 -> #DIV/0! | Y29: =Y20/Y$26 -> #DIV/0! | Z29: =Z20/Z$26 -> #DIV/0! | AA29: =AA20/AA$26 -> #DIV/0! | AB29: =AB20/AB$26 -> #DIV/0! | AC29: =AC20/AC$26 -> #DIV/0! | ... AE29: =AE20/AE$26 -> #DIV/0!
B30: =B21&"(%)" -> XXX(%) | C30: =C21/C$26 -> #DIV/0! | D30: =D21/D$26 -> #DIV/0! | E30: =E21/E$26 -> #DIV/0! | F30: =F21/F$26 -> #DIV/0! | H30: =H21/H$26 -> #DIV/0! | I30: =I21/I$26 -> #DIV/0! | J30: =J21/J$26 -> #DIV/0! | K30: =K21/K$26 -> #DIV/0! | L30: =L21/L$26 -> #DIV/0! | M30: =M21/M$26 -> #DIV/0! | N30: =N21/N$26 -> #DIV/0! | O30: =O21/O$26 -> #DIV/0! | ... T30: =T21/T$26 -> #DIV/0! | V30: =V21/V$26 -> #DIV/0! | W30: =W21/W$26 -> #DIV/0! | X30: =X21/X$26 -> #DIV/0! | Y30: =Y21/Y$26 -> #DIV/0! | Z30: =Z21/Z$26 -> #DIV/0! | AA30: =AA21/AA$26 -> #DIV/0! | AB30: =AB21/AB$26 -> #DIV/0! | AC30: =AC21/AC$26 -> #DIV/0! | ... AE30: =AE21/AE$26 -> #DIV/0!
B31: =B22&"(%)" -> XXX(%) | C31: =C22/C$26 -> #DIV/0! | D31: =D22/D$26 -> #DIV/0! | E31: =E22/E$26 -> #DIV/0! | F31: =F22/F$26 -> #DIV/0! | H31: =H22/H$26 -> #DIV/0! | I31: =I22/I$26 -> #DIV/0! | J31: =J22/J$26 -> #DIV/0! | K31: =K22/K$26 -> #DIV/0! | L31: =L22/L$26 -> #DIV/0! | M31: =M22/M$26 -> #DIV/0! | N31: =N22/N$26 -> #DIV/0! | O31: =O22/O$26 -> #DIV/0! | ... T31: =T22/T$26 -> #DIV/0! | V31: =V22/V$26 -> #DIV/0! | W31: =W22/W$26 -> #DIV/0! | X31: =X22/X$26 -> #DIV/0! | Y31: =Y22/Y$26 -> #DIV/0! | Z31: =Z22/Z$26 -> #DIV/0! | AA31: =AA22/AA$26 -> #DIV/0! | AB31: =AB22/AB$26 -> #DIV/0! | AC31: =AC22/AC$26 -> #DIV/0! | ... AE31: =AE22/AE$26 -> #DIV/0!
B32: =B23&"(%)" -> XXX(%) | C32: =C23/C$26 -> #DIV/0! | D32: =D23/D$26 -> #DIV/0! | E32: =E23/E$26 -> #DIV/0! | F32: =F23/F$26 -> #DIV/0! | H32: =H23/H$26 -> #DIV/0! | I32: =I23/I$26 -> #DIV/0! | J32: =J23/J$26 -> #DIV/0! | K32: =K23/K$26 -> #DIV/0! | L32: =L23/L$26 -> #DIV/0! | M32: =M23/M$26 -> #DIV/0! | N32: =N23/N$26 -> #DIV/0! | O32: =O23/O$26 -> #DIV/0! | ... T32: =T23/T$26 -> #DIV/0! | V32: =V23/V$26 -> #DIV/0! | W32: =W23/W$26 -> #DIV/0! | X32: =X23/X$26 -> #DIV/0! | Y32: =Y23/Y$26 -> #DIV/0! | Z32: =Z23/Z$26 -> #DIV/0! | AA32: =AA23/AA$26 -> #DIV/0! | AB32: =AB23/AB$26 -> #DIV/0! | AC32: =AC23/AC$26 -> #DIV/0! | ... AE32: =AE23/AE$26 -> #DIV/0!
B33: =B24&"(%)" -> XXX(%) | C33: =C24/C$26 -> #DIV/0! | D33: =D24/D$26 -> #DIV/0! | E33: =E24/E$26 -> #DIV/0! | F33: =F24/F$26 -> #DIV/0! | H33: =H24/H$26 -> #DIV/0! | I33: =I24/I$26 -> #DIV/0! | J33: =J24/J$26 -> #DIV/0! | K33: =K24/K$26 -> #DIV/0! | L33: =L24/L$26 -> #DIV/0! | M33: =M24/M$26 -> #DIV/0! | N33: =N24/N$26 -> #DIV/0! | O33: =O24/O$26 -> #DIV/0! | ... T33: =T24/T$26 -> #DIV/0! | V33: =V24/V$26 -> #DIV/0! | W33: =W24/W$26 -> #DIV/0! | X33: =X24/X$26 -> #DIV/0! | Y33: =Y24/Y$26 -> #DIV/0! | Z33: =Z24/Z$26 -> #DIV/0! | AA33: =AA24/AA$26 -> #DIV/0! | AB33: =AB24/AB$26 -> #DIV/0! | AC33: =AC24/AC$26 -> #DIV/0! | ... AE33: =AE24/AE$26 -> #DIV/0!
B34: =B25&"(%)" -> XXX(%) | C34: =C25/C$26 -> #DIV/0! | D34: =D25/D$26 -> #DIV/0! | E34: =E25/E$26 -> #DIV/0! | F34: =F25/F$26 -> #DIV/0! | H34: =H25/H$26 -> #DIV/0! | I34: =I25/I$26 -> #DIV/0! | J34: =J25/J$26 -> #DIV/0! | K34: =K25/K$26 -> #DIV/0! | L34: =L25/L$26 -> #DIV/0! | M34: =M25/M$26 -> #DIV/0! | N34: =N25/N$26 -> #DIV/0! | O34: =O25/O$26 -> #DIV/0! | ... T34: =T25/T$26 -> #DIV/0! | V34: =V25/V$26 -> #DIV/0! | W34: =W25/W$26 -> #DIV/0! | X34: =X25/X$26 -> #DIV/0! | Y34: =Y25/Y$26 -> #DIV/0! | Z34: =Z25/Z$26 -> #DIV/0! | AA34: =AA25/AA$26 -> #DIV/0! | AB34: =AB25/AB$26 -> #DIV/0! | AC34: =AC25/AC$26 -> #DIV/0! | ... AE34: =AE25/AE$26 -> #DIV/0!

Sheet FCF
B2: ='Historical Financials'!B2 -> Snap Inc (NASDAQ: SNAP) | D2: FYE | H2: Quarterly | R2: Quarterly | Z2: LTM | AA2: LTM | AG2: Variance
B3: FCF Analysis | C3: ='Historical Financials'!C7 -> 2022 | D3: ='Historical Financials'!D7 -> 2023 | E3: ='Historical Financials'!E7 -> 2024 | F3: ='Historical Financials'!#REF! -> #REF! | H3: ='Historical Financials'!G7 -> 1Q23 | I3: ='Historical Financials'!H7 -> 2Q23 | J3: ='Historical Financials'!I7 -> 3Q23 | K3: ='Historical Financials'!J7 -> 4Q23 | L3: ='Historical Financials'!K7 -> 1Q24 | M3: ='Historical Financials'!L7 -> 2Q24 | N3: ='Historical Financials'!M7 -> 3Q24 | O3: ='Historical Financials'!N7 -> 4Q24 | ... R3: ='Historical Financials'!Q7 -> 3Q25 | S3: ='Historical Financials'!#REF! -> #REF! | T3: ='Historical Financials'!#REF! -> #REF! | V3: =K3 -> 4Q23 | W3: =L3 -> 1Q24 | X3: =M3 -> 2Q24 | Y3: =N3 -> 3Q24 | Z3: =O3 -> 4Q24 | AA3: =P3 -> 1Q25 | AB3: =Q3 -> 2Q25 | AC3: =R3 -> 3Q25 | ... AE3: =T3 -> #REF!
B4: ($ In Millions) | C4: ='Historical Financials'!C8 -> 44926 | D4: ='Historical Financials'!D8 -> 45291 | E4: ='Historical Financials'!E8 -> 45657 | F4: ='Historical Financials'!#REF! -> #REF! | H4: ='Historical Financials'!G8 -> 45016 | I4: ='Historical Financials'!H8 -> 45107 | J4: ='Historical Financials'!I8 -> 45199 | K4: ='Historical Financials'!J8 -> 45291 | L4: ='Historical Financials'!K8 -> 45382 | M4: ='Historical Financials'!L8 -> 45473 | N4: ='Historical Financials'!M8 -> 45565 | O4: ='Historical Financials'!N8 -> 45657 | ... R4: ='Historical Financials'!Q8 -> 45930 | S4: ='Historical Financials'!#REF! -> #REF! | T4: ='Historical Financials'!#REF! -> #REF! | V4: =K4 -> 45291 | W4: =L4 -> 45382 | X4: =M4 -> 45473 | Y4: =N4 -> 45565 | Z4: =O4 -> 45657 | AA4: =P4 -> 45747 | AB4: =Q4 -> 45838 | AC4: =R4 -> 45930 | ... AE4: =T4 -> #REF!
B6: XXX | V6: =SUM(H6:K6) -> 0 | W6: =SUM(I6:L6) -> 0 | X6: =SUM(J6:M6) -> 0 | Y6: =SUM(K6:N6) -> 0 | Z6: =SUM(L6:O6) -> 0 | AA6: =SUM(M6:P6) -> 0 | AB6: =SUM(N6:Q6) -> 0 | AC6: =SUM(O6:R6) -> 0 | ... AE6: =SUM(Q6:T6) -> 0 | AG6: =SUM(AE6/AA6)-1 -> #DIV/0!
B7: XXX | V7: =SUM(H7:K7) -> 0 | W7: =SUM(I7:L7) -> 0 | X7: =SUM(J7:M7) -> 0 | Y7: =SUM(K7:N7) -> 0 | Z7: =SUM(L7:O7) -> 0 | AA7: =SUM(M7:P7) -> 0 | AB7: =SUM(N7:Q7) -> 0 | AC7: =SUM(O7:R7) -> 0 | ... AE7: =SUM(Q7:T7) -> 0 | AG7: =SUM(AE7/AA7)-1 -> #DIV/0!
B8: XXX | V8: =SUM(H8:K8) -> 0 | W8: =SUM(I8:L8) -> 0 | X8: =SUM(J8:M8) -> 0 | Y8: =SUM(K8:N8) -> 0 | Z8: =SUM(L8:O8) -> 0 | AA8: =SUM(M8:P8) -> 0 | AB8: =SUM(N8:Q8) -> 0 | AC8: =SUM(O8:R8) -> 0 | ... AE8: =SUM(Q8:T8) -> 0 | AG8: =SUM(AE8/AA8)-1 -> #DIV/0!
B9: XXX | V9: =SUM(H9:K9) -> 0 | W9: =SUM(I9:L9) -> 0 | X9: =SUM(J9:M9) -> 0 | Y9: =SUM(K9:N9) -> 0 | Z9: =SUM(L9:O9) -> 0 | AA9: =SUM(M9:P9) -> 0 | AB9: =SUM(N9:Q9) -> 0 | AC9: =SUM(O9:R9) -> 0 | ... AE9: =SUM(Q9:T9) -> 0 | AG9: =SUM(AE9/AA9)-1 -> #DIV/0!
B10: XXX | V10: =SUM(H10:K10) -> 0 | W10: =SUM(I10:L10) -> 0 | X10: =SUM(J10:M10) -> 0 | Y10: =SUM(K10:N10) -> 0 | Z10: =SUM(L10:O10) -> 0 | AA10: =SUM(M10:P10) -> 0 | AB10: =SUM(N10:Q10) -> 0 | AC10: =SUM(O10:R10) -> 0 | ... AE10: =SUM(Q10:T10) -> 0 | AG10: =SUM(AE10/AA10)-1 -> #DIV/0!
B11: XXX | V11: =SUM(H11:K11) -> 0 | W11: =SUM(I11:L11) -> 0 | X11: =SUM(J11:M11) -> 0 | Y11: =SUM(K11:N11) -> 0 | Z11: =SUM(L11:O11) -> 0 | AA11: =SUM(M11:P11) -> 0 | AB11: =SUM(N11:Q11) -> 0 | AC11: =SUM(O11:R11) -> 0 | ... AE11: =SUM(Q11:T11) -> 0 | AG11: =SUM(AE11/AA11)-1 -> #DIV/0!
B12: Total Revenue | C12: =SUM(C6:C11) -> 0 | D12: =SUM(D6:D11) -> 0 | E12: =SUM(E6:E11) -> 0 | F12: =SUM(F6:F11) -> 0 | H12: =SUM(H6:H11) -> 0 | I12: =SUM(I6:I11) -> 0 | J12: =SUM(J6:J11) -> 0 | K12: =SUM(K6:K11) -> 0 | L12: =SUM(L6:L11) -> 0 | M12: =SUM(M6:M11) -> 0 | N12: =SUM(N6:N11) -> 0 | O12: =SUM(O6:O11) -> 0 | ... T12: =SUM(T6:T11) -> 0 | V12: =SUM(V6:V11) -> 0 | W12: =SUM(W6:W11) -> 0 | X12: =SUM(X6:X11) -> 0 | Y12: =SUM(Y6:Y11) -> 0 | Z12: =SUM(Z6:Z11) -> 0 | AA12: =SUM(AA6:AA11) -> 0 | AB12: =SUM(AB6:AB11) -> 0 | AC12: =SUM(AC6:AC11) -> 0 | ... AE12: =SUM(AE6:AE11) -> 0 | AG12: =SUM(AE12/AA12)-1 -> #DIV/0!
B13: Y/Y Growth (%) | C13: =SUM(C12/#REF!)-1 -> #REF! | D13: =SUM(D12/C12)-1 -> #DIV/0! | E13: =SUM(E12/D12)-1 -> #DIV/0! | F13: =SUM(F12/E12)-1 -> #DIV/0! | L13: =SUM(L12/H12)-1 -> #DIV/0! | M13: =SUM(M12/I12)-1 -> #DIV/0! | N13: =SUM(N12/J12)-1 -> #DIV/0! | O13: =SUM(O12/K12)-1 -> #DIV/0! | P13: =SUM(P12/L12)-1 -> #DIV/0! | Q13: =SUM(Q12/M12)-1 -> #DIV/0! | R13: =SUM(R12/N12)-1 -> #DIV/0! | S13: =SUM(S12/O12)-1 -> #DIV/0! | T13: =SUM(T12/P12)-1 -> #DIV/0! | Z13: =SUM(Z12/V12)-1 -> #DIV/0! | AA13: =SUM(AA12/W12)-1 -> #DIV/0! | AB13: =SUM(AB12/X12)-1 -> #DIV/0! | AC13: =SUM(AC12/Y12)-1 -> #DIV/0! | AD13: =SUM(AD12/Z12)-1 -> #DIV/0! | AE13: =SUM(AE12/AA12)-1 -> #DIV/0! | AG13: =SUM(AE13-AA13)*10000 -> #DIV/0!
B14: Q/Q Growth (%) | C14: N/A | D14: N/A | E14: N/A | F14: N/A | I14: =SUM(I12/H12)-1 -> #DIV/0! | J14: =SUM(J12/I12)-1 -> #DIV/0! | K14: =SUM(K12/J12)-1 -> #DIV/0! | L14: =SUM(L12/K12)-1 -> #DIV/0! | M14: =SUM(M12/L12)-1 -> #DIV/0! | N14: =SUM(N12/M12)-1 -> #DIV/0! | O14: =SUM(O12/N12)-1 -> #DIV/0! | P14: =SUM(P12/O12)-1 -> #DIV/0! | ... T14: =SUM(T12/S12)-1 -> #DIV/0! | V14: N/A | W14: N/A | X14: N/A | Y14: N/A | Z14: N/A | AA14: N/A | AB14: N/A | AC14: N/A | AD14: N/A | AE14: N/A
B16: (-) Cost of Sales | V16: =SUM(H16:K16) -> 0 | W16: =SUM(I16:L16) -> 0 | X16: =SUM(J16:M16) -> 0 | Y16: =SUM(K16:N16) -> 0 | Z16: =SUM(L16:O16) -> 0 | AA16: =SUM(M16:P16) -> 0 | AB16: =SUM(N16:Q16) -> 0 | AC16: =SUM(O16:R16) -> 0 | ... AE16: =SUM(Q16:T16) -> 0 | AG16: =SUM(AE16/AA16)-1 -> #DIV/0!
B17: Gross Profit | C17: =SUM(C12+SUM(C16:C16)) -> 0 | D17: =SUM(D12+SUM(D16:D16)) -> 0 | E17: =SUM(E12+SUM(E16:E16)) -> 0 | F17: =SUM(F12+SUM(F16:F16)) -> 0 | H17: =SUM(H12+SUM(H16:H16)) -> 0 | I17: =SUM(I12+SUM(I16:I16)) -> 0 | J17: =SUM(J12+SUM(J16:J16)) -> 0 | K17: =SUM(K12+SUM(K16:K16)) -> 0 | L17: =SUM(L12+SUM(L16:L16)) -> 0 | M17: =SUM(M12+SUM(M16:M16)) -> 0 | N17: =SUM(N12+SUM(N16:N16)) -> 0 | O17: =SUM(O12+SUM(O16:O16)) -> 0 | ... T17: =SUM(T12+SUM(T16:T16)) -> 0 | V17: =SUM(V12+SUM(V16:V16)) -> 0 | W17: =SUM(W12+SUM(W16:W16)) -> 0 | X17: =SUM(X12+SUM(X16:X16)) -> 0 | Y17: =SUM(Y12+SUM(Y16:Y16)) -> 0 | Z17: =SUM(Z12+SUM(Z16:Z16)) -> 0 | AA17: =SUM(AA12+SUM(AA16:AA16)) -> 0 | AB17: =SUM(AB12+SUM(AB16:AB16)) -> 0 | AC17: =SUM(AC12+SUM(AC16:AC16)) -> 0 | ... AE17: =SUM(AE12+SUM(AE16:AE16)) -> 0 | AG17: =SUM(AE17/AA17)-1 -> #DIV/0!
B18: Gross Margin (%) | C18: =C17/C12 -> #DIV/0! | D18: =D17/D12 -> #DIV/0! | E18: =E17/E12 -> #DIV/0! | F18: =F17/F12 -> #DIV/0! | H18: =H17/H12 -> #DIV/0! | I18: =I17/I12 -> #DIV/0! | J18: =J17/J12 -> #DIV/0! | K18: =K17/K12 -> #DIV/0! | L18: =L17/L12 -> #DIV/0! | M18: =M17/M12 -> #DIV/0! | N18: =N17/N12 -> #DIV/0! | O18: =O17/O12 -> #DIV/0! | ... T18: =T17/T12 -> #DIV/0! | V18: =V17/V12 -> #DIV/0! | W18: =W17/W12 -> #DIV/0! | X18: =X17/X12 -> #DIV/0! | Y18: =Y17/Y12 -> #DIV/0! | Z18: =Z17/Z12 -> #DIV/0! | AA18: =AA17/AA12 -> #DIV/0! | AB18: =AB17/AB12 -> #DIV/0! | AC18: =AC17/AC12 -> #DIV/0! | ... AE18: =AE17/AE12 -> #DIV/0! | AG18: =SUM(AE18-AA18)*10000 -> #DIV/0!
B20: (-) XXX | V20: =SUM(H20:K20) -> 0 | W20: =SUM(I20:L20) -> 0 | X20: =SUM(J20:M20) -> 0 | Y20: =SUM(K20:N20) -> 0 | Z20: =SUM(L20:O20) -> 0 | AA20: =SUM(M20:P20) -> 0 | AB20: =SUM(N20:Q20) -> 0 | AC20: =SUM(O20:R20) -> 0 | ... AE20: =SUM(Q20:T20) -> 0 | AG20: =SUM(AE20/AA20)-1 -> #DIV/0!
B21: (-) XXX | V21: =SUM(H21:K21) -> 0 | W21: =SUM(I21:L21) -> 0 | X21: =SUM(J21:M21) -> 0 | Y21: =SUM(K21:N21) -> 0 | Z21: =SUM(L21:O21) -> 0 | AA21: =SUM(M21:P21) -> 0 | AB21: =SUM(N21:Q21) -> 0 | AC21: =SUM(O21:R21) -> 0 | ... AE21: =SUM(Q21:T21) -> 0 | AG21: =SUM(AE21/AA21)-1 -> #DIV/0!
B22: (-) XXX | V22: =SUM(H22:K22) -> 0 | W22: =SUM(I22:L22) -> 0 | X22: =SUM(J22:M22) -> 0 | Y22: =SUM(K22:N22) -> 0 | Z22: =SUM(L22:O22) -> 0 | AA22: =SUM(M22:P22) -> 0 | AB22: =SUM(N22:Q22) -> 0 | AC22: =SUM(O22:R22) -> 0 | ... AE22: =SUM(Q22:T22) -> 0 | AG22: =SUM(AE22/AA22)-1 -> #DIV/0!
B23: (-) XXX | V23: =SUM(H23:K23) -> 0 | W23: =SUM(I23:L23) -> 0 | X23: =SUM(J23:M23) -> 0 | Y23: =SUM(K23:N23) -> 0 | Z23: =SUM(L23:O23) -> 0 | AA23: =SUM(M23:P23) -> 0 | AB23: =SUM(N23:Q23) -> 0 | AC23: =SUM(O23:R23) -> 0 | ... AE23: =SUM(Q23:T23) -> 0 | AG23: =SUM(AE23/AA23)-1 -> #DIV/0!
B24: (-) XXX | V24: =SUM(H24:K24) -> 0 | W24: =SUM(I24:L24) -> 0 | X24: =SUM(J24:M24) -> 0 | Y24: =SUM(K24:N24) -> 0 | Z24: =SUM(L24:O24) -> 0 | AA24: =SUM(M24:P24) -> 0 | AB24: =SUM(N24:Q24) -> 0 | AC24: =SUM(O24:R24) -> 0 | ... AE24: =SUM(Q24:T24) -> 0 | AG24: =SUM(AE24/AA24)-1 -> #DIV/0!
B25: Earning before Interest & Taxes (EBIT) | C25: =SUM(C17+SUM(C20:C24)) -> 0 | D25: =SUM(D17+SUM(D20:D24)) -> 0 | E25: =SUM(E17+SUM(E20:E24)) -> 0 | F25: =SUM(F17+SUM(F20:F24)) -> 0 | H25: =SUM(H17+SUM(H20:H24)) -> 0 | I25: =SUM(I17+SUM(I20:I24)) -> 0 | J25: =SUM(J17+SUM(J20:J24)) -> 0 | K25: =SUM(K17+SUM(K20:K24)) -> 0 | L25: =SUM(L17+SUM(L20:L24)) -> 0 | M25: =SUM(M17+SUM(M20:M24)) -> 0 | N25: =SUM(N17+SUM(N20:N24)) -> 0 | O25: =SUM(O17+SUM(O20:O24)) -> 0 | ... T25: =SUM(T17+SUM(T20:T24)) -> 0 | V25: =SUM(V17+SUM(V20:V24)) -> 0 | W25: =SUM(W17+SUM(W20:W24)) -> 0 | X25: =SUM(X17+SUM(X20:X24)) -> 0 | Y25: =SUM(Y17+SUM(Y20:Y24)) -> 0 | Z25: =SUM(Z17+SUM(Z20:Z24)) -> 0 | AA25: =SUM(AA17+SUM(AA20:AA24)) -> 0 | AB25: =SUM(AB17+SUM(AB20:AB24)) -> 0 | AC25: =SUM(AC17+SUM(AC20:AC24)) -> 0 | ... AE25: =SUM(AE17+SUM(AE20:AE24)) -> 0 | AG25: =SUM(AE25/AA25)-1 -> #DIV/0!
B26: Operating Margin (%) | C26: =C25/C12 -> #DIV/0! | D26: =D25/D12 -> #DIV/0! | E26: =E25/E12 -> #DIV/0! | F26: =F25/F12 -> #DIV/0! | H26: =H25/H12 -> #DIV/0! | I26: =I25/I12 -> #DIV/0! | J26: =J25/J12 -> #DIV/0! | K26: =K25/K12 -> #DIV/0! | L26: =L25/L12 -> #DIV/0! | M26: =M25/M12 -> #DIV/0! | N26: =N25/N12 -> #DIV/0! | O26: =O25/O12 -> #DIV/0! | ... T26: =T25/T12 -> #DIV/0! | V26: =V25/V12 -> #DIV/0! | W26: =W25/W12 -> #DIV/0! | X26: =X25/X12 -> #DIV/0! | Y26: =Y25/Y12 -> #DIV/0! | Z26: =Z25/Z12 -> #DIV/0! | AA26: =AA25/AA12 -> #DIV/0! | AB26: =AB25/AB12 -> #DIV/0! | AC26: =AC25/AC12 -> #DIV/0! | ... AE26: =AE25/AE12 -> #DIV/0! | AG26: =SUM(AE26-AA26)*10000 -> #DIV/0!
B28: (+) Depreciation and Amortization (D&A) | V28: =SUM(H28:K28) -> 0 | W28: =SUM(I28:L28) -> 0 | X28: =SUM(J28:M28) -> 0 | Y28: =SUM(K28:N28) -> 0 | Z28: =SUM(L28:O28) -> 0 | AA28: =SUM(M28:P28) -> 0 | AB28: =SUM(N28:Q28) -> 0 | AC28: =SUM(O28:R28) -> 0 | ... AE28: =SUM(Q28:T28) -> 0 | AG28: =SUM(AE28/AA28)-1 -> #DIV/0!
B29: EBITDA | C29: =SUM(C25+SUM(C28:C28)) -> 0 | D29: =SUM(D25+SUM(D28:D28)) -> 0 | E29: =SUM(E25+SUM(E28:E28)) -> 0 | F29: =SUM(F25+SUM(F28:F28)) -> 0 | H29: =SUM(H25+SUM(H28:H28)) -> 0 | I29: =SUM(I25+SUM(I28:I28)) -> 0 | J29: =SUM(J25+SUM(J28:J28)) -> 0 | K29: =SUM(K25+SUM(K28:K28)) -> 0 | L29: =SUM(L25+SUM(L28:L28)) -> 0 | M29: =SUM(M25+SUM(M28:M28)) -> 0 | N29: =SUM(N25+SUM(N28:N28)) -> 0 | O29: =SUM(O25+SUM(O28:O28)) -> 0 | ... T29: =SUM(T25+SUM(T28:T28)) -> 0 | V29: =SUM(V25+SUM(V28:V28)) -> 0 | W29: =SUM(W25+SUM(W28:W28)) -> 0 | X29: =SUM(X25+SUM(X28:X28)) -> 0 | Y29: =SUM(Y25+SUM(Y28:Y28)) -> 0 | Z29: =SUM(Z25+SUM(Z28:Z28)) -> 0 | AA29: =SUM(AA25+SUM(AA28:AA28)) -> 0 | AB29: =SUM(AB25+SUM(AB28:AB28)) -> 0 | AC29: =SUM(AC25+SUM(AC28:AC28)) -> 0 | ... AE29: =SUM(AE25+SUM(AE28:AE28)) -> 0 | AG29: =SUM(AE29/AA29)-1 -> #DIV/0!
B30: EBITDA Margin (%) | C30: =C29/C12 -> #DIV/0! | D30: =D29/D12 -> #DIV/0! | E30: =E29/E12 -> #DIV/0! | F30: =F29/F12 -> #DIV/0! | H30: =H29/H12 -> #DIV/0! | I30: =I29/I12 -> #DIV/0! | J30: =J29/J12 -> #DIV/0! | K30: =K29/K12 -> #DIV/0! | L30: =L29/L12 -> #DIV/0! | M30: =M29/M12 -> #DIV/0! | N30: =N29/N12 -> #DIV/0! | O30: =O29/O12 -> #DIV/0! | ... T30: =T29/T12 -> #DIV/0! | V30: =V29/V12 -> #DIV/0! | W30: =W29/W12 -> #DIV/0! | X30: =X29/X12 -> #DIV/0! | Y30: =Y29/Y12 -> #DIV/0! | Z30: =Z29/Z12 -> #DIV/0! | AA30: =AA29/AA12 -> #DIV/0! | AB30: =AB29/AB12 -> #DIV/0! | AC30: =AC29/AC12 -> #DIV/0! | ... AE30: =AE29/AE12 -> #DIV/0! | AG30: =SUM(AE30-AA30)*10000 -> #DIV/0!
B32: (+) Stock-Based Compensation (SBC) | V32: =SUM(H32:K32) -> 0 | W32: =SUM(I32:L32) -> 0 | X32: =SUM(J32:M32) -> 0 | Y32: =SUM(K32:N32) -> 0 | Z32: =SUM(L32:O32) -> 0 | AA32: =SUM(M32:P32) -> 0 | AB32: =SUM(N32:Q32) -> 0 | AC32: =SUM(O32:R32) -> 0 | ... AE32: =SUM(Q32:T32) -> 0 | AG32: =SUM(AE32/AA32)-1 -> #DIV/0!
B33: (+) XXX | V33: =SUM(H33:K33) -> 0 | W33: =SUM(I33:L33) -> 0 | X33: =SUM(J33:M33) -> 0 | Y33: =SUM(K33:N33) -> 0 | Z33: =SUM(L33:O33) -> 0 | AA33: =SUM(M33:P33) -> 0 | AB33: =SUM(N33:Q33) -> 0 | AC33: =SUM(O33:R33) -> 0 | ... AE33: =SUM(Q33:T33) -> 0 | AG33: =SUM(AE33/AA33)-1 -> #DIV/0!
B34: Adj. EBITDA | C34: =+SUM(C29+SUM(C32:C32)) -> 0 | D34: =+SUM(D29+SUM(D32:D32)) -> 0 | E34: =+SUM(E29+SUM(E32:E32)) -> 0 | F34: =+SUM(F29+SUM(F32:F32)) -> 0 | H34: =+SUM(H29+SUM(H32:H32)) -> 0 | I34: =+SUM(I29+SUM(I32:I32)) -> 0 | J34: =+SUM(J29+SUM(J32:J32)) -> 0 | K34: =+SUM(K29+SUM(K32:K32)) -> 0 | L34: =+SUM(L29+SUM(L32:L32)) -> 0 | M34: =+SUM(M29+SUM(M32:M32)) -> 0 | N34: =+SUM(N29+SUM(N32:N32)) -> 0 | O34: =+SUM(O29+SUM(O32:O32)) -> 0 | ... T34: =+SUM(T29+SUM(T32:T32)) -> 0 | V34: =+SUM(V29+SUM(V32:V32)) -> 0 | W34: =+SUM(W29+SUM(W32:W32)) -> 0 | X34: =+SUM(X29+SUM(X32:X32)) -> 0 | Y34: =+SUM(Y29+SUM(Y32:Y32)) -> 0 | Z34: =+SUM(Z29+SUM(Z32:Z32)) -> 0 | AA34: =+SUM(AA29+SUM(AA32:AA32)) -> 0 | AB34: =+SUM(AB29+SUM(AB32:AB32)) -> 0 | AC34: =+SUM(AC29+SUM(AC32:AC32)) -> 0 | ... AE34: =+SUM(AE29+SUM(AE32:AE32)) -> 0 | AG34: =SUM(AE34/AA34)-1 -> #DIV/0!
B35: Adj. EBITDA Margin (%) | C35: =C34/C12 -> #DIV/0! | D35: =D34/D12 -> #DIV/0! | E35: =E34/E12 -> #DIV/0! | F35: =F34/F12 -> #DIV/0! | H35: =H34/H12 -> #DIV/0! | I35: =I34/I12 -> #DIV/0! | J35: =J34/J12 -> #DIV/0! | K35: =K34/K12 -> #DIV/0! | L35: =L34/L12 -> #DIV/0! | M35: =M34/M12 -> #DIV/0! | N35: =N34/N12 -> #DIV/0! | O35: =O34/O12 -> #DIV/0! | ... T35: =T34/T12 -> #DIV/0! | V35: =V34/V12 -> #DIV/0! | W35: =W34/W12 -> #DIV/0! | X35: =X34/X12 -> #DIV/0! | Y35: =Y34/Y12 -> #DIV/0! | Z35: =Z34/Z12 -> #DIV/0! | AA35: =AA34/AA12 -> #DIV/0! | AB35: =AB34/AB12 -> #DIV/0! | AC35: =AC34/AC12 -> #DIV/0! | ... AE35: =AE34/AE12 -> #DIV/0! | AG35: =SUM(AE35-AA35)*10000 -> #DIV/0!
B37: (-) Capital Expenditures | V37: =SUM(H37:K37) -> 0 | W37: =SUM(I37:L37) -> 0 | X37: =SUM(J37:M37) -> 0 | Y37: =SUM(K37:N37) -> 0 | Z37: =SUM(L37:O37) -> 0 | AA37: =SUM(M37:P37) -> 0 | AB37: =SUM(N37:Q37) -> 0 | AC37: =SUM(O37:R37) -> 0 | ... AE37: =SUM(Q37:T37) -> 0 | AG37: =SUM(AE37/AA37)-1 -> #DIV/0!
B38: (-) Cash Taxes | V38: =SUM(H38:K38) -> 0 | W38: =SUM(I38:L38) -> 0 | X38: =SUM(J38:M38) -> 0 | Y38: =SUM(K38:N38) -> 0 | Z38: =SUM(L38:O38) -> 0 | AA38: =SUM(M38:P38) -> 0 | AB38: =SUM(N38:Q38) -> 0 | AC38: =SUM(O38:R38) -> 0 | ... AE38: =SUM(Q38:T38) -> 0 | AG38: =SUM(AE38/AA38)-1 -> #DIV/0!
B39: (-) Cash Interest | V39: =SUM(H39:K39) -> 0 | W39: =SUM(I39:L39) -> 0 | X39: =SUM(J39:M39) -> 0 | Y39: =SUM(K39:N39) -> 0 | Z39: =SUM(L39:O39) -> 0 | AA39: =SUM(M39:P39) -> 0 | AB39: =SUM(N39:Q39) -> 0 | AC39: =SUM(O39:R39) -> 0 | ... AE39: =SUM(Q39:T39) -> 0 | AG39: =SUM(AE39/AA39)-1 -> #DIV/0!
B40: (-) Mandatory Outflows | V40: =SUM(H40:K40) -> 0 | W40: =SUM(I40:L40) -> 0 | X40: =SUM(J40:M40) -> 0 | Y40: =SUM(K40:N40) -> 0 | Z40: =SUM(L40:O40) -> 0 | AA40: =SUM(M40:P40) -> 0 | AB40: =SUM(N40:Q40) -> 0 | AC40: =SUM(O40:R40) -> 0 | ... AE40: =SUM(Q40:T40) -> 0 | AG40: =SUM(AE40/AA40)-1 -> #DIV/0!
B41: (+/-) Changes in NWC | V41: =SUM(H41:K41) -> 0 | W41: =SUM(I41:L41) -> 0 | X41: =SUM(J41:M41) -> 0 | Y41: =SUM(K41:N41) -> 0 | Z41: =SUM(L41:O41) -> 0 | AA41: =SUM(M41:P41) -> 0 | AB41: =SUM(N41:Q41) -> 0 | AC41: =SUM(O41:R41) -> 0 | ... AE41: =SUM(Q41:T41) -> 0 | AG41: =SUM(AE41/AA41)-1 -> #DIV/0!
B42: Discretionary Cash-Flows | C42: =SUM(C34+SUM(C37:C41)) -> 0 | D42: =SUM(D34+SUM(D37:D41)) -> 0 | E42: =SUM(E34+SUM(E37:E41)) -> 0 | F42: =SUM(F34+SUM(F37:F41)) -> 0 | H42: =SUM(H34+SUM(H37:H41)) -> 0 | I42: =SUM(I34+SUM(I37:I41)) -> 0 | J42: =SUM(J34+SUM(J37:J41)) -> 0 | K42: =SUM(K34+SUM(K37:K41)) -> 0 | L42: =SUM(L34+SUM(L37:L41)) -> 0 | M42: =SUM(M34+SUM(M37:M41)) -> 0 | N42: =SUM(N34+SUM(N37:N41)) -> 0 | O42: =SUM(O34+SUM(O37:O41)) -> 0 | ... T42: =SUM(T34+SUM(T37:T41)) -> 0 | V42: =SUM(V34+SUM(V37:V41)) -> 0 | W42: =SUM(W34+SUM(W37:W41)) -> 0 | X42: =SUM(X34+SUM(X37:X41)) -> 0 | Y42: =SUM(Y34+SUM(Y37:Y41)) -> 0 | Z42: =SUM(Z34+SUM(Z37:Z41)) -> 0 | AA42: =SUM(AA34+SUM(AA37:AA41)) -> 0 | AB42: =SUM(AB34+SUM(AB37:AB41)) -> 0 | AC42: =SUM(AC34+SUM(AC37:AC41)) -> 0 | ... AE42: =SUM(AE34+SUM(AE37:AE41)) -> 0 | AG42: =SUM(AE42/AA42)-1 -> #DIV/0!
B44: (+/-) XXX | V44: =SUM(H44:K44) -> 0 | W44: =SUM(I44:L44) -> 0 | X44: =SUM(J44:M44) -> 0 | Y44: =SUM(K44:N44) -> 0 | Z44: =SUM(L44:O44) -> 0 | AA44: =SUM(M44:P44) -> 0 | AB44: =SUM(N44:Q44) -> 0 | AC44: =SUM(O44:R44) -> 0 | ... AE44: =SUM(Q44:T44) -> 0
B45: (+/-) XXX | V45: =SUM(H45:K45) -> 0 | W45: =SUM(I45:L45) -> 0 | X45: =SUM(J45:M45) -> 0 | Y45: =SUM(K45:N45) -> 0 | Z45: =SUM(L45:O45) -> 0 | AA45: =SUM(M45:P45) -> 0 | AB45: =SUM(N45:Q45) -> 0 | AC45: =SUM(O45:R45) -> 0 | ... AE45: =SUM(Q45:T45) -> 0
B46: (+/-) XXX | V46: =SUM(H46:K46) -> 0 | W46: =SUM(I46:L46) -> 0 | X46: =SUM(J46:M46) -> 0 | Y46: =SUM(K46:N46) -> 0 | Z46: =SUM(L46:O46) -> 0 | AA46: =SUM(M46:P46) -> 0 | AB46: =SUM(N46:Q46) -> 0 | AC46: =SUM(O46:R46) -> 0 | ... AE46: =SUM(Q46:T46) -> 0
B47: (+/-) XXX | V47: =SUM(H47:K47) -> 0 | W47: =SUM(I47:L47) -> 0 | X47: =SUM(J47:M47) -> 0 | Y47: =SUM(K47:N47) -> 0 | Z47: =SUM(L47:O47) -> 0 | AA47: =SUM(M47:P47) -> 0 | AB47: =SUM(N47:Q47) -> 0 | AC47: =SUM(O47:R47) -> 0 | ... AE47: =SUM(Q47:T47) -> 0
B48: (+/-) XXX | V48: =SUM(H48:K48) -> 0 | W48: =SUM(I48:L48) -> 0 | X48: =SUM(J48:M48) -> 0 | Y48: =SUM(K48:N48) -> 0 | Z48: =SUM(L48:O48) -> 0 | AA48: =SUM(M48:P48) -> 0 | AB48: =SUM(N48:Q48) -> 0 | AC48: =SUM(O48:R48) -> 0 | ... AE48: =SUM(Q48:T48) -> 0
B49: (+/-) Other | D49: =SUM(D54)-SUM(C54)-SUM(D42:D48) -> 0 | E49: =SUM(E54)-SUM(D54)-SUM(E42:E48) -> 0 | F49: =SUM(F54)-SUM(E54)-SUM(F42:F48) -> 0 | H49: =SUM(H54)-SUM(C54)-SUM(H42:H48) -> 0 | I49: =SUM(I54)-SUM(H54)-SUM(I42:I48) -> 0 | J49: =SUM(J54)-SUM(I54)-SUM(J42:J48) -> 0 | K49: =SUM(K54)-SUM(J54)-SUM(K42:K48) -> 1780.4 | L49: =SUM(L54)-SUM(K54)-SUM(L42:L48) -> -1780.4 | M49: =SUM(M54)-SUM(L54)-SUM(M42:M48) -> 0 | N49: =SUM(N54)-SUM(M54)-SUM(N42:N48) -> 0 | O49: =SUM(O54)-SUM(N54)-SUM(O42:O48) -> 1046.5 | P49: =SUM(P54)-SUM(O54)-SUM(P42:P48) -> -1046.5 | ... T49: =SUM(T54)-SUM(S54)-SUM(T42:T48) -> #REF! | V49: =SUM(H49:K49) -> 1780.4 | W49: =SUM(I49:L49) -> 0 | X49: =SUM(J49:M49) -> 0 | Y49: =SUM(K49:N49) -> 0 | Z49: =SUM(L49:O49) -> -733.9 | AA49: =SUM(M49:P49) -> 0 | AB49: =SUM(N49:Q49) -> 0 | AC49: =SUM(O49:R49) -> 0 | ... AE49: =SUM(Q49:T49) -> #REF!
B50: Free-Cash Flows | C50: =SUM(C42+SUM(C44:C49)) -> 0 | D50: =SUM(D42+SUM(D44:D49)) -> 0 | E50: =SUM(E42+SUM(E44:E49)) -> 0 | F50: =SUM(F42+SUM(F44:F49)) -> 0 | H50: =SUM(H42+SUM(H44:H49)) -> 0 | I50: =SUM(I42+SUM(I44:I49)) -> 0 | J50: =SUM(J42+SUM(J44:J49)) -> 0 | K50: =SUM(K42+SUM(K44:K49)) -> 1780.4 | L50: =SUM(L42+SUM(L44:L49)) -> -1780.4 | M50: =SUM(M42+SUM(M44:M49)) -> 0 | N50: =SUM(N42+SUM(N44:N49)) -> 0 | O50: =SUM(O42+SUM(O44:O49)) -> 1046.5 | ... T50: =SUM(T42+SUM(T44:T49)) -> #REF! | V50: =SUM(V42+SUM(V44:V49)) -> 1780.4 | W50: =SUM(W42+SUM(W44:W49)) -> 0 | X50: =SUM(X42+SUM(X44:X49)) -> 0 | Y50: =SUM(Y42+SUM(Y44:Y49)) -> 0 | Z50: =SUM(Z42+SUM(Z44:Z49)) -> -733.9 | AA50: =SUM(AA42+SUM(AA44:AA49)) -> 0 | AB50: =SUM(AB42+SUM(AB44:AB49)) -> 0 | AC50: =SUM(AC42+SUM(AC44:AC49)) -> 0 | ... AE50: =SUM(AE42+SUM(AE44:AE49)) -> #REF!
B52: Capitalization
B54: Cash & Cash Equivelants | K54: ='Historical Financials'!J44 -> 1780.4 | O54: ='Historical Financials'!N44 -> 1046.5 | S54: ='Historical Financials'!#REF! -> #REF! | V54: =K54 -> 1780.4 | W54: =L54 -> 0 | X54: =M54 -> 0 | Y54: =N54 -> 0 | Z54: =O54 -> 1046.5 | AA54: =P54 -> 0 | AB54: =Q54 -> 0 | AC54: =R54 -> 0 | ... AE54: =T54 -> 0
B55: XXX | K55: ='Historical Financials'!J45 -> 1763.68 | O55: ='Historical Financials'!N45 -> 2329.745 | S55: ='Historical Financials'!#REF! -> #REF! | V55: =K55 -> 1763.68 | W55: =L55 -> 0 | X55: =M55 -> 0 | Y55: =N55 -> 0 | Z55: =O55 -> 2329.745 | AA55: =P55 -> 0 | AB55: =Q55 -> 0 | AC55: =R55 -> 0 | ... AE55: =T55 -> 0
B56: XXX | K56: =D56 -> 0 | O56: =E56 -> 0 | S56: =F56 -> 0 | V56: =K56 -> 0 | W56: =L56 -> 0 | X56: =M56 -> 0 | Y56: =N56 -> 0 | Z56: =O56 -> 0 | AA56: =P56 -> 0 | AB56: =Q56 -> 0 | AC56: =R56 -> 0 | ... AE56: =T56 -> 0
B57: Total Liquidity | C57: =SUM(C54:C56) -> 0 | D57: =SUM(D54:D56) -> 0 | E57: =SUM(E54:E56) -> 0 | F57: =SUM(F54:F56) -> 0 | H57: =SUM(H54:H56) -> 0 | I57: =SUM(I54:I56) -> 0 | J57: =SUM(J54:J56) -> 0 | K57: =SUM(K54:K56) -> 3544.08 | L57: =SUM(L54:L56) -> 0 | M57: =SUM(M54:M56) -> 0 | N57: =SUM(N54:N56) -> 0 | O57: =SUM(O54:O56) -> 3376.245 | ... T57: =SUM(T54:T56) -> 0 | V57: =SUM(V54:V56) -> 3544.08 | W57: =SUM(W54:W56) -> 0 | X57: =SUM(X54:X56) -> 0 | Y57: =SUM(Y54:Y56) -> 0 | Z57: =SUM(Z54:Z56) -> 3376.245 | AA57: =SUM(AA54:AA56) -> 0 | AB57: =SUM(AB54:AB56) -> 0 | AC57: =SUM(AC54:AC56) -> 0 | ... AE57: =SUM(AE54:AE56) -> 0
B59: Balance Sheet Metrics:
B60: XXX | V60: =K60 -> 0 | W60: =L60 -> 0 | X60: =M60 -> 0 | Y60: =N60 -> 0 | Z60: =O60 -> 0 | AA60: =P60 -> 0 | AB60: =Q60 -> 0 | AC60: =R60 -> 0 | ... AE60: =T60 -> 0
B61: XXX | V61: =K61 -> 0 | W61: =L61 -> 0 | X61: =M61 -> 0 | Y61: =N61 -> 0 | Z61: =O61 -> 0 | AA61: =P61 -> 0 | AB61: =Q61 -> 0 | AC61: =R61 -> 0 | ... AE61: =T61 -> 0
B62: XXX | V62: =K62 -> 0 | W62: =L62 -> 0 | X62: =M62 -> 0 | Y62: =N62 -> 0 | Z62: =O62 -> 0 | AA62: =P62 -> 0 | AB62: =Q62 -> 0 | AC62: =R62 -> 0 | ... AE62: =T62 -> 0
B63: XXX | V63: =K63 -> 0 | W63: =L63 -> 0 | X63: =M63 -> 0 | Y63: =N63 -> 0 | Z63: =O63 -> 0 | AA63: =P63 -> 0 | AB63: =Q63 -> 0 | AC63: =R63 -> 0 | ... AE63: =T63 -> 0
B64: XXX | V64: =K64 -> 0 | W64: =L64 -> 0 | X64: =M64 -> 0 | Y64: =N64 -> 0 | Z64: =O64 -> 0 | AA64: =P64 -> 0 | AB64: =Q64 -> 0 | AC64: =R64 -> 0 | ... AE64: =T64 -> 0
B65: XXX | V65: =K65 -> 0 | W65: =L65 -> 0 | X65: =M65 -> 0 | Y65: =N65 -> 0 | Z65: =O65 -> 0 | AA65: =P65 -> 0 | AB65: =Q65 -> 0 | AC65: =R65 -> 0 | ... AE65: =T65 -> 0
B66: XXX | V66: =K66 -> 0 | W66: =L66 -> 0 | X66: =M66 -> 0 | Y66: =N66 -> 0 | Z66: =O66 -> 0 | AA66: =P66 -> 0 | AB66: =Q66 -> 0 | AC66: =R66 -> 0 | ... AE66: =T66 -> 0
B68: Summary Debt:
B69: CPLTD | V69: =K69 -> 0 | W69: =L69 -> 0 | X69: =M69 -> 0 | Y69: =N69 -> 0 | Z69: =O69 -> 0 | AA69: =P69 -> 0 | AB69: =Q69 -> 0 | AC69: =R69 -> 0 | ... AE69: =T69 -> 0
B70: LTD | V70: =K70 -> 0 | W70: =L70 -> 0 | X70: =M70 -> 0 | Y70: =N70 -> 0 | Z70: =O70 -> 0 | AA70: =P70 -> 0 | AB70: =Q70 -> 0 | AC70: =R70 -> 0 | ... AE70: =T70 -> 0
B72: XXX | K72: =D72 -> 0 | O72: =E72 -> 0 | S72: =F72 -> 0 | V72: =K72 -> 0 | W72: =L72 -> 0 | X72: =M72 -> 0 | Y72: =N72 -> 0 | Z72: =O72 -> 0 | AA72: =P72 -> 0 | AB72: =Q72 -> 0 | AC72: =R72 -> 0 | ... AE72: =T72 -> 0
B73: XXX | K73: =D73 -> 0 | O73: =E73 -> 0 | S73: =F73 -> 0 | V73: =K73 -> 0 | W73: =L73 -> 0 | X73: =M73 -> 0 | Y73: =N73 -> 0 | Z73: =O73 -> 0 | AA73: =P73 -> 0 | AB73: =Q73 -> 0 | AC73: =R73 -> 0 | ... AE73: =T73 -> 0
B74: XXX | K74: =D74 -> 0 | O74: =E74 -> 0 | S74: =F74 -> 0 | V74: =K74 -> 0 | W74: =L74 -> 0 | X74: =M74 -> 0 | Y74: =N74 -> 0 | Z74: =O74 -> 0 | AA74: =P74 -> 0 | AB74: =Q74 -> 0 | AC74: =R74 -> 0 | ... AE74: =T74 -> 0
B75: XXX | K75: ='Historical Financials'!#REF!+'Historical Financials'!#REF! -> #REF! | O75: ='Historical Financials'!#REF!+'Historical Financials'!#REF! -> #REF! | S75: ='Historical Financials'!#REF!+'Historical Financials'!#REF! -> #REF! | V75: =K75 -> #REF! | W75: =L75 -> 0 | X75: =M75 -> 0 | Y75: =N75 -> 0 | Z75: =O75 -> #REF! | AA75: =P75 -> 0 | AB75: =Q75 -> 0 | AC75: =R75 -> 0 | ... AE75: =T75 -> 0
B76: Total Debt | C76: =SUM(C72:C75) -> 0 | D76: =SUM(D72:D75) -> 0 | E76: =SUM(E72:E75) -> 0 | F76: =SUM(F72:F75) -> 0 | H76: =SUM(H72:H75) -> 0 | I76: =SUM(I72:I75) -> 0 | J76: =SUM(J72:J75) -> 0 | K76: =SUM(K72:K75) -> #REF! | L76: =SUM(L72:L75) -> 0 | M76: =SUM(M72:M75) -> 0 | N76: =SUM(N72:N75) -> 0 | O76: =SUM(O72:O75) -> #REF! | ... T76: =SUM(T72:T75) -> 0 | V76: =SUM(V72:V75) -> #REF! | W76: =SUM(W72:W75) -> 0 | X76: =SUM(X72:X75) -> 0 | Y76: =SUM(Y72:Y75) -> 0 | Z76: =SUM(Z72:Z75) -> #REF! | AA76: =SUM(AA72:AA75) -> 0 | AB76: =SUM(AB72:AB75) -> 0 | AC76: =SUM(AC72:AC75) -> 0 | ... AE76: =SUM(AE72:AE75) -> 0
B78: Total Shareholder Equity | V78: =K78 -> 0 | W78: =L78 -> 0 | X78: =M78 -> 0 | Y78: =N78 -> 0 | Z78: =O78 -> 0 | AA78: =P78 -> 0 | AB78: =Q78 -> 0 | AC78: =R78 -> 0 | ... AE78: =T78 -> 0
B79: Total Book Capitalization | C79: =SUM(C76:C78) -> 0 | D79: =SUM(D76:D78) -> 0 | E79: =SUM(E76:E78) -> 0 | F79: =SUM(F76:F78) -> 0 | H79: =SUM(H76:H78) -> 0 | I79: =SUM(I76:I78) -> 0 | J79: =SUM(J76:J78) -> 0 | K79: =SUM(K76:K78) -> #REF! | L79: =SUM(L76:L78) -> 0 | M79: =SUM(M76:M78) -> 0 | N79: =SUM(N76:N78) -> 0 | O79: =SUM(O76:O78) -> #REF! | ... T79: =SUM(T76:T78) -> 0 | V79: =SUM(V76:V78) -> #REF! | W79: =SUM(W76:W78) -> 0 | X79: =SUM(X76:X78) -> 0 | Y79: =SUM(Y76:Y78) -> 0 | Z79: =SUM(Z76:Z78) -> #REF! | AA79: =SUM(AA76:AA78) -> 0 | AB79: =SUM(AB76:AB78) -> 0 | AC79: =SUM(AC76:AC78) -> 0 | ... AE79: =SUM(AE76:AE78) -> 0
B81: Credit Metrics
B83: LTM Total Leverage | C83: =C76/C34 -> #DIV/0! | D83: =D76/D34 -> #DIV/0! | E83: =E76/E34 -> #DIV/0! | F83: =F76/F34 -> #DIV/0! | K83: =SUM(K76/SUM(H34:K34)) -> #REF! | L83: =SUM(L76/SUM(I34:L34)) -> #DIV/0! | M83: =SUM(M76/SUM(J34:M34)) -> #DIV/0! | N83: =SUM(N76/SUM(K34:N34)) -> #DIV/0! | O83: =SUM(O76/SUM(L34:O34)) -> #REF! | P83: =SUM(P76/SUM(M34:P34)) -> #DIV/0! | Q83: =SUM(Q76/SUM(N34:Q34)) -> #DIV/0! | R83: =SUM(R76/SUM(O34:R34)) -> #DIV/0! | ... T83: =SUM(T76/SUM(Q34:T34)) -> #DIV/0! | V83: =V76/V34 -> #REF! | W83: =W76/W34 -> #DIV/0! | X83: =X76/X34 -> #DIV/0! | Y83: =Y76/Y34 -> #DIV/0! | Z83: =Z76/Z34 -> #REF! | AA83: =AA76/AA34 -> #DIV/0! | AB83: =AB76/AB34 -> #DIV/0! | AC83: =AC76/AC34 -> #DIV/0! | ... AE83: =AE76/AE34 -> #DIV/0!
B84: LTM Net Leverage | C84: =SUM(C76-C54)/C34 -> #DIV/0! | D84: =SUM(D76-D54)/D34 -> #DIV/0! | E84: =SUM(E76-E54)/E34 -> #DIV/0! | F84: =SUM(F76-F54)/F34 -> #DIV/0! | K84: =SUM(K76-K54)/SUM(H34:K34) -> #REF! | L84: =SUM(L76-L54)/SUM(I34:L34) -> #DIV/0! | M84: =SUM(M76-M54)/SUM(J34:M34) -> #DIV/0! | N84: =SUM(N76-N54)/SUM(K34:N34) -> #DIV/0! | O84: =SUM(O76-O54)/SUM(L34:O34) -> #REF! | P84: =SUM(P76-P54)/SUM(M34:P34) -> #DIV/0! | Q84: =SUM(Q76-Q54)/SUM(N34:Q34) -> #DIV/0! | R84: =SUM(R76-R54)/SUM(O34:R34) -> #DIV/0! | ... T84: =SUM(T76-T54)/SUM(Q34:T34) -> #DIV/0! | V84: =SUM(V76-V54)/V34 -> #REF! | W84: =SUM(W76-W54)/W34 -> #DIV/0! | X84: =SUM(X76-X54)/X34 -> #DIV/0! | Y84: =SUM(Y76-Y54)/Y34 -> #DIV/0! | Z84: =SUM(Z76-Z54)/Z34 -> #REF! | AA84: =SUM(AA76-AA54)/AA34 -> #DIV/0! | AB84: =SUM(AB76-AB54)/AB34 -> #DIV/0! | AC84: =SUM(AC76-AC54)/AC34 -> #DIV/0! | ... AE84: =SUM(AE76-AE54)/AE34 -> #DIV/0!
B85: LTM Interest Coverage | C85: =C34/-C39 -> #DIV/0! | D85: =D34/-D39 -> #DIV/0! | E85: =E34/-E39 -> #DIV/0! | F85: =F34/-F39 -> #DIV/0! | K85: {=SUM(H34:K34)/SUM(-H39:K39)} -> #DIV/0! | L85: {=SUM(I34:L34)/SUM(-I39:L39)} -> #DIV/0! | M85: {=SUM(J34:M34)/SUM(-J39:M39)} -> #DIV/0! | N85: {=SUM(K34:N34)/SUM(-K39:N39)} -> #DIV/0! | O85: {=SUM(L34:O34)/SUM(-L39:O39)} -> #DIV/0! | P85: {=SUM(M34:P34)/SUM(-M39:P39)} -> #DIV/0! | Q85: {=SUM(N34:Q34)/SUM(-N39:Q39)} -> #DIV/0! | R85: {=SUM(O34:R34)/SUM(-O39:R39)} -> #DIV/0! | ... T85: {=SUM(Q34:T34)/SUM(-Q39:T39)} -> #DIV/0! | V85: =V34/-V39 -> #DIV/0! | W85: =W34/-W39 -> #DIV/0! | X85: =X34/-X39 -> #DIV/0! | Y85: =Y34/-Y39 -> #DIV/0! | Z85: =Z34/-Z39 -> #DIV/0! | AA85: =AA34/-AA39 -> #DIV/0! | AB85: =AB34/-AB39 -> #DIV/0! | AC85: =AC34/-AC39 -> #DIV/0! | ... AE85: =AE34/-AE39 -> #DIV/0!
B86: LTM Debt Service Coverage | C86: {=SUM(C34+C37)/SUM(-C38:C39)} -> #DIV/0! | D86: {=SUM(D34+D37)/SUM(-D38:D39)} -> #DIV/0! | E86: {=SUM(E34+E37)/SUM(-E38:E39)} -> #DIV/0! | F86: {=SUM(F34+F37)/SUM(-F38:F39)} -> #DIV/0! | K86: {=SUM(H34:K34+H37:K37)/SUM(-H38:K39)} -> #DIV/0! | L86: {=SUM(I34:L34+I37:L37)/SUM(-I38:L39)} -> #DIV/0! | M86: {=SUM(J34:M34+J37:M37)/SUM(-J38:M39)} -> #DIV/0! | N86: {=SUM(K34:N34+K37:N37)/SUM(-K38:N39)} -> #DIV/0! | O86: {=SUM(L34:O34+L37:O37)/SUM(-L38:O39)} -> #DIV/0! | P86: {=SUM(M34:P34+M37:P37)/SUM(-M38:P39)} -> #DIV/0! | Q86: {=SUM(N34:Q34+N37:Q37)/SUM(-N38:Q39)} -> #DIV/0! | R86: {=SUM(O34:R34+O37:R37)/SUM(-O38:R39)} -> #DIV/0! | ... T86: {=SUM(Q34:T34+Q37:T37)/SUM(-Q38:T39)} -> #DIV/0! | V86: {=SUM(V34+V37)/SUM(-V38:V39)} -> #DIV/0! | W86: {=SUM(W34+W37)/SUM(-W38:W39)} -> #DIV/0! | X86: {=SUM(X34+X37)/SUM(-X38:X39)} -> #DIV/0! | Y86: {=SUM(Y34+Y37)/SUM(-Y38:Y39)} -> #DIV/0! | Z86: {=SUM(Z34+Z37)/SUM(-Z38:Z39)} -> #DIV/0! | AA86: {=SUM(AA34+AA37)/SUM(-AA38:AA39)} -> #DIV/0! | AB86: {=SUM(AB34+AB37)/SUM(-AB38:AB39)} -> #DIV/0! | AC86: {=SUM(AC34+AC37)/SUM(-AC38:AC39)} -> #DIV/0! | ... AE86: {=SUM(AE34+AE37)/SUM(-AE38:AE39)} -> #DIV/0!
B87: LTM Fixed Charge Coverage | C87: {=SUM(C34)/SUM(-C37:C39)} -> #DIV/0! | D87: {=SUM(D34)/SUM(-D37:D39)} -> #DIV/0! | E87: {=SUM(E34)/SUM(-E37:E39)} -> #DIV/0! | F87: {=SUM(F34)/SUM(-F37:F39)} -> #DIV/0! | K87: {=SUM(H34:K34)/SUM(-H37:K39)} -> #DIV/0! | L87: {=SUM(I34:L34)/SUM(-I37:L39)} -> #DIV/0! | M87: {=SUM(J34:M34)/SUM(-J37:M39)} -> #DIV/0! | N87: {=SUM(K34:N34)/SUM(-K37:N39)} -> #DIV/0! | O87: {=SUM(L34:O34)/SUM(-L37:O39)} -> #DIV/0! | P87: {=SUM(M34:P34)/SUM(-M37:P39)} -> #DIV/0! | Q87: {=SUM(N34:Q34)/SUM(-N37:Q39)} -> #DIV/0! | R87: {=SUM(O34:R34)/SUM(-O37:R39)} -> #DIV/0! | ... T87: {=SUM(Q34:T34)/SUM(-Q37:T39)} -> #DIV/0! | V87: {=SUM(V34)/SUM(-V37:V39)} -> #DIV/0! | W87: {=SUM(W34)/SUM(-W37:W39)} -> #DIV/0! | X87: {=SUM(X34)/SUM(-X37:X39)} -> #DIV/0! | Y87: {=SUM(Y34)/SUM(-Y37:Y39)} -> #DIV/0! | Z87: {=SUM(Z34)/SUM(-Z37:Z39)} -> #DIV/0! | AA87: {=SUM(AA34)/SUM(-AA37:AA39)} -> #DIV/0! | AB87: {=SUM(AB34)/SUM(-AB37:AB39)} -> #DIV/0! | AC87: {=SUM(AC34)/SUM(-AC37:AC39)} -> #DIV/0! | ... AE87: {=SUM(AE34)/SUM(-AE37:AE39)} -> #DIV/0!
B88: Debt-to-Book Capitalization | C88: =C79/C76 -> #DIV/0! | D88: =D79/D76 -> #DIV/0! | E88: =E79/E76 -> #DIV/0! | F88: =F79/F76 -> #DIV/0! | K88: =K79/K76 -> #REF! | L88: =L79/L76 -> #DIV/0! | M88: =M79/M76 -> #DIV/0! | N88: =N79/N76 -> #DIV/0! | O88: =O79/O76 -> #REF! | P88: =P79/P76 -> #DIV/0! | Q88: =Q79/Q76 -> #DIV/0! | R88: =R79/R76 -> #DIV/0! | ... T88: =T79/T76 -> #DIV/0! | V88: =V79/V76 -> #REF! | W88: =W79/W76 -> #DIV/0! | X88: =X79/X76 -> #DIV/0! | Y88: =Y79/Y76 -> #DIV/0! | Z88: =Z79/Z76 -> #REF! | AA88: =AA79/AA76 -> #DIV/0! | AB88: =AB79/AB76 -> #DIV/0! | AC88: =AC79/AC76 -> #DIV/0! | ... AE88: =AE79/AE76 -> #DIV/0!
