Workbook

Sheet Historical Financials
B2: Apple Inc. (NASDAQ: AAPL)
B3: Historical Financials
B4: $ mm except per share
A10: X | B10: Income Statement | C10: FYE | M10: Quarterly | S10: Quarterly | V10: Quarterly | W10: Quarterly | AI10: LTM | AO10: Variance
B11: Fiscal Period | C11: 2016 | D11: 2017 | E11: 2018 | F11: 2019 | G11: 2020 | H11: 2021 | I11: 2022 | J11: 2023 | K11: 2024 | M11: 1Q22 | N11: 2Q22 | O11: 3Q22 | P11: 4Q22 | Q11: 1Q23 | R11: 2Q23 | S11: 3Q23 | T11: 4Q23 | U11: 1Q24 | V11: 2Q24 | W11: 3Q24 | X11: 4Q24 | Y11: 1Q25 | Z11: 2Q25 | AA11: 3Q25 | AC11: =Q11 -> 1Q23 | AD11: =R11 -> 2Q23 | AE11: =S11 -> 3Q23 | AF11: =T11 -> 4Q23 | AG11: =U11 -> 1Q24 | AH11: =V11 -> 2Q24 | AI11: =W11 -> 3Q24 | AJ11: =X11 -> 4Q24 | ... AM11: =AA11 -> 3Q25
B12: Fiscal Period End Date | C12: 42643 | D12: 43008 | E12: 43372 | F12: 43737 | G12: 44104 | H12: 44469 | I12: 44834 | J12: 45192 | K12: 45559 | M12: 44560 | N12: 44650 | O12: 44742 | P12: =I12 -> 44834 | Q12: 44917 | R12: 45008 | S12: 45100 | T12: =J12 -> 45192 | U12: 45283 | V12: 45375 | W12: 45467 | X12: =K12 -> 45559 | Y12: 45650 | Z12: 45741 | AA12: 45833 | AC12: =Q12 -> 44917 | AD12: =R12 -> 45008 | AE12: =S12 -> 45100 | AF12: =T12 -> 45192 | AG12: =U12 -> 45283 | AH12: =V12 -> 45375 | AI12: =W12 -> 45467 | AJ12: =X12 -> 45559 | ... AM12: =AA12 -> 45833
B14: Consolidated Revenue | C14: 215639 | D14: 229234 | E14: 265595 | F14: 260174 | G14: 274515 | H14: 365817 | I14: 394328 | J14: 383285 | K14: 391035 | M14: 123945 | N14: 97278 | O14: 82959 | P14: =SUM(I14-SUM(M14:O14)) -> 90146 | Q14: 117154 | R14: 94836 | S14: 81797 | T14: =SUM(J14-SUM(Q14:S14)) -> 89498 | U14: 119575 | V14: 90753 | W14: 85777 | X14: =SUM(K14-SUM(U14:W14)) -> 94930 | Y14: 124300 | Z14: 95359 | AA14: 94036 | AC14: =SUM(N14:Q14) -> 387537 | AD14: =SUM(O14:R14) -> 385095 | AE14: =SUM(P14:S14) -> 383933 | AF14: =SUM(Q14:T14) -> 383285 | AG14: =SUM(R14:U14) -> 385706 | AH14: =SUM(S14:V14) -> 381623 | AI14: =SUM(T14:W14) -> 385603 | AJ14: =SUM(U14:X14) -> 391035 | ... AM14: =SUM(X14:AA14) -> 408625 | AO14: =SUM(AM14/AI14)-1 -> 0.059703892
B15: Total Revenue | C15: =+SUM(C14:C14) -> 215639 | D15: =+SUM(D14:D14) -> 229234 | E15: =+SUM(E14:E14) -> 265595 | F15: =+SUM(F14:F14) -> 260174 | G15: =+SUM(G14:G14) -> 274515 | H15: =+SUM(H14:H14) -> 365817 | I15: =+SUM(I14:I14) -> 394328 | J15: =+SUM(J14:J14) -> 383285 | K15: =+SUM(K14:K14) -> 391035 | M15: =+SUM(M14:M14) -> 123945 | N15: =+SUM(N14:N14) -> 97278 | O15: =+SUM(O14:O14) -> 82959 | P15: =+SUM(P14:P14) -> 90146 | Q15: =+SUM(Q14:Q14) -> 117154 | R15: =+SUM(R14:R14) -> 94836 | S15: =+SUM(S14:S14) -> 81797 | T15: =+SUM(T14:T14) -> 89498 | ... AA15: =+SUM(AA14:AA14) -> 94036 | AC15: =+SUM(AC14:AC14) -> 387537 | AD15: =+SUM(AD14:AD14) -> 385095 | AE15: =+SUM(AE14:AE14) -> 383933 | AF15: =+SUM(AF14:AF14) -> 383285 | AG15: =+SUM(AG14:AG14) -> 385706 | AH15: =+SUM(AH14:AH14) -> 381623 | AI15: =+SUM(AI14:AI14) -> 385603 | AJ15: =+SUM(AJ14:AJ14) -> 391035 | ... AM15: =+SUM(AM14:AM14) -> 408625 | AO15: =SUM(AM15/AI15)-1 -> 0.059703892
B17: Cost of Sales | C17: -131376 | D17: -141048 | E17: -163756 | F17: -161782 | G17: -169559 | H17: -212981 | I17: -223546 | J17: -214137 | K17: -210352 | M17: -69702 | N17: -54719 | O17: -47074 | P17: =SUM(I17-SUM(M17:O17)) -> -52051 | Q17: -66822 | R17: -52860 | S17: -45384 | T17: =SUM(J17-SUM(Q17:S17)) -> -49071 | U17: -64720 | V17: -48482 | W17: -46099 | X17: =SUM(K17-SUM(U17:W17)) -> -51051 | Y17: -66025 | Z17: -50492 | AA17: -50318 | AC17: =SUM(N17:Q17) -> -220666 | AD17: =SUM(O17:R17) -> -218807 | AE17: =SUM(P17:S17) -> -217117 | AF17: =SUM(Q17:T17) -> -214137 | AG17: =SUM(R17:U17) -> -212035 | AH17: =SUM(S17:V17) -> -207657 | AI17: =SUM(T17:W17) -> -208372 | AJ17: =SUM(U17:X17) -> -210352 | ... AM17: =SUM(X17:AA17) -> -217886 | AO17: =SUM(AM17/AI17)-1 -> 0.045658726
B18: Gross Profit | C18: =+SUM(C15+SUM(C17:C17)) -> 84263 | D18: =+SUM(D15+SUM(D17:D17)) -> 88186 | E18: =+SUM(E15+SUM(E17:E17)) -> 101839 | F18: =+SUM(F15+SUM(F17:F17)) -> 98392 | G18: =+SUM(G15+SUM(G17:G17)) -> 104956 | H18: =+SUM(H15+SUM(H17:H17)) -> 152836 | I18: =+SUM(I15+SUM(I17:I17)) -> 170782 | J18: =+SUM(J15+SUM(J17:J17)) -> 169148 | K18: =+SUM(K15+SUM(K17:K17)) -> 180683 | M18: =+SUM(M15+SUM(M17:M17)) -> 54243 | N18: =+SUM(N15+SUM(N17:N17)) -> 42559 | O18: =+SUM(O15+SUM(O17:O17)) -> 35885 | P18: =+SUM(P15+SUM(P17:P17)) -> 38095 | Q18: =+SUM(Q15+SUM(Q17:Q17)) -> 50332 | R18: =+SUM(R15+SUM(R17:R17)) -> 41976 | S18: =+SUM(S15+SUM(S17:S17)) -> 36413 | T18: =+SUM(T15+SUM(T17:T17)) -> 40427 | ... AA18: =+SUM(AA15+SUM(AA17:AA17)) -> 43718 | AC18: =+SUM(AC15+SUM(AC17:AC17)) -> 166871 | AD18: =+SUM(AD15+SUM(AD17:AD17)) -> 166288 | AE18: =+SUM(AE15+SUM(AE17:AE17)) -> 166816 | AF18: =+SUM(AF15+SUM(AF17:AF17)) -> 169148 | AG18: =+SUM(AG15+SUM(AG17:AG17)) -> 173671 | AH18: =+SUM(AH15+SUM(AH17:AH17)) -> 173966 | AI18: =+SUM(AI15+SUM(AI17:AI17)) -> 177231 | AJ18: =+SUM(AJ15+SUM(AJ17:AJ17)) -> 180683 | ... AM18: =+SUM(AM15+SUM(AM17:AM17)) -> 190739 | AO18: =SUM(AM18/AI18)-1 -> 0.076216915
B19: Gross Margin (%) | C19: =C18/C15 -> 0.39075956 | D19: =D18/D15 -> 0.3846986 | E19: =E18/E15 -> 0.38343719 | F19: =F18/F15 -> 0.37817768 | G19: =G18/G15 -> 0.38233248 | H19: =H18/H15 -> 0.4177936 | I19: =I18/I15 -> 0.43309631 | J19: =J18/J15 -> 0.4413113 | K19: =K18/K15 -> 0.4620635 | M19: =M18/M15 -> 0.43763766 | N19: =N18/N15 -> 0.43749872 | O19: =O18/O15 -> 0.43256307 | P19: =P18/P15 -> 0.42259224 | Q19: =Q18/Q15 -> 0.42962255 | R19: =R18/R15 -> 0.44261673 | S19: =S18/S15 -> 0.44516303 | T19: =T18/T15 -> 0.45170842 | ... AA19: =AA18/AA15 -> 0.46490706 | AC19: =AC18/AC15 -> 0.43059372 | AD19: =AD18/AD15 -> 0.43181033 | AE19: =AE18/AE15 -> 0.43449248 | AF19: =AF18/AF15 -> 0.4413113 | AG19: =AG18/AG15 -> 0.45026782 | AH19: =AH18/AH15 -> 0.45585827 | AI19: =AI18/AI15 -> 0.45962039 | AJ19: =AJ18/AJ15 -> 0.4620635 | ... AM19: =AM18/AM15 -> 0.4667825 | AO19: =SUM(AM19-AI19)*1000 -> 7.1621155
B21: Research & Development | C21: -10045 | D21: -11581 | E21: -14236 | F21: -16217 | G21: -18752 | H21: -21914 | I21: -26251 | J21: -29915 | K21: -31370 | M21: -6306 | N21: -6387 | O21: -6797 | P21: =SUM(I21-SUM(M21:O21)) -> -6761 | Q21: -7709 | R21: -7457 | S21: -7442 | T21: =SUM(J21-SUM(Q21:S21)) -> -7307 | U21: -7696 | V21: -7903 | W21: -8006 | X21: =SUM(K21-SUM(U21:W21)) -> -7765 | Y21: -8268 | Z21: -8550 | AA21: -8866 | AC21: =SUM(N21:Q21) -> -27654 | AD21: =SUM(O21:R21) -> -28724 | AE21: =SUM(P21:S21) -> -29369 | AF21: =SUM(Q21:T21) -> -29915 | AG21: =SUM(R21:U21) -> -29902 | AH21: =SUM(S21:V21) -> -30348 | AI21: =SUM(T21:W21) -> -30912 | AJ21: =SUM(U21:X21) -> -31370 | ... AM21: =SUM(X21:AA21) -> -33449 | AO21: =SUM(AM21/AI21)-1 -> 0.082071687
B22: Selling, General & Administrative | C22: -14194 | D22: -15261 | E22: -16705 | F22: -18245 | G22: -19916 | H22: -21973 | I22: -25094 | J22: -24932 | K22: -26097 | M22: -6449 | N22: -6193 | O22: -6012 | P22: =SUM(I22-SUM(M22:O22)) -> -6440 | Q22: -6607 | R22: -6201 | S22: -5973 | T22: =SUM(J22-SUM(Q22:S22)) -> -6151 | U22: -6786 | V22: -6468 | W22: -6320 | X22: =SUM(K22-SUM(U22:W22)) -> -6523 | Y22: -7175 | Z22: -6728 | AA22: -6650 | AC22: =SUM(N22:Q22) -> -25252 | AD22: =SUM(O22:R22) -> -25260 | AE22: =SUM(P22:S22) -> -25221 | AF22: =SUM(Q22:T22) -> -24932 | AG22: =SUM(R22:U22) -> -25111 | AH22: =SUM(S22:V22) -> -25378 | AI22: =SUM(T22:W22) -> -25725 | AJ22: =SUM(U22:X22) -> -26097 | ... AM22: =SUM(X22:AA22) -> -27076 | AO22: =SUM(AM22/AI22)-1 -> 0.052517007
B23: Profit From Operations | C23: =SUM(C18+SUM(C21:C22)) -> 60024 | D23: =SUM(D18+SUM(D21:D22)) -> 61344 | E23: =SUM(E18+SUM(E21:E22)) -> 70898 | F23: =SUM(F18+SUM(F21:F22)) -> 63930 | G23: =SUM(G18+SUM(G21:G22)) -> 66288 | H23: =SUM(H18+SUM(H21:H22)) -> 108949 | I23: =SUM(I18+SUM(I21:I22)) -> 119437 | J23: =SUM(J18+SUM(J21:J22)) -> 114301 | K23: =SUM(K18+SUM(K21:K22)) -> 123216 | M23: =SUM(M18+SUM(M21:M22)) -> 41488 | N23: =SUM(N18+SUM(N21:N22)) -> 29979 | O23: =SUM(O18+SUM(O21:O22)) -> 23076 | P23: =SUM(P18+SUM(P21:P22)) -> 24894 | Q23: =SUM(Q18+SUM(Q21:Q22)) -> 36016 | R23: =SUM(R18+SUM(R21:R22)) -> 28318 | S23: =SUM(S18+SUM(S21:S22)) -> 22998 | T23: =SUM(T18+SUM(T21:T22)) -> 26969 | ... AA23: =SUM(AA18+SUM(AA21:AA22)) -> 28202 | AC23: =SUM(AC18+SUM(AC21:AC22)) -> 113965 | AD23: =SUM(AD18+SUM(AD21:AD22)) -> 112304 | AE23: =SUM(AE18+SUM(AE21:AE22)) -> 112226 | AF23: =SUM(AF18+SUM(AF21:AF22)) -> 114301 | AG23: =SUM(AG18+SUM(AG21:AG22)) -> 118658 | AH23: =SUM(AH18+SUM(AH21:AH22)) -> 118240 | AI23: =SUM(AI18+SUM(AI21:AI22)) -> 120594 | AJ23: =SUM(AJ18+SUM(AJ21:AJ22)) -> 123216 | ... AM23: =SUM(AM18+SUM(AM21:AM22)) -> 130214 | AO23: =SUM(AM23/AI23)-1 -> 0.079771796
B24: Operating Margin (%) | C24: =C23/C15 -> 0.2783541 | D24: =D23/D15 -> 0.26760428 | E24: =E23/E15 -> 0.26694027 | F24: =F23/F15 -> 0.24572017 | G24: =G23/G15 -> 0.24147314 | H24: =H23/H15 -> 0.29782378 | I24: =I23/I15 -> 0.30288744 | J24: =J23/J15 -> 0.29821412 | K24: =K23/K15 -> 0.31510223 | M24: =M23/M15 -> 0.33472911 | N24: =N23/N15 -> 0.30817862 | O24: =O23/O15 -> 0.2781615 | P24: =P23/P15 -> 0.27615202 | Q24: =Q23/Q15 -> 0.30742442 | R24: =R23/R15 -> 0.29859969 | S24: =S23/S15 -> 0.28115946 | T24: =T23/T15 -> 0.30133634 | ... AA24: =AA23/AA15 -> 0.29990642 | AC24: =AC23/AC15 -> 0.29407515 | AD24: =AD23/AD15 -> 0.29162674 | AE24: =AE23/AE15 -> 0.29230621 | AF24: =AF23/AF15 -> 0.29821412 | AG24: =AG23/AG15 -> 0.30763846 | AH24: =AH23/AH15 -> 0.30983457 | AI24: =AI23/AI15 -> 0.31274134 | AJ24: =AJ23/AJ15 -> 0.31510223 | ... AM24: =AM23/AM15 -> 0.31866381 | AO24: =SUM(AM24-AI24)*1000 -> 5.9224688
B26: Other income/(expense), net | C26: 1348 | D26: 2745 | E26: 2005 | F26: 1807 | G26: 803 | H26: 258 | I26: -334 | J26: -565 | K26: 269 | M26: -247 | N26: 160 | O26: -10 | P26: =SUM(I26-SUM(M26:O26)) -> -237 | Q26: -393 | R26: 64 | S26: -265 | T26: =SUM(J26-SUM(Q26:S26)) -> 29 | U26: -50 | V26: 158 | W26: 142 | X26: =SUM(K26-SUM(U26:W26)) -> 19 | Y26: -248 | Z26: -279 | AA26: -171 | AC26: =SUM(N26:Q26) -> -480 | AD26: =SUM(O26:R26) -> -576 | AE26: =SUM(P26:S26) -> -831 | AF26: =SUM(Q26:T26) -> -565 | AG26: =SUM(R26:U26) -> -222 | AH26: =SUM(S26:V26) -> -128 | AI26: =SUM(T26:W26) -> 279 | AJ26: =SUM(U26:X26) -> 269 | ... AM26: =SUM(X26:AA26) -> -679 | AO26: =SUM(AM26/AI26)-1 -> -3.4336918
B27: Net loss before provision for income taxes | C27: =SUM(C26:C26)+C23 -> 61372 | D27: =SUM(D26:D26)+D23 -> 64089 | E27: =SUM(E26:E26)+E23 -> 72903 | F27: =SUM(F26:F26)+F23 -> 65737 | G27: =SUM(G26:G26)+G23 -> 67091 | H27: =SUM(H26:H26)+H23 -> 109207 | I27: =SUM(I26:I26)+I23 -> 119103 | J27: =SUM(J26:J26)+J23 -> 113736 | K27: =SUM(K26:K26)+K23 -> 123485 | M27: =SUM(M26:M26)+M23 -> 41241 | N27: =SUM(N26:N26)+N23 -> 30139 | O27: =SUM(O26:O26)+O23 -> 23066 | P27: =SUM(P26:P26)+P23 -> 24657 | Q27: =SUM(Q26:Q26)+Q23 -> 35623 | R27: =SUM(R26:R26)+R23 -> 28382 | S27: =SUM(S26:S26)+S23 -> 22733 | T27: =SUM(T26:T26)+T23 -> 26998 | ... AA27: =SUM(AA26:AA26)+AA23 -> 28031 | AC27: =SUM(AC26:AC26)+AC23 -> 113485 | AD27: =SUM(AD26:AD26)+AD23 -> 111728 | AE27: =SUM(AE26:AE26)+AE23 -> 111395 | AF27: =SUM(AF26:AF26)+AF23 -> 113736 | AG27: =SUM(AG26:AG26)+AG23 -> 118436 | AH27: =SUM(AH26:AH26)+AH23 -> 118112 | AI27: =SUM(AI26:AI26)+AI23 -> 120873 | AJ27: =SUM(AJ26:AJ26)+AJ23 -> 123485 | ... AM27: =SUM(AM26:AM26)+AM23 -> 129535 | AO27: =SUM(AM27/AI27)-1 -> 0.071661992
B29: Provision for taxes | C29: -15685 | D29: -15738 | E29: -13372 | F29: -10481 | G29: -9680 | H29: -14527 | I29: -19300 | J29: -16741 | K29: -29749 | M29: -6611 | N29: -5129 | O29: -3624 | P29: =SUM(I29-SUM(M29:O29)) -> -3936 | Q29: -5625 | R29: -4222 | S29: -2852 | T29: =SUM(J29-SUM(Q29:S29)) -> -4042 | U29: -6407 | V29: -4422 | W29: -4046 | X29: =SUM(K29-SUM(U29:W29)) -> -14874 | Y29: -6254 | Z29: -4530 | AA29: -4597 | AC29: =SUM(N29:Q29) -> -18314 | AD29: =SUM(O29:R29) -> -17407 | AE29: =SUM(P29:S29) -> -16635 | AF29: =SUM(Q29:T29) -> -16741 | AG29: =SUM(R29:U29) -> -17523 | AH29: =SUM(S29:V29) -> -17723 | AI29: =SUM(T29:W29) -> -18917 | AJ29: =SUM(U29:X29) -> -29749 | ... AM29: =SUM(X29:AA29) -> -30255 | AO29: =SUM(AM29/AI29)-1 -> 0.59935508
B30: Net loss | C30: =SUM(C27+C29) -> 45687 | D30: =SUM(D27+D29) -> 48351 | E30: =SUM(E27+E29) -> 59531 | F30: =SUM(F27+F29) -> 55256 | G30: =SUM(G27+G29) -> 57411 | H30: =SUM(H27+H29) -> 94680 | I30: =SUM(I27+I29) -> 99803 | J30: =SUM(J27+J29) -> 96995 | K30: =SUM(K27+K29) -> 93736 | M30: =SUM(M27+M29) -> 34630 | N30: =SUM(N27+N29) -> 25010 | O30: =SUM(O27+O29) -> 19442 | P30: =SUM(P27+P29) -> 20721 | Q30: =SUM(Q27+Q29) -> 29998 | R30: =SUM(R27+R29) -> 24160 | S30: =SUM(S27+S29) -> 19881 | T30: =SUM(T27+T29) -> 22956 | ... AA30: =SUM(AA27+AA29) -> 23434 | AC30: =SUM(AC27+AC29) -> 95171 | AD30: =SUM(AD27+AD29) -> 94321 | AE30: =SUM(AE27+AE29) -> 94760 | AF30: =SUM(AF27+AF29) -> 96995 | AG30: =SUM(AG27+AG29) -> 100913 | AH30: =SUM(AH27+AH29) -> 100389 | AI30: =SUM(AI27+AI29) -> 101956 | AJ30: =SUM(AJ27+AJ29) -> 93736 | ... AM30: =SUM(AM27+AM29) -> 99280 | AO30: =SUM(AM30/AI30)-1 -> -0.026246616
B31: Net Margin (%) | C31: =C30/C15 -> 0.21186798 | D31: =D30/D15 -> 0.21092421 | E31: =E30/E15 -> 0.22414202 | F31: =F30/F15 -> 0.21238095 | G31: =G30/G15 -> 0.20913611 | H31: =H30/H15 -> 0.25881793 | I31: =I30/I15 -> 0.25309641 | J31: =J30/J15 -> 0.25306234 | K31: =K30/K15 -> 0.23971256 | M31: =M30/M15 -> 0.27939812 | N31: =N30/N15 -> 0.25709821 | O31: =O30/O15 -> 0.23435673 | P31: =P30/P15 -> 0.22986045 | Q31: =Q30/Q15 -> 0.25605613 | R31: =R30/R15 -> 0.25475558 | S31: =S30/S15 -> 0.24305292 | T31: =T30/T15 -> 0.25649735 | ... AA31: =AA30/AA15 -> 0.24920243 | AC31: =AC30/AC15 -> 0.24557913 | AD31: =AD30/AD15 -> 0.24492917 | AE31: =AE30/AE15 -> 0.2468139 | AF31: =AF30/AF15 -> 0.25306234 | AG31: =AG30/AG15 -> 0.26163192 | AH31: =AH30/AH15 -> 0.26305804 | AI31: =AI30/AI15 -> 0.26440666 | AJ31: =AJ30/AJ15 -> 0.23971256 | ... AM31: =AM30/AM15 -> 0.24296115 | AO31: =SUM(AM31-AI31)*1000 -> -21.445506
B33: Basic shares | C33: 21883.281 | D33: 20868.968 | E33: 19821.51 | F33: 18471.336 | G33: 17352.119 | H33: 16701.272 | I33: 16215.963 | J33: 15744.231 | K33: 15343.783 | M33: 16391.724 | N33: 16278.802 | O33: 16162.945 | P33: =I33 -> 16215.963 | Q33: 15892.723 | R33: 15787.154 | S33: 15697.614 | T33: =J33 -> 15744.231 | U33: 15509.763 | V33: 15405.856 | W33: 15287.521 | X33: =K33 -> 15343.783 | Y33: 15081.724 | Z33: 14994.082 | AA33: 14902.886 | AC33: =Q33 -> 15892.723 | AD33: =R33 -> 15787.154 | AE33: =S33 -> 15697.614 | AF33: =T33 -> 15744.231 | AG33: =U33 -> 15509.763 | AH33: =V33 -> 15405.856 | AI33: =W33 -> 15287.521 | AJ33: =X33 -> 15343.783 | ... AM33: =AA33 -> 14902.886
B34: Basic EPS | C34: =C30/C33 -> 2.0877582 | D34: =D30/D33 -> 2.3168851 | E34: =E30/E33 -> 3.0033534 | F34: =F30/F33 -> 2.9914458 | G34: =G30/G33 -> 3.3085873 | H34: =H30/H33 -> 5.6690293 | I34: =I30/I33 -> 6.1546144 | J34: =J30/J33 -> 6.1606693 | K34: =K30/K33 -> 6.1090541 | M34: =M30/M33 -> 2.1126515 | N34: =N30/N33 -> 1.5363538 | O34: =O30/O33 -> 1.2028748 | P34: =P30/P33 -> 1.277815 | Q34: =Q30/Q33 -> 1.8875305 | R34: =R30/R33 -> 1.5303582 | S34: =S30/S33 -> 1.2664982 | T34: =T30/T33 -> 1.4580579 | ... AA34: =AA30/AA33 -> 1.5724471 | AC34: =AC30/AC33 -> 5.9883382 | AD34: =AD30/AD33 -> 5.9745411 | AE34: =AE30/AE33 -> 6.0365862 | AF34: =AF30/AF33 -> 6.1606693 | AG34: =AG30/AG33 -> 6.5064179 | AH34: =AH30/AH33 -> 6.5162884 | AI34: =AI30/AI33 -> 6.6692304 | AJ34: =AJ30/AJ33 -> 6.1090541 | ... AM34: =AM30/AM33 -> 6.6617969 | AO34: =SUM(AM34/AI34)-1 -> -0.0011145959
B36: Fully Diluted Shares | C36: 22001.127 | D36: 21006.767 | E36: 20000.436 | F36: 18595.651 | G36: 17528.214 | H36: 16864.919 | I36: 16325.819 | J36: 15812.547 | K36: 15408.095 | M36: 16519.291 | N36: 16403.316 | O36: 16262.203 | P36: =I36 -> 16325.819 | Q36: 15955.718 | R36: 15847.05 | S36: 15775.021 | T36: =J36 -> 15812.547 | U36: 15576.641 | V36: 15464.709 | W36: 15348.175 | X36: =K36 -> 15408.095 | Y36: 15150.865 | Z36: 15056.133 | AA36: 14948.179 | AC36: =Q36 -> 15955.718 | AD36: =R36 -> 15847.05 | AE36: =S36 -> 15775.021 | AF36: =T36 -> 15812.547 | AG36: =U36 -> 15576.641 | AH36: =V36 -> 15464.709 | AI36: =W36 -> 15348.175 | AJ36: =X36 -> 15408.095 | ... AM36: =AA36 -> 14948.179
B37: Diluted EPS | C37: =C30/C36 -> 2.0765754 | D37: =D30/D36 -> 2.3016869 | E37: =E30/E36 -> 2.9764851 | F37: =F30/F36 -> 2.9714475 | G37: =G30/G36 -> 3.275348 | H37: =H30/H36 -> 5.6140204 | I37: =I30/I36 -> 6.1132002 | J37: =J30/J36 -> 6.1340529 | K37: =K30/K36 -> 6.0835554 | M37: =M30/M36 -> 2.0963369 | N37: =N30/N36 -> 1.5246917 | O37: =O30/O36 -> 1.195533 | P37: =P30/P36 -> 1.2692166 | Q37: =Q30/Q36 -> 1.8800784 | R37: =R30/R36 -> 1.524574 | S37: =S30/S36 -> 1.2602836 | T37: =T30/T36 -> 1.4517585 | ... AA37: =AA30/AA36 -> 1.5676826 | AC37: =AC30/AC36 -> 5.9646955 | AD37: =AD30/AD36 -> 5.9519595 | AE37: =AE30/AE36 -> 6.0069651 | AF37: =AF30/AF36 -> 6.1340529 | AG37: =AG30/AG36 -> 6.4784827 | AH37: =AH30/AH36 -> 6.4914898 | AI37: =AI30/AI36 -> 6.6428745 | AJ37: =AJ30/AJ36 -> 6.0835554 | ... AM37: =AM30/AM36 -> 6.6416117 | AO37: =SUM(AM37/AI37)-1 -> -0.00019010064
A39: X | B39: Balance Sheet | C39: FYE | M39: Quarterly | AI39: LTM | AO39: Variance
B40: =B11 -> Fiscal Period | C40: =C11 -> 2016 | D40: =D11 -> 2017 | E40: =E11 -> 2018 | F40: =F11 -> 2019 | G40: =G11 -> 2020 | H40: =H11 -> 2021 | I40: =I11 -> 2022 | ... K40: =K11 -> 2024 | M40: =M11 -> 1Q22 | N40: =N11 -> 2Q22 | O40: =O11 -> 3Q22 | P40: =P11 -> 4Q22 | Q40: =Q11 -> 1Q23 | R40: =R11 -> 2Q23 | S40: =S11 -> 3Q23 | T40: =T11 -> 4Q23 | ... AA40: =AA11 -> 3Q25 | AC40: =AC11 -> 1Q23 | AD40: =AD11 -> 2Q23 | AE40: =AE11 -> 3Q23 | AF40: =AF11 -> 4Q23 | AG40: =AG11 -> 1Q24 | AH40: =AH11 -> 2Q24 | AI40: =AI11 -> 3Q24 | AJ40: =AJ11 -> 4Q24 | ... AM40: =AM11 -> 3Q25
B41: =B12 -> Fiscal Period End Date | C41: =C12 -> 42643 | D41: =D12 -> 43008 | E41: =E12 -> 43372 | F41: =F12 -> 43737 | G41: =G12 -> 44104 | H41: =H12 -> 44469 | I41: =I12 -> 44834 | ... K41: =K12 -> 45559 | M41: =M12 -> 44560 | N41: =N12 -> 44650 | O41: =O12 -> 44742 | P41: =P12 -> 44834 | Q41: =Q12 -> 44917 | R41: =R12 -> 45008 | S41: =S12 -> 45100 | T41: =T12 -> 45192 | ... AA41: =AA12 -> 45833 | AC41: =AC12 -> 44917 | AD41: =AD12 -> 45008 | AE41: =AE12 -> 45100 | AF41: =AF12 -> 45192 | AG41: =AG12 -> 45283 | AH41: =AH12 -> 45375 | AI41: =AI12 -> 45467 | AJ41: =AJ12 -> 45559 | ... AM41: =AM12 -> 45833
B43: Cash/Equivalents | C43: 20484 | D43: 20289 | E43: 25913 | F43: 48844 | G43: 38016 | H43: 34940 | I43: 23646 | J43: 29965 | K43: 29943 | M43: 37119 | N43: 28098 | O43: 27502 | P43: =I43 -> 23646 | Q43: 20535 | R43: 24687 | S43: 28408 | T43: =J43 -> 29965 | U43: 40760 | V43: 32695 | W43: 25565 | X43: =K43 -> 29943 | Y43: 30299 | Z43: 28162 | AA43: 36269 | AC43: =Q43 -> 20535 | AD43: =R43 -> 24687 | AE43: =S43 -> 28408 | AF43: =T43 -> 29965 | AG43: =U43 -> 40760 | AH43: =V43 -> 32695 | AI43: =W43 -> 25565 | AJ43: =X43 -> 29943 | ... AM43: =AA43 -> 36269 | AO43: =SUM(AM43/AI43)-1 -> 0.41869744
B44: Marketable Securities, Current | C44: 46671 | D44: 53892 | E44: 40388 | F44: 51713 | G44: 52927 | H44: 27699 | I44: 24658 | J44: 31590 | K44: 35228 | M44: 26794 | N44: 23413 | O44: 20729 | P44: =I44 -> 24658 | Q44: 30820 | R44: 31185 | S44: 34074 | T44: =J44 -> 31590 | U44: 32340 | V44: 34455 | W44: 36236 | X44: =K44 -> 35228 | Y44: 23476 | Z44: 20336 | AA44: 19103 | AC44: =Q44 -> 30820 | AD44: =R44 -> 31185 | AE44: =S44 -> 34074 | AF44: =T44 -> 31590 | AG44: =U44 -> 32340 | AH44: =V44 -> 34455 | AI44: =W44 -> 36236 | AJ44: =X44 -> 35228 | ... AM44: =AA44 -> 19103 | AO44: =SUM(AM44/AI44)-1 -> -0.47281709
B45: Accounts Receivable | C45: 15754 | D45: 17874 | E45: 23186 | F45: 22926 | G45: 16120 | H45: 26278 | I45: 28184 | J45: 29508 | K45: 66243 | M45: 30213 | N45: 20815 | O45: 21803 | P45: =I45 -> 28184 | Q45: 23752 | R45: 17936 | S45: 19549 | T45: =J45 -> 29508 | U45: 23194 | V45: 21837 | W45: 22795 | X45: =K45 -> 66243 | Y45: 29639 | Z45: 49798 | AA45: 46835 | AC45: =Q45 -> 23752 | AD45: =R45 -> 17936 | AE45: =S45 -> 19549 | AF45: =T45 -> 29508 | AG45: =U45 -> 23194 | AH45: =V45 -> 21837 | AI45: =W45 -> 22795 | AJ45: =X45 -> 66243 | ... AM45: =AA45 -> 46835 | AO45: =SUM(AM45/AI45)-1 -> 1.0546172
B46: Inventory | C46: 2132 | D46: 4855 | E46: 3956 | F46: 4106 | G46: 4061 | H46: 6580 | I46: 4946 | J46: 6331 | K46: 7286 | M46: 5876 | N46: 5460 | O46: 5433 | P46: =I46 -> 4946 | Q46: 6820 | R46: 7482 | S46: 7351 | T46: =J46 -> 6331 | U46: 6511 | V46: 6232 | W46: 6165 | X46: =K46 -> 7286 | Y46: 6911 | Z46: 6269 | AA46: 5925 | AC46: =Q46 -> 6820 | AD46: =R46 -> 7482 | AE46: =S46 -> 7351 | AF46: =T46 -> 6331 | AG46: =U46 -> 6511 | AH46: =V46 -> 6232 | AI46: =W46 -> 6165 | AJ46: =X46 -> 7286 | ... AM46: =AA46 -> 5925 | AO46: =SUM(AM46/AI46)-1 -> -0.03892944
B47: Other Current Assets | C47: 21828 | D47: =13936+17799 -> 31735 | E47: 37896 | F47: 35230 | G47: 32589 | H47: 39339 | I47: 53971 | J47: 46172 | K47: 14287 | M47: 53152 | N47: 40394 | O47: 36825 | P47: =I47 -> 53971 | Q47: 46850 | R47: 31623 | S47: 33277 | T47: =J47 -> 46172 | U47: 40887 | V47: 33197 | W47: 34674 | X47: =K47 -> 14287 | Y47: 42915 | Z47: 14109 | AA47: 14359 | AC47: =Q47 -> 46850 | AD47: =R47 -> 31623 | AE47: =S47 -> 33277 | AF47: =T47 -> 46172 | AG47: =U47 -> 40887 | AH47: =V47 -> 33197 | AI47: =W47 -> 34674 | AJ47: =X47 -> 14287 | ... AM47: =AA47 -> 14359 | AO47: =SUM(AM47/AI47)-1 -> -0.58588568
B48: Total Current Assets | C48: =SUM(C43:C47) -> 106869 | D48: =SUM(D43:D47) -> 128645 | E48: =SUM(E43:E47) -> 131339 | F48: =SUM(F43:F47) -> 162819 | G48: =SUM(G43:G47) -> 143713 | H48: =SUM(H43:H47) -> 134836 | I48: =SUM(I43:I47) -> 135405 | J48: =SUM(J43:J47) -> 143566 | K48: =SUM(K43:K47) -> 152987 | M48: =SUM(M43:M47) -> 153154 | N48: =SUM(N43:N47) -> 118180 | O48: =SUM(O43:O47) -> 112292 | P48: =SUM(P43:P47) -> 135405 | Q48: =SUM(Q43:Q47) -> 128777 | R48: =SUM(R43:R47) -> 112913 | S48: =SUM(S43:S47) -> 122659 | T48: =SUM(T43:T47) -> 143566 | ... AA48: =SUM(AA43:AA47) -> 122491 | AC48: =SUM(AC43:AC47) -> 128777 | AD48: =SUM(AD43:AD47) -> 112913 | AE48: =SUM(AE43:AE47) -> 122659 | AF48: =SUM(AF43:AF47) -> 143566 | AG48: =SUM(AG43:AG47) -> 143692 | AH48: =SUM(AH43:AH47) -> 128416 | AI48: =SUM(AI43:AI47) -> 125435 | AJ48: =SUM(AJ43:AJ47) -> 152987 | ... AM48: =SUM(AM43:AM47) -> 122491 | AO48: =SUM(AM48/AI48)-1 -> -0.023470323
B50: PP&E | C50: 27010 | D50: 33783 | E50: 41304 | F50: 37378 | G50: 36766 | H50: 39440 | I50: 42117 | J50: 43715 | K50: 45680 | M50: 39245 | N50: 39304 | O50: 40335 | P50: =I50 -> 42117 | Q50: 42951 | R50: 43398 | S50: 43550 | T50: =J50 -> 43715 | U50: 43666 | V50: 43546 | W50: 44502 | X50: =K50 -> 45680 | Y50: 46069 | Z50: 46876 | AA50: 48508 | AC50: =Q50 -> 42951 | AD50: =R50 -> 43398 | AE50: =S50 -> 43550 | AF50: =T50 -> 43715 | AG50: =U50 -> 43666 | AH50: =V50 -> 43546 | AI50: =W50 -> 44502 | AJ50: =X50 -> 45680 | ... AM50: =AA50 -> 48508 | AO50: =SUM(AM50/AI50)-1 -> 0.090018426
B51: Marketable Securities, Net of Current Portion | C51: 170430 | D51: 194714 | E51: 170799 | F51: 105341 | G51: 100887 | H51: 127877 | I51: 120805 | J51: 100544 | K51: 91479 | M51: 138683 | N51: 141219 | O51: 131077 | P51: =I51 -> 120805 | Q51: 114095 | R51: 110461 | S51: 104061 | T51: =J51 -> 100544 | U51: 99475 | V51: 95187 | W51: 91240 | X51: =K51 -> 91479 | Y51: 87593 | Z51: 84424 | AA51: 77614 | AC51: =Q51 -> 114095 | AD51: =R51 -> 110461 | AE51: =S51 -> 104061 | AF51: =T51 -> 100544 | AG51: =U51 -> 99475 | AH51: =V51 -> 95187 | AI51: =W51 -> 91240 | AJ51: =X51 -> 91479 | ... AM51: =AA51 -> 77614 | AO51: =SUM(AM51/AI51)-1 -> -0.14934239
B52: Other Assets | C52: =5414+3206+8757 -> 17377 | D52: 18177 | E52: 22283 | F52: 32978 | G52: 42522 | H52: 48849 | I52: 54428 | J52: 64758 | K52: 74834 | M52: 42071 | N52: 43921 | O52: 44567 | P52: =I52 -> 54428 | Q52: 52886 | R52: 57350 | S52: 56730 | T52: =J52 -> 64758 | U52: 58643 | V52: 62224 | W52: 62397 | X52: =K52 -> 74834 | Y52: 77183 | Z52: 81259 | AA52: 82882 | AC52: =Q52 -> 52886 | AD52: =R52 -> 57350 | AE52: =S52 -> 56730 | AF52: =T52 -> 64758 | AG52: =U52 -> 58643 | AH52: =V52 -> 62224 | AI52: =W52 -> 62397 | AJ52: =X52 -> 74834 | ... AM52: =AA52 -> 82882 | AO52: =SUM(AM52/AI52)-1 -> 0.32830104
B53: Total Assets | C53: =SUM(C50:C52)+C48 -> 321686 | D53: =SUM(D50:D52)+D48 -> 375319 | E53: =SUM(E50:E52)+E48 -> 365725 | F53: =SUM(F50:F52)+F48 -> 338516 | G53: =SUM(G50:G52)+G48 -> 323888 | H53: =SUM(H50:H52)+H48 -> 351002 | I53: =SUM(I50:I52)+I48 -> 352755 | J53: =SUM(J50:J52)+J48 -> 352583 | K53: =SUM(K50:K52)+K48 -> 364980 | M53: =SUM(M50:M52)+M48 -> 373153 | N53: =SUM(N50:N52)+N48 -> 342624 | O53: =SUM(O50:O52)+O48 -> 328271 | P53: =SUM(P50:P52)+P48 -> 352755 | Q53: =SUM(Q50:Q52)+Q48 -> 338709 | R53: =SUM(R50:R52)+R48 -> 324122 | S53: =SUM(S50:S52)+S48 -> 327000 | T53: =SUM(T50:T52)+T48 -> 352583 | ... AA53: =SUM(AA50:AA52)+AA48 -> 331495 | AC53: =SUM(AC50:AC52)+AC48 -> 338709 | AD53: =SUM(AD50:AD52)+AD48 -> 324122 | AE53: =SUM(AE50:AE52)+AE48 -> 327000 | AF53: =SUM(AF50:AF52)+AF48 -> 352583 | AG53: =SUM(AG50:AG52)+AG48 -> 345476 | AH53: =SUM(AH50:AH52)+AH48 -> 329373 | AI53: =SUM(AI50:AI52)+AI48 -> 323574 | AJ53: =SUM(AJ50:AJ52)+AJ48 -> 364980 | ... AM53: =SUM(AM50:AM52)+AM48 -> 331495 | AO53: =SUM(AM53/AI53)-1 -> 0.024479717
B55: Accounts Payable | C55: 37294 | D55: 44242 | E55: 55888 | F55: 46236 | G55: 42296 | H55: 54763 | I55: 64115 | J55: 62611 | K55: 68960 | M55: 74362 | N55: 52682 | O55: 48343 | P55: =I55 -> 64115 | Q55: 57918 | R55: 42945 | S55: 46699 | T55: =J55 -> 62611 | U55: 58146 | V55: 45753 | W55: 47574 | X55: =K55 -> 68960 | Y55: 61910 | Z55: 54126 | AA55: 50374 | AC55: =Q55 -> 57918 | AD55: =R55 -> 42945 | AE55: =S55 -> 46699 | AF55: =T55 -> 62611 | AG55: =U55 -> 58146 | AH55: =V55 -> 45753 | AI55: =W55 -> 47574 | AJ55: =X55 -> 68960 | ... AM55: =AA55 -> 50374 | AO55: =SUM(AM55/AI55)-1 -> 0.058855677
B56: Deferred Revenue - Current | C56: 8080 | D56: 7548 | E56: 7543 | F56: 5522 | G56: 6643 | H56: 7612 | I56: 7912 | J56: 8061 | K56: 8249 | M56: 7876 | N56: 7920 | O56: 7728 | P56: =I56 -> 7912 | Q56: 7992 | R56: 8131 | S56: 8158 | T56: =J56 -> 8061 | U56: 8264 | V56: 8012 | W56: 8053 | X56: =K56 -> 8249 | Y56: 8461 | Z56: 8976 | AA56: 8979 | AC56: =Q56 -> 7992 | AD56: =R56 -> 8131 | AE56: =S56 -> 8158 | AF56: =T56 -> 8061 | AG56: =U56 -> 8264 | AH56: =V56 -> 8012 | AI56: =W56 -> 8053 | AJ56: =X56 -> 8249 | ... AM56: =AA56 -> 8979 | AO56: =SUM(AM56/AI56)-1 -> 0.1149882
B57: Other Current Liabilities (accrued exp) | C57: 22027 | D57: 30551 | E57: 32687 | F57: 37720 | G57: 42684 | H57: 47493 | I57: 60845 | J57: 58829 | K57: 78304 | M57: 49167 | N57: 50248 | O57: 48811 | P57: =I57 -> 60845 | Q57: 59893 | R57: 56425 | S57: 58897 | T57: =J57 -> 58829 | U57: 54611 | V57: 57298 | W57: 60889 | X57: =K57 -> 78304 | Y57: 61151 | Z57: 61849 | AA57: 62499 | AC57: =Q57 -> 59893 | AD57: =R57 -> 56425 | AE57: =S57 -> 58897 | AF57: =T57 -> 58829 | AG57: =U57 -> 54611 | AH57: =V57 -> 57298 | AI57: =W57 -> 60889 | AJ57: =X57 -> 78304 | ... AM57: =AA57 -> 62499 | AO57: =SUM(AM57/AI57)-1 -> 0.026441558
B58: Commerical Paper | C58: 8105 | D58: 11977 | E58: 11964 | F58: 5980 | G58: 4996 | H58: 6000 | I58: 9982 | J58: 5985 | K58: 9967 | M58: 5000 | N58: 6999 | O58: 10982 | P58: 9982 | Q58: 1743 | R58: 1996 | S58: 3993 | T58: 5985 | U58: 1998 | V58: 1997 | W58: 2994 | X58: 9967 | Y58: 1995 | Z58: 5982 | AA58: 9923 | AI58: =W58 -> 2994 | AJ58: =X58 -> 9967 | AK58: =Y58 -> 1995 | AL58: =Z58 -> 5982 | AM58: =AA58 -> 9923
B59: Term Debt, Current Portion | C59: 3500 | D59: 6496 | E59: 8784 | F59: 10260 | G59: 8773 | H59: 9613 | I59: 11128 | J59: 9822 | K59: 10912 | M59: 11169 | N59: 9659 | O59: 14009 | P59: 11128 | Q59: 9740 | R59: 10578 | S59: 7216 | T59: 9822 | U59: 10954 | V59: 10762 | W59: 12114 | X59: 10912 | Y59: 10848 | Z59: 13638 | AA59: 9345 | AC59: =Q59 -> 9740 | AD59: =R59 -> 10578 | AE59: =S59 -> 7216 | AF59: =T59 -> 9822 | AG59: =U59 -> 10954 | AH59: =V59 -> 10762 | AI59: =W59 -> 12114 | AJ59: =X59 -> 10912 | ... AM59: =AA59 -> 9345 | AO59: =SUM(AM59/AI59)-1 -> -0.2285785
B60: Total Current Liabilities | C60: =SUM(C55:C59) -> 79006 | D60: =SUM(D55:D59) -> 100814 | E60: =SUM(E55:E59) -> 116866 | F60: =SUM(F55:F59) -> 105718 | G60: =SUM(G55:G59) -> 105392 | H60: =SUM(H55:H59) -> 125481 | I60: =SUM(I55:I59) -> 153982 | J60: =SUM(J55:J59) -> 145308 | K60: =SUM(K55:K59) -> 176392 | M60: =SUM(M55:M59) -> 147574 | N60: =SUM(N55:N59) -> 127508 | O60: =SUM(O55:O59) -> 129873 | P60: =SUM(P55:P59) -> 153982 | Q60: =SUM(Q55:Q59) -> 137286 | R60: =SUM(R55:R59) -> 120075 | S60: =SUM(S55:S59) -> 124963 | T60: =SUM(T55:T59) -> 145308 | ... AA60: =SUM(AA55:AA59) -> 141120 | AC60: =SUM(AC55:AC59) -> 135543 | AD60: =SUM(AD55:AD59) -> 118079 | AE60: =SUM(AE55:AE59) -> 120970 | AF60: =SUM(AF55:AF59) -> 139323 | AG60: =SUM(AG55:AG59) -> 131975 | AH60: =SUM(AH55:AH59) -> 121825 | AI60: =SUM(AI55:AI59) -> 131624 | AJ60: =SUM(AJ55:AJ59) -> 176392 | ... AM60: =SUM(AM55:AM59) -> 141120 | AO60: =SUM(AM60/AI60)-1 -> 0.072144898
B62: Long-Term Debt | C62: 75427 | D62: 97207 | E62: 93735 | F62: 91807 | G62: 98667 | H62: 109106 | I62: 98959 | J62: 95281 | K62: 85750 | M62: 106629 | N62: 103323 | O62: 94700 | P62: =I62 -> 98959 | Q62: 99627 | R62: 97041 | S62: 98071 | T62: =J62 -> 95281 | U62: 95088 | V62: 91831 | W62: 86196 | X62: =K62 -> 85750 | Y62: 83956 | Z62: 78566 | AA62: 82430 | AC62: =Q62 -> 99627 | AD62: =R62 -> 97041 | AE62: =S62 -> 98071 | AF62: =T62 -> 95281 | AG62: =U62 -> 95088 | AH62: =V62 -> 91831 | AI62: =W62 -> 86196 | AJ62: =X62 -> 85750 | ... AM62: =AA62 -> 82430 | AO62: =SUM(AM62/AI62)-1 -> -0.043691123
B63: Deferred Revenue - Non-Current | C63: 2930 | D63: 2836 | E63: 2797 | F63: 0 | G63: 0 | H63: 0 | I63: 0 | J63: 0 | K63: 0 | M63: 0 | N63: 0 | O63: 0 | P63: =I63 -> 0 | Q63: 0 | R63: 0 | S63: 0 | T63: =J63 -> 0 | U63: 0 | V63: 0 | W63: 0 | X63: =K63 -> 0 | Y63: 0 | Z63: 0 | AA63: 0 | AC63: =Q63 -> 0 | AD63: =R63 -> 0 | AE63: =S63 -> 0 | AF63: =T63 -> 0 | AG63: =U63 -> 0 | AH63: =V63 -> 0 | AI63: =W63 -> 0 | AJ63: =X63 -> 0 | ... AM63: =AA63 -> 0
B64: Other Non-Current Liabilities | C64: 36074 | D64: 40415 | E64: 45180 | F64: 50503 | G64: 54490 | H64: 53325 | I64: 49142 | J64: 49848 | K64: 45888 | M64: 55056 | N64: 52432 | O64: 53629 | P64: =I64 -> 49142 | Q64: 53107 | R64: 52886 | S64: 51730 | T64: =J64 -> 49848 | U64: 50353 | V64: 47564 | W64: 47084 | X64: =K64 -> 45888 | Y64: 49006 | Z64: 41300 | AA64: 42115 | AC64: =Q64 -> 53107 | AD64: =R64 -> 52886 | AE64: =S64 -> 51730 | AF64: =T64 -> 49848 | AG64: =U64 -> 50353 | AH64: =V64 -> 47564 | AI64: =W64 -> 47084 | AJ64: =X64 -> 45888 | ... AM64: =AA64 -> 42115 | AO64: =SUM(AM64/AI64)-1 -> -0.10553479
B65: Total Liabilities | C65: =SUM(C62:C64)+C60 -> 193437 | D65: =SUM(D62:D64)+D60 -> 241272 | E65: =SUM(E62:E64)+E60 -> 258578 | F65: =SUM(F62:F64)+F60 -> 248028 | G65: =SUM(G62:G64)+G60 -> 258549 | H65: =SUM(H62:H64)+H60 -> 287912 | I65: =SUM(I62:I64)+I60 -> 302083 | J65: =SUM(J62:J64)+J60 -> 290437 | K65: =SUM(K62:K64)+K60 -> 308030 | M65: =SUM(M62:M64)+M60 -> 309259 | N65: =SUM(N62:N64)+N60 -> 283263 | O65: =SUM(O62:O64)+O60 -> 278202 | P65: =SUM(P62:P64)+P60 -> 302083 | Q65: =SUM(Q62:Q64)+Q60 -> 290020 | R65: =SUM(R62:R64)+R60 -> 270002 | S65: =SUM(S62:S64)+S60 -> 274764 | T65: =SUM(T62:T64)+T60 -> 290437 | ... AA65: =SUM(AA62:AA64)+AA60 -> 265665 | AC65: =SUM(AC62:AC64)+AC60 -> 288277 | AD65: =SUM(AD62:AD64)+AD60 -> 268006 | AE65: =SUM(AE62:AE64)+AE60 -> 270771 | AF65: =SUM(AF62:AF64)+AF60 -> 284452 | AG65: =SUM(AG62:AG64)+AG60 -> 277416 | AH65: =SUM(AH62:AH64)+AH60 -> 261220 | AI65: =SUM(AI62:AI64)+AI60 -> 264904 | AJ65: =SUM(AJ62:AJ64)+AJ60 -> 308030 | ... AM65: =SUM(AM62:AM64)+AM60 -> 265665 | AO65: =SUM(AM65/AI65)-1 -> 0.0028727388
B67: Common Stock | C67: 31251 | D67: 35867 | E67: 40201 | F67: 45174 | G67: 50779 | H67: 57365 | I67: 64849 | J67: 73812 | K67: 83276 | M67: 58424 | N67: 61181 | O67: 62115 | P67: =I67 -> 64849 | Q67: 66399 | R67: 69568 | S67: 70667 | T67: =J67 -> 73812 | U67: 75236 | V67: 75236 | W67: 79850 | X67: =K67 -> 83276 | Y67: 84768 | Z67: 88711 | AA67: 89806 | AC67: =Q67 -> 66399 | AD67: =R67 -> 69568 | AE67: =S67 -> 70667 | AF67: =T67 -> 73812 | AG67: =U67 -> 75236 | AH67: =V67 -> 75236 | AI67: =W67 -> 79850 | AJ67: =X67 -> 83276 | ... AM67: =AA67 -> 89806 | AO67: =SUM(AM67/AI67)-1 -> 0.12468378
B68: Retained Earnings (Deficit) | C68: 96364 | D68: 98330 | E68: 70400 | F68: 45898 | G68: 14966 | H68: 5562 | I68: -3068 | J68: -214 | K68: -19154 | M68: 6397 | N68: 4674 | O68: -2749 | P68: =I68 -> -3068 | Q68: -4798 | R68: -3702 | S68: -6630 | T68: =J68 -> -214 | U68: 204 | V68: -120 | W68: -12764 | X68: =K68 -> -19154 | Y68: -11221 | Z68: -15552 | AA68: -17613 | AC68: =Q68 -> -4798 | AD68: =R68 -> -3702 | AE68: =S68 -> -6630 | AF68: =T68 -> -214 | AG68: =U68 -> 204 | AH68: =V68 -> -120 | AI68: =W68 -> -12764 | AJ68: =X68 -> -19154 | ... AM68: =AA68 -> -17613 | AO68: =SUM(AM68/AI68)-1 -> 0.37989658
B69: Accumulated Other comprehensive income | C69: 634 | D69: -150 | E69: -3454 | F69: -584 | G69: -406 | H69: 163 | I69: -11109 | J69: -11452 | K69: -7172 | M69: -927 | N69: -6494 | O69: -9297 | P69: =I69 -> -11109 | Q69: -12912 | R69: -11746 | S69: -11801 | T69: =J69 -> -11452 | U69: -9378 | V69: -8960 | W69: -8416 | X69: =K69 -> -7172 | Y69: -6789 | Z69: -6363 | AA69: -6363 | AC69: =Q69 -> -12912 | AD69: =R69 -> -11746 | AE69: =S69 -> -11801 | AF69: =T69 -> -11452 | AG69: =U69 -> -9378 | AH69: =V69 -> -8960 | AI69: =W69 -> -8416 | AJ69: =X69 -> -7172 | ... AM69: =AA69 -> -6363 | AO69: =SUM(AM69/AI69)-1 -> -0.24394011
B70: Total stockholders' equity | C70: =SUM(C67:C69) -> 128249 | D70: =SUM(D67:D69) -> 134047 | E70: =SUM(E67:E69) -> 107147 | F70: =SUM(F67:F69) -> 90488 | G70: =SUM(G67:G69) -> 65339 | H70: =SUM(H67:H69) -> 63090 | I70: =SUM(I67:I69) -> 50672 | J70: =SUM(J67:J69) -> 62146 | K70: =SUM(K67:K69) -> 56950 | M70: =SUM(M67:M69) -> 63894 | N70: =SUM(N67:N69) -> 59361 | O70: =SUM(O67:O69) -> 50069 | P70: =SUM(P67:P69) -> 50672 | Q70: =SUM(Q67:Q69) -> 48689 | R70: =SUM(R67:R69) -> 54120 | S70: =SUM(S67:S69) -> 52236 | T70: =SUM(T67:T69) -> 62146 | ... AA70: =SUM(AA67:AA69) -> 65830 | AC70: =SUM(AC67:AC69) -> 48689 | AD70: =SUM(AD67:AD69) -> 54120 | AE70: =SUM(AE67:AE69) -> 52236 | AF70: =SUM(AF67:AF69) -> 62146 | AG70: =SUM(AG67:AG69) -> 66062 | AH70: =SUM(AH67:AH69) -> 66156 | AI70: =SUM(AI67:AI69) -> 58670 | AJ70: =SUM(AJ67:AJ69) -> 56950 | ... AM70: =SUM(AM67:AM69) -> 65830 | AO70: =SUM(AM70/AI70)-1 -> 0.12203852
B71: Total liabilities and stockholders' equity | C71: =SUM(C70+C65) -> 321686 | D71: =SUM(D70+D65) -> 375319 | E71: =SUM(E70+E65) -> 365725 | F71: =SUM(F70+F65) -> 338516 | G71: =SUM(G70+G65) -> 323888 | H71: =SUM(H70+H65) -> 351002 | I71: =SUM(I70+I65) -> 352755 | J71: =SUM(J70+J65) -> 352583 | K71: =SUM(K70+K65) -> 364980 | M71: =SUM(M70+M65) -> 373153 | N71: =SUM(N70+N65) -> 342624 | O71: =SUM(O70+O65) -> 328271 | P71: =SUM(P70+P65) -> 352755 | Q71: =SUM(Q70+Q65) -> 338709 | R71: =SUM(R70+R65) -> 324122 | S71: =SUM(S70+S65) -> 327000 | T71: =SUM(T70+T65) -> 352583 | ... AA71: =SUM(AA70+AA65) -> 331495 | AC71: =SUM(AC70+AC65) -> 336966 | AD71: =SUM(AD70+AD65) -> 322126 | AE71: =SUM(AE70+AE65) -> 323007 | AF71: =SUM(AF70+AF65) -> 346598 | AG71: =SUM(AG70+AG65) -> 343478 | AH71: =SUM(AH70+AH65) -> 327376 | AI71: =SUM(AI70+AI65) -> 323574 | AJ71: =SUM(AJ70+AJ65) -> 364980 | ... AM71: =SUM(AM70+AM65) -> 331495 | AO71: =SUM(AM71/AI71)-1 -> 0.024479717
B73: Balance Check | C73: =C71-C53 -> 0 | D73: =D71-D53 -> 0 | E73: =E71-E53 -> 0 | F73: =F71-F53 -> 0 | G73: =G71-G53 -> 0 | H73: =H71-H53 -> 0 | I73: =I71-I53 -> 0 | J73: =J71-J53 -> 0 | K73: =K71-K53 -> 0 | M73: =M71-M53 -> 0 | N73: =N71-N53 -> 0 | O73: =O71-O53 -> 0 | P73: =P71-P53 -> 0 | Q73: =Q71-Q53 -> 0 | R73: =R71-R53 -> 0 | S73: =S71-S53 -> 0 | T73: =T71-T53 -> 0 | ... AA73: =AA71-AA53 -> 0 | AC73: =AC71-AC53 -> -1743 | AD73: =AD71-AD53 -> -1996 | AE73: =AE71-AE53 -> -3993 | AF73: =AF71-AF53 -> -5985 | AG73: =AG71-AG53 -> -1998 | AH73: =AH71-AH53 -> -1997 | AI73: =AI71-AI53 -> 0 | AJ73: =AJ71-AJ53 -> 0 | ... AM73: =AM71-AM53 -> 0
A75: X | B75: Cash-Flows Statement | C75: FYE | M75: Quarterly | AI75: LTM | AO75: Variance
B76: =B11 -> Fiscal Period | C76: =C11 -> 2016 | D76: =D11 -> 2017 | E76: =E11 -> 2018 | F76: =F11 -> 2019 | G76: =G11 -> 2020 | H76: =H11 -> 2021 | I76: =I11 -> 2022 | ... K76: =K11 -> 2024 | M76: =M11 -> 1Q22 | N76: =N11 -> 2Q22 | O76: =O11 -> 3Q22 | P76: =P11 -> 4Q22 | Q76: =Q11 -> 1Q23 | R76: =R11 -> 2Q23 | S76: =S11 -> 3Q23 | T76: =T11 -> 4Q23 | ... AA76: =AA11 -> 3Q25 | AC76: =AC11 -> 1Q23 | AD76: =AD11 -> 2Q23 | AE76: =AE11 -> 3Q23 | AF76: =AF11 -> 4Q23 | AG76: =AG11 -> 1Q24 | AH76: =AH11 -> 2Q24 | AI76: =AI11 -> 3Q24 | AJ76: =AJ11 -> 4Q24 | ... AM76: =AM11 -> 3Q25
B77: =B12 -> Fiscal Period End Date | C77: =C12 -> 42643 | D77: =D12 -> 43008 | E77: =E12 -> 43372 | F77: =F12 -> 43737 | G77: =G12 -> 44104 | H77: =H12 -> 44469 | I77: =I12 -> 44834 | ... K77: =K12 -> 45559 | M77: =M12 -> 44560 | N77: =N12 -> 44650 | O77: =O12 -> 44742 | P77: =P12 -> 44834 | Q77: =Q12 -> 44917 | R77: =R12 -> 45008 | S77: =S12 -> 45100 | T77: =T12 -> 45192 | ... AA77: =AA12 -> 45833 | AC77: =AC12 -> 44917 | AD77: =AD12 -> 45008 | AE77: =AE12 -> 45100 | AF77: =AF12 -> 45192 | AG77: =AG12 -> 45283 | AH77: =AH12 -> 45375 | AI77: =AI12 -> 45467 | AJ77: =AJ12 -> 45559 | ... AM77: =AM12 -> 45833
B79: Cash-Flows From Operating Activities
B80: Net income (loss) | C80: =C30 -> 45687 | D80: =D30 -> 48351 | E80: =E30 -> 59531 | F80: =F30 -> 55256 | G80: =G30 -> 57411 | H80: =H30 -> 94680 | I80: =I30 -> 99803 | J80: =J30 -> 96995 | K80: =K30 -> 93736 | M80: =M30 -> 34630 | N80: =N30 -> 25010 | O80: =O30 -> 19442 | P80: =P30 -> 20721 | Q80: =Q30 -> 29998 | R80: =R30 -> 24160 | S80: =S30 -> 19881 | T80: =T30 -> 22956 | ... AA80: =AA30 -> 23434 | AC80: =SUM(N80:Q80) -> 95171 | AD80: =SUM(O80:R80) -> 94321 | AE80: =SUM(P80:S80) -> 94760 | AF80: =SUM(Q80:T80) -> 96995 | AG80: =SUM(R80:U80) -> 100913 | AH80: =SUM(S80:V80) -> 100389 | AI80: =SUM(T80:W80) -> 101956 | AJ80: =SUM(U80:X80) -> 93736 | ... AM80: =SUM(X80:AA80) -> 99280 | AO80: =SUM(AM80/AI80)-1 -> -0.026246616
B82: Adjustments to reconcile net income: | AO82: =SUM(AM82/AI82)-1 -> #DIV/0!
B83: Depreciation and Amortization | C83: 10505 | D83: 10157 | E83: 10903 | F83: 12547 | G83: 11056 | H83: 11284 | I83: 11104 | J83: 11519 | K83: 11445 | M83: 2697 | N83: =5434-M83 -> 2737 | O83: =8239-SUM(M83:N83) -> 2805 | P83: =SUM(I83-SUM(M83:O83)) -> 2865 | Q83: 2916 | R83: =5814-Q83 -> 2898 | S83: 3052 | T83: =SUM(J83-SUM(Q83:S83)) -> 2653 | U83: 2848 | V83: =5684-U83 -> 2836 | W83: =8534-V83-U83 -> 2850 | X83: =SUM(K83-SUM(U83:W83)) -> 2911 | Y83: 3080 | Z83: =5741-Y83 -> 2661 | AA83: =8571-Z83-Y83 -> 2830 | AC83: =SUM(N83:Q83) -> 11323 | AD83: =SUM(O83:R83) -> 11484 | AE83: =SUM(P83:S83) -> 11731 | AF83: =SUM(Q83:T83) -> 11519 | AG83: =SUM(R83:U83) -> 11451 | AH83: =SUM(S83:V83) -> 11389 | AI83: =SUM(T83:W83) -> 11187 | AJ83: =SUM(U83:X83) -> 11445 | ... AM83: =SUM(X83:AA83) -> 11482 | AO83: =SUM(AM83/AI83)-1 -> 0.026369894
B84: Stock Based Compensation | C84: 4210 | D84: 4840 | E84: 5340 | F84: 6068 | G84: 6829 | H84: 7906 | I84: 9038 | J84: 10833 | K84: 11688 | M84: 2265 | N84: =4517-M84 -> 2252 | O84: =6760-SUM(M84:N84) -> 2243 | P84: =SUM(I84-SUM(M84:O84)) -> 2278 | Q84: 2905 | R84: =5591-Q84 -> 2686 | S84: 2617 | T84: =SUM(J84-SUM(Q84:S84)) -> 2625 | U84: 2997 | V84: =5961-U84+3 -> 2967 | W84: =8830-V84-U84 -> 2866 | X84: =SUM(K84-SUM(U84:W84)) -> 2858 | Y84: 3286 | Z84: =6512-Y84 -> 3226 | AA84: =9680-Z84-Y84 -> 3168 | AC84: =SUM(N84:Q84) -> 9678 | AD84: =SUM(O84:R84) -> 10112 | AE84: =SUM(P84:S84) -> 10486 | AF84: =SUM(Q84:T84) -> 10833 | AG84: =SUM(R84:U84) -> 10925 | AH84: =SUM(S84:V84) -> 11206 | AI84: =SUM(T84:W84) -> 11455 | AJ84: =SUM(U84:X84) -> 11688 | ... AM84: =SUM(X84:AA84) -> 12538 | AO84: =SUM(AM84/AI84)-1 -> 0.094543867
B85: Deferred Taxes | C85: 4938 | D85: 5966 | E85: -32590 | F85: -340 | G85: -215 | H85: -4774 | I85: 895 | J85: 0 | K85: 0 | M85: 682 | N85: =1088-M85 -> 406 | O85: =2756-SUM(M85:N85) -> 1668 | P85: =SUM(I85-SUM(M85:O85)) -> -1861 | Q85: 0 | R85: =Q85 -> 0 | S85: 0 | T85: =SUM(J85-SUM(Q85:S85)) -> 0 | U85: =T85 -> 0 | V85: 0 | W85: 0 | X85: =SUM(K85-SUM(U85:W85)) -> 0 | Y85: =X85 -> 0 | Z85: =Y85 -> 0 | AA85: 0 | AC85: =SUM(N85:Q85) -> 213 | AD85: =SUM(O85:R85) -> -193 | AE85: =SUM(P85:S85) -> -1861 | AF85: =SUM(Q85:T85) -> 0 | AG85: =SUM(R85:U85) -> 0 | AH85: =SUM(S85:V85) -> 0 | AI85: =SUM(T85:W85) -> 0 | AJ85: =SUM(U85:X85) -> 0 | ... AM85: =SUM(X85:AA85) -> 0 | AO85: =SUM(AM85/AI85)-1 -> #DIV/0!
B86: Other - Loss on disposition of PPE | C86: 0 | D86: -166 | E86: -444 | F86: -652 | G86: -97 | H86: -147 | I86: 111 | J86: -2227 | K86: -2266 | M86: 167 | N86: =-20-M86 -> -187 | O86: =-61-SUM(M86:N86) -> -41 | P86: =SUM(I86-SUM(M86:O86)) -> 172 | Q86: -317 | R86: =-1732-Q86 -> -1415 | S86: 81 | T86: =SUM(J86-SUM(Q86:S86)) -> -576 | U86: -989 | V86: =-1971-U86 -> -982 | W86: =-1964-V86-U86 -> 7 | X86: =SUM(K86-SUM(U86:W86)) -> -302 | Y86: -2009 | Z86: =-2217-Y86 -> -208 | AA86: =-1748-Z86-Y86 -> 469 | AC86: =SUM(N86:Q86) -> -373 | AD86: =SUM(O86:R86) -> -1601 | AE86: =SUM(P86:S86) -> -1479 | AF86: =SUM(Q86:T86) -> -2227 | AG86: =SUM(R86:U86) -> -2899 | AH86: =SUM(S86:V86) -> -2466 | AI86: =SUM(T86:W86) -> -2540 | AJ86: =SUM(U86:X86) -> -2266 | ... AM86: =SUM(X86:AA86) -> -2050 | AO86: =SUM(AM86/AI86)-1 -> -0.19291339
B88: Changes in assets and liabilities: | AO88: =SUM(AM88/AI88)-1 -> #DIV/0!
B89: Accounts Receivable | C89: 1095 | D89: -2093 | E89: -5322 | F89: 245 | G89: 6917 | H89: -10125 | I89: -1823 | J89: -1688 | K89: -3788 | M89: -3934 | N89: =5542-M89 -> 9476 | O89: =4561-SUM(M89:N89) -> -981 | P89: =SUM(I89-SUM(M89:O89)) -> -6384 | Q89: 4275 | R89: =9596-Q89 -> 5321 | S89: -1987 | T89: =SUM(J89-SUM(Q89:S89)) -> -9297 | U89: 6555 | V89: =7727-U89 -> 1172 | W89: =6697-V89-U89 -> -1030 | X89: =SUM(K89-SUM(U89:W89)) -> -10485 | Y89: 3597 | Z89: =7266-Y89 -> 3669 | AA89: =5685-Z89-Y89 -> -1581 | AC89: =SUM(N89:Q89) -> 6386 | AD89: =SUM(O89:R89) -> 2231 | AE89: =SUM(P89:S89) -> 1225 | AF89: =SUM(Q89:T89) -> -1688 | AG89: =SUM(R89:U89) -> 592 | AH89: =SUM(S89:V89) -> -3557 | AI89: =SUM(T89:W89) -> -2600 | AJ89: =SUM(U89:X89) -> -3788 | ... AM89: =SUM(X89:AA89) -> -4800 | AO89: =SUM(AM89/AI89)-1 -> 0.84615385
B90: Inventory | C90: 217 | D90: -2723 | E90: 828 | F90: -289 | G90: -127 | H90: -2642 | I90: 1484 | J90: -1618 | K90: -1046 | M90: 681 | N90: =1065-M90 -> 384 | O90: =1049-SUM(M90:N90) -> -16 | P90: =SUM(I90-SUM(M90:O90)) -> 435 | Q90: -1807 | R90: =-2548-Q90 -> -741 | S90: -22 | T90: =SUM(J90-SUM(Q90:S90)) -> 952 | U90: -137 | V90: =53-U90 -> 190 | W90: =41-V90-U90 -> -12 | X90: =SUM(K90-SUM(U90:W90)) -> -1087 | Y90: 215 | Z90: =858-Y90 -> 643 | AA90: =1223-Z90-Y90 -> 365 | AC90: =SUM(N90:Q90) -> -1004 | AD90: =SUM(O90:R90) -> -2129 | AE90: =SUM(P90:S90) -> -2135 | AF90: =SUM(Q90:T90) -> -1618 | AG90: =SUM(R90:U90) -> 52 | AH90: =SUM(S90:V90) -> 983 | AI90: =SUM(T90:W90) -> 993 | AJ90: =SUM(U90:X90) -> -1046 | ... AM90: =SUM(X90:AA90) -> 136 | AO90: =SUM(AM90/AI90)-1 -> -0.86304129
B91: Other Current Assets | C91: 1039 | D91: -9572 | E91: -8433 | F91: 3804 | G91: -8035 | H91: -11945 | I91: -14019 | J91: -4413 | K91: -13087 | M91: =-9812-4921 -> -14733 | N91: =643-3542-M91 -> 11834 | O91: =4789-3289-SUM(M91:N91) -> 4399 | P91: =SUM(I91-SUM(M91:O91)) -> -15519 | Q91: =-4099+2320 -> -1779 | R91: =14785-4092-Q91 -> 12472 | S91: -2445 | T91: =SUM(J91-SUM(Q91:S91)) -> -12661 | U91: =4569-1457 -> 3112 | V91: =12161-4438-U91 -> 4611 | W91: =11100-5626-V91-U91 -> -2249 | X91: =SUM(K91-SUM(U91:W91)) -> -18561 | Y91: 4105 | Z91: =9171+-4371-Y91 -> 695 | AA91: =13555+-6116-Z91-Y91 -> 2639 | AC91: =SUM(N91:Q91) -> -1065 | AD91: =SUM(O91:R91) -> -427 | AE91: =SUM(P91:S91) -> -7271 | AF91: =SUM(Q91:T91) -> -4413 | AG91: =SUM(R91:U91) -> 478 | AH91: =SUM(S91:V91) -> -7383 | AI91: =SUM(T91:W91) -> -7187 | AJ91: =SUM(U91:X91) -> -13087 | ... AM91: =SUM(X91:AA91) -> -11122 | AO91: =SUM(AM91/AI91)-1 -> 0.54751635
B92: Accounts Payable | C92: 1791 | D92: 9618 | E92: 9175 | F92: -1923 | G92: -4062 | H92: 12326 | I92: 9448 | J92: -1889 | K92: 6020 | M92: 19813 | N92: =-1750-M92 -> -21563 | O92: =-6108-SUM(M92:N92) -> -4358 | P92: =SUM(I92-SUM(M92:O92)) -> 15556 | Q92: -6075 | R92: =-20764-Q92 -> -14689 | S92: 3974 | T92: =SUM(J92-SUM(Q92:S92)) -> 14901 | U92: -4542 | V92: =-16710-U92 -> -12168 | W92: =-15171-V92-U92 -> 1539 | X92: =SUM(K92-SUM(U92:W92)) -> 21191 | Y92: -6671 | Z92: =-14604-Y92 -> -7933 | AA92: =-18479-Z92-Y92 -> -3875 | AC92: =SUM(N92:Q92) -> -16440 | AD92: =SUM(O92:R92) -> -9566 | AE92: =SUM(P92:S92) -> -1234 | AF92: =SUM(Q92:T92) -> -1889 | AG92: =SUM(R92:U92) -> -356 | AH92: =SUM(S92:V92) -> 2165 | AI92: =SUM(T92:W92) -> -270 | AJ92: =SUM(U92:X92) -> 6020 | ... AM92: =SUM(X92:AA92) -> 2712 | AO92: =SUM(AM92/AI92)-1 -> -11.044444
B93: Deferred Revenue | C93: -1554 | D93: -626 | E93: -44 | F93: -625 | G93: 2081 | H93: 1676 | I93: 478 | J93: 0 | K93: 0 | M93: 462 | N93: =627-M93 -> 165 | O93: =260-SUM(M93:N93) -> -367 | P93: =SUM(I93-SUM(M93:O93)) -> 218 | Q93: 131 | R93: =0-Q93 -> -131 | S93: 0 | T93: =SUM(J93-SUM(Q93:S93)) -> 0 | U93: 0 | V93: 0 | W93: 0 | X93: =SUM(K93-SUM(U93:W93)) -> 0 | Y93: 0 | AA93: 0 | AC93: =SUM(N93:Q93) -> 147 | AD93: =SUM(O93:R93) -> -149 | AE93: =SUM(P93:S93) -> 218 | AF93: =SUM(Q93:T93) -> 0 | AG93: =SUM(R93:U93) -> -131 | AH93: =SUM(S93:V93) -> 0 | AI93: =SUM(T93:W93) -> 0 | AJ93: =SUM(U93:X93) -> 0 | ... AM93: =SUM(X93:AA93) -> 0 | AO93: =SUM(AM93/AI93)-1 -> #DIV/0!
B94: Other Asset and Other Liabilities | C94: -2104 | D94: -154 | E94: 38490 | F94: -4700 | G94: 8916 | H94: 5799 | I94: 5632 | J94: 3031 | K94: 15552 | M94: 4236 | N94: =1888-M94 -> -2348 | O94: =-14-SUM(M94:N94) -> -1902 | P94: =SUM(I94-SUM(M94:O94)) -> 5646 | Q94: 3758 | R94: =1757-Q94 -> -2001 | S94: 1229 | T94: =SUM(J94-SUM(Q94:S94)) -> 45 | U94: -3865 | V94: =-3437-U94 -> 428 | W94: =2-V94-U94 -> 3439 | X94: =SUM(K94-SUM(U94:W94)) -> 15550 | Y94: -11998 | Z94: =-15579-Y94 -> -3581 | AA94: =-15161-Z94-Y94 -> 418 | AC94: =SUM(N94:Q94) -> 5154 | AD94: =SUM(O94:R94) -> 5501 | AE94: =SUM(P94:S94) -> 8632 | AF94: =SUM(Q94:T94) -> 3031 | AG94: =SUM(R94:U94) -> -4592 | AH94: =SUM(S94:V94) -> -2163 | AI94: =SUM(T94:W94) -> 47 | AJ94: =SUM(U94:X94) -> 15552 | ... AM94: =SUM(X94:AA94) -> 389 | AO94: =SUM(AM94/AI94)-1 -> 7.2765957
B95: Net cash used in operating activities | C95: =SUM(C80:C94) -> 65824 | D95: =SUM(D80:D94) -> 63598 | E95: =SUM(E80:E94) -> 77434 | F95: =SUM(F80:F94) -> 69391 | G95: =SUM(G80:G94) -> 80674 | H95: =SUM(H80:H94) -> 104038 | I95: =SUM(I80:I94) -> 122151 | J95: =SUM(J80:J94) -> 110543 | K95: =SUM(K80:K94) -> 118254 | M95: =SUM(M80:M94) -> 46966 | N95: =SUM(N80:N94) -> 28166 | O95: =SUM(O80:O94) -> 22892 | P95: =SUM(P80:P94) -> 24127 | Q95: =SUM(Q80:Q94) -> 34005 | R95: =SUM(R80:R94) -> 28560 | S95: =SUM(S80:S94) -> 26380 | T95: =SUM(T80:T94) -> 21598 | ... AA95: =SUM(AA80:AA94) -> 27867 | AC95: =SUM(AC80:AC94) -> 109190 | AD95: =SUM(AD80:AD94) -> 109584 | AE95: =SUM(AE80:AE94) -> 113072 | AF95: =SUM(AF80:AF94) -> 110543 | AG95: =SUM(AG80:AG94) -> 116433 | AH95: =SUM(AH80:AH94) -> 110563 | AI95: =SUM(AI80:AI94) -> 113041 | AJ95: =SUM(AJ80:AJ94) -> 118254 | ... AM95: =SUM(AM80:AM94) -> 108565 | AO95: =SUM(AM95/AI95)-1 -> -0.039596253
B97: Cash flows from investing activities:
B98: Capital Expenditures | C98: -12734 | D98: -12451 | E98: -13313 | F98: -10495 | G98: -7309 | H98: -11085 | I98: -10708 | J98: -10959 | K98: -9447 | M98: -2803 | N98: =-5317-M98 -> -2514 | O98: =-7419-SUM(M98:N98) -> -2102 | P98: =SUM(I98-SUM(M98:O98)) -> -3289 | Q98: -3787 | R98: =-6703-Q98 -> -2916 | S98: -2093 | T98: =SUM(J98-SUM(Q98:S98)) -> -2163 | U98: -2392 | V98: =-4388-U98 -> -1996 | W98: =-6539-V98-U98 -> -2151 | X98: =SUM(K98-SUM(U98:W98)) -> -2908 | Y98: -2940 | Z98: =-6011-Y98 -> -3071 | AA98: =-9473-Z98-Y98 -> -3462 | AC98: =SUM(N98:Q98) -> -11692 | AD98: =SUM(O98:R98) -> -12094 | AE98: =SUM(P98:S98) -> -12085 | AF98: =SUM(Q98:T98) -> -10959 | AG98: =SUM(R98:U98) -> -9564 | AH98: =SUM(S98:V98) -> -8644 | AI98: =SUM(T98:W98) -> -8702 | AJ98: =SUM(U98:X98) -> -9447 | ... AM98: =SUM(X98:AA98) -> -12381 | AO98: =SUM(AM98/AI98)-1 -> 0.42277637
B99: Proceeds of investments | C99: 111794 | D99: 126339 | E99: 103719 | F99: 97090 | G99: 120391 | H99: 106483 | I99: 67363 | J99: 45514 | K99: 62346 | M99: =11309+10675 -> 21984 | N99: =18000+24668-M99 -> 20684 | O99: =24203+33609-SUM(M99:N99) -> 15144 | P99: =SUM(I99-SUM(M99:O99)) -> 9551 | Q99: =7127+509 -> 7636 | R99: =17124+1897-Q99 -> 11385 | S99: 12795 | T99: =SUM(J99-SUM(Q99:S99)) -> 13698 | U99: =13046+1337 -> 14383 | V99: =27462+4314-U99 -> 17393 | W99: =39838+7382-V99-U99 -> 15444 | X99: =SUM(K99-SUM(U99:W99)) -> 15126 | Y99: 19459 | Z99: =26587+5210-Y99 -> 12338 | AA99: =35036+10785-Z99-Y99 -> 14024 | AC99: =SUM(N99:Q99) -> 53015 | AD99: =SUM(O99:R99) -> 43716 | AE99: =SUM(P99:S99) -> 41367 | AF99: =SUM(Q99:T99) -> 45514 | AG99: =SUM(R99:U99) -> 52261 | AH99: =SUM(S99:V99) -> 58269 | AI99: =SUM(T99:W99) -> 60918 | AJ99: =SUM(U99:X99) -> 62346 | ... AM99: =SUM(X99:AA99) -> 60947 | AO99: =SUM(AM99/AI99)-1 -> 0.00047604977
B100: Purchase of Investments | C100: -142428 | D100: -159486 | E100: -71356 | F100: -39630 | G100: -114938 | H100: -109558 | I100: -76923 | J100: -29513 | K100: -48656 | M100: -34913 | N100: =-61987-M100 -> -27074 | O100: =-70178-SUM(M100:N100) -> -8191 | P100: =SUM(I100-SUM(M100:O100)) -> -6745 | Q100: -5153 | R100: =-11197-Q100 -> -6044 | S100: -9759 | T100: =SUM(J100-SUM(Q100:S100)) -> -8557 | U100: -9780 | V100: =-25042-U100 -> -15262 | W100: =-38074-V100-U100 -> -13032 | X100: =SUM(K100-SUM(U100:W100)) -> -10582 | Y100: -6124 | Z100: =-12442-Y100 -> -6318 | AA100: =-17591-Z100-Y100 -> -5149 | AC100: =SUM(N100:Q100) -> -47163 | AD100: =SUM(O100:R100) -> -26133 | AE100: =SUM(P100:S100) -> -27701 | AF100: =SUM(Q100:T100) -> -29513 | AG100: =SUM(R100:U100) -> -34140 | AH100: =SUM(S100:V100) -> -43358 | AI100: =SUM(T100:W100) -> -46631 | AJ100: =SUM(U100:X100) -> -48656 | ... AM100: =SUM(X100:AA100) -> -28173 | AO100: =SUM(AM100/AI100)-1 -> -0.3958311
B101: Acquisitions/intang assets | C101: -1111 | D101: -673 | E101: -721 | F101: -624 | G101: -1524 | H101: -33 | I101: -306 | J101: 0 | K101: 0 | M101: 0 | N101: -167 | O101: =-169-SUM(M101:N101) -> -2 | P101: =SUM(I101-SUM(M101:O101)) -> -137 | Q101: 0 | R101: 0 | S101: 0 | T101: =SUM(J101-SUM(Q101:S101)) -> 0 | U101: 0 | V101: 0 | W101: 0 | X101: =SUM(K101-SUM(U101:W101)) -> 0 | Y101: 0 | Z101: 0 | AA101: 0 | AC101: =SUM(N101:Q101) -> -306 | AD101: =SUM(O101:R101) -> -139 | AE101: =SUM(P101:S101) -> -137 | AF101: =SUM(Q101:T101) -> 0 | AG101: =SUM(R101:U101) -> 0 | AH101: =SUM(S101:V101) -> 0 | AI101: =SUM(T101:W101) -> 0 | AJ101: =SUM(U101:X101) -> 0 | ... AM101: =SUM(X101:AA101) -> 0 | AO101: =SUM(AM101/AI101)-1 -> #DIV/0!
B102: Other/Strategic investments | C102: -1498 | D102: -175 | E102: -2263 | F102: -445 | G102: -909 | H102: -352 | I102: -1780 | J102: -1337 | K102: -1308 | M102: -374 | N102: =-568-M102 -> -194 | O102: =-1183-SUM(M102:N102) -> -615 | P102: =SUM(I102-SUM(M102:O102)) -> -597 | Q102: -141 | R102: =-247-Q102 -> -106 | S102: -506 | T102: =SUM(J102-SUM(Q102:S102)) -> -584 | U102: -284 | V102: =-729-U102 -> -445 | W102: =-1117-V102-U102 -> -388 | X102: =SUM(K102-SUM(U102:W102)) -> -191 | Y102: -603 | Z102: =-635-Y102 -> -32 | AA102: =-975-Z102-Y102 -> -340 | AC102: =SUM(N102:Q102) -> -1547 | AD102: =SUM(O102:R102) -> -1459 | AE102: =SUM(P102:S102) -> -1350 | AF102: =SUM(Q102:T102) -> -1337 | AG102: =SUM(R102:U102) -> -1480 | AH102: =SUM(S102:V102) -> -1819 | AI102: =SUM(T102:W102) -> -1701 | AJ102: =SUM(U102:X102) -> -1308 | ... AM102: =SUM(X102:AA102) -> -1166 | AO102: =SUM(AM102/AI102)-1 -> -0.31452087
B103: Net cash used in investing activities | C103: =SUM(C98:C102) -> -45977 | D103: =SUM(D98:D102) -> -46446 | E103: =SUM(E98:E102) -> 16066 | F103: =SUM(F98:F102) -> 45896 | G103: =SUM(G98:G102) -> -4289 | H103: =SUM(H98:H102) -> -14545 | I103: =SUM(I98:I102) -> -22354 | J103: =SUM(J98:J102) -> 3705 | K103: =SUM(K98:K102) -> 2935 | M103: =SUM(M98:M102) -> -16106 | N103: =SUM(N98:N102) -> -9265 | O103: =SUM(O98:O102) -> 4234 | P103: =SUM(P98:P102) -> -1217 | Q103: =SUM(Q98:Q102) -> -1445 | R103: =SUM(R98:R102) -> 2319 | S103: =SUM(S98:S102) -> 437 | T103: =SUM(T98:T102) -> 2394 | ... AA103: =SUM(AA98:AA102) -> 5073 | AC103: =SUM(AC98:AC102) -> -7693 | AD103: =SUM(AD98:AD102) -> 3891 | AE103: =SUM(AE98:AE102) -> 94 | AF103: =SUM(AF98:AF102) -> 3705 | AG103: =SUM(AG98:AG102) -> 7077 | AH103: =SUM(AH98:AH102) -> 4448 | AI103: =SUM(AI98:AI102) -> 3884 | AJ103: =SUM(AJ98:AJ102) -> 2935 | ... AM103: =SUM(AM98:AM102) -> 19227 | AO103: =SUM(AM103/AI103)-1 -> 3.950309
B105: Cash flows from financing activities:
B106: Proceeds from the issuance of term debt, net | C106: 22454 | D106: 28662 | E106: 6969 | F106: 6963 | G106: 16091 | H106: 20393 | I106: 5465 | J106: 5228 | K106: 0 | M106: 0 | N106: 0 | O106: 0 | P106: =SUM(I106-SUM(M106:O106)) -> 5465 | Q106: 0 | R106: 0 | S106: 5228 | T106: =SUM(J106-SUM(Q106:S106)) -> 0 | U106: 0 | V106: 0 | W106: 0 | X106: =SUM(K106-SUM(U106:W106)) -> 0 | Y106: 0 | Z106: 0 | AA106: =4481-Z106-Y106 -> 4481 | AC106: =SUM(N106:Q106) -> 5465 | AD106: =SUM(O106:R106) -> 5465 | AE106: =SUM(P106:S106) -> 10693 | AF106: =SUM(Q106:T106) -> 5228 | AG106: =SUM(R106:U106) -> 5228 | AH106: =SUM(S106:V106) -> 5228 | AI106: =SUM(T106:W106) -> 0 | AJ106: =SUM(U106:X106) -> 0 | ... AM106: =SUM(X106:AA106) -> 4481 | AO106: =SUM(AM106/AI106)-1 -> #DIV/0!
B107: Repayments of term debt | C107: 0 | D107: -3500 | E107: -6500 | F107: -8805 | G107: -12629 | H107: -8750 | I107: -9543 | J107: -11151.108 | K107: -9958 | M107: 0 | N107: -3750 | O107: -3000 | P107: =SUM(I107-SUM(M107:O107)) -> -2793 | Q107: -1401 | R107: -2250 | S107: -7500 | T107: =SUM(J107-SUM(Q107:S107)) -> -0.108 | U107: 0 | V107: -3150 | W107: -4250 | X107: =SUM(K107-SUM(U107:W107)) -> -2558 | Y107: -1009 | Z107: =-4009-Y107 -> -3000 | AA107: =-9682-Z107-Y107 -> -5673 | AC107: =SUM(N107:Q107) -> -10944 | AD107: =SUM(O107:R107) -> -9444 | AE107: =SUM(P107:S107) -> -13944 | AF107: =SUM(Q107:T107) -> -11151.108 | AG107: =SUM(R107:U107) -> -9750.108 | AH107: =SUM(S107:V107) -> -10650.108 | AI107: =SUM(T107:W107) -> -7400.108 | AJ107: =SUM(U107:X107) -> -9958 | ... AM107: =SUM(X107:AA107) -> -12240 | AO107: =SUM(AM107/AI107)-1 -> 0.65402991
B108: Issuance of Common | C108: 495 | D108: 555 | E108: 669 | F108: 781 | G108: 880 | H108: 1105 | I108: 0 | J108: 0 | K108: 0 | M108: 0 | N108: 0 | O108: 0 | P108: =SUM(I108-SUM(M108:O108)) -> 0 | Q108: 0 | R108: 0 | S108: 0 | T108: =SUM(J108-SUM(Q108:S108)) -> 0 | U108: 0 | V108: 0 | W108: 0 | X108: =SUM(K108-SUM(U108:W108)) -> 0 | Y108: 0 | Z108: 0 | AA108: 0 | AC108: =SUM(N108:Q108) -> 0 | AD108: =SUM(O108:R108) -> 0 | AE108: =SUM(P108:S108) -> 0 | AF108: =SUM(Q108:T108) -> 0 | AG108: =SUM(R108:U108) -> 0 | AH108: =SUM(S108:V108) -> 0 | AI108: =SUM(T108:W108) -> 0 | AJ108: =SUM(U108:X108) -> 0 | ... AM108: =SUM(X108:AA108) -> 0 | AO108: =SUM(AM108/AI108)-1 -> #DIV/0!
B109: Treasury Stock | C109: -29722 | D109: -32900 | E109: -72738 | F109: -66897 | G109: -72358 | H109: -85971 | I109: -89402 | J109: -77550 | K109: -94949 | M109: -20478 | N109: =-43109-M109 -> -22631 | O109: =-64974-SUM(M109:N109) -> -21865 | P109: =SUM(I109-SUM(M109:O109)) -> -24428 | Q109: -19475 | R109: =-39069-Q109 -> -19594 | S109: -17478 | T109: =SUM(J109-SUM(Q109:S109)) -> -21003 | U109: -20139 | V109: =-43344-U109 -> -23205 | W109: =-69866-V109-U109 -> -26522 | X109: =SUM(K109-SUM(U109:W109)) -> -25083 | Y109: -23606 | Z109: =-49504-Y109 -> -25898 | AA109: =-70579-Z109-Y109 -> -21075 | AC109: =SUM(N109:Q109) -> -88399 | AD109: =SUM(O109:R109) -> -85362 | AE109: =SUM(P109:S109) -> -80975 | AF109: =SUM(Q109:T109) -> -77550 | AG109: =SUM(R109:U109) -> -78214 | AH109: =SUM(S109:V109) -> -81825 | AI109: =SUM(T109:W109) -> -90869 | AJ109: =SUM(U109:X109) -> -94949 | ... AM109: =SUM(X109:AA109) -> -95662 | AO109: =SUM(AM109/AI109)-1 -> 0.052746261
B110: Change in commercial paper, net | C110: -397 | D110: 3852 | E110: -37 | F110: -5977 | G110: -963 | H110: 1022 | I110: 3955 | J110: -3978 | K110: 3960 | M110: -1000 | N110: =999-M110 -> 1999 | O110: =4970-SUM(M110:N110) -> 3971 | P110: =SUM(I110-SUM(M110:O110)) -> -1015 | Q110: -8214 | R110: =-7960-Q110 -> 254 | S110: 1989 | T110: =SUM(J110-SUM(Q110:S110)) -> 1993 | U110: -3984 | V110: =-3982-U110 -> 2 | W110: =-2985-V110-U110 -> 997 | X110: =SUM(K110-SUM(U110:W110)) -> 6945 | Y110: -7944 | Z110: =-3968-Y110 -> 3976 | AA110: =-65-Z110-Y110 -> 3903 | AC110: =SUM(N110:Q110) -> -3259 | AD110: =SUM(O110:R110) -> -5004 | AE110: =SUM(P110:S110) -> -6986 | AF110: =SUM(Q110:T110) -> -3978 | AG110: =SUM(R110:U110) -> 252 | AH110: =SUM(S110:V110) -> 0 | AI110: =SUM(T110:W110) -> -992 | AJ110: =SUM(U110:X110) -> 3960 | ... AM110: =SUM(X110:AA110) -> 6880 | AO110: =SUM(AM110/AI110)-1 -> -7.9354839
B111: Preferred Stock | C111: 0 | D111: 0 | E111: 0 | F111: 0 | G111: 0 | H111: 0 | I111: 0 | J111: 0 | K111: 0 | M111: 0 | N111: 0 | O111: 0 | P111: =SUM(I111-SUM(M111:O111)) -> 0 | Q111: 0 | R111: 0 | S111: 0 | T111: =SUM(J111-SUM(Q111:S111)) -> 0 | U111: 0 | V111: 0 | W111: 0 | X111: =SUM(K111-SUM(U111:W111)) -> 0 | Y111: 0 | Z111: 0 | AA111: 0 | AC111: =SUM(N111:Q111) -> 0 | AD111: =SUM(O111:R111) -> 0 | AE111: =SUM(P111:S111) -> 0 | AF111: =SUM(Q111:T111) -> 0 | AG111: =SUM(R111:U111) -> 0 | AH111: =SUM(S111:V111) -> 0 | AI111: =SUM(T111:W111) -> 0 | AJ111: =SUM(U111:X111) -> 0 | ... AM111: =SUM(X111:AA111) -> 0 | AO111: =SUM(AM111/AI111)-1 -> #DIV/0!
B112: Other | C112: -1163 | D112: -1247 | E112: -2527 | F112: -2922 | G112: -3760 | H112: -6685 | I112: -6383 | J112: -6012 | K112: -5802 | M112: =-2888-61 -> -2949 | N112: =-3218-105-M112 -> -374 | O112: =-148-5915-SUM(M112:N112) -> -2740 | P112: =SUM(I112-SUM(M112:O112)) -> -320 | Q112: =-2316-389 -> -2705 | R112: =-2734-455-Q112 -> -484 | S112: -2438 | T112: =SUM(J112-SUM(Q112:S112)) -> -385 | U112: =-2591-46 -> -2637 | V112: =-2875-U112-132 -> -370 | W112: =-5163-191-V112-U112 -> -2347 | X112: =SUM(K112-SUM(U112:W112)) -> -448 | Y112: =-2921-35 -> -2956 | Z112: =-3205+-77-Y112 -> -326 | AA112: =-5719+-87-Z112-Y112 -> -2524 | AC112: =SUM(N112:Q112) -> -6139 | AD112: =SUM(O112:R112) -> -6249 | AE112: =SUM(P112:S112) -> -5947 | AF112: =SUM(Q112:T112) -> -6012 | AG112: =SUM(R112:U112) -> -5944 | AH112: =SUM(S112:V112) -> -5830 | AI112: =SUM(T112:W112) -> -5739 | AJ112: =SUM(U112:X112) -> -5802 | ... AM112: =SUM(X112:AA112) -> -6254 | AO112: =SUM(AM112/AI112)-1 -> 0.089736888
B113: Dividends | C113: -12150 | D113: -12769 | E113: -13712 | F113: -14119 | G113: -14081 | H113: -14467 | I113: -14841 | J113: -14875 | K113: -15234 | M113: -3732 | N113: =-7327-M113 -> -3595 | O113: =-11138-SUM(M113:N113) -> -3811 | P113: =SUM(I113-SUM(M113:O113)) -> -3703 | Q113: -3768 | R113: =-7418-Q113 -> -3650 | S113: -3849 | T113: =SUM(J113-SUM(Q113:S113)) -> -3608 | U113: -3825 | V113: =-7535-U113 -> -3710 | W113: =-11430-V113-U113 -> -3895 | X113: =SUM(K113-SUM(U113:W113)) -> -3804 | Y113: -3856 | Z113: =-7614-Y113 -> -3758 | AA113: =-11559-Z113-Y113 -> -3945 | AC113: =SUM(N113:Q113) -> -14877 | AD113: =SUM(O113:R113) -> -14932 | AE113: =SUM(P113:S113) -> -14970 | AF113: =SUM(Q113:T113) -> -14875 | AG113: =SUM(R113:U113) -> -14932 | AH113: =SUM(S113:V113) -> -14992 | AI113: =SUM(T113:W113) -> -15038 | AJ113: =SUM(U113:X113) -> -15234 | ... AM113: =SUM(X113:AA113) -> -15363 | AO113: =SUM(AM113/AI113)-1 -> 0.021611916
B114: Net cash provided by financing activities | C114: =SUM(C106:C113) -> -20483 | D114: =SUM(D106:D113) -> -17347 | E114: =SUM(E106:E113) -> -87876 | F114: =SUM(F106:F113) -> -90976 | G114: =SUM(G106:G113) -> -86820 | H114: =SUM(H106:H113) -> -93353 | I114: =SUM(I106:I113) -> -110749 | J114: =SUM(J106:J113) -> -108338.11 | K114: =SUM(K106:K113) -> -121983 | M114: =SUM(M106:M113) -> -28159 | N114: =SUM(N106:N113) -> -28351 | O114: =SUM(O106:O113) -> -27445 | P114: =SUM(P106:P113) -> -26794 | Q114: =SUM(Q106:Q113) -> -35563 | R114: =SUM(R106:R113) -> -25724 | S114: =SUM(S106:S113) -> -24048 | T114: =SUM(T106:T113) -> -23003.108 | ... AA114: =SUM(AA106:AA113) -> -24833 | AC114: =SUM(AC106:AC113) -> -118153 | AD114: =SUM(AD106:AD113) -> -115526 | AE114: =SUM(AE106:AE113) -> -112129 | AF114: =SUM(AF106:AF113) -> -108338.11 | AG114: =SUM(AG106:AG113) -> -103360.11 | AH114: =SUM(AH106:AH113) -> -108069.11 | AI114: =SUM(AI106:AI113) -> -120038.11 | AJ114: =SUM(AJ106:AJ113) -> -121983 | ... AM114: =SUM(AM106:AM113) -> -118158 | AO114: =SUM(AM114/AI114)-1 -> -0.015662593
B117: Cash BOP | C117: 48844 | D117: 48844 | E117: 48844 | F117: 48844 | G117: 48844 | H117: =G123 -> 38016 | I117: =H123 -> 34940 | J117: =I123 -> 23646 | K117: =J123 -> 29965 | M117: =H123 -> 34940 | N117: =M123 -> 37119 | O117: =N123 -> 28098 | P117: =O123 -> 27502 | Q117: =P123 -> 23646 | R117: =Q123 -> 20535 | S117: =R123 -> 24687 | T117: =S123 -> 28408 | U117: =T123 -> 29965 | ... AA117: =Z123 -> 28162 | AC117: =M123 -> 37119 | AD117: =N123 -> 28098 | AE117: =O123 -> 27502 | AF117: =P123 -> 23646 | AG117: =Q123 -> 20535 | AH117: =R123 -> 24687 | AI117: =S123 -> 28408 | AJ117: =T123 -> 29965 | ... AM117: =W123 -> 25565
B118: BOP Restricted Cash Adjustments | F118: =23+1357 -> 1380 | G118: =23+1357 -> 1380 | H118: =-G121 -> 1773 | I118: =-H121 -> 989 | J118: =-I121 -> 1331 | K118: =-J121 -> 921.892 | M118: =-H121 -> 989 | N118: =-M121 -> 1511 | O118: =-N121 -> 1082 | P118: =-O121 -> 1359 | Q118: =-P121 -> 1331 | R118: =-Q121 -> 1439 | S118: =-R121 -> 2442 | T118: =-S121 -> 1490 | U118: =-T121 -> 921.892 | ... AA118: =-Z121 -> 149.892 | AC118: =-M121 -> 1511 | AD118: =-N121 -> 1082 | AE118: =-O121 -> 1359 | AF118: =-P121 -> 1331 | AG118: =-Q121 -> 1439 | AH118: =-R121 -> 2442 | AI118: =-S121 -> 1490 | AJ118: =-T121 -> 921.892 | ... AM118: =-W121 -> 1219.892
B119: Adjusted Cash Position BOP | C119: =SUM(C117:C118) -> 48844 | D119: =SUM(D117:D118) -> 48844 | E119: =SUM(E117:E118) -> 48844 | F119: =SUM(F117:F118) -> 50224 | G119: =SUM(G117:G118) -> 50224 | H119: =SUM(H117:H118) -> 39789 | I119: =SUM(I117:I118) -> 35929 | J119: =SUM(J117:J118) -> 24977 | K119: =SUM(K117:K118) -> 30886.892 | M119: =SUM(M117:M118) -> 35929 | N119: =SUM(N117:N118) -> 38630 | O119: =SUM(O117:O118) -> 29180 | P119: =SUM(P117:P118) -> 28861 | Q119: =SUM(Q117:Q118) -> 24977 | R119: =SUM(R117:R118) -> 21974 | S119: =SUM(S117:S118) -> 27129 | T119: =SUM(T117:T118) -> 29898 | ... AA119: =SUM(AA117:AA118) -> 28311.892 | AC119: =SUM(AC117:AC118) -> 38630 | AD119: =SUM(AD117:AD118) -> 29180 | AE119: =SUM(AE117:AE118) -> 28861 | AF119: =SUM(AF117:AF118) -> 24977 | AG119: =SUM(AG117:AG118) -> 21974 | AH119: =SUM(AH117:AH118) -> 27129 | AI119: =SUM(AI117:AI118) -> 29898 | AJ119: =SUM(AJ117:AJ118) -> 30886.892 | ... AM119: =SUM(AM117:AM118) -> 26784.892
B121: EOP Restricted Cash Adjustments | G121: =-(1737+36) -> -1773 | H121: -989 | I121: -1331 | J121: -921.892 | K121: -149.892 | M121: -1511 | N121: -1082 | O121: -1359 | P121: -1331 | Q121: -1439 | R121: -2442 | S121: -1490 | T121: -921.892 | U121: -1363.892 | V121: -1375.892 | W121: -1219.892 | X121: -149.892 | Y121: -149.892 | Z121: -149.892 | AA121: -149.892 | AC121: =Q121 -> -1439 | AD121: =R121 -> -2442 | AE121: =S121 -> -1490 | AF121: =T121 -> -921.892 | AG121: =U121 -> -1363.892 | AH121: =V121 -> -1375.892 | AI121: =W121 -> -1219.892 | AJ121: =X121 -> -149.892 | ... AM121: =AA121 -> -149.892
B122: Net Change in Cash | C122: =+C114+C103+C95 -> -636 | D122: =+D114+D103+D95 -> -195 | E122: =+E114+E103+E95 -> 5624 | F122: =+F114+F103+F95 -> 24311 | G122: =+G114+G103+G95 -> -10435 | H122: =+H114+H103+H95 -> -3860 | I122: =+I114+I103+I95 -> -10952 | J122: =+J114+J103+J95 -> 5909.892 | K122: =+K114+K103+K95 -> -794 | M122: =+M114+M103+M95 -> 2701 | N122: =+N114+N103+N95 -> -9450 | O122: =+O114+O103+O95 -> -319 | P122: =+P114+P103+P95 -> -3884 | Q122: =+Q114+Q103+Q95 -> -3003 | R122: =+R114+R103+R95 -> 5155 | S122: =+S114+S103+S95 -> 2769 | T122: =+T114+T103+T95 -> 988.892 | ... AA122: =+AA114+AA103+AA95 -> 8107 | AC122: =+AC114+AC103+AC95 -> -16656 | AD122: =+AD114+AD103+AD95 -> -2051 | AE122: =+AE114+AE103+AE95 -> 1037 | AF122: =+AF114+AF103+AF95 -> 5909.892 | AG122: =+AG114+AG103+AG95 -> 20149.892 | AH122: =+AH114+AH103+AH95 -> 6941.892 | AI122: =+AI114+AI103+AI95 -> -3113.108 | AJ122: =+AJ114+AJ103+AJ95 -> -794 | ... AM122: =+AM114+AM103+AM95 -> 9634
B123: Adjusted Cash Position EOP | C123: =SUM(C119:C122) -> 48208 | D123: =SUM(D119:D122) -> 48649 | E123: =SUM(E119:E122) -> 54468 | F123: =SUM(F119:F122) -> 74535 | G123: =SUM(G119:G122) -> 38016 | H123: =SUM(H119:H122) -> 34940 | I123: =SUM(I119:I122) -> 23646 | J123: =SUM(J119:J122) -> 29965 | K123: =SUM(K119:K122) -> 29943 | M123: =SUM(M119:M122) -> 37119 | N123: =SUM(N119:N122) -> 28098 | O123: =SUM(O119:O122) -> 27502 | P123: =SUM(P119:P122) -> 23646 | Q123: =SUM(Q119:Q122) -> 20535 | R123: =SUM(R119:R122) -> 24687 | S123: =SUM(S119:S122) -> 28408 | T123: =SUM(T119:T122) -> 29965 | ... AA123: =SUM(AA119:AA122) -> 36269 | AC123: =SUM(AC119:AC122) -> 20535 | AD123: =SUM(AD119:AD122) -> 24687 | AE123: =SUM(AE119:AE122) -> 28408 | AF123: =SUM(AF119:AF122) -> 29965 | AG123: =SUM(AG119:AG122) -> 40760 | AH123: =SUM(AH119:AH122) -> 32695 | AI123: =SUM(AI119:AI122) -> 25565 | AJ123: =SUM(AJ119:AJ122) -> 29943 | ... AM123: =SUM(AM119:AM122) -> 36269
B125: Balance Check | C125: =C123-C43 -> 27724 | D125: =D123-D43 -> 28360 | E125: =E123-E43 -> 28555 | F125: =F123-F43 -> 25691 | G125: =G123-G43 -> 0 | H125: =H123-H43 -> 0 | I125: =I123-I43 -> 0 | J125: =J123-J43 -> 0 | K125: =K123-K43 -> 0 | M125: =M123-M43 -> 0 | N125: =N123-N43 -> 0 | O125: =O123-O43 -> 0 | P125: =P123-P43 -> 0 | Q125: =Q123-Q43 -> 0 | R125: =R123-R43 -> 0 | S125: =S123-S43 -> 0 | T125: =T123-T43 -> 0 | ... AA125: =AA123-AA43 -> 0 | AC125: =AC123-AC43 -> 0 | AD125: =AD123-AD43 -> 0 | AE125: =AE123-AE43 -> 0 | AF125: =AF123-AF43 -> 0 | AG125: =AG123-AG43 -> 0 | AH125: =AH123-AH43 -> 0 | AI125: =AI123-AI43 -> 0 | AJ125: =AJ123-AJ43 -> 0 | ... AM125: =AM123-AM43 -> 0
B127: Cash paid during the period for:
B128: Cash paid for income taxes, net | D128: 11591 | E128: 10417 | F128: 15263 | G128: 9501 | H128: 25385 | I128: 19573 | J128: 18679 | K128: 26102 | M128: 5235 | N128: =9301-M128 -> 4066 | O128: =12251-N128-M128 -> 2950 | P128: =SUM(I128-SUM(M128:O128)) -> 7322 | Q128: 828 | R128: =4894-Q128 -> 4066 | S128: =7020-R128-Q128 -> 2126 | T128: =SUM(J128-SUM(Q128:S128)) -> 11659 | U128: 7255 | V128: =14531-U128 -> 7276 | W128: =19230-V128-U128 -> 4699 | X128: =SUM(K128-SUM(U128:W128)) -> 6872 | Y128: 18651 | Z128: =31683-Y128 -> 13032 | AA128: =37332-Z128-Y128 -> 5649 | AC128: =SUM(N128:Q128) -> 15166 | AD128: =SUM(O128:R128) -> 15166 | AE128: =SUM(P128:S128) -> 14342 | AF128: =SUM(Q128:T128) -> 18679 | AG128: =SUM(R128:U128) -> 25106 | AH128: =SUM(S128:V128) -> 28316 | AI128: =SUM(T128:W128) -> 30889 | AJ128: =SUM(U128:X128) -> 26102 | ... AM128: =SUM(X128:AA128) -> 44204
B129: Cash paid for interest | D129: 2092 | E129: 3022 | F129: 3423 | G129: 3002 | H129: 2687 | I129: 2865 | J129: 3803 | K129: 0 | M129: 531 | N129: =1406-M129 -> 875 | O129: =1910-N129-M129 -> 504 | P129: =SUM(I129-SUM(M129:O129)) -> 955 | Q129: 703 | R129: =1873-Q129 -> 1170 | S129: =2590-R129-Q129 -> 717 | T129: =SUM(J129-SUM(Q129:S129)) -> 1213 | U129: 0 | V129: 0 | W129: 0 | X129: =SUM(K129-SUM(U129:W129)) -> 0 | Y129: 0 | Z129: 0 | AA129: 0 | AC129: =SUM(N129:Q129) -> 3037 | AD129: =SUM(O129:R129) -> 3332 | AE129: =SUM(P129:S129) -> 3545 | AF129: =SUM(Q129:T129) -> 3803 | AG129: =SUM(R129:U129) -> 3100 | AH129: =SUM(S129:V129) -> 1930 | AI129: =SUM(T129:W129) -> 1213 | AJ129: =SUM(U129:X129) -> 0 | ... AM129: =SUM(X129:AA129) -> 0
B131: 1) Includes $50MM cash recorded within other current assets on the Consolidated Condensed Balance Sheets relating to Altera cash held for sale.

Sheet Revenue Drivers
B2: Apple Inc. (NASDAQ: AAPL) | C2: FYE | M2: Quarterly | U2: Quarterly | V2: Quarterly | AC2: LTM | AG2: LTM | AO2: Variance
B3: Segment Anaysis | C3: ='Historical Financials'!C11 -> 2016 | D3: ='Historical Financials'!D11 -> 2017 | E3: ='Historical Financials'!E11 -> 2018 | F3: ='Historical Financials'!F11 -> 2019 | G3: ='Historical Financials'!G11 -> 2020 | H3: ='Historical Financials'!H11 -> 2021 | I3: ='Historical Financials'!I11 -> 2022 | J3: ='Historical Financials'!J11 -> 2023 | K3: ='Historical Financials'!K11 -> 2024 | M3: 1Q22 | N3: 2Q22 | O3: 3Q22 | P3: 4Q22 | Q3: 1Q23 | R3: 2Q23 | S3: 3Q23 | T3: 4Q23 | U3: 1Q24 | V3: 2Q24 | W3: 3Q24 | X3: 4Q24 | Y3: 1Q25 | Z3: 2Q25 | AA3: 3Q25 | AC3: 1Q23 | AD3: 2Q23 | AE3: 3Q23 | AF3: 4Q23 | AG3: 1Q24 | AH3: 2Q24 | AI3: 3Q24 | AJ3: 4Q24 | AK3: 1Q25 | AL3: 2Q25 | AM3: 3Q25
B4: $ mm except per share | C4: ='Historical Financials'!C12 -> 42643 | D4: ='Historical Financials'!D12 -> 43008 | E4: ='Historical Financials'!E12 -> 43372 | F4: ='Historical Financials'!F12 -> 43737 | G4: ='Historical Financials'!G12 -> 44104 | H4: ='Historical Financials'!H12 -> 44469 | I4: ='Historical Financials'!I12 -> 44834 | J4: ='Historical Financials'!J12 -> 45192 | K4: ='Historical Financials'!K12 -> 45559 | M4: 44560 | N4: 44650 | O4: 44742 | P4: 44834 | Q4: 44917 | R4: 45008 | S4: 45100 | T4: 45192 | U4: 45283 | V4: 45375 | W4: 45467 | X4: 45559 | Y4: 45650 | Z4: 45741 | AA4: 45833 | AC4: 44917 | AD4: 45008 | AE4: 45100 | AF4: 45192 | AG4: 45283 | AH4: 45375 | AI4: 45467 | AJ4: 45559 | AK4: 45650 | AL4: 45741 | AM4: 45833
A6: X | B6: Revenue by End Product
B7: iPhone Revenue | C7: 136700 | D7: 141319 | E7: 164888 | F7: 142381 | G7: 137781 | H7: 191973 | I7: 205489 | J7: 200583 | K7: 201183 | M7: 71628 | N7: 50570 | O7: 40665 | P7: 42626 | Q7: 65775 | R7: 51334 | S7: 39669 | T7: 43805 | U7: 69702 | V7: 45963 | W7: 39296 | X7: 46222 | Y7: 69138 | Z7: 46841 | AA7: 44582 | AC7: =SUM(N7:Q7) -> 199636 | AD7: =SUM(O7:R7) -> 200400 | AE7: =SUM(P7:S7) -> 199404 | AF7: =SUM(Q7:T7) -> 200583 | AG7: =SUM(R7:U7) -> 204510 | AH7: =SUM(S7:V7) -> 199139 | AI7: =SUM(T7:W7) -> 198766 | AJ7: =SUM(U7:X7) -> 201183 | ... AM7: =SUM(X7:AA7) -> 206783 | AO7: =SUM(AM7/AI7)-1 -> 0.04033386
B8: Mac Revenue | C8: 22831 | D8: 25850 | E8: 25198 | F8: 25740 | G8: 28622 | H8: 35190 | I8: 40177 | J8: 29357 | K8: 29984 | M8: 10852 | N8: 10435 | O8: 7382 | P8: 11508 | Q8: 7735 | R8: 7168 | S8: 6840 | T8: 7614 | U8: 7780 | V8: 7451 | W8: 7009 | X8: 7744 | Y8: 8987 | Z8: 7949 | AA8: 8046 | AC8: =SUM(N8:Q8) -> 37060 | AD8: =SUM(O8:R8) -> 33793 | AE8: =SUM(P8:S8) -> 33251 | AF8: =SUM(Q8:T8) -> 29357 | AG8: =SUM(R8:U8) -> 29402 | AH8: =SUM(S8:V8) -> 29685 | AI8: =SUM(T8:W8) -> 29854 | AJ8: =SUM(U8:X8) -> 29984 | ... AM8: =SUM(X8:AA8) -> 32726 | AO8: =SUM(AM8/AI8)-1 -> 0.096201514
B9: iPad Revenue | C9: 20628 | D9: 19222 | E9: 18380 | F9: 21280 | G9: 23724 | H9: 31862 | I9: 29292 | J9: 28300 | K9: 26694 | M9: 7248 | N9: 7646 | O9: 7224 | P9: 7174 | Q9: 9396 | R9: 6670 | S9: 5791 | T9: 6443 | U9: 7023 | V9: 5559 | W9: 7162 | X9: 6950 | Y9: 8088 | Z9: 6402 | AA9: 6581 | AC9: =SUM(N9:Q9) -> 31440 | AD9: =SUM(O9:R9) -> 30464 | AE9: =SUM(P9:S9) -> 29031 | AF9: =SUM(Q9:T9) -> 28300 | AG9: =SUM(R9:U9) -> 25927 | AH9: =SUM(S9:V9) -> 24816 | AI9: =SUM(T9:W9) -> 26187 | AJ9: =SUM(U9:X9) -> 26694 | ... AM9: =SUM(X9:AA9) -> 28021 | AO9: =SUM(AM9/AI9)-1 -> 0.07003475
B10: Services Revenue | C10: 24348 | D10: 29980 | E10: 39748 | F10: 46291 | G10: 53768 | H10: 68425 | I10: 78129 | J10: 85200 | K10: 96169 | M10: 19516 | N10: 19821 | O10: 19604 | P10: 19188 | Q10: 20766 | R10: 20907 | S10: 21213 | T10: 22314 | U10: 23117 | V10: 23867 | W10: 24213 | X10: 24972 | Y10: 26340 | Z10: 26645 | AA10: 27423 | AI10: =SUM(T10:W10) -> 93511 | AJ10: =SUM(U10:X10) -> 96169 | AK10: =SUM(V10:Y10) -> 99392 | AL10: =SUM(W10:Z10) -> 102170 | AM10: =SUM(X10:AA10) -> 105380
B11: Wearables, Home, and Accessories Revenue | C11: 11132 | D11: 12863 | E11: 17381 | F11: 24482 | G11: 30620 | H11: 38367 | I11: 41241 | J11: 39845 | K11: 37005 | M11: 14701 | N11: 8806 | O11: 8084 | P11: 9650 | Q11: 13482 | R11: 8757 | S11: 8284 | T11: 9322 | U11: 11953 | V11: 7913 | W11: 8097 | X11: 9042 | Y11: 11747 | Z11: 7522 | AA11: 7404 | AI11: =SUM(T11:W11) -> 37285 | AJ11: =SUM(U11:X11) -> 37005 | AK11: =SUM(V11:Y11) -> 36799 | AL11: =SUM(W11:Z11) -> 36408 | AM11: =SUM(X11:AA11) -> 35715
B12: Total Net Revenue | C12: =SUM(C7:C11) -> 215639 | D12: =SUM(D7:D11) -> 229234 | E12: =SUM(E7:E11) -> 265595 | F12: =SUM(F7:F11) -> 260174 | G12: =SUM(G7:G11) -> 274515 | H12: =SUM(H7:H11) -> 365817 | I12: =SUM(I7:I11) -> 394328 | J12: =SUM(J7:J11) -> 383285 | K12: =SUM(K7:K11) -> 391035 | M12: =SUM(M7:M11) -> 123945 | N12: =SUM(N7:N11) -> 97278 | O12: =SUM(O7:O11) -> 82959 | P12: =SUM(P7:P11) -> 90146 | Q12: =SUM(Q7:Q11) -> 117154 | R12: =SUM(R7:R11) -> 94836 | S12: =SUM(S7:S11) -> 81797 | T12: =SUM(T7:T11) -> 89498 | ... AA12: =SUM(AA7:AA11) -> 94036 | AC12: =SUM(AC7:AC9) -> 268136 | AD12: =SUM(AD7:AD9) -> 264657 | AE12: =SUM(AE7:AE9) -> 261686 | AF12: =SUM(AF7:AF9) -> 258240 | AG12: =SUM(AG7:AG9) -> 259839 | AH12: =SUM(AH7:AH9) -> 253640 | AI12: =SUM(AI7:AI11) -> 385603 | AJ12: =SUM(AJ7:AJ11) -> 391035 | AK12: =SUM(AK7:AK11) -> 395760 | AL12: =SUM(AL7:AL11) -> 400366 | AM12: =SUM(AM7:AM11) -> 408625 | AO12: =SUM(AM12/AI12)-1 -> 0.059703892
B13: Balance Check | C13: =C12-'Historical Financials'!C15 -> 0 | D13: =D12-'Historical Financials'!D15 -> 0 | E13: =E12-'Historical Financials'!E15 -> 0 | F13: =F12-'Historical Financials'!F15 -> 0 | G13: =G12-'Historical Financials'!G15 -> 0 | H13: =H12-'Historical Financials'!H15 -> 0 | I13: =I12-'Historical Financials'!I15 -> 0 | J13: =J12-'Historical Financials'!J15 -> 0 | K13: =K12-'Historical Financials'!K15 -> 0 | M13: =M12-'Historical Financials'!M15 -> 0 | N13: =N12-'Historical Financials'!N15 -> 0 | O13: =O12-'Historical Financials'!O15 -> 0 | P13: =P12-'Historical Financials'!P15 -> 0 | Q13: =Q12-'Historical Financials'!Q15 -> 0 | R13: =R12-'Historical Financials'!R15 -> 0 | S13: =S12-'Historical Financials'!S15 -> 0 | T13: =T12-'Historical Financials'!T15 -> 0 | ... AA13: =AA12-'Historical Financials'!AA15 -> 0 | AC13: =AC12-'Historical Financials'!AC15 -> -119401 | AD13: =AD12-'Historical Financials'!AD15 -> -120438 | AE13: =AE12-'Historical Financials'!AE15 -> -122247 | AF13: =AF12-'Historical Financials'!AF15 -> -125045 | AG13: =AG12-'Historical Financials'!AG15 -> -125867 | AH13: =AH12-'Historical Financials'!AH15 -> -127983 | AI13: =AI12-'Historical Financials'!AI15 -> 0 | AJ13: =AJ12-'Historical Financials'!AJ15 -> 0 | ... AM13: =AM12-'Historical Financials'!AM15 -> 0
A15: X | B15: Revenue by Product Offerings: Wearables, Home, and Accessories
B16: Accessories | G16: 16019.941 | H16: 20596.468 | I16: 21262.875 | J16: 19827.709 | K16: 18865.888 | M16: 5656.6733 | N16: 6070.4168 | O16: 4391.8204 | P16: 5143.9643 | Q16: 4250.8013 | R16: 5709.2465 | S16: 4595.9109 | T16: 5271.75 | U16: 4111.1639 | V16: 5174.0625 | W16: 4782.089 | X16: 4798.5722 | Y16: 3839.2947 | Z16: 4674.9385 | AA16: 4052.9944 | AC16: =SUM(N16:Q16) -> 19857.003 | AD16: =SUM(O16:R16) -> 19495.832 | AE16: =SUM(P16:S16) -> 19699.923 | AF16: =SUM(Q16:T16) -> 19827.709 | AG16: =SUM(R16:U16) -> 19688.071 | AH16: =SUM(S16:V16) -> 19152.887 | AI16: =SUM(T16:W16) -> 19339.065 | AJ16: =SUM(U16:X16) -> 18865.888 | ... AM16: =SUM(X16:AA16) -> 17365.8 | AO16: =SUM(AM16/AI16)-1 -> -0.10203521
B17: Apple Watch | G17: 14229.125 | H17: 17479.962 | I17: 19750.272 | J17: 19838.618 | K17: 17999.002 | M17: 8954.015 | N17: 2690.982 | O17: 3644.0381 | P17: 4461.2373 | Q17: 9160.4076 | R17: 3012.7635 | S17: 3650.3329 | T17: 4015.1136 | U17: 7786.3465 | V17: 2711.4871 | W17: 3285.2996 | X17: 4215.8692 | Y17: 7864.2099 | Z17: 2847.0615 | AA17: 3351.0056 | AC17: =SUM(N17:Q17) -> 19956.665 | AD17: =SUM(O17:R17) -> 20278.447 | AE17: =SUM(P17:S17) -> 20284.741 | AF17: =SUM(Q17:T17) -> 19838.618 | AG17: =SUM(R17:U17) -> 18464.556 | AH17: =SUM(S17:V17) -> 18163.28 | AI17: =SUM(T17:W17) -> 17798.247 | AJ17: =SUM(U17:X17) -> 17999.002 | ... AM17: =SUM(X17:AA17) -> 18278.146 | AO17: =SUM(AM17/AI17)-1 -> 0.026963301
B18: Total Intel Products Revenue | G18: =SUM(G16:G17) -> 30249.066 | H18: =SUM(H16:H17) -> 38076.431 | I18: =SUM(I16:I17) -> 41013.147 | J18: =SUM(J16:J17) -> 39666.326 | K18: =SUM(K16:K17) -> 36864.89 | M18: =SUM(M16:M17) -> 14610.688 | N18: =SUM(N16:N17) -> 8761.3988 | O18: =SUM(O16:O17) -> 8035.8585 | P18: =SUM(P16:P17) -> 9605.2016 | Q18: =SUM(Q16:Q17) -> 13411.209 | R18: =SUM(R16:R17) -> 8722.01 | S18: =SUM(S16:S17) -> 8246.2439 | T18: =SUM(T16:T17) -> 9286.8636 | ... AA18: =SUM(AA16:AA17) -> 7404 | AC18: =SUM(AC16:AC17) -> 39813.668 | AD18: =SUM(AD16:AD17) -> 39774.279 | AE18: =SUM(AE16:AE17) -> 39984.664 | AF18: =SUM(AF16:AF17) -> 39666.326 | AG18: =SUM(AG16:AG17) -> 38152.628 | AH18: =SUM(AH16:AH17) -> 37316.167 | AI18: =SUM(AI16:AI17) -> 37137.312 | AJ18: =SUM(AJ16:AJ17) -> 36864.89 | ... AM18: =SUM(AM16:AM17) -> 35643.946 | AO18: =SUM(AM18/AI18)-1 -> -0.040212015
B19: Balance Check | G19: =G11-G18 -> 370.93376 | H19: =H11-H18 -> 290.56925 | I19: =I11-I18 -> 227.85276 | J19: =J11-J18 -> 178.67374 | K19: =K11-K18 -> 140.10996 | M19: =M11-M18 -> 90.311719 | N19: =N11-N18 -> 44.601177 | O19: =O11-O18 -> 48.141511 | P19: =P11-P18 -> 44.798357 | Q19: =Q11-Q18 -> 70.79113 | R19: =R11-R18 -> 34.990036 | S19: =S11-S18 -> 37.756146 | T19: =T11-T18 -> 35.136432 | ... AA19: =AA11-AA18 -> 0 | AC19: =AC7-AC18 -> 159822.33 | AD19: =AD7-AD18 -> 160625.72 | AE19: =AE7-AE18 -> 159419.34 | AF19: =AF7-AF18 -> 160916.67 | AG19: =AG7-AG18 -> 166357.37 | AH19: =AH7-AH18 -> 161822.83 | AI19: =AI7-AI18 -> 161628.69 | AJ19: =AJ7-AJ18 -> 164318.11 | ... AM19: =AM7-AM18 -> 171139.05

Sheet FCF
B2: Apple Inc. (NASDAQ: AAPL) | C2: FYE | I2: Quarterly | Q2: Quarterly | S2: Quarterly | Y2: LTM | AC2: LTM | AF2: LTM | AL2: Variance
B3: FCF Analysis | C3: 2020 | D3: 2021 | E3: 2022 | F3: 2023 | G3: 2024 | I3: 1Q22 | J3: 2Q22 | K3: 3Q22 | L3: 4Q22 | M3: 1Q23 | N3: 2Q23 | O3: 3Q23 | P3: 4Q23 | Q3: 1Q24 | R3: 2Q24 | S3: 3Q24 | T3: 4Q24 | U3: 1Q25 | V3: 2Q25 | W3: 3Q25 | Y3: 4Q22 | Z3: 1Q23 | AA3: 2Q23 | AB3: 3Q23 | AC3: 4Q23 | AD3: 1Q24 | AE3: 2Q24 | AF3: 3Q24 | AG3: 4Q24 | AH3: 1Q25 | AI3: 2Q25 | AJ3: 3Q25
B4: $ mm except per share | C4: 44104 | D4: 44469 | E4: 44834 | F4: 45192 | G4: 45559 | I4: 44560 | J4: 44650 | K4: 44742 | L4: 44834 | M4: 44917 | N4: 45008 | O4: 45100 | P4: 45192 | Q4: 45283 | R4: 45375 | S4: 45467 | T4: 45559 | U4: 45650 | V4: 45741 | W4: 45833 | Y4: 44834 | Z4: 44917 | AA4: 45008 | AB4: 45100 | AC4: 45192 | AD4: 45283 | AE4: 45375 | AF4: 45467 | AG4: 45559 | AH4: 45650 | AI4: 45741 | AJ4: 45833
B6: ='Revenue Drivers'!B7 -> iPhone Revenue | C6: ='Revenue Drivers'!G7 -> 137781 | D6: ='Revenue Drivers'!H7 -> 191973 | E6: ='Revenue Drivers'!I7 -> 205489 | F6: ='Revenue Drivers'!J7 -> 200583 | G6: ='Revenue Drivers'!K7 -> 201183 | I6: ='Revenue Drivers'!M7 -> 71628 | J6: ='Revenue Drivers'!N7 -> 50570 | K6: ='Revenue Drivers'!O7 -> 40665 | L6: ='Revenue Drivers'!P7 -> 42626 | M6: ='Revenue Drivers'!Q7 -> 65775 | N6: ='Revenue Drivers'!R7 -> 51334 | O6: ='Revenue Drivers'!S7 -> 39669 | P6: ='Revenue Drivers'!T7 -> 43805 | ... W6: ='Revenue Drivers'!AA7 -> 44582 | Y6: =SUM(I6:L6) -> 205489 | Z6: =SUM(J6:M6) -> 199636 | AA6: =SUM(K6:N6) -> 200400 | AB6: =SUM(L6:O6) -> 199404 | AC6: =SUM(M6:P6) -> 200583 | AD6: =SUM(N6:Q6) -> 204510 | AE6: =SUM(O6:R6) -> 199139 | AF6: =SUM(P6:S6) -> 198766 | ... AJ6: =SUM(T6:W6) -> 206783 | AL6: =SUM(AJ6/AF6)-1 -> 0.04033386
B7: ='Revenue Drivers'!B8 -> Mac Revenue | C7: ='Revenue Drivers'!G8 -> 28622 | D7: ='Revenue Drivers'!H8 -> 35190 | E7: ='Revenue Drivers'!I8 -> 40177 | F7: ='Revenue Drivers'!J8 -> 29357 | G7: ='Revenue Drivers'!K8 -> 29984 | I7: ='Revenue Drivers'!M8 -> 10852 | J7: ='Revenue Drivers'!N8 -> 10435 | K7: ='Revenue Drivers'!O8 -> 7382 | L7: ='Revenue Drivers'!P8 -> 11508 | M7: ='Revenue Drivers'!Q8 -> 7735 | N7: ='Revenue Drivers'!R8 -> 7168 | O7: ='Revenue Drivers'!S8 -> 6840 | P7: ='Revenue Drivers'!T8 -> 7614 | ... W7: ='Revenue Drivers'!AA8 -> 8046 | Y7: =SUM(I7:L7) -> 40177 | Z7: =SUM(J7:M7) -> 37060 | AA7: =SUM(K7:N7) -> 33793 | AB7: =SUM(L7:O7) -> 33251 | AC7: =SUM(M7:P7) -> 29357 | AD7: =SUM(N7:Q7) -> 29402 | AE7: =SUM(O7:R7) -> 29685 | AF7: =SUM(P7:S7) -> 29854 | ... AJ7: =SUM(T7:W7) -> 32726 | AL7: =SUM(AJ7/AF7)-1 -> 0.096201514
B8: ='Revenue Drivers'!B9 -> iPad Revenue | C8: ='Revenue Drivers'!G9 -> 23724 | D8: ='Revenue Drivers'!H9 -> 31862 | E8: ='Revenue Drivers'!I9 -> 29292 | F8: ='Revenue Drivers'!J9 -> 28300 | G8: ='Revenue Drivers'!K9 -> 26694 | I8: ='Revenue Drivers'!M9 -> 7248 | J8: ='Revenue Drivers'!N9 -> 7646 | K8: ='Revenue Drivers'!O9 -> 7224 | L8: ='Revenue Drivers'!P9 -> 7174 | M8: ='Revenue Drivers'!Q9 -> 9396 | N8: ='Revenue Drivers'!R9 -> 6670 | O8: ='Revenue Drivers'!S9 -> 5791 | P8: ='Revenue Drivers'!T9 -> 6443 | ... W8: ='Revenue Drivers'!AA9 -> 6581 | Y8: =SUM(I8:L8) -> 29292 | Z8: =SUM(J8:M8) -> 31440 | AA8: =SUM(K8:N8) -> 30464 | AB8: =SUM(L8:O8) -> 29031 | AC8: =SUM(M8:P8) -> 28300 | AD8: =SUM(N8:Q8) -> 25927 | AE8: =SUM(O8:R8) -> 24816 | AF8: =SUM(P8:S8) -> 26187 | ... AJ8: =SUM(T8:W8) -> 28021 | AL8: =SUM(AJ8/AF8)-1 -> 0.07003475
B9: ='Revenue Drivers'!B10 -> Services Revenue | C9: ='Revenue Drivers'!G10 -> 53768 | D9: ='Revenue Drivers'!H10 -> 68425 | E9: ='Revenue Drivers'!I10 -> 78129 | F9: ='Revenue Drivers'!J10 -> 85200 | G9: ='Revenue Drivers'!K10 -> 96169 | I9: ='Revenue Drivers'!M10 -> 19516 | J9: ='Revenue Drivers'!N10 -> 19821 | K9: ='Revenue Drivers'!O10 -> 19604 | L9: ='Revenue Drivers'!P10 -> 19188 | M9: ='Revenue Drivers'!Q10 -> 20766 | N9: ='Revenue Drivers'!R10 -> 20907 | O9: ='Revenue Drivers'!S10 -> 21213 | P9: ='Revenue Drivers'!T10 -> 22314 | ... W9: ='Revenue Drivers'!AA10 -> 27423 | Y9: =SUM(I9:L9) -> 78129 | Z9: =SUM(J9:M9) -> 79379 | AA9: =SUM(K9:N9) -> 80465 | AB9: =SUM(L9:O9) -> 82074 | AC9: =SUM(M9:P9) -> 85200 | AD9: =SUM(N9:Q9) -> 87551 | AE9: =SUM(O9:R9) -> 90511 | AF9: =SUM(P9:S9) -> 93511 | ... AJ9: =SUM(T9:W9) -> 105380 | AL9: =SUM(AJ9/AF9)-1 -> 0.12692624
B10: ='Revenue Drivers'!B11 -> Wearables, Home, and Accessories Revenue | C10: ='Revenue Drivers'!G11 -> 30620 | D10: ='Revenue Drivers'!H11 -> 38367 | E10: ='Revenue Drivers'!I11 -> 41241 | F10: ='Revenue Drivers'!J11 -> 39845 | G10: ='Revenue Drivers'!K11 -> 37005 | I10: ='Revenue Drivers'!M11 -> 14701 | J10: ='Revenue Drivers'!N11 -> 8806 | K10: ='Revenue Drivers'!O11 -> 8084 | L10: ='Revenue Drivers'!P11 -> 9650 | M10: ='Revenue Drivers'!Q11 -> 13482 | N10: ='Revenue Drivers'!R11 -> 8757 | O10: ='Revenue Drivers'!S11 -> 8284 | P10: ='Revenue Drivers'!T11 -> 9322 | ... W10: ='Revenue Drivers'!AA11 -> 7404 | Y10: =SUM(I10:L10) -> 41241 | Z10: =SUM(J10:M10) -> 40022 | AA10: =SUM(K10:N10) -> 39973 | AB10: =SUM(L10:O10) -> 40173 | AC10: =SUM(M10:P10) -> 39845 | AD10: =SUM(N10:Q10) -> 38316 | AE10: =SUM(O10:R10) -> 37472 | AF10: =SUM(P10:S10) -> 37285 | ... AJ10: =SUM(T10:W10) -> 35715 | AL10: =SUM(AJ10/AF10)-1 -> -0.042108086
B11: Total Revenue | C11: =SUM(C6:C10) -> 274515 | D11: =SUM(D6:D10) -> 365817 | E11: =SUM(E6:E10) -> 394328 | F11: =SUM(F6:F10) -> 383285 | G11: =SUM(G6:G10) -> 391035 | I11: =SUM(I6:I10) -> 123945 | J11: =SUM(J6:J10) -> 97278 | K11: =SUM(K6:K10) -> 82959 | L11: =SUM(L6:L10) -> 90146 | M11: =SUM(M6:M10) -> 117154 | N11: =SUM(N6:N10) -> 94836 | O11: =SUM(O6:O10) -> 81797 | P11: =SUM(P6:P10) -> 89498 | ... W11: =SUM(W6:W10) -> 94036 | Y11: =SUM(Y6:Y10) -> 394328 | Z11: =SUM(Z6:Z10) -> 387537 | AA11: =SUM(AA6:AA10) -> 385095 | AB11: =SUM(AB6:AB10) -> 383933 | AC11: =SUM(AC6:AC10) -> 383285 | AD11: =SUM(AD6:AD10) -> 385706 | AE11: =SUM(AE6:AE10) -> 381623 | AF11: =SUM(AF6:AF10) -> 385603 | ... AJ11: =SUM(AJ6:AJ10) -> 408625 | AL11: =SUM(AJ11/AF11)-1 -> 0.059703892
B12: Y/Y Growth (%) | D12: =SUM(D11/C11)-1 -> 0.33259385 | E12: =SUM(E11/D11)-1 -> 0.077937876 | F12: =SUM(F11/E11)-1 -> -0.028004605 | G12: =SUM(G11/F11)-1 -> 0.020219941 | M12: =SUM(M11/I11)-1 -> -0.054790431 | N12: =SUM(N11/J11)-1 -> -0.025103312 | O12: =SUM(O11/K11)-1 -> -0.014006919 | P12: =SUM(P11/L11)-1 -> -0.0071883389 | Q12: =SUM(Q11/M11)-1 -> 0.020665107 | R12: =SUM(R11/N11)-1 -> -0.043053271 | S12: =SUM(S11/O11)-1 -> 0.048657041 | T12: =SUM(T11/P11)-1 -> 0.060694094 | ... W12: =SUM(W11/S11)-1 -> 0.096284552 | AC12: =SUM(AC11/Y11)-1 -> -0.028004605 | AD12: =SUM(AD11/Z11)-1 -> -0.0047247102 | AE12: =SUM(AE11/AA11)-1 -> -0.0090159571 | AF12: =SUM(AF11/AB11)-1 -> 0.0043497173 | AG12: =SUM(AG11/AC11)-1 -> 0.020219941 | AH12: =SUM(AH11/AD11)-1 -> 0.026066486 | AI12: =SUM(AI11/AE11)-1 -> 0.049113916 | AJ12: =SUM(AJ11/AF11)-1 -> 0.059703892 | AL12: =SUM(AJ12-AF12)*10000 -> 553.54175
B13: Q/Q Growth (%) | C13: N/A | D13: N/A | E13: N/A | F13: N/A | G13: N/A | J13: =SUM(J11/I11)-1 -> -0.21515188 | K13: =SUM(K11/J11)-1 -> -0.14719669 | L13: =SUM(L11/K11)-1 -> 0.086633156 | M13: =SUM(M11/L11)-1 -> 0.29960287 | N13: =SUM(N11/M11)-1 -> -0.19050139 | O13: =SUM(O11/N11)-1 -> -0.13748998 | P13: =SUM(P11/O11)-1 -> 0.094147707 | Q13: =SUM(Q11/P11)-1 -> 0.33606338 | ... W13: =SUM(W11/V11)-1 -> -0.013873887 | Y13: N/A | Z13: N/A | AA13: N/A | AB13: N/A | AC13: N/A | AD13: N/A | AE13: N/A | AF13: N/A | AG13: N/A | AH13: N/A | AI13: N/A | AJ13: N/A
B15: (-) Cost of Sales | C15: ='Historical Financials'!G17 -> -169559 | D15: ='Historical Financials'!H17 -> -212981 | E15: ='Historical Financials'!I17 -> -223546 | F15: ='Historical Financials'!J17 -> -214137 | G15: ='Historical Financials'!K17 -> -210352 | I15: ='Historical Financials'!M17 -> -69702 | J15: ='Historical Financials'!N17 -> -54719 | K15: ='Historical Financials'!O17 -> -47074 | L15: ='Historical Financials'!P17 -> -52051 | M15: ='Historical Financials'!Q17 -> -66822 | N15: ='Historical Financials'!R17 -> -52860 | O15: ='Historical Financials'!S17 -> -45384 | P15: ='Historical Financials'!T17 -> -49071 | ... W15: ='Historical Financials'!AA17 -> -50318 | Y15: =SUM(I15:L15) -> -223546 | Z15: =SUM(J15:M15) -> -220666 | AA15: =SUM(K15:N15) -> -218807 | AB15: =SUM(L15:O15) -> -217117 | AC15: =SUM(M15:P15) -> -214137 | AD15: =SUM(N15:Q15) -> -212035 | AE15: =SUM(O15:R15) -> -207657 | AF15: =SUM(P15:S15) -> -208372 | ... AJ15: =SUM(T15:W15) -> -217886 | AL15: =SUM(AJ15/AF15)-1 -> 0.045658726
B16: Gross Profit | C16: =+C11+C15 -> 104956 | D16: =+D11+D15 -> 152836 | E16: =+E11+E15 -> 170782 | F16: =+F11+F15 -> 169148 | G16: =+G11+G15 -> 180683 | I16: =+I11+I15 -> 54243 | J16: =+J11+J15 -> 42559 | K16: =+K11+K15 -> 35885 | L16: =+L11+L15 -> 38095 | M16: =+M11+M15 -> 50332 | N16: =+N11+N15 -> 41976 | O16: =+O11+O15 -> 36413 | P16: =+P11+P15 -> 40427 | ... W16: =+W11+W15 -> 43718 | Y16: =+Y11+Y15 -> 170782 | Z16: =+Z11+Z15 -> 166871 | AA16: =+AA11+AA15 -> 166288 | AB16: =+AB11+AB15 -> 166816 | AC16: =+AC11+AC15 -> 169148 | AD16: =+AD11+AD15 -> 173671 | AE16: =+AE11+AE15 -> 173966 | AF16: =+AF11+AF15 -> 177231 | ... AJ16: =+AJ11+AJ15 -> 190739 | AL16: =SUM(AJ16/AF16)-1 -> 0.076216915
B17: Gross Margin (%) | C17: =C16/C11 -> 0.38233248 | D17: =D16/D11 -> 0.4177936 | E17: =E16/E11 -> 0.43309631 | F17: =F16/F11 -> 0.4413113 | G17: =G16/G11 -> 0.4620635 | I17: =I16/I11 -> 0.43763766 | J17: =J16/J11 -> 0.43749872 | K17: =K16/K11 -> 0.43256307 | L17: =L16/L11 -> 0.42259224 | M17: =M16/M11 -> 0.42962255 | N17: =N16/N11 -> 0.44261673 | O17: =O16/O11 -> 0.44516303 | P17: =P16/P11 -> 0.45170842 | ... W17: =W16/W11 -> 0.46490706 | Y17: =Y16/Y11 -> 0.43309631 | Z17: =Z16/Z11 -> 0.43059372 | AA17: =AA16/AA11 -> 0.43181033 | AB17: =AB16/AB11 -> 0.43449248 | AC17: =AC16/AC11 -> 0.4413113 | AD17: =AD16/AD11 -> 0.45026782 | AE17: =AE16/AE11 -> 0.45585827 | AF17: =AF16/AF11 -> 0.45962039 | ... AJ17: =AJ16/AJ11 -> 0.4667825 | AL17: =SUM(AJ17-AF17)*10000 -> 71.621155
B19: (-) Research and Development (R&D) | C19: ='Historical Financials'!G21 -> -18752 | D19: ='Historical Financials'!H21 -> -21914 | E19: ='Historical Financials'!I21 -> -26251 | F19: ='Historical Financials'!J21 -> -29915 | G19: ='Historical Financials'!K21 -> -31370 | I19: ='Historical Financials'!M21 -> -6306 | J19: ='Historical Financials'!N21 -> -6387 | K19: ='Historical Financials'!O21 -> -6797 | L19: ='Historical Financials'!P21 -> -6761 | M19: ='Historical Financials'!Q21 -> -7709 | N19: ='Historical Financials'!R21 -> -7457 | O19: ='Historical Financials'!S21 -> -7442 | P19: ='Historical Financials'!T21 -> -7307 | ... W19: ='Historical Financials'!AA21 -> -8866 | Y19: =SUM(I19:L19) -> -26251 | Z19: =SUM(J19:M19) -> -27654 | AA19: =SUM(K19:N19) -> -28724 | AB19: =SUM(L19:O19) -> -29369 | AC19: =SUM(M19:P19) -> -29915 | AD19: =SUM(N19:Q19) -> -29902 | AE19: =SUM(O19:R19) -> -30348 | AF19: =SUM(P19:S19) -> -30912 | ... AJ19: =SUM(T19:W19) -> -33449 | AL19: =SUM(AJ19/AF19)-1 -> 0.082071687
B20: (-) Selling, General & Administrative (SG&A) | C20: ='Historical Financials'!G22 -> -19916 | D20: ='Historical Financials'!H22 -> -21973 | E20: ='Historical Financials'!I22 -> -25094 | F20: ='Historical Financials'!J22 -> -24932 | G20: ='Historical Financials'!K22 -> -26097 | I20: ='Historical Financials'!M22 -> -6449 | J20: ='Historical Financials'!N22 -> -6193 | K20: ='Historical Financials'!O22 -> -6012 | L20: ='Historical Financials'!P22 -> -6440 | M20: ='Historical Financials'!Q22 -> -6607 | N20: ='Historical Financials'!R22 -> -6201 | O20: ='Historical Financials'!S22 -> -5973 | P20: ='Historical Financials'!T22 -> -6151 | ... W20: ='Historical Financials'!AA22 -> -6650 | Y20: =SUM(I20:L20) -> -25094 | Z20: =SUM(J20:M20) -> -25252 | AA20: =SUM(K20:N20) -> -25260 | AB20: =SUM(L20:O20) -> -25221 | AC20: =SUM(M20:P20) -> -24932 | AD20: =SUM(N20:Q20) -> -25111 | AE20: =SUM(O20:R20) -> -25378 | AF20: =SUM(P20:S20) -> -25725 | ... AJ20: =SUM(T20:W20) -> -27076 | AL20: =SUM(AJ20/AF20)-1 -> 0.052517007
B21: Earning before Interest & Taxes (EBIT) | C21: =SUM(C16+SUM(C19:C20)) -> 66288 | D21: =SUM(D16+SUM(D19:D20)) -> 108949 | E21: =SUM(E16+SUM(E19:E20)) -> 119437 | F21: =SUM(F16+SUM(F19:F20)) -> 114301 | G21: =SUM(G16+SUM(G19:G20)) -> 123216 | I21: =SUM(I16+SUM(I19:I20)) -> 41488 | J21: =SUM(J16+SUM(J19:J20)) -> 29979 | K21: =SUM(K16+SUM(K19:K20)) -> 23076 | L21: =SUM(L16+SUM(L19:L20)) -> 24894 | M21: =SUM(M16+SUM(M19:M20)) -> 36016 | N21: =SUM(N16+SUM(N19:N20)) -> 28318 | O21: =SUM(O16+SUM(O19:O20)) -> 22998 | P21: =SUM(P16+SUM(P19:P20)) -> 26969 | ... W21: =SUM(W16+SUM(W19:W20)) -> 28202 | Y21: =SUM(Y16+SUM(Y19:Y20)) -> 119437 | Z21: =SUM(Z16+SUM(Z19:Z20)) -> 113965 | AA21: =SUM(AA16+SUM(AA19:AA20)) -> 112304 | AB21: =SUM(AB16+SUM(AB19:AB20)) -> 112226 | AC21: =SUM(AC16+SUM(AC19:AC20)) -> 114301 | AD21: =SUM(AD16+SUM(AD19:AD20)) -> 118658 | AE21: =SUM(AE16+SUM(AE19:AE20)) -> 118240 | AF21: =SUM(AF16+SUM(AF19:AF20)) -> 120594 | ... AJ21: =SUM(AJ16+SUM(AJ19:AJ20)) -> 130214 | AL21: =SUM(AJ21/AF21)-1 -> 0.079771796
B22: Operating Margin (%) | C22: =C21/C11 -> 0.24147314 | D22: =D21/D11 -> 0.29782378 | E22: =E21/E11 -> 0.30288744 | F22: =F21/F11 -> 0.29821412 | G22: =G21/G11 -> 0.31510223 | I22: =I21/I11 -> 0.33472911 | J22: =J21/J11 -> 0.30817862 | K22: =K21/K11 -> 0.2781615 | L22: =L21/L11 -> 0.27615202 | M22: =M21/M11 -> 0.30742442 | N22: =N21/N11 -> 0.29859969 | O22: =O21/O11 -> 0.28115946 | P22: =P21/P11 -> 0.30133634 | ... W22: =W21/W11 -> 0.29990642 | Y22: =Y21/Y11 -> 0.30288744 | Z22: =Z21/Z11 -> 0.29407515 | AA22: =AA21/AA11 -> 0.29162674 | AB22: =AB21/AB11 -> 0.29230621 | AC22: =AC21/AC11 -> 0.29821412 | AD22: =AD21/AD11 -> 0.30763846 | AE22: =AE21/AE11 -> 0.30983457 | AF22: =AF21/AF11 -> 0.31274134 | ... AJ22: =AJ21/AJ11 -> 0.31866381 | AL22: =SUM(AJ22-AF22)*10000 -> 59.224688
B24: (+) Depreciation and Amortization | C24: ='Historical Financials'!G83 -> 11056 | D24: ='Historical Financials'!H83 -> 11284 | E24: ='Historical Financials'!I83 -> 11104 | F24: ='Historical Financials'!J83 -> 11519 | G24: ='Historical Financials'!K83 -> 11445 | I24: ='Historical Financials'!M83 -> 2697 | J24: ='Historical Financials'!N83 -> 2737 | K24: ='Historical Financials'!O83 -> 2805 | L24: ='Historical Financials'!P83 -> 2865 | M24: ='Historical Financials'!Q83 -> 2916 | N24: ='Historical Financials'!R83 -> 2898 | O24: ='Historical Financials'!S83 -> 3052 | P24: ='Historical Financials'!T83 -> 2653 | ... W24: ='Historical Financials'!AA83 -> 2830 | Y24: =SUM(I24:L24) -> 11104 | Z24: =SUM(J24:M24) -> 11323 | AA24: =SUM(K24:N24) -> 11484 | AB24: =SUM(L24:O24) -> 11731 | AC24: =SUM(M24:P24) -> 11519 | AD24: =SUM(N24:Q24) -> 11451 | AE24: =SUM(O24:R24) -> 11389 | AF24: =SUM(P24:S24) -> 11187 | ... AJ24: =SUM(T24:W24) -> 11482 | AL24: =SUM(AJ24/AF24)-1 -> 0.026369894
B25: EBITDA | C25: =SUM(C21+C24) -> 77344 | D25: =SUM(D21+D24) -> 120233 | E25: =SUM(E21+E24) -> 130541 | F25: =SUM(F21+F24) -> 125820 | G25: =SUM(G21+G24) -> 134661 | I25: =SUM(I21+I24) -> 44185 | J25: =SUM(J21+J24) -> 32716 | K25: =SUM(K21+K24) -> 25881 | L25: =SUM(L21+L24) -> 27759 | M25: =SUM(M21+M24) -> 38932 | N25: =SUM(N21+N24) -> 31216 | O25: =SUM(O21+O24) -> 26050 | P25: =SUM(P21+P24) -> 29622 | ... W25: =SUM(W21+W24) -> 31032 | Y25: =SUM(Y21+Y24) -> 130541 | Z25: =SUM(Z21+Z24) -> 125288 | AA25: =SUM(AA21+AA24) -> 123788 | AB25: =SUM(AB21+AB24) -> 123957 | AC25: =SUM(AC21+AC24) -> 125820 | AD25: =SUM(AD21+AD24) -> 130109 | AE25: =SUM(AE21+AE24) -> 129629 | AF25: =SUM(AF21+AF24) -> 131781 | ... AJ25: =SUM(AJ21+AJ24) -> 141696 | AL25: =SUM(AJ25/AF25)-1 -> 0.075238464
B26: EBITDA Margin (%) | C26: =C25/C11 -> 0.28174781 | D26: =D25/D11 -> 0.3286698 | E26: =E25/E11 -> 0.33104674 | F26: =F25/F11 -> 0.32826748 | G26: =G25/G11 -> 0.34437071 | I26: =I25/I11 -> 0.35648877 | J26: =J25/J11 -> 0.33631448 | K26: =K25/K11 -> 0.31197338 | L26: =L25/L11 -> 0.3079338 | M26: =M25/M11 -> 0.33231473 | N26: =N25/N11 -> 0.3291577 | O26: =O25/O11 -> 0.31847134 | P26: =P25/P11 -> 0.33097946 | ... W26: =W25/W11 -> 0.33000128 | Y26: =Y25/Y11 -> 0.33104674 | Z26: =Z25/Z11 -> 0.323293 | AA26: =AA25/AA11 -> 0.32144795 | AB26: =AB25/AB11 -> 0.32286102 | AC26: =AC25/AC11 -> 0.32826748 | AD26: =AD25/AD11 -> 0.33732688 | AE26: =AE25/AE11 -> 0.33967816 | AF26: =AF25/AF11 -> 0.34175305 | ... AJ26: =AJ25/AJ11 -> 0.34676292 | AL26: =SUM(AJ26-AF26)*10000 -> 50.098779
B28: (+) Share-based Compensation | C28: ='Historical Financials'!G84 -> 6829 | D28: ='Historical Financials'!H84 -> 7906 | E28: ='Historical Financials'!I84 -> 9038 | F28: ='Historical Financials'!J84 -> 10833 | G28: ='Historical Financials'!K84 -> 11688 | I28: ='Historical Financials'!M84 -> 2265 | J28: ='Historical Financials'!N84 -> 2252 | K28: ='Historical Financials'!O84 -> 2243 | L28: ='Historical Financials'!P84 -> 2278 | M28: ='Historical Financials'!Q84 -> 2905 | N28: ='Historical Financials'!R84 -> 2686 | O28: ='Historical Financials'!S84 -> 2617 | P28: ='Historical Financials'!T84 -> 2625 | ... W28: ='Historical Financials'!AA84 -> 3168 | Y28: =SUM(I28:L28) -> 9038 | Z28: =SUM(J28:M28) -> 9678 | AA28: =SUM(K28:N28) -> 10112 | AB28: =SUM(L28:O28) -> 10486 | AC28: =SUM(M28:P28) -> 10833 | AD28: =SUM(N28:Q28) -> 10925 | AE28: =SUM(O28:R28) -> 11206 | AF28: =SUM(P28:S28) -> 11455 | ... AJ28: =SUM(T28:W28) -> 12538 | AL28: =SUM(AJ28/AF28)-1 -> 0.094543867
B29: Adj. EBITDA | C29: =+SUM(C25+SUM(C28:C28)) -> 84173 | D29: =+SUM(D25+SUM(D28:D28)) -> 128139 | E29: =+SUM(E25+SUM(E28:E28)) -> 139579 | F29: =+SUM(F25+SUM(F28:F28)) -> 136653 | G29: =+SUM(G25+SUM(G28:G28)) -> 146349 | I29: =+SUM(I25+SUM(I28:I28)) -> 46450 | J29: =+SUM(J25+SUM(J28:J28)) -> 34968 | K29: =+SUM(K25+SUM(K28:K28)) -> 28124 | L29: =+SUM(L25+SUM(L28:L28)) -> 30037 | M29: =+SUM(M25+SUM(M28:M28)) -> 41837 | N29: =+SUM(N25+SUM(N28:N28)) -> 33902 | O29: =+SUM(O25+SUM(O28:O28)) -> 28667 | P29: =+SUM(P25+SUM(P28:P28)) -> 32247 | ... W29: =+SUM(W25+SUM(W28:W28)) -> 34200 | Y29: =+SUM(Y25+SUM(Y28:Y28)) -> 139579 | Z29: =+SUM(Z25+SUM(Z28:Z28)) -> 134966 | AA29: =+SUM(AA25+SUM(AA28:AA28)) -> 133900 | AB29: =+SUM(AB25+SUM(AB28:AB28)) -> 134443 | AC29: =+SUM(AC25+SUM(AC28:AC28)) -> 136653 | AD29: =+SUM(AD25+SUM(AD28:AD28)) -> 141034 | AE29: =+SUM(AE25+SUM(AE28:AE28)) -> 140835 | AF29: =+SUM(AF25+SUM(AF28:AF28)) -> 143236 | ... AJ29: =+SUM(AJ25+SUM(AJ28:AJ28)) -> 154234 | AL29: =SUM(AJ29/AF29)-1 -> 0.076782373
B30: Adj. EBITDA Margin (%) | C30: =C29/C11 -> 0.30662441 | D30: =D29/D11 -> 0.3502817 | E30: =E29/E11 -> 0.35396675 | F30: =F29/F11 -> 0.35653104 | G30: =G29/G11 -> 0.37426062 | I30: =I29/I11 -> 0.374763 | J30: =J29/J11 -> 0.35946463 | K30: =K29/K11 -> 0.33901084 | L30: =L29/L11 -> 0.33320391 | M30: =M29/M11 -> 0.35711115 | N30: =N29/N11 -> 0.35748028 | O30: =O29/O11 -> 0.35046518 | P30: =P29/P11 -> 0.36030973 | ... W30: =W29/W11 -> 0.3636905 | Y30: =Y29/Y11 -> 0.35396675 | Z30: =Z29/Z11 -> 0.3482661 | AA30: =AA29/AA11 -> 0.34770641 | AB30: =AB29/AB11 -> 0.35017308 | AC30: =AC29/AC11 -> 0.35653104 | AD30: =AD29/AD11 -> 0.36565156 | AE30: =AE29/AE11 -> 0.36904222 | AF30: =AF29/AF11 -> 0.37145977 | ... AJ30: =AJ29/AJ11 -> 0.37744631 | AL30: =SUM(AJ30-AF30)*10000 -> 59.865482
B32: (-) Capital Expenditures | C32: ='Historical Financials'!G98 -> -7309 | D32: ='Historical Financials'!H98 -> -11085 | E32: ='Historical Financials'!I98 -> -10708 | F32: ='Historical Financials'!J98 -> -10959 | G32: ='Historical Financials'!K98 -> -9447 | I32: ='Historical Financials'!M98 -> -2803 | J32: ='Historical Financials'!N98 -> -2514 | K32: ='Historical Financials'!O98 -> -2102 | L32: ='Historical Financials'!P98 -> -3289 | M32: ='Historical Financials'!Q98 -> -3787 | N32: ='Historical Financials'!R98 -> -2916 | O32: ='Historical Financials'!S98 -> -2093 | P32: ='Historical Financials'!T98 -> -2163 | ... W32: ='Historical Financials'!AA98 -> -3462 | Y32: =SUM(I32:L32) -> -10708 | Z32: =SUM(J32:M32) -> -11692 | AA32: =SUM(K32:N32) -> -12094 | AB32: =SUM(L32:O32) -> -12085 | AC32: =SUM(M32:P32) -> -10959 | AD32: =SUM(N32:Q32) -> -9564 | AE32: =SUM(O32:R32) -> -8644 | AF32: =SUM(P32:S32) -> -8702 | ... AJ32: =SUM(T32:W32) -> -12381 | AL32: =SUM(AJ32/AF32)-1 -> 0.42277637
B33: (-) Cash Taxes | C33: =-'Historical Financials'!G128 -> -9501 | D33: =-'Historical Financials'!H128 -> -25385 | E33: =-'Historical Financials'!I128 -> -19573 | F33: =-'Historical Financials'!J128 -> -18679 | G33: =-'Historical Financials'!K128 -> -26102 | I33: =-'Historical Financials'!M128 -> -5235 | J33: =-'Historical Financials'!N128 -> -4066 | K33: =-'Historical Financials'!O128 -> -2950 | L33: =-'Historical Financials'!P128 -> -7322 | M33: =-'Historical Financials'!Q128 -> -828 | N33: =-'Historical Financials'!R128 -> -4066 | O33: =-'Historical Financials'!S128 -> -2126 | P33: =-'Historical Financials'!T128 -> -11659 | ... W33: =-'Historical Financials'!AA128 -> -5649 | Y33: =SUM(I33:L33) -> -19573 | Z33: =SUM(J33:M33) -> -15166 | AA33: =SUM(K33:N33) -> -15166 | AB33: =SUM(L33:O33) -> -14342 | AC33: =SUM(M33:P33) -> -18679 | AD33: =SUM(N33:Q33) -> -25106 | AE33: =SUM(O33:R33) -> -28316 | AF33: =SUM(P33:S33) -> -30889 | ... AJ33: =SUM(T33:W33) -> -44204 | AL33: =SUM(AJ33/AF33)-1 -> 0.4310596
B34: (-) Cash Interest | C34: =-'Historical Financials'!G129 -> -3002 | D34: =-'Historical Financials'!H129 -> -2687 | E34: =-'Historical Financials'!I129 -> -2865 | F34: =-'Historical Financials'!J129 -> -3803 | G34: =-'Historical Financials'!K129 -> 0 | I34: =-'Historical Financials'!M129 -> -531 | J34: =-'Historical Financials'!N129 -> -875 | K34: =-'Historical Financials'!O129 -> -504 | L34: =-'Historical Financials'!P129 -> -955 | M34: =-'Historical Financials'!Q129 -> -703 | N34: =-'Historical Financials'!R129 -> -1170 | O34: =-'Historical Financials'!S129 -> -717 | P34: =-'Historical Financials'!T129 -> -1213 | ... W34: =-'Historical Financials'!AA129 -> 0 | Y34: =SUM(I34:L34) -> -2865 | Z34: =SUM(J34:M34) -> -3037 | AA34: =SUM(K34:N34) -> -3332 | AB34: =SUM(L34:O34) -> -3545 | AC34: =SUM(M34:P34) -> -3803 | AD34: =SUM(N34:Q34) -> -3100 | AE34: =SUM(O34:R34) -> -1930 | AF34: =SUM(P34:S34) -> -1213 | ... AJ34: =SUM(T34:W34) -> 0 | AL34: =SUM(AJ34/AF34)-1 -> -1
B35: (+/-) Changes in NWC | C35: =SUM('Historical Financials'!G89:G94) -> 5690 | D35: =SUM('Historical Financials'!H89:H94) -> -4911 | E35: =SUM('Historical Financials'!I89:I94) -> 1200 | F35: =SUM('Historical Financials'!J89:J94) -> -6577 | G35: =SUM('Historical Financials'!K89:K94) -> 3651 | I35: =SUM('Historical Financials'!M89:M94) -> 6525 | J35: =SUM('Historical Financials'!N89:N94) -> -2052 | K35: =SUM('Historical Financials'!O89:O94) -> -3225 | L35: =SUM('Historical Financials'!P89:P94) -> -48 | M35: =SUM('Historical Financials'!Q89:Q94) -> -1497 | N35: =SUM('Historical Financials'!R89:R94) -> 231 | O35: =SUM('Historical Financials'!S89:S94) -> 749 | P35: =SUM('Historical Financials'!T89:T94) -> -6060 | ... W35: =SUM('Historical Financials'!AA89:AA94) -> -2034 | Y35: =SUM(I35:L35) -> 1200 | Z35: =SUM(J35:M35) -> -6822 | AA35: =SUM(K35:N35) -> -4539 | AB35: =SUM(L35:O35) -> -565 | AC35: =SUM(M35:P35) -> -6577 | AD35: =SUM(N35:Q35) -> -3957 | AE35: =SUM(O35:R35) -> -9955 | AF35: =SUM(P35:S35) -> -9017 | ... AJ35: =SUM(T35:W35) -> -12685 | AL35: =SUM(AJ35/AF35)-1 -> 0.40678718
B36: Discretionary Cash-Flows | C36: =SUM(C29+SUM(C32:C35)) -> 70051 | D36: =SUM(D29+SUM(D32:D35)) -> 84071 | E36: =SUM(E29+SUM(E32:E35)) -> 107633 | F36: =SUM(F29+SUM(F32:F35)) -> 96635 | G36: =SUM(G29+SUM(G32:G35)) -> 114451 | I36: =SUM(I29+SUM(I32:I35)) -> 44406 | J36: =SUM(J29+SUM(J32:J35)) -> 25461 | K36: =SUM(K29+SUM(K32:K35)) -> 19343 | L36: =SUM(L29+SUM(L32:L35)) -> 18423 | M36: =SUM(M29+SUM(M32:M35)) -> 35022 | N36: =SUM(N29+SUM(N32:N35)) -> 25981 | O36: =SUM(O29+SUM(O32:O35)) -> 24480 | P36: =SUM(P29+SUM(P32:P35)) -> 11152 | ... W36: =SUM(W29+SUM(W32:W35)) -> 23055 | Y36: =SUM(Y29+SUM(Y32:Y35)) -> 107633 | Z36: =SUM(Z29+SUM(Z32:Z35)) -> 98249 | AA36: =SUM(AA29+SUM(AA32:AA35)) -> 98769 | AB36: =SUM(AB29+SUM(AB32:AB35)) -> 103906 | AC36: =SUM(AC29+SUM(AC32:AC35)) -> 96635 | AD36: =SUM(AD29+SUM(AD32:AD35)) -> 99307 | AE36: =SUM(AE29+SUM(AE32:AE35)) -> 91990 | AF36: =SUM(AF29+SUM(AF32:AF35)) -> 93415 | ... AJ36: =SUM(AJ29+SUM(AJ32:AJ35)) -> 84964 | AL36: =SUM(AJ36/AF36)-1 -> -0.09046727
B38: (+/-) Proceeds / (Purchases) of Investments | C38: =SUM('Historical Financials'!G99:G100) -> 5453 | D38: =SUM('Historical Financials'!H99:H100) -> -3075 | E38: =SUM('Historical Financials'!I99:I100) -> -9560 | F38: =SUM('Historical Financials'!J99:J100) -> 16001 | G38: =SUM('Historical Financials'!K99:K100) -> 13690 | I38: =SUM('Historical Financials'!M99:M100) -> -12929 | J38: =SUM('Historical Financials'!N99:N100) -> -6390 | K38: =SUM('Historical Financials'!O99:O100) -> 6953 | L38: =SUM('Historical Financials'!P99:P100) -> 2806 | M38: =SUM('Historical Financials'!Q99:Q100) -> 2483 | N38: =SUM('Historical Financials'!R99:R100) -> 5341 | O38: =SUM('Historical Financials'!S99:S100) -> 3036 | P38: =SUM('Historical Financials'!T99:T100) -> 5141 | ... W38: =SUM('Historical Financials'!AA99:AA100) -> 8875 | Y38: =SUM(I38:L38) -> -9560 | Z38: =SUM(J38:M38) -> 5852 | AA38: =SUM(K38:N38) -> 17583 | AB38: =SUM(L38:O38) -> 13666 | AC38: =SUM(M38:P38) -> 16001 | AD38: =SUM(N38:Q38) -> 18121 | AE38: =SUM(O38:R38) -> 14911 | AF38: =SUM(P38:S38) -> 14287 | ... AJ38: =SUM(T38:W38) -> 32774
B39: (+/-) Proceeds / (Purchases) of Other/Strategic investments | C39: ='Historical Financials'!G102 -> -909 | D39: ='Historical Financials'!H102 -> -352 | E39: ='Historical Financials'!I102 -> -1780 | F39: ='Historical Financials'!J102 -> -1337 | G39: ='Historical Financials'!K102 -> -1308 | I39: ='Historical Financials'!M102 -> -374 | J39: ='Historical Financials'!N102 -> -194 | K39: ='Historical Financials'!O102 -> -615 | L39: ='Historical Financials'!P102 -> -597 | M39: ='Historical Financials'!Q102 -> -141 | N39: ='Historical Financials'!R102 -> -106 | O39: ='Historical Financials'!S102 -> -506 | P39: ='Historical Financials'!T102 -> -584 | ... W39: ='Historical Financials'!AA102 -> -340 | Y39: =SUM(I39:L39) -> -1780 | Z39: =SUM(J39:M39) -> -1547 | AA39: =SUM(K39:N39) -> -1459 | AB39: =SUM(L39:O39) -> -1350 | AC39: =SUM(M39:P39) -> -1337 | AD39: =SUM(N39:Q39) -> -1480 | AE39: =SUM(O39:R39) -> -1819 | AF39: =SUM(P39:S39) -> -1701 | ... AJ39: =SUM(T39:W39) -> -1166
B40: (+/-) Issuance / (Repayment) of Debt | C40: =SUM('Historical Financials'!G106:G107) -> 3462 | D40: =SUM('Historical Financials'!H106:H107) -> 11643 | E40: =SUM('Historical Financials'!I106:I107) -> -4078 | F40: =SUM('Historical Financials'!J106:J107) -> -5923.108 | G40: =SUM('Historical Financials'!K106:K107) -> -9958 | I40: =SUM('Historical Financials'!M106:M107) -> 0 | J40: =SUM('Historical Financials'!N106:N107) -> -3750 | K40: =SUM('Historical Financials'!O106:O107) -> -3000 | L40: =SUM('Historical Financials'!P106:P107) -> 2672 | M40: =SUM('Historical Financials'!Q106:Q107) -> -1401 | N40: =SUM('Historical Financials'!R106:R107) -> -2250 | O40: =SUM('Historical Financials'!S106:S107) -> -2272 | P40: =SUM('Historical Financials'!T106:T107) -> -0.108 | ... W40: =SUM('Historical Financials'!AA106:AA107) -> -1192 | Y40: =SUM(I40:L40) -> -4078 | Z40: =SUM(J40:M40) -> -5479 | AA40: =SUM(K40:N40) -> -3979 | AB40: =SUM(L40:O40) -> -3251 | AC40: =SUM(M40:P40) -> -5923.108 | AD40: =SUM(N40:Q40) -> -4522.108 | AE40: =SUM(O40:R40) -> -5422.108 | AF40: =SUM(P40:S40) -> -7400.108 | ... AJ40: =SUM(T40:W40) -> -7759
B41: (+/-) Issuances / (Share Repurchases) | C41: =SUM('Historical Financials'!G108:G109) -> -71478 | D41: =SUM('Historical Financials'!H108:H109) -> -84866 | E41: =SUM('Historical Financials'!I108:I109) -> -89402 | F41: =SUM('Historical Financials'!J108:J109) -> -77550 | G41: =SUM('Historical Financials'!K108:K109) -> -94949 | I41: =SUM('Historical Financials'!M108:M109) -> -20478 | J41: =SUM('Historical Financials'!N108:N109) -> -22631 | K41: =SUM('Historical Financials'!O108:O109) -> -21865 | L41: =SUM('Historical Financials'!P108:P109) -> -24428 | M41: =SUM('Historical Financials'!Q108:Q109) -> -19475 | N41: =SUM('Historical Financials'!R108:R109) -> -19594 | O41: =SUM('Historical Financials'!S108:S109) -> -17478 | P41: =SUM('Historical Financials'!T108:T109) -> -21003 | ... W41: =SUM('Historical Financials'!AA108:AA109) -> -21075 | Y41: =SUM(I41:L41) -> -89402 | Z41: =SUM(J41:M41) -> -88399 | AA41: =SUM(K41:N41) -> -85362 | AB41: =SUM(L41:O41) -> -80975 | AC41: =SUM(M41:P41) -> -77550 | AD41: =SUM(N41:Q41) -> -78214 | AE41: =SUM(O41:R41) -> -81825 | AF41: =SUM(P41:S41) -> -90869 | ... AJ41: =SUM(T41:W41) -> -95662
B42: (+/-) Change in commercial paper, net | C42: ='Historical Financials'!G110 -> -963 | D42: ='Historical Financials'!H110 -> 1022 | E42: ='Historical Financials'!I110 -> 3955 | F42: ='Historical Financials'!J110 -> -3978 | G42: ='Historical Financials'!K110 -> 3960 | I42: ='Historical Financials'!M110 -> -1000 | J42: ='Historical Financials'!N110 -> 1999 | K42: ='Historical Financials'!O110 -> 3971 | L42: ='Historical Financials'!P110 -> -1015 | M42: ='Historical Financials'!Q110 -> -8214 | N42: ='Historical Financials'!R110 -> 254 | O42: ='Historical Financials'!S110 -> 1989 | P42: ='Historical Financials'!T110 -> 1993 | ... W42: ='Historical Financials'!AA110 -> 3903 | Y42: =SUM(I42:L42) -> 3955 | Z42: =SUM(J42:M42) -> -3259 | AA42: =SUM(K42:N42) -> -5004 | AB42: =SUM(L42:O42) -> -6986 | AC42: =SUM(M42:P42) -> -3978 | AD42: =SUM(N42:Q42) -> 252 | AE42: =SUM(O42:R42) -> 0 | AF42: =SUM(P42:S42) -> -992 | ... AJ42: =SUM(T42:W42) -> 6880
B43: (+/-) Dividends | C43: ='Historical Financials'!G113 -> -14081 | D43: ='Historical Financials'!H113 -> -14467 | E43: ='Historical Financials'!I113 -> -14841 | F43: ='Historical Financials'!J113 -> -14875 | G43: ='Historical Financials'!K113 -> -15234 | I43: ='Historical Financials'!M113 -> -3732 | J43: ='Historical Financials'!N113 -> -3595 | K43: ='Historical Financials'!O113 -> -3811 | L43: ='Historical Financials'!P113 -> -3703 | M43: ='Historical Financials'!Q113 -> -3768 | N43: ='Historical Financials'!R113 -> -3650 | O43: ='Historical Financials'!S113 -> -3849 | P43: ='Historical Financials'!T113 -> -3608 | ... W43: ='Historical Financials'!AA113 -> -3945 | AE43: =SUM(O43:R43) -> -14992 | AF43: =SUM(P43:S43) -> -15038 | AG43: =SUM(Q43:T43) -> -15234 | AH43: =SUM(R43:U43) -> -15265 | AI43: =SUM(S43:V43) -> -15313 | AJ43: =SUM(T43:W43) -> -15363
B44: (+/-) Other | D44: =SUM(D49-C49)-SUM(D36:D43) -> 2948 | E44: =SUM(E49-D49)-SUM(E36:E43) -> -3221 | F44: =SUM(F49-E49)-SUM(F36:F43) -> -2653.892 | G44: =SUM(G49-F49)-SUM(G36:G43) -> -10674 | I44: =SUM(I49-D49)-SUM(I36:I43) -> -3714 | J44: =SUM(J49-I49)-SUM(J36:J43) -> 79 | K44: =SUM(K49-J49)-SUM(K36:K43) -> -1572 | L44: =SUM(L49-K49)-SUM(L36:L43) -> 1986 | M44: =SUM(M49-L49)-SUM(M36:M43) -> -7617 | N44: =SUM(N49-M49)-SUM(N36:N43) -> -1824 | O44: =SUM(O49-N49)-SUM(O36:O43) -> -1679 | P44: =SUM(P49-O49)-SUM(P36:P43) -> 8466.108 | Q44: =SUM(Q49-P49)-SUM(Q36:Q43) -> -3270 | ... W44: =SUM(W49-V49)-SUM(W36:W43) -> -1174 | Y44: =SUM(I44:L44) -> -3221 | Z44: =SUM(J44:M44) -> -7124 | AA44: =SUM(K44:N44) -> -9027 | AB44: =SUM(L44:O44) -> -9134 | AC44: =SUM(M44:P44) -> -2653.892 | AD44: =SUM(N44:Q44) -> 1693.108 | AE44: =SUM(O44:R44) -> 5165.108 | AF44: =SUM(P44:S44) -> 5455.108 | ... AJ44: =SUM(T44:W44) -> 6036
B45: Free-Cash Flows | C45: =SUM(C36+SUM(C38:C44)) -> -8465 | D45: =SUM(D36+SUM(D38:D44)) -> -3076 | E45: =SUM(E36+SUM(E38:E44)) -> -11294 | F45: =SUM(F36+SUM(F38:F44)) -> 6319 | G45: =SUM(G36+SUM(G38:G44)) -> -22 | I45: =SUM(I36+SUM(I38:I44)) -> 2179 | J45: =SUM(J36+SUM(J38:J44)) -> -9021 | K45: =SUM(K36+SUM(K38:K44)) -> -596 | L45: =SUM(L36+SUM(L38:L44)) -> -3856 | M45: =SUM(M36+SUM(M38:M44)) -> -3111 | N45: =SUM(N36+SUM(N38:N44)) -> 4152 | O45: =SUM(O36+SUM(O38:O44)) -> 3721 | P45: =SUM(P36+SUM(P38:P44)) -> 1557 | ... W45: =SUM(W36+SUM(W38:W44)) -> 8107 | Y45: =SUM(Y36+SUM(Y38:Y44)) -> 3547 | Z45: =SUM(Z36+SUM(Z38:Z44)) -> -1707 | AA45: =SUM(AA36+SUM(AA38:AA44)) -> 11521 | AB45: =SUM(AB36+SUM(AB38:AB44)) -> 15876 | AC45: =SUM(AC36+SUM(AC38:AC44)) -> 21194 | AD45: =SUM(AD36+SUM(AD38:AD44)) -> 35157 | AE45: =SUM(AE36+SUM(AE38:AE44)) -> 8008 | AF45: =SUM(AF36+SUM(AF38:AF44)) -> -2843 | ... AJ45: =SUM(AJ36+SUM(AJ38:AJ44)) -> 10704
B47: Capitalization
B49: Cash & Cash Equivelants | C49: ='Historical Financials'!G43 -> 38016 | D49: ='Historical Financials'!H43 -> 34940 | E49: ='Historical Financials'!I43 -> 23646 | F49: ='Historical Financials'!J43 -> 29965 | G49: ='Historical Financials'!K43 -> 29943 | I49: ='Historical Financials'!M43 -> 37119 | J49: ='Historical Financials'!N43 -> 28098 | K49: ='Historical Financials'!O43 -> 27502 | L49: ='Historical Financials'!P43 -> 23646 | M49: ='Historical Financials'!Q43 -> 20535 | N49: ='Historical Financials'!R43 -> 24687 | O49: ='Historical Financials'!S43 -> 28408 | P49: ='Historical Financials'!T43 -> 29965 | ... W49: ='Historical Financials'!AA43 -> 36269 | Y49: =L49 -> 23646 | Z49: =M49 -> 20535 | AA49: =N49 -> 24687 | AB49: =O49 -> 28408 | AC49: =P49 -> 29965 | AD49: =Q49 -> 40760 | AE49: =R49 -> 32695 | AF49: =S49 -> 25565 | ... AJ49: =W49 -> 36269
B50: Marketable Securities, Current | C50: ='Historical Financials'!G44 -> 52927 | D50: ='Historical Financials'!H44 -> 27699 | E50: ='Historical Financials'!I44 -> 24658 | F50: ='Historical Financials'!J44 -> 31590 | G50: ='Historical Financials'!K44 -> 35228 | I50: ='Historical Financials'!M44 -> 26794 | J50: ='Historical Financials'!N44 -> 23413 | K50: ='Historical Financials'!O44 -> 20729 | L50: ='Historical Financials'!P44 -> 24658 | M50: ='Historical Financials'!Q44 -> 30820 | N50: ='Historical Financials'!R44 -> 31185 | O50: ='Historical Financials'!S44 -> 34074 | P50: ='Historical Financials'!T44 -> 31590 | ... W50: ='Historical Financials'!AA44 -> 19103 | Y50: =L50 -> 24658 | Z50: =M50 -> 30820 | AA50: =N50 -> 31185 | AB50: =O50 -> 34074 | AC50: =P50 -> 31590 | AD50: =Q50 -> 32340 | AE50: =R50 -> 34455 | AF50: =S50 -> 36236 | ... AJ50: =W50 -> 19103
B51: Marketable Securities, Net of Current Portion | C51: ='Historical Financials'!G51 -> 100887 | D51: ='Historical Financials'!H51 -> 127877 | E51: ='Historical Financials'!I51 -> 120805 | F51: ='Historical Financials'!J51 -> 100544 | G51: ='Historical Financials'!K51 -> 91479 | I51: ='Historical Financials'!M51 -> 138683 | J51: ='Historical Financials'!N51 -> 141219 | K51: ='Historical Financials'!O51 -> 131077 | L51: ='Historical Financials'!P51 -> 120805 | M51: ='Historical Financials'!Q51 -> 114095 | N51: ='Historical Financials'!R51 -> 110461 | O51: ='Historical Financials'!S51 -> 104061 | P51: ='Historical Financials'!T51 -> 100544 | ... W51: ='Historical Financials'!AA51 -> 77614 | Y51: =L51 -> 120805 | Z51: =M51 -> 114095 | AA51: =N51 -> 110461 | AB51: =O51 -> 104061 | AC51: =P51 -> 100544 | AD51: =Q51 -> 99475 | AE51: =R51 -> 95187 | AF51: =S51 -> 91240 | ... AJ51: =W51 -> 77614
B52: Total Liquidity | C52: =SUM(C49:C51) -> 191830 | D52: =SUM(D49:D51) -> 190516 | E52: =SUM(E49:E51) -> 169109 | F52: =SUM(F49:F51) -> 162099 | G52: =SUM(G49:G51) -> 156650 | I52: =SUM(I49:I51) -> 202596 | J52: =SUM(J49:J51) -> 192730 | K52: =SUM(K49:K51) -> 179308 | L52: =SUM(L49:L51) -> 169109 | M52: =SUM(M49:M51) -> 165450 | N52: =SUM(N49:N51) -> 166333 | O52: =SUM(O49:O51) -> 166543 | P52: =SUM(P49:P51) -> 162099 | ... W52: =SUM(W49:W51) -> 132986 | Y52: =SUM(Y49:Y51) -> 169109 | Z52: =SUM(Z49:Z51) -> 165450 | AA52: =SUM(AA49:AA51) -> 166333 | AB52: =SUM(AB49:AB51) -> 166543 | AC52: =SUM(AC49:AC51) -> 162099 | AD52: =SUM(AD49:AD51) -> 172575 | AE52: =SUM(AE49:AE51) -> 162337 | AF52: =SUM(AF49:AF51) -> 153041 | ... AJ52: =SUM(AJ49:AJ51) -> 132986
B54: Balance Sheet Metrics:
B55: Accounts Receivable | C55: ='Historical Financials'!G45 -> 16120 | D55: ='Historical Financials'!H45 -> 26278 | E55: ='Historical Financials'!I45 -> 28184 | F55: ='Historical Financials'!J45 -> 29508 | G55: ='Historical Financials'!K45 -> 66243 | I55: ='Historical Financials'!M45 -> 30213 | J55: ='Historical Financials'!N45 -> 20815 | K55: ='Historical Financials'!O45 -> 21803 | L55: ='Historical Financials'!P45 -> 28184 | M55: ='Historical Financials'!Q45 -> 23752 | N55: ='Historical Financials'!R45 -> 17936 | O55: ='Historical Financials'!S45 -> 19549 | P55: ='Historical Financials'!T45 -> 29508 | ... W55: ='Historical Financials'!AA45 -> 46835 | Y55: =L55 -> 28184 | Z55: =M55 -> 23752 | AA55: =N55 -> 17936 | AB55: =O55 -> 19549 | AC55: =P55 -> 29508 | AD55: =Q55 -> 23194 | AE55: =R55 -> 21837 | AF55: =S55 -> 22795 | ... AJ55: =W55 -> 46835
B56: Accounts Payable | C56: ='Historical Financials'!G55 -> 42296 | D56: ='Historical Financials'!H55 -> 54763 | E56: ='Historical Financials'!I55 -> 64115 | F56: ='Historical Financials'!J55 -> 62611 | G56: ='Historical Financials'!K55 -> 68960 | I56: ='Historical Financials'!M55 -> 74362 | J56: ='Historical Financials'!N55 -> 52682 | K56: ='Historical Financials'!O55 -> 48343 | L56: ='Historical Financials'!P55 -> 64115 | M56: ='Historical Financials'!Q55 -> 57918 | N56: ='Historical Financials'!R55 -> 42945 | O56: ='Historical Financials'!S55 -> 46699 | P56: ='Historical Financials'!T55 -> 62611 | ... W56: ='Historical Financials'!AA55 -> 50374 | Y56: =L56 -> 64115 | Z56: =M56 -> 57918 | AA56: =N56 -> 42945 | AB56: =O56 -> 46699 | AC56: =P56 -> 62611 | AD56: =Q56 -> 58146 | AE56: =R56 -> 45753 | AF56: =S56 -> 47574 | ... AJ56: =W56 -> 50374
B57: Inventories | C57: ='Historical Financials'!G46 -> 4061 | D57: ='Historical Financials'!H46 -> 6580 | E57: ='Historical Financials'!I46 -> 4946 | F57: ='Historical Financials'!J46 -> 6331 | G57: ='Historical Financials'!K46 -> 7286 | I57: ='Historical Financials'!M46 -> 5876 | J57: ='Historical Financials'!N46 -> 5460 | K57: ='Historical Financials'!O46 -> 5433 | L57: ='Historical Financials'!P46 -> 4946 | M57: ='Historical Financials'!Q46 -> 6820 | N57: ='Historical Financials'!R46 -> 7482 | O57: ='Historical Financials'!S46 -> 7351 | P57: ='Historical Financials'!T46 -> 6331 | ... W57: ='Historical Financials'!AA46 -> 5925 | AE57: =R57 -> 6232 | AF57: =S57 -> 6165 | AG57: =T57 -> 7286 | AH57: =U57 -> 6911 | AI57: =V57 -> 6269 | AJ57: =W57 -> 5925
B58: Property Plant, and Equiptment | C58: ='Historical Financials'!G50 -> 36766 | D58: ='Historical Financials'!H50 -> 39440 | E58: ='Historical Financials'!I50 -> 42117 | F58: ='Historical Financials'!J50 -> 43715 | G58: ='Historical Financials'!K50 -> 45680 | I58: ='Historical Financials'!M50 -> 39245 | J58: ='Historical Financials'!N50 -> 39304 | K58: ='Historical Financials'!O50 -> 40335 | L58: ='Historical Financials'!P50 -> 42117 | M58: ='Historical Financials'!Q50 -> 42951 | N58: ='Historical Financials'!R50 -> 43398 | O58: ='Historical Financials'!S50 -> 43550 | P58: ='Historical Financials'!T50 -> 43715 | ... W58: ='Historical Financials'!AA50 -> 48508 | Y58: =L58 -> 42117 | Z58: =M58 -> 42951 | AA58: =N58 -> 43398 | AB58: =O58 -> 43550 | AC58: =P58 -> 43715 | AD58: =Q58 -> 43666 | AE58: =R58 -> 43546 | AF58: =S58 -> 44502 | ... AJ58: =W58 -> 48508
B59: Current Liabilities | C59: ='Historical Financials'!G65 -> 258549 | D59: ='Historical Financials'!H65 -> 287912 | E59: ='Historical Financials'!I65 -> 302083 | F59: ='Historical Financials'!J65 -> 290437 | G59: ='Historical Financials'!K65 -> 308030 | I59: ='Historical Financials'!M65 -> 309259 | J59: ='Historical Financials'!N65 -> 283263 | K59: ='Historical Financials'!O65 -> 278202 | L59: ='Historical Financials'!P65 -> 302083 | M59: ='Historical Financials'!Q65 -> 290020 | N59: ='Historical Financials'!R65 -> 270002 | O59: ='Historical Financials'!S65 -> 274764 | P59: ='Historical Financials'!T65 -> 290437 | ... W59: ='Historical Financials'!AA65 -> 265665 | Y59: =L59 -> 302083 | Z59: =M59 -> 290020 | AA59: =N59 -> 270002 | AB59: =O59 -> 274764 | AC59: =P59 -> 290437 | AD59: =Q59 -> 279414 | AE59: =R59 -> 263217 | AF59: =S59 -> 264904 | ... AJ59: =W59 -> 265665
B60: Total Liabilities | C60: ='Historical Financials'!G65 -> 258549 | D60: ='Historical Financials'!H65 -> 287912 | E60: ='Historical Financials'!I65 -> 302083 | F60: ='Historical Financials'!J65 -> 290437 | G60: ='Historical Financials'!K65 -> 308030 | I60: ='Historical Financials'!M65 -> 309259 | J60: ='Historical Financials'!N65 -> 283263 | K60: ='Historical Financials'!O65 -> 278202 | L60: ='Historical Financials'!P65 -> 302083 | M60: ='Historical Financials'!Q65 -> 290020 | N60: ='Historical Financials'!R65 -> 270002 | O60: ='Historical Financials'!S65 -> 274764 | P60: ='Historical Financials'!T65 -> 290437 | ... W60: ='Historical Financials'!AA65 -> 265665 | Y60: =L60 -> 302083 | Z60: =M60 -> 290020 | AA60: =N60 -> 270002 | AB60: =O60 -> 274764 | AC60: =P60 -> 290437 | AD60: =Q60 -> 279414 | AE60: =R60 -> 263217 | AF60: =S60 -> 264904 | ... AJ60: =W60 -> 265665
B62: Summary Debt (BS):
B63: CPLTD | C63: =+'Historical Financials'!G58+'Historical Financials'!G59 -> 13769 | D63: =+'Historical Financials'!H58+'Historical Financials'!H59 -> 15613 | E63: =+'Historical Financials'!I58+'Historical Financials'!I59 -> 21110 | F63: =+'Historical Financials'!J58+'Historical Financials'!J59 -> 15807 | G63: =+'Historical Financials'!K58+'Historical Financials'!K59 -> 20879 | I63: =+'Historical Financials'!M58+'Historical Financials'!M59 -> 16169 | J63: =+'Historical Financials'!N58+'Historical Financials'!N59 -> 16658 | K63: =+'Historical Financials'!O58+'Historical Financials'!O59 -> 24991 | L63: =+'Historical Financials'!P58+'Historical Financials'!P59 -> 21110 | M63: =+'Historical Financials'!Q58+'Historical Financials'!Q59 -> 11483 | N63: =+'Historical Financials'!R58+'Historical Financials'!R59 -> 12574 | O63: =+'Historical Financials'!S58+'Historical Financials'!S59 -> 11209 | P63: =+'Historical Financials'!T58+'Historical Financials'!T59 -> 15807 | ... W63: =+'Historical Financials'!AA58+'Historical Financials'!AA59 -> 19268 | Y63: =L63 -> 21110 | Z63: =M63 -> 11483 | AA63: =N63 -> 12574 | AB63: =O63 -> 11209 | AC63: =P63 -> 15807 | AD63: =Q63 -> 12952 | AE63: =R63 -> 12759 | AF63: =S63 -> 15108 | ... AJ63: =W63 -> 19268
B64: LTD | C64: ='Historical Financials'!G62 -> 98667 | D64: ='Historical Financials'!H62 -> 109106 | E64: ='Historical Financials'!I62 -> 98959 | F64: ='Historical Financials'!J62 -> 95281 | G64: ='Historical Financials'!K62 -> 85750 | I64: ='Historical Financials'!M62 -> 106629 | J64: ='Historical Financials'!N62 -> 103323 | K64: ='Historical Financials'!O62 -> 94700 | L64: ='Historical Financials'!P62 -> 98959 | M64: ='Historical Financials'!Q62 -> 99627 | N64: ='Historical Financials'!R62 -> 97041 | O64: ='Historical Financials'!S62 -> 98071 | P64: ='Historical Financials'!T62 -> 95281 | ... W64: ='Historical Financials'!AA62 -> 82430 | Y64: =L64 -> 98959 | Z64: =M64 -> 99627 | AA64: =N64 -> 97041 | AB64: =O64 -> 98071 | AC64: =P64 -> 95281 | AD64: =Q64 -> 95088 | AE64: =R64 -> 91831 | AF64: =S64 -> 86196 | ... AJ64: =W64 -> 82430
B66: Commercial Paper Outstanding | C66: ='Historical Financials'!G58 -> 4996 | D66: ='Historical Financials'!H58 -> 6000 | E66: ='Historical Financials'!I58 -> 9982 | F66: ='Historical Financials'!J58 -> 5985 | G66: ='Historical Financials'!K58 -> 9967 | I66: ='Historical Financials'!M58 -> 5000 | J66: ='Historical Financials'!N58 -> 6999 | K66: ='Historical Financials'!O58 -> 10982 | L66: ='Historical Financials'!P58 -> 9982 | M66: ='Historical Financials'!Q58 -> 1743 | N66: ='Historical Financials'!R58 -> 1996 | O66: ='Historical Financials'!S58 -> 3993 | P66: ='Historical Financials'!T58 -> 5985 | ... W66: ='Historical Financials'!AA58 -> 9923 | Y66: =L66 -> 9982 | Z66: =M66 -> 1743 | AA66: =N66 -> 1996 | AB66: =O66 -> 3993 | AC66: =P66 -> 5985 | AD66: =Q66 -> 1998 | AE66: =R66 -> 1997 | AF66: =S66 -> 2994 | ... AJ66: =W66 -> 9923
B67: Aggregate Term Debt, Current Portion | C67: ='Historical Financials'!G59 -> 8773 | D67: ='Historical Financials'!H59 -> 9613 | E67: ='Historical Financials'!I59 -> 11128 | F67: ='Historical Financials'!J59 -> 9822 | G67: ='Historical Financials'!K59 -> 10912 | I67: ='Historical Financials'!M59 -> 11169 | J67: ='Historical Financials'!N59 -> 9659 | K67: ='Historical Financials'!O59 -> 14009 | L67: ='Historical Financials'!P59 -> 11128 | M67: ='Historical Financials'!Q59 -> 9740 | N67: ='Historical Financials'!R59 -> 10578 | O67: ='Historical Financials'!S59 -> 7216 | P67: ='Historical Financials'!T59 -> 9822 | ... W67: ='Historical Financials'!AA59 -> 9345 | AF67: =S67 -> 12114 | AG67: =T67 -> 10912 | AH67: =U67 -> 10848 | AI67: =V67 -> 13638 | AJ67: =W67 -> 9345
B68: Aggregate Term Debt, Net of Current Portion | C68: ='Historical Financials'!G62 -> 98667 | D68: ='Historical Financials'!H62 -> 109106 | E68: ='Historical Financials'!I62 -> 98959 | F68: ='Historical Financials'!J62 -> 95281 | G68: ='Historical Financials'!K62 -> 85750 | I68: ='Historical Financials'!M62 -> 106629 | J68: ='Historical Financials'!N62 -> 103323 | K68: ='Historical Financials'!O62 -> 94700 | L68: ='Historical Financials'!P62 -> 98959 | M68: ='Historical Financials'!Q62 -> 99627 | N68: ='Historical Financials'!R62 -> 97041 | O68: ='Historical Financials'!S62 -> 98071 | P68: ='Historical Financials'!T62 -> 95281 | ... W68: ='Historical Financials'!AA62 -> 82430 | Y68: =L68 -> 98959 | Z68: =M68 -> 99627 | AA68: =N68 -> 97041 | AB68: =O68 -> 98071 | AC68: =P68 -> 95281 | AD68: =Q68 -> 95088 | AE68: =R68 -> 91831 | AF68: =S68 -> 86196 | ... AJ68: =W68 -> 82430
B69: Total Debt | C69: =SUM(C66:C68) -> 112436 | D69: =SUM(D66:D68) -> 124719 | E69: =SUM(E66:E68) -> 120069 | F69: =SUM(F66:F68) -> 111088 | G69: =SUM(G66:G68) -> 106629 | I69: =SUM(I66:I68) -> 122798 | J69: =SUM(J66:J68) -> 119981 | K69: =SUM(K66:K68) -> 119691 | L69: =SUM(L66:L68) -> 120069 | M69: =SUM(M66:M68) -> 111110 | N69: =SUM(N66:N68) -> 109615 | O69: =SUM(O66:O68) -> 109280 | P69: =SUM(P66:P68) -> 111088 | ... W69: =SUM(W66:W68) -> 101698 | Y69: =SUM(Y66:Y68) -> 108941 | Z69: =SUM(Z66:Z68) -> 101370 | AA69: =SUM(AA66:AA68) -> 99037 | AB69: =SUM(AB66:AB68) -> 102064 | AC69: =SUM(AC66:AC68) -> 101266 | AD69: =SUM(AD66:AD68) -> 97086 | AE69: =SUM(AE66:AE68) -> 93828 | AF69: =SUM(AF66:AF68) -> 101304 | ... AJ69: =SUM(AJ66:AJ68) -> 101698
B71: Total Shareholder Equity | C71: ='Historical Financials'!G70 -> 65339 | D71: ='Historical Financials'!H70 -> 63090 | E71: ='Historical Financials'!I70 -> 50672 | F71: ='Historical Financials'!J70 -> 62146 | G71: ='Historical Financials'!K70 -> 56950 | I71: ='Historical Financials'!M70 -> 63894 | J71: ='Historical Financials'!N70 -> 59361 | K71: ='Historical Financials'!O70 -> 50069 | L71: ='Historical Financials'!P70 -> 50672 | M71: ='Historical Financials'!Q70 -> 48689 | N71: ='Historical Financials'!R70 -> 54120 | O71: ='Historical Financials'!S70 -> 52236 | P71: ='Historical Financials'!T70 -> 62146 | ... W71: ='Historical Financials'!AA70 -> 65830 | Y71: =L71 -> 50672 | Z71: =M71 -> 48689 | AA71: =N71 -> 54120 | AB71: =O71 -> 52236 | AC71: =P71 -> 62146 | AD71: =Q71 -> 66062 | AE71: =R71 -> 66156 | AF71: =S71 -> 58670 | ... AJ71: =W71 -> 65830
B72: Total Book Capitalization | C72: =SUM(C69:C71) -> 177775 | D72: =SUM(D69:D71) -> 187809 | E72: =SUM(E69:E71) -> 170741 | F72: =SUM(F69:F71) -> 173234 | G72: =SUM(G69:G71) -> 163579 | I72: =SUM(I69:I71) -> 186692 | J72: =SUM(J69:J71) -> 179342 | K72: =SUM(K69:K71) -> 169760 | L72: =SUM(L69:L71) -> 170741 | M72: =SUM(M69:M71) -> 159799 | N72: =SUM(N69:N71) -> 163735 | O72: =SUM(O69:O71) -> 161516 | P72: =SUM(P69:P71) -> 173234 | ... W72: =SUM(W69:W71) -> 167528 | Y72: =SUM(Y69:Y71) -> 159613 | Z72: =SUM(Z69:Z71) -> 150059 | AA72: =SUM(AA69:AA71) -> 153157 | AB72: =SUM(AB69:AB71) -> 154300 | AC72: =SUM(AC69:AC71) -> 163412 | AD72: =SUM(AD69:AD71) -> 163148 | AE72: =SUM(AE69:AE71) -> 159984 | AF72: =SUM(AF69:AF71) -> 159974 | ... AJ72: =SUM(AJ69:AJ71) -> 167528
B74: Credit Metrics
B76: Total Leverage | C76: =C69/C29 -> 1.3357728 | D76: =D69/D29 -> 0.97331023 | E76: =E69/E29 -> 0.86022253 | F76: =F69/F29 -> 0.81292032 | G76: =G69/G29 -> 0.72859398 | L76: =SUM(L69/SUM(I29:L29)) -> 0.86022253 | M76: =SUM(M69/SUM(J29:M29)) -> 0.82324437 | N76: =SUM(N69/SUM(K29:N29)) -> 0.81863331 | O76: =SUM(O69/SUM(L29:O29)) -> 0.81283518 | P76: =SUM(P69/SUM(M29:P29)) -> 0.81292032 | Q76: =SUM(Q69/SUM(N29:Q29)) -> 0.76605641 | R76: =SUM(R69/SUM(O29:R29)) -> 0.7426421 | S76: =SUM(S69/SUM(P29:S29)) -> 0.70725237 | ... W76: =SUM(W69/SUM(T29:W29)) -> 0.65937472 | Y76: =Y69/Y29 -> 0.78049707 | Z76: =Z69/Z29 -> 0.75107805 | AA76: =AA69/AA29 -> 0.73963406 | AB76: =AB69/AB29 -> 0.75916188 | AC76: =AC69/AC29 -> 0.74104484 | AD76: =AD69/AD29 -> 0.6883872 | AE76: =AE69/AE29 -> 0.66622644 | AF76: =AF69/AF29 -> 0.70725237 | ... AJ76: =AJ69/AJ29 -> 0.65937472
B77: Net Leverage (C&CE) | C77: =SUM(C69-C49)/C29 -> 0.88413149 | D77: =SUM(D69-D49)/D29 -> 0.70063759 | E77: =SUM(E69-E49)/E29 -> 0.69081309 | F77: =SUM(F69-F49)/F29 -> 0.59364229 | G77: =SUM(G69-G49)/G29 -> 0.52399401 | L77: =SUM(L69-L49)/SUM(I29:L29) -> 0.69081309 | M77: =SUM(M69-M49)/SUM(J29:M29) -> 0.67109494 | N77: =SUM(N69-N49)/SUM(K29:N29) -> 0.63426438 | O77: =SUM(O69-O49)/SUM(L29:O29) -> 0.60153374 | P77: =SUM(P69-P49)/SUM(M29:P29) -> 0.59364229 | Q77: =SUM(Q69-Q49)/SUM(N29:Q29) -> 0.47704809 | R77: =SUM(R69-R49)/SUM(O29:R29) -> 0.510491 | S77: =SUM(S69-S49)/SUM(P29:S29) -> 0.5287707 | ... W77: =SUM(W69-W49)/SUM(T29:W29) -> 0.42421904 | Y77: =SUM(Y69-Y49)/Y29 -> 0.61108763 | Z77: =SUM(Z69-Z49)/Z29 -> 0.59892862 | AA77: =SUM(AA69-AA49)/AA29 -> 0.55526512 | AB77: =SUM(AB69-AB49)/AB29 -> 0.54786043 | AC77: =SUM(AC69-AC49)/AC29 -> 0.52176681 | AD77: =SUM(AD69-AD49)/AD29 -> 0.39937887 | AE77: =SUM(AE69-AE49)/AE29 -> 0.43407534 | AF77: =SUM(AF69-AF49)/AF29 -> 0.5287707 | ... AJ77: =SUM(AJ69-AJ49)/AJ29 -> 0.42421904
B78: Interest Coverage | C78: =C29/-C33 -> 8.8593832 | D78: =D29/-D33 -> 5.0478235 | E78: =E29/-E33 -> 7.1312011 | F78: =F29/-F33 -> 7.3158627 | G78: =G29/-G33 -> 5.6068117 | L78: {=SUM(I29:L29)/SUM(-I33:L33)} -> 7.1312011 | M78: {=SUM(J29:M29)/SUM(-J33:M33)} -> 8.8992483 | N78: {=SUM(K29:N29)/SUM(-K33:N33)} -> 8.8289595 | O78: {=SUM(L29:O29)/SUM(-L33:O33)} -> 9.3740761 | P78: {=SUM(M29:P29)/SUM(-M33:P33)} -> 7.3158627 | Q78: {=SUM(N29:Q29)/SUM(-N33:Q33)} -> 5.6175416 | R78: {=SUM(O29:R29)/SUM(-O33:R33)} -> 4.9736898 | S78: {=SUM(P29:S29)/SUM(-P33:S33)} -> 4.63712 | ... W78: {=SUM(T29:W29)/SUM(-T33:W33)} -> 3.4891413 | Y78: =Y29/-Y33 -> 7.1312011 | Z78: =Z29/-Z33 -> 8.8992483 | AA78: =AA29/-AA33 -> 8.8289595 | AB78: =AB29/-AB33 -> 9.3740761 | AC78: =AC29/-AC33 -> 7.3158627 | AD78: =AD29/-AD33 -> 5.6175416 | AE78: =AE29/-AE33 -> 4.9736898 | AF78: =AF29/-AF33 -> 4.63712 | ... AJ78: =AJ29/-AJ33 -> 3.4891413
B79: Debt Service Coverage | C79: {=SUM(C29+C32)/SUM(-C33:C34)} -> 6.1476446 | D79: {=SUM(D29+D32)/SUM(-D33:D34)} -> 4.1697777 | E79: {=SUM(E29+E32)/SUM(-E33:E34)} -> 5.7434263 | F79: {=SUM(F29+F32)/SUM(-F33:F34)} -> 5.5908727 | G79: {=SUM(G29+G32)/SUM(-G33:G34)} -> 5.2448854 | L79: {=SUM(I29:L29+I32:L32)/SUM(-I33:L34)} -> 5.7434263 | M79: {=SUM(J29:M29+J32:M32)/SUM(-J33:M34)} -> 6.7721804 | N79: {=SUM(K29:N29+K32:N32)/SUM(-K33:N34)} -> 6.58482 | O79: {=SUM(L29:O29+L32:O32)/SUM(-L33:O34)} -> 6.8406105 | P79: {=SUM(M29:P29+M32:P32)/SUM(-M33:P34)} -> 5.5908727 | Q79: {=SUM(N29:Q29+N32:Q32)/SUM(-N33:Q34)} -> 4.661065 | R79: {=SUM(O29:R29+O32:R32)/SUM(-O33:R34)} -> 4.3705283 | S79: {=SUM(P29:S29+P32:S32)/SUM(-P33:S34)} -> 4.1908292 | ... W79: {=SUM(T29:W29+T32:W32)/SUM(-T33:W34)} -> 3.2090535 | Y79: {=SUM(Y29+Y32)/SUM(-Y33:Y34)} -> 5.7434263 | Z79: {=SUM(Z29+Z32)/SUM(-Z33:Z34)} -> 6.7721804 | AA79: {=SUM(AA29+AA32)/SUM(-AA33:AA34)} -> 6.58482 | AB79: {=SUM(AB29+AB32)/SUM(-AB33:AB34)} -> 6.8406105 | AC79: {=SUM(AC29+AC32)/SUM(-AC33:AC34)} -> 5.5908727 | AD79: {=SUM(AD29+AD32)/SUM(-AD33:AD34)} -> 4.661065 | AE79: {=SUM(AE29+AE32)/SUM(-AE33:AE34)} -> 4.3705283 | AF79: {=SUM(AF29+AF32)/SUM(-AF33:AF34)} -> 4.1908292 | ... AJ79: {=SUM(AJ29+AJ32)/SUM(-AJ33:AJ34)} -> 3.2090535
B80: Fixed Charge Coverage | C80: {=SUM(C29)/SUM(-C32:C34)} -> 4.2485867 | D80: {=SUM(D29)/SUM(-D32:D34)} -> 3.2724417 | E80: {=SUM(E29)/SUM(-E32:E34)} -> 4.211036 | F80: {=SUM(F29)/SUM(-F32:F34)} -> 4.086391 | G80: {=SUM(G29)/SUM(-G32:G34)} -> 4.1168247 | L80: {=SUM(I29:L29)/SUM(-I32:L34)} -> 4.211036 | M80: {=SUM(J29:M29)/SUM(-J32:M34)} -> 4.514668 | N80: {=SUM(K29:N29)/SUM(-K32:N34)} -> 4.3769613 | O80: {=SUM(L29:O29)/SUM(-L32:O34)} -> 4.4856199 | P80: {=SUM(M29:P29)/SUM(-M32:P34)} -> 4.086391 | Q80: {=SUM(N29:Q29)/SUM(-N32:Q34)} -> 3.7340217 | R80: {=SUM(O29:R29)/SUM(-O32:R34)} -> 3.621368 | S80: {=SUM(P29:S29)/SUM(-P32:S34)} -> 3.5103421 | ... W80: {=SUM(T29:W29)/SUM(-T32:W34)} -> 2.7257047 | Y80: {=SUM(Y29)/SUM(-Y32:Y34)} -> 4.211036 | Z80: {=SUM(Z29)/SUM(-Z32:Z34)} -> 4.514668 | AA80: {=SUM(AA29)/SUM(-AA32:AA34)} -> 4.3769613 | AB80: {=SUM(AB29)/SUM(-AB32:AB34)} -> 4.4856199 | AC80: {=SUM(AC29)/SUM(-AC32:AC34)} -> 4.086391 | AD80: {=SUM(AD29)/SUM(-AD32:AD34)} -> 3.7340217 | AE80: {=SUM(AE29)/SUM(-AE32:AE34)} -> 3.621368 | AF80: {=SUM(AF29)/SUM(-AF32:AF34)} -> 3.5103421 | ... AJ80: {=SUM(AJ29)/SUM(-AJ32:AJ34)} -> 2.7257047
B81: Debt-to-Book Capitalization | C81: =C72/C69 -> 1.5811217 | D81: =D72/D69 -> 1.5058572 | E81: =E72/E69 -> 1.422024 | F81: =F72/F69 -> 1.5594304 | G81: =G72/G69 -> 1.5340949 | L81: =L72/L69 -> 1.422024 | M81: =M72/M69 -> 1.4382054 | N81: =N72/N69 -> 1.493728 | O81: =O72/O69 -> 1.4780015 | P81: =P72/P69 -> 1.5594304 | Q81: =Q72/Q69 -> 1.6114587 | R81: =R72/R69 -> 1.632527 | S81: =S72/S69 -> 1.5791479 | ... W81: =W72/W69 -> 1.6473087 | Y81: =Y72/Y69 -> 1.4651325 | Z81: =Z72/Z69 -> 1.4803098 | AA81: =AA72/AA69 -> 1.5464624 | AB81: =AB72/AB69 -> 1.5117965 | AC81: =AC72/AC69 -> 1.6136907 | AD81: =AD72/AD69 -> 1.6804483 | AE81: =AE72/AE69 -> 1.7050774 | AF81: =AF72/AF69 -> 1.5791479 | ... AJ81: =AJ72/AJ69 -> 1.6473087

Sheet 3-Statement Model
B2: =C6&"(NASDAQ: AAPL)" -> Apple Inc. (NASDAQ: AAPL)
B3: 3-Statement Model
B4: $ mm except per share
B6: Company name | C6: Apple Inc. | I6: Select an operating scenario: | K6: Base case
B7: Ticker | C7: AAPL
B8: Circ break 1=off, 0=on | C8: 1
B9: Latest closing share price | C9: 262.82
B10: Latest closing share price date | C10: =NOW() -> 45961.736
B11: Latest fiscal year end date | C11: ='Historical Financials'!K12 -> 45559
B12: Shares outstanding (millions) | C12: 4443.265
A14: X | B14: Income Statement | C14: Actuals | G14: Forecast
B15: Fiscal year | C15: =D15-1 -> 2021 | D15: =E15-1 -> 2022 | E15: =F15-1 -> 2023 | F15: =YEAR(C11) -> 2024 | G15: =F15+1 -> 2025 | H15: =G15+1 -> 2026 | I15: =H15+1 -> 2027 | J15: =I15+1 -> 2028 | K15: =J15+1 -> 2029
B16: Fiscal year end date | C16: =EOMONTH(D16,-12) -> 44469 | D16: =EOMONTH(E16,-12) -> 44834 | E16: =EOMONTH(F16,-12) -> 45199 | F16: =C11 -> 45559 | G16: =EOMONTH(F16,12) -> 45930 | H16: =EOMONTH(G16,12) -> 46295 | I16: =EOMONTH(H16,12) -> 46660 | J16: =EOMONTH(I16,12) -> 47026 | K16: =EOMONTH(J16,12) -> 47391 | M16: Commentary
B18: ='Revenue Drivers'!B7 -> iPhone Revenue | C18: ='Revenue Drivers'!H7 -> 191973 | D18: ='Revenue Drivers'!I7 -> 205489 | E18: ='Revenue Drivers'!J7 -> 200583 | F18: ='Revenue Drivers'!K7 -> 201183 | G18: =F18*(1+G55) -> 209997 | H18: =G18*(1+H55) -> 221832.97 | I18: =H18*(1+I55) -> 234412.09 | J18: =I18*(1+J55) -> 243754.74 | K18: =J18*(1+K55) -> 253469.75 | M18: Previous year's revenues x (1+revenue growth rate)
B19: ='Revenue Drivers'!B8 -> Mac Revenue | C19: ='Revenue Drivers'!H8 -> 35190 | D19: ='Revenue Drivers'!I8 -> 40177 | E19: ='Revenue Drivers'!J8 -> 29357 | F19: ='Revenue Drivers'!K8 -> 29984 | G19: =F19*(1+G56) -> 33889.726 | H19: =G19*(1+H56) -> 34928.374 | I19: =H19*(1+I56) -> 36231.99 | J19: =I19*(1+J56) -> 37767.69 | K19: =J19*(1+K56) -> 39368.482
B20: ='Revenue Drivers'!B9 -> iPad Revenue | C20: ='Revenue Drivers'!H9 -> 31862 | D20: ='Revenue Drivers'!I9 -> 29292 | E20: ='Revenue Drivers'!J9 -> 28300 | F20: ='Revenue Drivers'!K9 -> 26694 | G20: =F20*(1+G57) -> 27924.321 | H20: =G20*(1+H57) -> 28098.397 | I20: =H20*(1+I57) -> 28709.607 | J20: =I20*(1+J57) -> 29570.485 | K20: =J20*(1+K57) -> 30457.177
B21: ='Revenue Drivers'!B10 -> Services Revenue | C21: ='Revenue Drivers'!H10 -> 68425 | D21: ='Revenue Drivers'!I10 -> 78129 | E21: ='Revenue Drivers'!J10 -> 85200 | F21: ='Revenue Drivers'!K10 -> 96169 | G21: =F21*(1+G58) -> 108694.5 | H21: =G21*(1+H58) -> 121735.44 | I21: =H21*(1+I58) -> 135521.32 | J21: =I21*(1+J58) -> 150697.52 | K21: =J21*(1+K58) -> 167573.2
B22: ='Revenue Drivers'!B11 -> Wearables, Home, and Accessories Revenue | C22: ='Revenue Drivers'!H11 -> 38367 | D22: ='Revenue Drivers'!I11 -> 41241 | E22: ='Revenue Drivers'!J11 -> 39845 | F22: ='Revenue Drivers'!K11 -> 37005 | G22: =F22*(1+G59) -> 35075.896 | H22: =G22*(1+H59) -> 36700.597 | I22: =H22*(1+I59) -> 38789.691 | J22: =I22*(1+J59) -> 41204.044 | K22: =J22*(1+K59) -> 43768.672
B23: Total Net Revenue | C23: =SUM(C18:C22) -> 365817 | D23: =SUM(D18:D22) -> 394328 | E23: =SUM(E18:E22) -> 383285 | F23: =SUM(F18:F22) -> 391035 | G23: =SUM(G18:G22) -> 415581.44 | H23: =SUM(H18:H22) -> 443295.78 | I23: =SUM(I18:I22) -> 473664.7 | J23: =SUM(J18:J22) -> 502994.48 | K23: =SUM(K18:K22) -> 534637.28
B24: Y/Y Growth (%) | D24: =SUM(D23/C23)-1 -> 0.077937876 | E24: =SUM(E23/D23)-1 -> -0.028004605 | F24: =SUM(F23/E23)-1 -> 0.020219941 | G24: =SUM(G23/F23)-1 -> 0.062773008 | H24: =SUM(H23/G23)-1 -> 0.066688096 | I24: =SUM(I23/H23)-1 -> 0.068507123 | J24: =SUM(J23/I23)-1 -> 0.061920976 | K24: =SUM(K23/J23)-1 -> 0.062908855
B26: Cost of Sales | C26: ='Historical Financials'!H17 -> -212981 | D26: ='Historical Financials'!I17 -> -223546 | E26: ='Historical Financials'!J17 -> -214137 | F26: ='Historical Financials'!K17 -> -210352 | G26: =+G27-G23 -> -221470.32 | H26: =+H27-H23 -> -234503.47 | I26: =+I27-I23 -> -247726.64 | J26: =+J27-J23 -> -260551.14 | K26: =+K27-K23 -> -276942.11 | M26: Plug = Revenue - Gross Profit
B27: Gross Profit | C27: =+C26+C23 -> 152836 | D27: =+D26+D23 -> 170782 | E27: =+E26+E23 -> 169148 | F27: =+F26+F23 -> 180683 | G27: =G61*G23 -> 194111.12 | H27: =H61*H23 -> 208792.31 | I27: =I61*I23 -> 225938.06 | J27: =J61*J23 -> 242443.34 | K27: =K61*K23 -> 257695.17 | M27: Revenue x Gross Profit Margin forecast
B28: Margin (%) | C28: =C27/C23 -> 0.4177936 | D28: =D27/D23 -> 0.43309631 | E28: =E27/E23 -> 0.4413113 | F28: =F27/F23 -> 0.4620635 | G28: =G27/G23 -> 0.46708323 | H28: =H27/H23 -> 0.471 | I28: =I27/I23 -> 0.477 | J28: =J27/J23 -> 0.482 | K28: =K27/K23 -> 0.482
B30: Research & Development (R&D) | C30: ='Historical Financials'!H21 -> -21914 | D30: ='Historical Financials'!I21 -> -26251 | E30: ='Historical Financials'!J21 -> -29915 | F30: ='Historical Financials'!K21 -> -31370 | G30: =-G62*G18 -> -25948.67 | H30: =-H62*H18 -> -28099.99 | I30: =-I62*I18 -> -30532.223 | J30: =-J62*J18 -> -32756.459 | K30: =-K62*K18 -> -33428.316 | M30: Revenue x R&D % of sales forecast
B31: Selling, General & Administrative (SG&A) | C31: ='Historical Financials'!H22 -> -21973 | D31: ='Historical Financials'!I22 -> -25094 | E31: ='Historical Financials'!J22 -> -24932 | F31: ='Historical Financials'!K22 -> -26097 | G31: =-G18*G63 -> -14054.908 | H31: =-H18*H63 -> -15167.052 | I31: =-I18*I63 -> -16216.786 | J31: =-J18*J63 -> -17282.676 | K31: =-K18*K63 -> -17515.171 | M31: Revenue x SG&A % of sales forecast
B32: Operating profit (EBIT) | C32: =C27+C30+C31 -> 108949 | D32: =D27+D30+D31 -> 119437 | E32: =E27+E30+E31 -> 114301 | F32: =+SUM(F27+SUM(F30:F31)) -> 123216 | G32: =G27+G30+G31 -> 154107.54 | H32: =H27+H30+H31 -> 165525.27 | I32: =I27+I30+I31 -> 179189.05 | J32: =J27+J30+J31 -> 192404.2 | K32: =K27+K30+K31 -> 206751.68 | M32: Gross Profit - R&D - SG&A
B33: Margin (%) | C33: =C32/C23 -> 0.29782378 | D33: =D32/D23 -> 0.30288744 | E33: =E32/E23 -> 0.29821412 | F33: =F32/F23 -> 0.31510223 | G33: =G32/G23 -> 0.37082393 | H33: =H32/H23 -> 0.3733969 | I33: =I32/I23 -> 0.37830358 | J33: =J32/J23 -> 0.38251752 | K33: =K32/K23 -> 0.38671393
B35: Interest Income | C35: 2843 | D35: 2825 | E35: 3750 | F35: 1583.2957 | G35: =G189 -> 1722.6586 | H35: =H189 -> 2071.7993 | I35: =I189 -> 2510.0353 | J35: =J189 -> 3052.946 | K35: =K189 -> 3707.6755 | M35: Reference from interest on cash schedule; Area of Model Mess Up
B36: Interest expense | C36: -2645 | D36: -2931 | E36: -3933 | F36: -515 | G36: =-G175 -> -2398.3918 | H36: =-H175 -> -2449.2168 | I36: =-I175 -> -2449.2168 | J36: =-J175 -> -2449.2168 | K36: =-K175 -> -2449.2168 | M36: Reference from interest expense schedule
B37: Other expense, net | C37: 60 | D37: -228 | E37: -382 | F37: -799.29575 | G37: =F37 -> -799.29575 | H37: =G37 -> -799.29575 | I37: =H37 -> -799.29575 | J37: =I37 -> -799.29575 | K37: =J37 -> -799.29575 | M37: Straight-line
B38: Pretax profit | C38: =SUM(C32:C37) -> 109207.3 | D38: =SUM(D32:D37) -> 119103.3 | E38: =SUM(E32:E37) -> 113736.3 | F38: =SUM(F32:F37) -> 123485.32 | G38: =SUM(G32:G37) -> 152632.89 | H38: =SUM(H32:H37) -> 164348.93 | I38: =SUM(I32:I37) -> 178450.95 | J38: =SUM(J32:J37) -> 192209.02 | K38: =SUM(K32:K37) -> 207211.23 | M38: EBIT + interest income less interest expense less other expense
B40: Taxes | C40: ='Historical Financials'!H29 -> -14527 | D40: ='Historical Financials'!I29 -> -19300 | E40: ='Historical Financials'!J29 -> -16741 | F40: ='Historical Financials'!K29 -> -29749 | G40: =-G64*G38 -> -24115.996 | H40: =-H64*H38 -> -26295.829 | I40: =-I64*I38 -> -28552.152 | J40: =-J64*J38 -> -30753.443 | K40: =-K64*K38 -> -33153.797 | M40: Pre-tax Profit x Tax Rate forecast
B41: Net income | C41: =SUM(C38:C40) -> 94680.298 | D41: =SUM(D38:D40) -> 99803.303 | E41: =SUM(E38:E40) -> 96995.298 | F41: =SUM(F38:F40) -> 93736.315 | G41: =SUM(G38:G40) -> 128516.89 | H41: =SUM(H38:H40) -> 138053.1 | I41: =SUM(I38:I40) -> 149898.8 | J41: =SUM(J38:J40) -> 161455.58 | K41: =SUM(K38:K40) -> 174057.44 | M41: Pre-tax Profit less taxes
B42: Margin (%) | C42: =C41/C23 -> 0.25881875 | D42: =D41/D23 -> 0.25309718 | E42: =E41/E23 -> 0.25306312 | F42: =F41/F23 -> 0.23971336 | G42: =G41/G23 -> 0.30924598 | H42: =H41/H23 -> 0.31142435 | I42: =I41/I23 -> 0.31646606 | J42: =J41/J23 -> 0.32098876 | K42: =K41/K23 -> 0.32556172
B44: Depreciation & amortization | C44: ='Historical Financials'!H83 -> 11284 | D44: ='Historical Financials'!I83 -> 11104 | E44: ='Historical Financials'!J83 -> 11519 | F44: ='Historical Financials'!K83 -> 11445 | G44: =G139 -> 12394.819 | H44: =H139 -> 11867.096 | I44: =I139 -> 13419.15 | J44: =J139 -> 13551.125 | K44: =K139 -> 13153.862 | M44: Reference from D&A schedule
B45: EBITDA | C45: =C32+C44 -> 120233 | D45: =D32+D44 -> 130541 | E45: =E32+E44 -> 125820 | F45: =F32+F44 -> 134661 | G45: =G32+G44 -> 166502.36 | H45: =H32+H44 -> 177392.37 | I45: =I32+I44 -> 192608.2 | J45: =J32+J44 -> 205955.33 | K45: =K32+K44 -> 219905.55 | M45: EBIT + D&A
B46: Margin (%) | C46: =C45/C23 -> 0.3286698 | D46: =D45/D23 -> 0.33104674 | E46: =E45/E23 -> 0.32826748 | F46: =F45/F23 -> 0.34437071 | G46: =G45/G23 -> 0.40064918 | H46: =H45/H23 -> 0.40016705 | I46: =I45/I23 -> 0.40663406 | J46: =J45/J23 -> 0.40945843 | K46: =K45/K23 -> 0.41131727
B48: Stock based compensation | C48: ='Historical Financials'!H84 -> 7906 | D48: ='Historical Financials'!I84 -> 9038 | E48: ='Historical Financials'!J84 -> 10833 | F48: ='Historical Financials'!K84 -> 11688 | G48: =F48*(1+G67) -> 12872.629 | H48: =G48*(1+H67) -> 13752.469 | I48: =H48*(1+I67) -> 14811.595 | J48: =I48*(1+J67) -> 15557.253 | K48: =J48*(1+K67) -> 16256.462 | M48: WSP assumption: grow SBC in-line with revenue growth
B49: Adjusted EBITDA | C49: =SUM(C45:C48) -> 128139.33 | D49: =SUM(D45:D48) -> 139579.33 | E49: =SUM(E45:E48) -> 136653.33 | F49: =SUM(F45:F48) -> 146349.34 | G49: =SUM(G45:G48) -> 179375.39 | H49: =SUM(H45:H48) -> 191145.23 | I49: =SUM(I45:I48) -> 207420.2 | J49: =SUM(J45:J48) -> 221512.99 | K49: =SUM(K45:K48) -> 236162.42 | M49: EBITDA + Stock-based compensation
B50: Margin (%) | C50: =C49/C23 -> 0.3502826 | D50: =D49/D23 -> 0.35396759 | E50: =E49/E23 -> 0.3565319 | F50: =F49/F23 -> 0.3742615 | G50: =G49/G23 -> 0.43162513 | H50: =H49/H23 -> 0.43119119 | I50: =I49/I23 -> 0.43790513 | J50: =J49/J23 -> 0.44038851 | K50: =K49/K23 -> 0.44172456
B52: Growth rates & margins
B54: Revenue growth | D54: =D23/C23-1 -> 0.077937876 | E54: =E23/D23-1 -> -0.028004605 | F54: =F23/E23-1 -> 0.020219941 | G54: ='Street Consensus'!L51 -> 0.061564822 | H54: ='Street Consensus'!M51 -> 0.062821839 | I54: ='Street Consensus'!N51 -> 0.068996967 | J54: ='Street Consensus'!O51 -> 0.053095052 | K54: ='Street Consensus'!P51 -> 0.06098213 | M54: Consensus estimates through 2030
B55: iPhone Revenue | D55: =SUM(D18/C18)-1 -> 0.070405734 | E55: =SUM(E18/D18)-1 -> -0.023874757 | F55: =SUM(F18/E18)-1 -> 0.0029912804 | G55: ='Street Consensus'!L64 -> 0.043810859 | H55: ='Street Consensus'!M64 -> 0.056362565 | I55: ='Street Consensus'!N64 -> 0.056705375 | J55: ='Street Consensus'!O64 -> 0.039855672 | K55: ='Street Consensus'!P64 -> 0.039855672 | M55: Consensus estimates through 2030
B56: Mac Revenue | D56: =SUM(D19/C19)-1 -> 0.1417164 | E56: =SUM(E19/D19)-1 -> -0.26930831 | F56: =SUM(F19/E19)-1 -> 0.021357768 | G56: ='Street Consensus'!L90 -> 0.13026034 | H56: ='Street Consensus'!M90 -> 0.030647887 | I56: ='Street Consensus'!N90 -> 0.037322528 | J56: ='Street Consensus'!O90 -> 0.042385208 | K56: ='Street Consensus'!P90 -> 0.042385208 | M56: Consensus estimates through 2030
B57: iPad Revenue | D57: =SUM(D20/C20)-1 -> -0.080660348 | E57: =SUM(E20/D20)-1 -> -0.033865902 | F57: =SUM(F20/E20)-1 -> -0.056749117 | G57: ='Street Consensus'!L78 -> 0.046089804 | H57: ='Street Consensus'!M78 -> 0.0062338519 | I57: ='Street Consensus'!N78 -> 0.021752458 | J57: ='Street Consensus'!O78 -> 0.029985721 | K57: ='Street Consensus'!P78 -> 0.029985721 | M57: Consensus estimates through 2030
B58: Services Revenue | D58: =SUM(D21/C21)-1 -> 0.14181951 | E58: =SUM(E21/D21)-1 -> 0.090504166 | F58: =SUM(F21/E21)-1 -> 0.12874413 | G58: ='Street Consensus'!L116 -> 0.13024467 | H58: ='Street Consensus'!M116 -> 0.11997792 | I58: ='Street Consensus'!N116 -> 0.11324458 | J58: ='Street Consensus'!O116 -> 0.11198384 | K58: ='Street Consensus'!P116 -> 0.11198384 | M58: Consensus estimates through 2030
B59: Wearables, Home, and Accessories Revenue | D59: =SUM(D22/C22)-1 -> 0.074908124 | E59: =SUM(E22/D22)-1 -> -0.03384981 | F59: =SUM(F22/E22)-1 -> -0.071276195 | G59: ='Street Consensus'!L104 -> -0.0521309 | H59: ='Street Consensus'!M104 -> 0.046319585 | I59: ='Street Consensus'!N104 -> 0.056922608 | J59: ='Street Consensus'!O104 -> 0.062242141 | K59: ='Street Consensus'!P104 -> 0.062242141 | M59: Consensus estimates through 2030
B61: Gross profit margin | C61: =C27/C23 -> 0.4177936 | D61: =D27/D23 -> 0.43309631 | E61: =E27/E23 -> 0.4413113 | F61: =F27/F23 -> 0.4620635 | G61: ='Street Consensus'!L133 -> 0.46708323 | H61: ='Street Consensus'!M133 -> 0.471 | I61: ='Street Consensus'!N133 -> 0.477 | J61: ='Street Consensus'!O133 -> 0.482 | K61: ='Street Consensus'!P133 -> 0.482 | M61: Consensus estimates through 2030
B62: R&D % of sales | C62: =-C30/C18 -> 0.11415147 | D62: =-D30/D18 -> 0.12774893 | E62: =-E30/E18 -> 0.14914026 | F62: =-F30/F18 -> 0.15592769 | G62: ='Street Consensus'!L146 -> 0.12356686 | H62: ='Street Consensus'!M146 -> 0.12667184 | I62: ='Street Consensus'!N146 -> 0.1302502 | J62: ='Street Consensus'!O146 -> 0.13438286 | K62: ='Street Consensus'!P146 -> 0.13188286 | M62: Consensus estimates through 2030
B63: SG&A % of sales | C63: =-C31/C18 -> 0.1144588 | D63: =-D31/D18 -> 0.12211846 | E63: =-E31/E18 -> 0.12429767 | F63: =-F31/F18 -> 0.12971772 | G63: ='Street Consensus'!L159 -> 0.066929088 | H63: ='Street Consensus'!M159 -> 0.068371495 | I63: ='Street Consensus'!N159 -> 0.069180674 | J63: ='Street Consensus'!O159 -> 0.070901908 | K63: ='Street Consensus'!P159 -> 0.069101623 | M63: Consensus estimates through 2030
B64: Tax rate | C64: =-(C40/C38) -> 0.13302225 | D64: =-(D40/D38) -> 0.1620442 | E64: =-(E40/E38) -> 0.14719136 | F64: =-(F40/F38) -> 0.24091124 | G64: ='Street Consensus'!L174 -> 0.158 | H64: ='Street Consensus'!M174 -> 0.16 | I64: ='Street Consensus'!N174 -> 0.16 | J64: ='Street Consensus'!O174 -> 0.16 | K64: ='Street Consensus'!P174 -> 0.16 | M64: Consensus estimates through 2030
B66: D&A | D66: =D44/C44-1 -> -0.01595179 | E66: =E44/D44-1 -> 0.037373919 | F66: =F44/E44-1 -> -0.0064241688 | G66: ='Street Consensus'!L189 -> 0.037276558 | H66: ='Street Consensus'!M189 -> 0.14078064 | I66: ='Street Consensus'!N189 -> 0.073981337 | J66: ='Street Consensus'!O189 -> 0.073981337 | K66: ='Street Consensus'!P189 -> 0.09151634 | M66: Consensus estimates through 2030
B67: SBC | D67: =D48/C48-1 -> 0.14318239 | E67: =E48/D48-1 -> 0.19860589 | F67: =F48/E48-1 -> 0.078925505 | G67: ='Street Consensus'!L200 -> 0.1013543 | H67: ='Street Consensus'!M200 -> 0.068349635 | I67: ='Street Consensus'!N200 -> 0.077013518 | J67: ='Street Consensus'!O200 -> 0.050342858 | K67: ='Street Consensus'!P200 -> 0.044944268 | M67: Consensus estimates through 2030
A69: X | B69: Balance Sheet | C69: Actuals | G69: Forecast
B70: =B15 -> Fiscal year | C70: =C15 -> 2021 | D70: =D15 -> 2022 | E70: =E15 -> 2023 | F70: =F15 -> 2024 | G70: =G15 -> 2025 | H70: =H15 -> 2026 | I70: =I15 -> 2027 | ... K70: =K15 -> 2029
B71: =B16 -> Fiscal year end date | C71: =C16 -> 44469 | D71: =D16 -> 44834 | E71: =E16 -> 45199 | F71: =F16 -> 45559 | G71: =G16 -> 45930 | H71: =H16 -> 46295 | I71: =I16 -> 46660 | ... K71: =K16 -> 47391
B73: Cash & equivalents, ST and LT marketable securities | C73: ='Historical Financials'!H43+'Historical Financials'!H44+'Historical Financials'!H51 -> 190516 | D73: ='Historical Financials'!I43+'Historical Financials'!I44+'Historical Financials'!I51 -> 169109 | E73: ='Historical Financials'!J43+'Historical Financials'!J44+'Historical Financials'!J51 -> 162099 | F73: ='Historical Financials'!K43+'Historical Financials'!K44+'Historical Financials'!K51 -> 156650 | G73: =+F73+G118 -> 187881.72 | H73: =+G73+H118 -> 226478.14 | I73: =+H73+I118 -> 275528.93 | J73: =+I73+J118 -> 335060.27 | K73: =+J73+K118 -> 406474.82 | M73: Reference from 'net change in cash' line on the cash flow statement
B74: Accounts receivable | C74: ='Historical Financials'!H45 -> 26278 | D74: ='Historical Financials'!I45 -> 28184 | E74: ='Historical Financials'!J45 -> 29508 | F74: ='Historical Financials'!K45 -> 66243 | G74: =F74*(1+G54) -> 70321.238 | H74: =G74*(1+H54) -> 74738.948 | I74: =H74*(1+I54) -> 79895.709 | J74: =I74*(1+J54) -> 84137.776 | K74: =J74*(1+K54) -> 89268.676 | M74: Grow in-line with revenue growth
B75: Inventories | C75: ='Historical Financials'!H46 -> 6580 | D75: ='Historical Financials'!I46 -> 4946 | E75: ='Historical Financials'!J46 -> 6331 | F75: ='Historical Financials'!K46 -> 7286 | G75: =F75*G26/F26 -> 7671.1073 | H75: =G75*H26/G26 -> 8122.5387 | I75: =H75*I26/H26 -> 8580.552 | J75: =I75*J26/I26 -> 9024.7566 | K75: =J75*K26/J26 -> 9592.4937 | M75: Grow in-line with cost of sales growth
B76: Other current assets | C76: ='Historical Financials'!H47 -> 39339 | D76: ='Historical Financials'!I47 -> 53971 | E76: ='Historical Financials'!J47 -> 46172 | F76: ='Historical Financials'!K47 -> 14287 | G76: =F76*(1+G54) -> 15166.577 | H76: =G76*(1+H54) -> 16119.369 | I76: =H76*(1+I54) -> 17231.556 | J76: =I76*(1+J54) -> 18146.467 | K76: =J76*(1+K54) -> 19253.077 | M76: Grow in-line with revenue growth
B77: Property, plant & equipment | C77: ='Historical Financials'!H50 -> 39440 | D77: ='Historical Financials'!I50 -> 42117 | E77: ='Historical Financials'!J50 -> 43715 | F77: ='Historical Financials'!K50 -> 45680 | G77: =G131 -> 43883.845 | H77: =H131 -> 42000.166 | I77: =I131 -> 40441.751 | J77: =J131 -> 39026.646 | K77: =K131 -> 37719.451 | M77: Reference from PP&E schedule
B78: Other non current assets | C78: ='Historical Financials'!H52 -> 48849 | D78: ='Historical Financials'!I52 -> 54428 | E78: ='Historical Financials'!J52 -> 64758 | F78: ='Historical Financials'!K52 -> 74834 | G78: =F78*(1+G54) -> 79441.142 | H78: =G78*(1+H54) -> 84431.78 | I78: =H78*(1+I54) -> 90257.317 | J78: =I78*(1+J54) -> 95049.534 | K78: =J78*(1+K54) -> 100845.86 | M78: Grow in-line with revenue growth
B79: Total Assets | C79: =SUM(C73:C78) -> 351002 | D79: =SUM(D73:D78) -> 352755 | E79: =SUM(E73:E78) -> 352583 | F79: =SUM(F73:F78) -> 364980 | G79: =SUM(G73:G78) -> 404365.63 | H79: =SUM(H73:H78) -> 451890.94 | I79: =SUM(I73:I78) -> 511935.81 | J79: =SUM(J73:J78) -> 580445.45 | K79: =SUM(K73:K78) -> 663154.38
B81: Accounts payable | C81: ='Historical Financials'!H55 -> 54763 | D81: ='Historical Financials'!I55 -> 64115 | E81: ='Historical Financials'!J55 -> 62611 | F81: ='Historical Financials'!K55 -> 68960 | G81: =F81*G26/F26 -> 72604.935 | H81: =G81*H26/G26 -> 76877.61 | I81: =H81*I26/H26 -> 81212.581 | J81: =I81*J26/I26 -> 85416.856 | K81: =J81*K26/J26 -> 90790.333 | M81: Grow in-line with cost of sales growth
B82: Other current liabilities | C82: ='Historical Financials'!H57 -> 47493 | D82: ='Historical Financials'!I57 -> 60845 | E82: ='Historical Financials'!J57 -> 58829 | F82: ='Historical Financials'!K57 -> 78304 | G82: =F82*(1+G54) -> 83124.772 | H82: =G82*(1+H54) -> 88346.823 | I82: =H82*(1+I54) -> 94442.486 | J82: =I82*(1+J54) -> 99456.914 | K82: =J82*(1+K54) -> 105522.01 | M82: Grow in-line with revenue growth
B83: Deferred revenue (current) | C83: ='Historical Financials'!H56 -> 7612 | D83: ='Historical Financials'!I56 -> 7912 | E83: ='Historical Financials'!J56 -> 8061 | F83: ='Historical Financials'!K56 -> 8249 | G83: =F83*(1+G54) -> 8756.8482 | H83: =G83*(1+H54) -> 9306.9695 | I83: =H83*(1+I54) -> 9949.1222 | J83: =I83*(1+J54) -> 10477.371 | K83: =J83*(1+K54) -> 11116.304 | M83: Grow in-line with revenue growth
B84: Commercial paper / revolver | C84: ='Historical Financials'!H58 -> 6000 | D84: ='Historical Financials'!I58 -> 9982 | E84: ='Historical Financials'!J58 -> 5985 | F84: ='Historical Financials'!K58 -> 9967 | G84: =G168 -> 12000 | H84: =H168 -> 12000 | I84: =I168 -> 12000 | J84: =J168 -> 12000 | K84: =K168 -> 12000 | M84: Reference EOP balance from CP/revolver schedule
B85: Long term debt (includes current portion) | C85: =+'Historical Financials'!H59+'Historical Financials'!H62 -> 118719 | D85: =+'Historical Financials'!I59+'Historical Financials'!I62 -> 110087 | E85: =+'Historical Financials'!J59+'Historical Financials'!J62 -> 105103 | F85: =+'Historical Financials'!K59+'Historical Financials'!K62 -> 96662 | G85: =F85 -> 96662 | H85: =G85 -> 96662 | I85: =H85 -> 96662 | J85: =I85 -> 96662 | K85: =J85 -> 96662 | M85: WSP assumption: straight-line
B86: Other non current liabilities | C86: ='Historical Financials'!H64 -> 53325 | D86: ='Historical Financials'!I64 -> 49142 | E86: ='Historical Financials'!J64 -> 49848 | F86: ='Historical Financials'!K64 -> 45888 | G86: =F86*(1+G54) -> 48713.087 | H86: =G86*(1+H54) -> 51773.332 | I86: =H86*(1+I54) -> 55345.535 | J86: =I86*(1+J54) -> 58284.109 | K86: =J86*(1+K54) -> 61838.398 | M86: Grow in-line with revenue growth
B87: Total liabilities | C87: =SUM(C81:C86) -> 287912 | D87: =SUM(D81:D86) -> 302083 | E87: =SUM(E81:E86) -> 290437 | F87: =SUM(F81:F86) -> 308030 | G87: =SUM(G81:G86) -> 321861.64 | H87: =SUM(H81:H86) -> 334966.73 | I87: =SUM(I81:I86) -> 349611.72 | J87: =SUM(J81:J86) -> 362297.25 | K87: =SUM(K81:K86) -> 377929.04
B89: Common stock | C89: ='Historical Financials'!H67 -> 57365 | D89: ='Historical Financials'!I67 -> 64849 | E89: ='Historical Financials'!J67 -> 73812 | F89: ='Historical Financials'!K67 -> 83276 | G89: =F89+G48 -> 96148.629 | H89: =G89+H48 -> 109901.1 | I89: =H89+I48 -> 124712.69 | J89: =I89+J48 -> 140269.94 | K89: =J89+K48 -> 156526.41 | M89: Increase by stock-based compensation forecasted in the I/S section
B90: Retained earnings | C90: ='Historical Financials'!H68 -> 5562 | D90: ='Historical Financials'!I68 -> -3068 | E90: ='Historical Financials'!J68 -> -214 | F90: ='Historical Financials'!K68 -> -19154 | G90: =G152 -> -6472.6396 | H90: =H152 -> 14195.109 | I90: =I152 -> 44783.398 | J90: =J152 -> 85050.258 | K90: =K152 -> 135870.93 | M90: Reference from Retained Earnings schedule
B91: Other comprehensive income | C91: ='Historical Financials'!H69 -> 163 | D91: ='Historical Financials'!I69 -> -11109 | E91: ='Historical Financials'!J69 -> -11452 | F91: ='Historical Financials'!K69 -> -7172 | G91: =F91 -> -7172 | H91: =G91 -> -7172 | I91: =H91 -> -7172 | J91: =I91 -> -7172 | K91: =J91 -> -7172 | M91: WSP assumption: straight-line
B92: Total equity | C92: =SUM(C89:C91) -> 63090 | D92: =SUM(D89:D91) -> 50672 | E92: =SUM(E89:E91) -> 62146 | F92: =SUM(F89:F91) -> 56950 | G92: =SUM(G89:G91) -> 82503.99 | H92: =SUM(H89:H91) -> 116924.21 | I92: =SUM(I89:I91) -> 162324.09 | J92: =SUM(J89:J91) -> 218148.2 | K92: =SUM(K89:K91) -> 285225.33
B93: Balance check | C93: =ROUND(C79-C87-C92,3) -> 0 | D93: =ROUND(D79-D87-D92,3) -> 0 | E93: =ROUND(E79-E87-E92,3) -> 0 | F93: =ROUND(F79-F87-F92,3) -> 0 | G93: =ROUND(G79-G87-G92,3) -> 0 | H93: =ROUND(H79-H87-H92,3) -> 0 | I93: =ROUND(I79-I87-I92,3) -> 0 | J93: =ROUND(J79-J87-J92,3) -> 0 | K93: =ROUND(K79-K87-K92,3) -> 0
A95: X | B95: Cash-Flows Statement | C95: Actuals | G95: Forecast
B96: =B15 -> Fiscal year | C96: =C70 -> 2021 | D96: =D70 -> 2022 | E96: =E70 -> 2023 | F96: =F70 -> 2024 | G96: =G15 -> 2025 | H96: =H15 -> 2026 | I96: =I15 -> 2027 | J96: =J15 -> 2028 | K96: =K15 -> 2029
B97: =B16 -> Fiscal year end date | C97: =C71 -> 44469 | D97: =D71 -> 44834 | E97: =E71 -> 45199 | F97: =F71 -> 45559 | G97: =G16 -> 45930 | H97: =H16 -> 46295 | I97: =I16 -> 46660 | J97: =J16 -> 47026 | K97: =K16 -> 47391
B99: Net income | D99: =D41 -> 99803.303 | E99: =E41 -> 96995.298 | F99: =F41 -> 93736.315 | G99: =G41 -> 128516.89 | H99: =H41 -> 138053.1 | I99: =I41 -> 149898.8 | J99: =J41 -> 161455.58 | K99: =K41 -> 174057.44 | M99: Reference from the I/S
B100: Depreciation and amortization | D100: =D44 -> 11104 | E100: =E44 -> 11519 | F100: =F44 -> 11445 | G100: =G44 -> 12394.819 | H100: =H44 -> 11867.096 | I100: =I44 -> 13419.15 | J100: =J44 -> 13551.125 | K100: =K44 -> 13153.862 | M100: Reference from the I/S
B101: Stock based compensation | D101: =D48 -> 9038 | E101: =E48 -> 10833 | F101: =F48 -> 11688 | G101: =G48 -> 12872.629 | H101: =H48 -> 13752.469 | I101: =I48 -> 14811.595 | J101: =J48 -> 15557.253 | K101: =K48 -> 16256.462
B102: Decreases / (Increases) in working capital assets | D102: =SUM(C74:C76)-SUM(D74:D76) -> -14904 | E102: =SUM(D74:D76)-SUM(E74:E76) -> 5090 | F102: =SUM(E74:E76)-SUM(F74:F76) -> -5805 | G102: =SUM(F74:F76)-SUM(G74:G76) -> -5342.9224 | H102: =SUM(G74:G76)-SUM(H74:H76) -> -5821.9331 | I102: =SUM(H74:H76)-SUM(I74:I76) -> -6726.9616 | J102: =SUM(I74:I76)-SUM(J74:J76) -> -5601.1818 | K102: =SUM(J74:J76)-SUM(K74:K76) -> -6805.248
B103: Increases / (Decreases) in working capital liabilities | D103: =SUM(D81:D83)-SUM(C81:C83) -> 23004 | E103: =SUM(E81:E83)-SUM(D81:D83) -> -3371 | F103: =SUM(F81:F83)-SUM(E81:E83) -> 26012 | G103: =SUM(G81:G83)-SUM(F81:F83) -> 8973.5553 | H103: =SUM(H81:H83)-SUM(G81:G83) -> 10044.847 | I103: =SUM(I81:I83)-SUM(H81:H83) -> 11072.786 | J103: =SUM(J81:J83)-SUM(I81:I83) -> 9746.9531 | K103: =SUM(K81:K83)-SUM(J81:J83) -> 12077.503
B104: Other non current assets | D104: =-D144 -> 0 | E104: =-E144 -> 0 | F104: =-F144 -> 0 | G104: =-G144 -> -25112.806 | H104: =-H144 -> -26652.055 | I104: =-I144 -> -28715.272 | J104: =-J144 -> -28594.238 | K104: =-K144 -> -30546.989 | M104: Reference from schedule NOT the B/S: Only include 'Additions' (as outflow)
B105: Other non current liabilities | D105: =D86-C86 -> -4183 | E105: =E86-D86 -> 706 | F105: =F86-E86 -> -3960 | G105: =G86-F86 -> 2825.0865 | H105: =H86-G86 -> 3060.2457 | I105: =I86-H86 -> 3572.2029 | J105: =J86-I86 -> 2938.5741 | K105: =K86-J86 -> 3554.2891
B106: Cash from Operating Activities | D106: =SUM(D99:D105) -> 123862.3 | E106: =SUM(E99:E105) -> 121772.3 | F106: =SUM(F99:F105) -> 133116.32 | G106: =SUM(G99:G105) -> 135127.25 | H106: =SUM(H99:H105) -> 144303.77 | I106: =SUM(I99:I105) -> 157332.3 | J106: =SUM(J99:J105) -> 169054.06 | K106: =SUM(K99:K105) -> 181747.32
B108: Capital Expenditures | D108: =-(D129) -> 10708 | E108: =-(E129) -> 10959 | F108: =-(F129) -> 9447 | G108: =-(G129) -> 9907 | H108: =-(H129) -> 11678 | I108: =-(I129) -> 11029 | J108: =-(J129) -> 11666 | K108: =-(K129) -> 12904 | M108: Reference from PP&E schedule
B109: Cash from Investing Activities | D109: =IFERROR(D108,"NA") -> 10708 | E109: =IFERROR(E108,"NA") -> 10959 | F109: =IFERROR(F108,"NA") -> 9447 | G109: =IFERROR(G108,"NA") -> 9907 | H109: =IFERROR(H108,"NA") -> 11678 | I109: =IFERROR(I108,"NA") -> 11029 | J109: =IFERROR(J108,"NA") -> 11666 | K109: =IFERROR(K108,"NA") -> 12904
B111: Long term debt | D111: =D85-C85 -> -8632 | E111: =E85-D85 -> -4984 | F111: =F85-E85 -> -8441 | G111: =G85-F85 -> 0 | H111: =H85-G85 -> 0 | I111: =I85-H85 -> 0 | J111: =J85-I85 -> 0 | K111: =K85-J85 -> 0
B112: Commercial paper/ Revolver | D112: =D84-C84 -> 3982 | E112: =E84-D84 -> -3997 | F112: =F84-E84 -> 3982 | G112: =G84-F84 -> 2033 | H112: =H84-G84 -> 0 | I112: =I84-H84 -> 0 | J112: =J84-I84 -> 0 | K112: =K84-J84 -> 0 | M112: Reference from B/S
B113: Share repurchases | D113: =D151 -> 0 | E113: =E151 -> 0 | F113: =F151 -> -94949 | G113: =G151 -> -94949 | H113: =H151 -> -94949 | I113: =I151 -> -94949 | J113: =J151 -> -94949 | K113: =K151 -> -94949 | M113: Reference from Retained Earnings schedule
B114: Common dividends | D114: =D150 -> 0 | E114: =E150 -> 0 | F114: =F150 -> -15234 | G114: =G150 -> -20886.529 | H114: =H150 -> -22436.352 | I114: =I150 -> -24361.511 | J114: =J150 -> -26239.715 | K114: =K150 -> -28287.766 | M114: Reference from Retained Earnings schedule
B115: Common dividends | D115: =D151 -> 0 | E115: =E151 -> 0 | F115: =F151 -> -94949 | G115: =G151 -> -94949 | H115: =H151 -> -94949 | I115: =I151 -> -94949 | J115: =J151 -> -94949 | K115: =K151 -> -94949 | M115: Reference from Retained Earnings schedule
B116: Cash from Financing Activities | D116: =SUM(D111:D114) -> -4650 | E116: =SUM(E111:E114) -> -8981 | F116: =SUM(F111:F114) -> -114642 | G116: =SUM(G111:G114) -> -113802.53 | H116: =SUM(H111:H114) -> -117385.35 | I116: =SUM(I111:I114) -> -119310.51 | J116: =SUM(J111:J114) -> -121188.72 | K116: =SUM(K111:K114) -> -123236.77
B118: Net change in cash during period | D118: =D106+D109+D116 -> 129920.3 | E118: =E106+E109+E116 -> 123750.3 | F118: =F106+F109+F116 -> 27921.315 | G118: =G106+G109+G116 -> 31231.722 | H118: =H106+H109+H116 -> 38596.419 | I118: =I106+I109+I116 -> 49050.789 | J118: =J106+J109+J116 -> 59531.345 | K118: =K106+K109+K116 -> 71414.549
A120: X | B120: Supporting Schedules | C120: Actuals | G120: Forecast
B121: Fiscal year | C121: 2021 | D121: 2022 | E121: 2023 | F121: 2024 | G121: 2025 | H121: 2026 | I121: 2027 | J121: 2028 | K121: 2029
B122: Fiscal year end date | C122: 44469 | D122: 44834 | E122: 45199 | F122: 45559 | G122: 45930 | H122: 46295 | I122: 46660 | J122: 47026 | K122: 47391
A124: X | B124: PROPERTY, PLANT & EQUIPMENT
B125: =B15 -> Fiscal year | D125: =D15 -> 2022 | E125: =E15 -> 2023 | F125: =F15 -> 2024 | G125: =G15 -> 2025 | H125: =H15 -> 2026 | I125: =I15 -> 2027 | J125: =J15 -> 2028 | K125: =K15 -> 2029
...

Sheet DCF
B2: ='3-Statement Model'!C6&"(NASDAQ: AAPL)" -> Apple Inc. (NASDAQ: AAPL)
B3: Discounted Cash Flow Valuation
B4: $ and shares in millions, except per share data
B6: Most recent fiscal year end | C6: ='Historical Financials'!K12 -> 45559 | F6: Discount rate (WACC) | H6: =WACC!E23 -> 0.088863708 | I6: Link from WACC
B7: End of first fiscal year | C7: =EOMONTH(C6,12) -> 45930 | F7: Share price (Public Co) | H7: 262.82 | I7: Source: CIQ
B8: Most recent quarter end date | C8: ='Historical Financials'!AA12 -> 45833 | F8: Share price date | H8: 45956
B9: Valuation date | C9: 45956 | F9: Midyear adjustment? | H9: 1
B10: Portion of First Year Cash Flows | C10: =YEARFRAC(C9,C7) -> 0.072222222 | F10: Case active: | H10: ='3-Statement Model'!K6 -> Base case
B12: Unlevered Free Cash Flows
C13: LTM | D13: Actual | E13: Forecasts
B14: Fiscal year ended | C14: =C9 -> 45956 | D14: =C6 -> 45559 | E14: =EOMONTH(D14,12) -> 45930 | F14: =EOMONTH(E14,12) -> 46295 | G14: =EOMONTH(F14,12) -> 46660 | H14: =EOMONTH(G14,12) -> 47026 | I14: =EOMONTH(H14,12) -> 47391
B16: Revenue | C16: =FCF!AJ11 -> 408625 | D16: =FCF!G11 -> 391035 | E16: ='3-Statement Model'!G18 -> 209997 | F16: ='3-Statement Model'!H18 -> 221832.97 | G16: ='3-Statement Model'!I18 -> 234412.09 | H16: ='3-Statement Model'!J18 -> 243754.74 | I16: ='3-Statement Model'!K18 -> 253469.75
B17: % growth | E17: =SUM(E16/D16)-1 -> -0.46297135 | F17: =SUM(F16/E16)-1 -> 0.056362565 | G17: =SUM(G16/F16)-1 -> 0.056705375 | H17: =SUM(H16/G16)-1 -> 0.039855672 | I17: =SUM(I16/H16)-1 -> 0.039855672
B18: EBITDA | C18: =FCF!AJ25 -> 141696 | D18: =FCF!G25 -> 134661 | E18: ='3-Statement Model'!G45 -> 166502.36 | F18: ='3-Statement Model'!H45 -> 177392.37 | G18: ='3-Statement Model'!I45 -> 192608.2 | H18: ='3-Statement Model'!J45 -> 205955.33 | I18: ='3-Statement Model'!K45 -> 219905.55
B19: % margin | D19: =D18/D16 -> 0.34437071 | E19: =E18/E16 -> 0.79287972 | F19: =F18/F16 -> 0.79966637 | G19: =G18/G16 -> 0.82166496 | H19: =H18/H16 -> 0.84492849 | I19: =I18/I16 -> 0.86758102
B20: EBIT | C20: =FCF!AJ21 -> 130214 | D20: =FCF!G21 -> 123216 | E20: ='3-Statement Model'!G32 -> 154107.54 | F20: ='3-Statement Model'!H32 -> 165525.27 | G20: ='3-Statement Model'!I32 -> 179189.05 | H20: ='3-Statement Model'!J32 -> 192404.2 | I20: ='3-Statement Model'!K32 -> 206751.68
B21: % margin | D21: =D20/D16 -> 0.31510223 | E21: =E20/E16 -> 0.73385593 | F21: =F20/F16 -> 0.74617073 | G21: =G20/G16 -> 0.76441898 | H21: =H20/H16 -> 0.78933522 | I21: =I20/I16 -> 0.81568583
B23: Tax on EBIT | D23: ='3-Statement Model'!F40 -> -29749 | E23: =+E20*E24 -> 24348.992 | F23: =+F20*F24 -> 26484.043 | G23: =+G20*G24 -> 28670.248 | H23: =+H20*H24 -> 30784.672 | I23: =+I20*I24 -> 33080.269
B24: Tax rate | D24: =D23/D20 -> -0.2414378 | E24: ='3-Statement Model'!G64 -> 0.158 | F24: ='3-Statement Model'!H64 -> 0.16 | G24: ='3-Statement Model'!I64 -> 0.16 | H24: ='3-Statement Model'!J64 -> 0.16 | I24: ='3-Statement Model'!K64 -> 0.16
B25: NOPAT (aka EBIAT) | D25: =+D23+D20 -> 93467 | E25: =E20*(1-E24) -> 129758.55 | F25: =F20*(1-F24) -> 139041.23 | G25: =G20*(1-G24) -> 150518.8 | H25: =H20*(1-H24) -> 161619.53 | I25: =I20*(1-I24) -> 173671.41
B27: Depreciation & amortization | D27: ='3-Statement Model'!F44 -> 11445 | E27: ='3-Statement Model'!G44 -> 12394.819 | F27: ='3-Statement Model'!H44 -> 11867.096 | G27: ='3-Statement Model'!I44 -> 13419.15 | H27: ='3-Statement Model'!J44 -> 13551.125 | I27: ='3-Statement Model'!K44 -> 13153.862
B28: Changes in net working capital | E28: =D34-E34 -> 17500.522 | F28: =E34-F34 -> -1550.3027 | G28: =F34-G34 -> -1932.9676 | H28: =G34-H34 -> 2451.613 | I28: =H34-I34 -> -3534.6166
B29: Capital expenditures | E29: =-'3-Statement Model'!G108 -> -9907 | F29: =-'3-Statement Model'!H108 -> -11678 | G29: =-'3-Statement Model'!I108 -> -11029 | H29: =-'3-Statement Model'!J108 -> -11666 | I29: =-'3-Statement Model'!K108 -> -12904
B30: as % of revenue | E30: =E29/E16 -> -0.047176864 | F30: =F29/F16 -> -0.052643212 | G30: =G29/G16 -> -0.047049621 | H30: =H29/H16 -> -0.047859582 | I30: =I29/I16 -> -0.050909428
B32: Unlevered free cash flows (UFCF) | E32: =+E25+E27+E28+E29 -> 149746.89 | F32: =+F25+F27+F28+F29 -> 137680.02 | G32: =+G25+G27+G28+G29 -> 150975.99 | H32: =+H25+H27+H28+H29 -> 165956.27 | I32: =+I25+I27+I28+I29 -> 170386.66
B34: Net working capital (WC Assets - WC liabilities) | D34: =SUM('3-Statement Model'!F103)-SUM('3-Statement Model'!F102) -> 31817 | E34: =SUM('3-Statement Model'!G103)-SUM('3-Statement Model'!G102) -> 14316.478 | F34: =SUM('3-Statement Model'!H103)-SUM('3-Statement Model'!H102) -> 15866.78 | G34: =SUM('3-Statement Model'!I103)-SUM('3-Statement Model'!I102) -> 17799.748 | H34: =SUM('3-Statement Model'!J103)-SUM('3-Statement Model'!J102) -> 15348.135 | I34: =SUM('3-Statement Model'!K103)-SUM('3-Statement Model'!K102) -> 18882.751
B35: as % of revenue | E35: =+E34/E16 -> 0.068174677 | F35: =+F34/F16 -> 0.071525799 | G35: =+G34/G16 -> 0.075933574 | H35: =+H34/H16 -> 0.062965482 | I35: =+I34/I16 -> 0.074497061
B37: ="Present value of UFCF on "&TEXT(C9,"mmm dd, yyyy")&" valuation date" -> Present value of UFCF on Oct 26, 2025 valuation date
D39: Val date | E39: Yr 1 - Stub | F39: Year 2 | G39: Year 3 | H39: Year 4 | I39: Year 5
B40: Date for discounting cash flows | D40: =C9 -> 45956 | E40: =IF($H$9=1,AVERAGE(E14,D40),E14) -> 45943 | F40: =IF($H$9=1,AVERAGE(F14,E14),F14) -> 46112.5 | G40: =IF($H$9=1,AVERAGE(G14,F14),G14) -> 46477.5 | H40: =IF($H$9=1,AVERAGE(H14,G14),H14) -> 46843 | I40: =IF($H$9=1,AVERAGE(I14,H14),I14) -> 47208.5
B41: Unlevered free cash flows (UFCF) stub adjusted | C41: =C10 -> 0.072222222 | E41: =E32*C41 -> 10815.053 | F41: =F32 -> 137680.02 | G41: =G32 -> 150975.99 | H41: =H32 -> 165956.27 | I41: =I32 -> 170386.66 | K41: <-Stub year counts first year cash flows starting at the valuation date
B42: Present value of of unlevered free cash flows | E42: =E41/(1+$H$6)^((E40-$C$9)/365) -> 10847.897 | F42: =F41/(1+$H$6)^((F40-$C$9)/365) -> 132744.91 | G42: =G41/(1+$H$6)^((G40-$C$9)/365) -> 133684.58 | H42: =H41/(1+$H$6)^((H40-$C$9)/365) -> 134940.69 | I42: =I41/(1+$H$6)^((I40-$C$9)/365) -> 127221.55
B44: Terminal value - growth in perpetuity approach | E44: Terminal value - EBITDA multiple approach
B46: Long term growth rate | C46: 0.03 | E46: Terminal year EBITDA | I46: =I18 -> 219905.55
B47: =YEAR(I14)&" FCF x (1+g)" -> 2029 FCF x (1+g) | C47: =I41*(1+C46) -> 175498.26 | E47: EBITDA multiple | I47: 16.2
B48: ="Terminal value in "&YEAR(I14) -> Terminal value in 2029 | C48: =C47/(H6-C46) -> 2981434 | E48: ="Terminal value in "&YEAR(I14) -> Terminal value in 2029 | I48: =I46*I47 -> 3562469.8
B49: Present value of terminal value | C49: =C48/(1+H6)^((I40-$D$40)/365) -> 2226128.9 | E49: Present value of terminal value | I49: =I48/(1+H6)^((I40-D40)/365) -> 2659967.3
B50: Present value of stage 1 cash flows | C50: =SUM(E42:I42) -> 539439.64 | E50: Present value of stage 1 cash flows | I50: =C50 -> 539439.64
B51: Total enterprise value (TEV) | C51: =C50+C49 -> 2765568.5 | E51: Enterprise value (stage 1 + 2) | I51: =SUM(I49:I50) -> 3199406.9
B53: Terminal value as % of TEV | C53: =C49/$C$51 -> 0.8049444 | E53: Terminal value as % of TEV | I53: =+I49/I51 -> 0.83139387
B54: Stage 1 cash flows as % of TEV | C54: =1-C53 -> 0.1950556 | E54: Cash flows as % of TEV | I54: =1-I53 -> 0.16860613
B55: Implied TV exit EBITDA multiple | C55: =(C48/I18) -> 13.557794 | E55: Implied terminal growth rate | I55: =(H6-I41/I48)/(1+I41/I48) -> 0.0391624
B57: Net debt | E57: Shares outstanding
B58: Source doc | C58: 3Q25 10Q
B59: Source date | C59: =C8 -> 45833 | G59: Source doc | H59: Date | I59: Shares
B60: Gross debt and equivalents | E60: Basic shares | G60: Capital IQ | H60: =NOW() -> 45961.736 | I60: 14840.39
B61: Debt | C61: =FCF!AJ69 -> 101698 | E61: Restricted stock / RSUs | G61: 3Q25 10Q | H61: 45833 | I61: 149.976
B62: Convertible debt | C62: =[1]Shares!E25+[1]Shares!E31 -> 0 | E62: Options / warrants | G62: 3Q25 10Q | H62: 45833 | I62: =Shares!E19 -> 0
B63: Preferred stock | C63: =[1]Shares!E34+[1]Shares!E41 -> 0 | E63: Convertible debt | G63: 3Q25 10Q | H63: 45833 | I63: =0 -> 0
B64: Noncontrolling (minority) interests | C64: 0 | E64: Convertible preferred stock | G64: 3Q25 10Q | H64: 45833 | I64: 0
B65: Nonoperating assets | E65: Net diluted shares outstanding | I65: =SUM(I60:I64) -> 14990.366
B66: Cash | C66: =FCF!AJ52 -> 132986
B67: Equity investments | C67: 0
B68: Net debt | C68: =SUM(C61:C64)-SUM(C66:C67) -> -31288
B70: Valuation
C72: Perpetuity | D72: EBITDA
B73: Enterprise value | C73: =C51 -> 2765568.5 | D73: =I51 -> 3199406.9
B74: Net debt | C74: =$C$68 -> -31288 | D74: =C74 -> -31288
B75: Equity value | C75: =C73-C74 -> 2796856.5 | D75: =D73-D74 -> 3230694.9
B76: Shares outstanding | C76: =$I$65 -> 14990.366 | D76: =C76 -> 14990.366
B77: Equity value per share | C77: =C75/C76 -> 186.57693 | D77: =D75/D76 -> 215.51808
C79: Last twelve months (LTM)
C80: Perpetuity | D80: EBITDA
B81: EV / Revenue | C81: =C$73/$C$16 -> 6.7679866 | D81: =D$73/$C$16 -> 7.8296897
B82: EV / EBITDA | C82: =C73/$C$18 -> 19.517619 | D82: =D73/$C$18 -> 22.579374
B83: EV / EBIT | C83: =C73/$C$20 -> 21.238642 | D83: =D73/$C$20 -> 24.570376
C84: Year 1
C85: Perpetuity | D85: EBITDA
B86: EV / Revenue | C86: =C73/$E$16 -> 13.169562 | D86: =D73/$E$16 -> 15.235489
B87: EV / EBITDA | C87: =C73/$E$18 -> 16.609785 | D87: =D73/$E$18 -> 19.215385
B88: EV / EBIT | C88: =C73/$E$20 -> 17.945705 | D88: =D73/$E$20 -> 20.760872
B90: Outputs
D92: Equity value per share | L92: LTM EBITDA multiple
E93: Long term growth rate (g):
D94: =C77 -> 186.57693 | E94: =F94-0.005 -> 0.02 | F94: =G94-0.005 -> 0.025 | G94: 0.03 | H94: =G94+0.005 -> 0.035 | I94: =H94+0.005 -> 0.04 | L94: =C82 -> 19.517619 | M94: =N94-0.005 -> 0.02 | N94: =O94-0.005 -> 0.025 | O94: 0.03 | P94: =O94+0.005 -> 0.035 | Q94: =P94+0.005 -> 0.04
D95: =D96+0.01 -> 0.11 | E95: 20.680633 | F95: 20.680633 | G95: 20.680633 | H95: 20.680633 | I95: 20.680633 | L95: =L96+0.01 -> 0.11 | M95: #DIV/0! | N95: #DIV/0! | O95: #DIV/0! | P95: #DIV/0! | Q95: #DIV/0!
D96: =D97+0.01 -> 0.1 | E96: 20.680633 | F96: 20.680633 | G96: 20.680633 | H96: 20.680633 | I96: 20.680633 | L96: =L97+0.01 -> 0.1 | M96: #DIV/0! | N96: #DIV/0! | O96: #DIV/0! | P96: #DIV/0! | Q96: #DIV/0!
C97: WACC: | D97: 0.09 | E97: 20.680633 | F97: 20.680633 | G97: 20.680633 | H97: 20.680633 | I97: 20.680633 | K97: WACC: | L97: 0.09 | M97: #DIV/0! | N97: #DIV/0! | O97: #DIV/0! | P97: #DIV/0! | Q97: #DIV/0!
D98: =D97-0.01 -> 0.08 | E98: 20.680633 | F98: 20.680633 | G98: 20.680633 | H98: 20.680633 | I98: 20.680633 | L98: =L97-0.01 -> 0.08 | M98: #DIV/0! | N98: #DIV/0! | O98: #DIV/0! | P98: #DIV/0! | Q98: #DIV/0!
B99: Data | D99: =D98-0.01 -> 0.07 | E99: 20.680633 | F99: 20.680633 | G99: 20.680633 | H99: 20.680633 | I99: 20.680633 | L99: =L98-0.01 -> 0.07 | M99: #DIV/0! | N99: #DIV/0! | O99: #DIV/0! | P99: #DIV/0! | Q99: #DIV/0!
B100: Tables
D101: Equity value per share | L101: LTM EBITDA multiple
E102: Exit EBITDA Multiple | M102: Exit EBITDA Multiple
D103: =D77 -> 215.51808 | E103: =F103-1 -> 11 | F103: =G103-1 -> 12 | G103: 13 | H103: =G103+1 -> 14 | I103: =H103+1 -> 15 | L103: =D82 -> 22.579374 | M103: =N103-1 -> 11 | N103: =O103-1 -> 12 | O103: 13 | P103: =O103+1 -> 14 | Q103: =P103+1 -> 15
D104: =D105+0.01 -> 0.11 | E104: 20.680633 | F104: 20.680633 | G104: 20.680633 | H104: 20.680633 | I104: 20.680633 | L104: =L105+0.01 -> 0.11 | M104: #DIV/0! | N104: #DIV/0! | O104: #DIV/0! | P104: #DIV/0! | Q104: #DIV/0!
D105: =D106+0.01 -> 0.1 | E105: 20.680633 | F105: 20.680633 | G105: 20.680633 | H105: 20.680633 | I105: 20.680633 | L105: =L106+0.01 -> 0.1 | M105: #DIV/0! | N105: #DIV/0! | O105: #DIV/0! | P105: #DIV/0! | Q105: #DIV/0!
C106: WACC: | D106: 0.09 | E106: 20.680633 | F106: 20.680633 | G106: 20.680633 | H106: 20.680633 | I106: 20.680633 | K106: WACC: | L106: 0.09 | M106: #DIV/0! | N106: #DIV/0! | O106: #DIV/0! | P106: #DIV/0! | Q106: #DIV/0!
D107: =D106-0.01 -> 0.08 | E107: 20.680633 | F107: 20.680633 | G107: 20.680633 | H107: 20.680633 | I107: 20.680633 | L107: =L106-0.01 -> 0.08 | M107: #DIV/0! | N107: #DIV/0! | O107: #DIV/0! | P107: #DIV/0! | Q107: #DIV/0!
D108: =D107-0.01 -> 0.07 | E108: 20.680633 | F108: 20.680633 | G108: 20.680633 | H108: 20.680633 | I108: 20.680633 | L108: =L107-0.01 -> 0.07 | M108: #DIV/0! | N108: #DIV/0! | O108: #DIV/0! | P108: #DIV/0! | Q108: #DIV/0!
B110: Equity value range | G110: Football field
C131: Low | D131: Diff. | E131: High | O131: Low | P131: Diff. | Q131: High
B132: ="DCF Value at "&TEXT(E103,"0.0x")&"-"&TEXT(I103,"0.0x")&" Exit EBITDA Range at "&TEXT(D106,"0.0%")&" WACC" -> DCF Value at 11.0x-15.0x Exit EBITDA Range at 9.0% WACC | C132: =E106 -> 20.680633 | D132: =E132-C132 -> 0 | E132: =I106 -> 20.680633 | G132: ="LTM EBITDA Purchase Multiple at "&TEXT(M94,"0.0%")&"-"&TEXT(Q94,"0.0%")&" Perpetuity Growth at "&TEXT(L97,"0.0%")&" WACC" -> LTM EBITDA Purchase Multiple at 2.0%-4.0% Perpetuity Growth at 9.0% WACC | O132: =M97 -> #DIV/0! | P132: =Q132-O132 -> #DIV/0! | Q132: =Q97 -> #DIV/0!
B133: ="DCF Value at "&TEXT(E94,"0.0%")&"-"&TEXT(I94,"0.0%")&" Perpetuity Range at "&TEXT(D106,"0.0%")&" WACC" -> DCF Value at 2.0%-4.0% Perpetuity Range at 9.0% WACC | C133: =E97 -> 20.680633 | D133: =E133-C133 -> 0 | E133: =I97 -> 20.680633 | G133: ="LTM EBITDA Purchase Multiple at "&TEXT(M106,"0.0x")&"-"&TEXT(Q106,"0.0x")&" Exit EBITDA Multiple at "&TEXT(L106,"0.0%")&" WACC" -> #DIV/0! | O133: =M106 -> #DIV/0! | P133: =Q133-O133 -> #DIV/0! | Q133: =Q106 -> #DIV/0!
B134: 52 Week Market High/Low | C134: 169.5 | D134: =E134-C134 -> 158.35 | E134: 327.85 | G134: ="LTM EBITDA Purchase Multiple at "&TEXT(L108,"0.0%")&"-"&TEXT(L104,"0.0%")&" WACC at "&TEXT(O103,"0.0x")&" Exit EBITDA" -> LTM EBITDA Purchase Multiple at 7.0%-11.0% WACC at 13.0x Exit EBITDA | O134: =O104 -> #DIV/0! | P134: =Q134-O134 -> #DIV/0! | Q134: =O108 -> #DIV/0!

Sheet Street Consensus
B2: Apple Inc. (NASDAQ: AAPL) | C2: Actuals | J2: CAGR | L2: Forecast | S2: CAGR
B3: Street Outlook | C3: 2019 | D3: 2020 | E3: 2021 | F3: 2022 | G3: 2023 | H3: 2024 | J3: 5-Year(A) | L3: 2025 | M3: 2026 | N3: 2027 | O3: 2028 | P3: 2029 | Q3: 2030 | S3: 5-Year(F)
B4: $ mm except per share | C4: 43737 | D4: 44104 | E4: 44469 | F4: 44834 | G4: 45192 | H4: 45559 | J4: =H4 -> 45559 | L4: 45930 | M4: 46295 | N4: 46660 | O4: 47026 | P4: 47391 | Q4: 47756 | S4: =Q4 -> 47756
B6: iPhone Revenue | C6: ='Revenue Drivers'!F7 -> 142381 | D6: ='Revenue Drivers'!G7 -> 137781 | E6: ='Revenue Drivers'!H7 -> 191973 | F6: ='Revenue Drivers'!I7 -> 205489 | G6: ='Revenue Drivers'!J7 -> 200583 | H6: ='Revenue Drivers'!K7 -> 201183 | J6: =((H6/C6)^(1/COUNT(D6:H6))-1) -> 0.071588016 | L6: =(H6*L64)+H6 -> 209997 | M6: =(L6*M64)+L6 -> 221832.97 | N6: =(M6*N64)+M6 -> 234412.09 | O6: =(N6*O64)+N6 -> 243754.74 | P6: =(O6*P64)+O6 -> 253469.75 | Q6: =(P6*Q64)+P6 -> 263571.96 | S6: =((Q6/H6)^(1/COUNT(L6:Q6))-1) -> 0.046047295
B7: iPad Revenue | C7: ='Revenue Drivers'!F9 -> 21280 | D7: ='Revenue Drivers'!G9 -> 23724 | E7: ='Revenue Drivers'!H9 -> 31862 | F7: ='Revenue Drivers'!I9 -> 29292 | G7: ='Revenue Drivers'!J9 -> 28300 | H7: ='Revenue Drivers'!K9 -> 26694 | J7: =((H7/C7)^(1/COUNT(D7:H7))-1) -> 0.046377534 | L7: =(H7*L77)+H7 -> 27887.642 | M7: =(L7*M77)+L7 -> 28651.914 | N7: =(M7*N77)+M7 -> 29238.671 | O7: =(N7*O77)+N7 -> 29986.062 | P7: =(O7*P77)+O7 -> 30752.557 | Q7: =(P7*Q77)+P7 -> 31538.645 | S7: =((Q7/H7)^(1/COUNT(L7:Q7))-1) -> 0.028185709
B8: Mac Revenue | C8: ='Revenue Drivers'!F8 -> 25740 | D8: ='Revenue Drivers'!G8 -> 28622 | E8: ='Revenue Drivers'!H8 -> 35190 | F8: ='Revenue Drivers'!I8 -> 40177 | G8: ='Revenue Drivers'!J8 -> 29357 | H8: ='Revenue Drivers'!K8 -> 29984 | J8: =((H8/C8)^(1/COUNT(D8:H8))-1) -> 0.03099416 | L8: =(H8*L90)+H8 -> 33889.726 | M8: =(L8*M90)+L8 -> 34928.374 | N8: =(M8*N90)+M8 -> 36231.99 | O8: =(N8*O90)+N8 -> 37767.69 | P8: =(O8*P90)+O8 -> 39368.482 | Q8: =(P8*Q90)+P8 -> 41037.123 | S8: =((Q8/H8)^(1/COUNT(L8:Q8))-1) -> 0.053694118
B9: Wearables, Home, and Accessories Revenue | C9: ='Revenue Drivers'!F11 -> 24482 | D9: ='Revenue Drivers'!G11 -> 30620 | E9: ='Revenue Drivers'!H11 -> 38367 | F9: ='Revenue Drivers'!I11 -> 41241 | G9: ='Revenue Drivers'!J11 -> 39845 | H9: ='Revenue Drivers'!K11 -> 37005 | J9: =((H9/C9)^(1/COUNT(D9:H9))-1) -> 0.086132235 | L9: =(H9*L104)+H9 -> 35075.896 | M9: =(L9*M104)+L9 -> 36700.597 | N9: =(M9*N104)+M9 -> 38789.691 | O9: =(N9*O104)+N9 -> 41204.044 | P9: =(O9*P104)+O9 -> 43768.672 | Q9: =(P9*Q104)+P9 -> 46492.928 | S9: =((Q9/H9)^(1/COUNT(L9:Q9))-1) -> 0.038774025
B10: Services Revenue | C10: ='Revenue Drivers'!F10 -> 46291 | D10: ='Revenue Drivers'!G10 -> 53768 | E10: ='Revenue Drivers'!H10 -> 68425 | F10: ='Revenue Drivers'!I10 -> 78129 | G10: ='Revenue Drivers'!J10 -> 85200 | H10: ='Revenue Drivers'!K10 -> 96169 | J10: =((H10/C10)^(1/COUNT(D10:H10))-1) -> 0.15746457 | L10: =(H10*L116)+H10 -> 108694.5 | M10: =(L10*M116)+L10 -> 121735.44 | N10: =(M10*N116)+M10 -> 135521.32 | O10: =(N10*O116)+N10 -> 150697.52 | P10: =(O10*P116)+O10 -> 167573.2 | Q10: =(P10*Q116)+P10 -> 186338.69 | S10: =((Q10/H10)^(1/COUNT(L10:Q10))-1) -> 0.11654952
B11: Total Revenue | C11: =SUM(C6:C10) -> 260174 | D11: =SUM(D6:D10) -> 274515 | E11: =SUM(E6:E10) -> 365817 | F11: =SUM(F6:F10) -> 394328 | G11: =SUM(G6:G10) -> 383285 | H11: =SUM(H6:H10) -> 391035 | J11: =((H11/C11)^(1/COUNT(D11:H11))-1) -> 0.084901594 | L11: =SUM(L6:L10) -> 415544.76 | M11: =SUM(M6:M10) -> 443849.3 | N11: =SUM(N6:N10) -> 474193.76 | O11: =SUM(O6:O10) -> 503410.05 | P11: =SUM(P6:P10) -> 534932.66 | Q11: =SUM(Q6:Q10) -> 568979.35 | S11: =((Q11/H11)^(1/COUNT(L11:Q11))-1) -> 0.064502809
B13: Cost of sales | C13: ='Historical Financials'!F17 -> -161782 | D13: ='Historical Financials'!G17 -> -169559 | E13: ='Historical Financials'!H17 -> -212981 | F13: ='Historical Financials'!I17 -> -223546 | G13: ='Historical Financials'!J17 -> -214137 | H13: ='Historical Financials'!K17 -> -210352 | J13: =((H13/C13)^(1/COUNT(D13:H13))-1) -> 0.053909427 | L13: =-(L11-L14) -> -221450.77 | M13: =-(M11-M14) -> -234796.28 | N13: =-(N11-N14) -> -248003.34 | O13: =-(O11-O14) -> -260766.41 | P13: =-(P11-P14) -> -277095.12 | Q13: =-(Q11-Q14) -> -294731.3 | S13: =((Q13/L13)^(1/COUNT(M13:Q13))-1) -> 0.058838713
B14: Gross Profit | C14: =+C13+C11 -> 98392 | D14: =+D13+D11 -> 104956 | E14: =+E13+E11 -> 152836 | F14: =+F13+F11 -> 170782 | G14: =+G13+G11 -> 169148 | H14: =+H13+H11 -> 180683 | J14: =((H14/C14)^(1/COUNT(D14:H14))-1) -> 0.12925364 | L14: =L11*L133 -> 194093.99 | M14: =M11*M133 -> 209053.02 | N14: =N11*N133 -> 226190.42 | O14: =O11*O133 -> 242643.65 | P14: =P11*P133 -> 257837.54 | Q14: =Q11*Q133 -> 274248.04 | S14: =((Q14/L14)^(1/COUNT(M14:Q14))-1) -> 0.071584173
B16: Research & Development | C16: ='Historical Financials'!F21 -> -16217 | D16: ='Historical Financials'!G21 -> -18752 | E16: ='Historical Financials'!H21 -> -21914 | F16: ='Historical Financials'!I21 -> -26251 | G16: ='Historical Financials'!J21 -> -29915 | H16: ='Historical Financials'!K21 -> -31370 | J16: =((H16/C16)^(1/COUNT(D16:H16))-1) -> 0.14106084 | L16: =-(L146*L11) -> -51347.563 | M16: =-(M146*M11) -> -56223.207 | N16: =-(N146*N11) -> -61763.834 | O16: =-(O146*O11) -> -67649.682 | P16: =-(P146*P11) -> -70548.449 | Q16: =-(Q146*Q11) -> -74634.757 | S16: =((Q16/L16)^(1/COUNT(M16:Q16))-1) -> 0.07766619
B17: Selling, General & Administrative | C17: ='Historical Financials'!F22 -> -18245 | D17: ='Historical Financials'!G22 -> -19916 | E17: ='Historical Financials'!H22 -> -21973 | F17: ='Historical Financials'!I22 -> -25094 | G17: ='Historical Financials'!J22 -> -24932 | H17: ='Historical Financials'!K22 -> -26097 | J17: =((H17/C17)^(1/COUNT(D17:H17))-1) -> 0.074210377 | L17: =-(L159*L11) -> -27812.032 | M17: =-(M159*M11) -> -30346.64 | N17: =-(N159*N11) -> -32805.044 | O17: =-(O159*O11) -> -35692.733 | P17: =-(P159*P11) -> -36964.715 | Q17: =-(Q159*Q11) -> -39206.228 | S17: =((Q17/L17)^(1/COUNT(M17:Q17))-1) -> 0.071086308
B18: Operating profit (EBIT) | C18: =SUM(C16:C17)+C14 -> 63930 | D18: =SUM(D16:D17)+D14 -> 66288 | E18: =SUM(E16:E17)+E14 -> 108949 | F18: =SUM(F16:F17)+F14 -> 119437 | G18: =SUM(G16:G17)+G14 -> 114301 | H18: =SUM(H16:H17)+H14 -> 123216 | J18: =((H18/C18)^(1/COUNT(D18:H18))-1) -> 0.14023004 | L18: =SUM(L16:L17)+L14 -> 114934.39 | M18: =SUM(M16:M17)+M14 -> 122483.17 | N18: =SUM(N16:N17)+N14 -> 131621.55 | O18: =SUM(O16:O17)+O14 -> 139301.23 | P18: =SUM(P16:P17)+P14 -> 150324.38 | Q18: =SUM(Q16:Q17)+Q14 -> 160407.06 | S18: =((Q18/L18)^(1/COUNT(M18:Q18))-1) -> 0.068943357
B20: Interest income | C20: 4961 | D20: 3763 | E20: 2843 | F20: 2825 | G20: 3750 | H20: 1583.2957 | J20: =((H20/C20)^(1/COUNT(D20:H20))-1) -> -0.20420984 | L20: =+(H20*L51)+H20 -> 1680.7711 | M20: =+(L20*M51)+L20 -> 1786.3602 | N20: =+(M20*N51)+M20 -> 1909.6136 | O20: =+(N20*O51)+N20 -> 2011.0047 | P20: =+(O20*P51)+O20 -> 2133.64 | Q20: =+(P20*Q51)+P20 -> 2263.7539 | S20: =((Q20/L20)^(1/COUNT(M20:Q20))-1) -> 0.061363457
B21: Interest expense | C21: -3576 | D21: -2873 | E21: -2645 | F21: -2931 | G21: -3933 | H21: -515 | J21: =((H21/C21)^(1/COUNT(D21:H21))-1) -> -0.3212936 | L21: =H21 -> -515 | M21: =L21 -> -515 | N21: =M21 -> -515 | O21: =N21 -> -515 | P21: =O21 -> -515 | Q21: =P21 -> -515 | S21: =((Q21/L21)^(1/COUNT(M21:Q21))-1) -> 0
B22: Other expense, net | C22: -422 | D22: -87 | E22: 60 | F22: -228 | G22: -382 | H22: -799.29575 | J22: =((H22/C22)^(1/COUNT(D22:H22))-1) -> 0.13626338 | L22: =H22 -> -799.29575 | M22: =L22 -> -799.29575 | N22: =M22 -> -799.29575 | O22: =N22 -> -799.29575 | P22: =O22 -> -799.29575 | Q22: =P22 -> -799.29575 | S22: =((Q22/L22)^(1/COUNT(M22:Q22))-1) -> 0
B23: Pretax profit | C23: =SUM(C20:C22)+C18 -> 64893 | D23: =SUM(D20:D22)+D18 -> 67091 | E23: =SUM(E20:E22)+E18 -> 109207 | F23: =SUM(F20:F22)+F18 -> 119103 | G23: =SUM(G20:G22)+G18 -> 113736 | H23: =SUM(H20:H22)+H18 -> 123485 | J23: =((H23/C23)^(1/COUNT(D23:H23))-1) -> 0.13732156 | L23: =SUM(L20:L22)+L18 -> 115300.87 | M23: =SUM(M20:M22)+M18 -> 122955.24 | N23: =SUM(N20:N22)+N18 -> 132216.86 | O23: =SUM(O20:O22)+O18 -> 139997.94 | P23: =SUM(P20:P22)+P18 -> 151143.72 | Q23: =SUM(Q20:Q22)+Q18 -> 161356.52 | S23: =((Q23/L23)^(1/COUNT(M23:Q23))-1) -> 0.069524618
B25: Taxes | C25: ='Historical Financials'!F29 -> -10481 | D25: ='Historical Financials'!G29 -> -9680 | E25: ='Historical Financials'!H29 -> -14527 | F25: ='Historical Financials'!I29 -> -19300 | G25: ='Historical Financials'!J29 -> -16741 | H25: ='Historical Financials'!K29 -> -29749 | J25: =((H25/C25)^(1/COUNT(D25:H25))-1) -> 0.23200914 | L25: =+(H25*L174)+H25 -> -34449.342 | M25: =+(L25*M174)+L25 -> -39961.237 | N25: =+(M25*N174)+M25 -> -46355.035 | O25: =+(N25*O174)+N25 -> -53771.84 | P25: =+(O25*P174)+O25 -> -62375.335 | Q25: =+(P25*Q174)+P25 -> -72355.388 | S25: =((Q25/L25)^(1/COUNT(M25:Q25))-1) -> 0.16
B26: Net income | C26: =+C23+C25 -> 54412 | D26: =+D23+D25 -> 57411 | E26: =+E23+E25 -> 94680 | F26: =+F23+F25 -> 99803 | G26: =+G23+G25 -> 96995 | H26: =+H23+H25 -> 93736 | J26: =((H26/C26)^(1/COUNT(D26:H26))-1) -> 0.11491651 | L26: =+L23+L25 -> 80851.528 | M26: =+M23+M25 -> 82993.999 | N26: =+N23+N25 -> 85861.829 | O26: =+O23+O25 -> 86226.099 | P26: =+P23+P25 -> 88768.389 | Q26: =+Q23+Q25 -> 89001.129 | S26: =((Q26/L26)^(1/COUNT(M26:Q26))-1) -> 0.019392554
B28: Depreciation & Amortization | C28: ='Historical Financials'!F83 -> 12547 | D28: ='Historical Financials'!G83 -> 11056 | E28: ='Historical Financials'!H83 -> 11284 | F28: ='Historical Financials'!I83 -> 11104 | G28: ='Historical Financials'!J83 -> 11519 | H28: ='Historical Financials'!K83 -> 11445 | J28: =((H28/C28)^(1/COUNT(D28:H28))-1) -> -0.018217742 | L28: =+(H28*L189)+H28 -> 11871.63 | M28: =+(L28*M189)+L28 -> 13542.926 | N28: =+(M28*N189)+M28 -> 14544.85 | O28: =+(N28*O189)+N28 -> 15620.897 | P28: =+(O28*P189)+O28 -> 17050.464 | Q28: =+(P28*Q189)+P28 -> 18690.543 | S28: =((Q28/L28)^(1/COUNT(M28:Q28))-1) -> 0.095020657
B29: EBITDA | C29: =+C18+C28 -> 76477 | D29: =+D18+D28 -> 77344 | E29: =+E18+E28 -> 120233 | F29: =+F18+F28 -> 130541 | G29: =+G18+G28 -> 125820 | H29: =+H18+H28 -> 134661 | J29: =((H29/C29)^(1/COUNT(D29:H29))-1) -> 0.11980447 | L29: =+L18+L28 -> 126806.03 | M29: =+M18+M28 -> 136026.1 | N29: =+N18+N28 -> 146166.4 | O29: =+O18+O28 -> 154922.13 | P29: =+P18+P28 -> 167374.84 | Q29: =+Q18+Q28 -> 179097.6 | S29: =((Q29/L29)^(1/COUNT(M29:Q29))-1) -> 0.071494575
B31: Stock Based Compensation | C31: ='Historical Financials'!F84 -> 6068 | D31: ='Historical Financials'!G84 -> 6829 | E31: ='Historical Financials'!H84 -> 7906 | F31: ='Historical Financials'!I84 -> 9038 | G31: ='Historical Financials'!J84 -> 10833 | H31: ='Historical Financials'!K84 -> 11688 | J31: =((H31/C31)^(1/COUNT(D31:H31))-1) -> 0.14008945 | L31: =+(H31*L200)+H31 -> 12872.629 | M31: =+(L31*M200)+L31 -> 13752.469 | N31: =+(M31*N200)+M31 -> 14811.595 | O31: =+(N31*O200)+N31 -> 15557.253 | P31: =+(O31*P200)+O31 -> 16256.462 | Q31: =+(P31*Q200)+P31 -> 17148.465 | S31: =((Q31/L31)^(1/COUNT(M31:Q31))-1) -> 0.05903814
B32: Adj. EBITDA | C32: =+C29+C31 -> 82545 | D32: =+D29+D31 -> 84173 | E32: =+E29+E31 -> 128139 | F32: =+F29+F31 -> 139579 | G32: =+G29+G31 -> 136653 | H32: =+H29+H31 -> 146349 | J32: =((H32/C32)^(1/COUNT(D32:H32))-1) -> 0.12134641 | L32: =+L29+L31 -> 139678.65 | M32: =+M29+M31 -> 149778.57 | N32: =+N29+N31 -> 160977.99 | O32: =+O29+O31 -> 170479.38 | P32: =+P29+P31 -> 183631.31 | Q32: =+Q29+Q31 -> 196246.07 | S32: =((Q32/L32)^(1/COUNT(M32:Q32))-1) -> 0.070370631
B35: Revenue Drivers | J35: Consensus
A37: X | B37: iPhone Revenue | D37: =SUM(D6/C6)-1 -> -0.032307682 | E37: =SUM(E6/D6)-1 -> 0.39331983 | F37: =SUM(F6/E6)-1 -> 0.070405734 | G37: =SUM(G6/F6)-1 -> -0.023874757 | H37: =SUM(H6/G6)-1 -> 0.0029912804 | J37: Total Revenue
B38: (%) of Total Revenue | C38: =C6/C$11 -> 0.54725299 | D38: =D6/D$11 -> 0.501907 | E38: =E6/E$11 -> 0.52477878 | F38: =F6/F$11 -> 0.52111187 | G38: =G6/G$11 -> 0.52332598 | H38: =H6/H$11 -> 0.51448847 | J38: BofA | L38: =+L55+L68+L94+L107+L81 -> 416040.4 | M38: =+M55+M68+M94+M107+M81 -> 447778.31 | N38: =+N55+N68+N94+N107+N81 -> 482123.51 | O38: =+O55+O68+O94+O107+O81 -> 482123.51 | P38: =+P55+P68+P94+P107+P81 -> 482123.51 | Q38: =+Q55+Q68+Q94+Q107+Q81 -> 482123.51
B39: iPad Revenue | D39: =SUM(D7/C7)-1 -> 0.11484962 | E39: =SUM(E7/D7)-1 -> 0.34302816 | F39: =SUM(F7/E7)-1 -> -0.080660348 | G39: =SUM(G7/F7)-1 -> -0.033865902 | H39: =SUM(H7/G7)-1 -> -0.056749117 | J39: Y/Y Growth (%) | L39: =SUM(L38/$H$11)-1 -> 0.063946708 | M39: =SUM(M38/L38)-1 -> 0.076285632 | N39: =SUM(N38/M38)-1 -> 0.076701364 | O39: =N39 -> 0.076701364 | P39: =O39 -> 0.076701364 | Q39: =P39 -> 0.076701364
B40: (%) of Total Revenue | C40: =C7/C$11 -> 0.081791417 | D40: =D7/D$11 -> 0.086421507 | E40: =E7/E$11 -> 0.087098194 | F40: =F7/F$11 -> 0.074283338 | G40: =G7/G$11 -> 0.073835397 | H40: =H7/H$11 -> 0.068264989 | J40: JP Morgan | L40: =+L57+L70+L96+L109+L83 -> 416621 | M40: =+M57+M70+M96+M109+M83 -> 445334 | N40: =+N57+N70+N96+N109+N83 -> 489169 | O40: =+O57+O70+O96+O109+O83 -> 500680 | P40: =+P57+P70+P96+P109+P83 -> 500680 | Q40: =+Q57+Q70+Q96+Q109+Q83 -> 500680
B41: Mac Revenue | D41: =SUM(D8/C8)-1 -> 0.11196581 | E41: =SUM(E8/D8)-1 -> 0.22947383 | F41: =SUM(F8/E8)-1 -> 0.1417164 | G41: =SUM(G8/F8)-1 -> -0.26930831 | H41: =SUM(H8/G8)-1 -> 0.021357768 | J41: Y/Y Growth (%) | L41: =SUM(L40/$H$11)-1 -> 0.065431483 | M41: =SUM(M40/L40)-1 -> 0.068918753 | N41: =SUM(N40/M40)-1 -> 0.098431739 | O41: =SUM(O40/N40)-1 -> 0.023531745 | P41: =O41 -> 0.023531745 | Q41: =P41 -> 0.023531745
J42: Barclays | L42: 414847 | M42: 438656 | N42: 465270 | O42: =N42 -> 465270 | P42: =O42 -> 465270 | Q42: =P42 -> 465270
J43: Y/Y Growth (%) | L43: =SUM(L42/$H$11)-1 -> 0.060894805 | M43: =SUM(M42/L42)-1 -> 0.057392243 | N43: =SUM(N42/M42)-1 -> 0.060671688 | O43: =N43 -> 0.060671688 | P43: =O43 -> 0.060671688 | Q43: =P43 -> 0.060671688
J44: Jefferies | L44: 410074 | M44: 425207 | N44: 464555 | O44: 478922 | P44: 535341 | Q44: 569147
J45: Y/Y Growth (%) | L45: =SUM(L44/$H$11)-1 -> 0.048688736 | M45: =SUM(M44/L44)-1 -> 0.036903096 | N45: =SUM(N44/M44)-1 -> 0.092538458 | O45: =SUM(O44/N44)-1 -> 0.03092637 | P45: =SUM(P44/O44)-1 -> 0.11780415 | Q45: =SUM(Q44/P44)-1 -> 0.063148535
B46: (%) of Total Revenue | C46: =C8/C$11 -> 0.09893379 | D46: =D8/D$11 -> 0.10426388 | E46: =E8/E$11 -> 0.096195639 | F46: =F8/F$11 -> 0.10188726 | G46: =G8/G$11 -> 0.076593136 | H46: =H8/H$11 -> 0.076678558 | J46: Morgan Stanley | L46: =+L59+L72+L98+L111+L85 -> 414913 | M46: =+M59+M72+M98+M111+M85 -> 441848 | N46: =+N59+N72+N98+N111+N85 -> 468930 | O46: =+O59+O72+O98+O111+O85 -> 468930 | P46: =+P59+P72+P98+P111+P85 -> 468930 | Q46: =+Q59+Q72+Q98+Q111+Q85 -> 468930
B47: Wearables, Home, and Accessories Revenue | D47: =SUM(D9/C9)-1 -> 0.25071481 | E47: =SUM(E9/D9)-1 -> 0.25300457 | F47: =SUM(F9/E9)-1 -> 0.074908124 | G47: =SUM(G9/F9)-1 -> -0.03384981 | H47: =SUM(H9/G9)-1 -> -0.071276195 | J47: Y/Y Growth (%) | L47: =SUM(L46/$H$11)-1 -> 0.061063588 | M47: =SUM(M46/L46)-1 -> 0.064917224 | N47: =SUM(N46/M46)-1 -> 0.061292571 | O47: =N47 -> 0.061292571 | P47: =O47 -> 0.061292571 | Q47: =P47 -> 0.061292571
B48: (%) of Total Revenue | C48: =C9/C$11 -> 0.094098565 | D48: =D9/D$11 -> 0.11154217 | E48: =E9/E$11 -> 0.10488031 | F48: =F9/F$11 -> 0.10458552 | G48: =G9/G$11 -> 0.10395659 | H48: =H9/H$11 -> 0.094633473 | J48: Wells Fargo | L48: =+L61+L74+L100+L113+L87 -> 415305 | M48: =+M61+M74+M100+M113+M87 -> 440525 | N48: =+N61+N74+N100+N113+N87 -> 460577 | O48: =+O61+O74+O100+O113+O87 -> 460577 | P48: =+P61+P74+P100+P113+P87 -> 460577 | Q48: =+Q61+Q74+Q100+Q113+Q87 -> 460577
B49: Services Revenue | D49: =SUM(D10/C10)-1 -> 0.16152168 | E49: =SUM(E10/D10)-1 -> 0.27259708 | F49: =SUM(F10/E10)-1 -> 0.14181951 | G49: =SUM(G10/F10)-1 -> 0.090504166 | H49: =SUM(H10/G10)-1 -> 0.12874413 | J49: Y/Y Growth (%) | L49: =SUM(L48/$H$11)-1 -> 0.062066055 | M49: =SUM(M48/L48)-1 -> 0.060726454 | N49: =SUM(N48/M48)-1 -> 0.045518416 | O49: =N49 -> 0.045518416 | P49: =O49 -> 0.045518416 | Q49: =P49 -> 0.045518416
B50: (%) of Total Revenue | C50: =C10/C$11 -> 0.17792324 | D50: =D10/D$11 -> 0.19586544 | E50: =E10/E$11 -> 0.18704708 | F50: =F10/F$11 -> 0.19813201 | G50: =G10/G$11 -> 0.2222889 | H50: =H10/H$11 -> 0.24593451
J51: Median (%) | L51: =MEDIAN(L$49,L$39,L$47,L$41,L$45,L$43) -> 0.061564822 | M51: =MEDIAN(M$49,M$39,M$47,M$41,M$45,M$43) -> 0.062821839 | N51: =MEDIAN(N$49,N$39,N$47,N$41,N$45,N$43) -> 0.068996967 | O51: =MEDIAN(O$49,O$39,O$47,O$41,O$45,O$43) -> 0.053095052 | P51: =MEDIAN(P$49,P$39,P$47,P$41,P$45,P$43) -> 0.06098213 | Q51: =MEDIAN(Q$49,Q$39,Q$47,Q$41,Q$45,Q$43) -> 0.06098213
J52: Average (%) | L52: =AVERAGE(L$49,L$39,L$47,L$41,L$45,L$43) -> 0.060348563 | M52: =AVERAGE(M$49,M$39,M$47,M$41,M$45,M$43) -> 0.060857234 | N52: =AVERAGE(N$49,N$39,N$47,N$41,N$45,N$43) -> 0.072525706 | O52: =AVERAGE(O$49,O$39,O$47,O$41,O$45,O$43) -> 0.049773692 | P52: =AVERAGE(P$49,P$39,P$47,P$41,P$45,P$43) -> 0.064253322 | Q52: =AVERAGE(Q$49,Q$39,Q$47,Q$41,Q$45,Q$43) -> 0.055144053
A54: X | B54: Revenue: iPhone Revenue | J54: Revenue: iPhone Revenue
J55: BofA | L55: 210271 | M55: 224197.5 | N55: 237444 | O55: =N55 -> 237444 | P55: =O55 -> 237444 | Q55: =P55 -> 237444
J56: Y/Y Growth (%) | L56: =SUM(L55/$H$6)-1 -> 0.045172803 | M56: =SUM(M55/L55)-1 -> 0.066231197 | N56: =SUM(N55/M55)-1 -> 0.059084067 | O56: =N56 -> 0.059084067 | P56: =O56 -> 0.059084067 | Q56: =P56 -> 0.059084067
J57: JP Morgan | L57: 210893 | M57: 223122 | N57: 249550 | O57: 240721 | P57: =O57 -> 240721 | Q57: =P57 -> 240721
J58: Y/Y Growth (%) | L58: =SUM(L57/$H$6)-1 -> 0.048264515 | M58: =SUM(M57/L57)-1 -> 0.057986752 | N58: =SUM(N57/M57)-1 -> 0.11844641 | O58: =SUM(O57/N57)-1 -> -0.035379683 | P58: =SUM(P57/O57)-1 -> 0 | Q58: =SUM(Q57/P57)-1 -> 0
J59: Morgan Stanley | L59: 209597 | M59: 221070 | N59: 233080 | O59: =N59 -> 233080 | P59: =O59 -> 233080 | Q59: =P59 -> 233080
J60: Y/Y Growth (%) | L60: =SUM(L59/$H$6)-1 -> 0.041822619 | M60: =SUM(M59/L59)-1 -> 0.054738379 | N60: =SUM(N59/M59)-1 -> 0.054326684 | O60: =N60 -> 0.054326684 | P60: =O60 -> 0.054326684 | Q60: =P60 -> 0.054326684
J61: Wells Fargo | L61: 209723 | M61: 221039 | N61: 226650 | O61: =N61 -> 226650 | P61: =O61 -> 226650 | Q61: =P61 -> 226650
J62: Y/Y Growth (%) | L62: =SUM(L61/$H$6)-1 -> 0.042448915 | M62: =SUM(M61/L61)-1 -> 0.053956886 | N62: =SUM(N61/M61)-1 -> 0.025384661 | O62: =N62 -> 0.025384661 | P62: =O62 -> 0.025384661 | Q62: =P62 -> 0.025384661
J64: Median (%) | L64: =MEDIAN(L$62,L$56,L$60,L$58) -> 0.043810859 | M64: =MEDIAN(M$62,M$56,M$60,M$58) -> 0.056362565 | N64: =MEDIAN(N$62,N$56,N$60,N$58) -> 0.056705375 | O64: =MEDIAN(O$62,O$56,O$60,O$58) -> 0.039855672 | P64: =MEDIAN(P$62,P$56,P$60,P$58) -> 0.039855672 | Q64: =MEDIAN(Q$62,Q$56,Q$60,Q$58) -> 0.039855672
J65: Average (%) | L65: =AVERAGE(L$62,L$56,L$60,L$58) -> 0.044427213 | M65: =AVERAGE(M$62,M$56,M$60,M$58) -> 0.058228303 | N65: =AVERAGE(N$62,N$56,N$60,N$58) -> 0.064310455 | O65: =AVERAGE(O$62,O$56,O$60,O$58) -> 0.025853932 | P65: =AVERAGE(P$62,P$56,P$60,P$58) -> 0.034698853 | Q65: =AVERAGE(Q$62,Q$56,Q$60,Q$58) -> 0.034698853
A67: X | B67: Revenue: iPad Revenue | J67: Revenue: iPad Revenue
J68: BofA | L68: 28208.285 | M68: 29955.43 | N68: 32016.946 | O68: =N68 -> 32016.946 | P68: =O68 -> 32016.946 | Q68: =P68 -> 32016.946
J69: Y/Y Growth (%) | L69: =SUM(L68/$H$7)-1 -> 0.056727538 | M69: =SUM(M68/L68)-1 -> 0.061937309 | N69: =SUM(N68/M68)-1 -> 0.068819444 | O69: =N69 -> 0.068819444 | P69: =O69 -> 0.068819444 | Q69: =P69 -> 0.068819444
J70: JP Morgan | L70: 28399 | M70: 29159 | N70: 30040 | O70: 31253 | P70: =O70 -> 31253 | Q70: =P70 -> 31253
J71: Y/Y Growth (%) | L71: =SUM(L70/$H$7)-1 -> 0.063872031 | M71: =SUM(M70/L70)-1 -> 0.026761506 | N71: =SUM(N70/M70)-1 -> 0.030213656 | O71: =SUM(O70/N70)-1 -> 0.040379494 | P71: =O71 -> 0.040379494 | Q71: =P71 -> 0.040379494
J72: Morgan Stanley | L72: 27523 | M72: 28295 | N72: 28599 | O72: =N72 -> 28599 | P72: =O72 -> 28599 | Q72: =P72 -> 28599
J73: Y/Y Growth (%) | L73: =SUM(L72/$H$7)-1 -> 0.031055668 | M73: =SUM(M72/L72)-1 -> 0.028049268 | N73: =SUM(N72/M72)-1 -> 0.010743948 | O73: =N73 -> 0.010743948 | P73: =O73 -> 0.010743948 | Q73: =P73 -> 0.010743948
J74: Wells Fargo | L74: 27567 | M74: 25036 | N74: 24466 | O74: =N74 -> 24466 | P74: =O74 -> 24466 | Q74: =P74 -> 24466
J75: Y/Y Growth (%) | L75: =SUM(L74/$H$7)-1 -> 0.032703978 | M75: =SUM(M74/L74)-1 -> -0.091812675 | N75: =SUM(N74/M74)-1 -> -0.022767215 | O75: 0 | P75: =O75 -> 0 | Q75: =P75 -> 0
J77: Median (%) | L77: =MEDIAN(L$75,L$69,L$73,L$71) -> 0.044715758 | M77: =MEDIAN(M$75,M$69,M$73,M$71) -> 0.027405387 | N77: =MEDIAN(N$75,N$69,N$73,N$71) -> 0.020478802 | O77: =MEDIAN(O$75,O$69,O$73,O$71) -> 0.025561721 | P77: =MEDIAN(P$75,P$69,P$73,P$71) -> 0.025561721 | Q77: =MEDIAN(Q$75,Q$69,Q$73,Q$71) -> 0.025561721
J78: Average (%) | L78: =AVERAGE(L$75,L$69,L$73,L$71) -> 0.046089804 | M78: =AVERAGE(M$75,M$69,M$73,M$71) -> 0.0062338519 | N78: =AVERAGE(N$75,N$69,N$73,N$71) -> 0.021752458 | O78: =AVERAGE(O$75,O$69,O$73,O$71) -> 0.029985721 | P78: =AVERAGE(P$75,P$69,P$73,P$71) -> 0.029985721 | Q78: =AVERAGE(Q$75,Q$69,Q$73,Q$71) -> 0.029985721
A80: X | B80: Revenue: Mac Revenue | J80: Revenue: Mac Revenue
J81: BofA | L81: 33477.452 | M81: 34521.796 | N81: 35879.893 | O81: =N81 -> 35879.893 | P81: =O81 -> 35879.893 | Q81: =P81 -> 35879.893
J82: Y/Y Growth (%) | L82: =SUM(L81/$H$8)-1 -> 0.11651054 | M82: =SUM(M81/L81)-1 -> 0.031195439 | N82: =SUM(N81/M81)-1 -> 0.03934027 | O82: =N82 -> 0.03934027 | P82: =O82 -> 0.03934027 | Q82: =P82 -> 0.03934027
J83: JP Morgan | L83: 33189 | M83: 34188 | N83: 35395 | O83: 37003 | P83: =O83 -> 37003 | Q83: =P83 -> 37003
J84: Y/Y Growth (%) | L84: =SUM(L83/$H$8)-1 -> 0.10689034 | M84: =SUM(M83/L83)-1 -> 0.030100334 | N84: =SUM(N83/M83)-1 -> 0.035304785 | O84: =SUM(O83/N83)-1 -> 0.045430146 | P84: =O84 -> 0.045430146 | Q84: =P84 -> 0.045430146
J85: Morgan Stanley | L85: 34302 | M85: 34888 | N85: 35155 | O85: =N85 -> 35155 | P85: =O85 -> 35155 | Q85: =P85 -> 35155
J86: Y/Y Growth (%) | L86: =SUM(L85/$H$8)-1 -> 0.14401014 | M86: =SUM(M85/L85)-1 -> 0.017083552 | N86: =SUM(N85/M85)-1 -> 0.0076530612 | O86: =N86 -> 0.0076530612 | P86: =O86 -> 0.0076530612 | Q86: =P86 -> 0.0076530612
J87: Wells Fargo | L87: 34644 | M87: 37934 | N87: 40252 | O87: =N87 -> 40252 | P87: =O87 -> 40252 | Q87: =P87 -> 40252
J88: Y/Y Growth (%) | L88: =SUM(L87/$H$8)-1 -> 0.15541622 | M88: =SUM(M87/L87)-1 -> 0.094965939 | N88: =SUM(N87/M87)-1 -> 0.061106132 | O88: =N88 -> 0.061106132 | P88: =O88 -> 0.061106132 | Q88: =P88 -> 0.061106132
J90: Median (%) | L90: =MEDIAN(L$88,L$82,L$86,L$84) -> 0.13026034 | M90: =MEDIAN(M$88,M$82,M$86,M$84) -> 0.030647887 | N90: =MEDIAN(N$88,N$82,N$86,N$84) -> 0.037322528 | O90: =MEDIAN(O$88,O$82,O$86,O$84) -> 0.042385208 | P90: =MEDIAN(P$88,P$82,P$86,P$84) -> 0.042385208 | Q90: =MEDIAN(Q$88,Q$82,Q$86,Q$84) -> 0.042385208
J91: Average (%) | L91: =AVERAGE(L$88,L$82,L$86,L$84) -> 0.13070681 | M91: =AVERAGE(M$88,M$82,M$86,M$84) -> 0.043336316 | N91: =AVERAGE(N$88,N$82,N$86,N$84) -> 0.035851062 | O91: =AVERAGE(O$88,O$82,O$86,O$84) -> 0.038382402 | P91: =AVERAGE(P$88,P$82,P$86,P$84) -> 0.038382402 | Q91: =AVERAGE(Q$88,Q$82,Q$86,Q$84) -> 0.038382402
A93: X | B93: Revenue: Wearables, Home and Accessories Revenue | J93: Revenue: Wearables, Home and Accessories Revenue
J94: BofA | L94: 35207.584 | M94: 37162.37 | N94: 39913.511 | O94: =N94 -> 39913.511 | P94: =O94 -> 39913.511 | Q94: =P94 -> 39913.511
J95: Y/Y Growth (%) | L95: =SUM(L94/$H$9)-1 -> -0.048572242 | M95: =SUM(M94/L94)-1 -> 0.055521733 | N95: =SUM(N94/M94)-1 -> 0.07403028 | O95: =N95 -> 0.07403028 | P95: =O95 -> 0.07403028 | Q95: =P95 -> 0.07403028
J96: JP Morgan | L96: 35441 | M96: 36050 | N96: 36689 | O96: 38120 | P96: =O96 -> 38120 | Q96: =P96 -> 38120
J97: Y/Y Growth (%) | L97: =SUM(L96/$H$9)-1 -> -0.042264559 | M97: =SUM(M96/L96)-1 -> 0.017183488 | N97: =SUM(N96/M96)-1 -> 0.017725381 | O97: =SUM(O96/N96)-1 -> 0.039003516 | P97: =O97 -> 0.039003516 | Q97: =P97 -> 0.039003516
J98: Morgan Stanley | L98: 34801 | M98: 35867 | N98: 37348 | O98: =N98 -> 37348 | P98: =O98 -> 37348 | Q98: =P98 -> 37348
J99: Y/Y Growth (%) | L99: =SUM(L98/$H$9)-1 -> -0.059559519 | M99: =SUM(M98/L98)-1 -> 0.030631304 | N99: =SUM(N98/M98)-1 -> 0.041291438 | O99: =N99 -> 0.041291438 | P99: =O99 -> 0.041291438 | Q99: =P99 -> 0.041291438
J100: Wells Fargo | L100: 34854 | M100: 37710 | N100: 41279 | O100: =N100 -> 41279 | P100: =O100 -> 41279 | Q100: =P100 -> 41279
J101: Y/Y Growth (%) | L101: =SUM(L100/$H$9)-1 -> -0.05812728 | M101: =SUM(M100/L100)-1 -> 0.081941814 | N101: =SUM(N100/M100)-1 -> 0.094643331 | O101: =N101 -> 0.094643331 | P101: =O101 -> 0.094643331 | Q101: =P101 -> 0.094643331
