Workbook

Sheet Historical Financials
B2: Apple Inc. (NASDAQ: AAPL)
B3: Historical Financials
B4: $ mm except per share
A6: X | B6: Income Statement | C6: FYE | F6: FYE | G6: FYE | N6: Quarterly | T6: Quarterly | W6: Quarterly | X6: Quarterly | AK6: LTM | AR6: Variance
B7: Fiscal Period | C7: 2016 | D7: 2017 | E7: 2018 | F7: 2019 | G7: 2020 | H7: 2021 | I7: 2022 | J7: 2023 | K7: 2024 | L7: 2025 | N7: 1Q22 | O7: 2Q22 | P7: 3Q22 | Q7: 4Q22 | R7: 1Q23 | S7: 2Q23 | T7: 3Q23 | U7: 4Q23 | V7: 1Q24 | W7: 2Q24 | X7: 3Q24 | Y7: 4Q24 | Z7: 1Q25 | AA7: 2Q25 | AB7: 3Q25 | AC7: 4Q25 | AE7: =R7 -> 1Q23 | AF7: =S7 -> 2Q23 | AG7: =T7 -> 3Q23 | AH7: =U7 -> 4Q23 | AI7: =V7 -> 1Q24 | AJ7: =W7 -> 2Q24 | AK7: =X7 -> 3Q24 | AL7: =Y7 -> 4Q24 | ... AP7: =AC7 -> 4Q25
B8: Fiscal Period End Date | C8: 42643 | D8: 43008 | E8: 43372 | F8: 43737 | G8: 44104 | H8: 44469 | I8: 44834 | J8: 45192 | K8: 45559 | L8: 45927 | N8: 44560 | O8: 44650 | P8: 44742 | Q8: =I8 -> 44834 | R8: 44917 | S8: 45008 | T8: 45100 | U8: =J8 -> 45192 | V8: 45283 | W8: 45375 | X8: 45467 | Y8: =K8 -> 45559 | Z8: 45650 | AA8: 45741 | AB8: 45833 | AC8: =L8 -> 45927 | AE8: =R8 -> 44917 | AF8: =S8 -> 45008 | AG8: =T8 -> 45100 | AH8: =U8 -> 45192 | AI8: =V8 -> 45283 | AJ8: =W8 -> 45375 | AK8: =X8 -> 45467 | AL8: =Y8 -> 45559 | ... AP8: =AC8 -> 45927
B10: Consolidated Revenue | C10: 215639 | D10: 229234 | E10: 265595 | F10: 260174 | G10: 274515 | H10: 365817 | I10: 394328 | J10: 383285 | K10: 391035 | L10: 416161 | N10: 123945 | O10: 97278 | P10: 82959 | Q10: =SUM(I10-SUM(N10:P10)) -> 90146 | R10: 117154 | S10: 94836 | T10: 81797 | U10: =SUM(J10-SUM(R10:T10)) -> 89498 | V10: 119575 | W10: 90753 | X10: 85777 | Y10: =SUM(K10-SUM(V10:X10)) -> 94930 | Z10: 124300 | AA10: 95359 | AB10: 94036 | AC10: =SUM(L10-SUM(Z10:AB10)) -> 102466 | AE10: =SUM(O10:R10) -> 387537 | AF10: =SUM(P10:S10) -> 385095 | AG10: =SUM(Q10:T10) -> 383933 | AH10: =SUM(R10:U10) -> 383285 | AI10: =SUM(S10:V10) -> 385706 | AJ10: =SUM(T10:W10) -> 381623 | AK10: =SUM(U10:X10) -> 385603 | AL10: =SUM(V10:Y10) -> 391035 | ... AP10: =SUM(Z10:AC10) -> 416161 | AR10: =SUM(AP10/AL10)-1 -> 0.064255118
B11: Total Revenue | C11: =+SUM(C10:C10) -> 215639 | D11: =+SUM(D10:D10) -> 229234 | E11: =+SUM(E10:E10) -> 265595 | F11: =+SUM(F10:F10) -> 260174 | G11: =+SUM(G10:G10) -> 274515 | H11: =+SUM(H10:H10) -> 365817 | I11: =+SUM(I10:I10) -> 394328 | J11: =+SUM(J10:J10) -> 383285 | ... L11: =+SUM(L10:L10) -> 416161 | N11: =+SUM(N10:N10) -> 123945 | O11: =+SUM(O10:O10) -> 97278 | P11: =+SUM(P10:P10) -> 82959 | Q11: =+SUM(Q10:Q10) -> 90146 | R11: =+SUM(R10:R10) -> 117154 | S11: =+SUM(S10:S10) -> 94836 | T11: =+SUM(T10:T10) -> 81797 | U11: =+SUM(U10:U10) -> 89498 | ... AC11: =+SUM(AC10:AC10) -> 102466 | AE11: =+SUM(AE10:AE10) -> 387537 | AF11: =+SUM(AF10:AF10) -> 385095 | AG11: =+SUM(AG10:AG10) -> 383933 | AH11: =+SUM(AH10:AH10) -> 383285 | AI11: =+SUM(AI10:AI10) -> 385706 | AJ11: =+SUM(AJ10:AJ10) -> 381623 | AK11: =+SUM(AK10:AK10) -> 385603 | AL11: =+SUM(AL10:AL10) -> 391035 | ... AP11: =+SUM(AP10:AP10) -> 416161 | AR11: =SUM(AP11/AL11)-1 -> 0.064255118
B13: Cost of Sales | C13: -131376 | D13: -141048 | E13: -163756 | F13: -161782 | G13: -169559 | H13: -212981 | I13: -223546 | J13: -214137 | K13: -210352 | L13: -220960 | N13: -69702 | O13: -54719 | P13: -47074 | Q13: =SUM(I13-SUM(N13:P13)) -> -52051 | R13: -66822 | S13: -52860 | T13: -45384 | U13: =SUM(J13-SUM(R13:T13)) -> -49071 | V13: -64720 | W13: -48482 | X13: -46099 | Y13: =SUM(K13-SUM(V13:X13)) -> -51051 | Z13: -66025 | AA13: -50492 | AB13: -50318 | AC13: =SUM(L13-SUM(Z13:AB13)) -> -54125 | AE13: =SUM(O13:R13) -> -220666 | AF13: =SUM(P13:S13) -> -218807 | AG13: =SUM(Q13:T13) -> -217117 | AH13: =SUM(R13:U13) -> -214137 | AI13: =SUM(S13:V13) -> -212035 | AJ13: =SUM(T13:W13) -> -207657 | AK13: =SUM(U13:X13) -> -208372 | AL13: =SUM(V13:Y13) -> -210352 | ... AP13: =SUM(Z13:AC13) -> -220960 | AR13: =SUM(AP13/AL13)-1 -> 0.050429756
B14: Gross Profit | C14: =+SUM(C11+SUM(C13:C13)) -> 84263 | D14: =+SUM(D11+SUM(D13:D13)) -> 88186 | E14: =+SUM(E11+SUM(E13:E13)) -> 101839 | F14: =+SUM(F11+SUM(F13:F13)) -> 98392 | G14: =+SUM(G11+SUM(G13:G13)) -> 104956 | H14: =+SUM(H11+SUM(H13:H13)) -> 152836 | I14: =+SUM(I11+SUM(I13:I13)) -> 170782 | J14: =+SUM(J11+SUM(J13:J13)) -> 169148 | ... L14: =+SUM(L11+SUM(L13:L13)) -> 195201 | N14: =+SUM(N11+SUM(N13:N13)) -> 54243 | O14: =+SUM(O11+SUM(O13:O13)) -> 42559 | P14: =+SUM(P11+SUM(P13:P13)) -> 35885 | Q14: =+SUM(Q11+SUM(Q13:Q13)) -> 38095 | R14: =+SUM(R11+SUM(R13:R13)) -> 50332 | S14: =+SUM(S11+SUM(S13:S13)) -> 41976 | T14: =+SUM(T11+SUM(T13:T13)) -> 36413 | U14: =+SUM(U11+SUM(U13:U13)) -> 40427 | ... AC14: =+SUM(AC11+SUM(AC13:AC13)) -> 48341 | AE14: =+SUM(AE11+SUM(AE13:AE13)) -> 166871 | AF14: =+SUM(AF11+SUM(AF13:AF13)) -> 166288 | AG14: =+SUM(AG11+SUM(AG13:AG13)) -> 166816 | AH14: =+SUM(AH11+SUM(AH13:AH13)) -> 169148 | AI14: =+SUM(AI11+SUM(AI13:AI13)) -> 173671 | AJ14: =+SUM(AJ11+SUM(AJ13:AJ13)) -> 173966 | AK14: =+SUM(AK11+SUM(AK13:AK13)) -> 177231 | AL14: =+SUM(AL11+SUM(AL13:AL13)) -> 180683 | ... AP14: =+SUM(AP11+SUM(AP13:AP13)) -> 195201 | AR14: =SUM(AP14/AL14)-1 -> 0.080350669
B15: Gross Margin (%) | C15: =C14/C11 -> 0.39075956 | D15: =D14/D11 -> 0.3846986 | E15: =E14/E11 -> 0.38343719 | F15: =F14/F11 -> 0.37817768 | G15: =G14/G11 -> 0.38233248 | H15: =H14/H11 -> 0.4177936 | I15: =I14/I11 -> 0.43309631 | J15: =J14/J11 -> 0.4413113 | ... L15: =L14/L11 -> 0.46905164 | N15: =N14/N11 -> 0.43763766 | O15: =O14/O11 -> 0.43749872 | P15: =P14/P11 -> 0.43256307 | Q15: =Q14/Q11 -> 0.42259224 | R15: =R14/R11 -> 0.42962255 | S15: =S14/S11 -> 0.44261673 | T15: =T14/T11 -> 0.44516303 | U15: =U14/U11 -> 0.45170842 | ... AC15: =AC14/AC11 -> 0.471776 | AE15: =AE14/AE11 -> 0.43059372 | AF15: =AF14/AF11 -> 0.43181033 | AG15: =AG14/AG11 -> 0.43449248 | AH15: =AH14/AH11 -> 0.4413113 | AI15: =AI14/AI11 -> 0.45026782 | AJ15: =AJ14/AJ11 -> 0.45585827 | AK15: =AK14/AK11 -> 0.45962039 | AL15: =AL14/AL11 -> 0.4620635 | ... AP15: =AP14/AP11 -> 0.46905164 | AR15: =SUM(AP15-AL15)*1000 -> 6.9881429
B17: Research & Development | C17: -10045 | D17: -11581 | E17: -14236 | F17: -16217 | G17: -18752 | H17: -21914 | I17: -26251 | J17: -29915 | K17: -31370 | L17: -34550 | N17: -6306 | O17: -6387 | P17: -6797 | Q17: =SUM(I17-SUM(N17:P17)) -> -6761 | R17: -7709 | S17: -7457 | T17: -7442 | U17: =SUM(J17-SUM(R17:T17)) -> -7307 | V17: -7696 | W17: -7903 | X17: -8006 | Y17: =SUM(K17-SUM(V17:X17)) -> -7765 | Z17: -8268 | AA17: -8550 | AB17: -8866 | AC17: =SUM(L17-SUM(Z17:AB17)) -> -8866 | AE17: =SUM(O17:R17) -> -27654 | AF17: =SUM(P17:S17) -> -28724 | AG17: =SUM(Q17:T17) -> -29369 | AH17: =SUM(R17:U17) -> -29915 | AI17: =SUM(S17:V17) -> -29902 | AJ17: =SUM(T17:W17) -> -30348 | AK17: =SUM(U17:X17) -> -30912 | AL17: =SUM(V17:Y17) -> -31370 | ... AP17: =SUM(Z17:AC17) -> -34550 | AR17: =SUM(AP17/AL17)-1 -> 0.10137074
B18: Selling, General & Administrative | C18: -14194 | D18: -15261 | E18: -16705 | F18: -18245 | G18: -19916 | H18: -21973 | I18: -25094 | J18: -24932 | K18: -26097 | L18: -27601 | N18: -6449 | O18: -6193 | P18: -6012 | Q18: =SUM(I18-SUM(N18:P18)) -> -6440 | R18: -6607 | S18: -6201 | T18: -5973 | U18: =SUM(J18-SUM(R18:T18)) -> -6151 | V18: -6786 | W18: -6468 | X18: -6320 | Y18: =SUM(K18-SUM(V18:X18)) -> -6523 | Z18: -7175 | AA18: -6728 | AB18: -6650 | AC18: =SUM(L18-SUM(Z18:AB18)) -> -7048 | AE18: =SUM(O18:R18) -> -25252 | AF18: =SUM(P18:S18) -> -25260 | AG18: =SUM(Q18:T18) -> -25221 | AH18: =SUM(R18:U18) -> -24932 | AI18: =SUM(S18:V18) -> -25111 | AJ18: =SUM(T18:W18) -> -25378 | AK18: =SUM(U18:X18) -> -25725 | AL18: =SUM(V18:Y18) -> -26097 | ... AP18: =SUM(Z18:AC18) -> -27601 | AR18: =SUM(AP18/AL18)-1 -> 0.057631145
B19: Profit From Operations | C19: =SUM(C14+SUM(C17:C18)) -> 60024 | D19: =SUM(D14+SUM(D17:D18)) -> 61344 | E19: =SUM(E14+SUM(E17:E18)) -> 70898 | F19: =SUM(F14+SUM(F17:F18)) -> 63930 | G19: =SUM(G14+SUM(G17:G18)) -> 66288 | H19: =SUM(H14+SUM(H17:H18)) -> 108949 | I19: =SUM(I14+SUM(I17:I18)) -> 119437 | J19: =SUM(J14+SUM(J17:J18)) -> 114301 | ... L19: =SUM(L14+SUM(L17:L18)) -> 133050 | N19: =SUM(N14+SUM(N17:N18)) -> 41488 | O19: =SUM(O14+SUM(O17:O18)) -> 29979 | P19: =SUM(P14+SUM(P17:P18)) -> 23076 | Q19: =SUM(Q14+SUM(Q17:Q18)) -> 24894 | R19: =SUM(R14+SUM(R17:R18)) -> 36016 | S19: =SUM(S14+SUM(S17:S18)) -> 28318 | T19: =SUM(T14+SUM(T17:T18)) -> 22998 | U19: =SUM(U14+SUM(U17:U18)) -> 26969 | ... AC19: =SUM(AC14+SUM(AC17:AC18)) -> 32427 | AE19: =SUM(AE14+SUM(AE17:AE18)) -> 113965 | AF19: =SUM(AF14+SUM(AF17:AF18)) -> 112304 | AG19: =SUM(AG14+SUM(AG17:AG18)) -> 112226 | AH19: =SUM(AH14+SUM(AH17:AH18)) -> 114301 | AI19: =SUM(AI14+SUM(AI17:AI18)) -> 118658 | AJ19: =SUM(AJ14+SUM(AJ17:AJ18)) -> 118240 | AK19: =SUM(AK14+SUM(AK17:AK18)) -> 120594 | AL19: =SUM(AL14+SUM(AL17:AL18)) -> 123216 | ... AP19: =SUM(AP14+SUM(AP17:AP18)) -> 133050 | AR19: =SUM(AP19/AL19)-1 -> 0.079811063
B20: Operating Margin (%) | C20: =C19/C11 -> 0.2783541 | D20: =D19/D11 -> 0.26760428 | E20: =E19/E11 -> 0.26694027 | F20: =F19/F11 -> 0.24572017 | G20: =G19/G11 -> 0.24147314 | H20: =H19/H11 -> 0.29782378 | I20: =I19/I11 -> 0.30288744 | J20: =J19/J11 -> 0.29821412 | ... L20: =L19/L11 -> 0.319708 | N20: =N19/N11 -> 0.33472911 | O20: =O19/O11 -> 0.30817862 | P20: =P19/P11 -> 0.2781615 | Q20: =Q19/Q11 -> 0.27615202 | R20: =R19/R11 -> 0.30742442 | S20: =S19/S11 -> 0.29859969 | T20: =T19/T11 -> 0.28115946 | U20: =U19/U11 -> 0.30133634 | ... AC20: =AC19/AC11 -> 0.31646595 | AE20: =AE19/AE11 -> 0.29407515 | AF20: =AF19/AF11 -> 0.29162674 | AG20: =AG19/AG11 -> 0.29230621 | AH20: =AH19/AH11 -> 0.29821412 | AI20: =AI19/AI11 -> 0.30763846 | AJ20: =AJ19/AJ11 -> 0.30983457 | AK20: =AK19/AK11 -> 0.31274134 | AL20: =AL19/AL11 -> 0.31510223 | ... AP20: =AP19/AP11 -> 0.319708 | AR20: =SUM(AP20-AL20)*1000 -> 4.6057689
B22: Other income/(expense), net | C22: 1348 | D22: 2745 | E22: 2005 | F22: 1807 | G22: 803 | H22: 258 | I22: -334 | J22: -565 | K22: 269 | L22: -321 | N22: -247 | O22: 160 | P22: -10 | Q22: =SUM(I22-SUM(N22:P22)) -> -237 | R22: -393 | S22: 64 | T22: -265 | U22: =SUM(J22-SUM(R22:T22)) -> 29 | V22: -50 | W22: 158 | X22: 142 | Y22: =SUM(K22-SUM(V22:X22)) -> 19 | Z22: -248 | AA22: -279 | AB22: -171 | AC22: =SUM(L22-SUM(Z22:AB22)) -> 377 | AE22: =SUM(O22:R22) -> -480 | AF22: =SUM(P22:S22) -> -576 | AG22: =SUM(Q22:T22) -> -831 | AH22: =SUM(R22:U22) -> -565 | AI22: =SUM(S22:V22) -> -222 | AJ22: =SUM(T22:W22) -> -128 | AK22: =SUM(U22:X22) -> 279 | AL22: =SUM(V22:Y22) -> 269 | ... AP22: =SUM(Z22:AC22) -> -321 | AR22: =SUM(AP22/AL22)-1 -> -2.1933086
B23: Net loss before provision for income taxes | C23: =SUM(C22:C22)+C19 -> 61372 | D23: =SUM(D22:D22)+D19 -> 64089 | E23: =SUM(E22:E22)+E19 -> 72903 | F23: =SUM(F22:F22)+F19 -> 65737 | G23: =SUM(G22:G22)+G19 -> 67091 | H23: =SUM(H22:H22)+H19 -> 109207 | I23: =SUM(I22:I22)+I19 -> 119103 | J23: =SUM(J22:J22)+J19 -> 113736 | ... L23: =SUM(L22:L22)+L19 -> 132729 | N23: =SUM(N22:N22)+N19 -> 41241 | O23: =SUM(O22:O22)+O19 -> 30139 | P23: =SUM(P22:P22)+P19 -> 23066 | Q23: =SUM(Q22:Q22)+Q19 -> 24657 | R23: =SUM(R22:R22)+R19 -> 35623 | S23: =SUM(S22:S22)+S19 -> 28382 | T23: =SUM(T22:T22)+T19 -> 22733 | U23: =SUM(U22:U22)+U19 -> 26998 | ... AC23: =SUM(AC22:AC22)+AC19 -> 32804 | AE23: =SUM(AE22:AE22)+AE19 -> 113485 | AF23: =SUM(AF22:AF22)+AF19 -> 111728 | AG23: =SUM(AG22:AG22)+AG19 -> 111395 | AH23: =SUM(AH22:AH22)+AH19 -> 113736 | AI23: =SUM(AI22:AI22)+AI19 -> 118436 | AJ23: =SUM(AJ22:AJ22)+AJ19 -> 118112 | AK23: =SUM(AK22:AK22)+AK19 -> 120873 | AL23: =SUM(AL22:AL22)+AL19 -> 123485 | ... AP23: =SUM(AP22:AP22)+AP19 -> 132729 | AR23: =SUM(AP23/AL23)-1 -> 0.074859295
B25: Provision for taxes | C25: -15685 | D25: -15738 | E25: -13372 | F25: -10481 | G25: -9680 | H25: -14527 | I25: -19300 | J25: -16741 | K25: -29749 | L25: -20719 | N25: -6611 | O25: -5129 | P25: -3624 | Q25: =SUM(I25-SUM(N25:P25)) -> -3936 | R25: -5625 | S25: -4222 | T25: -2852 | U25: =SUM(J25-SUM(R25:T25)) -> -4042 | V25: -6407 | W25: -4422 | X25: -4046 | Y25: =SUM(K25-SUM(V25:X25)) -> -14874 | Z25: -6254 | AA25: -4530 | AB25: -4597 | AC25: =SUM(L25-SUM(Z25:AB25)) -> -5338 | AE25: =SUM(O25:R25) -> -18314 | AF25: =SUM(P25:S25) -> -17407 | AG25: =SUM(Q25:T25) -> -16635 | AH25: =SUM(R25:U25) -> -16741 | AI25: =SUM(S25:V25) -> -17523 | AJ25: =SUM(T25:W25) -> -17723 | AK25: =SUM(U25:X25) -> -18917 | AL25: =SUM(V25:Y25) -> -29749 | ... AP25: =SUM(Z25:AC25) -> -20719 | AR25: =SUM(AP25/AL25)-1 -> -0.30353961
B26: Net loss | C26: =SUM(C23+C25) -> 45687 | D26: =SUM(D23+D25) -> 48351 | E26: =SUM(E23+E25) -> 59531 | F26: =SUM(F23+F25) -> 55256 | G26: =SUM(G23+G25) -> 57411 | H26: =SUM(H23+H25) -> 94680 | I26: =SUM(I23+I25) -> 99803 | J26: =SUM(J23+J25) -> 96995 | ... L26: =SUM(L23+L25) -> 112010 | N26: =SUM(N23+N25) -> 34630 | O26: =SUM(O23+O25) -> 25010 | P26: =SUM(P23+P25) -> 19442 | Q26: =SUM(Q23+Q25) -> 20721 | R26: =SUM(R23+R25) -> 29998 | S26: =SUM(S23+S25) -> 24160 | T26: =SUM(T23+T25) -> 19881 | U26: =SUM(U23+U25) -> 22956 | ... AC26: =SUM(AC23+AC25) -> 27466 | AE26: =SUM(AE23+AE25) -> 95171 | AF26: =SUM(AF23+AF25) -> 94321 | AG26: =SUM(AG23+AG25) -> 94760 | AH26: =SUM(AH23+AH25) -> 96995 | AI26: =SUM(AI23+AI25) -> 100913 | AJ26: =SUM(AJ23+AJ25) -> 100389 | AK26: =SUM(AK23+AK25) -> 101956 | AL26: =SUM(AL23+AL25) -> 93736 | ... AP26: =SUM(AP23+AP25) -> 112010 | AR26: =SUM(AP26/AL26)-1 -> 0.19495178
B27: Net Margin (%) | C27: =C26/C11 -> 0.21186798 | D27: =D26/D11 -> 0.21092421 | E27: =E26/E11 -> 0.22414202 | F27: =F26/F11 -> 0.21238095 | G27: =G26/G11 -> 0.20913611 | H27: =H26/H11 -> 0.25881793 | I27: =I26/I11 -> 0.25309641 | J27: =J26/J11 -> 0.25306234 | ... L27: =L26/L11 -> 0.26915064 | N27: =N26/N11 -> 0.27939812 | O27: =O26/O11 -> 0.25709821 | P27: =P26/P11 -> 0.23435673 | Q27: =Q26/Q11 -> 0.22986045 | R27: =R26/R11 -> 0.25605613 | S27: =S26/S11 -> 0.25475558 | T27: =T26/T11 -> 0.24305292 | U27: =U26/U11 -> 0.25649735 | ... AC27: =AC26/AC11 -> 0.26804989 | AE27: =AE26/AE11 -> 0.24557913 | AF27: =AF26/AF11 -> 0.24492917 | AG27: =AG26/AG11 -> 0.2468139 | AH27: =AH26/AH11 -> 0.25306234 | AI27: =AI26/AI11 -> 0.26163192 | AJ27: =AJ26/AJ11 -> 0.26305804 | AK27: =AK26/AK11 -> 0.26440666 | AL27: =AL26/AL11 -> 0.23971256 | ... AP27: =AP26/AP11 -> 0.26915064 | AR27: =SUM(AP27-AL27)*1000 -> 29.438084
B29: Basic shares | C29: 21883.281 | D29: 20868.968 | E29: 19821.51 | F29: 18471.336 | G29: 17352.119 | H29: 16701.272 | I29: 16215.963 | J29: 15744.231 | K29: 15343.783 | L29: 14948.5 | N29: 16391.724 | O29: 16278.802 | P29: 16162.945 | Q29: =I29 -> 16215.963 | R29: 15892.723 | S29: 15787.154 | T29: 15697.614 | U29: =J29 -> 15744.231 | V29: 15509.763 | W29: 15405.856 | X29: 15287.521 | Y29: =K29 -> 15343.783 | Z29: 15081.724 | AA29: 14994.082 | AB29: 14902.886 | AC29: =L29 -> 14948.5 | AE29: =R29 -> 15892.723 | AF29: =S29 -> 15787.154 | AG29: =T29 -> 15697.614 | AH29: =U29 -> 15744.231 | AI29: =V29 -> 15509.763 | AJ29: =W29 -> 15405.856 | AK29: =X29 -> 15287.521 | AL29: =Y29 -> 15343.783 | ... AP29: =AC29 -> 14948.5 | AR29: =SUM(AP29/AL29)-1 -> -0.025761769
B30: Basic EPS | C30: =C26/C29 -> 2.0877582 | D30: =D26/D29 -> 2.3168851 | E30: =E26/E29 -> 3.0033534 | F30: =F26/F29 -> 2.9914458 | G30: =G26/G29 -> 3.3085873 | H30: =H26/H29 -> 5.6690293 | I30: =I26/I29 -> 6.1546144 | J30: =J26/J29 -> 6.1606693 | ... L30: =L26/L29 -> 7.4930595 | N30: =N26/N29 -> 2.1126515 | O30: =O26/O29 -> 1.5363538 | P30: =P26/P29 -> 1.2028748 | Q30: =Q26/Q29 -> 1.277815 | R30: =R26/R29 -> 1.8875305 | S30: =S26/S29 -> 1.5303582 | T30: =T26/T29 -> 1.2664982 | U30: =U26/U29 -> 1.4580579 | ... AC30: =AC26/AC29 -> 1.837375 | AE30: =AE26/AE29 -> 5.9883382 | AF30: =AF26/AF29 -> 5.9745411 | AG30: =AG26/AG29 -> 6.0365862 | AH30: =AH26/AH29 -> 6.1606693 | AI30: =AI26/AI29 -> 6.5064179 | AJ30: =AJ26/AJ29 -> 6.5162884 | AK30: =AK26/AK29 -> 6.6692304 | AL30: =AL26/AL29 -> 6.1090541 | ... AP30: =AP26/AP29 -> 7.4930595 | AR30: =SUM(AP30/AL30)-1 -> 0.22654987
B32: Fully Diluted Shares | C32: 22001.127 | D32: 21006.767 | E32: 20000.436 | F32: 18595.651 | G32: 17528.214 | H32: 16864.919 | I32: 16325.819 | J32: 15812.547 | K32: 15408.095 | L32: 15004.697 | N32: 16519.291 | O32: 16403.316 | P32: 16262.203 | Q32: =I32 -> 16325.819 | R32: 15955.718 | S32: 15847.05 | T32: 15775.021 | U32: =J32 -> 15812.547 | V32: 15576.641 | W32: 15464.709 | X32: 15348.175 | Y32: =K32 -> 15408.095 | Z32: 15150.865 | AA32: 15056.133 | AB32: 14948.179 | AC32: =L32 -> 15004.697 | AE32: =R32 -> 15955.718 | AF32: =S32 -> 15847.05 | AG32: =T32 -> 15775.021 | AH32: =U32 -> 15812.547 | AI32: =V32 -> 15576.641 | AJ32: =W32 -> 15464.709 | AK32: =X32 -> 15348.175 | AL32: =Y32 -> 15408.095 | ... AP32: =AC32 -> 15004.697 | AR32: =SUM(AP32/AL32)-1 -> -0.026180913
B33: Diluted EPS | C33: =C26/C32 -> 2.0765754 | D33: =D26/D32 -> 2.3016869 | E33: =E26/E32 -> 2.9764851 | F33: =F26/F32 -> 2.9714475 | G33: =G26/G32 -> 3.275348 | H33: =H26/H32 -> 5.6140204 | I33: =I26/I32 -> 6.1132002 | J33: =J26/J32 -> 6.1340529 | ... L33: =L26/L32 -> 7.4649958 | N33: =N26/N32 -> 2.0963369 | O33: =O26/O32 -> 1.5246917 | P33: =P26/P32 -> 1.195533 | Q33: =Q26/Q32 -> 1.2692166 | R33: =R26/R32 -> 1.8800784 | S33: =S26/S32 -> 1.524574 | T33: =T26/T32 -> 1.2602836 | U33: =U26/U32 -> 1.4517585 | ... AC33: =AC26/AC32 -> 1.8304935 | AE33: =AE26/AE32 -> 5.9646955 | AF33: =AF26/AF32 -> 5.9519595 | AG33: =AG26/AG32 -> 6.0069651 | AH33: =AH26/AH32 -> 6.1340529 | AI33: =AI26/AI32 -> 6.4784827 | AJ33: =AJ26/AJ32 -> 6.4914898 | AK33: =AK26/AK32 -> 6.6428745 | AL33: =AL26/AL32 -> 6.0835554 | ... AP33: =AP26/AP32 -> 7.4649958 | AR33: =SUM(AP33/AL33)-1 -> 0.2270778
A35: X | B35: Balance Sheet | C35: FYE | N35: Quarterly | AK35: LTM | AR35: Variance
B36: =B7 -> Fiscal Period | C36: =C7 -> 2016 | D36: =D7 -> 2017 | E36: =E7 -> 2018 | F36: =F7 -> 2019 | G36: =G7 -> 2020 | H36: =H7 -> 2021 | I36: =I7 -> 2022 | ... L36: =L7 -> 2025 | N36: =N7 -> 1Q22 | O36: =O7 -> 2Q22 | P36: =P7 -> 3Q22 | Q36: =Q7 -> 4Q22 | R36: =R7 -> 1Q23 | S36: =S7 -> 2Q23 | T36: =T7 -> 3Q23 | U36: =U7 -> 4Q23 | ... AC36: =AC7 -> 4Q25 | AE36: =AE7 -> 1Q23 | AF36: =AF7 -> 2Q23 | AG36: =AG7 -> 3Q23 | AH36: =AH7 -> 4Q23 | AI36: =AI7 -> 1Q24 | AJ36: =AJ7 -> 2Q24 | AK36: =AK7 -> 3Q24 | AL36: =AL7 -> 4Q24 | ... AP36: =AP7 -> 4Q25
B37: =B8 -> Fiscal Period End Date | C37: =C8 -> 42643 | D37: =D8 -> 43008 | E37: =E8 -> 43372 | F37: =F8 -> 43737 | G37: =G8 -> 44104 | H37: =H8 -> 44469 | I37: =I8 -> 44834 | ... L37: =L8 -> 45927 | N37: =N8 -> 44560 | O37: =O8 -> 44650 | P37: =P8 -> 44742 | Q37: =Q8 -> 44834 | R37: =R8 -> 44917 | S37: =S8 -> 45008 | T37: =T8 -> 45100 | U37: =U8 -> 45192 | ... AC37: =AC8 -> 45927 | AE37: =AE8 -> 44917 | AF37: =AF8 -> 45008 | AG37: =AG8 -> 45100 | AH37: =AH8 -> 45192 | AI37: =AI8 -> 45283 | AJ37: =AJ8 -> 45375 | AK37: =AK8 -> 45467 | AL37: =AL8 -> 45559 | ... AP37: =AP8 -> 45927
B39: Cash/Equivalents | C39: 20484 | D39: 20289 | E39: 25913 | F39: 48844 | G39: 38016 | H39: 34940 | I39: 23646 | J39: 29965 | K39: 29943 | L39: 35934 | N39: 37119 | O39: 28098 | P39: 27502 | Q39: =I39 -> 23646 | R39: 20535 | S39: 24687 | T39: 28408 | U39: =J39 -> 29965 | V39: 40760 | W39: 32695 | X39: 25565 | Y39: =K39 -> 29943 | Z39: 30299 | AA39: 28162 | AB39: 36269 | AC39: =L39 -> 35934 | AE39: =R39 -> 20535 | AF39: =S39 -> 24687 | AG39: =T39 -> 28408 | AH39: =U39 -> 29965 | AI39: =V39 -> 40760 | AJ39: =W39 -> 32695 | AK39: =X39 -> 25565 | AL39: =Y39 -> 29943 | ... AP39: =AC39 -> 35934 | AR39: =SUM(AP39/AL39)-1 -> 0.20008015
B40: Marketable Securities, Current | C40: 46671 | D40: 53892 | E40: 40388 | F40: 51713 | G40: 52927 | H40: 27699 | I40: 24658 | J40: 31590 | K40: 35228 | L40: 18763 | N40: 26794 | O40: 23413 | P40: 20729 | Q40: =I40 -> 24658 | R40: 30820 | S40: 31185 | T40: 34074 | U40: =J40 -> 31590 | V40: 32340 | W40: 34455 | X40: 36236 | Y40: =K40 -> 35228 | Z40: 23476 | AA40: 20336 | AB40: 19103 | AC40: =L40 -> 18763 | AE40: =R40 -> 30820 | AF40: =S40 -> 31185 | AG40: =T40 -> 34074 | AH40: =U40 -> 31590 | AI40: =V40 -> 32340 | AJ40: =W40 -> 34455 | AK40: =X40 -> 36236 | AL40: =Y40 -> 35228 | ... AP40: =AC40 -> 18763 | AR40: =SUM(AP40/AL40)-1 -> -0.4673839
B41: Accounts Receivable | C41: 15754 | D41: 17874 | E41: 23186 | F41: 22926 | G41: 16120 | H41: 26278 | I41: 28184 | J41: 29508 | K41: 66243 | L41: 39777 | N41: 30213 | O41: 20815 | P41: 21803 | Q41: =I41 -> 28184 | R41: 23752 | S41: 17936 | T41: 19549 | U41: =J41 -> 29508 | V41: 23194 | W41: 21837 | X41: 22795 | Y41: =K41 -> 66243 | Z41: 29639 | AA41: 49798 | AB41: 46835 | AC41: =L41 -> 39777 | AE41: =R41 -> 23752 | AF41: =S41 -> 17936 | AG41: =T41 -> 19549 | AH41: =U41 -> 29508 | AI41: =V41 -> 23194 | AJ41: =W41 -> 21837 | AK41: =X41 -> 22795 | AL41: =Y41 -> 66243 | ... AP41: =AC41 -> 39777 | AR41: =SUM(AP41/AL41)-1 -> -0.39952901
B42: Inventory | C42: 2132 | D42: 4855 | E42: 3956 | F42: 4106 | G42: 4061 | H42: 6580 | I42: 4946 | J42: 6331 | K42: 7286 | L42: 5718 | N42: 5876 | O42: 5460 | P42: 5433 | Q42: =I42 -> 4946 | R42: 6820 | S42: 7482 | T42: 7351 | U42: =J42 -> 6331 | V42: 6511 | W42: 6232 | X42: 6165 | Y42: =K42 -> 7286 | Z42: 6911 | AA42: 6269 | AB42: 5925 | AC42: =L42 -> 5718 | AE42: =R42 -> 6820 | AF42: =S42 -> 7482 | AG42: =T42 -> 7351 | AH42: =U42 -> 6331 | AI42: =V42 -> 6511 | AJ42: =W42 -> 6232 | AK42: =X42 -> 6165 | AL42: =Y42 -> 7286 | ... AP42: =AC42 -> 5718 | AR42: =SUM(AP42/AL42)-1 -> -0.21520725
B43: Other Current Assets | C43: 21828 | D43: =13936+17799 -> 31735 | E43: 37896 | F43: 35230 | G43: 32589 | H43: 39339 | I43: 53971 | J43: 46172 | K43: 14287 | L43: =33180+14585 -> 47765 | N43: 53152 | O43: 40394 | P43: 36825 | Q43: =I43 -> 53971 | R43: 46850 | S43: 31623 | T43: 33277 | U43: =J43 -> 46172 | V43: 40887 | W43: 33197 | X43: 34674 | Y43: =K43 -> 14287 | Z43: 42915 | AA43: 14109 | AB43: 14359 | AC43: =L43 -> 47765 | AE43: =R43 -> 46850 | AF43: =S43 -> 31623 | AG43: =T43 -> 33277 | AH43: =U43 -> 46172 | AI43: =V43 -> 40887 | AJ43: =W43 -> 33197 | AK43: =X43 -> 34674 | AL43: =Y43 -> 14287 | ... AP43: =AC43 -> 47765 | AR43: =SUM(AP43/AL43)-1 -> 2.3432491
B44: Total Current Assets | C44: =SUM(C39:C43) -> 106869 | D44: =SUM(D39:D43) -> 128645 | E44: =SUM(E39:E43) -> 131339 | F44: =SUM(F39:F43) -> 162819 | G44: =SUM(G39:G43) -> 143713 | H44: =SUM(H39:H43) -> 134836 | I44: =SUM(I39:I43) -> 135405 | J44: =SUM(J39:J43) -> 143566 | ... L44: =SUM(L39:L43) -> 147957 | N44: =SUM(N39:N43) -> 153154 | O44: =SUM(O39:O43) -> 118180 | P44: =SUM(P39:P43) -> 112292 | Q44: =SUM(Q39:Q43) -> 135405 | R44: =SUM(R39:R43) -> 128777 | S44: =SUM(S39:S43) -> 112913 | T44: =SUM(T39:T43) -> 122659 | U44: =SUM(U39:U43) -> 143566 | ... AC44: =SUM(AC39:AC43) -> 147957 | AE44: =SUM(AE39:AE43) -> 128777 | AF44: =SUM(AF39:AF43) -> 112913 | AG44: =SUM(AG39:AG43) -> 122659 | AH44: =SUM(AH39:AH43) -> 143566 | AI44: =SUM(AI39:AI43) -> 143692 | AJ44: =SUM(AJ39:AJ43) -> 128416 | AK44: =SUM(AK39:AK43) -> 125435 | AL44: =SUM(AL39:AL43) -> 152987 | ... AP44: =SUM(AP39:AP43) -> 147957 | AR44: =SUM(AP44/AL44)-1 -> -0.032878611
B46: Property, plant & equipment | C46: 27010 | D46: 33783 | E46: 41304 | F46: 37378 | G46: 36766 | H46: 39440 | I46: 42117 | J46: 43715 | K46: 45680 | L46: 49834 | N46: 39245 | O46: 39304 | P46: 40335 | Q46: =I46 -> 42117 | R46: 42951 | S46: 43398 | T46: 43550 | U46: =J46 -> 43715 | V46: 43666 | W46: 43546 | X46: 44502 | Y46: =K46 -> 45680 | Z46: 46069 | AA46: 46876 | AB46: 48508 | AC46: =L46 -> 49834 | AE46: =R46 -> 42951 | AF46: =S46 -> 43398 | AG46: =T46 -> 43550 | AH46: =U46 -> 43715 | AI46: =V46 -> 43666 | AJ46: =W46 -> 43546 | AK46: =X46 -> 44502 | AL46: =Y46 -> 45680 | ... AP46: =AC46 -> 49834 | AR46: =SUM(AP46/AL46)-1 -> 0.090936953
B47: Marketable Securities, Net of Current Portion | C47: 170430 | D47: 194714 | E47: 170799 | F47: 105341 | G47: 100887 | H47: 127877 | I47: 120805 | J47: 100544 | K47: 91479 | L47: 77723 | N47: 138683 | O47: 141219 | P47: 131077 | Q47: =I47 -> 120805 | R47: 114095 | S47: 110461 | T47: 104061 | U47: =J47 -> 100544 | V47: 99475 | W47: 95187 | X47: 91240 | Y47: =K47 -> 91479 | Z47: 87593 | AA47: 84424 | AB47: 77614 | AC47: =L47 -> 77723 | AE47: =R47 -> 114095 | AF47: =S47 -> 110461 | AG47: =T47 -> 104061 | AH47: =U47 -> 100544 | AI47: =V47 -> 99475 | AJ47: =W47 -> 95187 | AK47: =X47 -> 91240 | AL47: =Y47 -> 91479 | ... AP47: =AC47 -> 77723 | AR47: =SUM(AP47/AL47)-1 -> -0.15037331
B48: Other Assets | C48: =5414+3206+8757 -> 17377 | D48: 18177 | E48: 22283 | F48: 32978 | G48: 42522 | H48: 48849 | I48: 54428 | J48: 64758 | K48: 74834 | L48: 83727 | N48: 42071 | O48: 43921 | P48: 44567 | Q48: =I48 -> 54428 | R48: 52886 | S48: 57350 | T48: 56730 | U48: =J48 -> 64758 | V48: 58643 | W48: 62224 | X48: 62397 | Y48: =K48 -> 74834 | Z48: 77183 | AA48: 81259 | AB48: 82882 | AC48: =L48 -> 83727 | AE48: =R48 -> 52886 | AF48: =S48 -> 57350 | AG48: =T48 -> 56730 | AH48: =U48 -> 64758 | AI48: =V48 -> 58643 | AJ48: =W48 -> 62224 | AK48: =X48 -> 62397 | AL48: =Y48 -> 74834 | ... AP48: =AC48 -> 83727 | AR48: =SUM(AP48/AL48)-1 -> 0.11883636
B49: Total Assets | C49: =SUM(C46:C48)+C44 -> 321686 | D49: =SUM(D46:D48)+D44 -> 375319 | E49: =SUM(E46:E48)+E44 -> 365725 | F49: =SUM(F46:F48)+F44 -> 338516 | G49: =SUM(G46:G48)+G44 -> 323888 | H49: =SUM(H46:H48)+H44 -> 351002 | I49: =SUM(I46:I48)+I44 -> 352755 | J49: =SUM(J46:J48)+J44 -> 352583 | ... L49: =SUM(L46:L48)+L44 -> 359241 | N49: =SUM(N46:N48)+N44 -> 373153 | O49: =SUM(O46:O48)+O44 -> 342624 | P49: =SUM(P46:P48)+P44 -> 328271 | Q49: =SUM(Q46:Q48)+Q44 -> 352755 | R49: =SUM(R46:R48)+R44 -> 338709 | S49: =SUM(S46:S48)+S44 -> 324122 | T49: =SUM(T46:T48)+T44 -> 327000 | U49: =SUM(U46:U48)+U44 -> 352583 | ... AC49: =SUM(AC46:AC48)+AC44 -> 359241 | AE49: =SUM(AE46:AE48)+AE44 -> 338709 | AF49: =SUM(AF46:AF48)+AF44 -> 324122 | AG49: =SUM(AG46:AG48)+AG44 -> 327000 | AH49: =SUM(AH46:AH48)+AH44 -> 352583 | AI49: =SUM(AI46:AI48)+AI44 -> 345476 | AJ49: =SUM(AJ46:AJ48)+AJ44 -> 329373 | AK49: =SUM(AK46:AK48)+AK44 -> 323574 | AL49: =SUM(AL46:AL48)+AL44 -> 364980 | ... AP49: =SUM(AP46:AP48)+AP44 -> 359241 | AR49: =SUM(AP49/AL49)-1 -> -0.015724149
B51: Accounts Payable | C51: 37294 | D51: 44242 | E51: 55888 | F51: 46236 | G51: 42296 | H51: 54763 | I51: 64115 | J51: 62611 | K51: 68960 | L51: 69860 | N51: 74362 | O51: 52682 | P51: 48343 | Q51: =I51 -> 64115 | R51: 57918 | S51: 42945 | T51: 46699 | U51: =J51 -> 62611 | V51: 58146 | W51: 45753 | X51: 47574 | Y51: =K51 -> 68960 | Z51: 61910 | AA51: 54126 | AB51: 50374 | AC51: =L51 -> 69860 | AE51: =R51 -> 57918 | AF51: =S51 -> 42945 | AG51: =T51 -> 46699 | AH51: =U51 -> 62611 | AI51: =V51 -> 58146 | AJ51: =W51 -> 45753 | AK51: =X51 -> 47574 | AL51: =Y51 -> 68960 | ... AP51: =AC51 -> 69860 | AR51: =SUM(AP51/AL51)-1 -> 0.013051044
B52: Deferred Revenue | C52: 8080 | D52: 7548 | E52: 7543 | F52: 5522 | G52: 6643 | H52: 7612 | I52: 7912 | J52: 8061 | K52: 8249 | L52: 9055 | N52: 7876 | O52: 7920 | P52: 7728 | Q52: =I52 -> 7912 | R52: 7992 | S52: 8131 | T52: 8158 | U52: =J52 -> 8061 | V52: 8264 | W52: 8012 | X52: 8053 | Y52: =K52 -> 8249 | Z52: 8461 | AA52: 8976 | AB52: 8979 | AC52: =L52 -> 9055 | AE52: =R52 -> 7992 | AF52: =S52 -> 8131 | AG52: =T52 -> 8158 | AH52: =U52 -> 8061 | AI52: =V52 -> 8264 | AJ52: =W52 -> 8012 | AK52: =X52 -> 8053 | AL52: =Y52 -> 8249 | ... AP52: =AC52 -> 9055 | AR52: =SUM(AP52/AL52)-1 -> 0.097708813
B53: Other Current Liabilities | C53: 22027 | D53: 30551 | E53: 32687 | F53: 37720 | G53: 42684 | H53: 47493 | I53: 60845 | J53: 58829 | K53: 78304 | L53: 66387 | N53: 49167 | O53: 50248 | P53: 48811 | Q53: =I53 -> 60845 | R53: 59893 | S53: 56425 | T53: 58897 | U53: =J53 -> 58829 | V53: 54611 | W53: 57298 | X53: 60889 | Y53: =K53 -> 78304 | Z53: 61151 | AA53: 61849 | AB53: 62499 | AC53: =L53 -> 66387 | AE53: =R53 -> 59893 | AF53: =S53 -> 56425 | AG53: =T53 -> 58897 | AH53: =U53 -> 58829 | AI53: =V53 -> 54611 | AJ53: =W53 -> 57298 | AK53: =X53 -> 60889 | AL53: =Y53 -> 78304 | ... AP53: =AC53 -> 66387 | AR53: =SUM(AP53/AL53)-1 -> -0.1521889
B54: Commerical Paper | C54: 8105 | D54: 11977 | E54: 11964 | F54: 5980 | G54: 4996 | H54: 6000 | I54: 9982 | J54: 5985 | K54: 9967 | L54: 7979 | N54: 5000 | O54: 6999 | P54: 10982 | Q54: 9982 | R54: 1743 | S54: 1996 | T54: 3993 | U54: 5985 | V54: 1998 | W54: 1997 | X54: 2994 | Y54: 9967 | Z54: 1995 | AA54: 5982 | AB54: 9923 | AC54: =L54 -> 7979 | AE54: =R54 -> 1743 | AF54: =S54 -> 1996 | AG54: =T54 -> 3993 | AH54: =U54 -> 5985 | AI54: =V54 -> 1998 | AJ54: =W54 -> 1997 | AK54: =X54 -> 2994 | AL54: =Y54 -> 9967 | ... AP54: =AC54 -> 7979 | AR54: =SUM(AP54/AL54)-1 -> -0.19945821
B55: Term Debt, Current Portion | C55: 3500 | D55: 6496 | E55: 8784 | F55: 10260 | G55: 8773 | H55: 9613 | I55: 11128 | J55: 9822 | K55: 10912 | L55: 12350 | N55: 11169 | O55: 9659 | P55: 14009 | Q55: 11128 | R55: 9740 | S55: 10578 | T55: 7216 | U55: 9822 | V55: 10954 | W55: 10762 | X55: 12114 | Y55: 10912 | Z55: 10848 | AA55: 13638 | AB55: 9345 | AC55: =L55 -> 12350 | AE55: =R55 -> 9740 | AF55: =S55 -> 10578 | AG55: =T55 -> 7216 | AH55: =U55 -> 9822 | AI55: =V55 -> 10954 | AJ55: =W55 -> 10762 | AK55: =X55 -> 12114 | AL55: =Y55 -> 10912 | ... AP55: =AC55 -> 12350 | AR55: =SUM(AP55/AL55)-1 -> 0.13178152
B56: Total Current Liabilities | C56: =SUM(C51:C55) -> 79006 | D56: =SUM(D51:D55) -> 100814 | E56: =SUM(E51:E55) -> 116866 | F56: =SUM(F51:F55) -> 105718 | G56: =SUM(G51:G55) -> 105392 | H56: =SUM(H51:H55) -> 125481 | I56: =SUM(I51:I55) -> 153982 | J56: =SUM(J51:J55) -> 145308 | ... L56: =SUM(L51:L55) -> 165631 | N56: =SUM(N51:N55) -> 147574 | O56: =SUM(O51:O55) -> 127508 | P56: =SUM(P51:P55) -> 129873 | Q56: =SUM(Q51:Q55) -> 153982 | R56: =SUM(R51:R55) -> 137286 | S56: =SUM(S51:S55) -> 120075 | T56: =SUM(T51:T55) -> 124963 | U56: =SUM(U51:U55) -> 145308 | ... AC56: =SUM(AC51:AC55) -> 165631 | AE56: =SUM(AE51:AE55) -> 137286 | AF56: =SUM(AF51:AF55) -> 120075 | AG56: =SUM(AG51:AG55) -> 124963 | AH56: =SUM(AH51:AH55) -> 145308 | AI56: =SUM(AI51:AI55) -> 133973 | AJ56: =SUM(AJ51:AJ55) -> 123822 | AK56: =SUM(AK51:AK55) -> 131624 | AL56: =SUM(AL51:AL55) -> 176392 | ... AP56: =SUM(AP51:AP55) -> 165631 | AR56: =SUM(AP56/AL56)-1 -> -0.061006168
B58: Long-Term Debt | C58: 75427 | D58: 97207 | E58: 93735 | F58: 91807 | G58: 98667 | H58: 109106 | I58: 98959 | J58: 95281 | K58: 85750 | L58: 78328 | N58: 106629 | O58: 103323 | P58: 94700 | Q58: =I58 -> 98959 | R58: 99627 | S58: 97041 | T58: 98071 | U58: =J58 -> 95281 | V58: 95088 | W58: 91831 | X58: 86196 | Y58: =K58 -> 85750 | Z58: 83956 | AA58: 78566 | AB58: 82430 | AC58: =L58 -> 78328 | AE58: =R58 -> 99627 | AF58: =S58 -> 97041 | AG58: =T58 -> 98071 | AH58: =U58 -> 95281 | AI58: =V58 -> 95088 | AJ58: =W58 -> 91831 | AK58: =X58 -> 86196 | AL58: =Y58 -> 85750 | ... AP58: =AC58 -> 78328 | AR58: =SUM(AP58/AL58)-1 -> -0.086553936
B59: Other Non-Current Liabilities | C59: =36074+2930 -> 39004 | D59: =40415+2836 -> 43251 | E59: =45180+2797 -> 47977 | F59: 50503 | G59: 54490 | H59: 53325 | I59: 49142 | J59: 49848 | K59: 45888 | L59: 41549 | N59: 55056 | O59: 52432 | P59: 53629 | Q59: =I59 -> 49142 | R59: 53107 | S59: 52886 | T59: 51730 | U59: =J59 -> 49848 | V59: 50353 | W59: 47564 | X59: 47084 | Y59: =K59 -> 45888 | Z59: 49006 | AA59: 41300 | AB59: 42115 | AC59: =L59 -> 41549 | AE59: =R59 -> 53107 | AF59: =S59 -> 52886 | AG59: =T59 -> 51730 | AH59: =U59 -> 49848 | AI59: =V59 -> 50353 | AJ59: =W59 -> 47564 | AK59: =X59 -> 47084 | AL59: =Y59 -> 45888 | ... AP59: =AC59 -> 41549 | AR59: =SUM(AP59/AL59)-1 -> -0.094556311
B60: Total Liabilities | C60: =SUM(C58:C59)+C56 -> 193437 | D60: =SUM(D58:D59)+D56 -> 241272 | E60: =SUM(E58:E59)+E56 -> 258578 | F60: =SUM(F58:F59)+F56 -> 248028 | G60: =SUM(G58:G59)+G56 -> 258549 | H60: =SUM(H58:H59)+H56 -> 287912 | I60: =SUM(I58:I59)+I56 -> 302083 | J60: =SUM(J58:J59)+J56 -> 290437 | ... L60: =SUM(L58:L59)+L56 -> 285508 | N60: =SUM(N58:N59)+N56 -> 309259 | O60: =SUM(O58:O59)+O56 -> 283263 | P60: =SUM(P58:P59)+P56 -> 278202 | Q60: =SUM(Q58:Q59)+Q56 -> 302083 | R60: =SUM(R58:R59)+R56 -> 290020 | S60: =SUM(S58:S59)+S56 -> 270002 | T60: =SUM(T58:T59)+T56 -> 274764 | U60: =SUM(U58:U59)+U56 -> 290437 | ... AC60: =SUM(AC58:AC59)+AC56 -> 285508 | AE60: =SUM(AE58:AE59)+AE56 -> 290020 | AF60: =SUM(AF58:AF59)+AF56 -> 270002 | AG60: =SUM(AG58:AG59)+AG56 -> 274764 | AH60: =SUM(AH58:AH59)+AH56 -> 290437 | AI60: =SUM(AI58:AI59)+AI56 -> 279414 | AJ60: =SUM(AJ58:AJ59)+AJ56 -> 263217 | AK60: =SUM(AK58:AK59)+AK56 -> 264904 | AL60: =SUM(AL58:AL59)+AL56 -> 308030 | ... AP60: =SUM(AP58:AP59)+AP56 -> 285508 | AR60: =SUM(AP60/AL60)-1 -> -0.073116255
B62: Common Stock | C62: 31251 | D62: 35867 | E62: 40201 | F62: 45174 | G62: 50779 | H62: 57365 | I62: 64849 | J62: 73812 | K62: 83276 | L62: 93568 | N62: 58424 | O62: 61181 | P62: 62115 | Q62: =I62 -> 64849 | R62: 66399 | S62: 69568 | T62: 70667 | U62: =J62 -> 73812 | V62: 75236 | W62: 75236 | X62: 79850 | Y62: =K62 -> 83276 | Z62: 84768 | AA62: 88711 | AB62: 89806 | AC62: =L62 -> 93568 | AE62: =R62 -> 66399 | AF62: =S62 -> 69568 | AG62: =T62 -> 70667 | AH62: =U62 -> 73812 | AI62: =V62 -> 75236 | AJ62: =W62 -> 75236 | AK62: =X62 -> 79850 | AL62: =Y62 -> 83276 | ... AP62: =AC62 -> 93568 | AR62: =SUM(AP62/AL62)-1 -> 0.12358903
B63: Retained Earnings (Deficit) | C63: 96364 | D63: 98330 | E63: 70400 | F63: 45898 | G63: 14966 | H63: 5562 | I63: -3068 | J63: -214 | K63: -19154 | L63: -14264 | N63: 6397 | O63: 4674 | P63: -2749 | Q63: =I63 -> -3068 | R63: -4798 | S63: -3702 | T63: -6630 | U63: =J63 -> -214 | V63: 204 | W63: -120 | X63: -12764 | Y63: =K63 -> -19154 | Z63: -11221 | AA63: -15552 | AB63: -17613 | AC63: =L63 -> -14264 | AE63: =R63 -> -4798 | AF63: =S63 -> -3702 | AG63: =T63 -> -6630 | AH63: =U63 -> -214 | AI63: =V63 -> 204 | AJ63: =W63 -> -120 | AK63: =X63 -> -12764 | AL63: =Y63 -> -19154 | ... AP63: =AC63 -> -14264 | AR63: =SUM(AP63/AL63)-1 -> -0.25529915
B64: Accumulated Other comprehensive income | C64: 634 | D64: -150 | E64: -3454 | F64: -584 | G64: -406 | H64: 163 | I64: -11109 | J64: -11452 | K64: -7172 | L64: -5571 | N64: -927 | O64: -6494 | P64: -9297 | Q64: =I64 -> -11109 | R64: -12912 | S64: -11746 | T64: -11801 | U64: =J64 -> -11452 | V64: -9378 | W64: -8960 | X64: -8416 | Y64: =K64 -> -7172 | Z64: -6789 | AA64: -6363 | AB64: -6363 | AC64: =L64 -> -5571 | AE64: =R64 -> -12912 | AF64: =S64 -> -11746 | AG64: =T64 -> -11801 | AH64: =U64 -> -11452 | AI64: =V64 -> -9378 | AJ64: =W64 -> -8960 | AK64: =X64 -> -8416 | AL64: =Y64 -> -7172 | ... AP64: =AC64 -> -5571 | AR64: =SUM(AP64/AL64)-1 -> -0.22322922
B65: Total stockholders' equity | C65: =SUM(C62:C64) -> 128249 | D65: =SUM(D62:D64) -> 134047 | E65: =SUM(E62:E64) -> 107147 | F65: =SUM(F62:F64) -> 90488 | G65: =SUM(G62:G64) -> 65339 | H65: =SUM(H62:H64) -> 63090 | I65: =SUM(I62:I64) -> 50672 | J65: =SUM(J62:J64) -> 62146 | ... L65: =SUM(L62:L64) -> 73733 | N65: =SUM(N62:N64) -> 63894 | O65: =SUM(O62:O64) -> 59361 | P65: =SUM(P62:P64) -> 50069 | Q65: =SUM(Q62:Q64) -> 50672 | R65: =SUM(R62:R64) -> 48689 | S65: =SUM(S62:S64) -> 54120 | T65: =SUM(T62:T64) -> 52236 | U65: =SUM(U62:U64) -> 62146 | ... AC65: =SUM(AC62:AC64) -> 73733 | AE65: =SUM(AE62:AE64) -> 48689 | AF65: =SUM(AF62:AF64) -> 54120 | AG65: =SUM(AG62:AG64) -> 52236 | AH65: =SUM(AH62:AH64) -> 62146 | AI65: =SUM(AI62:AI64) -> 66062 | AJ65: =SUM(AJ62:AJ64) -> 66156 | AK65: =SUM(AK62:AK64) -> 58670 | AL65: =SUM(AL62:AL64) -> 56950 | ... AP65: =SUM(AP62:AP64) -> 73733 | AR65: =SUM(AP65/AL65)-1 -> 0.2946971
B66: Total liabilities and stockholders' equity | C66: =SUM(C65+C60) -> 321686 | D66: =SUM(D65+D60) -> 375319 | E66: =SUM(E65+E60) -> 365725 | F66: =SUM(F65+F60) -> 338516 | G66: =SUM(G65+G60) -> 323888 | H66: =SUM(H65+H60) -> 351002 | I66: =SUM(I65+I60) -> 352755 | J66: =SUM(J65+J60) -> 352583 | ... L66: =SUM(L65+L60) -> 359241 | N66: =SUM(N65+N60) -> 373153 | O66: =SUM(O65+O60) -> 342624 | P66: =SUM(P65+P60) -> 328271 | Q66: =SUM(Q65+Q60) -> 352755 | R66: =SUM(R65+R60) -> 338709 | S66: =SUM(S65+S60) -> 324122 | T66: =SUM(T65+T60) -> 327000 | U66: =SUM(U65+U60) -> 352583 | ... AC66: =SUM(AC65+AC60) -> 359241 | AE66: =SUM(AE65+AE60) -> 338709 | AF66: =SUM(AF65+AF60) -> 324122 | AG66: =SUM(AG65+AG60) -> 327000 | AH66: =SUM(AH65+AH60) -> 352583 | AI66: =SUM(AI65+AI60) -> 345476 | AJ66: =SUM(AJ65+AJ60) -> 329373 | AK66: =SUM(AK65+AK60) -> 323574 | AL66: =SUM(AL65+AL60) -> 364980 | ... AP66: =SUM(AP65+AP60) -> 359241 | AR66: =SUM(AP66/AL66)-1 -> -0.015724149
B68: Balance Check | C68: =C66-C49 -> 0 | D68: =D66-D49 -> 0 | E68: =E66-E49 -> 0 | F68: =F66-F49 -> 0 | G68: =G66-G49 -> 0 | H68: =H66-H49 -> 0 | I68: =I66-I49 -> 0 | J68: =J66-J49 -> 0 | ... L68: =L66-L49 -> 0 | N68: =N66-N49 -> 0 | O68: =O66-O49 -> 0 | P68: =P66-P49 -> 0 | Q68: =Q66-Q49 -> 0 | R68: =R66-R49 -> 0 | S68: =S66-S49 -> 0 | T68: =T66-T49 -> 0 | U68: =U66-U49 -> 0 | ... AC68: =AC66-AC49 -> 0 | AE68: =AE66-AE49 -> 0 | AF68: =AF66-AF49 -> 0 | AG68: =AG66-AG49 -> 0 | AH68: =AH66-AH49 -> 0 | AI68: =AI66-AI49 -> 0 | AJ68: =AJ66-AJ49 -> 0 | AK68: =AK66-AK49 -> 0 | AL68: =AL66-AL49 -> 0 | ... AP68: =AP66-AP49 -> 0
A70: X | B70: Cash-Flows Statement | C70: FYE | N70: Quarterly | AK70: LTM | AR70: Variance
B71: =B7 -> Fiscal Period | C71: =C7 -> 2016 | D71: =D7 -> 2017 | E71: =E7 -> 2018 | F71: =F7 -> 2019 | G71: =G7 -> 2020 | H71: =H7 -> 2021 | I71: =I7 -> 2022 | ... L71: =L7 -> 2025 | N71: =N7 -> 1Q22 | O71: =O7 -> 2Q22 | P71: =P7 -> 3Q22 | Q71: =Q7 -> 4Q22 | R71: =R7 -> 1Q23 | S71: =S7 -> 2Q23 | T71: =T7 -> 3Q23 | U71: =U7 -> 4Q23 | ... AC71: =AC7 -> 4Q25 | AE71: =AE7 -> 1Q23 | AF71: =AF7 -> 2Q23 | AG71: =AG7 -> 3Q23 | AH71: =AH7 -> 4Q23 | AI71: =AI7 -> 1Q24 | AJ71: =AJ7 -> 2Q24 | AK71: =AK7 -> 3Q24 | AL71: =AL7 -> 4Q24 | ... AP71: =AP7 -> 4Q25
B72: =B8 -> Fiscal Period End Date | C72: =C8 -> 42643 | D72: =D8 -> 43008 | E72: =E8 -> 43372 | F72: =F8 -> 43737 | G72: =G8 -> 44104 | H72: =H8 -> 44469 | I72: =I8 -> 44834 | ... L72: =L8 -> 45927 | N72: =N8 -> 44560 | O72: =O8 -> 44650 | P72: =P8 -> 44742 | Q72: =Q8 -> 44834 | R72: =R8 -> 44917 | S72: =S8 -> 45008 | T72: =T8 -> 45100 | U72: =U8 -> 45192 | ... AC72: =AC8 -> 45927 | AE72: =AE8 -> 44917 | AF72: =AF8 -> 45008 | AG72: =AG8 -> 45100 | AH72: =AH8 -> 45192 | AI72: =AI8 -> 45283 | AJ72: =AJ8 -> 45375 | AK72: =AK8 -> 45467 | AL72: =AL8 -> 45559 | ... AP72: =AP8 -> 45927
B74: Cash-Flows From Operating Activities
B75: Net income (loss) | C75: =C26 -> 45687 | D75: =D26 -> 48351 | E75: =E26 -> 59531 | F75: =F26 -> 55256 | G75: =G26 -> 57411 | H75: =H26 -> 94680 | I75: =I26 -> 99803 | J75: =J26 -> 96995 | ... L75: =L26 -> 112010 | N75: =N26 -> 34630 | O75: =O26 -> 25010 | P75: =P26 -> 19442 | Q75: =Q26 -> 20721 | R75: =R26 -> 29998 | S75: =S26 -> 24160 | T75: =T26 -> 19881 | U75: =U26 -> 22956 | ... AC75: =AC26 -> 27466 | AE75: =SUM(O75:R75) -> 95171 | AF75: =SUM(P75:S75) -> 94321 | AG75: =SUM(Q75:T75) -> 94760 | AH75: =SUM(R75:U75) -> 96995 | AI75: =SUM(S75:V75) -> 100913 | AJ75: =SUM(T75:W75) -> 100389 | AK75: =SUM(U75:X75) -> 101956 | AL75: =SUM(V75:Y75) -> 93736 | ... AP75: =SUM(Z75:AC75) -> 112010 | AR75: =SUM(AP75/AL75)-1 -> 0.19495178
B77: Adjustments to reconcile net income:
B78: Depreciation and Amortization | C78: 10505 | D78: 10157 | E78: 10903 | F78: 12547 | G78: 11056 | H78: 11284 | I78: 11104 | J78: 11519 | K78: 11445 | L78: 11698 | N78: 2697 | O78: =5434-N78 -> 2737 | P78: =8239-SUM(N78:O78) -> 2805 | Q78: =SUM(I78-SUM(N78:P78)) -> 2865 | R78: 2916 | S78: =5814-R78 -> 2898 | T78: 3052 | U78: =SUM(J78-SUM(R78:T78)) -> 2653 | V78: 2848 | W78: =5684-V78 -> 2836 | X78: =8534-W78-V78 -> 2850 | Y78: =SUM(K78-SUM(V78:X78)) -> 2911 | Z78: 3080 | AA78: =5741-Z78 -> 2661 | AB78: =8571-AA78-Z78 -> 2830 | AC78: =SUM(L78-SUM(Z78:AB78)) -> 3127 | AE78: =SUM(O78:R78) -> 11323 | AF78: =SUM(P78:S78) -> 11484 | AG78: =SUM(Q78:T78) -> 11731 | AH78: =SUM(R78:U78) -> 11519 | AI78: =SUM(S78:V78) -> 11451 | AJ78: =SUM(T78:W78) -> 11389 | AK78: =SUM(U78:X78) -> 11187 | AL78: =SUM(V78:Y78) -> 11445 | ... AP78: =SUM(Z78:AC78) -> 11698 | AR78: =SUM(AP78/AL78)-1 -> 0.022105723
B79: Stock Based Compensation | C79: 4210 | D79: 4840 | E79: 5340 | F79: 6068 | G79: 6829 | H79: 7906 | I79: 9038 | J79: 10833 | K79: 11688 | L79: 12863 | N79: 2265 | O79: =4517-N79 -> 2252 | P79: =6760-SUM(N79:O79) -> 2243 | Q79: =SUM(I79-SUM(N79:P79)) -> 2278 | R79: 2905 | S79: =5591-R79 -> 2686 | T79: 2617 | U79: =SUM(J79-SUM(R79:T79)) -> 2625 | V79: 2997 | W79: =5961-V79+3 -> 2967 | X79: =8830-W79-V79 -> 2866 | Y79: =SUM(K79-SUM(V79:X79)) -> 2858 | Z79: 3286 | AA79: =6512-Z79 -> 3226 | AB79: =9680-AA79-Z79 -> 3168 | AC79: =SUM(L79-SUM(Z79:AB79)) -> 3183 | AE79: =SUM(O79:R79) -> 9678 | AF79: =SUM(P79:S79) -> 10112 | AG79: =SUM(Q79:T79) -> 10486 | AH79: =SUM(R79:U79) -> 10833 | AI79: =SUM(S79:V79) -> 10925 | AJ79: =SUM(T79:W79) -> 11206 | AK79: =SUM(U79:X79) -> 11455 | AL79: =SUM(V79:Y79) -> 11688 | ... AP79: =SUM(Z79:AC79) -> 12863 | AR79: =SUM(AP79/AL79)-1 -> 0.10053046
B80: Deferred Taxes | C80: 4938 | D80: 5966 | E80: -32590 | F80: -340 | G80: -215 | H80: -4774 | I80: 895 | J80: 0 | K80: 0 | L80: 0 | N80: 682 | O80: =1088-N80 -> 406 | P80: =2756-SUM(N80:O80) -> 1668 | Q80: =SUM(I80-SUM(N80:P80)) -> -1861 | R80: 0 | S80: =R80 -> 0 | T80: 0 | U80: =SUM(J80-SUM(R80:T80)) -> 0 | V80: =U80 -> 0 | W80: 0 | X80: 0 | Y80: =SUM(K80-SUM(V80:X80)) -> 0 | Z80: =Y80 -> 0 | AA80: =Z80 -> 0 | AB80: 0 | AC80: =SUM(L80-SUM(Z80:AB80)) -> 0 | AE80: =SUM(O80:R80) -> 213 | AF80: =SUM(P80:S80) -> -193 | AG80: =SUM(Q80:T80) -> -1861 | AH80: =SUM(R80:U80) -> 0 | AI80: =SUM(S80:V80) -> 0 | AJ80: =SUM(T80:W80) -> 0 | AK80: =SUM(U80:X80) -> 0 | AL80: =SUM(V80:Y80) -> 0 | ... AP80: =SUM(Z80:AC80) -> 0 | AR80: =SUM(AP80/AL80)-1 -> #DIV/0!
B81: Other | C81: 0 | D81: -166 | E81: -444 | F81: -652 | G81: -97 | H81: -147 | I81: 111 | J81: -2227 | K81: -2266 | L81: -89 | N81: 167 | O81: =-20-N81 -> -187 | P81: =-61-SUM(N81:O81) -> -41 | Q81: =SUM(I81-SUM(N81:P81)) -> 172 | R81: -317 | S81: =-1732-R81 -> -1415 | T81: 81 | U81: =SUM(J81-SUM(R81:T81)) -> -576 | V81: -989 | W81: =-1971-V81 -> -982 | X81: =-1964-W81-V81 -> 7 | Y81: =SUM(K81-SUM(V81:X81)) -> -302 | Z81: -2009 | AA81: =-2217-Z81 -> -208 | AB81: =-1748-AA81-Z81 -> 469 | AC81: =SUM(L81-SUM(Z81:AB81)) -> 1659 | AE81: =SUM(O81:R81) -> -373 | AF81: =SUM(P81:S81) -> -1601 | AG81: =SUM(Q81:T81) -> -1479 | AH81: =SUM(R81:U81) -> -2227 | AI81: =SUM(S81:V81) -> -2899 | AJ81: =SUM(T81:W81) -> -2466 | AK81: =SUM(U81:X81) -> -2540 | AL81: =SUM(V81:Y81) -> -2266 | ... AP81: =SUM(Z81:AC81) -> -89 | AR81: =SUM(AP81/AL81)-1 -> -0.96072374
B83: Changes in assets and liabilities:
B84: Accounts Receivable | C84: 1095 | D84: -2093 | E84: -5322 | F84: 245 | G84: 6917 | H84: -10125 | I84: -1823 | J84: -1688 | K84: -3788 | L84: -6682 | N84: -3934 | O84: =5542-N84 -> 9476 | P84: =4561-SUM(N84:O84) -> -981 | Q84: =SUM(I84-SUM(N84:P84)) -> -6384 | R84: 4275 | S84: =9596-R84 -> 5321 | T84: -1987 | U84: =SUM(J84-SUM(R84:T84)) -> -9297 | V84: 6555 | W84: =7727-V84 -> 1172 | X84: =6697-W84-V84 -> -1030 | Y84: =SUM(K84-SUM(V84:X84)) -> -10485 | Z84: 3597 | AA84: =7266-Z84 -> 3669 | AB84: =5685-AA84-Z84 -> -1581 | AC84: =SUM(L84-SUM(Z84:AB84)) -> -12367 | AE84: =SUM(O84:R84) -> 6386 | AF84: =SUM(P84:S84) -> 2231 | AG84: =SUM(Q84:T84) -> 1225 | AH84: =SUM(R84:U84) -> -1688 | AI84: =SUM(S84:V84) -> 592 | AJ84: =SUM(T84:W84) -> -3557 | AK84: =SUM(U84:X84) -> -2600 | AL84: =SUM(V84:Y84) -> -3788 | ... AP84: =SUM(Z84:AC84) -> -6682 | AR84: =SUM(AP84/AL84)-1 -> 0.76399155
B85: Inventory | C85: 217 | D85: -2723 | E85: 828 | F85: -289 | G85: -127 | H85: -2642 | I85: 1484 | J85: -1618 | K85: -1046 | L85: -9197 | N85: 681 | O85: =1065-N85 -> 384 | P85: =1049-SUM(N85:O85) -> -16 | Q85: =SUM(I85-SUM(N85:P85)) -> 435 | R85: -1807 | S85: =-2548-R85 -> -741 | T85: -22 | U85: =SUM(J85-SUM(R85:T85)) -> 952 | V85: -137 | W85: =53-V85 -> 190 | X85: =41-W85-V85 -> -12 | Y85: =SUM(K85-SUM(V85:X85)) -> -1087 | Z85: 215 | AA85: =858-Z85 -> 643 | AB85: =1223-AA85-Z85 -> 365 | AC85: =SUM(L85-SUM(Z85:AB85)) -> -10420 | AE85: =SUM(O85:R85) -> -1004 | AF85: =SUM(P85:S85) -> -2129 | AG85: =SUM(Q85:T85) -> -2135 | AH85: =SUM(R85:U85) -> -1618 | AI85: =SUM(S85:V85) -> 52 | AJ85: =SUM(T85:W85) -> 983 | AK85: =SUM(U85:X85) -> 993 | AL85: =SUM(V85:Y85) -> -1046 | ... AP85: =SUM(Z85:AC85) -> -9197 | AR85: =SUM(AP85/AL85)-1 -> 7.792543
B86: Other current and non-current assets | C86: 1039 | D86: -9572 | E86: -8433 | F86: 3804 | G86: -8035 | H86: -11945 | I86: -14019 | J86: -4413 | K86: -13087 | L86: 1400 | N86: =-9812-4921 -> -14733 | O86: =643-3542-N86 -> 11834 | P86: =4789-3289-SUM(N86:O86) -> 4399 | Q86: =SUM(I86-SUM(N86:P86)) -> -15519 | R86: =-4099+2320 -> -1779 | S86: =14785-4092-R86 -> 12472 | T86: -2445 | U86: =SUM(J86-SUM(R86:T86)) -> -12661 | V86: =4569-1457 -> 3112 | W86: =12161-4438-V86 -> 4611 | X86: =11100-5626-W86-V86 -> -2249 | Y86: =SUM(K86-SUM(V86:X86)) -> -18561 | Z86: 4105 | AA86: =9171+-4371-Z86 -> 695 | AB86: =13555+-6116-AA86-Z86 -> 2639 | AC86: =SUM(L86-SUM(Z86:AB86)) -> -6039 | AE86: =SUM(O86:R86) -> -1065 | AF86: =SUM(P86:S86) -> -427 | AG86: =SUM(Q86:T86) -> -7271 | AH86: =SUM(R86:U86) -> -4413 | AI86: =SUM(S86:V86) -> 478 | AJ86: =SUM(T86:W86) -> -7383 | AK86: =SUM(U86:X86) -> -7187 | AL86: =SUM(V86:Y86) -> -13087 | ... AP86: =SUM(Z86:AC86) -> 1400 | AR86: =SUM(AP86/AL86)-1 -> -1.1069764
B87: Accounts Payable | C87: 1791 | D87: 9618 | E87: 9175 | F87: -1923 | G87: -4062 | H87: 12326 | I87: 9448 | J87: -1889 | K87: 6020 | L87: 902 | N87: 19813 | O87: =-1750-N87 -> -21563 | P87: =-6108-SUM(N87:O87) -> -4358 | Q87: =SUM(I87-SUM(N87:P87)) -> 15556 | R87: -6075 | S87: =-20764-R87 -> -14689 | T87: 3974 | U87: =SUM(J87-SUM(R87:T87)) -> 14901 | V87: -4542 | W87: =-16710-V87 -> -12168 | X87: =-15171-W87-V87 -> 1539 | Y87: =SUM(K87-SUM(V87:X87)) -> 21191 | Z87: -6671 | AA87: =-14604-Z87 -> -7933 | AB87: =-18479-AA87-Z87 -> -3875 | AC87: =SUM(L87-SUM(Z87:AB87)) -> 19381 | AE87: =SUM(O87:R87) -> -16440 | AF87: =SUM(P87:S87) -> -9566 | AG87: =SUM(Q87:T87) -> -1234 | AH87: =SUM(R87:U87) -> -1889 | AI87: =SUM(S87:V87) -> -356 | AJ87: =SUM(T87:W87) -> 2165 | AK87: =SUM(U87:X87) -> -270 | AL87: =SUM(V87:Y87) -> 6020 | ... AP87: =SUM(Z87:AC87) -> 902 | AR87: =SUM(AP87/AL87)-1 -> -0.85016611
B88: Deferred Revenue | C88: -1554 | D88: -626 | E88: -44 | F88: -625 | G88: 2081 | H88: 1676 | I88: 478 | J88: 0 | K88: 0 | L88: 0 | N88: 462 | O88: =627-N88 -> 165 | P88: =260-SUM(N88:O88) -> -367 | Q88: =SUM(I88-SUM(N88:P88)) -> 218 | R88: 131 | S88: =0-R88 -> -131 | T88: 0 | U88: =SUM(J88-SUM(R88:T88)) -> 0 | V88: 0 | W88: 0 | X88: 0 | Y88: =SUM(K88-SUM(V88:X88)) -> 0 | Z88: 0 | AA88: 0 | AB88: 0 | AC88: =SUM(L88-SUM(Z88:AB88)) -> 0 | AE88: =SUM(O88:R88) -> 147 | AF88: =SUM(P88:S88) -> -149 | AG88: =SUM(Q88:T88) -> 218 | AH88: =SUM(R88:U88) -> 0 | AI88: =SUM(S88:V88) -> -131 | AJ88: =SUM(T88:W88) -> 0 | AK88: =SUM(U88:X88) -> 0 | AL88: =SUM(V88:Y88) -> 0 | ... AP88: =SUM(Z88:AC88) -> 0 | AR88: =SUM(AP88/AL88)-1 -> #DIV/0!
B89: Other Asset and Other Liabilities | C89: -2104 | D89: -154 | E89: 38490 | F89: -4700 | G89: 8916 | H89: 5799 | I89: 5632 | J89: 3031 | K89: 15552 | L89: =-347-11076 -> -11423 | N89: 4236 | O89: =1888-N89 -> -2348 | P89: =-14-SUM(N89:O89) -> -1902 | Q89: =SUM(I89-SUM(N89:P89)) -> 5646 | R89: 3758 | S89: =1757-R89 -> -2001 | T89: 1229 | U89: =SUM(J89-SUM(R89:T89)) -> 45 | V89: -3865 | W89: =-3437-V89 -> 428 | X89: =2-W89-V89 -> 3439 | Y89: =SUM(K89-SUM(V89:X89)) -> 15550 | Z89: -11998 | AA89: =-15579-Z89 -> -3581 | AB89: =-15161-AA89-Z89 -> 418 | AC89: =SUM(L89-SUM(Z89:AB89)) -> 3738 | AE89: =SUM(O89:R89) -> 5154 | AF89: =SUM(P89:S89) -> 5501 | AG89: =SUM(Q89:T89) -> 8632 | AH89: =SUM(R89:U89) -> 3031 | AI89: =SUM(S89:V89) -> -4592 | AJ89: =SUM(T89:W89) -> -2163 | AK89: =SUM(U89:X89) -> 47 | AL89: =SUM(V89:Y89) -> 15552 | ... AP89: =SUM(Z89:AC89) -> -11423 | AR89: =SUM(AP89/AL89)-1 -> -1.7345036
B90: Net cash used in operating activities | C90: =SUM(C75:C89) -> 65824 | D90: =SUM(D75:D89) -> 63598 | E90: =SUM(E75:E89) -> 77434 | F90: =SUM(F75:F89) -> 69391 | G90: =SUM(G75:G89) -> 80674 | H90: =SUM(H75:H89) -> 104038 | I90: =SUM(I75:I89) -> 122151 | J90: =SUM(J75:J89) -> 110543 | ... L90: =SUM(L75:L89) -> 111482 | N90: =SUM(N75:N89) -> 46966 | O90: =SUM(O75:O89) -> 28166 | P90: =SUM(P75:P89) -> 22892 | Q90: =SUM(Q75:Q89) -> 24127 | R90: =SUM(R75:R89) -> 34005 | S90: =SUM(S75:S89) -> 28560 | T90: =SUM(T75:T89) -> 26380 | U90: =SUM(U75:U89) -> 21598 | ... AC90: =SUM(AC75:AC89) -> 29728 | AE90: =SUM(AE75:AE89) -> 109190 | AF90: =SUM(AF75:AF89) -> 109584 | AG90: =SUM(AG75:AG89) -> 113072 | AH90: =SUM(AH75:AH89) -> 110543 | AI90: =SUM(AI75:AI89) -> 116433 | AJ90: =SUM(AJ75:AJ89) -> 110563 | AK90: =SUM(AK75:AK89) -> 113041 | AL90: =SUM(AL75:AL89) -> 118254 | ... AP90: =SUM(AP75:AP89) -> 111482 | AR90: =SUM(AP90/AL90)-1 -> -0.057266562
B92: Cash flows from investing activities:
B93: Capital Expenditures | C93: -12734 | D93: -12451 | E93: -13313 | F93: -10495 | G93: -7309 | H93: -11085 | I93: -10708 | J93: -10959 | K93: -9447 | L93: -12715 | N93: -2803 | O93: =-5317-N93 -> -2514 | P93: =-7419-SUM(N93:O93) -> -2102 | Q93: =SUM(I93-SUM(N93:P93)) -> -3289 | R93: -3787 | S93: =-6703-R93 -> -2916 | T93: -2093 | U93: =SUM(J93-SUM(R93:T93)) -> -2163 | V93: -2392 | W93: =-4388-V93 -> -1996 | X93: =-6539-W93-V93 -> -2151 | Y93: =SUM(K93-SUM(V93:X93)) -> -2908 | Z93: -2940 | AA93: =-6011-Z93 -> -3071 | AB93: =-9473-AA93-Z93 -> -3462 | AC93: =SUM(L93-SUM(Z93:AB93)) -> -3242 | AE93: =SUM(O93:R93) -> -11692 | AF93: =SUM(P93:S93) -> -12094 | AG93: =SUM(Q93:T93) -> -12085 | AH93: =SUM(R93:U93) -> -10959 | AI93: =SUM(S93:V93) -> -9564 | AJ93: =SUM(T93:W93) -> -8644 | AK93: =SUM(U93:X93) -> -8702 | AL93: =SUM(V93:Y93) -> -9447 | ... AP93: =SUM(Z93:AC93) -> -12715 | AR93: =SUM(AP93/AL93)-1 -> 0.34592992
B94: Proceeds of investments | C94: 111794 | D94: 126339 | E94: 103719 | F94: 97090 | G94: 120391 | H94: 106483 | I94: 67363 | J94: 45514 | K94: 62346 | L94: =40907+12890 -> 53797 | N94: =11309+10675 -> 21984 | O94: =18000+24668-N94 -> 20684 | P94: =24203+33609-SUM(N94:O94) -> 15144 | Q94: =SUM(I94-SUM(N94:P94)) -> 9551 | R94: =7127+509 -> 7636 | S94: =17124+1897-R94 -> 11385 | T94: 12795 | U94: =SUM(J94-SUM(R94:T94)) -> 13698 | V94: =13046+1337 -> 14383 | W94: =27462+4314-V94 -> 17393 | X94: =39838+7382-W94-V94 -> 15444 | Y94: =SUM(K94-SUM(V94:X94)) -> 15126 | Z94: 19459 | AA94: =26587+5210-Z94 -> 12338 | AB94: =35036+10785-AA94-Z94 -> 14024 | AC94: =SUM(L94-SUM(Z94:AB94)) -> 7976 | AE94: =SUM(O94:R94) -> 53015 | AF94: =SUM(P94:S94) -> 43716 | AG94: =SUM(Q94:T94) -> 41367 | AH94: =SUM(R94:U94) -> 45514 | AI94: =SUM(S94:V94) -> 52261 | AJ94: =SUM(T94:W94) -> 58269 | AK94: =SUM(U94:X94) -> 60918 | AL94: =SUM(V94:Y94) -> 62346 | ... AP94: =SUM(Z94:AC94) -> 53797 | AR94: =SUM(AP94/AL94)-1 -> -0.13712187
B95: Purchase of Investments | C95: -142428 | D95: -159486 | E95: -71356 | F95: -39630 | G95: -114938 | H95: -109558 | I95: -76923 | J95: -29513 | K95: -48656 | L95: -24407 | N95: -34913 | O95: =-61987-N95 -> -27074 | P95: =-70178-SUM(N95:O95) -> -8191 | Q95: =SUM(I95-SUM(N95:P95)) -> -6745 | R95: -5153 | S95: =-11197-R95 -> -6044 | T95: -9759 | U95: =SUM(J95-SUM(R95:T95)) -> -8557 | V95: -9780 | W95: =-25042-V95 -> -15262 | X95: =-38074-W95-V95 -> -13032 | Y95: =SUM(K95-SUM(V95:X95)) -> -10582 | Z95: -6124 | AA95: =-12442-Z95 -> -6318 | AB95: =-17591-AA95-Z95 -> -5149 | AC95: =SUM(L95-SUM(Z95:AB95)) -> -6816 | AE95: =SUM(O95:R95) -> -47163 | AF95: =SUM(P95:S95) -> -26133 | AG95: =SUM(Q95:T95) -> -27701 | AH95: =SUM(R95:U95) -> -29513 | AI95: =SUM(S95:V95) -> -34140 | AJ95: =SUM(T95:W95) -> -43358 | AK95: =SUM(U95:X95) -> -46631 | AL95: =SUM(V95:Y95) -> -48656 | ... AP95: =SUM(Z95:AC95) -> -24407 | AR95: =SUM(AP95/AL95)-1 -> -0.49837636
B96: Acquisitions/intang assets | C96: -1111 | D96: -673 | E96: -721 | F96: -624 | G96: -1524 | H96: -33 | I96: -306 | J96: 0 | K96: 0 | L96: 0 | N96: 0 | O96: -167 | P96: =-169-SUM(N96:O96) -> -2 | Q96: =SUM(I96-SUM(N96:P96)) -> -137 | R96: 0 | S96: 0 | T96: 0 | U96: =SUM(J96-SUM(R96:T96)) -> 0 | V96: 0 | W96: 0 | X96: 0 | Y96: =SUM(K96-SUM(V96:X96)) -> 0 | Z96: 0 | AA96: 0 | AB96: 0 | AC96: =SUM(L96-SUM(Z96:AB96)) -> 0 | AE96: =SUM(O96:R96) -> -306 | AF96: =SUM(P96:S96) -> -139 | AG96: =SUM(Q96:T96) -> -137 | AH96: =SUM(R96:U96) -> 0 | AI96: =SUM(S96:V96) -> 0 | AJ96: =SUM(T96:W96) -> 0 | AK96: =SUM(U96:X96) -> 0 | AL96: =SUM(V96:Y96) -> 0 | ... AP96: =SUM(Z96:AC96) -> 0 | AR96: =SUM(AP96/AL96)-1 -> #DIV/0!
B97: Other investing activities | C97: -1498 | D97: -175 | E97: -2263 | F97: -445 | G97: -909 | H97: -352 | I97: -1780 | J97: -1337 | K97: -1308 | L97: -1480 | N97: -374 | O97: =-568-N97 -> -194 | P97: =-1183-SUM(N97:O97) -> -615 | Q97: =SUM(I97-SUM(N97:P97)) -> -597 | R97: -141 | S97: =-247-R97 -> -106 | T97: -506 | U97: =SUM(J97-SUM(R97:T97)) -> -584 | V97: -284 | W97: =-729-V97 -> -445 | X97: =-1117-W97-V97 -> -388 | Y97: =SUM(K97-SUM(V97:X97)) -> -191 | Z97: -603 | AA97: =-635-Z97 -> -32 | AB97: =-975-AA97-Z97 -> -340 | AC97: =SUM(L97-SUM(Z97:AB97)) -> -505 | AE97: =SUM(O97:R97) -> -1547 | AF97: =SUM(P97:S97) -> -1459 | AG97: =SUM(Q97:T97) -> -1350 | AH97: =SUM(R97:U97) -> -1337 | AI97: =SUM(S97:V97) -> -1480 | AJ97: =SUM(T97:W97) -> -1819 | AK97: =SUM(U97:X97) -> -1701 | AL97: =SUM(V97:Y97) -> -1308 | ... AP97: =SUM(Z97:AC97) -> -1480 | AR97: =SUM(AP97/AL97)-1 -> 0.13149847
B98: Net cash used in investing activities | C98: =SUM(C93:C97) -> -45977 | D98: =SUM(D93:D97) -> -46446 | E98: =SUM(E93:E97) -> 16066 | F98: =SUM(F93:F97) -> 45896 | G98: =SUM(G93:G97) -> -4289 | H98: =SUM(H93:H97) -> -14545 | I98: =SUM(I93:I97) -> -22354 | J98: =SUM(J93:J97) -> 3705 | ... L98: =SUM(L93:L97) -> 15195 | N98: =SUM(N93:N97) -> -16106 | O98: =SUM(O93:O97) -> -9265 | P98: =SUM(P93:P97) -> 4234 | Q98: =SUM(Q93:Q97) -> -1217 | R98: =SUM(R93:R97) -> -1445 | S98: =SUM(S93:S97) -> 2319 | T98: =SUM(T93:T97) -> 437 | U98: =SUM(U93:U97) -> 2394 | ... AC98: =SUM(AC93:AC97) -> -2587 | AE98: =SUM(AE93:AE97) -> -7693 | AF98: =SUM(AF93:AF97) -> 3891 | AG98: =SUM(AG93:AG97) -> 94 | AH98: =SUM(AH93:AH97) -> 3705 | AI98: =SUM(AI93:AI97) -> 7077 | AJ98: =SUM(AJ93:AJ97) -> 4448 | AK98: =SUM(AK93:AK97) -> 3884 | AL98: =SUM(AL93:AL97) -> 2935 | ... AP98: =SUM(AP93:AP97) -> 15195 | AR98: =SUM(AP98/AL98)-1 -> 4.1771721
B100: Cash flows from financing activities:
B101: Proceeds from the issuance of term debt, net | C101: 22454 | D101: 28662 | E101: 6969 | F101: 6963 | G101: 16091 | H101: 20393 | I101: 5465 | J101: 5228 | K101: 0 | L101: 4481 | N101: 0 | O101: 0 | P101: 0 | Q101: =SUM(I101-SUM(N101:P101)) -> 5465 | R101: 0 | S101: 0 | T101: 5228 | U101: =SUM(J101-SUM(R101:T101)) -> 0 | V101: 0 | W101: 0 | X101: 0 | Y101: =SUM(K101-SUM(V101:X101)) -> 0 | Z101: 0 | AA101: 0 | AB101: =4481-AA101-Z101 -> 4481 | AC101: =SUM(L101-SUM(Z101:AB101)) -> 0 | AE101: =SUM(O101:R101) -> 5465 | AF101: =SUM(P101:S101) -> 5465 | AG101: =SUM(Q101:T101) -> 10693 | AH101: =SUM(R101:U101) -> 5228 | AI101: =SUM(S101:V101) -> 5228 | AJ101: =SUM(T101:W101) -> 5228 | AK101: =SUM(U101:X101) -> 0 | AL101: =SUM(V101:Y101) -> 0 | ... AP101: =SUM(Z101:AC101) -> 4481 | AR101: =SUM(AP101/AL101)-1 -> #DIV/0!
B102: Repayments of term debt | C102: 0 | D102: -3500 | E102: -6500 | F102: -8805 | G102: -12629 | H102: -8750 | I102: -9543 | J102: -11151.108 | K102: -9958 | L102: -10932 | N102: 0 | O102: -3750 | P102: -3000 | Q102: =SUM(I102-SUM(N102:P102)) -> -2793 | R102: -1401 | S102: -2250 | T102: -7500 | U102: =SUM(J102-SUM(R102:T102)) -> -0.108 | V102: 0 | W102: -3150 | X102: -4250 | Y102: =SUM(K102-SUM(V102:X102)) -> -2558 | Z102: -1009 | AA102: =-4009-Z102 -> -3000 | AB102: =-9682-AA102-Z102 -> -5673 | AC102: =SUM(L102-SUM(Z102:AB102)) -> -1250 | AE102: =SUM(O102:R102) -> -10944 | AF102: =SUM(P102:S102) -> -9444 | AG102: =SUM(Q102:T102) -> -13944 | AH102: =SUM(R102:U102) -> -11151.108 | AI102: =SUM(S102:V102) -> -9750.108 | AJ102: =SUM(T102:W102) -> -10650.108 | AK102: =SUM(U102:X102) -> -7400.108 | AL102: =SUM(V102:Y102) -> -9958 | ... AP102: =SUM(Z102:AC102) -> -10932 | AR102: =SUM(AP102/AL102)-1 -> 0.097810805
B103: Issuance of Common | C103: 495 | D103: 555 | E103: 669 | F103: 781 | G103: 880 | H103: 1105 | I103: 0 | J103: 0 | K103: 0 | L103: 0 | N103: 0 | O103: 0 | P103: 0 | Q103: =SUM(I103-SUM(N103:P103)) -> 0 | R103: 0 | S103: 0 | T103: 0 | U103: =SUM(J103-SUM(R103:T103)) -> 0 | V103: 0 | W103: 0 | X103: 0 | Y103: =SUM(K103-SUM(V103:X103)) -> 0 | Z103: 0 | AA103: 0 | AB103: 0 | AC103: =SUM(L103-SUM(Z103:AB103)) -> 0 | AE103: =SUM(O103:R103) -> 0 | AF103: =SUM(P103:S103) -> 0 | AG103: =SUM(Q103:T103) -> 0 | AH103: =SUM(R103:U103) -> 0 | AI103: =SUM(S103:V103) -> 0 | AJ103: =SUM(T103:W103) -> 0 | AK103: =SUM(U103:X103) -> 0 | AL103: =SUM(V103:Y103) -> 0 | ... AP103: =SUM(Z103:AC103) -> 0 | AR103: =SUM(AP103/AL103)-1 -> #DIV/0!
B104: Treasury Stock | C104: -29722 | D104: -32900 | E104: -72738 | F104: -66897 | G104: -72358 | H104: -85971 | I104: -89402 | J104: -77550 | K104: -94949 | L104: -90711 | N104: -20478 | O104: =-43109-N104 -> -22631 | P104: =-64974-SUM(N104:O104) -> -21865 | Q104: =SUM(I104-SUM(N104:P104)) -> -24428 | R104: -19475 | S104: =-39069-R104 -> -19594 | T104: -17478 | U104: =SUM(J104-SUM(R104:T104)) -> -21003 | V104: -20139 | W104: =-43344-V104 -> -23205 | X104: =-69866-W104-V104 -> -26522 | Y104: =SUM(K104-SUM(V104:X104)) -> -25083 | Z104: -23606 | AA104: =-49504-Z104 -> -25898 | AB104: =-70579-AA104-Z104 -> -21075 | AC104: =SUM(L104-SUM(Z104:AB104)) -> -20132 | AE104: =SUM(O104:R104) -> -88399 | AF104: =SUM(P104:S104) -> -85362 | AG104: =SUM(Q104:T104) -> -80975 | AH104: =SUM(R104:U104) -> -77550 | AI104: =SUM(S104:V104) -> -78214 | AJ104: =SUM(T104:W104) -> -81825 | AK104: =SUM(U104:X104) -> -90869 | AL104: =SUM(V104:Y104) -> -94949 | ... AP104: =SUM(Z104:AC104) -> -90711 | AR104: =SUM(AP104/AL104)-1 -> -0.044634488
B105: Change in commercial paper, net | C105: -397 | D105: 3852 | E105: -37 | F105: -5977 | G105: -963 | H105: 1022 | I105: 3955 | J105: -3978 | K105: 3960 | L105: -2032 | N105: -1000 | O105: =999-N105 -> 1999 | P105: =4970-SUM(N105:O105) -> 3971 | Q105: =SUM(I105-SUM(N105:P105)) -> -1015 | R105: -8214 | S105: =-7960-R105 -> 254 | T105: 1989 | U105: =SUM(J105-SUM(R105:T105)) -> 1993 | V105: -3984 | W105: =-3982-V105 -> 2 | X105: =-2985-W105-V105 -> 997 | Y105: =SUM(K105-SUM(V105:X105)) -> 6945 | Z105: -7944 | AA105: =-3968-Z105 -> 3976 | AB105: =-65-AA105-Z105 -> 3903 | AC105: =SUM(L105-SUM(Z105:AB105)) -> -1967 | AE105: =SUM(O105:R105) -> -3259 | AF105: =SUM(P105:S105) -> -5004 | AG105: =SUM(Q105:T105) -> -6986 | AH105: =SUM(R105:U105) -> -3978 | AI105: =SUM(S105:V105) -> 252 | AJ105: =SUM(T105:W105) -> 0 | AK105: =SUM(U105:X105) -> -992 | AL105: =SUM(V105:Y105) -> 3960 | ... AP105: =SUM(Z105:AC105) -> -2032 | AR105: =SUM(AP105/AL105)-1 -> -1.5131313
B106: Preferred Stock | C106: 0 | D106: 0 | E106: 0 | F106: 0 | G106: 0 | H106: 0 | I106: 0 | J106: 0 | K106: 0 | L106: 0 | N106: 0 | O106: 0 | P106: 0 | Q106: =SUM(I106-SUM(N106:P106)) -> 0 | R106: 0 | S106: 0 | T106: 0 | U106: =SUM(J106-SUM(R106:T106)) -> 0 | V106: 0 | W106: 0 | X106: 0 | Y106: =SUM(K106-SUM(V106:X106)) -> 0 | Z106: 0 | AA106: 0 | AB106: 0 | AC106: =SUM(L106-SUM(Z106:AB106)) -> 0 | AE106: =SUM(O106:R106) -> 0 | AF106: =SUM(P106:S106) -> 0 | AG106: =SUM(Q106:T106) -> 0 | AH106: =SUM(R106:U106) -> 0 | AI106: =SUM(S106:V106) -> 0 | AJ106: =SUM(T106:W106) -> 0 | AK106: =SUM(U106:X106) -> 0 | AL106: =SUM(V106:Y106) -> 0 | ... AP106: =SUM(Z106:AC106) -> 0 | AR106: =SUM(AP106/AL106)-1 -> #DIV/0!
B107: Other | C107: -1163 | D107: -1247 | E107: -2527 | F107: -2922 | G107: -3760 | H107: -6685 | I107: -6383 | J107: -6012 | K107: -5802 | L107: =-5960-111 -> -6071 | N107: =-2888-61 -> -2949 | O107: =-3218-105-N107 -> -374 | P107: =-148-5915-SUM(N107:O107) -> -2740 | Q107: =SUM(I107-SUM(N107:P107)) -> -320 | R107: =-2316-389 -> -2705 | S107: =-2734-455-R107 -> -484 | T107: -2438 | U107: =SUM(J107-SUM(R107:T107)) -> -385 | V107: =-2591-46 -> -2637 | W107: =-2875-V107-132 -> -370 | X107: =-5163-191-W107-V107 -> -2347 | Y107: =SUM(K107-SUM(V107:X107)) -> -448 | Z107: =-2921-35 -> -2956 | AA107: =-3205+-77-Z107 -> -326 | AB107: =-5719+-87-AA107-Z107 -> -2524 | AC107: =SUM(L107-SUM(Z107:AB107)) -> -265 | AE107: =SUM(O107:R107) -> -6139 | AF107: =SUM(P107:S107) -> -6249 | AG107: =SUM(Q107:T107) -> -5947 | AH107: =SUM(R107:U107) -> -6012 | AI107: =SUM(S107:V107) -> -5944 | AJ107: =SUM(T107:W107) -> -5830 | AK107: =SUM(U107:X107) -> -5739 | AL107: =SUM(V107:Y107) -> -5802 | ... AP107: =SUM(Z107:AC107) -> -6071 | AR107: =SUM(AP107/AL107)-1 -> 0.046363323
B108: Dividends | C108: -12150 | D108: -12769 | E108: -13712 | F108: -14119 | G108: -14081 | H108: -14467 | I108: -14841 | J108: -14875 | K108: -15234 | L108: -15421 | N108: -3732 | O108: =-7327-N108 -> -3595 | P108: =-11138-SUM(N108:O108) -> -3811 | Q108: =SUM(I108-SUM(N108:P108)) -> -3703 | R108: -3768 | S108: =-7418-R108 -> -3650 | T108: -3849 | U108: =SUM(J108-SUM(R108:T108)) -> -3608 | V108: -3825 | W108: =-7535-V108 -> -3710 | X108: =-11430-W108-V108 -> -3895 | Y108: =SUM(K108-SUM(V108:X108)) -> -3804 | Z108: -3856 | AA108: =-7614-Z108 -> -3758 | AB108: =-11559-AA108-Z108 -> -3945 | AC108: =SUM(L108-SUM(Z108:AB108)) -> -3862 | AE108: =SUM(O108:R108) -> -14877 | AF108: =SUM(P108:S108) -> -14932 | AG108: =SUM(Q108:T108) -> -14970 | AH108: =SUM(R108:U108) -> -14875 | AI108: =SUM(S108:V108) -> -14932 | AJ108: =SUM(T108:W108) -> -14992 | AK108: =SUM(U108:X108) -> -15038 | AL108: =SUM(V108:Y108) -> -15234 | ... AP108: =SUM(Z108:AC108) -> -15421 | AR108: =SUM(AP108/AL108)-1 -> 0.012275174
B109: Net cash provided by financing activities | C109: =SUM(C101:C108) -> -20483 | D109: =SUM(D101:D108) -> -17347 | E109: =SUM(E101:E108) -> -87876 | F109: =SUM(F101:F108) -> -90976 | G109: =SUM(G101:G108) -> -86820 | H109: =SUM(H101:H108) -> -93353 | I109: =SUM(I101:I108) -> -110749 | J109: =SUM(J101:J108) -> -108338.11 | ... L109: =SUM(L101:L108) -> -120686 | N109: =SUM(N101:N108) -> -28159 | O109: =SUM(O101:O108) -> -28351 | P109: =SUM(P101:P108) -> -27445 | Q109: =SUM(Q101:Q108) -> -26794 | R109: =SUM(R101:R108) -> -35563 | S109: =SUM(S101:S108) -> -25724 | T109: =SUM(T101:T108) -> -24048 | U109: =SUM(U101:U108) -> -23003.108 | ... AC109: =SUM(AC101:AC108) -> -27476 | AE109: =SUM(AE101:AE108) -> -118153 | AF109: =SUM(AF101:AF108) -> -115526 | AG109: =SUM(AG101:AG108) -> -112129 | AH109: =SUM(AH101:AH108) -> -108338.11 | AI109: =SUM(AI101:AI108) -> -103360.11 | AJ109: =SUM(AJ101:AJ108) -> -108069.11 | AK109: =SUM(AK101:AK108) -> -120038.11 | AL109: =SUM(AL101:AL108) -> -121983 | ... AP109: =SUM(AP101:AP108) -> -120686 | AR109: =SUM(AP109/AL109)-1 -> -0.010632629
B112: Cash Position BOP | C112: 21120 | D112: =C119 -> 20484 | E112: =D119 -> 20289 | F112: =E119 -> 25913 | G112: =F119 -> 48844 | H112: =G119 -> 38016 | I112: =H119 -> 34940 | J112: =I119 -> 23646 | K112: =J119 -> 29965 | L112: =K119 -> 29943 | N112: =I112 -> 34940 | O112: =N119 -> 37119 | P112: =O119 -> 28098 | Q112: =P119 -> 27502 | R112: =Q119 -> 23646 | S112: =R119 -> 20535 | T112: =S119 -> 24687 | U112: =T119 -> 28408 | V112: =U119 -> 29965 | ... AC112: =AB119 -> 36269 | AE112: =N119 -> 37119 | AF112: =O119 -> 28098 | AG112: =P119 -> 27502 | AH112: =Q119 -> 23646 | AI112: =R119 -> 20535 | AJ112: =S119 -> 24687 | AK112: =T119 -> 28408 | AL112: =U119 -> 29965 | ... AP112: =Y119 -> 29943
B113: BOP Restricted Cash Adjustments | C113: 0 | D113: =-C117 -> 0 | E113: =-D117 -> 0 | F113: =-E117 -> 0 | G113: =-F117 -> 1380 | H113: =-G117 -> 1773 | I113: =-H117 -> 989 | J113: =-I117 -> 1331 | K113: =-J117 -> 921.892 | L113: =-K117 -> 149.892 | N113: =I113 -> 989 | O113: =-N117 -> 1511 | P113: =-O117 -> 1082 | Q113: =-P117 -> 1359 | R113: =-Q117 -> 1331 | S113: =-R117 -> 1439 | T113: =-S117 -> 2442 | U113: =-T117 -> 1490 | V113: =-U117 -> 921.892 | ... AC113: =-AB117 -> 149.892 | AE113: =-N117 -> 1511 | AF113: =-O117 -> 1082 | AG113: =-P117 -> 1359 | AH113: =-Q117 -> 1331 | AI113: =-R117 -> 1439 | AJ113: =-S117 -> 2442 | AK113: =-T117 -> 1490 | AL113: =-U117 -> 921.892 | ... AP113: =-Y117 -> 149.892
B114: Adjusted Cash Position BOP | C114: =SUM(C112:C113) -> 21120 | D114: =SUM(D112:D113) -> 20484 | E114: =SUM(E112:E113) -> 20289 | F114: =SUM(F112:F113) -> 25913 | G114: =SUM(G112:G113) -> 50224 | H114: =SUM(H112:H113) -> 39789 | I114: =SUM(I112:I113) -> 35929 | J114: =SUM(J112:J113) -> 24977 | ... L114: =SUM(L112:L113) -> 30092.892 | N114: =SUM(N112:N113) -> 35929 | O114: =SUM(O112:O113) -> 38630 | P114: =SUM(P112:P113) -> 29180 | Q114: =SUM(Q112:Q113) -> 28861 | R114: =SUM(R112:R113) -> 24977 | S114: =SUM(S112:S113) -> 21974 | T114: =SUM(T112:T113) -> 27129 | U114: =SUM(U112:U113) -> 29898 | ... AC114: =SUM(AC112:AC113) -> 36418.892 | AE114: =SUM(AE112:AE113) -> 38630 | AF114: =SUM(AF112:AF113) -> 29180 | AG114: =SUM(AG112:AG113) -> 28861 | AH114: =SUM(AH112:AH113) -> 24977 | AI114: =SUM(AI112:AI113) -> 21974 | AJ114: =SUM(AJ112:AJ113) -> 27129 | AK114: =SUM(AK112:AK113) -> 29898 | AL114: =SUM(AL112:AL113) -> 30886.892 | ... AP114: =SUM(AP112:AP113) -> 30092.892
B116: EOP FX Adjustments | C116: 0 | D116: 0 | E116: 0 | F116: 0 | G116: 0 | H116: 0 | I116: 0 | J116: 0 | K116: 0 | L116: 0 | N116: 0 | O116: 0 | P116: 0 | Q116: =SUM(I116-SUM(N116:P116)) -> 0 | R116: 0 | S116: 0 | T116: 0 | U116: =SUM(J116-SUM(R116:T116)) -> 0 | V116: 0 | W116: 0 | X116: 0 | Y116: =SUM(K116-SUM(V116:X116)) -> 0 | Z116: 0 | AA116: 0 | AB116: 0 | AC116: =SUM(L116-SUM(Z116:AB116)) -> 0 | AE116: =R116 -> 0 | AF116: =S116 -> 0 | AG116: =T116 -> 0 | AH116: =U116 -> 0 | AI116: =V116 -> 0 | AJ116: =W116 -> 0 | AK116: =X116 -> 0 | AL116: =Y116 -> 0 | ... AP116: =AC116 -> 0
B117: EOP Restricted Cash Adjustments | C117: 0 | D117: 0 | E117: 0 | F117: =-23-1357 -> -1380 | G117: =-(1737+36) -> -1773 | H117: -989 | I117: -1331 | J117: -921.892 | K117: -149.892 | L117: -149.892 | N117: -1511 | O117: -1082 | P117: -1359 | Q117: -1331 | R117: -1439 | S117: -2442 | T117: -1490 | U117: -921.892 | V117: -1363.892 | W117: -1375.892 | X117: -1219.892 | Y117: -149.892 | Z117: -149.892 | AA117: -149.892 | AB117: -149.892 | AC117: =L117 -> -149.892 | AE117: =R117 -> -1439 | AF117: =S117 -> -2442 | AG117: =T117 -> -1490 | AH117: =U117 -> -921.892 | AI117: =V117 -> -1363.892 | AJ117: =W117 -> -1375.892 | AK117: =X117 -> -1219.892 | AL117: =Y117 -> -149.892 | ... AP117: =AC117 -> -149.892
B118: Net Change in Cash | C118: =+C109+C98+C90 -> -636 | D118: =+D109+D98+D90 -> -195 | E118: =+E109+E98+E90 -> 5624 | F118: =+F109+F98+F90 -> 24311 | G118: =+G109+G98+G90 -> -10435 | H118: =+H109+H98+H90 -> -3860 | I118: =+I109+I98+I90 -> -10952 | J118: =+J109+J98+J90 -> 5909.892 | ... L118: =+L109+L98+L90 -> 5991 | N118: =+N109+N98+N90 -> 2701 | O118: =+O109+O98+O90 -> -9450 | P118: =+P109+P98+P90 -> -319 | Q118: =+Q109+Q98+Q90 -> -3884 | R118: =+R109+R98+R90 -> -3003 | S118: =+S109+S98+S90 -> 5155 | T118: =+T109+T98+T90 -> 2769 | U118: =+U109+U98+U90 -> 988.892 | ... AC118: =+AC109+AC98+AC90 -> -335 | AE118: =+AE109+AE98+AE90 -> -16656 | AF118: =+AF109+AF98+AF90 -> -2051 | AG118: =+AG109+AG98+AG90 -> 1037 | AH118: =+AH109+AH98+AH90 -> 5909.892 | AI118: =+AI109+AI98+AI90 -> 20149.892 | AJ118: =+AJ109+AJ98+AJ90 -> 6941.892 | AK118: =+AK109+AK98+AK90 -> -3113.108 | AL118: =+AL109+AL98+AL90 -> -794 | ... AP118: =+AP109+AP98+AP90 -> 5991
B119: Adjusted Cash Position EOP | C119: =SUM(C114:C118) -> 20484 | D119: =SUM(D114:D118) -> 20289 | E119: =SUM(E114:E118) -> 25913 | F119: =SUM(F114:F118) -> 48844 | G119: =SUM(G114:G118) -> 38016 | H119: =SUM(H114:H118) -> 34940 | I119: =SUM(I114:I118) -> 23646 | J119: =SUM(J114:J118) -> 29965 | ... L119: =SUM(L114:L118) -> 35934 | N119: =SUM(N114:N118) -> 37119 | O119: =SUM(O114:O118) -> 28098 | P119: =SUM(P114:P118) -> 27502 | Q119: =SUM(Q114:Q118) -> 23646 | R119: =SUM(R114:R118) -> 20535 | S119: =SUM(S114:S118) -> 24687 | T119: =SUM(T114:T118) -> 28408 | U119: =SUM(U114:U118) -> 29965 | ... AC119: =SUM(AC114:AC118) -> 35934 | AE119: =SUM(AE114:AE118) -> 20535 | AF119: =SUM(AF114:AF118) -> 24687 | AG119: =SUM(AG114:AG118) -> 28408 | AH119: =SUM(AH114:AH118) -> 29965 | AI119: =SUM(AI114:AI118) -> 40760 | AJ119: =SUM(AJ114:AJ118) -> 32695 | AK119: =SUM(AK114:AK118) -> 25565 | AL119: =SUM(AL114:AL118) -> 29943 | ... AP119: =SUM(AP114:AP118) -> 35934
B121: Balance Check | C121: =C119-C39 -> 0 | D121: =D119-D39 -> 0 | E121: =E119-E39 -> 0 | F121: =F119-F39 -> 0 | G121: =G119-G39 -> 0 | H121: =H119-H39 -> 0 | I121: =I119-I39 -> 0 | J121: =J119-J39 -> 0 | ... L121: =L119-L39 -> 0 | N121: =N119-N39 -> 0 | O121: =O119-O39 -> 0 | P121: =P119-P39 -> 0 | Q121: =Q119-Q39 -> 0 | R121: =R119-R39 -> 0 | S121: =S119-S39 -> 0 | T121: =T119-T39 -> 0 | U121: =U119-U39 -> 0 | ... AC121: =AC119-AC39 -> 0 | AE121: =AE119-AE39 -> 0 | AF121: =AF119-AF39 -> 0 | AG121: =AG119-AG39 -> 0 | AH121: =AH119-AH39 -> 0 | AI121: =AI119-AI39 -> 0 | AJ121: =AJ119-AJ39 -> 0 | AK121: =AK119-AK39 -> 0 | AL121: =AL119-AL39 -> 0 | ... AP121: =AP119-AP39 -> 0
B123: Cash paid during the period for:
B124: Cash paid for income taxes, net | C124: 10444 | D124: 11591 | E124: 10417 | F124: 15263 | G124: 9501 | H124: 25385 | I124: 19573 | J124: 18679 | K124: 26102 | L124: 43369 | N124: 5235 | O124: =9301-N124 -> 4066 | P124: =12251-O124-N124 -> 2950 | Q124: =SUM(I124-SUM(N124:P124)) -> 7322 | R124: 828 | S124: =4894-R124 -> 4066 | T124: =7020-S124-R124 -> 2126 | U124: =SUM(J124-SUM(R124:T124)) -> 11659 | V124: 7255 | W124: =14531-V124 -> 7276 | X124: =19230-W124-V124 -> 4699 | Y124: =SUM(K124-SUM(V124:X124)) -> 6872 | Z124: 18651 | AA124: =31683-Z124 -> 13032 | AB124: =37332-AA124-Z124 -> 5649 | AC124: =SUM(L124-SUM(Z124:AB124)) -> 6037 | AE124: =SUM(O124:R124) -> 15166 | AF124: =SUM(P124:S124) -> 15166 | AG124: =SUM(Q124:T124) -> 14342 | AH124: =SUM(R124:U124) -> 18679 | AI124: =SUM(S124:V124) -> 25106 | AJ124: =SUM(T124:W124) -> 28316 | AK124: =SUM(U124:X124) -> 30889 | AL124: =SUM(V124:Y124) -> 26102 | ... AP124: =SUM(Z124:AC124) -> 43369
B125: Cash paid for interest | C125: 1316 | D125: 2092 | E125: 3022 | F125: 3423 | G125: 3002 | H125: 2687 | I125: 2865 | J125: 3803 | K125: 0 | L125: 0 | N125: 531 | O125: =1406-N125 -> 875 | P125: =1910-O125-N125 -> 504 | Q125: =SUM(I125-SUM(N125:P125)) -> 955 | R125: 703 | S125: =1873-R125 -> 1170 | T125: =2590-S125-R125 -> 717 | U125: =SUM(J125-SUM(R125:T125)) -> 1213 | V125: 0 | W125: 0 | X125: 0 | Y125: =SUM(K125-SUM(V125:X125)) -> 0 | Z125: 0 | AA125: 0 | AB125: 0 | AC125: =SUM(L125-SUM(Z125:AB125)) -> 0 | AE125: =SUM(O125:R125) -> 3037 | AF125: =SUM(P125:S125) -> 3332 | AG125: =SUM(Q125:T125) -> 3545 | AH125: =SUM(R125:U125) -> 3803 | AI125: =SUM(S125:V125) -> 3100 | AJ125: =SUM(T125:W125) -> 1930 | AK125: =SUM(U125:X125) -> 1213 | AL125: =SUM(V125:Y125) -> 0 | ... AP125: =SUM(Z125:AC125) -> 0

Sheet Revenue Drivers
B2: Apple Inc. (NASDAQ: AAPL) | C2: FYE | N2: Quarterly | V2: Quarterly | W2: Quarterly | AE2: LTM | AI2: LTM | AR2: Variance
B3: Segment Anaysis | C3: ='Historical Financials'!C7 -> 2016 | D3: ='Historical Financials'!D7 -> 2017 | E3: ='Historical Financials'!E7 -> 2018 | F3: ='Historical Financials'!F7 -> 2019 | G3: ='Historical Financials'!G7 -> 2020 | H3: ='Historical Financials'!H7 -> 2021 | I3: ='Historical Financials'!I7 -> 2022 | J3: ='Historical Financials'!J7 -> 2023 | ... L3: ='Historical Financials'!L7 -> 2025 | N3: ='Historical Financials'!N7 -> 1Q22 | O3: ='Historical Financials'!O7 -> 2Q22 | P3: ='Historical Financials'!P7 -> 3Q22 | Q3: ='Historical Financials'!Q7 -> 4Q22 | R3: ='Historical Financials'!R7 -> 1Q23 | S3: ='Historical Financials'!S7 -> 2Q23 | T3: ='Historical Financials'!T7 -> 3Q23 | U3: ='Historical Financials'!U7 -> 4Q23 | ... AC3: ='Historical Financials'!AC7 -> 4Q25 | AE3: =R3 -> 1Q23 | AF3: =S3 -> 2Q23 | AG3: =T3 -> 3Q23 | AH3: =U3 -> 4Q23 | AI3: =V3 -> 1Q24 | AJ3: =W3 -> 2Q24 | AK3: =X3 -> 3Q24 | AL3: =Y3 -> 4Q24 | ... AP3: =AC3 -> 4Q25
B4: $ mm except per share | C4: ='Historical Financials'!C8 -> 42643 | D4: ='Historical Financials'!D8 -> 43008 | E4: ='Historical Financials'!E8 -> 43372 | F4: ='Historical Financials'!F8 -> 43737 | G4: ='Historical Financials'!G8 -> 44104 | H4: ='Historical Financials'!H8 -> 44469 | I4: ='Historical Financials'!I8 -> 44834 | J4: ='Historical Financials'!J8 -> 45192 | ... L4: ='Historical Financials'!L8 -> 45927 | N4: ='Historical Financials'!N8 -> 44560 | O4: ='Historical Financials'!O8 -> 44650 | P4: ='Historical Financials'!P8 -> 44742 | Q4: ='Historical Financials'!Q8 -> 44834 | R4: ='Historical Financials'!R8 -> 44917 | S4: ='Historical Financials'!S8 -> 45008 | T4: ='Historical Financials'!T8 -> 45100 | U4: ='Historical Financials'!U8 -> 45192 | ... AC4: ='Historical Financials'!AC8 -> 45927 | AE4: =R4 -> 44917 | AF4: =S4 -> 45008 | AG4: =T4 -> 45100 | AH4: =U4 -> 45192 | AI4: =V4 -> 45283 | AJ4: =W4 -> 45375 | AK4: =X4 -> 45467 | AL4: =Y4 -> 45559 | ... AP4: =AC4 -> 45927
A6: X | B6: Revenue by reportable segment
A8: X | B8: Revenue by End Product
B9: iPhone Revenue | C9: 136700 | D9: 141319 | E9: 164888 | F9: 142381 | G9: 137781 | H9: 191973 | I9: 205489 | J9: 200583 | K9: 201183 | L9: 209586 | N9: 71628 | O9: 50570 | P9: 40665 | Q9: =SUM(I9-SUM(N9:P9)) -> 42626 | R9: 65775 | S9: 51334 | T9: 39669 | U9: =SUM(J9-SUM(R9:T9)) -> 43805 | V9: 69702 | W9: 45963 | X9: 39296 | Y9: =SUM(K9-SUM(V9:X9)) -> 46222 | Z9: 69138 | AA9: 46841 | AB9: 44582 | AC9: =SUM(L9-SUM(Z9:AB9)) -> 49025 | AE9: =SUM(O9:R9) -> 199636 | AF9: =SUM(P9:S9) -> 200400 | AG9: =SUM(Q9:T9) -> 199404 | AH9: =SUM(R9:U9) -> 200583 | AI9: =SUM(S9:V9) -> 204510 | AJ9: =SUM(T9:W9) -> 199139 | AK9: =SUM(U9:X9) -> 198766 | AL9: =SUM(V9:Y9) -> 201183 | ... AP9: =SUM(Z9:AC9) -> 209586 | AR9: =SUM(AO9/AK9)-1 -> 0.04033386
B10: Mac Revenue | C10: 22831 | D10: 25850 | E10: 25198 | F10: 25740 | G10: 28622 | H10: 35190 | I10: 40177 | J10: 29357 | K10: 29984 | L10: 33708 | N10: 10852 | O10: 10435 | P10: 7382 | Q10: =SUM(I10-SUM(N10:P10)) -> 11508 | R10: 7735 | S10: 7168 | T10: 6840 | U10: =SUM(J10-SUM(R10:T10)) -> 7614 | V10: 7780 | W10: 7451 | X10: 7009 | Y10: =SUM(K10-SUM(V10:X10)) -> 7744 | Z10: 8987 | AA10: 7949 | AB10: 8046 | AC10: =SUM(L10-SUM(Z10:AB10)) -> 8726 | AE10: =SUM(O10:R10) -> 37060 | AF10: =SUM(P10:S10) -> 33793 | AG10: =SUM(Q10:T10) -> 33251 | AH10: =SUM(R10:U10) -> 29357 | AI10: =SUM(S10:V10) -> 29402 | AJ10: =SUM(T10:W10) -> 29685 | AK10: =SUM(U10:X10) -> 29854 | AL10: =SUM(V10:Y10) -> 29984 | ... AP10: =SUM(Z10:AC10) -> 33708 | AR10: =SUM(AO10/AK10)-1 -> 0.096201514
B11: iPad Revenue | C11: 20628 | D11: 19222 | E11: 18380 | F11: 21280 | G11: 23724 | H11: 31862 | I11: 29292 | J11: 28300 | K11: 26694 | L11: 28023 | N11: 7248 | O11: 7646 | P11: 7224 | Q11: =SUM(I11-SUM(N11:P11)) -> 7174 | R11: 9396 | S11: 6670 | T11: 5791 | U11: =SUM(J11-SUM(R11:T11)) -> 6443 | V11: 7023 | W11: 5559 | X11: 7162 | Y11: =SUM(K11-SUM(V11:X11)) -> 6950 | Z11: 8088 | AA11: 6402 | AB11: 6581 | AC11: =SUM(L11-SUM(Z11:AB11)) -> 6952 | AE11: =SUM(O11:R11) -> 31440 | AF11: =SUM(P11:S11) -> 30464 | AG11: =SUM(Q11:T11) -> 29031 | AH11: =SUM(R11:U11) -> 28300 | AI11: =SUM(S11:V11) -> 25927 | AJ11: =SUM(T11:W11) -> 24816 | AK11: =SUM(U11:X11) -> 26187 | AL11: =SUM(V11:Y11) -> 26694 | ... AP11: =SUM(Z11:AC11) -> 28023 | AR11: =SUM(AO11/AK11)-1 -> 0.07003475
B12: Services Revenue | C12: 24348 | D12: 29980 | E12: 39748 | F12: 46291 | G12: 53768 | H12: 68425 | I12: 78129 | J12: 85200 | K12: 96169 | L12: 109158 | N12: 19516 | O12: 19821 | P12: 19604 | Q12: =SUM(I12-SUM(N12:P12)) -> 19188 | R12: 20766 | S12: 20907 | T12: 21213 | U12: =SUM(J12-SUM(R12:T12)) -> 22314 | V12: 23117 | W12: 23867 | X12: 24213 | Y12: =SUM(K12-SUM(V12:X12)) -> 24972 | Z12: 26340 | AA12: 26645 | AB12: 27423 | AC12: =SUM(L12-SUM(Z12:AB12)) -> 28750 | AE12: =SUM(O12:R12) -> 79379 | AF12: =SUM(P12:S12) -> 80465 | AG12: =SUM(Q12:T12) -> 82074 | AH12: =SUM(R12:U12) -> 85200 | AI12: =SUM(S12:V12) -> 87551 | AJ12: =SUM(T12:W12) -> 90511 | AK12: =SUM(U12:X12) -> 93511 | AL12: =SUM(V12:Y12) -> 96169 | ... AP12: =SUM(Z12:AC12) -> 109158 | AR12: =SUM(AO12/AK12)-1 -> 0.12692624
B13: Wearables, Home, and Accessories Revenue | C13: 11132 | D13: 12863 | E13: 17381 | F13: 24482 | G13: 30620 | H13: 38367 | I13: 41241 | J13: 39845 | K13: 37005 | L13: 35686 | N13: 14701 | O13: 8806 | P13: 8084 | Q13: =SUM(I13-SUM(N13:P13)) -> 9650 | R13: 13482 | S13: 8757 | T13: 8284 | U13: =SUM(J13-SUM(R13:T13)) -> 9322 | V13: 11953 | W13: 7913 | X13: 8097 | Y13: =SUM(K13-SUM(V13:X13)) -> 9042 | Z13: 11747 | AA13: 7522 | AB13: 7404 | AC13: =SUM(L13-SUM(Z13:AB13)) -> 9013 | AE13: =SUM(O13:R13) -> 40022 | AF13: =SUM(P13:S13) -> 39973 | AG13: =SUM(Q13:T13) -> 40173 | AH13: =SUM(R13:U13) -> 39845 | AI13: =SUM(S13:V13) -> 38316 | AJ13: =SUM(T13:W13) -> 37472 | AK13: =SUM(U13:X13) -> 37285 | AL13: =SUM(V13:Y13) -> 37005 | ... AP13: =SUM(Z13:AC13) -> 35686 | AR13: =SUM(AO13/AK13)-1 -> -0.042108086
B14: Total Net Revenue | C14: =SUM(C9:C13) -> 215639 | D14: =SUM(D9:D13) -> 229234 | E14: =SUM(E9:E13) -> 265595 | F14: =SUM(F9:F13) -> 260174 | G14: =SUM(G9:G13) -> 274515 | H14: =SUM(H9:H13) -> 365817 | I14: =SUM(I9:I13) -> 394328 | J14: =SUM(J9:J13) -> 383285 | ... L14: =SUM(L9:L13) -> 416161 | N14: =SUM(N9:N13) -> 123945 | O14: =SUM(O9:O13) -> 97278 | P14: =SUM(P9:P13) -> 82959 | Q14: =SUM(Q9:Q13) -> 90146 | R14: =SUM(R9:R13) -> 117154 | S14: =SUM(S9:S13) -> 94836 | T14: =SUM(T9:T13) -> 81797 | U14: =SUM(U9:U13) -> 89498 | ... AC14: =SUM(AC9:AC13) -> 102466 | AE14: =SUM(AE9:AE13) -> 387537 | AF14: =SUM(AF9:AF13) -> 385095 | AG14: =SUM(AG9:AG13) -> 383933 | AH14: =SUM(AH9:AH13) -> 383285 | AI14: =SUM(AI9:AI13) -> 385706 | AJ14: =SUM(AJ9:AJ13) -> 381623 | AK14: =SUM(AK9:AK13) -> 385603 | AL14: =SUM(AL9:AL13) -> 391035 | ... AP14: =SUM(AP9:AP13) -> 416161 | AR14: =SUM(AO14/AK14)-1 -> 0.059703892
B15: Variance Check | C15: =C14-'Historical Financials'!C11 -> 0 | D15: =D14-'Historical Financials'!D11 -> 0 | E15: =E14-'Historical Financials'!E11 -> 0 | F15: =F14-'Historical Financials'!F11 -> 0 | G15: =G14-'Historical Financials'!G11 -> 0 | H15: =H14-'Historical Financials'!H11 -> 0 | I15: =I14-'Historical Financials'!I11 -> 0 | J15: =J14-'Historical Financials'!J11 -> 0 | ... L15: =L14-'Historical Financials'!L11 -> 0 | N15: =N14-'Historical Financials'!N11 -> 0 | O15: =O14-'Historical Financials'!O11 -> 0 | P15: =P14-'Historical Financials'!P11 -> 0 | Q15: =Q14-'Historical Financials'!Q11 -> 0 | R15: =R14-'Historical Financials'!R11 -> 0 | S15: =S14-'Historical Financials'!S11 -> 0 | T15: =T14-'Historical Financials'!T11 -> 0 | U15: =U14-'Historical Financials'!U11 -> 0 | ... AC15: =AC14-'Historical Financials'!AC11 -> 0 | AE15: =AE14-'Historical Financials'!AE11 -> 0 | AF15: =AF14-'Historical Financials'!AF11 -> 0 | AG15: =AG14-'Historical Financials'!AG11 -> 0 | AH15: =AH14-'Historical Financials'!AH11 -> 0 | AI15: =AI14-'Historical Financials'!AI11 -> 0 | AJ15: =AJ14-'Historical Financials'!AJ11 -> 0 | AK15: =AK14-'Historical Financials'!AK11 -> 0 | AL15: =AL14-'Historical Financials'!AL11 -> 0 | ... AO15: =AO14-'Historical Financials'!AO11 -> 0 | AP15: =AP14-'Historical Financials'!AQ11 -> 416161
B17: Segments as a % of Total Revenue
B18: =B9&"(%)" -> iPhone Revenue(%) | C18: =SUM(C9/C$14) -> 0.63392985 | D18: =SUM(D9/D$14) -> 0.61648359 | E18: =SUM(E9/E$14) -> 0.62082494 | F18: =SUM(F9/F$14) -> 0.54725299 | G18: =SUM(G9/G$14) -> 0.501907 | H18: =SUM(H9/H$14) -> 0.52477878 | I18: =SUM(I9/I$14) -> 0.52111187 | J18: =SUM(J9/J$14) -> 0.52332598 | ... L18: =SUM(L9/L$14) -> 0.50361759 | N18: =SUM(N9/N$14) -> 0.57790149 | O18: =SUM(O9/O$14) -> 0.51985033 | P18: =SUM(P9/P$14) -> 0.4901819 | Q18: =SUM(Q9/Q$14) -> 0.47285515 | R18: =SUM(R9/R$14) -> 0.5614405 | S18: =SUM(S9/S$14) -> 0.54129234 | T18: =SUM(T9/T$14) -> 0.48496889 | U18: =SUM(U9/U$14) -> 0.48945228 | ... AC18: =SUM(AC9/AC$14) -> 0.47845139 | AE18: =SUM(AE9/AE$14) -> 0.51514049 | AF18: =SUM(AF9/AF$14) -> 0.52039107 | AG18: =SUM(AG9/AG$14) -> 0.51937187 | AH18: =SUM(AH9/AH$14) -> 0.52332598 | AI18: =SUM(AI9/AI$14) -> 0.5302225 | AJ18: =SUM(AJ9/AJ$14) -> 0.52182127 | AK18: =SUM(AK9/AK$14) -> 0.51546798 | AL18: =SUM(AL9/AL$14) -> 0.51448847 | ... AP18: =SUM(AP9/AP$14) -> 0.50361759
B19: =B10&"(%)" -> Mac Revenue(%) | C19: =SUM(C10/C$14) -> 0.10587602 | D19: =SUM(D10/D$14) -> 0.11276687 | E19: =SUM(E10/E$14) -> 0.094873774 | F19: =SUM(F10/F$14) -> 0.09893379 | G19: =SUM(G10/G$14) -> 0.10426388 | H19: =SUM(H10/H$14) -> 0.096195639 | I19: =SUM(I10/I$14) -> 0.10188726 | J19: =SUM(J10/J$14) -> 0.076593136 | ... L19: =SUM(L10/L$14) -> 0.080997499 | N19: =SUM(N10/N$14) -> 0.087554964 | O19: =SUM(O10/O$14) -> 0.10726989 | P19: =SUM(P10/P$14) -> 0.088983715 | Q19: =SUM(Q10/Q$14) -> 0.12765957 | R19: =SUM(R10/R$14) -> 0.066024207 | S19: =SUM(S10/S$14) -> 0.075583112 | T19: =SUM(T10/T$14) -> 0.083621649 | U19: =SUM(U10/U$14) -> 0.085074527 | ... AC19: =SUM(AC10/AC$14) -> 0.085159955 | AE19: =SUM(AE10/AE$14) -> 0.095629579 | AF19: =SUM(AF10/AF$14) -> 0.087752373 | AG19: =SUM(AG10/AG$14) -> 0.086606257 | AH19: =SUM(AH10/AH$14) -> 0.076593136 | AI19: =SUM(AI10/AI$14) -> 0.076229045 | AJ19: =SUM(AJ10/AJ$14) -> 0.077786192 | AK19: =SUM(AK10/AK$14) -> 0.077421597 | AL19: =SUM(AL10/AL$14) -> 0.076678558 | ... AP19: =SUM(AP10/AP$14) -> 0.080997499
B20: =B11&"(%)" -> iPad Revenue(%) | C20: =SUM(C11/C$14) -> 0.095659876 | D20: =SUM(D11/D$14) -> 0.083853181 | E20: =SUM(E11/E$14) -> 0.06920311 | F20: =SUM(F11/F$14) -> 0.081791417 | G20: =SUM(G11/G$14) -> 0.086421507 | H20: =SUM(H11/H$14) -> 0.087098194 | I20: =SUM(I11/I$14) -> 0.074283338 | J20: =SUM(J11/J$14) -> 0.073835397 | ... L20: =SUM(L11/L$14) -> 0.06733692 | N20: =SUM(N11/N$14) -> 0.058477551 | O20: =SUM(O11/O$14) -> 0.078599478 | P20: =SUM(P11/P$14) -> 0.08707916 | Q20: =SUM(Q11/Q$14) -> 0.079582011 | R20: =SUM(R11/R$14) -> 0.080202127 | S20: =SUM(S11/S$14) -> 0.070331941 | T20: =SUM(T11/T$14) -> 0.070797218 | U20: =SUM(U11/U$14) -> 0.071990436 | ... AC20: =SUM(AC11/AC$14) -> 0.067846896 | AE20: =SUM(AE11/AE$14) -> 0.081127737 | AF20: =SUM(AF11/AF$14) -> 0.079107753 | AG20: =SUM(AG11/AG$14) -> 0.075614756 | AH20: =SUM(AH11/AH$14) -> 0.073835397 | AI20: =SUM(AI11/AI$14) -> 0.067219592 | AJ20: =SUM(AJ11/AJ$14) -> 0.065027527 | AK20: =SUM(AK11/AK$14) -> 0.067911816 | AL20: =SUM(AL11/AL$14) -> 0.068264989 | ... AP20: =SUM(AP11/AP$14) -> 0.06733692
B21: =B12&"(%)" -> Services Revenue(%) | C21: =SUM(C12/C$14) -> 0.11291093 | D21: =SUM(D12/D$14) -> 0.13078339 | E21: =SUM(E12/E$14) -> 0.14965643 | F21: =SUM(F12/F$14) -> 0.17792324 | G21: =SUM(G12/G$14) -> 0.19586544 | H21: =SUM(H12/H$14) -> 0.18704708 | I21: =SUM(I12/I$14) -> 0.19813201 | J21: =SUM(J12/J$14) -> 0.2222889 | ... L21: =SUM(L12/L$14) -> 0.26229752 | N21: =SUM(N12/N$14) -> 0.15745694 | O21: =SUM(O12/O$14) -> 0.20375624 | P21: =SUM(P12/P$14) -> 0.2363095 | Q21: =SUM(Q12/Q$14) -> 0.2128547 | R21: =SUM(R12/R$14) -> 0.17725387 | S21: =SUM(S12/S$14) -> 0.22045426 | T21: =SUM(T12/T$14) -> 0.25933714 | U21: =SUM(U12/U$14) -> 0.24932401 | ... AC21: =SUM(AC12/AC$14) -> 0.28058088 | AE21: =SUM(AE12/AE$14) -> 0.20482947 | AF21: =SUM(AF12/AF$14) -> 0.20894844 | AG21: =SUM(AG12/AG$14) -> 0.21377167 | AH21: =SUM(AH12/AH$14) -> 0.2222889 | AI21: =SUM(AI12/AI$14) -> 0.22698895 | AJ21: =SUM(AJ12/AJ$14) -> 0.23717386 | AK21: =SUM(AK12/AK$14) -> 0.24250589 | AL21: =SUM(AL12/AL$14) -> 0.24593451 | ... AP21: =SUM(AP12/AP$14) -> 0.26229752
B22: =B13&"(%)" -> Wearables, Home, and Accessories Revenue(%) | C22: =SUM(C13/C$14) -> 0.051623315 | D22: =SUM(D13/D$14) -> 0.056112968 | E22: =SUM(E13/E$14) -> 0.065441744 | F22: =SUM(F13/F$14) -> 0.094098565 | G22: =SUM(G13/G$14) -> 0.11154217 | H22: =SUM(H13/H$14) -> 0.10488031 | I22: =SUM(I13/I$14) -> 0.10458552 | J22: =SUM(J13/J$14) -> 0.10395659 | ... L22: =SUM(L13/L$14) -> 0.085750467 | N22: =SUM(N13/N$14) -> 0.11860906 | O22: =SUM(O13/O$14) -> 0.090524065 | P22: =SUM(P13/P$14) -> 0.097445726 | Q22: =SUM(Q13/Q$14) -> 0.10704857 | R22: =SUM(R13/R$14) -> 0.1150793 | S22: =SUM(S13/S$14) -> 0.092338353 | T22: =SUM(T13/T$14) -> 0.10127511 | U22: =SUM(U13/U$14) -> 0.10415875 | ... AC22: =SUM(AC13/AC$14) -> 0.087960885 | AE22: =SUM(AE13/AE$14) -> 0.10327272 | AF22: =SUM(AF13/AF$14) -> 0.10380036 | AG22: =SUM(AG13/AG$14) -> 0.10463544 | AH22: =SUM(AH13/AH$14) -> 0.10395659 | AI22: =SUM(AI13/AI$14) -> 0.099339912 | AJ22: =SUM(AJ13/AJ$14) -> 0.098191147 | AK22: =SUM(AK13/AK$14) -> 0.096692712 | AL22: =SUM(AL13/AL$14) -> 0.094633473 | ... AP22: =SUM(AP13/AP$14) -> 0.085750467
B23: Y/Y Growth Rates (%)
B24: =B9&"(%)" -> iPhone Revenue(%) | C24: N/A | D24: =SUM(D9/C9)-1 -> 0.03378932 | E24: =SUM(E9/D9)-1 -> 0.16677871 | F24: =SUM(F9/E9)-1 -> -0.13649871 | G24: =SUM(G9/F9)-1 -> -0.032307682 | H24: =SUM(H9/G9)-1 -> 0.39331983 | I24: =SUM(I9/H9)-1 -> 0.070405734 | J24: =SUM(J9/I9)-1 -> -0.023874757 | K24: =SUM(K9/J9)-1 -> 0.0029912804 | L24: =SUM(L9/K9)-1 -> 0.041767943 | N24: N/A | O24: N/A | P24: N/A | Q24: N/A | R24: =SUM(R9/N9)-1 -> -0.081713855 | S24: =SUM(S9/R9)-1 -> -0.2195515 | T24: =SUM(T9/S9)-1 -> -0.22723731 | U24: =SUM(U9/T9)-1 -> 0.10426277 | V24: =SUM(V9/U9)-1 -> 0.59118822 | W24: =SUM(W9/V9)-1 -> -0.34057846 | X24: =SUM(X9/W9)-1 -> -0.14505145 | Y24: =SUM(Y9/X9)-1 -> 0.17625204 | Z24: =SUM(Z9/Y9)-1 -> 0.49578123 | ... AC24: =SUM(AC9/AB9)-1 -> 0.099659055 | AE24: N/A | AF24: N/A | AG24: N/A | AH24: N/A | AI24: =SUM(AI9/AE9)-1 -> 0.024414434 | AJ24: =SUM(AJ9/AF9)-1 -> -0.0062924152 | AK24: =SUM(AK9/AG9)-1 -> -0.0031995346 | AL24: =SUM(AL9/AH9)-1 -> 0.0029912804 | AM24: =SUM(AM9/AI9)-1 -> -0.019025965 | AN24: =SUM(AN9/AJ9)-1 -> 0.011840975 | AO24: =SUM(AO9/AK9)-1 -> 0.04033386 | AP24: =SUM(AP9/AL9)-1 -> 0.041767943
B25: =B10&"(%)" -> Mac Revenue(%) | C25: N/A | D25: =SUM(D10/C10)-1 -> 0.13223249 | E25: =SUM(E10/D10)-1 -> -0.025222437 | F25: =SUM(F10/E10)-1 -> 0.021509644 | G25: =SUM(G10/F10)-1 -> 0.11196581 | H25: =SUM(H10/G10)-1 -> 0.22947383 | I25: =SUM(I10/H10)-1 -> 0.1417164 | J25: =SUM(J10/I10)-1 -> -0.26930831 | K25: =SUM(K10/J10)-1 -> 0.021357768 | L25: =SUM(L10/K10)-1 -> 0.12419957 | N25: N/A | O25: N/A | P25: N/A | Q25: N/A | R25: =SUM(R10/N10)-1 -> -0.28722816 | S25: =SUM(S10/R10)-1 -> -0.073303167 | T25: =SUM(T10/S10)-1 -> -0.045758929 | U25: =SUM(U10/T10)-1 -> 0.11315789 | V25: =SUM(V10/U10)-1 -> 0.021801944 | W25: =SUM(W10/V10)-1 -> -0.042287918 | X25: =SUM(X10/W10)-1 -> -0.059320897 | Y25: =SUM(Y10/X10)-1 -> 0.10486517 | Z25: =SUM(Z10/Y10)-1 -> 0.16051136 | ... AC25: =SUM(AC10/AB10)-1 -> 0.084514044 | AE25: N/A | AF25: N/A | AG25: N/A | AH25: N/A | AI25: =SUM(AI10/AE10)-1 -> -0.20663788 | AJ25: =SUM(AJ10/AF10)-1 -> -0.12156364 | AK25: =SUM(AK10/AG10)-1 -> -0.10216234 | AL25: =SUM(AL10/AH10)-1 -> 0.021357768 | AM25: =SUM(AM10/AI10)-1 -> 0.060846201 | AN25: =SUM(AN10/AJ10)-1 -> 0.067508843 | AO25: =SUM(AO10/AK10)-1 -> 0.096201514 | AP25: =SUM(AP10/AL10)-1 -> 0.12419957
B26: =B11&"(%)" -> iPad Revenue(%) | C26: N/A | D26: =SUM(D11/C11)-1 -> -0.068159783 | E26: =SUM(E11/D11)-1 -> -0.043803975 | F26: =SUM(F11/E11)-1 -> 0.1577802 | G26: =SUM(G11/F11)-1 -> 0.11484962 | H26: =SUM(H11/G11)-1 -> 0.34302816 | I26: =SUM(I11/H11)-1 -> -0.080660348 | J26: =SUM(J11/I11)-1 -> -0.033865902 | K26: =SUM(K11/J11)-1 -> -0.056749117 | L26: =SUM(L11/K11)-1 -> 0.049786469 | N26: N/A | O26: N/A | P26: N/A | Q26: N/A | R26: =SUM(R11/N11)-1 -> 0.29635762 | S26: =SUM(S11/R11)-1 -> -0.29012346 | T26: =SUM(T11/S11)-1 -> -0.13178411 | U26: =SUM(U11/T11)-1 -> 0.1125885 | V26: =SUM(V11/U11)-1 -> 0.090020177 | W26: =SUM(W11/V11)-1 -> -0.20845792 | X26: =SUM(X11/W11)-1 -> 0.28836122 | Y26: =SUM(Y11/X11)-1 -> -0.02960067 | Z26: =SUM(Z11/Y11)-1 -> 0.16374101 | ... AC26: =SUM(AC11/AB11)-1 -> 0.056374411 | AE26: N/A | AF26: N/A | AG26: N/A | AH26: N/A | AI26: =SUM(AI11/AE11)-1 -> -0.17534987 | AJ26: =SUM(AJ11/AF11)-1 -> -0.18539916 | AK26: =SUM(AK11/AG11)-1 -> -0.097964245 | AL26: =SUM(AL11/AH11)-1 -> -0.056749117 | AM26: =SUM(AM11/AI11)-1 -> 0.07065993 | AN26: =SUM(AN11/AJ11)-1 -> 0.15256286 | AO26: =SUM(AO11/AK11)-1 -> 0.07003475 | AP26: =SUM(AP11/AL11)-1 -> 0.049786469
B27: =B12&"(%)" -> Services Revenue(%) | C27: N/A | D27: =SUM(D12/C12)-1 -> 0.23131263 | E27: =SUM(E12/D12)-1 -> 0.32581721 | F27: =SUM(F12/E12)-1 -> 0.16461206 | G27: =SUM(G12/F12)-1 -> 0.16152168 | H27: =SUM(H12/G12)-1 -> 0.27259708 | I27: =SUM(I12/H12)-1 -> 0.14181951 | J27: =SUM(J12/I12)-1 -> 0.090504166 | K27: =SUM(K12/J12)-1 -> 0.12874413 | L27: =SUM(L12/K12)-1 -> 0.13506431 | N27: N/A | O27: N/A | P27: N/A | Q27: N/A | R27: =SUM(R12/N12)-1 -> 0.06405001 | S27: =SUM(S12/R12)-1 -> 0.0067899451 | T27: =SUM(T12/S12)-1 -> 0.014636246 | U27: =SUM(U12/T12)-1 -> 0.051902135 | V27: =SUM(V12/U12)-1 -> 0.035986376 | W27: =SUM(W12/V12)-1 -> 0.032443656 | X27: =SUM(X12/W12)-1 -> 0.014497004 | Y27: =SUM(Y12/X12)-1 -> 0.031346797 | Z27: =SUM(Z12/Y12)-1 -> 0.054781355 | ... AC27: =SUM(AC12/AB12)-1 -> 0.048390038 | AE27: N/A | AF27: N/A | AG27: N/A | AH27: N/A | AI27: =SUM(AI12/AE12)-1 -> 0.10294914 | AJ27: =SUM(AJ12/AF12)-1 -> 0.12484931 | AK27: =SUM(AK12/AG12)-1 -> 0.13934986 | AL27: =SUM(AL12/AH12)-1 -> 0.12874413 | AM27: =SUM(AM12/AI12)-1 -> 0.13524688 | AN27: =SUM(AN12/AJ12)-1 -> 0.12881307 | AO27: =SUM(AO12/AK12)-1 -> 0.12692624 | AP27: =SUM(AP12/AL12)-1 -> 0.13506431
B28: =B13&"(%)" -> Wearables, Home, and Accessories Revenue(%) | C28: N/A | D28: =SUM(D13/C13)-1 -> 0.15549766 | E28: =SUM(E13/D13)-1 -> 0.35123999 | F28: =SUM(F13/E13)-1 -> 0.40854957 | G28: =SUM(G13/F13)-1 -> 0.25071481 | H28: =SUM(H13/G13)-1 -> 0.25300457 | I28: =SUM(I13/H13)-1 -> 0.074908124 | J28: =SUM(J13/I13)-1 -> -0.03384981 | K28: =SUM(K13/J13)-1 -> -0.071276195 | L28: =SUM(L13/K13)-1 -> -0.035643832 | N28: N/A | O28: N/A | P28: N/A | Q28: N/A | R28: =SUM(R13/N13)-1 -> -0.082919529 | S28: =SUM(S13/R13)-1 -> -0.35046729 | T28: =SUM(T13/S13)-1 -> -0.054013932 | U28: =SUM(U13/T13)-1 -> 0.12530179 | V28: =SUM(V13/U13)-1 -> 0.28223557 | W28: =SUM(W13/V13)-1 -> -0.33799046 | X28: =SUM(X13/W13)-1 -> 0.023252875 | Y28: =SUM(Y13/X13)-1 -> 0.11670989 | Z28: =SUM(Z13/Y13)-1 -> 0.29915948 | ... AC28: =SUM(AC13/AB13)-1 -> 0.21731496 | AE28: N/A | AF28: N/A | AG28: N/A | AH28: N/A | AI28: =SUM(AI13/AE13)-1 -> -0.042626555 | AJ28: =SUM(AJ13/AF13)-1 -> -0.062567233 | AK28: =SUM(AK13/AG13)-1 -> -0.07188908 | AL28: =SUM(AL13/AH13)-1 -> -0.071276195 | AM28: =SUM(AM13/AI13)-1 -> -0.039591815 | AN28: =SUM(AN13/AJ13)-1 -> -0.028394535 | AO28: =SUM(AO13/AK13)-1 -> -0.042108086 | AP28: =SUM(AP13/AL13)-1 -> -0.035643832
B29: Q/Q Growth Rates (%)
B30: =B9&"(%)" -> iPhone Revenue(%) | C30: N/A | D30: N/A | E30: N/A | F30: N/A | G30: N/A | H30: N/A | I30: N/A | J30: N/A | K30: N/A | L30: N/A | N30: N/A | O30: =SUM(O9/N9)-1 -> -0.29399118 | P30: =SUM(P9/O9)-1 -> -0.19586711 | Q30: =SUM(Q9/P9)-1 -> 0.048223288 | R30: =SUM(R9/Q9)-1 -> 0.5430723 | S30: =SUM(S9/R9)-1 -> -0.2195515 | T30: =SUM(T9/S9)-1 -> -0.22723731 | U30: =SUM(U9/T9)-1 -> 0.10426277 | V30: =SUM(V9/U9)-1 -> 0.59118822 | ... AC30: =SUM(AC9/AB9)-1 -> 0.099659055 | AE30: N/A | AF30: N/A | AG30: N/A | AH30: N/A | AI30: N/A | AJ30: N/A | AK30: N/A | AL30: N/A | AM30: N/A | AN30: N/A | AO30: N/A | AP30: N/A
B31: =B10&"(%)" -> Mac Revenue(%) | C31: N/A | D31: N/A | E31: N/A | F31: N/A | G31: N/A | H31: N/A | I31: N/A | J31: N/A | K31: N/A | L31: N/A | N31: N/A | O31: =SUM(O10/N10)-1 -> -0.038426097 | P31: =SUM(P10/O10)-1 -> -0.29257307 | Q31: =SUM(Q10/P10)-1 -> 0.55892712 | R31: =SUM(R10/Q10)-1 -> -0.32785888 | S31: =SUM(S10/R10)-1 -> -0.073303167 | T31: =SUM(T10/S10)-1 -> -0.045758929 | U31: =SUM(U10/T10)-1 -> 0.11315789 | V31: =SUM(V10/U10)-1 -> 0.021801944 | ... AC31: =SUM(AC10/AB10)-1 -> 0.084514044 | AE31: N/A | AF31: N/A | AG31: N/A | AH31: N/A | AI31: N/A | AJ31: N/A | AK31: N/A | AL31: N/A | AM31: N/A | AN31: N/A | AO31: N/A | AP31: N/A
B32: =B11&"(%)" -> iPad Revenue(%) | C32: N/A | D32: N/A | E32: N/A | F32: N/A | G32: N/A | H32: N/A | I32: N/A | J32: N/A | K32: N/A | L32: N/A | N32: N/A | O32: =SUM(O11/N11)-1 -> 0.0549117 | P32: =SUM(P11/O11)-1 -> -0.055192257 | Q32: =SUM(Q11/P11)-1 -> -0.0069213732 | R32: =SUM(R11/Q11)-1 -> 0.30972958 | S32: =SUM(S11/R11)-1 -> -0.29012346 | T32: =SUM(T11/S11)-1 -> -0.13178411 | U32: =SUM(U11/T11)-1 -> 0.1125885 | V32: =SUM(V11/U11)-1 -> 0.090020177 | ... AC32: =SUM(AC11/AB11)-1 -> 0.056374411 | AE32: N/A | AF32: N/A | AG32: N/A | AH32: N/A | AI32: N/A | AJ32: N/A | AK32: N/A | AL32: N/A | AM32: N/A | AN32: N/A | AO32: N/A | AP32: N/A
B33: =B12&"(%)" -> Services Revenue(%) | C33: N/A | D33: N/A | E33: N/A | F33: N/A | G33: N/A | H33: N/A | I33: N/A | J33: N/A | K33: N/A | L33: N/A | N33: N/A | O33: =SUM(O12/N12)-1 -> 0.015628203 | P33: =SUM(P12/O12)-1 -> -0.010947984 | Q33: =SUM(Q12/P12)-1 -> -0.021220159 | R33: =SUM(R12/Q12)-1 -> 0.082238899 | S33: =SUM(S12/R12)-1 -> 0.0067899451 | T33: =SUM(T12/S12)-1 -> 0.014636246 | U33: =SUM(U12/T12)-1 -> 0.051902135 | V33: =SUM(V12/U12)-1 -> 0.035986376 | ... AC33: =SUM(AC12/AB12)-1 -> 0.048390038 | AE33: N/A | AF33: N/A | AG33: N/A | AH33: N/A | AI33: N/A | AJ33: N/A | AK33: N/A | AL33: N/A | AM33: N/A | AN33: N/A | AO33: N/A | AP33: N/A
B34: =B13&"(%)" -> Wearables, Home, and Accessories Revenue(%) | C34: N/A | D34: N/A | E34: N/A | F34: N/A | G34: N/A | H34: N/A | I34: N/A | J34: N/A | K34: N/A | L34: N/A | N34: N/A | O34: =SUM(O13/N13)-1 -> -0.40099313 | P34: =SUM(P13/O13)-1 -> -0.081989553 | Q34: =SUM(Q13/P13)-1 -> 0.19371598 | R34: =SUM(R13/Q13)-1 -> 0.39709845 | S34: =SUM(S13/R13)-1 -> -0.35046729 | T34: =SUM(T13/S13)-1 -> -0.054013932 | U34: =SUM(U13/T13)-1 -> 0.12530179 | V34: =SUM(V13/U13)-1 -> 0.28223557 | ... AC34: =SUM(AC13/AB13)-1 -> 0.21731496 | AE34: N/A | AF34: N/A | AG34: N/A | AH34: N/A | AI34: N/A | AJ34: N/A | AK34: N/A | AL34: N/A | AM34: N/A | AN34: N/A | AO34: N/A | AP34: N/A
A36: X | B36: Per Unit Data (k)
A38: X | B38: Total Units Sold per End Market
B39: iPhone | C39: 211884 | D39: 216756 | E39: 217722 | F39: 186000 | G39: 186860 | H39: 235000 | I39: 245000 | J39: 218000 | K39: 224000 | L39: 231000 | N39: 82000 | O39: 60000 | P39: 50000 | Q39: =SUM(I39-SUM(N39:P39)) -> 53000 | R39: 70000 | S39: 55000 | T39: 42000 | U39: =SUM(J39-SUM(R39:T39)) -> 51000 | V39: 77000 | W39: 52000 | X39: 43000 | Y39: =SUM(K39-SUM(V39:X39)) -> 52000 | Z39: 75000 | AA39: 53000 | AB39: 49000 | AC39: =SUM(L39-SUM(Z39:AB39)) -> 54000 | AE39: =SUM(O39:R39) -> 233000 | AF39: =SUM(P39:S39) -> 228000 | AG39: =SUM(Q39:T39) -> 220000 | AH39: =SUM(R39:U39) -> 218000 | AI39: =SUM(S39:V39) -> 225000 | AJ39: =SUM(T39:W39) -> 222000 | AK39: =SUM(U39:X39) -> 223000 | AL39: =SUM(V39:Y39) -> 224000 | ... AP39: =SUM(Z39:AC39) -> 231000 | AR39: =SUM(AO39/AK39)-1 -> 0.02690583
B40: iPad | C40: 45590 | D40: 43753 | E40: 43535 | F40: 45307.857 | G40: 52626 | H40: 68511 | I40: 59348.24 | J40: 52508.536 | K40: 50349.696 | L40: 50850 | N40: 15648 | O40: 15806 | P40: 14810 | Q40: =SUM(I40-SUM(N40:P40)) -> 13084.24 | R40: 14709.12 | S40: 13435.1 | T40: 12588.5 | U40: =SUM(J40-SUM(R40:T40)) -> 11775.816 | V40: 11767.296 | W40: 12991.742 | X40: 13343.81 | Y40: =SUM(K40-SUM(V40:X40)) -> 12246.849 | Z40: 12237.988 | AA40: 13251.577 | AB40: 13610.686 | AC40: =SUM(L40-SUM(Z40:AB40)) -> 11749.749 | AE40: =SUM(O40:R40) -> 58409.36 | AF40: =SUM(P40:S40) -> 56038.46 | AG40: =SUM(Q40:T40) -> 53816.96 | AH40: =SUM(R40:U40) -> 52508.536 | AI40: =SUM(S40:V40) -> 49566.712 | AJ40: =SUM(T40:W40) -> 49123.354 | AK40: =SUM(U40:X40) -> 49878.664 | AL40: =SUM(V40:Y40) -> 50349.696 | ... AP40: =SUM(Z40:AC40) -> 50850 | AR40: =SUM(AO40/AK40)-1 -> 0.029440153
B41: Mac | C41: 18484 | D41: 19251 | E41: 18209 | F41: 18433.59 | G41: 20907.113 | H41: 27537.026 | I41: 28368.573 | J41: 24996.716 | K41: 24935.376 | L41: 26947 | N41: 7608.573 | O41: 7160 | P41: 5500 | Q41: =SUM(I41-SUM(N41:P41)) -> 8100 | R41: 6847.7157 | S41: 6444 | T41: 5225 | U41: =SUM(J41-SUM(R41:T41)) -> 6480 | V41: 6368.3756 | W41: 6444 | X41: 5643 | Y41: =SUM(K41-SUM(V41:X41)) -> 6480 | Z41: 7005.2132 | AA41: 6766.2 | AB41: 6545.88 | AC41: =SUM(L41-SUM(Z41:AB41)) -> 6629.7068 | AE41: =SUM(O41:R41) -> 27607.716 | AF41: =SUM(P41:S41) -> 26891.716 | AG41: =SUM(Q41:T41) -> 26616.716 | AH41: =SUM(R41:U41) -> 24996.716 | AI41: =SUM(S41:V41) -> 24517.376 | AJ41: =SUM(T41:W41) -> 24517.376 | AK41: =SUM(U41:X41) -> 24935.376 | AL41: =SUM(V41:Y41) -> 24935.376 | ... AP41: =SUM(Z41:AC41) -> 26947 | AR41: =SUM(AO41/AK41)-1 -> 0.074669722
B42: Apple Watch | C42: 10500 | D42: 14000 | E42: 20700 | F42: 30350 | G42: 41627.5 | H42: 49942.75 | I42: 54498.707 | J42: 47633.541 | K42: 43243.04 | L42: 43916 | N42: 25582.9 | O42: 7688.52 | P42: 10411.538 | Q42: =SUM(I42-SUM(N42:P42)) -> 10815.75 | R42: 21745.465 | S42: 7304.094 | T42: 8849.8069 | U42: =SUM(J42-SUM(R42:T42)) -> 9734.175 | V42: 18483.645 | W42: 6573.6846 | X42: 7964.8262 | Y42: =SUM(K42-SUM(V42:X42)) -> 10220.884 | Z42: 18668.482 | AA42: 6902.3688 | AB42: 8124.1227 | AC42: =SUM(L42-SUM(Z42:AB42)) -> 10221.027 | AE42: =SUM(O42:R42) -> 50661.272 | AF42: =SUM(P42:S42) -> 50276.846 | AG42: =SUM(Q42:T42) -> 48715.116 | AH42: =SUM(R42:U42) -> 47633.541 | AI42: =SUM(S42:V42) -> 44371.721 | AJ42: =SUM(T42:W42) -> 43641.312 | AK42: =SUM(U42:X42) -> 42756.331 | AL42: =SUM(V42:Y42) -> 43243.04 | ... AP42: =SUM(Z42:AC42) -> 43916 | AR42: =SUM(AO42/AK42)-1 -> 0.027119398
B43: Total Units Sold | C43: =SUM(C39:C42) -> 286458 | D43: =SUM(D39:D42) -> 293760 | E43: =SUM(E39:E42) -> 300166 | F43: =SUM(F39:F42) -> 280091.45 | G43: =SUM(G39:G42) -> 302020.61 | H43: =SUM(H39:H42) -> 380990.78 | I43: =SUM(I39:I42) -> 387215.52 | J43: =SUM(J39:J42) -> 343138.79 | ... L43: =SUM(L39:L42) -> 352713 | N43: =SUM(N39:N42) -> 130839.47 | O43: =SUM(O39:O42) -> 90654.52 | P43: =SUM(P39:P42) -> 80721.538 | Q43: =SUM(Q39:Q42) -> 84999.99 | R43: =SUM(R39:R42) -> 113302.3 | S43: =SUM(S39:S42) -> 82183.194 | T43: =SUM(T39:T42) -> 68663.307 | U43: =SUM(U39:U42) -> 78989.991 | ... AC43: =SUM(AC39:AC42) -> 82600.483 | AE43: =SUM(AE39:AE41) -> 319017.08 | AF43: =SUM(AF39:AF41) -> 310930.18 | AG43: =SUM(AG39:AG41) -> 300433.68 | AH43: =SUM(AH39:AH41) -> 295505.25 | AI43: =SUM(AI39:AI41) -> 299084.09 | AJ43: =SUM(AJ39:AJ41) -> 295640.73 | AK43: =SUM(AK39:AK42) -> 340570.37 | AL43: =SUM(AL39:AL42) -> 342528.11 | AM43: =SUM(AM39:AM42) -> 341820.48 | AN43: =SUM(AN39:AN42) -> 343731.2 | AO43: =SUM(AO39:AO42) -> 351060.25 | AP43: =SUM(AP39:AP42) -> 352713 | AR43: =SUM(AO43/AK43)-1 -> 0.030800915
B45: Segments as a % of Total Revenue
B46: =B39&"(%)" -> iPhone(%) | C46: =SUM(C39/C$43) -> 0.73966864 | D46: =SUM(D39/D$43) -> 0.73786765 | E46: =SUM(E39/E$43) -> 0.72533865 | F46: =SUM(F39/F$43) -> 0.66406883 | G46: =SUM(G39/G$43) -> 0.61869949 | H46: =SUM(H39/H$43) -> 0.61681283 | I46: =SUM(I39/I$43) -> 0.63272257 | J46: =SUM(J39/J$43) -> 0.63531144 | ... L46: =SUM(L39/L$43) -> 0.65492341 | N46: =SUM(N39/N$43) -> 0.62672218 | O46: =SUM(O39/O$43) -> 0.66185337 | P46: =SUM(P39/P$43) -> 0.61941338 | Q46: =SUM(Q39/Q$43) -> 0.62352949 | R46: =SUM(R39/R$43) -> 0.61781623 | S46: =SUM(S39/S$43) -> 0.66923658 | T46: =SUM(T39/T$43) -> 0.61168041 | U46: =SUM(U39/U$43) -> 0.64565142 | ... AC46: =SUM(AC39/AC$43) -> 0.6537492 | AE46: =SUM(AE39/AE$43) -> 0.73036843 | AF46: =SUM(AF39/AF$43) -> 0.7332836 | AG46: =SUM(AG39/AG$43) -> 0.73227477 | AH46: =SUM(AH39/AH$43) -> 0.73771955 | AI46: =SUM(AI39/AI$43) -> 0.75229679 | AJ46: =SUM(AJ39/AJ$43) -> 0.75091142 | AK46: =SUM(AK39/AK$43) -> 0.65478391 | AL46: =SUM(AL39/AL$43) -> 0.65396092 | ... AP46: =SUM(AP39/AP$43) -> 0.65492341
B47: =B40&"(%)" -> iPad(%) | C47: =SUM(C40/C$43) -> 0.15915073 | D47: =SUM(D40/D$43) -> 0.14894131 | E47: =SUM(E40/E$43) -> 0.14503641 | F47: =SUM(F40/F$43) -> 0.16176094 | G47: =SUM(G40/G$43) -> 0.17424638 | H47: =SUM(H40/H$43) -> 0.17982325 | I47: =SUM(I40/I$43) -> 0.15326927 | J47: =SUM(J40/J$43) -> 0.15302419 | ... L47: =SUM(L40/L$43) -> 0.1441682 | N47: =SUM(N40/N$43) -> 0.11959694 | O47: =SUM(O40/O$43) -> 0.17435424 | P47: =SUM(P40/P$43) -> 0.18347024 | Q47: =SUM(Q40/Q$43) -> 0.15393225 | R47: =SUM(R40/R$43) -> 0.1298219 | S47: =SUM(S40/S$43) -> 0.16347746 | T47: =SUM(T40/T$43) -> 0.18333664 | U47: =SUM(U40/U$43) -> 0.14907985 | ... AC47: =SUM(AC40/AC$43) -> 0.14224795 | AE47: =SUM(AE40/AE$43) -> 0.18309164 | AF47: =SUM(AF40/AF$43) -> 0.18022844 | AG47: =SUM(AG40/AG$43) -> 0.17913092 | AH47: =SUM(AH40/AH$43) -> 0.1776907 | AI47: =SUM(AI40/AI$43) -> 0.16572835 | AJ47: =SUM(AJ40/AJ$43) -> 0.16615895 | AK47: =SUM(AK40/AK$43) -> 0.14645626 | AL47: =SUM(AL40/AL$43) -> 0.14699435 | ... AP47: =SUM(AP40/AP$43) -> 0.1441682
B48: =B41&"(%)" -> Mac(%) | C48: =SUM(C41/C$43) -> 0.064526039 | D48: =SUM(D41/D$43) -> 0.065533088 | E48: =SUM(E41/E$43) -> 0.0606631 | F48: =SUM(F41/F$43) -> 0.065812756 | G48: =SUM(G41/G$43) -> 0.069224128 | H48: =SUM(H41/H$43) -> 0.072277408 | I48: =SUM(I41/I$43) -> 0.073263006 | J48: =SUM(J41/J$43) -> 0.072847245 | ... L48: =SUM(L41/L$43) -> 0.076399225 | N48: =SUM(N41/N$43) -> 0.058151969 | O48: =SUM(O41/O$43) -> 0.078981169 | P48: =SUM(P41/P$43) -> 0.068135471 | Q48: =SUM(Q41/Q$43) -> 0.095294129 | R48: =SUM(R41/R$43) -> 0.06043757 | S48: =SUM(S41/S$43) -> 0.078410192 | T48: =SUM(T41/T$43) -> 0.076095956 | U48: =SUM(U41/U$43) -> 0.08203571 | ... AC48: =SUM(AC41/AC$43) -> 0.080262325 | AE48: =SUM(AE41/AE$43) -> 0.086539931 | AF48: =SUM(AF41/AF$43) -> 0.086487957 | AG48: =SUM(AG41/AG$43) -> 0.088594315 | AH48: =SUM(AH41/AH$43) -> 0.084589751 | AI48: =SUM(AI41/AI$43) -> 0.081974858 | AJ48: =SUM(AJ41/AJ$43) -> 0.082929628 | AK48: =SUM(AK41/AK$43) -> 0.073216515 | AL48: =SUM(AL41/AL$43) -> 0.072798041 | ... AP48: =SUM(AP41/AP$43) -> 0.076399225
B49: =B42&"(%)" -> Apple Watch(%) | C49: =SUM(C42/C$43) -> 0.036654588 | D49: =SUM(D42/D$43) -> 0.047657952 | E49: =SUM(E42/E$43) -> 0.068961841 | F49: =SUM(F42/F$43) -> 0.10835747 | G49: =SUM(G42/G$43) -> 0.13783 | H49: =SUM(H42/H$43) -> 0.13108651 | I49: =SUM(I42/I$43) -> 0.14074515 | J49: =SUM(J42/J$43) -> 0.13881713 | ... L49: =SUM(L42/L$43) -> 0.12450916 | N49: =SUM(N42/N$43) -> 0.19552891 | O49: =SUM(O42/O$43) -> 0.084811215 | P49: =SUM(P42/P$43) -> 0.12898091 | Q49: =SUM(Q42/Q$43) -> 0.12724413 | R49: =SUM(R42/R$43) -> 0.1919243 | S49: =SUM(S42/S$43) -> 0.088875762 | T49: =SUM(T42/T$43) -> 0.12888699 | U49: =SUM(U42/U$43) -> 0.12323302 | ... AC49: =SUM(AC42/AC$43) -> 0.12374052 | AE49: =SUM(AE42/AE$43) -> 0.15880427 | AF49: =SUM(AF42/AF$43) -> 0.16169819 | AG49: =SUM(AG42/AG$43) -> 0.16214932 | AH49: =SUM(AH42/AH$43) -> 0.16119355 | AI49: =SUM(AI42/AI$43) -> 0.14835868 | AJ49: =SUM(AJ42/AJ$43) -> 0.14761603 | AK49: =SUM(AK42/AK$43) -> 0.12554331 | AL49: =SUM(AL42/AL$43) -> 0.12624669 | ... AP49: =SUM(AP42/AP$43) -> 0.12450916
B50: Y/Y Growth Rates (%)
B51: =B39&"(%)" -> iPhone(%) | C51: N/A | D51: =SUM(D39/C39)-1 -> 0.022993714 | E51: =SUM(E39/D39)-1 -> 0.004456624 | F51: =SUM(F39/E39)-1 -> -0.14569956 | G51: =SUM(G39/F39)-1 -> 0.0046236559 | H51: =SUM(H39/G39)-1 -> 0.25762603 | I51: =SUM(I39/H39)-1 -> 0.042553191 | J51: =SUM(J39/I39)-1 -> -0.11020408 | K51: =SUM(K39/J39)-1 -> 0.027522936 | L51: =SUM(L39/K39)-1 -> 0.03125 | N51: N/A | O51: N/A | P51: N/A | Q51: N/A | R51: =SUM(R39/Q39)-1 -> 0.32075472 | S51: =SUM(S39/R39)-1 -> -0.21428571 | T51: =SUM(T39/S39)-1 -> -0.23636364 | U51: =SUM(U39/T39)-1 -> 0.21428571 | V51: =SUM(V39/U39)-1 -> 0.50980392 | W51: =SUM(W39/V39)-1 -> -0.32467532 | X51: =SUM(X39/W39)-1 -> -0.17307692 | Y51: =SUM(Y39/X39)-1 -> 0.20930233 | ... AC51: =SUM(AC39/AB39)-1 -> 0.10204082 | AE51: N/A | AF51: N/A | AG51: N/A | AH51: N/A | AI51: =SUM(AI39/AE39)-1 -> -0.034334764 | AJ51: =SUM(AJ39/AF39)-1 -> -0.026315789 | AK51: =SUM(AK39/AG39)-1 -> 0.013636364 | AL51: =SUM(AL39/AH39)-1 -> 0.027522936 | AM51: =SUM(AM39/AI39)-1 -> -0.013333333 | AN51: =SUM(AN39/AJ39)-1 -> 0.0045045045 | AO51: =SUM(AO39/AK39)-1 -> 0.02690583 | AP51: =SUM(AP39/AL39)-1 -> 0.03125
B52: =B40&"(%)" -> iPad(%) | C52: N/A | D52: =SUM(D40/C40)-1 -> -0.040293924 | E52: =SUM(E40/D40)-1 -> -0.0049825155 | F52: =SUM(F40/E40)-1 -> 0.040722571 | G52: =SUM(G40/F40)-1 -> 0.16152039 | H52: =SUM(H40/G40)-1 -> 0.301847 | I52: =SUM(I40/H40)-1 -> -0.13374144 | J52: =SUM(J40/I40)-1 -> -0.11524696 | K52: =SUM(K40/J40)-1 -> -0.041114071 | L52: =SUM(L40/K40)-1 -> 0.0099365775 | N52: N/A | O52: N/A | P52: N/A | Q52: N/A | R52: =SUM(R40/Q40)-1 -> 0.12418604 | S52: =SUM(S40/R40)-1 -> -0.086614291 | T52: =SUM(T40/S40)-1 -> -0.063014045 | U52: =SUM(U40/T40)-1 -> -0.064557652 | V52: =SUM(V40/U40)-1 -> -0.00072351674 | W52: =SUM(W40/V40)-1 -> 0.10405498 | X52: =SUM(X40/W40)-1 -> 0.027099392 | Y52: =SUM(Y40/X40)-1 -> -0.082207507 | ... AC52: =SUM(AC40/AB40)-1 -> -0.13672615 | AE52: N/A | AF52: N/A | AG52: N/A | AH52: N/A | AI52: =SUM(AI40/AE40)-1 -> -0.15139094 | AJ52: =SUM(AJ40/AF40)-1 -> -0.12339929 | AK52: =SUM(AK40/AG40)-1 -> -0.073179464 | AL52: =SUM(AL40/AH40)-1 -> -0.041114071 | AM52: =SUM(AM40/AI40)-1 -> 0.025292704 | AN52: =SUM(AN40/AJ40)-1 -> 0.039835825 | AO52: =SUM(AO40/AK40)-1 -> 0.029440153 | AP52: =SUM(AP40/AL40)-1 -> 0.0099365775
B53: =B41&"(%)" -> Mac(%) | C53: N/A | D53: =SUM(D41/C41)-1 -> 0.041495347 | E53: =SUM(E41/D41)-1 -> -0.054127058 | F53: =SUM(F41/E41)-1 -> 0.012334011 | G53: =SUM(G41/F41)-1 -> 0.13418566 | H53: =SUM(H41/G41)-1 -> 0.31711276 | I53: =SUM(I41/H41)-1 -> 0.03019742 | J53: =SUM(J41/I41)-1 -> -0.1188589 | K53: =SUM(K41/J41)-1 -> -0.0024539263 | L53: =SUM(L41/K41)-1 -> 0.080673515 | N53: N/A | O53: N/A | P53: N/A | Q53: N/A | R53: =SUM(R41/Q41)-1 -> -0.154603 | S53: =SUM(S41/R41)-1 -> -0.058956259 | T53: =SUM(T41/S41)-1 -> -0.18916822 | U53: =SUM(U41/T41)-1 -> 0.24019139 | V53: =SUM(V41/U41)-1 -> -0.017225988 | W53: =SUM(W41/V41)-1 -> 0.01187499 | X53: =SUM(X41/W41)-1 -> -0.12430168 | Y53: =SUM(Y41/X41)-1 -> 0.14832536 | ... AC53: =SUM(AC41/AB41)-1 -> 0.012806046 | AE53: N/A | AF53: N/A | AG53: N/A | AH53: N/A | AI53: =SUM(AI41/AE41)-1 -> -0.11193755 | AJ53: =SUM(AJ41/AF41)-1 -> -0.088292622 | AK53: =SUM(AK41/AG41)-1 -> -0.063168579 | AL53: =SUM(AL41/AH41)-1 -> -0.0024539263 | AM53: =SUM(AM41/AI41)-1 -> 0.043024081 | AN53: =SUM(AN41/AJ41)-1 -> 0.056165781 | AO53: =SUM(AO41/AK41)-1 -> 0.074669722 | AP53: =SUM(AP41/AL41)-1 -> 0.080673515
B54: =B42&"(%)" -> Apple Watch(%) | C54: N/A | D54: =SUM(D42/C42)-1 -> 0.33333333 | E54: =SUM(E42/D42)-1 -> 0.47857143 | F54: =SUM(F42/E42)-1 -> 0.46618357 | G54: =SUM(G42/F42)-1 -> 0.37158155 | H54: =SUM(H42/G42)-1 -> 0.19975377 | I54: =SUM(I42/H42)-1 -> 0.091223601 | J54: =SUM(J42/I42)-1 -> -0.12596935 | K54: =SUM(K42/J42)-1 -> -0.092172469 | L54: =SUM(L42/K42)-1 -> 0.015562278 | N54: N/A | O54: N/A | P54: N/A | Q54: N/A | R54: =SUM(R42/Q42)-1 -> 1.0105369 | S54: =SUM(S42/R42)-1 -> -0.66410955 | T54: =SUM(T42/S42)-1 -> 0.21162281 | U54: =SUM(U42/T42)-1 -> 0.099930782 | V54: =SUM(V42/U42)-1 -> 0.89884045 | W54: =SUM(W42/V42)-1 -> -0.64435129 | X54: =SUM(X42/W42)-1 -> 0.21162281 | Y54: =SUM(Y42/X42)-1 -> 0.28325258 | ... AC54: =SUM(AC42/AB42)-1 -> 0.25810837 | AE54: N/A | AF54: N/A | AG54: N/A | AH54: N/A | AI54: =SUM(AI42/AE42)-1 -> -0.1241491 | AJ54: =SUM(AJ42/AF42)-1 -> -0.13197993 | AK54: =SUM(AK42/AG42)-1 -> -0.12231901 | AL54: =SUM(AL42/AH42)-1 -> -0.092172469 | AM54: =SUM(AM42/AI42)-1 -> -0.021271316 | AN54: =SUM(AN42/AJ42)-1 -> 0.0026408176 | AO54: =SUM(AO42/AK42)-1 -> 0.027119398 | AP54: =SUM(AP42/AL42)-1 -> 0.015562278
B55: Q/Q Growth Rates (%)
B56: =B39&"(%)" -> iPhone(%) | C56: N/A | D56: N/A | E56: N/A | F56: N/A | G56: N/A | H56: N/A | I56: N/A | J56: N/A | K56: N/A | L56: N/A | N56: N/A | O56: =SUM(O39/N39)-1 -> -0.26829268 | P56: =SUM(P39/O39)-1 -> -0.16666667 | Q56: =SUM(Q39/P39)-1 -> 0.06 | R56: =SUM(R39/Q39)-1 -> 0.32075472 | S56: =SUM(S39/R39)-1 -> -0.21428571 | T56: =SUM(T39/S39)-1 -> -0.23636364 | U56: =SUM(U39/T39)-1 -> 0.21428571 | V56: =SUM(V39/U39)-1 -> 0.50980392 | ... AC56: =SUM(AC39/AB39)-1 -> 0.10204082 | AE56: N/A | AF56: N/A | AG56: N/A | AH56: N/A | AI56: N/A | AJ56: N/A | AK56: N/A | AL56: N/A | AM56: N/A | AN56: N/A | AO56: N/A | AP56: N/A
B57: =B40&"(%)" -> iPad(%) | C57: N/A | D57: N/A | E57: N/A | F57: N/A | G57: N/A | H57: N/A | I57: N/A | J57: N/A | K57: N/A | L57: N/A | N57: N/A | O57: =SUM(O40/N40)-1 -> 0.010097137 | P57: =SUM(P40/O40)-1 -> -0.063014045 | Q57: =SUM(Q40/P40)-1 -> -0.11652667 | R57: =SUM(R40/Q40)-1 -> 0.12418604 | S57: =SUM(S40/R40)-1 -> -0.086614291 | T57: =SUM(T40/S40)-1 -> -0.063014045 | U57: =SUM(U40/T40)-1 -> -0.064557652 | V57: =SUM(V40/U40)-1 -> -0.00072351674 | ... AC57: =SUM(AC40/AB40)-1 -> -0.13672615 | AE57: N/A | AF57: N/A | AG57: N/A | AH57: N/A | AI57: N/A | AJ57: N/A | AK57: N/A | AL57: N/A | AM57: N/A | AN57: N/A | AO57: N/A | AP57: N/A
B58: =B41&"(%)" -> Mac(%) | C58: N/A | D58: N/A | E58: N/A | F58: N/A | G58: N/A | H58: N/A | I58: N/A | J58: N/A | K58: N/A | L58: N/A | N58: N/A | O58: =SUM(O41/N41)-1 -> -0.058956259 | P58: =SUM(P41/O41)-1 -> -0.23184358 | Q58: =SUM(Q41/P41)-1 -> 0.47272727 | R58: =SUM(R41/Q41)-1 -> -0.154603 | S58: =SUM(S41/R41)-1 -> -0.058956259 | T58: =SUM(T41/S41)-1 -> -0.18916822 | U58: =SUM(U41/T41)-1 -> 0.24019139 | V58: =SUM(V41/U41)-1 -> -0.017225988 | ... AC58: =SUM(AC41/AB41)-1 -> 0.012806046 | AE58: N/A | AF58: N/A | AG58: N/A | AH58: N/A | AI58: N/A | AJ58: N/A | AK58: N/A | AL58: N/A | AM58: N/A | AN58: N/A | AO58: N/A | AP58: N/A
B59: =B42&"(%)" -> Apple Watch(%) | C59: N/A | D59: N/A | E59: N/A | F59: N/A | G59: N/A | H59: N/A | I59: N/A | J59: N/A | K59: N/A | L59: N/A | N59: N/A | O59: =SUM(O42/N42)-1 -> -0.69946644 | P59: =SUM(P42/O42)-1 -> 0.35416667 | Q59: =SUM(Q42/P42)-1 -> 0.038823517 | R59: =SUM(R42/Q42)-1 -> 1.0105369 | S59: =SUM(S42/R42)-1 -> -0.66410955 | T59: =SUM(T42/S42)-1 -> 0.21162281 | U59: =SUM(U42/T42)-1 -> 0.099930782 | V59: =SUM(V42/U42)-1 -> 0.89884045 | ... AC59: =SUM(AC42/AB42)-1 -> 0.25810837 | AE59: N/A | AF59: N/A | AG59: N/A | AH59: N/A | AI59: N/A | AJ59: N/A | AK59: N/A | AL59: N/A | AM59: N/A | AN59: N/A | AO59: N/A | AP59: N/A
A61: X | B61: ASP Per End Product
B62: iPhone | C62: 618.72432 | D62: 617.99173 | E62: 783.87255 | F62: 775.86047 | G62: 695.89474 | H62: 793.22449 | I62: 804.26415 | J62: 858.92157 | K62: 888.88462 | L62: 907 | N62: 873.5122 | O62: 842.83333 | P62: 813.3 | Q62: =I62 -> 804.26415 | R62: 939.64286 | S62: 933.34545 | T62: 944.5 | U62: =J62 -> 858.92157 | V62: 905.22078 | W62: 883.90385 | X62: 913.86047 | Y62: =K62 -> 888.88462 | Z62: 921.84 | AA62: 883.79245 | AB62: 909.83673 | AC62: =L62 -> 907 | AE62: =SUM(O62:R62) -> 3400.0403 | AF62: =SUM(P62:S62) -> 3490.5525 | AG62: =SUM(Q62:T62) -> 3621.7525 | AH62: =SUM(R62:U62) -> 3676.4099 | AI62: =SUM(S62:V62) -> 3641.9878 | AJ62: =SUM(T62:W62) -> 3592.5462 | AK62: =SUM(U62:X62) -> 3561.9067 | AL62: =SUM(V62:Y62) -> 3591.8697 | ... AP62: =SUM(Z62:AC62) -> 3622.4692 | AR62: =SUM(AO62/AK62)-1 -> 0.011916973
B63: iPad | C63: 459.15615 | D63: 467.84815 | E63: 410.66089 | F63: 459.235 | G63: 451.02853 | H63: 477.60157 | I63: 548.29321 | J63: 547.1383 | K63: 567.49293 | L63: 551 | N63: 463.19018 | O63: 483.74035 | P63: 487.77853 | Q63: =I63 -> 548.29321 | R63: 638.78736 | S63: 496.46076 | T63: 460.02304 | U63: =J63 -> 547.1383 | V63: 596.8236 | W63: 427.8872 | X63: 536.72827 | Y63: =K63 -> 567.49293 | Z63: 634.23351 | AA63: 458.53702 | AB63: 459.34615 | AC63: =L63 -> 551 | AE63: =SUM(O63:R63) -> 2158.5995 | AF63: =SUM(P63:S63) -> 2171.3199 | AG63: =SUM(Q63:T63) -> 2143.5644 | AH63: =SUM(R63:U63) -> 2142.4095 | AI63: =SUM(S63:V63) -> 2100.4457 | AJ63: =SUM(T63:W63) -> 2031.8721 | AK63: =SUM(U63:X63) -> 2108.5774 | AL63: =SUM(V63:Y63) -> 2128.932 | ... AP63: =SUM(Z63:AC63) -> 2103.1167 | AR63: =SUM(AO63/AK63)-1 -> 0.0052320694
B64: Mac | C64: 1153.6661 | D64: 1311.5135 | E64: 1365.3085 | F64: 1368.4272 | G64: 1313.4847 | H64: 1269.8014 | I64: 1404.5724 | J64: 1153.3969 | K64: 1172.6039 | L64: 1251 | N64: 1410.458 | O64: 1439.991 | P64: 1319.0705 | Q64: =I64 -> 1404.5724 | R64: 1110.1514 | S64: 1091.2347 | T64: 1282.6795 | U64: =J64 -> 1153.3969 | V64: 1199.3479 | W64: 1133.6492 | X64: 1216.2039 | Y64: =K64 -> 1172.6039 | Z64: 1219.3201 | AA64: 1152.5273 | AB64: 1228.366 | AC64: =L64 -> 1251 | AE64: =SUM(O64:R64) -> 5273.7852 | AF64: =SUM(P64:S64) -> 4925.0289 | AG64: =SUM(Q64:T64) -> 4888.6379 | AH64: =SUM(R64:U64) -> 4637.4624 | AI64: =SUM(S64:V64) -> 4726.6589 | AJ64: =SUM(T64:W64) -> 4769.0735 | AK64: =SUM(U64:X64) -> 4702.5979 | AL64: =SUM(V64:Y64) -> 4721.8049 | ... AP64: =SUM(Z64:AC64) -> 4851.2133 | AR64: =SUM(AO64/AK64)-1 -> 0.01493202
B65: Apple Watch | C65: 452.126 | D65: 432.126 | E65: 400.726 | F65: 400 | G65: 375 | H65: 350 | I65: 412.476 | J65: 412.476 | K65: 412.476 | L65: 416 | N65: 350 | O65: 350 | P65: 350 | Q65: =I65 -> 412.476 | R65: 421.256 | S65: 412.476 | T65: 412.476 | U65: =J65 -> 412.476 | V65: 421.256 | W65: 412.476 | X65: 412.476 | Y65: =K65 -> 412.476 | Z65: 421.256 | AA65: 412.476 | AB65: 412.476 | AC65: =L65 -> 416 | AE65: =SUM(O65:R65) -> 1533.732 | AF65: =SUM(P65:S65) -> 1596.208 | AG65: =SUM(Q65:T65) -> 1658.684 | AH65: =SUM(R65:U65) -> 1658.684 | AI65: =SUM(S65:V65) -> 1658.684 | AJ65: =SUM(T65:W65) -> 1658.684 | AK65: =SUM(U65:X65) -> 1658.684 | AL65: =SUM(V65:Y65) -> 1658.684 | ... AP65: =SUM(Z65:AC65) -> 1662.208
B67: Y/Y Growth Rates (%)
B68: =B62&"(%)" -> iPhone(%) | C68: N/A | D68: =SUM(D62/C62)-1 -> -0.0011840332 | E68: =SUM(E62/D62)-1 -> 0.26841916 | F68: =SUM(F62/E62)-1 -> -0.010221158 | G68: =SUM(G62/F62)-1 -> -0.10306715 | H68: =SUM(H62/G62)-1 -> 0.13986275 | I68: =SUM(I62/H62)-1 -> 0.013917449 | J68: =SUM(J62/I62)-1 -> 0.067959535 | K68: =SUM(K62/J62)-1 -> 0.034884497 | L68: =SUM(L62/K62)-1 -> 0.020379906 | N68: N/A | O68: N/A | P68: N/A | Q68: N/A | R68: =SUM(R62/Q62)-1 -> 0.16832617 | S68: =SUM(S62/R62)-1 -> -0.0067019108 | T68: =SUM(T62/S62)-1 -> 0.011951143 | U68: =SUM(U62/T62)-1 -> -0.090607127 | V68: =SUM(V62/U62)-1 -> 0.053903886 | W68: =SUM(W62/V62)-1 -> -0.023548877 | X68: =SUM(X62/W62)-1 -> 0.033891264 | Y68: =SUM(Y62/X62)-1 -> -0.027330047 | ... AC68: =SUM(AC62/AB62)-1 -> -0.0031178503 | AE68: N/A | AF68: N/A | AG68: N/A | AH68: N/A | AI68: =SUM(AI62/AE62)-1 -> 0.071160174 | AJ68: =SUM(AJ62/AF62)-1 -> 0.029219939 | AK68: =SUM(AK62/AG62)-1 -> -0.016523991 | AL68: =SUM(AL62/AH62)-1 -> -0.022995307 | AM68: =SUM(AM62/AI62)-1 -> -0.0091979648 | AN68: =SUM(AN62/AJ62)-1 -> 0.0044067184 | AO68: =SUM(AO62/AK62)-1 -> 0.011916973 | AP68: =SUM(AP62/AL62)-1 -> 0.0085190957
B69: =B63&"(%)" -> iPad(%) | C69: N/A | D69: =SUM(D63/C63)-1 -> 0.01893039 | E69: =SUM(E63/D63)-1 -> -0.12223466 | F69: =SUM(F63/E63)-1 -> 0.11828277 | G69: =SUM(G63/F63)-1 -> -0.017869869 | H69: =SUM(H63/G63)-1 -> 0.05891654 | I69: =SUM(I63/H63)-1 -> 0.14801383 | J69: =SUM(J63/I63)-1 -> -0.0021063718 | K69: =SUM(K63/J63)-1 -> 0.037201972 | L69: =SUM(L63/K63)-1 -> -0.029062791 | N69: N/A | O69: N/A | P69: N/A | Q69: N/A | R69: =SUM(R63/Q63)-1 -> 0.165047 | S69: =SUM(S63/R63)-1 -> -0.22280748 | T69: =SUM(T63/S63)-1 -> -0.073394977 | U69: =SUM(U63/T63)-1 -> 0.18937153 | V69: =SUM(V63/U63)-1 -> 0.090809396 | W69: =SUM(W63/V63)-1 -> -0.28305918 | X69: =SUM(X63/W63)-1 -> 0.25436859 | Y69: =SUM(Y63/X63)-1 -> 0.057318879 | ... AC69: =SUM(AC63/AB63)-1 -> 0.19953112 | AE69: N/A | AF69: N/A | AG69: N/A | AH69: N/A | AI69: =SUM(AI63/AE63)-1 -> -0.026940501 | AJ69: =SUM(AJ63/AF63)-1 -> -0.064222561 | AK69: =SUM(AK63/AG63)-1 -> -0.016321881 | AL69: =SUM(AL63/AH63)-1 -> -0.0062908002 | AM69: =SUM(AM63/AI63)-1 -> 0.031372481 | AN69: =SUM(AN63/AJ63)-1 -> 0.081264744 | AO69: =SUM(AO63/AK63)-1 -> 0.0052320694 | AP69: =SUM(AP63/AL63)-1 -> -0.012125953
B70: =B64&"(%)" -> Mac(%) | C70: N/A | D70: =SUM(D64/C64)-1 -> 0.13682236 | E70: =SUM(E64/D64)-1 -> 0.041017547 | F70: =SUM(F64/E64)-1 -> 0.0022842079 | G70: =SUM(G64/F64)-1 -> -0.040150122 | H70: =SUM(H64/G64)-1 -> -0.033257504 | I70: =SUM(I64/H64)-1 -> 0.10613545 | J70: =SUM(J64/I64)-1 -> -0.178827 | K70: =SUM(K64/J64)-1 -> 0.016652521 | L70: =SUM(L64/K64)-1 -> 0.066856434 | N70: N/A | O70: N/A | P70: N/A | Q70: N/A | R70: =SUM(R64/Q64)-1 -> -0.2096161 | S70: =SUM(S64/R64)-1 -> -0.017039785 | T70: =SUM(T64/S64)-1 -> 0.17543872 | U70: =SUM(U64/T64)-1 -> -0.100791 | V70: =SUM(V64/U64)-1 -> 0.039839697 | W70: =SUM(W64/V64)-1 -> -0.0547787 | X70: =SUM(X64/W64)-1 -> 0.072822119 | Y70: =SUM(Y64/X64)-1 -> -0.03584928 | ... AC70: =SUM(AC64/AB64)-1 -> 0.018426138 | AE70: N/A | AF70: N/A | AG70: N/A | AH70: N/A | AI70: =SUM(AI64/AE64)-1 -> -0.10374451 | AJ70: =SUM(AJ64/AF64)-1 -> -0.031665898 | AK70: =SUM(AK64/AG64)-1 -> -0.038055587 | AL70: =SUM(AL64/AH64)-1 -> 0.018187198 | AM70: =SUM(AM64/AI64)-1 -> 0.003198477 | AN70: =SUM(AN64/AJ64)-1 -> -0.0017651855 | AO70: =SUM(AO64/AK64)-1 -> 0.01493202 | AP70: =SUM(AP64/AL64)-1 -> 0.027406561
B71: =B65&"(%)" -> Apple Watch(%) | C71: N/A | D71: =SUM(D65/C65)-1 -> -0.044235456 | E71: =SUM(E65/D65)-1 -> -0.072663992 | F71: =SUM(F65/E65)-1 -> -0.0018117117 | G71: =SUM(G65/F65)-1 -> -0.0625 | H71: =SUM(H65/G65)-1 -> -0.066666667 | I71: =SUM(I65/H65)-1 -> 0.17850286 | J71: =SUM(J65/I65)-1 -> 0 | K71: =SUM(K65/J65)-1 -> 0 | L71: =SUM(L65/K65)-1 -> 0.0085435274 | N71: N/A | O71: N/A | P71: N/A | Q71: N/A | R71: =SUM(R65/Q65)-1 -> 0.021286087 | S71: =SUM(S65/R65)-1 -> -0.020842433 | T71: =SUM(T65/S65)-1 -> 0 | U71: =SUM(U65/T65)-1 -> 0 | V71: =SUM(V65/U65)-1 -> 0.021286087 | W71: =SUM(W65/V65)-1 -> -0.020842433 | X71: =SUM(X65/W65)-1 -> 0 | Y71: =SUM(Y65/X65)-1 -> 0 | ... AC71: =SUM(AC65/AB65)-1 -> 0.0085435274 | AE71: N/A | AF71: N/A | AG71: N/A | AH71: N/A | AI71: =SUM(AI65/AE65)-1 -> 0.081469253 | AJ71: =SUM(AJ65/AF65)-1 -> 0.039140262 | AK71: =SUM(AK65/AG65)-1 -> 0 | AL71: =SUM(AL65/AH65)-1 -> 0 | AM71: =SUM(AM65/AI65)-1 -> 0 | AN71: =SUM(AN65/AJ65)-1 -> 0 | AO71: =SUM(AO65/AK65)-1 -> 0 | AP71: =SUM(AP65/AL65)-1 -> 0.0021245759
B72: Q/Q Growth Rates (%)
B73: =B62&"(%)" -> iPhone(%) | C73: N/A | D73: N/A | E73: N/A | F73: N/A | G73: N/A | H73: N/A | I73: N/A | J73: N/A | K73: N/A | L73: N/A | N73: N/A | O73: =SUM(O62/N62)-1 -> -0.035121275 | P73: =SUM(P62/O62)-1 -> -0.035040538 | Q73: =SUM(Q62/P62)-1 -> -0.011110106 | R73: =SUM(R62/Q62)-1 -> 0.16832617 | S73: =SUM(S62/R62)-1 -> -0.0067019108 | T73: =SUM(T62/S62)-1 -> 0.011951143 | U73: =SUM(U62/T62)-1 -> -0.090607127 | V73: =SUM(V62/U62)-1 -> 0.053903886 | ... AC73: =SUM(AC62/AB62)-1 -> -0.0031178503 | AE73: N/A | AF73: N/A | AG73: N/A | AH73: N/A | AI73: N/A | AJ73: N/A | AK73: N/A | AL73: N/A | AM73: N/A | AN73: N/A | AO73: N/A | AP73: N/A
B74: =B63&"(%)" -> iPad(%) | C74: N/A | D74: N/A | E74: N/A | F74: N/A | G74: N/A | H74: N/A | I74: N/A | J74: N/A | K74: N/A | L74: N/A | N74: N/A | O74: =SUM(O63/N63)-1 -> 0.044366587 | P74: =SUM(P63/O63)-1 -> 0.0083478177 | Q74: =SUM(Q63/P63)-1 -> 0.12406181 | R74: =SUM(R63/Q63)-1 -> 0.165047 | S74: =SUM(S63/R63)-1 -> -0.22280748 | T74: =SUM(T63/S63)-1 -> -0.073394977 | U74: =SUM(U63/T63)-1 -> 0.18937153 | V74: =SUM(V63/U63)-1 -> 0.090809396 | ... AC74: =SUM(AC63/AB63)-1 -> 0.19953112 | AE74: N/A | AF74: N/A | AG74: N/A | AH74: N/A | AI74: N/A | AJ74: N/A | AK74: N/A | AL74: N/A | AM74: N/A | AN74: N/A | AO74: N/A | AP74: N/A
B75: =B64&"(%)" -> Mac(%) | C75: N/A | D75: N/A | E75: N/A | F75: N/A | G75: N/A | H75: N/A | I75: N/A | J75: N/A | K75: N/A | L75: N/A | N75: N/A | O75: =SUM(O64/N64)-1 -> 0.020938525 | P75: =SUM(P64/O64)-1 -> -0.083973068 | Q75: =SUM(Q64/P64)-1 -> 0.064819807 | R75: =SUM(R64/Q64)-1 -> -0.2096161 | S75: =SUM(S64/R64)-1 -> -0.017039785 | T75: =SUM(T64/S64)-1 -> 0.17543872 | U75: =SUM(U64/T64)-1 -> -0.100791 | V75: =SUM(V64/U64)-1 -> 0.039839697 | ... AC75: =SUM(AC64/AB64)-1 -> 0.018426138 | AE75: N/A | AF75: N/A | AG75: N/A | AH75: N/A | AI75: N/A | AJ75: N/A | AK75: N/A | AL75: N/A | AM75: N/A | AN75: N/A | AO75: N/A | AP75: N/A
B76: =B65&"(%)" -> Apple Watch(%) | C76: N/A | D76: N/A | E76: N/A | F76: N/A | G76: N/A | H76: N/A | I76: N/A | J76: N/A | K76: N/A | L76: N/A | N76: N/A | O76: =SUM(O65/N65)-1 -> 0 | P76: =SUM(P65/O65)-1 -> 0 | Q76: =SUM(Q65/P65)-1 -> 0.17850286 | R76: =SUM(R65/Q65)-1 -> 0.021286087 | S76: =SUM(S65/R65)-1 -> -0.020842433 | T76: =SUM(T65/S65)-1 -> 0 | U76: =SUM(U65/T65)-1 -> 0 | V76: =SUM(V65/U65)-1 -> 0.021286087 | ... AC76: =SUM(AC65/AB65)-1 -> 0.0085435274 | AE76: N/A | AF76: N/A | AG76: N/A | AH76: N/A | AI76: N/A | AJ76: N/A | AK76: N/A | AL76: N/A | AM76: N/A | AN76: N/A | AO76: N/A | AP76: N/A
A78: 0 | B78: Revenues By Region
A80: X | B80: Revenue by End Product
B81: Americas | C81: 86613 | D81: 96600 | E81: 112093 | F81: 116914 | G81: 124556 | H81: 153306 | I81: 169658 | J81: 162560 | K81: 167045 | L81: 178353 | N81: 51496 | O81: 40882 | P81: 37472 | Q81: =SUM(I81-SUM(N81:P81)) -> 39808 | R81: 49278 | S81: 37784 | T81: 35383 | U81: =SUM(J81-SUM(R81:T81)) -> 40115 | V81: 50430 | W81: 37273 | X81: 37678 | Y81: =SUM(K81-SUM(V81:X81)) -> 41664 | Z81: 52648 | AA81: 40315 | AB81: 41198 | AC81: =SUM(L81-SUM(Z81:AB81)) -> 44192 | AE81: =SUM(O81:R81) -> 167440 | AF81: =SUM(P81:S81) -> 164342 | AG81: =SUM(Q81:T81) -> 162253 | AH81: =SUM(R81:U81) -> 162560 | AI81: =SUM(S81:V81) -> 163712 | AJ81: =SUM(T81:W81) -> 163201 | AK81: =SUM(U81:X81) -> 165496 | AL81: =SUM(V81:Y81) -> 167045 | ... AP81: =SUM(Z81:AC81) -> 178353 | AR81: =SUM(AO81/AK81)-1 -> 0.062412385
B82: Europe | C82: 49952 | D82: 54938 | E82: 62420 | F82: 60288 | G82: 68640 | H82: 89307 | I82: 95118 | J82: 94294 | K82: 101328 | L82: 111032 | N82: 29749 | O82: 23287 | P82: 19287 | Q82: =SUM(I82-SUM(N82:P82)) -> 22795 | R82: 27681 | S82: 23945 | T82: 20205 | U82: =SUM(J82-SUM(R82:T82)) -> 22463 | V82: 30397 | W82: 24123 | X82: 21884 | Y82: =SUM(K82-SUM(V82:X82)) -> 24924 | Z82: 33861 | AA82: 24454 | AB82: 24014 | AC82: =SUM(L82-SUM(Z82:AB82)) -> 28703 | AE82: =SUM(O82:R82) -> 93050 | AF82: =SUM(P82:S82) -> 93708 | AG82: =SUM(Q82:T82) -> 94626 | AH82: =SUM(R82:U82) -> 94294 | AI82: =SUM(S82:V82) -> 97010 | AJ82: =SUM(T82:W82) -> 97188 | AK82: =SUM(U82:X82) -> 98867 | AL82: =SUM(V82:Y82) -> 101328 | ... AP82: =SUM(Z82:AC82) -> 111032 | AR82: =SUM(AO82/AK82)-1 -> 0.084821022
B83: Japan | C83: 16928 | D83: 17733 | E83: 21733 | F83: 21506 | G83: 21418 | H83: 28482 | I83: 25977 | J83: 24257 | K83: 25052 | L83: 28703 | N83: 7107 | O83: 7724 | P83: 5446 | Q83: =SUM(I83-SUM(N83:P83)) -> 5700 | R83: 6755 | S83: 7176 | T83: 4821 | U83: =SUM(J83-SUM(R83:T83)) -> 5505 | V83: 7767 | W83: 6262 | X83: 5097 | Y83: =SUM(K83-SUM(V83:X83)) -> 5926 | Z83: 8987 | AA83: 7298 | AB83: 5782 | AC83: =SUM(L83-SUM(Z83:AB83)) -> 6636 | AE83: =SUM(O83:R83) -> 25625 | AF83: =SUM(P83:S83) -> 25077 | AG83: =SUM(Q83:T83) -> 24452 | AH83: =SUM(R83:U83) -> 24257 | AI83: =SUM(S83:V83) -> 25269 | AJ83: =SUM(T83:W83) -> 24355 | AK83: =SUM(U83:X83) -> 24631 | AL83: =SUM(V83:Y83) -> 25052 | ... AP83: =SUM(Z83:AC83) -> 28703 | AR83: =SUM(AO83/AK83)-1 -> 0.13649466
B84: Asia Pacific | C84: 62146 | D84: 59963 | E84: 69349 | F84: 61466 | G84: 59901 | H84: 94722 | I84: 103575 | J84: 102174 | K84: 97610 | L84: =64377+33696 -> 98073 | N84: 35593 | O84: 25385 | P84: 20754 | Q84: =SUM(I84-SUM(N84:P84)) -> 21843 | R84: 33440 | S84: 25931 | T84: 21388 | U84: =SUM(J84-SUM(R84:T84)) -> 21415 | V84: 30981 | W84: 23095 | X84: 21118 | Y84: =SUM(K84-SUM(V84:X84)) -> 22416 | Z84: 28804 | AA84: 23292 | AB84: 23042 | AC84: =SUM(L84-SUM(Z84:AB84)) -> 22935 | AE84: =SUM(O84:R84) -> 101422 | AF84: =SUM(P84:S84) -> 101968 | AG84: =SUM(Q84:T84) -> 102602 | AH84: =SUM(R84:U84) -> 102174 | AI84: =SUM(S84:V84) -> 99715 | AJ84: =SUM(T84:W84) -> 96879 | AK84: =SUM(U84:X84) -> 96609 | AL84: =SUM(V84:Y84) -> 97610 | ... AP84: =SUM(Z84:AC84) -> 98073 | AR84: =SUM(AO84/AK84)-1 -> 0.0097816974
B85: Total Net Revenue | C85: =SUM(C81:C84) -> 215639 | D85: =SUM(D81:D84) -> 229234 | E85: =SUM(E81:E84) -> 265595 | F85: =SUM(F81:F84) -> 260174 | G85: =SUM(G81:G84) -> 274515 | H85: =SUM(H81:H84) -> 365817 | I85: =SUM(I81:I84) -> 394328 | J85: =SUM(J81:J84) -> 383285 | ... L85: =SUM(L81:L84) -> 416161 | N85: =SUM(N81:N84) -> 123945 | O85: =SUM(O81:O84) -> 97278 | P85: =SUM(P81:P84) -> 82959 | Q85: =SUM(Q81:Q84) -> 90146 | R85: =SUM(R81:R84) -> 117154 | S85: =SUM(S81:S84) -> 94836 | T85: =SUM(T81:T84) -> 81797 | U85: =SUM(U81:U84) -> 89498 | ... AC85: =SUM(AC81:AC84) -> 102466 | AE85: =SUM(AE81:AE83) -> 286115 | AF85: =SUM(AF81:AF83) -> 283127 | AG85: =SUM(AG81:AG83) -> 281331 | AH85: =SUM(AH81:AH83) -> 281111 | AI85: =SUM(AI81:AI83) -> 285991 | AJ85: =SUM(AJ81:AJ83) -> 284744 | AK85: =SUM(AK81:AK84) -> 385603 | AL85: =SUM(AL81:AL84) -> 391035 | AM85: =SUM(AM81:AM84) -> 395760 | AN85: =SUM(AN81:AN84) -> 400366 | AO85: =SUM(AO81:AO84) -> 408625 | AP85: =SUM(AP81:AP84) -> 416161 | AR85: =SUM(AO85/AK85)-1 -> 0.059703892
B86: Variance Check | C86: =C85-C14 -> 0 | D86: =D85-D14 -> 0 | E86: =E85-E14 -> 0 | F86: =F85-F14 -> 0 | G86: =G85-G14 -> 0 | H86: =H85-H14 -> 0 | I86: =I85-I14 -> 0 | J86: =J85-J14 -> 0 | ... L86: =L85-L14 -> 0 | N86: =N85-N14 -> 0 | O86: =O85-O14 -> 0 | P86: =P85-P14 -> 0 | Q86: =Q85-Q14 -> 0 | R86: =R85-R14 -> 0 | S86: =S85-S14 -> 0 | T86: =T85-T14 -> 0 | U86: =U85-U14 -> 0 | ... AC86: =AC85-AC14 -> 0 | AE86: =AE85-AE14 -> -101422 | AF86: =AF85-AF14 -> -101968 | AG86: =AG85-AG14 -> -102602 | AH86: =AH85-AH14 -> -102174 | AI86: =AI85-AI14 -> -99715 | AJ86: =AJ85-AJ14 -> -96879 | AK86: =AK85-AK14 -> 0 | AL86: =AL85-AL14 -> 0 | ... AP86: =AP85-AP14 -> 0
B88: Segments as a % of Total Revenue
B89: =B81&"(%)" -> Americas(%) | C89: =SUM(C81/C$85) -> 0.4016574 | D89: =SUM(D81/D$85) -> 0.42140346 | E89: =SUM(E81/E$85) -> 0.42204484 | F89: =SUM(F81/F$85) -> 0.4493685 | G89: =SUM(G81/G$85) -> 0.45373113 | H89: =SUM(H81/H$85) -> 0.41907839 | I89: =SUM(I81/I$85) -> 0.43024589 | J89: =SUM(J81/J$85) -> 0.42412304 | ... L89: =SUM(L81/L$85) -> 0.42856731 | N89: =SUM(N81/N$85) -> 0.41547461 | O89: =SUM(O81/O$85) -> 0.42025946 | P89: =SUM(P81/P$85) -> 0.451693 | Q89: =SUM(Q81/Q$85) -> 0.44159475 | R89: =SUM(R81/R$85) -> 0.42062584 | S89: =SUM(S81/S$85) -> 0.3984141 | T89: =SUM(T81/T$85) -> 0.43257088 | U89: =SUM(U81/U$85) -> 0.44822231 | ... AC89: =SUM(AC81/AC$85) -> 0.43128452 | AE89: =SUM(AE81/AE$85) -> 0.58521923 | AF89: =SUM(AF81/AF$85) -> 0.58045329 | AG89: =SUM(AG81/AG$85) -> 0.57673346 | AH89: =SUM(AH81/AH$85) -> 0.57827691 | AI89: =SUM(AI81/AI$85) -> 0.57243759 | AJ89: =SUM(AJ81/AJ$85) -> 0.57314992 | AK89: =SUM(AK81/AK$85) -> 0.42918753 | AL89: =SUM(AL81/AL$85) -> 0.42718682 | ... AP89: =SUM(AP81/AP$85) -> 0.42856731
B90: =B82&"(%)" -> Europe(%) | C90: =SUM(C82/C$85) -> 0.23164641 | D90: =SUM(D82/D$85) -> 0.23965904 | E90: =SUM(E82/E$85) -> 0.23501948 | F90: =SUM(F82/F$85) -> 0.23172185 | G90: =SUM(G82/G$85) -> 0.25004098 | H90: =SUM(H82/H$85) -> 0.24413026 | I90: =SUM(I82/I$85) -> 0.24121543 | J90: =SUM(J82/J$85) -> 0.24601537 | ... L90: =SUM(L82/L$85) -> 0.26680059 | N90: =SUM(N82/N$85) -> 0.24001775 | O90: =SUM(O82/O$85) -> 0.23938609 | P90: =SUM(P82/P$85) -> 0.23248834 | Q90: =SUM(Q82/Q$85) -> 0.25286757 | R90: =SUM(R82/R$85) -> 0.23627874 | S90: =SUM(S82/S$85) -> 0.25248851 | T90: =SUM(T82/T$85) -> 0.24701395 | U90: =SUM(U82/U$85) -> 0.25098885 | ... AC90: =SUM(AC82/AC$85) -> 0.28012219 | AE90: =SUM(AE82/AE$85) -> 0.32521888 | AF90: =SUM(AF82/AF$85) -> 0.33097515 | AG90: =SUM(AG82/AG$85) -> 0.33635113 | AH90: =SUM(AH82/AH$85) -> 0.33543333 | AI90: =SUM(AI82/AI$85) -> 0.33920648 | AJ90: =SUM(AJ82/AJ$85) -> 0.34131711 | AK90: =SUM(AK82/AK$85) -> 0.25639583 | AL90: =SUM(AL82/AL$85) -> 0.2591277 | ... AP90: =SUM(AP82/AP$85) -> 0.26680059
B91: =B83&"(%)" -> Japan(%) | C91: =SUM(C83/C$85) -> 0.07850157 | D91: =SUM(D83/D$85) -> 0.077357635 | E91: =SUM(E83/E$85) -> 0.081827595 | F91: =SUM(F83/F$85) -> 0.082660066 | G91: =SUM(G83/G$85) -> 0.078021237 | H91: =SUM(H83/H$85) -> 0.077858601 | I91: =SUM(I83/I$85) -> 0.065876631 | J91: =SUM(J83/J$85) -> 0.06328711 | ... L91: =SUM(L83/L$85) -> 0.068970903 | N91: =SUM(N83/N$85) -> 0.057339949 | O91: =SUM(O83/O$85) -> 0.079401303 | P91: =SUM(P83/P$85) -> 0.065646886 | Q91: =SUM(Q83/Q$85) -> 0.063230759 | R91: =SUM(R83/R$85) -> 0.057659149 | S91: =SUM(S83/S$85) -> 0.075667468 | T91: =SUM(T83/T$85) -> 0.058938592 | U91: =SUM(U83/U$85) -> 0.061509754 | ... AC91: =SUM(AC83/AC$85) -> 0.064762946 | AE91: =SUM(AE83/AE$85) -> 0.089561889 | AF91: =SUM(AF83/AF$85) -> 0.08857156 | AG91: =SUM(AG83/AG$85) -> 0.086915413 | AH91: =SUM(AH83/AH$85) -> 0.086289757 | AI91: =SUM(AI83/AI$85) -> 0.088355927 | AJ91: =SUM(AJ83/AJ$85) -> 0.08553297 | AK91: =SUM(AK83/AK$85) -> 0.063876578 | AL91: =SUM(AL83/AL$85) -> 0.064065876 | ... AP91: =SUM(AP83/AP$85) -> 0.068970903
B92: =B84&"(%)" -> Asia Pacific(%) | C92: =SUM(C84/C$85) -> 0.28819462 | D92: =SUM(D84/D$85) -> 0.26157987 | E92: =SUM(E84/E$85) -> 0.26110808 | F92: =SUM(F84/F$85) -> 0.23624959 | G92: =SUM(G84/G$85) -> 0.21820666 | H92: =SUM(H84/H$85) -> 0.25893275 | I92: =SUM(I84/I$85) -> 0.26266205 | J92: =SUM(J84/J$85) -> 0.26657448 | ... L92: =SUM(L84/L$85) -> 0.2356612 | N92: =SUM(N84/N$85) -> 0.2871677 | O92: =SUM(O84/O$85) -> 0.26095314 | P92: =SUM(P84/P$85) -> 0.25017177 | Q92: =SUM(Q84/Q$85) -> 0.24230692 | R92: =SUM(R84/R$85) -> 0.28543626 | S92: =SUM(S84/S$85) -> 0.27342992 | T92: =SUM(T84/T$85) -> 0.26147658 | U92: =SUM(U84/U$85) -> 0.23927909 | ... AC92: =SUM(AC84/AC$85) -> 0.22383034 | AE92: =SUM(AE84/AE$85) -> 0.35447984 | AF92: =SUM(AF84/AF$85) -> 0.36014933 | AG92: =SUM(AG84/AG$85) -> 0.36470208 | AH92: =SUM(AH84/AH$85) -> 0.36346497 | AI92: =SUM(AI84/AI$85) -> 0.34866482 | AJ92: =SUM(AJ84/AJ$85) -> 0.34023193 | AK92: =SUM(AK84/AK$85) -> 0.25054006 | AL92: =SUM(AL84/AL$85) -> 0.2496196 | ... AP92: =SUM(AP84/AP$85) -> 0.2356612
B93: Y/Y Growth Rates (%)
B94: =B81&"(%)" -> Americas(%) | C94: N/A | D94: =SUM(D81/C81)-1 -> 0.11530602 | E94: =SUM(E81/D81)-1 -> 0.16038302 | F94: =SUM(F81/E81)-1 -> 0.04300893 | G94: =SUM(G81/F81)-1 -> 0.065364285 | H94: =SUM(H81/G81)-1 -> 0.23081987 | I94: =SUM(I81/H81)-1 -> 0.10666249 | J94: =SUM(J81/I81)-1 -> -0.041837108 | K94: =SUM(K81/J81)-1 -> 0.027589813 | L94: =SUM(L81/K81)-1 -> 0.067694334 | N94: N/A | O94: N/A | P94: N/A | Q94: N/A | R94: =SUM(R81/N81)-1 -> -0.043071307 | S94: =SUM(S81/R81)-1 -> -0.2332481 | T94: =SUM(T81/S81)-1 -> -0.063545416 | U94: =SUM(U81/T81)-1 -> 0.13373654 | V94: =SUM(V81/U81)-1 -> 0.25713573 | W94: =SUM(W81/V81)-1 -> -0.26089629 | X94: =SUM(X81/W81)-1 -> 0.010865774 | Y94: =SUM(Y81/X81)-1 -> 0.10579118 | Z94: =SUM(Z81/Y81)-1 -> 0.26363287 | ... AC94: =SUM(AC81/AB81)-1 -> 0.072673431 | AE94: N/A | AF94: N/A | AG94: N/A | AH94: N/A | AI94: =SUM(AI81/AE81)-1 -> -0.022264692 | AJ94: =SUM(AJ81/AF81)-1 -> -0.0069428387 | AK94: =SUM(AK81/AG81)-1 -> 0.019987304 | AL94: =SUM(AL81/AH81)-1 -> 0.027589813 | AM94: =SUM(AM81/AI81)-1 -> 0.033907105 | AN94: =SUM(AN81/AJ81)-1 -> 0.055783972 | AO94: =SUM(AO81/AK81)-1 -> 0.062412385 | AP94: =SUM(AP81/AL81)-1 -> 0.067694334
B95: =B82&"(%)" -> Europe(%) | C95: N/A | D95: =SUM(D82/C82)-1 -> 0.099815823 | E95: =SUM(E82/D82)-1 -> 0.13618989 | F95: =SUM(F82/E82)-1 -> -0.034155719 | G95: =SUM(G82/F82)-1 -> 0.13853503 | H95: =SUM(H82/G82)-1 -> 0.30109266 | I95: =SUM(I82/H82)-1 -> 0.065067688 | J95: =SUM(J82/I82)-1 -> -0.0086629239 | K95: =SUM(K82/J82)-1 -> 0.074596475 | L95: =SUM(L82/K82)-1 -> 0.095768198 | N95: N/A | O95: N/A | P95: N/A | Q95: N/A | R95: =SUM(R82/N82)-1 -> -0.069514942 | S95: =SUM(S82/R82)-1 -> -0.13496622 | T95: =SUM(T82/S82)-1 -> -0.15619127 | U95: =SUM(U82/T82)-1 -> 0.11175452 | V95: =SUM(V82/U82)-1 -> 0.35320305 | W95: =SUM(W82/V82)-1 -> -0.20640195 | X95: =SUM(X82/W82)-1 -> -0.092815985 | Y95: =SUM(Y82/X82)-1 -> 0.13891428 | Z95: =SUM(Z82/Y82)-1 -> 0.35857005 | ... AC95: =SUM(AC82/AB82)-1 -> 0.1952611 | AE95: N/A | AF95: N/A | AG95: N/A | AH95: N/A | AI95: =SUM(AI82/AE82)-1 -> 0.042557765 | AJ95: =SUM(AJ82/AF82)-1 -> 0.037136637 | AK95: =SUM(AK82/AG82)-1 -> 0.044818549 | AL95: =SUM(AL82/AH82)-1 -> 0.074596475 | AM95: =SUM(AM82/AI82)-1 -> 0.080218534 | AN95: =SUM(AN82/AJ82)-1 -> 0.081645882 | AO95: =SUM(AO82/AK82)-1 -> 0.084821022 | AP95: =SUM(AP82/AL82)-1 -> 0.095768198
B96: =B83&"(%)" -> Japan(%) | C96: N/A | D96: =SUM(D83/C83)-1 -> 0.047554348 | E96: =SUM(E83/D83)-1 -> 0.22556815 | F96: =SUM(F83/E83)-1 -> -0.010444945 | G96: =SUM(G83/F83)-1 -> -0.0040918813 | H96: =SUM(H83/G83)-1 -> 0.32981604 | I96: =SUM(I83/H83)-1 -> -0.087950284 | J96: =SUM(J83/I83)-1 -> -0.066212419 | K96: =SUM(K83/J83)-1 -> 0.032774045 | L96: =SUM(L83/K83)-1 -> 0.14573687 | N96: N/A | O96: N/A | P96: N/A | Q96: N/A | R96: =SUM(R83/N83)-1 -> -0.049528634 | S96: =SUM(S83/R83)-1 -> 0.062324204 | T96: =SUM(T83/S83)-1 -> -0.32817726 | U96: =SUM(U83/T83)-1 -> 0.14187928 | V96: =SUM(V83/U83)-1 -> 0.41089918 | W96: =SUM(W83/V83)-1 -> -0.19376851 | X96: =SUM(X83/W83)-1 -> -0.1860428 | Y96: =SUM(Y83/X83)-1 -> 0.16264469 | Z96: =SUM(Z83/Y83)-1 -> 0.51653729 | ... AC96: =SUM(AC83/AB83)-1 -> 0.14769976 | AE96: N/A | AF96: N/A | AG96: N/A | AH96: N/A | AI96: =SUM(AI83/AE83)-1 -> -0.013892683 | AJ96: =SUM(AJ83/AF83)-1 -> -0.028791323 | AK96: =SUM(AK83/AG83)-1 -> 0.0073204646 | AL96: =SUM(AL83/AH83)-1 -> 0.032774045 | AM96: =SUM(AM83/AI83)-1 -> 0.039692904 | AN96: =SUM(AN83/AJ83)-1 -> 0.1212482 | AO96: =SUM(AO83/AK83)-1 -> 0.13649466 | AP96: =SUM(AP83/AL83)-1 -> 0.14573687
B97: =B84&"(%)" -> Asia Pacific(%) | C97: N/A | D97: =SUM(D84/C84)-1 -> -0.035126959 | E97: =SUM(E84/D84)-1 -> 0.15652986 | F97: =SUM(F84/E84)-1 -> -0.11367143 | G97: =SUM(G84/F84)-1 -> -0.025461231 | H97: =SUM(H84/G84)-1 -> 0.58130916 | I97: =SUM(I84/H84)-1 -> 0.093462976 | J97: =SUM(J84/I84)-1 -> -0.01352643 | K97: =SUM(K84/J84)-1 -> -0.044668898 | L97: =SUM(L84/K84)-1 -> 0.0047433665 | N97: N/A | O97: N/A | P97: N/A | Q97: N/A | R97: =SUM(R84/N84)-1 -> -0.060489422 | S97: =SUM(S84/R84)-1 -> -0.22455144 | T97: =SUM(T84/S84)-1 -> -0.17519571 | U97: =SUM(U84/T84)-1 -> 0.0012623901 | V97: =SUM(V84/U84)-1 -> 0.44669624 | W97: =SUM(W84/V84)-1 -> -0.25454311 | X97: =SUM(X84/W84)-1 -> -0.085602944 | Y97: =SUM(Y84/X84)-1 -> 0.061464154 | Z97: =SUM(Z84/Y84)-1 -> 0.28497502 | ... AC97: =SUM(AC84/AB84)-1 -> -0.0046436941 | AE97: N/A | AF97: N/A | AG97: N/A | AH97: N/A | AI97: =SUM(AI84/AE84)-1 -> -0.016830668 | AJ97: =SUM(AJ84/AF84)-1 -> -0.049907814 | AK97: =SUM(AK84/AG84)-1 -> -0.058410167 | AL97: =SUM(AL84/AH84)-1 -> -0.044668898 | AM97: =SUM(AM84/AI84)-1 -> -0.042942386 | AN97: =SUM(AN84/AJ84)-1 -> -0.012892371 | AO97: =SUM(AO84/AK84)-1 -> 0.0097816974 | AP97: =SUM(AP84/AL84)-1 -> 0.0047433665
B98: Q/Q Growth Rates (%)
B99: =B81&"(%)" -> Americas(%) | C99: N/A | D99: N/A | E99: N/A | F99: N/A | G99: N/A | H99: N/A | I99: N/A | J99: N/A | K99: N/A | L99: N/A | N99: N/A | O99: =SUM(O81/N81)-1 -> -0.2061131 | P99: =SUM(P81/O81)-1 -> -0.083410792 | Q99: =SUM(Q81/P81)-1 -> 0.06233988 | R99: =SUM(R81/Q81)-1 -> 0.23789188 | S99: =SUM(S81/R81)-1 -> -0.2332481 | T99: =SUM(T81/S81)-1 -> -0.063545416 | U99: =SUM(U81/T81)-1 -> 0.13373654 | V99: =SUM(V81/U81)-1 -> 0.25713573 | ... AC99: =SUM(AC81/AB81)-1 -> 0.072673431 | AE99: N/A | AF99: N/A | AG99: N/A | AH99: N/A | AI99: N/A | AJ99: N/A | AK99: N/A | AL99: N/A | AM99: N/A | AN99: N/A | AO99: N/A | AP99: N/A
B100: =B82&"(%)" -> Europe(%) | C100: N/A | D100: N/A | E100: N/A | F100: N/A | G100: N/A | H100: N/A | I100: N/A | J100: N/A | K100: N/A | L100: N/A | N100: N/A | O100: =SUM(O82/N82)-1 -> -0.21721739 | P100: =SUM(P82/O82)-1 -> -0.17176966 | Q100: =SUM(Q82/P82)-1 -> 0.18188417 | R100: =SUM(R82/Q82)-1 -> 0.21434525 | S100: =SUM(S82/R82)-1 -> -0.13496622 | T100: =SUM(T82/S82)-1 -> -0.15619127 | U100: =SUM(U82/T82)-1 -> 0.11175452 | V100: =SUM(V82/U82)-1 -> 0.35320305 | ... AC100: =SUM(AC82/AB82)-1 -> 0.1952611 | AE100: N/A | AF100: N/A | AG100: N/A | AH100: N/A | AI100: N/A | AJ100: N/A | AK100: N/A | AL100: N/A | AM100: N/A | AN100: N/A | AO100: N/A | AP100: N/A
B101: =B83&"(%)" -> Japan(%) | C101: N/A | D101: N/A | E101: N/A | F101: N/A | G101: N/A | H101: N/A | I101: N/A | J101: N/A | K101: N/A | L101: N/A | N101: N/A | O101: =SUM(O83/N83)-1 -> 0.086815815 | P101: =SUM(P83/O83)-1 -> -0.29492491 | Q101: =SUM(Q83/P83)-1 -> 0.046639736 | R101: =SUM(R83/Q83)-1 -> 0.18508772 | S101: =SUM(S83/R83)-1 -> 0.062324204 | T101: =SUM(T83/S83)-1 -> -0.32817726 | U101: =SUM(U83/T83)-1 -> 0.14187928 | V101: =SUM(V83/U83)-1 -> 0.41089918 | ... AC101: =SUM(AC83/AB83)-1 -> 0.14769976 | AE101: N/A | AF101: N/A | AG101: N/A | AH101: N/A | AI101: N/A | AJ101: N/A | AK101: N/A | AL101: N/A | AM101: N/A | AN101: N/A | AO101: N/A | AP101: N/A
B102: =B84&"(%)" -> Asia Pacific(%) | C102: N/A | D102: N/A | E102: N/A | F102: N/A | G102: N/A | H102: N/A | I102: N/A | J102: N/A | K102: N/A | L102: N/A | N102: N/A | O102: =SUM(O84/N84)-1 -> -0.28679797 | P102: =SUM(P84/O84)-1 -> -0.18243057 | Q102: =SUM(Q84/P84)-1 -> 0.052471813 | R102: =SUM(R84/Q84)-1 -> 0.53092524 | S102: =SUM(S84/R84)-1 -> -0.22455144 | T102: =SUM(T84/S84)-1 -> -0.17519571 | U102: =SUM(U84/T84)-1 -> 0.0012623901 | V102: =SUM(V84/U84)-1 -> 0.44669624 | ... AC102: =SUM(AC84/AB84)-1 -> -0.0046436941 | AE102: N/A | AF102: N/A | AG102: N/A | AH102: N/A | AI102: N/A | AJ102: N/A | AK102: N/A | AL102: N/A | AM102: N/A | AN102: N/A | AO102: N/A | AP102: N/A

Sheet Balance Sheet Drivers
B2: Apple Inc. (NASDAQ: AAPL) | C2: FYE | F2: FYE | N2: Quarterly | T2: Quarterly | W2: Quarterly | X2: Quarterly | AK2: LTM | AQ2: Variance
B3: Balance Sheet Drivers | C3: ='Historical Financials'!C7 -> 2016 | D3: ='Historical Financials'!D7 -> 2017 | E3: ='Historical Financials'!E7 -> 2018 | F3: ='Historical Financials'!F7 -> 2019 | G3: ='Historical Financials'!G7 -> 2020 | H3: ='Historical Financials'!H7 -> 2021 | I3: ='Historical Financials'!I7 -> 2022 | J3: ='Historical Financials'!J7 -> 2023 | ... L3: ='Historical Financials'!L7 -> 2025 | N3: ='Historical Financials'!N7 -> 1Q22 | O3: ='Historical Financials'!O7 -> 2Q22 | P3: ='Historical Financials'!P7 -> 3Q22 | Q3: ='Historical Financials'!Q7 -> 4Q22 | R3: ='Historical Financials'!R7 -> 1Q23 | S3: ='Historical Financials'!S7 -> 2Q23 | T3: ='Historical Financials'!T7 -> 3Q23 | U3: ='Historical Financials'!U7 -> 4Q23 | ... AC3: ='Historical Financials'!AC7 -> 4Q25 | AE3: =R3 -> 1Q23 | AF3: =S3 -> 2Q23 | AG3: =T3 -> 3Q23 | AH3: =U3 -> 4Q23 | AI3: =V3 -> 1Q24 | AJ3: =W3 -> 2Q24 | AK3: =X3 -> 3Q24 | AL3: =Y3 -> 4Q24 | ... AP3: =AC3 -> 4Q25
B4: ($ in Millions) | C4: ='Historical Financials'!C8 -> 42643 | D4: ='Historical Financials'!D8 -> 43008 | E4: ='Historical Financials'!E8 -> 43372 | F4: ='Historical Financials'!F8 -> 43737 | G4: ='Historical Financials'!G8 -> 44104 | H4: ='Historical Financials'!H8 -> 44469 | I4: ='Historical Financials'!I8 -> 44834 | J4: ='Historical Financials'!J8 -> 45192 | ... L4: ='Historical Financials'!L8 -> 45927 | N4: ='Historical Financials'!N8 -> 44560 | O4: ='Historical Financials'!O8 -> 44650 | P4: ='Historical Financials'!P8 -> 44742 | Q4: ='Historical Financials'!Q8 -> 44834 | R4: ='Historical Financials'!R8 -> 44917 | S4: ='Historical Financials'!S8 -> 45008 | T4: ='Historical Financials'!T8 -> 45100 | U4: ='Historical Financials'!U8 -> 45192 | ... AC4: ='Historical Financials'!AC8 -> 45927 | AE4: =R4 -> 44917 | AF4: =S4 -> 45008 | AG4: =T4 -> 45100 | AH4: =U4 -> 45192 | AI4: =V4 -> 45283 | AJ4: =W4 -> 45375 | AK4: =X4 -> 45467 | AL4: =Y4 -> 45559 | ... AP4: =AC4 -> 45927
A6: X | B6: Working Capital
B8: Accounts Receivable | C8: ='Historical Financials'!C41 -> 15754 | D8: ='Historical Financials'!D41 -> 17874 | E8: ='Historical Financials'!E41 -> 23186 | F8: ='Historical Financials'!F41 -> 22926 | G8: ='Historical Financials'!G41 -> 16120 | H8: ='Historical Financials'!H41 -> 26278 | I8: ='Historical Financials'!I41 -> 28184 | J8: ='Historical Financials'!J41 -> 29508 | ... L8: ='Historical Financials'!L41 -> 39777 | N8: ='Historical Financials'!N41 -> 30213 | O8: ='Historical Financials'!O41 -> 20815 | P8: ='Historical Financials'!P41 -> 21803 | Q8: ='Historical Financials'!Q41 -> 28184 | R8: ='Historical Financials'!R41 -> 23752 | S8: ='Historical Financials'!S41 -> 17936 | T8: ='Historical Financials'!T41 -> 19549 | U8: ='Historical Financials'!U41 -> 29508 | ... AC8: ='Historical Financials'!AC41 -> 39777 | AE8: ='Historical Financials'!AE41 -> 23752 | AF8: ='Historical Financials'!AF41 -> 17936 | AG8: ='Historical Financials'!AG41 -> 19549 | AH8: ='Historical Financials'!AH41 -> 29508 | AI8: ='Historical Financials'!AI41 -> 23194 | AJ8: ='Historical Financials'!AJ41 -> 21837 | AK8: ='Historical Financials'!AK41 -> 22795 | AL8: ='Historical Financials'!AL41 -> 66243 | ... AP8: ='Historical Financials'!AP41 -> 39777
B9: Inventory | C9: ='Historical Financials'!C42 -> 2132 | D9: ='Historical Financials'!D42 -> 4855 | E9: ='Historical Financials'!E42 -> 3956 | F9: ='Historical Financials'!F42 -> 4106 | G9: ='Historical Financials'!G42 -> 4061 | H9: ='Historical Financials'!H42 -> 6580 | I9: ='Historical Financials'!I42 -> 4946 | J9: ='Historical Financials'!J42 -> 6331 | ... L9: ='Historical Financials'!L42 -> 5718 | N9: ='Historical Financials'!N42 -> 5876 | O9: ='Historical Financials'!O42 -> 5460 | P9: ='Historical Financials'!P42 -> 5433 | Q9: ='Historical Financials'!Q42 -> 4946 | R9: ='Historical Financials'!R42 -> 6820 | S9: ='Historical Financials'!S42 -> 7482 | T9: ='Historical Financials'!T42 -> 7351 | U9: ='Historical Financials'!U42 -> 6331 | ... AC9: ='Historical Financials'!AC42 -> 5718 | AE9: ='Historical Financials'!AE42 -> 6820 | AF9: ='Historical Financials'!AF42 -> 7482 | AG9: ='Historical Financials'!AG42 -> 7351 | AH9: ='Historical Financials'!AH42 -> 6331 | AI9: ='Historical Financials'!AI42 -> 6511 | AJ9: ='Historical Financials'!AJ42 -> 6232 | AK9: ='Historical Financials'!AK42 -> 6165 | AL9: ='Historical Financials'!AL42 -> 7286 | ... AP9: ='Historical Financials'!AP42 -> 5718
B10: Other Current Assets | C10: ='Historical Financials'!C43 -> 21828 | D10: ='Historical Financials'!D43 -> 31735 | E10: ='Historical Financials'!E43 -> 37896 | F10: ='Historical Financials'!F43 -> 35230 | G10: ='Historical Financials'!G43 -> 32589 | H10: ='Historical Financials'!H43 -> 39339 | I10: ='Historical Financials'!I43 -> 53971 | J10: ='Historical Financials'!J43 -> 46172 | ... L10: ='Historical Financials'!L43 -> 47765 | N10: ='Historical Financials'!N43 -> 53152 | O10: ='Historical Financials'!O43 -> 40394 | P10: ='Historical Financials'!P43 -> 36825 | Q10: ='Historical Financials'!Q43 -> 53971 | R10: ='Historical Financials'!R43 -> 46850 | S10: ='Historical Financials'!S43 -> 31623 | T10: ='Historical Financials'!T43 -> 33277 | U10: ='Historical Financials'!U43 -> 46172 | ... AC10: ='Historical Financials'!AC43 -> 47765 | AE10: ='Historical Financials'!AE43 -> 46850 | AF10: ='Historical Financials'!AF43 -> 31623 | AG10: ='Historical Financials'!AG43 -> 33277 | AH10: ='Historical Financials'!AH43 -> 46172 | AI10: ='Historical Financials'!AI43 -> 40887 | AJ10: ='Historical Financials'!AJ43 -> 33197 | AK10: ='Historical Financials'!AK43 -> 34674 | AL10: ='Historical Financials'!AL43 -> 14287 | ... AP10: ='Historical Financials'!AP43 -> 47765
B11: Total Current Assets | C11: =SUM(C8:C10) -> 39714 | D11: =SUM(D8:D10) -> 54464 | E11: =SUM(E8:E10) -> 65038 | F11: =SUM(F8:F10) -> 62262 | G11: =SUM(G8:G10) -> 52770 | H11: =SUM(H8:H10) -> 72197 | I11: =SUM(I8:I10) -> 87101 | J11: =SUM(J8:J10) -> 82011 | ... L11: =SUM(L8:L10) -> 93260 | N11: =SUM(N8:N10) -> 89241 | O11: =SUM(O8:O10) -> 66669 | P11: =SUM(P8:P10) -> 64061 | Q11: =SUM(Q8:Q10) -> 87101 | R11: =SUM(R8:R10) -> 77422 | S11: =SUM(S8:S10) -> 57041 | T11: =SUM(T8:T10) -> 60177 | U11: =SUM(U8:U10) -> 82011 | ... AC11: =SUM(AC8:AC10) -> 93260 | AE11: =SUM(AE8:AE10) -> 77422 | AF11: =SUM(AF8:AF10) -> 57041 | AG11: =SUM(AG8:AG10) -> 60177 | AH11: =SUM(AH8:AH10) -> 82011 | AI11: =SUM(AI8:AI10) -> 70592 | AJ11: =SUM(AJ8:AJ10) -> 61266 | AK11: =SUM(AK8:AK10) -> 63634 | AL11: =SUM(AL8:AL10) -> 87816 | ... AP11: =SUM(AP8:AP10) -> 93260
B13: Accounts Payable | C13: ='Historical Financials'!C51 -> 37294 | D13: ='Historical Financials'!D51 -> 44242 | E13: ='Historical Financials'!E51 -> 55888 | F13: ='Historical Financials'!F51 -> 46236 | G13: ='Historical Financials'!G51 -> 42296 | H13: ='Historical Financials'!H51 -> 54763 | I13: ='Historical Financials'!I51 -> 64115 | J13: ='Historical Financials'!J51 -> 62611 | ... L13: ='Historical Financials'!L51 -> 69860 | N13: ='Historical Financials'!N51 -> 74362 | O13: ='Historical Financials'!O51 -> 52682 | P13: ='Historical Financials'!P51 -> 48343 | Q13: ='Historical Financials'!Q51 -> 64115 | R13: ='Historical Financials'!R51 -> 57918 | S13: ='Historical Financials'!S51 -> 42945 | T13: ='Historical Financials'!T51 -> 46699 | U13: ='Historical Financials'!U51 -> 62611 | ... AC13: ='Historical Financials'!AC51 -> 69860 | AE13: ='Historical Financials'!AE51 -> 57918 | AF13: ='Historical Financials'!AF51 -> 42945 | AG13: ='Historical Financials'!AG51 -> 46699 | AH13: ='Historical Financials'!AH51 -> 62611 | AI13: ='Historical Financials'!AI51 -> 58146 | AJ13: ='Historical Financials'!AJ51 -> 45753 | AK13: ='Historical Financials'!AK51 -> 47574 | AL13: ='Historical Financials'!AL51 -> 68960 | ... AP13: ='Historical Financials'!AP51 -> 69860
B14: Deferred Revenue | C14: ='Historical Financials'!C52 -> 8080 | D14: ='Historical Financials'!D52 -> 7548 | E14: ='Historical Financials'!E52 -> 7543 | F14: ='Historical Financials'!F52 -> 5522 | G14: ='Historical Financials'!G52 -> 6643 | H14: ='Historical Financials'!H52 -> 7612 | I14: ='Historical Financials'!I52 -> 7912 | J14: ='Historical Financials'!J52 -> 8061 | ... L14: ='Historical Financials'!L52 -> 9055 | N14: ='Historical Financials'!N52 -> 7876 | O14: ='Historical Financials'!O52 -> 7920 | P14: ='Historical Financials'!P52 -> 7728 | Q14: ='Historical Financials'!Q52 -> 7912 | R14: ='Historical Financials'!R52 -> 7992 | S14: ='Historical Financials'!S52 -> 8131 | T14: ='Historical Financials'!T52 -> 8158 | U14: ='Historical Financials'!U52 -> 8061 | ... AC14: ='Historical Financials'!AC52 -> 9055 | AE14: ='Historical Financials'!AE52 -> 7992 | AF14: ='Historical Financials'!AF52 -> 8131 | AG14: ='Historical Financials'!AG52 -> 8158 | AH14: ='Historical Financials'!AH52 -> 8061 | AI14: ='Historical Financials'!AI52 -> 8264 | AJ14: ='Historical Financials'!AJ52 -> 8012 | AK14: ='Historical Financials'!AK52 -> 8053 | AL14: ='Historical Financials'!AL52 -> 8249 | ... AP14: ='Historical Financials'!AP52 -> 9055
B15: Other Current Liabilities | C15: ='Historical Financials'!C53 -> 22027 | D15: ='Historical Financials'!D53 -> 30551 | E15: ='Historical Financials'!E53 -> 32687 | F15: ='Historical Financials'!F53 -> 37720 | G15: ='Historical Financials'!G53 -> 42684 | H15: ='Historical Financials'!H53 -> 47493 | I15: ='Historical Financials'!I53 -> 60845 | J15: ='Historical Financials'!J53 -> 58829 | ... L15: ='Historical Financials'!L53 -> 66387 | N15: ='Historical Financials'!N53 -> 49167 | O15: ='Historical Financials'!O53 -> 50248 | P15: ='Historical Financials'!P53 -> 48811 | Q15: ='Historical Financials'!Q53 -> 60845 | R15: ='Historical Financials'!R53 -> 59893 | S15: ='Historical Financials'!S53 -> 56425 | T15: ='Historical Financials'!T53 -> 58897 | U15: ='Historical Financials'!U53 -> 58829 | ... AC15: ='Historical Financials'!AC53 -> 66387 | AE15: ='Historical Financials'!AE53 -> 59893 | AF15: ='Historical Financials'!AF53 -> 56425 | AG15: ='Historical Financials'!AG53 -> 58897 | AH15: ='Historical Financials'!AH53 -> 58829 | AI15: ='Historical Financials'!AI53 -> 54611 | AJ15: ='Historical Financials'!AJ53 -> 57298 | AK15: ='Historical Financials'!AK53 -> 60889 | AL15: ='Historical Financials'!AL53 -> 78304 | ... AP15: ='Historical Financials'!AP53 -> 66387
B16: Total Current Liabilities | C16: =SUM(C13:C15) -> 67401 | D16: =SUM(D13:D15) -> 82341 | E16: =SUM(E13:E15) -> 96118 | F16: =SUM(F13:F15) -> 89478 | G16: =SUM(G13:G15) -> 91623 | H16: =SUM(H13:H15) -> 109868 | I16: =SUM(I13:I15) -> 132872 | J16: =SUM(J13:J15) -> 129501 | ... L16: =SUM(L13:L15) -> 145302 | N16: =SUM(N13:N15) -> 131405 | O16: =SUM(O13:O15) -> 110850 | P16: =SUM(P13:P15) -> 104882 | Q16: =SUM(Q13:Q15) -> 132872 | R16: =SUM(R13:R15) -> 125803 | S16: =SUM(S13:S15) -> 107501 | T16: =SUM(T13:T15) -> 113754 | U16: =SUM(U13:U15) -> 129501 | ... AC16: =SUM(AC13:AC15) -> 145302 | AE16: =SUM(AE13:AE15) -> 125803 | AF16: =SUM(AF13:AF15) -> 107501 | AG16: =SUM(AG13:AG15) -> 113754 | AH16: =SUM(AH13:AH15) -> 129501 | AI16: =SUM(AI13:AI15) -> 121021 | AJ16: =SUM(AJ13:AJ15) -> 111063 | AK16: =SUM(AK13:AK15) -> 116516 | AL16: =SUM(AL13:AL15) -> 155513 | ... AP16: =SUM(AP13:AP15) -> 145302
B18: Net Working capital | C18: =C11-C16 -> -27687 | D18: =D11-D16 -> -27877 | E18: =E11-E16 -> -31080 | F18: =F11-F16 -> -27216 | G18: =G11-G16 -> -38853 | H18: =H11-H16 -> -37671 | I18: =I11-I16 -> -45771 | J18: =J11-J16 -> -47490 | ... L18: =L11-L16 -> -52042 | N18: =N11-N16 -> -42164 | O18: =O11-O16 -> -44181 | P18: =P11-P16 -> -40821 | Q18: =Q11-Q16 -> -45771 | R18: =R11-R16 -> -48381 | S18: =S11-S16 -> -50460 | T18: =T11-T16 -> -53577 | U18: =U11-U16 -> -47490 | ... AC18: =AC11-AC16 -> -52042 | AE18: =AE11-AE16 -> -48381 | AF18: =AF11-AF16 -> -50460 | AG18: =AG11-AG16 -> -53577 | AH18: =AH11-AH16 -> -47490 | AI18: =AI11-AI16 -> -50429 | AJ18: =AJ11-AJ16 -> -49797 | AK18: =AK11-AK16 -> -52882 | AL18: =AL11-AL16 -> -67697 | ... AP18: =AP11-AP16 -> -52042
B19: Changes in working capital | C19: N/A | D19: =SUM(D18-C18) -> -190 | E19: =SUM(E18-D18) -> -3203 | F19: =SUM(F18-E18) -> 3864 | G19: =SUM(G18-F18) -> -11637 | H19: =SUM(H18-G18) -> 1182 | I19: =SUM(I18-H18) -> -8100 | J19: =SUM(J18-I18) -> -1719 | K19: =SUM(K18-J18) -> -20207 | L19: =SUM(L18-K18) -> 15655 | N19: N/A | O19: =SUM(O18-N18) -> -2017 | P19: =SUM(P18-O18) -> 3360 | Q19: =SUM(Q18-P18) -> -4950 | R19: =SUM(R18-Q18) -> -2610 | S19: =SUM(S18-R18) -> -2079 | T19: =SUM(T18-S18) -> -3117 | U19: =SUM(U18-T18) -> 6087 | V19: =SUM(V18-U18) -> -2939 | ... AC19: =SUM(AC18-AB18) -> 2691 | AE19: N/A | AF19: =SUM(AF18-AE18) -> -2079 | AG19: =SUM(AG18-AF18) -> -3117 | AH19: =SUM(AH18-AG18) -> 6087 | AI19: =SUM(AI18-AH18) -> -2939 | AJ19: =SUM(AJ18-AI18) -> 632 | AK19: =SUM(AK18-AJ18) -> -3085 | AL19: =SUM(AL18-AK18) -> -14815 | AM19: =SUM(AM18-AL18) -> 15640 | ... AP19: =SUM(AP18-AO18) -> 2691
B21: Cash Conversion Cycle (CCC)
B22: Days Sales Outstanding (DSO) | C22: N/A | D22: {=AVERAGE(C8:D8/'Historical Financials'!D10)*360} -> 26.405507 | E22: {=AVERAGE(D8:E8/'Historical Financials'!E10)*360} -> 27.827331 | F22: {=AVERAGE(E8:F8/'Historical Financials'!F10)*360} -> 31.902342 | G22: {=AVERAGE(F8:G8/'Historical Financials'!G10)*360} -> 25.602535 | H22: {=AVERAGE(G8:H8/'Historical Financials'!H10)*360} -> 20.861906 | I22: {=AVERAGE(H8:I8/'Historical Financials'!I10)*360} -> 24.860421 | J22: {=AVERAGE(I8:J8/'Historical Financials'!J10)*360} -> 27.093573 | K22: {=AVERAGE(J8:K8/'Historical Financials'!K10)*360} -> 44.075799 | L22: {=AVERAGE(K8:L8/'Historical Financials'!L10)*360} -> 45.856291 | N22: N/A | O22: {=AVERAGE(N8:O8/('Historical Financials'!O10*4)*360)} -> 23.605132 | P22: {=AVERAGE(O8:P8/('Historical Financials'!P10*4)*360)} -> 23.117564 | Q22: {=AVERAGE(P8:Q8/('Historical Financials'!Q10*4)*360)} -> 24.953021 | R22: {=AVERAGE(Q8:R8/('Historical Financials'!R10*4)*360)} -> 19.949127 | S22: {=AVERAGE(R8:S8/('Historical Financials'!S10*4)*360)} -> 19.781096 | T22: {=AVERAGE(S8:T8/('Historical Financials'!T10*4)*360)} -> 20.622089 | U22: {=AVERAGE(T8:U8/('Historical Financials'!U10*4)*360)} -> 24.666082 | V22: {=AVERAGE(U8:V8/('Historical Financials'!V10*4)*360)} -> 19.833494 | ... AC22: {=AVERAGE(AB8:AC8/('Historical Financials'!AC10*4)*360)} -> 38.037398 | AE22: N/A | AF22: {=AVERAGE(AE8:AF8/'Historical Financials'!AF10)*360} -> 19.485685 | AG22: {=AVERAGE(AF8:AG8/'Historical Financials'!AG10)*360} -> 17.57416 | AH22: {=AVERAGE(AG8:AH8/'Historical Financials'!AH10)*360} -> 23.038366 | AI22: {=AVERAGE(AH8:AI8/'Historical Financials'!AI10)*360} -> 24.594795 | AJ22: {=AVERAGE(AI8:AJ8/'Historical Financials'!AJ10)*360} -> 21.239758 | AK22: {=AVERAGE(AJ8:AK8/'Historical Financials'!AK10)*360} -> 20.834278 | AL22: {=AVERAGE(AK8:AL8/'Historical Financials'!AL10)*360} -> 40.985692 | AM22: {=AVERAGE(AL8:AM8/'Historical Financials'!AM10)*360} -> 43.609157 | ... AP22: {=AVERAGE(AO8:AP8/'Historical Financials'!AP10)*360} -> 37.461848
B23: Inventory Turnover Rate | C23: N/A | D23: =('Historical Financials'!D10)/AVERAGE(C9:D9) -> 65.617289 | E23: =('Historical Financials'!E10)/AVERAGE(D9:E9) -> 60.287141 | F23: =('Historical Financials'!F10)/AVERAGE(E9:F9) -> 64.54329 | G23: =('Historical Financials'!G10)/AVERAGE(F9:G9) -> 67.225419 | H23: =('Historical Financials'!H10)/AVERAGE(G9:H9) -> 68.756132 | I23: =('Historical Financials'!I10)/AVERAGE(H9:I9) -> 68.424085 | J23: =('Historical Financials'!J10)/AVERAGE(I9:J9) -> 67.976412 | K23: =('Historical Financials'!K10)/AVERAGE(J9:K9) -> 57.433355 | L23: =('Historical Financials'!L10)/AVERAGE(K9:L9) -> 64.005075 | N23: N/A | O23: =('Historical Financials'!O10*4)/AVERAGE(N9:O9) -> 68.65067 | P23: =('Historical Financials'!P10*4)/AVERAGE(O9:P9) -> 60.926467 | Q23: =('Historical Financials'!Q10*4)/AVERAGE(P9:Q9) -> 69.48338 | R23: =('Historical Financials'!R10*4)/AVERAGE(Q9:R9) -> 79.655958 | S23: =('Historical Financials'!S10*4)/AVERAGE(R9:S9) -> 53.047686 | T23: =('Historical Financials'!T10*4)/AVERAGE(S9:T9) -> 44.116227 | U23: =('Historical Financials'!U10*4)/AVERAGE(T9:U9) -> 52.330361 | V23: =('Historical Financials'!V10*4)/AVERAGE(U9:V9) -> 74.489955 | ... AC23: =('Historical Financials'!AC10*4)/AVERAGE(AB9:AC9) -> 70.405222 | AE23: N/A | AF23: =('Historical Financials'!AF10)/AVERAGE(AE9:AF9) -> 53.851909 | AG23: =('Historical Financials'!AG10)/AVERAGE(AF9:AG9) -> 51.767411 | AH23: =('Historical Financials'!AH10)/AVERAGE(AG9:AH9) -> 56.027628 | AI23: =('Historical Financials'!AI10)/AVERAGE(AH9:AI9) -> 60.06946 | AJ23: =('Historical Financials'!AJ10)/AVERAGE(AI9:AJ9) -> 59.895315 | AK23: =('Historical Financials'!AK10)/AVERAGE(AJ9:AK9) -> 62.209083 | AL23: =('Historical Financials'!AL10)/AVERAGE(AK9:AL9) -> 58.142146 | AM23: =('Historical Financials'!AM10)/AVERAGE(AL9:AM9) -> 55.752624 | ... AP23: =('Historical Financials'!AP10)/AVERAGE(AO9:AP9) -> 71.486902
B24: Days Inventory Outstanding (DIO) | C24: N/A | D24: {=-AVERAGE(C9:D9/'Historical Financials'!D13)*360} -> 8.9165391 | E24: {=-AVERAGE(D9:E9/'Historical Financials'!E13)*360} -> 9.6850192 | F24: {=-AVERAGE(E9:F9/'Historical Financials'!F13)*360} -> 8.9698483 | G24: {=-AVERAGE(F9:G9/'Historical Financials'!G13)*360} -> 8.6699025 | H24: {=-AVERAGE(G9:H9/'Historical Financials'!H13)*360} -> 8.9931966 | I24: {=-AVERAGE(H9:I9/'Historical Financials'!I13)*360} -> 9.2807744 | J24: {=-AVERAGE(I9:J9/'Historical Financials'!J13)*360} -> 9.4792586 | K24: {=-AVERAGE(J9:K9/'Historical Financials'!K13)*360} -> 11.652183 | L24: {=-AVERAGE(K9:L9/'Historical Financials'!L13)*360} -> 10.593411 | N24: N/A | O24: {=-AVERAGE(N9:O9/('Historical Financials'!O13*4)*360)} -> 9.3225388 | P24: {=-AVERAGE(O9:P9/('Historical Financials'!P13*4)*360)} -> 10.413073 | Q24: {=-AVERAGE(P9:Q9/('Historical Financials'!Q13*4)*360)} -> 8.9730265 | R24: {=-AVERAGE(Q9:R9/('Historical Financials'!R13*4)*360)} -> 7.923588 | S24: {=-AVERAGE(R9:S9/('Historical Financials'!S13*4)*360)} -> 12.175369 | T24: {=-AVERAGE(S9:T9/('Historical Financials'!T13*4)*360)} -> 14.707496 | U24: {=-AVERAGE(T9:U9/('Historical Financials'!U13*4)*360)} -> 12.546922 | V24: {=-AVERAGE(U9:V9/('Historical Financials'!V13*4)*360)} -> 8.9290791 | ... AC24: {=-AVERAGE(AB9:AC9/('Historical Financials'!AC13*4)*360)} -> 9.6800924 | AE24: N/A | AF24: {=-AVERAGE(AE9:AF9/'Historical Financials'!AF13)*360} -> 11.765437 | AG24: {=-AVERAGE(AF9:AG9/'Historical Financials'!AG13)*360} -> 12.297241 | AH24: {=-AVERAGE(AG9:AH9/'Historical Financials'!AH13)*360} -> 11.500862 | AI24: {=-AVERAGE(AH9:AI9/'Historical Financials'!AI13)*360} -> 10.901785 | AJ24: {=-AVERAGE(AI9:AJ9/'Historical Financials'!AJ13)*360} -> 11.045811 | AK24: {=-AVERAGE(AJ9:AK9/'Historical Financials'!AK13)*360} -> 10.70902 | AL24: {=-AVERAGE(AK9:AL9/'Historical Financials'!AL13)*360} -> 11.510135 | AM24: {=-AVERAGE(AL9:AM9/'Historical Financials'!AM13)*360} -> 12.073591 | ... AP24: {=-AVERAGE(AO9:AP9/'Historical Financials'!AP13)*360} -> 9.4847031
B25: Days Payable Outstanding (DPO) | C25: N/A | D25: {=-AVERAGE(C13:D13/'Historical Financials'!D13)*360} -> 104.05309 | E25: {=-AVERAGE(D13:E13/'Historical Financials'!E13)*360} -> 110.06253 | F25: {=-AVERAGE(E13:F13/'Historical Financials'!F13)*360} -> 113.62401 | G25: {=-AVERAGE(F13:G13/'Historical Financials'!G13)*360} -> 93.983569 | H25: {=-AVERAGE(G13:H13/'Historical Financials'!H13)*360} -> 82.029007 | I25: {=-AVERAGE(H13:I13/'Historical Financials'!I13)*360} -> 95.72097 | J25: {=-AVERAGE(I13:J13/'Historical Financials'!J13)*360} -> 106.52377 | K25: {=-AVERAGE(J13:K13/'Historical Financials'!K13)*360} -> 112.58643 | L25: {=-AVERAGE(K13:L13/'Historical Financials'!L13)*360} -> 113.08653 | N25: N/A | O25: {=-AVERAGE(N13:O13/('Historical Financials'!O13*4)*360)} -> 104.47888 | P25: {=-AVERAGE(O13:P13/('Historical Financials'!P13*4)*360)} -> 96.574011 | Q25: {=-AVERAGE(P13:Q13/('Historical Financials'!Q13*4)*360)} -> 97.224069 | R25: {=-AVERAGE(Q13:R13/('Historical Financials'!R13*4)*360)} -> 82.180794 | S25: {=-AVERAGE(R13:S13/('Historical Financials'!S13*4)*360)} -> 85.86521 | T25: {=-AVERAGE(S13:T13/('Historical Financials'!T13*4)*360)} -> 88.88551 | U25: {=-AVERAGE(T13:U13/('Historical Financials'!U13*4)*360)} -> 100.24149 | V25: {=-AVERAGE(U13:V13/('Historical Financials'!V13*4)*360)} -> 83.962685 | ... AC25: {=-AVERAGE(AB13:AC13/('Historical Financials'!AC13*4)*360)} -> 99.963603 | AE25: N/A | AF25: {=-AVERAGE(AE13:AF13/'Historical Financials'!AF13)*360} -> 82.974219 | AG25: {=-AVERAGE(AF13:AG13/'Historical Financials'!AG13)*360} -> 74.319008 | AH25: {=-AVERAGE(AG13:AH13/'Historical Financials'!AH13)*360} -> 91.884168 | AI25: {=-AVERAGE(AH13:AI13/'Historical Financials'!AI13)*360} -> 102.5126 | AJ25: {=-AVERAGE(AI13:AJ13/'Historical Financials'!AJ13)*360} -> 90.06111 | AK25: {=-AVERAGE(AJ13:AK13/'Historical Financials'!AK13)*360} -> 80.619565 | AL25: {=-AVERAGE(AK13:AL13/'Historical Financials'!AL13)*360} -> 99.719137 | AM25: {=-AVERAGE(AL13:AM13/'Historical Financials'!AM13)*360} -> 111.29611 | ... AP25: {=-AVERAGE(AO13:AP13/'Historical Financials'!AP13)*360} -> 97.945873
B26: Cash Conversion Cycle (CCC) | C26: N/A | D26: =D22+D24-D25 -> -68.731042 | E26: =E22+E24-E25 -> -72.550182 | F26: =F22+F24-F25 -> -72.751822 | G26: =G22+G24-G25 -> -59.711131 | H26: =H22+H24-H25 -> -52.173904 | I26: =I22+I24-I25 -> -61.579775 | J26: =J22+J24-J25 -> -69.950936 | K26: =K22+K24-K25 -> -56.858445 | L26: =L22+L24-L25 -> -56.63683 | N26: N/A | O26: =O22+O24-O25 -> -71.551213 | P26: =P22+P24-P25 -> -63.043374 | Q26: =Q22+Q24-Q25 -> -63.298022 | R26: =R22+R24-R25 -> -54.308079 | S26: =S22+S24-S25 -> -53.908745 | T26: =T22+T24-T25 -> -53.555925 | U26: =U22+U24-U25 -> -63.028483 | V26: =V22+V24-V25 -> -55.200113 | ... AC26: =AC22+AC24-AC25 -> -52.246113 | AE26: N/A | AF26: =AF22+AF24-AF25 -> -51.723097 | AG26: =AG22+AG24-AG25 -> -44.447607 | AH26: =AH22+AH24-AH25 -> -57.34494 | AI26: =AI22+AI24-AI25 -> -67.016024 | AJ26: =AJ22+AJ24-AJ25 -> -57.775542 | AK26: =AK22+AK24-AK25 -> -49.076267 | AL26: =AL22+AL24-AL25 -> -47.22331 | AM26: =AM22+AM24-AM25 -> -55.613359 | ... AP26: =AP22+AP24-AP25 -> -50.999322
A28: X | B28: Per Share Analysis
B30: Book Value per Basic Share
B31: Basic Shares | C31: ='Historical Financials'!C29 -> 21883.281 | D31: ='Historical Financials'!D29 -> 20868.968 | E31: ='Historical Financials'!E29 -> 19821.51 | F31: ='Historical Financials'!F29 -> 18471.336 | G31: ='Historical Financials'!G29 -> 17352.119 | H31: ='Historical Financials'!H29 -> 16701.272 | I31: ='Historical Financials'!I29 -> 16215.963 | J31: ='Historical Financials'!J29 -> 15744.231 | ... L31: ='Historical Financials'!L29 -> 14948.5 | N31: ='Historical Financials'!N29 -> 16391.724 | O31: ='Historical Financials'!O29 -> 16278.802 | P31: ='Historical Financials'!P29 -> 16162.945 | Q31: ='Historical Financials'!Q29 -> 16215.963 | R31: ='Historical Financials'!R29 -> 15892.723 | S31: ='Historical Financials'!S29 -> 15787.154 | T31: ='Historical Financials'!T29 -> 15697.614 | U31: ='Historical Financials'!U29 -> 15744.231 | ... AC31: ='Historical Financials'!AC29 -> 14948.5 | AE31: ='Historical Financials'!AE29 -> 15892.723 | AF31: ='Historical Financials'!AF29 -> 15787.154 | AG31: ='Historical Financials'!AG29 -> 15697.614 | AH31: ='Historical Financials'!AH29 -> 15744.231 | AI31: ='Historical Financials'!AI29 -> 15509.763 | AJ31: ='Historical Financials'!AJ29 -> 15405.856 | AK31: ='Historical Financials'!AK29 -> 15287.521 | AL31: ='Historical Financials'!AL29 -> 15343.783 | ... AP31: ='Historical Financials'!AP29 -> 14948.5
B32: Shareholder Equity | C32: ='Historical Financials'!C65 -> 128249 | D32: ='Historical Financials'!D65 -> 134047 | E32: ='Historical Financials'!E65 -> 107147 | F32: ='Historical Financials'!F65 -> 90488 | G32: ='Historical Financials'!G65 -> 65339 | H32: ='Historical Financials'!H65 -> 63090 | I32: ='Historical Financials'!I65 -> 50672 | J32: ='Historical Financials'!J65 -> 62146 | ... L32: ='Historical Financials'!L65 -> 73733 | N32: ='Historical Financials'!N65 -> 63894 | O32: ='Historical Financials'!O65 -> 59361 | P32: ='Historical Financials'!P65 -> 50069 | Q32: ='Historical Financials'!Q65 -> 50672 | R32: ='Historical Financials'!R65 -> 48689 | S32: ='Historical Financials'!S65 -> 54120 | T32: ='Historical Financials'!T65 -> 52236 | U32: ='Historical Financials'!U65 -> 62146 | ... AC32: ='Historical Financials'!AC65 -> 73733 | AE32: ='Historical Financials'!AE65 -> 48689 | AF32: ='Historical Financials'!AF65 -> 54120 | AG32: ='Historical Financials'!AG65 -> 52236 | AH32: ='Historical Financials'!AH65 -> 62146 | AI32: ='Historical Financials'!AI65 -> 66062 | AJ32: ='Historical Financials'!AJ65 -> 66156 | AK32: ='Historical Financials'!AK65 -> 58670 | AL32: ='Historical Financials'!AL65 -> 56950 | ... AP32: ='Historical Financials'!AP65 -> 73733
B33: Total Book Value per Basic Shares | C33: =C32/C31 -> 5.8605928 | D33: =D32/D31 -> 6.4232692 | E33: =E32/E31 -> 5.4055922 | F33: =F32/F31 -> 4.8988335 | G33: =G32/G31 -> 3.7654767 | H33: =H32/H31 -> 3.7775566 | I33: =I32/I31 -> 3.1248221 | J33: =J32/J31 -> 3.9472236 | ... L33: =L32/L31 -> 4.9324681 | N33: =N32/N31 -> 3.8979426 | O33: =O32/O31 -> 3.6465214 | P33: =P32/P31 -> 3.0977647 | Q33: =Q32/Q31 -> 3.1248221 | R33: =R32/R31 -> 3.0636034 | S33: =S32/S31 -> 3.4281036 | T33: =T32/T31 -> 3.3276395 | U33: =U32/U31 -> 3.9472236 | ... AC33: =AC32/AC31 -> 4.9324681 | AE33: =AE32/AE31 -> 3.0636034 | AF33: =AF32/AF31 -> 3.4281036 | AG33: =AG32/AG31 -> 3.3276395 | AH33: =AH32/AH31 -> 3.9472236 | AI33: =AI32/AI31 -> 4.2593817 | AJ33: =AJ32/AJ31 -> 4.2942112 | AK33: =AK32/AK31 -> 3.8377707 | AL33: =AL32/AL31 -> 3.711601 | ... AP33: =AP32/AP31 -> 4.9324681
B35: Book Value per Fully Diluted Shares
B36: Fully Diluted Shares | C36: ='Historical Financials'!C32 -> 22001.127 | D36: ='Historical Financials'!D32 -> 21006.767 | E36: ='Historical Financials'!E32 -> 20000.436 | F36: ='Historical Financials'!F32 -> 18595.651 | G36: ='Historical Financials'!G32 -> 17528.214 | H36: ='Historical Financials'!H32 -> 16864.919 | I36: ='Historical Financials'!I32 -> 16325.819 | J36: ='Historical Financials'!J32 -> 15812.547 | ... L36: ='Historical Financials'!L32 -> 15004.697 | N36: ='Historical Financials'!N32 -> 16519.291 | O36: ='Historical Financials'!O32 -> 16403.316 | P36: ='Historical Financials'!P32 -> 16262.203 | Q36: ='Historical Financials'!Q32 -> 16325.819 | R36: ='Historical Financials'!R32 -> 15955.718 | S36: ='Historical Financials'!S32 -> 15847.05 | T36: ='Historical Financials'!T32 -> 15775.021 | U36: ='Historical Financials'!U32 -> 15812.547 | ... AC36: ='Historical Financials'!AC32 -> 15004.697 | AE36: ='Historical Financials'!AE32 -> 15955.718 | AF36: ='Historical Financials'!AF32 -> 15847.05 | AG36: ='Historical Financials'!AG32 -> 15775.021 | AH36: ='Historical Financials'!AH32 -> 15812.547 | AI36: ='Historical Financials'!AI32 -> 15576.641 | AJ36: ='Historical Financials'!AJ32 -> 15464.709 | AK36: ='Historical Financials'!AK32 -> 15348.175 | AL36: ='Historical Financials'!AL32 -> 15408.095 | ... AP36: ='Historical Financials'!AP32 -> 15004.697
B37: Shareholder Equity | C37: =C32 -> 128249 | D37: =D32 -> 134047 | E37: =E32 -> 107147 | F37: =F32 -> 90488 | G37: =G32 -> 65339 | H37: =H32 -> 63090 | I37: =I32 -> 50672 | J37: =J32 -> 62146 | ... L37: =L32 -> 73733 | N37: =N32 -> 63894 | O37: =O32 -> 59361 | P37: =P32 -> 50069 | Q37: =Q32 -> 50672 | R37: =R32 -> 48689 | S37: =S32 -> 54120 | T37: =T32 -> 52236 | U37: =U32 -> 62146 | ... AC37: =AC32 -> 73733 | AE37: =AE32 -> 48689 | AF37: =AF32 -> 54120 | AG37: =AG32 -> 52236 | AH37: =AH32 -> 62146 | AI37: =AI32 -> 66062 | AJ37: =AJ32 -> 66156 | AK37: =AK32 -> 58670 | AL37: =AL32 -> 56950 | ... AP37: =AP32 -> 73733
B38: Total Book Value per Basic Shares | C38: =C37/C36 -> 5.8292014 | D38: =D37/D36 -> 6.3811342 | E38: =E37/E36 -> 5.3572332 | F38: =F37/F36 -> 4.866084 | G38: =G37/G36 -> 3.7276473 | H38: =H37/H36 -> 3.7409015 | I38: =I37/I36 -> 3.1037953 | J38: =J37/J36 -> 3.9301701 | ... L38: =L37/L36 -> 4.9139946 | N38: =N37/N36 -> 3.8678415 | O38: =O37/O36 -> 3.6188415 | P38: =P37/P36 -> 3.0788572 | Q38: =Q37/Q36 -> 3.1037953 | R38: =R37/R36 -> 3.0515079 | S38: =S37/S36 -> 3.4151467 | T38: =T37/T36 -> 3.311311 | U38: =U37/U36 -> 3.9301701 | ... AC38: =AC37/AC36 -> 4.9139946 | AE38: =AE37/AE36 -> 3.0515079 | AF38: =AF37/AF36 -> 3.4151467 | AG38: =AG37/AG36 -> 3.311311 | AH38: =AH37/AH36 -> 3.9301701 | AI38: =AI37/AI36 -> 4.2410941 | AJ38: =AJ37/AJ36 -> 4.2778691 | AK38: =AK37/AK36 -> 3.8226043 | AL38: =AL37/AL36 -> 3.6961091 | ... AP38: =AP37/AP36 -> 4.9139946
B40: Gross Cash & Investments per Basic Shares
B41: Cash + MS | C41: =SUM('Historical Financials'!C39+'Historical Financials'!C40+'Historical Financials'!C47) -> 237585 | D41: =SUM('Historical Financials'!D39+'Historical Financials'!D40+'Historical Financials'!D47) -> 268895 | E41: =SUM('Historical Financials'!E39+'Historical Financials'!E40+'Historical Financials'!E47) -> 237100 | F41: =SUM('Historical Financials'!F39+'Historical Financials'!F40+'Historical Financials'!F47) -> 205898 | G41: =SUM('Historical Financials'!G39+'Historical Financials'!G40+'Historical Financials'!G47) -> 191830 | H41: =SUM('Historical Financials'!H39+'Historical Financials'!H40+'Historical Financials'!H47) -> 190516 | I41: =SUM('Historical Financials'!I39+'Historical Financials'!I40+'Historical Financials'!I47) -> 169109 | J41: =SUM('Historical Financials'!J39+'Historical Financials'!J40+'Historical Financials'!J47) -> 162099 | ... L41: =SUM('Historical Financials'!L39+'Historical Financials'!L40+'Historical Financials'!L47) -> 132420 | N41: =SUM('Historical Financials'!N39+'Historical Financials'!N40+'Historical Financials'!N47) -> 202596 | O41: =SUM('Historical Financials'!O39+'Historical Financials'!O40+'Historical Financials'!O47) -> 192730 | P41: =SUM('Historical Financials'!P39+'Historical Financials'!P40+'Historical Financials'!P47) -> 179308 | Q41: =SUM('Historical Financials'!Q39+'Historical Financials'!Q40+'Historical Financials'!Q47) -> 169109 | R41: =SUM('Historical Financials'!R39+'Historical Financials'!R40+'Historical Financials'!R47) -> 165450 | S41: =SUM('Historical Financials'!S39+'Historical Financials'!S40+'Historical Financials'!S47) -> 166333 | T41: =SUM('Historical Financials'!T39+'Historical Financials'!T40+'Historical Financials'!T47) -> 166543 | U41: =SUM('Historical Financials'!U39+'Historical Financials'!U40+'Historical Financials'!U47) -> 162099 | ... AC41: =SUM('Historical Financials'!AC39+'Historical Financials'!AC40+'Historical Financials'!AC47) -> 132420 | AE41: =SUM('Historical Financials'!AE39+'Historical Financials'!AE40+'Historical Financials'!AE47) -> 165450 | AF41: =SUM('Historical Financials'!AF39+'Historical Financials'!AF40+'Historical Financials'!AF47) -> 166333 | AG41: =SUM('Historical Financials'!AG39+'Historical Financials'!AG40+'Historical Financials'!AG47) -> 166543 | AH41: =SUM('Historical Financials'!AH39+'Historical Financials'!AH40+'Historical Financials'!AH47) -> 162099 | AI41: =SUM('Historical Financials'!AI39+'Historical Financials'!AI40+'Historical Financials'!AI47) -> 172575 | AJ41: =SUM('Historical Financials'!AJ39+'Historical Financials'!AJ40+'Historical Financials'!AJ47) -> 162337 | AK41: =SUM('Historical Financials'!AK39+'Historical Financials'!AK40+'Historical Financials'!AK47) -> 153041 | AL41: =SUM('Historical Financials'!AL39+'Historical Financials'!AL40+'Historical Financials'!AL47) -> 156650 | ... AP41: =SUM('Historical Financials'!AP39+'Historical Financials'!AP40+'Historical Financials'!AP47) -> 132420
B42: Basic Shares | C42: =C31 -> 21883.281 | D42: =D31 -> 20868.968 | E42: =E31 -> 19821.51 | F42: =F31 -> 18471.336 | G42: =G31 -> 17352.119 | H42: =H31 -> 16701.272 | I42: =I31 -> 16215.963 | J42: =J31 -> 15744.231 | ... L42: =L31 -> 14948.5 | N42: =N31 -> 16391.724 | O42: =O31 -> 16278.802 | P42: =P31 -> 16162.945 | Q42: =Q31 -> 16215.963 | R42: =R31 -> 15892.723 | S42: =S31 -> 15787.154 | T42: =T31 -> 15697.614 | U42: =U31 -> 15744.231 | ... AC42: =AC31 -> 14948.5 | AE42: =AE31 -> 15892.723 | AF42: =AF31 -> 15787.154 | AG42: =AG31 -> 15697.614 | AH42: =AH31 -> 15744.231 | AI42: =AI31 -> 15509.763 | AJ42: =AJ31 -> 15405.856 | AK42: =AK31 -> 15287.521 | AL42: =AL31 -> 15343.783 | ... AP42: =AP31 -> 14948.5
B43: Total Gross Cash & MS per Basic Shares | C43: =C41/C42 -> 10.856919 | D43: =D41/D42 -> 12.884921 | E43: =E41/E42 -> 11.961753 | F43: =F41/F42 -> 11.146893 | G43: =G41/G42 -> 11.055134 | H43: =H41/H42 -> 11.407275 | I43: =I41/I42 -> 10.428551 | J43: =J41/J42 -> 10.295771 | ... L43: =L41/L42 -> 8.8584139 | N43: =N41/N42 -> 12.359652 | O43: =O41/O42 -> 11.839323 | P43: =P41/P42 -> 11.09377 | Q43: =Q41/Q42 -> 10.428551 | R43: =R41/R42 -> 10.410425 | S43: =S41/S42 -> 10.535971 | T43: =T41/T42 -> 10.609447 | U43: =U41/U42 -> 10.295771 | ... AC43: =AC41/AC42 -> 8.8584139 | AE43: =AE41/AE42 -> 10.410425 | AF43: =AF41/AF42 -> 10.535971 | AG43: =AG41/AG42 -> 10.609447 | AH43: =AH41/AH42 -> 10.295771 | AI43: =AI41/AI42 -> 11.126862 | AJ43: =AJ41/AJ42 -> 10.537357 | AK43: =AK41/AK42 -> 10.010845 | AL43: =AL41/AL42 -> 10.209347 | ... AP43: =AP41/AP42 -> 8.8584139
B45: Gross Cash & Investments per Fully Diluted Shares
B46: Cash + MS | C46: =C41 -> 237585 | D46: =D41 -> 268895 | E46: =E41 -> 237100 | F46: =F41 -> 205898 | G46: =G41 -> 191830 | H46: =H41 -> 190516 | I46: =I41 -> 169109 | J46: =J41 -> 162099 | ... L46: =L41 -> 132420 | N46: =N41 -> 202596 | O46: =O41 -> 192730 | P46: =P41 -> 179308 | Q46: =Q41 -> 169109 | R46: =R41 -> 165450 | S46: =S41 -> 166333 | T46: =T41 -> 166543 | U46: =U41 -> 162099 | ... AC46: =AC41 -> 132420 | AE46: =AE41 -> 165450 | AF46: =AF41 -> 166333 | AG46: =AG41 -> 166543 | AH46: =AH41 -> 162099 | AI46: =AI41 -> 172575 | AJ46: =AJ41 -> 162337 | AK46: =AK41 -> 153041 | AL46: =AL41 -> 156650 | ... AP46: =AP41 -> 132420
B47: Fully Diluted Shares | C47: =C36 -> 22001.127 | D47: =D36 -> 21006.767 | E47: =E36 -> 20000.436 | F47: =F36 -> 18595.651 | G47: =G36 -> 17528.214 | H47: =H36 -> 16864.919 | I47: =I36 -> 16325.819 | J47: =J36 -> 15812.547 | ... L47: =L36 -> 15004.697 | N47: =N36 -> 16519.291 | O47: =O36 -> 16403.316 | P47: =P36 -> 16262.203 | Q47: =Q36 -> 16325.819 | R47: =R36 -> 15955.718 | S47: =S36 -> 15847.05 | T47: =T36 -> 15775.021 | U47: =U36 -> 15812.547 | ... AC47: =AC36 -> 15004.697 | AE47: =AE36 -> 15955.718 | AF47: =AF36 -> 15847.05 | AG47: =AG36 -> 15775.021 | AH47: =AH36 -> 15812.547 | AI47: =AI36 -> 15576.641 | AJ47: =AJ36 -> 15464.709 | AK47: =AK36 -> 15348.175 | AL47: =AL36 -> 15408.095 | ... AP47: =AP36 -> 15004.697
B48: Total Gross Cash & MS per Fully Diluted Shares | C48: =C46/C47 -> 10.798765 | D48: =D46/D47 -> 12.800399 | E48: =E46/E47 -> 11.854742 | F48: =F46/F47 -> 11.072374 | G48: =G46/G47 -> 10.94407 | H48: =H46/H47 -> 11.296586 | I48: =I46/I47 -> 10.358378 | J48: =J46/J47 -> 10.25129 | ... L48: =L46/L47 -> 8.8252365 | N48: =N46/N47 -> 12.264207 | O48: =O46/O47 -> 11.749454 | P48: =P46/P47 -> 11.026058 | Q48: =Q46/Q47 -> 10.358378 | R48: =R46/R47 -> 10.369323 | S48: =S46/S47 -> 10.496149 | T48: =T46/T47 -> 10.557387 | U48: =U46/U47 -> 10.25129 | ... AC48: =AC46/AC47 -> 8.8252365 | AE48: =AE46/AE47 -> 10.369323 | AF48: =AF46/AF47 -> 10.496149 | AG48: =AG46/AG47 -> 10.557387 | AH48: =AH46/AH47 -> 10.25129 | AI48: =AI46/AI47 -> 11.07909 | AJ48: =AJ46/AJ47 -> 10.497255 | AK48: =AK46/AK47 -> 9.9712832 | AL48: =AL46/AL47 -> 10.166734 | ... AP48: =AP46/AP47 -> 8.8252365
B50: Net Cash & Investments per Basic Shares
B51: Total Debt | C51: =-SUM('Historical Financials'!C58+'Historical Financials'!C55+'Historical Financials'!C54) -> -87032 | D51: =-SUM('Historical Financials'!D58+'Historical Financials'!D55+'Historical Financials'!D54) -> -115680 | E51: =-SUM('Historical Financials'!E58+'Historical Financials'!E55+'Historical Financials'!E54) -> -114483 | F51: =-SUM('Historical Financials'!F58+'Historical Financials'!F55+'Historical Financials'!F54) -> -108047 | G51: =-SUM('Historical Financials'!G58+'Historical Financials'!G55+'Historical Financials'!G54) -> -112436 | H51: =-SUM('Historical Financials'!H58+'Historical Financials'!H55+'Historical Financials'!H54) -> -124719 | I51: =-SUM('Historical Financials'!I58+'Historical Financials'!I55+'Historical Financials'!I54) -> -120069 | J51: =-SUM('Historical Financials'!J58+'Historical Financials'!J55+'Historical Financials'!J54) -> -111088 | ... L51: =-SUM('Historical Financials'!L58+'Historical Financials'!L55+'Historical Financials'!L54) -> -98657 | N51: =-SUM('Historical Financials'!N58+'Historical Financials'!N55+'Historical Financials'!N54) -> -122798 | O51: =-SUM('Historical Financials'!O58+'Historical Financials'!O55+'Historical Financials'!O54) -> -119981 | P51: =-SUM('Historical Financials'!P58+'Historical Financials'!P55+'Historical Financials'!P54) -> -119691 | Q51: =-SUM('Historical Financials'!Q58+'Historical Financials'!Q55+'Historical Financials'!Q54) -> -120069 | R51: =-SUM('Historical Financials'!R58+'Historical Financials'!R55+'Historical Financials'!R54) -> -111110 | S51: =-SUM('Historical Financials'!S58+'Historical Financials'!S55+'Historical Financials'!S54) -> -109615 | T51: =-SUM('Historical Financials'!T58+'Historical Financials'!T55+'Historical Financials'!T54) -> -109280 | U51: =-SUM('Historical Financials'!U58+'Historical Financials'!U55+'Historical Financials'!U54) -> -111088 | ... AC51: =-SUM('Historical Financials'!AC58+'Historical Financials'!AC55+'Historical Financials'!AC54) -> -98657 | AE51: =-SUM('Historical Financials'!AE58+'Historical Financials'!AE55+'Historical Financials'!AE54) -> -111110 | AF51: =-SUM('Historical Financials'!AF58+'Historical Financials'!AF55+'Historical Financials'!AF54) -> -109615 | AG51: =-SUM('Historical Financials'!AG58+'Historical Financials'!AG55+'Historical Financials'!AG54) -> -109280 | AH51: =-SUM('Historical Financials'!AH58+'Historical Financials'!AH55+'Historical Financials'!AH54) -> -111088 | AI51: =-SUM('Historical Financials'!AI58+'Historical Financials'!AI55+'Historical Financials'!AI54) -> -108040 | AJ51: =-SUM('Historical Financials'!AJ58+'Historical Financials'!AJ55+'Historical Financials'!AJ54) -> -104590 | AK51: =-SUM('Historical Financials'!AK58+'Historical Financials'!AK55+'Historical Financials'!AK54) -> -101304 | AL51: =-SUM('Historical Financials'!AL58+'Historical Financials'!AL55+'Historical Financials'!AL54) -> -106629 | ... AP51: =-SUM('Historical Financials'!AP58+'Historical Financials'!AP55+'Historical Financials'!AP54) -> -98657
B52: Net Cash & Investments | C52: =C41+C51 -> 150553 | D52: =D41+D51 -> 153215 | E52: =E41+E51 -> 122617 | F52: =F41+F51 -> 97851 | G52: =G41+G51 -> 79394 | H52: =H41+H51 -> 65797 | I52: =I41+I51 -> 49040 | J52: =J41+J51 -> 51011 | ... L52: =L41+L51 -> 33763 | N52: =N41+N51 -> 79798 | O52: =O41+O51 -> 72749 | P52: =P41+P51 -> 59617 | Q52: =Q41+Q51 -> 49040 | R52: =R41+R51 -> 54340 | S52: =S41+S51 -> 56718 | T52: =T41+T51 -> 57263 | U52: =U41+U51 -> 51011 | ... AC52: =AC41+AC51 -> 33763 | AE52: =AE41+AE51 -> 54340 | AF52: =AF41+AF51 -> 56718 | AG52: =AG41+AG51 -> 57263 | AH52: =AH41+AH51 -> 51011 | AI52: =AI41+AI51 -> 64535 | AJ52: =AJ41+AJ51 -> 57747 | AK52: =AK41+AK51 -> 51737 | AL52: =AL41+AL51 -> 50021 | ... AP52: =AP41+AP51 -> 33763
B53: Basic Shares | C53: =C31 -> 21883.281 | D53: =D31 -> 20868.968 | E53: =E31 -> 19821.51 | F53: =F31 -> 18471.336 | G53: =G31 -> 17352.119 | H53: =H31 -> 16701.272 | I53: =I31 -> 16215.963 | J53: =J31 -> 15744.231 | ... L53: =L31 -> 14948.5 | N53: =N31 -> 16391.724 | O53: =O31 -> 16278.802 | P53: =P31 -> 16162.945 | Q53: =Q31 -> 16215.963 | R53: =R31 -> 15892.723 | S53: =S31 -> 15787.154 | T53: =T31 -> 15697.614 | U53: =U31 -> 15744.231 | ... AC53: =AC31 -> 14948.5 | AE53: =AE31 -> 15892.723 | AF53: =AF31 -> 15787.154 | AG53: =AG31 -> 15697.614 | AH53: =AH31 -> 15744.231 | AI53: =AI31 -> 15509.763 | AJ53: =AJ31 -> 15405.856 | AK53: =AK31 -> 15287.521 | AL53: =AL31 -> 15343.783 | ... AP53: =AP31 -> 14948.5
B54: Total Gross Cash & MS per Basic Shares | C54: =C52/C53 -> 6.8798184 | D54: =D52/D53 -> 7.3417622 | E54: =E52/E53 -> 6.1860575 | F54: =F52/F53 -> 5.2974511 | G54: =G52/G53 -> 4.5754642 | H54: =H52/H53 -> 3.93964 | I54: =I52/I53 -> 3.0241806 | J54: =J52/J53 -> 3.2399804 | ... L54: =L52/L53 -> 2.2586213 | N54: =N52/N53 -> 4.8681884 | O54: =O52/O53 -> 4.4689407 | P54: =P52/P53 -> 3.6884986 | Q54: =Q52/Q53 -> 3.0241806 | R54: =R52/R53 -> 3.4191749 | S54: =S52/S53 -> 3.5926678 | T54: =T52/T53 -> 3.6478792 | U54: =U52/U53 -> 3.2399804 | ... AC54: =AC52/AC53 -> 2.2586213 | AE54: =AE52/AE53 -> 3.4191749 | AF54: =AF52/AF53 -> 3.5926678 | AG54: =AG52/AG53 -> 3.6478792 | AH54: =AH52/AH53 -> 3.2399804 | AI54: =AI52/AI53 -> 4.1609275 | AJ54: =AJ52/AJ53 -> 3.7483798 | AK54: =AK52/AK53 -> 3.3842635 | AL54: =AL52/AL53 -> 3.2600174 | ... AP54: =AP52/AP53 -> 2.2586213
B56: Net Cash & Investments per Fully Diluted Shares
B57: Total Debt | C57: =C51 -> -87032 | D57: =D51 -> -115680 | E57: =E51 -> -114483 | F57: =F51 -> -108047 | G57: =G51 -> -112436 | H57: =H51 -> -124719 | I57: =I51 -> -120069 | J57: =J51 -> -111088 | ... L57: =L51 -> -98657 | N57: =N51 -> -122798 | O57: =O51 -> -119981 | P57: =P51 -> -119691 | Q57: =Q51 -> -120069 | R57: =R51 -> -111110 | S57: =S51 -> -109615 | T57: =T51 -> -109280 | U57: =U51 -> -111088 | ... AC57: =AC51 -> -98657 | AE57: =AE51 -> -111110 | AF57: =AF51 -> -109615 | AG57: =AG51 -> -109280 | AH57: =AH51 -> -111088 | AI57: =AI51 -> -108040 | AJ57: =AJ51 -> -104590 | AK57: =AK51 -> -101304 | AL57: =AL51 -> -106629 | ... AP57: =AP51 -> -98657
B58: Net Cash & Investments | C58: =C41+C57 -> 150553 | D58: =D41+D57 -> 153215 | E58: =E41+E57 -> 122617 | F58: =F41+F57 -> 97851 | G58: =G41+G57 -> 79394 | H58: =H41+H57 -> 65797 | I58: =I41+I57 -> 49040 | J58: =J41+J57 -> 51011 | ... L58: =L41+L57 -> 33763 | N58: =N41+N57 -> 79798 | O58: =O41+O57 -> 72749 | P58: =P41+P57 -> 59617 | Q58: =Q41+Q57 -> 49040 | R58: =R41+R57 -> 54340 | S58: =S41+S57 -> 56718 | T58: =T41+T57 -> 57263 | U58: =U41+U57 -> 51011 | ... AC58: =AC41+AC57 -> 33763 | AE58: =AE41+AE57 -> 54340 | AF58: =AF41+AF57 -> 56718 | AG58: =AG41+AG57 -> 57263 | AH58: =AH41+AH57 -> 51011 | AI58: =AI41+AI57 -> 64535 | AJ58: =AJ41+AJ57 -> 57747 | AK58: =AK41+AK57 -> 51737 | AL58: =AL41+AL57 -> 50021 | ... AP58: =AP41+AP57 -> 33763
B59: Fully Diluted Shares | C59: =C36 -> 22001.127 | D59: =D36 -> 21006.767 | E59: =E36 -> 20000.436 | F59: =F36 -> 18595.651 | G59: =G36 -> 17528.214 | H59: =H36 -> 16864.919 | I59: =I36 -> 16325.819 | J59: =J36 -> 15812.547 | ... L59: =L36 -> 15004.697 | N59: =N36 -> 16519.291 | O59: =O36 -> 16403.316 | P59: =P36 -> 16262.203 | Q59: =Q36 -> 16325.819 | R59: =R36 -> 15955.718 | S59: =S36 -> 15847.05 | T59: =T36 -> 15775.021 | U59: =U36 -> 15812.547 | ... AC59: =AC36 -> 15004.697 | AE59: =AE36 -> 15955.718 | AF59: =AF36 -> 15847.05 | AG59: =AG36 -> 15775.021 | AH59: =AH36 -> 15812.547 | AI59: =AI36 -> 15576.641 | AJ59: =AJ36 -> 15464.709 | AK59: =AK36 -> 15348.175 | AL59: =AL36 -> 15408.095 | ... AP59: =AP36 -> 15004.697
B60: Total Gross Cash & MS per Fully Diluted Shares | C60: =C58/C59 -> 6.8429676 | D60: =D58/D59 -> 7.2936021 | E60: =E58/E59 -> 6.1307164 | F60: =F58/F59 -> 5.2620368 | G60: =G58/G59 -> 4.5294974 | H60: =H58/H59 -> 3.9014122 | I60: =I58/I59 -> 3.0038309 | J60: =J58/J59 -> 3.2259825 | ... L60: =L58/L59 -> 2.2501621 | N60: =N58/N59 -> 4.8305947 | O60: =O58/O59 -> 4.4350179 | P60: =P58/P59 -> 3.6659855 | Q60: =Q58/Q59 -> 3.0038309 | R60: =R58/R59 -> 3.4056756 | S60: =S58/S59 -> 3.5790889 | T60: =T58/T59 -> 3.6299793 | U60: =U58/U59 -> 3.2259825 | ... AC60: =AC58/AC59 -> 2.2501621 | AE60: =AE58/AE59 -> 3.4056756 | AF60: =AF58/AF59 -> 3.5790889 | AG60: =AG58/AG59 -> 3.6299793 | AH60: =AH58/AH59 -> 3.2259825 | AI60: =AI58/AI59 -> 4.1430627 | AJ60: =AJ58/AJ59 -> 3.7341149 | AK60: =AK58/AK59 -> 3.3708894 | AL60: =AL58/AL59 -> 3.2464104 | ... AP60: =AP58/AP59 -> 2.2501621

Sheet FCF
B2: Apple Inc. (NASDAQ: AAPL) | C2: FYE | I2: FYE | N2: Quarterly | V2: Quarterly | X2: Quarterly | AE2: LTM | AI2: LTM | AL2: LTM | AM2: LTM | AS2: Variance
B3: FCF Analysis | C3: ='Historical Financials'!C7 -> 2016 | D3: ='Historical Financials'!D7 -> 2017 | E3: ='Historical Financials'!E7 -> 2018 | F3: ='Historical Financials'!F7 -> 2019 | G3: ='Historical Financials'!G7 -> 2020 | H3: ='Historical Financials'!H7 -> 2021 | I3: ='Historical Financials'!I7 -> 2022 | J3: ='Historical Financials'!J7 -> 2023 | ... L3: ='Historical Financials'!L7 -> 2025 | N3: ='Historical Financials'!N7 -> 1Q22 | O3: ='Historical Financials'!O7 -> 2Q22 | P3: ='Historical Financials'!P7 -> 3Q22 | Q3: ='Historical Financials'!Q7 -> 4Q22 | R3: ='Historical Financials'!R7 -> 1Q23 | S3: ='Historical Financials'!S7 -> 2Q23 | T3: ='Historical Financials'!T7 -> 3Q23 | U3: ='Historical Financials'!U7 -> 4Q23 | ... AC3: ='Historical Financials'!AC7 -> 4Q25 | AE3: =Q3 -> 4Q22 | AF3: =R3 -> 1Q23 | AG3: =S3 -> 2Q23 | AH3: =T3 -> 3Q23 | AI3: =U3 -> 4Q23 | AJ3: =V3 -> 1Q24 | AK3: =W3 -> 2Q24 | AL3: =X3 -> 3Q24 | ... AQ3: =AC3 -> 4Q25
B4: ($ in Millions) | C4: ='Historical Financials'!C8 -> 42643 | D4: ='Historical Financials'!D8 -> 43008 | E4: ='Historical Financials'!E8 -> 43372 | F4: ='Historical Financials'!F8 -> 43737 | G4: ='Historical Financials'!G8 -> 44104 | H4: ='Historical Financials'!H8 -> 44469 | I4: ='Historical Financials'!I8 -> 44834 | J4: ='Historical Financials'!J8 -> 45192 | ... L4: ='Historical Financials'!L8 -> 45927 | N4: ='Historical Financials'!N8 -> 44560 | O4: ='Historical Financials'!O8 -> 44650 | P4: ='Historical Financials'!P8 -> 44742 | Q4: ='Historical Financials'!Q8 -> 44834 | R4: ='Historical Financials'!R8 -> 44917 | S4: ='Historical Financials'!S8 -> 45008 | T4: ='Historical Financials'!T8 -> 45100 | U4: ='Historical Financials'!U8 -> 45192 | ... AC4: ='Historical Financials'!AC8 -> 45927 | AE4: =Q4 -> 44834 | AF4: =R4 -> 44917 | AG4: =S4 -> 45008 | AH4: =T4 -> 45100 | AI4: =U4 -> 45192 | AJ4: =V4 -> 45283 | AK4: =W4 -> 45375 | AL4: =X4 -> 45467 | ... AQ4: =AC4 -> 45927
B6: ='Revenue Drivers'!B9 -> iPhone Revenue | C6: ='Revenue Drivers'!C9 -> 136700 | D6: ='Revenue Drivers'!D9 -> 141319 | E6: ='Revenue Drivers'!E9 -> 164888 | F6: ='Revenue Drivers'!F9 -> 142381 | G6: ='Revenue Drivers'!G9 -> 137781 | H6: ='Revenue Drivers'!H9 -> 191973 | I6: ='Revenue Drivers'!I9 -> 205489 | ... L6: ='Revenue Drivers'!L9 -> 209586 | N6: ='Revenue Drivers'!N9 -> 71628 | O6: ='Revenue Drivers'!O9 -> 50570 | P6: ='Revenue Drivers'!P9 -> 40665 | Q6: ='Revenue Drivers'!Q9 -> 42626 | R6: ='Revenue Drivers'!R9 -> 65775 | S6: ='Revenue Drivers'!S9 -> 51334 | T6: ='Revenue Drivers'!T9 -> 39669 | U6: ='Revenue Drivers'!U9 -> 43805 | ... AC6: ='Revenue Drivers'!AC9 -> 49025 | AE6: =SUM(N6:Q6) -> 205489 | AF6: =SUM(O6:R6) -> 199636 | AG6: =SUM(P6:S6) -> 200400 | AH6: =SUM(Q6:T6) -> 199404 | AI6: =SUM(R6:U6) -> 200583 | AJ6: =SUM(S6:V6) -> 204510 | AK6: =SUM(T6:W6) -> 199139 | AL6: =SUM(U6:X6) -> 198766 | ... AQ6: =SUM(Z6:AC6) -> 209586 | AS6: =SUM(AQ6/AM6)-1 -> 0.041767943
B7: ='Revenue Drivers'!B10 -> Mac Revenue | C7: ='Revenue Drivers'!C10 -> 22831 | D7: ='Revenue Drivers'!D10 -> 25850 | E7: ='Revenue Drivers'!E10 -> 25198 | F7: ='Revenue Drivers'!F10 -> 25740 | G7: ='Revenue Drivers'!G10 -> 28622 | H7: ='Revenue Drivers'!H10 -> 35190 | I7: ='Revenue Drivers'!I10 -> 40177 | ... L7: ='Revenue Drivers'!L10 -> 33708 | N7: ='Revenue Drivers'!N10 -> 10852 | O7: ='Revenue Drivers'!O10 -> 10435 | P7: ='Revenue Drivers'!P10 -> 7382 | Q7: ='Revenue Drivers'!Q10 -> 11508 | R7: ='Revenue Drivers'!R10 -> 7735 | S7: ='Revenue Drivers'!S10 -> 7168 | T7: ='Revenue Drivers'!T10 -> 6840 | U7: ='Revenue Drivers'!U10 -> 7614 | ... AC7: ='Revenue Drivers'!AC10 -> 8726 | AE7: =SUM(N7:Q7) -> 40177 | AF7: =SUM(O7:R7) -> 37060 | AG7: =SUM(P7:S7) -> 33793 | AH7: =SUM(Q7:T7) -> 33251 | AI7: =SUM(R7:U7) -> 29357 | AJ7: =SUM(S7:V7) -> 29402 | AK7: =SUM(T7:W7) -> 29685 | AL7: =SUM(U7:X7) -> 29854 | ... AQ7: =SUM(Z7:AC7) -> 33708 | AS7: =SUM(AQ7/AM7)-1 -> 0.12419957
B8: ='Revenue Drivers'!B11 -> iPad Revenue | C8: ='Revenue Drivers'!C11 -> 20628 | D8: ='Revenue Drivers'!D11 -> 19222 | E8: ='Revenue Drivers'!E11 -> 18380 | F8: ='Revenue Drivers'!F11 -> 21280 | G8: ='Revenue Drivers'!G11 -> 23724 | H8: ='Revenue Drivers'!H11 -> 31862 | I8: ='Revenue Drivers'!I11 -> 29292 | ... L8: ='Revenue Drivers'!L11 -> 28023 | N8: ='Revenue Drivers'!N11 -> 7248 | O8: ='Revenue Drivers'!O11 -> 7646 | P8: ='Revenue Drivers'!P11 -> 7224 | Q8: ='Revenue Drivers'!Q11 -> 7174 | R8: ='Revenue Drivers'!R11 -> 9396 | S8: ='Revenue Drivers'!S11 -> 6670 | T8: ='Revenue Drivers'!T11 -> 5791 | U8: ='Revenue Drivers'!U11 -> 6443 | ... AC8: ='Revenue Drivers'!AC11 -> 6952 | AE8: =SUM(N8:Q8) -> 29292 | AF8: =SUM(O8:R8) -> 31440 | AG8: =SUM(P8:S8) -> 30464 | AH8: =SUM(Q8:T8) -> 29031 | AI8: =SUM(R8:U8) -> 28300 | AJ8: =SUM(S8:V8) -> 25927 | AK8: =SUM(T8:W8) -> 24816 | AL8: =SUM(U8:X8) -> 26187 | ... AQ8: =SUM(Z8:AC8) -> 28023 | AS8: =SUM(AQ8/AM8)-1 -> 0.049786469
B9: ='Revenue Drivers'!B12 -> Services Revenue | C9: ='Revenue Drivers'!C12 -> 24348 | D9: ='Revenue Drivers'!D12 -> 29980 | E9: ='Revenue Drivers'!E12 -> 39748 | F9: ='Revenue Drivers'!F12 -> 46291 | G9: ='Revenue Drivers'!G12 -> 53768 | H9: ='Revenue Drivers'!H12 -> 68425 | I9: ='Revenue Drivers'!I12 -> 78129 | ... L9: ='Revenue Drivers'!L12 -> 109158 | N9: ='Revenue Drivers'!N12 -> 19516 | O9: ='Revenue Drivers'!O12 -> 19821 | P9: ='Revenue Drivers'!P12 -> 19604 | Q9: ='Revenue Drivers'!Q12 -> 19188 | R9: ='Revenue Drivers'!R12 -> 20766 | S9: ='Revenue Drivers'!S12 -> 20907 | T9: ='Revenue Drivers'!T12 -> 21213 | U9: ='Revenue Drivers'!U12 -> 22314 | ... AC9: ='Revenue Drivers'!AC12 -> 28750 | AE9: =SUM(N9:Q9) -> 78129 | AF9: =SUM(O9:R9) -> 79379 | AG9: =SUM(P9:S9) -> 80465 | AH9: =SUM(Q9:T9) -> 82074 | AI9: =SUM(R9:U9) -> 85200 | AJ9: =SUM(S9:V9) -> 87551 | AK9: =SUM(T9:W9) -> 90511 | AL9: =SUM(U9:X9) -> 93511 | ... AQ9: =SUM(Z9:AC9) -> 109158 | AS9: =SUM(AQ9/AM9)-1 -> 0.13506431
B10: ='Revenue Drivers'!B13 -> Wearables, Home, and Accessories Revenue | C10: ='Revenue Drivers'!C13 -> 11132 | D10: ='Revenue Drivers'!D13 -> 12863 | E10: ='Revenue Drivers'!E13 -> 17381 | F10: ='Revenue Drivers'!F13 -> 24482 | G10: ='Revenue Drivers'!G13 -> 30620 | H10: ='Revenue Drivers'!H13 -> 38367 | I10: ='Revenue Drivers'!I13 -> 41241 | ... L10: ='Revenue Drivers'!L13 -> 35686 | N10: ='Revenue Drivers'!N13 -> 14701 | O10: ='Revenue Drivers'!O13 -> 8806 | P10: ='Revenue Drivers'!P13 -> 8084 | Q10: ='Revenue Drivers'!Q13 -> 9650 | R10: ='Revenue Drivers'!R13 -> 13482 | S10: ='Revenue Drivers'!S13 -> 8757 | T10: ='Revenue Drivers'!T13 -> 8284 | U10: ='Revenue Drivers'!U13 -> 9322 | ... AC10: ='Revenue Drivers'!AC13 -> 9013 | AE10: =SUM(N10:Q10) -> 41241 | AF10: =SUM(O10:R10) -> 40022 | AG10: =SUM(P10:S10) -> 39973 | AH10: =SUM(Q10:T10) -> 40173 | AI10: =SUM(R10:U10) -> 39845 | AJ10: =SUM(S10:V10) -> 38316 | AK10: =SUM(T10:W10) -> 37472 | AL10: =SUM(U10:X10) -> 37285 | ... AQ10: =SUM(Z10:AC10) -> 35686 | AS10: =SUM(AQ10/AM10)-1 -> -0.035643832
B11: Total Revenue | C11: =SUM(C6:C10) -> 215639 | D11: =SUM(D6:D10) -> 229234 | E11: =SUM(E6:E10) -> 265595 | F11: =SUM(F6:F10) -> 260174 | G11: =SUM(G6:G10) -> 274515 | H11: =SUM(H6:H10) -> 365817 | I11: =SUM(I6:I10) -> 394328 | J11: =SUM(J6:J10) -> 383285 | ... L11: =SUM(L6:L10) -> 416161 | N11: =SUM(N6:N10) -> 123945 | O11: =SUM(O6:O10) -> 97278 | P11: =SUM(P6:P10) -> 82959 | Q11: =SUM(Q6:Q10) -> 90146 | R11: =SUM(R6:R10) -> 117154 | S11: =SUM(S6:S10) -> 94836 | T11: =SUM(T6:T10) -> 81797 | U11: =SUM(U6:U10) -> 89498 | ... AC11: =SUM(AC6:AC10) -> 102466 | AE11: =SUM(AE6:AE10) -> 394328 | AF11: =SUM(AF6:AF10) -> 387537 | AG11: =SUM(AG6:AG10) -> 385095 | AH11: =SUM(AH6:AH10) -> 383933 | AI11: =SUM(AI6:AI10) -> 383285 | AJ11: =SUM(AJ6:AJ10) -> 385706 | AK11: =SUM(AK6:AK10) -> 381623 | AL11: =SUM(AL6:AL10) -> 385603 | ... AQ11: =SUM(AQ6:AQ10) -> 416161 | AS11: =SUM(AQ11/AM11)-1 -> 0.064255118
B12: Y/Y Growth (%) | D12: =SUM(D11/C11)-1 -> 0.063045182 | E12: =SUM(E11/D11)-1 -> 0.15861958 | F12: =SUM(F11/E11)-1 -> -0.020410776 | G12: =SUM(G11/F11)-1 -> 0.055120804 | H12: =SUM(H11/G11)-1 -> 0.33259385 | I12: =SUM(I11/H11)-1 -> 0.077937876 | J12: =SUM(J11/I11)-1 -> -0.028004605 | K12: =SUM(K11/J11)-1 -> 0.020219941 | L12: =SUM(L11/K11)-1 -> 0.064255118 | R12: =SUM(R11/N11)-1 -> -0.054790431 | S12: =SUM(S11/O11)-1 -> -0.025103312 | T12: =SUM(T11/P11)-1 -> -0.014006919 | U12: =SUM(U11/Q11)-1 -> -0.0071883389 | V12: =SUM(V11/R11)-1 -> 0.020665107 | W12: =SUM(W11/S11)-1 -> -0.043053271 | X12: =SUM(X11/T11)-1 -> 0.048657041 | Y12: =SUM(Y11/U11)-1 -> 0.060694094 | ... AC12: =SUM(AC11/Y11)-1 -> 0.07938481 | AI12: =SUM(AI11/AE11)-1 -> -0.028004605 | AJ12: =SUM(AJ11/AF11)-1 -> -0.0047247102 | AK12: =SUM(AK11/AG11)-1 -> -0.0090159571 | AL12: =SUM(AL11/AH11)-1 -> 0.0043497173 | AM12: =SUM(AM11/AI11)-1 -> 0.020219941 | AN12: =SUM(AN11/AJ11)-1 -> 0.026066486 | AO12: =SUM(AO11/AK11)-1 -> 0.049113916 | AP12: =SUM(AP11/AL11)-1 -> 0.059703892 | AQ12: =SUM(AQ11/AM11)-1 -> 0.064255118 | AS12: =SUM(AQ12-AM12)*10000 -> 440.35177
B13: Q/Q Growth (%) | C13: N/A | D13: N/A | E13: N/A | F13: N/A | G13: N/A | H13: N/A | I13: N/A | J13: N/A | K13: N/A | L13: N/A | O13: =SUM(O11/N11)-1 -> -0.21515188 | P13: =SUM(P11/O11)-1 -> -0.14719669 | Q13: =SUM(Q11/P11)-1 -> 0.086633156 | R13: =SUM(R11/Q11)-1 -> 0.29960287 | S13: =SUM(S11/R11)-1 -> -0.19050139 | T13: =SUM(T11/S11)-1 -> -0.13748998 | U13: =SUM(U11/T11)-1 -> 0.094147707 | V13: =SUM(V11/U11)-1 -> 0.33606338 | ... AC13: =SUM(AC11/AB11)-1 -> 0.089646518 | AE13: N/A | AF13: N/A | AG13: N/A | AH13: N/A | AI13: N/A | AJ13: N/A | AK13: N/A | AL13: N/A | AM13: N/A | AN13: N/A | AO13: N/A | AP13: N/A | AQ13: N/A
B15: (-) Cost of Sales | C15: ='Historical Financials'!C13 -> -131376 | D15: ='Historical Financials'!D13 -> -141048 | E15: ='Historical Financials'!E13 -> -163756 | F15: ='Historical Financials'!F13 -> -161782 | G15: ='Historical Financials'!G13 -> -169559 | H15: ='Historical Financials'!H13 -> -212981 | I15: ='Historical Financials'!I13 -> -223546 | J15: ='Historical Financials'!J13 -> -214137 | ... L15: ='Historical Financials'!L13 -> -220960 | N15: ='Historical Financials'!N13 -> -69702 | O15: ='Historical Financials'!O13 -> -54719 | P15: ='Historical Financials'!P13 -> -47074 | Q15: ='Historical Financials'!Q13 -> -52051 | R15: ='Historical Financials'!R13 -> -66822 | S15: ='Historical Financials'!S13 -> -52860 | T15: ='Historical Financials'!T13 -> -45384 | U15: ='Historical Financials'!U13 -> -49071 | ... AC15: ='Historical Financials'!AC13 -> -54125 | AE15: =SUM(N15:Q15) -> -223546 | AF15: =SUM(O15:R15) -> -220666 | AG15: =SUM(P15:S15) -> -218807 | AH15: =SUM(Q15:T15) -> -217117 | AI15: =SUM(R15:U15) -> -214137 | AJ15: =SUM(S15:V15) -> -212035 | AK15: =SUM(T15:W15) -> -207657 | AL15: =SUM(U15:X15) -> -208372 | ... AQ15: =SUM(Z15:AC15) -> -220960 | AS15: =SUM(AQ15/AM15)-1 -> 0.050429756
B16: Gross Profit | C16: =+C11+C15 -> 84263 | D16: =+D11+D15 -> 88186 | E16: =+E11+E15 -> 101839 | F16: =+F11+F15 -> 98392 | G16: =+G11+G15 -> 104956 | H16: =+H11+H15 -> 152836 | I16: =+I11+I15 -> 170782 | J16: =+J11+J15 -> 169148 | ... L16: =+L11+L15 -> 195201 | N16: =+N11+N15 -> 54243 | O16: =+O11+O15 -> 42559 | P16: =+P11+P15 -> 35885 | Q16: =+Q11+Q15 -> 38095 | R16: =+R11+R15 -> 50332 | S16: =+S11+S15 -> 41976 | T16: =+T11+T15 -> 36413 | U16: =+U11+U15 -> 40427 | ... AC16: =+AC11+AC15 -> 48341 | AE16: =+AE11+AE15 -> 170782 | AF16: =+AF11+AF15 -> 166871 | AG16: =+AG11+AG15 -> 166288 | AH16: =+AH11+AH15 -> 166816 | AI16: =+AI11+AI15 -> 169148 | AJ16: =+AJ11+AJ15 -> 173671 | AK16: =+AK11+AK15 -> 173966 | AL16: =+AL11+AL15 -> 177231 | ... AQ16: =+AQ11+AQ15 -> 195201 | AS16: =SUM(AQ16/AM16)-1 -> 0.080350669
B17: Gross Margin (%) | C17: =C16/C11 -> 0.39075956 | D17: =D16/D11 -> 0.3846986 | E17: =E16/E11 -> 0.38343719 | F17: =F16/F11 -> 0.37817768 | G17: =G16/G11 -> 0.38233248 | H17: =H16/H11 -> 0.4177936 | I17: =I16/I11 -> 0.43309631 | J17: =J16/J11 -> 0.4413113 | ... L17: =L16/L11 -> 0.46905164 | N17: =N16/N11 -> 0.43763766 | O17: =O16/O11 -> 0.43749872 | P17: =P16/P11 -> 0.43256307 | Q17: =Q16/Q11 -> 0.42259224 | R17: =R16/R11 -> 0.42962255 | S17: =S16/S11 -> 0.44261673 | T17: =T16/T11 -> 0.44516303 | U17: =U16/U11 -> 0.45170842 | ... AC17: =AC16/AC11 -> 0.471776 | AE17: =AE16/AE11 -> 0.43309631 | AF17: =AF16/AF11 -> 0.43059372 | AG17: =AG16/AG11 -> 0.43181033 | AH17: =AH16/AH11 -> 0.43449248 | AI17: =AI16/AI11 -> 0.4413113 | AJ17: =AJ16/AJ11 -> 0.45026782 | AK17: =AK16/AK11 -> 0.45585827 | AL17: =AL16/AL11 -> 0.45962039 | ... AQ17: =AQ16/AQ11 -> 0.46905164 | AS17: =SUM(AQ17-AM17)*10000 -> 69.881429
B19: (-) Research and Development (R&D) | C19: ='Historical Financials'!C17 -> -10045 | D19: ='Historical Financials'!D17 -> -11581 | E19: ='Historical Financials'!E17 -> -14236 | F19: ='Historical Financials'!F17 -> -16217 | G19: ='Historical Financials'!G17 -> -18752 | H19: ='Historical Financials'!H17 -> -21914 | I19: ='Historical Financials'!I17 -> -26251 | J19: ='Historical Financials'!J17 -> -29915 | ... L19: ='Historical Financials'!L17 -> -34550 | N19: ='Historical Financials'!N17 -> -6306 | O19: ='Historical Financials'!O17 -> -6387 | P19: ='Historical Financials'!P17 -> -6797 | Q19: ='Historical Financials'!Q17 -> -6761 | R19: ='Historical Financials'!R17 -> -7709 | S19: ='Historical Financials'!S17 -> -7457 | T19: ='Historical Financials'!T17 -> -7442 | U19: ='Historical Financials'!U17 -> -7307 | ... AC19: ='Historical Financials'!AC17 -> -8866 | AE19: =SUM(N19:Q19) -> -26251 | AF19: =SUM(O19:R19) -> -27654 | AG19: =SUM(P19:S19) -> -28724 | AH19: =SUM(Q19:T19) -> -29369 | AI19: =SUM(R19:U19) -> -29915 | AJ19: =SUM(S19:V19) -> -29902 | AK19: =SUM(T19:W19) -> -30348 | AL19: =SUM(U19:X19) -> -30912 | ... AQ19: =SUM(Z19:AC19) -> -34550 | AS19: =SUM(AQ19/AM19)-1 -> 0.10137074
B20: (-) Selling, General & Administrative (SG&A) | C20: ='Historical Financials'!C18 -> -14194 | D20: ='Historical Financials'!D18 -> -15261 | E20: ='Historical Financials'!E18 -> -16705 | F20: ='Historical Financials'!F18 -> -18245 | G20: ='Historical Financials'!G18 -> -19916 | H20: ='Historical Financials'!H18 -> -21973 | I20: ='Historical Financials'!I18 -> -25094 | J20: ='Historical Financials'!J18 -> -24932 | ... L20: ='Historical Financials'!L18 -> -27601 | N20: ='Historical Financials'!N18 -> -6449 | O20: ='Historical Financials'!O18 -> -6193 | P20: ='Historical Financials'!P18 -> -6012 | Q20: ='Historical Financials'!Q18 -> -6440 | R20: ='Historical Financials'!R18 -> -6607 | S20: ='Historical Financials'!S18 -> -6201 | T20: ='Historical Financials'!T18 -> -5973 | U20: ='Historical Financials'!U18 -> -6151 | ... AC20: ='Historical Financials'!AC18 -> -7048 | AE20: =SUM(N20:Q20) -> -25094 | AF20: =SUM(O20:R20) -> -25252 | AG20: =SUM(P20:S20) -> -25260 | AH20: =SUM(Q20:T20) -> -25221 | AI20: =SUM(R20:U20) -> -24932 | AJ20: =SUM(S20:V20) -> -25111 | AK20: =SUM(T20:W20) -> -25378 | AL20: =SUM(U20:X20) -> -25725 | ... AQ20: =SUM(Z20:AC20) -> -27601 | AS20: =SUM(AQ20/AM20)-1 -> 0.057631145
B21: Earning before Interest & Taxes (EBIT) | C21: =SUM(C16+SUM(C19:C20)) -> 60024 | D21: =SUM(D16+SUM(D19:D20)) -> 61344 | E21: =SUM(E16+SUM(E19:E20)) -> 70898 | F21: =SUM(F16+SUM(F19:F20)) -> 63930 | G21: =SUM(G16+SUM(G19:G20)) -> 66288 | H21: =SUM(H16+SUM(H19:H20)) -> 108949 | I21: =SUM(I16+SUM(I19:I20)) -> 119437 | J21: =SUM(J16+SUM(J19:J20)) -> 114301 | ... L21: =SUM(L16+SUM(L19:L20)) -> 133050 | N21: =SUM(N16+SUM(N19:N20)) -> 41488 | O21: =SUM(O16+SUM(O19:O20)) -> 29979 | P21: =SUM(P16+SUM(P19:P20)) -> 23076 | Q21: =SUM(Q16+SUM(Q19:Q20)) -> 24894 | R21: =SUM(R16+SUM(R19:R20)) -> 36016 | S21: =SUM(S16+SUM(S19:S20)) -> 28318 | T21: =SUM(T16+SUM(T19:T20)) -> 22998 | U21: =SUM(U16+SUM(U19:U20)) -> 26969 | ... AC21: =SUM(AC16+SUM(AC19:AC20)) -> 32427 | AE21: =SUM(AE16+SUM(AE19:AE20)) -> 119437 | AF21: =SUM(AF16+SUM(AF19:AF20)) -> 113965 | AG21: =SUM(AG16+SUM(AG19:AG20)) -> 112304 | AH21: =SUM(AH16+SUM(AH19:AH20)) -> 112226 | AI21: =SUM(AI16+SUM(AI19:AI20)) -> 114301 | AJ21: =SUM(AJ16+SUM(AJ19:AJ20)) -> 118658 | AK21: =SUM(AK16+SUM(AK19:AK20)) -> 118240 | AL21: =SUM(AL16+SUM(AL19:AL20)) -> 120594 | ... AQ21: =SUM(AQ16+SUM(AQ19:AQ20)) -> 133050 | AS21: =SUM(AQ21/AM21)-1 -> 0.079811063
B22: Operating Margin (%) | C22: =C21/C11 -> 0.2783541 | D22: =D21/D11 -> 0.26760428 | E22: =E21/E11 -> 0.26694027 | F22: =F21/F11 -> 0.24572017 | G22: =G21/G11 -> 0.24147314 | H22: =H21/H11 -> 0.29782378 | I22: =I21/I11 -> 0.30288744 | J22: =J21/J11 -> 0.29821412 | ... L22: =L21/L11 -> 0.319708 | N22: =N21/N11 -> 0.33472911 | O22: =O21/O11 -> 0.30817862 | P22: =P21/P11 -> 0.2781615 | Q22: =Q21/Q11 -> 0.27615202 | R22: =R21/R11 -> 0.30742442 | S22: =S21/S11 -> 0.29859969 | T22: =T21/T11 -> 0.28115946 | U22: =U21/U11 -> 0.30133634 | ... AC22: =AC21/AC11 -> 0.31646595 | AE22: =AE21/AE11 -> 0.30288744 | AF22: =AF21/AF11 -> 0.29407515 | AG22: =AG21/AG11 -> 0.29162674 | AH22: =AH21/AH11 -> 0.29230621 | AI22: =AI21/AI11 -> 0.29821412 | AJ22: =AJ21/AJ11 -> 0.30763846 | AK22: =AK21/AK11 -> 0.30983457 | AL22: =AL21/AL11 -> 0.31274134 | ... AQ22: =AQ21/AQ11 -> 0.319708 | AS22: =SUM(AQ22-AM22)*10000 -> 46.057689
B24: (+) Depreciation and Amortization | C24: ='Historical Financials'!C78 -> 10505 | D24: ='Historical Financials'!D78 -> 10157 | E24: ='Historical Financials'!E78 -> 10903 | F24: ='Historical Financials'!F78 -> 12547 | G24: ='Historical Financials'!G78 -> 11056 | H24: ='Historical Financials'!H78 -> 11284 | I24: ='Historical Financials'!I78 -> 11104 | J24: ='Historical Financials'!J78 -> 11519 | ... L24: ='Historical Financials'!L78 -> 11698 | N24: ='Historical Financials'!N78 -> 2697 | O24: ='Historical Financials'!O78 -> 2737 | P24: ='Historical Financials'!P78 -> 2805 | Q24: ='Historical Financials'!Q78 -> 2865 | R24: ='Historical Financials'!R78 -> 2916 | S24: ='Historical Financials'!S78 -> 2898 | T24: ='Historical Financials'!T78 -> 3052 | U24: ='Historical Financials'!U78 -> 2653 | ... AC24: ='Historical Financials'!AC78 -> 3127 | AE24: =SUM(N24:Q24) -> 11104 | AF24: =SUM(O24:R24) -> 11323 | AG24: =SUM(P24:S24) -> 11484 | AH24: =SUM(Q24:T24) -> 11731 | AI24: =SUM(R24:U24) -> 11519 | AJ24: =SUM(S24:V24) -> 11451 | AK24: =SUM(T24:W24) -> 11389 | AL24: =SUM(U24:X24) -> 11187 | ... AQ24: =SUM(Z24:AC24) -> 11698 | AS24: =SUM(AQ24/AM24)-1 -> 0.022105723
