Workbook

Sheet Historical Financials
B2: Cassava Sciences (NASDAQ: SAVA)
B3: Historical Financials
B4: $ in thousands except per share
A6: X | B6: Income Statement | C6: FYE | G6: Quarterly | Q6: Quarterly | Y6: LTM | AE6: Variance
B7: Fiscal Period | C7: 2021 | D7: 2022 | E7: 2023 | G7: 1Q22 | H7: 2Q22 | I7: 3Q22 | J7: 4Q22 | K7: 1Q23 | L7: 2Q23 | M7: 3Q23 | N7: 4Q23 | O7: 1Q24 | P7: 2Q24 | Q7: 3Q24 | S7: =J7 -> 4Q22 | T7: =K7 -> 1Q23 | U7: =L7 -> 2Q23 | V7: =M7 -> 3Q23 | W7: =N7 -> 4Q23 | X7: =O7 -> 1Q24 | Y7: =P7 -> 2Q24 | Z7: =Q7 -> 3Q24 | AA7: =#REF! -> #REF! | AB7: =#REF! -> #REF! | AC7: =Q7 -> 3Q24
B8: Fiscal Period End Date | C8: 44561 | D8: 44926 | E8: 45291 | G8: 44651 | H8: 44742 | I8: 44834 | J8: 44926 | K8: 45016 | L8: 45107 | M8: 45199 | N8: 45291 | O8: 45382 | P8: 45473 | Q8: 45565 | S8: =J8 -> 44926 | T8: =K8 -> 45016 | U8: =L8 -> 45107 | V8: =M8 -> 45199 | W8: =N8 -> 45291 | X8: =O8 -> 45382 | Y8: =P8 -> 45473 | Z8: =Q8 -> 45565 | AA8: =#REF! -> #REF! | AB8: =#REF! -> #REF! | AC8: =Q8 -> 45565
B10: Consolidated Revenue | C10: 0 | D10: 0 | E10: 0 | G10: 0 | H10: 0 | I10: 0 | J10: =SUM(D10-SUM(G10:I10)) -> 0 | K10: 0 | L10: 0 | M10: 0 | N10: =SUM(E10-SUM(K10:M10)) -> 0 | O10: 0 | P10: 0 | Q10: 0 | S10: =SUM(D10:G10) -> 0 | T10: =SUM(E10:H10) -> 0 | U10: =SUM(F10:I10) -> 0 | V10: =SUM(G10:J10) -> 0 | W10: =SUM(H10:K10) -> 0 | X10: =SUM(I10:L10) -> 0 | Y10: =SUM(J10:M10) -> 0 | Z10: =SUM(K10:N10) -> 0 | ... AC10: =SUM(N10:Q10) -> 0 | AE10: =SUM(AC10/Y10)-1 -> #DIV/0!
B11: Total Revenue | C11: =+SUM(C10:C10) -> 0 | D11: =+SUM(D10:D10) -> 0 | E11: =+SUM(E10:E10) -> 0 | G11: =+SUM(G10:G10) -> 0 | H11: =+SUM(H10:H10) -> 0 | I11: =+SUM(I10:I10) -> 0 | J11: =+SUM(J10:J10) -> 0 | K11: =+SUM(K10:K10) -> 0 | L11: =+SUM(L10:L10) -> 0 | M11: =+SUM(M10:M10) -> 0 | N11: =+SUM(N10:N10) -> 0 | ... Q11: =+SUM(Q10:Q10) -> 0 | S11: =+SUM(S10:S10) -> 0 | T11: =+SUM(T10:T10) -> 0 | U11: =+SUM(U10:U10) -> 0 | V11: =+SUM(V10:V10) -> 0 | W11: =+SUM(W10:W10) -> 0 | X11: =+SUM(X10:X10) -> 0 | Y11: =+SUM(Y10:Y10) -> 0 | Z11: =+SUM(Z10:Z10) -> 0 | ... AC11: =+SUM(AC10:AC10) -> 0 | AE11: =SUM(AC11/Y11)-1 -> #DIV/0!
B13: Cost of Sales | C13: 0 | D13: 0 | E13: 0 | G13: 0 | H13: 0 | I13: 0 | J13: =SUM(D13-SUM(G13:I13)) -> 0 | K13: 0 | L13: 0 | M13: 0 | N13: =SUM(E13-SUM(K13:M13)) -> 0 | O13: 0 | P13: 0 | Q13: 0 | S13: =SUM(H13:K13) -> 0 | T13: =SUM(I13:L13) -> 0 | U13: =SUM(J13:M13) -> 0 | V13: =SUM(K13:N13) -> 0 | W13: =SUM(L13:O13) -> 0 | X13: =SUM(M13:P13) -> 0 | Y13: =SUM(J13:M13) -> 0 | Z13: =SUM(K13:N13) -> 0 | AA13: =SUM(L13:O13) -> 0 | AB13: =SUM(M13:P13) -> 0 | AC13: =SUM(N13:Q13) -> 0 | AE13: =SUM(AC13/Y13)-1 -> #DIV/0!
B14: Gross Profit | C14: =+SUM(C11+SUM(C13:C13)) -> 0 | D14: =+SUM(D11+SUM(D13:D13)) -> 0 | E14: =+SUM(E11+SUM(E13:E13)) -> 0 | G14: =+SUM(G11+SUM(G13:G13)) -> 0 | H14: =+SUM(H11+SUM(H13:H13)) -> 0 | I14: =+SUM(I11+SUM(I13:I13)) -> 0 | J14: =+SUM(J11+SUM(J13:J13)) -> 0 | K14: =+SUM(K11+SUM(K13:K13)) -> 0 | L14: =+SUM(L11+SUM(L13:L13)) -> 0 | M14: =+SUM(M11+SUM(M13:M13)) -> 0 | N14: =+SUM(N11+SUM(N13:N13)) -> 0 | ... Q14: =+SUM(Q11+SUM(Q13:Q13)) -> 0 | S14: =+SUM(S11+SUM(S13:S13)) -> 0 | T14: =+SUM(T11+SUM(T13:T13)) -> 0 | U14: =+SUM(U11+SUM(U13:U13)) -> 0 | V14: =+SUM(V11+SUM(V13:V13)) -> 0 | W14: =+SUM(W11+SUM(W13:W13)) -> 0 | X14: =+SUM(X11+SUM(X13:X13)) -> 0 | Y14: =+SUM(Y11+SUM(Y13:Y13)) -> 0 | Z14: =+SUM(Z11+SUM(Z13:Z13)) -> 0 | ... AC14: =+SUM(AC11+SUM(AC13:AC13)) -> 0 | AE14: =SUM(AC14/Y14)-1 -> #DIV/0!
B15: Gross Margin (%) | C15: =C14/C11 -> #DIV/0! | D15: =D14/D11 -> #DIV/0! | E15: =E14/E11 -> #DIV/0! | G15: =G14/G11 -> #DIV/0! | H15: =H14/H11 -> #DIV/0! | I15: =I14/I11 -> #DIV/0! | J15: =J14/J11 -> #DIV/0! | K15: =K14/K11 -> #DIV/0! | L15: =L14/L11 -> #DIV/0! | M15: =M14/M11 -> #DIV/0! | N15: =N14/N11 -> #DIV/0! | ... Q15: =Q14/Q11 -> #DIV/0! | S15: =S14/S11 -> #DIV/0! | T15: =T14/T11 -> #DIV/0! | U15: =U14/U11 -> #DIV/0! | V15: =V14/V11 -> #DIV/0! | W15: =W14/W11 -> #DIV/0! | X15: =X14/X11 -> #DIV/0! | Y15: =Y14/Y11 -> #DIV/0! | Z15: =Z14/Z11 -> #DIV/0! | ... AC15: =AC14/AC11 -> #DIV/0! | AE15: =SUM(AC15-Y15)*1000 -> #DIV/0!
B17: Research and development, net of grant reimbursement | C17: -24813 | D17: -68032 | E17: -89423 | G17: -14906 | H17: -16948 | I17: -18526 | J17: =SUM(D17-SUM(G17:I17)) -> -17652 | K17: -22120 | L17: -24969 | M17: -23603 | N17: =SUM(E17-SUM(K17:M17)) -> -18731 | O17: -16233 | P17: -15198 | Q17: -17676 | S17: =SUM(H17:K17) -> -75246 | T17: =SUM(I17:L17) -> -83267 | U17: =SUM(J17:M17) -> -88344 | V17: =SUM(K17:N17) -> -89423 | W17: =SUM(L17:O17) -> -83536 | X17: =SUM(M17:P17) -> -73765 | Y17: =SUM(J17:M17) -> -88344 | Z17: =SUM(K17:N17) -> -89423 | AA17: =SUM(L17:O17) -> -83536 | AB17: =SUM(M17:P17) -> -73765 | AC17: =SUM(N17:Q17) -> -67838 | AE17: =SUM(AC17/Y17)-1 -> -0.23211537
B18: General and administrative | C18: -8055 | D18: -11988 | E18: -16534 | G18: -2915 | H18: -2969 | I18: -2819 | J18: =SUM(D18-SUM(G18:I18)) -> -3285 | K18: -4392 | L18: -3808 | M18: -4276 | N18: =SUM(E18-SUM(K18:M18)) -> -4058 | O18: -3701 | P18: -46204 | Q18: -12947 | S18: =SUM(H18:K18) -> -13465 | T18: =SUM(I18:L18) -> -14304 | U18: =SUM(J18:M18) -> -15761 | V18: =SUM(K18:N18) -> -16534 | W18: =SUM(L18:O18) -> -15843 | X18: =SUM(M18:P18) -> -58239 | Y18: =SUM(J18:M18) -> -15761 | Z18: =SUM(K18:N18) -> -16534 | AA18: =SUM(L18:O18) -> -15843 | AB18: =SUM(M18:P18) -> -58239 | AC18: =SUM(N18:Q18) -> -66910 | AE18: =SUM(AC18/Y18)-1 -> 3.245289
B19: Operating Profit | C19: =+SUM(C14+SUM(C17:C18)) -> -32868 | D19: =+SUM(D14+SUM(D17:D18)) -> -80020 | E19: =+SUM(E14+SUM(E17:E18)) -> -105957 | G19: =+SUM(G14+SUM(G17:G18)) -> -17821 | H19: =+SUM(H14+SUM(H17:H18)) -> -19917 | I19: =+SUM(I14+SUM(I17:I18)) -> -21345 | J19: =+SUM(J14+SUM(J17:J18)) -> -20937 | K19: =+SUM(K14+SUM(K17:K18)) -> -26512 | L19: =+SUM(L14+SUM(L17:L18)) -> -28777 | M19: =+SUM(M14+SUM(M17:M18)) -> -27879 | N19: =+SUM(N14+SUM(N17:N18)) -> -22789 | ... Q19: =+SUM(Q14+SUM(Q17:Q18)) -> -30623 | S19: =+SUM(S14+SUM(S17:S18)) -> -88711 | T19: =+SUM(T14+SUM(T17:T18)) -> -97571 | U19: =+SUM(U14+SUM(U17:U18)) -> -104105 | V19: =+SUM(V14+SUM(V17:V18)) -> -105957 | W19: =+SUM(W14+SUM(W17:W18)) -> -99379 | X19: =+SUM(X14+SUM(X17:X18)) -> -132004 | Y19: =+SUM(Y14+SUM(Y17:Y18)) -> -104105 | Z19: =+SUM(Z14+SUM(Z17:Z18)) -> -105957 | ... AC19: =+SUM(AC14+SUM(AC17:AC18)) -> -134748 | AE19: =SUM(AC19/Y19)-1 -> 0.29434705
B20: Operating Margin (%) | C20: =C19/C11 -> #DIV/0! | D20: =D19/D11 -> #DIV/0! | E20: =E19/E11 -> #DIV/0! | G20: =G19/G11 -> #DIV/0! | H20: =H19/H11 -> #DIV/0! | I20: =I19/I11 -> #DIV/0! | J20: =J19/J11 -> #DIV/0! | K20: =K19/K11 -> #DIV/0! | L20: =L19/L11 -> #DIV/0! | M20: =M19/M11 -> #DIV/0! | N20: =N19/N11 -> #DIV/0! | ... Q20: =Q19/Q11 -> #DIV/0! | S20: =S19/S11 -> #DIV/0! | T20: =T19/T11 -> #DIV/0! | U20: =U19/U11 -> #DIV/0! | V20: =V19/V11 -> #DIV/0! | W20: =W19/W11 -> #DIV/0! | X20: =X19/X11 -> #DIV/0! | Y20: =Y19/Y11 -> #DIV/0! | Z20: =Z19/Z11 -> #DIV/0! | ... AC20: =AC19/AC11 -> #DIV/0! | AE20: =SUM(AC20-Y20)*1000 -> #DIV/0!
B22: Interest income | C22: 49 | D22: 2777 | E22: 7833 | G22: 31 | H22: 314 | I22: 878 | J22: =SUM(D22-SUM(G22:I22)) -> 1554 | K22: 2051 | L22: 2198 | M22: 2005 | N22: =SUM(E22-SUM(K22:M22)) -> 1579 | O22: 1776 | P22: 2316 | Q22: 2618 | S22: =SUM(H22:K22) -> 4797 | T22: =SUM(I22:L22) -> 6681 | U22: =SUM(J22:M22) -> 7808 | V22: =SUM(K22:N22) -> 7833 | W22: =SUM(L22:O22) -> 7558 | X22: =SUM(M22:P22) -> 7676 | Y22: =SUM(J22:M22) -> 7808 | Z22: =SUM(K22:N22) -> 7833 | AA22: =SUM(L22:O22) -> 7558 | AB22: =SUM(M22:P22) -> 7676 | AC22: =SUM(N22:Q22) -> 8289 | AE22: =SUM(AC22/Y22)-1 -> 0.061603484
B23: Other income, net | C23: 434 | D23: 997 | E23: 907 | G23: 263 | H23: 275 | I23: 210 | J23: =SUM(D23-SUM(G23:I23)) -> 249 | K23: 190 | L23: 203 | M23: 223 | N23: =SUM(E23-SUM(K23:M23)) -> 291 | O23: 160 | P23: 99 | Q23: 62 | Y23: =SUM(J23:M23) -> 865 | Z23: =SUM(K23:N23) -> 907 | AA23: =SUM(L23:O23) -> 877 | AB23: =SUM(M23:P23) -> 773 | AC23: =SUM(N23:Q23) -> 612 | AE23: =SUM(AC23/Y23)-1 -> -0.29248555
B24: Gain from change in fair value of warrant liabilities | C24: 0 | D24: 0 | E24: 0 | G24: 0 | H24: 0 | I24: 0 | J24: =SUM(D24-SUM(G24:I24)) -> 0 | K24: 0 | L24: 0 | M24: 0 | N24: =SUM(E24-SUM(K24:M24)) -> 0 | O24: 43041 | P24: 65142 | Q24: 0 | Y24: =SUM(J24:M24) -> 0 | Z24: =SUM(K24:N24) -> 0 | AA24: =SUM(L24:O24) -> 43041 | AB24: =SUM(M24:P24) -> 108183 | AC24: =SUM(N24:Q24) -> 108183 | AE24: =SUM(AC24/Y24)-1 -> #DIV/0!
B25: Earning Before Taxes | C25: =SUM(C19+SUM(C22:C24)) -> -32385 | D25: =SUM(D19+SUM(D22:D24)) -> -76246 | E25: =SUM(E19+SUM(E22:E24)) -> -97217 | G25: =SUM(G19+SUM(G22:G24)) -> -17527 | H25: =SUM(H19+SUM(H22:H24)) -> -19328 | I25: =SUM(I19+SUM(I22:I24)) -> -20257 | J25: =SUM(J19+SUM(J22:J24)) -> -19134 | K25: =SUM(K19+SUM(K22:K24)) -> -24271 | L25: =SUM(L19+SUM(L22:L24)) -> -26376 | M25: =SUM(M19+SUM(M22:M24)) -> -25651 | N25: =SUM(N19+SUM(N22:N24)) -> -20919 | ... Q25: =SUM(Q19+SUM(Q22:Q24)) -> -27943 | S25: =SUM(S19+SUM(S22:S24)) -> -83914 | T25: =SUM(T19+SUM(T22:T24)) -> -90890 | U25: =SUM(U19+SUM(U22:U24)) -> -96297 | V25: =SUM(V19+SUM(V22:V24)) -> -98124 | W25: =SUM(W19+SUM(W22:W24)) -> -91821 | X25: =SUM(X19+SUM(X22:X24)) -> -124328 | Y25: =SUM(Y19+SUM(Y22:Y24)) -> -95432 | Z25: =SUM(Z19+SUM(Z22:Z24)) -> -97217 | ... AC25: =SUM(AC19+SUM(AC22:AC24)) -> -17664 | AE25: =SUM(AC25/Y25)-1 -> -0.81490485
B26: EBT Margin (%) | C26: =C25/C11 -> #DIV/0! | D26: =D25/D11 -> #DIV/0! | E26: =E25/E11 -> #DIV/0! | G26: =G25/G11 -> #DIV/0! | H26: =H25/H11 -> #DIV/0! | I26: =I25/I11 -> #DIV/0! | J26: =J25/J11 -> #DIV/0! | K26: =K25/K11 -> #DIV/0! | L26: =L25/L11 -> #DIV/0! | M26: =M25/M11 -> #DIV/0! | N26: =N25/N11 -> #DIV/0! | ... Q26: =Q25/Q11 -> #DIV/0! | S26: =S25/S11 -> #DIV/0! | T26: =T25/T11 -> #DIV/0! | U26: =U25/U11 -> #DIV/0! | V26: =V25/V11 -> #DIV/0! | W26: =W25/W11 -> #DIV/0! | X26: =X25/X11 -> #DIV/0! | Y26: =Y25/Y11 -> #DIV/0! | Z26: =Z25/Z11 -> #DIV/0! | ... AC26: =AC25/AC11 -> #DIV/0! | AE26: =SUM(AC26-Y26)*1000 -> #DIV/0!
B28: Provision for taxes | C28: 0 | D28: 0 | E28: 0 | G28: 0 | H28: 0 | I28: 0 | J28: =SUM(C28-SUM(G28:I28)) -> 0 | K28: 0 | L28: 0 | M28: 0 | N28: =SUM(D28-SUM(K28:M28)) -> 0 | O28: 0 | P28: 0 | Q28: 0 | S28: =SUM(H28:K28) -> 0 | T28: =SUM(I28:L28) -> 0 | U28: =SUM(J28:M28) -> 0 | V28: =SUM(K28:N28) -> 0 | W28: =SUM(L28:O28) -> 0 | X28: =SUM(M28:P28) -> 0 | Y28: =SUM(J28:M28) -> 0 | Z28: =SUM(K28:N28) -> 0 | AA28: =SUM(L28:O28) -> 0 | AB28: =SUM(M28:P28) -> 0 | AC28: =SUM(N28:Q28) -> 0 | AE28: =SUM(AC28/Y28)-1 -> #DIV/0!
B29: Net loss | C29: =SUM(C25+C28) -> -32385 | D29: =SUM(D25+D28) -> -76246 | E29: =SUM(E25+E28) -> -97217 | G29: =SUM(G25+G28) -> -17527 | H29: =SUM(H25+H28) -> -19328 | I29: =SUM(I25+I28) -> -20257 | J29: =SUM(J25+J28) -> -19134 | K29: =SUM(K25+K28) -> -24271 | L29: =SUM(L25+L28) -> -26376 | M29: =SUM(M25+M28) -> -25651 | N29: =SUM(N25+N28) -> -20919 | ... Q29: =SUM(Q25+Q28) -> -27943 | S29: =SUM(S25+S28) -> -83914 | T29: =SUM(T25+T28) -> -90890 | U29: =SUM(U25+U28) -> -96297 | V29: =SUM(V25+V28) -> -98124 | W29: =SUM(W25+W28) -> -91821 | X29: =SUM(X25+X28) -> -124328 | Y29: =SUM(Y25+Y28) -> -95432 | Z29: =SUM(Z25+Z28) -> -97217 | ... AC29: =SUM(AC25+AC28) -> -17664 | AE29: =SUM(AC29/Y29)-1 -> -0.81490485
B30: Net Margin (%) | C30: =C29/C11 -> #DIV/0! | D30: =D29/D11 -> #DIV/0! | E30: =E29/E11 -> #DIV/0! | G30: =G29/G11 -> #DIV/0! | H30: =H29/H11 -> #DIV/0! | I30: =I29/I11 -> #DIV/0! | J30: =J29/J11 -> #DIV/0! | K30: =K29/K11 -> #DIV/0! | L30: =L29/L11 -> #DIV/0! | M30: =M29/M11 -> #DIV/0! | N30: =N29/N11 -> #DIV/0! | ... Q30: =Q29/Q11 -> #DIV/0! | S30: =S29/S11 -> #DIV/0! | T30: =T29/T11 -> #DIV/0! | U30: =U29/U11 -> #DIV/0! | V30: =V29/V11 -> #DIV/0! | W30: =W29/W11 -> #DIV/0! | X30: =X29/X11 -> #DIV/0! | Y30: =Y29/Y11 -> #DIV/0! | Z30: =Z29/Z11 -> #DIV/0! | ... AC30: =AC29/AC11 -> #DIV/0! | AE30: =SUM(AC30-Y30)*1000 -> #DIV/0!
B32: Basic shares | J32: =C32 -> 0 | N32: =D32 -> 0 | S32: =G32 -> 0 | T32: =H32 -> 0 | U32: =I32 -> 0 | V32: =J32 -> 0 | W32: =K32 -> 0 | X32: =L32 -> 0 | Y32: =M32 -> 0 | Z32: =N32 -> 0 | ... AC32: =Q32 -> 0 | AE32: =SUM(AC32/Y32)-1 -> #DIV/0!
B33: Basic EPS | C33: =C29/C32 -> #DIV/0! | D33: =D29/D32 -> #DIV/0! | E33: =E29/E32 -> #DIV/0! | G33: =G29/G32 -> #DIV/0! | H33: =H29/H32 -> #DIV/0! | I33: =I29/I32 -> #DIV/0! | J33: =J29/J32 -> #DIV/0! | K33: =K29/K32 -> #DIV/0! | L33: =L29/L32 -> #DIV/0! | M33: =M29/M32 -> #DIV/0! | N33: =N29/N32 -> #DIV/0! | ... Q33: =Q29/Q32 -> #DIV/0! | S33: =S29/S32 -> #DIV/0! | T33: =T29/T32 -> #DIV/0! | U33: =U29/U32 -> #DIV/0! | V33: =V29/V32 -> #DIV/0! | W33: =W29/W32 -> #DIV/0! | X33: =X29/X32 -> #DIV/0! | Y33: =Y29/Y32 -> #DIV/0! | Z33: =Z29/Z32 -> #DIV/0! | ... AC33: =AC29/AC32 -> #DIV/0! | AE33: =SUM(AC33/Y33)-1 -> #DIV/0!
B35: Fully Diluted Shares | J35: =C35 -> 0 | N35: =D35 -> 0 | S35: =K35 -> 0 | T35: =L35 -> 0 | U35: =M35 -> 0 | V35: =N35 -> 0 | W35: =O35 -> 0 | X35: =P35 -> 0 | Y35: =M35 -> 0 | Z35: =N35 -> 0 | AA35: =O35 -> 0 | AB35: =P35 -> 0 | AC35: =Q35 -> 0 | AE35: =SUM(AC35/Y35)-1 -> #DIV/0!
B36: Diluted EPS | C36: =C29/C35 -> #DIV/0! | D36: =D29/D35 -> #DIV/0! | E36: =E29/E35 -> #DIV/0! | G36: =G29/G35 -> #DIV/0! | H36: =H29/H35 -> #DIV/0! | I36: =I29/I35 -> #DIV/0! | J36: =J29/J35 -> #DIV/0! | K36: =K29/K35 -> #DIV/0! | L36: =L29/L35 -> #DIV/0! | M36: =M29/M35 -> #DIV/0! | N36: =N29/N35 -> #DIV/0! | ... Q36: =Q29/Q35 -> #DIV/0! | S36: =S29/S35 -> #DIV/0! | T36: =T29/T35 -> #DIV/0! | U36: =U29/U35 -> #DIV/0! | V36: =V29/V35 -> #DIV/0! | W36: =W29/W35 -> #DIV/0! | X36: =X29/X35 -> #DIV/0! | Y36: =Y29/Y35 -> #DIV/0! | Z36: =Z29/Z35 -> #DIV/0! | ... AC36: =AC29/AC35 -> #DIV/0! | AE36: =SUM(AC36/Y36)-1 -> #DIV/0!
A38: X | B38: Balance Sheet | C38: FYE | G38: Quarterly | Q38: Quarterly | Y38: LTM | AE38: Variance
B39: =B7 -> Fiscal Period | C39: =C7 -> 2021 | D39: =D7 -> 2022 | E39: =E7 -> 2023 | G39: =G7 -> 1Q22 | H39: =H7 -> 2Q22 | I39: =I7 -> 3Q22 | J39: =J7 -> 4Q22 | K39: =K7 -> 1Q23 | L39: =L7 -> 2Q23 | M39: =M7 -> 3Q23 | N39: =N7 -> 4Q23 | ... Q39: =Q7 -> 3Q24 | S39: =S7 -> 4Q22 | T39: =T7 -> 1Q23 | U39: =U7 -> 2Q23 | V39: =V7 -> 3Q23 | W39: =W7 -> 4Q23 | X39: =X7 -> 1Q24 | Y39: =Y7 -> 2Q24 | Z39: =Z7 -> 3Q24 | ... AC39: =AC7 -> 3Q24
B40: =B8 -> Fiscal Period End Date | C40: =C8 -> 44561 | D40: =D8 -> 44926 | E40: =E8 -> 45291 | G40: =G8 -> 44651 | H40: =H8 -> 44742 | I40: =I8 -> 44834 | J40: =J8 -> 44926 | K40: =K8 -> 45016 | L40: =L8 -> 45107 | M40: =M8 -> 45199 | N40: =N8 -> 45291 | ... Q40: =Q8 -> 45565 | S40: =S8 -> 44926 | T40: =T8 -> 45016 | U40: =U8 -> 45107 | V40: =V8 -> 45199 | W40: =W8 -> 45291 | X40: =X8 -> 45382 | Y40: =Y8 -> 45473 | Z40: =Z8 -> 45565 | ... AC40: =AC8 -> 45565
B42: Current Assets
B43: Cash and cash equivalents | C43: 233437 | D43: 201015 | E43: 121136 | G43: 209693 | H43: 197232 | I43: 174662 | J43: =D43 -> 201015 | K43: 187467 | L43: 168438 | M43: 142350 | N43: =E43 -> 121136 | O43: 124169 | P43: 207291 | Q43: 148978 | S43: =G43 -> 209693 | T43: =H43 -> 197232 | U43: =I43 -> 174662 | V43: =J43 -> 201015 | W43: =K43 -> 187467 | X43: =L43 -> 168438 | Y43: =M43 -> 142350 | Z43: =N43 -> 121136 | ... AC43: =Q43 -> 148978 | AE43: =SUM(AC43/Y43)-1 -> 0.046561293
B44: Prepaid expenses and other current assets | C44: 11045 | D44: 10211 | E44: 8497 | G44: 12507 | H44: 6969 | I44: 8610 | J44: =D44 -> 10211 | K44: 7532 | L44: 6095 | M44: 7834 | N44: =E44 -> 8497 | O44: 9830 | P44: 14831 | Q44: 13571 | S44: =G44 -> 12507 | T44: =H44 -> 6969 | U44: =I44 -> 8610 | V44: =J44 -> 10211 | W44: =K44 -> 7532 | X44: =L44 -> 6095 | Y44: =M44 -> 7834 | Z44: =N44 -> 8497 | ... AC44: =Q44 -> 13571 | AE44: =SUM(AC44/Y44)-1 -> 0.73232065
B45: Restricted cash | C45: 0 | D45: 0 | E45: 0 | G45: 0 | H45: 0 | I45: 0 | J45: =D45 -> 0 | K45: 0 | L45: 0 | M45: 0 | N45: =E45 -> 0 | O45: 0 | P45: 0 | Q45: 40000 | S45: =G45 -> 0 | T45: =H45 -> 0 | U45: =I45 -> 0 | V45: =J45 -> 0 | W45: =K45 -> 0 | X45: =L45 -> 0 | Y45: =M45 -> 0 | Z45: =N45 -> 0 | ... AC45: =Q45 -> 40000 | AE45: =SUM(AC45/Y45)-1 -> #DIV/0!
B46: Total Current Assets | C46: =SUM(C43:C45) -> 244482 | D46: =SUM(D43:D45) -> 211226 | E46: =SUM(E43:E45) -> 129633 | G46: =SUM(G43:G45) -> 222200 | H46: =SUM(H43:H45) -> 204201 | I46: =SUM(I43:I45) -> 183272 | J46: =SUM(J43:J45) -> 211226 | K46: =SUM(K43:K45) -> 194999 | L46: =SUM(L43:L45) -> 174533 | M46: =SUM(M43:M45) -> 150184 | N46: =SUM(N43:N45) -> 129633 | ... Q46: =SUM(Q43:Q45) -> 202549 | S46: =SUM(S43:S45) -> 222200 | T46: =SUM(T43:T45) -> 204201 | U46: =SUM(U43:U45) -> 183272 | V46: =SUM(V43:V45) -> 211226 | W46: =SUM(W43:W45) -> 194999 | X46: =SUM(X43:X45) -> 174533 | Y46: =SUM(Y43:Y45) -> 150184 | Z46: =SUM(Z43:Z45) -> 129633 | ... AC46: =SUM(AC43:AC45) -> 202549 | AE46: =SUM(AC46/Y46)-1 -> 0.3486723
B48: Non-Current Assets
B49: Operating lease right-of-use assets | C49: 210 | D49: 122 | E49: 0 | G49: 188 | H49: 166 | I49: 144 | J49: =D49 -> 122 | K49: - | L49: - | M49: - | N49: =E49 -> 0 | O49: - | P49: - | Q49: - | S49: =J49 -> 122 | T49: =K49 -> - | U49: =L49 -> - | V49: =M49 -> - | W49: =N49 -> 0 | X49: =O49 -> - | Y49: =M49 -> - | Z49: =N49 -> 0 | AA49: =O49 -> - | AB49: =P49 -> - | AC49: =Q49 -> - | AE49: =SUM(AC49/Y49)-1 -> #VALUE!
B50: Property and equipment, net | C50: 20616 | D50: 22864 | E50: 21854 | G50: 20863 | H50: 22155 | I50: 23130 | J50: =D50 -> 22864 | K50: 22609 | L50: 22328 | M50: 22077 | N50: =E50 -> 21854 | O50: 21604 | P50: 21364 | Q50: 21135 | S50: =K50 -> 22609 | T50: =L50 -> 22328 | U50: =M50 -> 22077 | V50: =N50 -> 21854 | W50: =O50 -> 21604 | X50: =P50 -> 21364 | Y50: =M50 -> 22077 | Z50: =N50 -> 21854 | AA50: =O50 -> 21604 | AB50: =P50 -> 21364 | AC50: =Q50 -> 21135 | AE50: =SUM(AC50/Y50)-1 -> -0.042668841
B51: Intangible assets, net | C51: 1075 | D51: 622 | E51: 176 | G51: 940 | H51: 859 | I51: 740 | J51: =D51 -> 622 | K51: 503 | L51: 387 | M51: 268 | N51: =E51 -> 176 | O51: 115 | P51: 82 | Q51: 0 | S51: =K51 -> 503 | T51: =L51 -> 387 | U51: =M51 -> 268 | V51: =N51 -> 176 | W51: =O51 -> 115 | X51: =P51 -> 82 | Y51: =M51 -> 268 | Z51: =N51 -> 176 | AA51: =O51 -> 115 | AB51: =P51 -> 82 | AC51: =Q51 -> 0 | AE51: =SUM(AC51/Y51)-1 -> -1
B52: Other assets | C52: 399 | D52: 0 | E52: 0 | G52: 0 | H52: 0 | I52: 0 | J52: =D52 -> 0 | L52: - | M52: - | N52: =E52 -> 0 | O52: 0 | P52: 0 | Q52: 0 | S52: =K52 -> 0 | T52: =L52 -> - | U52: =M52 -> - | V52: =N52 -> 0 | W52: =O52 -> 0 | X52: =P52 -> 0 | Y52: =M52 -> - | Z52: =N52 -> 0 | AA52: =O52 -> 0 | AB52: =P52 -> 0 | AC52: =Q52 -> 0 | AE52: =SUM(AC52/Y52)-1 -> #VALUE!
B53: Total Assets | C53: =SUM(C49:C52)+C46 -> 266782 | D53: =SUM(D49:D52)+D46 -> 234834 | E53: =SUM(E49:E52)+E46 -> 151663 | G53: =SUM(G49:G52)+G46 -> 244191 | H53: =SUM(H49:H52)+H46 -> 227381 | I53: =SUM(I49:I52)+I46 -> 207286 | J53: =SUM(J49:J52)+J46 -> 234834 | K53: =SUM(K49:K52)+K46 -> 218111 | L53: =SUM(L49:L52)+L46 -> 197248 | M53: =SUM(M49:M52)+M46 -> 172529 | N53: =SUM(N49:N52)+N46 -> 151663 | ... Q53: =SUM(Q49:Q52)+Q46 -> 223684 | S53: =SUM(S49:S52)+S46 -> 245434 | T53: =SUM(T49:T52)+T46 -> 226916 | U53: =SUM(U49:U52)+U46 -> 205617 | V53: =SUM(V49:V52)+V46 -> 233256 | W53: =SUM(W49:W52)+W46 -> 216718 | X53: =SUM(X49:X52)+X46 -> 195979 | Y53: =SUM(Y49:Y52)+Y46 -> 172529 | Z53: =SUM(Z49:Z52)+Z46 -> 151663 | ... AC53: =SUM(AC49:AC52)+AC46 -> 223684 | AE53: =SUM(AC53/Y53)-1 -> 0.29650088
B55: Current Liabilities
B56: Accounts payable and other accrued expenses | C56: 7126 | D56: 4017 | E56: 10573 | G56: 3332 | H56: 4758 | I56: 3534 | J56: =D56 -> 4017 | K56: 8242 | L56: 10338 | M56: 9492 | N56: =E56 -> 10573 | O56: 9603 | P56: 52552 | Q56: 52244 | S56: =K56 -> 8242 | T56: =L56 -> 10338 | U56: =M56 -> 9492 | V56: =N56 -> 10573 | W56: =O56 -> 9603 | X56: =P56 -> 52552 | Y56: =M56 -> 9492 | Z56: =N56 -> 10573 | AA56: =O56 -> 9603 | AB56: =P56 -> 52552 | AC56: =Q56 -> 52244 | AE56: =SUM(AC56/Y56)-1 -> 4.5040034
B57: Accrued development expense | C57: 2803 | D57: 2280 | E57: 3037 | G57: 2925 | H57: 3318 | I57: 4096 | J57: =D57 -> 2280 | K57: 5276 | L57: 7044 | M57: 7344 | N57: =E57 -> 3037 | O57: 1797 | P57: 1596 | Q57: 2543 | S57: =K57 -> 5276 | T57: =L57 -> 7044 | U57: =M57 -> 7344 | V57: =N57 -> 3037 | W57: =O57 -> 1797 | X57: =P57 -> 1596 | Y57: =M57 -> 7344 | Z57: =N57 -> 3037 | AA57: =O57 -> 1797 | AB57: =P57 -> 1596 | AC57: =Q57 -> 2543 | AE57: =SUM(AC57/Y57)-1 -> -0.65373094
B58: Accrued compensation and benefits | C58: 1877 | D58: 170 | E58: 200 | G58: 172 | H58: 176 | I58: 160 | J58: =D58 -> 170 | K58: 212 | L58: 220 | M58: 187 | N58: =E58 -> 200 | O58: 228 | P58: 218 | Q58: 1950 | Y58: =M58 -> 187 | Z58: =N58 -> 200 | AA58: =O58 -> 228 | AB58: =P58 -> 218 | AC58: =Q58 -> 1950 | AE58: =SUM(AC58/Y58)-1 -> 9.4278075
B59: Operating lease liabilities, current | C59: 97 | D59: 104 | E59: 0 | G59: 99 | H59: 100 | I59: 102 | J59: =D59 -> 104 | K59: 0 | L59: 0 | M59: 0 | N59: =E59 -> 0 | O59: - | P59: 0 | Q59: 0 | Y59: =M59 -> 0 | Z59: =N59 -> 0 | AA59: =O59 -> - | AB59: =P59 -> 0 | AC59: =Q59 -> 0 | AE59: =SUM(AC59/Y59)-1 -> #DIV/0!
B60: Warrant liabilities | C60: 0 | D60: 0 | E60: 0 | G60: 0 | H60: 0 | I60: 0 | J60: =D60 -> 0 | K60: 0 | L60: 0 | M60: 0 | N60: =E60 -> 0 | O60: 65368 | P60: 0 | Q60: 0 | S60: =K60 -> 0 | T60: =L60 -> 0 | U60: =M60 -> 0 | V60: =N60 -> 0 | W60: =O60 -> 65368 | X60: =P60 -> 0 | Y60: =M60 -> 0 | Z60: =N60 -> 0 | AA60: =O60 -> 65368 | AB60: =P60 -> 0 | AC60: =Q60 -> 0 | AE60: =SUM(AC60/Y60)-1 -> #DIV/0!
B61: Other current liabilities | C61: 631 | D61: 492 | E61: 385 | G61: 261 | H61: 370 | I61: 416 | J61: =D61 -> 492 | K61: 179 | L61: 293 | M61: 391 | N61: =E61 -> 385 | O61: 125 | P61: 228 | Q61: 297 | S61: =K61 -> 179 | T61: =L61 -> 293 | U61: =M61 -> 391 | V61: =N61 -> 385 | W61: =O61 -> 125 | X61: =P61 -> 228 | Y61: =M61 -> 391 | Z61: =N61 -> 385 | AA61: =O61 -> 125 | AB61: =P61 -> 228 | AC61: =Q61 -> 297 | AE61: =SUM(AC61/Y61)-1 -> -0.24040921
B62: Total Current Liabilities | C62: =SUM(C56:C61) -> 12534 | D62: =SUM(D56:D61) -> 7063 | E62: =SUM(E56:E61) -> 14195 | G62: =SUM(G56:G61) -> 6789 | H62: =SUM(H56:H61) -> 8722 | I62: =SUM(I56:I61) -> 8308 | J62: =SUM(J56:J61) -> 7063 | K62: =SUM(K56:K61) -> 13909 | L62: =SUM(L56:L61) -> 17895 | M62: =SUM(M56:M61) -> 17414 | N62: =SUM(N56:N61) -> 14195 | ... Q62: =SUM(Q56:Q61) -> 57034 | S62: =SUM(S56:S61) -> 13697 | T62: =SUM(T56:T61) -> 17675 | U62: =SUM(U56:U61) -> 17227 | V62: =SUM(V56:V61) -> 13995 | W62: =SUM(W56:W61) -> 76893 | X62: =SUM(X56:X61) -> 54376 | Y62: =SUM(Y56:Y61) -> 17414 | Z62: =SUM(Z56:Z61) -> 14195 | ... AC62: =SUM(AC56:AC61) -> 57034 | AE62: =SUM(AC62/Y62)-1 -> 2.2751809
B64: Non-Current Liabilities
B65: Operating lease liabilities, non-current | C65: 139 | D65: 35 | E65: 0 | G65: 114 | H65: 88 | I65: 62 | J65: =D65 -> 35 | K65: 0 | L65: 0 | M65: 0 | N65: =E65 -> 0 | O65: 0 | P65: 0 | Q65: 0 | S65: =K65 -> 0 | T65: =L65 -> 0 | U65: =M65 -> 0 | V65: =N65 -> 0 | W65: =O65 -> 0 | X65: =P65 -> 0 | Y65: =M65 -> 0 | Z65: =N65 -> 0 | AA65: =O65 -> 0 | AB65: =P65 -> 0 | AC65: =Q65 -> 0 | AE65: =SUM(AC65/Y65)-1 -> #DIV/0!
B66: Other non-current liabilities | C66: 194 | D66: 197 | E66: 0 | G66: 194 | H66: 201 | I66: 197 | J66: =D66 -> 197 | K66: 197 | L66: 0 | M66: 0 | N66: =E66 -> 0 | O66: 0 | P66: 0 | Q66: 80 | S66: =K66 -> 197 | T66: =L66 -> 0 | U66: =M66 -> 0 | V66: =N66 -> 0 | W66: =O66 -> 0 | X66: =P66 -> 0 | Y66: =M66 -> 0 | Z66: =N66 -> 0 | AA66: =O66 -> 0 | AB66: =P66 -> 0 | AC66: =Q66 -> 80 | AE66: =SUM(AC66/Y66)-1 -> #DIV/0!
B67: Total Liabilities | C67: =SUM(C65:C66)+C62 -> 12867 | D67: =SUM(D65:D66)+D62 -> 7295 | E67: =SUM(E65:E66)+E62 -> 14195 | G67: =SUM(G65:G66)+G62 -> 7097 | H67: =SUM(H65:H66)+H62 -> 9011 | I67: =SUM(I65:I66)+I62 -> 8567 | J67: =SUM(J65:J66)+J62 -> 7295 | K67: =SUM(K65:K66)+K62 -> 14106 | L67: =SUM(L65:L66)+L62 -> 17895 | M67: =SUM(M65:M66)+M62 -> 17414 | N67: =SUM(N65:N66)+N62 -> 14195 | ... Q67: =SUM(Q65:Q66)+Q62 -> 57114 | S67: =SUM(S65:S66)+S62 -> 13894 | T67: =SUM(T65:T66)+T62 -> 17675 | U67: =SUM(U65:U66)+U62 -> 17227 | V67: =SUM(V65:V66)+V62 -> 13995 | W67: =SUM(W65:W66)+W62 -> 76893 | X67: =SUM(X65:X66)+X62 -> 54376 | Y67: =SUM(Y65:Y66)+Y62 -> 17414 | Z67: =SUM(Z65:Z66)+Z62 -> 14195 | ... AC67: =SUM(AC65:AC66)+AC62 -> 57114 | AE67: =SUM(AC67/Y67)-1 -> 2.2797749
B69: Preferred stock | J69: =D69 -> 0 | N69: =E69 -> 0 | S69: =K69 -> 0 | T69: =L69 -> 0 | U69: =M69 -> 0 | V69: =N69 -> 0 | W69: =O69 -> 0 | X69: =P69 -> 0 | Y69: =M69 -> 0 | Z69: =N69 -> 0 | AA69: =O69 -> 0 | AB69: =P69 -> 0 | AC69: =Q69 -> 0 | AE69: =SUM(AC69/Y69)-1 -> #DIV/0!
B70: Common stock | C70: 40 | D70: 42 | E70: 42 | G70: 40 | H70: 40 | I70: 40 | J70: =D70 -> 42 | K70: 42 | L70: 42 | M70: 42 | N70: =E70 -> 42 | O70: 43 | P70: 48 | Q70: 48 | Y70: =M70 -> 42 | Z70: =N70 -> 42 | AA70: =O70 -> 43 | AB70: =P70 -> 48 | AC70: =Q70 -> 48 | AE70: =SUM(AC70/Y70)-1 -> 0.14285714
B71: Additional paid-in capital | C71: 461181 | D71: 511049 | E71: 518195 | G71: 461887 | H71: 462491 | I71: 463097 | J71: =D71 -> 511049 | K71: 511786 | L71: 513510 | M71: 514923 | N71: =E71 -> 518195 | O71: 434280 | P71: 538497 | Q71: 544105 | Y71: =M71 -> 514923 | Z71: =N71 -> 518195 | AA71: =O71 -> 434280 | AB71: =P71 -> 538497 | AC71: =Q71 -> 544105 | AE71: =SUM(AC71/Y71)-1 -> 0.056672551
B72: Accumulated deficit | C72: -207306 | D72: -283552 | E72: -380769 | G72: -224833 | H72: -244161 | I72: -264418 | J72: =D72 -> -283552 | K72: -307823 | L72: -334199 | M72: -359850 | N72: =E72 -> -380769 | O72: -355726 | P72: -349571 | Q72: -377514 | S72: =K72 -> -307823 | T72: =L72 -> -334199 | U72: =M72 -> -359850 | V72: =N72 -> -380769 | W72: =O72 -> -355726 | X72: =P72 -> -349571 | Y72: =M72 -> -359850 | Z72: =N72 -> -380769 | AA72: =O72 -> -355726 | AB72: =P72 -> -349571 | AC72: =Q72 -> -377514 | AE72: =SUM(AC72/Y72)-1 -> 0.04908712
B73: Total stockholders' equity | C73: =SUM(C69:C72) -> 253915 | D73: =SUM(D69:D72) -> 227539 | E73: =SUM(E69:E72) -> 137468 | G73: =SUM(G69:G72) -> 237094 | H73: =SUM(H69:H72) -> 218370 | I73: =SUM(I69:I72) -> 198719 | J73: =SUM(J69:J72) -> 227539 | K73: =SUM(K69:K72) -> 204005 | L73: =SUM(L69:L72) -> 179353 | M73: =SUM(M69:M72) -> 155115 | N73: =SUM(N69:N72) -> 137468 | ... Q73: =SUM(Q69:Q72) -> 166639 | S73: =SUM(S69:S72) -> -307823 | T73: =SUM(T69:T72) -> -334199 | U73: =SUM(U69:U72) -> -359850 | V73: =SUM(V69:V72) -> -380769 | W73: =SUM(W69:W72) -> -355726 | X73: =SUM(X69:X72) -> -349571 | Y73: =SUM(Y69:Y72) -> 155115 | Z73: =SUM(Z69:Z72) -> 137468 | ... AC73: =SUM(AC69:AC72) -> 166639 | AE73: =SUM(AC73/Y73)-1 -> 0.074293266
B74: Total liabilities and stockholders' equity | C74: =SUM(C73+C67) -> 266782 | D74: =SUM(D73+D67) -> 234834 | E74: =SUM(E73+E67) -> 151663 | G74: =SUM(G73+G67) -> 244191 | H74: =SUM(H73+H67) -> 227381 | I74: =SUM(I73+I67) -> 207286 | J74: =SUM(J73+J67) -> 234834 | K74: =SUM(K73+K67) -> 218111 | L74: =SUM(L73+L67) -> 197248 | M74: =SUM(M73+M67) -> 172529 | N74: =SUM(N73+N67) -> 151663 | ... Q74: =SUM(Q73+Q67) -> 223753 | S74: =SUM(S73+S67) -> -293929 | T74: =SUM(T73+T67) -> -316524 | U74: =SUM(U73+U67) -> -342623 | V74: =SUM(V73+V67) -> -366774 | W74: =SUM(W73+W67) -> -278833 | X74: =SUM(X73+X67) -> -295195 | Y74: =SUM(Y73+Y67) -> 172529 | Z74: =SUM(Z73+Z67) -> 151663 | ... AC74: =SUM(AC73+AC67) -> 223753 | AE74: =SUM(AC74/Y74)-1 -> 0.29690081
B76: Balance Check | C76: =C74-C53 -> 0 | D76: =D74-D53 -> 0 | E76: =E74-E53 -> 0 | G76: =G74-G53 -> 0 | H76: =H74-H53 -> 0 | I76: =I74-I53 -> 0 | J76: =J74-J53 -> 0 | K76: =K74-K53 -> 0 | L76: =L74-L53 -> 0 | M76: =M74-M53 -> 0 | N76: =N74-N53 -> 0 | ... Q76: =Q74-Q53 -> 69 | S76: =S74-S53 -> -539363 | T76: =T74-T53 -> -543440 | U76: =U74-U53 -> -548240 | V76: =V74-V53 -> -600030 | W76: =W74-W53 -> -495551 | X76: =X74-X53 -> -491174 | Y76: =Y74-Y53 -> 0 | Z76: =Z74-Z53 -> 0 | ... AC76: =AC74-AC53 -> 69
B78: 1) xxx
A80: X | B80: Cash-Flows Statement | C80: FYE | G80: Quarterly | Q80: Quarterly | Y80: LTM | AE80: Variance
B81: =B7 -> Fiscal Period | C81: =C7 -> 2021 | D81: =D7 -> 2022 | E81: =E7 -> 2023 | G81: =G7 -> 1Q22 | H81: =H7 -> 2Q22 | I81: =I7 -> 3Q22 | J81: =J7 -> 4Q22 | K81: =K7 -> 1Q23 | L81: =L7 -> 2Q23 | M81: =M7 -> 3Q23 | N81: =N7 -> 4Q23 | ... Q81: =Q7 -> 3Q24 | S81: =S7 -> 4Q22 | T81: =T7 -> 1Q23 | U81: =U7 -> 2Q23 | V81: =V7 -> 3Q23 | W81: =W7 -> 4Q23 | X81: =X7 -> 1Q24 | Y81: =Y7 -> 2Q24 | Z81: =Z7 -> 3Q24 | ... AC81: =AC7 -> 3Q24
B82: =B8 -> Fiscal Period End Date | C82: =C8 -> 44561 | D82: =D8 -> 44926 | E82: =E8 -> 45291 | G82: =G8 -> 44651 | H82: =H8 -> 44742 | I82: =I8 -> 44834 | J82: =J8 -> 44926 | K82: =K8 -> 45016 | L82: =L8 -> 45107 | M82: =M8 -> 45199 | N82: =N8 -> 45291 | ... Q82: =Q8 -> 45565 | S82: =S8 -> 44926 | T82: =T8 -> 45016 | U82: =U8 -> 45107 | V82: =V8 -> 45199 | W82: =W8 -> 45291 | X82: =X8 -> 45382 | Y82: =Y8 -> 45473 | Z82: =Z8 -> 45565 | ... AC82: =AC8 -> 45565
B84: Cash-Flows From Operating Activities
B85: Net income (loss) | C85: =C29 -> -32385 | D85: =D29 -> -76246 | E85: =E29 -> -97217 | G85: =G29 -> -17527 | H85: =H29 -> -19328 | I85: =I29 -> -20257 | J85: =J29 -> -19134 | K85: =K29 -> -24271 | L85: =L29 -> -26376 | M85: =M29 -> -25651 | N85: =SUM(D85-SUM(K85:M85)) -> 52 | O85: =O29 -> 25043 | P85: =P29 -> 6155 | Q85: =Q29 -> -27943 | S85: =SUM(H85:K85) -> -82990 | T85: =SUM(I85:L85) -> -90038 | U85: =SUM(J85:M85) -> -95432 | V85: =SUM(K85:N85) -> -76246 | W85: =SUM(L85:O85) -> -26932 | X85: =SUM(M85:P85) -> 5599 | Y85: =SUM(J85:M85) -> -95432 | Z85: =SUM(K85:N85) -> -76246 | AA85: =SUM(L85:O85) -> -26932 | AB85: =SUM(M85:P85) -> 5599 | AC85: =SUM(N85:Q85) -> 3307 | AE85: =SUM(AC85/Y85)-1 -> -1.0346529
B87: Adjustments to reconcile net income:
B88: Stock-based compensation | C88: 1759 | D88: 2066 | E88: 4586 | G88: 495 | H88: =980-G88 -> 485 | I88: =1450-H88-G88 -> 470 | J88: =SUM(D88-SUM(G88:I88)) -> 616 | K88: 673 | L88: =1508-K88 -> 835 | M88: =2457-L88-K88 -> 949 | N88: =SUM(E88-SUM(K88:M88)) -> 2129 | O88: 2335 | P88: =4939-O88 -> 2604 | Q88: =10547-P88-O88 -> 5608 | S88: =SUM(H88:K88) -> 2244 | T88: =SUM(I88:L88) -> 2594 | U88: =SUM(J88:M88) -> 3073 | V88: =SUM(K88:N88) -> 4586 | W88: =SUM(L88:O88) -> 6248 | X88: =SUM(M88:P88) -> 8017 | Y88: =SUM(J88:M88) -> 3073 | Z88: =SUM(K88:N88) -> 4586 | AA88: =SUM(L88:O88) -> 6248 | AB88: =SUM(M88:P88) -> 8017 | AC88: =SUM(N88:Q88) -> 12676 | AE88: =SUM(AC88/Y88)-1 -> 3.1249593
B89: Gain from change in fair value of warrant liabilities | G89: 0 | H89: 0 | I89: 0 | J89: =SUM(D89-SUM(G89:I89)) -> 0 | K89: 0 | L89: 0 | M89: 0 | N89: =SUM(E89-SUM(K89:M89)) -> 0 | O89: -43041 | P89: =-108183-O89 -> -65142 | Q89: =-108183-P89-O89 -> 0 | S89: =SUM(H89:K89) -> 0 | T89: =SUM(I89:L89) -> 0 | U89: =SUM(J89:M89) -> 0 | V89: =SUM(K89:N89) -> 0 | W89: =SUM(L89:O89) -> -43041 | X89: =SUM(M89:P89) -> -108183 | Y89: =SUM(J89:M89) -> 0 | Z89: =SUM(K89:N89) -> 0 | AA89: =SUM(L89:O89) -> -43041 | AB89: =SUM(M89:P89) -> -108183 | AC89: =SUM(N89:Q89) -> -108183 | AE89: =SUM(AC89/Y89)-1 -> #DIV/0!
B90: Depreciation | C90: 310 | D90: 804 | E90: 1084 | G90: 178 | H90: =352-G90 -> 174 | I90: =533-H90-G90 -> 181 | J90: =SUM(D90-SUM(G90:I90)) -> 271 | K90: 272 | L90: =544-K90 -> 272 | M90: =817-L90-K90 -> 273 | N90: =SUM(E90-SUM(K90:M90)) -> 267 | O90: 250 | P90: =496-O90 -> 246 | Q90: =724-P90-O90 -> 228 | S90: =SUM(H90:K90) -> 898 | T90: =SUM(I90:L90) -> 996 | U90: =SUM(J90:M90) -> 1088 | V90: =SUM(K90:N90) -> 1084 | W90: =SUM(L90:O90) -> 1062 | X90: =SUM(M90:P90) -> 1036 | Y90: =SUM(J90:M90) -> 1088 | Z90: =SUM(K90:N90) -> 1084 | AA90: =SUM(L90:O90) -> 1062 | AB90: =SUM(M90:P90) -> 1036 | AC90: =SUM(N90:Q90) -> 991 | AE90: =SUM(AC90/Y90)-1 -> -0.089154412
B91: Amortization of intangible assets | C91: 224 | D91: 497 | E91: 446 | G91: 135 | H91: =260-G91 -> 125 | I91: =379-H91-G91 -> 119 | J91: =SUM(D91-SUM(G91:I91)) -> 118 | K91: 119 | L91: =238-K91 -> 119 | M91: =357-L91-K91 -> 119 | N91: =SUM(E91-SUM(K91:M91)) -> 89 | O91: 61 | P91: =117-O91 -> 56 | Q91: =148-P91-O91 -> 31 | S91: =SUM(H91:K91) -> 481 | T91: =SUM(I91:L91) -> 475 | U91: =SUM(J91:M91) -> 475 | V91: =SUM(K91:N91) -> 446 | W91: =SUM(L91:O91) -> 388 | X91: =SUM(M91:P91) -> 325 | Y91: =SUM(J91:M91) -> 475 | Z91: =SUM(K91:N91) -> 446 | AA91: =SUM(L91:O91) -> 388 | AB91: =SUM(M91:P91) -> 325 | AC91: =SUM(N91:Q91) -> 237 | AE91: =SUM(AC91/Y91)-1 -> -0.50105263
B93: Changes in assets and liabilities:
B94: Prepaid and other assets | C94: -10956 | D94: 1189 | E94: 1714 | G94: -1063 | H94: =4431-G94 -> 5494 | I94: =2790-H94-G94 -> -1641 | J94: =SUM(D94-SUM(G94:I94)) -> -1601 | K94: 2679 | L94: =4116-K94 -> 1437 | M94: =2377-L94-K94 -> -1739 | N94: =SUM(E94-SUM(K94:M94)) -> -663 | O94: -1333 | P94: =-6334-O94 -> -5001 | Q94: =+-5074-P94-O94 -> 1260 | S94: =SUM(H94:K94) -> 4931 | T94: =SUM(I94:L94) -> 874 | U94: =SUM(J94:M94) -> 776 | V94: =SUM(K94:N94) -> 1714 | W94: =SUM(L94:O94) -> -2298 | X94: =SUM(M94:P94) -> -8736 | Y94: =SUM(J94:M94) -> 776 | Z94: =SUM(K94:N94) -> 1714 | AA94: =SUM(L94:O94) -> -2298 | AB94: =SUM(M94:P94) -> -8736 | AC94: =SUM(N94:Q94) -> -5737 | AE94: =SUM(AC94/Y94)-1 -> -8.3930412
B95: Operating lease right-of-use assets and liabilities | C95: 28 | D95: -9 | E95: -17 | G95: -1 | H95: =-4-G95 -> -3 | I95: =-6-H95-G95 -> -2 | J95: =SUM(D95-SUM(G95:I95)) -> -3 | K95: -17 | L95: =-17+K95 -> -34 | M95: =-17-L95-K95 -> 34 | N95: =SUM(E95-SUM(K95:M95)) -> 0 | O95: - | P95: 0 | Q95: 0 | S95: =SUM(H95:K95) -> -25 | T95: =SUM(I95:L95) -> -56 | U95: =SUM(J95:M95) -> -20 | V95: =SUM(K95:N95) -> -17 | W95: =SUM(L95:O95) -> 0 | X95: =SUM(M95:P95) -> 34 | Y95: =SUM(J95:M95) -> -20 | Z95: =SUM(K95:N95) -> -17 | AA95: =SUM(L95:O95) -> 0 | AB95: =SUM(M95:P95) -> 34 | AC95: =SUM(N95:Q95) -> 0 | AE95: =SUM(AC95/Y95)-1 -> -1
B96: Accounts payable and other accrued expenses | C96: 6215 | D96: -3449 | E96: 6896 | G96: -3794 | H96: =-2368-G96 -> 1426 | I96: =-3592-H96-G96 -> -1224 | J96: =SUM(D96-SUM(G96:I96)) -> 143 | K96: 4565 | L96: =6661-K96 -> 2096 | M96: =5815-L96-K96 -> -846 | N96: =SUM(E96-SUM(K96:M96)) -> 1081 | O96: -970 | P96: =41979-O96 -> 42949 | Q96: =41671-P96-O96 -> -308 | S96: =SUM(H96:K96) -> 4910 | T96: =SUM(I96:L96) -> 5580 | U96: =SUM(J96:M96) -> 5958 | V96: =SUM(K96:N96) -> 6896 | W96: =SUM(L96:O96) -> 1361 | X96: =SUM(M96:P96) -> 42214 | Y96: =SUM(J96:M96) -> 5958 | Z96: =SUM(K96:N96) -> 6896 | AA96: =SUM(L96:O96) -> 1361 | AB96: =SUM(M96:P96) -> 42214 | AC96: =SUM(N96:Q96) -> 42752 | AE96: =SUM(AC96/Y96)-1 -> 6.1755623
B97: Accrued development expense | C97: 2084 | D97: -523 | E97: 757 | G97: 122 | H97: =515-G97 -> 393 | I97: =1293-H97-G97 -> 778 | J97: =SUM(D97-SUM(G97:I97)) -> -1816 | K97: 2996 | L97: =4764-K97 -> 1768 | M97: =5064-L97-K97 -> 300 | N97: =SUM(E97-SUM(K97:M97)) -> -4307 | O97: -1240 | P97: =-1441-O97 -> -201 | Q97: =+-494-P97-O97 -> 947 | S97: =SUM(H97:K97) -> 2351 | T97: =SUM(I97:L97) -> 3726 | U97: =SUM(J97:M97) -> 3248 | V97: =SUM(K97:N97) -> 757 | W97: =SUM(L97:O97) -> -3479 | X97: =SUM(M97:P97) -> -5448 | Y97: =SUM(J97:M97) -> 3248 | Z97: =SUM(K97:N97) -> 757 | AA97: =SUM(L97:O97) -> -3479 | AB97: =SUM(M97:P97) -> -5448 | AC97: =SUM(N97:Q97) -> -4801 | AE97: =SUM(AC97/Y97)-1 -> -2.4781404
B98: Accrued compensation and benefits | C98: 1794 | D98: -1707 | E98: 30 | G98: -1705 | H98: =-1701-G98 -> 4 | I98: =-1717-H98-G98 -> -16 | J98: =SUM(D98-SUM(G98:I98)) -> 10 | K98: 42 | L98: =50-K98 -> 8 | M98: =17-L98-K98 -> -33 | N98: =SUM(E98-SUM(K98:M98)) -> 13 | O98: 28 | P98: =18-O98 -> -10 | Q98: =1750-P98-O98 -> 1732 | S98: =SUM(H98:K98) -> 40 | T98: =SUM(I98:L98) -> 44 | U98: =SUM(J98:M98) -> 27 | V98: =SUM(K98:N98) -> 30 | W98: =SUM(L98:O98) -> 16 | X98: =SUM(M98:P98) -> -2 | Y98: =SUM(J98:M98) -> 27 | Z98: =SUM(K98:N98) -> 30 | AA98: =SUM(L98:O98) -> 16 | AB98: =SUM(M98:P98) -> -2 | AC98: =SUM(N98:Q98) -> 1763 | AE98: =SUM(AC98/Y98)-1 -> 64.296296
B99: Other liabilities | C99: 731 | D99: -136 | E99: -304 | G99: -370 | H99: =-254-G99 -> 116 | I99: =-212-H99-G99 -> 42 | J99: =SUM(D99-SUM(G99:I99)) -> 76 | K99: -313 | L99: =-396-K99 -> -83 | M99: =-298-L99-K99 -> 98 | N99: =SUM(E99-SUM(K99:M99)) -> -6 | O99: -260 | P99: =-157-O99 -> 103 | Q99: =+-8-P99-O99 -> 149 | S99: =SUM(H99:K99) -> -79 | T99: =SUM(I99:L99) -> -278 | U99: =SUM(J99:M99) -> -222 | V99: =SUM(K99:N99) -> -304 | W99: =SUM(L99:O99) -> -251 | X99: =SUM(M99:P99) -> -65 | Y99: =SUM(J99:M99) -> -222 | Z99: =SUM(K99:N99) -> -304 | AA99: =SUM(L99:O99) -> -251 | AB99: =SUM(M99:P99) -> -65 | AC99: =SUM(N99:Q99) -> -14 | AE99: =SUM(AC99/Y99)-1 -> -0.93693694
B100: Net cash used in operating activities | C100: =SUM(C85:C99) -> -30196 | D100: =SUM(D85:D99) -> -77514 | E100: =SUM(E85:E99) -> -82025 | G100: =SUM(G85:G99) -> -23530 | H100: =SUM(H85:H99) -> -11114 | I100: =SUM(I85:I99) -> -21550 | J100: =SUM(J85:J99) -> -21320 | K100: =SUM(K85:K99) -> -13255 | L100: =SUM(L85:L99) -> -19958 | M100: =SUM(M85:M99) -> -26496 | N100: =SUM(N85:N99) -> -1345 | ... Q100: =SUM(Q85:Q99) -> -18296 | S100: =SUM(S85:S99) -> -67239 | T100: =SUM(T85:T99) -> -76083 | U100: =SUM(U85:U99) -> -81029 | V100: =SUM(V85:V99) -> -61054 | W100: =SUM(W85:W99) -> -66926 | X100: =SUM(X85:X99) -> -65209 | Y100: =SUM(Y85:Y99) -> -81029 | Z100: =SUM(Z85:Z99) -> -61054 | ... AC100: =SUM(AC85:AC99) -> -57009 | AE100: =SUM(AC100/Y100)-1 -> -0.29643708
B102: Cash flows from investing activities:
B103: Purchase of property and equipment | C103: -22214 | D103: -2712 | E103: -414 | G103: -425 | H103: =-1891-G103 -> -1466 | I103: =-3047-H103-G103 -> -1156 | J103: =SUM(D103-SUM(G103:I103)) -> 335 | K103: -357 | L103: =-351-K103 -> 6 | M103: =-373-L103-K103 -> -22 | N103: =SUM(E103-SUM(K103:M103)) -> -41 | O103: 0 | P103: =-29-O103 -> -29 | Q103: =+-46-P103-O103 -> -17 | S103: =SUM(H103:K103) -> -2644 | T103: =SUM(I103:L103) -> -1172 | U103: =SUM(J103:M103) -> -38 | V103: =SUM(K103:N103) -> -414 | W103: =SUM(L103:O103) -> -57 | X103: =SUM(M103:P103) -> -92 | Y103: =SUM(J103:M103) -> -38 | Z103: =SUM(K103:N103) -> -414 | AA103: =SUM(L103:O103) -> -57 | AB103: =SUM(M103:P103) -> -92 | AC103: =SUM(N103:Q103) -> -87 | AE103: =SUM(AC103/Y103)-1 -> 1.2894737
B104: Net cash used in investing activities | C104: =SUM(C103:C103) -> -22214 | D104: =SUM(D103:D103) -> -2712 | E104: =SUM(E103:E103) -> -414 | G104: =SUM(G103:G103) -> -425 | H104: =SUM(H103:H103) -> -1466 | I104: =SUM(I103:I103) -> -1156 | J104: =SUM(J103:J103) -> 335 | K104: =SUM(K103:K103) -> -357 | L104: =SUM(L103:L103) -> 6 | M104: =SUM(M103:M103) -> -22 | N104: =SUM(N103:N103) -> -41 | ... Q104: =SUM(Q103:Q103) -> -17 | S104: =SUM(S103:S103) -> -2644 | T104: =SUM(T103:T103) -> -1172 | U104: =SUM(U103:U103) -> -38 | V104: =SUM(V103:V103) -> -414 | W104: =SUM(W103:W103) -> -57 | X104: =SUM(X103:X103) -> -92 | Y104: =SUM(Y103:Y103) -> -38 | Z104: =SUM(Z103:Z103) -> -414 | ... AC104: =SUM(AC103:AC103) -> -87 | AE104: =SUM(AC104/Y104)-1 -> 1.2894737
B106: Cash flows from financing activities:
B107: Proceeds from issuance of common stock upon exercise of stock options | C107: 1824 | D107: 475 | E107: 2560 | G107: 211 | H107: =330-G107 -> 119 | I107: =466-H107-G107 -> 136 | J107: =SUM(D107-SUM(G107:I107)) -> 9 | K107: 64 | L107: =953-K107 -> 889 | M107: =1417-L107-K107 -> 464 | N107: =SUM(E107-SUM(K107:M107)) -> 1143 | O107: 0 | P107: 0 | Q107: 0 | Y107: =SUM(J107:M107) -> 1426 | Z107: =SUM(K107:N107) -> 2560 | AA107: =SUM(L107:O107) -> 2496 | AB107: =SUM(M107:P107) -> 1607 | AC107: =SUM(N107:Q107) -> 1143 | AE107: =SUM(AC107/Y107)-1 -> -0.19845722
B108: Proceeds from issuance of common stock upon exercise of 2018 warrants | C108: 692 | D108: 0 | E108: 0 | G108: 0 | H108: 0 | I108: 0 | J108: =SUM(D108-SUM(G108:I108)) -> 0 | K108: 0 | L108: 0 | M108: 0 | N108: =SUM(E108-SUM(K108:M108)) -> 0 | O108: 0 | P108: 0 | Q108: 0 | Y108: =SUM(J108:M108) -> 0 | Z108: =SUM(K108:N108) -> 0 | AA108: =SUM(L108:O108) -> 0 | AB108: =SUM(M108:P108) -> 0 | AC108: =SUM(N108:Q108) -> 0 | AE108: =SUM(AC108/Y108)-1 -> #DIV/0!
B109: Proceeds from exercise of common stock warrants, net of exercise costs | C109: 0 | D109: 0 | E109: 0 | G109: 0 | H109: 0 | I109: 0 | J109: =SUM(D109-SUM(G109:I109)) -> 0 | K109: 0 | L109: 0 | M109: 0 | N109: =SUM(E109-SUM(K109:M109)) -> 0 | O109: 22160 | P109: =123552-O109 -> 101392 | Q109: =123552-P109-O109 -> 0 | S109: =SUM(H109:K109) -> 0 | T109: =SUM(I109:L109) -> 0 | U109: =SUM(J109:M109) -> 0 | V109: =SUM(K109:N109) -> 0 | W109: =SUM(L109:O109) -> 22160 | X109: =SUM(M109:P109) -> 123552 | Y109: =SUM(J109:M109) -> 0 | Z109: =SUM(K109:N109) -> 0 | AA109: =SUM(L109:O109) -> 22160 | AB109: =SUM(M109:P109) -> 123552 | AC109: =SUM(N109:Q109) -> 123552 | AE109: =SUM(AC109/Y109)-1 -> #DIV/0!
B110: Proceeds from common stock offering, net of issuance costs | C110: 189825 | D110: 47329 | E110: 0 | G110: 0 | H110: 0 | I110: 0 | J110: =SUM(D110-SUM(G110:I110)) -> 47329 | K110: 0 | L110: 0 | M110: 0 | N110: =SUM(E110-SUM(K110:M110)) -> 0 | O110: 0 | P110: 0 | Q110: 0 | Y110: =SUM(J110:M110) -> 47329 | Z110: =SUM(K110:N110) -> 0 | AA110: =SUM(L110:O110) -> 0 | AB110: =SUM(M110:P110) -> 0 | AC110: =SUM(N110:Q110) -> 0 | AE110: =SUM(AC110/Y110)-1 -> -1
B111: Net cash provided by financing activities | C111: =SUM(C107:C110) -> 192341 | D111: =SUM(D107:D110) -> 47804 | E111: =SUM(E107:E110) -> 2560 | G111: =SUM(G107:G110) -> 211 | H111: =SUM(H107:H110) -> 119 | I111: =SUM(I107:I110) -> 136 | J111: =SUM(J107:J110) -> 47338 | K111: =SUM(K107:K110) -> 64 | L111: =SUM(L107:L110) -> 889 | M111: =SUM(M107:M110) -> 464 | N111: =SUM(N107:N110) -> 1143 | ... Q111: =SUM(Q107:Q110) -> 0 | S111: =SUM(S107:S110) -> 0 | T111: =SUM(T107:T110) -> 0 | U111: =SUM(U107:U110) -> 0 | V111: =SUM(V107:V110) -> 0 | W111: =SUM(W107:W110) -> 22160 | X111: =SUM(X107:X110) -> 123552 | Y111: =SUM(Y107:Y110) -> 48755 | Z111: =SUM(Z107:Z110) -> 2560 | ... AC111: =SUM(AC107:AC110) -> 124695 | AE111: =SUM(AC111/Y111)-1 -> 1.5575838
B114: Cash BOP | D114: =C120 -> 139931 | E114: =D120 -> 107509 | H114: =G120 -> -23744 | I114: =H120 -> -36205 | J114: =I120 -> -58775 | K114: =J120 -> -32422 | L114: =K120 -> -45970 | M114: =L120 -> -65033 | N114: =M120 -> -91087 | O114: =N120 -> -91330 | ... Q114: =P120 -> -5175 | S114: =G120 -> -23744 | T114: =H120 -> -36205 | U114: =I120 -> -58775 | V114: =J120 -> -32422 | W114: =K120 -> -45970 | X114: =L120 -> -65033 | Y114: =M120 -> -91087 | Z114: =N120 -> -91330 | ... AB114: =P120 -> -5175 | AC114: =SUM(N114:Q114) -> -275889
B115: BOP Restricted Cash Adjustments (Changes in FX; Restricted Cash) | D115: 0 | E115: 0 | H115: 0 | I115: 0 | J115: 0 | K115: 0 | L115: 0 | M115: 0 | N115: 0 | O115: 0 | P115: 0 | Q115: 0 | S115: =SUM(H115:K115) -> 0 | T115: =SUM(I115:L115) -> 0 | U115: =SUM(J115:M115) -> 0 | V115: =SUM(K115:N115) -> 0 | W115: =SUM(L115:O115) -> 0 | X115: =SUM(M115:P115) -> 0 | Y115: =SUM(N115:Q115) -> 0 | Z115: =SUM(O115:Q115) -> 0 | AA115: =SUM(P115:Q115) -> 0 | AB115: =SUM(Q115:Q115) -> 0 | AC115: =SUM(N115:Q115) -> 0
B116: Adjusted Cash Position BOP | C116: =SUM(C114:C115) -> 0 | D116: =SUM(D114:D115) -> 139931 | E116: =SUM(E114:E115) -> 107509 | G116: =SUM(G114:G115) -> 0 | H116: =SUM(H114:H115) -> -23744 | I116: =SUM(I114:I115) -> -36205 | J116: =SUM(J114:J115) -> -58775 | K116: =SUM(K114:K115) -> -32422 | L116: =SUM(L114:L115) -> -45970 | M116: =SUM(M114:M115) -> -65033 | N116: =SUM(N114:N115) -> -91087 | ... Q116: =SUM(Q114:Q115) -> -5175 | S116: =SUM(S114:S115) -> -23744 | T116: =SUM(T114:T115) -> -36205 | U116: =SUM(U114:U115) -> -58775 | V116: =SUM(V114:V115) -> -32422 | W116: =SUM(W114:W115) -> -45970 | X116: =SUM(X114:X115) -> -65033 | Y116: =SUM(Y114:Y115) -> -91087 | Z116: =SUM(Z114:Z115) -> -91330 | ... AC116: =SUM(AC114:AC115) -> -275889
B118: EOP Restricted Cash Adjustments (Changes in FX; Restricted Cash) | J118: =C118 -> 0 | N118: =D118 -> 0 | S118: =SUM(H118:K118) -> 0 | T118: =SUM(I118:L118) -> 0 | U118: =SUM(J118:M118) -> 0 | V118: =SUM(K118:N118) -> 0 | W118: =SUM(L118:O118) -> 0 | X118: =SUM(M118:P118) -> 0 | Y118: =SUM(N118:Q118) -> 0 | Z118: =SUM(O118:Q118) -> 0 | AA118: =SUM(P118:Q118) -> 0 | AB118: =SUM(Q118:Q118) -> 0 | AC118: =SUM(N118:Q118) -> 0
B119: Net Change in Cash | C119: =+C111+C104+C100 -> 139931 | D119: =+D111+D104+D100 -> -32422 | E119: =+E111+E104+E100 -> -79879 | G119: =+G111+G104+G100 -> -23744 | H119: =+H111+H104+H100 -> -12461 | I119: =+I111+I104+I100 -> -22570 | J119: =+J111+J104+J100 -> 26353 | K119: =+K111+K104+K100 -> -13548 | L119: =+L111+L104+L100 -> -19063 | M119: =+M111+M104+M100 -> -26054 | N119: =+N111+N104+N100 -> -243 | ... Q119: =+Q111+Q104+Q100 -> -18313 | S119: =SUM(H119:K119) -> -22226 | T119: =SUM(I119:L119) -> -28828 | U119: =SUM(J119:M119) -> -32312 | V119: =SUM(K119:N119) -> -58908 | W119: =SUM(L119:O119) -> -42327 | X119: =SUM(M119:P119) -> 59858 | Y119: =SUM(N119:Q119) -> 67599 | Z119: =SUM(O119:Q119) -> 67842 | AA119: =SUM(P119:Q119) -> 64809 | AB119: =SUM(Q119:Q119) -> -18313 | AC119: =SUM(N119:Q119) -> 67599
B120: Adjusted Cash Position EOP | C120: =SUM(C116:C119) -> 139931 | D120: =SUM(D116:D119) -> 107509 | E120: =SUM(E116:E119) -> 27630 | G120: =SUM(G116:G119) -> -23744 | H120: =SUM(H116:H119) -> -36205 | I120: =SUM(I116:I119) -> -58775 | J120: =SUM(J116:J119) -> -32422 | K120: =SUM(K116:K119) -> -45970 | L120: =SUM(L116:L119) -> -65033 | M120: =SUM(M116:M119) -> -91087 | N120: =SUM(N116:N119) -> -91330 | ... Q120: =SUM(Q116:Q119) -> -23488 | S120: =SUM(S116:S119) -> -45970 | T120: =SUM(T116:T119) -> -65033 | U120: =SUM(U116:U119) -> -91087 | V120: =SUM(V116:V119) -> -91330 | W120: =SUM(W116:W119) -> -88297 | X120: =SUM(X116:X119) -> -5175 | Y120: =SUM(Y116:Y119) -> -23488 | Z120: =SUM(Z116:Z119) -> -23488 | ... AC120: =SUM(AC116:AC119) -> -208290
B122: Balance Check | C122: =C120-C43 -> -93506 | D122: =D120-D43 -> -93506 | E122: =E120-E43 -> -93506 | G122: =G120-G43 -> -233437 | H122: =H120-H43 -> -233437 | I122: =I120-I43 -> -233437 | J122: =J120-J43 -> -233437 | K122: =K120-K43 -> -233437 | L122: =L120-L43 -> -233471 | M122: =M120-M43 -> -233437 | N122: =N120-N43 -> -212466 | ... Q122: =Q120-Q43 -> -172466 | S122: =S120-S43 -> -255663 | T122: =T120-T43 -> -262265 | U122: =U120-U43 -> -265749 | V122: =V120-V43 -> -292345 | W122: =W120-W43 -> -275764 | X122: =X120-X43 -> -173613 | Y122: =Y120-Y43 -> -165838 | Z122: =Z120-Z43 -> -144624 | ... AC122: =AC120-AC43 -> -357268
B125: Supplemental disclosures of other cash flow information:
B126: Cash paid for interest | J126: =SUM(C126-SUM(G126:I126)) -> 0 | N126: =SUM(D126-SUM(K126:M126)) -> 0
B128: 1) xxx
B129: 2) xxx

Sheet Revenue Drivers
B2: Cassava Sciences (NASDAQ: SAVA) | H2: Quarterly | P2: Quarterly | Q2: Quarterly | W2: LTM | AA2: LTM | AC2: LTM
B3: Segment Anaysis | C3: ='Historical Financials'!#REF! -> #REF! | D3: ='Historical Financials'!C7 -> 2021 | E3: ='Historical Financials'!D7 -> 2022 | F3: ='Historical Financials'!E7 -> 2023 | H3: ='Historical Financials'!G7 -> 1Q22 | I3: ='Historical Financials'!H7 -> 2Q22 | J3: ='Historical Financials'!I7 -> 3Q22 | K3: ='Historical Financials'!J7 -> 4Q22 | L3: ='Historical Financials'!K7 -> 1Q23 | M3: ='Historical Financials'!L7 -> 2Q23 | N3: ='Historical Financials'!M7 -> 3Q23 | O3: ='Historical Financials'!N7 -> 4Q23 | ... R3: ='Historical Financials'!Q7 -> 3Q24 | S3: ='Historical Financials'!#REF! -> #REF! | T3: ='Historical Financials'!#REF! -> #REF! | U3: ='Historical Financials'!#REF! -> #REF! | W3: =L3 -> 1Q23 | X3: =M3 -> 2Q23 | Y3: =N3 -> 3Q23 | Z3: =O3 -> 4Q23 | AA3: =P3 -> 1Q24 | AB3: =Q3 -> 2Q24 | AC3: =S3 -> #REF! | AD3: =T3 -> #REF! | AE3: =U3 -> #REF! | AF3: =#REF! -> #REF!
B4: $ in thousands except per share | C4: ='Historical Financials'!#REF! -> #REF! | D4: ='Historical Financials'!C8 -> 44561 | E4: ='Historical Financials'!D8 -> 44926 | F4: ='Historical Financials'!E8 -> 45291 | H4: ='Historical Financials'!G8 -> 44651 | I4: ='Historical Financials'!H8 -> 44742 | J4: ='Historical Financials'!I8 -> 44834 | K4: ='Historical Financials'!J8 -> 44926 | L4: ='Historical Financials'!K8 -> 45016 | M4: ='Historical Financials'!L8 -> 45107 | N4: ='Historical Financials'!M8 -> 45199 | O4: ='Historical Financials'!N8 -> 45291 | ... R4: ='Historical Financials'!Q8 -> 45565 | S4: ='Historical Financials'!#REF! -> #REF! | T4: ='Historical Financials'!#REF! -> #REF! | U4: ='Historical Financials'!#REF! -> #REF! | W4: =L4 -> 45016 | X4: =M4 -> 45107 | Y4: =N4 -> 45199 | Z4: =O4 -> 45291 | AA4: =P4 -> 45382 | AB4: =Q4 -> 45473 | AC4: =S4 -> #REF! | AD4: =T4 -> #REF! | AE4: =U4 -> #REF! | AF4: =#REF! -> #REF!
A6: X | B6: Net Revenues by Channel
W7: =SUM(I7:L7) -> 0 | X7: =SUM(J7:M7) -> 0 | Y7: =SUM(K7:N7) -> 0 | Z7: =SUM(L7:O7) -> 0 | AA7: =SUM(M7:P7) -> 0 | AB7: =SUM(N7:Q7) -> 0 | AC7: =SUM(P7:S7) -> 0 | AD7: =SUM(Q7:T7) -> 0 | AE7: =SUM(R7:U7) -> 0 | AF7: =SUM(S7:U7) -> 0
W8: =SUM(I8:L8) -> 0 | X8: =SUM(J8:M8) -> 0 | Y8: =SUM(K8:N8) -> 0 | Z8: =SUM(L8:O8) -> 0 | AA8: =SUM(M8:P8) -> 0 | AB8: =SUM(N8:Q8) -> 0 | AC8: =SUM(P8:S8) -> 0 | AD8: =SUM(Q8:T8) -> 0 | AE8: =SUM(R8:U8) -> 0 | AF8: =SUM(S8:U8) -> 0
B9: Total Net Revenue | D9: =SUM(D7:D8) -> 0 | E9: =SUM(E7:E8) -> 0 | F9: =SUM(F7:F8) -> 0 | P9: =SUM(P7:P8) -> 0 | Q9: =SUM(Q7:Q8) -> 0 | R9: =SUM(R7:R8) -> 0 | S9: =SUM(S7:S8) -> 0 | T9: =SUM(T7:T8) -> 0 | U9: =SUM(U7:U8) -> 0 | W9: =SUM(W7:W8) -> 0 | X9: =SUM(X7:X8) -> 0 | Y9: =SUM(Y7:Y8) -> 0 | Z9: =SUM(Z7:Z8) -> 0 | AA9: =SUM(AA7:AA8) -> 0 | AB9: =SUM(AB7:AB8) -> 0 | AC9: =SUM(AC7:AC8) -> 0 | AD9: =SUM(AD7:AD8) -> 0 | ... AF9: =SUM(AF7:AF8) -> 0
B10: Balance Check | D10: =+D9-'Historical Financials'!C11 -> 0 | E10: =+E9-'Historical Financials'!D11 -> 0 | F10: =+F9-'Historical Financials'!E11 -> 0 | P10: =+P9-'Historical Financials'!O11 -> 0 | Q10: =+Q9-'Historical Financials'!P11 -> 0 | R10: =+R9-'Historical Financials'!Q11 -> 0 | S10: =+S9-'Historical Financials'!#REF! -> #REF! | T10: =+T9-'Historical Financials'!#REF! -> #REF! | U10: =+U9-'Historical Financials'!#REF! -> #REF! | W10: =W9-'Historical Financials'!S11 -> 0 | X10: =X9-'Historical Financials'!T11 -> 0 | Y10: =Y9-'Historical Financials'!U11 -> 0 | Z10: =Z9-'Historical Financials'!V11 -> 0 | AA10: =AA9-'Historical Financials'!W11 -> 0 | AB10: =AB9-'Historical Financials'!X11 -> 0 | AC10: =AC9-'Historical Financials'!Z11 -> 0 | AD10: =AD9-'Historical Financials'!AA11 -> 0 | AE10: =AE9-'Historical Financials'!AB11 -> 0 | AF10: =AF9-'Historical Financials'!AC11 -> 0
A12: X | B12: Revenue by Channel
W13: =SUM(I13:L13) -> 0 | X13: =SUM(J13:M13) -> 0 | Y13: =SUM(K13:N13) -> 0 | Z13: =SUM(L13:O13) -> 0 | AA13: =SUM(M13:P13) -> 0 | AB13: =SUM(N13:Q13) -> 0 | AC13: =SUM(P13:S13) -> 0 | AD13: =SUM(Q13:T13) -> 0 | AE13: =SUM(R13:U13) -> 0 | AF13: =SUM(S13:U13) -> 0
W14: =SUM(I14:L14) -> 0 | X14: =SUM(J14:M14) -> 0 | Y14: =SUM(K14:N14) -> 0 | Z14: =SUM(L14:O14) -> 0 | AA14: =SUM(M14:P14) -> 0 | AB14: =SUM(N14:Q14) -> 0 | AC14: =SUM(P14:S14) -> 0 | AD14: =SUM(Q14:T14) -> 0 | AE14: =SUM(R14:U14) -> 0 | AF14: =SUM(S14:U14) -> 0
B15: Total Net U.S Revenue | D15: =SUM(D13:D14) -> 0 | E15: =SUM(E13:E14) -> 0 | F15: =SUM(F13:F14) -> 0 | P15: =SUM(P13:P14) -> 0 | Q15: =SUM(Q13:Q14) -> 0 | R15: =SUM(R13:R14) -> 0 | S15: =SUM(S13:S14) -> 0 | T15: =SUM(T13:T14) -> 0 | U15: =SUM(U13:U14) -> 0 | W15: =SUM(W13:W14) -> 0 | X15: =SUM(X13:X14) -> 0 | Y15: =SUM(Y13:Y14) -> 0 | Z15: =SUM(Z13:Z14) -> 0 | AA15: =SUM(AA13:AA14) -> 0 | AB15: =SUM(AB13:AB14) -> 0 | AC15: =SUM(AC13:AC14) -> 0 | AD15: =SUM(AD13:AD14) -> 0 | ... AF15: =SUM(AF13:AF14) -> 0
B16: Balance Check | D16: =+D15-D9 -> 0 | E16: =+E15-E9 -> 0 | F16: =+F15-F9 -> 0 | P16: =+P15-P9 -> 0 | Q16: =+Q15-Q9 -> 0 | R16: =+R15-R9 -> 0 | S16: =+S15-S9 -> 0 | T16: =+T15-T9 -> 0 | U16: =+U15-U9 -> 0 | W16: =W15-'Historical Financials'!S17 -> 75246 | X16: =X15-'Historical Financials'!T17 -> 83267 | Y16: =Y15-'Historical Financials'!U17 -> 88344 | Z16: =Z15-'Historical Financials'!V17 -> 89423 | AA16: =AA15-'Historical Financials'!W17 -> 83536 | AB16: =AB15-'Historical Financials'!X17 -> 73765 | AC16: =+AC15-AC9 -> 0 | AD16: =+AD15-AD9 -> 0 | AE16: =+AE15-AE9 -> 0 | AF16: =+AF15-AF9 -> 0

Sheet FCF
B2: Cassava Sciences (NASDAQ: SAVA) | D2: FYE | H2: Quarterly | Q2: Quarterly | R2: Quarterly | X2: LTM | AE2: LTM | AK2: Variance
B3: FCF Analysis | C3: ='Historical Financials'!#REF! -> #REF! | D3: ='Historical Financials'!C7 -> 2021 | E3: ='Historical Financials'!D7 -> 2022 | F3: ='Historical Financials'!E7 -> 2023 | H3: ='Historical Financials'!G7 -> 1Q22 | I3: ='Historical Financials'!H7 -> 2Q22 | J3: ='Historical Financials'!I7 -> 3Q22 | K3: ='Historical Financials'!J7 -> 4Q22 | L3: ='Historical Financials'!K7 -> 1Q23 | M3: ='Historical Financials'!L7 -> 2Q23 | N3: ='Historical Financials'!M7 -> 3Q23 | O3: ='Historical Financials'!N7 -> 4Q23 | ... R3: ='Historical Financials'!Q7 -> 3Q24 | S3: ='Historical Financials'!#REF! -> #REF! | T3: ='Historical Financials'!#REF! -> #REF! | U3: ='Historical Financials'!#REF! -> #REF! | V3: ='Historical Financials'!#REF! -> #REF! | X3: =K3 -> 4Q22 | Y3: =L3 -> 1Q23 | Z3: =M3 -> 2Q23 | AA3: =N3 -> 3Q23 | AB3: =O3 -> 4Q23 | AC3: =P3 -> 1Q24 | AD3: =Q3 -> 2Q24 | AE3: =R3 -> 3Q24 | ... AI3: =V3 -> #REF!
B4: $ in thousands except per share | C4: ='Historical Financials'!#REF! -> #REF! | D4: ='Historical Financials'!C8 -> 44561 | E4: ='Historical Financials'!D8 -> 44926 | F4: ='Historical Financials'!E8 -> 45291 | H4: ='Historical Financials'!G8 -> 44651 | I4: ='Historical Financials'!H8 -> 44742 | J4: ='Historical Financials'!I8 -> 44834 | K4: ='Historical Financials'!J8 -> 44926 | L4: ='Historical Financials'!K8 -> 45016 | M4: ='Historical Financials'!L8 -> 45107 | N4: ='Historical Financials'!M8 -> 45199 | O4: ='Historical Financials'!N8 -> 45291 | ... R4: ='Historical Financials'!Q8 -> 45565 | S4: ='Historical Financials'!#REF! -> #REF! | T4: ='Historical Financials'!#REF! -> #REF! | U4: ='Historical Financials'!#REF! -> #REF! | V4: ='Historical Financials'!#REF! -> #REF! | X4: =K4 -> 44926 | Y4: =L4 -> 45016 | Z4: =M4 -> 45107 | AA4: =N4 -> 45199 | AB4: =O4 -> 45291 | AC4: =P4 -> 45382 | AD4: =Q4 -> 45473 | AE4: =R4 -> 45565 | ... AI4: =V4 -> #REF!
P6: ='Revenue Drivers'!P7 -> 0 | Q6: ='Revenue Drivers'!Q7 -> 0 | AC6: =SUM(M6:P6) -> 0 | AD6: =SUM(N6:Q6) -> 0 | AE6: =SUM(O6:R6) -> 0 | AF6: =SUM(P6:S6) -> 0 | AG6: =SUM(Q6:T6) -> 0 | AH6: =SUM(R6:U6) -> 0 | AI6: =SUM(S6:V6) -> 0 | AK6: =SUM(AI6/AE6)-1 -> #DIV/0!
P7: ='Revenue Drivers'!P8 -> 0 | Q7: ='Revenue Drivers'!Q8 -> 0 | AC7: =SUM(M7:P7) -> 0 | AD7: =SUM(N7:Q7) -> 0 | AE7: =SUM(O7:R7) -> 0 | AF7: =SUM(P7:S7) -> 0 | AG7: =SUM(Q7:T7) -> 0 | AH7: =SUM(R7:U7) -> 0 | AI7: =SUM(S7:V7) -> 0 | AK7: =SUM(AI7/AE7)-1 -> #DIV/0!
B8: Total Revenue | C8: ='Historical Financials'!#REF! -> #REF! | D8: =SUM(D6:D7) -> 0 | E8: =SUM(E6:E7) -> 0 | F8: =SUM(F6:F7) -> 0 | H8: ='Historical Financials'!G11 -> 0 | I8: ='Historical Financials'!H11 -> 0 | J8: ='Historical Financials'!I11 -> 0 | K8: ='Historical Financials'!J11 -> 0 | L8: ='Historical Financials'!K11 -> 0 | M8: ='Historical Financials'!L11 -> 0 | N8: ='Historical Financials'!M11 -> 0 | O8: ='Historical Financials'!N11 -> 0 | P8: =SUM(P6:P7) -> 0 | Q8: =SUM(Q6:Q7) -> 0 | R8: =SUM(R6:R7) -> 0 | S8: =SUM(S6:S7) -> 0 | T8: =SUM(T6:T7) -> 0 | U8: =SUM(U6:U7) -> 0 | V8: =SUM(V6:V7) -> 0 | X8: =SUM(H8:K8) -> 0 | Y8: =SUM(I8:L8) -> 0 | Z8: =SUM(J8:M8) -> 0 | AA8: =SUM(K8:N8) -> 0 | AB8: =SUM(L8:O8) -> 0 | AC8: =SUM(AC6:AC7) -> 0 | AD8: =SUM(AD6:AD7) -> 0 | AE8: =SUM(AE6:AE7) -> 0 | AF8: =SUM(AF6:AF7) -> 0 | AG8: =SUM(AG6:AG7) -> 0 | AH8: =SUM(AH6:AH7) -> 0 | AI8: =SUM(AI6:AI7) -> 0 | AK8: =SUM(AI8/AE8)-1 -> #DIV/0!
B9: Y/Y Growth (%) | D9: =SUM(D8/C8)-1 -> #REF! | E9: =SUM(E8/D8)-1 -> #DIV/0! | F9: =SUM(F8/E8)-1 -> #DIV/0! | M9: =SUM(M8/I8)-1 -> #DIV/0! | N9: =SUM(N8/J8)-1 -> #DIV/0! | O9: =SUM(O8/K8)-1 -> #DIV/0! | P9: =SUM(P8/L8)-1 -> #DIV/0! | Q9: =SUM(Q8/M8)-1 -> #DIV/0! | R9: =SUM(R8/N8)-1 -> #DIV/0! | S9: =SUM(S8/O8)-1 -> #DIV/0! | T9: =SUM(T8/P8)-1 -> #DIV/0! | ... V9: =SUM(V8/R8)-1 -> #DIV/0! | AB9: =SUM(AB8/X8)-1 -> #DIV/0! | AC9: =SUM(AC8/Y8)-1 -> #DIV/0! | AD9: =SUM(AD8/Z8)-1 -> #DIV/0! | AE9: =SUM(AE8/AA8)-1 -> #DIV/0! | AF9: =SUM(AF8/AB8)-1 -> #DIV/0! | AG9: =SUM(AG8/AC8)-1 -> #DIV/0! | AH9: =SUM(AH8/AD8)-1 -> #DIV/0! | AI9: =SUM(AI8/AE8)-1 -> #DIV/0! | AK9: =SUM(AI9-AE9)*10000 -> #DIV/0!
B10: Q/Q Growth (%) | C10: N/A | D10: N/A | E10: N/A | F10: N/A | J10: =SUM(J8/I8)-1 -> #DIV/0! | K10: =SUM(K8/J8)-1 -> #DIV/0! | L10: =SUM(L8/K8)-1 -> #DIV/0! | M10: =SUM(M8/L8)-1 -> #DIV/0! | N10: =SUM(N8/M8)-1 -> #DIV/0! | O10: =SUM(O8/N8)-1 -> #DIV/0! | P10: =SUM(P8/O8)-1 -> #DIV/0! | Q10: =SUM(Q8/P8)-1 -> #DIV/0! | ... V10: =SUM(V8/U8)-1 -> #DIV/0! | X10: N/A | Y10: N/A | Z10: N/A | AA10: N/A | AB10: N/A | AC10: N/A | AD10: N/A | AE10: N/A | AF10: N/A | AG10: N/A | AH10: N/A | AI10: N/A
B12: (-) Cost of Sales | C12: ='Historical Financials'!#REF! -> #REF! | H12: ='Historical Financials'!G13 -> 0 | I12: ='Historical Financials'!H13 -> 0 | J12: ='Historical Financials'!I13 -> 0 | K12: ='Historical Financials'!J13 -> 0 | L12: ='Historical Financials'!K13 -> 0 | M12: ='Historical Financials'!L13 -> 0 | N12: ='Historical Financials'!M13 -> 0 | O12: ='Historical Financials'!N13 -> 0 | ... Q12: ='Historical Financials'!P13 -> 0 | X12: =SUM(G12:K12) -> 0 | Y12: =SUM(I12:L12) -> 0 | Z12: =SUM(J12:M12) -> 0 | AA12: =SUM(K12:N12) -> 0 | AB12: =SUM(L12:O12) -> 0 | AC12: =SUM(M12:P12) -> 0 | AD12: =SUM(N12:Q12) -> 0 | AE12: =SUM(O12:R12) -> 0 | AF12: =SUM(P12:S12) -> 0 | ... AI12: =SUM(S12:V12) -> 0 | AK12: =SUM(AI12/AE12)-1 -> #DIV/0!
B13: Gross Profit | C13: =+C8+C12 -> #REF! | D13: =+D8+D12 -> 0 | E13: =+E8+E12 -> 0 | F13: =+F8+F12 -> 0 | H13: =+H8+H12 -> 0 | I13: =+I8+I12 -> 0 | J13: =+J8+J12 -> 0 | K13: =+K8+K12 -> 0 | L13: =+L8+L12 -> 0 | M13: =+M8+M12 -> 0 | N13: =+N8+N12 -> 0 | O13: =+O8+O12 -> 0 | ... V13: =+V8+V12 -> 0 | X13: =+X8+X12 -> 0 | Y13: =+Y8+Y12 -> 0 | Z13: =+Z8+Z12 -> 0 | AA13: =+AA8+AA12 -> 0 | AB13: =+AB8+AB12 -> 0 | AC13: =+AC8+AC12 -> 0 | AD13: =+AD8+AD12 -> 0 | AE13: =+AE8+AE12 -> 0 | ... AI13: =+AI8+AI12 -> 0 | AK13: =SUM(AI13/AE13)-1 -> #DIV/0!
B14: Gross Margin (%) | C14: =C13/C8 -> #REF! | D14: =D13/D8 -> #DIV/0! | E14: =E13/E8 -> #DIV/0! | F14: =F13/F8 -> #DIV/0! | H14: =H13/H8 -> #DIV/0! | I14: =I13/I8 -> #DIV/0! | J14: =J13/J8 -> #DIV/0! | K14: =K13/K8 -> #DIV/0! | L14: =L13/L8 -> #DIV/0! | M14: =M13/M8 -> #DIV/0! | N14: =N13/N8 -> #DIV/0! | O14: =O13/O8 -> #DIV/0! | ... V14: =V13/V8 -> #DIV/0! | X14: =X13/X8 -> #DIV/0! | Y14: =Y13/Y8 -> #DIV/0! | Z14: =Z13/Z8 -> #DIV/0! | AA14: =AA13/AA8 -> #DIV/0! | AB14: =AB13/AB8 -> #DIV/0! | AC14: =AC13/AC8 -> #DIV/0! | AD14: =AD13/AD8 -> #DIV/0! | AE14: =AE13/AE8 -> #DIV/0! | ... AI14: =AI13/AI8 -> #DIV/0! | AK14: =SUM(AI14-AE14)*10000 -> #DIV/0!
B16: (-) Research and development | C16: ='Historical Financials'!#REF! -> #REF! | H16: ='Historical Financials'!G17 -> -14906 | I16: ='Historical Financials'!H17 -> -16948 | J16: ='Historical Financials'!I17 -> -18526 | K16: ='Historical Financials'!J17 -> -17652 | L16: ='Historical Financials'!K17 -> -22120 | M16: ='Historical Financials'!L17 -> -24969 | N16: ='Historical Financials'!M17 -> -23603 | O16: ='Historical Financials'!N17 -> -18731 | ... Q16: ='Historical Financials'!P17 -> -15198 | X16: =SUM(G16:K16) -> -68032 | Y16: =SUM(I16:L16) -> -75246 | Z16: =SUM(J16:M16) -> -83267 | AA16: =SUM(K16:N16) -> -88344 | AB16: =SUM(L16:O16) -> -89423 | AC16: =SUM(M16:P16) -> -83536 | AD16: =SUM(N16:Q16) -> -73765 | AE16: =SUM(O16:R16) -> -50162 | AF16: =SUM(P16:S16) -> -31431 | ... AI16: =SUM(S16:V16) -> 0 | AK16: =SUM(AI16/AE16)-1 -> -1
B17: (-) Sales and marketing | C17: ='Historical Financials'!#REF! -> #REF! | H17: ='Historical Financials'!G18 -> -2915 | I17: ='Historical Financials'!H18 -> -2969 | J17: ='Historical Financials'!I18 -> -2819 | K17: ='Historical Financials'!J18 -> -3285 | L17: ='Historical Financials'!K18 -> -4392 | M17: ='Historical Financials'!L18 -> -3808 | N17: ='Historical Financials'!M18 -> -4276 | O17: ='Historical Financials'!N18 -> -4058 | ... Q17: ='Historical Financials'!P18 -> -46204 | X17: =SUM(G17:K17) -> -11988 | Y17: =SUM(I17:L17) -> -13465 | Z17: =SUM(J17:M17) -> -14304 | AA17: =SUM(K17:N17) -> -15761 | AB17: =SUM(L17:O17) -> -16534 | AC17: =SUM(M17:P17) -> -15843 | AD17: =SUM(N17:Q17) -> -58239 | AE17: =SUM(O17:R17) -> -53963 | AF17: =SUM(P17:S17) -> -49905 | ... AI17: =SUM(S17:V17) -> 0 | AK17: =SUM(AI17/AE17)-1 -> -1
B18: (-) General and administrative | C18: ='Historical Financials'!#REF! -> #REF! | H18: ='Historical Financials'!#REF! -> #REF! | I18: ='Historical Financials'!#REF! -> #REF! | J18: ='Historical Financials'!#REF! -> #REF! | K18: ='Historical Financials'!#REF! -> #REF! | L18: ='Historical Financials'!#REF! -> #REF! | M18: ='Historical Financials'!#REF! -> #REF! | N18: ='Historical Financials'!#REF! -> #REF! | O18: ='Historical Financials'!#REF! -> #REF! | ... Q18: ='Historical Financials'!#REF! -> #REF! | X18: =SUM(G18:K18) -> #REF! | Y18: =SUM(I18:L18) -> #REF! | Z18: =SUM(J18:M18) -> #REF! | AA18: =SUM(K18:N18) -> #REF! | AB18: =SUM(L18:O18) -> #REF! | AC18: =SUM(M18:P18) -> #REF! | AD18: =SUM(N18:Q18) -> #REF! | AE18: =SUM(O18:R18) -> #REF! | AF18: =SUM(P18:S18) -> #REF! | ... AI18: =SUM(S18:V18) -> 0 | AK18: =SUM(AI18/AE18)-1 -> #REF!
B19: (-) Depreciation and amortization | C19: ='Historical Financials'!#REF! -> #REF! | H19: ='Historical Financials'!#REF! -> #REF! | I19: ='Historical Financials'!#REF! -> #REF! | J19: ='Historical Financials'!#REF! -> #REF! | K19: ='Historical Financials'!#REF! -> #REF! | L19: ='Historical Financials'!#REF! -> #REF! | M19: ='Historical Financials'!#REF! -> #REF! | N19: ='Historical Financials'!#REF! -> #REF! | O19: ='Historical Financials'!#REF! -> #REF! | ... Q19: ='Historical Financials'!#REF! -> #REF! | X19: =SUM(G19:K19) -> #REF! | Y19: =SUM(I19:L19) -> #REF! | Z19: =SUM(J19:M19) -> #REF! | AA19: =SUM(K19:N19) -> #REF! | AB19: =SUM(L19:O19) -> #REF! | AC19: =SUM(M19:P19) -> #REF! | AD19: =SUM(N19:Q19) -> #REF! | AE19: =SUM(O19:R19) -> #REF! | AF19: =SUM(P19:S19) -> #REF! | ... AI19: =SUM(S19:V19) -> 0 | AK19: =SUM(AI19/AE19)-1 -> #REF!
B20: Earning before Interest & Taxes (EBIT) | C20: =SUM(C13+SUM(C16:C19)) -> #REF! | D20: =SUM(D13+SUM(D16:D19)) -> 0 | E20: =SUM(E13+SUM(E16:E19)) -> 0 | F20: =SUM(F13+SUM(F16:F19)) -> 0 | H20: =SUM(H13+SUM(H16:H19)) -> #REF! | I20: =SUM(I13+SUM(I16:I19)) -> #REF! | J20: =SUM(J13+SUM(J16:J19)) -> #REF! | K20: =SUM(K13+SUM(K16:K19)) -> #REF! | L20: =SUM(L13+SUM(L16:L19)) -> #REF! | M20: =SUM(M13+SUM(M16:M19)) -> #REF! | N20: =SUM(N13+SUM(N16:N19)) -> #REF! | O20: =SUM(O13+SUM(O16:O19)) -> #REF! | ... V20: =SUM(V13+SUM(V16:V19)) -> 0 | X20: =SUM(X13+SUM(X16:X19)) -> #REF! | Y20: =SUM(Y13+SUM(Y16:Y19)) -> #REF! | Z20: =SUM(Z13+SUM(Z16:Z19)) -> #REF! | AA20: =SUM(AA13+SUM(AA16:AA19)) -> #REF! | AB20: =SUM(AB13+SUM(AB16:AB19)) -> #REF! | AC20: =SUM(AC13+SUM(AC16:AC19)) -> #REF! | AD20: =SUM(AD13+SUM(AD16:AD19)) -> #REF! | AE20: =SUM(AE13+SUM(AE16:AE19)) -> #REF! | ... AI20: =SUM(AI13+SUM(AI16:AI19)) -> 0 | AK20: =SUM(AI20/AE20)-1 -> #REF!
B21: Operating Margin (%) | C21: =C20/C8 -> #REF! | D21: =D20/D8 -> #DIV/0! | E21: =E20/E8 -> #DIV/0! | F21: =F20/F8 -> #DIV/0! | H21: =H20/H8 -> #REF! | I21: =I20/I8 -> #REF! | J21: =J20/J8 -> #REF! | K21: =K20/K8 -> #REF! | L21: =L20/L8 -> #REF! | M21: =M20/M8 -> #REF! | N21: =N20/N8 -> #REF! | O21: =O20/O8 -> #REF! | ... V21: =V20/V8 -> #DIV/0! | X21: =X20/X8 -> #REF! | Y21: =Y20/Y8 -> #REF! | Z21: =Z20/Z8 -> #REF! | AA21: =AA20/AA8 -> #REF! | AB21: =AB20/AB8 -> #REF! | AC21: =AC20/AC8 -> #REF! | AD21: =AD20/AD8 -> #REF! | AE21: =AE20/AE8 -> #REF! | ... AI21: =AI20/AI8 -> #DIV/0! | AK21: =SUM(AI21-AE21)*10000 -> #DIV/0!
B23: (+) Depreciation and Amortization | C23: =-C19 -> #REF! | H23: =-H19 -> #REF! | I23: =-I19 -> #REF! | J23: =-J19 -> #REF! | K23: =-K19 -> #REF! | L23: =-L19 -> #REF! | M23: =-M19 -> #REF! | N23: =-N19 -> #REF! | O23: =-O19 -> #REF! | ... Q23: =-Q19 -> #REF! | X23: =SUM(G23:K23) -> #REF! | Y23: =SUM(I23:L23) -> #REF! | Z23: =SUM(J23:M23) -> #REF! | AA23: =SUM(K23:N23) -> #REF! | AB23: =SUM(L23:O23) -> #REF! | AC23: =SUM(M23:P23) -> #REF! | AD23: =SUM(N23:Q23) -> #REF! | AE23: =SUM(O23:R23) -> #REF! | AF23: =SUM(P23:S23) -> #REF! | ... AI23: =SUM(S23:V23) -> 0 | AK23: =SUM(AI23/AE23)-1 -> #REF!
B24: EBITDA | C24: =SUM(C20+C23) -> #REF! | D24: =SUM(D20+D23) -> 0 | E24: =SUM(E20+E23) -> 0 | F24: =SUM(F20+F23) -> 0 | H24: =SUM(H20+H23) -> #REF! | I24: =SUM(I20+I23) -> #REF! | J24: =SUM(J20+J23) -> #REF! | K24: =SUM(K20+K23) -> #REF! | L24: =SUM(L20+L23) -> #REF! | M24: =SUM(M20+M23) -> #REF! | N24: =SUM(N20+N23) -> #REF! | O24: =SUM(O20+O23) -> #REF! | ... V24: =SUM(V20+V23) -> 0 | X24: =SUM(X20+X23) -> #REF! | Y24: =SUM(Y20+Y23) -> #REF! | Z24: =SUM(Z20+Z23) -> #REF! | AA24: =SUM(AA20+AA23) -> #REF! | AB24: =SUM(AB20+AB23) -> #REF! | AC24: =SUM(AC20+AC23) -> #REF! | AD24: =SUM(AD20+AD23) -> #REF! | AE24: =SUM(AE20+AE23) -> #REF! | ... AI24: =SUM(AI20+AI23) -> 0 | AK24: =SUM(AI24/AE24)-1 -> #REF!
B25: EBITDA Margin (%) | C25: =C24/C8 -> #REF! | D25: =D24/D8 -> #DIV/0! | E25: =E24/E8 -> #DIV/0! | F25: =F24/F8 -> #DIV/0! | H25: =H24/H8 -> #REF! | I25: =I24/I8 -> #REF! | J25: =J24/J8 -> #REF! | K25: =K24/K8 -> #REF! | L25: =L24/L8 -> #REF! | M25: =M24/M8 -> #REF! | N25: =N24/N8 -> #REF! | O25: =O24/O8 -> #REF! | ... V25: =V24/V8 -> #DIV/0! | X25: =X24/X8 -> #REF! | Y25: =Y24/Y8 -> #REF! | Z25: =Z24/Z8 -> #REF! | AA25: =AA24/AA8 -> #REF! | AB25: =AB24/AB8 -> #REF! | AC25: =AC24/AC8 -> #REF! | AD25: =AD24/AD8 -> #REF! | AE25: =AE24/AE8 -> #REF! | ... AI25: =AI24/AI8 -> #DIV/0! | AK25: =SUM(AI25-AE25)*10000 -> #DIV/0!
B27: (+) Share-based Compensation | C27: ='Historical Financials'!#REF! -> #REF! | H27: ='Historical Financials'!G89 -> 0 | I27: ='Historical Financials'!H89 -> 0 | J27: ='Historical Financials'!I89 -> 0 | K27: ='Historical Financials'!J89 -> 0 | L27: ='Historical Financials'!K89 -> 0 | M27: ='Historical Financials'!L89 -> 0 | N27: ='Historical Financials'!M89 -> 0 | O27: ='Historical Financials'!N89 -> 0 | ... Q27: ='Historical Financials'!P89 -> -65142 | X27: =SUM(G27:K27) -> 0 | Y27: =SUM(I27:L27) -> 0 | Z27: =SUM(J27:M27) -> 0 | AA27: =SUM(K27:N27) -> 0 | AB27: =SUM(L27:O27) -> 0 | AC27: =SUM(M27:P27) -> -43041 | AD27: =SUM(N27:Q27) -> -108183 | AE27: =SUM(O27:R27) -> -108183 | AF27: =SUM(P27:S27) -> -108183 | ... AI27: =SUM(S27:V27) -> 0 | AK27: =SUM(AI27/AE27)-1 -> -1
B28: Adj. EBITDA | C28: =+SUM(C24+SUM(C27:C27)) -> #REF! | D28: =+SUM(D24+SUM(D27:D27)) -> 0 | E28: =+SUM(E24+SUM(E27:E27)) -> 0 | F28: =+SUM(F24+SUM(F27:F27)) -> 0 | H28: =+SUM(H24+SUM(H27:H27)) -> #REF! | I28: =+SUM(I24+SUM(I27:I27)) -> #REF! | J28: =+SUM(J24+SUM(J27:J27)) -> #REF! | K28: =+SUM(K24+SUM(K27:K27)) -> #REF! | L28: =+SUM(L24+SUM(L27:L27)) -> #REF! | M28: =+SUM(M24+SUM(M27:M27)) -> #REF! | N28: =+SUM(N24+SUM(N27:N27)) -> #REF! | O28: =+SUM(O24+SUM(O27:O27)) -> #REF! | ... V28: =+SUM(V24+SUM(V27:V27)) -> 0 | X28: =+SUM(X24+SUM(X27:X27)) -> #REF! | Y28: =+SUM(Y24+SUM(Y27:Y27)) -> #REF! | Z28: =+SUM(Z24+SUM(Z27:Z27)) -> #REF! | AA28: =+SUM(AA24+SUM(AA27:AA27)) -> #REF! | AB28: =+SUM(AB24+SUM(AB27:AB27)) -> #REF! | AC28: =+SUM(AC24+SUM(AC27:AC27)) -> #REF! | AD28: =+SUM(AD24+SUM(AD27:AD27)) -> #REF! | AE28: =+SUM(AE24+SUM(AE27:AE27)) -> #REF! | ... AI28: =+SUM(AI24+SUM(AI27:AI27)) -> 0 | AK28: =SUM(AI28/AE28)-1 -> #REF!
B29: Adj. EBITDA Margin (%) | C29: =C28/C8 -> #REF! | D29: =D28/D8 -> #DIV/0! | E29: =E28/E8 -> #DIV/0! | F29: =F28/F8 -> #DIV/0! | H29: =H28/H8 -> #REF! | I29: =I28/I8 -> #REF! | J29: =J28/J8 -> #REF! | K29: =K28/K8 -> #REF! | L29: =L28/L8 -> #REF! | M29: =M28/M8 -> #REF! | N29: =N28/N8 -> #REF! | O29: =O28/O8 -> #REF! | ... V29: =V28/V8 -> #DIV/0! | X29: =X28/X8 -> #REF! | Y29: =Y28/Y8 -> #REF! | Z29: =Z28/Z8 -> #REF! | AA29: =AA28/AA8 -> #REF! | AB29: =AB28/AB8 -> #REF! | AC29: =AC28/AC8 -> #REF! | AD29: =AD28/AD8 -> #REF! | AE29: =AE28/AE8 -> #REF! | ... AI29: =AI28/AI8 -> #DIV/0! | AK29: =SUM(AI29-AE29)*10000 -> #DIV/0!
B31: (-) Capital Expenditures | C31: =SUM('Historical Financials'!#REF!+'Historical Financials'!#REF!) -> #REF! | H31: =SUM('Historical Financials'!G103+'Historical Financials'!#REF!) -> #REF! | I31: =SUM('Historical Financials'!H103+'Historical Financials'!#REF!) -> #REF! | J31: =SUM('Historical Financials'!I103+'Historical Financials'!#REF!) -> #REF! | K31: =SUM('Historical Financials'!J103+'Historical Financials'!#REF!) -> #REF! | L31: =SUM('Historical Financials'!K103+'Historical Financials'!#REF!) -> #REF! | M31: =SUM('Historical Financials'!L103+'Historical Financials'!#REF!) -> #REF! | N31: =SUM('Historical Financials'!M103+'Historical Financials'!#REF!) -> #REF! | O31: =SUM('Historical Financials'!N103+'Historical Financials'!#REF!) -> #REF! | ... Q31: =SUM('Historical Financials'!P103+'Historical Financials'!#REF!) -> #REF! | X31: =SUM(G31:K31) -> #REF! | Y31: =SUM(I31:L31) -> #REF! | Z31: =SUM(J31:M31) -> #REF! | AA31: =SUM(K31:N31) -> #REF! | AB31: =SUM(L31:O31) -> #REF! | AC31: =SUM(M31:P31) -> #REF! | AD31: =SUM(N31:Q31) -> #REF! | AE31: =SUM(O31:R31) -> #REF! | AF31: =SUM(P31:S31) -> #REF! | ... AI31: =SUM(S31:V31) -> 0 | AK31: =SUM(AI31/AE31)-1 -> #REF!
B32: (-) Cash Taxes | C32: ='Historical Financials'!#REF! -> #REF! | H32: ='Historical Financials'!G28 -> 0 | I32: ='Historical Financials'!H28 -> 0 | J32: ='Historical Financials'!I28 -> 0 | K32: ='Historical Financials'!J28 -> 0 | L32: ='Historical Financials'!K28 -> 0 | M32: ='Historical Financials'!L28 -> 0 | N32: ='Historical Financials'!M28 -> 0 | O32: ='Historical Financials'!N28 -> 0 | ... Q32: ='Historical Financials'!P28 -> 0 | X32: =SUM(G32:K32) -> 0 | Y32: =SUM(I32:L32) -> 0 | Z32: =SUM(J32:M32) -> 0 | AA32: =SUM(K32:N32) -> 0 | AB32: =SUM(L32:O32) -> 0 | AC32: =SUM(M32:P32) -> 0 | AD32: =SUM(N32:Q32) -> 0 | AE32: =SUM(O32:R32) -> 0 | AF32: =SUM(P32:S32) -> 0 | ... AI32: =SUM(S32:V32) -> 0 | AK32: =SUM(AI32/AE32)-1 -> #DIV/0!
B33: (-) Cash Interest | C33: 0 | H33: 0 | I33: 0 | J33: 0 | K33: =D33 -> 0 | L33: 0 | M33: 0 | N33: 0 | O33: =E33 -> 0 | P33: 0 | Q33: 0 | X33: =SUM(G33:K33) -> 0 | Y33: =SUM(I33:L33) -> 0 | Z33: =SUM(J33:M33) -> 0 | AA33: =SUM(K33:N33) -> 0 | AB33: =SUM(L33:O33) -> 0 | AC33: =SUM(M33:P33) -> 0 | AD33: =SUM(N33:Q33) -> 0 | AE33: =SUM(O33:R33) -> 0 | AF33: =SUM(P33:S33) -> 0 | ... AI33: =SUM(S33:V33) -> 0 | AK33: =SUM(AI33/AE33)-1 -> #DIV/0!
B34: (+/-) Changes in NWC | C34: =SUM('Historical Financials'!#REF!) -> #REF! | H34: =SUM('Historical Financials'!G94:G99) -> -6811 | I34: =SUM('Historical Financials'!H94:H99) -> 7430 | J34: =SUM('Historical Financials'!I94:I99) -> -2063 | K34: =SUM('Historical Financials'!J94:J99) -> -3191 | L34: =SUM('Historical Financials'!K94:K99) -> 9952 | M34: =SUM('Historical Financials'!L94:L99) -> 5192 | N34: =SUM('Historical Financials'!M94:M99) -> -2186 | O34: =SUM('Historical Financials'!N94:N99) -> -3882 | ... Q34: =SUM('Historical Financials'!P94:P99) -> 37840 | X34: =SUM(G34:K34) -> -4635 | Y34: =SUM(I34:L34) -> 12128 | Z34: =SUM(J34:M34) -> 9890 | AA34: =SUM(K34:N34) -> 9767 | AB34: =SUM(L34:O34) -> 9076 | AC34: =SUM(M34:P34) -> -4651 | AD34: =SUM(N34:Q34) -> 27997 | AE34: =SUM(O34:R34) -> 30183 | AF34: =SUM(P34:S34) -> 34065 | ... AI34: =SUM(S34:V34) -> 0 | AK34: =SUM(AI34/AE34)-1 -> -1
B35: Discretionary Cash-Flows | C35: =SUM(C28+SUM(C31:C34)) -> #REF! | D35: =SUM(D28+SUM(D31:D34)) -> 0 | E35: =SUM(E28+SUM(E31:E34)) -> 0 | F35: =SUM(F28+SUM(F31:F34)) -> 0 | H35: =SUM(H28+SUM(H31:H34)) -> #REF! | I35: =SUM(I28+SUM(I31:I34)) -> #REF! | J35: =SUM(J28+SUM(J31:J34)) -> #REF! | K35: =SUM(K28+SUM(K31:K34)) -> #REF! | L35: =SUM(L28+SUM(L31:L34)) -> #REF! | M35: =SUM(M28+SUM(M31:M34)) -> #REF! | N35: =SUM(N28+SUM(N31:N34)) -> #REF! | O35: =SUM(O28+SUM(O31:O34)) -> #REF! | ... V35: =SUM(V28+SUM(V31:V34)) -> 0 | X35: =SUM(X28+SUM(X31:X34)) -> #REF! | Y35: =SUM(Y28+SUM(Y31:Y34)) -> #REF! | Z35: =SUM(Z28+SUM(Z31:Z34)) -> #REF! | AA35: =SUM(AA28+SUM(AA31:AA34)) -> #REF! | AB35: =SUM(AB28+SUM(AB31:AB34)) -> #REF! | AC35: =SUM(AC28+SUM(AC31:AC34)) -> #REF! | AD35: =SUM(AD28+SUM(AD31:AD34)) -> #REF! | AE35: =SUM(AE28+SUM(AE31:AE34)) -> #REF! | ... AI35: =SUM(AI28+SUM(AI31:AI34)) -> 0 | AK35: =SUM(AI35/AE35)-1 -> #REF!
B37: (+/-) Proceeds / (Purchases) of Equity, net | C37: ='Historical Financials'!#REF! -> #REF! | H37: ='Historical Financials'!#REF! -> #REF! | I37: ='Historical Financials'!#REF! -> #REF! | J37: ='Historical Financials'!#REF! -> #REF! | K37: ='Historical Financials'!#REF! -> #REF! | L37: ='Historical Financials'!#REF! -> #REF! | M37: ='Historical Financials'!#REF! -> #REF! | N37: ='Historical Financials'!#REF! -> #REF! | O37: ='Historical Financials'!#REF! -> #REF! | ... Q37: ='Historical Financials'!#REF! -> #REF! | X37: =SUM(G37:K37) -> #REF! | Y37: =SUM(I37:L37) -> #REF! | Z37: =SUM(J37:M37) -> #REF! | AA37: =SUM(K37:N37) -> #REF! | AB37: =SUM(L37:O37) -> #REF! | AC37: =SUM(M37:P37) -> #REF! | AD37: =SUM(N37:Q37) -> #REF! | AE37: =SUM(O37:R37) -> #REF! | AF37: =SUM(P37:S37) -> #REF! | ... AI37: =SUM(S37:V37) -> 0
B38: (+/-) Maturities / (Purchases) of available-for-sale securities | C38: =SUM('Historical Financials'!#REF!) -> #REF! | H38: =SUM('Historical Financials'!#REF!) -> #REF! | I38: =SUM('Historical Financials'!#REF!) -> #REF! | J38: =SUM('Historical Financials'!#REF!) -> #REF! | K38: =SUM('Historical Financials'!#REF!) -> #REF! | L38: =SUM('Historical Financials'!#REF!) -> #REF! | M38: =SUM('Historical Financials'!#REF!) -> #REF! | N38: =SUM('Historical Financials'!#REF!) -> #REF! | O38: =SUM('Historical Financials'!#REF!) -> #REF! | ... Q38: =SUM('Historical Financials'!#REF!) -> #REF! | X38: =SUM(G38:K38) -> #REF! | Y38: =SUM(I38:L38) -> #REF! | Z38: =SUM(J38:M38) -> #REF! | AA38: =SUM(K38:N38) -> #REF! | AB38: =SUM(L38:O38) -> #REF! | AC38: =SUM(M38:P38) -> #REF! | AD38: =SUM(N38:Q38) -> #REF! | AE38: =SUM(O38:R38) -> #REF! | AF38: =SUM(P38:S38) -> #REF! | ... AI38: =SUM(S38:V38) -> 0
B39: (+/-) Divestitures / (Acquisitions) | C39: ='Historical Financials'!#REF! -> #REF! | H39: ='Historical Financials'!#REF! -> #REF! | I39: ='Historical Financials'!#REF! -> #REF! | J39: ='Historical Financials'!#REF! -> #REF! | K39: ='Historical Financials'!#REF! -> #REF! | L39: ='Historical Financials'!#REF! -> #REF! | M39: ='Historical Financials'!#REF! -> #REF! | N39: ='Historical Financials'!#REF! -> #REF! | O39: ='Historical Financials'!#REF! -> #REF! | ... Q39: ='Historical Financials'!#REF! -> #REF! | X39: =SUM(G39:K39) -> #REF! | Y39: =SUM(I39:L39) -> #REF! | Z39: =SUM(J39:M39) -> #REF! | AA39: =SUM(K39:N39) -> #REF! | AB39: =SUM(L39:O39) -> #REF! | AC39: =SUM(M39:P39) -> #REF! | AD39: =SUM(N39:Q39) -> #REF! | AE39: =SUM(O39:R39) -> #REF! | AF39: =SUM(P39:S39) -> #REF! | ... AI39: =SUM(S39:V39) -> 0
B40: (+/-) Other Investing Activities | C40: ='Historical Financials'!#REF! -> #REF! | H40: ='Historical Financials'!#REF! -> #REF! | I40: ='Historical Financials'!#REF! -> #REF! | J40: ='Historical Financials'!#REF! -> #REF! | K40: ='Historical Financials'!#REF! -> #REF! | L40: ='Historical Financials'!#REF! -> #REF! | M40: ='Historical Financials'!#REF! -> #REF! | N40: ='Historical Financials'!#REF! -> #REF! | O40: ='Historical Financials'!#REF! -> #REF! | ... Q40: ='Historical Financials'!#REF! -> #REF! | X40: =SUM(G40:K40) -> #REF! | Y40: =SUM(I40:L40) -> #REF! | Z40: =SUM(J40:M40) -> #REF! | AA40: =SUM(K40:N40) -> #REF! | AB40: =SUM(L40:O40) -> #REF! | AC40: =SUM(M40:P40) -> #REF! | AD40: =SUM(N40:Q40) -> #REF! | AE40: =SUM(O40:R40) -> #REF! | AF40: =SUM(P40:S40) -> #REF! | ... AI40: =SUM(S40:V40) -> 0
B41: (+/-) Other Financing Activities | C41: ='Historical Financials'!#REF! -> #REF! | H41: ='Historical Financials'!#REF! -> #REF! | I41: ='Historical Financials'!#REF! -> #REF! | J41: ='Historical Financials'!#REF! -> #REF! | K41: ='Historical Financials'!#REF! -> #REF! | L41: ='Historical Financials'!#REF! -> #REF! | M41: ='Historical Financials'!#REF! -> #REF! | N41: ='Historical Financials'!#REF! -> #REF! | O41: ='Historical Financials'!#REF! -> #REF! | ... Q41: ='Historical Financials'!#REF! -> #REF! | X41: =SUM(G41:K41) -> #REF! | Y41: =SUM(I41:L41) -> #REF! | Z41: =SUM(J41:M41) -> #REF! | AA41: =SUM(K41:N41) -> #REF! | AB41: =SUM(L41:O41) -> #REF! | AC41: =SUM(M41:P41) -> #REF! | AD41: =SUM(N41:Q41) -> #REF! | AE41: =SUM(O41:R41) -> #REF! | AF41: =SUM(P41:S41) -> #REF! | ... AI41: =SUM(S41:V41) -> 0
B42: (+/-) Other Operating Activities | C42: ='Historical Financials'!#REF! -> #REF! | H42: ='Historical Financials'!#REF! -> #REF! | I42: ='Historical Financials'!#REF! -> #REF! | J42: ='Historical Financials'!#REF! -> #REF! | K42: ='Historical Financials'!#REF! -> #REF! | L42: ='Historical Financials'!#REF! -> #REF! | M42: ='Historical Financials'!#REF! -> #REF! | N42: ='Historical Financials'!#REF! -> #REF! | O42: ='Historical Financials'!#REF! -> #REF! | ... Q42: ='Historical Financials'!#REF! -> #REF! | X42: =SUM(G42:K42) -> #REF! | Y42: =SUM(I42:L42) -> #REF! | Z42: =SUM(J42:M42) -> #REF! | AA42: =SUM(K42:N42) -> #REF! | AB42: =SUM(L42:O42) -> #REF! | AC42: =SUM(M42:P42) -> #REF! | AD42: =SUM(N42:Q42) -> #REF! | AE42: =SUM(O42:R42) -> #REF! | AF42: =SUM(P42:S42) -> #REF! | ... AI42: =SUM(S42:V42) -> 0
B43: (+/-) Other | H43: =SUM(H48:H49)-SUM(C48:C49)-SUM(H35:H42) -> #REF! | I43: =SUM(I48:I49)-SUM(H48:H49)-SUM(I35:I42) -> #REF! | J43: =SUM(J48:J49)-SUM(I48:I49)-SUM(J35:J42) -> #REF! | K43: =SUM(K48:K49)-SUM(J48:J49)-SUM(K35:K42) -> #REF! | L43: =SUM(L48:L49)-SUM(K48:K49)-SUM(L35:L42) -> #REF! | M43: =SUM(M48:M49)-SUM(L48:L49)-SUM(M35:M42) -> #REF! | N43: =SUM(N48:N49)-SUM(M48:M49)-SUM(N35:N42) -> #REF! | O43: =SUM(O48:O49)-SUM(N48:N49)-SUM(O35:O42) -> #REF! | P43: =SUM(P48:P49)-SUM(O48:O49)-SUM(P35:P42) -> #REF! | Q43: =SUM(Q48:Q49)-SUM(P48:P49)-SUM(Q35:Q42) -> #REF! | X43: =SUM(G43:K43) -> #REF! | Y43: =SUM(I43:L43) -> #REF! | Z43: =SUM(J43:M43) -> #REF! | AA43: =SUM(K43:N43) -> #REF! | AB43: =SUM(L43:O43) -> #REF! | AC43: =SUM(M43:P43) -> #REF! | AD43: =SUM(N43:Q43) -> #REF! | AE43: =SUM(O43:R43) -> #REF! | AF43: =SUM(P43:S43) -> #REF! | ... AI43: =SUM(S43:V43) -> 0
B44: Free-Cash Flows | C44: =SUM(C35+SUM(C37:C43)) -> #REF! | D44: =SUM(D35+SUM(D37:D43)) -> 0 | E44: =SUM(E35+SUM(E37:E43)) -> 0 | F44: =SUM(F35+SUM(F37:F43)) -> 0 | H44: =SUM(H35+SUM(H37:H43)) -> #REF! | I44: =SUM(I35+SUM(I37:I43)) -> #REF! | J44: =SUM(J35+SUM(J37:J43)) -> #REF! | K44: =SUM(K35+SUM(K37:K43)) -> #REF! | L44: =SUM(L35+SUM(L37:L43)) -> #REF! | M44: =SUM(M35+SUM(M37:M43)) -> #REF! | N44: =SUM(N35+SUM(N37:N43)) -> #REF! | O44: =SUM(O35+SUM(O37:O43)) -> #REF! | ... V44: =SUM(V35+SUM(V37:V43)) -> 0 | X44: =SUM(X35+SUM(X37:X43)) -> #REF! | Y44: =SUM(Y35+SUM(Y37:Y43)) -> #REF! | Z44: =SUM(Z35+SUM(Z37:Z43)) -> #REF! | AA44: =SUM(AA35+SUM(AA37:AA43)) -> #REF! | AB44: =SUM(AB35+SUM(AB37:AB43)) -> #REF! | AC44: =SUM(AC35+SUM(AC37:AC43)) -> #REF! | AD44: =SUM(AD35+SUM(AD37:AD43)) -> #REF! | AE44: =SUM(AE35+SUM(AE37:AE43)) -> #REF! | ... AI44: =SUM(AI35+SUM(AI37:AI43)) -> 0
B46: Capitalization
B48: Cash & Cash Equivelants | C48: ='Historical Financials'!#REF! -> #REF! | H48: ='Historical Financials'!G43 -> 209693 | I48: ='Historical Financials'!H43 -> 197232 | J48: ='Historical Financials'!I43 -> 174662 | K48: ='Historical Financials'!J43 -> 201015 | L48: ='Historical Financials'!K43 -> 187467 | M48: ='Historical Financials'!L43 -> 168438 | N48: ='Historical Financials'!M43 -> 142350 | O48: ='Historical Financials'!N43 -> 121136 | ... Q48: ='Historical Financials'!P43 -> 207291 | X48: =K48 -> 201015 | Y48: =L48 -> 187467 | Z48: =M48 -> 168438 | AA48: =N48 -> 142350 | AB48: =O48 -> 121136 | AC48: =P48 -> 124169 | AD48: =Q48 -> 207291 | AE48: =R48 -> 0 | ... AI48: =V48 -> 0
B49: Restricted Cash | C49: ='Historical Financials'!#REF! -> #REF! | H49: ='Historical Financials'!#REF! -> #REF! | I49: ='Historical Financials'!#REF! -> #REF! | J49: ='Historical Financials'!#REF! -> #REF! | K49: ='Historical Financials'!#REF! -> #REF! | L49: ='Historical Financials'!#REF! -> #REF! | M49: ='Historical Financials'!#REF! -> #REF! | N49: ='Historical Financials'!#REF! -> #REF! | O49: ='Historical Financials'!#REF! -> #REF! | ... Q49: ='Historical Financials'!#REF! -> #REF! | X49: =K49 -> #REF! | Y49: =L49 -> #REF! | Z49: =M49 -> #REF! | AA49: =N49 -> #REF! | AB49: =O49 -> #REF! | AC49: =P49 -> #REF! | AD49: =Q49 -> #REF! | AE49: =R49 -> 0 | ... AI49: =V49 -> 0
B50: Short-term Investments | C50: ='Historical Financials'!#REF! -> #REF! | H50: ='Historical Financials'!#REF! -> #REF! | I50: ='Historical Financials'!#REF! -> #REF! | J50: ='Historical Financials'!#REF! -> #REF! | K50: ='Historical Financials'!#REF! -> #REF! | L50: ='Historical Financials'!#REF! -> #REF! | M50: ='Historical Financials'!#REF! -> #REF! | N50: ='Historical Financials'!#REF! -> #REF! | O50: ='Historical Financials'!#REF! -> #REF! | ... Q50: ='Historical Financials'!#REF! -> #REF! | X50: =K50 -> #REF! | Y50: =L50 -> #REF! | Z50: =M50 -> #REF! | AA50: =N50 -> #REF! | AB50: =O50 -> #REF! | AC50: =P50 -> #REF! | AD50: =Q50 -> #REF! | AE50: =R50 -> 0 | ... AI50: =V50 -> 0
B51: Long-term Investments | C51: ='Historical Financials'!#REF! -> #REF! | H51: ='Historical Financials'!G49 -> 188 | I51: ='Historical Financials'!H49 -> 166 | J51: ='Historical Financials'!I49 -> 144 | K51: ='Historical Financials'!J49 -> 122 | L51: ='Historical Financials'!K49 -> - | M51: ='Historical Financials'!L49 -> - | N51: ='Historical Financials'!M49 -> - | O51: ='Historical Financials'!N49 -> 0 | ... Q51: ='Historical Financials'!P49 -> - | X51: =K51 -> 122 | Y51: =L51 -> - | Z51: =M51 -> - | AA51: =N51 -> - | AB51: =O51 -> 0 | AC51: =P51 -> - | AD51: =Q51 -> - | AE51: =R51 -> 0 | ... AI51: =V51 -> 0
B52: Total Liquidity | C52: =SUM(C48:C51) -> #REF! | D52: =SUM(D48:D51) -> 0 | E52: =SUM(E48:E51) -> 0 | F52: =SUM(F48:F51) -> 0 | H52: =SUM(H48:H51) -> #REF! | I52: =SUM(I48:I51) -> #REF! | J52: =SUM(J48:J51) -> #REF! | K52: =SUM(K48:K51) -> #REF! | L52: =SUM(L48:L51) -> #REF! | M52: =SUM(M48:M51) -> #REF! | N52: =SUM(N48:N51) -> #REF! | O52: =SUM(O48:O51) -> #REF! | ... V52: =SUM(V48:V51) -> 0 | X52: =SUM(X48:X51) -> #REF! | Y52: =SUM(Y48:Y51) -> #REF! | Z52: =SUM(Z48:Z51) -> #REF! | AA52: =SUM(AA48:AA51) -> #REF! | AB52: =SUM(AB48:AB51) -> #REF! | AC52: =SUM(AC48:AC51) -> #REF! | AD52: =SUM(AD48:AD51) -> #REF! | AE52: =SUM(AE48:AE51) -> 0 | ... AI52: =SUM(AI48:AI51) -> 0
B54: Balance Sheet Metrics:
B55: Accounts Receivable | C55: ='Historical Financials'!#REF! -> #REF! | H55: ='Historical Financials'!#REF! -> #REF! | I55: ='Historical Financials'!#REF! -> #REF! | J55: ='Historical Financials'!#REF! -> #REF! | K55: ='Historical Financials'!#REF! -> #REF! | L55: ='Historical Financials'!#REF! -> #REF! | M55: ='Historical Financials'!#REF! -> #REF! | N55: ='Historical Financials'!#REF! -> #REF! | O55: ='Historical Financials'!#REF! -> #REF! | ... Q55: ='Historical Financials'!#REF! -> #REF! | X55: =K55 -> #REF! | Y55: =L55 -> #REF! | Z55: =M55 -> #REF! | AA55: =N55 -> #REF! | AB55: =O55 -> #REF! | AC55: =P55 -> #REF! | AD55: =Q55 -> #REF! | AE55: =R55 -> 0 | ... AI55: =V55 -> 0
B56: Accounts Payable | C56: ='Historical Financials'!#REF! -> #REF! | H56: ='Historical Financials'!G56 -> 3332 | I56: ='Historical Financials'!H56 -> 4758 | J56: ='Historical Financials'!I56 -> 3534 | K56: ='Historical Financials'!J56 -> 4017 | L56: ='Historical Financials'!K56 -> 8242 | M56: ='Historical Financials'!L56 -> 10338 | N56: ='Historical Financials'!M56 -> 9492 | O56: ='Historical Financials'!N56 -> 10573 | ... Q56: ='Historical Financials'!P56 -> 52552 | X56: =K56 -> 4017 | Y56: =L56 -> 8242 | Z56: =M56 -> 10338 | AA56: =N56 -> 9492 | AB56: =O56 -> 10573 | AC56: =P56 -> 9603 | AD56: =Q56 -> 52552 | AE56: =R56 -> 0 | ... AI56: =V56 -> 0
B57: Unearned Revenue, Current | C57: ='Historical Financials'!#REF! -> #REF! | H57: ='Historical Financials'!G61 -> 261 | I57: ='Historical Financials'!H61 -> 370 | J57: ='Historical Financials'!I61 -> 416 | K57: ='Historical Financials'!J61 -> 492 | L57: ='Historical Financials'!K61 -> 179 | M57: ='Historical Financials'!L61 -> 293 | N57: ='Historical Financials'!M61 -> 391 | O57: ='Historical Financials'!N61 -> 385 | ... Q57: ='Historical Financials'!P61 -> 228 | X57: =K57 -> 492 | Y57: =L57 -> 179 | Z57: =M57 -> 293 | AA57: =N57 -> 391 | AB57: =O57 -> 385 | AC57: =P57 -> 125 | AD57: =Q57 -> 228 | AE57: =R57 -> 0 | ... AI57: =V57 -> 0
B58: Unearned Revenue, Non-Current | C58: ='Historical Financials'!#REF! -> #REF! | H58: ='Historical Financials'!#REF! -> #REF! | I58: ='Historical Financials'!#REF! -> #REF! | J58: ='Historical Financials'!#REF! -> #REF! | K58: ='Historical Financials'!#REF! -> #REF! | L58: ='Historical Financials'!#REF! -> #REF! | M58: ='Historical Financials'!#REF! -> #REF! | N58: ='Historical Financials'!#REF! -> #REF! | O58: ='Historical Financials'!#REF! -> #REF! | ... Q58: ='Historical Financials'!#REF! -> #REF! | X58: =K58 -> #REF! | Y58: =L58 -> #REF! | Z58: =M58 -> #REF! | AA58: =N58 -> #REF! | AB58: =O58 -> #REF! | AC58: =P58 -> #REF! | AD58: =Q58 -> #REF! | AE58: =R58 -> 0 | ... AI58: =V58 -> 0
B59: Property Plant, and Equiptment | C59: ='Historical Financials'!#REF! -> #REF! | H59: ='Historical Financials'!G51 -> 940 | I59: ='Historical Financials'!H51 -> 859 | J59: ='Historical Financials'!I51 -> 740 | K59: ='Historical Financials'!J51 -> 622 | L59: ='Historical Financials'!K51 -> 503 | M59: ='Historical Financials'!L51 -> 387 | N59: ='Historical Financials'!M51 -> 268 | O59: ='Historical Financials'!N51 -> 176 | ... Q59: ='Historical Financials'!P51 -> 82 | X59: =K59 -> 622 | Y59: =L59 -> 503 | Z59: =M59 -> 387 | AA59: =N59 -> 268 | AB59: =O59 -> 176 | AC59: =P59 -> 115 | AD59: =Q59 -> 82 | AE59: =R59 -> 0 | ... AI59: =V59 -> 0
B60: Current Liabilities | C60: ='Historical Financials'!#REF! -> #REF! | H60: ='Historical Financials'!G62 -> 6789 | I60: ='Historical Financials'!H62 -> 8722 | J60: ='Historical Financials'!I62 -> 8308 | K60: ='Historical Financials'!J62 -> 7063 | L60: ='Historical Financials'!K62 -> 13909 | M60: ='Historical Financials'!L62 -> 17895 | N60: ='Historical Financials'!M62 -> 17414 | O60: ='Historical Financials'!N62 -> 14195 | ... Q60: ='Historical Financials'!P62 -> 54594 | X60: =K60 -> 7063 | Y60: =L60 -> 13909 | Z60: =M60 -> 17895 | AA60: =N60 -> 17414 | AB60: =O60 -> 14195 | AC60: =P60 -> 77121 | AD60: =Q60 -> 54594 | AE60: =R60 -> 0 | ... AI60: =V60 -> 0
B61: Total Liabilities | C61: ='Historical Financials'!#REF! -> #REF! | H61: ='Historical Financials'!G67 -> 7097 | I61: ='Historical Financials'!H67 -> 9011 | J61: ='Historical Financials'!I67 -> 8567 | K61: ='Historical Financials'!J67 -> 7295 | L61: ='Historical Financials'!K67 -> 14106 | M61: ='Historical Financials'!L67 -> 17895 | N61: ='Historical Financials'!M67 -> 17414 | O61: ='Historical Financials'!N67 -> 14195 | ... Q61: ='Historical Financials'!P67 -> 54594 | X61: =K61 -> 7295 | Y61: =L61 -> 14106 | Z61: =M61 -> 17895 | AA61: =N61 -> 17414 | AB61: =O61 -> 14195 | AC61: =P61 -> 77121 | AD61: =Q61 -> 54594 | AE61: =R61 -> 0 | ... AI61: =V61 -> 0
B63: Consolidated Debt | C63: 0 | H63: 0 | I63: 0 | J63: 0 | K63: =D63 -> 0 | L63: 0 | M63: 0 | N63: 0 | O63: =E63 -> 0 | P63: 0 | Q63: 0 | X63: =K63 -> 0 | Y63: =L63 -> 0 | Z63: =M63 -> 0 | AA63: =N63 -> 0 | AB63: =O63 -> 0 | AC63: =P63 -> 0 | AD63: =Q63 -> 0 | AE63: =R63 -> 0 | ... AI63: =V63 -> 0
B64: Total Debt | C64: =SUM(C63:C63) -> 0 | D64: =SUM(D63:D63) -> 0 | E64: =SUM(E63:E63) -> 0 | F64: =SUM(F63:F63) -> 0 | H64: =SUM(H63:H63) -> 0 | I64: =SUM(I63:I63) -> 0 | J64: =SUM(J63:J63) -> 0 | K64: =SUM(K63:K63) -> 0 | L64: =SUM(L63:L63) -> 0 | M64: =SUM(M63:M63) -> 0 | N64: =SUM(N63:N63) -> 0 | O64: =SUM(O63:O63) -> 0 | ... V64: =SUM(V63:V63) -> 0 | X64: =SUM(X63:X63) -> 0 | Y64: =SUM(Y63:Y63) -> 0 | Z64: =SUM(Z63:Z63) -> 0 | AA64: =SUM(AA63:AA63) -> 0 | AB64: =SUM(AB63:AB63) -> 0 | AC64: =SUM(AC63:AC63) -> 0 | AD64: =SUM(AD63:AD63) -> 0 | AE64: =SUM(AE63:AE63) -> 0 | ... AI64: =SUM(AI63:AI63) -> 0
B66: Total Shareholder Equity | C66: ='Historical Financials'!#REF! -> #REF! | H66: ='Historical Financials'!G73 -> 237094 | I66: ='Historical Financials'!H73 -> 218370 | J66: ='Historical Financials'!I73 -> 198719 | K66: ='Historical Financials'!J73 -> 227539 | L66: ='Historical Financials'!K73 -> 204005 | M66: ='Historical Financials'!L73 -> 179353 | N66: ='Historical Financials'!M73 -> 155115 | O66: ='Historical Financials'!N73 -> 137468 | ... Q66: ='Historical Financials'!P73 -> 188974 | X66: =K66 -> 227539 | Y66: =L66 -> 204005 | Z66: =M66 -> 179353 | AA66: =N66 -> 155115 | AB66: =O66 -> 137468 | AC66: =P66 -> 78597 | AD66: =Q66 -> 188974 | AE66: =R66 -> 0 | ... AI66: =V66 -> 0
B67: Total Book Capitalization | C67: =SUM(C64:C66) -> #REF! | D67: =SUM(D64:D66) -> 0 | E67: =SUM(E64:E66) -> 0 | F67: =SUM(F64:F66) -> 0 | H67: =SUM(H64:H66) -> 237094 | I67: =SUM(I64:I66) -> 218370 | J67: =SUM(J64:J66) -> 198719 | K67: =SUM(K64:K66) -> 227539 | L67: =SUM(L64:L66) -> 204005 | M67: =SUM(M64:M66) -> 179353 | N67: =SUM(N64:N66) -> 155115 | O67: =SUM(O64:O66) -> 137468 | ... V67: =SUM(V64:V66) -> 0 | X67: =SUM(X64:X66) -> 227539 | Y67: =SUM(Y64:Y66) -> 204005 | Z67: =SUM(Z64:Z66) -> 179353 | AA67: =SUM(AA64:AA66) -> 155115 | AB67: =SUM(AB64:AB66) -> 137468 | AC67: =SUM(AC64:AC66) -> 78597 | AD67: =SUM(AD64:AD66) -> 188974 | AE67: =SUM(AE64:AE66) -> 0 | ... AI67: =SUM(AI64:AI66) -> 0
B69: Credit Metrics
B71: Total Leverage | C71: NM | L71: NM | M71: NM | N71: NM | O71: NM | P71: NM | Q71: NM | X71: NM | Y71: NM | Z71: NM | AA71: NM | AB71: NM | AC71: NM | AD71: NM
B72: Net Leverage (C&CE) | C72: NM | L72: NM | M72: NM | N72: NM | O72: NM | P72: NM | Q72: NM | X72: NM | Y72: NM | Z72: NM | AA72: NM | AB72: NM | AC72: NM | AD72: NM
B73: Interest Coverage | C73: NM | L73: NM | M73: NM | N73: NM | O73: NM | P73: NM | Q73: NM | X73: NM | Y73: NM | Z73: NM | AA73: NM | AB73: NM | AC73: NM | AD73: NM
B74: Debt Service Coverage | C74: NM | L74: NM | M74: NM | N74: NM | O74: NM | P74: NM | Q74: NM | X74: NM | Y74: NM | Z74: NM | AA74: NM | AB74: NM | AC74: NM | AD74: NM
B75: Fixed Charge Coverage | C75: NM | L75: NM | M75: NM | N75: NM | O75: NM | P75: NM | Q75: NM | X75: NM | Y75: NM | Z75: NM | AA75: NM | AB75: NM | AC75: NM | AD75: NM
B76: Debt-to-Book Capitalization | C76: NM | L76: NM | M76: NM | N76: NM | O76: NM | P76: NM | Q76: NM | X76: NM | Y76: NM | Z76: NM | AA76: NM | AB76: NM | AC76: NM | AD76: NM
