Workbook

Sheet Historical Financials
B2: Alphabet Inc. (NASDAQ: GOOG)
B3: Historical Financials
B4: $ mm except per share
A6: X | B6: Income Statement | G6: FYE | O6: Quarterly | Y6: Quarterly | AE6: LTM | AS6: LTM | AT6: LTM | AZ6: Variance
B7: Fiscal Period | C7: 2018 | D7: 2019 | E7: 2020 | F7: 2021 | G7: 2022 | H7: 2023 | I7: 2024 | K7: 1Q21 | L7: 2Q21 | M7: 3Q21 | N7: 4Q21 | O7: 1Q22 | P7: 2Q22 | Q7: 3Q22 | R7: 4Q22 | S7: 1Q23 | T7: 2Q23 | U7: 3Q23 | V7: 4Q23 | W7: 1Q24 | X7: 2Q24 | Y7: 3Q24 | Z7: 4Q24 | AA7: 1Q25 | AB7: 2Q25 | AC7: 3Q25 | AE7: =#REF! -> #REF! | AF7: =K7 -> 1Q21 | AG7: =L7 -> 2Q21 | AH7: =M7 -> 3Q21 | AI7: =N7 -> 4Q21 | AJ7: =O7 -> 1Q22 | AK7: =P7 -> 2Q22 | AL7: =Q7 -> 3Q22 | AM7: =R7 -> 4Q22 | ... AX7: =AC7 -> 3Q25
B8: Fiscal Period End Date | C8: 43465 | D8: 43830 | E8: 44196 | F8: 44561 | G8: 44926 | H8: 45291 | I8: 45657 | K8: 44286 | L8: 44377 | M8: 44469 | N8: =F8 -> 44561 | O8: 44651 | P8: 44742 | Q8: 44834 | R8: =G8 -> 44926 | S8: 45016 | T8: 45107 | U8: 45199 | V8: =H8 -> 45291 | W8: 45382 | X8: 45473 | Y8: 45565 | Z8: =I8 -> 45657 | AA8: 45747 | AB8: 45838 | AC8: 45930 | AE8: =#REF! -> #REF! | AF8: =K8 -> 44286 | AG8: =L8 -> 44377 | AH8: =M8 -> 44469 | AI8: =N8 -> 44561 | AJ8: =O8 -> 44651 | AK8: =P8 -> 44742 | AL8: =Q8 -> 44834 | AM8: =R8 -> 44926 | ... AX8: =AC8 -> 45930
B10: Consolidated Revenue | C10: 136819 | D10: 161857 | E10: 182527 | F10: 257637 | G10: 282836 | H10: 307394 | I10: 350018 | K10: 55314 | L10: 61880 | M10: 65118 | N10: =SUM(F10-SUM(K10:M10)) -> 75325 | O10: 68011 | P10: 69685 | Q10: 69092 | R10: =SUM(G10-SUM(O10:Q10)) -> 76048 | S10: 69787 | T10: 74604 | U10: 76693 | V10: =SUM(H10-SUM(S10:U10)) -> 86310 | W10: 80539 | X10: 84742 | Y10: 88268 | Z10: =SUM(I10-SUM(W10:Y10)) -> 96469 | AA10: 90234 | AB10: 96428 | AC10: 102346 | AE10: =SUM(#REF!) -> #REF! | AF10: =SUM(K10:K10) -> 55314 | AG10: =SUM(K10:L10) -> 117194 | AH10: =SUM(K10:M10) -> 182312 | AI10: =SUM(K10:N10) -> 257637 | AJ10: =SUM(L10:O10) -> 270334 | AK10: =SUM(M10:P10) -> 278139 | AL10: =SUM(N10:Q10) -> 282113 | AM10: =SUM(O10:R10) -> 282836 | AN10: =SUM(P10:S10) -> 284612 | AO10: =SUM(Q10:T10) -> 289531 | AP10: =SUM(R10:U10) -> 297132 | ... AX10: =SUM(Z10:AC10) -> 385477 | AZ10: =SUM(AX10/AT10)-1 -> 0.13422625
B11: Total Revenue | C11: =+SUM(C10:C10) -> 136819 | D11: =+SUM(D10:D10) -> 161857 | E11: =+SUM(E10:E10) -> 182527 | F11: =+SUM(F10:F10) -> 257637 | G11: =+SUM(G10:G10) -> 282836 | H11: =+SUM(H10:H10) -> 307394 | I11: =+SUM(I10:I10) -> 350018 | K11: =+SUM(K10:K10) -> 55314 | L11: =+SUM(L10:L10) -> 61880 | M11: =+SUM(M10:M10) -> 65118 | N11: =+SUM(N10:N10) -> 75325 | O11: =+SUM(O10:O10) -> 68011 | P11: =+SUM(P10:P10) -> 69685 | Q11: =+SUM(Q10:Q10) -> 69092 | R11: =+SUM(R10:R10) -> 76048 | ... AC11: =+SUM(AC10:AC10) -> 102346 | AE11: =+SUM(AE10:AE10) -> #REF! | AF11: =+SUM(AF10:AF10) -> 55314 | AG11: =+SUM(AG10:AG10) -> 117194 | AH11: =+SUM(AH10:AH10) -> 182312 | AI11: =+SUM(AI10:AI10) -> 257637 | AJ11: =+SUM(AJ10:AJ10) -> 270334 | AK11: =+SUM(AK10:AK10) -> 278139 | AL11: =+SUM(AL10:AL10) -> 282113 | ... AX11: =+SUM(AX10:AX10) -> 385477 | AZ11: =SUM(AX11/AT11)-1 -> 0.13422625
B13: Cost of Sales | C13: -59549 | D13: -71896 | E13: -84732 | F13: -110939 | G13: -126203 | H13: -133332 | I13: -146306 | K13: -24103 | L13: -26227 | M13: -27621 | N13: =SUM(F13-SUM(K13:M13)) -> -32988 | O13: -29599 | P13: -30104 | Q13: -31158 | R13: =SUM(G13-SUM(O13:Q13)) -> -35342 | S13: -30612 | T13: -31916 | U13: -33229 | V13: =SUM(H13-SUM(S13:U13)) -> -37575 | W13: -33712 | X13: -35507 | Y13: -36474 | Z13: =SUM(I13-SUM(W13:Y13)) -> -40613 | AA13: -36361 | AB13: -39039 | AC13: -41369 | AE13: =SUM(#REF!) -> #REF! | AF13: =SUM(K13:K13) -> -24103 | AG13: =SUM(K13:L13) -> -50330 | AH13: =SUM(K13:M13) -> -77951 | AI13: =SUM(K13:N13) -> -110939 | AJ13: =SUM(L13:O13) -> -116435 | AK13: =SUM(M13:P13) -> -120312 | AL13: =SUM(N13:Q13) -> -123849 | AM13: =SUM(O13:R13) -> -126203 | AN13: =SUM(P13:S13) -> -127216 | AO13: =SUM(Q13:T13) -> -129028 | AP13: =SUM(R13:U13) -> -131099 | ... AX13: =SUM(Z13:AC13) -> -157382 | AZ13: =SUM(AX13/AT13)-1 -> 0.098514672
B14: Gross Profit | C14: =+SUM(C11+SUM(C13:C13)) -> 77270 | D14: =+SUM(D11+SUM(D13:D13)) -> 89961 | E14: =+SUM(E11+SUM(E13:E13)) -> 97795 | F14: =+SUM(F11+SUM(F13:F13)) -> 146698 | G14: =+SUM(G11+SUM(G13:G13)) -> 156633 | H14: =+SUM(H11+SUM(H13:H13)) -> 174062 | I14: =+SUM(I11+SUM(I13:I13)) -> 203712 | K14: =+SUM(K11+SUM(K13:K13)) -> 31211 | L14: =+SUM(L11+SUM(L13:L13)) -> 35653 | M14: =+SUM(M11+SUM(M13:M13)) -> 37497 | N14: =+SUM(N11+SUM(N13:N13)) -> 42337 | O14: =+SUM(O11+SUM(O13:O13)) -> 38412 | P14: =+SUM(P11+SUM(P13:P13)) -> 39581 | Q14: =+SUM(Q11+SUM(Q13:Q13)) -> 37934 | R14: =+SUM(R11+SUM(R13:R13)) -> 40706 | ... AC14: =+SUM(AC11+SUM(AC13:AC13)) -> 60977 | AE14: =+SUM(AE11+SUM(AE13:AE13)) -> #REF! | AF14: =+SUM(AF11+SUM(AF13:AF13)) -> 31211 | AG14: =+SUM(AG11+SUM(AG13:AG13)) -> 66864 | AH14: =+SUM(AH11+SUM(AH13:AH13)) -> 104361 | AI14: =+SUM(AI11+SUM(AI13:AI13)) -> 146698 | AJ14: =+SUM(AJ11+SUM(AJ13:AJ13)) -> 153899 | AK14: =+SUM(AK11+SUM(AK13:AK13)) -> 157827 | AL14: =+SUM(AL11+SUM(AL13:AL13)) -> 158264 | ... AX14: =+SUM(AX11+SUM(AX13:AX13)) -> 228095 | AZ14: =SUM(AX14/AT14)-1 -> 0.16025149
B15: Gross Margin (%) | C15: =C14/C11 -> 0.56476074 | D15: =D14/D11 -> 0.55580543 | E15: =E14/E11 -> 0.53578375 | F15: =F14/F11 -> 0.56939803 | G15: =G14/G11 -> 0.55379443 | H15: =H14/H11 -> 0.56625048 | I15: =I14/I11 -> 0.58200435 | K15: =K14/K11 -> 0.56425136 | L15: =L14/L11 -> 0.57616354 | M15: =M14/M11 -> 0.57583157 | N15: =N14/N11 -> 0.56205775 | O15: =O14/O11 -> 0.56479099 | P15: =P14/P11 -> 0.56799885 | Q15: =Q14/Q11 -> 0.54903607 | R15: =R14/R11 -> 0.5352672 | ... AC15: =AC14/AC11 -> 0.5957927 | AE15: =AE14/AE11 -> #REF! | AF15: =AF14/AF11 -> 0.56425136 | AG15: =AG14/AG11 -> 0.57054115 | AH15: =AH14/AH11 -> 0.57243078 | AI15: =AI14/AI11 -> 0.56939803 | AJ15: =AJ14/AJ11 -> 0.56929206 | AK15: =AK14/AK11 -> 0.5674393 | AL15: =AL14/AL11 -> 0.56099506 | ... AX15: =AX14/AX11 -> 0.59172143 | AZ15: =SUM(AX15-AT15)*1000 -> 13.272716
B17: Research & Development (R&D) | C17: -21419 | D17: -26018 | E17: -27573 | F17: -31562 | G17: -39500 | H17: -45427 | I17: -49326 | K17: -7485 | L17: -7675 | M17: -7694 | N17: =SUM(F17-SUM(K17:M17)) -> -8708 | O17: -9119 | P17: -9841 | Q17: -10273 | R17: =SUM(G17-SUM(O17:Q17)) -> -10267 | S17: -11468 | T17: -10588 | U17: -11258 | V17: =SUM(H17-SUM(S17:U17)) -> -12113 | W17: -11903 | X17: -11860 | Y17: -12447 | Z17: =SUM(I17-SUM(W17:Y17)) -> -13116 | AA17: -13556 | AB17: -13808 | AC17: -15151 | AE17: =SUM(#REF!) -> #REF! | AF17: =SUM(K17:K17) -> -7485 | AG17: =SUM(K17:L17) -> -15160 | AH17: =SUM(K17:M17) -> -22854 | AI17: =SUM(K17:N17) -> -31562 | AJ17: =SUM(L17:O17) -> -33196 | AK17: =SUM(M17:P17) -> -35362 | AL17: =SUM(N17:Q17) -> -37941 | AM17: =SUM(O17:R17) -> -39500 | AN17: =SUM(P17:S17) -> -41849 | AO17: =SUM(Q17:T17) -> -42596 | AP17: =SUM(R17:U17) -> -43581 | ... AX17: =SUM(Z17:AC17) -> -55631 | AZ17: =SUM(AX17/AT17)-1 -> 0.15123233
B18: Sales and Marketing (S&M) | C18: -16333 | D18: -18464 | E18: -17946 | F18: -22912 | G18: -26567 | H18: -27917 | I18: -27808 | K18: -4516 | L18: -5276 | M18: -5516 | N18: =SUM(F18-SUM(K18:M18)) -> -7604 | O18: -5825 | P18: -6630 | Q18: -6929 | R18: =SUM(G18-SUM(O18:Q18)) -> -7183 | S18: -6533 | T18: -6781 | U18: -6884 | V18: =SUM(H18-SUM(S18:U18)) -> -7719 | W18: -6426 | X18: -6792 | Y18: -7227 | Z18: =SUM(I18-SUM(W18:Y18)) -> -7363 | AA18: -6172 | AB18: -7101 | AC18: -7205 | AE18: =SUM(#REF!) -> #REF! | AF18: =SUM(K18:K18) -> -4516 | AG18: =SUM(K18:L18) -> -9792 | AH18: =SUM(K18:M18) -> -15308 | AI18: =SUM(K18:N18) -> -22912 | AJ18: =SUM(L18:O18) -> -24221 | AK18: =SUM(M18:P18) -> -25575 | AL18: =SUM(N18:Q18) -> -26988 | AM18: =SUM(O18:R18) -> -26567 | AN18: =SUM(P18:S18) -> -27275 | AO18: =SUM(Q18:T18) -> -27426 | AP18: =SUM(R18:U18) -> -27381 | ... AX18: =SUM(Z18:AC18) -> -27841 | AZ18: =SUM(AX18/AT18)-1 -> -0.011468541
B19: General and Administrative (G&A) | C19: -6923 | D19: -9551 | E19: -11052 | F19: -13510 | G19: -15724 | H19: -16425 | I19: -14188 | K19: -2773 | L19: -3341 | M19: -3256 | N19: =SUM(F19-SUM(K19:M19)) -> -4140 | O19: -3374 | P19: -3657 | Q19: -3597 | R19: =SUM(G19-SUM(O19:Q19)) -> -5096 | S19: -3759 | T19: -3481 | U19: -3979 | V19: =SUM(H19-SUM(S19:U19)) -> -5206 | W19: -3026 | X19: -3158 | Y19: -3599 | Z19: =SUM(I19-SUM(W19:Y19)) -> -4405 | AA19: -3539 | AB19: -5209 | AC19: -7393 | AE19: =SUM(#REF!) -> #REF! | AF19: =SUM(K19:K19) -> -2773 | AG19: =SUM(K19:L19) -> -6114 | AH19: =SUM(K19:M19) -> -9370 | AI19: =SUM(K19:N19) -> -13510 | AJ19: =SUM(L19:O19) -> -14111 | AK19: =SUM(M19:P19) -> -14427 | AL19: =SUM(N19:Q19) -> -14768 | AM19: =SUM(O19:R19) -> -15724 | AN19: =SUM(P19:S19) -> -16109 | AO19: =SUM(Q19:T19) -> -15933 | AP19: =SUM(R19:U19) -> -16315 | ... AX19: =SUM(Z19:AC19) -> -20546 | AZ19: =SUM(AX19/AT19)-1 -> 0.37073854
B20: European Commission Fines | C20: -5071 | D20: -1697 | E20: 0 | F20: 0 | G20: 0 | H20: 0 | I20: 0 | K20: 0 | N20: =SUM(F20-SUM(K20:M20)) -> 0 | R20: =SUM(G20-SUM(O20:Q20)) -> 0 | V20: =SUM(H20-SUM(S20:U20)) -> 0 | W20: 0 | Z20: =SUM(I20-SUM(W20:Y20)) -> 0 | AZ20: =SUM(AX20/AT20)-1 -> #DIV/0!
B21: Operating Profit | C21: =+SUM(C14+SUM(C17:C20)) -> 27524 | D21: =+SUM(D14+SUM(D17:D20)) -> 34231 | E21: =+SUM(E14+SUM(E17:E20)) -> 41224 | F21: =+SUM(F14+SUM(F17:F20)) -> 78714 | G21: =+SUM(G14+SUM(G17:G20)) -> 74842 | H21: =+SUM(H14+SUM(H17:H20)) -> 84293 | I21: =+SUM(I14+SUM(I17:I20)) -> 112390 | K21: =+SUM(K14+SUM(K17:K20)) -> 16437 | L21: =+SUM(L14+SUM(L17:L20)) -> 19361 | M21: =+SUM(M14+SUM(M17:M20)) -> 21031 | N21: =+SUM(N14+SUM(N17:N20)) -> 21885 | O21: =+SUM(O14+SUM(O17:O20)) -> 20094 | P21: =+SUM(P14+SUM(P17:P20)) -> 19453 | Q21: =+SUM(Q14+SUM(Q17:Q20)) -> 17135 | R21: =+SUM(R14+SUM(R17:R20)) -> 18160 | ... AC21: =+SUM(AC14+SUM(AC17:AC20)) -> 31228 | AE21: =+SUM(AE14+SUM(AE17:AE19)) -> #REF! | AF21: =+SUM(AF14+SUM(AF17:AF19)) -> 16437 | AG21: =+SUM(AG14+SUM(AG17:AG19)) -> 35798 | AH21: =+SUM(AH14+SUM(AH17:AH19)) -> 56829 | AI21: =+SUM(AI14+SUM(AI17:AI19)) -> 78714 | AJ21: =+SUM(AJ14+SUM(AJ17:AJ19)) -> 82371 | AK21: =+SUM(AK14+SUM(AK17:AK19)) -> 82463 | AL21: =+SUM(AL14+SUM(AL17:AL19)) -> 78567 | ... AX21: =+SUM(AX14+SUM(AX17:AX19)) -> 124077 | AZ21: =SUM(AX21/AT21)-1 -> 0.1803929
B22: Operating Margin (%) | C22: =C21/C11 -> 0.20117089 | D22: =D21/D11 -> 0.21148915 | E22: =E21/E11 -> 0.22585152 | F22: =F21/F11 -> 0.30552289 | G22: =G21/G11 -> 0.26461271 | H22: =H21/H11 -> 0.2742181 | I22: =I21/I11 -> 0.32109777 | K22: =K21/K11 -> 0.29715804 | L22: =L21/L11 -> 0.31287977 | M22: =M21/M11 -> 0.32296754 | N22: =N21/N11 -> 0.29054099 | O22: =O21/O11 -> 0.29545221 | P22: =P21/P11 -> 0.2791562 | Q22: =Q21/Q11 -> 0.24800266 | R22: =R21/R11 -> 0.23879655 | ... AC22: =AC21/AC11 -> 0.30512184 | AE22: =AE21/AE11 -> #REF! | AF22: =AF21/AF11 -> 0.29715804 | AG22: =AG21/AG11 -> 0.30545932 | AH22: =AH21/AH11 -> 0.31171289 | AI22: =AI21/AI11 -> 0.30552289 | AJ22: =AJ21/AJ11 -> 0.30470085 | AK22: =AK21/AK11 -> 0.29648126 | AL22: =AL21/AL11 -> 0.27849479 | ... AX22: =AX21/AX11 -> 0.32187913 | AZ22: =SUM(AX22-AT22)*1000 -> 12.589097
B24: Interest Income | C24: 1878 | D24: 2427 | E24: 1865 | F24: 1499 | G24: 2174 | H24: 3865 | I24: 4482 | K24: 345 | L24: 389 | M24: 387 | N24: =SUM(F24-SUM(K24:M24)) -> 378 | O24: 414 | P24: 486 | Q24: 615 | R24: =SUM(G24-SUM(O24:Q24)) -> 659 | S24: 797 | T24: 892 | U24: 1066 | V24: =SUM(H24-SUM(S24:U24)) -> 1110 | W24: 1061 | X24: 1090 | Y24: 1243 | Z24: =SUM(I24-SUM(W24:Y24)) -> 1088 | AA24: 1001 | AB24: 1050 | AC24: 1076 | AE24: =SUM(#REF!) -> #REF! | AF24: =SUM(K24:K24) -> 345 | AG24: =SUM(K24:L24) -> 734 | AH24: =SUM(K24:M24) -> 1121 | AI24: =SUM(K24:N24) -> 1499 | AJ24: =SUM(L24:O24) -> 1568 | AK24: =SUM(M24:P24) -> 1665 | AL24: =SUM(N24:Q24) -> 1893 | AM24: =SUM(O24:R24) -> 2174 | AN24: =SUM(P24:S24) -> 2557 | AO24: =SUM(Q24:T24) -> 2963 | AP24: =SUM(R24:U24) -> 3414 | ... AX24: =SUM(Z24:AC24) -> 4215 | AZ24: =SUM(AX24/AT24)-1 -> -0.064165187
B25: Interest Expense | C25: -114 | D25: -100 | E25: -135 | F25: -346 | G25: -357 | H25: -308 | I25: -268 | K25: -76 | L25: -76 | M25: -77 | N25: =SUM(F25-SUM(K25:M25)) -> -117 | O25: -83 | P25: -83 | Q25: -101 | R25: =SUM(G25-SUM(O25:Q25)) -> -90 | S25: -80 | T25: -43 | U25: -116 | V25: =SUM(H25-SUM(S25:U25)) -> -69 | W25: -94 | X25: -67 | Y25: -54 | Z25: =SUM(I25-SUM(W25:Y25)) -> -53 | AA25: -34 | AB25: -261 | AC25: -143 | AE25: =SUM(#REF!) -> #REF! | AF25: =SUM(K25:K25) -> -76 | AG25: =SUM(K25:L25) -> -152 | AH25: =SUM(K25:M25) -> -229 | AI25: =SUM(K25:N25) -> -346 | AJ25: =SUM(L25:O25) -> -353 | AK25: =SUM(M25:P25) -> -360 | AL25: =SUM(N25:Q25) -> -384 | AM25: =SUM(O25:R25) -> -357 | AN25: =SUM(P25:S25) -> -354 | AO25: =SUM(Q25:T25) -> -314 | AP25: =SUM(R25:U25) -> -329 | ... AX25: =SUM(Z25:AC25) -> -491 | AZ25: =SUM(AX25/AT25)-1 -> 0.72887324
B26: Other Income/Gains (Expenses/Losses) | C26: =-80+1190+5460-1203-120+378 -> 5625 | D26: =103+149+2649-326+390+102 -> 3067 | E26: =-344+725+5592-609+401-637 -> 5128 | F26: =-240-110+12380-1908+334+411 -> 10867 | G26: =-654-2064-3455+798-337+381 -> -5331 | H26: =-1238-1215+392+257-628+299 -> -2133 | I26: =-409-1043+3714+218-188+919 -> 3211 | K26: =113-86+4837-665+5+373 -> 4577 | L26: =-51+111+2772-523+92-90 -> 2311 | M26: =-139+37+2121-492+188+8 -> 1723 | N26: =SUM(F26-SUM(K26:M26)) -> 2256 | O26: =-73-367-1070+233-89-125 -> -1491 | P26: =-260-790-251+318-118+259 -> -842 | Q26: =-136-731-647+54-99+143 -> -1416 | R26: =SUM(G26-SUM(O26:Q26)) -> -1582 | S26: =-210-293+377+118-51+132 -> 73 | T26: =-268-304-205+5-106+94 -> -784 | U26: =-311-503-366+179-215+120 -> -1096 | V26: =SUM(H26-SUM(S26:U26)) -> -326 | W26: =-238-462+2243+104-26+255 -> 1876 | X26: =-173-310-714+128+32+140 -> -897 | Y26: =23+160+1821+29-107+70 -> 1996 | Z26: =SUM(I26-SUM(W26:Y26)) -> 236 | AA26: =-106+202+9758-40-22+424 -> 10216 | AB26: =-69+165+1286-83+419+155 -> 1873 | AC26: =-143+122+10734-174-30+1317 -> 11826 | AE26: =SUM(#REF!) -> #REF! | AF26: =SUM(K26:K26) -> 4577 | AG26: =SUM(K26:L26) -> 6888 | AH26: =SUM(K26:M26) -> 8611 | AI26: =SUM(K26:N26) -> 10867 | AJ26: =SUM(L26:O26) -> 4799 | AK26: =SUM(M26:P26) -> 1646 | AL26: =SUM(N26:Q26) -> -1493 | AM26: =SUM(O26:R26) -> -5331 | AN26: =SUM(P26:S26) -> -3767 | AO26: =SUM(Q26:T26) -> -3709 | AP26: =SUM(R26:U26) -> -3389 | ... AX26: =SUM(Z26:AC26) -> 24151 | AZ26: =SUM(AX26/AT26)-1 -> 8.1170253
B27: Earning Before Taxes | C27: =SUM(C21+SUM(C24:C26)) -> 34913 | D27: =SUM(D21+SUM(D24:D26)) -> 39625 | E27: =SUM(E21+SUM(E24:E26)) -> 48082 | F27: =SUM(F21+SUM(F24:F26)) -> 90734 | G27: =SUM(G21+SUM(G24:G26)) -> 71328 | H27: =SUM(H21+SUM(H24:H26)) -> 85717 | I27: =SUM(I21+SUM(I24:I26)) -> 119815 | K27: =SUM(K21+SUM(K24:K26)) -> 21283 | L27: =SUM(L21+SUM(L24:L26)) -> 21985 | M27: =SUM(M21+SUM(M24:M26)) -> 23064 | N27: =SUM(N21+SUM(N24:N26)) -> 24402 | O27: =SUM(O21+SUM(O24:O26)) -> 18934 | P27: =SUM(P21+SUM(P24:P26)) -> 19014 | Q27: =SUM(Q21+SUM(Q24:Q26)) -> 16233 | R27: =SUM(R21+SUM(R24:R26)) -> 17147 | ... AC27: =SUM(AC21+SUM(AC24:AC26)) -> 43987 | AE27: =SUM(AE21+SUM(AE24:AE26)) -> #REF! | AF27: =SUM(AF21+SUM(AF24:AF26)) -> 21283 | AG27: =SUM(AG21+SUM(AG24:AG26)) -> 43268 | AH27: =SUM(AH21+SUM(AH24:AH26)) -> 66332 | AI27: =SUM(AI21+SUM(AI24:AI26)) -> 90734 | AJ27: =SUM(AJ21+SUM(AJ24:AJ26)) -> 88385 | AK27: =SUM(AK21+SUM(AK24:AK26)) -> 85414 | AL27: =SUM(AL21+SUM(AL24:AL26)) -> 78583 | ... AX27: =SUM(AX21+SUM(AX24:AX26)) -> 151952 | AZ27: =SUM(AX27/AT27)-1 -> 0.35690813
B28: EBT Margin (%) | C28: =C27/C11 -> 0.25517655 | D28: =D27/D11 -> 0.24481487 | E28: =E27/E11 -> 0.26342404 | F28: =F27/F11 -> 0.35217768 | G28: =G27/G11 -> 0.25218855 | H28: =H27/H11 -> 0.2788506 | I28: =I27/I11 -> 0.34231097 | K28: =K27/K11 -> 0.38476697 | L28: =L27/L11 -> 0.35528442 | M28: =M27/M11 -> 0.35418778 | N28: =N27/N11 -> 0.32395619 | O28: =O27/O11 -> 0.27839614 | P28: =P27/P11 -> 0.27285643 | Q28: =Q27/Q11 -> 0.23494761 | R28: =R27/R11 -> 0.22547602 | ... AC28: =AC27/AC11 -> 0.42978719 | AE28: =AE27/AE11 -> #REF! | AF28: =AF27/AF11 -> 0.38476697 | AG28: =AG27/AG11 -> 0.36919979 | AH28: =AH27/AH11 -> 0.36383782 | AI28: =AI27/AI11 -> 0.35217768 | AJ28: =AJ27/AJ11 -> 0.32694741 | AK28: =AK27/AK11 -> 0.30709106 | AL28: =AL27/AL11 -> 0.2785515 | ... AX28: =AX27/AX11 -> 0.39419213 | AZ28: =SUM(AX28-AT28)*1000 -> 64.690779
B30: Provision for taxes | C30: -4177 | D30: -5282 | E30: -7813 | F30: -14701 | G30: -11356 | H30: -11922 | I30: -19697 | K30: -3353 | L30: -3460 | M30: -4128 | N30: =SUM(F30-SUM(K30:M30)) -> -3760 | O30: -2498 | P30: -3012 | Q30: -2323 | R30: =SUM(G30-SUM(O30:Q30)) -> -3523 | S30: -3154 | T30: -3535 | U30: -1508 | V30: =SUM(H30-SUM(S30:U30)) -> -3725 | W30: -4653 | X30: -3932 | Y30: -5405 | Z30: =SUM(I30-SUM(W30:Y30)) -> -5707 | AA30: -7249 | AB30: -5737 | AC30: -9008 | AE30: =SUM(#REF!) -> #REF! | AF30: =SUM(K30:K30) -> -3353 | AG30: =SUM(K30:L30) -> -6813 | AH30: =SUM(K30:M30) -> -10941 | AI30: =SUM(K30:N30) -> -14701 | AJ30: =SUM(L30:O30) -> -13846 | AK30: =SUM(M30:P30) -> -13398 | AL30: =SUM(N30:Q30) -> -11593 | AM30: =SUM(O30:R30) -> -11356 | AN30: =SUM(P30:S30) -> -12012 | AO30: =SUM(Q30:T30) -> -12535 | AP30: =SUM(R30:U30) -> -11720 | ... AX30: =SUM(Z30:AC30) -> -27701 | AZ30: =SUM(AX30/AT30)-1 -> 0.56370308
B31: Net loss | C31: =SUM(C27+SUM(C30:C30)) -> 30736 | D31: =SUM(D27+SUM(D30:D30)) -> 34343 | E31: =SUM(E27+SUM(E30:E30)) -> 40269 | F31: =SUM(F27+SUM(F30:F30)) -> 76033 | G31: =SUM(G27+SUM(G30:G30)) -> 59972 | H31: =SUM(H27+SUM(H30:H30)) -> 73795 | I31: =SUM(I27+SUM(I30:I30)) -> 100118 | K31: =SUM(K27+SUM(K30:K30)) -> 17930 | L31: =SUM(L27+SUM(L30:L30)) -> 18525 | M31: =SUM(M27+SUM(M30:M30)) -> 18936 | N31: =SUM(N27+SUM(N30:N30)) -> 20642 | O31: =SUM(O27+SUM(O30:O30)) -> 16436 | P31: =SUM(P27+SUM(P30:P30)) -> 16002 | Q31: =SUM(Q27+SUM(Q30:Q30)) -> 13910 | R31: =SUM(R27+SUM(R30:R30)) -> 13624 | ... AC31: =SUM(AC27+SUM(AC30:AC30)) -> 34979 | AE31: =SUM(AE27+SUM(AE30:AE30)) -> #REF! | AF31: =SUM(AF27+SUM(AF30:AF30)) -> 17930 | AG31: =SUM(AG27+SUM(AG30:AG30)) -> 36455 | AH31: =SUM(AH27+SUM(AH30:AH30)) -> 55391 | AI31: =SUM(AI27+SUM(AI30:AI30)) -> 76033 | AJ31: =SUM(AJ27+SUM(AJ30:AJ30)) -> 74539 | AK31: =SUM(AK27+SUM(AK30:AK30)) -> 72016 | AL31: =SUM(AL27+SUM(AL30:AL30)) -> 66990 | ... AX31: =SUM(AX27+SUM(AX30:AX30)) -> 124251 | AZ31: =SUM(AX31/AT31)-1 -> 0.31804729
B32: Net Margin (%) | C32: =C31/C11 -> 0.22464716 | D32: =D31/D11 -> 0.21218112 | E32: =E31/E11 -> 0.22061942 | F32: =F31/F11 -> 0.29511677 | G32: =G31/G11 -> 0.21203807 | H32: =H31/H11 -> 0.24006649 | I32: =I31/I11 -> 0.28603672 | K32: =K31/K11 -> 0.3241494 | L32: =L31/L11 -> 0.29936975 | M32: =M31/M11 -> 0.29079517 | N32: =N31/N11 -> 0.27403916 | O32: =O31/O11 -> 0.24166679 | P32: =P31/P11 -> 0.22963335 | Q32: =Q31/Q11 -> 0.20132577 | R32: =R31/R11 -> 0.17915001 | ... AC32: =AC31/AC11 -> 0.34177203 | AE32: =AE31/AE11 -> #REF! | AF32: =AF31/AF11 -> 0.3241494 | AG32: =AG31/AG11 -> 0.31106541 | AH32: =AH31/AH11 -> 0.30382531 | AI32: =AI31/AI11 -> 0.29511677 | AJ32: =AJ31/AJ11 -> 0.27572928 | AK32: =AK31/AK11 -> 0.2589209 | AL32: =AL31/AL11 -> 0.23745804 | ... AX32: =AX31/AX11 -> 0.32233052 | AZ32: =SUM(AX32-AT32)*1000 -> 44.953721
B34: Basic EPS | C34: =EPS!C18 -> 1.3075276 | D34: =EPS!D18 -> 1.3475749 | E34: =EPS!E18 -> 1.4113478 | F34: =EPS!F18 -> 5.6940762 | G34: =EPS!G18 -> 4.5909822 | H34: =EPS!H18 -> 5.8428345 | I34: =EPS!I18 -> 8.1271207 | K34: =EPS!K18 -> 1.3316598 | L34: =EPS!L18 -> 1.3846161 | M34: =EPS!M18 -> 1.4221384 | N34: =EPS!N18 -> 1.5458698 | O34: =EPS!O18 -> 1.244829 | P34: =EPS!P18 -> 1.2184573 | Q34: =EPS!Q18 -> 1.0685205 | R34: =EPS!R18 -> 1.0429457 | ... AC34: =EPS!AC18 -> 2.8941751 | AE34: =EPS!#REF! -> #REF! | AF34: =EPS!#REF! -> #REF! | AG34: =EPS!#REF! -> #REF! | AH34: =EPS!#REF! -> #REF! | AI34: =EPS!AE18 -> 5.6940762 | AJ34: =EPS!AF18 -> 5.6454313 | AK34: =EPS!AG18 -> 5.483591 | AL34: =EPS!AH18 -> 5.1459518 | AM34: =EPS!AI18 -> 4.5909822 | AN34: =EPS!AJ18 -> 4.5839136 | AO34: =EPS!AK18 -> 4.8115725 | AP34: =EPS!AL18 -> 5.3041889 | ... AX34: =EPS!AT18 -> 10.280573 | AZ34: =SUM(AX34/AT34)-1 -> 0.34029465
B35: Fully Diluted EPS | C35: =EPS!C24 -> 2.1851659 | D35: =EPS!D24 -> 2.4581154 | E35: =EPS!E24 -> 2.9306747 | F35: =EPS!F24 -> 5.6098431 | G35: =EPS!G24 -> 4.0336484 | H35: =EPS!H24 -> 5.139897 | I35: =EPS!I24 -> 6.8015243 | K35: =EPS!K24 -> 1.3143777 | L35: =EPS!L24 -> 1.3629457 | M35: =EPS!M24 -> 1.399526 | N35: =EPS!N24 -> 1.5228037 | O35: =EPS!O24 -> 1.2311013 | P35: =EPS!P24 -> 1.2086932 | Q35: =EPS!Q24 -> 1.0620798 | R35: =EPS!R24 -> 1.0363805 | ... AC35: =EPS!AC24 -> 2.8664929 | AE35: =EPS!#REF! -> #REF! | AF35: =EPS!#REF! -> #REF! | AG35: =EPS!#REF! -> #REF! | AH35: =EPS!#REF! -> #REF! | AI35: =EPS!AE24 -> 5.6114444 | AJ35: =EPS!AF24 -> 5.5841942 | AK35: =EPS!AG24 -> 5.4389778 | AL35: =EPS!AH24 -> 5.1118581 | AM35: =EPS!AI24 -> 4.5574541 | AN35: =EPS!AJ24 -> 4.565008 | AO35: =EPS!AK24 -> 4.7831228 | AP35: =EPS!AL24 -> 5.2555449 | ... AX35: =EPS!AT24 -> 10.186772 | AZ35: =SUM(AX35/AT35)-1 -> 0.34231121
A37: X | B37: Balance Sheet | AS37: LTM | AZ37: Variance
B38: =B7 -> Fiscal Period | C38: =C7 -> 2018 | D38: =D7 -> 2019 | E38: =E7 -> 2020 | F38: =F7 -> 2021 | G38: =G7 -> 2022 | H38: =H7 -> 2023 | I38: =I7 -> 2024 | K38: =K7 -> 1Q21 | L38: =L7 -> 2Q21 | M38: =M7 -> 3Q21 | N38: =N7 -> 4Q21 | O38: =O7 -> 1Q22 | P38: =P7 -> 2Q22 | Q38: =Q7 -> 3Q22 | R38: =R7 -> 4Q22 | ... AC38: =AC7 -> 3Q25 | AE38: =AE7 -> #REF! | AF38: =AF7 -> 1Q21 | AG38: =AG7 -> 2Q21 | AH38: =AH7 -> 3Q21 | AI38: =AI7 -> 4Q21 | AJ38: =AJ7 -> 1Q22 | AK38: =AK7 -> 2Q22 | AL38: =AL7 -> 3Q22 | ... AX38: =AX7 -> 3Q25
B39: =B8 -> Fiscal Period End Date | C39: =C8 -> 43465 | D39: =D8 -> 43830 | E39: =E8 -> 44196 | F39: =F8 -> 44561 | G39: =G8 -> 44926 | H39: =H8 -> 45291 | I39: =I8 -> 45657 | K39: =K8 -> 44286 | L39: =L8 -> 44377 | M39: =M8 -> 44469 | N39: =N8 -> 44561 | O39: =O8 -> 44651 | P39: =P8 -> 44742 | Q39: =Q8 -> 44834 | R39: =R8 -> 44926 | ... AC39: =AC8 -> 45930 | AE39: =AE8 -> #REF! | AF39: =AF8 -> 44286 | AG39: =AG8 -> 44377 | AH39: =AH8 -> 44469 | AI39: =AI8 -> 44561 | AJ39: =AJ8 -> 44651 | AK39: =AK8 -> 44742 | AL39: =AL8 -> 44834 | ... AX39: =AX8 -> 45930
B41: Current Assets
B42: Cash and Cash Equivalents | C42: 16701 | D42: 18498 | E42: 26465 | F42: 20945 | G42: 21879 | H42: 24048 | I42: 23466 | K42: 26622 | L42: 23630 | M42: 23719 | N42: =F42 -> 20945 | O42: 20886 | P42: 17936 | Q42: 21984 | R42: =G42 -> 21879 | S42: 25924 | T42: 25929 | U42: 30702 | V42: =H42 -> 24048 | W42: 24493 | X42: 27225 | Y42: 19959 | Z42: =I42 -> 23466 | AA42: 23264 | AB42: 21036 | AC42: 23090 | AE42: =#REF! -> #REF! | AF42: =K42 -> 26622 | AG42: =L42 -> 23630 | AH42: =M42 -> 23719 | AI42: =N42 -> 20945 | AJ42: =O42 -> 20886 | AK42: =P42 -> 17936 | AL42: =Q42 -> 21984 | AM42: =R42 -> 21879 | ... AX42: =AC42 -> 23090 | AZ42: =SUM(AX42/AT42)-1 -> 0.15687159
B43: Marketable securities | C43: 92439 | D43: 101177 | E43: 110229 | F43: 118704 | G43: 91883 | H43: 86868 | I43: 72191 | K43: 108482 | L43: 112233 | M43: 118284 | N43: =F43 -> 118704 | O43: 113084 | P43: 107061 | Q43: 94275 | R43: =G43 -> 91883 | S43: 89178 | T43: 92403 | U43: 89233 | V43: =H43 -> 86868 | W43: 83597 | X43: 73500 | Y43: 73271 | Z43: =I43 -> 72191 | AA43: 72064 | AB43: 74112 | AC43: 75406 | AE43: =#REF! -> #REF! | AF43: =K43 -> 108482 | AG43: =L43 -> 112233 | AH43: =M43 -> 118284 | AI43: =N43 -> 118704 | AJ43: =O43 -> 113084 | AK43: =P43 -> 107061 | AL43: =Q43 -> 94275 | AM43: =R43 -> 91883 | ... AX43: =AC43 -> 75406 | AZ43: =SUM(AX43/AT43)-1 -> 0.029138404
B44: Accounts Receivables | C44: 20838 | D44: 25326 | E44: 30930 | F44: 39304 | G44: 40258 | H44: 47964 | I44: 52340 | K44: 28006 | L44: 31967 | M44: 34047 | N44: =F44 -> 39304 | O44: 34703 | P44: 35707 | Q44: 34697 | R44: =G44 -> 40258 | S44: 36036 | T44: 38804 | U44: 41020 | V44: =H44 -> 47964 | W44: 44552 | X44: 47087 | Y44: 49104 | Z44: =I44 -> 52340 | AA44: 51000 | AB44: 55048 | AC44: 57148 | AE44: =#REF! -> #REF! | AF44: =K44 -> 28006 | AG44: =L44 -> 31967 | AH44: =M44 -> 34047 | AI44: =N44 -> 39304 | AJ44: =O44 -> 34703 | AK44: =P44 -> 35707 | AL44: =Q44 -> 34697 | AM44: =R44 -> 40258 | ... AX44: =AC44 -> 57148 | AZ44: =SUM(AX44/AT44)-1 -> 0.16381558
B45: Other Current Assets | C45: =4236+1107+355 -> 5698 | D45: =2166+999+4412 -> 7577 | E45: =454+728+5490 -> 6672 | F45: =1170+8020 -> 9190 | G45: =8105+2670 -> 10775 | H45: 12650 | I45: 15714 | K45: =493+888+7646 -> 9027 | L45: =6076+884+907 -> 7867 | M45: =1278+753+6029 -> 8060 | N45: =F45 -> 9190 | O45: =6892+919+1369 -> 9180 | P45: =8321+1980+1366 -> 11667 | Q45: =10518+3156+1479 -> 15153 | R45: =G45 -> 10775 | S45: =8532+2315 -> 10847 | T45: =9421+2231 -> 11652 | U45: =12398+2957 -> 15355 | V45: =H45 -> 12650 | W45: 12829 | X45: 14183 | Y45: 15207 | Z45: =I45 -> 15714 | AA45: 15724 | AB45: 16020 | AC45: 18303 | AE45: =#REF! -> #REF! | AF45: =K45 -> 9027 | AG45: =L45 -> 7867 | AH45: =M45 -> 8060 | AI45: =N45 -> 9190 | AJ45: =O45 -> 9180 | AK45: =P45 -> 11667 | AL45: =Q45 -> 15153 | AM45: =R45 -> 10775 | ... AX45: =AC45 -> 18303 | AZ45: =SUM(AX45/AT45)-1 -> 0.20359045
B46: Total Current Assets | C46: =SUM(C42:C45) -> 135676 | D46: =SUM(D42:D45) -> 152578 | E46: =SUM(E42:E45) -> 174296 | F46: =SUM(F42:F45) -> 188143 | G46: =SUM(G42:G45) -> 164795 | H46: =SUM(H42:H45) -> 171530 | I46: =SUM(I42:I45) -> 163711 | K46: =SUM(K42:K45) -> 172137 | L46: =SUM(L42:L45) -> 175697 | M46: =SUM(M42:M45) -> 184110 | N46: =SUM(N42:N45) -> 188143 | O46: =SUM(O42:O45) -> 177853 | P46: =SUM(P42:P45) -> 172371 | Q46: =SUM(Q42:Q45) -> 166109 | R46: =SUM(R42:R45) -> 164795 | ... AC46: =SUM(AC42:AC45) -> 173947 | AE46: =SUM(AE42:AE45) -> #REF! | AF46: =SUM(AF42:AF45) -> 172137 | AG46: =SUM(AG42:AG45) -> 175697 | AH46: =SUM(AH42:AH45) -> 184110 | AI46: =SUM(AI42:AI45) -> 188143 | AJ46: =SUM(AJ42:AJ45) -> 177853 | AK46: =SUM(AK42:AK45) -> 172371 | AL46: =SUM(AL42:AL45) -> 166109 | ... AX46: =SUM(AX42:AX45) -> 173947 | AZ46: =SUM(AX46/AT46)-1 -> 0.10413797
B48: Non-Current Assets
B49: Non-marketable securities | C49: 13859 | D49: 13078 | E49: 20703 | F49: 29549 | G49: 30492 | H49: 31008 | I49: 37982 | K49: 25294 | L49: 25532 | M49: 26101 | N49: =F49 -> 29549 | O49: 30544 | P49: 30665 | Q49: 30419 | R49: =G49 -> 30492 | S49: 31213 | T49: 31224 | U49: 30907 | V49: =H49 -> 31008 | W49: 33994 | X49: 34172 | Y49: 36177 | Z49: =I49 -> 37982 | AA49: 51029 | AB49: 52574 | AC49: 63800 | AE49: =#REF! -> #REF! | AF49: =K49 -> 25294 | AG49: =L49 -> 25532 | AH49: =M49 -> 26101 | AI49: =N49 -> 29549 | AJ49: =O49 -> 30544 | AK49: =P49 -> 30665 | AL49: =Q49 -> 30419 | AM49: =R49 -> 30492 | ... AX49: =AC49 -> 63800 | AZ49: =SUM(AX49/AT49)-1 -> 0.76355143
B50: Deferred income taxes | C50: 737 | D50: 721 | E50: 1084 | F50: 1284 | G50: 5261 | H50: 12169 | I50: 17180 | K50: 1129 | L50: 1153 | M50: 1195 | N50: =F50 -> 1284 | O50: 1388 | P50: 1490 | Q50: 2991 | R50: =G50 -> 5261 | S50: 6885 | T50: 9357 | U50: 10983 | V50: =H50 -> 12169 | W50: 11687 | X50: 14958 | Y50: 15915 | Z50: =I50 -> 17180 | AA50: 18386 | AB50: 19289 | AC50: 10331 | AE50: =#REF! -> #REF! | AF50: =K50 -> 1129 | AG50: =L50 -> 1153 | AH50: =M50 -> 1195 | AI50: =N50 -> 1284 | AJ50: =O50 -> 1388 | AK50: =P50 -> 1490 | AL50: =Q50 -> 2991 | AM50: =R50 -> 5261 | ... AX50: =AC50 -> 10331 | AZ50: =SUM(AX50/AT50)-1 -> -0.35086396
B51: Property and equipment, net | C51: 59719 | D51: 73646 | E51: 84749 | F51: 97599 | G51: 112668 | H51: 134345 | I51: 171036 | K51: 87606 | L51: 91697 | M51: 94631 | N51: =F51 -> 97599 | O51: 104218 | P51: 106223 | Q51: 108363 | R51: =G51 -> 112668 | S51: 117560 | T51: 121208 | U51: 125705 | V51: =H51 -> 134345 | W51: 143182 | X51: 151155 | Y51: 161270 | Z51: =I51 -> 171036 | AA51: 185062 | AB51: 203231 | AC51: 223787 | AE51: =#REF! -> #REF! | AF51: =K51 -> 87606 | AG51: =L51 -> 91697 | AH51: =M51 -> 94631 | AI51: =N51 -> 97599 | AJ51: =O51 -> 104218 | AK51: =P51 -> 106223 | AL51: =Q51 -> 108363 | AM51: =R51 -> 112668 | ... AX51: =AC51 -> 223787 | AZ51: =SUM(AX51/AT51)-1 -> 0.38765424
B52: Operating lease assets | C52: 0 | D52: 10941 | E52: 12211 | F52: 12959 | G52: 14381 | H52: 14091 | I52: 13588 | K52: 12598 | L52: 12978 | M52: 12918 | N52: =F52 -> 12959 | O52: 12992 | P52: 13398 | Q52: 13677 | R52: =G52 -> 14381 | S52: 14447 | T52: 14469 | U52: 14199 | V52: =H52 -> 14091 | W52: 13768 | X52: 13606 | Y52: 13561 | Z52: =I52 -> 13588 | AA52: 13722 | AB52: 14255 | AC52: 14524 | AE52: =#REF! -> #REF! | AF52: =K52 -> 12598 | AG52: =L52 -> 12978 | AH52: =M52 -> 12918 | AI52: =N52 -> 12959 | AJ52: =O52 -> 12992 | AK52: =P52 -> 13398 | AL52: =Q52 -> 13677 | AM52: =R52 -> 14381 | ... AX52: =AC52 -> 14524 | AZ52: =SUM(AX52/AT52)-1 -> 0.071012462
B53: Goodwill | C53: 17888 | D53: 20624 | E53: 21175 | F53: 22956 | G53: 28960 | H53: 29198 | I53: 31885 | K53: 22341 | L53: 22406 | M53: 22623 | N53: =F53 -> 22956 | O53: 23010 | P53: 23949 | Q53: 28834 | R53: =G53 -> 28960 | S53: 28994 | T53: 29210 | U53: 29146 | V53: =H53 -> 29198 | W53: 29183 | X53: 29185 | Y53: 31935 | Z53: =I53 -> 31885 | AA53: 32173 | AB53: 32335 | AC53: 33269 | AE53: =#REF! -> #REF! | AF53: =K53 -> 22341 | AG53: =L53 -> 22406 | AH53: =M53 -> 22623 | AI53: =N53 -> 22956 | AJ53: =O53 -> 23010 | AK53: =P53 -> 23949 | AL53: =Q53 -> 28834 | AM53: =R53 -> 28960 | ... AX53: =AC53 -> 33269 | AZ53: =SUM(AX53/AT53)-1 -> 0.04177235
B54: Other non-current assets | C54: =2693+2220 -> 4913 | D54: =1979+2342 -> 4321 | E54: =1445+3953 -> 5398 | F54: =5361+1417 -> 6778 | G54: =2084+6623 -> 8707 | H54: 10051 | I54: 14874 | K54: =1823+4167 -> 5990 | L54: =4298+1626 -> 5924 | M54: =4276+1549 -> 5825 | N54: =F54 -> 6778 | O54: =1313+5778 -> 7091 | P54: =5712+1377 -> 7089 | Q54: =2192+5670 -> 7862 | R54: =G54 -> 8707 | S54: =1968+6439 -> 8407 | T54: =6822+1966 -> 8788 | U54: =7628+1833 -> 9461 | V54: =H54 -> 10051 | W54: =10065 -> 10065 | X54: =9699 -> 9699 | Y54: =13867 -> 13867 | Z54: =I54 -> 14874 | AA54: 12950 | AB54: 14153 | AC54: 16811 | AE54: =#REF! -> #REF! | AF54: =K54 -> 5990 | AG54: =L54 -> 5924 | AH54: =M54 -> 5825 | AI54: =N54 -> 6778 | AJ54: =O54 -> 7091 | AK54: =P54 -> 7089 | AL54: =Q54 -> 7862 | AM54: =R54 -> 8707 | ... AX54: =AC54 -> 16811 | AZ54: =SUM(AX54/AT54)-1 -> 0.21230259
B55: Total Assets | C55: =SUM(C49:C54)+C46 -> 232792 | D55: =SUM(D49:D54)+D46 -> 275909 | E55: =SUM(E49:E54)+E46 -> 319616 | F55: =SUM(F49:F54)+F46 -> 359268 | G55: =SUM(G49:G54)+G46 -> 365264 | H55: =SUM(H49:H54)+H46 -> 402392 | I55: =SUM(I49:I54)+I46 -> 450256 | K55: =SUM(K49:K54)+K46 -> 327095 | L55: =SUM(L49:L54)+L46 -> 335387 | M55: =SUM(M49:M54)+M46 -> 347403 | N55: =SUM(N49:N54)+N46 -> 359268 | O55: =SUM(O49:O54)+O46 -> 357096 | P55: =SUM(P49:P54)+P46 -> 355185 | Q55: =SUM(Q49:Q54)+Q46 -> 358255 | R55: =SUM(R49:R54)+R46 -> 365264 | ... AC55: =SUM(AC49:AC54)+AC46 -> 536469 | AE55: =SUM(AE49:AE54)+AE46 -> #REF! | AF55: =SUM(AF49:AF54)+AF46 -> 327095 | AG55: =SUM(AG49:AG54)+AG46 -> 335387 | AH55: =SUM(AH49:AH54)+AH46 -> 347403 | AI55: =SUM(AI49:AI54)+AI46 -> 359268 | AJ55: =SUM(AJ49:AJ54)+AJ46 -> 357096 | AK55: =SUM(AK49:AK54)+AK46 -> 355185 | AL55: =SUM(AL49:AL54)+AL46 -> 358255 | ... AX55: =SUM(AX49:AX54)+AX46 -> 536469 | AZ55: =SUM(AX55/AT55)-1 -> 0.24683103
B57: Current Liabilities
B58: Accounts Payable | C58: 4378 | D58: 5561 | E58: 5589 | F58: 6037 | G58: 5128 | H58: 7493 | I58: 7987 | K58: 4801 | L58: 4708 | M58: 4616 | N58: =F58 -> 6037 | O58: 3436 | P58: 4409 | Q58: 6303 | R58: =G58 -> 5128 | S58: 4184 | T58: 5313 | U58: 5803 | V58: =H58 -> 7493 | W58: 6198 | X58: 6092 | Y58: 7049 | Z58: =I58 -> 7987 | AA58: 8497 | AB58: 8347 | AC58: 10546 | AE58: =#REF! -> #REF! | AF58: =K58 -> 4801 | AG58: =L58 -> 4708 | AH58: =M58 -> 4616 | AI58: =N58 -> 6037 | AJ58: =O58 -> 3436 | AK58: =P58 -> 4409 | AL58: =Q58 -> 6303 | AM58: =R58 -> 5128 | ... AX58: =AC58 -> 10546 | AZ58: =SUM(AX58/AT58)-1 -> 0.49609874
B59: Accrued Compensation and Benefits | C59: 6839 | D59: 8495 | E59: 11086 | F59: 13889 | G59: 14028 | H59: 15140 | I59: 15069 | K59: 8375 | L59: 10088 | M59: 12170 | N59: =F59 -> 13889 | O59: 9803 | P59: 10852 | Q59: 12366 | R59: =G59 -> 14028 | S59: 9954 | T59: 11260 | U59: 12562 | V59: =H59 -> 15140 | W59: 9703 | X59: 11373 | Y59: 12908 | Z59: =I59 -> 15069 | AA59: 9984 | AB59: 12168 | AC59: 13944 | AE59: =#REF! -> #REF! | AF59: =K59 -> 8375 | AG59: =L59 -> 10088 | AH59: =M59 -> 12170 | AI59: =N59 -> 13889 | AJ59: =O59 -> 9803 | AK59: =P59 -> 10852 | AL59: =Q59 -> 12366 | AM59: =R59 -> 14028 | ... AX59: =AC59 -> 13944 | AZ59: =SUM(AX59/AT59)-1 -> 0.080260304
B60: Accrued Expenses and Other Current Liabilities | C60: =16958+69 -> 17027 | D60: =23067+274 -> 23341 | E60: =28631+1485 -> 30116 | F60: 32044 | G60: 37866 | H60: =46168 -> 46168 | I60: =51228 -> 51228 | K60: =30732+1893 -> 32625 | L60: =28981+1811 -> 30792 | M60: =30113+4170 -> 34283 | N60: =F60 -> 32044 | O60: =33051+4344 -> 37395 | P60: =32976+1956 -> 34932 | Q60: =35038+1025 -> 36063 | R60: =G60 -> 37866 | S60: 43185 | T60: 49300 | U60: 55602 | V60: =H60 -> 46168 | W60: 48603 | X60: 47298 | Y60: 46585 | Z60: =I60 -> 51228 | AA60: 58300 | AB60: 52039 | AC60: 59437 | AE60: =#REF! -> #REF! | AF60: =K60 -> 32625 | AG60: =L60 -> 30792 | AH60: =M60 -> 34283 | AI60: =N60 -> 32044 | AJ60: =O60 -> 37395 | AK60: =P60 -> 34932 | AL60: =Q60 -> 36063 | AM60: =R60 -> 37866 | ... AX60: =AC60 -> 59437 | AZ60: =SUM(AX60/AT60)-1 -> 0.27588279
B61: Accrued Revenue Share | C61: 4592 | D61: 5916 | E61: 7500 | F61: 8996 | G61: 8370 | H61: 8876 | I61: 9802 | K61: 6962 | L61: 7438 | M61: 7745 | N61: =F61 -> 8996 | O61: 8116 | P61: 7889 | Q61: 7662 | R61: =G61 -> 8370 | S61: 7816 | T61: 7990 | U61: 8025 | V61: =H61 -> 8876 | W61: 8520 | X61: 8899 | Y61: 9365 | Z61: =I61 -> 9802 | AA61: 9965 | AB61: 9787 | AC61: 10081 | AE61: =#REF! -> #REF! | AF61: =K61 -> 6962 | AG61: =L61 -> 7438 | AH61: =M61 -> 7745 | AI61: =N61 -> 8996 | AJ61: =O61 -> 8116 | AK61: =P61 -> 7889 | AL61: =Q61 -> 7662 | AM61: =R61 -> 8370 | ... AX61: =AC61 -> 10081 | AZ61: =SUM(AX61/AT61)-1 -> 0.076454885
B62: Deferred Revenue, Current | C62: 1784 | D62: 1908 | E62: 2543 | F62: 3288 | G62: 3908 | H62: 4137 | I62: 5036 | K62: 2690 | L62: 2715 | M62: 2968 | N62: =F62 -> 3288 | O62: 3198 | P62: 3272 | Q62: 3585 | R62: =G62 -> 3908 | S62: 3715 | T62: 3846 | U62: 4303 | V62: =H62 -> 4137 | W62: 3973 | X62: 4251 | Y62: 4896 | Z62: =I62 -> 5036 | AA62: 4908 | AB62: 4969 | AC62: 5542 | AE62: =#REF! -> #REF! | AF62: =K62 -> 2690 | AG62: =L62 -> 2715 | AH62: =M62 -> 2968 | AI62: =N62 -> 3288 | AJ62: =O62 -> 3198 | AK62: =P62 -> 3272 | AL62: =Q62 -> 3585 | AM62: =R62 -> 3908 | ... AX62: =AC62 -> 5542 | AZ62: =SUM(AX62/AT62)-1 -> 0.13194444
B63: Total Current Liabilities | C63: =SUM(C58:C62) -> 34620 | D63: =SUM(D58:D62) -> 45221 | E63: =SUM(E58:E62) -> 56834 | F63: =SUM(F58:F62) -> 64254 | G63: =SUM(G58:G62) -> 69300 | H63: =SUM(H58:H62) -> 81814 | I63: =SUM(I58:I62) -> 89122 | K63: =SUM(K58:K62) -> 55453 | L63: =SUM(L58:L62) -> 55741 | M63: =SUM(M58:M62) -> 61782 | N63: =SUM(N58:N62) -> 64254 | O63: =SUM(O58:O62) -> 61948 | P63: =SUM(P58:P62) -> 61354 | Q63: =SUM(Q58:Q62) -> 65979 | R63: =SUM(R58:R62) -> 69300 | ... AC63: =SUM(AC58:AC62) -> 99550 | AE63: =SUM(AE58:AE62) -> #REF! | AF63: =SUM(AF58:AF62) -> 55453 | AG63: =SUM(AG58:AG62) -> 55741 | AH63: =SUM(AH58:AH62) -> 61782 | AI63: =SUM(AI58:AI62) -> 64254 | AJ63: =SUM(AJ58:AJ62) -> 61948 | AK63: =SUM(AK58:AK62) -> 61354 | AL63: =SUM(AL58:AL62) -> 65979 | ... AX63: =SUM(AX58:AX62) -> 99550 | AZ63: =SUM(AX63/AT63)-1 -> 0.23200871
B65: Non-Current Liabilities
B66: Long-Term Debt | C66: 4012 | D66: 4554 | E66: 13932 | F66: 14817 | G66: 14701 | H66: 11870 | I66: 10883 | K66: 13887 | L66: 14328 | M66: 14288 | N66: =F66 -> 14817 | O66: 14791 | P66: 14734 | Q66: 14653 | R66: =G66 -> 14701 | S66: 13697 | T66: 13705 | U66: 13781 | V66: =H66 -> 11870 | W66: 13228 | X66: 13238 | Y66: 12297 | Z66: =I66 -> 10883 | AA66: 10886 | AB66: 23607 | AC66: 21607 | AE66: =#REF! -> #REF! | AF66: =K66 -> 13887 | AG66: =L66 -> 14328 | AH66: =M66 -> 14288 | AI66: =N66 -> 14817 | AJ66: =O66 -> 14791 | AK66: =P66 -> 14734 | AL66: =Q66 -> 14653 | AM66: =R66 -> 14701 | ... AX66: =AC66 -> 21607 | AZ66: =SUM(AX66/AT66)-1 -> 0.75709523
B67: Income taxes payable, non-current | C67: =11327+1264 -> 12591 | D67: =9885+1701 -> 11586 | E67: =8849+3561 -> 12410 | F67: =9176+5257 -> 14433 | G67: =9258+514 -> 9772 | H67: 8474 | I67: 8782 | K67: =9278+4406 -> 13684 | L67: =8651+4703 -> 13354 | M67: =8984+3551 -> 12535 | N67: =F67 -> 14433 | O67: =9406+2843 -> 12249 | P67: =8163+924 -> 9087 | Q67: =8572+476 -> 9048 | R67: =G67 -> 9772 | S67: =9722+542 -> 10264 | T67: =8753+558 -> 9311 | U67: =8038+528 -> 8566 | V67: =H67 -> 8474 | W67: =9234+486 -> 9720 | X67: =7703+717 -> 8420 | Y67: =1015+8219 -> 9234 | Z67: =I67 -> 8782 | AA67: 9773 | AB67: 10027 | AC67: 10072 | AE67: =#REF! -> #REF! | AF67: =K67 -> 13684 | AG67: =L67 -> 13354 | AH67: =M67 -> 12535 | AI67: =N67 -> 14433 | AJ67: =O67 -> 12249 | AK67: =P67 -> 9087 | AL67: =Q67 -> 9048 | AM67: =R67 -> 9772 | ... AX67: =AC67 -> 10072 | AZ67: =SUM(AX67/AT67)-1 -> 0.09075157
B68: Operating Lease Liabilities | C68: 0 | D68: 10214 | E68: 11146 | F68: 11389 | G68: 12501 | H68: 12460 | I68: 11691 | K68: 11382 | L68: 11619 | M68: 11471 | N68: =F68 -> 11389 | O68: 11363 | P68: 11697 | Q68: 11984 | R68: =G68 -> 12501 | S68: 12799 | T68: 12746 | U68: 12550 | V68: =H68 -> 12460 | W68: 11957 | X68: 11708 | Y68: 11654 | Z68: =I68 -> 11691 | AA68: 11678 | AB68: 11952 | AC68: 12106 | AE68: =#REF! -> #REF! | AF68: =K68 -> 11382 | AG68: =L68 -> 11619 | AH68: =M68 -> 11471 | AI68: =N68 -> 11389 | AJ68: =O68 -> 11363 | AK68: =P68 -> 11697 | AL68: =Q68 -> 11984 | AM68: =R68 -> 12501 | ... AX68: =AC68 -> 12106 | AZ68: =SUM(AX68/AT68)-1 -> 0.038784967
B69: Other long-term liabilities | C69: =396+3545 -> 3941 | D69: =358+2534 -> 2892 | E69: =481+2269 -> 2750 | F69: =535+2205 -> 2740 | G69: =599+2247 -> 2846 | H69: 4395 | I69: 4694 | K69: =530+2146 -> 2676 | L69: =510+2270 -> 2780 | M69: =510+2250 -> 2760 | N69: =F69 -> 2740 | O69: =2242+499 -> 2741 | P69: =2422+472 -> 2894 | Q69: =2371+594 -> 2965 | R69: =G69 -> 2846 | S69: =610+2373 -> 2983 | T69: =1765+667 -> 2432 | U69: =1433+884 -> 2317 | V69: =H69 -> 4395 | W69: =1683+921 -> 2604 | X69: =1753+985 -> 2738 | Y69: =1453+706 -> 2159 | Z69: =I69 -> 4694 | AA69: 6116 | AB69: 6241 | AC69: 6267 | AE69: =#REF! -> #REF! | AF69: =K69 -> 2676 | AG69: =L69 -> 2780 | AH69: =M69 -> 2760 | AI69: =N69 -> 2740 | AJ69: =O69 -> 2741 | AK69: =P69 -> 2894 | AL69: =Q69 -> 2965 | AM69: =R69 -> 2846 | ... AX69: =AC69 -> 6267 | AZ69: =SUM(AX69/AT69)-1 -> 1.9027327
B70: Total Liabilities | C70: =SUM(C66:C69)+C63 -> 55164 | D70: =SUM(D66:D69)+D63 -> 74467 | E70: =SUM(E66:E69)+E63 -> 97072 | F70: =SUM(F66:F69)+F63 -> 107633 | G70: =SUM(G66:G69)+G63 -> 109120 | H70: =SUM(H66:H69)+H63 -> 119013 | I70: =SUM(I66:I69)+I63 -> 125172 | K70: =SUM(K66:K69)+K63 -> 97082 | L70: =SUM(L66:L69)+L63 -> 97822 | M70: =SUM(M66:M69)+M63 -> 102836 | N70: =SUM(N66:N69)+N63 -> 107633 | O70: =SUM(O66:O69)+O63 -> 103092 | P70: =SUM(P66:P69)+P63 -> 99766 | Q70: =SUM(Q66:Q69)+Q63 -> 104629 | R70: =SUM(R66:R69)+R63 -> 109120 | ... AC70: =SUM(AC66:AC69)+AC63 -> 149602 | AE70: =SUM(AE66:AE69)+AE63 -> #REF! | AF70: =SUM(AF66:AF69)+AF63 -> 97082 | AG70: =SUM(AG66:AG69)+AG63 -> 97822 | AH70: =SUM(AH66:AH69)+AH63 -> 102836 | AI70: =SUM(AI66:AI69)+AI63 -> 107633 | AJ70: =SUM(AJ66:AJ69)+AJ63 -> 103092 | AK70: =SUM(AK66:AK69)+AK63 -> 99766 | AL70: =SUM(AL66:AL69)+AL63 -> 104629 | ... AX70: =SUM(AX66:AX69)+AX63 -> 149602 | AZ70: =SUM(AX70/AT70)-1 -> 0.28804016
B72: Preferred Stock | C72: 0 | D72: 0 | E72: 0 | F72: 0 | G72: 0 | H72: 0 | I72: 0 | K72: 0 | L72: 0 | M72: 0 | N72: =F72 -> 0 | O72: 0 | P72: 0 | Q72: 0 | R72: =G72 -> 0 | S72: 0 | T72: 0 | U72: 0 | V72: =H72 -> 0 | W72: 0 | X72: 0 | Y72: 0 | Z72: =I72 -> 0 | AA72: 0 | AB72: 0 | AC72: 0 | AE72: =#REF! -> #REF! | AF72: =K72 -> 0 | AG72: =L72 -> 0 | AH72: =M72 -> 0 | AI72: =N72 -> 0 | AJ72: =O72 -> 0 | AK72: =P72 -> 0 | AL72: =Q72 -> 0 | AM72: =R72 -> 0 | ... AX72: =AC72 -> 0 | AZ72: =SUM(AX72/AT72)-1 -> #DIV/0!
B73: Common Stock & Additional Paid in Capital | C73: 45049 | D73: 50552 | E73: 58510 | F73: 61774 | G73: 68184 | H73: 76534 | I73: 84800 | K73: 59436 | L73: 60436 | M73: 61193 | N73: =F73 -> 61774 | O73: 62832 | P73: 64402 | Q73: 66258 | R73: =G73 -> 68184 | S73: 70269 | T73: 72248 | U73: 74591 | V73: =H73 -> 76534 | W73: 77913 | X73: 79732 | Y73: 82030 | Z73: =I73 -> 84800 | AA73: 86725 | AB73: 89283 | AC73: 91695 | AE73: =#REF! -> #REF! | AF73: =K73 -> 59436 | AG73: =L73 -> 60436 | AH73: =M73 -> 61193 | AI73: =N73 -> 61774 | AJ73: =O73 -> 62832 | AK73: =P73 -> 64402 | AL73: =Q73 -> 66258 | AM73: =R73 -> 68184 | ... AX73: =AC73 -> 91695 | AZ73: =SUM(AX73/AT73)-1 -> 0.11782275
B74: Accumulated other comprehensive income (loss) | C74: -2306 | D74: -1232 | E74: 633 | F74: -1623 | G74: -7603 | H74: -4402 | I74: -4800 | K74: -3 | L74: 190 | M74: -408 | N74: =F74 -> -1623 | O74: -4049 | P74: -5828 | Q74: -8852 | R74: =G74 -> -7603 | S74: -6000 | T74: -5991 | U74: -7036 | V74: =H74 -> -4402 | W74: -4839 | X74: -5012 | Y74: -3228 | Z74: =I74 -> -4800 | AA74: -4086 | AB74: -2127 | AC74: -2054 | AE74: =#REF! -> #REF! | AF74: =K74 -> -3 | AG74: =L74 -> 190 | AH74: =M74 -> -408 | AI74: =N74 -> -1623 | AJ74: =O74 -> -4049 | AK74: =P74 -> -5828 | AL74: =Q74 -> -8852 | AM74: =R74 -> -7603 | ... AX74: =AC74 -> -2054 | AZ74: =SUM(AX74/AT74)-1 -> -0.36369269
B75: Retained earnings | C75: 134885 | D75: 152122 | E75: 163401 | F75: 191484 | G75: 195563 | H75: 211247 | I75: 245084 | K75: 170580 | L75: 176939 | M75: 183782 | N75: =F75 -> 191484 | O75: 195221 | P75: 196845 | Q75: 196220 | R75: =G75 -> 195563 | S75: 196625 | T75: 200884 | U75: 205647 | V75: =H75 -> 211247 | W75: 219770 | X75: 226033 | Y75: 235317 | Z75: =I75 -> 245084 | AA75: 262628 | AB75: 275760 | AC75: 297226 | AE75: =#REF! -> #REF! | AF75: =K75 -> 170580 | AG75: =L75 -> 176939 | AH75: =M75 -> 183782 | AI75: =N75 -> 191484 | AJ75: =O75 -> 195221 | AK75: =P75 -> 196845 | AL75: =Q75 -> 196220 | AM75: =R75 -> 195563 | ... AX75: =AC75 -> 297226 | AZ75: =SUM(AX75/AT75)-1 -> 0.26308766
B76: Total stockholders' equity | C76: =SUM(C72:C75) -> 177628 | D76: =SUM(D72:D75) -> 201442 | E76: =SUM(E72:E75) -> 222544 | F76: =SUM(F72:F75) -> 251635 | G76: =SUM(G72:G75) -> 256144 | H76: =SUM(H72:H75) -> 283379 | I76: =SUM(I72:I75) -> 325084 | K76: =SUM(K72:K75) -> 230013 | L76: =SUM(L72:L75) -> 237565 | M76: =SUM(M72:M75) -> 244567 | N76: =SUM(N72:N75) -> 251635 | O76: =SUM(O72:O75) -> 254004 | P76: =SUM(P72:P75) -> 255419 | Q76: =SUM(Q72:Q75) -> 253626 | R76: =SUM(R72:R75) -> 256144 | ... AC76: =SUM(AC72:AC75) -> 386867 | AE76: =SUM(AE72:AE75) -> #REF! | AF76: =SUM(AF72:AF75) -> 230013 | AG76: =SUM(AG72:AG75) -> 237565 | AH76: =SUM(AH72:AH75) -> 244567 | AI76: =SUM(AI72:AI75) -> 251635 | AJ76: =SUM(AJ72:AJ75) -> 254004 | AK76: =SUM(AK72:AK75) -> 255419 | AL76: =SUM(AL72:AL75) -> 253626 | ... AX76: =SUM(AX72:AX75) -> 386867 | AZ76: =SUM(AX76/AT76)-1 -> 0.23159376
B77: Total liabilities and stockholders' equity | C77: =SUM(C76+C70) -> 232792 | D77: =SUM(D76+D70) -> 275909 | E77: =SUM(E76+E70) -> 319616 | F77: =SUM(F76+F70) -> 359268 | G77: =SUM(G76+G70) -> 365264 | H77: =SUM(H76+H70) -> 402392 | I77: =SUM(I76+I70) -> 450256 | K77: =SUM(K76+K70) -> 327095 | L77: =SUM(L76+L70) -> 335387 | M77: =SUM(M76+M70) -> 347403 | N77: =SUM(N76+N70) -> 359268 | O77: =SUM(O76+O70) -> 357096 | P77: =SUM(P76+P70) -> 355185 | Q77: =SUM(Q76+Q70) -> 358255 | R77: =SUM(R76+R70) -> 365264 | ... AC77: =SUM(AC76+AC70) -> 536469 | AE77: =SUM(AE76+AE70) -> #REF! | AF77: =SUM(AF76+AF70) -> 327095 | AG77: =SUM(AG76+AG70) -> 335387 | AH77: =SUM(AH76+AH70) -> 347403 | AI77: =SUM(AI76+AI70) -> 359268 | AJ77: =SUM(AJ76+AJ70) -> 357096 | AK77: =SUM(AK76+AK70) -> 355185 | AL77: =SUM(AL76+AL70) -> 358255 | ... AX77: =SUM(AX76+AX70) -> 536469 | AZ77: =SUM(AX77/AT77)-1 -> 0.24683103
B79: Balance Check | C79: =C77-C55 -> 0 | D79: =D77-D55 -> 0 | E79: =E77-E55 -> 0 | F79: =F77-F55 -> 0 | G79: =G77-G55 -> 0 | H79: =H77-H55 -> 0 | I79: =I77-I55 -> 0 | K79: =K77-K55 -> 0 | L79: =L77-L55 -> 0 | M79: =M77-M55 -> 0 | N79: =N77-N55 -> 0 | O79: =O77-O55 -> 0 | P79: =P77-P55 -> 0 | Q79: =Q77-Q55 -> 0 | R79: =R77-R55 -> 0 | ... AC79: =AC77-AC55 -> 0 | AE79: =AE77-AE55 -> #REF! | AF79: =AF77-AF55 -> 0 | AG79: =AG77-AG55 -> 0 | AH79: =AH77-AH55 -> 0 | AI79: =AI77-AI55 -> 0 | AJ79: =AJ77-AJ55 -> 0 | AK79: =AK77-AK55 -> 0 | AL79: =AL77-AL55 -> 0 | ... AX79: =AX77-AX55 -> 0
A82: X | B82: Cash-Flows Statement | AS82: LTM | AZ82: Variance
B83: =B7 -> Fiscal Period | C83: =C7 -> 2018 | D83: =D7 -> 2019 | E83: =E7 -> 2020 | F83: =F7 -> 2021 | G83: =G7 -> 2022 | H83: =H7 -> 2023 | I83: =I7 -> 2024 | K83: =K7 -> 1Q21 | L83: =L7 -> 2Q21 | M83: =M7 -> 3Q21 | N83: =N7 -> 4Q21 | O83: =O7 -> 1Q22 | P83: =P7 -> 2Q22 | Q83: =Q7 -> 3Q22 | R83: =R7 -> 4Q22 | ... AC83: =AC7 -> 3Q25 | AE83: =AE7 -> #REF! | AF83: =AF7 -> 1Q21 | AG83: =AG7 -> 2Q21 | AH83: =AH7 -> 3Q21 | AI83: =AI7 -> 4Q21 | AJ83: =AJ7 -> 1Q22 | AK83: =AK7 -> 2Q22 | AL83: =AL7 -> 3Q22 | ... AX83: =AX7 -> 3Q25
B84: =B8 -> Fiscal Period End Date | C84: =C8 -> 43465 | D84: =D8 -> 43830 | E84: =E8 -> 44196 | F84: =F8 -> 44561 | G84: =G8 -> 44926 | H84: =H8 -> 45291 | I84: =I8 -> 45657 | K84: =K8 -> 44286 | L84: =L8 -> 44377 | M84: =M8 -> 44469 | N84: =N8 -> 44561 | O84: =O8 -> 44651 | P84: =P8 -> 44742 | Q84: =Q8 -> 44834 | R84: =R8 -> 44926 | ... AC84: =AC8 -> 45930 | AE84: =AE8 -> #REF! | AF84: =AF8 -> 44286 | AG84: =AG8 -> 44377 | AH84: =AH8 -> 44469 | AI84: =AI8 -> 44561 | AJ84: =AJ8 -> 44651 | AK84: =AK8 -> 44742 | AL84: =AL8 -> 44834 | ... AX84: =AX8 -> 45930
B86: Cash-Flows From Operating Activities
B87: Net income (loss) | C87: =C31 -> 30736 | D87: =D31 -> 34343 | E87: =E31 -> 40269 | F87: =F31 -> 76033 | G87: =G31 -> 59972 | H87: =H31 -> 73795 | I87: =I31 -> 100118 | K87: =K31 -> 17930 | L87: =L31 -> 18525 | M87: =M31 -> 18936 | N87: =N31 -> 20642 | O87: =O31 -> 16436 | P87: =P31 -> 16002 | Q87: =Q31 -> 13910 | R87: =R31 -> 13624 | ... AC87: =AC31 -> 34979 | AE87: =SUM(#REF!) -> #REF! | AF87: =SUM(K87:K87) -> 17930 | AG87: =SUM(K87:L87) -> 36455 | AH87: =SUM(K87:M87) -> 55391 | AI87: =SUM(K87:N87) -> 76033 | AJ87: =SUM(L87:O87) -> 74539 | AK87: =SUM(M87:P87) -> 72016 | AL87: =SUM(N87:Q87) -> 66990 | AM87: =SUM(O87:R87) -> 59972 | AN87: =SUM(P87:S87) -> 58587 | AO87: =SUM(Q87:T87) -> 60953 | AP87: =SUM(R87:U87) -> 66732 | ... AX87: =SUM(Z87:AC87) -> 124251 | AZ87: =SUM(AX87/AT87)-1 -> 0.31804729
B89: Adjustments to reconcile net income:
B90: Depreciation of property and equipment | C90: =8164+871 -> 9035 | D90: =10856+925 -> 11781 | E90: =12905+792 -> 13697 | F90: =11555+886 -> 12441 | G90: 13475 | H90: 11946 | I90: 15311 | K90: =2525+228 -> 2753 | L90: =5255+443 -K90 -> 2945 | M90: =8340+662-L90-K90 -> 3304 | N90: =SUM(F90-SUM(K90:M90)) -> 3439 | O90: =3591+191 -> 3782 | P90: =7289+392-O90 -> 3899 | Q90: =11222+505-P90-O90 -> 4046 | R90: =SUM(G90-SUM(O90:Q90)) -> 1748 | S90: =3060+126 -> 3186 | T90: =6339+244-S90 -> 3397 | U90: =10010+373-T90-S90 -> 3800 | V90: =SUM(H90-SUM(S90:U90)) -> 1563 | W90: 3413 | X90: =7121-W90 -> 3708 | Y90: =11106-X90-W90 -> 3985 | Z90: =SUM(I90-SUM(W90:Y90)) -> 4205 | AA90: 4487 | AB90: =9485-AA90 -> 4998 | AC90: =15096-AB90-AA90 -> 5611 | AE90: =SUM(#REF!) -> #REF! | AF90: =SUM(K90:K90) -> 2753 | AG90: =SUM(K90:L90) -> 5698 | AH90: =SUM(K90:M90) -> 9002 | AI90: =SUM(K90:N90) -> 12441 | AJ90: =SUM(L90:O90) -> 13470 | AK90: =SUM(M90:P90) -> 14424 | AL90: =SUM(N90:Q90) -> 15166 | AM90: =SUM(O90:R90) -> 13475 | AN90: =SUM(P90:S90) -> 12879 | AO90: =SUM(Q90:T90) -> 12377 | AP90: =SUM(R90:U90) -> 12131 | ... AX90: =SUM(Z90:AC90) -> 19301 | AZ90: =SUM(AX90/AT90)-1 -> 0.52348252
B91: Stock-based Compensation Expense | C91: 9353 | D91: 10794 | E91: 12991 | F91: 15376 | G91: 19362 | H91: 22460 | I91: 22785 | K91: 3745 | L91: =7548-K91 -> 3803 | M91: =11422-L91-K91 -> 3874 | N91: =SUM(F91-SUM(K91:M91)) -> 3954 | O91: 4504 | P91: =9286-O91 -> 4782 | Q91: =14262-P91-O91 -> 4976 | R91: =SUM(G91-SUM(O91:Q91)) -> 5100 | S91: 5284 | T91: =11058-S91 -> 5774 | U91: =16801-T91-S91 -> 5743 | V91: =SUM(H91-SUM(S91:U91)) -> 5659 | W91: 5264 | X91: =11129-W91 -> 5865 | Y91: =16975-X91-W91 -> 5846 | Z91: =SUM(I91-SUM(W91:Y91)) -> 5810 | AA91: 5516 | AB91: =11514-AA91 -> 5998 | AC91: =17882-AB91-AA91 -> 6368 | AE91: =SUM(#REF!) -> #REF! | AF91: =SUM(K91:K91) -> 3745 | AG91: =SUM(K91:L91) -> 7548 | AH91: =SUM(K91:M91) -> 11422 | AI91: =SUM(K91:N91) -> 15376 | AJ91: =SUM(L91:O91) -> 16135 | AK91: =SUM(M91:P91) -> 17114 | AL91: =SUM(N91:Q91) -> 18216 | AM91: =SUM(O91:R91) -> 19362 | AN91: =SUM(P91:S91) -> 20142 | AO91: =SUM(Q91:T91) -> 21134 | AP91: =SUM(R91:U91) -> 21901 | ... AX91: =SUM(Z91:AC91) -> 23692 | AZ91: =SUM(AX91/AT91)-1 -> 0.046743837
B92: Deferred income taxes | C92: 778 | D92: 173 | E92: 1390 | F92: 1808 | G92: -8081 | H92: -7763 | I92: -5257 | K92: 1100 | L92: =1479-K92 -> 379 | M92: =192-L92-K92 -> -1287 | N92: =SUM(F92-SUM(K92:M92)) -> 1616 | O92: -2090 | P92: =-4237-O92 -> -2147 | Q92: =-6157-P92-O92 -> -1920 | R92: =SUM(G92-SUM(O92:Q92)) -> -1924 | S92: -1854 | T92: =-4269-S92 -> -2415 | U92: =-6093-T92-S92 -> -1824 | V92: =SUM(H92-SUM(S92:U92)) -> -1670 | W92: 419 | X92: =-2738-W92 -> -3157 | Y92: =-3809-X92-W92 -> -1071 | Z92: =SUM(I92-SUM(W92:Y92)) -> -1448 | AA92: -1152 | AB92: =-1596-AA92 -> -444 | AC92: =7130-AB92-AA92 -> 8726 | AE92: =SUM(#REF!) -> #REF! | AF92: =SUM(K92:K92) -> 1100 | AG92: =SUM(K92:L92) -> 1479 | AH92: =SUM(K92:M92) -> 192 | AI92: =SUM(K92:N92) -> 1808 | AJ92: =SUM(L92:O92) -> -1382 | AK92: =SUM(M92:P92) -> -3908 | AL92: =SUM(N92:Q92) -> -4541 | AM92: =SUM(O92:R92) -> -8081 | AN92: =SUM(P92:S92) -> -7845 | AO92: =SUM(Q92:T92) -> -8113 | AP92: =SUM(R92:U92) -> -8017 | ... AX92: =SUM(Z92:AC92) -> 5682 | AZ92: =SUM(AX92/AT92)-1 -> -2.0370506
B93: Loss (gain) on debt and equity securities, net | C93: -6650 | D93: -2798 | E93: -6317 | F93: -12270 | G93: 5519 | H93: 823 | I93: -2671 | K93: -4751 | L93: =-7634-K93 -> -2883 | M93: =-9792-L93-K93 -> -2158 | N93: =SUM(F93-SUM(K93:M93)) -> -2478 | O93: 1437 | P93: =2478-O93 -> 1041 | Q93: =3856-P93-O93 -> 1378 | R93: =SUM(G93-SUM(O93:Q93)) -> 1663 | S93: -84 | T93: =425-S93 -> 509 | U93: =1294-T93-S93 -> 869 | V93: =SUM(H93-SUM(S93:U93)) -> -471 | W93: -1781 | X93: =-757-W93 -> 1024 | Y93: =-2738-X93-W93 -> -1981 | Z93: =SUM(I93-SUM(W93:Y93)) -> 67 | AA93: -9960 | AB93: =-11411-AA93 -> -1451 | AC93: =-22266-AB93-AA93 -> -10855 | AE93: =SUM(#REF!) -> #REF! | AF93: =SUM(K93:K93) -> -4751 | AG93: =SUM(K93:L93) -> -7634 | AH93: =SUM(K93:M93) -> -9792 | AI93: =SUM(K93:N93) -> -12270 | AJ93: =SUM(L93:O93) -> -6082 | AK93: =SUM(M93:P93) -> -2158 | AL93: =SUM(N93:Q93) -> 1378 | AM93: =SUM(O93:R93) -> 5519 | AN93: =SUM(P93:S93) -> 3998 | AO93: =SUM(Q93:T93) -> 3466 | AP93: =SUM(R93:U93) -> 2957 | ... AX93: =SUM(Z93:AC93) -> -22199 | AZ93: =SUM(AX93/AT93)-1 -> 5.9177314
B94: Other | C94: -189 | D94: -592 | E94: 1267 | F94: -213 | G94: 3483 | H94: 4330 | I94: 3419 | K94: -255 | L94: =-263-K94 -> -8 | M94: =-199-L94-K94 -> 64 | N94: =SUM(F94-SUM(K94:M94)) -> -14 | O94: 140 | P94: =202-O94 -> 62 | Q94: =369-P94-O94 -> 167 | R94: =SUM(G94-SUM(O94:Q94)) -> 3114 | S94: 553 | T94: =650-S94 -> 97 | U94: =912-T94-S94 -> 262 | V94: =SUM(H94-SUM(S94:U94)) -> 3418 | W94: 334 | X94: =1185-W94 -> 851 | Y94: =2592-X94-W94 -> 1407 | Z94: =SUM(I94-SUM(W94:Y94)) -> 827 | AA94: 481 | AB94: =1041-AA94 -> 560 | AC94: =843-AB94-AA94 -> -198 | AE94: =SUM(#REF!) -> #REF! | AF94: =SUM(K94:K94) -> -255 | AG94: =SUM(K94:L94) -> -263 | AH94: =SUM(K94:M94) -> -199 | AI94: =SUM(K94:N94) -> -213 | AJ94: =SUM(L94:O94) -> 182 | AK94: =SUM(M94:P94) -> 252 | AL94: =SUM(N94:Q94) -> 355 | AM94: =SUM(O94:R94) -> 3483 | AN94: =SUM(P94:S94) -> 3896 | AO94: =SUM(Q94:T94) -> 3931 | AP94: =SUM(R94:U94) -> 4026 | ... AX94: =SUM(Z94:AC94) -> 1670 | AZ94: =SUM(AX94/AT94)-1 -> -0.72212978
B95: Changes in assets and liabilities:
B96: Accounts receivable, net | C96: -2169 | D96: -4340 | E96: -6524 | F96: -9095 | G96: -2317 | H96: -7833 | I96: -5891 | K96: 2794 | L96: =-867-K96 -> -3661 | M96: =-3276-L96-K96 -> -2409 | N96: =SUM(F96-SUM(K96:M96)) -> -5819 | O96: 4364 | P96: =2395-O96 -> -1969 | Q96: =2298-P96-O96 -> -97 | R96: =SUM(G96-SUM(O96:Q96)) -> -4615 | S96: 4454 | T96: =1506-S96 -> -2948 | U96: =-1315-T96-S96 -> -2821 | V96: =SUM(H96-SUM(S96:U96)) -> -6518 | W96: 3167 | X96: =110-W96 -> -3057 | Y96: =-1321-X96-W96 -> -1431 | Z96: =SUM(I96-SUM(W96:Y96)) -> -4570 | AA96: 1638 | AB96: =-1201-AA96 -> -2839 | AC96: =-3582-AB96-AA96 -> -2381 | AE96: =SUM(#REF!) -> #REF! | AF96: =SUM(K96:K96) -> 2794 | AG96: =SUM(K96:L96) -> -867 | AH96: =SUM(K96:M96) -> -3276 | AI96: =SUM(K96:N96) -> -9095 | AJ96: =SUM(L96:O96) -> -7525 | AK96: =SUM(M96:P96) -> -5833 | AL96: =SUM(N96:Q96) -> -3521 | AM96: =SUM(O96:R96) -> -2317 | AN96: =SUM(P96:S96) -> -2227 | AO96: =SUM(Q96:T96) -> -3206 | AP96: =SUM(R96:U96) -> -5930 | ... AX96: =SUM(Z96:AC96) -> -8152 | AZ96: =SUM(AX96/AT96)-1 -> 0.039928562
B97: Income taxes, net | C97: -2251 | D97: -3128 | E97: 1209 | F97: -625 | G97: 584 | H97: 523 | I97: -2418 | K97: 785 | L97: =-297-K97 -> -1082 | M97: =2744-L97-K97 -> 3041 | N97: =SUM(F97-SUM(K97:M97)) -> -3369 | O97: 3820 | P97: =-253-O97 -> -4073 | Q97: =-862-P97-O97 -> -609 | R97: =SUM(G97-SUM(O97:Q97)) -> 1446 | S97: 4069 | T97: =8520-S97 -> 4451 | U97: =10392-T97-S97 -> 1872 | V97: =SUM(H97-SUM(S97:U97)) -> -9869 | W97: 3011 | X97: =-889-W97 -> -3900 | Y97: =-2797-X97-W97 -> -1908 | Z97: =SUM(I97-SUM(W97:Y97)) -> 379 | AA97: 7197 | AB97: =-2434-AA97 -> -9631 | AC97: =-3292-AB97-AA97 -> -858 | AE97: =SUM(#REF!) -> #REF! | AF97: =SUM(K97:K97) -> 785 | AG97: =SUM(K97:L97) -> -297 | AH97: =SUM(K97:M97) -> 2744 | AI97: =SUM(K97:N97) -> -625 | AJ97: =SUM(L97:O97) -> 2410 | AK97: =SUM(M97:P97) -> -581 | AL97: =SUM(N97:Q97) -> -4231 | AM97: =SUM(O97:R97) -> 584 | AN97: =SUM(P97:S97) -> 833 | AO97: =SUM(Q97:T97) -> 9357 | AP97: =SUM(R97:U97) -> 11838 | ... AX97: =SUM(Z97:AC97) -> -2913 | AZ97: =SUM(AX97/AT97)-1 -> -0.77001421
B98: Other assets | C98: -1207 | D98: -621 | E98: -1330 | F98: -1846 | G98: -5046 | H98: -2143 | I98: -1397 | K98: 7 | L98: =-192-K98 -> -199 | M98: =-1447-L98-K98 -> -1255 | N98: =SUM(F98-SUM(K98:M98)) -> -399 | O98: -776 | P98: =-1621-O98 -> -845 | Q98: =-4268-P98-O98 -> -2647 | R98: =SUM(G98-SUM(O98:Q98)) -> -778 | S98: -746 | T98: =-1259-S98 -> -513 | U98: =-2883-T98-S98 -> -1624 | V98: =SUM(H98-SUM(S98:U98)) -> 740 | W98: -1000 | X98: =-1532-W98 -> -532 | Y98: =-2334-X98-W98 -> -802 | Z98: =SUM(I98-SUM(W98:Y98)) -> 937 | AA98: -1288 | AB98: =-2767-AA98 -> -1479 | AC98: =-4060-AB98-AA98 -> -1293 | AE98: =SUM(#REF!) -> #REF! | AF98: =SUM(K98:K98) -> 7 | AG98: =SUM(K98:L98) -> -192 | AH98: =SUM(K98:M98) -> -1447 | AI98: =SUM(K98:N98) -> -1846 | AJ98: =SUM(L98:O98) -> -2629 | AK98: =SUM(M98:P98) -> -3275 | AL98: =SUM(N98:Q98) -> -4667 | AM98: =SUM(O98:R98) -> -5046 | AN98: =SUM(P98:S98) -> -5016 | AO98: =SUM(Q98:T98) -> -4684 | AP98: =SUM(R98:U98) -> -3661 | ... AX98: =SUM(Z98:AC98) -> -3123 | AZ98: =SUM(AX98/AT98)-1 -> 0.95922208
B99: Accounts payable | C99: 1067 | D99: 428 | E99: 694 | F99: 283 | G99: 707 | H99: 664 | I99: 359 | K99: -982 | L99: =-1112-K99 -> -130 | M99: =-874-L99-K99 -> 238 | N99: =SUM(F99-SUM(K99:M99)) -> 1157 | O99: -2373 | P99: =-1172-O99 -> 1201 | Q99: =735-P99-O99 -> 1907 | R99: =SUM(G99-SUM(O99:Q99)) -> -28 | S99: -1105 | T99: =14-S99 -> 1119 | U99: =237-T99-S99 -> 223 | V99: =SUM(H99-SUM(S99:U99)) -> 427 | W99: -2124 | X99: =-563-W99 -> 1561 | Y99: =-42-X99-W99 -> 521 | Z99: =SUM(I99-SUM(W99:Y99)) -> 401 | AA99: -880 | AB99: =-327-AA99 -> 553 | AC99: =-771-AB99-AA99 -> -444 | AE99: =SUM(#REF!) -> #REF! | AF99: =SUM(K99:K99) -> -982 | AG99: =SUM(K99:L99) -> -1112 | AH99: =SUM(K99:M99) -> -874 | AI99: =SUM(K99:N99) -> 283 | AJ99: =SUM(L99:O99) -> -1108 | AK99: =SUM(M99:P99) -> 223 | AL99: =SUM(N99:Q99) -> 1892 | AM99: =SUM(O99:R99) -> 707 | AN99: =SUM(P99:S99) -> 1975 | AO99: =SUM(Q99:T99) -> 1893 | AP99: =SUM(R99:U99) -> 209 | ... AX99: =SUM(Z99:AC99) -> -370 | AZ99: =SUM(AX99/AT99)-1 -> -1.961039
B100: Accrued expenses and other liabilities | C100: 8614 | D100: 7170 | E100: 5504 | F100: 7304 | G100: 3915 | H100: 3937 | I100: -1161 | K100: -3530 | L100: =201-K100 -> 3731 | M100: =2763-L100-K100 -> 2562 | N100: =SUM(F100-SUM(K100:M100)) -> 4541 | O100: -3216 | P100: =-1719-O100 -> 1497 | Q100: =491-P100-O100 -> 2210 | R100: =SUM(G100-SUM(O100:Q100)) -> 3424 | S100: -4496 | T100: =-4037-S100 -> 459 | U100: =-380-T100-S100 -> 3657 | V100: =SUM(H100-SUM(S100:U100)) -> 4317 | W100: -5054 | X100: =-5176-W100 -> -122 | Y100: =-6366-X100-W100 -> -1190 | Z100: =SUM(I100-SUM(W100:Y100)) -> 5205 | AA100: -5045 | AB100: =-1560-AA100 -> 3485 | AC100: =6199-AB100-AA100 -> 7759 | AE100: =SUM(#REF!) -> #REF! | AF100: =SUM(K100:K100) -> -3530 | AG100: =SUM(K100:L100) -> 201 | AH100: =SUM(K100:M100) -> 2763 | AI100: =SUM(K100:N100) -> 7304 | AJ100: =SUM(L100:O100) -> 7618 | AK100: =SUM(M100:P100) -> 5384 | AL100: =SUM(N100:Q100) -> 5032 | AM100: =SUM(O100:R100) -> 3915 | AN100: =SUM(P100:S100) -> 2635 | AO100: =SUM(Q100:T100) -> 1597 | AP100: =SUM(R100:U100) -> 3044 | ... AX100: =SUM(Z100:AC100) -> 11404 | AZ100: =SUM(AX100/AT100)-1 -> -6.5656418
B101: Accrued revenue share | C101: 483 | D101: 1273 | E101: 1639 | F101: 1682 | G101: -445 | H101: 482 | I101: 1059 | K101: -444 | L101: =29 -K101 -> 473 | M101: =386-L101-K101 -> 357 | N101: =SUM(F101-SUM(K101:M101)) -> 1296 | O101: -828 | P101: =-942-O101 -> -114 | Q101: =-1022-P101-O101 -> -80 | R101: =SUM(G101-SUM(O101:Q101)) -> 577 | S101: -602 | T101: =-418-S101 -> 184 | U101: =-315-T101-S101 -> 103 | V101: =SUM(H101-SUM(S101:U101)) -> 797 | W101: -322 | X101: =97 -W101 -> 419 | Y101: =478-X101-W101 -> 381 | Z101: =SUM(I101-SUM(W101:Y101)) -> 581 | AA101: 116 | AB101: =-219-AA101 -> -335 | AC101: =100-AB101-AA101 -> 319 | AE101: =SUM(#REF!) -> #REF! | AF101: =SUM(K101:K101) -> -444 | AG101: =SUM(K101:L101) -> 29 | AH101: =SUM(K101:M101) -> 386 | AI101: =SUM(K101:N101) -> 1682 | AJ101: =SUM(L101:O101) -> 1298 | AK101: =SUM(M101:P101) -> 711 | AL101: =SUM(N101:Q101) -> 274 | AM101: =SUM(O101:R101) -> -445 | AN101: =SUM(P101:S101) -> -219 | AO101: =SUM(Q101:T101) -> 79 | AP101: =SUM(R101:U101) -> 262 | ... AX101: =SUM(Z101:AC101) -> 681 | AZ101: =SUM(AX101/AT101)-1 -> -0.46588235
B102: Deferred revenue | C102: 371 | D102: 37 | E102: 635 | F102: 774 | G102: 367 | H102: 525 | I102: 1043 | K102: 137 | L102: =134 -K102 -> -3 | M102: =406-L102-K102 -> 272 | N102: =SUM(F102-SUM(K102:M102)) -> 368 | O102: -94 | P102: =-8-O102 -> 86 | Q102: =104-P102-O102 -> 112 | R102: =SUM(G102-SUM(O102:Q102)) -> 263 | S102: -201 | T102: =-17-S102 -> 184 | U102: =690-T102-S102 -> 707 | V102: =SUM(H102-SUM(S102:U102)) -> -165 | W102: -141 | X102: =220 -W102 -> 361 | Y102: =860-X102-W102 -> 640 | Z102: =SUM(I102-SUM(W102:Y102)) -> 183 | AA102: 500 | AB102: =636-AA102 -> 136 | AC102: =1317-AB102-AA102 -> 681 | AE102: =SUM(#REF!) -> #REF! | AF102: =SUM(K102:K102) -> 137 | AG102: =SUM(K102:L102) -> 134 | AH102: =SUM(K102:M102) -> 406 | AI102: =SUM(K102:N102) -> 774 | AJ102: =SUM(L102:O102) -> 543 | AK102: =SUM(M102:P102) -> 632 | AL102: =SUM(N102:Q102) -> 472 | AM102: =SUM(O102:R102) -> 367 | AN102: =SUM(P102:S102) -> 260 | AO102: =SUM(Q102:T102) -> 358 | AP102: =SUM(R102:U102) -> 953 | ... AX102: =SUM(Z102:AC102) -> 1500 | AZ102: =SUM(AX102/AT102)-1 -> 1.1582734
B103: Net cash used in operating activities | C103: =SUM(C87:C102) -> 47971 | D103: =SUM(D87:D102) -> 54520 | E103: =SUM(E87:E102) -> 65124 | F103: =SUM(F87:F102) -> 91652 | G103: =SUM(G87:G102) -> 91495 | H103: =SUM(H87:H102) -> 101746 | I103: =SUM(I87:I102) -> 125299 | K103: =SUM(K87:K102) -> 19289 | L103: =SUM(L87:L102) -> 21890 | M103: =SUM(M87:M102) -> 25539 | N103: =SUM(N87:N102) -> 24934 | O103: =SUM(O87:O102) -> 25106 | P103: =SUM(P87:P102) -> 19422 | Q103: =SUM(Q87:Q102) -> 23353 | R103: =SUM(R87:R102) -> 23614 | ... AC103: =SUM(AC87:AC102) -> 48414 | AE103: =SUM(AE87:AE102) -> #REF! | AF103: =SUM(AF87:AF102) -> 19289 | AG103: =SUM(AG87:AG102) -> 41179 | AH103: =SUM(AH87:AH102) -> 66718 | AI103: =SUM(AI87:AI102) -> 91652 | AJ103: =SUM(AJ87:AJ102) -> 97469 | AK103: =SUM(AK87:AK102) -> 95001 | AL103: =SUM(AL87:AL102) -> 92815 | ... AX103: =SUM(AX87:AX102) -> 151424 | AZ103: =SUM(AX103/AT103)-1 -> 0.44074747
B105: Cash flows from investing activities:
B106: Purchases of property and equipment | C106: -25139 | D106: -23548 | E106: -22281 | F106: -24640 | G106: -31485 | H106: -32251 | I106: -52535 | K106: -5942 | L106: =-11438-K106 -> -5496 | M106: =-18257-L106-K106 -> -6819 | N106: =SUM(F106-SUM(K106:M106)) -> -6383 | O106: -9786 | P106: =-16614-O106 -> -6828 | Q106: =-23890-P106-O106 -> -7276 | R106: =SUM(G106-SUM(O106:Q106)) -> -7595 | S106: -6289 | T106: =-13177-S106 -> -6888 | U106: =-21232-T106-S106 -> -8055 | V106: =SUM(H106-SUM(S106:U106)) -> -11019 | W106: -12012 | X106: =-25198-W106 -> -13186 | Y106: =-38259-X106-W106 -> -13061 | Z106: =SUM(I106-SUM(W106:Y106)) -> -14276 | AA106: -17197 | AB106: =-39643-AA106 -> -22446 | AC106: =-63596-AB106-AA106 -> -23953 | AE106: =SUM(#REF!) -> #REF! | AF106: =SUM(K106:K106) -> -5942 | AG106: =SUM(K106:L106) -> -11438 | AH106: =SUM(K106:M106) -> -18257 | AI106: =SUM(K106:N106) -> -24640 | AJ106: =SUM(L106:O106) -> -28484 | AK106: =SUM(M106:P106) -> -29816 | AL106: =SUM(N106:Q106) -> -30273 | AM106: =SUM(O106:R106) -> -31485 | AN106: =SUM(P106:S106) -> -27988 | AO106: =SUM(Q106:T106) -> -28048 | AP106: =SUM(R106:U106) -> -28827 | ... AX106: =SUM(Z106:AC106) -> -77872 | AZ106: =SUM(AX106/AT106)-1 -> 0.58025894
B107: Proceeds / (Purchases) of Marketable Securities | C107: =-50158+48507 -> -1651 | D107: =-100315+97825 -> -2490 | E107: =-136576+132906 -> -3670 | F107: =-135196+128294 -> -6902 | G107: =-78874+97822 -> 18948 | H107: =-77858+86672 -> 8814 | I107: =-86679+103428 -> 16749 | K107: =-36426+39248 -> 2822 | L107: =-60609+60667-K107 -> -2764 | M107: =-95106+92126-L107-K107 -> -3038 | N107: =SUM(F107-SUM(K107:M107)) -> -3922 | O107: =-28462+29779 -> 1317 | P107: =-50199+55374-O107 -> 3858 | Q107: =-67253+84087-P107-O107 -> 11659 | R107: =SUM(G107-SUM(O107:Q107)) -> 2114 | S107: =-14227+18327 -> 4100 | T107: =-35589+37049-S107 -> -2640 | U107: =-49422+52642-T107-S107 -> 1760 | V107: =SUM(H107-SUM(S107:U107)) -> 5594 | W107: =-20684+24985 -> 4301 | X107: =-43011+58577-W107 -> 11265 | Y107: =-65034+81779-X107-W107 -> 1179 | Z107: =SUM(I107-SUM(W107:Y107)) -> 4 | AA107: =-18453+20345 -> 1892 | AB107: =-39870+40930-AA107 -> -832 | AC107: =-60834+61301-AB107-AA107 -> -593 | AT107: =SUM(V107:Y107) -> 22339 | AU107: =SUM(W107:Z107) -> 16749 | AV107: =SUM(X107:AA107) -> 14340 | AW107: =SUM(Y107:AB107) -> 2243 | AX107: =SUM(Z107:AC107) -> 471 | AZ107: =SUM(AX107/AT107)-1 -> -0.9789158
B108: Proceeds / (Purchases) of Non-Marketable Securities | C108: =-2073+1752 -> -321 | D108: =-1932+405 -> -1527 | E108: =-7175+1023 -> -6152 | F108: =-2838+934 -> -1904 | G108: =-2531+150 -> -2381 | H108: =-3027+947 -> -2080 | I108: =-5034+882 -> -4152 | K108: =-646+19 -> -627 | L108: =-1412+256 -K108 -> -529 | M108: =-2068+590-L108-K108 -> -322 | N108: =SUM(F108-SUM(K108:M108)) -> -426 | O108: =-776+12 -> -764 | P108: =-1264+125-O108 -> -375 | Q108: =-1628+131-P108-O108 -> -358 | R108: =SUM(G108-SUM(O108:Q108)) -> -884 | S108: =-626+36 -> -590 | T108: =-1513+181-S108 -> -742 | U108: =-2176+743-T108-S108 -> -101 | V108: =SUM(H108-SUM(S108:U108)) -> -647 | W108: =-1206+313 -> -893 | X108: =-2199+605 -W108 -> -701 | Y108: =-3234+732-X108-W108 -> -908 | Z108: =SUM(I108-SUM(W108:Y108)) -> -1650 | AA108: =-958+259 -> -699 | AB108: =-2312+873-AA108 -> -740 | AC108: =-3312+1196-AB108-AA108 -> -677 | AT108: =SUM(V108:Y108) -> -3149 | AU108: =SUM(W108:Z108) -> -4152 | AV108: =SUM(X108:AA108) -> -3958 | AW108: =SUM(Y108:AB108) -> -3997 | AX108: =SUM(Z108:AC108) -> -3766 | AZ108: =SUM(AX108/AT108)-1 -> 0.19593522
B109: Acquisitions, net of cash acquired, and purchases of intangible assets | C109: -1491 | D109: -2515 | E109: -738 | F109: -2618 | G109: -6969 | H109: -495 | I109: -2931 | K109: -1666 | L109: =-1974-K109 -> -308 | M109: =-2233-L109-K109 -> -259 | N109: =SUM(F109-SUM(K109:M109)) -> -385 | O109: -173 | P109: =-1236-O109 -> -1063 | Q109: =-6885-P109-O109 -> -5649 | R109: =SUM(G109-SUM(O109:Q109)) -> -84 | S109: -42 | T109: =-340-S109 -> -298 | U109: =-466-T109-S109 -> -126 | V109: =SUM(H109-SUM(S109:U109)) -> -29 | W109: -61 | X109: =-87-W109 -> -26 | Y109: =-2840-X109-W109 -> -2753 | Z109: =SUM(I109-SUM(W109:Y109)) -> -91 | AA109: -340 | AB109: =-353-AA109 -> -13 | AC109: =-1425-AB109-AA109 -> -1072 | AE109: =SUM(#REF!) -> #REF! | AF109: =SUM(K109:K109) -> -1666 | AG109: =SUM(K109:L109) -> -1974 | AH109: =SUM(K109:M109) -> -2233 | AI109: =SUM(K109:N109) -> -2618 | AJ109: =SUM(L109:O109) -> -1125 | AK109: =SUM(M109:P109) -> -1880 | AL109: =SUM(N109:Q109) -> -7270 | AM109: =SUM(O109:R109) -> -6969 | AN109: =SUM(P109:S109) -> -6838 | AO109: =SUM(Q109:T109) -> -6073 | AP109: =SUM(R109:U109) -> -550 | ... AX109: =SUM(Z109:AC109) -> -1516 | AZ109: =SUM(AX109/AT109)-1 -> -0.47159289
B110: Other investing activities | C110: 98 | D110: 589 | E110: 68 | F110: 541 | G110: 1589 | H110: -1051 | I110: -2667 | K110: 30 | L110: =53 -K110 -> 23 | M110: =441-L110-K110 -> 388 | N110: =SUM(F110-SUM(K110:M110)) -> 100 | O110: 355 | P110: =576-O110 -> 221 | Q110: =1367-P110-O110 -> 791 | R110: =SUM(G110-SUM(O110:Q110)) -> 222 | S110: -125 | T110: =-357-S110 -> -232 | U110: =-985-T110-S110 -> -628 | V110: =SUM(H110-SUM(S110:U110)) -> -66 | W110: 101 | X110: =-32-W110 -> -133 | Y110: =-2500-X110-W110 -> -2468 | Z110: =SUM(I110-SUM(W110:Y110)) -> -167 | AA110: 150 | AB110: =-363-AA110 -> -513 | AC110: =-1845-AB110-AA110 -> -1482 | AE110: =SUM(#REF!) -> #REF! | AF110: =SUM(K110:K110) -> 30 | AG110: =SUM(K110:L110) -> 53 | AH110: =SUM(K110:M110) -> 441 | AI110: =SUM(K110:N110) -> 541 | AJ110: =SUM(L110:O110) -> 866 | AK110: =SUM(M110:P110) -> 1064 | AL110: =SUM(N110:Q110) -> 1467 | AM110: =SUM(O110:R110) -> 1589 | AN110: =SUM(P110:S110) -> 1109 | AO110: =SUM(Q110:T110) -> 656 | AP110: =SUM(R110:U110) -> -763 | ... AX110: =SUM(Z110:AC110) -> -2012 | AZ110: =SUM(AX110/AT110)-1 -> -0.21590023
B111: Net cash used in investing activities | C111: =SUM(C106:C110) -> -28504 | D111: =SUM(D106:D110) -> -29491 | E111: =SUM(E106:E110) -> -32773 | F111: =SUM(F106:F110) -> -35523 | G111: =SUM(G106:G110) -> -20298 | H111: =SUM(H106:H110) -> -27063 | I111: =SUM(I106:I110) -> -45536 | K111: =SUM(K106:K110) -> -5383 | L111: =SUM(L106:L110) -> -9074 | M111: =SUM(M106:M110) -> -10050 | N111: =SUM(N106:N110) -> -11016 | O111: =SUM(O106:O110) -> -9051 | P111: =SUM(P106:P110) -> -4187 | Q111: =SUM(Q106:Q110) -> -833 | R111: =SUM(R106:R110) -> -6227 | ... AC111: =SUM(AC106:AC110) -> -27777 | AE111: =SUM(AE106:AE110) -> #REF! | AF111: =SUM(AF106:AF110) -> -7578 | AG111: =SUM(AG106:AG110) -> -13359 | AH111: =SUM(AH106:AH110) -> -20049 | AI111: =SUM(AI106:AI110) -> -26717 | AJ111: =SUM(AJ106:AJ110) -> -28743 | AK111: =SUM(AK106:AK110) -> -30632 | AL111: =SUM(AL106:AL110) -> -36076 | ... AX111: =SUM(AX106:AX110) -> -84695 | AZ111: =SUM(AX111/AT111)-1 -> 1.3842299
B113: Cash flows from financing activities: | AE113: =SUM(#REF!) -> #REF! | AF113: =SUM(K113:K113) -> 0 | AG113: =SUM(K113:L113) -> 0 | AH113: =SUM(K113:M113) -> 0 | AI113: =SUM(K113:N113) -> 0 | AJ113: =SUM(L113:O113) -> 0 | AK113: =SUM(M113:P113) -> 0 | AL113: =SUM(N113:Q113) -> 0 | AM113: =SUM(O113:R113) -> 0 | AN113: =SUM(P113:S113) -> 0 | AO113: =SUM(Q113:T113) -> 0 | AP113: =SUM(R113:U113) -> 0 | ... AX113: =SUM(Z113:AC113) -> 0 | AZ113: =SUM(AX113/AT113)-1 -> #DIV/0!
B114: Net payments related to stock-based award activities | C114: -4993 | D114: -4765 | E114: -5720 | F114: -10162 | G114: -9300 | H114: -9837 | I114: -12190 | K114: -2184 | L114: =-4637-K114 -> -2453 | M114: =-7239-L114-K114 -> -2602 | N114: =SUM(F114-SUM(K114:M114)) -> -2923 | O114: -2916 | P114: =-5180-O114 -> -2264 | Q114: =-7221-P114-O114 -> -2041 | R114: =SUM(G114-SUM(O114:Q114)) -> -2079 | S114: -1989 | T114: =-4725-S114 -> -2736 | U114: =-7157-T114-S114 -> -2432 | V114: =SUM(H114-SUM(S114:U114)) -> -2680 | W114: -2929 | X114: =-6138-W114 -> -3209 | Y114: =-9141-X114-W114 -> -3003 | Z114: =SUM(I114-SUM(W114:Y114)) -> -3049 | AA114: -3110 | AB114: =-5731-AA114 -> -2621 | AC114: =-9001-AB114-AA114 -> -3270 | AE114: =SUM(#REF!) -> #REF! | AF114: =SUM(K114:K114) -> -2184 | AG114: =SUM(K114:L114) -> -4637 | AH114: =SUM(K114:M114) -> -7239 | AI114: =SUM(K114:N114) -> -10162 | AJ114: =SUM(L114:O114) -> -10894 | AK114: =SUM(M114:P114) -> -10705 | AL114: =SUM(N114:Q114) -> -10144 | AM114: =SUM(O114:R114) -> -9300 | AN114: =SUM(P114:S114) -> -8373 | AO114: =SUM(Q114:T114) -> -8845 | AP114: =SUM(R114:U114) -> -9236 | ... AX114: =SUM(Z114:AC114) -> -12050 | AZ114: =SUM(AX114/AT114)-1 -> 0.019372304
B115: Repurchases of stock | C115: -9075 | D115: -18396 | E115: -31149 | F115: -50274 | G115: -59296 | H115: -61504 | I115: -62222 | K115: -11395 | L115: =-24191-K115 -> -12796 | M115: =-36801-L115-K115 -> -12610 | N115: =SUM(F115-SUM(K115:M115)) -> -13473 | O115: -13300 | P115: =-28497-O115 -> -15197 | Q115: =-43889-P115-O115 -> -15392 | R115: =SUM(G115-SUM(O115:Q115)) -> -15407 | S115: -14557 | T115: =-29526-S115 -> -14969 | U115: =-45313-T115-S115 -> -15787 | V115: =SUM(H115-SUM(S115:U115)) -> -16191 | W115: -15696 | X115: =-31380-W115 -> -15684 | Y115: =-46671-X115-W115 -> -15291 | Z115: =SUM(I115-SUM(W115:Y115)) -> -15551 | AA115: -15068 | AB115: =-28706-AA115 -> -13638 | AC115: =-40210-AB115-AA115 -> -11504 | AE115: =SUM(#REF!) -> #REF! | AF115: =SUM(K115:K115) -> -11395 | AG115: =SUM(K115:L115) -> -24191 | AH115: =SUM(K115:M115) -> -36801 | AI115: =SUM(K115:N115) -> -50274 | AJ115: =SUM(L115:O115) -> -52179 | AK115: =SUM(M115:P115) -> -54580 | AL115: =SUM(N115:Q115) -> -57362 | AM115: =SUM(O115:R115) -> -59296 | AN115: =SUM(P115:S115) -> -60553 | AO115: =SUM(Q115:T115) -> -60325 | AP115: =SUM(R115:U115) -> -60720 | ... AX115: =SUM(Z115:AC115) -> -55761 | AZ115: =SUM(AX115/AT115)-1 -> -0.11296173
B116: Dividend payments | C116: 0 | D116: 0 | E116: 0 | F116: 0 | G116: 0 | H116: 0 | I116: -7363 | K116: 0 | L116: 0 | M116: 0 | N116: =SUM(F116-SUM(K116:M116)) -> 0 | O116: 0 | P116: 0 | Q116: 0 | R116: =SUM(G116-SUM(O116:Q116)) -> 0 | S116: 0 | T116: 0 | U116: 0 | V116: =SUM(H116-SUM(S116:U116)) -> 0 | W116: 0 | X116: =-2466-W116 -> -2466 | Y116: =-4921-X116-W116 -> -2455 | Z116: =SUM(I116-SUM(W116:Y116)) -> -2442 | AA116: -2434 | AB116: =-4977-AA116 -> -2543 | AC116: =-7513-AB116-AA116 -> -2536 | AE116: =SUM(#REF!) -> #REF! | AF116: =SUM(K116:K116) -> 0 | AG116: =SUM(K116:L116) -> 0 | AH116: =SUM(K116:M116) -> 0 | AI116: =SUM(K116:N116) -> 0 | AJ116: =SUM(L116:O116) -> 0 | AK116: =SUM(M116:P116) -> 0 | AL116: =SUM(N116:Q116) -> 0 | AM116: =SUM(O116:R116) -> 0 | AN116: =SUM(P116:S116) -> 0 | AO116: =SUM(Q116:T116) -> 0 | AP116: =SUM(R116:U116) -> 0 | ... AX116: =SUM(Z116:AC116) -> -9955 | AZ116: =SUM(AX116/AT116)-1 -> 1.0229628
B117: Issuance / (Repayment) of Debt, net | C117: =6766-6827 -> -61 | D117: =317-585 -> -268 | E117: =11761-2100 -> 9661 | F117: =20199-21435 -> -1236 | G117: =52872-54068 -> -1196 | H117: =10790-11550 -> -760 | I117: =13589-12701 -> 888 | K117: =-937+900 -> -37 | L117: =-8678+7599-K117 -> -1042 | M117: =-15070+13949-L117-K117 -> -42 | N117: =SUM(F117-SUM(K117:M117)) -> -115 | O117: =-16420+16422 -> 2 | P117: =-29582+29228-O117 -> -356 | Q117: =-45350+44322-P117-O117 -> -674 | R117: =SUM(G117-SUM(O117:Q117)) -> -168 | S117: =-6952+6927 -> -25 | T117: =-8207+8050-S117 -> -132 | U117: =-9621+9298-T117-S117 -> -166 | V117: =SUM(H117-SUM(S117:U117)) -> -437 | W117: =-3079+1982 -> -1097 | X117: =-5502+4875-W117 -> 470 | Y117: =-8951+8694-X117-W117 -> 370 | Z117: =SUM(I117-SUM(W117:Y117)) -> 1145 | AA117: =-4521+4532 -> 11 | AB117: =-18397+31378-AA117 -> 12970 | AC117: =-26094+38002-AB117-AA117 -> -1073 | AT117: =SUM(V117:Y117) -> -694 | AU117: =SUM(W117:Z117) -> 888 | AV117: =SUM(X117:AA117) -> 1996 | AW117: =SUM(Y117:AB117) -> 14496 | AX117: =SUM(Z117:AC117) -> 13053 | AZ117: =SUM(AX117/AT117)-1 -> -19.808357
B118: Proceeds from sale of interest in consolidated entities, net | C118: 950 | D118: 220 | E118: 2800 | F118: 310 | G118: 35 | H118: 8 | I118: 1154 | K118: 10 | L118: =310 -K118 -> 300 | M118: =310-L118-K118 -> 0 | N118: =SUM(F118-SUM(K118:M118)) -> 0 | O118: 0 | P118: 0 | Q118: =10-P118-O118 -> 10 | R118: =SUM(G118-SUM(O118:Q118)) -> 25 | S118: 3 | T118: =5-S118 -> 2 | U118: =8-T118-S118 -> 3 | V118: =SUM(H118-SUM(S118:U118)) -> 0 | W118: 8 | X118: =8-W118 -> 0 | Y118: =293-X118-W118 -> 285 | Z118: =SUM(I118-SUM(W118:Y118)) -> 861 | AA118: 400 | AB118: =400-AA118 -> 0 | AC118: =400-AB118-AA118 -> 0 | AE118: =SUM(#REF!) -> #REF! | AF118: =SUM(K118:K118) -> 10 | AG118: =SUM(K118:L118) -> 310 | AH118: =SUM(K118:M118) -> 310 | AI118: =SUM(K118:N118) -> 310 | AJ118: =SUM(L118:O118) -> 300 | AK118: =SUM(M118:P118) -> 0 | AL118: =SUM(N118:Q118) -> 10 | AM118: =SUM(O118:R118) -> 35 | AN118: =SUM(P118:S118) -> 38 | AO118: =SUM(Q118:T118) -> 40 | AP118: =SUM(R118:U118) -> 33 | ... AX118: =SUM(Z118:AC118) -> 1261 | AZ118: =SUM(AX118/AT118)-1 -> 3.3037543
B119: Net cash provided by financing activities | C119: =SUM(C114:C118) -> -13179 | D119: =SUM(D114:D118) -> -23209 | E119: =SUM(E114:E118) -> -24408 | F119: =SUM(F114:F118) -> -61362 | G119: =SUM(G114:G118) -> -69757 | H119: =SUM(H114:H118) -> -72093 | I119: =SUM(I114:I118) -> -79733 | K119: =SUM(K114:K118) -> -13606 | L119: =SUM(L114:L118) -> -15991 | M119: =SUM(M114:M118) -> -15254 | N119: =SUM(N114:N118) -> -16511 | O119: =SUM(O114:O118) -> -16214 | P119: =SUM(P114:P118) -> -17817 | Q119: =SUM(Q114:Q118) -> -18097 | R119: =SUM(R114:R118) -> -17629 | ... AC119: =SUM(AC114:AC118) -> -18383 | AE119: =SUM(AE114:AE118) -> #REF! | AF119: =SUM(AF114:AF118) -> -13569 | AG119: =SUM(AG114:AG118) -> -28518 | AH119: =SUM(AH114:AH118) -> -43730 | AI119: =SUM(AI114:AI118) -> -60126 | AJ119: =SUM(AJ114:AJ118) -> -62773 | AK119: =SUM(AK114:AK118) -> -65285 | AL119: =SUM(AL114:AL118) -> -67496 | ... AX119: =SUM(AX114:AX118) -> -63452 | AZ119: =SUM(AX119/AT119)-1 -> -0.20689957
B122: Unrestricted Cash BOP | C122: 10715 | D122: =C128 -> 16701 | E122: =D128 -> 18498 | F122: =E128 -> 26465 | G122: =F128 -> 20945 | H122: =G128 -> 21879 | I122: =H128 -> 24048 | K122: =E128 -> 26465 | L122: =K128 -> 26622 | M122: =L128 -> 23630 | N122: =M128 -> 23719 | O122: =N128 -> 20945 | P122: =O128 -> 20886 | Q122: =P128 -> 17936 | R122: =Q128 -> 21984 | S122: =R128 -> 21879 | ... AC122: =AB128 -> 21036 | AE122: =#REF! -> #REF! | AF122: =#REF! -> #REF! | AG122: =#REF! -> #REF! | AH122: =#REF! -> #REF! | AI122: =#REF! -> #REF! | AJ122: =K128 -> 26622 | AK122: =L128 -> 23630 | AL122: =M128 -> 23719 | AM122: =N128 -> 20945 | AN122: =O128 -> 20886 | AO122: =P128 -> 17936 | AP122: =Q128 -> 21984 | AQ122: =R128 -> 21879 | ... AX122: =Y128 -> 19959
B123: BOP FX Adjustment | C123: 0 | D123: 0 | E123: 0 | F123: 0 | G123: 0 | H123: 0 | I123: 0 | K123: 0 | L123: 0 | M123: 0 | N123: =SUM(F123-SUM(K123:M123)) -> 0 | O123: 0 | P123: 0 | Q123: 0 | R123: =SUM(G123-SUM(O123:Q123)) -> 0 | T123: 0 | U123: 0 | V123: =SUM(H123-SUM(S123:U123)) -> 0 | W123: 0 | X123: 0 | Y123: 0 | Z123: =SUM(I123-SUM(W123:Y123)) -> 0 | AA123: 0 | AB123: 0 | AC123: 0 | AE123: =SUM(#REF!) -> #REF! | AF123: =SUM(K123:K123) -> 0 | AG123: =SUM(K123:L123) -> 0 | AH123: =SUM(K123:M123) -> 0 | AI123: =SUM(K123:N123) -> 0 | AJ123: =SUM(L123:O123) -> 0 | AK123: =SUM(M123:P123) -> 0 | AL123: =SUM(N123:Q123) -> 0 | AM123: =SUM(O123:R123) -> 0 | AN123: =SUM(P123:S123) -> 0 | AO123: =SUM(Q123:T123) -> 0 | AP123: =SUM(R123:U123) -> 0 | ... AX123: =SUM(Z123:AC123) -> 0
...

Sheet EPS
B2: Alphabet Inc. (NASDAQ: GOOG)
B3: EPS Build-Up
B4: ($ in Bns, Including Shares)
B6: Stock Split Converter | C6: 1
B7: Stock Split Amount | C7: 20
B8: Stock Split End Period | C8: 2Q22
B10: Net Income Per Share | G10: FYE | O10: Quarterly | Y10: Quarterly | AO10: LTM | AP10: LTM
B11: Fiscal Period | C11: 2018 | D11: 2019 | E11: 2020 | F11: 2021 | G11: 2022 | H11: 2023 | I11: 2024 | K11: 1Q21 | L11: 2Q21 | M11: 3Q21 | N11: 4Q21 | O11: 1Q22 | P11: 2Q22 | Q11: 3Q22 | R11: 4Q22 | S11: 1Q23 | T11: 2Q23 | U11: 3Q23 | V11: 4Q23 | W11: 1Q24 | X11: 2Q24 | Y11: 3Q24 | Z11: 4Q24 | AA11: 1Q25 | AB11: 2Q25 | AC11: 3Q25 | AE11: =N11 -> 4Q21 | AF11: =O11 -> 1Q22 | AG11: =P11 -> 2Q22 | AH11: =Q11 -> 3Q22 | AI11: =R11 -> 4Q22 | AJ11: =S11 -> 1Q23 | AK11: =T11 -> 2Q23 | AL11: =U11 -> 3Q23 | ... AT11: =AC11 -> 3Q25
B12: Fiscal Period End Date | C12: 43465 | D12: 43830 | E12: 44196 | F12: 44561 | G12: 44926 | H12: 45291 | I12: 45657 | K12: 44289 | L12: 44380 | M12: 44471 | N12: 44561 | O12: 44653 | P12: 44744 | Q12: 44835 | R12: 44926 | S12: 45017 | T12: 45108 | U12: 45199 | V12: 45291 | W12: 45381 | X12: 45472 | Y12: 45563 | Z12: 45657 | AA12: 45745 | AB12: 45836 | AC12: 45927 | AE12: =N12 -> 44561 | AF12: =O12 -> 44653 | AG12: =P12 -> 44744 | AH12: =Q12 -> 44835 | AI12: =R12 -> 44926 | AJ12: =S12 -> 45017 | AK12: =T12 -> 45108 | AL12: =U12 -> 45199 | ... AT12: =AC12 -> 45927
A14: X | B14: Consolidated Basic EPS
B16: Consolidated Allocation of undistributed earnings | C16: =C29+C35+C41 -> 30736 | D16: =D29+D35+D41 -> 34343 | E16: =E29+E35+E41 -> 40269 | F16: =F29+F35+F41 -> 76033 | G16: =G29+G35+G41 -> 59972 | H16: =H29+H35+H41 -> 73795 | I16: =I29+I35+I41 -> 100118 | K16: =K29+K35+K41 -> 17930 | L16: =L29+L35+L41 -> 18525 | M16: =M29+M35+M41 -> 18936 | N16: =N29+N35+N41 -> 20642 | O16: =O29+O35+O41 -> 16436 | P16: =P29+P35+P41 -> 16002 | Q16: =Q29+Q35+Q41 -> 13910 | R16: =R29+R35+R41 -> 13624 | ... AC16: =AC29+AC35+AC41 -> 34979 | AE16: =AE29+AE35+AE41 -> 76033 | AF16: =AF29+AF35+AF41 -> 74539 | AG16: =AG29+AG35+AG41 -> 72016 | AH16: =AH29+AH35+AH41 -> 66990 | AI16: =AI29+AI35+AI41 -> 59972 | AJ16: =AJ29+AJ35+AJ41 -> 58587 | AK16: =AK29+AK35+AK41 -> 60953 | AL16: =AL29+AL35+AL41 -> 66732 | ... AT16: =AT29+AT35+AT41 -> 124251
B17: Consolidated Basic Shares | C17: =IF($C$6=1,C30+C35+C41,C31+C37+C43) -> 23506.96 | D17: =IF($C$6=1,D30+D35+D41,D31+D37+D43) -> 25485.04 | E17: =IF($C$6=1,E30+E35+E41,E31+E37+E43) -> 28532.3 | F17: =IF($C$6=1,F30+F36+F42,F31+F37+F43) -> 13353 | G17: =IF($C$6=1,G30+G36+G42,G31+G37+G43) -> 13063 | H17: =IF($C$6=1,H30+H36+H42,H31+H37+H43) -> 12630 | I17: =IF($C$6=1,I30+I36+I42,I31+I37+I43) -> 12319 | K17: =IF($C$6=1,K30+K36+K42,K31+K37+K43) -> 13464.4 | L17: =IF($C$6=1,L30+L36+L42,L31+L37+L43) -> 13379.16 | M17: =IF($C$6=1,M30+M36+M42,M31+M37+M43) -> 13315.16 | N17: =IF($C$6=1,N30+N36+N42,N31+N37+N43) -> 13353 | O17: =IF($C$6=1,O30+O36+O42,O31+O37+O43) -> 13203.42 | P17: =IF($C$6=1,P30+P36+P42,P31+P37+P43) -> 13133 | Q17: =IF($C$6=1,Q30+Q36+Q42,Q31+Q37+Q43) -> 13018 | R17: =IF($C$6=1,R30+R36+R42,R31+R37+R43) -> 13063 | ... AC17: =IF($C$6=1,AC30+AC36+AC42,AC31+AC37+AC43) -> 12086 | AE17: =IF($C$6=1,AE30+AE36+AE42,AE31+AE37+AE43) -> 13353 | AF17: =IF($C$6=1,AF30+AF36+AF42,AF31+AF37+AF43) -> 13203.42 | AG17: =IF($C$6=1,AG30+AG36+AG42,AG31+AG37+AG43) -> 13133 | AH17: =IF($C$6=1,AH30+AH36+AH42,AH31+AH37+AH43) -> 13018 | AI17: =IF($C$6=1,AI30+AI36+AI42,AI31+AI37+AI43) -> 13063 | AJ17: =IF($C$6=1,AJ30+AJ36+AJ42,AJ31+AJ37+AJ43) -> 12781 | AK17: =IF($C$6=1,AK30+AK36+AK42,AK31+AK37+AK43) -> 12668 | AL17: =IF($C$6=1,AL30+AL36+AL42,AL31+AL37+AL43) -> 12581 | ... AT17: =IF($C$6=1,AT30+AT36+AT42,AT31+AT37+AT43) -> 12086
B18: Consolidated Basic EPS | C18: =C16/C17 -> 1.3075276 | D18: =D16/D17 -> 1.3475749 | E18: =E16/E17 -> 1.4113478 | F18: =F16/F17 -> 5.6940762 | G18: =G16/G17 -> 4.5909822 | H18: =H16/H17 -> 5.8428345 | I18: =I16/I17 -> 8.1271207 | K18: =K16/K17 -> 1.3316598 | L18: =L16/L17 -> 1.3846161 | M18: =M16/M17 -> 1.4221384 | N18: =N16/N17 -> 1.5458698 | O18: =O16/O17 -> 1.244829 | P18: =P16/P17 -> 1.2184573 | Q18: =Q16/Q17 -> 1.0685205 | R18: =R16/R17 -> 1.0429457 | ... AC18: =AC16/AC17 -> 2.8941751 | AE18: =AE16/AE17 -> 5.6940762 | AF18: =AF16/AF17 -> 5.6454313 | AG18: =AG16/AG17 -> 5.483591 | AH18: =AH16/AH17 -> 5.1459518 | AI18: =AI16/AI17 -> 4.5909822 | AJ18: =AJ16/AJ17 -> 4.5839136 | AK18: =AK16/AK17 -> 4.8115725 | AL18: =AL16/AL17 -> 5.3041889 | ... AT18: =AT16/AT17 -> 10.280573
A20: X | B20: Consolidated Fully Diluted EPS
B22: Consolidated Allocation of undistributed earnings | C22: =+C49+C58+C64 -> 32784 | D22: =+D49+D58+D64 -> 36630 | E22: =+E49+E58+E64 -> 42976 | F22: =+F49+F58+F64 -> 81130 | G22: =+G49+G58+G64 -> 64014 | H22: =+H49+H58+H64 -> 78882 | I22: =+I49+I58+I64 -> 107090 | K22: =+K49+K58+K64 -> 19135 | L22: =+L49+L58+L64 -> 19771 | M22: =+M49+M58+M64 -> 20207 | N22: =+N49+N58+N64 -> 22017 | O22: =+O49+O58+O64 -> 17533 | P22: =+P49+P58+P64 -> 17074 | Q22: =+Q49+Q58+Q64 -> 14850 | R22: =+R49+R58+R64 -> 14557 | ... AC22: =+AC49+AC58+AC64 -> 37402 | AE22: =+AE49+AE58+AE64 -> 81130 | AF22: =+AF49+AF58+AF64 -> 79528 | AG22: =+AG49+AG58+AG64 -> 76831 | AH22: =+AH49+AH58+AH64 -> 71474 | AI22: =+AI49+AI58+AI64 -> 64014 | AJ22: =+AJ49+AJ58+AJ64 -> 62568 | AK22: =+AK49+AK58+AK64 -> 65127 | AL22: =+AL49+AL58+AL64 -> 71323 | ... AT22: =+AT49+AT58+AT64 -> 132917
B23: Consolidated Fully Diluted Shares | C23: =+C50+C59+C65 -> 15002.98 | D23: =+D50+D59+D65 -> 14901.66 | E23: =+E50+E59+E65 -> 14664.2 | F23: =+F50+F59+F65 -> 14462.08 | G23: =+G50+G59+G65 -> 15870 | H23: =+H50+H59+H65 -> 15347 | I23: =+I50+I59+I65 -> 15745 | K23: =+K50+K59+K65 -> 14558.22 | L23: =+L50+L59+L65 -> 14506.08 | M23: =+M50+M59+M65 -> 14438.46 | N23: =+N50+N59+N65 -> 14458.2 | O23: =+O50+O59+O65 -> 14241.72 | P23: =+P50+P59+P65 -> 14126 | Q23: =+Q50+Q59+Q65 -> 13982 | R23: =+R50+R59+R65 -> 14046 | ... AC23: =+AC50+AC59+AC65 -> 13048 | AE23: =+AE50+AE59+AE65 -> 14457.953 | AF23: =+AF50+AF59+AF65 -> 14241.625 | AG23: =+AG50+AG59+AG65 -> 14126 | AH23: =+AH50+AH59+AH65 -> 13982 | AI23: =+AI50+AI59+AI65 -> 14046 | AJ23: =+AJ50+AJ59+AJ65 -> 13706 | AK23: =+AK50+AK59+AK65 -> 13616 | AL23: =+AL50+AL59+AL65 -> 13571 | ... AT23: =+AT50+AT59+AT65 -> 13048
B24: Consolidated Basic EPS | C24: =C22/C23 -> 2.1851659 | D24: =D22/D23 -> 2.4581154 | E24: =E22/E23 -> 2.9306747 | F24: =F22/F23 -> 5.6098431 | G24: =G22/G23 -> 4.0336484 | H24: =H22/H23 -> 5.139897 | I24: =I22/I23 -> 6.8015243 | K24: =K22/K23 -> 1.3143777 | L24: =L22/L23 -> 1.3629457 | M24: =M22/M23 -> 1.399526 | N24: =N22/N23 -> 1.5228037 | O24: =O22/O23 -> 1.2311013 | P24: =P22/P23 -> 1.2086932 | Q24: =Q22/Q23 -> 1.0620798 | R24: =R22/R23 -> 1.0363805 | ... AC24: =AC22/AC23 -> 2.8664929 | AE24: =AE22/AE23 -> 5.6114444 | AF24: =AF22/AF23 -> 5.5841942 | AG24: =AG22/AG23 -> 5.4389778 | AH24: =AH22/AH23 -> 5.1118581 | AI24: =AI22/AI23 -> 4.5574541 | AJ24: =AJ22/AJ23 -> 4.565008 | AK24: =AK22/AK23 -> 4.7831228 | AL24: =AL22/AL23 -> 5.2555449 | ... AT24: =AT22/AT23 -> 10.186772
A26: X | B26: Basic EPS Per Share Class
B28: Class A
B29: Allocation of undistributed earnings | C29: 13200 | D29: 14846 | E29: 17733 | F29: 34200 | G29: 27518 | H29: 34601 | I29: 47594 | K29: 8011 | L29: 8321 | M29: 8548 | N29: =SUM(F29-SUM(K29:M29)) -> 9320 | O29: 7481 | P29: 7329 | Q29: 6393 | R29: =SUM(G29-SUM(O29:Q29)) -> 6315 | S29: 7006 | T29: 8600 | U29: 9271 | V29: =SUM(H29-SUM(S29:U29)) -> 9724 | W29: 11213 | X29: 11219 | Y29: 12521 | Z29: =SUM(I29-SUM(W29:Y29)) -> 12641 | AA29: 16534 | AB29: 13536 | AC29: 16839 | AE29: =SUM(K29:N29) -> 34200 | AF29: =SUM(L29:O29) -> 33670 | AG29: =SUM(M29:P29) -> 32678 | AH29: =SUM(N29:Q29) -> 30523 | AI29: =SUM(O29:R29) -> 27518 | AJ29: =SUM(P29:S29) -> 27043 | AK29: =SUM(Q29:T29) -> 28314 | AL29: =SUM(R29:U29) -> 31192 | ... AT29: =SUM(Z29:AC29) -> 59550
B30: Stock Split Adjusted Basic Shares | C30: =IF($C$6=1,C31*20,C31) -> 5970.96 | D30: =IF($C$6=1,D31*20,D31) -> 5988.04 | E30: =IF($C$6=1,E31*20,E31) -> 5996.3 | F30: =IF($C$6=1,F31*20,F31) -> 6006.2 | G30: =G31 -> 5994 | H30: =H31 -> 5922 | I30: =I31 -> 5855 | K30: =IF($C$6=1,K31*20,K31) -> 6016 | L30: =IF($C$6=1,L31*20,L31) -> 6009.7 | M30: =IF($C$6=1,M31*20,M31) -> 6010.38 | N30: =IF($C$6=1,N31*20,N31) -> 6006.2 | O30: =IF($C$6=1,O31*20,O31) -> 6009.56 | P30: =P31 -> 6015 | Q30: =Q31 -> 5983 | R30: =R31 -> 5994 | S30: =S31 -> 5949 | T30: =T31 -> 5931 | U30: =U31 -> 5924 | V30: =V31 -> 5922 | W30: =W31 -> 5883 | ... AC30: =AC31 -> 5818 | AE30: =N30 -> 6006.2 | AF30: =O30 -> 6009.56 | AG30: =P30 -> 6015 | AH30: =Q30 -> 5983 | AI30: =R30 -> 5994 | AJ30: =S30 -> 5949 | AK30: =T30 -> 5931 | AL30: =U30 -> 5924 | ... AT30: =AC30 -> 5818
B31: Unadjusted Basic Shares | C31: 298.548 | D31: 299.402 | E31: 299.815 | F31: 300.31 | G31: 5994 | H31: 5922 | I31: 5855 | K31: 300.8 | L31: 300.485 | M31: 300.519 | N31: =F31 -> 300.31 | O31: 300.478 | P31: 6015 | Q31: 5983 | R31: =G31 -> 5994 | S31: 5949 | T31: 5931 | U31: 5924 | V31: =H31 -> 5922 | W31: 5883 | X31: 5862 | Y31: 5850 | Z31: =I31 -> 5855 | AA31: 5831 | AB31: 5819 | AC31: 5818 | AE31: =N31 -> 300.31 | AF31: =O31 -> 300.478 | AG31: =P31 -> 6015 | AH31: =Q31 -> 5983 | AI31: =R31 -> 5994 | AJ31: =S31 -> 5949 | AK31: =T31 -> 5931 | AL31: =U31 -> 5924 | ... AT31: =AC31 -> 5818
B32: Class A Basic EPS | C32: =IF($C$6=1, C29/C30,C29/C31) -> 2.2106998 | D32: =IF($C$6=1, D29/D30,D29/D31) -> 2.4792754 | E32: =IF($C$6=1, E29/E30,E29/E31) -> 2.9573237 | F32: =IF($C$6=1, F29/F30,F29/F31) -> 5.6941161 | G32: =IF($C$6=1, G29/G30,G29/G31) -> 4.5909243 | H32: =IF($C$6=1, H29/H30,H29/H31) -> 5.8427896 | I32: =IF($C$6=1, I29/I30,I29/I31) -> 8.1287788 | K32: =IF($C$6=1, K29/K30,K29/K31) -> 1.3316157 | L32: =IF($C$6=1, L29/L30,L29/L31) -> 1.3845949 | M32: =IF($C$6=1, M29/M30,M29/M31) -> 1.4222062 | N32: =IF($C$6=1, N29/N30,N29/N31) -> 1.5517299 | O32: =IF($C$6=1, O29/O30,O29/O31) -> 1.2448499 | P32: =IF($C$6=1, P29/P30,P29/P31) -> 1.2184539 | Q32: =IF($C$6=1, Q29/Q30,Q29/Q31) -> 1.0685275 | R32: =IF($C$6=1, R29/R30,R29/R31) -> 1.0535536 | ... AC32: =IF($C$6=1, AC29/AC30,AC29/AC31) -> 2.8942936 | AE32: =IF($C$6=1, AE29/AE30,AE29/AE31) -> 5.6941161 | AF32: =IF($C$6=1, AF29/AF30,AF29/AF31) -> 5.6027396 | AG32: =IF($C$6=1, AG29/AG30,AG29/AG31) -> 5.4327515 | AH32: =IF($C$6=1, AH29/AH30,AH29/AH31) -> 5.1016213 | AI32: =IF($C$6=1, AI29/AI30,AI29/AI31) -> 4.5909243 | AJ32: =IF($C$6=1, AJ29/AJ30,AJ29/AJ31) -> 4.545806 | AK32: =IF($C$6=1, AK29/AK30,AK29/AK31) -> 4.7738998 | AL32: =IF($C$6=1, AL29/AL30,AL29/AL31) -> 5.2653612 | ... AT32: =IF($C$6=1, AT29/AT30,AT29/AT31) -> 10.235476
B34: Class B
B35: Allocation of undistributed earnings | C35: 2072 | D35: 2307 | E35: 2732 | F35: 5174 | G35: 4072 | H35: 5124 | I35: 7039 | K35: 1221 | L35: 1265 | M35: 1291 | N35: =SUM(F35-SUM(K35:M35)) -> 1397 | O35: 1109 | P35: 1081 | Q35: 946 | R35: =SUM(G35-SUM(O35:Q35)) -> 936 | S35: 1040 | T35: 1275 | U35: 1369 | V35: =SUM(H35-SUM(S35:U35)) -> 1440 | W35: 1656 | X35: 1657 | Y35: 1851 | Z35: =SUM(I35-SUM(W35:Y35)) -> 1875 | AA35: 2435 | AB35: 1981 | AC35: 2445 | AE35: =SUM(K35:N35) -> 5174 | AF35: =SUM(L35:O35) -> 5062 | AG35: =SUM(M35:P35) -> 4878 | AH35: =SUM(N35:Q35) -> 4533 | AI35: =SUM(O35:R35) -> 4072 | AJ35: =SUM(P35:S35) -> 4003 | AK35: =SUM(Q35:T35) -> 4197 | AL35: =SUM(R35:U35) -> 4620 | ... AT35: =SUM(Z35:AC35) -> 8736
B36: Stock Split Adjusted Basic Shares | C36: =IF($C$6=1,C37*20,C37) -> 937.28 | D36: =IF($C$6=1,D37*20,D37) -> 930.54 | E36: =IF($C$6=1,E37*20,E37) -> 923.64 | F36: =IF($C$6=1,F37*20,F37) -> 908.6 | G36: =G37 -> 887 | H36: =H37 -> 877 | I36: =I37 -> 866 | K36: =IF($C$6=1,K37*20,K37) -> 916.8 | L36: =IF($C$6=1,L37*20,L37) -> 913.84 | M36: =IF($C$6=1,M37*20,M37) -> 908.08 | N36: =IF($C$6=1,N37*20,N37) -> 908.6 | O36: =IF($C$6=1,O37*20,O37) -> 890.7 | P36: =P37 -> 887 | Q36: =Q37 -> 885 | R36: =R37 -> 887 | S36: =S37 -> 883 | T36: =T37 -> 879 | U36: =U37 -> 875 | V36: =V37 -> 877 | W36: =W37 -> 869 | ... AC36: =AC37 -> 845 | AE36: =N36 -> 908.6 | AF36: =O36 -> 890.7 | AG36: =P36 -> 887 | AH36: =Q36 -> 885 | AI36: =R36 -> 887 | AJ36: =S36 -> 883 | AK36: =T36 -> 879 | AL36: =U36 -> 875 | ... AT36: =AC36 -> 845
B37: Unadjusted Basic Shares | C37: 46.864 | D37: 46.527 | E37: 46.182 | F37: 45.43 | G37: 887 | H37: 877 | I37: 866 | K37: 45.84 | L37: 45.692 | M37: 45.404 | N37: =F37 -> 45.43 | O37: 44.535 | P37: 887 | Q37: 885 | R37: =G37 -> 887 | S37: 883 | T37: 879 | U37: 875 | V37: =H37 -> 877 | W37: 869 | X37: 866 | Y37: 865 | Z37: =I37 -> 866 | AA37: 859 | AB37: 852 | AC37: 845 | AE37: =N37 -> 45.43 | AF37: =O37 -> 44.535 | AG37: =P37 -> 887 | AH37: =Q37 -> 885 | AI37: =R37 -> 887 | AJ37: =S37 -> 883 | AK37: =T37 -> 879 | AL37: =U37 -> 875 | ... AT37: =AC37 -> 845
B38: Class B Basic EPS | C38: =IF($C$6=1, C35/C36,C35/C37) -> 2.2106521 | D38: =IF($C$6=1, D35/D36,D35/D37) -> 2.4792056 | E38: =IF($C$6=1, E35/E36,E35/E37) -> 2.9578624 | F38: =IF($C$6=1, F35/F36,F35/F37) -> 5.694475 | G38: =IF($C$6=1, G35/G36,G35/G37) -> 4.5907554 | H38: =IF($C$6=1, H35/H36,H35/H37) -> 5.8426454 | I38: =IF($C$6=1, I35/I36,I35/I37) -> 8.1281755 | K38: =IF($C$6=1, K35/K36,K35/K37) -> 1.3318063 | L38: =IF($C$6=1, L35/L36,L35/L37) -> 1.3842686 | M38: =IF($C$6=1, M35/M36,M35/M37) -> 1.4216809 | N38: =IF($C$6=1, N35/N36,N35/N37) -> 1.5375303 | O38: =IF($C$6=1, O35/O36,O35/O37) -> 1.2450881 | P38: =IF($C$6=1, P35/P36,P35/P37) -> 1.2187148 | Q38: =IF($C$6=1, Q35/Q36,Q35/Q37) -> 1.0689266 | R38: =IF($C$6=1, R35/R36,R35/R37) -> 1.0552424 | ... AC38: =IF($C$6=1, AC35/AC36,AC35/AC37) -> 2.8934911 | AE38: =IF($C$6=1, AE35/AE36,AE35/AE37) -> 5.694475 | AF38: =IF($C$6=1, AF35/AF36,AF35/AF37) -> 5.6831705 | AG38: =IF($C$6=1, AG35/AG36,AG35/AG37) -> 5.4994363 | AH38: =IF($C$6=1, AH35/AH36,AH35/AH37) -> 5.1220339 | AI38: =IF($C$6=1, AI35/AI36,AI35/AI37) -> 4.5907554 | AJ38: =IF($C$6=1, AJ35/AJ36,AJ35/AJ37) -> 4.5334088 | AK38: =IF($C$6=1, AK35/AK36,AK35/AK37) -> 4.774744 | AL38: =IF($C$6=1, AL35/AL36,AL35/AL37) -> 5.28 | ... AT38: =IF($C$6=1, AT35/AT36,AT35/AT37) -> 10.338462
B40: Class C
B41: Allocation of undistributed earnings | C41: 15464 | D41: 17190 | E41: 19804 | F41: 36659 | G41: 28382 | H41: 34070 | I41: 45485 | K41: 8698 | L41: 8939 | M41: 9097 | N41: =SUM(F41-SUM(K41:M41)) -> 9925 | O41: 7846 | P41: 7592 | Q41: 6571 | R41: =SUM(G41-SUM(O41:Q41)) -> 6373 | S41: 7005 | T41: 8493 | U41: 9049 | V41: =SUM(H41-SUM(S41:U41)) -> 9523 | W41: 10793 | X41: 10743 | Y41: 11929 | Z41: =SUM(I41-SUM(W41:Y41)) -> 12020 | AA41: 15571 | AB41: 12679 | AC41: 15695 | AE41: =SUM(K41:N41) -> 36659 | AF41: =SUM(L41:O41) -> 35807 | AG41: =SUM(M41:P41) -> 34460 | AH41: =SUM(N41:Q41) -> 31934 | AI41: =SUM(O41:R41) -> 28382 | AJ41: =SUM(P41:S41) -> 27541 | AK41: =SUM(Q41:T41) -> 28442 | AL41: =SUM(R41:U41) -> 30920 | ... AT41: =SUM(Z41:AC41) -> 55965
B42: Stock Split Adjusted Basic Shares | C42: =IF($C$6=1,C43*20,C43) -> 6994.56 | D42: =IF($C$6=1,D43*20,D43) -> 6933.34 | E42: =IF($C$6=1,E43*20,E43) -> 6696.38 | F42: =IF($C$6=1,F43*20,F43) -> 6438.2 | G42: =G43 -> 6182 | H42: =H43 -> 5831 | I42: =I43 -> 5598 | K42: =IF($C$6=1,K43*20,K43) -> 6531.6 | L42: =IF($C$6=1,L43*20,L43) -> 6455.62 | M42: =IF($C$6=1,M43*20,M43) -> 6396.7 | N42: =IF($C$6=1,N43*20,N43) -> 6438.2 | O42: =IF($C$6=1,O43*20,O43) -> 6303.16 | P42: =P43 -> 6231 | Q42: =Q43 -> 6150 | R42: =R43 -> 6182 | S42: =S43 -> 5949 | T42: =T43 -> 5858 | U42: =U43 -> 5782 | V42: =V43 -> 5831 | W42: =W43 -> 5663 | ... AC42: =AC43 -> 5423 | AE42: =N42 -> 6438.2 | AF42: =O42 -> 6303.16 | AG42: =P42 -> 6231 | AH42: =Q42 -> 6150 | AI42: =R42 -> 6182 | AJ42: =S42 -> 5949 | AK42: =T42 -> 5858 | AL42: =U42 -> 5782 | ... AT42: =AC42 -> 5423
B43: Unadjusted Basic Shares | C43: 349.728 | D43: 346.667 | E43: 334.819 | F43: 321.91 | G43: 6182 | H43: 5831 | I43: 5598 | K43: 326.58 | L43: 322.781 | M43: 319.835 | N43: =F43 -> 321.91 | O43: 315.158 | P43: 6231 | Q43: 6150 | R43: =G43 -> 6182 | S43: 5949 | T43: 5858 | U43: 5782 | V43: =H43 -> 5831 | W43: 5663 | X43: 5615 | Y43: 5575 | Z43: =I43 -> 5598 | AA43: 5493 | AB43: 5451 | AC43: 5423 | AE43: =N43 -> 321.91 | AF43: =O43 -> 315.158 | AG43: =P43 -> 6231 | AH43: =Q43 -> 6150 | AI43: =R43 -> 6182 | AJ43: =S43 -> 5949 | AK43: =T43 -> 5858 | AL43: =U43 -> 5782 | ... AT43: =AC43 -> 5423
B44: Class C Basic EPS | C44: =IF($C$6=1, C41/C42,C41/C43) -> 2.210861 | D44: =IF($C$6=1, D41/D42,D41/D43) -> 2.4793245 | E44: =IF($C$6=1, E41/E42,E41/E43) -> 2.9574188 | F44: =IF($C$6=1, F41/F42,F41/F43) -> 5.6939828 | G44: =IF($C$6=1, G41/G42,G41/G43) -> 4.5910709 | H44: =IF($C$6=1, H41/H42,H41/H43) -> 5.8429086 | I44: =IF($C$6=1, I41/I42,I41/I43) -> 8.1252233 | K44: =IF($C$6=1, K41/K42,K41/K43) -> 1.3316798 | L44: =IF($C$6=1, L41/L42,L41/L43) -> 1.384685 | M44: =IF($C$6=1, M41/M42,M41/M43) -> 1.4221395 | N44: =IF($C$6=1, N41/N42,N41/N43) -> 1.5415799 | O44: =IF($C$6=1, O41/O42,O41/O43) -> 1.2447725 | P44: =IF($C$6=1, P41/P42,P41/P43) -> 1.218424 | Q44: =IF($C$6=1, Q41/Q42,Q41/Q43) -> 1.0684553 | R44: =IF($C$6=1, R41/R42,R41/R43) -> 1.0308962 | ... AC44: =IF($C$6=1, AC41/AC42,AC41/AC43) -> 2.8941545 | AE44: =IF($C$6=1, AE41/AE42,AE41/AE43) -> 5.6939828 | AF44: =IF($C$6=1, AF41/AF42,AF41/AF43) -> 5.6808014 | AG44: =IF($C$6=1, AG41/AG42,AG41/AG43) -> 5.5304125 | AH44: =IF($C$6=1, AH41/AH42,AH41/AH43) -> 5.1925203 | AI44: =IF($C$6=1, AI41/AI42,AI41/AI43) -> 4.5910709 | AJ44: =IF($C$6=1, AJ41/AJ42,AJ41/AJ43) -> 4.6295176 | AK44: =IF($C$6=1, AK41/AK42,AK41/AK43) -> 4.8552407 | AL44: =IF($C$6=1, AL41/AL42,AL41/AL43) -> 5.3476306 | ... AT44: =IF($C$6=1, AT41/AT42,AT41/AT43) -> 10.319934
A46: X | B46: Fully Diluted EPS Per Share Class
B48: Class A
B49: Allocation of undistributed earnings | C49: 15126 | D49: 17027 | E49: 20285 | F49: 38793 | G49: 31360 | H49: 39438 | I49: 54113 | K49: 9113 | L49: 9437 | M49: 9683 | N49: =SUM(F49-SUM(K49:M49)) -> 10560 | O49: 8495 | P49: 8342 | Q49: 7294 | R49: =SUM(G49-SUM(O49:Q49)) -> 7229 | S49: 8019 | T49: 9800 | U49: 10544 | V49: =SUM(H49-SUM(S49:U49)) -> 11075 | W49: 12754 | X49: 12736 | Y49: 14237 | Z49: =SUM(I49-SUM(W49:Y49)) -> 14386 | AA49: 18813 | AB49: 15429 | AC49: 19113 | AE49: =SUM(K49:N49) -> 38793 | AF49: =SUM(L49:O49) -> 38175 | AG49: =SUM(M49:P49) -> 37080 | AH49: =SUM(N49:Q49) -> 34691 | AI49: =SUM(O49:R49) -> 31360 | AJ49: =SUM(P49:S49) -> 30884 | AK49: =SUM(Q49:T49) -> 32342 | AL49: =SUM(R49:U49) -> 35592 | ... AT49: =SUM(Z49:AC49) -> 67741
B50: Fully Diluted Shares | C50: =SUM(C51:C53) -> 6922.02 | D50: =SUM(D51:D53) -> 6926.84 | E50: =SUM(E51:E53) -> 6921.68 | F50: =SUM(F51:F53) -> 6915.1 | G50: =SUM(G51:G53) -> 6881 | H50: =SUM(H51:H53) -> 6799 | I50: =SUM(I51:I53) -> 6721 | K50: =SUM(K51:K53) -> 6933.16 | L50: =SUM(L51:L53) -> 6923.84 | M50: =SUM(M51:M53) -> 6918.74 | N50: =SUM(N51:N53) -> 6915.06 | O50: =SUM(O51:O53) -> 6900.36 | P50: =SUM(P51:P53) -> 6902 | Q50: =SUM(Q51:Q53) -> 6868 | R50: =SUM(R51:R53) -> 6881 | ... AC50: =SUM(AC51:AC53) -> 6663 | AE50: =SUM(AE51:AE53) -> 6914.813 | AF50: =SUM(AF51:AF53) -> 6900.265 | AG50: =SUM(AG51:AG53) -> 6902 | AH50: =SUM(AH51:AH53) -> 6868 | AI50: =SUM(AI51:AI53) -> 6881 | AJ50: =SUM(AJ51:AJ53) -> 6832 | AK50: =SUM(AK51:AK53) -> 6810 | AL50: =SUM(AL51:AL53) -> 6799 | ... AT50: =SUM(AT51:AT53) -> 6663
B51: Number of shares used in basic computation | C51: =IF($C$6=1,C30,C31) -> 5970.96 | D51: =IF($C$6=1,D30,D31) -> 5988.04 | E51: =IF($C$6=1,E30,E31) -> 5996.3 | F51: =IF($C$6=1,F30,F31) -> 6006.2 | G51: =IF($C$6=1,G30,G31) -> 5994 | H51: =IF($C$6=1,H30,H31) -> 5922 | I51: =IF($C$6=1,I30,I31) -> 5855 | K51: =IF($C$6=1,K30,K31) -> 6016 | L51: =IF($C$6=1,L30,L31) -> 6009.7 | M51: =IF($C$6=1,M30,M31) -> 6010.38 | N51: =IF($C$6=1,N30,N31) -> 6006.2 | O51: =IF($C$6=1,O30,O31) -> 6009.56 | P51: =IF($C$6=1,P30,P31) -> 6015 | Q51: =IF($C$6=1,Q30,Q31) -> 5983 | R51: =IF($C$6=1,R30,R31) -> 5994 | ... AC51: =IF($C$6=1,AC30,AC31) -> 5818 | AE51: =IF($C$6=1,AE30,AE31) -> 6006.2 | AF51: =IF($C$6=1,AF30,AF31) -> 6009.56 | AG51: =IF($C$6=1,AG30,AG31) -> 6015 | AH51: =IF($C$6=1,AH30,AH31) -> 5983 | AI51: =IF($C$6=1,AI30,AI31) -> 5994 | AJ51: =IF($C$6=1,AJ30,AJ31) -> 5949 | AK51: =IF($C$6=1,AK30,AK31) -> 5931 | AL51: =IF($C$6=1,AL30,AL31) -> 5924 | ... AT51: =IF($C$6=1,AT30,AT31) -> 5818
B52: Conversion of Class B to Class A common shares outstanding | C52: =IF($C$6=1,C36,C37) -> 937.28 | D52: =IF($C$6=1,D36,D37) -> 930.54 | E52: =IF($C$6=1,E36,E37) -> 923.64 | F52: =IF($C$6=1,F36,F37) -> 908.6 | G52: =IF($C$6=1,G36,G37) -> 887 | H52: =IF($C$6=1,H36,H37) -> 877 | I52: =IF($C$6=1,I36,I37) -> 866 | K52: =IF($C$6=1,K36,K37) -> 916.8 | L52: =IF($C$6=1,L36,L37) -> 913.84 | M52: =IF($C$6=1,M36,M37) -> 908.08 | N52: =IF($C$6=1,N36,N37) -> 908.6 | O52: =IF($C$6=1,O36,O37) -> 890.7 | P52: =IF($C$6=1,P36,P37) -> 887 | Q52: =IF($C$6=1,Q36,Q37) -> 885 | R52: =IF($C$6=1,R36,R37) -> 887 | ... AC52: =IF($C$6=1,AC36,AC37) -> 845 | AE52: =IF($C$6=1,AE36,AE37) -> 908.6 | AF52: =IF($C$6=1,AF36,AF37) -> 890.7 | AG52: =IF($C$6=1,AG36,AG37) -> 887 | AH52: =IF($C$6=1,AH36,AH37) -> 885 | AI52: =IF($C$6=1,AI36,AI37) -> 887 | AJ52: =IF($C$6=1,AJ36,AJ37) -> 883 | AK52: =IF($C$6=1,AK36,AK37) -> 879 | AL52: =IF($C$6=1,AL36,AL37) -> 875 | ... AT52: =IF($C$6=1,AT36,AT37) -> 845
B53: Adjusted RSUs and other contingently issuable shares | C53: =IF($C$6=1,C54*20,C54) -> 13.78 | D53: =IF($C$6=1,D54*20,D54) -> 8.26 | E53: =IF($C$6=1,E54*20,E54) -> 1.74 | F53: =IF($C$6=1,F54*20,F54) -> 0.3 | G53: =IF($C$6=1,G54*20,G54) -> 0 | H53: =IF($C$6=1,H54*20,H54) -> 0 | I53: =IF($C$6=1,I54*20,I54) -> 0 | K53: =IF($C$6=1,K54*20,K54) -> 0.36 | L53: =IF($C$6=1,L54*20,L54) -> 0.3 | M53: =IF($C$6=1,M54*20,M54) -> 0.28 | N53: =IF($C$6=1,N54*20,N54) -> 0.26 | O53: =IF($C$6=1,O54*20,O54) -> 0.1 | P53: =IF($C$6=1,P54*20,P54) -> 0 | Q53: =Q54 -> 0 | R53: =R54 -> 0 | S53: =S54 -> 0 | T53: =T54 -> 0 | U53: =U54 -> 0 | V53: =V54 -> 0 | W53: =W54 -> 0 | X53: =X54 -> 0 | ... AC53: =AC54 -> 0 | AE53: =AE54 -> 0.013 | AF53: =AF54 -> 0.005 | AG53: =AG54 -> 0 | AH53: =AH54 -> 0 | AI53: =AI54 -> 0 | AJ53: =AJ54 -> 0 | AK53: =AK54 -> 0 | AL53: =AL54 -> 0 | ... AT53: =AT54 -> 0
B54: RSUs and other contingently issuable shares | C54: 0.689 | D54: 0.413 | E54: 0.087 | F54: 0.015 | G54: 0 | H54: 0 | I54: 0 | K54: 0.018 | L54: 0.015 | M54: 0.014 | N54: =SUM(F54*4)-SUM(K54:M54) -> 0.013 | O54: 0.005 | P54: 0 | Q54: 0 | R54: =G54 -> 0 | S54: 0 | T54: 0 | U54: 0 | V54: =H54 -> 0 | W54: 0 | X54: 0 | Y54: 0 | Z54: =I54 -> 0 | AA54: 0 | AB54: 0 | AC54: 0 | AE54: =N54 -> 0.013 | AF54: =O54 -> 0.005 | AG54: =P54 -> 0 | AH54: =Q54 -> 0 | AI54: =R54 -> 0 | AJ54: =S54 -> 0 | AK54: =T54 -> 0 | AL54: =U54 -> 0 | ... AT54: =AC54 -> 0
B55: Fully Diluted EPS | C55: =C49/C50 -> 2.1852003 | D55: =D49/D50 -> 2.4581194 | E55: =E49/E50 -> 2.9306469 | F55: =F49/F50 -> 5.6098972 | G55: =G49/G50 -> 4.5574771 | H55: =H49/H50 -> 5.8005589 | I55: =I49/I50 -> 8.0513316 | K55: =K49/K50 -> 1.3144079 | L55: =L49/L50 -> 1.362972 | M55: =M49/M50 -> 1.3995323 | N55: =N49/N50 -> 1.5271017 | O55: =O49/O50 -> 1.2310952 | P55: =P49/P50 -> 1.2086352 | Q55: =Q49/Q50 -> 1.0620268 | R55: =R49/R50 -> 1.050574 | ... AC55: =AC49/AC50 -> 2.8685277 | AE55: =AE49/AE50 -> 5.61013 | AF55: =AF49/AF50 -> 5.5323962 | AG55: =AG49/AG50 -> 5.3723558 | AH55: =AH49/AH50 -> 5.0511066 | AI55: =AI49/AI50 -> 4.5574771 | AJ55: =AJ49/AJ50 -> 4.5204918 | AK55: =AK49/AK50 -> 4.7491924 | AL55: =AL49/AL50 -> 5.2348875 | ... AT55: =AT49/AT50 -> 10.166742
B57: Class B
B58: Allocation of undistributed earnings | C58: 2048 | D58: 2287 | E58: 2707 | F58: 5097 | G58: 4042 | H58: 5087 | I58: 6972 | K58: 1205 | L58: 1246 | M58: 1271 | N58: =SUM(F58-SUM(K58:M58)) -> 1375 | O58: 1097 | P58: 1072 | Q58: 940 | R58: =SUM(G58-SUM(O58:Q58)) -> 933 | S58: 1036 | T58: 1265 | U58: 1357 | V58: =SUM(H58-SUM(S58:U58)) -> 1429 | W58: 1641 | X58: 1639 | Y58: 1834 | Z58: =SUM(I58-SUM(W58:Y58)) -> 1858 | AA58: 2415 | AB58: 1970 | AC58: 2423 | AE58: =SUM(K58:N58) -> 5097 | AF58: =SUM(L58:O58) -> 4989 | AG58: =SUM(M58:P58) -> 4815 | AH58: =SUM(N58:Q58) -> 4484 | AI58: =SUM(O58:R58) -> 4042 | AJ58: =SUM(P58:S58) -> 3981 | AK58: =SUM(Q58:T58) -> 4174 | AL58: =SUM(R58:U58) -> 4591 | ... AT58: =SUM(Z58:AC58) -> 8666
B59: Fully Diluted Shares | C59: =SUM(C60:C60) -> 937.28 | D59: =SUM(D60:D60) -> 930.54 | E59: =SUM(E60:E60) -> 923.64 | F59: =SUM(F60:F60) -> 908.6 | G59: =SUM(G60:G60) -> 887 | H59: =SUM(H60:H60) -> 877 | I59: =SUM(I60:I60) -> 866 | K59: =SUM(K60:K60) -> 916.8 | L59: =SUM(L60:L60) -> 913.84 | M59: =SUM(M60:M60) -> 908.08 | N59: =SUM(N60:N60) -> 908.6 | O59: =SUM(O60:O60) -> 890.7 | P59: =SUM(P60:P60) -> 887 | Q59: =SUM(Q60:Q60) -> 885 | R59: =SUM(R60:R60) -> 887 | ... AC59: =SUM(AC60:AC60) -> 845 | AE59: =SUM(AE60:AE60) -> 908.6 | AF59: =SUM(AF60:AF60) -> 890.7 | AG59: =SUM(AG60:AG60) -> 887 | AH59: =SUM(AH60:AH60) -> 885 | AI59: =SUM(AI60:AI60) -> 887 | AJ59: =SUM(AJ60:AJ60) -> 883 | AK59: =SUM(AK60:AK60) -> 879 | AL59: =SUM(AL60:AL60) -> 875 | ... AT59: =SUM(AT60:AT60) -> 845
B60: Number of shares used in basic computation | C60: =IF($C$6=1,C36,C37) -> 937.28 | D60: =IF($C$6=1,D36,D37) -> 930.54 | E60: =IF($C$6=1,E36,E37) -> 923.64 | F60: =IF($C$6=1,F36,F37) -> 908.6 | G60: =IF($C$6=1,G36,G37) -> 887 | H60: =IF($C$6=1,H36,H37) -> 877 | I60: =IF($C$6=1,I36,I37) -> 866 | K60: =IF($C$6=1,K36,K37) -> 916.8 | L60: =IF($C$6=1,L36,L37) -> 913.84 | M60: =IF($C$6=1,M36,M37) -> 908.08 | N60: =IF($C$6=1,N36,N37) -> 908.6 | O60: =IF($C$6=1,O36,O37) -> 890.7 | P60: =IF($C$6=1,P36,P37) -> 887 | Q60: =IF($C$6=1,Q36,Q37) -> 885 | R60: =G60 -> 887 | S60: =IF($C$6=1,S36,S37) -> 883 | T60: =IF($C$6=1,T36,T37) -> 879 | U60: =IF($C$6=1,U36,U37) -> 875 | V60: =IF($C$6=1,V36,V37) -> 877 | W60: =IF($C$6=1,W36,W37) -> 869 | X60: =IF($C$6=1,X36,X37) -> 866 | Y60: =IF($C$6=1,Y36,Y37) -> 865 | Z60: =IF($C$6=1,Z36,Z37) -> 866 | ... AC60: =IF($C$6=1,AC36,AC37) -> 845 | AE60: =N60 -> 908.6 | AF60: =O60 -> 890.7 | AG60: =P60 -> 887 | AH60: =Q60 -> 885 | AI60: =R60 -> 887 | AJ60: =S60 -> 883 | AK60: =T60 -> 879 | AL60: =U60 -> 875 | ... AT60: =AC60 -> 845
B61: Fully Diluted EPS | C61: =C58/C59 -> 2.1850461 | D61: =D58/D59 -> 2.4577127 | E61: =E58/E59 -> 2.9307955 | F61: =F58/F59 -> 5.6097293 | G61: =G58/G59 -> 4.5569335 | H61: =H58/H59 -> 5.8004561 | I61: =I58/I59 -> 8.0508083 | K61: =K58/K59 -> 1.3143543 | L61: =L58/L59 -> 1.3634772 | M61: =M58/M59 -> 1.3996564 | N61: =N58/N59 -> 1.5133172 | O61: =O58/O59 -> 1.2316156 | P61: =P58/P59 -> 1.2085682 | Q61: =Q58/Q59 -> 1.0621469 | R61: =R58/R59 -> 1.0518602 | ... AC61: =AC58/AC59 -> 2.8674556 | AE61: =AE58/AE59 -> 5.6097293 | AF61: =AF58/AF59 -> 5.6012125 | AG61: =AG58/AG59 -> 5.4284104 | AH61: =AH58/AH59 -> 5.0666667 | AI61: =AI58/AI59 -> 4.5569335 | AJ61: =AJ58/AJ59 -> 4.5084938 | AK61: =AK58/AK59 -> 4.7485779 | AL61: =AL58/AL59 -> 5.2468571 | ... AT61: =AT58/AT59 -> 10.255621
B63: Class C
B64: Allocation of undistributed earnings | C64: 15610 | D64: 17316 | E64: 19984 | F64: 37240 | G64: 28612 | H64: 34357 | I64: 46005 | K64: 8817 | L64: 9088 | M64: 9253 | N64: =SUM(F64-SUM(K64:M64)) -> 10082 | O64: 7941 | P64: 7660 | Q64: 6616 | R64: =SUM(G64-SUM(O64:Q64)) -> 6395 | S64: 7032 | T64: 8568 | U64: 9145 | V64: =SUM(H64-SUM(S64:U64)) -> 9612 | W64: 10908 | X64: 10883 | Y64: 12064 | Z64: =SUM(I64-SUM(W64:Y64)) -> 12150 | AA64: 15727 | AB64: 12767 | AC64: 15866 | AE64: =SUM(K64:N64) -> 37240 | AF64: =SUM(L64:O64) -> 36364 | AG64: =SUM(M64:P64) -> 34936 | AH64: =SUM(N64:Q64) -> 32299 | AI64: =SUM(O64:R64) -> 28612 | AJ64: =SUM(P64:S64) -> 27703 | AK64: =SUM(Q64:T64) -> 28611 | AL64: =SUM(R64:U64) -> 31140 | ... AT64: =SUM(Z64:AC64) -> 56510
B65: Fully Diluted Shares | C65: =SUM(C66:C67) -> 7143.68 | D65: =SUM(D66:D67) -> 7044.28 | E65: =SUM(E66:E67) -> 6818.88 | F65: =SUM(F66:F67) -> 6638.38 | G65: =SUM(G66:G67) -> 8102 | H65: =SUM(H66:H67) -> 7671 | I65: =SUM(I66:I67) -> 8158 | K65: =SUM(K66:K67) -> 6708.26 | L65: =SUM(L66:L67) -> 6668.4 | M65: =SUM(M66:M67) -> 6611.64 | N65: =SUM(N66:N67) -> 6634.54 | O65: =SUM(O66:O67) -> 6450.66 | P65: =SUM(P66:P67) -> 6337 | Q65: =SUM(Q66:Q67) -> 6229 | R65: =SUM(R66:R67) -> 6278 | ... AC65: =SUM(AC66:AC67) -> 5540 | AE65: =SUM(AE66:AE67) -> 6634.54 | AF65: =SUM(AF66:AF67) -> 6450.66 | AG65: =SUM(AG66:AG67) -> 6337 | AH65: =SUM(AH66:AH67) -> 6229 | AI65: =SUM(AI66:AI67) -> 6278 | AJ65: =SUM(AJ66:AJ67) -> 5991 | AK65: =SUM(AK66:AK67) -> 5927 | AL65: =SUM(AL66:AL67) -> 5897 | ... AT65: =SUM(AT66:AT67) -> 5540
B66: Basic Shares | C66: =IF($C$6=1,C42,C43) -> 6994.56 | D66: =IF($C$6=1,D42,D43) -> 6933.34 | E66: =IF($C$6=1,E42,E43) -> 6696.38 | F66: =IF($C$6=1,F42,F43) -> 6438.2 | G66: =IF($C$6=1,G42,G43) -> 6182 | H66: =IF($C$6=1,H42,H43) -> 5831 | I66: =IF($C$6=1,I42,I43) -> 5598 | K66: =IF($C$6=1,K42,K43) -> 6531.6 | L66: =IF($C$6=1,L42,L43) -> 6455.62 | M66: =IF($C$6=1,M42,M43) -> 6396.7 | N66: =IF($C$6=1,N42,N43) -> 6438.2 | O66: =IF($C$6=1,O42,O43) -> 6303.16 | P66: =IF($C$6=1,P42,P43) -> 6231 | Q66: =IF($C$6=1,Q42,Q43) -> 6150 | R66: =IF($C$6=1,R42,R43) -> 6182 | ... AC66: =IF($C$6=1,AC42,AC43) -> 5423 | AE66: =N66 -> 6438.2 | AF66: =O66 -> 6303.16 | AG66: =P66 -> 6231 | AH66: =Q66 -> 6150 | AI66: =R66 -> 6182 | AJ66: =S66 -> 5949 | AK66: =T66 -> 5858 | AL66: =U66 -> 5782 | ... AT66: =AC66 -> 5423
B67: Adjusted RSUs and other contingently issuable shares | C67: =IF($C$6=1,C68*20,C68) -> 149.12 | D67: =IF($C$6=1,D68*20,D68) -> 110.94 | E67: =IF($C$6=1,E68*20,E68) -> 122.5 | F67: =IF($C$6=1,F68*20,F68) -> 200.18 | G67: =IF($C$6=1,G68*20,G68) -> 1920 | H67: =IF($C$6=1,H68*20,H68) -> 1840 | I67: =IF($C$6=1,I68*20,I68) -> 2560 | K67: =IF($C$6=1,K68*20,K68) -> 176.66 | L67: =IF($C$6=1,L68*20,L68) -> 212.78 | M67: =IF($C$6=1,M68*20,M68) -> 214.94 | N67: =IF($C$6=1,N68*20,N68) -> 196.34 | O67: =IF($C$6=1,O68*20,O68) -> 147.5 | P67: =P68 -> 106 | Q67: =Q68 -> 79 | R67: =R68 -> 96 | S67: =S68 -> 42 | T67: =T68 -> 69 | U67: =U68 -> 115 | V67: =V68 -> 92 | W67: =W68 -> 112 | ... AC67: =AC68 -> 117 | AE67: =N67 -> 196.34 | AF67: =O67 -> 147.5 | AG67: =P67 -> 106 | AH67: =Q67 -> 79 | AI67: =R67 -> 96 | AJ67: =S67 -> 42 | AK67: =T67 -> 69 | AL67: =U67 -> 115 | ... AT67: =AC67 -> 117
B68: RSUs and other contingently issuable shares | C68: 7.456 | D68: 5.547 | E68: 6.125 | F68: 10.009 | G68: 96 | H68: 92 | I68: 128 | K68: 8.833 | L68: 10.639 | M68: 10.747 | N68: =SUM(F68*4)-SUM(K68:M68) -> 9.817 | O68: 7.375 | P68: 106 | Q68: 79 | R68: =G68 -> 96 | S68: 42 | T68: 69 | U68: 115 | V68: =H68 -> 92 | W68: 112 | X68: 152 | Y68: 129 | Z68: =I68 -> 128 | AA68: 108 | AB68: 76 | AC68: 117 | AE68: =N68 -> 9.817 | AF68: =O68 -> 7.375 | AG68: =P68 -> 106 | AH68: =Q68 -> 79 | AI68: =R68 -> 96 | AJ68: =S68 -> 42 | AK68: =T68 -> 69 | AL68: =U68 -> 115 | ... AT68: =AC68 -> 117
B69: Fully Diluted EPS | C69: =C64/C65 -> 2.1851483 | D69: =D64/D65 -> 2.4581646 | E69: =E64/E65 -> 2.9306866 | F69: =F64/F65 -> 5.6098024 | G69: =G64/G65 -> 3.5314737 | H69: =H64/H65 -> 4.4788163 | I69: =I64/I65 -> 5.6392498 | K69: =K64/K65 -> 1.3143498 | L69: =L64/L65 -> 1.3628457 | M69: =M64/M65 -> 1.3995015 | N69: =N64/N65 -> 1.5196231 | O69: =O64/O65 -> 1.2310368 | P69: =P64/P65 -> 1.2087739 | Q69: =Q64/Q65 -> 1.0621288 | R69: =R64/R65 -> 1.0186365 | ... AC69: =AC64/AC65 -> 2.8638989 | AE69: =AE64/AE65 -> 5.6130493 | AF69: =AF64/AF65 -> 5.6372526 | AG69: =AG64/AG65 -> 5.5130188 | AH69: =AH64/AH65 -> 5.1852625 | AI69: =AI64/AI65 -> 4.5575024 | AJ69: =AJ64/AJ65 -> 4.6241028 | AK69: =AK64/AK65 -> 4.8272313 | AL69: =AL64/AL65 -> 5.2806512 | ... AT69: =AT64/AT65 -> 10.200361

Sheet Revenue Drivers
B2: ='Historical Financials'!B2 -> Alphabet Inc. (NASDAQ: GOOG) | C2: FYE | G2: FYE | K2: Quarterly | S2: Quarterly | T2: Quarterly | AA2: LTM | AE2: LTM | AG2: LTM | AM2: Variance
B3: Segment Anaysis | C3: ='Historical Financials'!C7 -> 2018 | D3: ='Historical Financials'!D7 -> 2019 | E3: ='Historical Financials'!E7 -> 2020 | F3: ='Historical Financials'!F7 -> 2021 | G3: ='Historical Financials'!G7 -> 2022 | H3: ='Historical Financials'!H7 -> 2023 | I3: ='Historical Financials'!I7 -> 2024 | K3: ='Historical Financials'!O7 -> 1Q22 | L3: ='Historical Financials'!P7 -> 2Q22 | M3: ='Historical Financials'!Q7 -> 3Q22 | N3: ='Historical Financials'!R7 -> 4Q22 | O3: ='Historical Financials'!S7 -> 1Q23 | P3: ='Historical Financials'!T7 -> 2Q23 | Q3: ='Historical Financials'!U7 -> 3Q23 | R3: ='Historical Financials'!V7 -> 4Q23 | ... Y3: ='Historical Financials'!AC7 -> 3Q25 | AA3: =O3 -> 1Q23 | AB3: =P3 -> 2Q23 | AC3: =Q3 -> 3Q23 | AD3: =R3 -> 4Q23 | AE3: =S3 -> 1Q24 | AF3: =T3 -> 2Q24 | AG3: =U3 -> 3Q24 | AH3: =V3 -> 4Q24 | ... AK3: =Y3 -> 3Q25
B4: $ mm except per share | C4: ='Historical Financials'!C8 -> 43465 | D4: ='Historical Financials'!D8 -> 43830 | E4: ='Historical Financials'!E8 -> 44196 | F4: ='Historical Financials'!F8 -> 44561 | G4: ='Historical Financials'!G8 -> 44926 | H4: ='Historical Financials'!H8 -> 45291 | I4: ='Historical Financials'!I8 -> 45657 | K4: ='Historical Financials'!O8 -> 44651 | L4: ='Historical Financials'!P8 -> 44742 | M4: ='Historical Financials'!Q8 -> 44834 | N4: ='Historical Financials'!R8 -> 44926 | O4: ='Historical Financials'!S8 -> 45016 | P4: ='Historical Financials'!T8 -> 45107 | Q4: ='Historical Financials'!U8 -> 45199 | R4: ='Historical Financials'!V8 -> 45291 | ... Y4: ='Historical Financials'!AC8 -> 45930 | AA4: =O4 -> 45016 | AB4: =P4 -> 45107 | AC4: =Q4 -> 45199 | AD4: =R4 -> 45291 | AE4: =S4 -> 45382 | AF4: =T4 -> 45473 | AG4: =U4 -> 45565 | AH4: =V4 -> 45657 | ... AK4: =Y4 -> 45930
A6: X | B6: Offerings Drivers
B8: Disaggregated Revenues
B9: Google Services | C9: =+C19 -> 130524 | D9: =+D19 -> 151825 | E9: =+E19 -> 168635 | F9: =+F19 -> 237529 | G9: =+G19 -> 253528 | H9: =+H19 -> 272543 | I9: =+I19 -> 304930 | K9: =+K19 -> 61472 | L9: =+L19 -> 62841 | M9: =+M19 -> 61377 | N9: =+N19 -> 67838 | O9: =+O19 -> 61961 | P9: =+P19 -> 66285 | Q9: =+Q19 -> 67986 | R9: =+R19 -> 76311 | ... Y9: =+Y19 -> 87052 | AA9: =SUM(L9:O9) -> 254017 | AB9: =SUM(M9:P9) -> 257461 | AC9: =SUM(N9:Q9) -> 264070 | AD9: =SUM(O9:R9) -> 272543 | AE9: =SUM(P9:S9) -> 280980 | AF9: =SUM(Q9:T9) -> 288623 | AG9: =SUM(R9:U9) -> 297147 | AH9: =SUM(S9:V9) -> 304930 | ... AK9: =SUM(V9:Y9) -> 330953 | AM9: =SUM(AK9/AG9)-1 -> 0.11376861
B10: Google Cloud | C10: 5838 | D10: 8918 | E10: 13059 | F10: 19206 | G10: 26280 | H10: 33088 | I10: 43229 | K10: 5821 | L10: 6276 | M10: 6868 | N10: =SUM(G10-SUM(K10:M10)) -> 7315 | O10: 7454 | P10: 8031 | Q10: 8411 | R10: =SUM(H10-SUM(O10:Q10)) -> 9192 | S10: 9574 | T10: 10347 | U10: 11353 | V10: =SUM(I10-SUM(S10:U10)) -> 11955 | W10: 12260 | X10: 13624 | Y10: 15157 | AG10: =SUM(R10:U10) -> 40466 | AH10: =SUM(S10:V10) -> 43229 | AI10: =SUM(T10:W10) -> 45915 | AJ10: =SUM(U10:X10) -> 49192 | AK10: =SUM(V10:Y10) -> 52996 | AM10: =SUM(AK10/AG10)-1 -> 0.30964266
B11: Other Bets | C11: 595 | D11: 659 | E11: 657 | F11: 753 | G11: 1068 | H11: 1527 | I11: 1648 | K11: 440 | L11: 193 | M11: 209 | N11: =SUM(G11-SUM(K11:M11)) -> 226 | O11: 288 | P11: 285 | Q11: 297 | R11: =SUM(H11-SUM(O11:Q11)) -> 657 | S11: 495 | T11: 365 | U11: 388 | V11: =SUM(I11-SUM(S11:U11)) -> 400 | W11: 450 | X11: 373 | Y11: 344 | AG11: =SUM(R11:U11) -> 1905 | AH11: =SUM(S11:V11) -> 1648 | AI11: =SUM(T11:W11) -> 1603 | AJ11: =SUM(U11:X11) -> 1611 | AK11: =SUM(V11:Y11) -> 1567 | AM11: =SUM(AK11/AG11)-1 -> -0.17742782
B12: Hedging gains (losses) | C12: -138 | D12: 455 | E12: 176 | F12: 149 | G12: 1960 | H12: 236 | I12: 211 | K12: 278 | L12: 375 | M12: 638 | N12: =SUM(G12-SUM(K12:M12)) -> 669 | O12: 84 | P12: 3 | Q12: -1 | R12: =SUM(H12-SUM(O12:Q12)) -> 150 | S12: 72 | T12: 102 | U12: 17 | V12: =SUM(I12-SUM(S12:U12)) -> 20 | W12: 260 | X12: -112 | Y12: -207 | AG12: =SUM(R12:U12) -> 341 | AH12: =SUM(S12:V12) -> 211 | AI12: =SUM(T12:W12) -> 399 | AJ12: =SUM(U12:X12) -> 185 | AK12: =SUM(V12:Y12) -> -39 | AM12: =SUM(AK12/AG12)-1 -> -1.1143695
B13: Total Net Revenue | C13: =SUM(C9:C12) -> 136819 | D13: =SUM(D9:D12) -> 161857 | E13: =SUM(E9:E12) -> 182527 | F13: =SUM(F9:F12) -> 257637 | G13: =SUM(G9:G12) -> 282836 | H13: =SUM(H9:H12) -> 307394 | I13: =SUM(I9:I12) -> 350018 | K13: =SUM(K9:K12) -> 68011 | L13: =SUM(L9:L12) -> 69685 | M13: =SUM(M9:M12) -> 69092 | N13: =SUM(N9:N12) -> 76048 | O13: =SUM(O9:O12) -> 69787 | P13: =SUM(P9:P12) -> 74604 | Q13: =SUM(Q9:Q12) -> 76693 | R13: =SUM(R9:R12) -> 86310 | ... Y13: =SUM(Y9:Y12) -> 102346 | AA13: =SUM(AA9:AA12) -> 254017 | AB13: =SUM(AB9:AB12) -> 257461 | AC13: =SUM(AC9:AC12) -> 264070 | AD13: =SUM(AD9:AD12) -> 272543 | AE13: =SUM(AE9:AE12) -> 280980 | AF13: =SUM(AF9:AF12) -> 288623 | AG13: =SUM(AG9:AG12) -> 339859 | AH13: =SUM(AH9:AH12) -> 350018 | ... AK13: =SUM(AK9:AK12) -> 385477 | AM13: =SUM(AK13/AG13)-1 -> 0.13422625
B14: Variance Check | C14: =+C13-'Historical Financials'!C11 -> 0 | D14: =+D13-'Historical Financials'!D11 -> 0 | E14: =+E13-'Historical Financials'!E11 -> 0 | F14: =+F13-'Historical Financials'!F11 -> 0 | G14: =+G13-'Historical Financials'!G11 -> 0 | H14: =+H13-'Historical Financials'!H11 -> 0 | I14: =+I13-'Historical Financials'!I11 -> 0 | K14: =K13-'Historical Financials'!O11 -> 0 | L14: =L13-'Historical Financials'!P11 -> 0 | M14: =M13-'Historical Financials'!Q11 -> 0 | N14: =N13-'Historical Financials'!R11 -> 0 | O14: =O13-'Historical Financials'!S11 -> 0 | P14: =P13-'Historical Financials'!T11 -> 0 | Q14: =Q13-'Historical Financials'!U11 -> 0 | R14: =R13-'Historical Financials'!V11 -> 0 | ... Y14: =Y13-'Historical Financials'!AC11 -> 0 | AA14: =+AA13-'Historical Financials'!AN11 -> -30595 | AB14: =+AB13-'Historical Financials'!AO11 -> -32070 | AC14: =+AC13-'Historical Financials'!AP11 -> -33062 | AD14: =+AD13-'Historical Financials'!AQ11 -> -34851 | AE14: =+AE13-'Historical Financials'!AR11 -> -37166 | AF14: =+AF13-'Historical Financials'!AS11 -> -39661 | AG14: =+AG13-'Historical Financials'!AT11 -> 0 | AH14: =+AH13-'Historical Financials'!AU11 -> 0 | ... AJ14: =+AJ13-'Historical Financials'!AW11 -> 0 | AK14: =AK13-'Historical Financials'!AX11 -> 0
B16: Google Services
B17: Google Advertising | C17: =+C25 -> 116461 | D17: =+D25 -> 134811 | E17: =+E25 -> 146924 | F17: =+F25 -> 209497 | G17: =+G25 -> 224473 | H17: =+H25 -> 237855 | I17: =+I25 -> 264590 | K17: =+K25 -> 54661 | L17: =+L25 -> 56288 | M17: =+M25 -> 54482 | N17: =+N25 -> 59042 | O17: =+O25 -> 54548 | P17: =+P25 -> 58143 | Q17: =+Q25 -> 59647 | R17: =+R25 -> 65517 | ... Y17: =+Y25 -> 74182 | AA17: =SUM(L17:O17) -> 224360 | AB17: =SUM(M17:P17) -> 226215 | AC17: =SUM(N17:Q17) -> 231380 | AD17: =SUM(O17:R17) -> 237855 | AE17: =SUM(P17:S17) -> 244966 | AF17: =SUM(Q17:T17) -> 251439 | AG17: =SUM(R17:U17) -> 257646 | AH17: =SUM(S17:V17) -> 264590 | ... AK17: =SUM(V17:Y17) -> 284868 | AM17: =SUM(AK17/AG17)-1 -> 0.1056566
B18: Google subscriptions, platforms, and devices | C18: =+C29 -> 14063 | D18: =+D29 -> 17014 | E18: =+E29 -> 21711 | F18: =+F29 -> 28032 | G18: =+G29 -> 29055 | H18: =+H29 -> 34688 | I18: =+I29 -> 40340 | K18: =+K29 -> 6811 | L18: =+L29 -> 6553 | M18: =+M29 -> 6895 | N18: =+N29 -> 8796 | O18: =+O29 -> 7413 | P18: =+P29 -> 8142 | Q18: =+Q29 -> 8339 | R18: =+R29 -> 10794 | ... Y18: =+Y29 -> 12870 | AG18: =SUM(R18:U18) -> 39501 | AH18: =SUM(S18:V18) -> 40340 | AI18: =SUM(T18:W18) -> 41980 | AJ18: =SUM(U18:X18) -> 43871 | AK18: =SUM(V18:Y18) -> 46085 | AM18: =SUM(AK18/AG18)-1 -> 0.16667932
B19: Total Google Services Revenue | C19: =SUM(C17:C18) -> 130524 | D19: =SUM(D17:D18) -> 151825 | E19: =SUM(E17:E18) -> 168635 | F19: =SUM(F17:F18) -> 237529 | G19: =SUM(G17:G18) -> 253528 | H19: =SUM(H17:H18) -> 272543 | I19: =SUM(I17:I18) -> 304930 | K19: =SUM(K17:K18) -> 61472 | L19: =SUM(L17:L18) -> 62841 | M19: =SUM(M17:M18) -> 61377 | N19: =SUM(N17:N18) -> 67838 | O19: =SUM(O17:O18) -> 61961 | P19: =SUM(P17:P18) -> 66285 | Q19: =SUM(Q17:Q18) -> 67986 | R19: =SUM(R17:R18) -> 76311 | ... Y19: =SUM(Y17:Y18) -> 87052 | AA19: =SUM(AA17:AA18) -> 224360 | AB19: =SUM(AB17:AB18) -> 226215 | AC19: =SUM(AC17:AC18) -> 231380 | AD19: =SUM(AD17:AD18) -> 237855 | AE19: =SUM(AE17:AE18) -> 244966 | AF19: =SUM(AF17:AF18) -> 251439 | AG19: =SUM(AG17:AG18) -> 297147 | AH19: =SUM(AH17:AH18) -> 304930 | ... AK19: =SUM(AK17:AK18) -> 330953 | AM19: =SUM(AK19/AG19)-1 -> 0.11376861
B21: Google Advertising
B22: Google Search & other | C22: 85296 | D22: 98115 | E22: 104062 | F22: 148951 | G22: 162450 | H22: 175033 | I22: 198084 | K22: 39618 | L22: 40689 | M22: 39539 | N22: =SUM(G22-SUM(K22:M22)) -> 42604 | O22: 40359 | P22: 42628 | Q22: 44026 | R22: =SUM(H22-SUM(O22:Q22)) -> 48020 | S22: 46156 | T22: 48509 | U22: 49385 | V22: =SUM(I22-SUM(S22:U22)) -> 54034 | W22: 50702 | X22: 54190 | Y22: 56567 | AA22: =SUM(L22:O22) -> 163191 | AB22: =SUM(M22:P22) -> 165130 | AC22: =SUM(N22:Q22) -> 169617 | AD22: =SUM(O22:R22) -> 175033 | AE22: =SUM(P22:S22) -> 180830 | AF22: =SUM(Q22:T22) -> 186711 | AG22: =SUM(R22:U22) -> 192070 | AH22: =SUM(S22:V22) -> 198084 | ... AK22: =SUM(V22:Y22) -> 215493 | AM22: =SUM(AK22/AG22)-1 -> 0.12195033
B23: YouTube ads | C23: 11155 | D23: 15149 | E23: 19772 | F23: 28845 | G23: 29243 | H23: 31510 | I23: 36147 | K23: 6869 | L23: 7340 | M23: 7071 | N23: =SUM(G23-SUM(K23:M23)) -> 7963 | O23: 6693 | P23: 7665 | Q23: 7952 | R23: =SUM(H23-SUM(O23:Q23)) -> 9200 | S23: 8090 | T23: 8663 | U23: 8921 | V23: =SUM(I23-SUM(S23:U23)) -> 10473 | W23: 8927 | X23: 9796 | Y23: 10261 | AG23: =SUM(R23:U23) -> 34874 | AH23: =SUM(S23:V23) -> 36147 | AI23: =SUM(T23:W23) -> 36984 | AJ23: =SUM(U23:X23) -> 38117 | AK23: =SUM(V23:Y23) -> 39457 | AM23: =SUM(AK23/AG23)-1 -> 0.13141595
B24: Google Network | C24: 20010 | D24: 21547 | E24: 23090 | F24: 31701 | G24: 32780 | H24: 31312 | I24: 30359 | K24: 8174 | L24: 8259 | M24: 7872 | N24: =SUM(G24-SUM(K24:M24)) -> 8475 | O24: 7496 | P24: 7850 | Q24: 7669 | R24: =SUM(H24-SUM(O24:Q24)) -> 8297 | S24: 7413 | T24: 7444 | U24: 7548 | V24: =SUM(I24-SUM(S24:U24)) -> 7954 | W24: 7256 | X24: 7354 | Y24: 7354 | AA24: =SUM(L24:O24) -> 32102 | AB24: =SUM(M24:P24) -> 31693 | AC24: =SUM(N24:Q24) -> 31490 | AD24: =SUM(O24:R24) -> 31312 | AE24: =SUM(P24:S24) -> 31229 | AF24: =SUM(Q24:T24) -> 30823 | AG24: =SUM(R24:U24) -> 30702 | AH24: =SUM(S24:V24) -> 30359 | ... AK24: =SUM(V24:Y24) -> 29918 | AM24: =SUM(AK24/AG24)-1 -> -0.025535796
B25: Total Google Advertising Revenue | C25: =SUM(C22:C24) -> 116461 | D25: =SUM(D22:D24) -> 134811 | E25: =SUM(E22:E24) -> 146924 | F25: =SUM(F22:F24) -> 209497 | G25: =SUM(G22:G24) -> 224473 | H25: =SUM(H22:H24) -> 237855 | I25: =SUM(I22:I24) -> 264590 | K25: =SUM(K22:K24) -> 54661 | L25: =SUM(L22:L24) -> 56288 | M25: =SUM(M22:M24) -> 54482 | N25: =SUM(N22:N24) -> 59042 | O25: =SUM(O22:O24) -> 54548 | P25: =SUM(P22:P24) -> 58143 | Q25: =SUM(Q22:Q24) -> 59647 | R25: =SUM(R22:R24) -> 65517 | ... Y25: =SUM(Y22:Y24) -> 74182 | AA25: =SUM(AA22:AA24) -> 195293 | AB25: =SUM(AB22:AB24) -> 196823 | AC25: =SUM(AC22:AC24) -> 201107 | AD25: =SUM(AD22:AD24) -> 206345 | AE25: =SUM(AE22:AE24) -> 212059 | AF25: =SUM(AF22:AF24) -> 217534 | AG25: =SUM(AG22:AG24) -> 257646 | AH25: =SUM(AH22:AH24) -> 264590 | ... AK25: =SUM(AK22:AK24) -> 284868 | AM25: =SUM(AK25/AG25)-1 -> 0.1056566
AM26: `
B27: Google subscriptions, platforms, and devices
B28: Google subscriptions, platforms, and devices | C28: 14063 | D28: 17014 | E28: 21711 | F28: 28032 | G28: 29055 | H28: 34688 | I28: 40340 | K28: 6811 | L28: 6553 | M28: 6895 | N28: =SUM(G28-SUM(K28:M28)) -> 8796 | O28: 7413 | P28: 8142 | Q28: 8339 | R28: =SUM(H28-SUM(O28:Q28)) -> 10794 | S28: 8739 | T28: 9312 | U28: 10656 | V28: =SUM(I28-SUM(S28:U28)) -> 11633 | W28: 10379 | X28: 11203 | Y28: 12870 | AA28: =SUM(L28:O28) -> 29657 | AB28: =SUM(M28:P28) -> 31246 | AC28: =SUM(N28:Q28) -> 32690 | AD28: =SUM(O28:R28) -> 34688 | AE28: =SUM(P28:S28) -> 36014 | AF28: =SUM(Q28:T28) -> 37184 | AG28: =SUM(R28:U28) -> 39501 | AH28: =SUM(S28:V28) -> 40340 | ... AK28: =SUM(V28:Y28) -> 46085 | AM28: =SUM(AK28/AG28)-1 -> 0.16667932
B29: Total Google subscriptions, platforms, and devices Revenue | C29: =SUM(C28:C28) -> 14063 | D29: =SUM(D28:D28) -> 17014 | E29: =SUM(E28:E28) -> 21711 | F29: =SUM(F28:F28) -> 28032 | G29: =SUM(G28:G28) -> 29055 | H29: =SUM(H28:H28) -> 34688 | I29: =SUM(I28:I28) -> 40340 | K29: =SUM(K28:K28) -> 6811 | L29: =SUM(L28:L28) -> 6553 | M29: =SUM(M28:M28) -> 6895 | N29: =SUM(N28:N28) -> 8796 | O29: =SUM(O28:O28) -> 7413 | P29: =SUM(P28:P28) -> 8142 | Q29: =SUM(Q28:Q28) -> 8339 | R29: =SUM(R28:R28) -> 10794 | ... Y29: =SUM(Y28:Y28) -> 12870 | AA29: =SUM(AA28:AA28) -> 29657 | AB29: =SUM(AB28:AB28) -> 31246 | AC29: =SUM(AC28:AC28) -> 32690 | AD29: =SUM(AD28:AD28) -> 34688 | AE29: =SUM(AE28:AE28) -> 36014 | AF29: =SUM(AF28:AF28) -> 37184 | AG29: =SUM(AG28:AG28) -> 39501 | AH29: =SUM(AH28:AH28) -> 40340 | ... AK29: =SUM(AK28:AK28) -> 46085 | AM29: =SUM(AK29/AG29)-1 -> 0.16667932
A31: X | B31: Revenues Disaggregated by Geography
B33: Google Advertising
B34: United States | C34: 63269 | D34: 74843 | E34: 85014 | F34: 117854 | G34: 134814 | H34: 146286 | I34: 170447 | K34: 31733 | L34: 32727 | M34: 33372 | N34: =SUM(G34-SUM(K34:M34)) -> 36982 | O34: 32864 | P34: 35073 | Q34: 36354 | R34: =SUM(H34-SUM(O34:Q34)) -> 41995 | S34: 38737 | T34: 41196 | U34: 43139 | V34: =SUM(I34-SUM(S34:U34)) -> 47375 | W34: 43964 | X34: 46063 | Y34: 48758 | AA34: =SUM(L34:O34) -> 135945 | AB34: =SUM(M34:P34) -> 138291 | AC34: =SUM(N34:Q34) -> 141273 | AD34: =SUM(O34:R34) -> 146286 | AE34: =SUM(P34:S34) -> 152159 | AF34: =SUM(Q34:T34) -> 158282 | AG34: =SUM(R34:U34) -> 165067 | AH34: =SUM(S34:V34) -> 170447 | ... AK34: =SUM(V34:Y34) -> 186160 | AM34: =SUM(AK34/AG34)-1 -> 0.12778448
B35: EMEA | C35: 44739 | D35: 50645 | E35: 55370 | F35: 79107 | G35: 82062 | H35: 91038 | I35: 102127 | K35: 20317 | L35: 20533 | M35: 19450 | N35: =SUM(G35-SUM(K35:M35)) -> 21762 | O35: 21078 | P35: 22289 | Q35: 22661 | R35: =SUM(H35-SUM(O35:Q35)) -> 25010 | S35: 23788 | T35: 24683 | U35: 25472 | V35: =SUM(I35-SUM(S35:U35)) -> 28184 | W35: 25923 | X35: 28262 | Y35: 29911 | AG35: =SUM(R35:U35) -> 98953 | AH35: =SUM(S35:V35) -> 102127 | AI35: =SUM(T35:W35) -> 104262 | AJ35: =SUM(U35:X35) -> 107841 | AK35: =SUM(V35:Y35) -> 112280 | AM35: =SUM(AK35/AG35)-1 -> 0.1346801
B36: APAC | C36: 21341 | D36: 26928 | E36: 32550 | F36: 46123 | G36: 47024 | H36: 51514 | I36: 56815 | K36: 11841 | L36: 11710 | M36: 11494 | N36: =SUM(G36-SUM(K36:M36)) -> 11979 | O36: 11681 | P36: 12728 | Q36: 13126 | R36: =SUM(H36-SUM(O36:Q36)) -> 13979 | S36: 13289 | T36: 13823 | U36: 14547 | V36: =SUM(I36-SUM(S36:U36)) -> 15156 | W36: 14854 | X36: 16480 | Y36: 17819 | AG36: =SUM(R36:U36) -> 55638 | AH36: =SUM(S36:V36) -> 56815 | AI36: =SUM(T36:W36) -> 58380 | AJ36: =SUM(U36:X36) -> 61037 | AK36: =SUM(V36:Y36) -> 64309 | AM36: =SUM(AK36/AG36)-1 -> 0.15584672
B37: Other Americas | C37: 7608 | D37: 8986 | E37: 9417 | F37: 14404 | G37: 16976 | H37: 18320 | I37: 20418 | K37: 3842 | L37: 4340 | M37: 4138 | N37: =SUM(G37-SUM(K37:M37)) -> 4656 | O37: 4080 | P37: 4511 | Q37: 4553 | R37: =SUM(H37-SUM(O37:Q37)) -> 5176 | S37: 4653 | T37: 4938 | U37: 5093 | V37: =SUM(I37-SUM(S37:U37)) -> 5734 | W37: 5233 | X37: 5735 | Y37: 6065 | AG37: =SUM(R37:U37) -> 19860 | AH37: =SUM(S37:V37) -> 20418 | AI37: =SUM(T37:W37) -> 20998 | AJ37: =SUM(U37:X37) -> 21795 | AK37: =SUM(V37:Y37) -> 22767 | AM37: =SUM(AK37/AG37)-1 -> 0.14637462
B38: Hedging gains (losses) | C38: -138 | D38: 455 | E38: 176 | F38: 149 | G38: 1960 | H38: 236 | I38: 211 | K38: 278 | L38: 375 | M38: 638 | N38: =SUM(G38-SUM(K38:M38)) -> 669 | O38: 84 | P38: 3 | Q38: -1 | R38: =SUM(H38-SUM(O38:Q38)) -> 150 | S38: 72 | T38: 102 | U38: 17 | V38: =SUM(I38-SUM(S38:U38)) -> 20 | W38: 260 | X38: -112 | Y38: -207 | AA38: =SUM(L38:O38) -> 1766 | AB38: =SUM(M38:P38) -> 1394 | AC38: =SUM(N38:Q38) -> 755 | AD38: =SUM(O38:R38) -> 236 | AE38: =SUM(P38:S38) -> 224 | AF38: =SUM(Q38:T38) -> 323 | AG38: =SUM(R38:U38) -> 341 | AH38: =SUM(S38:V38) -> 211 | ... AK38: =SUM(V38:Y38) -> -39 | AM38: =SUM(AK38/AG38)-1 -> -1.1143695
B39: Total Google Advertising Revenue | C39: =SUM(C34:C38) -> 136819 | D39: =SUM(D34:D38) -> 161857 | E39: =SUM(E34:E38) -> 182527 | F39: =SUM(F34:F38) -> 257637 | G39: =SUM(G34:G38) -> 282836 | H39: =SUM(H34:H38) -> 307394 | I39: =SUM(I34:I38) -> 350018 | K39: =SUM(K34:K38) -> 68011 | L39: =SUM(L34:L38) -> 69685 | M39: =SUM(M34:M38) -> 69092 | N39: =SUM(N34:N38) -> 76048 | O39: =SUM(O34:O38) -> 69787 | P39: =SUM(P34:P38) -> 74604 | Q39: =SUM(Q34:Q38) -> 76693 | R39: =SUM(R34:R38) -> 86310 | ... Y39: =SUM(Y34:Y38) -> 102346 | AA39: =SUM(AA34:AA38) -> 137711 | AB39: =SUM(AB34:AB38) -> 139685 | AC39: =SUM(AC34:AC38) -> 142028 | AD39: =SUM(AD34:AD38) -> 146522 | AE39: =SUM(AE34:AE38) -> 152383 | AF39: =SUM(AF34:AF38) -> 158605 | AG39: =SUM(AG34:AG38) -> 339859 | AH39: =SUM(AH34:AH38) -> 350018 | ... AK39: =SUM(AK34:AK38) -> 385477 | AM39: =SUM(AK39/AG39)-1 -> 0.13422625
B40: Variance Check | C40: =+C39-'Historical Financials'!C11 -> 0 | D40: =+D39-'Historical Financials'!D11 -> 0 | E40: =+E39-'Historical Financials'!E11 -> 0 | F40: =+F39-'Historical Financials'!F11 -> 0 | G40: =+G39-'Historical Financials'!G11 -> 0 | H40: =+H39-'Historical Financials'!H11 -> 0 | I40: =+I39-'Historical Financials'!I11 -> 0 | K40: =+K39-'Historical Financials'!O11 -> 0 | L40: =+L39-'Historical Financials'!P11 -> 0 | M40: =+M39-'Historical Financials'!Q11 -> 0 | N40: =+N39-'Historical Financials'!R11 -> 0 | O40: =+O39-'Historical Financials'!S11 -> 0 | P40: =+P39-'Historical Financials'!T11 -> 0 | Q40: =+Q39-'Historical Financials'!U11 -> 0 | R40: =+R39-'Historical Financials'!V11 -> 0 | ... Y40: =+Y39-'Historical Financials'!AC11 -> 0 | AA40: =+AA39-'Historical Financials'!AN11 -> -146901 | AB40: =+AB39-'Historical Financials'!AO11 -> -149846 | AC40: =+AC39-'Historical Financials'!AP11 -> -155104 | AD40: =+AD39-'Historical Financials'!AQ11 -> -160872 | AE40: =+AE39-'Historical Financials'!AR11 -> -165763 | AF40: =+AF39-'Historical Financials'!AS11 -> -169679 | AG40: =+AG39-'Historical Financials'!AT11 -> 0 | AH40: =+AH39-'Historical Financials'!AU11 -> 0 | ... AK40: =+AK39-'Historical Financials'!AX11 -> 0

Sheet FCF
B2: ='Historical Financials'!B2 -> Alphabet Inc. (NASDAQ: GOOG) | C2: FYE | E2: FYE | I2: Quarterly | S2: Quarterly | Y2: LTM | AF2: LTM | AG2: LTM | AM2: Variance
B3: FCF Analysis | C3: ='Historical Financials'!E7 -> 2020 | D3: ='Historical Financials'!F7 -> 2021 | E3: ='Historical Financials'!G7 -> 2022 | F3: ='Historical Financials'!H7 -> 2023 | G3: ='Historical Financials'!I7 -> 2024 | I3: ='Historical Financials'!O7 -> 1Q22 | J3: ='Historical Financials'!P7 -> 2Q22 | K3: ='Historical Financials'!Q7 -> 3Q22 | L3: ='Historical Financials'!R7 -> 4Q22 | M3: ='Historical Financials'!S7 -> 1Q23 | N3: ='Historical Financials'!T7 -> 2Q23 | O3: ='Historical Financials'!U7 -> 3Q23 | P3: ='Historical Financials'!V7 -> 4Q23 | ... W3: ='Historical Financials'!AC7 -> 3Q25 | Y3: =K3 -> 3Q22 | Z3: =L3 -> 4Q22 | AA3: =M3 -> 1Q23 | AB3: =N3 -> 2Q23 | AC3: =O3 -> 3Q23 | AD3: =P3 -> 4Q23 | AE3: =Q3 -> 1Q24 | AF3: =R3 -> 2Q24 | ... AK3: =W3 -> 3Q25
B4: $ mm except per share | C4: ='Historical Financials'!E8 -> 44196 | D4: ='Historical Financials'!F8 -> 44561 | E4: ='Historical Financials'!G8 -> 44926 | F4: ='Historical Financials'!H8 -> 45291 | G4: ='Historical Financials'!I8 -> 45657 | I4: ='Historical Financials'!O8 -> 44651 | J4: ='Historical Financials'!P8 -> 44742 | K4: ='Historical Financials'!Q8 -> 44834 | L4: ='Historical Financials'!R8 -> 44926 | M4: ='Historical Financials'!S8 -> 45016 | N4: ='Historical Financials'!T8 -> 45107 | O4: ='Historical Financials'!U8 -> 45199 | P4: ='Historical Financials'!V8 -> 45291 | ... W4: ='Historical Financials'!AC8 -> 45930 | Y4: =K4 -> 44834 | Z4: =L4 -> 44926 | AA4: =M4 -> 45016 | AB4: =N4 -> 45107 | AC4: =O4 -> 45199 | AD4: =P4 -> 45291 | AE4: =Q4 -> 45382 | AF4: =R4 -> 45473 | ... AK4: =W4 -> 45930
B6: ='Revenue Drivers'!B9 -> Google Services | C6: ='Revenue Drivers'!E9 -> 168635 | D6: ='Revenue Drivers'!F9 -> 237529 | E6: ='Revenue Drivers'!G9 -> 253528 | F6: ='Revenue Drivers'!H9 -> 272543 | G6: ='Revenue Drivers'!I9 -> 304930 | I6: ='Revenue Drivers'!K9 -> 61472 | J6: ='Revenue Drivers'!L9 -> 62841 | K6: ='Revenue Drivers'!M9 -> 61377 | L6: ='Revenue Drivers'!N9 -> 67838 | M6: ='Revenue Drivers'!O9 -> 61961 | N6: ='Revenue Drivers'!P9 -> 66285 | O6: ='Revenue Drivers'!Q9 -> 67986 | P6: ='Revenue Drivers'!R9 -> 76311 | ... W6: ='Revenue Drivers'!Y9 -> 87052 | Y6: =SUM(H6:K6) -> 185690 | Z6: =SUM(I6:L6) -> 253528 | AA6: =SUM(J6:M6) -> 254017 | AB6: =SUM(K6:N6) -> 257461 | AC6: =SUM(L6:O6) -> 264070 | AD6: =SUM(M6:P6) -> 272543 | AE6: =SUM(N6:Q6) -> 280980 | AF6: =SUM(O6:R6) -> 288623 | ... AK6: =SUM(T6:W6) -> 330953 | AM6: =SUM(AK6/AG6)-1 -> 0.11376861
B7: ='Revenue Drivers'!B10 -> Google Cloud | C7: ='Revenue Drivers'!E10 -> 13059 | D7: ='Revenue Drivers'!F10 -> 19206 | E7: ='Revenue Drivers'!G10 -> 26280 | F7: ='Revenue Drivers'!H10 -> 33088 | G7: ='Revenue Drivers'!I10 -> 43229 | I7: ='Revenue Drivers'!K10 -> 5821 | J7: ='Revenue Drivers'!L10 -> 6276 | K7: ='Revenue Drivers'!M10 -> 6868 | L7: ='Revenue Drivers'!N10 -> 7315 | M7: ='Revenue Drivers'!O10 -> 7454 | N7: ='Revenue Drivers'!P10 -> 8031 | O7: ='Revenue Drivers'!Q10 -> 8411 | P7: ='Revenue Drivers'!R10 -> 9192 | ... W7: ='Revenue Drivers'!Y10 -> 15157 | AG7: =SUM(P7:S7) -> 40466 | AH7: =SUM(Q7:T7) -> 43229 | AI7: =SUM(R7:U7) -> 45915 | AJ7: =SUM(S7:V7) -> 49192 | AK7: =SUM(T7:W7) -> 52996 | AM7: =SUM(AK7/AG7)-1 -> 0.30964266
B8: ='Revenue Drivers'!B11 -> Other Bets | C8: ='Revenue Drivers'!E11 -> 657 | D8: ='Revenue Drivers'!F11 -> 753 | E8: ='Revenue Drivers'!G11 -> 1068 | F8: ='Revenue Drivers'!H11 -> 1527 | G8: ='Revenue Drivers'!I11 -> 1648 | I8: ='Revenue Drivers'!K11 -> 440 | J8: ='Revenue Drivers'!L11 -> 193 | K8: ='Revenue Drivers'!M11 -> 209 | L8: ='Revenue Drivers'!N11 -> 226 | M8: ='Revenue Drivers'!O11 -> 288 | N8: ='Revenue Drivers'!P11 -> 285 | O8: ='Revenue Drivers'!Q11 -> 297 | P8: ='Revenue Drivers'!R11 -> 657 | ... W8: ='Revenue Drivers'!Y11 -> 344 | AG8: =SUM(P8:S8) -> 1905 | AH8: =SUM(Q8:T8) -> 1648 | AI8: =SUM(R8:U8) -> 1603 | AJ8: =SUM(S8:V8) -> 1611 | AK8: =SUM(T8:W8) -> 1567 | AM8: =SUM(AK8/AG8)-1 -> -0.17742782
B9: ='Revenue Drivers'!B12 -> Hedging gains (losses) | C9: ='Revenue Drivers'!E12 -> 176 | D9: ='Revenue Drivers'!F12 -> 149 | E9: ='Revenue Drivers'!G12 -> 1960 | F9: ='Revenue Drivers'!H12 -> 236 | G9: ='Revenue Drivers'!I12 -> 211 | I9: ='Revenue Drivers'!K12 -> 278 | J9: ='Revenue Drivers'!L12 -> 375 | K9: ='Revenue Drivers'!M12 -> 638 | L9: ='Revenue Drivers'!N12 -> 669 | M9: ='Revenue Drivers'!O12 -> 84 | N9: ='Revenue Drivers'!P12 -> 3 | O9: ='Revenue Drivers'!Q12 -> -1 | P9: ='Revenue Drivers'!R12 -> 150 | ... W9: ='Revenue Drivers'!Y12 -> -207 | AG9: =SUM(P9:S9) -> 341 | AH9: =SUM(Q9:T9) -> 211 | AI9: =SUM(R9:U9) -> 399 | AJ9: =SUM(S9:V9) -> 185 | AK9: =SUM(T9:W9) -> -39 | AM9: =SUM(AK9/AG9)-1 -> -1.1143695
B10: Total Revenue | C10: =SUM(C6:C9) -> 182527 | D10: =SUM(D6:D9) -> 257637 | E10: =SUM(E6:E9) -> 282836 | F10: =SUM(F6:F9) -> 307394 | G10: =SUM(G6:G9) -> 350018 | I10: =SUM(I6:I9) -> 68011 | J10: =SUM(J6:J9) -> 69685 | K10: =SUM(K6:K9) -> 69092 | L10: =SUM(L6:L9) -> 76048 | M10: =SUM(M6:M9) -> 69787 | N10: =SUM(N6:N9) -> 74604 | O10: =SUM(O6:O9) -> 76693 | P10: =SUM(P6:P9) -> 86310 | ... W10: =SUM(W6:W9) -> 102346 | Y10: =SUM(Y6:Y9) -> 185690 | Z10: =SUM(Z6:Z9) -> 253528 | AA10: =SUM(AA6:AA9) -> 254017 | AB10: =SUM(AB6:AB9) -> 257461 | AC10: =SUM(AC6:AC9) -> 264070 | AD10: =SUM(AD6:AD9) -> 272543 | AE10: =SUM(AE6:AE9) -> 280980 | AF10: =SUM(AF6:AF9) -> 288623 | ... AK10: =SUM(AK6:AK9) -> 385477 | AM10: =SUM(AK10/AG10)-1 -> 0.13422625
B11: Y/Y Growth (%) | D11: =SUM(D10/C10)-1 -> 0.41150076 | E11: =SUM(E10/D10)-1 -> 0.097808156 | F11: =SUM(F10/E10)-1 -> 0.086827702 | G11: =SUM(G10/F10)-1 -> 0.13866243 | M11: =SUM(M10/I10)-1 -> 0.026113423 | N11: =SUM(N10/J10)-1 -> 0.070589079 | O11: =SUM(O10/K10)-1 -> 0.11001274 | P11: =SUM(P10/L10)-1 -> 0.13494109 | Q11: =SUM(Q10/M10)-1 -> 0.15406881 | R11: =SUM(R10/N10)-1 -> 0.13589084 | S11: =SUM(S10/O10)-1 -> 0.15092642 | T11: =SUM(T10/P10)-1 -> 0.11770363 | ... W11: =SUM(W10/S10)-1 -> 0.15949155 | AC11: =SUM(AC10/Y10)-1 -> 0.42210135 | AD11: =SUM(AD10/Z10)-1 -> 0.075001578 | AE11: =SUM(AE10/AA10)-1 -> 0.10614644 | AF11: =SUM(AF10/AB10)-1 -> 0.12103581 | AG11: =SUM(AG10/AC10)-1 -> 0.28700345 | AH11: =SUM(AH10/AD10)-1 -> 0.28426707 | AI11: =SUM(AI10/AE10)-1 -> 0.28020856 | AJ11: =SUM(AJ10/AF10)-1 -> 0.28679627 | AK11: =SUM(AK10/AG10)-1 -> 0.13422625 | AM11: =SUM(AK11-AG11)*10000 -> -1527.7719
B12: Q/Q Growth (%) | C12: N/A | D12: N/A | E12: N/A | F12: N/A | G12: N/A | J12: =SUM(J10/I10)-1 -> 0.024613665 | K12: =SUM(K10/J10)-1 -> -0.0085097223 | L12: =SUM(L10/K10)-1 -> 0.10067736 | M12: =SUM(M10/L10)-1 -> -0.082329581 | N12: =SUM(N10/M10)-1 -> 0.069024317 | O12: =SUM(O10/N10)-1 -> 0.02800118 | P12: =SUM(P10/O10)-1 -> 0.12539606 | Q12: =SUM(Q10/P10)-1 -> -0.066863631 | ... W12: =SUM(W10/V10)-1 -> 0.061372216 | Y12: N/A | Z12: N/A | AA12: N/A | AB12: N/A | AC12: N/A | AD12: N/A | AE12: N/A | AF12: N/A | AG12: N/A | AH12: N/A | AI12: N/A | AJ12: N/A | AK12: N/A
B14: (-) Cost of Sales | C14: ='Historical Financials'!E13 -> -84732 | D14: ='Historical Financials'!F13 -> -110939 | E14: ='Historical Financials'!G13 -> -126203 | F14: ='Historical Financials'!H13 -> -133332 | G14: ='Historical Financials'!I13 -> -146306 | I14: ='Historical Financials'!O13 -> -29599 | J14: ='Historical Financials'!P13 -> -30104 | K14: ='Historical Financials'!Q13 -> -31158 | L14: ='Historical Financials'!R13 -> -35342 | M14: ='Historical Financials'!S13 -> -30612 | N14: ='Historical Financials'!T13 -> -31916 | O14: ='Historical Financials'!U13 -> -33229 | P14: ='Historical Financials'!V13 -> -37575 | ... W14: ='Historical Financials'!AC13 -> -41369 | Y14: =SUM(H14:K14) -> -90861 | Z14: =SUM(I14:L14) -> -126203 | AA14: =SUM(J14:M14) -> -127216 | AB14: =SUM(K14:N14) -> -129028 | AC14: =SUM(L14:O14) -> -131099 | AD14: =SUM(M14:P14) -> -133332 | AE14: =SUM(N14:Q14) -> -136432 | AF14: =SUM(O14:R14) -> -140023 | ... AK14: =SUM(T14:W14) -> -157382 | AM14: =SUM(AK14/AG14)-1 -> 0.098514672
B15: Gross Profit | C15: =+C10+C14 -> 97795 | D15: =+D10+D14 -> 146698 | E15: =+E10+E14 -> 156633 | F15: =+F10+F14 -> 174062 | G15: =+G10+G14 -> 203712 | I15: =+I10+I14 -> 38412 | J15: =+J10+J14 -> 39581 | K15: =+K10+K14 -> 37934 | L15: =+L10+L14 -> 40706 | M15: =+M10+M14 -> 39175 | N15: =+N10+N14 -> 42688 | O15: =+O10+O14 -> 43464 | P15: =+P10+P14 -> 48735 | ... W15: =+W10+W14 -> 60977 | Y15: =+Y10+Y14 -> 94829 | Z15: =+Z10+Z14 -> 127325 | AA15: =+AA10+AA14 -> 126801 | AB15: =+AB10+AB14 -> 128433 | AC15: =+AC10+AC14 -> 132971 | AD15: =+AD10+AD14 -> 139211 | AE15: =+AE10+AE14 -> 144548 | AF15: =+AF10+AF14 -> 148600 | ... AK15: =+AK10+AK14 -> 228095 | AM15: =SUM(AK15/AG15)-1 -> 0.16025149
B16: Gross Margin (%) | C16: =C15/C10 -> 0.53578375 | D16: =D15/D10 -> 0.56939803 | E16: =E15/E10 -> 0.55379443 | F16: =F15/F10 -> 0.56625048 | G16: =G15/G10 -> 0.58200435 | I16: =I15/I10 -> 0.56479099 | J16: =J15/J10 -> 0.56799885 | K16: =K15/K10 -> 0.54903607 | L16: =L15/L10 -> 0.5352672 | M16: =M15/M10 -> 0.56135097 | N16: =N15/N10 -> 0.57219452 | O16: =O15/O10 -> 0.56672708 | P16: =P15/P10 -> 0.56465068 | ... W16: =W15/W10 -> 0.5957927 | Y16: =Y15/Y10 -> 0.51068447 | Z16: =Z15/Z10 -> 0.50221277 | AA16: =AA15/AA10 -> 0.49918313 | AB16: =AB15/AB10 -> 0.49884449 | AC16: =AC15/AC10 -> 0.50354451 | AD16: =AD15/AD10 -> 0.51078545 | AE16: =AE15/AE10 -> 0.51444231 | AF16: =AF15/AF10 -> 0.51485848 | ... AK16: =AK15/AK10 -> 0.59172143 | AM16: =SUM(AK16-AG16)*10000 -> 132.72716
B18: (-) Research & Development (R&D) | C18: ='Historical Financials'!E17 -> -27573 | D18: ='Historical Financials'!F17 -> -31562 | E18: ='Historical Financials'!G17 -> -39500 | F18: ='Historical Financials'!H17 -> -45427 | G18: ='Historical Financials'!I17 -> -49326 | I18: ='Historical Financials'!O17 -> -9119 | J18: ='Historical Financials'!P17 -> -9841 | K18: ='Historical Financials'!Q17 -> -10273 | L18: ='Historical Financials'!R17 -> -10267 | M18: ='Historical Financials'!S17 -> -11468 | N18: ='Historical Financials'!T17 -> -10588 | O18: ='Historical Financials'!U17 -> -11258 | P18: ='Historical Financials'!V17 -> -12113 | ... W18: ='Historical Financials'!AC17 -> -15151 | Y18: =SUM(H18:K18) -> -29233 | Z18: =SUM(I18:L18) -> -39500 | AA18: =SUM(J18:M18) -> -41849 | AB18: =SUM(K18:N18) -> -42596 | AC18: =SUM(L18:O18) -> -43581 | AD18: =SUM(M18:P18) -> -45427 | AE18: =SUM(N18:Q18) -> -45862 | AF18: =SUM(O18:R18) -> -47134 | ... AK18: =SUM(T18:W18) -> -55631 | AM18: =SUM(AK18/AG18)-1 -> 0.15123233
B19: (-) Sales and Marketing (S&M) | C19: ='Historical Financials'!E18 -> -17946 | D19: ='Historical Financials'!F18 -> -22912 | E19: ='Historical Financials'!G18 -> -26567 | F19: ='Historical Financials'!H18 -> -27917 | G19: ='Historical Financials'!I18 -> -27808 | I19: ='Historical Financials'!O18 -> -5825 | J19: ='Historical Financials'!P18 -> -6630 | K19: ='Historical Financials'!Q18 -> -6929 | L19: ='Historical Financials'!R18 -> -7183 | M19: ='Historical Financials'!S18 -> -6533 | N19: ='Historical Financials'!T18 -> -6781 | O19: ='Historical Financials'!U18 -> -6884 | P19: ='Historical Financials'!V18 -> -7719 | ... W19: ='Historical Financials'!AC18 -> -7205 | Y19: =SUM(H19:K19) -> -19384 | Z19: =SUM(I19:L19) -> -26567 | AA19: =SUM(J19:M19) -> -27275 | AB19: =SUM(K19:N19) -> -27426 | AC19: =SUM(L19:O19) -> -27381 | AD19: =SUM(M19:P19) -> -27917 | AE19: =SUM(N19:Q19) -> -27810 | AF19: =SUM(O19:R19) -> -27821 | ... AK19: =SUM(T19:W19) -> -27841 | AM19: =SUM(AK19/AG19)-1 -> -0.011468541
B20: (-) General and Administrative (G&A) | C20: ='Historical Financials'!E19 -> -11052 | D20: ='Historical Financials'!F19 -> -13510 | E20: ='Historical Financials'!G19 -> -15724 | F20: ='Historical Financials'!H19 -> -16425 | G20: ='Historical Financials'!I19 -> -14188 | I20: ='Historical Financials'!O19 -> -3374 | J20: ='Historical Financials'!P19 -> -3657 | K20: ='Historical Financials'!Q19 -> -3597 | L20: ='Historical Financials'!R19 -> -5096 | M20: ='Historical Financials'!S19 -> -3759 | N20: ='Historical Financials'!T19 -> -3481 | O20: ='Historical Financials'!U19 -> -3979 | P20: ='Historical Financials'!V19 -> -5206 | ... W20: ='Historical Financials'!AC19 -> -7393 | Y20: =SUM(H20:K20) -> -10628 | Z20: =SUM(I20:L20) -> -15724 | AA20: =SUM(J20:M20) -> -16109 | AB20: =SUM(K20:N20) -> -15933 | AC20: =SUM(L20:O20) -> -16315 | AD20: =SUM(M20:P20) -> -16425 | AE20: =SUM(N20:Q20) -> -15692 | AF20: =SUM(O20:R20) -> -15369 | ... AK20: =SUM(T20:W20) -> -20546 | AM20: =SUM(AK20/AG20)-1 -> 0.37073854
B21: Earning before Interest & Taxes (EBIT) | C21: =SUM(C15+SUM(C18:C20)) -> 41224 | D21: =SUM(D15+SUM(D18:D20)) -> 78714 | E21: =SUM(E15+SUM(E18:E20)) -> 74842 | F21: =SUM(F15+SUM(F18:F20)) -> 84293 | G21: =SUM(G15+SUM(G18:G20)) -> 112390 | I21: =SUM(I15+SUM(I18:I20)) -> 20094 | J21: =SUM(J15+SUM(J18:J20)) -> 19453 | K21: =SUM(K15+SUM(K18:K20)) -> 17135 | L21: =SUM(L15+SUM(L18:L20)) -> 18160 | M21: =SUM(M15+SUM(M18:M20)) -> 17415 | N21: =SUM(N15+SUM(N18:N20)) -> 21838 | O21: =SUM(O15+SUM(O18:O20)) -> 21343 | P21: =SUM(P15+SUM(P18:P20)) -> 23697 | ... W21: =SUM(W15+SUM(W18:W20)) -> 31228 | Y21: =SUM(Y15+SUM(Y18:Y20)) -> 35584 | Z21: =SUM(Z15+SUM(Z18:Z20)) -> 45534 | AA21: =SUM(AA15+SUM(AA18:AA20)) -> 41568 | AB21: =SUM(AB15+SUM(AB18:AB20)) -> 42478 | AC21: =SUM(AC15+SUM(AC18:AC20)) -> 45694 | AD21: =SUM(AD15+SUM(AD18:AD20)) -> 49442 | AE21: =SUM(AE15+SUM(AE18:AE20)) -> 55184 | AF21: =SUM(AF15+SUM(AF18:AF20)) -> 58276 | ... AK21: =SUM(AK15+SUM(AK18:AK20)) -> 124077 | AM21: =SUM(AK21/AG21)-1 -> 0.1803929
B22: Operating Margin (%) | C22: =C21/C10 -> 0.22585152 | D22: =D21/D10 -> 0.30552289 | E22: =E21/E10 -> 0.26461271 | F22: =F21/F10 -> 0.2742181 | G22: =G21/G10 -> 0.32109777 | I22: =I21/I10 -> 0.29545221 | J22: =J21/J10 -> 0.2791562 | K22: =K21/K10 -> 0.24800266 | L22: =L21/L10 -> 0.23879655 | M22: =M21/M10 -> 0.24954504 | N22: =N21/N10 -> 0.29271889 | O22: =O21/O10 -> 0.27829137 | P22: =P21/P10 -> 0.27455683 | ... W22: =W21/W10 -> 0.30512184 | Y22: =Y21/Y10 -> 0.19163121 | Z22: =Z21/Z10 -> 0.17960146 | AA22: =AA21/AA10 -> 0.16364259 | AB22: =AB21/AB10 -> 0.1649881 | AC22: =AC21/AC10 -> 0.17303745 | AD22: =AD21/AD10 -> 0.18140991 | AE22: =AE21/AE10 -> 0.19639832 | AF22: =AF21/AF10 -> 0.20191045 | ... AK22: =AK21/AK10 -> 0.32187913 | AM22: =SUM(AK22-AG22)*10000 -> 125.89097
B24: (+) Depreciation and Amortization | C24: ='Historical Financials'!E90 -> 13697 | D24: ='Historical Financials'!F90 -> 12441 | E24: ='Historical Financials'!G90 -> 13475 | F24: ='Historical Financials'!H90 -> 11946 | G24: ='Historical Financials'!I90 -> 15311 | I24: ='Historical Financials'!O90 -> 3782 | J24: ='Historical Financials'!P90 -> 3899 | K24: ='Historical Financials'!Q90 -> 4046 | L24: ='Historical Financials'!R90 -> 1748 | M24: ='Historical Financials'!S90 -> 3186 | N24: ='Historical Financials'!T90 -> 3397 | O24: ='Historical Financials'!U90 -> 3800 | P24: ='Historical Financials'!V90 -> 1563 | ... W24: ='Historical Financials'!AC90 -> 5611 | Y24: =SUM(H24:K24) -> 11727 | Z24: =SUM(I24:L24) -> 13475 | AA24: =SUM(J24:M24) -> 12879 | AB24: =SUM(K24:N24) -> 12377 | AC24: =SUM(L24:O24) -> 12131 | AD24: =SUM(M24:P24) -> 11946 | AE24: =SUM(N24:Q24) -> 12173 | AF24: =SUM(O24:R24) -> 12484 | ... AK24: =SUM(T24:W24) -> 19301 | AM24: =SUM(AK24/AG24)-1 -> 0.52348252
B25: EBITDA | C25: =SUM(C21+C24) -> 54921 | D25: =SUM(D21+D24) -> 91155 | E25: =SUM(E21+E24) -> 88317 | F25: =SUM(F21+F24) -> 96239 | G25: =SUM(G21+G24) -> 127701 | I25: =SUM(I21+I24) -> 23876 | J25: =SUM(J21+J24) -> 23352 | K25: =SUM(K21+K24) -> 21181 | L25: =SUM(L21+L24) -> 19908 | M25: =SUM(M21+M24) -> 20601 | N25: =SUM(N21+N24) -> 25235 | O25: =SUM(O21+O24) -> 25143 | P25: =SUM(P21+P24) -> 25260 | ... W25: =SUM(W21+W24) -> 36839 | Y25: =SUM(Y21+Y24) -> 47311 | Z25: =SUM(Z21+Z24) -> 59009 | AA25: =SUM(AA21+AA24) -> 54447 | AB25: =SUM(AB21+AB24) -> 54855 | AC25: =SUM(AC21+AC24) -> 57825 | AD25: =SUM(AD21+AD24) -> 61388 | AE25: =SUM(AE21+AE24) -> 67357 | AF25: =SUM(AF21+AF24) -> 70760 | ... AK25: =SUM(AK21+AK24) -> 143378 | AM25: =SUM(AK25/AG25)-1 -> 0.21729607
B26: EBITDA Margin (%) | C26: =C25/C10 -> 0.30089247 | D26: =D25/D10 -> 0.35381176 | E26: =E25/E10 -> 0.31225516 | F26: =F25/F10 -> 0.31308028 | G26: =G25/G10 -> 0.36484124 | I26: =I25/I10 -> 0.35106086 | J26: =J25/J10 -> 0.33510799 | K26: =K25/K10 -> 0.30656226 | L26: =L25/L10 -> 0.26178203 | M26: =M25/M10 -> 0.29519825 | N26: =N25/N10 -> 0.33825264 | O26: =O25/O10 -> 0.32783957 | P26: =P25/P10 -> 0.29266597 | ... W26: =W25/W10 -> 0.35994567 | Y26: =Y25/Y10 -> 0.25478486 | Z26: =Z25/Z10 -> 0.23275141 | AA26: =AA25/AA10 -> 0.21434392 | AB26: =AB25/AB10 -> 0.2130614 | AC26: =AC25/AC10 -> 0.21897603 | AD26: =AD25/AD10 -> 0.22524152 | AE26: =AE25/AE10 -> 0.23972169 | AF26: =AF25/AF10 -> 0.24516411 | ... AK26: =AK25/AK10 -> 0.37194956 | AM26: =SUM(AK26-AG26)*10000 -> 253.82306
B28: (+) Share-based Compensation | C28: ='Historical Financials'!E91 -> 12991 | D28: ='Historical Financials'!F91 -> 15376 | E28: ='Historical Financials'!G91 -> 19362 | F28: ='Historical Financials'!H91 -> 22460 | G28: ='Historical Financials'!I91 -> 22785 | I28: ='Historical Financials'!O91 -> 4504 | J28: ='Historical Financials'!P91 -> 4782 | K28: ='Historical Financials'!Q91 -> 4976 | L28: ='Historical Financials'!R91 -> 5100 | M28: ='Historical Financials'!S91 -> 5284 | N28: ='Historical Financials'!T91 -> 5774 | O28: ='Historical Financials'!U91 -> 5743 | P28: ='Historical Financials'!V91 -> 5659 | ... W28: ='Historical Financials'!AC91 -> 6368 | Y28: =SUM(H28:K28) -> 14262 | Z28: =SUM(I28:L28) -> 19362 | AA28: =SUM(J28:M28) -> 20142 | AB28: =SUM(K28:N28) -> 21134 | AC28: =SUM(L28:O28) -> 21901 | AD28: =SUM(M28:P28) -> 22460 | AE28: =SUM(N28:Q28) -> 22440 | AF28: =SUM(O28:R28) -> 22531 | ... AK28: =SUM(T28:W28) -> 23692 | AM28: =SUM(AK28/AG28)-1 -> 0.046743837
B29: Adj. EBITDA | C29: =+SUM(C25+SUM(C28:C28)) -> 67912 | D29: =+SUM(D25+SUM(D28:D28)) -> 106531 | E29: =+SUM(E25+SUM(E28:E28)) -> 107679 | F29: =+SUM(F25+SUM(F28:F28)) -> 118699 | G29: =+SUM(G25+SUM(G28:G28)) -> 150486 | I29: =+SUM(I25+SUM(I28:I28)) -> 28380 | J29: =+SUM(J25+SUM(J28:J28)) -> 28134 | K29: =+SUM(K25+SUM(K28:K28)) -> 26157 | L29: =+SUM(L25+SUM(L28:L28)) -> 25008 | M29: =+SUM(M25+SUM(M28:M28)) -> 25885 | N29: =+SUM(N25+SUM(N28:N28)) -> 31009 | O29: =+SUM(O25+SUM(O28:O28)) -> 30886 | P29: =+SUM(P25+SUM(P28:P28)) -> 30919 | ... W29: =+SUM(W25+SUM(W28:W28)) -> 43207 | Y29: =+SUM(Y25+SUM(Y28:Y28)) -> 61573 | Z29: =+SUM(Z25+SUM(Z28:Z28)) -> 78371 | AA29: =+SUM(AA25+SUM(AA28:AA28)) -> 74589 | AB29: =+SUM(AB25+SUM(AB28:AB28)) -> 75989 | AC29: =+SUM(AC25+SUM(AC28:AC28)) -> 79726 | AD29: =+SUM(AD25+SUM(AD28:AD28)) -> 83848 | AE29: =+SUM(AE25+SUM(AE28:AE28)) -> 89797 | AF29: =+SUM(AF25+SUM(AF28:AF28)) -> 93291 | ... AK29: =+SUM(AK25+SUM(AK28:AK28)) -> 167070 | AM29: =SUM(AK29/AG29)-1 -> 0.18980473
B30: Adj. EBITDA Margin (%) | C30: =C29/C10 -> 0.3720655 | D30: =D29/D10 -> 0.41349263 | E30: =E29/E10 -> 0.38071179 | F30: =F29/F10 -> 0.38614612 | G30: =G29/G10 -> 0.42993789 | I30: =I29/I10 -> 0.41728544 | J30: =J29/J10 -> 0.40373108 | K30: =K29/K10 -> 0.37858218 | L30: =L29/L10 -> 0.32884494 | M30: =M29/M10 -> 0.37091435 | N30: =N29/N10 -> 0.41564795 | O30: =O29/O10 -> 0.40272254 | P30: =P29/P10 -> 0.35823195 | ... W30: =W29/W10 -> 0.42216599 | Y30: =Y29/Y10 -> 0.33159028 | Z30: =Z29/Z10 -> 0.30912167 | AA30: =AA29/AA10 -> 0.29363783 | AB30: =AB29/AB10 -> 0.29514761 | AC30: =AC29/AC10 -> 0.30191237 | AD30: =AD29/AD10 -> 0.30765054 | AE30: =AE29/AE10 -> 0.31958502 | AF30: =AF29/AF10 -> 0.32322788 | ... AK30: =AK29/AK10 -> 0.43341107 | AM30: =SUM(AK30-AG30)*10000 -> 202.45613
B32: (-) Capital Expenditures | C32: ='Historical Financials'!C106 -> -25139 | D32: ='Historical Financials'!D106 -> -23548 | E32: ='Historical Financials'!E106 -> -22281 | F32: ='Historical Financials'!F106 -> -24640 | G32: ='Historical Financials'!G106 -> -31485 | I32: ='Historical Financials'!O106 -> -9786 | J32: ='Historical Financials'!P106 -> -6828 | K32: ='Historical Financials'!Q106 -> -7276 | L32: ='Historical Financials'!R106 -> -7595 | M32: ='Historical Financials'!S106 -> -6289 | N32: ='Historical Financials'!T106 -> -6888 | O32: ='Historical Financials'!U106 -> -8055 | P32: ='Historical Financials'!V106 -> -11019 | ... W32: ='Historical Financials'!AC106 -> -23953 | Y32: =SUM(H32:K32) -> -23890 | Z32: =SUM(I32:L32) -> -31485 | AA32: =SUM(J32:M32) -> -27988 | AB32: =SUM(K32:N32) -> -28048 | AC32: =SUM(L32:O32) -> -28827 | AD32: =SUM(M32:P32) -> -32251 | AE32: =SUM(N32:Q32) -> -37974 | AF32: =SUM(O32:R32) -> -44272 | ... AK32: =SUM(T32:W32) -> -77872 | AM32: =SUM(AK32/AG32)-1 -> 0.58025894
B33: (-) Cash Taxes | C33: =-'Historical Financials'!E133 -> -4990 | D33: =-'Historical Financials'!F133 -> -13412 | E33: =-'Historical Financials'!G133 -> -18892 | F33: =-'Historical Financials'!H133 -> -19164 | G33: =-'Historical Financials'!I133 -> -18900 | I33: =-'Historical Financials'!O133 -> -4723 | J33: =-'Historical Financials'!P133 -> -4723 | K33: =-'Historical Financials'!Q133 -> -4723 | L33: =-'Historical Financials'!R133 -> -4723 | M33: =-'Historical Financials'!S133 -> -4791 | N33: =-'Historical Financials'!T133 -> -4791 | O33: =-'Historical Financials'!U133 -> -4791 | P33: =-'Historical Financials'!V133 -> -4791 | ... W33: =-'Historical Financials'!AC133 -> -4725 | Y33: =SUM(H33:K33) -> -14169 | Z33: =SUM(I33:L33) -> -18892 | AA33: =SUM(J33:M33) -> -18960 | AB33: =SUM(K33:N33) -> -19028 | AC33: =SUM(L33:O33) -> -19096 | AD33: =SUM(M33:P33) -> -19164 | AE33: =SUM(N33:Q33) -> -19098 | AF33: =SUM(O33:R33) -> -19032 | ... AK33: =SUM(T33:W33) -> -18900 | AM33: =SUM(AK33/AG33)-1 -> -0.0034799114
B34: (-) Cash Interest | C34: ='Historical Financials'!E25 -> -135 | D34: ='Historical Financials'!F25 -> -346 | E34: ='Historical Financials'!G25 -> -357 | F34: ='Historical Financials'!H25 -> -308 | G34: ='Historical Financials'!I25 -> -268 | I34: ='Historical Financials'!O25 -> -83 | J34: ='Historical Financials'!P25 -> -83 | K34: ='Historical Financials'!Q25 -> -101 | L34: ='Historical Financials'!R25 -> -90 | M34: ='Historical Financials'!S25 -> -80 | N34: ='Historical Financials'!T25 -> -43 | O34: ='Historical Financials'!U25 -> -116 | P34: ='Historical Financials'!V25 -> -69 | ... W34: ='Historical Financials'!AC25 -> -143 | Y34: =SUM(H34:K34) -> -267 | Z34: =SUM(I34:L34) -> -357 | AA34: =SUM(J34:M34) -> -354 | AB34: =SUM(K34:N34) -> -314 | AC34: =SUM(L34:O34) -> -329 | AD34: =SUM(M34:P34) -> -308 | AE34: =SUM(N34:Q34) -> -322 | AF34: =SUM(O34:R34) -> -346 | ... AK34: =SUM(T34:W34) -> -491 | AM34: =SUM(AK34/AG34)-1 -> 0.72887324
B35: (+/-) Changes in NWC | C35: =SUM('Historical Financials'!E96:E102) -> 1827 | D35: =SUM('Historical Financials'!F96:F102) -> -1523 | E35: =SUM('Historical Financials'!G96:G102) -> -2235 | F35: =SUM('Historical Financials'!H96:H102) -> -3845 | G35: =SUM('Historical Financials'!I96:I102) -> -8406 | I35: =SUM('Historical Financials'!O96:O102) -> 897 | J35: =SUM('Historical Financials'!P96:P102) -> -4217 | K35: =SUM('Historical Financials'!Q96:Q102) -> 796 | L35: =SUM('Historical Financials'!R96:R102) -> 289 | M35: =SUM('Historical Financials'!S96:S102) -> 1373 | N35: =SUM('Historical Financials'!T96:T102) -> 2936 | O35: =SUM('Historical Financials'!U96:U102) -> 2117 | P35: =SUM('Historical Financials'!V96:V102) -> -10271 | ... W35: =SUM('Historical Financials'!AC96:AC102) -> 3783 | Y35: =SUM(H35:K35) -> -2524 | Z35: =SUM(I35:L35) -> -2235 | AA35: =SUM(J35:M35) -> -1759 | AB35: =SUM(K35:N35) -> 5394 | AC35: =SUM(L35:O35) -> 6715 | AD35: =SUM(M35:P35) -> -3845 | AE35: =SUM(N35:Q35) -> -7681 | AF35: =SUM(O35:R35) -> -15887 | ... AK35: =SUM(T35:W35) -> -973 | AM35: =SUM(AK35/AG35)-1 -> -0.95535264
B36: Discretionary Cash-Flows | C36: =SUM(C29+SUM(C32:C35)) -> 39475 | D36: =SUM(D29+SUM(D32:D35)) -> 67702 | E36: =SUM(E29+SUM(E32:E35)) -> 63914 | F36: =SUM(F29+SUM(F32:F35)) -> 70742 | G36: =SUM(G29+SUM(G32:G35)) -> 91427 | I36: =SUM(I29+SUM(I32:I35)) -> 14685 | J36: =SUM(J29+SUM(J32:J35)) -> 12283 | K36: =SUM(K29+SUM(K32:K35)) -> 14853 | L36: =SUM(L29+SUM(L32:L35)) -> 12889 | M36: =SUM(M29+SUM(M32:M35)) -> 16098 | N36: =SUM(N29+SUM(N32:N35)) -> 22223 | O36: =SUM(O29+SUM(O32:O35)) -> 20041 | P36: =SUM(P29+SUM(P32:P35)) -> 4769 | ... W36: =SUM(W29+SUM(W32:W35)) -> 18169 | Y36: =SUM(Y29+SUM(Y32:Y35)) -> 20723 | Z36: =SUM(Z29+SUM(Z32:Z35)) -> 25402 | AA36: =SUM(AA29+SUM(AA32:AA35)) -> 25528 | AB36: =SUM(AB29+SUM(AB32:AB35)) -> 33993 | AC36: =SUM(AC29+SUM(AC32:AC35)) -> 38189 | AD36: =SUM(AD29+SUM(AD32:AD35)) -> 28280 | AE36: =SUM(AE29+SUM(AE32:AE35)) -> 24722 | AF36: =SUM(AF29+SUM(AF32:AF35)) -> 13754 | ... AK36: =SUM(AK29+SUM(AK32:AK35)) -> 68834 | AM36: =SUM(AK36/AG36)-1 -> 0.37401441
B38: (+/-) Proceeds / (Purchases) of Marketable Securities | C38: ='Historical Financials'!E107 -> -3670 | D38: ='Historical Financials'!F107 -> -6902 | E38: ='Historical Financials'!G107 -> 18948 | F38: ='Historical Financials'!H107 -> 8814 | G38: ='Historical Financials'!I107 -> 16749 | I38: ='Historical Financials'!O107 -> 1317 | J38: ='Historical Financials'!P107 -> 3858 | K38: ='Historical Financials'!Q107 -> 11659 | L38: ='Historical Financials'!R107 -> 2114 | M38: ='Historical Financials'!S107 -> 4100 | N38: ='Historical Financials'!T107 -> -2640 | O38: ='Historical Financials'!U107 -> 1760 | P38: ='Historical Financials'!V107 -> 5594 | ... W38: ='Historical Financials'!AC107 -> -593 | Y38: =SUM(H38:K38) -> 16834 | Z38: =SUM(I38:L38) -> 18948 | AA38: =SUM(J38:M38) -> 21731 | AB38: =SUM(K38:N38) -> 15233 | AC38: =SUM(L38:O38) -> 5334 | AD38: =SUM(M38:P38) -> 8814 | AE38: =SUM(N38:Q38) -> 9015 | AF38: =SUM(O38:R38) -> 22920 | ... AK38: =SUM(T38:W38) -> 471
B39: (+/-) Proceeds / (Purchases) of Non-Marketable Securities | C39: ='Historical Financials'!E108 -> -6152 | D39: ='Historical Financials'!F108 -> -1904 | E39: ='Historical Financials'!G108 -> -2381 | F39: ='Historical Financials'!H108 -> -2080 | G39: ='Historical Financials'!I108 -> -4152 | I39: ='Historical Financials'!O108 -> -764 | J39: ='Historical Financials'!P108 -> -375 | K39: ='Historical Financials'!Q108 -> -358 | L39: ='Historical Financials'!R108 -> -884 | M39: ='Historical Financials'!S108 -> -590 | N39: ='Historical Financials'!T108 -> -742 | O39: ='Historical Financials'!U108 -> -101 | P39: ='Historical Financials'!V108 -> -647 | ... W39: ='Historical Financials'!AC108 -> -677 | Y39: =SUM(H39:K39) -> -1497 | Z39: =SUM(I39:L39) -> -2381 | AA39: =SUM(J39:M39) -> -2207 | AB39: =SUM(K39:N39) -> -2574 | AC39: =SUM(L39:O39) -> -2317 | AD39: =SUM(M39:P39) -> -2080 | AE39: =SUM(N39:Q39) -> -2383 | AF39: =SUM(O39:R39) -> -2342 | ... AK39: =SUM(T39:W39) -> -3766
B40: (+/-) Divestiture / Acquisitions | C40: ='Historical Financials'!E109+'Historical Financials'!E118 -> 2062 | D40: ='Historical Financials'!F109+'Historical Financials'!F118 -> -2308 | E40: ='Historical Financials'!G109+'Historical Financials'!G118 -> -6934 | F40: ='Historical Financials'!H109+'Historical Financials'!H118 -> -487 | G40: ='Historical Financials'!I109+'Historical Financials'!I118 -> -1777 | I40: ='Historical Financials'!O109+'Historical Financials'!O118 -> -173 | J40: ='Historical Financials'!P109+'Historical Financials'!P118 -> -1063 | K40: ='Historical Financials'!Q109+'Historical Financials'!Q118 -> -5639 | L40: ='Historical Financials'!R109+'Historical Financials'!R118 -> -59 | M40: ='Historical Financials'!S109+'Historical Financials'!S118 -> -39 | N40: ='Historical Financials'!T109+'Historical Financials'!T118 -> -296 | O40: ='Historical Financials'!U109+'Historical Financials'!U118 -> -123 | P40: ='Historical Financials'!V109+'Historical Financials'!V118 -> -29 | ... W40: ='Historical Financials'!AC109+'Historical Financials'!AC118 -> -1072 | Y40: =SUM(H40:K40) -> -6875 | Z40: =SUM(I40:L40) -> -6934 | AA40: =SUM(J40:M40) -> -6800 | AB40: =SUM(K40:N40) -> -6033 | AC40: =SUM(L40:O40) -> -517 | AD40: =SUM(M40:P40) -> -487 | AE40: =SUM(N40:Q40) -> -501 | AF40: =SUM(O40:R40) -> -231 | ... AK40: =SUM(T40:W40) -> -255
B41: (-) Share Repurchases | C41: ='Historical Financials'!E115 -> -31149 | D41: ='Historical Financials'!F115 -> -50274 | E41: ='Historical Financials'!G115 -> -59296 | F41: ='Historical Financials'!H115 -> -61504 | G41: ='Historical Financials'!I115 -> -62222 | I41: ='Historical Financials'!O115 -> -13300 | J41: ='Historical Financials'!P115 -> -15197 | K41: ='Historical Financials'!Q115 -> -15392 | L41: ='Historical Financials'!R115 -> -15407 | M41: ='Historical Financials'!S115 -> -14557 | N41: ='Historical Financials'!T115 -> -14969 | O41: ='Historical Financials'!U115 -> -15787 | P41: ='Historical Financials'!V115 -> -16191 | ... W41: ='Historical Financials'!AC115 -> -11504 | AG41: =SUM(P41:S41) -> -62862 | AH41: =SUM(Q41:T41) -> -62222 | AI41: =SUM(R41:U41) -> -61594 | AJ41: =SUM(S41:V41) -> -59548 | AK41: =SUM(T41:W41) -> -55761
B42: (-) Dividend Payments | C42: ='Historical Financials'!E116 -> 0 | D42: ='Historical Financials'!F116 -> 0 | E42: ='Historical Financials'!G116 -> 0 | F42: ='Historical Financials'!H116 -> 0 | G42: ='Historical Financials'!I116 -> -7363 | I42: ='Historical Financials'!O116 -> 0 | J42: ='Historical Financials'!P116 -> 0 | K42: ='Historical Financials'!Q116 -> 0 | L42: ='Historical Financials'!R116 -> 0 | M42: ='Historical Financials'!S116 -> 0 | N42: ='Historical Financials'!T116 -> 0 | O42: ='Historical Financials'!U116 -> 0 | P42: ='Historical Financials'!V116 -> 0 | ... W42: ='Historical Financials'!AC116 -> -2536 | AG42: =SUM(P42:S42) -> -4921 | AH42: =SUM(Q42:T42) -> -7363 | AI42: =SUM(R42:U42) -> -9797 | AJ42: =SUM(S42:V42) -> -9874 | AK42: =SUM(T42:W42) -> -9955
B43: (+/-) Other Investing Activities | C43: ='Historical Financials'!E110 -> 68 | D43: ='Historical Financials'!F110 -> 541 | E43: ='Historical Financials'!G110 -> 1589 | F43: ='Historical Financials'!H110 -> -1051 | G43: ='Historical Financials'!I110 -> -2667 | I43: ='Historical Financials'!O110 -> 355 | J43: ='Historical Financials'!P110 -> 221 | K43: ='Historical Financials'!Q110 -> 791 | L43: ='Historical Financials'!R110 -> 222 | M43: ='Historical Financials'!S110 -> -125 | N43: ='Historical Financials'!T110 -> -232 | O43: ='Historical Financials'!U110 -> -628 | P43: ='Historical Financials'!V110 -> -66 | ... W43: ='Historical Financials'!AC110 -> -1482 | AF43: =SUM(O43:R43) -> -726 | AG43: =SUM(P43:S43) -> -2566 | AH43: =SUM(Q43:T43) -> -2667 | AI43: =SUM(R43:U43) -> -2618 | AJ43: =SUM(S43:V43) -> -2998 | AK43: =SUM(T43:W43) -> -2012
B44: (+/-) Other Operating Activities | C44: ='Historical Financials'!E92+'Historical Financials'!E93+'Historical Financials'!E94 -> -3660 | D44: ='Historical Financials'!F92+'Historical Financials'!F93+'Historical Financials'!F94 -> -10675 | E44: ='Historical Financials'!G92+'Historical Financials'!G93+'Historical Financials'!G94 -> 921 | F44: ='Historical Financials'!H92+'Historical Financials'!H93+'Historical Financials'!H94 -> -2610 | G44: ='Historical Financials'!I92+'Historical Financials'!I93+'Historical Financials'!I94 -> -4509 | I44: ='Historical Financials'!O92+'Historical Financials'!O93+'Historical Financials'!O94 -> -513 | J44: ='Historical Financials'!P92+'Historical Financials'!P93+'Historical Financials'!P94 -> -1044 | K44: ='Historical Financials'!Q92+'Historical Financials'!Q93+'Historical Financials'!Q94 -> -375 | L44: ='Historical Financials'!R92+'Historical Financials'!R93+'Historical Financials'!R94 -> 2853 | M44: ='Historical Financials'!S92+'Historical Financials'!S93+'Historical Financials'!S94 -> -1385 | N44: ='Historical Financials'!T92+'Historical Financials'!T93+'Historical Financials'!T94 -> -1809 | O44: ='Historical Financials'!U92+'Historical Financials'!U93+'Historical Financials'!U94 -> -693 | P44: ='Historical Financials'!V92+'Historical Financials'!V93+'Historical Financials'!V94 -> 1277 | ... W44: ='Historical Financials'!AC92+'Historical Financials'!AC93+'Historical Financials'!AC94 -> -2327 | AG44: =SUM(P44:S44) -> -2678 | AH44: =SUM(Q44:T44) -> -4509 | AI44: =SUM(R44:U44) -> -14112 | AJ44: =SUM(S44:V44) -> -14165 | AK44: =SUM(T44:W44) -> -14847
B45: (+/-) Other | D45: =SUM(D50-C50)-SUM(D36:D43) -> -12375 | E45: =SUM(E50-D50)-SUM(E36:E43) -> -14906 | F45: =SUM(F50-E50)-SUM(F36:F43) -> -12265 | G45: =SUM(G50-F50)-SUM(G36:G44) -> -26068 | I45: =SUM(I50-D50)-SUM(I36:I44) -> -1666 | J45: =SUM(J50-I50)-SUM(J36:J44) -> -1633 | K45: =SUM(K50-J50)-SUM(K36:K44) -> -1491 | L45: =SUM(L50-K50)-SUM(L36:L44) -> -1833 | M45: =SUM(M50-L50)-SUM(M36:M44) -> 543 | N45: =SUM(N50-M50)-SUM(N36:N44) -> -1530 | O45: =SUM(O50-N50)-SUM(O36:O44) -> 304 | P45: =SUM(P50-O50)-SUM(P36:P44) -> -1361 | Q45: =SUM(Q50-P50)-SUM(Q36:Q44) -> -1142 | ... W45: =SUM(W50-V50)-SUM(W36:W44) -> 4076 | Y45: =SUM(H45:K45) -> -4790 | Z45: =SUM(I45:L45) -> -6623 | AA45: =SUM(J45:M45) -> -4414 | AB45: =SUM(K45:N45) -> -4311 | AC45: =SUM(L45:O45) -> -2516 | AD45: =SUM(M45:P45) -> -2044 | AE45: =SUM(N45:Q45) -> -3729 | AF45: =SUM(O45:R45) -> -4190 | ... AK45: =SUM(T45:W45) -> 20422
B46: Free-Cash Flows | C46: =SUM(C36+SUM(C38:C45)) -> -3026 | D46: =SUM(D36+SUM(D38:D45)) -> -16195 | E46: =SUM(E36+SUM(E38:E45)) -> 1855 | F46: =SUM(F36+SUM(F38:F45)) -> -441 | G46: =SUM(G36+SUM(G38:G45)) -> -582 | I46: =SUM(I36+SUM(I38:I45)) -> -59 | J46: =SUM(J36+SUM(J38:J45)) -> -2950 | K46: =SUM(K36+SUM(K38:K45)) -> 4048 | L46: =SUM(L36+SUM(L38:L45)) -> -105 | M46: =SUM(M36+SUM(M38:M45)) -> 4045 | N46: =SUM(N36+SUM(N38:N45)) -> 5 | O46: =SUM(O36+SUM(O38:O45)) -> 4773 | P46: =SUM(P36+SUM(P38:P45)) -> -6654 | ... W46: =SUM(W36+SUM(W38:W45)) -> 2054 | Y46: =SUM(Y36+SUM(Y38:Y45)) -> 24395 | Z46: =SUM(Z36+SUM(Z38:Z45)) -> 28412 | AA46: =SUM(AA36+SUM(AA38:AA45)) -> 33838 | AB46: =SUM(AB36+SUM(AB38:AB45)) -> 36308 | AC46: =SUM(AC36+SUM(AC38:AC45)) -> 38173 | AD46: =SUM(AD36+SUM(AD38:AD45)) -> 32483 | AE46: =SUM(AE36+SUM(AE38:AE45)) -> 27124 | AF46: =SUM(AF36+SUM(AF38:AF45)) -> 29185 | ... AK46: =SUM(AK36+SUM(AK38:AK45)) -> 3131
B48: Capitalization
B50: Cash & Cash Equivelants | C50: ='Historical Financials'!E42 -> 26465 | D50: ='Historical Financials'!F42 -> 20945 | E50: ='Historical Financials'!G42 -> 21879 | F50: ='Historical Financials'!H42 -> 24048 | G50: ='Historical Financials'!I42 -> 23466 | I50: ='Historical Financials'!O42 -> 20886 | J50: ='Historical Financials'!P42 -> 17936 | K50: ='Historical Financials'!Q42 -> 21984 | L50: ='Historical Financials'!R42 -> 21879 | M50: ='Historical Financials'!S42 -> 25924 | N50: ='Historical Financials'!T42 -> 25929 | O50: ='Historical Financials'!U42 -> 30702 | P50: ='Historical Financials'!V42 -> 24048 | ... W50: ='Historical Financials'!AC42 -> 23090 | Y50: =K50 -> 21984 | Z50: =L50 -> 21879 | AA50: =M50 -> 25924 | AB50: =N50 -> 25929 | AC50: =O50 -> 30702 | AD50: =P50 -> 24048 | AE50: =Q50 -> 24493 | AF50: =R50 -> 27225 | ... AK50: =W50 -> 23090
B51: Marketable Securities | C51: ='Historical Financials'!E43 -> 110229 | D51: ='Historical Financials'!F43 -> 118704 | E51: ='Historical Financials'!G43 -> 91883 | F51: ='Historical Financials'!H43 -> 86868 | G51: ='Historical Financials'!I43 -> 72191 | I51: ='Historical Financials'!O43 -> 113084 | J51: ='Historical Financials'!P43 -> 107061 | K51: ='Historical Financials'!Q43 -> 94275 | L51: ='Historical Financials'!R43 -> 91883 | M51: ='Historical Financials'!S43 -> 89178 | N51: ='Historical Financials'!T43 -> 92403 | O51: ='Historical Financials'!U43 -> 89233 | P51: ='Historical Financials'!V43 -> 86868 | ... W51: ='Historical Financials'!AC43 -> 75406 | AG51: =S51 -> 73271 | AH51: =T51 -> 72191 | AI51: =U51 -> 72064 | AJ51: =V51 -> 74112 | AK51: =W51 -> 75406
B52: $10Bn RCF due April 2025, April 2028 (CP Backstop) | C52: 4000 | D52: 10000 | E52: 10000 | F52: 10000 | G52: 10000 | I52: 10000 | J52: 10000 | K52: 10000 | L52: =E52 -> 10000 | M52: 10000 | N52: 10000 | O52: 10000 | P52: =F52 -> 10000 | Q52: 10000 | R52: 10000 | S52: 10000 | T52: =G52 -> 10000 | U52: 10000 | V52: 10000 | W52: 10000 | AG52: =S52 -> 10000 | AH52: =T52 -> 10000 | AI52: =U52 -> 10000 | AJ52: =V52 -> 10000 | AK52: =W52 -> 10000
B53: Total Liquidity | C53: =SUM(C50:C52) -> 140694 | D53: =SUM(D50:D52) -> 149649 | E53: =SUM(E50:E52) -> 123762 | F53: =SUM(F50:F52) -> 120916 | G53: =SUM(G50:G52) -> 105657 | I53: =SUM(I50:I52) -> 143970 | J53: =SUM(J50:J52) -> 134997 | K53: =SUM(K50:K52) -> 126259 | L53: =SUM(L50:L52) -> 123762 | M53: =SUM(M50:M52) -> 125102 | N53: =SUM(N50:N52) -> 128332 | O53: =SUM(O50:O52) -> 129935 | P53: =SUM(P50:P52) -> 120916 | ... W53: =SUM(W50:W52) -> 108496 | Y53: =SUM(Y50:Y50) -> 21984 | Z53: =SUM(Z50:Z50) -> 21879 | AA53: =SUM(AA50:AA50) -> 25924 | AB53: =SUM(AB50:AB50) -> 25929 | AC53: =SUM(AC50:AC50) -> 30702 | AD53: =SUM(AD50:AD50) -> 24048 | AE53: =SUM(AE50:AE50) -> 24493 | AF53: =SUM(AF50:AF50) -> 27225 | AG53: =SUM(AG50:AG52) -> 103230 | AH53: =SUM(AH50:AH52) -> 105657 | AI53: =SUM(AI50:AI52) -> 105328 | AJ53: =SUM(AJ50:AJ52) -> 105148 | AK53: =SUM(AK50:AK52) -> 108496
B55: Balance Sheet Metrics:
B56: Accounts Receivable | C56: ='Historical Financials'!E44 -> 30930 | D56: ='Historical Financials'!F44 -> 39304 | E56: ='Historical Financials'!G44 -> 40258 | F56: ='Historical Financials'!H44 -> 47964 | G56: ='Historical Financials'!I44 -> 52340 | I56: ='Historical Financials'!O44 -> 34703 | J56: ='Historical Financials'!P44 -> 35707 | K56: ='Historical Financials'!Q44 -> 34697 | L56: ='Historical Financials'!R44 -> 40258 | M56: ='Historical Financials'!S44 -> 36036 | N56: ='Historical Financials'!T44 -> 38804 | O56: ='Historical Financials'!U44 -> 41020 | P56: ='Historical Financials'!V44 -> 47964 | ... W56: ='Historical Financials'!AC44 -> 57148 | Y56: =K56 -> 34697 | Z56: =L56 -> 40258 | AA56: =M56 -> 36036 | AB56: =N56 -> 38804 | AC56: =O56 -> 41020 | AD56: =P56 -> 47964 | AE56: =Q56 -> 44552 | AF56: =R56 -> 47087 | ... AK56: =W56 -> 57148
B57: Accounts Payable | C57: ='Historical Financials'!E58 -> 5589 | D57: ='Historical Financials'!F58 -> 6037 | E57: ='Historical Financials'!G58 -> 5128 | F57: ='Historical Financials'!H58 -> 7493 | G57: ='Historical Financials'!I58 -> 7987 | I57: ='Historical Financials'!O58 -> 3436 | J57: ='Historical Financials'!P58 -> 4409 | K57: ='Historical Financials'!Q58 -> 6303 | L57: ='Historical Financials'!R58 -> 5128 | M57: ='Historical Financials'!S58 -> 4184 | N57: ='Historical Financials'!T58 -> 5313 | O57: ='Historical Financials'!U58 -> 5803 | P57: ='Historical Financials'!V58 -> 7493 | ... W57: ='Historical Financials'!AC58 -> 10546 | Y57: =K57 -> 6303 | Z57: =L57 -> 5128 | AA57: =M57 -> 4184 | AB57: =N57 -> 5313 | AC57: =O57 -> 5803 | AD57: =P57 -> 7493 | AE57: =Q57 -> 6198 | AF57: =R57 -> 6092 | ... AK57: =W57 -> 10546
B58: Property Plant, and Equiptment | C58: ='Historical Financials'!E51 -> 84749 | D58: ='Historical Financials'!F51 -> 97599 | E58: ='Historical Financials'!G51 -> 112668 | F58: ='Historical Financials'!H51 -> 134345 | G58: ='Historical Financials'!I51 -> 171036 | I58: ='Historical Financials'!O51 -> 104218 | J58: ='Historical Financials'!P51 -> 106223 | K58: ='Historical Financials'!Q51 -> 108363 | L58: ='Historical Financials'!R51 -> 112668 | M58: ='Historical Financials'!S51 -> 117560 | N58: ='Historical Financials'!T51 -> 121208 | O58: ='Historical Financials'!U51 -> 125705 | P58: ='Historical Financials'!V51 -> 134345 | ... W58: ='Historical Financials'!AC51 -> 223787 | Y58: =K58 -> 108363 | Z58: =L58 -> 112668 | AA58: =M58 -> 117560 | AB58: =N58 -> 121208 | AC58: =O58 -> 125705 | AD58: =P58 -> 134345 | AE58: =Q58 -> 143182 | AF58: =R58 -> 151155 | ... AK58: =W58 -> 223787
B59: Current Liabilities | C59: ='Historical Financials'!E63 -> 56834 | D59: ='Historical Financials'!F63 -> 64254 | E59: ='Historical Financials'!G63 -> 69300 | F59: ='Historical Financials'!H63 -> 81814 | G59: ='Historical Financials'!I63 -> 89122 | I59: ='Historical Financials'!O63 -> 61948 | J59: ='Historical Financials'!P63 -> 61354 | K59: ='Historical Financials'!Q63 -> 65979 | L59: ='Historical Financials'!R63 -> 69300 | M59: ='Historical Financials'!S63 -> 68854 | N59: ='Historical Financials'!T63 -> 77709 | O59: ='Historical Financials'!U63 -> 86295 | P59: ='Historical Financials'!V63 -> 81814 | ... W59: ='Historical Financials'!AC63 -> 99550 | Y59: =K59 -> 65979 | Z59: =L59 -> 69300 | AA59: =M59 -> 68854 | AB59: =N59 -> 77709 | AC59: =O59 -> 86295 | AD59: =P59 -> 81814 | AE59: =Q59 -> 76997 | AF59: =R59 -> 77913 | ... AK59: =W59 -> 99550
B60: Total Liabilities | C60: ='Historical Financials'!E70 -> 97072 | D60: ='Historical Financials'!F70 -> 107633 | E60: ='Historical Financials'!G70 -> 109120 | F60: ='Historical Financials'!H70 -> 119013 | G60: ='Historical Financials'!I70 -> 125172 | I60: ='Historical Financials'!O70 -> 103092 | J60: ='Historical Financials'!P70 -> 99766 | K60: ='Historical Financials'!Q70 -> 104629 | L60: ='Historical Financials'!R70 -> 109120 | M60: ='Historical Financials'!S70 -> 108597 | N60: ='Historical Financials'!T70 -> 115903 | O60: ='Historical Financials'!U70 -> 123509 | P60: ='Historical Financials'!V70 -> 119013 | ... W60: ='Historical Financials'!AC70 -> 149602 | Y60: =K60 -> 104629 | Z60: =L60 -> 109120 | AA60: =M60 -> 108597 | AB60: =N60 -> 115903 | AC60: =O60 -> 123509 | AD60: =P60 -> 119013 | AE60: =Q60 -> 114506 | AF60: =R60 -> 114017 | ... AK60: =W60 -> 149602
B62: $10Bn 4.4000% Commercial Paper Program | C62: 0 | D62: 0 | E62: 0 | F62: 0 | G62: 2300 | I62: 0 | J62: 0 | K62: 0 | L62: =E62 -> 0 | M62: 0 | N62: 0 | O62: 0 | P62: =F62 -> 0 | Q62: 0 | R62: 0 | S62: 0 | T62: =G62 -> 2300 | U62: 2500 | V62: 3000 | W62: 3000 | Y62: =K62 -> 0 | Z62: =L62 -> 0 | AA62: =M62 -> 0 | AB62: =N62 -> 0 | AC62: =O62 -> 0 | AD62: =P62 -> 0 | AE62: =Q62 -> 0 | AF62: =R62 -> 0 | ... AK62: =W62 -> 3000
B63: Consolidated Sr. Unsecured Notes | C63: 14000 | D63: 13000 | E63: 13000 | F63: =10000+2000+1000 -> 13000 | G63: =10000+2000+2000 -> 14000 | I63: 13000 | J63: 13000 | K63: 13000 | L63: =E63 -> 13000 | M63: 13000 | N63: 13000 | O63: 13000 | P63: =F63 -> 13000 | Q63: 12000 | R63: 12000 | S63: 12000 | T63: =G63 -> 14000 | U63: 12000 | V63: =2000+10000+5000+7903 -> 24903 | W63: =2000+9000+5000+7892 -> 23892 | AG63: =S63 -> 12000 | AH63: =T63 -> 14000 | AI63: =U63 -> 12000 | AJ63: =V63 -> 24903 | AK63: =W63 -> 23892
B64: Finance Lease Obligations | C64: 1201 | D64: 2086 | E64: 2142 | F64: 1666 | G64: 1677 | I64: 2125 | J64: 1966 | K64: 2213 | L64: =E64 -> 2142 | M64: 2208 | N64: 2159 | O64: 2314 | P64: =F64 -> 1666 | Q64: 1672 | R64: 2280 | S64: 2785 | T64: =G64 -> 1677 | U64: 2061 | V64: 2102 | W64: 2388 | Y64: =K64 -> 2213 | Z64: =L64 -> 2142 | AA64: =M64 -> 2208 | AB64: =N64 -> 2159 | AC64: =O64 -> 2314 | AD64: =P64 -> 1666 | AE64: =Q64 -> 1672 | AF64: =R64 -> 2280 | ... AK64: =W64 -> 2388
B65: Total Debt | C65: =SUM(C62:C64) -> 15201 | D65: =SUM(D62:D64) -> 15086 | E65: =SUM(E62:E64) -> 15142 | F65: =SUM(F62:F64) -> 14666 | G65: =SUM(G62:G64) -> 17977 | I65: =SUM(I62:I64) -> 15125 | J65: =SUM(J62:J64) -> 14966 | K65: =SUM(K62:K64) -> 15213 | L65: =SUM(L62:L64) -> 15142 | M65: =SUM(M62:M64) -> 15208 | N65: =SUM(N62:N64) -> 15159 | O65: =SUM(O62:O64) -> 15314 | P65: =SUM(P62:P64) -> 14666 | ... W65: =SUM(W62:W64) -> 29280 | Y65: =SUM(Y62:Y64) -> 2213 | Z65: =SUM(Z62:Z64) -> 2142 | AA65: =SUM(AA62:AA64) -> 2208 | AB65: =SUM(AB62:AB64) -> 2159 | AC65: =SUM(AC62:AC64) -> 2314 | AD65: =SUM(AD62:AD64) -> 1666 | AE65: =SUM(AE62:AE64) -> 1672 | AF65: =SUM(AF62:AF64) -> 2280 | ... AK65: =SUM(AK62:AK64) -> 29280
B67: Total Shareholder Equity | C67: ='Historical Financials'!E76 -> 222544 | D67: ='Historical Financials'!F76 -> 251635 | E67: ='Historical Financials'!G76 -> 256144 | F67: ='Historical Financials'!H76 -> 283379 | G67: ='Historical Financials'!I76 -> 325084 | I67: ='Historical Financials'!O76 -> 254004 | J67: ='Historical Financials'!P76 -> 255419 | K67: ='Historical Financials'!Q76 -> 253626 | L67: ='Historical Financials'!R76 -> 256144 | M67: ='Historical Financials'!S76 -> 260894 | N67: ='Historical Financials'!T76 -> 267141 | O67: ='Historical Financials'!U76 -> 273202 | P67: ='Historical Financials'!V76 -> 283379 | ... W67: ='Historical Financials'!AC76 -> 386867 | Y67: =K67 -> 253626 | Z67: =L67 -> 256144 | AA67: =M67 -> 260894 | AB67: =N67 -> 267141 | AC67: =O67 -> 273202 | AD67: =P67 -> 283379 | AE67: =Q67 -> 292844 | AF67: =R67 -> 300753 | ... AK67: =W67 -> 386867
B68: Total Book Capitalization | C68: =SUM(C65:C67) -> 237745 | D68: =SUM(D65:D67) -> 266721 | E68: =SUM(E65:E67) -> 271286 | F68: =SUM(F65:F67) -> 298045 | G68: =SUM(G65:G67) -> 343061 | I68: =SUM(I65:I67) -> 269129 | J68: =SUM(J65:J67) -> 270385 | K68: =SUM(K65:K67) -> 268839 | L68: =SUM(L65:L67) -> 271286 | M68: =SUM(M65:M67) -> 276102 | N68: =SUM(N65:N67) -> 282300 | O68: =SUM(O65:O67) -> 288516 | P68: =SUM(P65:P67) -> 298045 | ... W68: =SUM(W65:W67) -> 416147 | Y68: =SUM(Y65:Y67) -> 255839 | Z68: =SUM(Z65:Z67) -> 258286 | AA68: =SUM(AA65:AA67) -> 263102 | AB68: =SUM(AB65:AB67) -> 269300 | AC68: =SUM(AC65:AC67) -> 275516 | AD68: =SUM(AD65:AD67) -> 285045 | AE68: =SUM(AE65:AE67) -> 294516 | AF68: =SUM(AF65:AF67) -> 303033 | ... AK68: =SUM(AK65:AK67) -> 416147
B70: Credit Metrics
B72: LTM Total Leverage | C72: =C65/C29 -> 0.22383378 | D72: =D65/D29 -> 0.14161136 | E72: =E65/E29 -> 0.14062166 | F72: =F65/F29 -> 0.12355622 | G72: =G65/G29 -> 0.11945962 | L72: =SUM(L65/SUM(I29:L29)) -> 0.14062166 | M72: =SUM(M65/SUM(J29:M29)) -> 0.14458473 | N72: =SUM(N65/SUM(K29:N29)) -> 0.14028447 | O72: =SUM(O65/SUM(L29:O29)) -> 0.13577686 | P72: =SUM(P65/SUM(M29:P29)) -> 0.12355622 | Q72: =SUM(Q65/SUM(N29:Q29)) -> 0.10768492 | R72: =SUM(R65/SUM(O29:R29)) -> 0.10740718 | S72: =SUM(S65/SUM(P29:S29)) -> 0.10529277 | ... W72: =SUM(W65/SUM(T29:W29)) -> 0.17525588 | Y72: =Y65/Y29 -> 0.035941078 | Z72: =Z65/Z29 -> 0.027331538 | AA72: =AA65/AA29 -> 0.02960222 | AB72: =AB65/AB29 -> 0.028412007 | AC72: =AC65/AC29 -> 0.029024409 | AD72: =AD65/AD29 -> 0.019869287 | AE72: =AE65/AE29 -> 0.018619776 | AF72: =AF65/AF29 -> 0.024439657 | ... AK72: =AK65/AK29 -> 0.17525588
B73: LTM Net Leverage | C73: =SUM(C65-C50)/C29 -> -0.1658617 | D73: =SUM(D65-D50)/D29 -> -0.054998076 | E73: =SUM(E65-E50)/E29 -> -0.062565588 | F73: =SUM(F65-F50)/F29 -> -0.079040262 | G73: =SUM(G65-G50)/G29 -> -0.036475154 | L73: =SUM(L65-L50)/SUM(I29:L29) -> -0.062565588 | M73: =SUM(M65-M50)/SUM(J29:M29) -> -0.10187861 | N73: =SUM(N65-N50)/SUM(K29:N29) -> -0.099667774 | O73: =SUM(O65-O50)/SUM(L29:O29) -> -0.13643295 | P73: =SUM(P65-P50)/SUM(M29:P29) -> -0.079040262 | Q73: =SUM(Q65-Q50)/SUM(N29:Q29) -> -0.085229555 | R73: =SUM(R65-R50)/SUM(O29:R29) -> -0.097365967 | S73: =SUM(S65-S50)/SUM(P29:S29) -> -0.036847128 | ... W73: =SUM(W65-W50)/SUM(T29:W29) -> 0.037050338 | Y73: =SUM(Y65-Y50)/Y29 -> -0.32109853 | Z73: =SUM(Z65-Z50)/Z29 -> -0.2518406 | AA73: =SUM(AA65-AA50)/AA29 -> -0.31795573 | AB73: =SUM(AB65-AB50)/AB29 -> -0.31280843 | AC73: =SUM(AC65-AC50)/AC29 -> -0.35606954 | AD73: =SUM(AD65-AD50)/AD29 -> -0.26693541 | AE73: =SUM(AE65-AE50)/AE29 -> -0.25413989 | AF73: =SUM(AF65-AF50)/AF29 -> -0.26738914 | ... AK73: =SUM(AK65-AK50)/AK29 -> 0.037050338
B74: LTM Interest Coverage | C74: =C29/-C34 -> 503.05185 | D74: =D29/-D34 -> 307.89306 | E74: =E29/-E34 -> 301.62185 | F74: =F29/-F34 -> 385.38636 | G74: =G29/-G34 -> 561.51493 | L74: {=SUM(I29:L29)/SUM(-I34:L34)} -> 301.62185 | M74: {=SUM(J29:M29)/SUM(-J34:M34)} -> 297.12994 | N74: {=SUM(K29:N29)/SUM(-K34:N34)} -> 344.13694 | O74: {=SUM(L29:O29)/SUM(-L34:O34)} -> 342.82067 | P74: {=SUM(M29:P29)/SUM(-M34:P34)} -> 385.38636 | Q74: {=SUM(N29:Q29)/SUM(-N34:Q34)} -> 394.29503 | R74: {=SUM(O29:R29)/SUM(-O34:R34)} -> 384.25434 | S74: {=SUM(P29:S29)/SUM(-P34:S34)} -> 494.42958 | ... W74: {=SUM(T29:W29)/SUM(-T34:W34)} -> 340.26477 | Y74: =Y29/-Y34 -> 230.61049 | Z74: =Z29/-Z34 -> 219.52661 | AA74: =AA29/-AA34 -> 210.70339 | AB74: =AB29/-AB34 -> 242.00318 | AC74: =AC29/-AC34 -> 242.32827 | AD74: =AD29/-AD34 -> 272.23377 | AE74: =AE29/-AE34 -> 278.87267 | AF74: =AF29/-AF34 -> 269.62717 | ... AK74: =AK29/-AK34 -> 340.26477
B75: LTM Debt Service Coverage | C75: {=SUM(C29+C32)/SUM(-C33:C34)} -> 8.3459512 | D75: {=SUM(D29+D32)/SUM(-D33:D34)} -> 6.031618 | E75: {=SUM(E29+E32)/SUM(-E33:E34)} -> 4.4364902 | F75: {=SUM(F29+F32)/SUM(-F33:F34)} -> 4.8304745 | G75: {=SUM(G29+G32)/SUM(-G33:G34)} -> 6.2083159 | L75: {=SUM(I29:L29+I32:L32)/SUM(-I33:L34)} -> 3.9583355 | M75: {=SUM(J29:M29+J32:M32)/SUM(-J33:M34)} -> 3.9968934 | N75: {=SUM(K29:N29+K32:N32)/SUM(-K33:N34)} -> 4.1366456 | O75: {=SUM(L29:O29+L32:O32)/SUM(-L33:O34)} -> 4.3223166 | P75: {=SUM(M29:P29+M32:P32)/SUM(-M33:P34)} -> 4.4396056 | Q75: {=SUM(N29:Q29+N32:Q32)/SUM(-N33:Q34)} -> 4.5823378 | R75: {=SUM(O29:R29+O32:R32)/SUM(-O33:R34)} -> 4.5763237 | S75: {=SUM(P29:S29+P32:S32)/SUM(-P33:S34)} -> 4.7345455 | ... W75: {=SUM(T29:W29+T32:W32)/SUM(-T33:W34)} -> 4.5999691 | Y75: {=SUM(Y29+Y32)/SUM(-Y33:Y34)} -> 2.6103491 | Z75: {=SUM(Z29+Z32)/SUM(-Z33:Z34)} -> 2.4357629 | AA75: {=SUM(AA29+AA32)/SUM(-AA33:AA34)} -> 2.4128094 | AB75: {=SUM(AB29+AB32)/SUM(-AB33:AB34)} -> 2.4785958 | AC75: {=SUM(AC29+AC32)/SUM(-AC33:AC34)} -> 2.6202831 | AD75: {=SUM(AD29+AD32)/SUM(-AD33:AD34)} -> 2.6498048 | AE75: {=SUM(AE29+AE32)/SUM(-AE33:AE34)} -> 2.6685376 | AF75: {=SUM(AF29+AF32)/SUM(-AF33:AF34)} -> 2.5296212 | ... AK75: {=SUM(AK29+AK32)/SUM(-AK33:AK34)} -> 4.5999691
B76: LTM Fixed Charge Coverage | C76: {=SUM(C29)/SUM(-C32:C34)} -> 2.2439863 | D76: {=SUM(D29)/SUM(-D32:D34)} -> 2.8555996 | E76: {=SUM(E29)/SUM(-E32:E34)} -> 2.5928004 | F76: {=SUM(F29)/SUM(-F32:F34)} -> 2.6908551 | G76: {=SUM(G29)/SUM(-G32:G34)} -> 2.9709198 | L76: {=SUM(I29:L29)/SUM(-I32:L34)} -> 2.1224228 | M76: {=SUM(J29:M29)/SUM(-J32:M34)} -> 2.2236692 | N76: {=SUM(K29:N29)/SUM(-K32:N34)} -> 2.2802068 | O76: {=SUM(L29:O29)/SUM(-L32:O34)} -> 2.3374782 | P76: {=SUM(M29:P29)/SUM(-M32:P34)} -> 2.2948978 | Q76: {=SUM(N29:Q29)/SUM(-N32:Q34)} -> 2.2121302 | R76: {=SUM(O29:R29)/SUM(-O32:R34)} -> 2.0887981 | S76: {=SUM(P29:S29)/SUM(-P32:S34)} -> 2.0490602 | ... W76: {=SUM(T29:W29)/SUM(-T32:W34)} -> 1.7177138 | Y76: {=SUM(Y29)/SUM(-Y32:Y34)} -> 1.6065595 | Z76: {=SUM(Z29)/SUM(-Z32:Z34)} -> 1.5447432 | AA76: {=SUM(AA29)/SUM(-AA32:AA34)} -> 1.5768678 | AB76: {=SUM(AB29)/SUM(-AB32:AB34)} -> 1.6034817 | AC76: {=SUM(AC29)/SUM(-AC32:AC34)} -> 1.6522838 | AD76: {=SUM(AD29)/SUM(-AD32:AD34)} -> 1.621097 | AE76: {=SUM(AE29)/SUM(-AE32:AE34)} -> 1.5645712 | AF76: {=SUM(AF29)/SUM(-AF32:AF34)} -> 1.4656874 | ... AK76: {=SUM(AK29)/SUM(-AK32:AK34)} -> 1.7177138
B77: Debt-to-Book Capitalization | C77: =C68/C65 -> 15.640089 | D77: =D68/D65 -> 17.680034 | E77: =E68/E65 -> 17.916127 | F77: =F68/F65 -> 20.322174 | G77: =G68/G65 -> 19.083329 | L77: =L68/L65 -> 17.916127 | M77: =M68/M65 -> 18.15505 | N77: =N68/N65 -> 18.6226 | O77: =O68/O65 -> 18.840016 | P77: =P68/P65 -> 20.322174 | Q77: =Q68/Q65 -> 22.419251 | R77: =R68/R65 -> 22.061134 | S77: =S68/S65 -> 22.24579 | ... W77: =W68/W65 -> 14.212671 | Y77: =Y68/Y65 -> 115.60732 | Z77: =Z68/Z65 -> 120.5817 | AA77: =AA68/AA65 -> 119.15851 | AB77: =AB68/AB65 -> 124.73367 | AC77: =AC68/AC65 -> 119.06482 | AD77: =AD68/AD65 -> 171.09544 | AE77: =AE68/AE65 -> 176.14593 | AF77: =AF68/AF65 -> 132.90921 | ... AK77: =AK68/AK65 -> 14.212671

Sheet 3-Statement Model
B2: Alphabet Inc. (NASDAQ: GOOG)
B3: 3-Statement Model
B4: $ mm except per share
B6: Company name | C6: Beyond Meat, Inc. | I6: Select an operating scenario: | K6: Base case
B7: Ticker | C7: GOOG
B8: Circ break 1=off, 0=on | C8: 0
B9: Latest closing share price
B10: Latest closing share price date | C10: =NOW() -> 45986.348
B11: Latest fiscal year end date | C11: ='Historical Financials'!I8 -> 45657
B12: Shares outstanding (millions) | C12: 4443.265
A14: X | B14: Income Statement | C14: Actuals | G14: Forecast
B15: Fiscal year | C15: =D15-1 -> 2021 | D15: =E15-1 -> 2022 | E15: =F15-1 -> 2023 | F15: =YEAR(C11) -> 2024 | G15: =F15+1 -> 2025 | H15: =G15+1 -> 2026 | I15: =H15+1 -> 2027 | J15: =I15+1 -> 2028 | K15: =J15+1 -> 2029
B16: Fiscal year end date | C16: =EOMONTH(D16,-12) -> 44561 | D16: =EOMONTH(E16,-12) -> 44926 | E16: =EOMONTH(F16,-12) -> 45291 | F16: =C11 -> 45657 | G16: =EOMONTH(F16,12) -> 46022 | H16: =EOMONTH(G16,12) -> 46387 | I16: =EOMONTH(H16,12) -> 46752 | J16: =EOMONTH(I16,12) -> 47118 | K16: =EOMONTH(J16,12) -> 47483 | M16: Commentary
B18: Google Search & Other | C18: ='Revenue Drivers'!F22 -> 148951 | D18: ='Revenue Drivers'!G22 -> 162450 | E18: ='Revenue Drivers'!H22 -> 175033 | F18: ='Revenue Drivers'!I22 -> 198084 | G18: =F18*(1+G61) -> 198084 | H18: =G18*(1+H61) -> 198084 | I18: =H18*(1+I61) -> 198084 | J18: =I18*(1+J61) -> 198084 | K18: =J18*(1+K61) -> 198084
B19: YouTube ads | C19: ='Revenue Drivers'!F23 -> 28845 | D19: ='Revenue Drivers'!G23 -> 29243 | E19: ='Revenue Drivers'!H23 -> 31510 | F19: ='Revenue Drivers'!I23 -> 36147
B20: Google Network | C20: ='Revenue Drivers'!F24 -> 31701 | D20: ='Revenue Drivers'!G24 -> 32780 | E20: ='Revenue Drivers'!H24 -> 31312 | F20: ='Revenue Drivers'!I24 -> 30359
B21: Total Advertising Revenue | C21: =SUM(C18:C20) -> 209497 | D21: =SUM(D18:D20) -> 224473 | E21: =SUM(E18:E20) -> 237855 | F21: =SUM(F18:F20) -> 264590 | G21: =SUM(G18:G20) -> 198084 | H21: =SUM(H18:H20) -> 198084 | I21: =SUM(I18:I20) -> 198084 | J21: =SUM(J18:J20) -> 198084 | K21: =SUM(K18:K20) -> 198084
G27: =F27*(1+G66) -> 0 | H27: =G27*(1+H66) -> 0 | I27: =H27*(1+I66) -> 0 | J27: =I27*(1+J66) -> 0 | K27: =J27*(1+K66) -> 0
B28: Total Net Revenue | C28: =SUM(C18:C27) -> 418994 | D28: =SUM(D18:D27) -> 448946 | E28: =SUM(E18:E27) -> 475710 | F28: =SUM(F18:F27) -> 529180 | G28: =SUM(G18:G27) -> 396168 | H28: =SUM(H18:H27) -> 396168 | I28: =SUM(I18:I27) -> 396168 | J28: =SUM(J18:J27) -> 396168 | K28: =SUM(K18:K27) -> 396168
B29: Y/Y Growth (%) | D29: =SUM(D28/C28)-1 -> 0.071485511 | E29: =SUM(E28/D28)-1 -> 0.059615188 | F29: =SUM(F28/E28)-1 -> 0.11240041 | G29: =SUM(G28/F28)-1 -> -0.25135493 | H29: =SUM(H28/G28)-1 -> 0 | I29: =SUM(I28/H28)-1 -> 0 | J29: =SUM(J28/I28)-1 -> 0 | K29: =SUM(K28/J28)-1 -> 0
B31: Cost of Sales | C31: ='Historical Financials'!E13 -> -84732 | D31: ='Historical Financials'!F13 -> -110939 | E31: ='Historical Financials'!G13 -> -126203 | F31: ='Historical Financials'!H13 -> -133332 | G31: =+G32-G28 -> -396168 | H31: =+H32-H28 -> -396168 | I31: =+I32-I28 -> -396168 | J31: =+J32-J28 -> -396168 | K31: =+K32-K28 -> -396168 | M31: Plug = Revenue - Gross Profit
B32: Gross Profit | C32: =+C31+C28 -> 334262 | D32: =+D31+D28 -> 338007 | E32: =+E31+E28 -> 349507 | F32: =+F31+F28 -> 395848 | G32: =G68*G28 -> 0 | H32: =H68*H28 -> 0 | I32: =I68*I28 -> 0 | J32: =J68*J28 -> 0 | K32: =K68*K28 -> 0 | M32: Revenue x Gross Profit Margin forecast
B33: Margin (%) | C33: =C32/C28 -> 0.79777276 | D33: =D32/D28 -> 0.7528901 | E33: =E32/E28 -> 0.73470602 | F33: =F32/F28 -> 0.74804036 | G33: =G32/G28 -> 0 | H33: =H32/H28 -> 0 | I33: =I32/I28 -> 0 | J33: =J32/J28 -> 0 | K33: =K32/K28 -> 0
B35: Selling, General & Administrative (SG&A) | G35: =-G69*G18 -> 0 | H35: =-H69*H18 -> 0 | I35: =-I69*I18 -> 0 | J35: =-J69*J18 -> 0 | K35: =-K69*K18 -> 0 | M35: Revenue x SG&A % of sales forecast
B36: Research & Development (R&D) | G36: =-G18*G70 -> 0 | H36: =-H18*H70 -> 0 | I36: =-I18*I70 -> 0 | J36: =-J18*J70 -> 0 | K36: =-K18*K70 -> 0 | M36: Revenue x R&D % of sales forecast
B37: Restructuring Charges & Other Impairments | G37: =-G27*G71 -> 0 | H37: =-H27*H71 -> 0 | I37: =-I27*I71 -> 0 | J37: =-J27*J71 -> 0 | K37: =-K27*K71 -> 0 | M37: Consensus
B38: Operating profit (EBIT) | C38: =C32+C35+C36+C37 -> 334262 | D38: =D32+D35+D36+D37 -> 338007 | E38: =E32+E35+E36+E37 -> 349507 | F38: =F32+F35+F36+F37 -> 395848 | G38: =G32+G35+G36+G37 -> 0 | H38: =H32+H35+H36+H37 -> 0 | I38: =I32+I35+I36+I37 -> 0 | J38: =J32+J35+J36+J37 -> 0 | K38: =K32+K35+K36+K37 -> 0
B39: Margin (%) | C39: =C38/C28 -> 0.79777276 | D39: =D38/D28 -> 0.7528901 | E39: =E38/E28 -> 0.73470602 | F39: =F38/F28 -> 0.74804036 | G39: =G38/G28 -> 0 | H39: =H38/H28 -> 0 | I39: =I38/I28 -> 0 | J39: =J38/J28 -> 0 | K39: =K38/K28 -> 0
B41: Interest Income | M41: Reference from interest on cash schedule
B42: Interest expense | M42: Reference from interest expense schedule
B43: Other expense, net | G43: =F43 -> 0 | H43: =G43 -> 0 | I43: =H43 -> 0 | J43: =I43 -> 0 | K43: =J43 -> 0 | M43: Straight-line
B44: Pretax profit | C44: =SUM(C38:C43) -> 334262.8 | D44: =SUM(D38:D43) -> 338007.75 | E44: =SUM(E38:E43) -> 349507.73 | F44: =SUM(F38:F43) -> 395848.75 | G44: =SUM(G38:G43) -> 0 | H44: =SUM(H38:H43) -> 0 | I44: =SUM(I38:I43) -> 0 | J44: =SUM(J38:J43) -> 0 | K44: =SUM(K38:K43) -> 0 | M44: EBIT + interest income less interest expense less other expense
B46: Taxes | G46: 0 | H46: 0 | I46: 0 | J46: 0 | K46: 0 | M46: Pre-tax Profit x Tax Rate forecast
B47: Net income | C47: =SUM(C44:C46) -> 334262.8 | D47: =SUM(D44:D46) -> 338007.75 | E47: =SUM(E44:E46) -> 349507.73 | F47: =SUM(F44:F46) -> 395848.75 | G47: =SUM(G44:G46) -> 0 | H47: =SUM(H44:H46) -> 0 | I47: =SUM(I44:I46) -> 0 | J47: =SUM(J44:J46) -> 0 | K47: =SUM(K44:K46) -> 0 | M47: Pre-tax Profit less taxes
B48: Margin (%) | C48: =C47/C28 -> 0.79777466 | D48: =D47/D28 -> 0.75289178 | E48: =E47/E28 -> 0.73470756 | F48: =F47/F28 -> 0.74804178 | G48: =G47/G28 -> 0 | H48: =H47/H28 -> 0 | I48: =I47/I28 -> 0 | J48: =J47/J28 -> 0 | K48: =K47/K28 -> 0
B50: Depreciation & Amortization (D&A) | M50: Reference from D&A schedule
B51: EBITDA | C51: =C38+C50 -> 334262 | D51: =D38+D50 -> 338007 | E51: =E38+E50 -> 349507 | F51: =F38+F50 -> 395848 | G51: =G38+G50 -> 0 | H51: =H38+H50 -> 0 | I51: =I38+I50 -> 0 | J51: =J38+J50 -> 0 | K51: =K38+K50 -> 0 | M51: EBIT + D&A
B52: Margin (%) | C52: =C51/C28 -> 0.79777276 | D52: =D51/D28 -> 0.7528901 | E52: =E51/E28 -> 0.73470602 | F52: =F51/F28 -> 0.74804036 | G52: =G51/G28 -> 0 | H52: =H51/H28 -> 0 | I52: =I51/I28 -> 0 | J52: =J51/J28 -> 0 | K52: =K51/K28 -> 0
B54: Stock-Based Compensation (SBC) | G54: =+(F54*G60)+F54 -> 0 | H54: =+(G54*H60)+G54 -> 0 | I54: =+(H54*I60)+H54 -> 0 | J54: =+(I54*J60)+I54 -> 0 | K54: =+(J54*K60)+J54 -> 0 | M54: grow SBC in-line with revenue growth
B55: Adjusted EBITDA | C55: =SUM(C51:C54) -> 334262.8 | D55: =SUM(D51:D54) -> 338007.75 | E55: =SUM(E51:E54) -> 349507.73 | F55: =SUM(F51:F54) -> 395848.75 | G55: =SUM(G51:G54) -> 0 | H55: =SUM(H51:H54) -> 0 | I55: =SUM(I51:I54) -> 0 | J55: =SUM(J51:J54) -> 0 | K55: =SUM(K51:K54) -> 0 | M55: EBITDA + Stock-based compensation
B56: Margin (%) | C56: =C55/C28 -> 0.79777466 | D56: =D55/D28 -> 0.75289178 | E56: =E55/E28 -> 0.73470756 | F56: =F55/F28 -> 0.74804178 | G56: =G55/G28 -> 0 | H56: =H55/H28 -> 0 | I56: =I55/I28 -> 0 | J56: =J55/J28 -> 0 | K56: =K55/K28 -> 0
B58: Growth rates & margins
B60: Revenue growth | D60: =D28/C28-1 -> 0.071485511 | E60: =E28/D28-1 -> 0.059615188 | F60: =F28/E28-1 -> 0.11240041 | M60: Consensus estimates
B61: Google Search & Other | D61: =SUM(D18/C18)-1 -> 0.090627119 | E61: =SUM(E18/D18)-1 -> 0.077457679 | F61: =SUM(F18/E18)-1 -> 0.13169517 | M61: Consensus estimates
B66: Foodservice | D66: =SUM(D27/C27)-1 -> #DIV/0! | E66: =SUM(E27/D27)-1 -> #DIV/0! | F66: =SUM(F27/E27)-1 -> #DIV/0! | M66: Consensus estimates
B68: Gross profit margin | C68: =C32/C28 -> 0.79777276 | D68: =D32/D28 -> 0.7528901 | E68: =E32/E28 -> 0.73470602 | F68: =F32/F28 -> 0.74804036 | M68: BofA Estimate
B69: R&D % of sales | C69: =-C35/C18 -> 0 | D69: =-D35/D18 -> 0 | E69: =-E35/E18 -> 0 | F69: =-F35/F18 -> 0 | M69: Consensus estimates
B70: SG&A % of sales | C70: =-C36/C18 -> 0 | D70: =-D36/D18 -> 0 | E70: =-E36/E18 -> 0 | F70: =-F36/F18 -> 0 | M70: Consensus estimates
B71: Tax rate | C71: =-(C46/C44) -> 0 | D71: =-(D46/D44) -> 0 | E71: =-(E46/E44) -> 0 | F71: =-(F46/F44) -> 0 | G71: =F71 -> 0 | H71: =G71 -> 0 | I71: =H71 -> 0 | J71: =I71 -> 0 | K71: =J71 -> 0 | M71: straight line
B73: D&A | D73: =D50/C50-1 -> #DIV/0! | E73: =E50/D50-1 -> #DIV/0! | F73: =F50/E50-1 -> #DIV/0! | M73: Consensus estimates
B74: SBC | D74: =D54/C54-1 -> #DIV/0! | E74: =E54/D54-1 -> #DIV/0! | F74: =F54/E54-1 -> #DIV/0! | M74: Consensus estimates
A76: X | B76: Balance Sheet | C76: Actuals | G76: Forecast
B77: =B15 -> Fiscal year | C77: =C15 -> 2021 | D77: =D15 -> 2022 | E77: =E15 -> 2023 | F77: =F15 -> 2024 | G77: =G15 -> 2025 | H77: =H15 -> 2026 | I77: =I15 -> 2027 | ... K77: =K15 -> 2029
B78: =B16 -> Fiscal year end date | C78: =C16 -> 44561 | D78: =D16 -> 44926 | E78: =E16 -> 45291 | F78: =F16 -> 45657 | G78: =G16 -> 46022 | H78: =H16 -> 46387 | I78: =I16 -> 46752 | ... K78: =K16 -> 47483
B80: Cash & equivalents, ST and LT marketable securities | G80: =+F80+G125 -> 0 | H80: =+G80+H125 -> #DIV/0! | I80: =+H80+I125 -> #DIV/0! | J80: =+I80+J125 -> #DIV/0! | K80: =+J80+K125 -> #DIV/0! | M80: Reference from 'net change in cash' line on the cash flow statement
B81: Accounts receivable | G81: =F81*(1+G60) -> 0 | H81: =G81*(1+H60) -> 0 | I81: =H81*(1+I60) -> 0 | J81: =I81*(1+J60) -> 0 | K81: =J81*(1+K60) -> 0 | M81: Grow in-line with revenue growth
B82: Inventories | G82: =F82*G31/F31 -> 0 | H82: =G82*H31/G31 -> 0 | I82: =H82*I31/H31 -> 0 | J82: =I82*J31/I31 -> 0 | K82: =J82*K31/J31 -> 0 | M82: Grow in-line with cost of sales growth
B83: Other current assets | G83: =F83*(1+G60) -> 0 | H83: =G83*(1+H60) -> 0 | I83: =H83*(1+I60) -> 0 | J83: =I83*(1+J60) -> 0 | K83: =J83*(1+K60) -> 0 | M83: Grow in-line with revenue growth
B84: Property, plant & equipment | M84: Reference from PP&E schedule
B85: Other non current assets | G85: =F85*(1+G60) -> 0 | H85: =G85*(1+H60) -> 0 | I85: =H85*(1+I60) -> 0 | J85: =I85*(1+J60) -> 0 | K85: =J85*(1+K60) -> 0 | M85: Grow in-line with revenue growth
B86: Total Assets | C86: =SUM(C80:C85) -> 0 | D86: =SUM(D80:D85) -> 0 | E86: =SUM(E80:E85) -> 0 | F86: =SUM(F80:F85) -> 0 | G86: =SUM(G80:G85) -> 0 | H86: =SUM(H80:H85) -> #DIV/0! | I86: =SUM(I80:I85) -> #DIV/0! | J86: =SUM(J80:J85) -> #DIV/0! | K86: =SUM(K80:K85) -> #DIV/0!
B88: Accounts payable | G88: =F88*G31/F31 -> 0 | H88: =G88*H31/G31 -> 0 | I88: =H88*I31/H31 -> 0 | J88: =I88*J31/I31 -> 0 | K88: =J88*K31/J31 -> 0 | M88: Grow in-line with cost of sales growth
B89: Other current liabilities | G89: =F89*(1+G60) -> 0 | H89: =G89*(1+H60) -> 0 | I89: =H89*(1+I60) -> 0 | J89: =I89*(1+J60) -> 0 | K89: =J89*(1+K60) -> 0 | M89: Grow in-line with revenue growth
B90: Deferred revenue (current) | G90: =F90*(1+G60) -> 0 | H90: =G90*(1+H60) -> 0 | I90: =H90*(1+I60) -> 0 | J90: =I90*(1+J60) -> 0 | K90: =J90*(1+K60) -> 0 | M90: Grow in-line with revenue growth
B91: Commercial paper / revolver | G91: =G175 -> 0 | H91: =H175 -> #DIV/0! | I91: =I175 -> #DIV/0! | J91: =J175 -> #DIV/0! | K91: =K175 -> #DIV/0! | M91: Reference EOP balance from CP/revolver schedule
B92: Long term debt (includes current portion) | G92: =F92 -> 0 | H92: =G92 -> 0 | I92: =H92 -> 0 | J92: =I92 -> 0 | K92: =J92 -> 0 | M92: straight-line
B93: Other non current liabilities | G93: =F93*(1+G60) -> 0 | H93: =G93*(1+H60) -> 0 | I93: =H93*(1+I60) -> 0 | J93: =I93*(1+J60) -> 0 | K93: =J93*(1+K60) -> 0 | M93: Grow in-line with revenue growth
B94: Total liabilities | C94: =SUM(C88:C93) -> 0 | D94: =SUM(D88:D93) -> 0 | E94: =SUM(E88:E93) -> 0 | F94: =SUM(F88:F93) -> 0 | G94: =SUM(G88:G93) -> 0 | H94: =SUM(H88:H93) -> #DIV/0! | I94: =SUM(I88:I93) -> #DIV/0! | J94: =SUM(J88:J93) -> #DIV/0! | K94: =SUM(K88:K93) -> #DIV/0!
B96: Common stock | G96: =F96+G54 -> 0 | H96: =G96+H54 -> 0 | I96: =H96+I54 -> 0 | J96: =I96+J54 -> 0 | K96: =J96+K54 -> 0 | M96: Increase by stock-based compensation forecasted in the I/S section
B97: Retained earnings | M97: Reference from Retained Earnings schedule
B98: Other comprehensive income | G98: =F98 -> 0 | H98: =G98 -> 0 | I98: =H98 -> 0 | J98: =I98 -> 0 | K98: =J98 -> 0 | M98: straight-line
B99: Total equity | C99: =SUM(C96:C98) -> 0 | D99: =SUM(D96:D98) -> 0 | E99: =SUM(E96:E98) -> 0 | F99: =SUM(F96:F98) -> 0 | G99: =SUM(G96:G98) -> 0 | H99: =SUM(H96:H98) -> 0 | I99: =SUM(I96:I98) -> 0 | J99: =SUM(J96:J98) -> 0 | K99: =SUM(K96:K98) -> 0
B100: Balance check | C100: =ROUND(C86-C94-C99,3) -> 0 | D100: =ROUND(D86-D94-D99,3) -> 0 | E100: =ROUND(E86-E94-E99,3) -> 0 | F100: =ROUND(F86-F94-F99,3) -> 0 | G100: =ROUND(G86-G94-G99,3) -> 0 | H100: =ROUND(H86-H94-H99,3) -> #DIV/0! | I100: =ROUND(I86-I94-I99,3) -> #DIV/0! | J100: =ROUND(J86-J94-J99,3) -> #DIV/0! | K100: =ROUND(K86-K94-K99,3) -> #DIV/0!
A102: X | B102: Cash-Flows Statement | G102: Forecast
B103: =B15 -> Fiscal year | G103: =G15 -> 2025 | H103: =H15 -> 2026 | I103: =I15 -> 2027 | J103: =J15 -> 2028 | K103: =K15 -> 2029
B104: =B16 -> Fiscal year end date | G104: =G16 -> 46022 | H104: =H16 -> 46387 | I104: =I16 -> 46752 | J104: =J16 -> 47118 | K104: =K16 -> 47483
B106: Net income | G106: =G47 -> 0 | H106: =H47 -> 0 | I106: =I47 -> 0 | J106: =J47 -> 0 | K106: =K47 -> 0 | M106: Reference from the I/S
B107: Depreciation and amortization | G107: =G50 -> 0 | H107: =H50 -> 0 | I107: =I50 -> 0 | J107: =J50 -> 0 | K107: =K50 -> 0 | M107: Reference from the I/S
B108: Stock based compensation | G108: =G54 -> 0 | H108: =H54 -> 0 | I108: =I54 -> 0 | J108: =J54 -> 0 | K108: =K54 -> 0
B109: Decreases / (Increases) in working capital assets | G109: =SUM(F81:F83)-SUM(G81:G83) -> 0 | H109: =SUM(G81:G83)-SUM(H81:H83) -> 0 | I109: =SUM(H81:H83)-SUM(I81:I83) -> 0 | J109: =SUM(I81:I83)-SUM(J81:J83) -> 0 | K109: =SUM(J81:J83)-SUM(K81:K83) -> 0
B110: Increases / (Decreases) in working capital liabilities | G110: =SUM(G88:G90)-SUM(F88:F90) -> 0 | H110: =SUM(H88:H90)-SUM(G88:G90) -> 0 | I110: =SUM(I88:I90)-SUM(H88:H90) -> 0 | J110: =SUM(J88:J90)-SUM(I88:I90) -> 0 | K110: =SUM(K88:K90)-SUM(J88:J90) -> 0
B111: Other non current assets | G111: =-G151 -> 0 | H111: =-H151 -> 0 | I111: =-I151 -> 0 | J111: =-J151 -> 0 | K111: =-K151 -> 0 | M111: Reference from schedule NOT the B/S: Only include 'Additions' (as outflow)
B112: Other non current liabilities | G112: =G93-F93 -> 0 | H112: =H93-G93 -> 0 | I112: =I93-H93 -> 0 | J112: =J93-I93 -> 0 | K112: =K93-J93 -> 0
B113: Cash from Operating Activities | G113: =SUM(G106:G112) -> 0 | H113: =SUM(H106:H112) -> 0 | I113: =SUM(I106:I112) -> 0 | J113: =SUM(J106:J112) -> 0 | K113: =SUM(K106:K112) -> 0
B115: Capital Expenditures | G115: =-(G136) -> 0 | H115: =-(H136) -> 0 | I115: =-(I136) -> 0 | J115: =-(J136) -> 0 | K115: =-(K136) -> 0 | M115: Reference from PP&E schedule
B116: Cash from Investing Activities | G116: =IFERROR(G115,"NA") -> 0 | H116: =IFERROR(H115,"NA") -> 0 | I116: =IFERROR(I115,"NA") -> 0 | J116: =IFERROR(J115,"NA") -> 0 | K116: =IFERROR(K115,"NA") -> 0
B118: Long term debt | G118: =G92-F92 -> 0 | H118: =H92-G92 -> 0 | I118: =I92-H92 -> 0 | J118: =J92-I92 -> 0 | K118: =K92-J92 -> 0
B119: Commercial paper/ Revolver | G119: =G91-F91 -> 0 | H119: =H91-G91 -> #DIV/0! | I119: =I91-H91 -> #DIV/0! | J119: =J91-I91 -> #DIV/0! | K119: =K91-J91 -> #DIV/0! | M119: Reference from B/S
B120: Share repurchases | G120: =G158 -> 0 | H120: =H158 -> 0 | I120: =I158 -> 0 | J120: =J158 -> 0 | K120: =K158 -> 0 | M120: Reference from Retained Earnings schedule
B121: Common dividends | G121: =G157 -> 0 | H121: =H157 -> #DIV/0! | I121: =I157 -> #DIV/0! | J121: =J157 -> #DIV/0! | K121: =K157 -> #DIV/0! | M121: Reference from Retained Earnings schedule
B122: Common dividends | G122: =G158 -> 0 | H122: =H158 -> 0 | I122: =I158 -> 0 | J122: =J158 -> 0 | K122: =K158 -> 0 | M122: Reference from Retained Earnings schedule
B123: Cash from Financing Activities | G123: =SUM(G118:G121) -> 0 | H123: =SUM(H118:H121) -> #DIV/0! | I123: =SUM(I118:I121) -> #DIV/0! | J123: =SUM(J118:J121) -> #DIV/0! | K123: =SUM(K118:K121) -> #DIV/0!
B125: Net change in cash during period | G125: =G113+G116+G123 -> 0 | H125: =H113+H116+H123 -> #DIV/0! | I125: =I113+I116+I123 -> #DIV/0! | J125: =J113+J116+J123 -> #DIV/0! | K125: =K113+K116+K123 -> #DIV/0!
A127: X | B127: Supporting Schedules | C127: Actuals | G127: Forecast
B128: Fiscal year | C128: 2021 | D128: 2022 | E128: 2023 | F128: 2024 | G128: 2025 | H128: 2026 | I128: 2027 | J128: 2028 | K128: 2029
B129: Fiscal year end date | C129: 44469 | D129: 44834 | E129: 45199 | F129: 45559 | G129: 45930 | H129: 46295 | I129: 46660 | J129: 47026 | K129: 47391
A131: X | B131: PROPERTY, PLANT & EQUIPMENT
B132: =B15 -> Fiscal year | D132: =D15 -> 2022 | E132: =E15 -> 2023 | F132: =F15 -> 2024 | G132: =G15 -> 2025 | H132: =H15 -> 2026 | I132: =I15 -> 2027 | J132: =J15 -> 2028 | K132: =K15 -> 2029
B133: =B16 -> Fiscal year end date | D133: =D16 -> 44926 | E133: =E16 -> 45291 | F133: =F16 -> 45657 | G133: =G16 -> 46022 | H133: =H16 -> 46387 | I133: =I16 -> 46752 | J133: =J16 -> 47118 | K133: =K16 -> 47483
G134: Forecast
...

Sheet Sheet1
B2: Alphabet Inc. (NASDAQ: GOOG)
B3: 3-Statement Model
B4: $ mm except per share
B6: Company name | C6: Alphabet Inc | O6: Select an operating scenario: | Q6: Base case
B7: Ticker | C7: GOOG
B8: Circ break 1=off, 0=on | C8: 0
B9: Latest closing share price
B10: Latest closing share price date
B11: Latest fiscal year end date
B12: Shares outstanding (millions)
B14: Income Statement | C14: Actuals | J14: CAGR | L14: Forecast | S14: CAGR
B15: Fiscal year | C15: 2019 | D15: 2020 | E15: 2021 | F15: 2022 | G15: 2023 | H15: 2024 | J15: 5-Year(A) | L15: =H15+1 -> 2025 | M15: =+L15+1 -> 2026 | N15: =+M15+1 -> 2027 | O15: =+N15+1 -> 2028 | P15: =+O15+1 -> 2029 | Q15: =+P15+1 -> 2030 | S15: 5-Year(F)
B16: Fiscal year end date | C16: 43830 | D16: 44196 | E16: 44561 | F16: 44926 | G16: 45291 | H16: 45657 | J16: =H16 -> 45657 | L16: =EOMONTH(H16,12) -> 46022 | M16: =EOMONTH(L16,12) -> 46387 | N16: =EOMONTH(M16,12) -> 46752 | O16: =EOMONTH(N16,12) -> 47118 | P16: =EOMONTH(O16,12) -> 47483 | Q16: =EOMONTH(P16,12) -> 47848 | S16: =Q16 -> 47848
B18: Google Search & Other | C18: ='Revenue Drivers'!D22 -> 98115 | D18: ='Revenue Drivers'!E22 -> 104062 | E18: ='Revenue Drivers'!F22 -> 148951 | F18: ='Revenue Drivers'!G22 -> 162450 | G18: ='Revenue Drivers'!H22 -> 175033 | H18: ='Revenue Drivers'!I22 -> 198084 | J18: =((H18/C18)^(1/COUNT(D18:H18))-1) -> 0.1508608 | L18: =Drivers!C35 -> 221130.19 | M18: =Drivers!D35 -> 243527.81 | N18: =Drivers!E35 -> 264237.04 | O18: =SUM(N18*O57)+N18 -> 285376 | P18: =SUM(O18*P57)+O18 -> 308206.08 | Q18: =SUM(P18*Q57)+P18 -> 332862.57 | S18: =((Q18/L18)^(1/COUNT(L18:Q18))-1) -> 0.070539801
B19: YouTube ads | C19: ='Revenue Drivers'!D23 -> 15149 | D19: ='Revenue Drivers'!E23 -> 19772 | E19: ='Revenue Drivers'!F23 -> 28845 | F19: ='Revenue Drivers'!G23 -> 29243 | G19: ='Revenue Drivers'!H23 -> 31510 | H19: ='Revenue Drivers'!I23 -> 36147 | J19: =((H19/C19)^(1/COUNT(D19:H19))-1) -> 0.18997451 | L19: =Drivers!C48 -> 41070.497 | M19: =Drivers!D48 -> 46634.941 | N19: =Drivers!E48 -> 52625.731 | O19: =SUM(N19*O58)+N19 -> 58414.561 | P19: =SUM(O19*P58)+O19 -> 64256.017 | Q19: =SUM(P19*Q58)+P19 -> 70039.059 | S19: =((Q19/L19)^(1/COUNT(L19:Q19))-1) -> 0.09303749
B20: Google Network | C20: ='Revenue Drivers'!D24 -> 21547 | D20: ='Revenue Drivers'!E24 -> 23090 | E20: ='Revenue Drivers'!F24 -> 31701 | F20: ='Revenue Drivers'!G24 -> 32780 | G20: ='Revenue Drivers'!H24 -> 31312 | H20: ='Revenue Drivers'!I24 -> 30359 | J20: =((H20/C20)^(1/COUNT(D20:H20))-1) -> 0.070976965 | L20: =Drivers!C61 -> 29632.23 | M20: =Drivers!D61 -> 29539.892 | N20: =Drivers!E61 -> 29601.512 | O20: =SUM(N20*O59)+N20 -> 29355.135 | P20: =SUM(O20*P59)+O20 -> 29263.613 | Q20: =SUM(P20*Q59)+P20 -> 29172.36 | S20: =((Q20/L20)^(1/COUNT(L20:Q20))-1) -> -0.0026034251
B21: Total Advertising Revenue | C21: =SUM(C18:C20) -> 134811 | D21: =SUM(D18:D20) -> 146924 | E21: =SUM(E18:E20) -> 209497 | F21: =SUM(F18:F20) -> 224473 | G21: =SUM(G18:G20) -> 237855 | H21: =SUM(H18:H20) -> 264590 | J21: =((H21/C21)^(1/COUNT(D21:H21))-1) -> 0.14437831 | L21: =SUM(L18:L20) -> 291832.92 | M21: =SUM(M18:M20) -> 319702.64 | N21: =SUM(N18:N20) -> 346464.28 | O21: =SUM(O18:O20) -> 373145.7 | P21: =SUM(P18:P20) -> 401725.71 | Q21: =SUM(Q18:Q20) -> 432073.99 | S21: =((Q21/L21)^(1/COUNT(L21:Q21))-1) -> 0.067588711
B23: Google subscriptions, platforms, and devices | C23: ='Revenue Drivers'!D28 -> 17014 | D23: ='Revenue Drivers'!E28 -> 21711 | E23: ='Revenue Drivers'!F28 -> 28032 | F23: ='Revenue Drivers'!G28 -> 29055 | G23: ='Revenue Drivers'!H28 -> 34688 | H23: ='Revenue Drivers'!I28 -> 40340 | J23: =((H23/C23)^(1/COUNT(D23:H23))-1) -> 0.18846362 | L23: =Drivers!C74 -> 47146.508 | M23: =Drivers!D74 -> 54034.477 | N23: =Drivers!E74 -> 60208.761 | O23: =Drivers!F74 -> 62475.761 | P23: =Drivers!G74 -> 65014.761 | Q23: =Drivers!H74 -> 67858.428 | S23: =((Q23/L23)^(1/COUNT(L23:Q23))-1) -> 0.062573653
B24: Total Google Services Revenue | C24: =+C23+C21 -> 151825 | D24: =+D23+D21 -> 168635 | E24: =+E23+E21 -> 237529 | F24: =+F23+F21 -> 253528 | G24: =+G23+G21 -> 272543 | H24: =+H23+H21 -> 304930 | J24: =((H24/C24)^(1/COUNT(D24:H24))-1) -> 0.14966517 | L24: =+L23+L21 -> 338979.43 | M24: =+M23+M21 -> 373737.11 | N24: =+N23+N21 -> 406673.04 | O24: =+O23+O21 -> 435621.46 | P24: =+P23+P21 -> 466740.47 | Q24: =+Q23+Q21 -> 499932.41 | S24: =((Q24/L24)^(1/COUNT(L24:Q24))-1) -> 0.066898223
B26: Google Cloud | C26: ='Revenue Drivers'!D10 -> 8918 | D26: ='Revenue Drivers'!E10 -> 13059 | E26: ='Revenue Drivers'!F10 -> 19206 | F26: ='Revenue Drivers'!G10 -> 26280 | G26: ='Revenue Drivers'!H10 -> 33088 | H26: ='Revenue Drivers'!I10 -> 43229 | J26: =((H26/C26)^(1/COUNT(D26:H26))-1) -> 0.37120234 | L26: =Drivers!C87 -> 56838.869 | M26: =Drivers!D87 -> 74972.973 | N26: =Drivers!E87 -> 96842.664 | O26: =SUM(N26*O61)+N26 -> 107908.45 | P26: =SUM(O26*P61)+O26 -> 120238.68 | Q26: =SUM(P26*Q61)+P26 -> 133977.83 | S26: =((Q26/L26)^(1/COUNT(L26:Q26))-1) -> 0.15362481
