Workbook

Sheet Historical Financials
B2: Affirm Holdings Inc (NASDAQ: AFRM)
B3: Historical Financials
B4: ($ In Millions, except EPS)
A6: X | B6: Income Statement | D6: FYE | H6: Quarterly | N6: Quarterly | AA6: LTM | AG6: Variance
B7: Fiscal Period | C7: 2022 | D7: 2023 | E7: 2024 | F7: 2025 | H7: 1Q23 | I7: 2Q23 | J7: 3Q23 | K7: 4Q23 | L7: 1Q24 | M7: 2Q24 | N7: 3Q24 | O7: 4Q24 | P7: 1Q25 | Q7: 2Q25 | R7: 3Q25 | S7: 4Q25 | T7: 1Q26 | V7: =K7 -> 4Q23 | W7: =L7 -> 1Q24 | X7: =M7 -> 2Q24 | Y7: =N7 -> 3Q24 | Z7: =O7 -> 4Q24 | AA7: =P7 -> 1Q25 | AB7: =Q7 -> 2Q25 | AC7: =R7 -> 3Q25 | ... AE7: =T7 -> 1Q26
B8: Fiscal Period End Date | C8: 44713 | D8: 45078 | E8: 45444 | F8: 45809 | H8: 44805 | I8: 44896 | J8: 44986 | K8: =D8 -> 45078 | L8: 45170 | M8: 45261 | N8: 45352 | O8: =E8 -> 45444 | P8: 45536 | Q8: 45627 | R8: 45717 | S8: =F8 -> 45809 | T8: 45901 | V8: =K8 -> 45078 | W8: =L8 -> 45170 | X8: =M8 -> 45261 | Y8: =N8 -> 45352 | Z8: =O8 -> 45444 | AA8: =P8 -> 45536 | AB8: =Q8 -> 45627 | AC8: =R8 -> 45717 | ... AE8: =T8 -> 45901
B10: Consolidated Revenue | C10: 1349.292 | D10: 1587.985 | E10: 2322.999 | F10: 3224.41 | H10: 361.624 | I10: 399.558 | J10: 380.978 | K10: =SUM(D10-SUM(H10:J10)) -> 445.825 | L10: 496.547 | M10: 591.11 | N10: 576.157 | O10: =SUM(E10-SUM(L10:N10)) -> 659.185 | P10: 698.479 | Q10: 866.381 | R10: 783.134 | S10: =SUM(F10-SUM(P10:R10)) -> 876.416 | T10: 933.337 | V10: =SUM(H10:K10) -> 1587.985 | W10: =SUM(I10:L10) -> 1722.908 | X10: =SUM(J10:M10) -> 1914.46 | Y10: =SUM(K10:N10) -> 2109.639 | Z10: =SUM(L10:O10) -> 2322.999 | AA10: =SUM(M10:P10) -> 2524.931 | AB10: =SUM(N10:Q10) -> 2800.202 | AC10: =SUM(O10:R10) -> 3007.179 | ... AE10: =SUM(Q10:T10) -> 3459.268 | AG10: =SUM(AE10/AA10)-1 -> 0.37004457
B11: Total Revenue | C11: =+SUM(C10:C10) -> 1349.292 | D11: =+SUM(D10:D10) -> 1587.985 | E11: =+SUM(E10:E10) -> 2322.999 | F11: =+SUM(F10:F10) -> 3224.41 | H11: =+SUM(H10:H10) -> 361.624 | I11: =+SUM(I10:I10) -> 399.558 | J11: =+SUM(J10:J10) -> 380.978 | K11: =+SUM(K10:K10) -> 445.825 | L11: =+SUM(L10:L10) -> 496.547 | M11: =+SUM(M10:M10) -> 591.11 | N11: =+SUM(N10:N10) -> 576.157 | O11: =+SUM(O10:O10) -> 659.185 | ... T11: =+SUM(T10:T10) -> 933.337 | V11: =+SUM(V10:V10) -> 1587.985 | W11: =+SUM(W10:W10) -> 1722.908 | X11: =+SUM(X10:X10) -> 1914.46 | Y11: =+SUM(Y10:Y10) -> 2109.639 | Z11: =+SUM(Z10:Z10) -> 2322.999 | AA11: =+SUM(AA10:AA10) -> 2524.931 | AB11: =+SUM(AB10:AB10) -> 2800.202 | AC11: =+SUM(AC10:AC10) -> 3007.179 | ... AE11: =+SUM(AE10:AE10) -> 3459.268 | AG11: =SUM(AE11/AA11)-1 -> 0.37004457
B13: Loss on loan purchase commitment | C13: -204.081 | D13: -140.265 | E13: -180.395 | F13: -242.264 | H13: -35.61 | I13: -38.422 | J13: -31.224 | K13: =SUM(D13-SUM(H13:J13)) -> -35.009 | L13: -34.866 | M13: -53.63 | N13: -44.143 | O13: =SUM(E13-SUM(L13:N13)) -> -47.756 | P13: -54.237 | Q13: -70.278 | R13: -57.29 | S13: =SUM(F13-SUM(P13:R13)) -> -60.459 | T13: -71.552 | V13: =SUM(H13:K13) -> -140.265 | W13: =SUM(I13:L13) -> -139.521 | X13: =SUM(J13:M13) -> -154.729 | Y13: =SUM(K13:N13) -> -167.648 | Z13: =SUM(L13:O13) -> -180.395 | AA13: =SUM(M13:P13) -> -199.766 | AB13: =SUM(N13:Q13) -> -216.414 | AC13: =SUM(O13:R13) -> -229.561 | ... AE13: =SUM(Q13:T13) -> -259.579 | AG13: =SUM(AE13/AA13)-1 -> 0.29941532
B14: Provision for credit losses | C14: -255.272 | D14: -331.86 | E14: -460.628 | F14: -616.683 | H14: -64.25 | I14: -106.689 | J14: -66.438 | K14: =SUM(D14-SUM(H14:J14)) -> -94.483 | L14: -99.696 | M14: -120.88 | N14: -122.443 | O14: =SUM(E14-SUM(L14:N14)) -> -117.609 | P14: -159.824 | Q14: -152.98 | R14: -147.252 | S14: =SUM(F14-SUM(P14:R14)) -> -156.627 | T14: -162.752 | V14: =SUM(H14:K14) -> -331.86 | W14: =SUM(I14:L14) -> -367.306 | X14: =SUM(J14:M14) -> -381.497 | Y14: =SUM(K14:N14) -> -437.502 | Z14: =SUM(L14:O14) -> -460.628 | AA14: =SUM(M14:P14) -> -520.756 | AB14: =SUM(N14:Q14) -> -552.856 | AC14: =SUM(O14:R14) -> -577.665 | ... AE14: =SUM(Q14:T14) -> -619.611 | AG14: =SUM(AE14/AA14)-1 -> 0.18982979
B15: Funding costs | C15: -69.694 | D15: -183.013 | E15: -344.253 | F15: -425.45 | H15: -25.066 | I15: -43.751 | J15: -51.188 | K15: =SUM(D15-SUM(H15:J15)) -> -63.008 | L15: -73.931 | M15: -84.617 | N15: -90.449 | O15: =SUM(E15-SUM(L15:N15)) -> -95.256 | P15: -104.145 | Q15: -107.762 | R15: -107.631 | S15: =SUM(F15-SUM(P15:R15)) -> -105.912 | T15: -110.027 | V15: =SUM(H15:K15) -> -183.013 | W15: =SUM(I15:L15) -> -231.878 | X15: =SUM(J15:M15) -> -272.744 | Y15: =SUM(K15:N15) -> -312.005 | Z15: =SUM(L15:O15) -> -344.253 | AA15: =SUM(M15:P15) -> -374.467 | AB15: =SUM(N15:Q15) -> -397.612 | AC15: =SUM(O15:R15) -> -414.794 | ... AE15: =SUM(Q15:T15) -> -431.332 | AG15: =SUM(AE15/AA15)-1 -> 0.15185584
B16: Processing and servicing | C16: -157.814 | D16: -257.343 | E16: -343.249 | F16: -457.849 | H16: -54.359 | I16: -66.508 | J16: -65.229 | K16: =SUM(D16-SUM(H16:J16)) -> -71.247 | L16: -75.671 | M16: -90.203 | N16: -88.209 | O16: =SUM(E16-SUM(L16:N16)) -> -89.166 | P16: -95.146 | Q16: -115.96 | R16: -118.398 | S16: =SUM(F16-SUM(P16:R16)) -> -128.345 | T16: -133.807 | V16: =SUM(H16:K16) -> -257.343 | W16: =SUM(I16:L16) -> -278.655 | X16: =SUM(J16:M16) -> -302.35 | Y16: =SUM(K16:N16) -> -325.33 | Z16: =SUM(L16:O16) -> -343.249 | AA16: =SUM(M16:P16) -> -362.724 | AB16: =SUM(N16:Q16) -> -388.481 | AC16: =SUM(O16:R16) -> -418.67 | ... AE16: =SUM(Q16:T16) -> -496.51 | AG16: =SUM(AE16/AA16)-1 -> 0.36883691
B17: Revenue Less Transaction Expenses | C17: =+SUM(C11+SUM(C13:C16)) -> 662.431 | D17: =+SUM(D11+SUM(D13:D16)) -> 675.504 | E17: =+SUM(E11+SUM(E13:E16)) -> 994.474 | F17: =+SUM(F11+SUM(F13:F16)) -> 1482.164 | H17: =+SUM(H11+SUM(H13:H16)) -> 182.339 | I17: =+SUM(I11+SUM(I13:I16)) -> 144.188 | J17: =+SUM(J11+SUM(J13:J16)) -> 166.899 | K17: =+SUM(K11+SUM(K13:K16)) -> 182.078 | L17: =+SUM(L11+SUM(L13:L16)) -> 212.383 | M17: =+SUM(M11+SUM(M13:M16)) -> 241.78 | N17: =+SUM(N11+SUM(N13:N16)) -> 230.913 | O17: =+SUM(O11+SUM(O13:O16)) -> 309.398 | ... T17: =+SUM(T11+SUM(T13:T16)) -> 455.199 | V17: =+SUM(V11+SUM(V13:V16)) -> 675.504 | W17: =+SUM(W11+SUM(W13:W16)) -> 705.548 | X17: =+SUM(X11+SUM(X13:X16)) -> 803.14 | Y17: =+SUM(Y11+SUM(Y13:Y16)) -> 867.154 | Z17: =+SUM(Z11+SUM(Z13:Z16)) -> 994.474 | AA17: =+SUM(AA11+SUM(AA13:AA16)) -> 1067.218 | AB17: =+SUM(AB11+SUM(AB13:AB16)) -> 1244.839 | AC17: =+SUM(AC11+SUM(AC13:AC16)) -> 1366.489 | ... AE17: =+SUM(AE11+SUM(AE13:AE16)) -> 1652.236 | AG17: =SUM(AE17/AA17)-1 -> 0.54817104
B18: Gross Margin (%) | C18: =C17/C11 -> 0.4909471 | D18: =D17/D11 -> 0.42538437 | E18: =E17/E11 -> 0.42809919 | F18: =F17/F11 -> 0.45966983 | H18: =H17/H11 -> 0.50422262 | I18: =I17/I11 -> 0.36086876 | J18: =J17/J11 -> 0.43808041 | K18: =K17/K11 -> 0.40840689 | L18: =L17/L11 -> 0.42771983 | M18: =M17/M11 -> 0.40902708 | N18: =N17/N11 -> 0.40078138 | O18: =O17/O11 -> 0.46936444 | ... T18: =T17/T11 -> 0.4877113 | V18: =V17/V11 -> 0.42538437 | W18: =W17/W11 -> 0.40950997 | X18: =X17/X11 -> 0.41951255 | Y18: =Y17/Y11 -> 0.41104379 | Z18: =Z17/Z11 -> 0.42809919 | AA18: =AA17/AA11 -> 0.42267214 | AB18: =AB17/AB11 -> 0.44455329 | AC18: =AC17/AC11 -> 0.45440893 | ... AE18: =AE17/AE11 -> 0.4776259 | AG18: =SUM(AE18-AA18)*1000 -> 54.953758
B20: Technology and data analytics | C20: -418.643 | D20: -615.818 | E20: -501.857 | F20: -589.723 | H20: -144.961 | I20: -156.747 | J20: -161.792 | K20: =SUM(D20-SUM(H20:J20)) -> -152.318 | L20: -132.965 | M20: -119.833 | N20: -124.828 | O20: =SUM(E20-SUM(L20:N20)) -> -124.231 | P20: -134.29 | Q20: -148.213 | R20: -152.62 | S20: =SUM(F20-SUM(P20:R20)) -> -154.6 | T20: -168.106 | V20: =SUM(H20:K20) -> -615.818 | W20: =SUM(I20:L20) -> -603.822 | X20: =SUM(J20:M20) -> -566.908 | Y20: =SUM(K20:N20) -> -529.944 | Z20: =SUM(L20:O20) -> -501.857 | AA20: =SUM(M20:P20) -> -503.182 | AB20: =SUM(N20:Q20) -> -531.562 | AC20: =SUM(O20:R20) -> -559.354 | ... AE20: =SUM(Q20:T20) -> -623.539 | AG20: =SUM(AE20/AA20)-1 -> 0.23919178
B21: Sales and marketing | C21: -532.343 | D21: -638.28 | E21: -576.405 | F21: -434.847 | H21: -163.873 | I21: -188.334 | J21: -140.942 | K21: =SUM(D21-SUM(H21:J21)) -> -145.131 | L21: -146.866 | M21: -161.265 | N21: -132.95 | O21: =SUM(E21-SUM(L21:N21)) -> -135.324 | P21: -145.233 | Q21: -136.038 | R21: -74.022 | S21: =SUM(F21-SUM(P21:R21)) -> -79.554 | T21: -78.491 | V21: =SUM(H21:K21) -> -638.28 | W21: =SUM(I21:L21) -> -621.273 | X21: =SUM(J21:M21) -> -594.204 | Y21: =SUM(K21:N21) -> -586.212 | Z21: =SUM(L21:O21) -> -576.405 | AA21: =SUM(M21:P21) -> -574.772 | AB21: =SUM(N21:Q21) -> -549.545 | AC21: =SUM(O21:R21) -> -490.617 | ... AE21: =SUM(Q21:T21) -> -368.105 | AG21: =SUM(AE21/AA21)-1 -> -0.35956344
B22: General and administrative | C22: -577.493 | D22: -586.398 | E22: -525.291 | F22: -545.053 | H22: -160.972 | I22: -158.639 | J22: -139.266 | K22: =SUM(D22-SUM(H22:J22)) -> -127.521 | L22: -140.334 | M22: -132.777 | N22: -128.721 | O22: =SUM(E22-SUM(L22:N22)) -> -123.459 | P22: -138.482 | Q22: -139.412 | R22: -134.303 | S22: =SUM(F22-SUM(P22:R22)) -> -132.856 | T22: -144.941 | V22: =SUM(H22:K22) -> -586.398 | W22: =SUM(I22:L22) -> -565.76 | X22: =SUM(J22:M22) -> -539.898 | Y22: =SUM(K22:N22) -> -529.353 | Z22: =SUM(L22:O22) -> -525.291 | AA22: =SUM(M22:P22) -> -523.439 | AB22: =SUM(N22:Q22) -> -530.074 | AC22: =SUM(O22:R22) -> -535.656 | ... AE22: =SUM(Q22:T22) -> -551.512 | AG22: =SUM(AE22/AA22)-1 -> 0.053631846
B23: Restructuring charges, net | C23: 0 | D23: -35.87 | E23: -6.768 | F23: 0.183 | H23: 0 | I23: 0 | J23: -34.934 | K23: =SUM(D23-SUM(H23:J23)) -> -0.936 | L23: -1.665 | M23: -0.056 | N23: -5.203 | O23: =SUM(E23-SUM(L23:N23)) -> 0.156 | P23: 0.255 | Q23: -0.06 | R23: -0.012 | S23: =SUM(F23-SUM(P23:R23)) -> 0 | T23: 0 | V23: =SUM(H23:K23) -> -35.87 | W23: =SUM(I23:L23) -> -37.535 | X23: =SUM(J23:M23) -> -37.591 | Y23: =SUM(K23:N23) -> -7.86 | Z23: =SUM(L23:O23) -> -6.768 | AA23: =SUM(M23:P23) -> -4.848 | AB23: =SUM(N23:Q23) -> -4.852 | AC23: =SUM(O23:R23) -> 0.339 | ... AE23: =SUM(Q23:T23) -> -0.072 | AG23: =SUM(AE23/AA23)-1 -> -0.98514851
B24: Operating Profit | C24: =+SUM(C17+SUM(C20:C23)) -> -866.048 | D24: =+SUM(D17+SUM(D20:D23)) -> -1200.862 | E24: =+SUM(E17+SUM(E20:E23)) -> -615.847 | F24: =+SUM(F17+SUM(F20:F23)) -> -87.276 | H24: =+SUM(H17+SUM(H20:H23)) -> -287.467 | I24: =+SUM(I17+SUM(I20:I23)) -> -359.532 | J24: =+SUM(J17+SUM(J20:J23)) -> -310.035 | K24: =+SUM(K17+SUM(K20:K23)) -> -243.828 | L24: =+SUM(L17+SUM(L20:L23)) -> -209.447 | M24: =+SUM(M17+SUM(M20:M23)) -> -172.151 | N24: =+SUM(N17+SUM(N20:N23)) -> -160.789 | O24: =+SUM(O17+SUM(O20:O23)) -> -73.46 | ... T24: =+SUM(T17+SUM(T20:T23)) -> 63.661 | V24: =+SUM(V17+SUM(V20:V23)) -> -1200.862 | W24: =+SUM(W17+SUM(W20:W23)) -> -1122.842 | X24: =+SUM(X17+SUM(X20:X23)) -> -935.461 | Y24: =+SUM(Y17+SUM(Y20:Y23)) -> -786.215 | Z24: =+SUM(Z17+SUM(Z20:Z23)) -> -615.847 | AA24: =+SUM(AA17+SUM(AA20:AA23)) -> -539.023 | AB24: =+SUM(AB17+SUM(AB20:AB23)) -> -371.194 | AC24: =+SUM(AC17+SUM(AC20:AC23)) -> -218.799 | ... AE24: =+SUM(AE17+SUM(AE20:AE23)) -> 109.008 | AG24: =SUM(AE24/AA24)-1 -> -1.2022326
B25: Operating Margin (%) | C25: =C24/C11 -> -0.64185365 | D25: =D24/D11 -> -0.75621747 | E25: =E24/E11 -> -0.26510859 | F25: =F24/F11 -> -0.027067277 | H25: =H24/H11 -> -0.79493341 | I25: =I24/I11 -> -0.89982431 | J25: =J24/J11 -> -0.81378715 | K25: =K24/K11 -> -0.54691415 | L25: =L24/L11 -> -0.421807 | M25: =M24/M11 -> -0.29123344 | N25: =N24/N11 -> -0.2790715 | O25: =O24/O11 -> -0.11144064 | ... T25: =T24/T11 -> 0.068207946 | V25: =V24/V11 -> -0.75621747 | W25: =W24/W11 -> -0.65171327 | X25: =X24/X11 -> -0.48862917 | Y25: =Y24/Y11 -> -0.37267751 | Z25: =Z24/Z11 -> -0.26510859 | AA25: =AA24/AA11 -> -0.21348029 | AB25: =AB24/AB11 -> -0.13255972 | AC25: =AC24/AC11 -> -0.072758888 | ... AE25: =AE24/AE11 -> 0.031511869 | AG25: =SUM(AE25-AA25)*1000 -> 244.99216
B27: Other income (expense), net | C27: 141.217 | D27: 211.617 | E27: 100.32 | F27: 148.739 | H27: 36.018 | I27: 35.527 | J27: 103.522 | K27: =SUM(D27-SUM(H27:J27)) -> 36.55 | L27: 38.707 | M27: 4.549 | N27: 27.743 | O27: =SUM(E27-SUM(L27:N27)) -> 29.321 | P27: 34.303 | Q27: 87.181 | R27: 13.738 | S27: =SUM(F27-SUM(P27:R27)) -> 13.517 | T27: 19.358 | V27: =SUM(H27:K27) -> 211.617 | W27: =SUM(I27:L27) -> 214.306 | X27: =SUM(J27:M27) -> 183.328 | Y27: =SUM(K27:N27) -> 107.549 | Z27: =SUM(L27:O27) -> 100.32 | AA27: =SUM(M27:P27) -> 95.916 | AB27: =SUM(N27:Q27) -> 178.548 | AC27: =SUM(O27:R27) -> 164.543 | ... AE27: =SUM(Q27:T27) -> 133.794 | AG27: =SUM(AE27/AA27)-1 -> 0.39490804
B28: Earnings before Taxes | C28: =SUM(C27:C27)+C24 -> -724.831 | D28: =SUM(D27:D27)+D24 -> -989.245 | E28: =SUM(E27:E27)+E24 -> -515.527 | F28: =SUM(F27:F27)+F24 -> 61.463 | H28: =SUM(H27:H27)+H24 -> -251.449 | I28: =SUM(I27:I27)+I24 -> -324.005 | J28: =SUM(J27:J27)+J24 -> -206.513 | K28: =SUM(K27:K27)+K24 -> -207.278 | L28: =SUM(L27:L27)+L24 -> -170.74 | M28: =SUM(M27:M27)+M24 -> -167.602 | N28: =SUM(N27:N27)+N24 -> -133.046 | O28: =SUM(O27:O27)+O24 -> -44.139 | ... T28: =SUM(T27:T27)+T24 -> 83.019 | V28: =SUM(V27:V27)+V24 -> -989.245 | W28: =SUM(W27:W27)+W24 -> -908.536 | X28: =SUM(X27:X27)+X24 -> -752.133 | Y28: =SUM(Y27:Y27)+Y24 -> -678.666 | Z28: =SUM(Z27:Z27)+Z24 -> -515.527 | AA28: =SUM(AA27:AA27)+AA24 -> -443.107 | AB28: =SUM(AB27:AB27)+AB24 -> -192.646 | AC28: =SUM(AC27:AC27)+AC24 -> -54.256 | ... AE28: =SUM(AE27:AE27)+AE24 -> 242.802 | AG28: =SUM(AE28/AA28)-1 -> -1.5479534
B29: EBT Margin (%) | C29: =C28/C11 -> -0.53719358 | D29: =D28/D11 -> -0.62295614 | E29: =E28/E11 -> -0.22192304 | F29: =F28/F11 -> 0.019061782 | H29: =H28/H11 -> -0.69533272 | I29: =I28/I11 -> -0.81090855 | J29: =J28/J11 -> -0.54206017 | K29: =K28/K11 -> -0.46493131 | L29: =L28/L11 -> -0.34385466 | M29: =M28/M11 -> -0.28353775 | N29: =N28/N11 -> -0.2309197 | O29: =O28/O11 -> -0.066959958 | ... T29: =T28/T11 -> 0.088948579 | V29: =V28/V11 -> -0.62295614 | W29: =W28/W11 -> -0.52732705 | X29: =X28/X11 -> -0.39286953 | Y29: =Y28/Y11 -> -0.32169769 | Z29: =Z28/Z11 -> -0.22192304 | AA29: =AA28/AA11 -> -0.17549272 | AB29: =AB28/AB11 -> -0.06879718 | AC29: =AC28/AC11 -> -0.018042158 | ... AE29: =AE28/AE11 -> 0.070188838 | AG29: =SUM(AE29-AA29)*1000 -> 245.68155
B31: Income tax benefit (expense) | C31: -18.308 | D31: 3.9 | E31: -2.23 | F31: -9.279 | H31: 0.18 | I31: 1.568 | J31: 0.836 | K31: =SUM(D31-SUM(H31:J31)) -> 1.316 | L31: -1.043 | M31: 0.7 | N31: -0.89 | O31: =SUM(E31-SUM(L31:N31)) -> -0.997 | P31: -1.902 | Q31: -2.499 | R31: -2.541 | S31: =SUM(F31-SUM(P31:R31)) -> -2.337 | T31: -2.326 | V31: =SUM(H31:K31) -> 3.9 | W31: =SUM(I31:L31) -> 2.677 | X31: =SUM(J31:M31) -> 1.809 | Y31: =SUM(K31:N31) -> 0.083 | Z31: =SUM(L31:O31) -> -2.23 | AA31: =SUM(M31:P31) -> -3.089 | AB31: =SUM(N31:Q31) -> -6.288 | AC31: =SUM(O31:R31) -> -7.939 | ... AE31: =SUM(Q31:T31) -> -9.703 | AG31: =SUM(AE31/AA31)-1 -> 2.141146
B32: Net loss | C32: =SUM(C28+SUM(C31:C31)) -> -743.139 | D32: =SUM(D28+SUM(D31:D31)) -> -985.345 | E32: =SUM(E28+SUM(E31:E31)) -> -517.757 | F32: =SUM(F28+SUM(F31:F31)) -> 52.184 | H32: =SUM(H28+SUM(H31:H31)) -> -251.269 | I32: =SUM(I28+SUM(I31:I31)) -> -322.437 | J32: =SUM(J28+SUM(J31:J31)) -> -205.677 | K32: =SUM(K28+SUM(K31:K31)) -> -205.962 | L32: =SUM(L28+SUM(L31:L31)) -> -171.783 | M32: =SUM(M28+SUM(M31:M31)) -> -166.902 | N32: =SUM(N28+SUM(N31:N31)) -> -133.936 | O32: =SUM(O28+SUM(O31:O31)) -> -45.136 | ... T32: =SUM(T28+SUM(T31:T31)) -> 80.693 | V32: =SUM(V28+SUM(V31:V31)) -> -985.345 | W32: =SUM(W28+SUM(W31:W31)) -> -905.859 | X32: =SUM(X28+SUM(X31:X31)) -> -750.324 | Y32: =SUM(Y28+SUM(Y31:Y31)) -> -678.583 | Z32: =SUM(Z28+SUM(Z31:Z31)) -> -517.757 | AA32: =SUM(AA28+SUM(AA31:AA31)) -> -446.196 | AB32: =SUM(AB28+SUM(AB31:AB31)) -> -198.934 | AC32: =SUM(AC28+SUM(AC31:AC31)) -> -62.195 | ... AE32: =SUM(AE28+SUM(AE31:AE31)) -> 233.099 | AG32: =SUM(AE32/AA32)-1 -> -1.5224139
B33: Net Margin (%) | C33: =C32/C11 -> -0.55076218 | D33: =D32/D11 -> -0.62050019 | E33: =E32/E11 -> -0.22288301 | F33: =F32/F11 -> 0.016184046 | H33: =H32/H11 -> -0.69483497 | I33: =I32/I11 -> -0.80698422 | J33: =J32/J11 -> -0.53986582 | K33: =K32/K11 -> -0.46197948 | L33: =L32/L11 -> -0.34595517 | M33: =M32/M11 -> -0.28235354 | N33: =N32/N11 -> -0.23246442 | O33: =O32/O11 -> -0.068472432 | ... T33: =T32/T11 -> 0.086456446 | V33: =V32/V11 -> -0.62050019 | W33: =W32/W11 -> -0.52577329 | X33: =X32/X11 -> -0.39192462 | Y33: =Y32/Y11 -> -0.32165835 | Z33: =Z32/Z11 -> -0.22288301 | AA33: =AA32/AA11 -> -0.17671612 | AB33: =AB32/AB11 -> -0.071042732 | AC33: =AC32/AC11 -> -0.020682174 | ... AE33: =AE32/AE11 -> 0.067383909 | AG33: =SUM(AE33-AA33)*1000 -> 244.10003
B35: Basic shares | C35: 281.73994 | D35: 295.36527 | E35: 309.85713 | F35: 322.85187 | H35: 290.92927 | I35: 293.68333 | J35: 297.20472 | K35: =D35 -> 295.36527 | L35: 303.83967 | M35: 307.5716 | N35: 312.62673 | O35: =E35 -> 309.85713 | P35: 318.23456 | Q35: 322.28233 | R35: 324.05397 | S35: =F35 -> 322.85187 | T35: 330.23802 | V35: =K35 -> 295.36527 | W35: =L35 -> 303.83967 | X35: =M35 -> 307.5716 | Y35: =N35 -> 312.62673 | Z35: =O35 -> 309.85713 | AA35: =P35 -> 318.23456 | AB35: =Q35 -> 322.28233 | AC35: =R35 -> 324.05397 | ... AE35: =T35 -> 330.23802 | AG35: =SUM(AE35/AA35)-1 -> 0.03771894
B36: Basic EPS | C36: =C32/C35 -> -2.6376771 | D36: =D32/D35 -> -3.3360219 | E36: =E32/E35 -> -1.670954 | F36: =F32/F35 -> 0.1616345 | H36: =H32/H35 -> -0.86367728 | I36: =I32/I35 -> -1.0979071 | J36: =J32/J35 -> -0.69203815 | K36: =K32/K35 -> -0.69731286 | L36: =L32/L35 -> -0.56537384 | M36: =M32/M35 -> -0.54264438 | N36: =N32/N35 -> -0.42842146 | O36: =O32/O35 -> -0.14566713 | ... T36: =T32/T35 -> 0.244348 | V36: =V32/V35 -> -3.3360219 | W36: =W32/W35 -> -2.9813717 | X36: =X32/X35 -> -2.43951 | Y36: =Y32/Y35 -> -2.1705854 | Z36: =Z32/Z35 -> -1.670954 | AA36: =AA32/AA35 -> -1.4020979 | AB36: =AB32/AB35 -> -0.61726623 | AC36: =AC32/AC35 -> -0.19192791 | ... AE36: =AE32/AE35 -> 0.70585148 | AG36: =SUM(AE36/AA36)-1 -> -1.5034253
B38: Fully Diluted Shares | C38: 281.73994 | D38: 295.36527 | E38: 309.85713 | F38: 341.02357 | H38: 313 | I38: 324 | J38: 321 | K38: =D38 -> 295.36527 | L38: 334 | M38: 341 | N38: 341 | O38: =E38 -> 309.85713 | P38: 357 | Q38: 356 | R38: 352 | S38: =F38 -> 341.02357 | T38: 361 | V38: =K38 -> 295.36527 | W38: =L38 -> 334 | X38: =M38 -> 341 | Y38: =N38 -> 341 | Z38: =O38 -> 309.85713 | AA38: =P38 -> 357 | AB38: =Q38 -> 356 | AC38: =R38 -> 352 | ... AE38: =T38 -> 361 | AG38: =SUM(AE38/AA38)-1 -> 0.011204482
B39: Diluted EPS | C39: =C32/C38 -> -2.6376771 | D39: =D32/D38 -> -3.3360219 | E39: =E32/E38 -> -1.670954 | F39: =F32/F38 -> 0.15302168 | H39: =H32/H38 -> -0.80277636 | I39: =I32/I38 -> -0.99517593 | J39: =J32/J38 -> -0.64073832 | K39: =K32/K38 -> -0.69731286 | L39: =L32/L38 -> -0.51432036 | M39: =M32/M38 -> -0.48944868 | N39: =N32/N38 -> -0.39277419 | O39: =O32/O38 -> -0.14566713 | ... T39: =T32/T38 -> 0.22352632 | V39: =V32/V38 -> -3.3360219 | W39: =W32/W38 -> -2.7121527 | X39: =X32/X38 -> -2.2003636 | Y39: =Y32/Y38 -> -1.9899795 | Z39: =Z32/Z38 -> -1.670954 | AA39: =AA32/AA38 -> -1.2498487 | AB39: =AB32/AB38 -> -0.55880337 | AC39: =AC32/AC38 -> -0.17669034 | ... AE39: =AE32/AE38 -> 0.6457036 | AG39: =SUM(AE39/AA39)-1 -> -1.5166254
A41: X | B41: Balance Sheet | C41: FYE | N41: Quarterly | AA41: LTM | AG41: Variance
B42: =B7 -> Fiscal Period | C42: =C7 -> 2022 | D42: =D7 -> 2023 | E42: =E7 -> 2024 | F42: =F7 -> 2025 | H42: =H7 -> 1Q23 | I42: =I7 -> 2Q23 | J42: =J7 -> 3Q23 | K42: =K7 -> 4Q23 | L42: =L7 -> 1Q24 | M42: =M7 -> 2Q24 | N42: =N7 -> 3Q24 | O42: =O7 -> 4Q24 | ... T42: =T7 -> 1Q26 | V42: =V7 -> 4Q23 | W42: =W7 -> 1Q24 | X42: =X7 -> 2Q24 | Y42: =Y7 -> 3Q24 | Z42: =Z7 -> 4Q24 | AA42: =AA7 -> 1Q25 | AB42: =AB7 -> 2Q25 | AC42: =AC7 -> 3Q25 | ... AE42: =AE7 -> 1Q26
B43: =B8 -> Fiscal Period End Date | C43: =C8 -> 44713 | D43: =D8 -> 45078 | E43: =E8 -> 45444 | F43: =F8 -> 45809 | H43: =H8 -> 44805 | I43: =I8 -> 44896 | J43: =J8 -> 44986 | K43: =K8 -> 45078 | L43: =L8 -> 45170 | M43: =M8 -> 45261 | N43: =N8 -> 45352 | O43: =O8 -> 45444 | ... T43: =T8 -> 45901 | V43: =V8 -> 45078 | W43: =W8 -> 45170 | X43: =X8 -> 45261 | Y43: =Y8 -> 45352 | Z43: =Z8 -> 45444 | AA43: =AA8 -> 45536 | AB43: =AB8 -> 45627 | AC43: =AC8 -> 45717 | ... AE43: =AE8 -> 45901
B46: Total Assets
B47: Cash and cash equivalents | C47: 1255.171 | D47: 892.027 | E47: 1013.106 | F47: 1354.455 | H47: 1530.132 | I47: 1440.333 | J47: 972.477 | K47: =D47 -> 892.027 | L47: 1079.261 | M47: 1036.719 | N47: 1272.76 | O47: =E47 -> 1013.106 | P47: 1046.16 | Q47: 1200.381 | R47: 1351.148 | S47: =F47 -> 1354.455 | T47: 1428.848 | V47: =K47 -> 892.027 | W47: =L47 -> 1079.261 | X47: =M47 -> 1036.719 | Y47: =N47 -> 1272.76 | Z47: =O47 -> 1013.106 | AA47: =P47 -> 1046.16 | AB47: =Q47 -> 1200.381 | AC47: =R47 -> 1351.148 | ... AE47: =T47 -> 1428.848 | AG47: =SUM(AE47/AA47)-1 -> 0.36580255
B48: Restricted cash | C48: 295.636 | D48: 367.917 | E48: 282.293 | F48: 401.968 | H48: 383.406 | I48: 424.46 | J48: 409.015 | K48: =D48 -> 367.917 | L48: 409.231 | M48: 411.259 | N48: 346.931 | O48: =E48 -> 282.293 | P48: 338.462 | Q48: 536.776 | R48: 384.811 | S48: =F48 -> 401.968 | T48: 668.762 | V48: =K48 -> 367.917 | W48: =L48 -> 409.231 | X48: =M48 -> 411.259 | Y48: =N48 -> 346.931 | Z48: =O48 -> 282.293 | AA48: =P48 -> 338.462 | AB48: =Q48 -> 536.776 | AC48: =R48 -> 384.811 | ... AE48: =T48 -> 668.762 | AG48: =SUM(AE48/AA48)-1 -> 0.97588503
B49: Securities available for sale at fair value | C49: 1595.373 | D49: 1174.653 | E49: 1131.628 | F49: 871.425 | H49: 1237.291 | I49: 914.923 | J49: 1059.031 | K49: =D49 -> 1174.653 | L49: 1021.63 | M49: 914.069 | N49: 781.402 | O49: =E49 -> 1131.628 | P49: 1073.685 | Q49: 666.684 | R49: 780.17 | S49: =F49 -> 871.425 | T49: 812.442 | V49: =K49 -> 1174.653 | W49: =L49 -> 1021.63 | X49: =M49 -> 914.069 | Y49: =N49 -> 781.402 | Z49: =O49 -> 1131.628 | AA49: =P49 -> 1073.685 | AB49: =Q49 -> 666.684 | AC49: =R49 -> 780.17 | ... AE49: =T49 -> 812.442 | AG49: =SUM(AE49/AA49)-1 -> -0.24331438
B50: Loans held for sale | C50: 2.67 | D50: 0.076 | E50: 0.036 | F50: 0 | H50: 7.112 | I50: 0.344 | J50: 0.122 | K50: =D50 -> 0.076 | L50: 0.145 | M50: 0.029 | N50: 0.127 | O50: =E50 -> 0.036 | P50: 0 | Q50: 0 | R50: 0.001 | S50: =F50 -> 0 | T50: 0.012 | V50: =K50 -> 0.076 | W50: =L50 -> 0.145 | X50: =M50 -> 0.029 | Y50: =N50 -> 0.127 | Z50: =O50 -> 0.036 | AA50: =P50 -> 0 | AB50: =Q50 -> 0 | AC50: =R50 -> 0.001 | ... AE50: =T50 -> 0.012 | AG50: =SUM(AE50/AA50)-1 -> #DIV/0!
B51: Loans held for investment, net | C51: 2348.169 | D51: 4198.431 | E51: 5360.959 | F51: 6628.605 | H51: 2528.612 | I51: 3473.404 | J51: 3599.206 | K51: =D51 -> 4198.431 | L51: 4317.354 | M51: 4976.608 | N51: 5172.319 | O51: =E51 -> 5360.959 | P51: 5960.228 | Q51: 6432.336 | R51: 6255.459 | S51: =F51 -> 6628.605 | T51: 6809.376 | V51: =K51 -> 4198.431 | W51: =L51 -> 4317.354 | X51: =M51 -> 4976.608 | Y51: =N51 -> 5172.319 | Z51: =O51 -> 5360.959 | AA51: =P51 -> 5960.228 | AB51: =Q51 -> 6432.336 | AC51: =R51 -> 6255.459 | ... AE51: =T51 -> 6809.376
B52: Accounts receivable, net | C52: 142.052 | D52: 199.085 | E52: 353.028 | F52: 426.177 | H52: 147.757 | I52: 201.622 | J52: 135.816 | K52: =D52 -> 199.085 | L52: 236.234 | M52: 307.286 | N52: 293.388 | O52: =E52 -> 353.028 | P52: 308.394 | Q52: 203.626 | R52: 220.279 | S52: =F52 -> 426.177 | T52: 283.726 | V52: =K52 -> 199.085 | W52: =L52 -> 236.234 | X52: =M52 -> 307.286 | Y52: =N52 -> 293.388 | Z52: =O52 -> 353.028 | AA52: =P52 -> 308.394 | AB52: =Q52 -> 203.626 | AC52: =R52 -> 220.279 | ... AE52: =T52 -> 283.726
B53: Goodwill | C53: 539.534 | D53: 542.571 | E53: 533.439 | F53: 534.156 | H53: 525 | I53: 527.63 | J53: 537.126 | K53: =D53 -> 542.571 | L53: 536.418 | M53: 541.156 | N53: 535.818 | O53: =E53 -> 533.439 | P53: 536.745 | Q53: 521.699 | R53: 522.346 | S53: =F53 -> 534.156 | T53: 529.91 | V53: =K53 -> 542.571 | W53: =L53 -> 536.418 | X53: =M53 -> 541.156 | Y53: =N53 -> 535.818 | Z53: =O53 -> 533.439 | AA53: =P53 -> 536.745 | AB53: =Q53 -> 521.699 | AC53: =R53 -> 522.346 | ... AE53: =T53 -> 529.91
B54: Property, equipment and software, net | C54: 171.482 | D54: 290.135 | E54: 427.686 | F54: 572.637 | H54: 208.46 | I54: 248.939 | J54: 277.156 | K54: =D54 -> 290.135 | L54: 338.749 | M54: 369.854 | N54: 401.535 | O54: =E54 -> 427.686 | P54: 473.019 | Q54: 506.334 | R54: 543.327 | S54: =F54 -> 572.637 | T54: 613.938 | V54: =K54 -> 290.135 | W54: =L54 -> 338.749 | X54: =M54 -> 369.854 | Y54: =N54 -> 401.535 | Z54: =O54 -> 427.686 | AA54: =P54 -> 473.019 | AB54: =Q54 -> 506.334 | AC54: =R54 -> 543.327 | ... AE54: =T54 -> 613.938
B55: Other assets | C55: 623.705 | D55: 490.72 | E55: 417.444 | F55: 365.505 | H55: 597.29 | I55: 573.096 | J55: 517.9 | K55: =D55 -> 490.72 | L55: 468.127 | M55: 508.009 | N55: 397.146 | O55: =E55 -> 417.444 | P55: 402.463 | Q55: 413.241 | R55: 378.646 | S55: =F55 -> 365.505 | T55: 331.552 | V55: =K55 -> 490.72 | W55: =L55 -> 468.127 | X55: =M55 -> 508.009 | Y55: =N55 -> 397.146 | Z55: =O55 -> 417.444 | AA55: =P55 -> 402.463 | AB55: =Q55 -> 413.241 | AC55: =R55 -> 378.646 | ... AE55: =T55 -> 331.552
B56: Total Assets | C56: =SUM(C47:C55) -> 6973.792 | D56: =SUM(D47:D55) -> 8155.615 | E56: =SUM(E47:E55) -> 9519.619 | F56: =SUM(F47:F55) -> 11154.928 | H56: =SUM(H47:H55) -> 7165.06 | I56: =SUM(I47:I55) -> 7804.751 | J56: =SUM(J47:J55) -> 7507.849 | K56: =SUM(K47:K55) -> 8155.615 | L56: =SUM(L47:L55) -> 8407.149 | M56: =SUM(M47:M55) -> 9064.989 | N56: =SUM(N47:N55) -> 9201.426 | O56: =SUM(O47:O55) -> 9519.619 | ... T56: =SUM(T47:T55) -> 11478.566 | V56: =SUM(V47:V55) -> 8155.615 | W56: =SUM(W47:W55) -> 8407.149 | X56: =SUM(X47:X55) -> 9064.989 | Y56: =SUM(Y47:Y55) -> 9201.426 | Z56: =SUM(Z47:Z55) -> 9519.619 | AA56: =SUM(AA47:AA55) -> 10139.156 | AB56: =SUM(AB47:AB55) -> 10481.077 | AC56: =SUM(AC47:AC55) -> 10436.187 | ... AE56: =SUM(AE47:AE55) -> 11478.566 | AG56: =SUM(AE56/AA56)-1 -> 0.13210271
B58: Total Liabilities
B59: Accounts payable | C59: 33.072 | D59: 28.602 | E59: 41.019 | F59: 82.82 | H59: 34.534 | I59: 28.974 | J59: 30.022 | K59: =D59 -> 28.602 | L59: 27.345 | M59: 59.8 | N59: 35.224 | O59: =E59 -> 41.019 | P59: 57.561 | Q59: 50.626 | R59: 41.057 | S59: =F59 -> 82.82 | T59: 58.019 | V59: =K59 -> 28.602 | W59: =L59 -> 27.345 | X59: =M59 -> 59.8 | Y59: =N59 -> 35.224 | Z59: =O59 -> 41.019 | AA59: =P59 -> 57.561 | AB59: =Q59 -> 50.626 | AC59: =R59 -> 41.057 | ... AE59: =T59 -> 58.019 | AG59: =SUM(AE59/AA59)-1 -> 0.0079567763
B60: Payable to third-party | C60: 71.383 | D60: 53.852 | E60: 159.643 | F60: 211.7 | H60: 90.811 | I60: 127.378 | J60: 44.187 | K60: =D60 -> 53.852 | L60: 109.498 | M60: 134.567 | N60: 129.73 | O60: =E60 -> 159.643 | P60: 152.035 | Q60: 157.245 | R60: 176.996 | S60: =F60 -> 211.7 | T60: 193.79 | V60: =K60 -> 53.852 | W60: =L60 -> 109.498 | X60: =M60 -> 134.567 | Y60: =N60 -> 129.73 | Z60: =O60 -> 159.643 | AA60: =P60 -> 152.035 | AB60: =Q60 -> 157.245 | AC60: =R60 -> 176.996 | ... AE60: =T60 -> 193.79
B61: Accrued interest payable | C61: 6.659 | D61: 13.498 | E61: 24.327 | F61: 24.465 | H61: 5.292 | I61: 11.971 | J61: 13.826 | K61: =D61 -> 13.498 | L61: 19.589 | M61: 22.181 | N61: 22.816 | O61: =E61 -> 24.327 | P61: 24.484 | Q61: 25.357 | R61: 23.944 | S61: =F61 -> 24.465 | T61: 25.649 | V61: =K61 -> 13.498 | W61: =L61 -> 19.589 | X61: =M61 -> 22.181 | Y61: =N61 -> 22.816 | Z61: =O61 -> 24.327 | AA61: =P61 -> 24.484 | AB61: =Q61 -> 25.357 | AC61: =R61 -> 23.944 | ... AE61: =T61 -> 25.649
B62: Accrued expenses and other liabilities | C62: 237.598 | D62: 180.883 | E62: 147.429 | F62: 157.272 | H62: 249.812 | I62: 220.619 | J62: 192.36 | K62: =D62 -> 180.883 | L62: 160.328 | M62: 150.272 | N62: 150.162 | O62: =E62 -> 147.429 | P62: 137.464 | Q62: 155.568 | R62: 173.629 | S62: =F62 -> 157.272 | T62: 165.83 | V62: =K62 -> 180.883 | W62: =L62 -> 160.328 | X62: =M62 -> 150.272 | Y62: =N62 -> 150.162 | Z62: =O62 -> 147.429 | AA62: =P62 -> 137.464 | AB62: =Q62 -> 155.568 | AC62: =R62 -> 173.629 | ... AE62: =T62 -> 165.83 | AG62: =SUM(AE62/AA62)-1 -> 0.20635221
B63: Convertible debt | C63: 1706.668 | D63: 1414.208 | E63: 1341.43 | F63: 1153 | H63: 1707.724 | I63: 1708.779 | J63: 1413.345 | K63: =D63 -> 1414.208 | L63: 1415.08 | M63: 1415.952 | N63: 1385.891 | O63: =E63 -> 1341.43 | P63: 1202.519 | Q63: 1151.048 | R63: 1152.019 | S63: =F63 -> 1153 | T63: 1127.668 | V63: =K63 -> 1414.208 | W63: =L63 -> 1415.08 | X63: =M63 -> 1415.952 | Y63: =N63 -> 1385.891 | Z63: =O63 -> 1341.43 | AA63: =P63 -> 1202.519 | AB63: =Q63 -> 1151.048 | AC63: =R63 -> 1152.019 | ... AE63: =T63 -> 1127.668 | AG63: =SUM(AE63/AA63)-1 -> -0.06224517
B64: Notes issued by securitization trusts | C64: 1627.58 | D64: 2165.577 | E64: 3236.873 | F64: 4833.855 | H64: 1720.812 | I64: 1314.212 | J64: 1788.853 | K64: =D64 -> 2165.577 | L64: 2398.758 | M64: 2740.656 | N64: 3240.871 | O64: =E64 -> 3236.873 | P64: 3985.484 | Q64: 3988.887 | R64: 4084.934 | S64: =F64 -> 4833.855 | T64: 4830.819 | V64: =K64 -> 2165.577 | W64: =L64 -> 2398.758 | X64: =M64 -> 2740.656 | Y64: =N64 -> 3240.871 | Z64: =O64 -> 3236.873 | AA64: =P64 -> 3985.484 | AB64: =Q64 -> 3988.887 | AC64: =R64 -> 4084.934 | ... AE64: =T64 -> 4830.819 | AG64: =SUM(AE64/AA64)-1 -> 0.21210347
B65: Funding debt | C65: 672.577 | D65: 1764.812 | E65: 1836.909 | F65: 1622.808 | H65: 792.637 | I65: 1882.67 | J65: 1514.12 | K65: =D65 -> 1764.812 | L65: 1709.751 | M65: 1906.672 | N65: 1613.272 | O65: =E65 -> 1836.909 | P65: 1744.04 | Q65: 2166.806 | R65: 1908.693 | S65: =F65 -> 1622.808 | T65: 1777.906 | V65: =K65 -> 1764.812 | W65: =L65 -> 1709.751 | X65: =M65 -> 1906.672 | Y65: =N65 -> 1613.272 | Z65: =O65 -> 1836.909 | AA65: =P65 -> 1744.04 | AB65: =Q65 -> 2166.806 | AC65: =R65 -> 1908.693 | ... AE65: =T65 -> 1777.906 | AG65: =SUM(AE65/AA65)-1 -> 0.019418133
B66: Total Liabilities | C66: =SUM(C59:C65) -> 4355.537 | D66: =SUM(D59:D65) -> 5621.432 | E66: =SUM(E59:E65) -> 6787.63 | F66: =SUM(F59:F65) -> 8085.92 | H66: =SUM(H59:H65) -> 4601.622 | I66: =SUM(I59:I65) -> 5294.603 | J66: =SUM(J59:J65) -> 4996.713 | K66: =SUM(K59:K65) -> 5621.432 | L66: =SUM(L59:L65) -> 5840.349 | M66: =SUM(M59:M65) -> 6430.1 | N66: =SUM(N59:N65) -> 6577.966 | O66: =SUM(O59:O65) -> 6787.63 | ... T66: =SUM(T59:T65) -> 8179.681 | V66: =SUM(V59:V65) -> 5621.432 | W66: =SUM(W59:W65) -> 5840.349 | X66: =SUM(X59:X65) -> 6430.1 | Y66: =SUM(Y59:Y65) -> 6577.966 | Z66: =SUM(Z59:Z65) -> 6787.63 | AA66: =SUM(AA59:AA65) -> 7303.587 | AB66: =SUM(AB59:AB65) -> 7695.537 | AC66: =SUM(AC59:AC65) -> 7561.272 | ... AE66: =SUM(AE59:AE65) -> 8179.681 | AG66: =SUM(AE66/AA66)-1 -> 0.11995393
B68: Class A common stock | C68: 0.002 | D68: 0.002 | E68: 0.002 | F68: 0.002 | H68: 0.002 | I68: 0.002 | J68: 0.002 | K68: =D68 -> 0.002 | L68: 0.002 | M68: 0.002 | N68: 0.002 | O68: =E68 -> 0.002 | P68: 0.002 | Q68: 0.002 | R68: 0.002 | S68: =F68 -> 0.002 | T68: 0.002 | V68: =K68 -> 0.002 | W68: =L68 -> 0.002 | X68: =M68 -> 0.002 | Y68: =N68 -> 0.002 | Z68: =O68 -> 0.002 | AA68: =P68 -> 0.002 | AB68: =Q68 -> 0.002 | AC68: =R68 -> 0.002 | ... AE68: =T68 -> 0.002 | AG68: =SUM(AE68/AA68)-1 -> 0
B69: Class B common stock | C69: 0.001 | D69: 0.001 | E69: 0.001 | F69: 0.001 | H69: 0.001 | I69: 0.001 | J69: 0.001 | K69: =D69 -> 0.001 | L69: 0.001 | M69: 0.001 | N69: 0.001 | O69: =E69 -> 0.001 | P69: 0.001 | Q69: 0.001 | R69: 0.001 | S69: =F69 -> 0.001 | T69: 0.001 | V69: =K69 -> 0.001 | W69: =L69 -> 0.001 | X69: =M69 -> 0.001 | Y69: =N69 -> 0.001 | Z69: =O69 -> 0.001 | AA69: =P69 -> 0.001 | AB69: =Q69 -> 0.001 | AC69: =R69 -> 0.001 | ... AE69: =T69 -> 0.001 | AG69: =SUM(AE69/AA69)-1 -> 0
B70: Additional paid in capital | C70: 4231.303 | D70: 5147.765 | E70: 5862.555 | F70: 6140.893 | H70: 4454.829 | I70: 4716.385 | J70: 4918.756 | K70: =D70 -> 5147.765 | L70: 5355.032 | M70: 5571.955 | N70: 5704.626 | O70: =E70 -> 5862.555 | P70: 6053.917 | Q70: 5961.956 | R70: 6045.479 | S70: =F70 -> 6140.893 | T70: 6299.395 | V70: =K70 -> 5147.765 | W70: =L70 -> 5355.032 | X70: =M70 -> 5571.955 | Y70: =N70 -> 5704.626 | Z70: =O70 -> 5862.555 | AA70: =P70 -> 6053.917 | AB70: =Q70 -> 5961.956 | AC70: =R70 -> 6045.479 | ... AE70: =T70 -> 6299.395 | AG70: =SUM(AE70/AA70)-1 -> 0.040548623
B71: Accumulated deficit | C71: -1605.902 | D71: -2591.247 | E71: -3109.004 | F71: -3056.818 | H71: -1857.171 | I71: -2179.608 | J71: -2385.285 | K71: =D71 -> -2591.247 | L71: -2763.03 | M71: -2929.932 | N71: -3063.868 | O71: =E71 -> -3109.004 | P71: -3209.226 | Q71: -3128.866 | R71: -3126.062 | S71: =F71 -> -3056.818 | T71: -2976.124 | V71: =K71 -> -2591.247 | W71: =L71 -> -2763.03 | X71: =M71 -> -2929.932 | Y71: =N71 -> -3063.868 | Z71: =O71 -> -3109.004 | AA71: =P71 -> -3209.226 | AB71: =Q71 -> -3128.866 | AC71: =R71 -> -3126.062 | ... AE71: =T71 -> -2976.124 | AG71: =SUM(AE71/AA71)-1 -> -0.072634959
B72: Accumulated other comprehensive loss | C72: -7.149 | D72: -22.338 | E72: -21.565 | F72: -15.069 | H72: -34.223 | I72: -26.632 | J72: -22.338 | K72: =D72 -> -22.338 | L72: -25.205 | M72: -7.142 | N72: -17.301 | O72: =E72 -> -21.565 | P72: -9.122 | Q72: -47.553 | R72: -44.504 | S72: =F72 -> -15.069 | T72: -24.389 | V72: =K72 -> -22.338 | W72: =L72 -> -25.205 | X72: =M72 -> -7.142 | Y72: =N72 -> -17.301 | Z72: =O72 -> -21.565 | AA72: =P72 -> -9.122 | AB72: =Q72 -> -47.553 | AC72: =R72 -> -44.504 | ... AE72: =T72 -> -24.389 | AG72: =SUM(AE72/AA72)-1 -> 1.6736461
B73: Total stockholders' equity | C73: =SUM(C68:C72) -> 2618.255 | D73: =SUM(D68:D72) -> 2534.183 | E73: =SUM(E68:E72) -> 2731.989 | F73: =SUM(F68:F72) -> 3069.009 | H73: =SUM(H68:H72) -> 2563.438 | I73: =SUM(I68:I72) -> 2510.148 | J73: =SUM(J68:J72) -> 2511.136 | K73: =SUM(K68:K72) -> 2534.183 | L73: =SUM(L68:L72) -> 2566.8 | M73: =SUM(M68:M72) -> 2634.884 | N73: =SUM(N68:N72) -> 2623.46 | O73: =SUM(O68:O72) -> 2731.989 | ... T73: =SUM(T68:T72) -> 3298.885 | V73: =SUM(V68:V72) -> 2534.183 | W73: =SUM(W68:W72) -> 2566.8 | X73: =SUM(X68:X72) -> 2634.884 | Y73: =SUM(Y68:Y72) -> 2623.46 | Z73: =SUM(Z68:Z72) -> 2731.989 | AA73: =SUM(AA68:AA72) -> 2835.572 | AB73: =SUM(AB68:AB72) -> 2785.54 | AC73: =SUM(AC68:AC72) -> 2874.916 | ... AE73: =SUM(AE68:AE72) -> 3298.885 | AG73: =SUM(AE73/AA73)-1 -> 0.16339314
B74: Total liabilities and stockholders' equity | C74: =SUM(C73+C66) -> 6973.792 | D74: =SUM(D73+D66) -> 8155.615 | E74: =SUM(E73+E66) -> 9519.619 | F74: =SUM(F73+F66) -> 11154.929 | H74: =SUM(H73+H66) -> 7165.06 | I74: =SUM(I73+I66) -> 7804.751 | J74: =SUM(J73+J66) -> 7507.849 | K74: =SUM(K73+K66) -> 8155.615 | L74: =SUM(L73+L66) -> 8407.149 | M74: =SUM(M73+M66) -> 9064.984 | N74: =SUM(N73+N66) -> 9201.426 | O74: =SUM(O73+O66) -> 9519.619 | ... T74: =SUM(T73+T66) -> 11478.566 | V74: =SUM(V73+V66) -> 8155.615 | W74: =SUM(W73+W66) -> 8407.149 | X74: =SUM(X73+X66) -> 9064.984 | Y74: =SUM(Y73+Y66) -> 9201.426 | Z74: =SUM(Z73+Z66) -> 9519.619 | AA74: =SUM(AA73+AA66) -> 10139.159 | AB74: =SUM(AB73+AB66) -> 10481.077 | AC74: =SUM(AC73+AC66) -> 10436.188 | ... AE74: =SUM(AE73+AE66) -> 11478.566 | AG74: =SUM(AE74/AA74)-1 -> 0.13210238
B76: Balance Check | C76: =ROUND(C74-C56,1) -> 0 | D76: =ROUND(D74-D56,1) -> 0 | E76: =ROUND(E74-E56,1) -> 0 | F76: =ROUND(F74-F56,1) -> 0 | H76: =ROUND(H74-H56,1) -> 0 | I76: =ROUND(I74-I56,1) -> 0 | J76: =ROUND(J74-J56,1) -> 0 | K76: =ROUND(K74-K56,1) -> 0 | L76: =ROUND(L74-L56,1) -> 0 | M76: =ROUND(M74-M56,1) -> 0 | N76: =ROUND(N74-N56,1) -> 0 | O76: =ROUND(O74-O56,1) -> 0 | ... T76: =ROUND(T74-T56,1) -> 0 | V76: =ROUND(V74-V56,1) -> 0 | W76: =ROUND(W74-W56,1) -> 0 | X76: =ROUND(X74-X56,1) -> 0 | Y76: =ROUND(Y74-Y56,1) -> 0 | Z76: =ROUND(Z74-Z56,1) -> 0 | AA76: =ROUND(AA74-AA56,1) -> 0 | AB76: =ROUND(AB74-AB56,1) -> 0 | AC76: =ROUND(AC74-AC56,1) -> 0 | ... AE76: =ROUND(AE74-AE56,1) -> 0
A79: X | B79: Cash-Flows Statement | C79: FYE | N79: Quarterly | AA79: LTM | AG79: Variance
B80: =B7 -> Fiscal Period | C80: =C7 -> 2022 | D80: =D7 -> 2023 | E80: =E7 -> 2024 | F80: =F7 -> 2025 | H80: =H7 -> 1Q23 | I80: =I7 -> 2Q23 | J80: =J7 -> 3Q23 | K80: =K7 -> 4Q23 | L80: =L7 -> 1Q24 | M80: =M7 -> 2Q24 | N80: =N7 -> 3Q24 | O80: =O7 -> 4Q24 | ... T80: =T7 -> 1Q26 | V80: =V7 -> 4Q23 | W80: =W7 -> 1Q24 | X80: =X7 -> 2Q24 | Y80: =Y7 -> 3Q24 | Z80: =Z7 -> 4Q24 | AA80: =AA7 -> 1Q25 | AB80: =AB7 -> 2Q25 | AC80: =AC7 -> 3Q25 | ... AE80: =AE7 -> 1Q26
B81: =B8 -> Fiscal Period End Date | C81: =C8 -> 44713 | D81: =D8 -> 45078 | E81: =E8 -> 45444 | F81: =F8 -> 45809 | H81: =H8 -> 44805 | I81: =I8 -> 44896 | J81: =J8 -> 44986 | K81: =K8 -> 45078 | L81: =L8 -> 45170 | M81: =M8 -> 45261 | N81: =N8 -> 45352 | O81: =O8 -> 45444 | ... T81: =T8 -> 45901 | V81: =V8 -> 45078 | W81: =W8 -> 45170 | X81: =X8 -> 45261 | Y81: =Y8 -> 45352 | Z81: =Z8 -> 45444 | AA81: =AA8 -> 45536 | AB81: =AB8 -> 45627 | AC81: =AC8 -> 45717 | ... AE81: =AE8 -> 45901
B83: Cash-Flows From Operating Activities
B84: Net income (loss) | C84: -707.417 | D84: =D32 -> -985.345 | E84: =E32 -> -517.757 | F84: =F32 -> 52.184 | H84: =H32 -> -251.269 | I84: =I32 -> -322.437 | J84: =J32 -> -205.677 | K84: =K32 -> -205.962 | L84: =L32 -> -171.783 | M84: =M32 -> -166.902 | N84: =N32 -> -133.936 | O84: =O32 -> -45.136 | ... T84: =T32 -> 80.693 | V84: =V32 -> -985.345 | W84: =W32 -> -905.859 | X84: =X32 -> -750.324 | Y84: =Y32 -> -678.583 | Z84: =Z32 -> -517.757 | AA84: =AA32 -> -446.196 | AB84: =AB32 -> -198.934 | AC84: =AC32 -> -62.195 | ... AE84: =AE32 -> 233.099 | AG84: =SUM(AE84/AA84)-1 -> -1.5224139
B86: Adjustments to reconcile net income:
B87: Provision for losses | C87: 255.272 | D87: 331.86 | E87: 460.628 | F87: 616.683 | H87: 64.25 | I87: 106.689 | J87: 66.438 | K87: =SUM(D87-SUM(H87:J87)) -> 94.483 | L87: 99.696 | M87: 120.88 | N87: 122.443 | O87: =SUM(E87-SUM(L87:N87)) -> 117.609 | P87: 159.824 | Q87: 152.98 | R87: 147.252 | S87: =SUM(F87-SUM(P87:R87)) -> 156.627 | T87: 162.752 | V87: =SUM(H87:K87) -> 331.86 | W87: =SUM(I87:L87) -> 367.306 | X87: =SUM(J87:M87) -> 381.497 | Y87: =SUM(K87:N87) -> 437.502 | Z87: =SUM(L87:O87) -> 460.628 | AA87: =SUM(M87:P87) -> 520.756 | AB87: =SUM(N87:Q87) -> 552.856 | AC87: =SUM(O87:R87) -> 577.665 | ... AE87: =SUM(Q87:T87) -> 619.611 | AG87: =SUM(AE87/AA87)-1 -> 0.18982979
B88: Amortization of premiums and discounts on loans | C88: -171.965 | D88: -141.075 | E88: -187.709 | F88: -233.8 | H88: -34.595 | I88: -34.258 | J88: -34.615 | K88: =SUM(D88-SUM(H88:J88)) -> -37.607 | L88: -41.138 | M88: -46.841 | N88: -49.704 | O88: =SUM(E88-SUM(L88:N88)) -> -50.026 | P88: -52.064 | Q88: -59.233 | R88: -60.531 | S88: =SUM(F88-SUM(P88:R88)) -> -61.972 | T88: -65.072 | V88: =SUM(H88:K88) -> -141.075 | W88: =SUM(I88:L88) -> -147.618 | X88: =SUM(J88:M88) -> -160.201 | Y88: =SUM(K88:N88) -> -175.29 | Z88: =SUM(L88:O88) -> -187.709 | AA88: =SUM(M88:P88) -> -198.635 | AB88: =SUM(N88:Q88) -> -211.027 | AC88: =SUM(O88:R88) -> -221.854 | ... AE88: =SUM(Q88:T88) -> -246.808 | AG88: =SUM(AE88/AA88)-1 -> 0.2425202
B89: (Gain) loss on sales of loans | C89: -196.435 | D89: -188.341 | E89: -197.153 | F89: -381.621 | H89: -63.595 | I89: -59.607 | J89: -32.813 | K89: =SUM(D89-SUM(H89:J89)) -> -32.326 | L89: -34.285 | M89: -52.702 | N89: -40.183 | O89: =SUM(E89-SUM(L89:N89)) -> -69.983 | P89: -63.613 | Q89: -125.287 | R89: -75.838 | S89: =SUM(F89-SUM(P89:R89)) -> -116.883 | T89: -119.049 | V89: =SUM(H89:K89) -> -188.341 | W89: =SUM(I89:L89) -> -159.031 | X89: =SUM(J89:M89) -> -152.126 | Y89: =SUM(K89:N89) -> -159.496 | Z89: =SUM(L89:O89) -> -197.153 | AA89: =SUM(M89:P89) -> -226.481 | AB89: =SUM(N89:Q89) -> -299.066 | AC89: =SUM(O89:R89) -> -334.721 | ... AE89: =SUM(Q89:T89) -> -437.057
B90: Changes in fair value of assets and liabilities | C90: -101.789 | D90: -15.883 | E90: -2.776 | F90: 7.146 | H90: 3.906 | I90: -14.941 | J90: 1.018 | K90: =SUM(D90-SUM(H90:J90)) -> -5.866 | L90: -4.11 | M90: -0.802 | N90: 1.267 | O90: =SUM(E90-SUM(L90:N90)) -> 0.869 | P90: 1.668 | Q90: 2.954 | R90: 0.834 | S90: =SUM(F90-SUM(P90:R90)) -> 1.69 | T90: -1.495 | V90: =SUM(H90:K90) -> -15.883 | W90: =SUM(I90:L90) -> -23.899 | X90: =SUM(J90:M90) -> -9.76 | Y90: =SUM(K90:N90) -> -9.511 | Z90: =SUM(L90:O90) -> -2.776 | AA90: =SUM(M90:P90) -> 3.002 | AB90: =SUM(N90:Q90) -> 6.758 | AC90: =SUM(O90:R90) -> 6.325 | ... AE90: =SUM(Q90:T90) -> 3.983
B91: Changes in fair value of servicing assets and liabilities | C91: 0 | D91: 0 | E91: 0 | F91: 0 | H91: 0 | I91: 0 | J91: 0 | K91: =SUM(D91-SUM(H91:J91)) -> 0 | L91: 0 | M91: 0 | N91: 0 | O91: =SUM(E91-SUM(L91:N91)) -> 0 | P91: 0 | Q91: 0 | R91: 0 | S91: =SUM(F91-SUM(P91:R91)) -> 0 | T91: -0.11 | V91: =SUM(H91:K91) -> 0 | W91: =SUM(I91:L91) -> 0 | X91: =SUM(J91:M91) -> 0 | Y91: =SUM(K91:N91) -> 0 | Z91: =SUM(L91:O91) -> 0 | AA91: =SUM(M91:P91) -> 0 | AB91: =SUM(N91:Q91) -> 0 | AC91: =SUM(O91:R91) -> 0 | ... AE91: =SUM(Q91:T91) -> -0.11
B92: Changes in fair value of residual trust certificates | E92: 0 | K92: =SUM(D92-SUM(H92:J92)) -> 0 | O92: =SUM(E92-SUM(L92:N92)) -> 0 | S92: =SUM(F92-SUM(P92:R92)) -> 0 | V92: =SUM(H92:K92) -> 0 | W92: =SUM(I92:L92) -> 0 | X92: =SUM(J92:M92) -> 0 | Y92: =SUM(K92:N92) -> 0 | Z92: =SUM(L92:O92) -> 0 | AA92: =SUM(M92:P92) -> 0 | AB92: =SUM(N92:Q92) -> 0 | AC92: =SUM(O92:R92) -> 0 | ... AE92: =SUM(Q92:T92) -> 0
B93: Amortization of commercial agreement | C93: 96.737 | D93: 85.524 | E93: 73.07 | F93: 47.392 | H93: 21.557 | I93: 21.557 | J93: 21.088 | K93: =SUM(D93-SUM(H93:J93)) -> 21.322 | L93: 21.557 | M93: 21.557 | N93: 15.855 | O93: =SUM(E93-SUM(L93:N93)) -> 14.101 | P93: 14.256 | Q93: 14.255 | R93: 10.913 | S93: =SUM(F93-SUM(P93:R93)) -> 7.968 | T93: 8.056 | V93: =SUM(H93:K93) -> 85.524 | W93: =SUM(I93:L93) -> 85.524 | X93: =SUM(J93:M93) -> 85.524 | Y93: =SUM(K93:N93) -> 80.291 | Z93: =SUM(L93:O93) -> 73.07 | AA93: =SUM(M93:P93) -> 65.769 | AB93: =SUM(N93:Q93) -> 58.467 | AC93: =SUM(O93:R93) -> 53.525 | ... AE93: =SUM(Q93:T93) -> 41.192
B94: Amortization of debt issuance costs | C94: 17.332 | D94: 20.535 | E94: 24.546 | F94: 30.389 | H94: 1.076 | I94: 0.676 | J94: 11.446 | K94: =SUM(D94-SUM(H94:J94)) -> 7.337 | L94: -6.586 | M94: 7.224 | N94: 6.13 | O94: =SUM(E94-SUM(L94:N94)) -> 17.778 | P94: 6.083 | Q94: 6.907 | R94: 10.308 | S94: =SUM(F94-SUM(P94:R94)) -> 7.091 | T94: 6.828 | V94: =SUM(H94:K94) -> 20.535 | W94: =SUM(I94:L94) -> 12.873 | X94: =SUM(J94:M94) -> 19.421 | Y94: =SUM(K94:N94) -> 14.105 | Z94: =SUM(L94:O94) -> 24.546 | AA94: =SUM(M94:P94) -> 37.215 | AB94: =SUM(N94:Q94) -> 36.898 | AC94: =SUM(O94:R94) -> 41.076 | ... AE94: =SUM(Q94:T94) -> 31.134
B95: Amortization of discount on securities available for sale | E95: -22.799
B96: Stock-based compensation | C96: 390.983 | D96: 451.709 | E96: 344.511 | F96: 321.433 | H96: 119.808 | I96: 121.775 | J96: 106.789 | K96: =SUM(D96-SUM(H96:J96)) -> 103.337 | L96: 112.359 | M96: 90.164 | N96: 77.075 | O96: =SUM(E96-SUM(L96:N96)) -> 64.913 | P96: 94.233 | Q96: 86.098 | R96: 75.607 | S96: =SUM(F96-SUM(P96:R96)) -> 65.495 | T96: 85.853 | V96: =SUM(H96:K96) -> 451.709 | W96: =SUM(I96:L96) -> 444.26 | X96: =SUM(J96:M96) -> 412.649 | Y96: =SUM(K96:N96) -> 382.935 | Z96: =SUM(L96:O96) -> 344.511 | AA96: =SUM(M96:P96) -> 326.385 | AB96: =SUM(N96:Q96) -> 322.319 | AC96: =SUM(O96:R96) -> 320.851 | ... AE96: =SUM(Q96:T96) -> 313.053
B97: Commercial agreement warrant expense | C97: 254.679 | D97: 421.934 | E97: 406.714 | F97: 271.562 | H97: 108.743 | I97: 128.053 | J97: 93.922 | K97: =SUM(D97-SUM(H97:J97)) -> 91.216 | L97: 95.91 | M97: 114.705 | N97: 95.973 | O97: =SUM(E97-SUM(L97:N97)) -> 100.126 | P97: 107.263 | Q97: 86.776 | R97: 36.063 | S97: =SUM(F97-SUM(P97:R97)) -> 41.46 | T97: 40.977 | V97: =SUM(H97:K97) -> 421.934 | W97: =SUM(I97:L97) -> 409.101 | X97: =SUM(J97:M97) -> 395.753 | Y97: =SUM(K97:N97) -> 397.804 | Z97: =SUM(L97:O97) -> 406.714 | AA97: =SUM(M97:P97) -> 418.067 | AB97: =SUM(N97:Q97) -> 390.138 | AC97: =SUM(O97:R97) -> 330.228 | ... AE97: =SUM(Q97:T97) -> 205.276 | AG97: =SUM(AE97/AA97)-1 -> -0.50898779
B98: Depreciation and amortization | C98: 52.722 | D98: 134.634 | E98: 169.044 | F98: 225.076 | H98: 20.882 | I98: 23.004 | J98: 47.469 | K98: =SUM(D98-SUM(H98:J98)) -> 43.279 | L98: 40.131 | M98: 26.512 | N98: 37.012 | O98: =SUM(E98-SUM(L98:N98)) -> 65.389 | P98: 46.72 | Q98: 54.894 | R98: 59.467 | S98: =SUM(F98-SUM(P98:R98)) -> 63.995 | T98: 65.329 | V98: =SUM(H98:K98) -> 134.634 | W98: =SUM(I98:L98) -> 153.883 | X98: =SUM(J98:M98) -> 157.391 | Y98: =SUM(K98:N98) -> 146.934 | Z98: =SUM(L98:O98) -> 169.044 | AA98: =SUM(M98:P98) -> 175.633 | AB98: =SUM(N98:Q98) -> 204.015 | AC98: =SUM(O98:R98) -> 226.47 | ... AE98: =SUM(Q98:T98) -> 243.685 | AG98: =SUM(AE98/AA98)-1 -> 0.38746705
B99: Impairment of right of use assets | E99: 0.752
B100: Deferred tax (benefit) expense | C100: 0 | D100: 0 | E100: 0 | F100: 0 | H100: 0 | I100: 0 | J100: 0 | K100: =SUM(D100-SUM(H100:J100)) -> 0 | L100: 0.752 | M100: 0 | N100: 0 | O100: =SUM(E100-SUM(L100:N100)) -> -0.752 | P100: 0 | Q100: 0 | R100: 0 | S100: =SUM(F100-SUM(P100:R100)) -> 0 | T100: 0 | V100: =SUM(H100:K100) -> 0 | W100: =SUM(I100:L100) -> 0.752 | X100: =SUM(J100:M100) -> 0.752 | Y100: =SUM(K100:N100) -> 0.752 | Z100: =SUM(L100:O100) -> 0 | AA100: =SUM(M100:P100) -> -0.752 | AB100: =SUM(N100:Q100) -> -0.752 | AC100: =SUM(O100:R100) -> -0.752 | ... AE100: =SUM(Q100:T100) -> 0 | AG100: =SUM(AE100/AA100)-1 -> -1
B101: Other | C101: -23.634 | D101: -133.482 | E101: -25.331 | F101: -112.746 | H101: -5.567 | I101: -8.22 | J101: -99.471 | K101: =SUM(D101-SUM(H101:J101)) -> -20.224 | L101: -4.73 | M101: 8.636 | N101: -8.003 | O101: =SUM(E101-SUM(L101:N101)) -> -21.234 | P101: -37.63 | Q101: -73.557 | R101: 4.567 | S101: =SUM(F101-SUM(P101:R101)) -> -6.126 | T101: -14.889 | V101: =SUM(H101:K101) -> -133.482 | W101: =SUM(I101:L101) -> -132.645 | X101: =SUM(J101:M101) -> -115.789 | Y101: =SUM(K101:N101) -> -24.321 | Z101: =SUM(L101:O101) -> -25.331 | AA101: =SUM(M101:P101) -> -58.231 | AB101: =SUM(N101:Q101) -> -140.424 | AC101: =SUM(O101:R101) -> -127.854 | ... AE101: =SUM(Q101:T101) -> -90.005 | AG101: =SUM(AE101/AA101)-1 -> 0.54565438
B102: Purchases of loans held for sale and proceeds from sale, net | C102: 29.373 | D102: 165.086 | E102: =(-4212299+4211687)/1000 -> -0.612 | F102: 0.037 | H102: 52.625 | I102: 52.298 | J102: 13.538 | K102: =SUM(D102-SUM(H102:J102)) -> 46.625 | M102: 11.403 | N102: 9.391 | O102: =SUM(E102-SUM(L102:N102)) -> -21.406 | P102: 0.039 | Q102: -0.017 | R102: 0.039 | S102: =SUM(F102-SUM(P102:R102)) -> -0.024 | T102: -0.441 | V102: =SUM(H102:K102) -> 165.086 | W102: =SUM(I102:L102) -> 112.461 | X102: =SUM(J102:M102) -> 71.566 | Y102: =SUM(K102:N102) -> 67.419 | Z102: =SUM(L102:O102) -> -0.612 | AA102: =SUM(M102:P102) -> -0.573 | AB102: =SUM(N102:Q102) -> -11.993 | AC102: =SUM(O102:R102) -> -21.345 | ... AE102: =SUM(Q102:T102) -> -0.443 | AG102: =SUM(AE102/AA102)-1 -> -0.22687609
B104: Changes in assets and liabilities:
B105: Accounts receivables, net | C105: -62.7 | D105: -67.69 | E105: -167.757 | F105: -84.952 | H105: -6.649 | I105: -56.767 | J105: 61.632 | K105: =SUM(D105-SUM(H105:J105)) -> -65.906 | L105: -1222.224 | M105: -74.279 | N105: 10.721 | O105: =SUM(E105-SUM(L105:N105)) -> 1118.025 | P105: 41.117 | Q105: 102.664 | R105: -19.884 | S105: =SUM(F105-SUM(P105:R105)) -> -208.849 | T105: 138.862 | V105: =SUM(H105:K105) -> -67.69 | W105: =SUM(I105:L105) -> -1283.265 | X105: =SUM(J105:M105) -> -1300.777 | Y105: =SUM(K105:N105) -> -1351.688 | Z105: =SUM(L105:O105) -> -167.757 | AA105: =SUM(M105:P105) -> 1095.584 | AB105: =SUM(N105:Q105) -> 1272.527 | AC105: =SUM(O105:R105) -> 1241.922 | ... AE105: =SUM(Q105:T105) -> 12.793 | AG105: =SUM(AE105/AA105)-1 -> -0.98832312
B106: Other assets | C106: -15.02 | D106: -14.466 | E106: 31.228 | F106: -12.175 | H106: -3 | I106: -10.727 | J106: 10.435 | K106: =SUM(D106-SUM(H106:J106)) -> -11.174 | L106: 1228.11 | M106: -29.103 | N106: 99.85 | O106: =SUM(E106-SUM(L106:N106)) -> -1267.629 | P106: -6.833 | Q106: -20.588 | R106: 9.429 | S106: =SUM(F106-SUM(P106:R106)) -> 5.817 | T106: 30.955 | V106: =SUM(H106:K106) -> -14.466 | W106: =SUM(I106:L106) -> 1216.644 | X106: =SUM(J106:M106) -> 1198.268 | Y106: =SUM(K106:N106) -> 1287.683 | Z106: =SUM(L106:O106) -> 31.228 | AA106: =SUM(M106:P106) -> -1203.715 | AB106: =SUM(N106:Q106) -> -1195.2 | AC106: =SUM(O106:R106) -> -1285.621 | ... AE106: =SUM(Q106:T106) -> 25.613 | AG106: =SUM(AE106/AA106)-1 -> -1.0212783
B107: Accrued interest payable | C107: 3.907 | D107: 7.915 | E107: -55.169 | F107: 2.386 | H107: -1.078 | I107: 6.981 | J107: 2.125 | K107: =SUM(D107-SUM(H107:J107)) -> -0.113 | L107: -42.208 | M107: 2.699 | N107: 0.65 | O107: =SUM(E107-SUM(L107:N107)) -> -16.31 | P107: 0.846 | Q107: 1.048 | R107: -2.277 | S107: =SUM(F107-SUM(P107:R107)) -> 2.769 | T107: 1.621 | V107: =SUM(H107:K107) -> 7.915 | W107: =SUM(I107:L107) -> -33.215 | X107: =SUM(J107:M107) -> -37.497 | Y107: =SUM(K107:N107) -> -38.972 | Z107: =SUM(L107:O107) -> -55.169 | AA107: =SUM(M107:P107) -> -12.115 | AB107: =SUM(N107:Q107) -> -13.766 | AC107: =SUM(O107:R107) -> -16.693 | ... AE107: =SUM(Q107:T107) -> 3.161
B108: Accounts payable | C108: -24.686 | D108: -5.038 | E108: 12.417 | F108: 41.801 | H108: 1.462 | I108: -5.56 | J108: 0.48 | K108: =SUM(D108-SUM(H108:J108)) -> -1.42 | L108: -1.257 | M108: 32.46 | N108: -24.581 | O108: =SUM(E108-SUM(L108:N108)) -> 5.795 | P108: 16.543 | Q108: -6.936 | R108: -9.568 | S108: =SUM(F108-SUM(P108:R108)) -> 41.762 | T108: -24.801 | V108: =SUM(H108:K108) -> -5.038 | W108: =SUM(I108:L108) -> -7.757 | X108: =SUM(J108:M108) -> 30.263 | Y108: =SUM(K108:N108) -> 5.202 | Z108: =SUM(L108:O108) -> 12.417 | AA108: =SUM(M108:P108) -> 30.217 | AB108: =SUM(N108:Q108) -> -9.179 | AC108: =SUM(O108:R108) -> 5.834 | ... AE108: =SUM(Q108:T108) -> 0.457
B109: Accrued expenses and other liabilities | C109: 67.537 | D109: -37.665 | E109: 11.138 | F109: -48.943 | H109: 3.231 | I109: -13.631 | J109: -34.388 | K109: =SUM(D109-SUM(H109:J109)) -> 7.123 | L109: -26.938 | M109: -16.359 | N109: -6.971 | O109: =SUM(E109-SUM(L109:N109)) -> 61.406 | P109: -23.755 | Q109: 3.489 | R109: 1.453 | S109: =SUM(F109-SUM(P109:R109)) -> -30.13 | T109: -3.586 | V109: =SUM(H109:K109) -> -37.665 | W109: =SUM(I109:L109) -> -67.834 | X109: =SUM(J109:M109) -> -70.562 | Y109: =SUM(K109:N109) -> -43.145 | Z109: =SUM(L109:O109) -> 11.138 | AA109: =SUM(M109:P109) -> 14.321 | AB109: =SUM(N109:Q109) -> 34.169 | AC109: =SUM(O109:R109) -> 42.593 | ... AE109: =SUM(Q109:T109) -> -28.774
B110: Payable to third-party loan owners | C110: 21.304 | D110: -17.531 | E110: 105.791 | F110: 52.056 | H110: 19.428 | I110: 36.567 | J110: -83.191 | K110: =SUM(D110-SUM(H110:J110)) -> 9.665 | L110: 55.646 | M110: 25.069 | N110: -4.837 | O110: =SUM(E110-SUM(L110:N110)) -> 29.913 | P110: -7.608 | Q110: 5.21 | R110: 19.751 | S110: =SUM(F110-SUM(P110:R110)) -> 34.703 | T110: -17.91 | V110: =SUM(H110:K110) -> -17.531 | W110: =SUM(I110:L110) -> 18.687 | X110: =SUM(J110:M110) -> 7.189 | Y110: =SUM(K110:N110) -> 85.543 | Z110: =SUM(L110:O110) -> 105.791 | AA110: =SUM(M110:P110) -> 42.537 | AB110: =SUM(N110:Q110) -> 22.678 | AC110: =SUM(O110:R110) -> 47.266 | ... AE110: =SUM(Q110:T110) -> 41.754 | AG110: =SUM(AE110/AA110)-1 -> -0.018407504
B111: Net cash used in operating activities | C111: =SUM(C84:C110) -> -113.8 | D111: =SUM(D84:D110) -> 12.681 | E111: =SUM(E84:E110) -> 462.776 | F111: =SUM(F84:F110) -> 793.908 | H111: =SUM(H84:H110) -> 51.215 | I111: =SUM(I84:I110) -> -28.548 | J111: =SUM(J84:J110) -> -53.775 | K111: =SUM(K84:K110) -> 43.789 | L111: =SUM(L84:L110) -> 98.902 | M111: =SUM(M84:M110) -> 74.321 | N111: =SUM(N84:N110) -> 208.152 | O111: =SUM(O84:O110) -> 103.448 | ... T111: =SUM(T84:T110) -> 374.573 | V111: =SUM(V84:V110) -> 12.681 | W111: =SUM(W84:W110) -> 60.368 | X111: =SUM(X84:X110) -> 163.237 | Y111: =SUM(Y84:Y110) -> 425.164 | Z111: =SUM(Z84:Z110) -> 484.823 | AA111: =SUM(AA84:AA110) -> 582.788 | AB111: =SUM(AB84:AB110) -> 820.484 | AC111: =SUM(AC84:AC110) -> 822.72 | ... AE111: =SUM(AE84:AE110) -> 971.614 | AG111: =SUM(AE111/AA111)-1 -> 0.66718258
B113: Cash flows from investing activities:
B114: Purchases of loans net of proceeds from sale and principal repayments | C114: -9581.772 | D114: -13586.251 | E114: -21488.547 | F114: -32545.595 | H114: -2744.825 | I114: -3790.632 | J114: -3086.832 | K114: =SUM(D114-SUM(H114:J114)) -> -3963.962 | L114: -4229.667 | M114: -6103.822 | N114: -5223.719 | O114: =SUM(E114-SUM(L114:N114)) -> -5931.339 | P114: -6388.35 | Q114: -8663.556 | R114: -7676.063 | S114: =SUM(F114-SUM(P114:R114)) -> -9817.626 | T114: -9797.362 | V114: =SUM(H114:K114) -> -13586.251 | W114: =SUM(I114:L114) -> -15071.093 | X114: =SUM(J114:M114) -> -17384.283 | Y114: =SUM(K114:N114) -> -19521.17 | Z114: =SUM(L114:O114) -> -21488.547 | AA114: =SUM(M114:P114) -> -23647.23 | AB114: =SUM(N114:Q114) -> -26206.964 | AC114: =SUM(O114:R114) -> -28659.308 | ... AE114: =SUM(Q114:T114) -> -35954.607 | AG114: =SUM(AE114/AA114)-1 -> 0.52045745
B115: Origination of loans, proceeds from sale of loans, net | C115: 1118.331 | D115: 1582.501 | E115: 6058.799 | F115: 12572.254 | H115: 326.713 | I115: 376.274 | J115: 390.907 | K115: =SUM(D115-SUM(H115:J115)) -> 488.607 | L115: 899.238 | M115: 2077.703 | N115: 1203.078 | O115: =SUM(E115-SUM(L115:N115)) -> 1878.78 | P115: 1630.671 | Q115: 3633.664 | R115: 2858.471 | S115: =SUM(F115-SUM(P115:R115)) -> 4449.448 | T115: 4282.839 | V115: =SUM(H115:K115) -> 1582.501 | W115: =SUM(I115:L115) -> 2155.026 | X115: =SUM(J115:M115) -> 3856.455 | Y115: =SUM(K115:N115) -> 4668.626 | Z115: =SUM(L115:O115) -> 6058.799 | AA115: =SUM(M115:P115) -> 6790.232 | AB115: =SUM(N115:Q115) -> 8346.193 | AC115: =SUM(O115:R115) -> 10001.586 | ... AE115: =SUM(Q115:T115) -> 15224.422 | AG115: =SUM(AE115/AA115)-1 -> 1.2421063
B116: Additions to property, equipment and software | C116: -86.29 | D116: -120.775 | E116: -159.296 | F116: -192.189 | H116: -31.151 | I116: -34.25 | J116: -30.516 | K116: =SUM(D116-SUM(H116:J116)) -> -24.858 | L116: -35.817 | M116: -38.747 | N116: -46.476 | O116: =SUM(E116-SUM(L116:N116)) -> -38.256 | P116: -44.152 | Q116: -43.905 | R116: -53.012 | S116: =SUM(F116-SUM(P116:R116)) -> -51.12 | T116: -54.365 | V116: =SUM(H116:K116) -> -120.775 | W116: =SUM(I116:L116) -> -125.441 | X116: =SUM(J116:M116) -> -129.938 | Y116: =SUM(K116:N116) -> -145.898 | Z116: =SUM(L116:O116) -> -159.296 | AA116: =SUM(M116:P116) -> -167.631 | AB116: =SUM(N116:Q116) -> -172.789 | AC116: =SUM(O116:R116) -> -179.325 | ... AE116: =SUM(Q116:T116) -> -202.402
B117: Principal repayment of loans | C117: 8121.583 | D117: 10028.452 | E117: 14147.034 | F117: 18655.657 | H117: 2206.725 | I117: 2422.1 | J117: 2570.743 | K117: =SUM(D117-SUM(H117:J117)) -> 2828.884 | L117: 3184.851 | M117: 3351.462 | N117: 3777.977 | O117: =SUM(E117-SUM(L117:N117)) -> 3832.744 | P117: 4132.682 | Q117: 4528.811 | R117: 4988.174 | S117: =SUM(F117-SUM(P117:R117)) -> 5005.99 | T117: 5359.253 | V117: =SUM(H117:K117) -> 10028.452 | W117: =SUM(I117:L117) -> 11006.578 | X117: =SUM(J117:M117) -> 11935.94 | Y117: =SUM(K117:N117) -> 13143.174 | Z117: =SUM(L117:O117) -> 14147.034 | AA117: =SUM(M117:P117) -> 15094.865 | AB117: =SUM(N117:Q117) -> 16272.214 | AC117: =SUM(O117:R117) -> 17482.411 | ... AE117: =SUM(Q117:T117) -> 19882.228
B118: Purchases of intangible assets | C118: -283.738 | D118: 0 | E118: -193.322 | F118: 0 | H118: 0 | I118: 0 | J118: 0 | K118: =SUM(D118-SUM(H118:J118)) -> 0 | L118: -96.813 | M118: -96.509 | N118: 0 | O118: =SUM(E118-SUM(L118:N118)) -> 0 | P118: 0 | Q118: 0 | R118: 0 | S118: =SUM(F118-SUM(P118:R118)) -> 0 | T118: 0 | V118: =SUM(H118:K118) -> 0 | W118: =SUM(I118:L118) -> -96.813 | X118: =SUM(J118:M118) -> -193.322 | Y118: =SUM(K118:N118) -> -193.322 | Z118: =SUM(L118:O118) -> -193.322 | AA118: =SUM(M118:P118) -> -96.509 | AB118: =SUM(N118:Q118) -> 0 | AC118: =SUM(O118:R118) -> 0 | ... AE118: =SUM(Q118:T118) -> 0
B119: Payments to acquire businesses, net of cash acquired | C119: -5.999 | D119: 0 | E119: 0 | F119: 0 | H119: 0 | I119: 0 | J119: 0 | K119: =SUM(D119-SUM(H119:J119)) -> 0 | L119: 262.293 | M119: 219.736 | N119: 0 | O119: =SUM(E119-SUM(L119:N119)) -> -482.029 | P119: 0 | Q119: 0 | R119: 0 | S119: =SUM(F119-SUM(P119:R119)) -> 0 | T119: 0 | V119: =SUM(H119:K119) -> 0 | W119: =SUM(I119:L119) -> 262.293 | X119: =SUM(J119:M119) -> 482.029 | Y119: =SUM(K119:N119) -> 482.029 | Z119: =SUM(L119:O119) -> 0 | AA119: =SUM(M119:P119) -> -262.293 | AB119: =SUM(N119:Q119) -> -482.029 | AC119: =SUM(O119:R119) -> -482.029 | ... AE119: =SUM(Q119:T119) -> 0
B120: Acquisition funds in transit / Other | C120: -1313.087 | D120: 443.003 | E120: -171.846 | F120: 426.808 | H120: 359.811 | I120: 334.297 | J120: -145.26 | K120: =SUM(D120-SUM(H120:J120)) -> -105.845 | L120: 0.056 | M120: -34.725 | N120: 142.385 | O120: =SUM(E120-SUM(L120:N120)) -> -279.562 | P120: 94.15 | Q120: 455.918 | R120: -82.052 | S120: =SUM(F120-SUM(P120:R120)) -> -41.208 | T120: 70.024 | V120: =SUM(H120:K120) -> 443.003 | W120: =SUM(I120:L120) -> 83.248 | X120: =SUM(J120:M120) -> -285.774 | Y120: =SUM(K120:N120) -> 1.871 | Z120: =SUM(L120:O120) -> -171.846 | AA120: =SUM(M120:P120) -> -77.752 | AB120: =SUM(N120:Q120) -> 412.891 | AC120: =SUM(O120:R120) -> 188.454 | ... AE120: =SUM(Q120:T120) -> 402.682
B121: Net cash used in investing activities | C121: =SUM(C114:C120) -> -2030.972 | D121: =SUM(D114:D120) -> -1653.07 | E121: =SUM(E114:E120) -> -1807.178 | F121: =SUM(F114:F120) -> -1083.065 | H121: =SUM(H114:H120) -> 117.273 | I121: =SUM(I114:I120) -> -692.211 | J121: =SUM(J114:J120) -> -300.958 | K121: =SUM(K114:K120) -> -777.174 | L121: =SUM(L114:L120) -> -15.859 | M121: =SUM(M114:M120) -> -624.902 | N121: =SUM(N114:N120) -> -146.755 | O121: =SUM(O114:O120) -> -1019.662 | ... T121: =SUM(T114:T120) -> -139.611 | V121: =SUM(V114:V120) -> -1653.07 | W121: =SUM(W114:W120) -> -1786.202 | X121: =SUM(X114:X120) -> -1718.893 | Y121: =SUM(Y114:Y120) -> -1564.69 | Z121: =SUM(Z114:Z120) -> -1807.178 | AA121: =SUM(AA114:AA120) -> -2366.318 | AB121: =SUM(AB114:AB120) -> -1830.484 | AC121: =SUM(AC114:AC120) -> -1648.211 | ... AE121: =SUM(AE114:AE120) -> -647.677 | AG121: =SUM(AE121/AA121)-1 -> -0.72629334
...

Sheet Revenue Drivers
B2: ='Historical Financials'!B2 -> Affirm Holdings Inc (NASDAQ: AFRM) | C2: FYE | N2: Quarterly | AA2: LTM
B3: Segment Anaysis | C3: ='Historical Financials'!C7 -> 2022 | D3: ='Historical Financials'!D7 -> 2023 | E3: ='Historical Financials'!E7 -> 2024 | F3: ='Historical Financials'!F7 -> 2025 | H3: ='Historical Financials'!H7 -> 1Q23 | I3: ='Historical Financials'!I7 -> 2Q23 | J3: ='Historical Financials'!J7 -> 3Q23 | K3: ='Historical Financials'!K7 -> 4Q23 | L3: ='Historical Financials'!L7 -> 1Q24 | M3: ='Historical Financials'!M7 -> 2Q24 | N3: ='Historical Financials'!N7 -> 3Q24 | O3: ='Historical Financials'!O7 -> 4Q24 | ... T3: ='Historical Financials'!T7 -> 1Q26 | V3: =K3 -> 4Q23 | W3: =L3 -> 1Q24 | X3: =M3 -> 2Q24 | Y3: =N3 -> 3Q24 | Z3: =O3 -> 4Q24 | AA3: =P3 -> 1Q25 | AB3: =Q3 -> 2Q25 | AC3: =R3 -> 3Q25 | ... AE3: =T3 -> 1Q26
B4: ($ In Millions) | C4: ='Historical Financials'!C8 -> 44713 | D4: ='Historical Financials'!D8 -> 45078 | E4: ='Historical Financials'!E8 -> 45444 | F4: ='Historical Financials'!F8 -> 45809 | H4: ='Historical Financials'!H8 -> 44805 | I4: ='Historical Financials'!I8 -> 44896 | J4: ='Historical Financials'!J8 -> 44986 | K4: ='Historical Financials'!K8 -> 45078 | L4: ='Historical Financials'!L8 -> 45170 | M4: ='Historical Financials'!M8 -> 45261 | N4: ='Historical Financials'!N8 -> 45352 | O4: ='Historical Financials'!O8 -> 45444 | ... T4: ='Historical Financials'!T8 -> 45901 | V4: =K4 -> 45078 | W4: =L4 -> 45170 | X4: =M4 -> 45261 | Y4: =N4 -> 45352 | Z4: =O4 -> 45444 | AA4: =P4 -> 45536 | AB4: =Q4 -> 45627 | AC4: =R4 -> 45717 | ... AE4: =T4 -> 45901
A6: X | B6: Revenue by reportable segment
A8: X | B8: Revenue Segment Anaysis
B9: Network revenue | C9: 559.207 | D9: 626.938 | E9: 826.008 | F9: 1113.966 | H9: 139.857 | I9: 163.136 | J9: 148.482 | K9: =SUM(D9-SUM(H9:J9)) -> 175.463 | L9: 179.426 | M9: 227.626 | N9: 194.968 | O9: =SUM(E9-SUM(L9:N9)) -> 223.988 | P9: 231.819 | Q9: 303.037 | R9: 272.545 | S9: =SUM(F9-SUM(P9:R9)) -> 306.565 | T9: 320.477 | V9: =SUM(H9:K9) -> 626.938 | W9: =SUM(I9:L9) -> 666.507 | X9: =SUM(J9:M9) -> 730.997 | Y9: =SUM(K9:N9) -> 777.483 | Z9: =SUM(L9:O9) -> 826.008 | AA9: =SUM(M9:P9) -> 878.401 | AB9: =SUM(N9:Q9) -> 953.812 | AC9: =SUM(O9:R9) -> 1031.389 | ... AE9: =SUM(Q9:T9) -> 1202.624
B10: Interest Income | C10: 527.88 | D10: 685.217 | E10: 1204.355 | F10: 1608.221 | H10: 136.802 | I10: 155.321 | J10: 178.27 | K10: =SUM(D10-SUM(H10:J10)) -> 214.824 | L10: 262.679 | M10: 288.346 | N10: 315.712 | O10: =SUM(E10-SUM(L10:N10)) -> 337.618 | P10: 377.064 | Q10: 409.367 | R10: 402.701 | S10: =SUM(F10-SUM(P10:R10)) -> 419.089 | T10: 454.122 | V10: =SUM(H10:K10) -> 685.217 | W10: =SUM(I10:L10) -> 811.094 | X10: =SUM(J10:M10) -> 944.119 | Y10: =SUM(K10:N10) -> 1081.561 | Z10: =SUM(L10:O10) -> 1204.355 | AA10: =SUM(M10:P10) -> 1318.74 | AB10: =SUM(N10:Q10) -> 1439.761 | AC10: =SUM(O10:R10) -> 1526.75 | ... AE10: =SUM(Q10:T10) -> 1685.279
B11: Gain (loss) on sales of loans | C11: 196.435 | D11: 188.341 | E11: 197.153 | F11: 381.622 | H11: 63.595 | I11: 59.607 | J11: 32.813 | K11: =SUM(D11-SUM(H11:J11)) -> 32.326 | L11: 34.285 | M11: 52.702 | N11: 40.183 | O11: =SUM(E11-SUM(L11:N11)) -> 69.983 | P11: 63.613 | Q11: 125.287 | R11: 75.838 | S11: =SUM(F11-SUM(P11:R11)) -> 116.884 | T11: 119.049 | V11: =SUM(H11:K11) -> 188.341 | W11: =SUM(I11:L11) -> 159.031 | X11: =SUM(J11:M11) -> 152.126 | Y11: =SUM(K11:N11) -> 159.496 | Z11: =SUM(L11:O11) -> 197.153 | AA11: =SUM(M11:P11) -> 226.481 | AB11: =SUM(N11:Q11) -> 299.066 | AC11: =SUM(O11:R11) -> 334.721 | ... AE11: =SUM(Q11:T11) -> 437.058
B12: Servicing income | C12: 65.77 | D12: 87.489 | E12: 95.483 | F12: 120.601 | H12: 21.37 | I12: 21.494 | J12: 21.413 | K12: =SUM(D12-SUM(H12:J12)) -> 23.212 | L12: 20.157 | M12: 22.436 | N12: 25.294 | O12: =SUM(E12-SUM(L12:N12)) -> 27.596 | P12: 25.983 | Q12: 28.69 | R12: 32.05 | S12: =SUM(F12-SUM(P12:R12)) -> 33.878 | T12: 39.689 | V12: =SUM(H12:K12) -> 87.489 | W12: =SUM(I12:L12) -> 86.276 | X12: =SUM(J12:M12) -> 87.218 | Y12: =SUM(K12:N12) -> 91.099 | Z12: =SUM(L12:O12) -> 95.483 | AA12: =SUM(M12:P12) -> 101.309 | AB12: =SUM(N12:Q12) -> 107.563 | AC12: =SUM(O12:R12) -> 114.319 | ... AE12: =SUM(Q12:T12) -> 134.307
B13: Total Net Revenue | C13: =SUM(C9:C12) -> 1349.292 | D13: =SUM(D9:D12) -> 1587.985 | E13: =SUM(E9:E12) -> 2322.999 | F13: =SUM(F9:F12) -> 3224.41 | H13: =SUM(H9:H12) -> 361.624 | I13: =SUM(I9:I12) -> 399.558 | J13: =SUM(J9:J12) -> 380.978 | K13: =SUM(K9:K12) -> 445.825 | L13: =SUM(L9:L12) -> 496.547 | M13: =SUM(M9:M12) -> 591.11 | N13: =SUM(N9:N12) -> 576.157 | O13: =SUM(O9:O12) -> 659.185 | ... T13: =SUM(T9:T12) -> 933.337 | V13: =SUM(V9:V12) -> 1587.985 | W13: =SUM(W9:W12) -> 1722.908 | X13: =SUM(X9:X12) -> 1914.46 | Y13: =SUM(Y9:Y12) -> 2109.639 | Z13: =SUM(Z9:Z12) -> 2322.999 | AA13: =SUM(AA9:AA12) -> 2524.931 | AB13: =SUM(AB9:AB12) -> 2800.202 | AC13: =SUM(AC9:AC12) -> 3007.179 | ... AE13: =SUM(AE9:AE12) -> 3459.268
B14: Balance Check | C14: =+C13-'Historical Financials'!C11 -> 0 | D14: =+D13-'Historical Financials'!D11 -> 0 | E14: =+E13-'Historical Financials'!E11 -> 0 | F14: =+F13-'Historical Financials'!F11 -> 0 | H14: =+H13-'Historical Financials'!H11 -> 0 | I14: =+I13-'Historical Financials'!I11 -> 0 | J14: =+J13-'Historical Financials'!J11 -> 0 | K14: =+K13-'Historical Financials'!K11 -> 0 | L14: =+L13-'Historical Financials'!L11 -> 0 | M14: =+M13-'Historical Financials'!M11 -> 0 | N14: =+N13-'Historical Financials'!N11 -> 0 | O14: =+O13-'Historical Financials'!O11 -> 0 | ... T14: =+T13-'Historical Financials'!T11 -> 0 | V14: =+V13-'Historical Financials'!V11 -> 0 | W14: =+W13-'Historical Financials'!W11 -> 0 | X14: =+X13-'Historical Financials'!X11 -> 0 | Y14: =+Y13-'Historical Financials'!Y11 -> 0 | Z14: =+Z13-'Historical Financials'!Z11 -> 0 | AA14: =+AA13-'Historical Financials'!AA11 -> 0 | AB14: =+AB13-'Historical Financials'!AB11 -> 0 | AC14: =+AC13-'Historical Financials'!AC11 -> 0 | ... AE14: =+AE13-'Historical Financials'!AE11 -> 0
B16: =B9&"(%)" -> Network revenue (%) | C16: =SUM(C9/C$13) -> 0.41444476 | D16: =SUM(D9/D$13) -> 0.39480096 | E16: =SUM(E9/E$13) -> 0.35557828 | F16: =SUM(F9/F$13) -> 0.34547902 | H16: =SUM(H9/H$13) -> 0.38674701 | I16: =SUM(I9/I$13) -> 0.40829116 | J16: =SUM(J9/J$13) -> 0.38973904 | K16: =SUM(K9/K$13) -> 0.39356923 | L16: =SUM(L9/L$13) -> 0.36134747 | M16: =SUM(M9/M$13) -> 0.3850823 | N16: =SUM(N9/N$13) -> 0.33839388 | O16: =SUM(O9/O$13) -> 0.33979535 | ... T16: =SUM(T9/T$13) -> 0.34336687 | V16: =I16 -> 0.40829116 | W16: =J16 -> 0.38973904 | X16: =K16 -> 0.39356923 | Y16: =L16 -> 0.36134747 | Z16: =M16 -> 0.3850823 | AA16: =N16 -> 0.33839388 | AB16: =O16 -> 0.33979535 | AC16: =P16 -> 0.33189115 | ... AE16: =R16 -> 0.34801835
B17: =B10&"(%)" -> Interest Income (%) | C17: =SUM(C10/C$13) -> 0.3912274 | D17: =SUM(D10/D$13) -> 0.43150093 | E17: =SUM(E10/E$13) -> 0.51844835 | F17: =SUM(F10/F$13) -> 0.49876443 | H17: =SUM(H10/H$13) -> 0.37829901 | I17: =SUM(I10/I$13) -> 0.38873205 | J17: =SUM(J10/J$13) -> 0.46792728 | K17: =SUM(K10/K$13) -> 0.48185723 | L17: =SUM(L10/L$13) -> 0.52901135 | M17: =SUM(M10/M$13) -> 0.4878043 | N17: =SUM(N10/N$13) -> 0.54796175 | O17: =SUM(O10/O$13) -> 0.51217488 | ... T17: =SUM(T10/T$13) -> 0.48655737 | V17: =I17 -> 0.38873205 | W17: =J17 -> 0.46792728 | X17: =K17 -> 0.48185723 | Y17: =L17 -> 0.52901135 | Z17: =M17 -> 0.4878043 | AA17: =N17 -> 0.54796175 | AB17: =O17 -> 0.51217488 | AC17: =P17 -> 0.53983584 | ... AE17: =R17 -> 0.51421723
B18: =B11&"(%)" -> Gain (loss) on sales of loans (%) | C18: =SUM(C11/C$13) -> 0.14558376 | D18: =SUM(D11/D$13) -> 0.11860377 | E18: =SUM(E11/E$13) -> 0.084870032 | F18: =SUM(F11/F$13) -> 0.11835406 | H18: =SUM(H11/H$13) -> 0.17585946 | I18: =SUM(I11/I$13) -> 0.14918235 | J18: =SUM(J11/J$13) -> 0.086128333 | K18: =SUM(K11/K$13) -> 0.072508271 | L18: =SUM(L11/L$13) -> 0.069046837 | M18: =SUM(M11/M$13) -> 0.089157686 | N18: =SUM(N11/N$13) -> 0.069743143 | O18: =SUM(O11/O$13) -> 0.10616595 | ... T18: =SUM(T11/T$13) -> 0.127552 | V18: =I18 -> 0.14918235 | W18: =J18 -> 0.086128333 | X18: =K18 -> 0.072508271 | Y18: =L18 -> 0.069046837 | Z18: =M18 -> 0.089157686 | AA18: =N18 -> 0.069743143 | AB18: =O18 -> 0.10616595 | AC18: =P18 -> 0.091073604 | ... AE18: =R18 -> 0.096839111
B19: =B12&"(%)" -> Servicing income (%) | C19: =SUM(C12/C$13) -> 0.048744082 | D19: =SUM(D12/D$13) -> 0.055094349 | E19: =SUM(E12/E$13) -> 0.041103332 | F19: =SUM(F12/F$13) -> 0.037402502 | H19: =SUM(H12/H$13) -> 0.059094529 | I19: =SUM(I12/I$13) -> 0.053794443 | J19: =SUM(J12/J$13) -> 0.056205345 | K19: =SUM(K12/K$13) -> 0.052065272 | L19: =SUM(L12/L$13) -> 0.040594345 | M19: =SUM(M12/M$13) -> 0.03795571 | N19: =SUM(N12/N$13) -> 0.043901228 | O19: =SUM(O12/O$13) -> 0.041863817 | ... T19: =SUM(T12/T$13) -> 0.042523762 | V19: =I19 -> 0.053794443 | W19: =J19 -> 0.056205345 | X19: =K19 -> 0.052065272 | Y19: =L19 -> 0.040594345 | Z19: =M19 -> 0.03795571 | AA19: =N19 -> 0.043901228 | AB19: =O19 -> 0.041863817 | AC19: =P19 -> 0.0371994 | ... AE19: =R19 -> 0.040925308
A21: X | B21: KPIs
A23: X | B23: Gross Merchandise Volume (GMV)
B24: GMW | C24: 15483 | D24: 20186 | E24: 26600 | F24: 36700 | H24: 4389 | I24: 5658 | J24: 4639 | K24: =SUM(D24-SUM(H24:J24)) -> 5500 | L24: 5600 | M24: 7500 | N24: 6300 | O24: =SUM(E24-SUM(L24:N24)) -> 7200 | P24: 7600 | Q24: 10100 | R24: 8600 | S24: =SUM(F24-SUM(P24:R24)) -> 10400 | T24: 10758 | V24: =SUM(H24:K24) -> 20186 | W24: =SUM(I24:L24) -> 21397 | X24: =SUM(J24:M24) -> 23239 | Y24: =SUM(K24:N24) -> 24900 | Z24: =SUM(L24:O24) -> 26600 | AA24: =SUM(M24:P24) -> 28600 | AB24: =SUM(N24:Q24) -> 31200 | AC24: =SUM(O24:R24) -> 33500 | ... AE24: =SUM(Q24:T24) -> 39858
B25: Total GMW | C25: =SUM(C24:C24) -> 15483 | D25: =SUM(D24:D24) -> 20186 | E25: =SUM(E24:E24) -> 26600 | F25: =SUM(F24:F24) -> 36700 | H25: =SUM(H24:H24) -> 4389 | I25: =SUM(I24:I24) -> 5658 | J25: =SUM(J24:J24) -> 4639 | K25: =SUM(K24:K24) -> 5500 | L25: =SUM(L24:L24) -> 5600 | M25: =SUM(M24:M24) -> 7500 | N25: =SUM(N24:N24) -> 6300 | O25: =SUM(O24:O24) -> 7200 | ... T25: =SUM(T24:T24) -> 10758 | V25: =SUM(V24:V24) -> 20186 | W25: =SUM(W24:W24) -> 21397 | X25: =SUM(X24:X24) -> 23239 | Y25: =SUM(Y24:Y24) -> 24900 | Z25: =SUM(Z24:Z24) -> 26600 | AA25: =SUM(AA24:AA24) -> 28600 | AB25: =SUM(AB24:AB24) -> 31200 | AC25: =SUM(AC24:AC24) -> 33500 | ... AE25: =SUM(AE24:AE24) -> 39858
B26: Y/Y Growth (%) | D26: =SUM(D25/C25)-1 -> 0.3037525 | E26: =SUM(E25/D25)-1 -> 0.31774497 | F26: =SUM(F25/E25)-1 -> 0.37969925 | L26: =SUM(L25/H25)-1 -> 0.27591707 | M26: =SUM(M25/I25)-1 -> 0.32555673 | N26: =SUM(N25/J25)-1 -> 0.3580513 | O26: =SUM(O25/K25)-1 -> 0.30909091 | P26: =SUM(P25/L25)-1 -> 0.35714286 | Q26: =SUM(Q25/M25)-1 -> 0.34666667 | R26: =SUM(R25/N25)-1 -> 0.36507937 | S26: =SUM(S25/O25)-1 -> 0.44444444 | T26: =SUM(T25/P25)-1 -> 0.41552632 | V26: =K26 -> 0 | W26: =L26 -> 0.27591707 | X26: =M26 -> 0.32555673 | Y26: =N26 -> 0.3580513 | Z26: =O26 -> 0.30909091 | AA26: =P26 -> 0.35714286 | AB26: =Q26 -> 0.34666667 | AC26: =R26 -> 0.36507937 | ... AE26: =T26 -> 0.41552632
B27: Q/Q Growth (%) | C27: N/A | D27: N/A | E27: N/A | F27: N/A | I27: =SUM(I25/H25)-1 -> 0.28913192 | J27: =SUM(J25/I25)-1 -> -0.18009897 | K27: =SUM(K25/J25)-1 -> 0.18560034 | L27: =SUM(L25/K25)-1 -> 0.018181818 | M27: =SUM(M25/L25)-1 -> 0.33928571 | N27: =SUM(N25/M25)-1 -> -0.16 | O27: =SUM(O25/N25)-1 -> 0.14285714 | P27: =SUM(P25/O25)-1 -> 0.055555556 | ... T27: =SUM(T25/S25)-1 -> 0.034423077 | V27: N/A | W27: N/A | X27: N/A | Y27: N/A | Z27: N/A | AA27: N/A | AB27: N/A | AC27: N/A | AD27: N/A | AE27: N/A
A29: X | B29: Merchants
B30: <=$1,000 TTM GMV | C30: 152000 | D30: 158000 | E30: 180000 | F30: 222000 | H30: 157000 | I30: 153000 | J30: 153000 | K30: =D30 -> 158000 | L30: 163000 | M30: 170000 | N30: 176000 | O30: =E30 -> 180000 | P30: 194000 | Q30: 201000 | R30: 210000 | S30: =F30 -> 222000 | T30: 251000 | V30: =K30 -> 158000 | W30: =L30 -> 163000 | X30: =M30 -> 170000 | Y30: =N30 -> 176000 | Z30: =O30 -> 180000 | AA30: =P30 -> 194000 | AB30: =Q30 -> 201000 | AC30: =R30 -> 210000 | ... AE30: =T30 -> 251000
B31: >$1,000 TTM GMV | C31: 83000 | D31: 96000 | E31: 123000 | F31: 155000 | H31: 88000 | I31: 90000 | J31: 92000 | K31: =D31 -> 96000 | L31: 103000 | M31: 109000 | N31: 117000 | O31: =E31 -> 123000 | P31: 129000 | Q31: 136000 | R31: 148000 | S31: =F31 -> 155000 | T31: 168000 | V31: =K31 -> 96000 | W31: =L31 -> 103000 | X31: =M31 -> 109000 | Y31: =N31 -> 117000 | Z31: =O31 -> 123000 | AA31: =P31 -> 129000 | AB31: =Q31 -> 136000 | AC31: =R31 -> 148000 | ... AE31: =T31 -> 168000
B32: Total Active Merchants | C32: =SUM(C30:C31) -> 235000 | D32: =SUM(D30:D31) -> 254000 | E32: =SUM(E30:E31) -> 303000 | F32: =SUM(F30:F31) -> 377000 | H32: =SUM(H30:H31) -> 245000 | I32: =SUM(I30:I31) -> 243000 | J32: =SUM(J30:J31) -> 245000 | K32: =SUM(K30:K31) -> 254000 | L32: =SUM(L30:L31) -> 266000 | M32: =SUM(M30:M31) -> 279000 | N32: =SUM(N30:N31) -> 293000 | O32: =SUM(O30:O31) -> 303000 | ... T32: =SUM(T30:T31) -> 419000 | V32: =SUM(V30:V31) -> 254000 | W32: =SUM(W30:W31) -> 266000 | X32: =SUM(X30:X31) -> 279000 | Y32: =SUM(Y30:Y31) -> 293000 | Z32: =SUM(Z30:Z31) -> 303000 | AA32: =SUM(AA30:AA31) -> 323000 | AB32: =SUM(AB30:AB31) -> 337000 | AC32: =SUM(AC30:AC31) -> 358000 | ... AE32: =SUM(AE30:AE31) -> 419000
B33: Y/Y Growth (%) | D33: =SUM(D32/C32)-1 -> 0.080851064 | E33: =SUM(E32/D32)-1 -> 0.19291339 | F33: =SUM(F32/E32)-1 -> 0.24422442 | L33: =SUM(L32/H32)-1 -> 0.085714286 | M33: =SUM(M32/I32)-1 -> 0.14814815 | N33: =SUM(N32/J32)-1 -> 0.19591837 | O33: =SUM(O32/K32)-1 -> 0.19291339 | P33: =SUM(P32/L32)-1 -> 0.21428571 | Q33: =SUM(Q32/M32)-1 -> 0.2078853 | R33: =SUM(R32/N32)-1 -> 0.221843 | S33: =SUM(S32/O32)-1 -> 0.24422442 | T33: =SUM(T32/P32)-1 -> 0.29721362 | V33: =K33 -> 0 | W33: =L33 -> 0.085714286 | X33: =M33 -> 0.14814815 | Y33: =N33 -> 0.19591837 | Z33: =O33 -> 0.19291339 | AA33: =P33 -> 0.21428571 | AB33: =Q33 -> 0.2078853 | AC33: =R33 -> 0.221843 | ... AE33: =T33 -> 0.29721362
B34: Q/Q Growth (%) | C34: N/A | D34: N/A | E34: N/A | F34: N/A | I34: =SUM(I32/H32)-1 -> -0.0081632653 | J34: =SUM(J32/I32)-1 -> 0.0082304527 | K34: =SUM(K32/J32)-1 -> 0.036734694 | L34: =SUM(L32/K32)-1 -> 0.047244094 | M34: =SUM(M32/L32)-1 -> 0.04887218 | N34: =SUM(N32/M32)-1 -> 0.050179211 | O34: =SUM(O32/N32)-1 -> 0.034129693 | P34: =SUM(P32/O32)-1 -> 0.066006601 | ... T34: =SUM(T32/S32)-1 -> 0.11140584 | V34: N/A | W34: N/A | X34: N/A | Y34: N/A | Z34: N/A | AA34: N/A | AB34: N/A | AC34: N/A | AD34: N/A | AE34: N/A
A36: X | B36: Total Loans Sold
B37: Loans sold | C37: =C42*C25 -> 7100.61 | D37: =D42*D25 -> 7500 | E37: =E42*E25 -> 10200 | F37: =F42*F25 -> 15800 | H37: =H42*H25 -> 2018.94 | I37: =I42*I25 -> 2093.46 | J37: =J42*J25 -> 1716.43 | K37: =K42*K25 -> 1671.17 | L37: =L42*L25 -> 2576 | M37: =M42*M25 -> 3100 | N37: =N42*N25 -> 2100 | O37: =O42*O25 -> 2424 | ... T37: =T42*T25 -> 4930 | V37: =SUM(H37:K37) -> 7500 | W37: =SUM(I37:L37) -> 8057.06 | X37: =SUM(J37:M37) -> 9063.6 | Y37: =SUM(K37:N37) -> 9447.17 | Z37: =SUM(L37:O37) -> 10200 | AA37: =SUM(M37:P37) -> 10424 | AB37: =SUM(N37:Q37) -> 11924 | AC37: =SUM(O37:R37) -> 13424 | ... AE37: =SUM(Q37:T37) -> 17930
B38: Total Active Merchants | C38: =C37 -> 7100.61 | D38: =D37 -> 7500 | E38: =E37 -> 10200 | F38: =F37 -> 15800 | H38: =H37 -> 2018.94 | I38: =I37 -> 2093.46 | J38: =J37 -> 1716.43 | K38: =K37 -> 1671.17 | L38: =L37 -> 2576 | M38: =M37 -> 3100 | N38: =N37 -> 2100 | O38: =O37 -> 2424 | ... T38: =T37 -> 4930 | V38: =V37 -> 7500 | W38: =W37 -> 8057.06 | X38: =X37 -> 9063.6 | Y38: =Y37 -> 9447.17 | Z38: =Z37 -> 10200 | AA38: =AA37 -> 10424 | AB38: =AB37 -> 11924 | AC38: =AC37 -> 13424 | ... AE38: =AE37 -> 17930
B39: Y/Y Growth (%) | D39: =SUM(D38/C38)-1 -> 0.05624728 | E39: =SUM(E38/D38)-1 -> 0.36 | F39: =SUM(F38/E38)-1 -> 0.54901961 | L39: =SUM(L38/H38)-1 -> 0.27591707 | M39: =SUM(M38/I38)-1 -> 0.48080212 | N39: =SUM(N38/J38)-1 -> 0.22346964 | O39: =SUM(O38/K38)-1 -> 0.4504808 | P39: =SUM(P38/L38)-1 -> 0.086956522 | Q39: =SUM(Q38/M38)-1 -> 0.48387097 | R39: =SUM(R38/N38)-1 -> 0.71428571 | S39: =SUM(S38/O38)-1 -> 0.98019802 | T39: =SUM(T38/P38)-1 -> 0.76071429 | V39: =K39 -> 0 | W39: =L39 -> 0.27591707 | X39: =M39 -> 0.48080212 | Y39: =N39 -> 0.22346964 | Z39: =O39 -> 0.4504808 | AA39: =P39 -> 0.086956522 | AB39: =Q39 -> 0.48387097 | AC39: =R39 -> 0.71428571 | ... AE39: =T39 -> 0.76071429
B40: Q/Q Growth (%) | C40: N/A | D40: N/A | E40: N/A | F40: N/A | I40: =SUM(I38/H38)-1 -> 0.036910458 | J40: =SUM(J38/I38)-1 -> -0.18009897 | K40: =SUM(K38/J38)-1 -> -0.026368684 | L40: =SUM(L38/K38)-1 -> 0.54143504 | M40: =SUM(M38/L38)-1 -> 0.20341615 | N40: =SUM(N38/M38)-1 -> -0.32258065 | O40: =SUM(O38/N38)-1 -> 0.15428571 | P40: =SUM(P38/O38)-1 -> 0.15511551 | ... T40: =SUM(T38/S38)-1 -> 0.027083333 | V40: N/A | W40: N/A | X40: N/A | Y40: N/A | Z40: N/A | AA40: N/A | AB40: N/A | AC40: N/A | AD40: N/A | AE40: N/A
B42: (%) of GMV sold | C42: 0.45860686 | D42: 0.37154463 | E42: 0.38345865 | F42: 0.43051771 | H42: 0.46 | I42: 0.37 | J42: 0.37 | K42: 0.30384909 | L42: 0.46 | M42: 0.41333333 | N42: 0.33333333 | O42: 0.33666667 | P42: 0.36842105 | Q42: 0.45544554 | R42: 0.41860465 | S42: 0.46153846 | T42: 0.45826362 | V42: =K42 -> 0.30384909 | W42: =L42 -> 0.46 | X42: =M42 -> 0.41333333 | Y42: =N42 -> 0.33333333 | Z42: =O42 -> 0.33666667 | AA42: =P42 -> 0.36842105 | AB42: =Q42 -> 0.45544554 | AC42: =R42 -> 0.41860465 | ... AE42: =T42 -> 0.45826362
A44: X | B44: GMV per active customer
B45: GMV per active customer | V45: =K45 -> 0 | W45: =L45 -> 0 | X45: =M45 -> 0 | Y45: =N45 -> 0 | Z45: =O45 -> 0 | AA45: =P45 -> 0 | AB45: =Q45 -> 0 | AC45: =R45 -> 0 | ... AE45: =T45 -> 0
B46: GMV per active customer | C46: =SUM(C45:C45) -> 0 | D46: =SUM(D45:D45) -> 0 | E46: =SUM(E45:E45) -> 0 | F46: =SUM(F45:F45) -> 0 | H46: =SUM(H45:H45) -> 0 | I46: =SUM(I45:I45) -> 0 | J46: =SUM(J45:J45) -> 0 | K46: =SUM(K45:K45) -> 0 | L46: =SUM(L45:L45) -> 0 | M46: =SUM(M45:M45) -> 0 | N46: =SUM(N45:N45) -> 0 | O46: =SUM(O45:O45) -> 0 | ... T46: =SUM(T45:T45) -> 0 | V46: =SUM(V45:V45) -> 0 | W46: =SUM(W45:W45) -> 0 | X46: =SUM(X45:X45) -> 0 | Y46: =SUM(Y45:Y45) -> 0 | Z46: =SUM(Z45:Z45) -> 0 | AA46: =SUM(AA45:AA45) -> 0 | AB46: =SUM(AB45:AB45) -> 0 | AC46: =SUM(AC45:AC45) -> 0 | ... AE46: =SUM(AE45:AE45) -> 0
B47: Y/Y Growth (%) | D47: =SUM(D46/C46)-1 -> #DIV/0! | E47: =SUM(E46/D46)-1 -> #DIV/0! | F47: =SUM(F46/E46)-1 -> #DIV/0! | L47: =SUM(L46/H46)-1 -> #DIV/0! | M47: =SUM(M46/I46)-1 -> #DIV/0! | N47: =SUM(N46/J46)-1 -> #DIV/0! | O47: =SUM(O46/K46)-1 -> #DIV/0! | P47: =SUM(P46/L46)-1 -> #DIV/0! | Q47: =SUM(Q46/M46)-1 -> #DIV/0! | R47: =SUM(R46/N46)-1 -> #DIV/0! | S47: =SUM(S46/O46)-1 -> #DIV/0! | T47: =SUM(T46/P46)-1 -> #DIV/0! | V47: =K47 -> 0 | W47: =L47 -> #DIV/0! | X47: =M47 -> #DIV/0! | Y47: =N47 -> #DIV/0! | Z47: =O47 -> #DIV/0! | AA47: =P47 -> #DIV/0! | AB47: =Q47 -> #DIV/0! | AC47: =R47 -> #DIV/0! | ... AE47: =T47 -> #DIV/0!
B48: Q/Q Growth (%) | C48: N/A | D48: N/A | E48: N/A | F48: N/A | I48: =SUM(I46/H46)-1 -> #DIV/0! | J48: =SUM(J46/I46)-1 -> #DIV/0! | K48: =SUM(K46/J46)-1 -> #DIV/0! | L48: =SUM(L46/K46)-1 -> #DIV/0! | M48: =SUM(M46/L46)-1 -> #DIV/0! | N48: =SUM(N46/M46)-1 -> #DIV/0! | O48: =SUM(O46/N46)-1 -> #DIV/0! | P48: =SUM(P46/O46)-1 -> #DIV/0! | ... T48: =SUM(T46/S46)-1 -> #DIV/0! | V48: N/A | W48: N/A | X48: N/A | Y48: N/A | Z48: N/A | AA48: N/A | AB48: N/A | AC48: N/A | AD48: N/A | AE48: N/A
A50: X | B50: GMV % Mix by loan type
B51: Core 0% APR | C51: 3899 | D51: 2684.65 | E51: 3052 | F51: 4723 | H51: 818 | I51: 565.8 | J51: 695.85 | K51: =SUM(D51-SUM(H51:J51)) -> 605 | L51: 616 | M51: 825 | N51: 819 | O51: =SUM(E51-SUM(L51:N51)) -> 792 | P51: 836 | Q51: 1313 | R51: 1118 | S51: =SUM(F51-SUM(P51:R51)) -> 1456 | T51: 1398.54 | V51: =SUM(H51:K51) -> 2684.65 | W51: =SUM(I51:L51) -> 2482.65 | X51: =SUM(J51:M51) -> 2741.85 | Y51: =SUM(K51:N51) -> 2865 | Z51: =SUM(L51:O51) -> 3052 | AA51: =SUM(M51:P51) -> 3272 | AB51: =SUM(N51:Q51) -> 3760 | AC51: =SUM(O51:R51) -> 4059 | ... AE51: =SUM(Q51:T51) -> 5285.54
B52: Interest-Bearing | C52: 8900 | D52: 13747.77 | E52: 19555 | F52: 26548 | H52: 2796 | I52: 3790.86 | J52: 3200.91 | K52: =SUM(D52-SUM(H52:J52)) -> 3960 | L52: 4144 | M52: 5475 | N52: 4536 | O52: =SUM(E52-SUM(L52:N52)) -> 5400 | P52: 5700 | Q52: 7272 | R52: 6192 | S52: =SUM(F52-SUM(P52:R52)) -> 7384 | T52: 7745.76 | V52: =SUM(H52:K52) -> 13747.77 | W52: =SUM(I52:L52) -> 15095.77 | X52: =SUM(J52:M52) -> 16779.91 | Y52: =SUM(K52:N52) -> 18115 | Z52: =SUM(L52:O52) -> 19555 | AA52: =SUM(M52:P52) -> 21111 | AB52: =SUM(N52:Q52) -> 22908 | AC52: =SUM(O52:R52) -> 24564 | ... AE52: =SUM(Q52:T52) -> 28593.76
B53: Pay in 4 (bi-weekly 0% APR) | C53: 2686 | D53: 3753.58 | E53: 3930 | F53: 5429 | H53: 775 | I53: 1301.34 | J53: 742.24 | K53: =SUM(D53-SUM(H53:J53)) -> 935 | L53: 840 | M53: 1200 | N53: 882 | O53: =SUM(E53-SUM(L53:N53)) -> 1008 | P53: 1064 | Q53: 1515 | R53: 1290 | S53: =SUM(F53-SUM(P53:R53)) -> 1560 | T53: 1613.7 | V53: =SUM(H53:K53) -> 3753.58 | W53: =SUM(I53:L53) -> 3818.58 | X53: =SUM(J53:M53) -> 3717.24 | Y53: =SUM(K53:N53) -> 3857 | Z53: =SUM(L53:O53) -> 3930 | AA53: =SUM(M53:P53) -> 4154 | AB53: =SUM(N53:Q53) -> 4469 | AC53: =SUM(O53:R53) -> 4877 | ... AE53: =SUM(Q53:T53) -> 5978.7
B54: Affirm Card / Direct to Consumer | C54: 0 | D54: 0 | E54: 0 | F54: 3435 | H54: 8 | I54: 11 | J54: 18 | K54: 129 | L54: 224 | M54: 397 | N54: 374 | O54: 507 | P54: 607 | Q54: 845 | R54: 807 | S54: =SUM(F54-SUM(P54:R54)) -> 1176 | T54: 1427 | V54: =SUM(H54:K54) -> 166 | W54: =SUM(I54:L54) -> 382 | X54: =SUM(J54:M54) -> 768 | Y54: =SUM(K54:N54) -> 1124 | Z54: =SUM(L54:O54) -> 1502 | AA54: =SUM(M54:P54) -> 1885 | AB54: =SUM(N54:Q54) -> 2333 | AC54: =SUM(O54:R54) -> 2766 | ... AE54: =SUM(Q54:T54) -> 4255
B55: Total Net Revenue | C55: =SUM(C51:C54) -> 15485 | D55: =SUM(D51:D54) -> 20186 | E55: =SUM(E51:E54) -> 26537 | F55: =SUM(F51:F54) -> 40135 | H55: =SUM(H51:H54) -> 4397 | I55: =SUM(I51:I54) -> 5669 | J55: =SUM(J51:J54) -> 4657 | K55: =SUM(K51:K54) -> 5629 | L55: =SUM(L51:L54) -> 5824 | M55: =SUM(M51:M54) -> 7897 | N55: =SUM(N51:N54) -> 6611 | O55: =SUM(O51:O54) -> 7707 | ... T55: =SUM(T51:T54) -> 12185 | V55: =SUM(V51:V54) -> 20352 | W55: =SUM(W51:W54) -> 21779 | X55: =SUM(X51:X54) -> 24007 | Y55: =SUM(Y51:Y54) -> 25961 | Z55: =SUM(Z51:Z54) -> 28039 | AA55: =SUM(AA51:AA54) -> 30422 | AB55: =SUM(AB51:AB54) -> 33470 | AC55: =SUM(AC51:AC54) -> 36266 | ... AE55: =SUM(AE51:AE54) -> 44113
B58: =B51&"(%)" -> Core 0% APR (%) | C58: =SUM(C51/C$55) -> 0.25179206 | D58: =SUM(D51/D$55) -> 0.13299564 | E58: =SUM(E51/E$55) -> 0.11500923 | F58: =SUM(F51/F$55) -> 0.11767784 | H58: =SUM(H51/H$55) -> 0.18603593 | I58: =SUM(I51/I$55) -> 0.099805962 | J58: =SUM(J51/J$55) -> 0.14942023 | K58: =SUM(K51/K$55) -> 0.10747913 | L58: =SUM(L51/L$55) -> 0.10576923 | M58: =SUM(M51/M$55) -> 0.10447005 | N58: =SUM(N51/N$55) -> 0.12388444 | O58: =SUM(O51/O$55) -> 0.10276372 | ... T58: =SUM(T51/T$55) -> 0.11477554 | V58: =I58 -> 0.099805962 | W58: =J58 -> 0.14942023 | X58: =K58 -> 0.10747913 | Y58: =L58 -> 0.10576923 | Z58: =M58 -> 0.10447005 | AA58: =N58 -> 0.12388444 | AB58: =O58 -> 0.10276372 | AC58: =P58 -> 0.10186426 | ... AE58: =R58 -> 0.11884767
B59: =B52&"(%)" -> Interest-Bearing (%) | C59: =SUM(C52/C$55) -> 0.57474976 | D59: =SUM(D52/D$55) -> 0.68105469 | E59: =SUM(E52/E$55) -> 0.73689566 | F59: =SUM(F52/F$55) -> 0.66146755 | H59: =SUM(H52/H$55) -> 0.63588811 | I59: =SUM(I52/I$55) -> 0.66869995 | J59: =SUM(J52/J$55) -> 0.68733305 | K59: =SUM(K52/K$55) -> 0.70349973 | L59: =SUM(L52/L$55) -> 0.71153846 | M59: =SUM(M52/M$55) -> 0.69330125 | N59: =SUM(N52/N$55) -> 0.68612918 | O59: =SUM(O52/O$55) -> 0.70066174 | ... T59: =SUM(T52/T$55) -> 0.63567993 | V59: =I59 -> 0.66869995 | W59: =J59 -> 0.68733305 | X59: =K59 -> 0.70349973 | Y59: =L59 -> 0.71153846 | Z59: =M59 -> 0.69330125 | AA59: =N59 -> 0.68612918 | AB59: =O59 -> 0.70066174 | AC59: =P59 -> 0.69452906 | ... AE59: =R59 -> 0.65823323
B60: =B53&"(%)" -> Pay in 4 (bi-weekly 0% APR)(%) | C60: =SUM(C53/C$55) -> 0.17345819 | D60: =SUM(D53/D$55) -> 0.18594967 | E60: =SUM(E53/E$55) -> 0.14809511 | F60: =SUM(F53/F$55) -> 0.13526847 | H60: =SUM(H53/H$55) -> 0.17625654 | I60: =SUM(I53/I$55) -> 0.22955371 | J60: =SUM(J53/J$55) -> 0.15938158 | K60: =SUM(K53/K$55) -> 0.1661041 | L60: =SUM(L53/L$55) -> 0.14423077 | M60: =SUM(M53/M$55) -> 0.15195644 | N60: =SUM(N53/N$55) -> 0.13341401 | O60: =SUM(O53/O$55) -> 0.13079019 | ... T60: =SUM(T53/T$55) -> 0.13243332 | V60: =I60 -> 0.22955371 | W60: =J60 -> 0.15938158 | X60: =K60 -> 0.1661041 | Y60: =L60 -> 0.14423077 | Z60: =M60 -> 0.15195644 | AA60: =N60 -> 0.13341401 | AB60: =O60 -> 0.13079019 | AC60: =P60 -> 0.12964542 | ... AE60: =R60 -> 0.13713192
B61: =B54&"(%)" -> Affirm Card / Direct to Consumer(%) | C61: =SUM(C54/C$55) -> 0 | D61: =SUM(D54/D$55) -> 0 | E61: =SUM(E54/E$55) -> 0 | F61: =SUM(F54/F$55) -> 0.085586147 | H61: =SUM(H54/H$55) -> 0.0018194223 | I61: =SUM(I54/I$55) -> 0.0019403775 | J61: =SUM(J54/J$55) -> 0.0038651492 | K61: =SUM(K54/K$55) -> 0.022917037 | L61: =SUM(L54/L$55) -> 0.038461538 | M61: =SUM(M54/M$55) -> 0.050272255 | N61: =SUM(N54/N$55) -> 0.056572379 | O61: =SUM(O54/O$55) -> 0.065784352 | ... T61: =SUM(T54/T$55) -> 0.1171112 | V61: =I61 -> 0.0019403775 | W61: =J61 -> 0.0038651492 | X61: =K61 -> 0.022917037 | Y61: =L61 -> 0.038461538 | Z61: =M61 -> 0.050272255 | AA61: =N61 -> 0.056572379 | AB61: =O61 -> 0.065784352 | AC61: =P61 -> 0.073961253 | ... AE61: =R61 -> 0.08578718

Sheet FCF
B2: ='Historical Financials'!B2 -> Affirm Holdings Inc (NASDAQ: AFRM) | D2: FYE | H2: Quarterly | R2: Quarterly | Z2: LTM | AA2: LTM | AG2: Variance
B3: FCF Analysis | C3: ='Historical Financials'!C7 -> 2022 | D3: ='Historical Financials'!D7 -> 2023 | E3: ='Historical Financials'!E7 -> 2024 | F3: ='Historical Financials'!F7 -> 2025 | H3: ='Historical Financials'!H7 -> 1Q23 | I3: ='Historical Financials'!I7 -> 2Q23 | J3: ='Historical Financials'!J7 -> 3Q23 | K3: ='Historical Financials'!K7 -> 4Q23 | L3: ='Historical Financials'!L7 -> 1Q24 | M3: ='Historical Financials'!M7 -> 2Q24 | N3: ='Historical Financials'!N7 -> 3Q24 | O3: ='Historical Financials'!O7 -> 4Q24 | ... T3: ='Historical Financials'!T7 -> 1Q26 | V3: =K3 -> 4Q23 | W3: =L3 -> 1Q24 | X3: =M3 -> 2Q24 | Y3: =N3 -> 3Q24 | Z3: =O3 -> 4Q24 | AA3: =P3 -> 1Q25 | AB3: =Q3 -> 2Q25 | AC3: =R3 -> 3Q25 | ... AE3: =T3 -> 1Q26
B4: ($ In Millions) | C4: ='Historical Financials'!C8 -> 44713 | D4: ='Historical Financials'!D8 -> 45078 | E4: ='Historical Financials'!E8 -> 45444 | F4: ='Historical Financials'!F8 -> 45809 | H4: ='Historical Financials'!H8 -> 44805 | I4: ='Historical Financials'!I8 -> 44896 | J4: ='Historical Financials'!J8 -> 44986 | K4: ='Historical Financials'!K8 -> 45078 | L4: ='Historical Financials'!L8 -> 45170 | M4: ='Historical Financials'!M8 -> 45261 | N4: ='Historical Financials'!N8 -> 45352 | O4: ='Historical Financials'!O8 -> 45444 | ... T4: ='Historical Financials'!T8 -> 45901 | V4: =K4 -> 45078 | W4: =L4 -> 45170 | X4: =M4 -> 45261 | Y4: =N4 -> 45352 | Z4: =O4 -> 45444 | AA4: =P4 -> 45536 | AB4: =Q4 -> 45627 | AC4: =R4 -> 45717 | ... AE4: =T4 -> 45901
B6: ='Revenue Drivers'!B9 -> Network revenue | C6: ='Revenue Drivers'!C9 -> 559.207 | D6: ='Revenue Drivers'!D9 -> 626.938 | E6: ='Revenue Drivers'!E9 -> 826.008 | F6: ='Revenue Drivers'!F9 -> 1113.966 | H6: ='Revenue Drivers'!H9 -> 139.857 | I6: ='Revenue Drivers'!I9 -> 163.136 | J6: ='Revenue Drivers'!J9 -> 148.482 | K6: ='Revenue Drivers'!K9 -> 175.463 | L6: ='Revenue Drivers'!L9 -> 179.426 | M6: ='Revenue Drivers'!M9 -> 227.626 | N6: ='Revenue Drivers'!N9 -> 194.968 | O6: ='Revenue Drivers'!O9 -> 223.988 | ... T6: ='Revenue Drivers'!T9 -> 320.477 | V6: =SUM(H6:K6) -> 626.938 | W6: =SUM(I6:L6) -> 666.507 | X6: =SUM(J6:M6) -> 730.997 | Y6: =SUM(K6:N6) -> 777.483 | Z6: =SUM(L6:O6) -> 826.008 | AA6: =SUM(M6:P6) -> 878.401 | AB6: =SUM(N6:Q6) -> 953.812 | AC6: =SUM(O6:R6) -> 1031.389 | ... AE6: =SUM(Q6:T6) -> 1202.624 | AG6: =SUM(AE6/AA6)-1 -> 0.36910591
B7: ='Revenue Drivers'!B10 -> Interest Income | C7: ='Revenue Drivers'!C10 -> 527.88 | D7: ='Revenue Drivers'!D10 -> 685.217 | E7: ='Revenue Drivers'!E10 -> 1204.355 | F7: ='Revenue Drivers'!F10 -> 1608.221 | H7: ='Revenue Drivers'!H10 -> 136.802 | I7: ='Revenue Drivers'!I10 -> 155.321 | J7: ='Revenue Drivers'!J10 -> 178.27 | K7: ='Revenue Drivers'!K10 -> 214.824 | L7: ='Revenue Drivers'!L10 -> 262.679 | M7: ='Revenue Drivers'!M10 -> 288.346 | N7: ='Revenue Drivers'!N10 -> 315.712 | O7: ='Revenue Drivers'!O10 -> 337.618 | ... T7: ='Revenue Drivers'!T10 -> 454.122 | V7: =SUM(H7:K7) -> 685.217 | W7: =SUM(I7:L7) -> 811.094 | X7: =SUM(J7:M7) -> 944.119 | Y7: =SUM(K7:N7) -> 1081.561 | Z7: =SUM(L7:O7) -> 1204.355 | AA7: =SUM(M7:P7) -> 1318.74 | AB7: =SUM(N7:Q7) -> 1439.761 | AC7: =SUM(O7:R7) -> 1526.75 | ... AE7: =SUM(Q7:T7) -> 1685.279 | AG7: =SUM(AE7/AA7)-1 -> 0.27794637
B8: ='Revenue Drivers'!B11 -> Gain (loss) on sales of loans | C8: ='Revenue Drivers'!C11 -> 196.435 | D8: ='Revenue Drivers'!D11 -> 188.341 | E8: ='Revenue Drivers'!E11 -> 197.153 | F8: ='Revenue Drivers'!F11 -> 381.622 | H8: ='Revenue Drivers'!H11 -> 63.595 | I8: ='Revenue Drivers'!I11 -> 59.607 | J8: ='Revenue Drivers'!J11 -> 32.813 | K8: ='Revenue Drivers'!K11 -> 32.326 | L8: ='Revenue Drivers'!L11 -> 34.285 | M8: ='Revenue Drivers'!M11 -> 52.702 | N8: ='Revenue Drivers'!N11 -> 40.183 | O8: ='Revenue Drivers'!O11 -> 69.983 | ... T8: ='Revenue Drivers'!T11 -> 119.049 | V8: =SUM(H8:K8) -> 188.341 | W8: =SUM(I8:L8) -> 159.031 | X8: =SUM(J8:M8) -> 152.126 | Y8: =SUM(K8:N8) -> 159.496 | Z8: =SUM(L8:O8) -> 197.153 | AA8: =SUM(M8:P8) -> 226.481 | AB8: =SUM(N8:Q8) -> 299.066 | AC8: =SUM(O8:R8) -> 334.721 | ... AE8: =SUM(Q8:T8) -> 437.058 | AG8: =SUM(AE8/AA8)-1 -> 0.92977777
B9: ='Revenue Drivers'!B12 -> Servicing income | C9: ='Revenue Drivers'!C12 -> 65.77 | D9: ='Revenue Drivers'!D12 -> 87.489 | E9: ='Revenue Drivers'!E12 -> 95.483 | F9: ='Revenue Drivers'!F12 -> 120.601 | H9: ='Revenue Drivers'!H12 -> 21.37 | I9: ='Revenue Drivers'!I12 -> 21.494 | J9: ='Revenue Drivers'!J12 -> 21.413 | K9: ='Revenue Drivers'!K12 -> 23.212 | L9: ='Revenue Drivers'!L12 -> 20.157 | M9: ='Revenue Drivers'!M12 -> 22.436 | N9: ='Revenue Drivers'!N12 -> 25.294 | O9: ='Revenue Drivers'!O12 -> 27.596 | ... T9: ='Revenue Drivers'!T12 -> 39.689 | V9: =SUM(H9:K9) -> 87.489 | W9: =SUM(I9:L9) -> 86.276 | X9: =SUM(J9:M9) -> 87.218 | Y9: =SUM(K9:N9) -> 91.099 | Z9: =SUM(L9:O9) -> 95.483 | AA9: =SUM(M9:P9) -> 101.309 | AB9: =SUM(N9:Q9) -> 107.563 | AC9: =SUM(O9:R9) -> 114.319 | ... AE9: =SUM(Q9:T9) -> 134.307 | AG9: =SUM(AE9/AA9)-1 -> 0.32571637
B10: Total Revenue | C10: =SUM(C6:C9) -> 1349.292 | D10: =SUM(D6:D9) -> 1587.985 | E10: =SUM(E6:E9) -> 2322.999 | F10: =SUM(F6:F9) -> 3224.41 | H10: =SUM(H6:H9) -> 361.624 | I10: =SUM(I6:I9) -> 399.558 | J10: =SUM(J6:J9) -> 380.978 | K10: =SUM(K6:K9) -> 445.825 | L10: =SUM(L6:L9) -> 496.547 | M10: =SUM(M6:M9) -> 591.11 | N10: =SUM(N6:N9) -> 576.157 | O10: =SUM(O6:O9) -> 659.185 | ... T10: =SUM(T6:T9) -> 933.337 | V10: =SUM(V6:V9) -> 1587.985 | W10: =SUM(W6:W9) -> 1722.908 | X10: =SUM(X6:X9) -> 1914.46 | Y10: =SUM(Y6:Y9) -> 2109.639 | Z10: =SUM(Z6:Z9) -> 2322.999 | AA10: =SUM(AA6:AA9) -> 2524.931 | AB10: =SUM(AB6:AB9) -> 2800.202 | AC10: =SUM(AC6:AC9) -> 3007.179 | ... AE10: =SUM(AE6:AE9) -> 3459.268 | AG10: =SUM(AE10/AA10)-1 -> 0.37004457
B11: Y/Y Growth (%) | D11: =SUM(D10/C10)-1 -> 0.17690241 | E11: =SUM(E10/D10)-1 -> 0.46285954 | F11: =SUM(F10/E10)-1 -> 0.38803762 | L11: =SUM(L10/H10)-1 -> 0.373103 | M11: =SUM(M10/I10)-1 -> 0.47940975 | N11: =SUM(N10/J10)-1 -> 0.51231042 | O11: =SUM(O10/K10)-1 -> 0.47857343 | P11: =SUM(P10/L10)-1 -> 0.40667248 | Q11: =SUM(Q10/M10)-1 -> 0.4656849 | R11: =SUM(R10/N10)-1 -> 0.35923715 | S11: =SUM(S10/O10)-1 -> 0.32954482 | T11: =SUM(T10/P10)-1 -> 0.33624203 | Z11: =SUM(Z10/V10)-1 -> 0.46285954 | AA11: =SUM(AA10/W10)-1 -> 0.46550541 | AB11: =SUM(AB10/X10)-1 -> 0.46265892 | AC11: =SUM(AC10/Y10)-1 -> 0.4254472 | AD11: =SUM(AD10/Z10)-1 -> 0.38803762 | AE11: =SUM(AE10/AA10)-1 -> 0.37004457 | AG11: =SUM(AE11-AA11)*10000 -> -954.60845
B12: Q/Q Growth (%) | C12: N/A | D12: N/A | E12: N/A | F12: N/A | I12: =SUM(I10/H10)-1 -> 0.10489901 | J12: =SUM(J10/I10)-1 -> -0.046501384 | K12: =SUM(K10/J10)-1 -> 0.17021193 | L12: =SUM(L10/K10)-1 -> 0.1137711 | M12: =SUM(M10/L10)-1 -> 0.19044119 | N12: =SUM(N10/M10)-1 -> -0.025296476 | O12: =SUM(O10/N10)-1 -> 0.14410655 | P12: =SUM(P10/O10)-1 -> 0.059609973 | ... T12: =SUM(T10/S10)-1 -> 0.064947468 | V12: N/A | W12: N/A | X12: N/A | Y12: N/A | Z12: N/A | AA12: N/A | AB12: N/A | AC12: N/A | AD12: N/A | AE12: N/A
B14: (-) Loss on loan purchase commitment | C14: ='Historical Financials'!C13 -> -204.081 | D14: ='Historical Financials'!D13 -> -140.265 | E14: ='Historical Financials'!E13 -> -180.395 | F14: ='Historical Financials'!F13 -> -242.264 | H14: ='Historical Financials'!H13 -> -35.61 | I14: ='Historical Financials'!I13 -> -38.422 | J14: ='Historical Financials'!J13 -> -31.224 | K14: ='Historical Financials'!K13 -> -35.009 | L14: ='Historical Financials'!L13 -> -34.866 | M14: ='Historical Financials'!M13 -> -53.63 | N14: ='Historical Financials'!N13 -> -44.143 | O14: ='Historical Financials'!O13 -> -47.756 | ... T14: ='Historical Financials'!T13 -> -71.552 | V14: =SUM(H14:K14) -> -140.265 | W14: =SUM(I14:L14) -> -139.521 | X14: =SUM(J14:M14) -> -154.729 | Y14: =SUM(K14:N14) -> -167.648 | Z14: =SUM(L14:O14) -> -180.395 | AA14: =SUM(M14:P14) -> -199.766 | AB14: =SUM(N14:Q14) -> -216.414 | AC14: =SUM(O14:R14) -> -229.561 | ... AE14: =SUM(Q14:T14) -> -259.579 | AG14: =SUM(AE14/AA14)-1 -> 0.29941532
B15: (-) Provision for credit losses | C15: ='Historical Financials'!C14 -> -255.272 | D15: ='Historical Financials'!D14 -> -331.86 | E15: ='Historical Financials'!E14 -> -460.628 | F15: ='Historical Financials'!F14 -> -616.683 | H15: ='Historical Financials'!H14 -> -64.25 | I15: ='Historical Financials'!I14 -> -106.689 | J15: ='Historical Financials'!J14 -> -66.438 | K15: ='Historical Financials'!K14 -> -94.483 | L15: ='Historical Financials'!L14 -> -99.696 | M15: ='Historical Financials'!M14 -> -120.88 | N15: ='Historical Financials'!N14 -> -122.443 | O15: ='Historical Financials'!O14 -> -117.609 | ... T15: ='Historical Financials'!T14 -> -162.752 | V15: =SUM(H15:K15) -> -331.86 | W15: =SUM(I15:L15) -> -367.306 | X15: =SUM(J15:M15) -> -381.497 | Y15: =SUM(K15:N15) -> -437.502 | Z15: =SUM(L15:O15) -> -460.628 | AA15: =SUM(M15:P15) -> -520.756 | AB15: =SUM(N15:Q15) -> -552.856 | AC15: =SUM(O15:R15) -> -577.665 | ... AE15: =SUM(Q15:T15) -> -619.611 | AG15: =SUM(AE15/AA15)-1 -> 0.18982979
B16: (-) Funding costs | C16: ='Historical Financials'!C15 -> -69.694 | D16: ='Historical Financials'!D15 -> -183.013 | E16: ='Historical Financials'!E15 -> -344.253 | F16: ='Historical Financials'!F15 -> -425.45 | H16: ='Historical Financials'!H15 -> -25.066 | I16: ='Historical Financials'!I15 -> -43.751 | J16: ='Historical Financials'!J15 -> -51.188 | K16: ='Historical Financials'!K15 -> -63.008 | L16: ='Historical Financials'!L15 -> -73.931 | M16: ='Historical Financials'!M15 -> -84.617 | N16: ='Historical Financials'!N15 -> -90.449 | O16: ='Historical Financials'!O15 -> -95.256 | ... T16: ='Historical Financials'!T15 -> -110.027 | V16: =SUM(H16:K16) -> -183.013 | W16: =SUM(I16:L16) -> -231.878 | X16: =SUM(J16:M16) -> -272.744 | Y16: =SUM(K16:N16) -> -312.005 | Z16: =SUM(L16:O16) -> -344.253 | AA16: =SUM(M16:P16) -> -374.467 | AB16: =SUM(N16:Q16) -> -397.612 | AC16: =SUM(O16:R16) -> -414.794 | ... AE16: =SUM(Q16:T16) -> -431.332 | AG16: =SUM(AE16/AA16)-1 -> 0.15185584
B17: (-) Processing and servicing | C17: ='Historical Financials'!C16 -> -157.814 | D17: ='Historical Financials'!D16 -> -257.343 | E17: ='Historical Financials'!E16 -> -343.249 | F17: ='Historical Financials'!F16 -> -457.849 | H17: ='Historical Financials'!H16 -> -54.359 | I17: ='Historical Financials'!I16 -> -66.508 | J17: ='Historical Financials'!J16 -> -65.229 | K17: ='Historical Financials'!K16 -> -71.247 | L17: ='Historical Financials'!L16 -> -75.671 | M17: ='Historical Financials'!M16 -> -90.203 | N17: ='Historical Financials'!N16 -> -88.209 | O17: ='Historical Financials'!O16 -> -89.166 | ... T17: ='Historical Financials'!T16 -> -133.807 | V17: =SUM(H17:K17) -> -257.343 | W17: =SUM(I17:L17) -> -278.655 | X17: =SUM(J17:M17) -> -302.35 | Y17: =SUM(K17:N17) -> -325.33 | Z17: =SUM(L17:O17) -> -343.249 | AA17: =SUM(M17:P17) -> -362.724 | AB17: =SUM(N17:Q17) -> -388.481 | AC17: =SUM(O17:R17) -> -418.67 | ... AE17: =SUM(Q17:T17) -> -496.51 | AG17: =SUM(AE17/AA17)-1 -> 0.36883691
B18: Gross Profit | C18: =SUM(C10+SUM(C14:C17)) -> 662.431 | D18: =SUM(D10+SUM(D14:D17)) -> 675.504 | E18: =SUM(E10+SUM(E14:E17)) -> 994.474 | F18: =SUM(F10+SUM(F14:F17)) -> 1482.164 | H18: =SUM(H10+SUM(H14:H17)) -> 182.339 | I18: =SUM(I10+SUM(I14:I17)) -> 144.188 | J18: =SUM(J10+SUM(J14:J17)) -> 166.899 | K18: =SUM(K10+SUM(K14:K17)) -> 182.078 | L18: =SUM(L10+SUM(L14:L17)) -> 212.383 | M18: =SUM(M10+SUM(M14:M17)) -> 241.78 | N18: =SUM(N10+SUM(N14:N17)) -> 230.913 | O18: =SUM(O10+SUM(O14:O17)) -> 309.398 | ... T18: =SUM(T10+SUM(T14:T17)) -> 455.199 | V18: =SUM(V10+SUM(V14:V17)) -> 675.504 | W18: =SUM(W10+SUM(W14:W17)) -> 705.548 | X18: =SUM(X10+SUM(X14:X17)) -> 803.14 | Y18: =SUM(Y10+SUM(Y14:Y17)) -> 867.154 | Z18: =SUM(Z10+SUM(Z14:Z17)) -> 994.474 | AA18: =SUM(AA10+SUM(AA14:AA17)) -> 1067.218 | AB18: =SUM(AB10+SUM(AB14:AB17)) -> 1244.839 | AC18: =SUM(AC10+SUM(AC14:AC17)) -> 1366.489 | ... AE18: =SUM(AE10+SUM(AE14:AE17)) -> 1652.236 | AG18: =SUM(AE18/AA18)-1 -> 0.54817104
B19: Gross Margin (%) | C19: =C18/C10 -> 0.4909471 | D19: =D18/D10 -> 0.42538437 | E19: =E18/E10 -> 0.42809919 | F19: =F18/F10 -> 0.45966983 | H19: =H18/H10 -> 0.50422262 | I19: =I18/I10 -> 0.36086876 | J19: =J18/J10 -> 0.43808041 | K19: =K18/K10 -> 0.40840689 | L19: =L18/L10 -> 0.42771983 | M19: =M18/M10 -> 0.40902708 | N19: =N18/N10 -> 0.40078138 | O19: =O18/O10 -> 0.46936444 | ... T19: =T18/T10 -> 0.4877113 | V19: =V18/V10 -> 0.42538437 | W19: =W18/W10 -> 0.40950997 | X19: =X18/X10 -> 0.41951255 | Y19: =Y18/Y10 -> 0.41104379 | Z19: =Z18/Z10 -> 0.42809919 | AA19: =AA18/AA10 -> 0.42267214 | AB19: =AB18/AB10 -> 0.44455329 | AC19: =AC18/AC10 -> 0.45440893 | ... AE19: =AE18/AE10 -> 0.4776259 | AG19: =SUM(AE19-AA19)*10000 -> 549.53758
B21: (-) Technology and data analytics | C21: ='Historical Financials'!C20 -> -418.643 | D21: ='Historical Financials'!D20 -> -615.818 | E21: ='Historical Financials'!E20 -> -501.857 | F21: ='Historical Financials'!F20 -> -589.723 | H21: ='Historical Financials'!H20 -> -144.961 | I21: ='Historical Financials'!I20 -> -156.747 | J21: ='Historical Financials'!J20 -> -161.792 | K21: ='Historical Financials'!K20 -> -152.318 | L21: ='Historical Financials'!L20 -> -132.965 | M21: ='Historical Financials'!M20 -> -119.833 | N21: ='Historical Financials'!N20 -> -124.828 | O21: ='Historical Financials'!O20 -> -124.231 | ... T21: ='Historical Financials'!T20 -> -168.106 | V21: =SUM(H21:K21) -> -615.818 | W21: =SUM(I21:L21) -> -603.822 | X21: =SUM(J21:M21) -> -566.908 | Y21: =SUM(K21:N21) -> -529.944 | Z21: =SUM(L21:O21) -> -501.857 | AA21: =SUM(M21:P21) -> -503.182 | AB21: =SUM(N21:Q21) -> -531.562 | AC21: =SUM(O21:R21) -> -559.354 | ... AE21: =SUM(Q21:T21) -> -623.539 | AG21: =SUM(AE21/AA21)-1 -> 0.23919178
B22: (-) Sales and marketing | C22: ='Historical Financials'!C21 -> -532.343 | D22: ='Historical Financials'!D21 -> -638.28 | E22: ='Historical Financials'!E21 -> -576.405 | F22: ='Historical Financials'!F21 -> -434.847 | H22: ='Historical Financials'!H21 -> -163.873 | I22: ='Historical Financials'!I21 -> -188.334 | J22: ='Historical Financials'!J21 -> -140.942 | K22: ='Historical Financials'!K21 -> -145.131 | L22: ='Historical Financials'!L21 -> -146.866 | M22: ='Historical Financials'!M21 -> -161.265 | N22: ='Historical Financials'!N21 -> -132.95 | O22: ='Historical Financials'!O21 -> -135.324 | ... T22: ='Historical Financials'!T21 -> -78.491 | V22: =SUM(H22:K22) -> -638.28 | W22: =SUM(I22:L22) -> -621.273 | X22: =SUM(J22:M22) -> -594.204 | Y22: =SUM(K22:N22) -> -586.212 | Z22: =SUM(L22:O22) -> -576.405 | AA22: =SUM(M22:P22) -> -574.772 | AB22: =SUM(N22:Q22) -> -549.545 | AC22: =SUM(O22:R22) -> -490.617 | ... AE22: =SUM(Q22:T22) -> -368.105 | AG22: =SUM(AE22/AA22)-1 -> -0.35956344
B23: (-) General and administrative | C23: ='Historical Financials'!C22 -> -577.493 | D23: ='Historical Financials'!D22 -> -586.398 | E23: ='Historical Financials'!E22 -> -525.291 | F23: ='Historical Financials'!F22 -> -545.053 | H23: ='Historical Financials'!H22 -> -160.972 | I23: ='Historical Financials'!I22 -> -158.639 | J23: ='Historical Financials'!J22 -> -139.266 | K23: ='Historical Financials'!K22 -> -127.521 | L23: ='Historical Financials'!L22 -> -140.334 | M23: ='Historical Financials'!M22 -> -132.777 | N23: ='Historical Financials'!N22 -> -128.721 | O23: ='Historical Financials'!O22 -> -123.459 | ... T23: ='Historical Financials'!T22 -> -144.941 | V23: =SUM(H23:K23) -> -586.398 | W23: =SUM(I23:L23) -> -565.76 | X23: =SUM(J23:M23) -> -539.898 | Y23: =SUM(K23:N23) -> -529.353 | Z23: =SUM(L23:O23) -> -525.291 | AA23: =SUM(M23:P23) -> -523.439 | AB23: =SUM(N23:Q23) -> -530.074 | AC23: =SUM(O23:R23) -> -535.656 | ... AE23: =SUM(Q23:T23) -> -551.512 | AG23: =SUM(AE23/AA23)-1 -> 0.053631846
B24: (-) Restructuring charges, net | C24: ='Historical Financials'!C23 -> 0 | D24: ='Historical Financials'!D23 -> -35.87 | E24: ='Historical Financials'!E23 -> -6.768 | F24: ='Historical Financials'!F23 -> 0.183 | H24: ='Historical Financials'!H23 -> 0 | I24: ='Historical Financials'!I23 -> 0 | J24: ='Historical Financials'!J23 -> -34.934 | K24: ='Historical Financials'!K23 -> -0.936 | L24: ='Historical Financials'!L23 -> -1.665 | M24: ='Historical Financials'!M23 -> -0.056 | N24: ='Historical Financials'!N23 -> -5.203 | O24: ='Historical Financials'!O23 -> 0.156 | ... T24: ='Historical Financials'!T23 -> 0 | V24: =SUM(H24:K24) -> -35.87 | W24: =SUM(I24:L24) -> -37.535 | X24: =SUM(J24:M24) -> -37.591 | Y24: =SUM(K24:N24) -> -7.86 | Z24: =SUM(L24:O24) -> -6.768 | AA24: =SUM(M24:P24) -> -4.848 | AB24: =SUM(N24:Q24) -> -4.852 | AC24: =SUM(O24:R24) -> 0.339 | ... AE24: =SUM(Q24:T24) -> -0.072 | AG24: =SUM(AE24/AA24)-1 -> -0.98514851
B25: Earning before Interest & Taxes (EBIT) | C25: =SUM(C18+SUM(C21:C24)) -> -866.048 | D25: =SUM(D18+SUM(D21:D24)) -> -1200.862 | E25: =SUM(E18+SUM(E21:E24)) -> -615.847 | F25: =SUM(F18+SUM(F21:F24)) -> -87.276 | H25: =SUM(H18+SUM(H21:H24)) -> -287.467 | I25: =SUM(I18+SUM(I21:I24)) -> -359.532 | J25: =SUM(J18+SUM(J21:J24)) -> -310.035 | K25: =SUM(K18+SUM(K21:K24)) -> -243.828 | L25: =SUM(L18+SUM(L21:L24)) -> -209.447 | M25: =SUM(M18+SUM(M21:M24)) -> -172.151 | N25: =SUM(N18+SUM(N21:N24)) -> -160.789 | O25: =SUM(O18+SUM(O21:O24)) -> -73.46 | ... T25: =SUM(T18+SUM(T21:T24)) -> 63.661 | V25: =SUM(V18+SUM(V21:V24)) -> -1200.862 | W25: =SUM(W18+SUM(W21:W24)) -> -1122.842 | X25: =SUM(X18+SUM(X21:X24)) -> -935.461 | Y25: =SUM(Y18+SUM(Y21:Y24)) -> -786.215 | Z25: =SUM(Z18+SUM(Z21:Z24)) -> -615.847 | AA25: =SUM(AA18+SUM(AA21:AA24)) -> -539.023 | AB25: =SUM(AB18+SUM(AB21:AB24)) -> -371.194 | AC25: =SUM(AC18+SUM(AC21:AC24)) -> -218.799 | ... AE25: =SUM(AE18+SUM(AE21:AE24)) -> 109.008 | AG25: =SUM(AE25/AA25)-1 -> -1.2022326
B26: Operating Margin (%) | C26: =C25/C10 -> -0.64185365 | D26: =D25/D10 -> -0.75621747 | E26: =E25/E10 -> -0.26510859 | F26: =F25/F10 -> -0.027067277 | H26: =H25/H10 -> -0.79493341 | I26: =I25/I10 -> -0.89982431 | J26: =J25/J10 -> -0.81378715 | K26: =K25/K10 -> -0.54691415 | L26: =L25/L10 -> -0.421807 | M26: =M25/M10 -> -0.29123344 | N26: =N25/N10 -> -0.2790715 | O26: =O25/O10 -> -0.11144064 | ... T26: =T25/T10 -> 0.068207946 | V26: =V25/V10 -> -0.75621747 | W26: =W25/W10 -> -0.65171327 | X26: =X25/X10 -> -0.48862917 | Y26: =Y25/Y10 -> -0.37267751 | Z26: =Z25/Z10 -> -0.26510859 | AA26: =AA25/AA10 -> -0.21348029 | AB26: =AB25/AB10 -> -0.13255972 | AC26: =AC25/AC10 -> -0.072758888 | ... AE26: =AE25/AE10 -> 0.031511869 | AG26: =SUM(AE26-AA26)*10000 -> 2449.9216
B28: (+) Depreciation and Amortization (D&A) | C28: ='Historical Financials'!C98 -> 52.722 | D28: ='Historical Financials'!D98 -> 134.634 | E28: ='Historical Financials'!E98 -> 169.044 | F28: ='Historical Financials'!F98 -> 225.076 | H28: ='Historical Financials'!H98 -> 20.882 | I28: ='Historical Financials'!I98 -> 23.004 | J28: ='Historical Financials'!J98 -> 47.469 | K28: ='Historical Financials'!K98 -> 43.279 | L28: ='Historical Financials'!L98 -> 40.131 | M28: ='Historical Financials'!M98 -> 26.512 | N28: ='Historical Financials'!N98 -> 37.012 | O28: ='Historical Financials'!O98 -> 65.389 | ... T28: ='Historical Financials'!T98 -> 65.329 | V28: =SUM(H28:K28) -> 134.634 | W28: =SUM(I28:L28) -> 153.883 | X28: =SUM(J28:M28) -> 157.391 | Y28: =SUM(K28:N28) -> 146.934 | Z28: =SUM(L28:O28) -> 169.044 | AA28: =SUM(M28:P28) -> 175.633 | AB28: =SUM(N28:Q28) -> 204.015 | AC28: =SUM(O28:R28) -> 226.47 | ... AE28: =SUM(Q28:T28) -> 243.685 | AG28: =SUM(AE28/AA28)-1 -> 0.38746705
B29: EBITDA | C29: =SUM(C25+SUM(C28:C28)) -> -813.326 | D29: =SUM(D25+SUM(D28:D28)) -> -1066.228 | E29: =SUM(E25+SUM(E28:E28)) -> -446.803 | F29: =SUM(F25+SUM(F28:F28)) -> 137.8 | H29: =SUM(H25+SUM(H28:H28)) -> -266.585 | I29: =SUM(I25+SUM(I28:I28)) -> -336.528 | J29: =SUM(J25+SUM(J28:J28)) -> -262.566 | K29: =SUM(K25+SUM(K28:K28)) -> -200.549 | L29: =SUM(L25+SUM(L28:L28)) -> -169.316 | M29: =SUM(M25+SUM(M28:M28)) -> -145.639 | N29: =SUM(N25+SUM(N28:N28)) -> -123.777 | O29: =SUM(O25+SUM(O28:O28)) -> -8.071 | ... T29: =SUM(T25+SUM(T28:T28)) -> 128.99 | V29: =SUM(V25+SUM(V28:V28)) -> -1066.228 | W29: =SUM(W25+SUM(W28:W28)) -> -968.959 | X29: =SUM(X25+SUM(X28:X28)) -> -778.07 | Y29: =SUM(Y25+SUM(Y28:Y28)) -> -639.281 | Z29: =SUM(Z25+SUM(Z28:Z28)) -> -446.803 | AA29: =SUM(AA25+SUM(AA28:AA28)) -> -363.39 | AB29: =SUM(AB25+SUM(AB28:AB28)) -> -167.179 | AC29: =SUM(AC25+SUM(AC28:AC28)) -> 7.671 | ... AE29: =SUM(AE25+SUM(AE28:AE28)) -> 352.693 | AG29: =SUM(AE29/AA29)-1 -> -1.9705633
B30: EBITDA Margin (%) | C30: =C29/C10 -> -0.60277983 | D30: =D29/D10 -> -0.67143455 | E30: =E29/E10 -> -0.19233887 | F30: =F29/F10 -> 0.042736501 | H30: =H29/H10 -> -0.73718835 | I30: =I29/I10 -> -0.84225069 | J30: =J29/J10 -> -0.6891894 | K30: =K29/K10 -> -0.44983794 | L30: =L29/L10 -> -0.34098686 | M30: =M29/M10 -> -0.24638223 | N30: =N29/N10 -> -0.21483207 | O30: =O29/O10 -> -0.012243907 | ... T30: =T29/T10 -> 0.13820303 | V30: =V29/V10 -> -0.67143455 | W30: =W29/W10 -> -0.56239741 | X30: =X29/X10 -> -0.40641748 | Y30: =Y29/Y10 -> -0.30302862 | Z30: =Z29/Z10 -> -0.19233887 | AA30: =AA29/AA10 -> -0.14392076 | AB30: =AB29/AB10 -> -0.059702479 | AC30: =AC29/AC10 -> 0.0025508957 | ... AE30: =AE29/AE10 -> 0.10195596 | AG30: =SUM(AE30-AA30)*10000 -> 2458.7673
B32: (+) Stock-Based Compensation (SBC) | C32: ='Historical Financials'!C96 -> 390.983 | D32: ='Historical Financials'!D96 -> 451.709 | E32: ='Historical Financials'!E96 -> 344.511 | F32: ='Historical Financials'!F96 -> 321.433 | H32: ='Historical Financials'!H96 -> 119.808 | I32: ='Historical Financials'!I96 -> 121.775 | J32: ='Historical Financials'!J96 -> 106.789 | K32: ='Historical Financials'!K96 -> 103.337 | L32: ='Historical Financials'!L96 -> 112.359 | M32: ='Historical Financials'!M96 -> 90.164 | N32: ='Historical Financials'!N96 -> 77.075 | O32: ='Historical Financials'!O96 -> 64.913 | ... T32: ='Historical Financials'!T96 -> 85.853 | V32: =SUM(H32:K32) -> 451.709 | W32: =SUM(I32:L32) -> 444.26 | X32: =SUM(J32:M32) -> 412.649 | Y32: =SUM(K32:N32) -> 382.935 | Z32: =SUM(L32:O32) -> 344.511 | AA32: =SUM(M32:P32) -> 326.385 | AB32: =SUM(N32:Q32) -> 322.319 | AC32: =SUM(O32:R32) -> 320.851 | ... AE32: =SUM(Q32:T32) -> 313.053 | AG32: =SUM(AE32/AA32)-1 -> -0.040847465
B33: Adj. EBITDA | C33: =+SUM(C29+SUM(C32:C32)) -> -422.343 | D33: =+SUM(D29+SUM(D32:D32)) -> -614.519 | E33: =+SUM(E29+SUM(E32:E32)) -> -102.292 | F33: =+SUM(F29+SUM(F32:F32)) -> 459.233 | H33: =+SUM(H29+SUM(H32:H32)) -> -146.777 | I33: =+SUM(I29+SUM(I32:I32)) -> -214.753 | J33: =+SUM(J29+SUM(J32:J32)) -> -155.777 | K33: =+SUM(K29+SUM(K32:K32)) -> -97.212 | L33: =+SUM(L29+SUM(L32:L32)) -> -56.957 | M33: =+SUM(M29+SUM(M32:M32)) -> -55.475 | N33: =+SUM(N29+SUM(N32:N32)) -> -46.702 | O33: =+SUM(O29+SUM(O32:O32)) -> 56.842 | ... T33: =+SUM(T29+SUM(T32:T32)) -> 214.843 | V33: =+SUM(V29+SUM(V32:V32)) -> -614.519 | W33: =+SUM(W29+SUM(W32:W32)) -> -524.699 | X33: =+SUM(X29+SUM(X32:X32)) -> -365.421 | Y33: =+SUM(Y29+SUM(Y32:Y32)) -> -256.346 | Z33: =+SUM(Z29+SUM(Z32:Z32)) -> -102.292 | AA33: =+SUM(AA29+SUM(AA32:AA32)) -> -37.005 | AB33: =+SUM(AB29+SUM(AB32:AB32)) -> 155.14 | AC33: =+SUM(AC29+SUM(AC32:AC32)) -> 328.522 | ... AE33: =+SUM(AE29+SUM(AE32:AE32)) -> 665.746 | AG33: =SUM(AE33/AA33)-1 -> -18.990704
B34: Adj. EBITDA Margin (%) | C34: =C33/C10 -> -0.31301082 | D34: =D33/D10 -> -0.38698036 | E34: =E33/E10 -> -0.044034457 | F34: =F33/F10 -> 0.14242389 | H34: =H33/H10 -> -0.40588291 | I34: =I33/I10 -> -0.53747641 | J34: =J33/J10 -> -0.40888713 | K34: =K33/K10 -> -0.21804968 | L34: =L33/L10 -> -0.11470616 | M34: =M33/M10 -> -0.093848861 | N34: =N33/N10 -> -0.081057767 | O34: =O33/O10 -> 0.086230724 | ... T34: =T33/T10 -> 0.23018802 | V34: =V33/V10 -> -0.38698036 | W34: =W33/W10 -> -0.30454267 | X34: =X33/X10 -> -0.19087419 | Y34: =Y33/Y10 -> -0.12151178 | Z34: =Z33/Z10 -> -0.044034457 | AA34: =AA33/AA10 -> -0.014655846 | AB34: =AB33/AB10 -> 0.055403146 | AC34: =AC33/AC10 -> 0.10924591 | ... AE34: =AE33/AE10 -> 0.19245285 | AG34: =SUM(AE34-AA34)*10000 -> 2071.087
B36: (-) Capital Expenditures | C36: ='Historical Financials'!C116 -> -86.29 | D36: ='Historical Financials'!D116 -> -120.775 | E36: ='Historical Financials'!E116 -> -159.296 | F36: ='Historical Financials'!F116 -> -192.189 | H36: ='Historical Financials'!H116 -> -31.151 | I36: ='Historical Financials'!I116 -> -34.25 | J36: ='Historical Financials'!J116 -> -30.516 | K36: ='Historical Financials'!K116 -> -24.858 | L36: ='Historical Financials'!L116 -> -35.817 | M36: ='Historical Financials'!M116 -> -38.747 | N36: ='Historical Financials'!N116 -> -46.476 | O36: ='Historical Financials'!O116 -> -38.256 | ... T36: ='Historical Financials'!T116 -> -54.365 | V36: =SUM(H36:K36) -> -120.775 | W36: =SUM(I36:L36) -> -125.441 | X36: =SUM(J36:M36) -> -129.938 | Y36: =SUM(K36:N36) -> -145.898 | Z36: =SUM(L36:O36) -> -159.296 | AA36: =SUM(M36:P36) -> -167.631 | AB36: =SUM(N36:Q36) -> -172.789 | AC36: =SUM(O36:R36) -> -179.325 | ... AE36: =SUM(Q36:T36) -> -202.402 | AG36: =SUM(AE36/AA36)-1 -> 0.20742583
B37: (-) Cash Taxes | C37: =-'Historical Financials'!C143 -> 0 | D37: =-'Historical Financials'!D143 -> 0 | E37: =-'Historical Financials'!E143 -> 0 | F37: =-'Historical Financials'!F143 -> 0 | H37: =-'Historical Financials'!H143 -> 0 | I37: =-'Historical Financials'!I143 -> 0 | J37: =-'Historical Financials'!J143 -> 0 | K37: =-'Historical Financials'!K143 -> 0 | L37: =-'Historical Financials'!L143 -> 0 | M37: =-'Historical Financials'!M143 -> 0 | N37: =-'Historical Financials'!N143 -> 0 | O37: =-'Historical Financials'!O143 -> 0 | ... T37: =-'Historical Financials'!T143 -> 0 | V37: =SUM(H37:K37) -> 0 | W37: =SUM(I37:L37) -> 0 | X37: =SUM(J37:M37) -> 0 | Y37: =SUM(K37:N37) -> 0 | Z37: =SUM(L37:O37) -> 0 | AA37: =SUM(M37:P37) -> 0 | AB37: =SUM(N37:Q37) -> 0 | AC37: =SUM(O37:R37) -> 0 | ... AE37: =SUM(Q37:T37) -> 0 | AG37: =SUM(AE37/AA37)-1 -> #DIV/0!
B38: (-) Cash Interest | C38: =-'Historical Financials'!C142 -> 0 | D38: =-'Historical Financials'!D142 -> 0 | E38: =-'Historical Financials'!E142 -> 0 | F38: =-'Historical Financials'!F142 -> 0 | H38: =-'Historical Financials'!H142 -> 0 | I38: =-'Historical Financials'!I142 -> 0 | J38: =-'Historical Financials'!J142 -> 0 | K38: =-'Historical Financials'!K142 -> 0 | L38: =-'Historical Financials'!L142 -> 0 | M38: =-'Historical Financials'!M142 -> 0 | N38: =-'Historical Financials'!N142 -> 0 | O38: =-'Historical Financials'!O142 -> 0 | ... T38: =-'Historical Financials'!T142 -> 0 | V38: =SUM(H38:K38) -> 0 | W38: =SUM(I38:L38) -> 0 | X38: =SUM(J38:M38) -> 0 | Y38: =SUM(K38:N38) -> 0 | Z38: =SUM(L38:O38) -> 0 | AA38: =SUM(M38:P38) -> 0 | AB38: =SUM(N38:Q38) -> 0 | AC38: =SUM(O38:R38) -> 0 | ... AE38: =SUM(Q38:T38) -> 0 | AG38: =SUM(AE38/AA38)-1 -> #DIV/0!
B39: (-) Mandatory Outflows | C39: =-'Historical Financials'!C143 -> 0 | D39: =-'Historical Financials'!D143 -> 0 | E39: =-'Historical Financials'!E143 -> 0 | F39: =-'Historical Financials'!F143 -> 0 | H39: =-'Historical Financials'!H143 -> 0 | I39: =-'Historical Financials'!I143 -> 0 | J39: =-'Historical Financials'!J143 -> 0 | K39: =-'Historical Financials'!K143 -> 0 | L39: =-'Historical Financials'!L143 -> 0 | M39: =-'Historical Financials'!M143 -> 0 | N39: =-'Historical Financials'!N143 -> 0 | O39: =-'Historical Financials'!O143 -> 0 | ... T39: =-'Historical Financials'!T143 -> 0 | V39: =SUM(H39:K39) -> 0 | W39: =SUM(I39:L39) -> 0 | X39: =SUM(J39:M39) -> 0 | Y39: =SUM(K39:N39) -> 0 | Z39: =SUM(L39:O39) -> 0 | AA39: =SUM(M39:P39) -> 0 | AB39: =SUM(N39:Q39) -> 0 | AC39: =SUM(O39:R39) -> 0 | ... AE39: =SUM(Q39:T39) -> 0 | AG39: =SUM(AE39/AA39)-1 -> #DIV/0!
B40: (+/-) Changes in NWC | V40: =SUM(H40:K40) -> 0 | W40: =SUM(I40:L40) -> 0 | X40: =SUM(J40:M40) -> 0 | Y40: =SUM(K40:N40) -> 0 | Z40: =SUM(L40:O40) -> 0 | AA40: =SUM(M40:P40) -> 0 | AB40: =SUM(N40:Q40) -> 0 | AC40: =SUM(O40:R40) -> 0 | ... AE40: =SUM(Q40:T40) -> 0 | AG40: =SUM(AE40/AA40)-1 -> #DIV/0!
B41: Discretionary Cash-Flows | C41: =SUM(C33+SUM(C36:C40)) -> -508.633 | D41: =SUM(D33+SUM(D36:D40)) -> -735.294 | E41: =SUM(E33+SUM(E36:E40)) -> -261.588 | F41: =SUM(F33+SUM(F36:F40)) -> 267.044 | H41: =SUM(H33+SUM(H36:H40)) -> -177.928 | I41: =SUM(I33+SUM(I36:I40)) -> -249.003 | J41: =SUM(J33+SUM(J36:J40)) -> -186.293 | K41: =SUM(K33+SUM(K36:K40)) -> -122.07 | L41: =SUM(L33+SUM(L36:L40)) -> -92.774 | M41: =SUM(M33+SUM(M36:M40)) -> -94.222 | N41: =SUM(N33+SUM(N36:N40)) -> -93.178 | O41: =SUM(O33+SUM(O36:O40)) -> 18.586 | ... T41: =SUM(T33+SUM(T36:T40)) -> 160.478 | V41: =SUM(V33+SUM(V36:V40)) -> -735.294 | W41: =SUM(W33+SUM(W36:W40)) -> -650.14 | X41: =SUM(X33+SUM(X36:X40)) -> -495.359 | Y41: =SUM(Y33+SUM(Y36:Y40)) -> -402.244 | Z41: =SUM(Z33+SUM(Z36:Z40)) -> -261.588 | AA41: =SUM(AA33+SUM(AA36:AA40)) -> -204.636 | AB41: =SUM(AB33+SUM(AB36:AB40)) -> -17.649 | AC41: =SUM(AC33+SUM(AC36:AC40)) -> 149.197 | ... AE41: =SUM(AE33+SUM(AE36:AE40)) -> 463.344 | AG41: =SUM(AE41/AA41)-1 -> -3.264235
B43: (+/-) XXX | V43: =SUM(H43:K43) -> 0 | W43: =SUM(I43:L43) -> 0 | X43: =SUM(J43:M43) -> 0 | Y43: =SUM(K43:N43) -> 0 | Z43: =SUM(L43:O43) -> 0 | AA43: =SUM(M43:P43) -> 0 | AB43: =SUM(N43:Q43) -> 0 | AC43: =SUM(O43:R43) -> 0 | ... AE43: =SUM(Q43:T43) -> 0
B44: (+/-) XXX | V44: =SUM(H44:K44) -> 0 | W44: =SUM(I44:L44) -> 0 | X44: =SUM(J44:M44) -> 0 | Y44: =SUM(K44:N44) -> 0 | Z44: =SUM(L44:O44) -> 0 | AA44: =SUM(M44:P44) -> 0 | AB44: =SUM(N44:Q44) -> 0 | AC44: =SUM(O44:R44) -> 0 | ... AE44: =SUM(Q44:T44) -> 0
B45: (+/-) XXX | V45: =SUM(H45:K45) -> 0 | W45: =SUM(I45:L45) -> 0 | X45: =SUM(J45:M45) -> 0 | Y45: =SUM(K45:N45) -> 0 | Z45: =SUM(L45:O45) -> 0 | AA45: =SUM(M45:P45) -> 0 | AB45: =SUM(N45:Q45) -> 0 | AC45: =SUM(O45:R45) -> 0 | ... AE45: =SUM(Q45:T45) -> 0
B46: (+/-) XXX | V46: =SUM(H46:K46) -> 0 | W46: =SUM(I46:L46) -> 0 | X46: =SUM(J46:M46) -> 0 | Y46: =SUM(K46:N46) -> 0 | Z46: =SUM(L46:O46) -> 0 | AA46: =SUM(M46:P46) -> 0 | AB46: =SUM(N46:Q46) -> 0 | AC46: =SUM(O46:R46) -> 0 | ... AE46: =SUM(Q46:T46) -> 0
B47: (+/-) XXX | V47: =SUM(H47:K47) -> 0 | W47: =SUM(I47:L47) -> 0 | X47: =SUM(J47:M47) -> 0 | Y47: =SUM(K47:N47) -> 0 | Z47: =SUM(L47:O47) -> 0 | AA47: =SUM(M47:P47) -> 0 | AB47: =SUM(N47:Q47) -> 0 | AC47: =SUM(O47:R47) -> 0 | ... AE47: =SUM(Q47:T47) -> 0
B48: (+/-) Other | D48: =SUM(D53:D54)-SUM(C53:C54)-SUM(D41:D47) -> 444.431 | E48: =SUM(E53:E54)-SUM(D53:D54)-SUM(E41:E47) -> 297.043 | F48: =SUM(F53:F54)-SUM(E53:E54)-SUM(F41:F47) -> 193.98 | H48: =SUM(H53:H54)-SUM(C53:C54)-SUM(H41:H47) -> 540.659 | I48: =SUM(I53:I54)-SUM(H53:H54)-SUM(I41:I47) -> 200.258 | J48: =SUM(J53:J54)-SUM(I53:I54)-SUM(J41:J47) -> -297.008 | K48: =SUM(K53:K54)-SUM(J53:J54)-SUM(K41:K47) -> 0.522 | L48: =SUM(L53:L54)-SUM(K53:K54)-SUM(L41:L47) -> 321.322 | M48: =SUM(M53:M54)-SUM(L53:L54)-SUM(M41:M47) -> 53.708 | N48: =SUM(N53:N54)-SUM(M53:M54)-SUM(N41:N47) -> 264.891 | O48: =SUM(O53:O54)-SUM(N53:N54)-SUM(O41:O47) -> -342.878 | P48: =SUM(P53:P54)-SUM(O53:O54)-SUM(P41:P47) -> 125.045 | ... T48: =SUM(T53:T54)-SUM(S53:S54)-SUM(T41:T47) -> 180.709 | V48: =SUM(H48:K48) -> 444.431 | W48: =SUM(I48:L48) -> 225.094 | X48: =SUM(J48:M48) -> 78.544 | Y48: =SUM(K48:N48) -> 640.443 | Z48: =SUM(L48:O48) -> 297.043 | AA48: =SUM(M48:P48) -> 100.766 | AB48: =SUM(N48:Q48) -> 306.828 | AC48: =SUM(O48:R48) -> -32.929 | ... AE48: =SUM(Q48:T48) -> 249.644
B49: Free-Cash Flows | C49: =SUM(C41+SUM(C43:C48)) -> -508.633 | D49: =SUM(D41+SUM(D43:D48)) -> -290.863 | E49: =SUM(E41+SUM(E43:E48)) -> 35.455 | F49: =SUM(F41+SUM(F43:F48)) -> 461.024 | H49: =SUM(H41+SUM(H43:H48)) -> 362.731 | I49: =SUM(I41+SUM(I43:I48)) -> -48.745 | J49: =SUM(J41+SUM(J43:J48)) -> -483.301 | K49: =SUM(K41+SUM(K43:K48)) -> -121.548 | L49: =SUM(L41+SUM(L43:L48)) -> 228.548 | M49: =SUM(M41+SUM(M43:M48)) -> -40.514 | N49: =SUM(N41+SUM(N43:N48)) -> 171.713 | O49: =SUM(O41+SUM(O43:O48)) -> -324.292 | ... T49: =SUM(T41+SUM(T43:T48)) -> 341.187 | V49: =SUM(V41+SUM(V43:V48)) -> -290.863 | W49: =SUM(W41+SUM(W43:W48)) -> -425.046 | X49: =SUM(X41+SUM(X43:X48)) -> -416.815 | Y49: =SUM(Y41+SUM(Y43:Y48)) -> 238.199 | Z49: =SUM(Z41+SUM(Z43:Z48)) -> 35.455 | AA49: =SUM(AA41+SUM(AA43:AA48)) -> -103.87 | AB49: =SUM(AB41+SUM(AB43:AB48)) -> 289.179 | AC49: =SUM(AC41+SUM(AC43:AC48)) -> 116.268 | ... AE49: =SUM(AE41+SUM(AE43:AE48)) -> 712.988
B51: Capitalization
B53: Cash & Cash Equivelants | C53: ='Historical Financials'!C47 -> 1255.171 | D53: ='Historical Financials'!D47 -> 892.027 | E53: ='Historical Financials'!E47 -> 1013.106 | F53: ='Historical Financials'!F47 -> 1354.455 | H53: ='Historical Financials'!H47 -> 1530.132 | I53: ='Historical Financials'!I47 -> 1440.333 | J53: ='Historical Financials'!J47 -> 972.477 | K53: ='Historical Financials'!K47 -> 892.027 | L53: ='Historical Financials'!L47 -> 1079.261 | M53: ='Historical Financials'!M47 -> 1036.719 | N53: ='Historical Financials'!N47 -> 1272.76 | O53: ='Historical Financials'!O47 -> 1013.106 | ... T53: ='Historical Financials'!T47 -> 1428.848 | V53: =K53 -> 892.027 | W53: =L53 -> 1079.261 | X53: =M53 -> 1036.719 | Y53: =N53 -> 1272.76 | Z53: =O53 -> 1013.106 | AA53: =P53 -> 1046.16 | AB53: =Q53 -> 1200.381 | AC53: =R53 -> 1351.148 | ... AE53: =T53 -> 1428.848
B54: Restricted cash | C54: ='Historical Financials'!C48 -> 295.636 | D54: ='Historical Financials'!D48 -> 367.917 | E54: ='Historical Financials'!E48 -> 282.293 | F54: ='Historical Financials'!F48 -> 401.968 | H54: ='Historical Financials'!H48 -> 383.406 | I54: ='Historical Financials'!I48 -> 424.46 | J54: ='Historical Financials'!J48 -> 409.015 | K54: ='Historical Financials'!K48 -> 367.917 | L54: ='Historical Financials'!L48 -> 409.231 | M54: ='Historical Financials'!M48 -> 411.259 | N54: ='Historical Financials'!N48 -> 346.931 | O54: ='Historical Financials'!O48 -> 282.293 | ... T54: ='Historical Financials'!T48 -> 668.762 | V54: =K54 -> 367.917 | W54: =L54 -> 409.231 | X54: =M54 -> 411.259 | Y54: =N54 -> 346.931 | Z54: =O54 -> 282.293 | AA54: =P54 -> 338.462 | AB54: =Q54 -> 536.776 | AC54: =R54 -> 384.811 | ... AE54: =T54 -> 668.762
B55: Securities available for sale at fair value | C55: ='Historical Financials'!C49 -> 1595.373 | D55: ='Historical Financials'!D49 -> 1174.653 | E55: ='Historical Financials'!E49 -> 1131.628 | F55: ='Historical Financials'!F49 -> 871.425 | H55: ='Historical Financials'!H49 -> 1237.291 | I55: ='Historical Financials'!I49 -> 914.923 | J55: ='Historical Financials'!J49 -> 1059.031 | K55: ='Historical Financials'!K49 -> 1174.653 | L55: ='Historical Financials'!L49 -> 1021.63 | M55: ='Historical Financials'!M49 -> 914.069 | N55: ='Historical Financials'!N49 -> 781.402 | O55: ='Historical Financials'!O49 -> 1131.628 | ... T55: ='Historical Financials'!T49 -> 812.442 | V55: =K55 -> 1174.653 | W55: =L55 -> 1021.63 | X55: =M55 -> 914.069 | Y55: =N55 -> 781.402 | Z55: =O55 -> 1131.628 | AA55: =P55 -> 1073.685 | AB55: =Q55 -> 666.684 | AC55: =R55 -> 780.17 | ... AE55: =T55 -> 812.442
B56: Total Liquidity | C56: =SUM(C53:C55) -> 3146.18 | D56: =SUM(D53:D55) -> 2434.597 | E56: =SUM(E53:E55) -> 2427.027 | F56: =SUM(F53:F55) -> 2627.848 | H56: =SUM(H53:H55) -> 3150.829 | I56: =SUM(I53:I55) -> 2779.716 | J56: =SUM(J53:J55) -> 2440.523 | K56: =SUM(K53:K55) -> 2434.597 | L56: =SUM(L53:L55) -> 2510.122 | M56: =SUM(M53:M55) -> 2362.047 | N56: =SUM(N53:N55) -> 2401.093 | O56: =SUM(O53:O55) -> 2427.027 | ... T56: =SUM(T53:T55) -> 2910.052 | V56: =SUM(V53:V55) -> 2434.597 | W56: =SUM(W53:W55) -> 2510.122 | X56: =SUM(X53:X55) -> 2362.047 | Y56: =SUM(Y53:Y55) -> 2401.093 | Z56: =SUM(Z53:Z55) -> 2427.027 | AA56: =SUM(AA53:AA55) -> 2458.307 | AB56: =SUM(AB53:AB55) -> 2403.841 | AC56: =SUM(AC53:AC55) -> 2516.129 | ... AE56: =SUM(AE53:AE55) -> 2910.052
B58: Balance Sheet Metrics:
B59: Accounts receivable, net | C59: ='Historical Financials'!C52 -> 142.052 | D59: ='Historical Financials'!D52 -> 199.085 | E59: ='Historical Financials'!E52 -> 353.028 | F59: ='Historical Financials'!F52 -> 426.177 | H59: ='Historical Financials'!H52 -> 147.757 | I59: ='Historical Financials'!I52 -> 201.622 | J59: ='Historical Financials'!J52 -> 135.816 | K59: ='Historical Financials'!K52 -> 199.085 | L59: ='Historical Financials'!L52 -> 236.234 | M59: ='Historical Financials'!M52 -> 307.286 | N59: ='Historical Financials'!N52 -> 293.388 | O59: ='Historical Financials'!O52 -> 353.028 | ... T59: ='Historical Financials'!T52 -> 283.726 | V59: =K59 -> 199.085 | W59: =L59 -> 236.234 | X59: =M59 -> 307.286 | Y59: =N59 -> 293.388 | Z59: =O59 -> 353.028 | AA59: =P59 -> 308.394 | AB59: =Q59 -> 203.626 | AC59: =R59 -> 220.279 | ... AE59: =T59 -> 283.726
B60: Property, equipment and software, net | C60: ='Historical Financials'!C54 -> 171.482 | D60: ='Historical Financials'!D54 -> 290.135 | E60: ='Historical Financials'!E54 -> 427.686 | F60: ='Historical Financials'!F54 -> 572.637 | H60: ='Historical Financials'!H54 -> 208.46 | I60: ='Historical Financials'!I54 -> 248.939 | J60: ='Historical Financials'!J54 -> 277.156 | K60: ='Historical Financials'!K54 -> 290.135 | L60: ='Historical Financials'!L54 -> 338.749 | M60: ='Historical Financials'!M54 -> 369.854 | N60: ='Historical Financials'!N54 -> 401.535 | O60: ='Historical Financials'!O54 -> 427.686 | ... T60: ='Historical Financials'!T54 -> 613.938 | V60: =K60 -> 290.135 | W60: =L60 -> 338.749 | X60: =M60 -> 369.854 | Y60: =N60 -> 401.535 | Z60: =O60 -> 427.686 | AA60: =P60 -> 473.019 | AB60: =Q60 -> 506.334 | AC60: =R60 -> 543.327 | ... AE60: =T60 -> 613.938
B61: Total Assets | C61: ='Historical Financials'!C56 -> 6973.792 | D61: ='Historical Financials'!D56 -> 8155.615 | E61: ='Historical Financials'!E56 -> 9519.619 | F61: ='Historical Financials'!F56 -> 11154.928 | H61: ='Historical Financials'!H56 -> 7165.06 | I61: ='Historical Financials'!I56 -> 7804.751 | J61: ='Historical Financials'!J56 -> 7507.849 | K61: ='Historical Financials'!K56 -> 8155.615 | L61: ='Historical Financials'!L56 -> 8407.149 | M61: ='Historical Financials'!M56 -> 9064.989 | N61: ='Historical Financials'!N56 -> 9201.426 | O61: ='Historical Financials'!O56 -> 9519.619 | ... T61: ='Historical Financials'!T56 -> 11478.566 | V61: =K61 -> 8155.615 | W61: =L61 -> 8407.149 | X61: =M61 -> 9064.989 | Y61: =N61 -> 9201.426 | Z61: =O61 -> 9519.619 | AA61: =P61 -> 10139.156 | AB61: =Q61 -> 10481.077 | AC61: =R61 -> 10436.187 | ... AE61: =T61 -> 11478.566
B62: Accounts payable | C62: ='Historical Financials'!C59 -> 33.072 | D62: ='Historical Financials'!D59 -> 28.602 | E62: ='Historical Financials'!E59 -> 41.019 | F62: ='Historical Financials'!F59 -> 82.82 | H62: ='Historical Financials'!H59 -> 34.534 | I62: ='Historical Financials'!I59 -> 28.974 | J62: ='Historical Financials'!J59 -> 30.022 | K62: ='Historical Financials'!K59 -> 28.602 | L62: ='Historical Financials'!L59 -> 27.345 | M62: ='Historical Financials'!M59 -> 59.8 | N62: ='Historical Financials'!N59 -> 35.224 | O62: ='Historical Financials'!O59 -> 41.019 | ... T62: ='Historical Financials'!T59 -> 58.019 | V62: =K62 -> 28.602 | W62: =L62 -> 27.345 | X62: =M62 -> 59.8 | Y62: =N62 -> 35.224 | Z62: =O62 -> 41.019 | AA62: =P62 -> 57.561 | AB62: =Q62 -> 50.626 | AC62: =R62 -> 41.057 | ... AE62: =T62 -> 58.019
B63: Payable to third-party | C63: ='Historical Financials'!C60 -> 71.383 | D63: ='Historical Financials'!D60 -> 53.852 | E63: ='Historical Financials'!E60 -> 159.643 | F63: ='Historical Financials'!F60 -> 211.7 | H63: ='Historical Financials'!H60 -> 90.811 | I63: ='Historical Financials'!I60 -> 127.378 | J63: ='Historical Financials'!J60 -> 44.187 | K63: ='Historical Financials'!K60 -> 53.852 | L63: ='Historical Financials'!L60 -> 109.498 | M63: ='Historical Financials'!M60 -> 134.567 | N63: ='Historical Financials'!N60 -> 129.73 | O63: ='Historical Financials'!O60 -> 159.643 | ... T63: ='Historical Financials'!T60 -> 193.79 | V63: =K63 -> 53.852 | W63: =L63 -> 109.498 | X63: =M63 -> 134.567 | Y63: =N63 -> 129.73 | Z63: =O63 -> 159.643 | AA63: =P63 -> 152.035 | AB63: =Q63 -> 157.245 | AC63: =R63 -> 176.996 | ... AE63: =T63 -> 193.79
B64: Funding debt | C64: ='Historical Financials'!C65 -> 672.577 | D64: ='Historical Financials'!D65 -> 1764.812 | E64: ='Historical Financials'!E65 -> 1836.909 | F64: ='Historical Financials'!F65 -> 1622.808 | H64: ='Historical Financials'!H65 -> 792.637 | I64: ='Historical Financials'!I65 -> 1882.67 | J64: ='Historical Financials'!J65 -> 1514.12 | K64: ='Historical Financials'!K65 -> 1764.812 | L64: ='Historical Financials'!L65 -> 1709.751 | M64: ='Historical Financials'!M65 -> 1906.672 | N64: ='Historical Financials'!N65 -> 1613.272 | O64: ='Historical Financials'!O65 -> 1836.909 | ... T64: ='Historical Financials'!T65 -> 1777.906 | V64: =K64 -> 1764.812 | W64: =L64 -> 1709.751 | X64: =M64 -> 1906.672 | Y64: =N64 -> 1613.272 | Z64: =O64 -> 1836.909 | AA64: =P64 -> 1744.04 | AB64: =Q64 -> 2166.806 | AC64: =R64 -> 1908.693 | ... AE64: =T64 -> 1777.906
B65: Total Liabilities | C65: ='Historical Financials'!C66 -> 4355.537 | D65: ='Historical Financials'!D66 -> 5621.432 | E65: ='Historical Financials'!E66 -> 6787.63 | F65: ='Historical Financials'!F66 -> 8085.92 | H65: ='Historical Financials'!H66 -> 4601.622 | I65: ='Historical Financials'!I66 -> 5294.603 | J65: ='Historical Financials'!J66 -> 4996.713 | K65: ='Historical Financials'!K66 -> 5621.432 | L65: ='Historical Financials'!L66 -> 5840.349 | M65: ='Historical Financials'!M66 -> 6430.1 | N65: ='Historical Financials'!N66 -> 6577.966 | O65: ='Historical Financials'!O66 -> 6787.63 | ... T65: ='Historical Financials'!T66 -> 8179.681 | V65: =K65 -> 5621.432 | W65: =L65 -> 5840.349 | X65: =M65 -> 6430.1 | Y65: =N65 -> 6577.966 | Z65: =O65 -> 6787.63 | AA65: =P65 -> 7303.587 | AB65: =Q65 -> 7695.537 | AC65: =R65 -> 7561.272 | ... AE65: =T65 -> 8179.681
B67: Summary Debt:
B68: Aggregate Debt | C68: ='Historical Financials'!C63+'Historical Financials'!C64+'Historical Financials'!C65 -> 4006.825 | D68: ='Historical Financials'!D63+'Historical Financials'!D64+'Historical Financials'!D65 -> 5344.597 | E68: ='Historical Financials'!E63+'Historical Financials'!E64+'Historical Financials'!E65 -> 6415.212 | F68: ='Historical Financials'!F63+'Historical Financials'!F64+'Historical Financials'!F65 -> 7609.663 | H68: ='Historical Financials'!H63+'Historical Financials'!H64+'Historical Financials'!H65 -> 4221.173 | I68: ='Historical Financials'!I63+'Historical Financials'!I64+'Historical Financials'!I65 -> 4905.661 | J68: ='Historical Financials'!J63+'Historical Financials'!J64+'Historical Financials'!J65 -> 4716.318 | K68: ='Historical Financials'!K63+'Historical Financials'!K64+'Historical Financials'!K65 -> 5344.597 | L68: ='Historical Financials'!L63+'Historical Financials'!L64+'Historical Financials'!L65 -> 5523.589 | M68: ='Historical Financials'!M63+'Historical Financials'!M64+'Historical Financials'!M65 -> 6063.28 | N68: ='Historical Financials'!N63+'Historical Financials'!N64+'Historical Financials'!N65 -> 6240.034 | O68: ='Historical Financials'!O63+'Historical Financials'!O64+'Historical Financials'!O65 -> 6415.212 | ... T68: ='Historical Financials'!T63+'Historical Financials'!T64+'Historical Financials'!T65 -> 7736.393 | V68: =K68 -> 5344.597 | W68: =L68 -> 5523.589 | X68: =M68 -> 6063.28 | Y68: =N68 -> 6240.034 | Z68: =O68 -> 6415.212 | AA68: =P68 -> 6932.043 | AB68: =Q68 -> 7306.741 | AC68: =R68 -> 7145.646 | ... AE68: =T68 -> 7736.393
B70: Convertible debt | C70: ='Historical Financials'!C63 -> 1706.668 | D70: ='Historical Financials'!D63 -> 1414.208 | E70: ='Historical Financials'!E63 -> 1341.43 | F70: ='Historical Financials'!F63 -> 1153 | H70: ='Historical Financials'!H63 -> 1707.724 | I70: ='Historical Financials'!I63 -> 1708.779 | J70: ='Historical Financials'!J63 -> 1413.345 | K70: ='Historical Financials'!K63 -> 1414.208 | L70: ='Historical Financials'!L63 -> 1415.08 | M70: ='Historical Financials'!M63 -> 1415.952 | N70: ='Historical Financials'!N63 -> 1385.891 | O70: ='Historical Financials'!O63 -> 1341.43 | ... T70: ='Historical Financials'!T63 -> 1127.668 | V70: =K70 -> 1414.208 | W70: =L70 -> 1415.08 | X70: =M70 -> 1415.952 | Y70: =N70 -> 1385.891 | Z70: =O70 -> 1341.43 | AA70: =P70 -> 1202.519 | AB70: =Q70 -> 1151.048 | AC70: =R70 -> 1152.019 | ... AE70: =T70 -> 1127.668
B71: Notes issued by securitization trusts | C71: ='Historical Financials'!C64 -> 1627.58 | D71: ='Historical Financials'!D64 -> 2165.577 | E71: ='Historical Financials'!E64 -> 3236.873 | F71: ='Historical Financials'!F64 -> 4833.855 | H71: ='Historical Financials'!H64 -> 1720.812 | I71: ='Historical Financials'!I64 -> 1314.212 | J71: ='Historical Financials'!J64 -> 1788.853 | K71: ='Historical Financials'!K64 -> 2165.577 | L71: ='Historical Financials'!L64 -> 2398.758 | M71: ='Historical Financials'!M64 -> 2740.656 | N71: ='Historical Financials'!N64 -> 3240.871 | O71: ='Historical Financials'!O64 -> 3236.873 | ... T71: ='Historical Financials'!T64 -> 4830.819 | V71: =K71 -> 2165.577 | W71: =L71 -> 2398.758 | X71: =M71 -> 2740.656 | Y71: =N71 -> 3240.871 | Z71: =O71 -> 3236.873 | AA71: =P71 -> 3985.484 | AB71: =Q71 -> 3988.887 | AC71: =R71 -> 4084.934 | ... AE71: =T71 -> 4830.819
B72: Funding debt | C72: ='Historical Financials'!C65 -> 672.577 | D72: ='Historical Financials'!D65 -> 1764.812 | E72: ='Historical Financials'!E65 -> 1836.909 | F72: ='Historical Financials'!F65 -> 1622.808 | H72: ='Historical Financials'!H65 -> 792.637 | I72: ='Historical Financials'!I65 -> 1882.67 | J72: ='Historical Financials'!J65 -> 1514.12 | K72: ='Historical Financials'!K65 -> 1764.812 | L72: ='Historical Financials'!L65 -> 1709.751 | M72: ='Historical Financials'!M65 -> 1906.672 | N72: ='Historical Financials'!N65 -> 1613.272 | O72: ='Historical Financials'!O65 -> 1836.909 | ... T72: ='Historical Financials'!T65 -> 1777.906 | V72: =K72 -> 1764.812 | W72: =L72 -> 1709.751 | X72: =M72 -> 1906.672 | Y72: =N72 -> 1613.272 | Z72: =O72 -> 1836.909 | AA72: =P72 -> 1744.04 | AB72: =Q72 -> 2166.806 | AC72: =R72 -> 1908.693 | ... AE72: =T72 -> 1777.906
B73: Total Debt | C73: =SUM(C70:C72) -> 4006.825 | D73: =SUM(D70:D72) -> 5344.597 | E73: =SUM(E70:E72) -> 6415.212 | F73: =SUM(F70:F72) -> 7609.663 | H73: =SUM(H70:H72) -> 4221.173 | I73: =SUM(I70:I72) -> 4905.661 | J73: =SUM(J70:J72) -> 4716.318 | K73: =SUM(K70:K72) -> 5344.597 | L73: =SUM(L70:L72) -> 5523.589 | M73: =SUM(M70:M72) -> 6063.28 | N73: =SUM(N70:N72) -> 6240.034 | O73: =SUM(O70:O72) -> 6415.212 | ... T73: =SUM(T70:T72) -> 7736.393 | V73: =SUM(V70:V72) -> 5344.597 | W73: =SUM(W70:W72) -> 5523.589 | X73: =SUM(X70:X72) -> 6063.28 | Y73: =SUM(Y70:Y72) -> 6240.034 | Z73: =SUM(Z70:Z72) -> 6415.212 | AA73: =SUM(AA70:AA72) -> 6932.043 | AB73: =SUM(AB70:AB72) -> 7306.741 | AC73: =SUM(AC70:AC72) -> 7145.646 | ... AE73: =SUM(AE70:AE72) -> 7736.393
B75: Total Shareholder Equity | C75: ='Historical Financials'!C73 -> 2618.255 | D75: ='Historical Financials'!D73 -> 2534.183 | E75: ='Historical Financials'!E73 -> 2731.989 | F75: ='Historical Financials'!F73 -> 3069.009 | H75: ='Historical Financials'!H73 -> 2563.438 | I75: ='Historical Financials'!I73 -> 2510.148 | J75: ='Historical Financials'!J73 -> 2511.136 | K75: ='Historical Financials'!K73 -> 2534.183 | L75: ='Historical Financials'!L73 -> 2566.8 | M75: ='Historical Financials'!M73 -> 2634.884 | N75: ='Historical Financials'!N73 -> 2623.46 | O75: ='Historical Financials'!O73 -> 2731.989 | ... T75: ='Historical Financials'!T73 -> 3298.885 | V75: =K75 -> 2534.183 | W75: =L75 -> 2566.8 | X75: =M75 -> 2634.884 | Y75: =N75 -> 2623.46 | Z75: =O75 -> 2731.989 | AA75: =P75 -> 2835.572 | AB75: =Q75 -> 2785.54 | AC75: =R75 -> 2874.916 | ... AE75: =T75 -> 3298.885
B76: Total Book Capitalization | C76: =SUM(C73:C75) -> 6625.08 | D76: =SUM(D73:D75) -> 7878.78 | E76: =SUM(E73:E75) -> 9147.201 | F76: =SUM(F73:F75) -> 10678.672 | H76: =SUM(H73:H75) -> 6784.611 | I76: =SUM(I73:I75) -> 7415.809 | J76: =SUM(J73:J75) -> 7227.454 | K76: =SUM(K73:K75) -> 7878.78 | L76: =SUM(L73:L75) -> 8090.389 | M76: =SUM(M73:M75) -> 8698.164 | N76: =SUM(N73:N75) -> 8863.494 | O76: =SUM(O73:O75) -> 9147.201 | ... T76: =SUM(T73:T75) -> 11035.278 | V76: =SUM(V73:V75) -> 7878.78 | W76: =SUM(W73:W75) -> 8090.389 | X76: =SUM(X73:X75) -> 8698.164 | Y76: =SUM(Y73:Y75) -> 8863.494 | Z76: =SUM(Z73:Z75) -> 9147.201 | AA76: =SUM(AA73:AA75) -> 9767.615 | AB76: =SUM(AB73:AB75) -> 10092.281 | AC76: =SUM(AC73:AC75) -> 10020.562 | ... AE76: =SUM(AE73:AE75) -> 11035.278
B78: Credit Metrics
B80: LTM Total Leverage | C80: =C73/C33 -> -9.4871349 | D80: =D73/D33 -> -8.6972038 | E80: =E73/E33 -> -62.714699 | F80: =F73/F33 -> 16.570375 | K80: =SUM(K73/SUM(H33:K33)) -> -8.6972038 | L80: =SUM(L73/SUM(I33:L33)) -> -10.527157 | M80: =SUM(M73/SUM(J33:M33)) -> -16.592588 | N80: =SUM(N73/SUM(K33:N33)) -> -24.342233 | O80: =SUM(O73/SUM(L33:O33)) -> -62.714699 | P80: =SUM(P73/SUM(M33:P33)) -> -187.3272 | Q80: =SUM(Q73/SUM(N33:Q33)) -> 47.097725 | R80: =SUM(R73/SUM(O33:R33)) -> 21.75089 | ... T80: =SUM(T73/SUM(Q33:T33)) -> 11.620638 | V80: =V73/V33 -> -8.6972038 | W80: =W73/W33 -> -10.527157 | X80: =X73/X33 -> -16.592588 | Y80: =Y73/Y33 -> -24.342233 | Z80: =Z73/Z33 -> -62.714699 | AA80: =AA73/AA33 -> -187.3272 | AB80: =AB73/AB33 -> 47.097725 | AC80: =AC73/AC33 -> 21.75089 | ... AE80: =AE73/AE33 -> 11.620638
B81: LTM Net Leverage | C81: =SUM(C73-C53)/C33 -> -6.5152116 | D81: =SUM(D73-D53)/D33 -> -7.2456181 | E81: =SUM(E73-E53)/E33 -> -52.81064 | F81: =SUM(F73-F53)/F33 -> 13.62099 | K81: =SUM(K73-K53)/SUM(H33:K33) -> -7.2456181 | L81: =SUM(L73-L53)/SUM(I33:L33) -> -8.4702429 | M81: =SUM(M73-M53)/SUM(J33:M33) -> -13.755534 | N81: =SUM(N73-N53)/SUM(K33:N33) -> -19.377225 | O81: =SUM(O73-O53)/SUM(L33:O33) -> -52.81064 | P81: =SUM(P73-P53)/SUM(M33:P33) -> -159.05642 | Q81: =SUM(Q73-Q53)/SUM(N33:Q33) -> 39.36032 | R81: =SUM(R73-R53)/SUM(O33:R33) -> 17.638082 | ... T81: =SUM(T73-T53)/SUM(Q33:T33) -> 9.4744016 | V81: =SUM(V73-V53)/V33 -> -7.2456181 | W81: =SUM(W73-W53)/W33 -> -8.4702429 | X81: =SUM(X73-X53)/X33 -> -13.755534 | Y81: =SUM(Y73-Y53)/Y33 -> -19.377225 | Z81: =SUM(Z73-Z53)/Z33 -> -52.81064 | AA81: =SUM(AA73-AA53)/AA33 -> -159.05642 | AB81: =SUM(AB73-AB53)/AB33 -> 39.36032 | AC81: =SUM(AC73-AC53)/AC33 -> 17.638082 | ... AE81: =SUM(AE73-AE53)/AE33 -> 9.4744016
B82: LTM Interest Coverage | C82: =C33/-C38 -> #DIV/0! | D82: =D33/-D38 -> #DIV/0! | E82: =E33/-E38 -> #DIV/0! | F82: =F33/-F38 -> #DIV/0! | K82: {=SUM(H33:K33)/SUM(-H38:K38)} -> #DIV/0! | L82: {=SUM(I33:L33)/SUM(-I38:L38)} -> #DIV/0! | M82: {=SUM(J33:M33)/SUM(-J38:M38)} -> #DIV/0! | N82: {=SUM(K33:N33)/SUM(-K38:N38)} -> #DIV/0! | O82: {=SUM(L33:O33)/SUM(-L38:O38)} -> #DIV/0! | P82: {=SUM(M33:P33)/SUM(-M38:P38)} -> #DIV/0! | Q82: {=SUM(N33:Q33)/SUM(-N38:Q38)} -> #DIV/0! | R82: {=SUM(O33:R33)/SUM(-O38:R38)} -> #DIV/0! | ... T82: {=SUM(Q33:T33)/SUM(-Q38:T38)} -> #DIV/0! | V82: =V33/-V38 -> #DIV/0! | W82: =W33/-W38 -> #DIV/0! | X82: =X33/-X38 -> #DIV/0! | Y82: =Y33/-Y38 -> #DIV/0! | Z82: =Z33/-Z38 -> #DIV/0! | AA82: =AA33/-AA38 -> #DIV/0! | AB82: =AB33/-AB38 -> #DIV/0! | AC82: =AC33/-AC38 -> #DIV/0! | ... AE82: =AE33/-AE38 -> #DIV/0!
B83: LTM Debt Service Coverage | C83: {=SUM(C33+C36)/SUM(-C37:C38)} -> #DIV/0! | D83: {=SUM(D33+D36)/SUM(-D37:D38)} -> #DIV/0! | E83: {=SUM(E33+E36)/SUM(-E37:E38)} -> #DIV/0! | F83: {=SUM(F33+F36)/SUM(-F37:F38)} -> #DIV/0! | K83: {=SUM(H33:K33+H36:K36)/SUM(-H37:K38)} -> #DIV/0! | L83: {=SUM(I33:L33+I36:L36)/SUM(-I37:L38)} -> #DIV/0! | M83: {=SUM(J33:M33+J36:M36)/SUM(-J37:M38)} -> #DIV/0! | N83: {=SUM(K33:N33+K36:N36)/SUM(-K37:N38)} -> #DIV/0! | O83: {=SUM(L33:O33+L36:O36)/SUM(-L37:O38)} -> #DIV/0! | P83: {=SUM(M33:P33+M36:P36)/SUM(-M37:P38)} -> #DIV/0! | Q83: {=SUM(N33:Q33+N36:Q36)/SUM(-N37:Q38)} -> #DIV/0! | R83: {=SUM(O33:R33+O36:R36)/SUM(-O37:R38)} -> #DIV/0! | ... T83: {=SUM(Q33:T33+Q36:T36)/SUM(-Q37:T38)} -> #DIV/0! | V83: {=SUM(V33+V36)/SUM(-V37:V38)} -> #DIV/0! | W83: {=SUM(W33+W36)/SUM(-W37:W38)} -> #DIV/0! | X83: {=SUM(X33+X36)/SUM(-X37:X38)} -> #DIV/0! | Y83: {=SUM(Y33+Y36)/SUM(-Y37:Y38)} -> #DIV/0! | Z83: {=SUM(Z33+Z36)/SUM(-Z37:Z38)} -> #DIV/0! | AA83: {=SUM(AA33+AA36)/SUM(-AA37:AA38)} -> #DIV/0! | AB83: {=SUM(AB33+AB36)/SUM(-AB37:AB38)} -> #DIV/0! | AC83: {=SUM(AC33+AC36)/SUM(-AC37:AC38)} -> #DIV/0! | ... AE83: {=SUM(AE33+AE36)/SUM(-AE37:AE38)} -> #DIV/0!
B84: LTM Fixed Charge Coverage | C84: {=SUM(C33)/SUM(-C36:C38)} -> -4.8944605 | D84: {=SUM(D33)/SUM(-D36:D38)} -> -5.0881308 | E84: {=SUM(E33)/SUM(-E36:E38)} -> -0.64215046 | F84: {=SUM(F33)/SUM(-F36:F38)} -> 2.3894864 | K84: {=SUM(H33:K33)/SUM(-H36:K38)} -> -5.0881308 | L84: {=SUM(I33:L33)/SUM(-I36:L38)} -> -4.182835 | M84: {=SUM(J33:M33)/SUM(-J36:M38)} -> -2.812272 | N84: {=SUM(K33:N33)/SUM(-K36:N38)} -> -1.757022 | O84: {=SUM(L33:O33)/SUM(-L36:O38)} -> -0.64215046 | P84: {=SUM(M33:P33)/SUM(-M36:P38)} -> -0.22075272 | Q84: {=SUM(N33:Q33)/SUM(-N36:Q38)} -> 0.89785808 | R84: {=SUM(O33:R33)/SUM(-O36:R38)} -> 1.8319922 | ... T84: {=SUM(Q33:T33)/SUM(-Q36:T38)} -> 3.2892264 | V84: {=SUM(V33)/SUM(-V36:V38)} -> -5.0881308 | W84: {=SUM(W33)/SUM(-W36:W38)} -> -4.182835 | X84: {=SUM(X33)/SUM(-X36:X38)} -> -2.812272 | Y84: {=SUM(Y33)/SUM(-Y36:Y38)} -> -1.757022 | Z84: {=SUM(Z33)/SUM(-Z36:Z38)} -> -0.64215046 | AA84: {=SUM(AA33)/SUM(-AA36:AA38)} -> -0.22075272 | AB84: {=SUM(AB33)/SUM(-AB36:AB38)} -> 0.89785808 | AC84: {=SUM(AC33)/SUM(-AC36:AC38)} -> 1.8319922 | ... AE84: {=SUM(AE33)/SUM(-AE36:AE38)} -> 3.2892264
B85: Debt-to-Book Capitalization | C85: =C76/C73 -> 1.6534488 | D85: =D76/D73 -> 1.4741579 | E85: =E76/E73 -> 1.4258611 | F85: =F76/F73 -> 1.4033042 | K85: =K76/K73 -> 1.4741579 | L85: =L76/L73 -> 1.4646979 | M85: =M76/M73 -> 1.4345641 | N85: =N76/N73 -> 1.420424 | O85: =O76/O73 -> 1.4258611 | P85: =P76/P73 -> 1.4090529 | Q85: =Q76/Q73 -> 1.3812288 | R85: =R76/R73 -> 1.4023312 | ... T85: =T76/T73 -> 1.4264112 | V85: =V76/V73 -> 1.4741579 | W85: =W76/W73 -> 1.4646979 | X85: =X76/X73 -> 1.4345641 | Y85: =Y76/Y73 -> 1.420424 | Z85: =Z76/Z73 -> 1.4258611 | AA85: =AA76/AA73 -> 1.4090529 | AB85: =AB76/AB73 -> 1.3812288 | AC85: =AC76/AC73 -> 1.4023312 | ... AE85: =AE76/AE73 -> 1.4264112
