Workbook

Sheet Historical Financials
B2: Microstrategy, Inc. (NASDAQ: MSTR)
B3: Historical Financials
B4: $ in thousands except per share
A6: X | B6: Income Statement | D6: FYE | H6: Quarterly | R6: Quarterly | AD6: LTM | AE6: LTM | AK6: Variance
B7: Fiscal Period | C7: 2021 | D7: 2022 | E7: 2023 | F7: 2024 | H7: 1Q22 | I7: 2Q22 | J7: 3Q22 | K7: 4Q22 | L7: 1Q23 | M7: 2Q23 | N7: 3Q23 | O7: 4Q23 | P7: 1Q24 | Q7: 2Q24 | R7: 3Q24 | S7: 4Q24 | T7: 1Q25 | U7: 2Q25 | V7: 3Q25 | X7: =K7 -> 4Q22 | Y7: =L7 -> 1Q23 | Z7: =M7 -> 2Q23 | AA7: =N7 -> 3Q23 | AB7: =O7 -> 4Q23 | AC7: =P7 -> 1Q24 | AD7: =Q7 -> 2Q24 | AE7: =R7 -> 3Q24 | ... AI7: =V7 -> 3Q25
B8: Fiscal Period End Date | C8: 44561 | D8: 44926 | E8: 45291 | F8: 45657 | H8: 44651 | I8: 44742 | J8: 44834 | K8: =D8 -> 44926 | L8: 45016 | M8: 45107 | N8: 45199 | O8: =E8 -> 45291 | P8: 45382 | Q8: 45473 | R8: 45565 | S8: =F8 -> 45657 | T8: 45747 | U8: 45838 | V8: 45930 | X8: =K8 -> 44926 | Y8: =L8 -> 45016 | Z8: =M8 -> 45107 | AA8: =N8 -> 45199 | AB8: =O8 -> 45291 | AC8: =P8 -> 45382 | AD8: =Q8 -> 45473 | AE8: =R8 -> 45565 | ... AI8: =V8 -> 45930
B10: Consolidated Revenue | C10: 510762 | D10: 499264 | E10: 496261 | F10: 463456 | H10: 119277 | I10: 122073 | J10: 125360 | K10: =SUM(D10-SUM(H10:J10)) -> 132554 | L10: 121915 | M10: 120400 | N10: 129462 | O10: =SUM(E10-SUM(L10:N10)) -> 124484 | P10: 115246 | Q10: 111442 | R10: 116071 | S10: =SUM(F10-SUM(P10:R10)) -> 120697 | T10: 111066 | U10: 114488 | V10: 128691 | X10: =SUM(H10:K10) -> 499264 | Y10: =SUM(I10:L10) -> 501902 | Z10: =SUM(J10:M10) -> 500229 | AA10: =SUM(K10:N10) -> 504331 | AB10: =SUM(L10:O10) -> 496261 | AC10: =SUM(M10:P10) -> 489592 | AD10: =SUM(N10:Q10) -> 480634 | AE10: =SUM(O10:R10) -> 467243 | ... AI10: =SUM(S10:V10) -> 474942 | AK10: =SUM(AH10/AD10)-1 -> -0.038099677
B11: Total Revenue | C11: =+SUM(C10:C10) -> 510762 | D11: =+SUM(D10:D10) -> 499264 | E11: =+SUM(E10:E10) -> 496261 | F11: =+SUM(F10:F10) -> 463456 | H11: =+SUM(H10:H10) -> 119277 | I11: =+SUM(I10:I10) -> 122073 | J11: =+SUM(J10:J10) -> 125360 | K11: =+SUM(K10:K10) -> 132554 | L11: =+SUM(L10:L10) -> 121915 | M11: =+SUM(M10:M10) -> 120400 | N11: =+SUM(N10:N10) -> 129462 | O11: =+SUM(O10:O10) -> 124484 | ... V11: =+SUM(V10:V10) -> 128691 | X11: =+SUM(X10:X10) -> 499264 | Y11: =+SUM(Y10:Y10) -> 501902 | Z11: =+SUM(Z10:Z10) -> 500229 | AA11: =+SUM(AA10:AA10) -> 504331 | AB11: =+SUM(AB10:AB10) -> 496261 | AC11: =+SUM(AC10:AC10) -> 489592 | AD11: =+SUM(AD10:AD10) -> 480634 | AE11: =+SUM(AE10:AE10) -> 467243 | ... AI11: =+SUM(AI10:AI10) -> 474942 | AK11: =SUM(AH11/AD11)-1 -> -0.038099677
B13: Cost of Revenue | C13: -91909 | D13: -102989 | E13: -109944 | F13: -129468 | H13: -25677 | I13: -25204 | J13: -25385 | K13: =SUM(D13-SUM(H13:J13)) -> -26723 | L13: -27941 | M13: -27121 | N13: -26661 | O13: =SUM(E13-SUM(L13:N13)) -> -28221 | P13: -30015 | Q13: -30935 | R13: -34349 | S13: =SUM(F13-SUM(P13:R13)) -> -34169 | T13: -33971 | U13: -35750 | V13: -38013 | X13: =SUM(I13:L13) -> -105253 | Y13: =SUM(J13:M13) -> -107170 | Z13: =SUM(K13:N13) -> -108446 | AA13: =SUM(L13:O13) -> -109944 | AB13: =SUM(M13:P13) -> -112018 | AC13: =SUM(N13:Q13) -> -115832 | AD13: =SUM(N13:Q13) -> -115832 | AE13: =SUM(O13:R13) -> -123520 | AF13: =SUM(P13:S13) -> -129468 | AG13: =SUM(Q13:T13) -> -133424 | AH13: =SUM(R13:U13) -> -138239 | AI13: =SUM(S13:V13) -> -141903 | AK13: =SUM(AH13/AD13)-1 -> 0.19344395
B14: Gross Profit | C14: =+SUM(C11+SUM(C13:C13)) -> 418853 | D14: =+SUM(D11+SUM(D13:D13)) -> 396275 | E14: =+SUM(E11+SUM(E13:E13)) -> 386317 | F14: =+SUM(F11+SUM(F13:F13)) -> 333988 | H14: =+SUM(H11+SUM(H13:H13)) -> 93600 | I14: =+SUM(I11+SUM(I13:I13)) -> 96869 | J14: =+SUM(J11+SUM(J13:J13)) -> 99975 | K14: =+SUM(K11+SUM(K13:K13)) -> 105831 | L14: =+SUM(L11+SUM(L13:L13)) -> 93974 | M14: =+SUM(M11+SUM(M13:M13)) -> 93279 | N14: =+SUM(N11+SUM(N13:N13)) -> 102801 | O14: =+SUM(O11+SUM(O13:O13)) -> 96263 | ... V14: =+SUM(V11+SUM(V13:V13)) -> 90678 | X14: =+SUM(X11+SUM(X13:X13)) -> 394011 | Y14: =+SUM(Y11+SUM(Y13:Y13)) -> 394732 | Z14: =+SUM(Z11+SUM(Z13:Z13)) -> 391783 | AA14: =+SUM(AA11+SUM(AA13:AA13)) -> 394387 | AB14: =+SUM(AB11+SUM(AB13:AB13)) -> 384243 | AC14: =+SUM(AC11+SUM(AC13:AC13)) -> 373760 | AD14: =+SUM(AD11+SUM(AD13:AD13)) -> 364802 | AE14: =+SUM(AE11+SUM(AE13:AE13)) -> 343723 | ... AI14: =+SUM(AI11+SUM(AI13:AI13)) -> 333039 | AK14: =SUM(AH14/AD14)-1 -> -0.11161945
B15: Gross Margin (%) | C15: =C14/C11 -> 0.82005513 | D15: =D14/D11 -> 0.79371835 | E15: =E14/E11 -> 0.77845529 | F15: =F14/F11 -> 0.72064662 | H15: =H14/H11 -> 0.78472799 | I15: =I14/I11 -> 0.79353338 | J15: =J14/J11 -> 0.79750319 | K15: =K14/K11 -> 0.79839914 | L15: =L14/L11 -> 0.77081573 | M15: =M14/M11 -> 0.77474252 | N15: =N14/N11 -> 0.79406312 | O15: =O14/O11 -> 0.77329617 | ... V15: =V14/V11 -> 0.70461804 | X15: =X14/X11 -> 0.78918368 | Y15: =Y14/Y11 -> 0.78647226 | Z15: =Z14/Z11 -> 0.78320729 | AA15: =AA14/AA11 -> 0.78200031 | AB15: =AB14/AB11 -> 0.77427604 | AC15: =AC14/AC11 -> 0.76341117 | AD15: =AD14/AD11 -> 0.75900165 | AE15: =AE14/AE11 -> 0.73564077 | ... AI15: =AI14/AI11 -> 0.70122036 | AK15: =SUM(AH15-AD15)*1000 -> -58.011866
B17: Sales and marketing | C17: -160141 | D17: -146882 | E17: -149671 | F17: -138081 | H17: -33240 | I17: -36862 | J17: -35409 | K17: =SUM(D17-SUM(H17:J17)) -> -41371 | L17: -36106 | M17: -37660 | N17: -35606 | O17: =SUM(E17-SUM(L17:N17)) -> -40299 | P17: -33451 | Q17: -34251 | R17: -35414 | S17: =SUM(F17-SUM(P17:R17)) -> -34965 | T17: -27532 | U17: -33691 | V17: -29908 | X17: =SUM(I17:L17) -> -149748 | Y17: =SUM(J17:M17) -> -150546 | Z17: =SUM(K17:N17) -> -150743 | AA17: =SUM(L17:O17) -> -149671 | AB17: =SUM(M17:P17) -> -147016 | AC17: =SUM(N17:Q17) -> -143607 | AD17: =SUM(N17:Q17) -> -143607 | AE17: =SUM(O17:R17) -> -143415 | AF17: =SUM(P17:S17) -> -138081 | AG17: =SUM(Q17:T17) -> -132162 | AH17: =SUM(R17:U17) -> -131602 | AI17: =SUM(S17:V17) -> -126096 | AK17: =SUM(AH17/AD17)-1 -> -0.083596204
B18: Research and development | C18: -117117 | D18: -127428 | E18: -120530 | F18: -118486 | H18: -33523 | I18: -31790 | J18: -30498 | K18: =SUM(D18-SUM(H18:J18)) -> -31617 | L18: -31358 | M18: -29354 | N18: -29660 | O18: =SUM(E18-SUM(L18:N18)) -> -30158 | P18: -29183 | Q18: -30311 | R18: -33301 | S18: =SUM(F18-SUM(P18:R18)) -> -25691 | T18: -24423 | U18: -24071 | V18: -22602 | X18: =SUM(I18:L18) -> -125263 | Y18: =SUM(J18:M18) -> -122827 | Z18: =SUM(K18:N18) -> -121989 | AA18: =SUM(L18:O18) -> -120530 | AB18: =SUM(M18:P18) -> -118355 | AC18: =SUM(N18:Q18) -> -119312 | AD18: =SUM(N18:Q18) -> -119312 | AE18: =SUM(O18:R18) -> -122953 | AF18: =SUM(P18:S18) -> -118486 | AG18: =SUM(Q18:T18) -> -113726 | AH18: =SUM(R18:U18) -> -107486 | AI18: =SUM(S18:V18) -> -96787 | AK18: =SUM(AH18/AD18)-1 -> -0.099118278
B19: General and administrative | C19: -95501 | D19: -111421 | E19: -115312 | F19: -140537 | H19: -26706 | I19: -28502 | J19: -27283 | K19: =SUM(D19-SUM(H19:J19)) -> -28930 | L19: -27906 | M19: -28830 | N19: -29223 | O19: =SUM(E19-SUM(L19:N19)) -> -29353 | P19: -34666 | Q19: -36129 | R19: -33505 | S19: =SUM(F19-SUM(P19:R19)) -> -36237 | T19: -40547 | U19: -36500 | V19: -38173 | X19: =SUM(I19:L19) -> -112621 | Y19: =SUM(J19:M19) -> -112949 | Z19: =SUM(K19:N19) -> -114889 | AA19: =SUM(L19:O19) -> -115312 | AB19: =SUM(M19:P19) -> -122072 | AC19: =SUM(N19:Q19) -> -129371 | AD19: =SUM(N19:Q19) -> -129371 | AE19: =SUM(O19:R19) -> -133653 | AF19: =SUM(P19:S19) -> -140537 | AG19: =SUM(Q19:T19) -> -146418 | AH19: =SUM(R19:U19) -> -146789 | AI19: =SUM(S19:V19) -> -151457 | AK19: =SUM(AH19/AD19)-1 -> 0.13463605
B20: Unrealized gain on digital assets | C20: 0 | D20: 0 | E20: 0 | F20: 0 | H20: 0 | I20: 0 | J20: 0 | K20: =SUM(D20-SUM(H20:J20)) -> 0 | L20: 0 | M20: 0 | N20: 0 | O20: =SUM(E20-SUM(L20:N20)) -> 0 | P20: 0 | Q20: 0 | R20: 0 | S20: =SUM(F20-SUM(P20:R20)) -> 0 | T20: -5906005 | U20: 14047514 | V20: 3890847 | X20: =SUM(I20:L20) -> 0 | Y20: =SUM(J20:M20) -> 0 | Z20: =SUM(K20:N20) -> 0 | AA20: =SUM(L20:O20) -> 0 | AB20: =SUM(M20:P20) -> 0 | AC20: =SUM(N20:Q20) -> 0 | AD20: =SUM(N20:Q20) -> 0 | AE20: =SUM(O20:R20) -> 0 | AF20: =SUM(P20:S20) -> 0 | AG20: =SUM(Q20:T20) -> -5906005 | AH20: =SUM(R20:U20) -> 8141509 | AI20: =SUM(S20:V20) -> 12032356 | AK20: =SUM(AH20/AD20)-1 -> #DIV/0!
B21: Digital asset impairment gains (losses on sale), net | C21: -830621 | D21: -1286286 | E21: -115851 | F21: -1789862 | H21: -170091 | I21: -917838 | J21: -727 | K21: =SUM(D21-SUM(H21:J21)) -> -197630 | L21: -18911 | M21: -24143 | N21: -33559 | O21: =SUM(E21-SUM(L21:N21)) -> -39238 | P21: -191633 | Q21: -180090 | R21: -412084 | S21: =SUM(F21-SUM(P21:R21)) -> -1006055 | T21: 0 | U21: 0 | V21: 0 | X21: =SUM(I21:L21) -> -1135106 | Y21: =SUM(J21:M21) -> -241411 | Z21: =SUM(K21:N21) -> -274243 | AA21: =SUM(L21:O21) -> -115851 | AB21: =SUM(M21:P21) -> -288573 | AC21: =SUM(N21:Q21) -> -444520 | AD21: =SUM(N21:Q21) -> -444520 | AE21: =SUM(O21:R21) -> -823045 | AF21: =SUM(P21:S21) -> -1789862 | AG21: =SUM(Q21:T21) -> -1598229 | AH21: =SUM(R21:U21) -> -1418139 | AI21: =SUM(S21:V21) -> -1006055 | AK21: =SUM(AH21/AD21)-1 -> 2.1902704
B22: Operating Profit | C22: =+SUM(C14+SUM(C17:C21)) -> -784527 | D22: =+SUM(D14+SUM(D17:D21)) -> -1275742 | E22: =+SUM(E14+SUM(E17:E21)) -> -115047 | F22: =+SUM(F14+SUM(F17:F21)) -> -1852978 | H22: =+SUM(H14+SUM(H17:H21)) -> -169960 | I22: =+SUM(I14+SUM(I17:I21)) -> -918123 | J22: =+SUM(J14+SUM(J17:J21)) -> 6058 | K22: =+SUM(K14+SUM(K17:K21)) -> -193717 | L22: =+SUM(L14+SUM(L17:L21)) -> -20307 | M22: =+SUM(M14+SUM(M17:M21)) -> -26708 | N22: =+SUM(N14+SUM(N17:N21)) -> -25247 | O22: =+SUM(O14+SUM(O17:O21)) -> -42785 | ... V22: =+SUM(V14+SUM(V17:V21)) -> 3890842 | X22: =+SUM(X14+SUM(X17:X21)) -> -1128727 | Y22: =+SUM(Y14+SUM(Y17:Y21)) -> -233001 | Z22: =+SUM(Z14+SUM(Z17:Z21)) -> -270081 | AA22: =+SUM(AA14+SUM(AA17:AA21)) -> -106977 | AB22: =+SUM(AB14+SUM(AB17:AB21)) -> -291773 | AC22: =+SUM(AC14+SUM(AC17:AC21)) -> -463050 | AD22: =+SUM(AD14+SUM(AD17:AD21)) -> -472008 | AE22: =+SUM(AE14+SUM(AE17:AE21)) -> -879343 | ... AI22: =+SUM(AI14+SUM(AI17:AI21)) -> 10985000 | AK22: =SUM(AH22/AD22)-1 -> -15.113269
B23: Operating Margin (%) | C23: =C22/C11 -> -1.5359933 | D23: =D22/D11 -> -2.5552453 | E23: =E22/E11 -> -0.23182761 | F23: =F22/F11 -> -3.9981746 | H23: =H22/H11 -> -1.4249185 | I23: =I22/I11 -> -7.521098 | J23: =J22/J11 -> 0.048324825 | K23: =K22/K11 -> -1.4614195 | L23: =L22/L11 -> -0.16656687 | M23: =M22/M11 -> -0.22182724 | N23: =N22/N11 -> -0.19501475 | O23: =O22/O11 -> -0.34369879 | ... V23: =V22/V11 -> 30.233987 | X23: =X22/X11 -> -2.2607819 | Y23: =Y22/Y11 -> -0.46423605 | Z23: =Z22/Z11 -> -0.53991472 | AA23: =AA22/AA11 -> -0.21211665 | AB23: =AB22/AB11 -> -0.58794264 | AC23: =AC22/AC11 -> -0.94578751 | AD23: =AD22/AD11 -> -0.98205287 | AE23: =AE22/AE11 -> -1.8819822 | ... AI23: =AI22/AI11 -> 23.12914 | AK23: =SUM(AH23-AD23)*1000 -> 15391.006
B25: Interest expense, net | C25: -29149 | D25: -53136 | E25: -48960 | F25: -61941 | H25: -11039 | I25: -13187 | J25: -14073 | K25: =SUM(D25-SUM(H25:J25)) -> -14837 | L25: -14930 | M25: -11095 | N25: -11006 | O25: =SUM(E25-SUM(L25:N25)) -> -11929 | P25: -11881 | Q25: -15466 | R25: -18129 | S25: =SUM(F25-SUM(P25:R25)) -> -16465 | T25: -17106 | U25: -17897 | V25: -18890 | X25: =SUM(I25:L25) -> -57027 | Y25: =SUM(J25:M25) -> -54935 | Z25: =SUM(K25:N25) -> -51868 | AA25: =SUM(L25:O25) -> -48960 | AB25: =SUM(M25:P25) -> -45911 | AC25: =SUM(N25:Q25) -> -50282 | AD25: =SUM(N25:Q25) -> -50282 | AE25: =SUM(O25:R25) -> -57405 | AF25: =SUM(P25:S25) -> -61941 | AG25: =SUM(Q25:T25) -> -67166 | AH25: =SUM(R25:U25) -> -69597 | AI25: =SUM(S25:V25) -> -70358 | AK25: =SUM(AH25/AD25)-1 -> 0.38413349
B26: Gain (Loss) on debt extinguishment | C26: 0 | D26: 0 | E26: 44686 | F26: -22933 | H26: 0 | I26: 0 | J26: 0 | K26: =SUM(D26-SUM(H26:J26)) -> 0 | L26: 44686 | M26: 0 | N26: 0 | O26: =SUM(E26-SUM(L26:N26)) -> 0 | P26: 0 | Q26: 0 | R26: -22933 | S26: =SUM(F26-SUM(P26:R26)) -> 0 | T26: 0 | U26: 0 | V26: 0 | X26: =SUM(I26:L26) -> 44686 | Y26: =SUM(J26:M26) -> 44686 | Z26: =SUM(K26:N26) -> 44686 | AA26: =SUM(L26:O26) -> 44686 | AB26: =SUM(M26:P26) -> 0 | AC26: =SUM(N26:Q26) -> 0 | AD26: =SUM(N26:Q26) -> 0 | AE26: =SUM(O26:R26) -> -22933 | AF26: =SUM(P26:S26) -> -22933 | AG26: =SUM(Q26:T26) -> -22933 | AH26: =SUM(R26:U26) -> -22933 | AI26: =SUM(S26:V26) -> 0 | AK26: =SUM(AH26/AD26)-1 -> #DIV/0!
B27: Other income (expense), net | C27: 2287 | D27: 6413 | E27: -5204 | F27: 3506 | H27: 2225 | I27: 5120 | J27: 4897 | K27: =SUM(D27-SUM(H27:J27)) -> -5829 | L27: -1443 | M27: -250 | N27: 2419 | O27: =SUM(E27-SUM(L27:N27)) -> -5930 | P27: 1696 | Q27: 694 | R27: -5034 | S27: =SUM(F27-SUM(P27:R27)) -> 6150 | T27: -3936 | U27: -8271 | V27: -716 | X27: =SUM(I27:L27) -> 2745 | Y27: =SUM(J27:M27) -> -2625 | Z27: =SUM(K27:N27) -> -5103 | AA27: =SUM(L27:O27) -> -5204 | AB27: =SUM(M27:P27) -> -2065 | AC27: =SUM(N27:Q27) -> -1121 | AD27: =SUM(N27:Q27) -> -1121 | AE27: =SUM(O27:R27) -> -8574 | AF27: =SUM(P27:S27) -> 3506 | AG27: =SUM(Q27:T27) -> -2126 | AH27: =SUM(R27:U27) -> -11091 | AI27: =SUM(S27:V27) -> -6773 | AK27: =SUM(AH27/AD27)-1 -> 8.8938448
B28: Earning Before Taxes | C28: =SUM(C22+SUM(C25:C27)) -> -811389 | D28: =SUM(D22+SUM(D25:D27)) -> -1322465 | E28: =SUM(E22+SUM(E25:E27)) -> -124525 | F28: =SUM(F22+SUM(F25:F27)) -> -1934346 | H28: =SUM(H22+SUM(H25:H27)) -> -178774 | I28: =SUM(I22+SUM(I25:I27)) -> -926190 | J28: =SUM(J22+SUM(J25:J27)) -> -3118 | K28: =SUM(K22+SUM(K25:K27)) -> -214383 | L28: =SUM(L22+SUM(L25:L27)) -> 8006 | M28: =SUM(M22+SUM(M25:M27)) -> -38053 | N28: =SUM(N22+SUM(N25:N27)) -> -33834 | O28: =SUM(O22+SUM(O25:O27)) -> -60644 | ... V28: =SUM(V22+SUM(V25:V27)) -> 3871236 | X28: =SUM(X22+SUM(X25:X27)) -> -1138323 | Y28: =SUM(Y22+SUM(Y25:Y27)) -> -245875 | Z28: =SUM(Z22+SUM(Z25:Z27)) -> -282366 | AA28: =SUM(AA22+SUM(AA25:AA27)) -> -116455 | AB28: =SUM(AB22+SUM(AB25:AB27)) -> -339749 | AC28: =SUM(AC22+SUM(AC25:AC27)) -> -514453 | AD28: =SUM(AD22+SUM(AD25:AD27)) -> -523411 | AE28: =SUM(AE22+SUM(AE25:AE27)) -> -968255 | ... AI28: =SUM(AI22+SUM(AI25:AI27)) -> 10907869 | AK28: =SUM(AH28/AD28)-1 -> -13.529265
B29: EBT Margin (%) | C29: =C28/C11 -> -1.5885853 | D29: =D28/D11 -> -2.6488291 | E29: =E28/E11 -> -0.25092643 | F29: =F28/F11 -> -4.1737425 | H29: =H28/H11 -> -1.4988137 | I29: =I28/I11 -> -7.5871814 | J29: =J28/J11 -> -0.024872368 | K29: =K28/K11 -> -1.6173258 | L29: =L28/L11 -> 0.065668704 | M29: =M28/M11 -> -0.31605482 | N29: =N28/N11 -> -0.2613431 | O29: =O28/O11 -> -0.48716301 | ... V29: =V28/V11 -> 30.081637 | X29: =X28/X11 -> -2.2800022 | Y29: =Y28/Y11 -> -0.48988647 | Z29: =Z28/Z11 -> -0.56447347 | AA29: =AA28/AA11 -> -0.23090986 | AB29: =AB28/AB11 -> -0.68461757 | AC29: =AC28/AC11 -> -1.050779 | AD29: =AD28/AD11 -> -1.0890012 | AE29: =AE28/AE11 -> -2.0722729 | ... AI29: =AI28/AI11 -> 22.966739 | AK29: =SUM(AH29-AD29)*1000 -> 15273.823
B31: Provision for income taxes | C31: 275909 | D31: -147332 | E31: 553646 | F31: 767685 | H31: 48023 | I31: -136108 | J31: -23961 | K31: =SUM(D31-SUM(H31:J31)) -> -35286 | L31: 453187 | M31: 60296 | N31: -109607 | O31: =SUM(E31-SUM(L31:N31)) -> 149770 | P31: 160769 | Q31: 112487 | R31: 138504 | S31: =SUM(F31-SUM(P31:R31)) -> 355925 | T31: 1725084 | U31: -3984976 | V31: -1086212 | X31: =SUM(I31:L31) -> 257832 | Y31: =SUM(J31:M31) -> 454236 | Z31: =SUM(K31:N31) -> 368590 | AA31: =SUM(L31:O31) -> 553646 | AB31: =SUM(M31:P31) -> 261228 | AC31: =SUM(N31:Q31) -> 313419 | AD31: =SUM(N31:Q31) -> 313419 | AE31: =SUM(O31:R31) -> 561530 | AF31: =SUM(P31:S31) -> 767685 | AG31: =SUM(Q31:T31) -> 2332000 | AH31: =SUM(R31:U31) -> -1765463 | AI31: =SUM(S31:V31) -> -2990179 | AK31: =SUM(AH31/AD31)-1 -> -6.6329163
B32: Net Income | C32: =SUM(C31+C28) -> -535480 | D32: =SUM(D31+D28) -> -1469797 | E32: =SUM(E31+E28) -> 429121 | F32: =SUM(F31+F28) -> -1166661 | H32: =SUM(H31+H28) -> -130751 | I32: =SUM(I31+I28) -> -1062298 | J32: =SUM(J31+J28) -> -27079 | K32: =SUM(K31+K28) -> -249669 | L32: =SUM(L31+L28) -> 461193 | M32: =SUM(M31+M28) -> 22243 | N32: =SUM(N31+N28) -> -143441 | O32: =SUM(O31+O28) -> 89126 | ... V32: =SUM(V31+V28) -> 2785024 | X32: =SUM(X31+X28) -> -880491 | Y32: =SUM(Y31+Y28) -> 208361 | Z32: =SUM(Z31+Z28) -> 86224 | AA32: =SUM(AA31+AA28) -> 437191 | AB32: =SUM(AB31+AB28) -> -78521 | AC32: =SUM(AC31+AC28) -> -201034 | AD32: =SUM(AD31+AD28) -> -209992 | AE32: =SUM(AE31+AE28) -> -406725 | ... AI32: =SUM(AI31+AI28) -> 7917690 | AK32: =SUM(AH32/AD32)-1 -> -23.82226
B33: Margin (%) | C33: =C32/C11 -> -1.0483944 | D33: =D32/D11 -> -2.9439275 | E33: =E32/E11 -> 0.86470829 | F33: =F32/F11 -> -2.5173069 | H33: =H32/H11 -> -1.0961962 | I33: =I32/I11 -> -8.7021536 | J33: =J32/J11 -> -0.21600989 | K33: =K32/K11 -> -1.8835267 | L33: =L32/L11 -> 3.7829061 | M33: =M32/M11 -> 0.18474252 | N33: =N32/N11 -> -1.1079776 | O33: =O32/O11 -> 0.7159635 | ... V33: =V32/V11 -> 21.641171 | X33: =X32/X11 -> -1.763578 | Y33: =Y32/Y11 -> 0.4151428 | Z33: =Z32/Z11 -> 0.17236905 | AA33: =AA32/AA11 -> 0.86687314 | AB33: =AB32/AB11 -> -0.15822521 | AC33: =AC32/AC11 -> -0.41061537 | AD33: =AD32/AD11 -> -0.43690625 | AE33: =AE32/AE11 -> -0.87047853 | ... AI33: =AI32/AI11 -> 16.670857 | AK33: =SUM(AH33-AD33)*1000 -> 10803.041
B35: Basic shares | C35: 10020 | D35: 113209 | E35: 136706 | F35: 192549 | H35: 11289 | I35: 11300 | J35: 11308 | K35: =D35 -> 113209 | L35: 11834 | M35: 13247 | N35: 142214 | O35: =E35 -> 136706 | P35: 171942 | Q35: 178607 | R35: 197273 | S35: =F35 -> 192549 | T35: 256473 | U35: 275244 | V35: 284376 | X35: =K35 -> 113209 | Y35: =L35 -> 11834 | Z35: =M35 -> 13247 | AA35: =N35 -> 142214 | AB35: =O35 -> 136706 | AC35: =P35 -> 171942 | AD35: =Q35 -> 178607 | AE35: =R35 -> 197273 | ... AI35: =V35 -> 284376 | AK35: =SUM(AH35/AD35)-1 -> 0.54105942
B36: Basic EPS | C36: =C32/C35 -> -53.441118 | D36: =D32/D35 -> -12.98304 | E36: =E32/E35 -> 3.1390063 | F36: =F32/F35 -> -6.0590343 | H36: =H32/H35 -> -11.58216 | I36: =I32/I35 -> -94.008673 | J36: =J32/J35 -> -2.3946763 | K36: =K32/K35 -> -2.2053812 | L36: =L32/L35 -> 38.971861 | M36: =M32/M35 -> 1.6790972 | N36: =N32/N35 -> -1.0086278 | O36: =O32/O35 -> 0.65195383 | ... V36: =V32/V35 -> 9.7934566 | X36: =X32/X35 -> -7.7775707 | Y36: =Y32/Y35 -> 17.60698 | Z36: =Z32/Z35 -> 6.5089454 | AA36: =AA32/AA35 -> 3.0741769 | AB36: =AB32/AB35 -> -0.57437859 | AC36: =AC32/AC35 -> -1.1691966 | AD36: =AD32/AD35 -> -1.175721 | AE36: =AE32/AE35 -> -2.0617368 | ... AI36: =AI32/AI35 -> 27.842328 | AK36: =SUM(AH36/AD36)-1 -> -15.809461
B38: Fully Diluted Shares | C38: 10020 | D38: 113209 | E38: 165662 | F38: 192549 | H38: 11289 | I38: 11300 | J38: 11308 | K38: =D38 -> 113209 | L38: 14575 | M38: 16095 | N38: 142214 | O38: =E38 -> 165662 | P38: 171942 | Q38: 178607 | R38: 197273 | S38: =F38 -> 192549 | T38: 256473 | U38: 306764 | V38: 315393 | X38: =L38 -> 14575 | Y38: =M38 -> 16095 | Z38: =N38 -> 142214 | AA38: =O38 -> 165662 | AB38: =P38 -> 171942 | AC38: =Q38 -> 178607 | AD38: =Q38 -> 178607 | AE38: =R38 -> 197273 | AF38: =S38 -> 192549 | AG38: =T38 -> 256473 | AH38: =U38 -> 306764 | AI38: =V38 -> 315393 | AK38: =SUM(AH38/AD38)-1 -> 0.71753627
B39: Diluted EPS | C39: =C32/C38 -> -53.441118 | D39: =D32/D38 -> -12.98304 | E39: =E32/E38 -> 2.5903406 | F39: =F32/F38 -> -6.0590343 | H39: =H32/H38 -> -11.58216 | I39: =I32/I38 -> -94.008673 | J39: =J32/J38 -> -2.3946763 | K39: =K32/K38 -> -2.2053812 | L39: =L32/L38 -> 31.642744 | M39: =M32/M38 -> 1.381982 | N39: =N32/N38 -> -1.0086278 | O39: =O32/O38 -> 0.53799906 | ... V39: =V32/V38 -> 8.8303291 | X39: =X32/X38 -> -60.411046 | Y39: =Y32/Y38 -> 12.945697 | Z39: =Z32/Z38 -> 0.60629755 | AA39: =AA32/AA38 -> 2.6390542 | AB39: =AB32/AB38 -> -0.45667144 | AC39: =AC32/AC38 -> -1.1255662 | AD39: =AD32/AD38 -> -1.175721 | AE39: =AE32/AE38 -> -2.0617368 | ... AI39: =AI32/AI38 -> 25.104203 | AK39: =SUM(AH39/AD39)-1 -> -14.287789
A41: X | B41: Balance Sheet | D41: FYE | H41: Quarterly | R41: Quarterly | AD41: LTM | AK41: Variance
B42: =B7 -> Fiscal Period | C42: =C7 -> 2021 | D42: =D7 -> 2022 | E42: =E7 -> 2023 | F42: =F7 -> 2024 | H42: =H7 -> 1Q22 | I42: =I7 -> 2Q22 | J42: =J7 -> 3Q22 | K42: =K7 -> 4Q22 | L42: =L7 -> 1Q23 | M42: =M7 -> 2Q23 | N42: =N7 -> 3Q23 | O42: =O7 -> 4Q23 | ... V42: =V7 -> 3Q25 | X42: =X7 -> 4Q22 | Y42: =Y7 -> 1Q23 | Z42: =Z7 -> 2Q23 | AA42: =AA7 -> 3Q23 | AB42: =AB7 -> 4Q23 | AC42: =AC7 -> 1Q24 | AD42: =AD7 -> 2Q24 | AE42: =AE7 -> 3Q24 | ... AI42: =AI7 -> 3Q25
B43: =B8 -> Fiscal Period End Date | C43: =C8 -> 44561 | D43: =D8 -> 44926 | E43: =E8 -> 45291 | F43: =F8 -> 45657 | H43: =H8 -> 44651 | I43: =I8 -> 44742 | J43: =J8 -> 44834 | K43: =K8 -> 44926 | L43: =L8 -> 45016 | M43: =M8 -> 45107 | N43: =N8 -> 45199 | O43: =O8 -> 45291 | ... V43: =V8 -> 45930 | X43: =X8 -> 44926 | Y43: =Y8 -> 45016 | Z43: =Z8 -> 45107 | AA43: =AA8 -> 45199 | AB43: =AB8 -> 45291 | AC43: =AC8 -> 45382 | AD43: =AD8 -> 45473 | AE43: =AE8 -> 45565 | ... AI43: =AI8 -> 45930
B45: Current Assets
B46: Cash and cash equivalents | C46: 63356 | D46: 43835 | E46: 46817 | F46: 38117 | H46: 92677 | I46: 69386 | J46: 60390 | K46: =D46 -> 43835 | L46: 94311 | M46: 65968 | N46: 45009 | O46: =E46 -> 46817 | P46: 81326 | Q46: 66923 | R46: 46343 | S46: =F46 -> 38117 | T46: 60298 | U46: 50095 | V46: 54285 | X46: =K46 -> 43835 | Y46: =L46 -> 94311 | Z46: =M46 -> 65968 | AA46: =N46 -> 45009 | AB46: =O46 -> 46817 | AC46: =P46 -> 81326 | AD46: =Q46 -> 66923 | AE46: =R46 -> 46343 | ... AI46: =V46 -> 54285 | AK46: =SUM(AH46/AD46)-1 -> -0.25145316
B47: Restricted cash | C47: 1078 | D47: 7033 | E47: 1856 | F47: 1780 | H47: 6265 | I47: 6155 | J47: 6578 | K47: =D47 -> 7033 | L47: 2153 | M47: 2085 | N47: 1865 | O47: =E47 -> 1856 | P47: 2402 | Q47: 1878 | R47: 1862 | S47: =F47 -> 1780 | T47: 1960 | U47: 2037 | V47: 1915 | X47: =K47 -> 7033 | Y47: =L47 -> 2153 | Z47: =M47 -> 2085 | AA47: =N47 -> 1865 | AB47: =O47 -> 1856 | AC47: =P47 -> 2402 | AD47: =Q47 -> 1878 | AE47: =R47 -> 1862 | ... AI47: =V47 -> 1915 | AK47: =SUM(AH47/AD47)-1 -> 0.084664537
B48: Accounts receivable, net | C48: 189280 | D48: 189280 | E48: 183815 | F48: 181203 | H48: 126930 | I48: 118645 | J48: 109926 | K48: =D48 -> 189280 | L48: 139178 | M48: 121901 | N48: 128650 | O48: =E48 -> 183815 | P48: 115150 | Q48: 112234 | R48: 107169 | S48: =F48 -> 181203 | T48: 104585 | U48: 117870 | V48: 113406 | X48: =K48 -> 189280 | Y48: =L48 -> 139178 | Z48: =M48 -> 121901 | AA48: =N48 -> 128650 | AB48: =O48 -> 183815 | AC48: =P48 -> 115150 | AD48: =Q48 -> 112234 | AE48: =R48 -> 107169 | ... AI48: =V48 -> 113406 | AK48: =SUM(AH48/AD48)-1 -> 0.050216512
B49: Prepaid expenses and other current assets | C49: 14251 | D49: 24418 | E49: 35407 | F49: 31224 | H49: 21116 | I49: 25496 | J49: 25399 | K49: =D49 -> 24418 | L49: 24034 | M49: 19680 | N49: 24041 | O49: =E49 -> 35407 | P49: 42714 | Q49: 27234 | R49: 30668 | S49: =F49 -> 31224 | T49: 36769 | U49: 43459 | V49: 44345 | X49: =K49 -> 24418 | Y49: =L49 -> 24034 | Z49: =M49 -> 19680 | AA49: =N49 -> 24041 | AB49: =O49 -> 35407 | AC49: =P49 -> 42714 | AD49: =Q49 -> 27234 | AE49: =R49 -> 30668 | ... AI49: =V49 -> 44345 | AK49: =SUM(AH49/AD49)-1 -> 0.59576265
B50: Total Current Assets | C50: =SUM(C46:C49) -> 267965 | D50: =SUM(D46:D49) -> 264566 | E50: =SUM(E46:E49) -> 267895 | F50: =SUM(F46:F49) -> 252324 | H50: =SUM(H46:H49) -> 246988 | I50: =SUM(I46:I49) -> 219682 | J50: =SUM(J46:J49) -> 202293 | K50: =SUM(K46:K49) -> 264566 | L50: =SUM(L46:L49) -> 259676 | M50: =SUM(M46:M49) -> 209634 | N50: =SUM(N46:N49) -> 199565 | O50: =SUM(O46:O49) -> 267895 | ... V50: =SUM(V46:V49) -> 213951 | X50: =SUM(X46:X49) -> 264566 | Y50: =SUM(Y46:Y49) -> 259676 | Z50: =SUM(Z46:Z49) -> 209634 | AA50: =SUM(AA46:AA49) -> 199565 | AB50: =SUM(AB46:AB49) -> 267895 | AC50: =SUM(AC46:AC49) -> 241592 | AD50: =SUM(AD46:AD49) -> 208269 | AE50: =SUM(AE46:AE49) -> 186042 | ... AI50: =SUM(AI46:AI49) -> 213951 | AK50: =SUM(AH50/AD50)-1 -> 0.024929298
B52: Non-Current Assets
B53: Digital assets | C53: 2850210 | D53: 1840028 | E53: 3626476 | F53: 23909373 | H53: 2895619 | I53: 1987781 | J53: 1993032 | K53: =D53 -> 1840028 | L53: 2000392 | M53: 2323252 | N53: 2451374 | O53: =E53 -> 3626476 | P53: 5074152 | Q53: 5687890 | R53: 6850879 | S53: =F53 -> 23909373 | T53: 43546079 | U53: 64362798 | V53: 73205725 | X53: =K53 -> 1840028 | Y53: =L53 -> 2000392 | Z53: =M53 -> 2323252 | AA53: =N53 -> 2451374 | AB53: =O53 -> 3626476 | AC53: =P53 -> 5074152 | AD53: =Q53 -> 5687890 | AE53: =R53 -> 6850879 | ... AI53: =V53 -> 73205725 | AK53: =SUM(AH53/AD53)-1 -> 10.31576
B54: Property and equipment, net | C54: 36587 | D54: 32311 | E54: 28941 | F54: 26327 | H54: 35680 | I54: 34580 | J54: 33033 | K54: =D54 -> 32311 | L54: 31338 | M54: 30507 | N54: 30192 | O54: =E54 -> 28941 | P54: 29108 | Q54: 28332 | R54: 27517 | S54: =F54 -> 26327 | T54: 28335 | U54: 30203 | V54: 29949 | X54: =K54 -> 32311 | Y54: =L54 -> 31338 | Z54: =M54 -> 30507 | AA54: =N54 -> 30192 | AB54: =O54 -> 28941 | AC54: =P54 -> 29108 | AD54: =Q54 -> 28332 | AE54: =R54 -> 27517 | ... AI54: =V54 -> 29949 | AK54: =SUM(AH54/AD54)-1 -> 0.066038402
B55: Right-of-use assets | C55: 66760 | D55: 61299 | E55: 57343 | F55: 54560 | H55: 64637 | I55: 65169 | J55: 62902 | K55: =D55 -> 61299 | L55: 59655 | M55: 58264 | N55: 54542 | O55: =E55 -> 57343 | P55: 55093 | Q55: 53591 | R55: 55308 | S55: =F55 -> 54560 | T55: 53070 | U55: 51573 | V55: 49236 | X55: =K55 -> 61299 | Y55: =L55 -> 59655 | Z55: =M55 -> 58264 | AA55: =N55 -> 54542 | AB55: =O55 -> 57343 | AC55: =P55 -> 55093 | AD55: =Q55 -> 53591 | AE55: =R55 -> 55308 | ... AI55: =V55 -> 49236 | AK55: =SUM(AH55/AD55)-1 -> -0.037655576
B56: Deposits and other assets | C56: 15820 | D56: 23916 | E56: 24300 | F56: 75794 | H56: 18181 | I56: 17786 | J56: 20992 | K56: =D56 -> 23916 | L56: 23825 | M56: 22421 | N56: 24156 | O56: =E56 -> 24300 | P56: 31757 | Q56: 43449 | R56: 51109 | S56: =F56 -> 75794 | T56: 83261 | U56: 109664 | V56: 114342 | X56: =K56 -> 23916 | Y56: =L56 -> 23825 | Z56: =M56 -> 22421 | AA56: =N56 -> 24156 | AB56: =O56 -> 24300 | AC56: =P56 -> 31757 | AD56: =Q56 -> 43449 | AE56: =R56 -> 51109 | ... AI56: =V56 -> 114342 | AK56: =SUM(AH56/AD56)-1 -> 1.5239706
B57: Deferred tax assets, net | C57: 319782 | D57: 188152 | E57: 757573 | F57: 1525307 | H57: 377282 | I57: 243367 | J57: 233034 | K57: =D57 -> 188152 | L57: 651516 | M57: 719026 | N57: 614112 | O57: =E57 -> 757573 | P57: 919837 | Q57: 1031542 | R57: 1172726 | S57: =F57 -> 1525307 | T57: 5403 | U57: 5716 | V57: 5835 | X57: =K57 -> 188152 | Y57: =L57 -> 651516 | Z57: =M57 -> 719026 | AA57: =N57 -> 614112 | AB57: =O57 -> 757573 | AC57: =P57 -> 919837 | AD57: =Q57 -> 1031542 | AE57: =R57 -> 1172726 | ... AI57: =V57 -> 5835 | AK57: =SUM(AH57/AD57)-1 -> -0.99445878
B58: Total Assets | C58: =SUM(C53:C57)+C50 -> 3557124 | D58: =SUM(D53:D57)+D50 -> 2410272 | E58: =SUM(E53:E57)+E50 -> 4762528 | F58: =SUM(F53:F57)+F50 -> 25843685 | H58: =SUM(H53:H57)+H50 -> 3638387 | I58: =SUM(I53:I57)+I50 -> 2568365 | J58: =SUM(J53:J57)+J50 -> 2545286 | K58: =SUM(K53:K57)+K50 -> 2410272 | L58: =SUM(L53:L57)+L50 -> 3026402 | M58: =SUM(M53:M57)+M50 -> 3363104 | N58: =SUM(N53:N57)+N50 -> 3373941 | O58: =SUM(O53:O57)+O50 -> 4762528 | ... V58: =SUM(V53:V57)+V50 -> 73619038 | X58: =SUM(X53:X57)+X50 -> 2410272 | Y58: =SUM(Y53:Y57)+Y50 -> 3026402 | Z58: =SUM(Z53:Z57)+Z50 -> 3363104 | AA58: =SUM(AA53:AA57)+AA50 -> 3373941 | AB58: =SUM(AB53:AB57)+AB50 -> 4762528 | AC58: =SUM(AC53:AC57)+AC50 -> 6351539 | AD58: =SUM(AD53:AD57)+AD50 -> 7053073 | AE58: =SUM(AE53:AE57)+AE50 -> 8343581 | ... AI58: =SUM(AI53:AI57)+AI50 -> 73619038 | AK58: =SUM(AH58/AD58)-1 -> 8.1837154
B60: Current Liabilities
B61: Accounts payable, accrued expenses, and operating lease liabilities | C61: 46084 | D61: 42976 | E61: 43090 | F61: 52982 | H61: 44388 | I61: 35960 | J61: 36846 | K61: =D61 -> 42976 | L61: 50604 | M61: 33660 | N61: 34306 | O61: =E61 -> 43090 | P61: 41866 | Q61: 44188 | R61: 45714 | S61: =F61 -> 52982 | T61: 53716 | U61: 44220 | V61: 48723 | X61: =K61 -> 42976 | Y61: =L61 -> 50604 | Z61: =M61 -> 33660 | AA61: =N61 -> 34306 | AB61: =O61 -> 43090 | AC61: =P61 -> 41866 | AD61: =Q61 -> 44188 | AE61: =R61 -> 45714 | ... AI61: =V61 -> 48723 | AK61: =SUM(AH61/AD61)-1 -> 0.00072417851
B62: Accrued compensation and employee benefits | C62: 54548 | D62: 53716 | E62: 50045 | F62: 58362 | H62: 43726 | I62: 47773 | J62: 46346 | K62: =D62 -> 53716 | L62: 39199 | M62: 41492 | N62: 43405 | O62: =E62 -> 50045 | P62: 40617 | Q62: 46853 | R62: 51686 | S62: =F62 -> 58362 | T62: 32785 | U62: 50132 | V62: 44514 | X62: =K62 -> 53716 | Y62: =L62 -> 39199 | Z62: =M62 -> 41492 | AA62: =N62 -> 43405 | AB62: =O62 -> 50045 | AC62: =P62 -> 40617 | AD62: =Q62 -> 46853 | AE62: =R62 -> 51686 | ... AI62: =V62 -> 44514 | AK62: =SUM(AH62/AD62)-1 -> 0.069984846
B63: Accrued interest | C63: 1493 | D63: 2829 | E63: 1493 | F63: 5549 | H63: 10544 | I63: 2269 | J63: 11394 | K63: =D63 -> 2829 | L63: 10368 | M63: 1493 | N63: 10368 | O63: =E63 -> 1493 | P63: 10878 | Q63: 5066 | R63: 5800 | S63: =F63 -> 5549 | T63: 5970 | U63: 5620 | V63: 29896 | X63: =K63 -> 2829 | Y63: =L63 -> 10368 | Z63: =M63 -> 1493 | AA63: =N63 -> 10368 | AB63: =O63 -> 1493 | AC63: =P63 -> 10878 | AD63: =Q63 -> 5066 | AE63: =R63 -> 5800 | ... AI63: =V63 -> 29896 | AK63: =SUM(AH63/AD63)-1 -> 0.10935649
B64: Current portion of long-term debt, net | C64: 0 | D64: 454 | E64: 483 | F64: 517 | H64: 0 | I64: 0 | J64: 0 | K64: =D64 -> 454 | L64: 460 | M64: 468 | N64: 475 | O64: =E64 -> 483 | P64: 492 | Q64: 145119 | R64: 509 | S64: =F64 -> 517 | T64: 525 | U64: 349 | V64: 316 | X64: =K64 -> 454 | Y64: =L64 -> 460 | Z64: =M64 -> 468 | AA64: =N64 -> 475 | AB64: =O64 -> 483 | AC64: =P64 -> 492 | AD64: =Q64 -> 145119 | AE64: =R64 -> 509 | ... AI64: =V64 -> 316 | AK64: =SUM(AH64/AD64)-1 -> -0.99759508
B65: Deferred revenue and advance payments | C65: 209860 | D65: 217428 | E65: 228162 | F65: 237974 | H65: 206217 | I65: 188098 | J65: 165934 | K65: =D65 -> 217428 | L65: 211768 | M65: 195817 | N65: 179167 | O65: =E65 -> 228162 | P65: 215955 | Q65: 204837 | R65: 184402 | S65: =F65 -> 237974 | T65: 215693 | U65: 214251 | V65: 200641 | X65: =K65 -> 217428 | Y65: =L65 -> 211768 | Z65: =M65 -> 195817 | AA65: =N65 -> 179167 | AB65: =O65 -> 228162 | AC65: =P65 -> 215955 | AD65: =Q65 -> 204837 | AE65: =R65 -> 184402 | ... AI65: =V65 -> 200641 | AK65: =SUM(AH65/AD65)-1 -> 0.045958494
B66: Total Current Liabilities | C66: =SUM(C61:C65) -> 311985 | D66: =SUM(D61:D65) -> 317403 | E66: =SUM(E61:E65) -> 323273 | F66: =SUM(F61:F65) -> 355384 | H66: =SUM(H61:H65) -> 304875 | I66: =SUM(I61:I65) -> 274100 | J66: =SUM(J61:J65) -> 260520 | K66: =SUM(K61:K65) -> 317403 | L66: =SUM(L61:L65) -> 312399 | M66: =SUM(M61:M65) -> 272930 | N66: =SUM(N61:N65) -> 267721 | O66: =SUM(O61:O65) -> 323273 | ... V66: =SUM(V61:V65) -> 324090 | X66: =SUM(X61:X65) -> 317403 | Y66: =SUM(Y61:Y65) -> 312399 | Z66: =SUM(Z61:Z65) -> 272930 | AA66: =SUM(AA61:AA65) -> 267721 | AB66: =SUM(AB61:AB65) -> 323273 | AC66: =SUM(AC61:AC65) -> 309808 | AD66: =SUM(AD61:AD65) -> 446063 | AE66: =SUM(AE61:AE65) -> 288111 | ... AI66: =SUM(AI61:AI65) -> 324090 | AK66: =SUM(AH66/AD66)-1 -> -0.29478123
B68: Non-Current Liabilities
B69: Long-term debt, net | C69: 2155151 | D69: 2378560 | E69: 2182108 | F69: 7191158 | H69: 2361865 | I69: 2374863 | J69: 2376935 | K69: =D69 -> 2378560 | L69: 2175918 | M69: 2177974 | N69: 2180038 | O69: =E69 -> 2182108 | P69: 3558801 | Q69: 3703381 | R69: 4211949 | S69: =F69 -> 7191158 | T69: 8140156 | U69: 8162281 | V69: 8173587 | X69: =K69 -> 2378560 | Y69: =L69 -> 2175918 | Z69: =M69 -> 2177974 | AA69: =N69 -> 2180038 | AB69: =O69 -> 2182108 | AC69: =P69 -> 3558801 | AD69: =Q69 -> 3703381 | AE69: =R69 -> 4211949 | ... AI69: =V69 -> 8173587 | AK69: =SUM(AH69/AD69)-1 -> 1.2040079
B70: Deferred revenue and advance payments | C70: 8089 | D70: 12763 | E70: 8524 | F70: 4970 | H70: 8236 | I70: 8497 | J70: 8754 | K70: =D70 -> 12763 | L70: 11646 | M70: 11244 | N70: 7638 | O70: =E70 -> 8524 | P70: 6486 | Q70: 5964 | R70: 6344 | S70: =F70 -> 4970 | T70: 3981 | U70: 4197 | V70: 3450 | X70: =K70 -> 12763 | Y70: =L70 -> 11646 | Z70: =M70 -> 11244 | AA70: =N70 -> 7638 | AB70: =O70 -> 8524 | AC70: =P70 -> 6486 | AD70: =Q70 -> 5964 | AE70: =R70 -> 6344 | ... AI70: =V70 -> 3450 | AK70: =SUM(AH70/AD70)-1 -> -0.29627767
B71: Operating lease liabilities | C71: 76608 | D71: 67344 | E71: 61086 | F71: 56403 | H71: 73956 | I71: 72162 | J71: 69278 | K71: =D71 -> 67344 | L71: 65355 | M71: 63814 | N71: 59720 | O71: =E71 -> 61086 | P71: 58430 | Q71: 56544 | R71: 57495 | S71: =F71 -> 56403 | T71: 53691 | U71: 51218 | V71: 48162 | X71: =K71 -> 67344 | Y71: =L71 -> 65355 | Z71: =M71 -> 63814 | AA71: =N71 -> 59720 | AB71: =O71 -> 61086 | AC71: =P71 -> 58430 | AD71: =Q71 -> 56544 | AE71: =R71 -> 57495 | ... AI71: =V71 -> 48162 | AK71: =SUM(AH71/AD71)-1 -> -0.094192134
B72: Other long-term liabilities | C72: 26224 | D72: 17124 | E72: 22208 | F72: 5379 | H72: 26347 | I72: 25706 | J72: 30088 | K72: =D72 -> 17124 | L72: 17675 | M72: 17826 | N72: 18231 | O72: =E72 -> 22208 | P72: 17552 | Q72: 5965 | R72: 5676 | S72: =F72 -> 5379 | T72: 4439 | U72: 4672 | V72: 4790 | X72: =K72 -> 17124 | Y72: =L72 -> 17675 | Z72: =M72 -> 17826 | AA72: =N72 -> 18231 | AB72: =O72 -> 22208 | AC72: =P72 -> 17552 | AD72: =Q72 -> 5965 | AE72: =R72 -> 5676 | ... AI72: =V72 -> 4790 | AK72: =SUM(AH72/AD72)-1 -> -0.21676446
B73: Deferred tax liabilities | C73: 109 | D73: 198 | E73: 357 | F73: 407 | H73: 109 | I73: 105 | J73: 0 | K73: =D73 -> 198 | L73: 198 | M73: 198 | N73: 198 | O73: =E73 -> 357 | P73: 357 | Q73: 357 | R73: 357 | S73: =F73 -> 407 | T73: 1883071 | U73: 5865510 | V73: 6947911 | X73: =K73 -> 198 | Y73: =L73 -> 198 | Z73: =M73 -> 198 | AA73: =N73 -> 198 | AB73: =O73 -> 357 | AC73: =P73 -> 357 | AD73: =Q73 -> 357 | AE73: =R73 -> 357 | ... AI73: =V73 -> 6947911 | AK73: =SUM(AH73/AD73)-1 -> 16429
B74: Total Liabilities | C74: =SUM(C69:C73)+C66 -> 2578166 | D74: =SUM(D69:D73)+D66 -> 2793392 | E74: =SUM(E69:E73)+E66 -> 2597556 | F74: =SUM(F69:F73)+F66 -> 7613701 | H74: =SUM(H69:H73)+H66 -> 2775388 | I74: =SUM(I69:I73)+I66 -> 2755433 | J74: =SUM(J69:J73)+J66 -> 2745575 | K74: =SUM(K69:K73)+K66 -> 2793392 | L74: =SUM(L69:L73)+L66 -> 2583191 | M74: =SUM(M69:M73)+M66 -> 2543986 | N74: =SUM(N69:N73)+N66 -> 2533546 | O74: =SUM(O69:O73)+O66 -> 2597556 | ... V74: =SUM(V69:V73)+V66 -> 15501990 | X74: =SUM(X69:X73)+X66 -> 2793392 | Y74: =SUM(Y69:Y73)+Y66 -> 2583191 | Z74: =SUM(Z69:Z73)+Z66 -> 2543986 | AA74: =SUM(AA69:AA73)+AA66 -> 2533546 | AB74: =SUM(AB69:AB73)+AB66 -> 2597556 | AC74: =SUM(AC69:AC73)+AC66 -> 3951434 | AD74: =SUM(AD69:AD73)+AD66 -> 4218274 | AE74: =SUM(AE69:AE73)+AE66 -> 4569932 | ... AI74: =SUM(AI69:AI73)+AI66 -> 15501990 | AK74: =SUM(AH74/AD74)-1 -> 2.4142993
B76: Preferred Stock | C76: 0 | D76: 0 | E76: 0 | F76: 0 | H76: 0 | I76: 0 | J76: 0 | K76: =D76 -> 0 | L76: 0 | M76: 0 | N76: 0 | O76: =E76 -> 0 | P76: 0 | Q76: 0 | R76: 0 | S76: =F76 -> 0 | T76: =593624+710873 -> 1304497 | U76: =1040394+874041+979486 -> 2893921 | V76: 5786330 | X76: =K76 -> 0 | Y76: =L76 -> 0 | Z76: =M76 -> 0 | AA76: =N76 -> 0 | AB76: =O76 -> 0 | AC76: =P76 -> 0 | AD76: =Q76 -> 0 | AE76: =R76 -> 0 | ... AI76: =V76 -> 5786330 | AK76: =SUM(AH76/AD76)-1 -> #DIV/0!
B77: Class A Common Stock | C77: 18 | D77: 18 | E77: 24 | F77: 226 | H77: 18 | I77: 18 | J77: 18 | K77: =D77 -> 18 | L77: 20 | M77: 21 | N77: 21 | O77: =E77 -> 24 | P77: 24 | Q77: 26 | R77: 192 | S77: =F77 -> 226 | T77: 247 | U77: 261 | V77: 267 | X77: =K77 -> 18 | Y77: =L77 -> 20 | Z77: =M77 -> 21 | AA77: =N77 -> 21 | AB77: =O77 -> 24 | AC77: =P77 -> 24 | AD77: =Q77 -> 26 | AE77: =R77 -> 192 | ... AI77: =V77 -> 267 | AK77: =SUM(AH77/AD77)-1 -> 9.0384615
B78: Class B Convertible Common Stock | C78: 2 | D78: 2 | E78: 2 | F78: 20 | H78: 2 | I78: 2 | J78: 2 | K78: =D78 -> 2 | L78: 2 | M78: 2 | N78: 2 | O78: =E78 -> 2 | P78: 2 | Q78: 2 | R78: 20 | S78: =F78 -> 20 | T78: 20 | U78: 20 | V78: 20 | X78: =K78 -> 2 | Y78: =L78 -> 2 | Z78: =M78 -> 2 | AA78: =N78 -> 2 | AB78: =O78 -> 2 | AC78: =P78 -> 2 | AD78: =Q78 -> 2 | AE78: =R78 -> 20 | ... AI78: =V78 -> 20 | AK78: =SUM(AH78/AD78)-1 -> 9
B79: Additional paid-in capital | C79: 1727143 | D79: 1841120 | E79: 3957728 | F79: 20411998 | H79: 1743944 | I79: 1760288 | J79: 1778660 | K79: =D79 -> 1841120 | L79: 2205518 | M79: 2559268 | N79: 2726191 | O79: =E79 -> 3957728 | P79: 4247704 | Q79: 4785336 | R79: 6060206 | S79: =F79 -> 20411998 | T79: 25881089 | U79: 31158044 | V79: 33390487 | X79: =K79 -> 1841120 | Y79: =L79 -> 2205518 | Z79: =M79 -> 2559268 | AA79: =N79 -> 2726191 | AB79: =O79 -> 3957728 | AC79: =P79 -> 4247704 | AD79: =Q79 -> 4785336 | AE79: =R79 -> 6060206 | ... AI79: =V79 -> 33390487 | AK79: =SUM(AH79/AD79)-1 -> 5.5111507
B80: Treasury stock | C80: -782104 | D80: -782104 | E80: -782104 | F80: 0 | H80: -782104 | I80: -782104 | J80: -782104 | K80: =D80 -> -782104 | L80: -782104 | M80: -782104 | N80: -782104 | O80: =E80 -> -782104 | P80: -782104 | Q80: -782104 | R80: -782104 | S80: =F80 -> 0 | T80: 0 | U80: 0 | V80: 0 | X80: =K80 -> -782104 | Y80: =L80 -> -782104 | Z80: =M80 -> -782104 | AA80: =N80 -> -782104 | AB80: =O80 -> -782104 | AC80: =P80 -> -782104 | AD80: =Q80 -> -782104 | AE80: =R80 -> -782104 | ... AI80: =V80 -> 0 | AK80: =SUM(AH80/AD80)-1 -> -1
B81: Accumulated other comprehensive loss | C81: -7543 | D81: -13801 | E81: -11444 | F81: -15384 | H81: -9552 | I81: -13665 | J81: -18179 | K81: =D81 -> -13801 | L81: -13063 | M81: -13150 | N81: -15355 | O81: =E81 -> -11444 | P81: -13169 | Q81: -13550 | R81: -9580 | S81: =F81 -> -15384 | T81: -11967 | U81: -5020 | V81: -5113 | X81: =K81 -> -13801 | Y81: =L81 -> -13063 | Z81: =M81 -> -13150 | AA81: =N81 -> -15355 | AB81: =O81 -> -11444 | AC81: =P81 -> -13169 | AD81: =Q81 -> -13550 | AE81: =R81 -> -9580 | ... AI81: =V81 -> -5113 | AK81: =SUM(AH81/AD81)-1 -> -0.6295203
B82: (Accumulated deficit) retained earnings | C82: 41442 | D82: -1428355 | E82: -999234 | F82: -2166876 | H82: -89309 | I82: -1151607 | J82: -1178686 | K82: =D82 -> -1428355 | L82: -967162 | M82: -944919 | N82: -1088360 | O82: =E82 -> -999234 | P82: -1052352 | Q82: -1154911 | R82: -1495085 | S82: =F82 -> -2166876 | T82: 6351847 | U82: 16323739 | V82: 18945057 | X82: =K82 -> -1428355 | Y82: =L82 -> -967162 | Z82: =M82 -> -944919 | AA82: =N82 -> -1088360 | AB82: =O82 -> -999234 | AC82: =P82 -> -1052352 | AD82: =Q82 -> -1154911 | AE82: =R82 -> -1495085 | ... AI82: =V82 -> 18945057 | AK82: =SUM(AH82/AD82)-1 -> -15.134196
B83: Total stockholders' equity | C83: =SUM(C76:C82) -> 978958 | D83: =SUM(D76:D82) -> -383120 | E83: =SUM(E76:E82) -> 2164972 | F83: =SUM(F76:F82) -> 18229984 | H83: =SUM(H76:H82) -> 862999 | I83: =SUM(I76:I82) -> -187068 | J83: =SUM(J76:J82) -> -200289 | K83: =SUM(K76:K82) -> -383120 | L83: =SUM(L76:L82) -> 443211 | M83: =SUM(M76:M82) -> 819118 | N83: =SUM(N76:N82) -> 840395 | O83: =SUM(O76:O82) -> 2164972 | ... V83: =SUM(V76:V82) -> 58117048 | X83: =SUM(X76:X82) -> -383120 | Y83: =SUM(Y76:Y82) -> 443211 | Z83: =SUM(Z76:Z82) -> 819118 | AA83: =SUM(AA76:AA82) -> 840395 | AB83: =SUM(AB76:AB82) -> 2164972 | AC83: =SUM(AC76:AC82) -> 2400105 | AD83: =SUM(AD76:AD82) -> 2834799 | AE83: =SUM(AE76:AE82) -> 3773649 | ... AI83: =SUM(AI76:AI82) -> 58117048 | AK83: =SUM(AH83/AD83)-1 -> 16.768796
B84: Total liabilities and stockholders' equity | C84: =SUM(C83+C74) -> 3557124 | D84: =SUM(D83+D74) -> 2410272 | E84: =SUM(E83+E74) -> 4762528 | F84: =SUM(F83+F74) -> 25843685 | H84: =SUM(H83+H74) -> 3638387 | I84: =SUM(I83+I74) -> 2568365 | J84: =SUM(J83+J74) -> 2545286 | K84: =SUM(K83+K74) -> 2410272 | L84: =SUM(L83+L74) -> 3026402 | M84: =SUM(M83+M74) -> 3363104 | N84: =SUM(N83+N74) -> 3373941 | O84: =SUM(O83+O74) -> 4762528 | ... V84: =SUM(V83+V74) -> 73619038 | X84: =SUM(X83+X74) -> 2410272 | Y84: =SUM(Y83+Y74) -> 3026402 | Z84: =SUM(Z83+Z74) -> 3363104 | AA84: =SUM(AA83+AA74) -> 3373941 | AB84: =SUM(AB83+AB74) -> 4762528 | AC84: =SUM(AC83+AC74) -> 6351539 | AD84: =SUM(AD83+AD74) -> 7053073 | AE84: =SUM(AE83+AE74) -> 8343581 | ... AI84: =SUM(AI83+AI74) -> 73619038 | AK84: =SUM(AH84/AD84)-1 -> 8.1837154
B86: Balance Check | C86: =C84-C58 -> 0 | D86: =D84-D58 -> 0 | E86: =E84-E58 -> 0 | F86: =F84-F58 -> 0 | H86: =H84-H58 -> 0 | I86: =I84-I58 -> 0 | J86: =J84-J58 -> 0 | K86: =K84-K58 -> 0 | L86: =L84-L58 -> 0 | M86: =M84-M58 -> 0 | N86: =N84-N58 -> 0 | O86: =O84-O58 -> 0 | ... V86: =V84-V58 -> 0 | X86: =X84-X58 -> 0 | Y86: =Y84-Y58 -> 0 | Z86: =Z84-Z58 -> 0 | AA86: =AA84-AA58 -> 0 | AB86: =AB84-AB58 -> 0 | AC86: =AC84-AC58 -> 0 | AD86: =AD84-AD58 -> 0 | AE86: =AE84-AE58 -> 0 | ... AI86: =AI84-AI58 -> 0
A89: X | B89: Cash-Flows Statement | D89: FYE | H89: Quarterly | R89: Quarterly | AD89: LTM | AK89: Variance
B90: =B7 -> Fiscal Period | C90: =C7 -> 2021 | D90: =D7 -> 2022 | E90: =E7 -> 2023 | F90: =F7 -> 2024 | H90: =H7 -> 1Q22 | I90: =I7 -> 2Q22 | J90: =J7 -> 3Q22 | K90: =K7 -> 4Q22 | L90: =L7 -> 1Q23 | M90: =M7 -> 2Q23 | N90: =N7 -> 3Q23 | O90: =O7 -> 4Q23 | ... V90: =V7 -> 3Q25 | X90: =X7 -> 4Q22 | Y90: =Y7 -> 1Q23 | Z90: =Z7 -> 2Q23 | AA90: =AA7 -> 3Q23 | AB90: =AB7 -> 4Q23 | AC90: =AC7 -> 1Q24 | AD90: =AD7 -> 2Q24 | AE90: =AE7 -> 3Q24 | ... AI90: =AI7 -> 3Q25
B91: =B8 -> Fiscal Period End Date | C91: =C8 -> 44561 | D91: =D8 -> 44926 | E91: =E8 -> 45291 | F91: =F8 -> 45657 | H91: =H8 -> 44651 | I91: =I8 -> 44742 | J91: =J8 -> 44834 | K91: =K8 -> 44926 | L91: =L8 -> 45016 | M91: =M8 -> 45107 | N91: =N8 -> 45199 | O91: =O8 -> 45291 | ... V91: =V8 -> 45930 | X91: =X8 -> 44926 | Y91: =Y8 -> 45016 | Z91: =Z8 -> 45107 | AA91: =AA8 -> 45199 | AB91: =AB8 -> 45291 | AC91: =AC8 -> 45382 | AD91: =AD8 -> 45473 | AE91: =AE8 -> 45565 | ... AI91: =AI8 -> 45930
B93: Cash-Flows From Operating Activities
B94: Net income (loss) | C94: =C32 -> -535480 | D94: =D32 -> -1469797 | E94: =E32 -> 429121 | F94: =F32 -> -1166661 | H94: =H32 -> -130751 | I94: =I32 -> -1062298 | J94: =J32 -> -27079 | K94: =K32 -> -249669 | L94: =L32 -> 461193 | M94: =M32 -> 22243 | N94: =N32 -> -143441 | O94: =O32 -> 89126 | ... V94: =V32 -> 2785024 | X94: =SUM(I94:L94) -> -877853 | Y94: =SUM(J94:M94) -> 206688 | Z94: =SUM(K94:N94) -> 90326 | AA94: =SUM(L94:O94) -> 429121 | AB94: =SUM(M94:P94) -> -85190 | AC94: =SUM(N94:Q94) -> -209992 | AD94: =SUM(N94:Q94) -> -209992 | AE94: =SUM(O94:R94) -> -406725 | AF94: =SUM(P94:S94) -> -1166661 | AG94: =SUM(Q94:T94) -> -5330913 | AH94: =SUM(R94:U94) -> 4792492 | AI94: =SUM(S94:V94) -> 7917690 | AK94: =SUM(AH94/AD94)-1 -> -23.82226
B96: Adjustments to reconcile net income:
B97: Depreciation and amortization | C97: 11358 | D97: 10874 | E97: 14527 | F97: 17808 | H97: 2691 | I97: =4767-H97 -> 2076 | J97: =6917-I97-H97 -> 2150 | K97: =SUM(D97-SUM(H97:J97)) -> 3957 | L97: 3431 | M97: =6661-L97 -> 3230 | N97: =9405-M97-L97 -> 2744 | O97: =SUM(E97-SUM(L97:N97)) -> 5122 | P97: 3050 | Q97: =6701-P97 -> 3651 | R97: =12679-Q97-P97 -> 5978 | S97: =SUM(F97-SUM(P97:R97)) -> 5129 | T97: 6575 | U97: =15693-T97 -> 9118 | V97: =19888-U97-T97 -> 4195 | X97: =SUM(H97:K97) -> 10874 | Y97: =SUM(I97:L97) -> 11614 | Z97: =SUM(J97:M97) -> 12768 | AA97: =SUM(K97:N97) -> 13362 | AB97: =SUM(L97:O97) -> 14527 | AC97: =SUM(M97:P97) -> 14146 | AD97: =SUM(N97:Q97) -> 14567 | AE97: =SUM(O97:R97) -> 17801 | ... AI97: =SUM(S97:V97) -> 25017 | AK97: =SUM(AH97/AD97)-1 -> 0.83977483
B98: Reduction in carrying amount of right-of-use assets | C98: 8189 | D98: 8072 | E98: 8643 | F98: 8475 | H98: 1994 | I98: =3990-H98 -> 1996 | J98: =6020-I98-H98 -> 2030 | K98: =SUM(D98-SUM(H98:J98)) -> 2052 | L98: 2124 | M98: =4320-L98 -> 2196 | N98: =6438-M98-L98 -> 2118 | O98: =SUM(E98-SUM(L98:N98)) -> 2205 | P98: 2110 | Q98: =4126-P98 -> 2016 | R98: =6228-Q98-P98 -> 2102 | S98: =SUM(F98-SUM(P98:R98)) -> 2247 | T98: 2240 | U98: =4526-T98 -> 2286 | V98: =6796-U98-T98 -> 2270 | X98: =SUM(H98:K98) -> 8072 | Y98: =SUM(I98:L98) -> 8202 | Z98: =SUM(J98:M98) -> 8402 | AA98: =SUM(K98:N98) -> 8490 | AB98: =SUM(L98:O98) -> 8643 | AC98: =SUM(M98:P98) -> 8629 | AD98: =SUM(N98:Q98) -> 8449 | AE98: =SUM(O98:R98) -> 8433 | ... AI98: =SUM(S98:V98) -> 9043 | AK98: =SUM(AH98/AD98)-1 -> 0.050420168
B99: Deferred taxes | C99: -284221 | D99: 131493 | E99: -568949 | F99: -774586 | H99: -57445 | I99: =76109-H99 -> 133554 | J99: =90166-I99-H99 -> 14057 | K99: =SUM(D99-SUM(H99:J99)) -> 41327 | L99: -460061 | M99: =-530628-L99 -> -70567 | N99: =-425986-M99-L99 -> 104642 | O99: =SUM(E99-SUM(L99:N99)) -> -142963 | P99: -161097 | Q99: =-278067-P99 -> -116970 | R99: =-419965-Q99-P99 -> -141898 | S99: =SUM(F99-SUM(P99:R99)) -> -354621 | T99: -1728363 | U99: =2254166-T99 -> 3982529 | V99: =3336445-U99-T99 -> 1082279 | X99: =SUM(H99:K99) -> 131493 | Y99: =SUM(I99:L99) -> -271123 | Z99: =SUM(J99:M99) -> -475244 | AA99: =SUM(K99:N99) -> -384659 | AB99: =SUM(L99:O99) -> -568949 | AC99: =SUM(M99:P99) -> -269985 | AD99: =SUM(N99:Q99) -> -316388 | AE99: =SUM(O99:R99) -> -562928 | ... AI99: =SUM(S99:V99) -> 2981824 | AK99: =SUM(AH99/AD99)-1 -> -6.5553529
B100: Share-based compensation expense | C100: 44126 | D100: 63619 | E100: 69571 | F100: 77124 | H100: 14394 | I100: =29688-H100 -> 15294 | J100: =46587-I100-H100 -> 16899 | K100: =SUM(D100-SUM(H100:J100)) -> 17032 | L100: 17555 | M100: =33049-L100 -> 15494 | N100: =49855-M100-L100 -> 16806 | O100: =SUM(E100-SUM(L100:N100)) -> 19716 | P100: 17791 | Q100: =38412-P100 -> 20621 | R100: =57789-Q100-P100 -> 19377 | S100: =SUM(F100-SUM(P100:R100)) -> 19335 | T100: 11819 | U100: =27561-T100 -> 15742 | V100: =43044-U100-T100 -> 15483 | X100: =SUM(H100:K100) -> 63619 | Y100: =SUM(I100:L100) -> 66780 | Z100: =SUM(J100:M100) -> 66980 | AA100: =SUM(K100:N100) -> 66887 | AB100: =SUM(L100:O100) -> 69571 | AC100: =SUM(M100:P100) -> 69807 | AD100: =SUM(N100:Q100) -> 74934 | AE100: =SUM(O100:R100) -> 77505 | ... AI100: =SUM(S100:V100) -> 62379 | AK100: =SUM(AH100/AD100)-1 -> -0.11558171
B101: Credit losses and sales allowances | C101: 1509 | D101: 939 | E101: 1387 | F101: 649 | H101: 272 | I101: =606-H101 -> 334 | J101: =1189-I101-H101 -> 583 | K101: =SUM(D101-SUM(H101:J101)) -> -250 | L101: 21 | M101: =438-L101 -> 417 | N101: =752-M101-L101 -> 314 | O101: =SUM(E101-SUM(L101:N101)) -> 635 | P101: 24 | Q101: =-44-P101 -> -68 | R101: =262-Q101-P101 -> 306 | S101: =SUM(F101-SUM(P101:R101)) -> 387 | T101: 0 | U101: 0 | V101: 0 | X101: =SUM(H101:K101) -> 939 | Y101: =SUM(I101:L101) -> 688 | Z101: =SUM(J101:M101) -> 771 | AA101: =SUM(K101:N101) -> 502 | AB101: =SUM(L101:O101) -> 1387 | AC101: =SUM(M101:P101) -> 1390 | AD101: =SUM(N101:Q101) -> 905 | AE101: =SUM(O101:R101) -> 897 | ... AI101: =SUM(S101:V101) -> 387 | AK101: =SUM(AH101/AD101)-1 -> -0.23425414
B102: Amortization of issuance costs on long-term debt | C102: 7201 | D102: 8694 | E102: 8808 | F102: 15336 | H102: 2129 | I102: =4297-H102 -> 2168 | J102: =6490-I102-H102 -> 2193 | K102: =SUM(D102-SUM(H102:J102)) -> 2204 | L102: 2210 | M102: =4400-L102 -> 2190 | N102: =6599-M102-L102 -> 2199 | O102: =SUM(E102-SUM(L102:N102)) -> 2209 | P102: 2557 | Q102: =6399-P102 -> 3842 | R102: =10231-Q102-P102 -> 3832 | S102: =SUM(F102-SUM(P102:R102)) -> 5105 | T102: 6048 | U102: =12445-T102 -> 6397 | V102: =18911-U102-T102 -> 6466 | X102: =SUM(H102:K102) -> 8694 | Y102: =SUM(I102:L102) -> 8775 | Z102: =SUM(J102:M102) -> 8797 | AA102: =SUM(K102:N102) -> 8803 | AB102: =SUM(L102:O102) -> 8808 | AC102: =SUM(M102:P102) -> 9155 | AD102: =SUM(N102:Q102) -> 10807 | AE102: =SUM(O102:R102) -> 12440 | ... AI102: =SUM(S102:V102) -> 24016 | AK102: =SUM(AH102/AD102)-1 -> 0.97853243
B103: Other Operating Activities | C103: =830621-561 -> 830060 | D103: =1286286-360 -> 1285926 | E103: =115851-44686-506 -> 70659 | F103: =1789862+22933-1265 -> 1811530 | H103: 170091 | I103: =1087929-H103 -> 917838 | J103: =1088656-I103-H103 -> 727 | K103: =SUM(D103-SUM(H103:J103)) -> 197270 | L103: =18911-44686-102 -> -25877 | M103: =43054-44686-102-L103 -> 24143 | N103: =76613-44686-162-M103-L103 -> 33499 | O103: =SUM(E103-SUM(L103:N103)) -> 38894 | P103: =191633-73 -> 191560 | Q103: =371723-73-P103 -> 180090 | R103: =783807+22933-73-Q103-P103 -> 435017 | S103: =SUM(F103-SUM(P103:R103)) -> 1004863 | T103: 5906005 | U103: =-8141509-T103 -> -14047514 | V103: =-12032356-U103-T103 -> -3890847 | X103: =SUM(H103:K103) -> 1285926 | Y103: =SUM(I103:L103) -> 1089958 | Z103: =SUM(J103:M103) -> 196263 | AA103: =SUM(K103:N103) -> 229035 | AB103: =SUM(L103:O103) -> 70659 | AC103: =SUM(M103:P103) -> 288096 | AD103: =SUM(N103:Q103) -> 444043 | AE103: =SUM(O103:R103) -> 845561 | ... AI103: =SUM(S103:V103) -> -11027493 | AK103: =SUM(AH103/AD103)-1 -> -16.092297
B105: Changes in assets and liabilities, net of effect of acquisitions:
B106: Accounts receivable | C106: 2618 | D106: -5292 | E106: 10307 | F106: 5688 | H106: 8183 | I106: =9281-H106 -> 1098 | J106: =5586-I106-H106 -> -3695 | K106: =SUM(D106-SUM(H106:J106)) -> -10878 | L106: 10241 | M106: =17737-L106 -> 7496 | N106: =6627-M106-L106 -> -11110 | O106: =SUM(E106-SUM(L106:N106)) -> 3680 | P106: 12166 | Q106: =20119-P106 -> 7953 | R106: =27374-Q106-P106 -> 7255 | S106: =SUM(F106-SUM(P106:R106)) -> -21686 | T106: 10542 | U106: =14962-T106 -> 4420 | V106: =24324-U106-T106 -> 9362 | X106: =SUM(H106:K106) -> -5292 | Y106: =SUM(I106:L106) -> -3234 | Z106: =SUM(J106:M106) -> 3164 | AA106: =SUM(K106:N106) -> -4251 | AB106: =SUM(L106:O106) -> 10307 | AC106: =SUM(M106:P106) -> 12232 | AD106: =SUM(N106:Q106) -> 12689 | AE106: =SUM(O106:R106) -> 31054 | ... AI106: =SUM(S106:V106) -> 2638 | AK106: =SUM(AH106/AD106)-1 -> -0.95815273
B107: Prepaid expenses and other current assets | C107: -25 | D107: -6342 | E107: -11358 | F107: 3804 | H107: -2838 | I107: =-7077-H107 -> -4239 | J107: =-7837-I107-H107 -> -760 | K107: =SUM(D107-SUM(H107:J107)) -> 1495 | L107: 423 | M107: =4861-L107 -> 4438 | N107: =-99-M107-L107 -> -4960 | O107: =SUM(E107-SUM(L107:N107)) -> -11259 | P107: -6260 | Q107: =7914-P107 -> 14174 | R107: =4868-Q107-P107 -> -3046 | S107: =SUM(F107-SUM(P107:R107)) -> -1064 | T107: =-7835 -> -7835 | U107: =-16029-T107 -> -8194 | V107: =-19129-U107-T107 -> -3100 | X107: =SUM(H107:K107) -> -6342 | Y107: =SUM(I107:L107) -> -3081 | Z107: =SUM(J107:M107) -> 5596 | AA107: =SUM(K107:N107) -> 1396 | AB107: =SUM(L107:O107) -> -11358 | AC107: =SUM(M107:P107) -> -18041 | AD107: =SUM(N107:Q107) -> -8305 | AE107: =SUM(O107:R107) -> -6391 | ... AI107: =SUM(S107:V107) -> -20193 | AK107: =SUM(AH107/AD107)-1 -> 1.4249247
B108: Deposits and other assets | C108: -1713 | D108: -7455 | E108: -632 | F108: -10668 | H108: -5801 | I108: =-6578-H108 -> -777 | J108: =-8314-I108-H108 -> -1736 | K108: =SUM(D108-SUM(H108:J108)) -> 859 | L108: -6 | M108: =1189-L108 -> 1195 | N108: =-321-M108-L108 -> -1510 | O108: =SUM(E108-SUM(L108:N108)) -> -311 | P108: -5339 | Q108: =-8163-P108 -> -2824 | R108: =-6748-Q108-P108 -> 1415 | S108: =SUM(F108-SUM(P108:R108)) -> -3920 | T108: -1519 | U108: =-2429-T108 -> -910 | V108: =1720-U108-T108 -> 4149 | X108: =SUM(H108:K108) -> -7455 | Y108: =SUM(I108:L108) -> -1660 | Z108: =SUM(J108:M108) -> 312 | AA108: =SUM(K108:N108) -> 538 | AB108: =SUM(L108:O108) -> -632 | AC108: =SUM(M108:P108) -> -5965 | AD108: =SUM(N108:Q108) -> -9984 | AE108: =SUM(O108:R108) -> -7059 | ... AI108: =SUM(S108:V108) -> -2200 | AK108: =SUM(AH108/AD108)-1 -> -0.50580929
B109: Accounts payable and accrued expenses | C109: 3749 | D109: -3521 | E109: -634 | F109: 1141 | H109: -2041 | I109: =-10216-H109 -> -8175 | J109: =-8880-I109-H109 -> 1336 | K109: =SUM(D109-SUM(H109:J109)) -> 5359 | L109: 4230 | M109: =-9400-L109 -> -13630 | N109: =-8005-M109-L109 -> 1395 | O109: =SUM(E109-SUM(L109:N109)) -> 7371 | P109: -2005 | Q109: =-8164-P109 -> -6159 | R109: =-8318-Q109-P109 -> -154 | S109: =SUM(F109-SUM(P109:R109)) -> 9459 | T109: -1431 | U109: =-3250-T109 -> -1819 | V109: =6709-U109-T109 -> 9959 | X109: =SUM(H109:K109) -> -3521 | Y109: =SUM(I109:L109) -> 2750 | Z109: =SUM(J109:M109) -> -2705 | AA109: =SUM(K109:N109) -> -2646 | AB109: =SUM(L109:O109) -> -634 | AC109: =SUM(M109:P109) -> -6869 | AD109: =SUM(N109:Q109) -> 602 | AE109: =SUM(O109:R109) -> -947 | ... AI109: =SUM(S109:V109) -> 16168 | AK109: =SUM(AH109/AD109)-1 -> 9.0581395
B110: Accrued compensation and employee benefits | C110: 2374 | D110: -12344 | E110: -12000 | F110: -34563 | H110: -12735 | I110: =-9802-H110 -> 2933 | J110: =-13105-I110-H110 -> -3303 | K110: =SUM(D110-SUM(H110:J110)) -> 761 | L110: -16327 | M110: =-15559-L110 -> 768 | N110: =-15186-M110-L110 -> 373 | O110: =SUM(E110-SUM(L110:N110)) -> 3186 | P110: -13279 | Q110: =-18059-P110 -> -4780 | R110: =-26383-Q110-P110 -> -8324 | S110: =SUM(F110-SUM(P110:R110)) -> -8180 | T110: -30385 | U110: =-28187-T110 -> 2198 | V110: =-40399-U110-T110 -> -12212 | X110: =SUM(H110:K110) -> -12344 | Y110: =SUM(I110:L110) -> -15936 | Z110: =SUM(J110:M110) -> -18101 | AA110: =SUM(K110:N110) -> -14425 | AB110: =SUM(L110:O110) -> -12000 | AC110: =SUM(M110:P110) -> -8952 | AD110: =SUM(N110:Q110) -> -14500 | AE110: =SUM(O110:R110) -> -23197 | ... AI110: =SUM(S110:V110) -> -48579 | AK110: =SUM(AH110/AD110)-1 -> 2.0821379
B111: Accrued interest | C111: 1222 | D111: 1336 | E111: -1336 | F111: 4193 | H111: 9051 | I111: =776-H111 -> -8275 | J111: =9901-I111-H111 -> 9125 | K111: =SUM(D111-SUM(H111:J111)) -> -8565 | L111: 7539 | M111: =-1336-L111 -> -8875 | N111: =7539-M111-L111 -> 8875 | O111: =SUM(E111-SUM(L111:N111)) -> -8875 | P111: 9385 | Q111: =3641-P111 -> -5744 | R111: =4444-Q111-P111 -> 803 | S111: =SUM(F111-SUM(P111:R111)) -> -251 | T111: 421 | U111: =71-T111 -> -350 | V111: =421-U111-T111 -> 350 | X111: =SUM(H111:K111) -> 1336 | Y111: =SUM(I111:L111) -> -176 | Z111: =SUM(J111:M111) -> -776 | AA111: =SUM(K111:N111) -> -1026 | AB111: =SUM(L111:O111) -> -1336 | AC111: =SUM(M111:P111) -> 510 | AD111: =SUM(N111:Q111) -> 3641 | AE111: =SUM(O111:R111) -> -4431 | ... AI111: =SUM(S111:V111) -> 170 | AK111: =SUM(AH111/AD111)-1 -> -0.82889316
B112: Deferred revenue and advance payments | C112: 14710 | D112: 14839 | E112: 2362 | F112: 1049 | H112: 48895 | I112: =36945-H112 -> -11950 | J112: =25401-I112-H112 -> -11544 | K112: =SUM(D112-SUM(H112:J112)) -> -10562 | L112: 33352 | M112: =26952-L112 -> -6400 | N112: =9901-M112-L112 -> -17051 | O112: =SUM(E112-SUM(L112:N112)) -> -7539 | P112: 41560 | Q112: =24994-P112 -> -16566 | R112: =3484-Q112-P112 -> -21510 | S112: =SUM(F112-SUM(P112:R112)) -> -2435 | T112: 43289 | U112: =26095-T112 -> -17194 | V112: =7027-U112-T112 -> -19068 | X112: =SUM(H112:K112) -> 14839 | Y112: =SUM(I112:L112) -> -704 | Z112: =SUM(J112:M112) -> 4846 | AA112: =SUM(K112:N112) -> -661 | AB112: =SUM(L112:O112) -> 2362 | AC112: =SUM(M112:P112) -> 10570 | AD112: =SUM(N112:Q112) -> 404 | AE112: =SUM(O112:R112) -> -4055 | ... AI112: =SUM(S112:V112) -> 4592 | AK112: =SUM(AH112/AD112)-1 -> 4.3217822
B113: Operating lease liabilities | C113: -10222 | D113: -9634 | E113: -10218 | F113: -10510 | H113: -2382 | I113: =-4835-H113 -> -2453 | J113: =-7390-I113-H113 -> -2555 | K113: =SUM(D113-SUM(H113:J113)) -> -2244 | L113: -2594 | M113: =-5233-L113 -> -2639 | N113: =-7954-M113-L113 -> -2721 | O113: =SUM(E113-SUM(L113:N113)) -> -2264 | P113: -2896 | Q113: =-5467-P113 -> -2571 | R113: =-7832-Q113-P113 -> -2365 | S113: =SUM(F113-SUM(P113:R113)) -> -2678 | T113: -2618 | U113: =-5308-T113 -> -2690 | V113: =-8001-U113-T113 -> -2693 | X113: =SUM(H113:K113) -> -9634 | Y113: =SUM(I113:L113) -> -9846 | Z113: =SUM(J113:M113) -> -10032 | AA113: =SUM(K113:N113) -> -10198 | AB113: =SUM(L113:O113) -> -10218 | AC113: =SUM(M113:P113) -> -10520 | AD113: =SUM(N113:Q113) -> -10452 | AE113: =SUM(O113:R113) -> -10096 | ... AI113: =SUM(S113:V113) -> -10679 | AK113: =SUM(AH113/AD113)-1 -> -0.0096632223
B114: Other long-term liabilities | C114: -1622 | D114: -8196 | E114: 2454 | F114: -2841 | H114: -25 | I114: =32-H114 -> 57 | J114: =150-I114-H114 -> 118 | K114: =SUM(D114-SUM(H114:J114)) -> -8346 | L114: -57 | M114: =-228-L114 -> -171 | N114: =203-M114-L114 -> 431 | O114: =SUM(E114-SUM(L114:N114)) -> 2251 | P114: -7622 | Q114: =-5057-P114 -> 2565 | R114: =-4637-Q114-P114 -> 420 | S114: =SUM(F114-SUM(P114:R114)) -> 1796 | T114: 193 | U114: =415-T114 -> 222 | V114: =488-U114-T114 -> 73 | X114: =SUM(H114:K114) -> -8196 | Y114: =SUM(I114:L114) -> -8228 | Z114: =SUM(J114:M114) -> -8456 | AA114: =SUM(K114:N114) -> -8143 | AB114: =SUM(L114:O114) -> 2454 | AC114: =SUM(M114:P114) -> -5111 | AD114: =SUM(N114:Q114) -> -2375 | AE114: =SUM(O114:R114) -> -2386 | ... AI114: =SUM(S114:V114) -> 2284 | AK114: =SUM(AH114/AD114)-1 -> -2.1077895
B115: Net cash used in operating activities | C115: =SUM(C94:C114) -> 93833 | D115: =SUM(D94:D114) -> 3211 | E115: =SUM(E94:E114) -> 12712 | F115: =SUM(F94:F114) -> -53032 | H115: =SUM(H94:H114) -> 43682 | I115: =SUM(I94:I114) -> -20819 | J115: =SUM(J94:J114) -> -1454 | K115: =SUM(K94:K114) -> -18198 | L115: =SUM(L94:L114) -> 37397 | M115: =SUM(M94:M114) -> -18472 | N115: =SUM(N94:N114) -> -7397 | O115: =SUM(O94:O114) -> 1184 | ... V115: =SUM(V94:V114) -> -8310 | X115: =SUM(X94:X114) -> 595155 | Y115: =SUM(Y94:Y114) -> 1081467 | Z115: =SUM(Z94:Z114) -> -117089 | AA115: =SUM(AA94:AA114) -> 332125 | AB115: =SUM(AB94:AB114) -> -501599 | AC115: =SUM(AC94:AC114) -> -120900 | AD115: =SUM(AD94:AD114) -> -955 | AE115: =SUM(AE94:AE114) -> -34524 | ... AI115: =SUM(AI94:AI114) -> -62936 | AK115: =SUM(AH115/AD115)-1 -> 99.096335
B117: Cash flows from investing activities:
B118: Purchases of digital assets | C118: -2626529 | D118: -287921 | E118: -1902299 | F118: -22072759 | H118: -215500 | I118: =-225500-H118 -> -10000 | J118: =-231478-I118-H118 -> -5978 | K118: =SUM(D118-SUM(H118:J118)) -> -56443 | L118: -179275 | M118: =-526278-L118 -> -347003 | N118: =-687959-M118-L118 -> -161681 | O118: =SUM(E118-SUM(L118:N118)) -> -1214340 | P118: -1639309 | Q118: =-2433137-P118 -> -793828 | R118: =-4008210-Q118-P118 -> -1575073 | S118: =SUM(F118-SUM(P118:R118)) -> -18064549 | T118: -7661663 | U118: =-14430868-T118 -> -6769205 | V118: =-19382948-U118-T118 -> -4952080 | X118: =SUM(H118:K118) -> -287921 | Y118: =SUM(I118:L118) -> -251696 | Z118: =SUM(J118:M118) -> -588699 | AA118: =SUM(K118:N118) -> -744402 | AB118: =SUM(L118:O118) -> -1902299 | AC118: =SUM(M118:P118) -> -3362333 | AD118: =SUM(N118:Q118) -> -3809158 | AE118: =SUM(O118:R118) -> -5222550 | ... AI118: =SUM(S118:V118) -> -37447497 | AK118: =SUM(AH118/AD118)-1 -> 7.9443625
B119: Purchases of property and equipment | C119: -2706 | D119: -2486 | E119: -2938 | F119: -2978 | H119: -641 | I119: =-1519-H119 -> -878 | J119: =-1851-I119-H119 -> -332 | K119: =SUM(D119-SUM(H119:J119)) -> -635 | L119: -499 | M119: =-1138-L119 -> -639 | N119: =-2591-M119-L119 -> -1453 | O119: =SUM(E119-SUM(L119:N119)) -> -347 | P119: -1545 | Q119: =-2268-P119 -> -723 | R119: =-2694-Q119-P119 -> -426 | S119: =SUM(F119-SUM(P119:R119)) -> -284 | T119: -2737 | U119: =-4831-T119 -> -2094 | V119: =-7628-U119-T119 -> -2797 | X119: =SUM(H119:K119) -> -2486 | Y119: =SUM(I119:L119) -> -2344 | Z119: =SUM(J119:M119) -> -2105 | AA119: =SUM(K119:N119) -> -3226 | AB119: =SUM(L119:O119) -> -2938 | AC119: =SUM(M119:P119) -> -3984 | AD119: =SUM(N119:Q119) -> -4068 | AE119: =SUM(O119:R119) -> -3041 | ... AI119: =SUM(S119:V119) -> -7912 | AK119: =SUM(AH119/AD119)-1 -> 0.3620944
B120: Other Investing Activities | C120: 0 | D120: 11817 | E120: 0 | F120: -10500 | H120: 0 | I120: 0 | J120: 0 | K120: =SUM(D120-SUM(H120:J120)) -> 11817 | L120: 0 | M120: 0 | N120: 0 | O120: =SUM(E120-SUM(L120:N120)) -> 0 | P120: 0 | Q120: 0 | R120: 0 | S120: =SUM(F120-SUM(P120:R120)) -> -10500 | T120: -6000 | U120: =-22000-T120 -> -16000 | V120: =-27000-U120-T120 -> -5000 | X120: =SUM(H120:K120) -> 11817 | Y120: =SUM(I120:L120) -> 11817 | Z120: =SUM(J120:M120) -> 11817 | AA120: =SUM(K120:N120) -> 11817 | AB120: =SUM(L120:O120) -> 0 | AC120: =SUM(M120:P120) -> 0 | AD120: =SUM(N120:Q120) -> 0 | AE120: =SUM(O120:R120) -> 0 | ... AI120: =SUM(S120:V120) -> -37500 | AK120: =SUM(AH120/AD120)-1 -> #DIV/0!
B121: Net cash used in investing activities | C121: =SUM(C118:C120) -> -2629235 | D121: =SUM(D118:D120) -> -278590 | E121: =SUM(E118:E120) -> -1905237 | F121: =SUM(F118:F120) -> -22086237 | H121: =SUM(H118:H120) -> -216141 | I121: =SUM(I118:I120) -> -10878 | J121: =SUM(J118:J120) -> -6310 | K121: =SUM(K118:K120) -> -45261 | L121: =SUM(L118:L120) -> -179774 | M121: =SUM(M118:M120) -> -347642 | N121: =SUM(N118:N120) -> -163134 | O121: =SUM(O118:O120) -> -1214687 | ... V121: =SUM(V118:V120) -> -4959877 | X121: =SUM(X118:X120) -> -278590 | Y121: =SUM(Y118:Y120) -> -242223 | Z121: =SUM(Z118:Z120) -> -578987 | AA121: =SUM(AA118:AA120) -> -735811 | AB121: =SUM(AB118:AB120) -> -1905237 | AC121: =SUM(AC118:AC120) -> -3366317 | AD121: =SUM(AD118:AD120) -> -3813226 | AE121: =SUM(AE118:AE120) -> -5225591 | ... AI121: =SUM(AI118:AI120) -> -37492909 | AK121: =SUM(AH121/AD121)-1 -> 7.9447966
B123: Cash flows from financing activities:
...

Sheet Revenue Drivers
B2: ='Historical Financials'!B2 -> Microstrategy, Inc. (NASDAQ: MSTR) | D2: FYE | H2: Quarterly | R2: Quarterly | AC2: LTM
B3: Segment Anaysis | C3: ='Historical Financials'!C7 -> 2021 | D3: ='Historical Financials'!D7 -> 2022 | E3: ='Historical Financials'!E7 -> 2023 | F3: ='Historical Financials'!F7 -> 2024 | H3: ='Historical Financials'!H7 -> 1Q22 | I3: ='Historical Financials'!I7 -> 2Q22 | J3: ='Historical Financials'!J7 -> 3Q22 | K3: ='Historical Financials'!K7 -> 4Q22 | L3: ='Historical Financials'!L7 -> 1Q23 | M3: ='Historical Financials'!M7 -> 2Q23 | N3: ='Historical Financials'!N7 -> 3Q23 | O3: ='Historical Financials'!O7 -> 4Q23 | ... V3: ='Historical Financials'!V7 -> 3Q25 | X3: =M3 -> 2Q23 | Y3: =N3 -> 3Q23 | Z3: =O3 -> 4Q23 | AA3: =P3 -> 1Q24 | AB3: =Q3 -> 2Q24 | AC3: =R3 -> 3Q24 | AD3: =S3 -> 4Q24 | AE3: =T3 -> 1Q25 | ... AG3: =V3 -> 3Q25
B4: ($ In Thousands) | C4: ='Historical Financials'!C8 -> 44561 | D4: ='Historical Financials'!D8 -> 44926 | E4: ='Historical Financials'!E8 -> 45291 | F4: ='Historical Financials'!F8 -> 45657 | H4: ='Historical Financials'!H8 -> 44651 | I4: ='Historical Financials'!I8 -> 44742 | J4: ='Historical Financials'!J8 -> 44834 | K4: ='Historical Financials'!K8 -> 44926 | L4: ='Historical Financials'!L8 -> 45016 | M4: ='Historical Financials'!M8 -> 45107 | N4: ='Historical Financials'!N8 -> 45199 | O4: ='Historical Financials'!O8 -> 45291 | ... V4: ='Historical Financials'!V8 -> 45930 | X4: =M4 -> 45107 | Y4: =N4 -> 45199 | Z4: =O4 -> 45291 | AA4: =P4 -> 45382 | AB4: =Q4 -> 45473 | AC4: =R4 -> 45565 | AD4: =S4 -> 45657 | AE4: =T4 -> 45747 | ... AG4: =V4 -> 45930
A6: X | B6: Offerings Drivers
A8: X | B8: Revenue Segment Anaysis
B9: Product Licenses and Subscription Services | C9: 144873 | D9: 147244 | E9: 156530 | F9: 155343 | H9: 29358 | I9: 34146 | J9: 38700 | K9: =SUM(D9-SUM(H9:J9)) -> 45040 | L9: 36222 | M9: 35400 | N9: 45019 | O9: =SUM(E9-SUM(L9:N9)) -> 39889 | P9: 35904 | Q9: 33366 | R9: 38887 | S9: =SUM(F9-SUM(P9:R9)) -> 47186 | T9: 44373 | U9: 48001 | V9: 63345 | X9: =SUM(J9:M9) -> 155362 | Y9: =SUM(K9:N9) -> 161681 | Z9: =SUM(L9:O9) -> 156530 | AA9: =SUM(M9:P9) -> 156212 | AB9: =SUM(N9:Q9) -> 154178 | AC9: =SUM(O9:R9) -> 148046 | AD9: =SUM(P9:S9) -> 155343 | AE9: =SUM(Q9:T9) -> 163812 | ... AG9: =SUM(S9:V9) -> 202905
B10: Product support | C10: 281209 | D10: 266521 | E10: 263888 | F10: 243805 | H10: 67151 | I10: 66521 | J10: 66010 | K10: =SUM(D10-SUM(H10:J10)) -> 66839 | L10: 65481 | M10: 66081 | N10: 66860 | O10: =SUM(E10-SUM(L10:N10)) -> 65466 | P10: 62685 | Q10: 61740 | R10: 61015 | S10: =SUM(F10-SUM(P10:R10)) -> 58365 | T10: 52529 | U10: 52081 | V10: 51118 | X10: =SUM(J10:M10) -> 264411 | Y10: =SUM(K10:N10) -> 265261 | Z10: =SUM(L10:O10) -> 263888 | AA10: =SUM(M10:P10) -> 261092 | AB10: =SUM(N10:Q10) -> 256751 | AC10: =SUM(O10:R10) -> 250906 | AD10: =SUM(P10:S10) -> 243805 | AE10: =SUM(Q10:T10) -> 233649 | ... AG10: =SUM(S10:V10) -> 214093
B11: Other services | C11: 84680 | D11: 85499 | E11: 75843 | F11: 64308 | H11: 22768 | I11: 21406 | J11: 20650 | K11: =SUM(D11-SUM(H11:J11)) -> 20675 | L11: 20212 | M11: 18919 | N11: 17583 | O11: =SUM(E11-SUM(L11:N11)) -> 19129 | P11: 16657 | Q11: 16336 | R11: 16169 | S11: =SUM(F11-SUM(P11:R11)) -> 15146 | T11: 14164 | U11: 14406 | V11: 14228 | X11: =SUM(J11:M11) -> 80456 | Y11: =SUM(K11:N11) -> 77389 | Z11: =SUM(L11:O11) -> 75843 | AA11: =SUM(M11:P11) -> 72288 | AB11: =SUM(N11:Q11) -> 69705 | AC11: =SUM(O11:R11) -> 68291 | AD11: =SUM(P11:S11) -> 64308 | AE11: =SUM(Q11:T11) -> 61815 | ... AG11: =SUM(S11:V11) -> 57944
B12: Total Net Revenue | C12: =SUM(C9:C11) -> 510762 | D12: =SUM(D9:D11) -> 499264 | E12: =SUM(E9:E11) -> 496261 | F12: =SUM(F9:F11) -> 463456 | H12: =SUM(H9:H11) -> 119277 | I12: =SUM(I9:I11) -> 122073 | J12: =SUM(J9:J11) -> 125360 | K12: =SUM(K9:K11) -> 132554 | L12: =SUM(L9:L11) -> 121915 | M12: =SUM(M9:M11) -> 120400 | N12: =SUM(N9:N11) -> 129462 | O12: =SUM(O9:O11) -> 124484 | ... V12: =SUM(V9:V11) -> 128691 | X12: =SUM(X9:X11) -> 500229 | Y12: =SUM(Y9:Y11) -> 504331 | Z12: =SUM(Z9:Z11) -> 496261 | AA12: =SUM(AA9:AA11) -> 489592 | AB12: =SUM(AB9:AB11) -> 480634 | AC12: =SUM(AC9:AC11) -> 467243 | AD12: =SUM(AD9:AD11) -> 463456 | AE12: =SUM(AE9:AE11) -> 459276 | ... AG12: =SUM(AG9:AG11) -> 474942
B13: Balance Check | C13: =C12-'Historical Financials'!C11 -> 0 | D13: =D12-'Historical Financials'!D11 -> 0 | E13: =E12-'Historical Financials'!E11 -> 0 | F13: =F12-'Historical Financials'!F11 -> 0 | H13: =H12-'Historical Financials'!H11 -> 0 | I13: =I12-'Historical Financials'!I11 -> 0 | J13: =J12-'Historical Financials'!J11 -> 0 | K13: =K12-'Historical Financials'!K11 -> 0 | L13: =L12-'Historical Financials'!L11 -> 0 | M13: =M12-'Historical Financials'!M11 -> 0 | N13: =N12-'Historical Financials'!N11 -> 0 | O13: =O12-'Historical Financials'!O11 -> 0 | ... V13: =V12-'Historical Financials'!V11 -> 0 | X13: =X12-'Historical Financials'!Z11 -> 0 | Y13: =Y12-'Historical Financials'!AA11 -> 0 | Z13: =Z12-'Historical Financials'!AB11 -> 0 | AA13: =AA12-'Historical Financials'!AC11 -> 0 | AB13: =AB12-'Historical Financials'!AD11 -> 0 | AC13: =AC12-'Historical Financials'!AE11 -> 0 | AD13: =AD12-'Historical Financials'!AF11 -> 0 | AE13: =AE12-'Historical Financials'!AG11 -> 0 | ... AG13: =AG12-'Historical Financials'!AI11 -> 0
B15: =B9&"(%)" -> Product Licenses and Subscription Services(%) | C15: =C9/C$12 -> 0.28364091 | D15: =D9/D$12 -> 0.29492213 | E15: =E9/E$12 -> 0.3154187 | F15: =F9/F$12 -> 0.33518392 | H15: =H9/H$12 -> 0.24613295 | I15: =I9/I$12 -> 0.27971787 | J15: =J9/J$12 -> 0.30871091 | K15: =K9/K$12 -> 0.33978605 | L15: =L9/L$12 -> 0.29710864 | M15: =M9/M$12 -> 0.29401993 | N15: =N9/N$12 -> 0.3477391 | O15: =O9/O$12 -> 0.32043475 | ... V15: =V9/V$12 -> 0.49222556 | X15: =M15 -> 0.29401993 | Y15: =N15 -> 0.3477391 | Z15: =O15 -> 0.32043475 | AA15: =P15 -> 0.31154227 | AB15: =Q15 -> 0.29940238 | AC15: =R15 -> 0.3350277 | AD15: =S15 -> 0.39094592 | AE15: =T15 -> 0.3995192 | ... AG15: =V15 -> 0.49222556
B16: =B10&"(%)" -> Product support(%) | C16: =C10/C$12 -> 0.55056758 | D16: =D10/D$12 -> 0.53382779 | E16: =E10/E$12 -> 0.53175244 | F16: =F10/F$12 -> 0.52605857 | H16: =H10/H$12 -> 0.56298364 | I16: =I10/I$12 -> 0.54492803 | J16: =J10/J$12 -> 0.5265635 | K16: =K10/K$12 -> 0.50423978 | L16: =L10/L$12 -> 0.53710372 | M16: =M10/M$12 -> 0.54884551 | N16: =N10/N$12 -> 0.51644498 | O16: =O10/O$12 -> 0.52589891 | ... V16: =V10/V$12 -> 0.39721503 | X16: =M16 -> 0.54884551 | Y16: =N16 -> 0.51644498 | Z16: =O16 -> 0.52589891 | AA16: =P16 -> 0.54392343 | AB16: =Q16 -> 0.55401016 | AC16: =R16 -> 0.52566963 | AD16: =S16 -> 0.48356629 | AE16: =T16 -> 0.47295302 | ... AG16: =V16 -> 0.39721503
B17: =B11&"(%)" -> Other services(%) | C17: =C11/C$12 -> 0.1657915 | D17: =D11/D$12 -> 0.17125008 | E17: =E11/E$12 -> 0.15282885 | F17: =F11/F$12 -> 0.13875751 | H17: =H11/H$12 -> 0.19088341 | I17: =I11/I$12 -> 0.17535409 | J17: =J11/J$12 -> 0.16472559 | K17: =K11/K$12 -> 0.15597417 | L17: =L11/L$12 -> 0.16578764 | M17: =M11/M$12 -> 0.15713455 | N17: =N11/N$12 -> 0.13581592 | O17: =O11/O$12 -> 0.15366633 | ... V17: =V11/V$12 -> 0.1105594 | X17: =M17 -> 0.15713455 | Y17: =N17 -> 0.13581592 | Z17: =O17 -> 0.15366633 | AA17: =P17 -> 0.1445343 | AB17: =Q17 -> 0.14658746 | AC17: =R17 -> 0.13930267 | AD17: =S17 -> 0.12548779 | AE17: =T17 -> 0.12752778 | ... AG17: =V17 -> 0.1105594
A19: X | B19: Product Licenses and Subscription Services
B20: Product licenses | C20: 101804 | D20: 86498 | E20: 75351 | F20: 48567 | H20: 16513 | I20: 20129 | J20: 22286 | K20: =SUM(D20-SUM(H20:J20)) -> 27570 | L20: 17412 | M20: 15522 | N20: 24045 | O20: =SUM(E20-SUM(L20:N20)) -> 18372 | P20: 12938 | Q20: 9286 | R20: 11087 | S20: =SUM(F20-SUM(P20:R20)) -> 15256 | T20: 7270 | U20: 7177 | V20: 17373 | X20: =SUM(J20:M20) -> 82790 | Y20: =SUM(K20:N20) -> 84549 | Z20: =SUM(L20:O20) -> 75351 | AA20: =SUM(M20:P20) -> 70877 | AB20: =SUM(N20:Q20) -> 64641 | AC20: =SUM(O20:R20) -> 51683 | AD20: =SUM(P20:S20) -> 48567 | AE20: =SUM(Q20:T20) -> 42899 | ... AG20: =SUM(S20:V20) -> 47076
B21: Subscription services | C21: 43069 | D21: 60746 | E21: 81179 | F21: 106776 | H21: 12845 | I21: 14017 | J21: 16414 | K21: =SUM(D21-SUM(H21:J21)) -> 17470 | L21: 18810 | M21: 19878 | N21: 20974 | O21: =SUM(E21-SUM(L21:N21)) -> 21517 | P21: 22966 | Q21: 24080 | R21: 27800 | S21: =SUM(F21-SUM(P21:R21)) -> 31930 | T21: 37103 | U21: 40824 | V21: 45972 | X21: =SUM(J21:M21) -> 72572 | Y21: =SUM(K21:N21) -> 77132 | Z21: =SUM(L21:O21) -> 81179 | AA21: =SUM(M21:P21) -> 85335 | AB21: =SUM(N21:Q21) -> 89537 | AC21: =SUM(O21:R21) -> 96363 | AD21: =SUM(P21:S21) -> 106776 | AE21: =SUM(Q21:T21) -> 120913 | ... AG21: =SUM(S21:V21) -> 155829
B22: Total Net Revenue | C22: =SUM(C20:C21) -> 144873 | D22: =SUM(D20:D21) -> 147244 | E22: =SUM(E20:E21) -> 156530 | F22: =SUM(F20:F21) -> 155343 | H22: =SUM(H20:H21) -> 29358 | I22: =SUM(I20:I21) -> 34146 | J22: =SUM(J20:J21) -> 38700 | K22: =SUM(K20:K21) -> 45040 | L22: =SUM(L20:L21) -> 36222 | M22: =SUM(M20:M21) -> 35400 | N22: =SUM(N20:N21) -> 45019 | O22: =SUM(O20:O21) -> 39889 | ... V22: =SUM(V20:V21) -> 63345 | X22: =SUM(X20:X21) -> 155362 | Y22: =SUM(Y20:Y21) -> 161681 | Z22: =SUM(Z20:Z21) -> 156530 | AA22: =SUM(AA20:AA21) -> 156212 | AB22: =SUM(AB20:AB21) -> 154178 | AC22: =SUM(AC20:AC21) -> 148046 | AD22: =SUM(AD20:AD21) -> 155343 | AE22: =SUM(AE20:AE21) -> 163812 | ... AG22: =SUM(AG20:AG21) -> 202905
B23: Balance Check | C23: =+C22-C9 -> 0 | D23: =+D22-D9 -> 0 | E23: =+E22-E9 -> 0 | F23: =+F22-F9 -> 0 | H23: =+H22-H9 -> 0 | I23: =+I22-I9 -> 0 | J23: =+J22-J9 -> 0 | K23: =+K22-K9 -> 0 | L23: =+L22-L9 -> 0 | M23: =+M22-M9 -> 0 | N23: =+N22-N9 -> 0 | O23: =+O22-O9 -> 0 | ... V23: =+V22-V9 -> 0 | X23: =+X22-X9 -> 0 | Y23: =+Y22-Y9 -> 0 | Z23: =+Z22-Z9 -> 0 | AA23: =+AA22-AA9 -> 0 | AB23: =+AB22-AB9 -> 0 | AC23: =+AC22-AC9 -> 0 | AD23: =+AD22-AD9 -> 0 | AE23: =+AE22-AE9 -> 0 | ... AG23: =+AG22-AG9 -> 0
B25: =B20&"(%)" -> Product licenses(%) | C25: =C20/C$22 -> 0.70271203 | D25: =D20/D$22 -> 0.58744669 | E25: =E20/E$22 -> 0.48138376 | F25: =F20/F$22 -> 0.31264363 | H25: =H20/H$22 -> 0.5624702 | I25: =I20/I$22 -> 0.58949804 | J25: =J20/J$22 -> 0.57586563 | K25: =K20/K$22 -> 0.61212256 | L25: =L20/L$22 -> 0.48070234 | M25: =M20/M$22 -> 0.43847458 | N25: =N20/N$22 -> 0.53410782 | O25: =O20/O$22 -> 0.4605781 | ... V25: =V20/V$22 -> 0.27426 | X25: =M25 -> 0.43847458 | Y25: =N25 -> 0.53410782 | Z25: =O25 -> 0.4605781 | AA25: =P25 -> 0.36034982 | AB25: =Q25 -> 0.27830726 | AC25: =R25 -> 0.28510813 | AD25: =S25 -> 0.32331624 | AE25: =T25 -> 0.16383837 | ... AG25: =V25 -> 0.27426
B26: =B21&"(%)" -> Subscription services(%) | C26: =C21/C$22 -> 0.29728797 | D26: =D21/D$22 -> 0.41255331 | E26: =E21/E$22 -> 0.51861624 | F26: =F21/F$22 -> 0.68735637 | H26: =H21/H$22 -> 0.4375298 | I26: =I21/I$22 -> 0.41050196 | J26: =J21/J$22 -> 0.42413437 | K26: =K21/K$22 -> 0.38787744 | L26: =L21/L$22 -> 0.51929766 | M26: =M21/M$22 -> 0.56152542 | N26: =N21/N$22 -> 0.46589218 | O26: =O21/O$22 -> 0.5394219 | ... V26: =V21/V$22 -> 0.72574 | X26: =M26 -> 0.56152542 | Y26: =N26 -> 0.46589218 | Z26: =O26 -> 0.5394219 | AA26: =P26 -> 0.63965018 | AB26: =Q26 -> 0.72169274 | AC26: =R26 -> 0.71489187 | AD26: =S26 -> 0.67668376 | AE26: =T26 -> 0.83616163 | ... AG26: =V26 -> 0.72574

Sheet FCF
B2: ='Historical Financials'!B2 -> Microstrategy, Inc. (NASDAQ: MSTR) | D2: FYE | H2: Quarterly | L2: Quarterly | R2: Quarterly | X2: LTM | AE2: LTM | AK2: Variance
B3: FCF Analysis | C3: ='Historical Financials'!C7 -> 2021 | D3: ='Historical Financials'!D7 -> 2022 | E3: ='Historical Financials'!E7 -> 2023 | F3: ='Historical Financials'!F7 -> 2024 | H3: ='Historical Financials'!H7 -> 1Q22 | I3: ='Historical Financials'!I7 -> 2Q22 | J3: ='Historical Financials'!J7 -> 3Q22 | K3: ='Historical Financials'!K7 -> 4Q22 | L3: ='Historical Financials'!L7 -> 1Q23 | M3: ='Historical Financials'!M7 -> 2Q23 | N3: ='Historical Financials'!N7 -> 3Q23 | O3: ='Historical Financials'!O7 -> 4Q23 | ... V3: ='Historical Financials'!V7 -> 3Q25 | X3: =K3 -> 4Q22 | Y3: =L3 -> 1Q23 | Z3: =M3 -> 2Q23 | AA3: =N3 -> 3Q23 | AB3: =O3 -> 4Q23 | AC3: =P3 -> 1Q24 | AD3: =Q3 -> 2Q24 | AE3: =R3 -> 3Q24 | ... AI3: =V3 -> 3Q25
B4: ($ In Millions) | C4: ='Historical Financials'!C8 -> 44561 | D4: ='Historical Financials'!D8 -> 44926 | E4: ='Historical Financials'!E8 -> 45291 | F4: ='Historical Financials'!F8 -> 45657 | H4: ='Historical Financials'!H8 -> 44651 | I4: ='Historical Financials'!I8 -> 44742 | J4: ='Historical Financials'!J8 -> 44834 | K4: ='Historical Financials'!K8 -> 44926 | L4: ='Historical Financials'!L8 -> 45016 | M4: ='Historical Financials'!M8 -> 45107 | N4: ='Historical Financials'!N8 -> 45199 | O4: ='Historical Financials'!O8 -> 45291 | ... V4: ='Historical Financials'!V8 -> 45930 | X4: =K4 -> 44926 | Y4: =L4 -> 45016 | Z4: =M4 -> 45107 | AA4: =N4 -> 45199 | AB4: =O4 -> 45291 | AC4: =P4 -> 45382 | AD4: =Q4 -> 45473 | AE4: =R4 -> 45565 | ... AI4: =V4 -> 45930
B6: ='Revenue Drivers'!B9 -> Product Licenses and Subscription Services | C6: ='Revenue Drivers'!C9 -> 144873 | D6: ='Revenue Drivers'!D9 -> 147244 | E6: ='Revenue Drivers'!E9 -> 156530 | F6: ='Revenue Drivers'!F9 -> 155343 | H6: ='Revenue Drivers'!H9 -> 29358 | I6: ='Revenue Drivers'!I9 -> 34146 | J6: ='Revenue Drivers'!J9 -> 38700 | K6: ='Revenue Drivers'!K9 -> 45040 | L6: ='Revenue Drivers'!L9 -> 36222 | M6: ='Revenue Drivers'!M9 -> 35400 | N6: ='Revenue Drivers'!N9 -> 45019 | O6: ='Revenue Drivers'!O9 -> 39889 | ... V6: ='Revenue Drivers'!V9 -> 63345 | X6: =SUM(H6:K6) -> 147244 | Y6: =SUM(I6:L6) -> 154108 | Z6: =SUM(J6:M6) -> 155362 | AA6: =SUM(K6:N6) -> 161681 | AB6: =SUM(L6:O6) -> 156530 | AC6: =SUM(M6:P6) -> 156212 | AD6: =SUM(N6:Q6) -> 154178 | AE6: =SUM(O6:R6) -> 148046 | ... AI6: =SUM(S6:V6) -> 202905 | AK6: =SUM(AI6/AE6)-1 -> 0.37055375
B7: Product support | C7: ='Revenue Drivers'!C10 -> 281209 | D7: ='Revenue Drivers'!D10 -> 266521 | E7: ='Revenue Drivers'!E10 -> 263888 | F7: ='Revenue Drivers'!F10 -> 243805 | H7: ='Revenue Drivers'!H10 -> 67151 | I7: ='Revenue Drivers'!I10 -> 66521 | J7: ='Revenue Drivers'!J10 -> 66010 | K7: ='Revenue Drivers'!K10 -> 66839 | L7: ='Revenue Drivers'!L10 -> 65481 | M7: ='Revenue Drivers'!M10 -> 66081 | N7: ='Revenue Drivers'!N10 -> 66860 | O7: ='Revenue Drivers'!O10 -> 65466 | ... V7: ='Revenue Drivers'!V10 -> 51118 | X7: =SUM(H7:K7) -> 266521 | Y7: =SUM(I7:L7) -> 264851 | Z7: =SUM(J7:M7) -> 264411 | AA7: =SUM(K7:N7) -> 265261 | AB7: =SUM(L7:O7) -> 263888 | AC7: =SUM(M7:P7) -> 261092 | AD7: =SUM(N7:Q7) -> 256751 | AE7: =SUM(O7:R7) -> 250906 | ... AI7: =SUM(S7:V7) -> 214093 | AK7: =SUM(AI7/AE7)-1 -> -0.14672029
B8: Other services | C8: ='Revenue Drivers'!C11 -> 84680 | D8: ='Revenue Drivers'!D11 -> 85499 | E8: ='Revenue Drivers'!E11 -> 75843 | F8: ='Revenue Drivers'!F11 -> 64308 | H8: ='Revenue Drivers'!H11 -> 22768 | I8: ='Revenue Drivers'!I11 -> 21406 | J8: ='Revenue Drivers'!J11 -> 20650 | K8: ='Revenue Drivers'!K11 -> 20675 | L8: ='Revenue Drivers'!L11 -> 20212 | M8: ='Revenue Drivers'!M11 -> 18919 | N8: ='Revenue Drivers'!N11 -> 17583 | O8: ='Revenue Drivers'!O11 -> 19129 | ... V8: ='Revenue Drivers'!V11 -> 14228 | X8: =SUM(H8:K8) -> 85499 | Y8: =SUM(I8:L8) -> 82943 | Z8: =SUM(J8:M8) -> 80456 | AA8: =SUM(K8:N8) -> 77389 | AB8: =SUM(L8:O8) -> 75843 | AC8: =SUM(M8:P8) -> 72288 | AD8: =SUM(N8:Q8) -> 69705 | AE8: =SUM(O8:R8) -> 68291 | ... AI8: =SUM(S8:V8) -> 57944 | AK8: =SUM(AI8/AE8)-1 -> -0.15151338
B9: Total Revenue | C9: =SUM(C6:C8) -> 510762 | D9: =SUM(D6:D8) -> 499264 | E9: =SUM(E6:E8) -> 496261 | F9: =SUM(F6:F8) -> 463456 | H9: =SUM(H6:H8) -> 119277 | I9: =SUM(I6:I8) -> 122073 | J9: =SUM(J6:J8) -> 125360 | K9: =SUM(K6:K8) -> 132554 | L9: =SUM(L6:L8) -> 121915 | M9: =SUM(M6:M8) -> 120400 | N9: =SUM(N6:N8) -> 129462 | O9: =SUM(O6:O8) -> 124484 | ... V9: =SUM(V6:V8) -> 128691 | X9: =SUM(X6:X8) -> 499264 | Y9: =SUM(Y6:Y8) -> 501902 | Z9: =SUM(Z6:Z8) -> 500229 | AA9: =SUM(AA6:AA8) -> 504331 | AB9: =SUM(AB6:AB8) -> 496261 | AC9: =SUM(AC6:AC8) -> 489592 | AD9: =SUM(AD6:AD8) -> 480634 | AE9: =SUM(AE6:AE8) -> 467243 | ... AI9: =SUM(AI6:AI8) -> 474942 | AK9: =SUM(AI9/AE9)-1 -> 0.016477507
B10: Y/Y Growth (%) | D10: =SUM(D9/C9)-1 -> -0.022511463 | E10: =SUM(E9/D9)-1 -> -0.0060148539 | F10: =SUM(F9/E9)-1 -> -0.066104328 | L10: =SUM(L9/H9)-1 -> 0.022116586 | M10: =SUM(M9/I9)-1 -> -0.013704914 | N10: =SUM(N9/J9)-1 -> 0.032721761 | O10: =SUM(O9/K9)-1 -> -0.060880849 | P10: =SUM(P9/L9)-1 -> -0.054702047 | Q10: =SUM(Q9/M9)-1 -> -0.074401993 | R10: =SUM(R9/N9)-1 -> -0.10343576 | S10: =SUM(S9/O9)-1 -> -0.03042158 | ... V10: =SUM(V9/R9)-1 -> 0.10872656 | X10: =SUM(X9/U9)-1 -> 3.3608413 | Y10: =SUM(Y9/V9)-1 -> 2.9000552 | Z10: =SUM(Z9/W9)-1 -> #DIV/0! | AA10: =SUM(AA9/#REF!)-1 -> #REF! | AB10: =SUM(AB9/X9)-1 -> -0.0060148539 | AC10: =SUM(AC9/Y9)-1 -> -0.0245267 | AD10: =SUM(AD9/Z9)-1 -> -0.039172059 | AE10: =SUM(AE9/AA9)-1 -> -0.073539005 | AF10: =SUM(AF9/AB9)-1 -> -0.066104328 | AG10: =SUM(AG9/AC9)-1 -> -0.061920946 | AH10: =SUM(AH9/AD9)-1 -> -0.038099677 | AI10: =SUM(AI9/AE9)-1 -> 0.016477507 | AK10: =SUM(AI10-AE10)*10000 -> 900.16513
B11: Q/Q Growth (%) | C11: N/A | D11: N/A | E11: N/A | F11: N/A | I11: =SUM(I9/H9)-1 -> 0.023441233 | J11: =SUM(J9/I9)-1 -> 0.026926511 | K11: =SUM(K9/J9)-1 -> 0.057386726 | L11: =SUM(L9/K9)-1 -> -0.080261629 | M11: =SUM(M9/L9)-1 -> -0.012426691 | N11: =SUM(N9/M9)-1 -> 0.075265781 | O11: =SUM(O9/N9)-1 -> -0.038451437 | P11: =SUM(P9/O9)-1 -> -0.07421034 | ... V11: =SUM(V9/U9)-1 -> 0.12405667 | X11: N/A | Y11: N/A | Z11: N/A | AA11: N/A | AB11: N/A | AC11: N/A | AD11: N/A | AE11: N/A | AF11: N/A | AG11: N/A | AH11: N/A | AI11: N/A
B13: (-) Cost of Revenues | C13: ='Historical Financials'!C13 -> -91909 | D13: ='Historical Financials'!D13 -> -102989 | E13: ='Historical Financials'!E13 -> -109944 | F13: ='Historical Financials'!F13 -> -129468 | H13: ='Historical Financials'!H13 -> -25677 | I13: ='Historical Financials'!I13 -> -25204 | J13: ='Historical Financials'!J13 -> -25385 | K13: ='Historical Financials'!K13 -> -26723 | L13: ='Historical Financials'!L13 -> -27941 | M13: ='Historical Financials'!M13 -> -27121 | N13: ='Historical Financials'!N13 -> -26661 | O13: ='Historical Financials'!O13 -> -28221 | ... V13: ='Historical Financials'!V13 -> -38013 | X13: =SUM(H13:K13) -> -102989 | Y13: =SUM(I13:L13) -> -105253 | Z13: =SUM(J13:M13) -> -107170 | AA13: =SUM(K13:N13) -> -108446 | AB13: =SUM(L13:O13) -> -109944 | AC13: =SUM(M13:P13) -> -112018 | AD13: =SUM(N13:Q13) -> -115832 | AE13: =SUM(O13:R13) -> -123520 | ... AI13: =SUM(S13:V13) -> -141903 | AK13: =SUM(AI13/AE13)-1 -> 0.1488261
B14: Gross Profit | C14: =SUM(C9+SUM(C13:C13)) -> 418853 | D14: =SUM(D9+SUM(D13:D13)) -> 396275 | E14: =SUM(E9+SUM(E13:E13)) -> 386317 | F14: =SUM(F9+SUM(F13:F13)) -> 333988 | H14: =SUM(H9+SUM(H13:H13)) -> 93600 | I14: =SUM(I9+SUM(I13:I13)) -> 96869 | J14: =SUM(J9+SUM(J13:J13)) -> 99975 | K14: =SUM(K9+SUM(K13:K13)) -> 105831 | L14: =SUM(L9+SUM(L13:L13)) -> 93974 | M14: =SUM(M9+SUM(M13:M13)) -> 93279 | N14: =SUM(N9+SUM(N13:N13)) -> 102801 | O14: =SUM(O9+SUM(O13:O13)) -> 96263 | ... V14: =SUM(V9+SUM(V13:V13)) -> 90678 | X14: =SUM(X9+SUM(X13:X13)) -> 396275 | Y14: =SUM(Y9+SUM(Y13:Y13)) -> 396649 | Z14: =SUM(Z9+SUM(Z13:Z13)) -> 393059 | AA14: =SUM(AA9+SUM(AA13:AA13)) -> 395885 | AB14: =SUM(AB9+SUM(AB13:AB13)) -> 386317 | AC14: =SUM(AC9+SUM(AC13:AC13)) -> 377574 | AD14: =SUM(AD9+SUM(AD13:AD13)) -> 364802 | AE14: =SUM(AE9+SUM(AE13:AE13)) -> 343723 | ... AI14: =SUM(AI9+SUM(AI13:AI13)) -> 333039 | AK14: =SUM(AI14/AE14)-1 -> -0.031083169
B15: Gross Margin (%) | C15: =C14/C9 -> 0.82005513 | D15: =D14/D9 -> 0.79371835 | E15: =E14/E9 -> 0.77845529 | F15: =F14/F9 -> 0.72064662 | H15: =H14/H9 -> 0.78472799 | I15: =I14/I9 -> 0.79353338 | J15: =J14/J9 -> 0.79750319 | K15: =K14/K9 -> 0.79839914 | L15: =L14/L9 -> 0.77081573 | M15: =M14/M9 -> 0.77474252 | N15: =N14/N9 -> 0.79406312 | O15: =O14/O9 -> 0.77329617 | ... V15: =V14/V9 -> 0.70461804 | X15: =X14/X9 -> 0.79371835 | Y15: =Y14/Y9 -> 0.79029173 | Z15: =Z14/Z9 -> 0.78575812 | AA15: =AA14/AA9 -> 0.78497058 | AB15: =AB14/AB9 -> 0.77845529 | AC15: =AC14/AC9 -> 0.77120133 | AD15: =AD14/AD9 -> 0.75900165 | AE15: =AE14/AE9 -> 0.73564077 | ... AI15: =AI14/AI9 -> 0.70122036 | AK15: =SUM(AI15-AE15)*10000 -> -344.2041
B17: (-) Sales and marketing | C17: ='Historical Financials'!C17 -> -160141 | D17: ='Historical Financials'!D17 -> -146882 | E17: ='Historical Financials'!E17 -> -149671 | F17: ='Historical Financials'!F17 -> -138081 | H17: ='Historical Financials'!H17 -> -33240 | I17: ='Historical Financials'!I17 -> -36862 | J17: ='Historical Financials'!J17 -> -35409 | K17: ='Historical Financials'!K17 -> -41371 | L17: ='Historical Financials'!L17 -> -36106 | M17: ='Historical Financials'!M17 -> -37660 | N17: ='Historical Financials'!N17 -> -35606 | O17: ='Historical Financials'!O17 -> -40299 | ... V17: ='Historical Financials'!V17 -> -29908 | X17: =SUM(H17:K17) -> -146882 | Y17: =SUM(I17:L17) -> -149748 | Z17: =SUM(J17:M17) -> -150546 | AA17: =SUM(K17:N17) -> -150743 | AB17: =SUM(L17:O17) -> -149671 | AC17: =SUM(M17:P17) -> -147016 | AD17: =SUM(N17:Q17) -> -143607 | AE17: =SUM(O17:R17) -> -143415 | ... AI17: =SUM(S17:V17) -> -126096 | AK17: =SUM(AI17/AE17)-1 -> -0.12076143
B18: (-) Research and development | C18: ='Historical Financials'!C18 -> -117117 | D18: ='Historical Financials'!D18 -> -127428 | E18: ='Historical Financials'!E18 -> -120530 | F18: ='Historical Financials'!F18 -> -118486 | H18: ='Historical Financials'!H18 -> -33523 | I18: ='Historical Financials'!I18 -> -31790 | J18: ='Historical Financials'!J18 -> -30498 | K18: ='Historical Financials'!K18 -> -31617 | L18: ='Historical Financials'!L18 -> -31358 | M18: ='Historical Financials'!M18 -> -29354 | N18: ='Historical Financials'!N18 -> -29660 | O18: ='Historical Financials'!O18 -> -30158 | ... V18: ='Historical Financials'!V18 -> -22602 | X18: =SUM(H18:K18) -> -127428 | Y18: =SUM(I18:L18) -> -125263 | Z18: =SUM(J18:M18) -> -122827 | AA18: =SUM(K18:N18) -> -121989 | AB18: =SUM(L18:O18) -> -120530 | AC18: =SUM(M18:P18) -> -118355 | AD18: =SUM(N18:Q18) -> -119312 | AE18: =SUM(O18:R18) -> -122953 | ... AI18: =SUM(S18:V18) -> -96787 | AK18: =SUM(AI18/AE18)-1 -> -0.21281303
B19: (-) General and administrative | C19: ='Historical Financials'!C19 -> -95501 | D19: ='Historical Financials'!D19 -> -111421 | E19: ='Historical Financials'!E19 -> -115312 | F19: ='Historical Financials'!F19 -> -140537 | H19: ='Historical Financials'!H19 -> -26706 | I19: ='Historical Financials'!I19 -> -28502 | J19: ='Historical Financials'!J19 -> -27283 | K19: ='Historical Financials'!K19 -> -28930 | L19: ='Historical Financials'!L19 -> -27906 | M19: ='Historical Financials'!M19 -> -28830 | N19: ='Historical Financials'!N19 -> -29223 | O19: ='Historical Financials'!O19 -> -29353 | ... V19: ='Historical Financials'!V19 -> -38173 | X19: =SUM(H19:K19) -> -111421 | Y19: =SUM(I19:L19) -> -112621 | Z19: =SUM(J19:M19) -> -112949 | AA19: =SUM(K19:N19) -> -114889 | AB19: =SUM(L19:O19) -> -115312 | AC19: =SUM(M19:P19) -> -122072 | AD19: =SUM(N19:Q19) -> -129371 | AE19: =SUM(O19:R19) -> -133653 | ... AI19: =SUM(S19:V19) -> -151457 | AK19: =SUM(AI19/AE19)-1 -> 0.13321063
B20: (-) Unrealized gain on digital assets | C20: ='Historical Financials'!C20 -> 0 | D20: ='Historical Financials'!D20 -> 0 | E20: ='Historical Financials'!E20 -> 0 | F20: ='Historical Financials'!F20 -> 0 | H20: ='Historical Financials'!H20 -> 0 | I20: ='Historical Financials'!I20 -> 0 | J20: ='Historical Financials'!J20 -> 0 | K20: ='Historical Financials'!K20 -> 0 | L20: ='Historical Financials'!L20 -> 0 | M20: ='Historical Financials'!M20 -> 0 | N20: ='Historical Financials'!N20 -> 0 | O20: ='Historical Financials'!O20 -> 0 | ... V20: ='Historical Financials'!V20 -> 3890847 | X20: =SUM(H20:K20) -> 0 | Y20: =SUM(I20:L20) -> 0 | Z20: =SUM(J20:M20) -> 0 | AA20: =SUM(K20:N20) -> 0 | AB20: =SUM(L20:O20) -> 0 | AC20: =SUM(M20:P20) -> 0 | AD20: =SUM(N20:Q20) -> 0 | AE20: =SUM(O20:R20) -> 0 | ... AI20: =SUM(S20:V20) -> 12032356 | AK20: =SUM(AI20/AE20)-1 -> #DIV/0!
B21: (-) Digital asset impairment gains (losses on sale), net | C21: ='Historical Financials'!C21 -> -830621 | D21: ='Historical Financials'!D21 -> -1286286 | E21: ='Historical Financials'!E21 -> -115851 | F21: ='Historical Financials'!F21 -> -1789862 | H21: ='Historical Financials'!H21 -> -170091 | I21: ='Historical Financials'!I21 -> -917838 | J21: ='Historical Financials'!J21 -> -727 | K21: ='Historical Financials'!K21 -> -197630 | L21: ='Historical Financials'!L21 -> -18911 | M21: ='Historical Financials'!M21 -> -24143 | N21: ='Historical Financials'!N21 -> -33559 | O21: ='Historical Financials'!O21 -> -39238 | ... V21: ='Historical Financials'!V21 -> 0 | X21: =SUM(H21:K21) -> -1286286 | Y21: =SUM(I21:L21) -> -1135106 | Z21: =SUM(J21:M21) -> -241411 | AA21: =SUM(K21:N21) -> -274243 | AB21: =SUM(L21:O21) -> -115851 | AC21: =SUM(M21:P21) -> -288573 | AD21: =SUM(N21:Q21) -> -444520 | AE21: =SUM(O21:R21) -> -823045 | ... AI21: =SUM(S21:V21) -> -1006055 | AK21: =SUM(AI21/AE21)-1 -> 0.22235722
B22: Earning before Interest & Taxes (EBIT) | C22: =SUM(C14+SUM(C17:C21)) -> -784527 | D22: =SUM(D14+SUM(D17:D21)) -> -1275742 | E22: =SUM(E14+SUM(E17:E21)) -> -115047 | F22: =SUM(F14+SUM(F17:F21)) -> -1852978 | H22: =SUM(H14+SUM(H17:H21)) -> -169960 | I22: =SUM(I14+SUM(I17:I21)) -> -918123 | J22: =SUM(J14+SUM(J17:J21)) -> 6058 | K22: =SUM(K14+SUM(K17:K21)) -> -193717 | L22: =SUM(L14+SUM(L17:L21)) -> -20307 | M22: =SUM(M14+SUM(M17:M21)) -> -26708 | N22: =SUM(N14+SUM(N17:N21)) -> -25247 | O22: =SUM(O14+SUM(O17:O21)) -> -42785 | ... V22: =SUM(V14+SUM(V17:V21)) -> 3890842 | X22: =SUM(X14+SUM(X17:X21)) -> -1275742 | Y22: =SUM(Y14+SUM(Y17:Y21)) -> -1126089 | Z22: =SUM(Z14+SUM(Z17:Z21)) -> -234674 | AA22: =SUM(AA14+SUM(AA17:AA21)) -> -265979 | AB22: =SUM(AB14+SUM(AB17:AB21)) -> -115047 | AC22: =SUM(AC14+SUM(AC17:AC21)) -> -298442 | AD22: =SUM(AD14+SUM(AD17:AD21)) -> -472008 | AE22: =SUM(AE14+SUM(AE17:AE21)) -> -879343 | ... AI22: =SUM(AI14+SUM(AI17:AI21)) -> 10985000 | AK22: =SUM(AI22/AE22)-1 -> -13.492281
B23: Operating Margin (%) | C23: =C22/C9 -> -1.5359933 | D23: =D22/D9 -> -2.5552453 | E23: =E22/E9 -> -0.23182761 | F23: =F22/F9 -> -3.9981746 | H23: =H22/H9 -> -1.4249185 | I23: =I22/I9 -> -7.521098 | J23: =J22/J9 -> 0.048324825 | K23: =K22/K9 -> -1.4614195 | L23: =L22/L9 -> -0.16656687 | M23: =M22/M9 -> -0.22182724 | N23: =N22/N9 -> -0.19501475 | O23: =O22/O9 -> -0.34369879 | ... V23: =V22/V9 -> 30.233987 | X23: =X22/X9 -> -2.5552453 | Y23: =Y22/Y9 -> -2.2436432 | Z23: =Z22/Z9 -> -0.46913314 | AA23: =AA22/AA9 -> -0.52738975 | AB23: =AB22/AB9 -> -0.23182761 | AC23: =AC22/AC9 -> -0.60957287 | AD23: =AD22/AD9 -> -0.98205287 | AE23: =AE22/AE9 -> -1.8819822 | ... AI23: =AI22/AI9 -> 23.12914 | AK23: =SUM(AI23-AE23)*10000 -> 250111.22
B25: (+) Depreciation and Amortization | C25: ='Historical Financials'!C97 -> 11358 | D25: ='Historical Financials'!D97 -> 10874 | E25: ='Historical Financials'!E97 -> 14527 | F25: ='Historical Financials'!F97 -> 17808 | H25: ='Historical Financials'!H97 -> 2691 | I25: ='Historical Financials'!I97 -> 2076 | J25: ='Historical Financials'!J97 -> 2150 | K25: ='Historical Financials'!K97 -> 3957 | L25: ='Historical Financials'!L97 -> 3431 | M25: ='Historical Financials'!M97 -> 3230 | N25: ='Historical Financials'!N97 -> 2744 | O25: ='Historical Financials'!O97 -> 5122 | ... V25: ='Historical Financials'!V97 -> 4195 | X25: =SUM(H25:K25) -> 10874 | Y25: =SUM(I25:L25) -> 11614 | Z25: =SUM(J25:M25) -> 12768 | AA25: =SUM(K25:N25) -> 13362 | AB25: =SUM(L25:O25) -> 14527 | AC25: =SUM(M25:P25) -> 14146 | AD25: =SUM(N25:Q25) -> 14567 | AE25: =SUM(O25:R25) -> 17801 | ... AI25: =SUM(S25:V25) -> 25017 | AK25: =SUM(AI25/AE25)-1 -> 0.40537048
B26: EBITDA | C26: =SUM(C22+SUM(C25:C25)) -> -773169 | D26: =SUM(D22+SUM(D25:D25)) -> -1264868 | E26: =SUM(E22+SUM(E25:E25)) -> -100520 | F26: =SUM(F22+SUM(F25:F25)) -> -1835170 | H26: =SUM(H22+SUM(H25:H25)) -> -167269 | I26: =SUM(I22+SUM(I25:I25)) -> -916047 | J26: =SUM(J22+SUM(J25:J25)) -> 8208 | K26: =SUM(K22+SUM(K25:K25)) -> -189760 | L26: =SUM(L22+SUM(L25:L25)) -> -16876 | M26: =SUM(M22+SUM(M25:M25)) -> -23478 | N26: =SUM(N22+SUM(N25:N25)) -> -22503 | O26: =SUM(O22+SUM(O25:O25)) -> -37663 | ... V26: =SUM(V22+SUM(V25:V25)) -> 3895037 | X26: =SUM(X22+SUM(X25:X25)) -> -1264868 | Y26: =SUM(Y22+SUM(Y25:Y25)) -> -1114475 | Z26: =SUM(Z22+SUM(Z25:Z25)) -> -221906 | AA26: =SUM(AA22+SUM(AA25:AA25)) -> -252617 | AB26: =SUM(AB22+SUM(AB25:AB25)) -> -100520 | AC26: =SUM(AC22+SUM(AC25:AC25)) -> -284296 | AD26: =SUM(AD22+SUM(AD25:AD25)) -> -457441 | AE26: =SUM(AE22+SUM(AE25:AE25)) -> -861542 | ... AI26: =SUM(AI22+SUM(AI25:AI25)) -> 11010017 | AK26: =SUM(AI26/AE26)-1 -> -13.779432
B27: EBITDA Margin (%) | C27: =C26/C9 -> -1.5137559 | D27: =D26/D9 -> -2.5334653 | E27: =E26/E9 -> -0.2025547 | F27: =F26/F9 -> -3.9597502 | H27: =H26/H9 -> -1.4023575 | I27: =I26/I9 -> -7.5040918 | J27: =J26/J9 -> 0.065475431 | K27: =K26/K9 -> -1.4315675 | L27: =L26/L9 -> -0.13842431 | M27: =M26/M9 -> -0.195 | N27: =N26/N9 -> -0.17381934 | O27: =O26/O9 -> -0.30255294 | ... V27: =V26/V9 -> 30.266584 | X27: =X26/X9 -> -2.5334653 | Y27: =Y26/Y9 -> -2.2205032 | Z27: =Z26/Z9 -> -0.44360883 | AA27: =AA26/AA9 -> -0.50089525 | AB27: =AB26/AB9 -> -0.2025547 | AC27: =AC26/AC9 -> -0.58067942 | AD27: =AD26/AD9 -> -0.95174499 | AE27: =AE26/AE9 -> -1.8438842 | ... AI27: =AI26/AI9 -> 23.181814 | AK27: =SUM(AI27-AE27)*10000 -> 250256.98
B29: (+) Share-Based Compensation (SBC) | C29: ='Historical Financials'!C100 -> 44126 | D29: ='Historical Financials'!D100 -> 63619 | E29: ='Historical Financials'!E100 -> 69571 | F29: ='Historical Financials'!F100 -> 77124 | H29: ='Historical Financials'!H100 -> 14394 | I29: ='Historical Financials'!I100 -> 15294 | J29: ='Historical Financials'!J100 -> 16899 | K29: ='Historical Financials'!K100 -> 17032 | L29: ='Historical Financials'!L100 -> 17555 | M29: ='Historical Financials'!M100 -> 15494 | N29: ='Historical Financials'!N100 -> 16806 | O29: ='Historical Financials'!O100 -> 19716 | ... V29: ='Historical Financials'!V100 -> 15483 | X29: =SUM(H29:K29) -> 63619 | Y29: =SUM(I29:L29) -> 66780 | Z29: =SUM(J29:M29) -> 66980 | AA29: =SUM(K29:N29) -> 66887 | AB29: =SUM(L29:O29) -> 69571 | AC29: =SUM(M29:P29) -> 69807 | AD29: =SUM(N29:Q29) -> 74934 | AE29: =SUM(O29:R29) -> 77505 | ... AI29: =SUM(S29:V29) -> 62379 | AK29: =SUM(AI29/AE29)-1 -> -0.1951616
B30: Adj. EBITDA | C30: =SUM(C26+SUM(C29:C29)) -> -729043 | D30: =SUM(D26+SUM(D29:D29)) -> -1201249 | E30: =SUM(E26+SUM(E29:E29)) -> -30949 | F30: =SUM(F26+SUM(F29:F29)) -> -1758046 | H30: =SUM(H26+SUM(H29:H29)) -> -152875 | I30: =SUM(I26+SUM(I29:I29)) -> -900753 | J30: =SUM(J26+SUM(J29:J29)) -> 25107 | K30: =SUM(K26+SUM(K29:K29)) -> -172728 | L30: =SUM(L26+SUM(L29:L29)) -> 679 | M30: =SUM(M26+SUM(M29:M29)) -> -7984 | N30: =SUM(N26+SUM(N29:N29)) -> -5697 | O30: =SUM(O26+SUM(O29:O29)) -> -17947 | ... V30: =SUM(V26+SUM(V29:V29)) -> 3910520 | X30: =SUM(X26+SUM(X29:X29)) -> -1201249 | Y30: =SUM(Y26+SUM(Y29:Y29)) -> -1047695 | Z30: =SUM(Z26+SUM(Z29:Z29)) -> -154926 | AA30: =SUM(AA26+SUM(AA29:AA29)) -> -185730 | AB30: =SUM(AB26+SUM(AB29:AB29)) -> -30949 | AC30: =SUM(AC26+SUM(AC29:AC29)) -> -214489 | AD30: =SUM(AD26+SUM(AD29:AD29)) -> -382507 | AE30: =SUM(AE26+SUM(AE29:AE29)) -> -784037 | ... AI30: =SUM(AI26+SUM(AI29:AI29)) -> 11072396 | AK30: =SUM(AI30/AE30)-1 -> -15.122288
B31: Adj. EBITDA Margin (%) | C31: =C30/C9 -> -1.4273634 | D31: =D30/D9 -> -2.4060397 | E31: =E30/E9 -> -0.062364361 | F31: =F30/F9 -> -3.7933396 | H31: =H30/H9 -> -1.2816805 | I31: =I30/I9 -> -7.3788061 | J31: =J30/J9 -> 0.2002792 | K31: =K30/K9 -> -1.3030765 | L31: =L30/L9 -> 0.0055694541 | M31: =M30/M9 -> -0.066312292 | N31: =N30/N9 -> -0.044005191 | O31: =O30/O9 -> -0.14417114 | ... V31: =V30/V9 -> 30.386896 | X31: =X30/X9 -> -2.4060397 | Y31: =Y30/Y9 -> -2.0874493 | Z31: =Z30/Z9 -> -0.30971015 | AA31: =AA30/AA9 -> -0.36827004 | AB31: =AB30/AB9 -> -0.062364361 | AC31: =AC30/AC9 -> -0.43809744 | AD31: =AD30/AD9 -> -0.79583841 | AE31: =AE30/AE9 -> -1.6780069 | ... AI31: =AI30/AI9 -> 23.313154 | AK31: =SUM(AI31-AE31)*10000 -> 249911.61
B33: (-) Capital Expenditures | C33: =SUM('Historical Financials'!C118,'Historical Financials'!C119) -> -2629235 | D33: =SUM('Historical Financials'!D118,'Historical Financials'!D119) -> -290407 | E33: =SUM('Historical Financials'!E118,'Historical Financials'!E119) -> -1905237 | F33: =SUM('Historical Financials'!F118,'Historical Financials'!F119) -> -22075737 | H33: =SUM('Historical Financials'!H118,'Historical Financials'!H119) -> -216141 | I33: =SUM('Historical Financials'!I118,'Historical Financials'!I119) -> -10878 | J33: =SUM('Historical Financials'!J118,'Historical Financials'!J119) -> -6310 | K33: =SUM('Historical Financials'!K118,'Historical Financials'!K119) -> -57078 | L33: =SUM('Historical Financials'!L118,'Historical Financials'!L119) -> -179774 | M33: =SUM('Historical Financials'!M118,'Historical Financials'!M119) -> -347642 | N33: =SUM('Historical Financials'!N118,'Historical Financials'!N119) -> -163134 | O33: =SUM('Historical Financials'!O118,'Historical Financials'!O119) -> -1214687 | ... V33: =SUM('Historical Financials'!V118,'Historical Financials'!V119) -> -4954877 | X33: =SUM(H33:K33) -> -290407 | Y33: =SUM(I33:L33) -> -254040 | Z33: =SUM(J33:M33) -> -590804 | AA33: =SUM(K33:N33) -> -747628 | AB33: =SUM(L33:O33) -> -1905237 | AC33: =SUM(M33:P33) -> -3366317 | AD33: =SUM(N33:Q33) -> -3813226 | AE33: =SUM(O33:R33) -> -5225591 | ... AI33: =SUM(S33:V33) -> -37455409 | AK33: =SUM(AI33/AE33)-1 -> 6.1676886
B34: (-) Cash Taxes | C34: =-'Historical Financials'!C146 -> -7010 | D34: =-'Historical Financials'!D146 -> -21973 | E34: =-'Historical Financials'!E146 -> -30318 | F34: =-'Historical Financials'!F146 -> -1059 | H34: ='Historical Financials'!H31 -> 48023 | I34: ='Historical Financials'!I31 -> -136108 | J34: ='Historical Financials'!J31 -> -23961 | K34: ='Historical Financials'!K31 -> -35286 | L34: ='Historical Financials'!L31 -> 453187 | M34: ='Historical Financials'!M31 -> 60296 | N34: ='Historical Financials'!N31 -> -109607 | O34: ='Historical Financials'!O31 -> 149770 | ... V34: ='Historical Financials'!V31 -> -1086212 | X34: =SUM(H34:K34) -> -147332 | Y34: =SUM(I34:L34) -> 257832 | Z34: =SUM(J34:M34) -> 454236 | AA34: =SUM(K34:N34) -> 368590 | AB34: =SUM(L34:O34) -> 553646 | AC34: =SUM(M34:P34) -> 261228 | AD34: =SUM(N34:Q34) -> 313419 | AE34: =SUM(O34:R34) -> 561530 | ... AI34: =SUM(S34:V34) -> -2990179 | AK34: =SUM(AI34/AE34)-1 -> -6.3250565
B35: (-) Cash Interest | C35: =-'Historical Financials'!C145 -> -20416 | D35: =-'Historical Financials'!D145 -> -43448 | E35: =-'Historical Financials'!E145 -> -41229 | F35: =-'Historical Financials'!F145 -> -44571 | H35: ='Historical Financials'!H25 -> -11039 | I35: ='Historical Financials'!I25 -> -13187 | J35: ='Historical Financials'!J25 -> -14073 | K35: ='Historical Financials'!K25 -> -14837 | L35: ='Historical Financials'!L25 -> -14930 | M35: ='Historical Financials'!M25 -> -11095 | N35: ='Historical Financials'!N25 -> -11006 | O35: ='Historical Financials'!O25 -> -11929 | ... V35: ='Historical Financials'!V25 -> -18890 | X35: =SUM(H35:K35) -> -53136 | Y35: =SUM(I35:L35) -> -57027 | Z35: =SUM(J35:M35) -> -54935 | AA35: =SUM(K35:N35) -> -51868 | AB35: =SUM(L35:O35) -> -48960 | AC35: =SUM(M35:P35) -> -45911 | AD35: =SUM(N35:Q35) -> -50282 | AE35: =SUM(O35:R35) -> -57405 | ... AI35: =SUM(S35:V35) -> -70358 | AK35: =SUM(AI35/AE35)-1 -> 0.22564237
B36: (-) Preferred Dividends | C36: ='Historical Financials'!C129 -> 0 | D36: ='Historical Financials'!D129 -> 0 | E36: ='Historical Financials'!E129 -> 0 | F36: ='Historical Financials'!F129 -> 0 | H36: ='Historical Financials'!H129 -> 0 | I36: ='Historical Financials'!I129 -> 0 | J36: ='Historical Financials'!J129 -> 0 | K36: ='Historical Financials'!K129 -> 0 | L36: ='Historical Financials'!L129 -> 0 | M36: ='Historical Financials'!M129 -> 0 | N36: ='Historical Financials'!N129 -> 0 | O36: ='Historical Financials'!O129 -> 0 | ... V36: ='Historical Financials'!V129 -> -139780 | X36: =SUM(H36:K36) -> 0 | Y36: =SUM(I36:L36) -> 0 | Z36: =SUM(J36:M36) -> 0 | AA36: =SUM(K36:N36) -> 0 | AB36: =SUM(L36:O36) -> 0 | AC36: =SUM(M36:P36) -> 0 | AD36: =SUM(N36:Q36) -> 0 | AE36: =SUM(O36:R36) -> 0 | ... AI36: =SUM(S36:V36) -> -197922 | AK36: =SUM(AI36/AE36)-1 -> #DIV/0!
B37: (+/-) Changes in NWC | C37: =SUM('Historical Financials'!C106:C114) -> 11091 | D37: =SUM('Historical Financials'!D106:D114) -> -36609 | E37: =SUM('Historical Financials'!E106:E114) -> -21055 | F37: =SUM('Historical Financials'!F106:F114) -> -42707 | H37: =SUM('Historical Financials'!H106:H114) -> 40307 | I37: =SUM('Historical Financials'!I106:I114) -> -31781 | J37: =SUM('Historical Financials'!J106:J114) -> -13014 | K37: =SUM('Historical Financials'!K106:K114) -> -32121 | L37: =SUM('Historical Financials'!L106:L114) -> 36801 | M37: =SUM('Historical Financials'!M106:M114) -> -17818 | N37: =SUM('Historical Financials'!N106:N114) -> -26278 | O37: =SUM('Historical Financials'!O106:O114) -> -13760 | ... V37: =SUM('Historical Financials'!V106:V114) -> -13180 | X37: =SUM(H37:K37) -> -36609 | Y37: =SUM(I37:L37) -> -40115 | Z37: =SUM(J37:M37) -> -26152 | AA37: =SUM(K37:N37) -> -39416 | AB37: =SUM(L37:O37) -> -21055 | AC37: =SUM(M37:P37) -> -32146 | AD37: =SUM(N37:Q37) -> -28280 | AE37: =SUM(O37:R37) -> -27508 | ... AI37: =SUM(S37:V37) -> -55799 | AK37: =SUM(AI37/AE37)-1 -> 1.0284644
B38: Discretionary Cash-Flows | C38: =SUM(C30+SUM(C33:C37)) -> -3374613 | D38: =SUM(D30+SUM(D33:D37)) -> -1593686 | E38: =SUM(E30+SUM(E33:E37)) -> -2028788 | F38: =SUM(F30+SUM(F33:F37)) -> -23922120 | H38: =SUM(H30+SUM(H33:H37)) -> -291725 | I38: =SUM(I30+SUM(I33:I37)) -> -1092707 | J38: =SUM(J30+SUM(J33:J37)) -> -32251 | K38: =SUM(K30+SUM(K33:K37)) -> -312050 | L38: =SUM(L30+SUM(L33:L37)) -> 295963 | M38: =SUM(M30+SUM(M33:M37)) -> -324243 | N38: =SUM(N30+SUM(N33:N37)) -> -315722 | O38: =SUM(O30+SUM(O33:O37)) -> -1108553 | ... V38: =SUM(V30+SUM(V33:V37)) -> -2302419 | X38: =SUM(X30+SUM(X33:X37)) -> -1728733 | Y38: =SUM(Y30+SUM(Y33:Y37)) -> -1141045 | Z38: =SUM(Z30+SUM(Z33:Z37)) -> -372581 | AA38: =SUM(AA30+SUM(AA33:AA37)) -> -656052 | AB38: =SUM(AB30+SUM(AB33:AB37)) -> -1452555 | AC38: =SUM(AC30+SUM(AC33:AC37)) -> -3397635 | AD38: =SUM(AD30+SUM(AD33:AD37)) -> -3960876 | AE38: =SUM(AE30+SUM(AE33:AE37)) -> -5533011 | ... AI38: =SUM(AI30+SUM(AI33:AI37)) -> -29697271 | AK38: =SUM(AI38/AE38)-1 -> 4.3672893
B40: (+/-) Proceeds from Debt Issuances / (Repayment) | C40: ='Historical Financials'!C124 -> 1512412 | D40: ='Historical Financials'!D124 -> 215170 | E40: ='Historical Financials'!E124 -> -160546 | F40: ='Historical Financials'!F124 -> 5616366 | H40: ='Historical Financials'!H124 -> 204693 | I40: ='Historical Financials'!I124 -> 10819 | J40: ='Historical Financials'!J124 -> -161 | K40: ='Historical Financials'!K124 -> -181 | L40: ='Historical Financials'!L124 -> -160028 | M40: ='Historical Financials'!M124 -> -259 | N40: ='Historical Financials'!N124 -> -128 | O40: ='Historical Financials'!O124 -> -131 | ... V40: ='Historical Financials'!V124 -> 4581 | X40: =SUM(H40:K40) -> 215170 | Y40: =SUM(I40:L40) -> -149551 | Z40: =SUM(J40:M40) -> -160629 | AA40: =SUM(K40:N40) -> -160596 | AB40: =SUM(L40:O40) -> -160546 | AC40: =SUM(M40:P40) -> 1375028 | AD40: =SUM(N40:Q40) -> 2161173 | AE40: =SUM(O40:R40) -> 2643971 | ... AI40: =SUM(S40:V40) -> 4977641
B41: (+/-) Proceeds from Equity Issuances / (Repurchases) | C41: ='Historical Financials'!C125 -> 990463 | D41: ='Historical Financials'!D125 -> 46234 | E41: ='Historical Financials'!E125 -> 2020073 | F41: ='Historical Financials'!F125 -> 16329857 | H41: ='Historical Financials'!H125 -> 0 | I41: ='Historical Financials'!I125 -> 0 | J41: ='Historical Financials'!J125 -> 0 | K41: ='Historical Financials'!K125 -> 46234 | L41: ='Historical Financials'!L125 -> 339017 | M41: ='Historical Financials'!M125 -> 333423 | N41: ='Historical Financials'!N125 -> 147219 | O41: ='Historical Financials'!O125 -> 1200414 | ... V41: ='Historical Financials'!V125 -> 5089979 | X41: =SUM(H41:K41) -> 46234 | Y41: =SUM(I41:L41) -> 385251 | Z41: =SUM(J41:M41) -> 718674 | AA41: =SUM(K41:N41) -> 865893 | AB41: =SUM(L41:O41) -> 2020073 | AC41: =SUM(M41:P41) -> 1818208 | AD41: =SUM(N41:Q41) -> 1484785 | AE41: =SUM(O41:R41) -> 2442707 | ... AI41: =SUM(S41:V41) -> 32714777
B42: (+/-) Proceeds from exercise of stock options | C42: ='Historical Financials'!C126 -> 40651 | D42: ='Historical Financials'!D126 -> 1393 | E42: ='Historical Financials'!E126 -> 30518 | F42: ='Historical Financials'!F126 -> 184287 | H42: ='Historical Financials'!H126 -> 288 | I42: ='Historical Financials'!I126 -> 423 | J42: ='Historical Financials'!J126 -> 621 | K42: ='Historical Financials'!K126 -> 61 | L42: ='Historical Financials'!L126 -> 6750 | M42: ='Historical Financials'!M126 -> 5354 | N42: ='Historical Financials'!N126 -> 2113 | O42: ='Historical Financials'!O126 -> 16301 | ... V42: ='Historical Financials'!V126 -> 14870 | X42: =SUM(H42:K42) -> 1393 | Y42: =SUM(I42:L42) -> 7855 | Z42: =SUM(J42:M42) -> 12786 | AA42: =SUM(K42:N42) -> 14278 | AB42: =SUM(L42:O42) -> 30518 | AC42: =SUM(M42:P42) -> 158642 | AD42: =SUM(N42:Q42) -> 171763 | AE42: =SUM(O42:R42) -> 173842 | ... AI42: =SUM(S42:V42) -> 63485
B43: (+/-) Proceeds from sales under employee stock purchase plan | C43: ='Historical Financials'!C127 -> 2854 | D43: ='Historical Financials'!D127 -> 4473 | E43: ='Historical Financials'!E127 -> 3955 | F43: ='Historical Financials'!F127 -> 4304 | H43: ='Historical Financials'!H127 -> 2805 | I43: ='Historical Financials'!I127 -> 0 | J43: ='Historical Financials'!J127 -> 1668 | K43: ='Historical Financials'!K127 -> 0 | L43: ='Historical Financials'!L127 -> 2380 | M43: ='Historical Financials'!M127 -> 0 | N43: ='Historical Financials'!N127 -> 1575 | O43: ='Historical Financials'!O127 -> 0 | ... V43: ='Historical Financials'!V127 -> 2732 | X43: =SUM(H43:K43) -> 4473 | Y43: =SUM(I43:L43) -> 4048 | Z43: =SUM(J43:M43) -> 4048 | AA43: =SUM(K43:N43) -> 3955 | AB43: =SUM(L43:O43) -> 3955 | AC43: =SUM(M43:P43) -> 3646 | AD43: =SUM(N43:Q43) -> 3646 | AE43: =SUM(O43:R43) -> 4304 | ... AI43: =SUM(S43:V43) -> 5435
B44: (+/-) Payment of withholding tax on vesting of RSUs | C44: ='Historical Financials'!C128 -> -4695 | D44: ='Historical Financials'!D128 -> -2082 | E44: ='Historical Financials'!E128 -> -4114 | F44: ='Historical Financials'!F128 -> -2173 | H44: ='Historical Financials'!H128 -> -495 | I44: ='Historical Financials'!I128 -> -46 | J44: ='Historical Financials'!J128 -> -564 | K44: ='Historical Financials'!K128 -> -977 | L44: ='Historical Financials'!L128 -> -497 | M44: ='Historical Financials'!M128 -> -229 | N44: ='Historical Financials'!N128 -> -665 | O44: ='Historical Financials'!O128 -> -2723 | ... V44: ='Historical Financials'!V128 -> 0 | X44: =SUM(H44:K44) -> -2082 | Y44: =SUM(I44:L44) -> -2084 | Z44: =SUM(J44:M44) -> -2267 | AA44: =SUM(K44:N44) -> -2368 | AB44: =SUM(L44:O44) -> -4114 | AC44: =SUM(M44:P44) -> -4860 | AD44: =SUM(N44:Q44) -> -5561 | AE44: =SUM(O44:R44) -> -4896 | ... AI44: =SUM(S44:V44) -> 0
B45: (+/-) Other Operating Activities | C45: ='Historical Financials'!C103 -> 830060 | D45: ='Historical Financials'!D103 -> 1285926 | E45: ='Historical Financials'!E103 -> 70659 | F45: ='Historical Financials'!F103 -> 1811530 | H45: ='Historical Financials'!H103 -> 170091 | I45: ='Historical Financials'!I103 -> 917838 | J45: ='Historical Financials'!J103 -> 727 | K45: ='Historical Financials'!K103 -> 197270 | L45: ='Historical Financials'!L103 -> -25877 | M45: ='Historical Financials'!M103 -> 24143 | N45: ='Historical Financials'!N103 -> 33499 | O45: ='Historical Financials'!O103 -> 38894 | ... V45: ='Historical Financials'!V103 -> -3890847 | X45: =SUM(H45:K45) -> 1285926 | Y45: =SUM(I45:L45) -> 1089958 | Z45: =SUM(J45:M45) -> 196263 | AA45: =SUM(K45:N45) -> 229035 | AB45: =SUM(L45:O45) -> 70659 | AC45: =SUM(M45:P45) -> 288096 | AD45: =SUM(N45:Q45) -> 444043 | AE45: =SUM(O45:R45) -> 845561 | ... AI45: =SUM(S45:V45) -> -11027493
B46: (+/-) Other Investing Activities | C46: ='Historical Financials'!C120 -> 0 | D46: ='Historical Financials'!D120 -> 11817 | E46: ='Historical Financials'!E120 -> 0 | F46: ='Historical Financials'!F120 -> -10500 | H46: ='Historical Financials'!H120 -> 0 | I46: ='Historical Financials'!I120 -> 0 | J46: ='Historical Financials'!J120 -> 0 | K46: ='Historical Financials'!K120 -> 11817 | L46: ='Historical Financials'!L120 -> 0 | M46: ='Historical Financials'!M120 -> 0 | N46: ='Historical Financials'!N120 -> 0 | O46: ='Historical Financials'!O120 -> 0 | ... V46: ='Historical Financials'!V120 -> -5000 | X46: =SUM(H46:K46) -> 11817 | Y46: =SUM(I46:L46) -> 11817 | Z46: =SUM(J46:M46) -> 11817 | AA46: =SUM(K46:N46) -> 11817 | AB46: =SUM(L46:O46) -> 0 | AC46: =SUM(M46:P46) -> 0 | AD46: =SUM(N46:Q46) -> 0 | AE46: =SUM(O46:R46) -> 0 | ... AI46: =SUM(S46:V46) -> -37500
B47: (+/-) Other | D47: =SUM(D52:D53)-SUM(C52:C53)-SUM(D38:D46) -> 17189 | E47: =SUM(E52:E53)-SUM(D52:D53)-SUM(E38:E46) -> 66048 | F47: =SUM(F52:F53)-SUM(E52:E53)-SUM(F38:F46) -> -20327 | H47: =SUM(H52:H53)-SUM(C52:C53)-SUM(H38:H46) -> -51149 | I47: =SUM(I52:I53)-SUM(H52:H53)-SUM(I38:I46) -> 140272 | J47: =SUM(J52:J53)-SUM(I52:I53)-SUM(J38:J46) -> 21387 | K47: =SUM(K52:K53)-SUM(J52:J53)-SUM(K38:K46) -> 41726 | L47: =SUM(L52:L53)-SUM(K52:K53)-SUM(L38:L46) -> -412112 | M47: =SUM(M52:M53)-SUM(L52:L53)-SUM(M38:M46) -> -66600 | N47: =SUM(N52:N53)-SUM(M52:M53)-SUM(N38:N46) -> 110930 | O47: =SUM(O52:O53)-SUM(N52:N53)-SUM(O38:O46) -> -142403 | P47: =SUM(P52:P53)-SUM(O52:O53)-SUM(P38:P46) -> -155788 | ... V47: =SUM(V52:V53)-SUM(U52:U53)-SUM(V38:V46) -> 1090172 | X47: =SUM(H47:K47) -> 152236 | Y47: =SUM(I47:L47) -> -208727 | Z47: =SUM(J47:M47) -> -415599 | AA47: =SUM(K47:N47) -> -326056 | AB47: =SUM(L47:O47) -> -510185 | AC47: =SUM(M47:P47) -> -253861 | AD47: =SUM(N47:Q47) -> -298225 | AE47: =SUM(O47:R47) -> -571147 | ... AI47: =SUM(S47:V47) -> 3008921
B48: Free-Cash Flows | C48: =SUM(C38+SUM(C40:C47)) -> -2868 | D48: =SUM(D38+SUM(D40:D47)) -> -13566 | E48: =SUM(E38+SUM(E40:E47)) -> -2195 | F48: =SUM(F38+SUM(F40:F47)) -> -8776 | H48: =SUM(H38+SUM(H40:H47)) -> 34508 | I48: =SUM(I38+SUM(I40:I47)) -> -23401 | J48: =SUM(J38+SUM(J40:J47)) -> -8573 | K48: =SUM(K38+SUM(K40:K47)) -> -16100 | L48: =SUM(L38+SUM(L40:L47)) -> 45596 | M48: =SUM(M38+SUM(M40:M47)) -> -28411 | N48: =SUM(N38+SUM(N40:N47)) -> -21179 | O48: =SUM(O38+SUM(O40:O47)) -> 1799 | ... V48: =SUM(V38+SUM(V40:V47)) -> 4068 | X48: =SUM(X38+SUM(X40:X47)) -> -13566 | Y48: =SUM(Y38+SUM(Y40:Y47)) -> -2478 | Z48: =SUM(Z38+SUM(Z40:Z47)) -> -7488 | AA48: =SUM(AA38+SUM(AA40:AA47)) -> -20094 | AB48: =SUM(AB38+SUM(AB40:AB47)) -> -2195 | AC48: =SUM(AC38+SUM(AC40:AC47)) -> -12736 | AD48: =SUM(AD38+SUM(AD40:AD47)) -> 748 | AE48: =SUM(AE38+SUM(AE40:AE47)) -> 1331 | ... AI48: =SUM(AI38+SUM(AI40:AI47)) -> 7995
B50: Capitalization
B52: Cash & Cash Equivelants | C52: ='Historical Financials'!C46 -> 63356 | D52: ='Historical Financials'!D46 -> 43835 | E52: ='Historical Financials'!E46 -> 46817 | F52: ='Historical Financials'!F46 -> 38117 | H52: ='Historical Financials'!H46 -> 92677 | I52: ='Historical Financials'!I46 -> 69386 | J52: ='Historical Financials'!J46 -> 60390 | K52: ='Historical Financials'!K46 -> 43835 | L52: ='Historical Financials'!L46 -> 94311 | M52: ='Historical Financials'!M46 -> 65968 | N52: ='Historical Financials'!N46 -> 45009 | O52: ='Historical Financials'!O46 -> 46817 | ... V52: ='Historical Financials'!V46 -> 54285 | X52: =K52 -> 43835 | Y52: =L52 -> 94311 | Z52: =M52 -> 65968 | AA52: =N52 -> 45009 | AB52: =O52 -> 46817 | AC52: =P52 -> 81326 | AD52: =Q52 -> 66923 | AE52: =R52 -> 46343 | ... AI52: =V52 -> 54285
B53: Restricted Cash | C53: ='Historical Financials'!C47 -> 1078 | D53: ='Historical Financials'!D47 -> 7033 | E53: ='Historical Financials'!E47 -> 1856 | F53: ='Historical Financials'!F47 -> 1780 | H53: ='Historical Financials'!H47 -> 6265 | I53: ='Historical Financials'!I47 -> 6155 | J53: ='Historical Financials'!J47 -> 6578 | K53: ='Historical Financials'!K47 -> 7033 | L53: ='Historical Financials'!L47 -> 2153 | M53: ='Historical Financials'!M47 -> 2085 | N53: ='Historical Financials'!N47 -> 1865 | O53: ='Historical Financials'!O47 -> 1856 | ... V53: ='Historical Financials'!V47 -> 1915 | X53: =K53 -> 7033 | Y53: =L53 -> 2153 | Z53: =M53 -> 2085 | AA53: =N53 -> 1865 | AB53: =O53 -> 1856 | AC53: =P53 -> 2402 | AD53: =Q53 -> 1878 | AE53: =R53 -> 1862 | ... AI53: =V53 -> 1915
B54: Total FIAT Liquidity | C54: =SUM(C52:C53) -> 64434 | D54: =SUM(D52:D53) -> 50868 | E54: =SUM(E52:E53) -> 48673 | F54: =SUM(F52:F53) -> 39897 | H54: =SUM(H52:H53) -> 98942 | I54: =SUM(I52:I53) -> 75541 | J54: =SUM(J52:J53) -> 66968 | K54: =SUM(K52:K53) -> 50868 | L54: =SUM(L52:L53) -> 96464 | M54: =SUM(M52:M53) -> 68053 | N54: =SUM(N52:N53) -> 46874 | O54: =SUM(O52:O53) -> 48673 | ... V54: =SUM(V52:V53) -> 56200 | X54: =SUM(X52:X53) -> 50868 | Y54: =SUM(Y52:Y53) -> 96464 | Z54: =SUM(Z52:Z53) -> 68053 | AA54: =SUM(AA52:AA53) -> 46874 | AB54: =SUM(AB52:AB53) -> 48673 | AC54: =SUM(AC52:AC53) -> 83728 | AD54: =SUM(AD52:AD53) -> 68801 | AE54: =SUM(AE52:AE53) -> 48205 | ... AI54: =SUM(AI52:AI53) -> 56200
B56: Digital Assets (Bitcoin Holdings) | C56: ='Historical Financials'!C53 -> 2850210 | D56: ='Historical Financials'!D53 -> 1840028 | E56: ='Historical Financials'!E53 -> 3626476 | F56: ='Historical Financials'!F53 -> 23909373 | H56: ='Historical Financials'!H53 -> 2895619 | I56: ='Historical Financials'!I53 -> 1987781 | J56: ='Historical Financials'!J53 -> 1993032 | K56: ='Historical Financials'!K53 -> 1840028 | L56: ='Historical Financials'!L53 -> 2000392 | M56: ='Historical Financials'!M53 -> 2323252 | N56: ='Historical Financials'!N53 -> 2451374 | O56: ='Historical Financials'!O53 -> 3626476 | ... V56: ='Historical Financials'!V53 -> 73205725 | X56: =K56 -> 1840028 | Y56: =L56 -> 2000392 | Z56: =M56 -> 2323252 | AA56: =N56 -> 2451374 | AB56: =O56 -> 3626476 | AC56: =P56 -> 5074152 | AD56: =Q56 -> 5687890 | AE56: =R56 -> 6850879 | ... AI56: =V56 -> 73205725
B57: Total Adj. Liquidity | C57: =SUM(C55:C56) -> 2850210 | D57: =SUM(D55:D56) -> 1840028 | E57: =SUM(E55:E56) -> 3626476 | F57: =SUM(F55:F56) -> 23909373 | H57: =SUM(H55:H56) -> 2895619 | I57: =SUM(I55:I56) -> 1987781 | J57: =SUM(J55:J56) -> 1993032 | K57: =SUM(K55:K56) -> 1840028 | L57: =SUM(L55:L56) -> 2000392 | M57: =SUM(M55:M56) -> 2323252 | N57: =SUM(N55:N56) -> 2451374 | O57: =SUM(O55:O56) -> 3626476 | ... V57: =SUM(V55:V56) -> 73205725 | X57: =SUM(X55:X56) -> 1840028 | Y57: =SUM(Y55:Y56) -> 2000392 | Z57: =SUM(Z55:Z56) -> 2323252 | AA57: =SUM(AA55:AA56) -> 2451374 | AB57: =SUM(AB55:AB56) -> 3626476 | AC57: =SUM(AC55:AC56) -> 5074152 | AD57: =SUM(AD55:AD56) -> 5687890 | AE57: =SUM(AE55:AE56) -> 6850879 | ... AI57: =SUM(AI55:AI56) -> 73205725
B59: Balance Sheet Metrics:
B60: Accounts Receivables | C60: ='Historical Financials'!C48 -> 189280 | D60: ='Historical Financials'!D48 -> 189280 | E60: ='Historical Financials'!E48 -> 183815 | F60: ='Historical Financials'!F48 -> 181203 | H60: ='Historical Financials'!H48 -> 126930 | I60: ='Historical Financials'!I48 -> 118645 | J60: ='Historical Financials'!J48 -> 109926 | K60: ='Historical Financials'!K48 -> 189280 | L60: ='Historical Financials'!L48 -> 139178 | M60: ='Historical Financials'!M48 -> 121901 | N60: ='Historical Financials'!N48 -> 128650 | O60: ='Historical Financials'!O48 -> 183815 | ... V60: ='Historical Financials'!V48 -> 113406 | X60: =K60 -> 189280 | Y60: =L60 -> 139178 | Z60: =M60 -> 121901 | AA60: =N60 -> 128650 | AB60: =O60 -> 183815 | AC60: =P60 -> 115150 | AD60: =Q60 -> 112234 | AE60: =R60 -> 107169 | ... AI60: =V60 -> 113406
B61: Property and Equipment | C61: ='Historical Financials'!C54 -> 36587 | D61: ='Historical Financials'!D54 -> 32311 | E61: ='Historical Financials'!E54 -> 28941 | F61: ='Historical Financials'!F54 -> 26327 | H61: ='Historical Financials'!H54 -> 35680 | I61: ='Historical Financials'!I54 -> 34580 | J61: ='Historical Financials'!J54 -> 33033 | K61: ='Historical Financials'!K54 -> 32311 | L61: ='Historical Financials'!L54 -> 31338 | M61: ='Historical Financials'!M54 -> 30507 | N61: ='Historical Financials'!N54 -> 30192 | O61: ='Historical Financials'!O54 -> 28941 | ... V61: ='Historical Financials'!V54 -> 29949 | X61: =K61 -> 32311 | Y61: =L61 -> 31338 | Z61: =M61 -> 30507 | AA61: =N61 -> 30192 | AB61: =O61 -> 28941 | AC61: =P61 -> 29108 | AD61: =Q61 -> 28332 | AE61: =R61 -> 27517 | ... AI61: =V61 -> 29949
B62: Accounts Payable | C62: ='Historical Financials'!C61 -> 46084 | D62: ='Historical Financials'!D61 -> 42976 | E62: ='Historical Financials'!E61 -> 43090 | F62: ='Historical Financials'!F61 -> 52982 | H62: ='Historical Financials'!H61 -> 44388 | I62: ='Historical Financials'!I61 -> 35960 | J62: ='Historical Financials'!J61 -> 36846 | K62: ='Historical Financials'!K61 -> 42976 | L62: ='Historical Financials'!L61 -> 50604 | M62: ='Historical Financials'!M61 -> 33660 | N62: ='Historical Financials'!N61 -> 34306 | O62: ='Historical Financials'!O61 -> 43090 | ... V62: ='Historical Financials'!V61 -> 48723 | X62: =K62 -> 42976 | Y62: =L62 -> 50604 | Z62: =M62 -> 33660 | AA62: =N62 -> 34306 | AB62: =O62 -> 43090 | AC62: =P62 -> 41866 | AD62: =Q62 -> 44188 | AE62: =R62 -> 45714 | ... AI62: =V62 -> 48723
B63: Deferred Revenue | C63: ='Historical Financials'!C65 -> 209860 | D63: ='Historical Financials'!D65 -> 217428 | E63: ='Historical Financials'!E65 -> 228162 | F63: ='Historical Financials'!F65 -> 237974 | H63: ='Historical Financials'!H65 -> 206217 | I63: ='Historical Financials'!I65 -> 188098 | J63: ='Historical Financials'!J65 -> 165934 | K63: ='Historical Financials'!K65 -> 217428 | L63: ='Historical Financials'!L65 -> 211768 | M63: ='Historical Financials'!M65 -> 195817 | N63: ='Historical Financials'!N65 -> 179167 | O63: ='Historical Financials'!O65 -> 228162 | ... V63: ='Historical Financials'!V65 -> 200641 | X63: =K63 -> 217428 | Y63: =L63 -> 211768 | Z63: =M63 -> 195817 | AA63: =N63 -> 179167 | AB63: =O63 -> 228162 | AC63: =P63 -> 215955 | AD63: =Q63 -> 204837 | AE63: =R63 -> 184402 | ... AI63: =V63 -> 200641
B64: Current Liabilities | C64: ='Historical Financials'!C66 -> 311985 | D64: ='Historical Financials'!D66 -> 317403 | E64: ='Historical Financials'!E66 -> 323273 | F64: ='Historical Financials'!F66 -> 355384 | H64: ='Historical Financials'!H66 -> 304875 | I64: ='Historical Financials'!I66 -> 274100 | J64: ='Historical Financials'!J66 -> 260520 | K64: ='Historical Financials'!K66 -> 317403 | L64: ='Historical Financials'!L66 -> 312399 | M64: ='Historical Financials'!M66 -> 272930 | N64: ='Historical Financials'!N66 -> 267721 | O64: ='Historical Financials'!O66 -> 323273 | ... V64: ='Historical Financials'!V66 -> 324090 | X64: =K64 -> 317403 | Y64: =L64 -> 312399 | Z64: =M64 -> 272930 | AA64: =N64 -> 267721 | AB64: =O64 -> 323273 | AC64: =P64 -> 309808 | AD64: =Q64 -> 446063 | AE64: =R64 -> 288111 | ... AI64: =V64 -> 324090
B65: Total Liabilities | C65: ='Historical Financials'!C83 -> 978958 | D65: ='Historical Financials'!D83 -> -383120 | E65: ='Historical Financials'!E83 -> 2164972 | F65: ='Historical Financials'!F83 -> 18229984 | H65: ='Historical Financials'!H83 -> 862999 | I65: ='Historical Financials'!I83 -> -187068 | J65: ='Historical Financials'!J83 -> -200289 | K65: ='Historical Financials'!K83 -> -383120 | L65: ='Historical Financials'!L83 -> 443211 | M65: ='Historical Financials'!M83 -> 819118 | N65: ='Historical Financials'!N83 -> 840395 | O65: ='Historical Financials'!O83 -> 2164972 | ... V65: ='Historical Financials'!V83 -> 58117048 | X65: =K65 -> -383120 | Y65: =L65 -> 443211 | Z65: =M65 -> 819118 | AA65: =N65 -> 840395 | AB65: =O65 -> 2164972 | AC65: =P65 -> 2400105 | AD65: =Q65 -> 2834799 | AE65: =R65 -> 3773649 | ... AI65: =V65 -> 58117048
B67: Summary Debt:
B68: CPLTD | C68: ='Historical Financials'!C64 -> 0 | D68: ='Historical Financials'!D64 -> 454 | E68: ='Historical Financials'!E64 -> 483 | F68: ='Historical Financials'!F64 -> 517 | H68: ='Historical Financials'!H64 -> 0 | I68: ='Historical Financials'!I64 -> 0 | J68: ='Historical Financials'!J64 -> 0 | K68: ='Historical Financials'!K64 -> 454 | L68: ='Historical Financials'!L64 -> 460 | M68: ='Historical Financials'!M64 -> 468 | N68: ='Historical Financials'!N64 -> 475 | O68: ='Historical Financials'!O64 -> 483 | ... V68: ='Historical Financials'!V64 -> 316 | X68: =K68 -> 454 | Y68: =L68 -> 460 | Z68: =M68 -> 468 | AA68: =N68 -> 475 | AB68: =O68 -> 483 | AC68: =P68 -> 492 | AD68: =Q68 -> 145119 | AE68: =R68 -> 509 | ... AI68: =V68 -> 316
B69: LTD | C69: ='Historical Financials'!C69 -> 2155151 | D69: ='Historical Financials'!D69 -> 2378560 | E69: ='Historical Financials'!E69 -> 2182108 | F69: ='Historical Financials'!F69 -> 7191158 | H69: ='Historical Financials'!H69 -> 2361865 | I69: ='Historical Financials'!I69 -> 2374863 | J69: ='Historical Financials'!J69 -> 2376935 | K69: ='Historical Financials'!K69 -> 2378560 | L69: ='Historical Financials'!L69 -> 2175918 | M69: ='Historical Financials'!M69 -> 2177974 | N69: ='Historical Financials'!N69 -> 2180038 | O69: ='Historical Financials'!O69 -> 2182108 | ... V69: ='Historical Financials'!V69 -> 8173587 | X69: =K69 -> 2378560 | Y69: =L69 -> 2175918 | Z69: =M69 -> 2177974 | AA69: =N69 -> 2180038 | AB69: =O69 -> 2182108 | AC69: =P69 -> 3558801 | AD69: =Q69 -> 3703381 | AE69: =R69 -> 4211949 | ... AI69: =V69 -> 8173587
B71: $650MM 0.750% Sr. Unsecured Convertible Notes due 2025 | C71: 637882 | D71: 640888 | E71: 643931 | F71: 1041352 | H71: 638630 | I71: 639380 | J71: 640133 | K71: =D71 -> 640888 | L71: 641645 | M71: 642405 | N71: 643167 | O71: =E71 -> 643931 | P71: 644698 | Q71: 144618 | R71: 0 | S71: =F71 -> 1041352 | T71: 0 | U71: 0 | V71: 0 | X71: =K71 -> 640888 | Y71: =L71 -> 641645 | Z71: =M71 -> 642405 | AA71: =N71 -> 643167 | AB71: =O71 -> 643931 | AC71: =P71 -> 644698 | AD71: =Q71 -> 144618 | AE71: =R71 -> 0 | ... AI71: =V71 -> 0
B72: $1.050Bn 0.000% Sr. Unsecured Convertible Notes due 2027 | C72: 1029263 | D72: 1033277 | E72: 1037306 | F72: 998543 | H72: 1030265 | I72: 1031268 | J72: 1032272 | K72: =D72 -> 1033277 | L72: 1034283 | M72: 1035290 | N72: 1036298 | O72: =E72 -> 1037306 | P72: 1038316 | Q72: 1039327 | R72: 1040339 | S72: =F72 -> 998543 | T72: 0 | U72: 0 | V72: 0 | X72: =K72 -> 1033277 | Y72: =L72 -> 1034283 | Z72: =M72 -> 1035290 | AA72: =N72 -> 1036298 | AB72: =O72 -> 1037306 | AC72: =P72 -> 1038316 | AD72: =Q72 -> 1039327 | AE72: =R72 -> 1040339 | ... AI72: =V72 -> 0
B73: $1.010Bn 0.625% Sr. Unsecured Convertible Notes due 2028 | C73: 0 | D73: 0 | E73: 0 | F73: 2975037 | H73: 0 | I73: 0 | J73: 0 | K73: =D73 -> 0 | L73: 0 | M73: 0 | N73: 0 | O73: =E73 -> 0 | P73: 0 | Q73: 0 | R73: 997502 | S73: =F73 -> 2975037 | T73: 999587 | U73: 1000634 | V73: 1001683 | X73: =K73 -> 0 | Y73: =L73 -> 0 | Z73: =M73 -> 0 | AA73: =N73 -> 0 | AB73: =O73 -> 0 | AC73: =P73 -> 0 | AD73: =Q73 -> 0 | AE73: =R73 -> 997502 | ... AI73: =V73 -> 1001683
B74: $3.0Bn 0.000% Sr. Unsecured Convertible Notes due 2029 | C74: 0 | D74: 0 | E74: 0 | F74: 0 | H74: 0 | I74: 0 | J74: 0 | K74: =D74 -> 0 | L74: 0 | M74: 0 | N74: 0 | O74: =E74 -> 0 | P74: 0 | Q74: 0 | R74: 0 | S74: =F74 -> 0 | T74: 2976855 | U74: 2978675 | V74: 2980495 | X74: =K74 -> 0 | Y74: =L74 -> 0 | Z74: =M74 -> 0 | AA74: =N74 -> 0 | AB74: =O74 -> 0 | AC74: =P74 -> 0 | AD74: =Q74 -> 0 | AE74: =R74 -> 0 | ... AI74: =V74 -> 2980495
B75: $800MM 0.625% Sr. Unsecured Convertible Notes due 2030 | C75: 0 | D75: 0 | E75: 0 | F75: 785172 | H75: 0 | I75: 0 | J75: 0 | K75: =D75 -> 0 | L75: 0 | M75: 0 | N75: 0 | O75: =E75 -> 0 | P75: 782248 | Q75: 783220 | R75: 784194 | S75: =F75 -> 785172 | T75: 786152 | U75: 787135 | V75: 788121 | X75: =K75 -> 0 | Y75: =L75 -> 0 | Z75: =M75 -> 0 | AA75: =N75 -> 0 | AB75: =O75 -> 0 | AC75: =P75 -> 782248 | AD75: =Q75 -> 783220 | AE75: =R75 -> 784194 | ... AI75: =V75 -> 788121
B76: $800MM 0.000% Sr. Unsecured Convertible Notes due 2030 | C76: 0 | D76: 0 | E76: 0 | F76: 0 | H76: 0 | I76: 0 | J76: 0 | K76: =D76 -> 0 | L76: 0 | M76: 0 | N76: 0 | O76: =E76 -> 0 | P76: 0 | Q76: 0 | R76: 0 | S76: =F76 -> 0 | T76: 1985365 | U76: 1986614 | V76: 1987864 | X76: =K76 -> 0 | Y76: =L76 -> 0 | Z76: =M76 -> 0 | AA76: =N76 -> 0 | AB76: =O76 -> 0 | AC76: =P76 -> 0 | AD76: =Q76 -> 0 | AE76: =R76 -> 0 | ... AI76: =V76 -> 1987864
B77: $603.8MM 0.875% Sr. Unsecured Convertible Notes due 2031 | C77: 0 | D77: 0 | E77: 0 | F77: 594476 | H77: 0 | I77: 0 | J77: 0 | K77: =D77 -> 0 | L77: 0 | M77: 0 | N77: 0 | O77: =E77 -> 0 | P77: 592368 | Q77: 593259 | R77: 593867 | S77: =F77 -> 594476 | T77: 595087 | U77: 595613 | V77: 596228 | X77: =K77 -> 0 | Y77: =L77 -> 0 | Z77: =M77 -> 0 | AA77: =N77 -> 0 | AB77: =O77 -> 0 | AC77: =P77 -> 592368 | AD77: =Q77 -> 593259 | AE77: =R77 -> 593867 | ... AI77: =V77 -> 596228
B78: $800MM 2.250% Sr. Unsecured Convertible Notes due 2032 | C78: 0 | D78: 0 | E78: 0 | F78: 787417 | H78: 0 | I78: 0 | J78: 0 | K78: =D78 -> 0 | L78: 0 | M78: 0 | N78: 0 | O78: =E78 -> 0 | P78: 0 | Q78: 786095 | R78: 786754 | S78: =F78 -> 787417 | T78: 788084 | U78: 788756 | V78: 789433 | X78: =K78 -> 0 | Y78: =L78 -> 0 | Z78: =M78 -> 0 | AA78: =N78 -> 0 | AB78: =O78 -> 0 | AC78: =P78 -> 0 | AD78: =Q78 -> 786095 | AE78: =R78 -> 786754 | ... AI78: =V78 -> 789433
B79: $500MM 6.580% 2028 Sr. Secured Notes due 2028 | C79: 488006 | D79: 489547 | E79: 491193 | F79: 0 | H79: 488382 | I79: 488764 | J79: 489152 | K79: =D79 -> 489547 | L79: 489948 | M79: 490356 | N79: 490771 | O79: =E79 -> 491193 | P79: 491622 | Q79: 492057 | R79: 0 | S79: =F79 -> 0 | T79: 0 | U79: 0 | V79: 0 | X79: =K79 -> 489547 | Y79: =L79 -> 489948 | Z79: =M79 -> 490356 | AA79: =N79 -> 490771 | AB79: =O79 -> 491193 | AC79: =P79 -> 491622 | AD79: =Q79 -> 492057 | AE79: =R79 -> 0 | ... AI79: =V79 -> 0
B80: $205MM 3.870% 2025 Secured Term Loan | C80: 0 | D80: 204688 | E80: 0 | F80: 0 | H80: 204588 | I80: 204621 | J80: 204654 | K80: =D80 -> 204688 | L80: 0 | M80: 0 | N80: 0 | O80: =E80 -> 0 | P80: 0 | Q80: 0 | R80: 0 | S80: =F80 -> 0 | T80: 0 | U80: 0 | V80: 0 | X80: =K80 -> 204688 | Y80: =L80 -> 0 | Z80: =M80 -> 0 | AA80: =N80 -> 0 | AB80: =O80 -> 0 | AC80: =P80 -> 0 | AD80: =Q80 -> 0 | AE80: =R80 -> 0 | ... AI80: =V80 -> 0
B81: Other long-term secured debt | C81: 0 | D81: 10160 | E81: 9678 | F81: 9678 | H81: 0 | I81: 10830 | J81: 10724 | K81: =D81 -> 10160 | L81: 10042 | M81: 9923 | N81: 9802 | O81: =E81 -> 9678 | P81: 9549 | Q81: 9924 | R81: 9802 | S81: =F81 -> 9678 | T81: 9551 | U81: 25203 | V81: 30079 | X81: =K81 -> 10160 | Y81: =L81 -> 10042 | Z81: =M81 -> 9923 | AA81: =N81 -> 9802 | AB81: =O81 -> 9678 | AC81: =P81 -> 9549 | AD81: =Q81 -> 9924 | AE81: =R81 -> 9802 | ... AI81: =V81 -> 30079
B82: Total Debt | C82: =SUM(C71:C81) -> 2155151 | D82: =SUM(D71:D81) -> 2378560 | E82: =SUM(E71:E81) -> 2182108 | F82: =SUM(F71:F81) -> 7191675 | H82: =SUM(H71:H81) -> 2361865 | I82: =SUM(I71:I81) -> 2374863 | J82: =SUM(J71:J81) -> 2376935 | K82: =SUM(K71:K81) -> 2378560 | L82: =SUM(L71:L81) -> 2175918 | M82: =SUM(M71:M81) -> 2177974 | N82: =SUM(N71:N81) -> 2180038 | O82: =SUM(O71:O81) -> 2182108 | ... V82: =SUM(V71:V81) -> 8173903 | X82: =SUM(X71:X81) -> 2378560 | Y82: =SUM(Y71:Y81) -> 2175918 | Z82: =SUM(Z71:Z81) -> 2177974 | AA82: =SUM(AA71:AA81) -> 2180038 | AB82: =SUM(AB71:AB81) -> 2182108 | AC82: =SUM(AC71:AC81) -> 3558801 | AD82: =SUM(AD71:AD81) -> 3848500 | AE82: =SUM(AE71:AE81) -> 4212458 | ... AI82: =SUM(AI71:AI81) -> 8173903
B84: Total Shareholder Equity | C84: ='Historical Financials'!C83 -> 978958 | D84: ='Historical Financials'!D83 -> -383120 | E84: ='Historical Financials'!E83 -> 2164972 | F84: ='Historical Financials'!F83 -> 18229984 | H84: ='Historical Financials'!H83 -> 862999 | I84: ='Historical Financials'!I83 -> -187068 | J84: ='Historical Financials'!J83 -> -200289 | K84: ='Historical Financials'!K83 -> -383120 | L84: ='Historical Financials'!L83 -> 443211 | M84: ='Historical Financials'!M83 -> 819118 | N84: ='Historical Financials'!N83 -> 840395 | O84: ='Historical Financials'!O83 -> 2164972 | ... V84: ='Historical Financials'!V83 -> 58117048 | X84: =K84 -> -383120 | Y84: =L84 -> 443211 | Z84: =M84 -> 819118 | AA84: =N84 -> 840395 | AB84: =O84 -> 2164972 | AC84: =P84 -> 2400105 | AD84: =Q84 -> 2834799 | AE84: =R84 -> 3773649 | ... AI84: =V84 -> 58117048
B85: Total Book Capitalization | C85: =SUM(C82:C84) -> 3134109 | D85: =SUM(D82:D84) -> 1995440 | E85: =SUM(E82:E84) -> 4347080 | F85: =SUM(F82:F84) -> 25421659 | H85: =SUM(H82:H84) -> 3224864 | I85: =SUM(I82:I84) -> 2187795 | J85: =SUM(J82:J84) -> 2176646 | K85: =SUM(K82:K84) -> 1995440 | L85: =SUM(L82:L84) -> 2619129 | M85: =SUM(M82:M84) -> 2997092 | N85: =SUM(N82:N84) -> 3020433 | O85: =SUM(O82:O84) -> 4347080 | ... V85: =SUM(V82:V84) -> 66290951 | X85: =SUM(X82:X84) -> 1995440 | Y85: =SUM(Y82:Y84) -> 2619129 | Z85: =SUM(Z82:Z84) -> 2997092 | AA85: =SUM(AA82:AA84) -> 3020433 | AB85: =SUM(AB82:AB84) -> 4347080 | AC85: =SUM(AC82:AC84) -> 5958906 | AD85: =SUM(AD82:AD84) -> 6683299 | AE85: =SUM(AE82:AE84) -> 7986107 | ... AI85: =SUM(AI82:AI84) -> 66290951
B87: Credit Metrics
B89: LTM Total Leverage | C89: =C82/C30 -> -2.956137 | D89: =D82/D30 -> -1.9800724 | E89: =E82/E30 -> -70.506575 | F89: =F82/F30 -> -4.0907206 | K89: =SUM(K82/SUM(H30:K30)) -> -1.9800724 | L89: =SUM(L82/SUM(I30:L30)) -> -2.0768621 | M89: =SUM(M82/SUM(J30:M30)) -> -14.058157 | N89: =SUM(N82/SUM(K30:N30)) -> -11.737673 | O89: =SUM(O82/SUM(L30:O30)) -> -70.506575 | P89: =SUM(P82/SUM(M30:P30)) -> -16.591998 | Q89: =SUM(Q82/SUM(N30:Q30)) -> -10.061254 | R89: =SUM(R82/SUM(O30:R30)) -> -5.3727796 | ... V89: =SUM(V82/SUM(S30:V30)) -> 0.73822351 | X89: =X82/X30 -> -1.9800724 | Y89: =Y82/Y30 -> -2.0768621 | Z89: =Z82/Z30 -> -14.058157 | AA89: =AA82/AA30 -> -11.737673 | AB89: =AB82/AB30 -> -70.506575 | AC89: =AC82/AC30 -> -16.591998 | AD89: =AD82/AD30 -> -10.061254 | AE89: =AE82/AE30 -> -5.3727796 | ... AI89: =AI82/AI30 -> 0.73822351
B90: LTM Net Leverage | C90: =SUM(C82-C52)/C30 -> -2.8692341 | D90: =SUM(D82-D52)/D30 -> -1.9435812 | E90: =SUM(E82-E52)/E30 -> -68.993861 | F90: =SUM(F82-F52)/F30 -> -4.0690391 | K90: =SUM(K82-K52)/SUM(H30:K30) -> -1.9435812 | L90: =SUM(L82-L52)/SUM(I30:L30) -> -1.9868445 | M90: =SUM(M82-M52)/SUM(J30:M30) -> -13.632354 | N90: =SUM(N82-N52)/SUM(K30:N30) -> -11.495337 | O90: =SUM(O82-O52)/SUM(L30:O30) -> -68.993861 | P90: =SUM(P82-P52)/SUM(M30:P30) -> -16.212836 | Q90: =SUM(Q82-Q52)/SUM(N30:Q30) -> -9.8862949 | R90: =SUM(R82-R52)/SUM(O30:R30) -> -5.3136714 | ... V90: =SUM(V82-V52)/SUM(S30:V30) -> 0.73332077 | X90: =SUM(X82-X52)/X30 -> -1.9435812 | Y90: =SUM(Y82-Y52)/Y30 -> -1.9868445 | Z90: =SUM(Z82-Z52)/Z30 -> -13.632354 | AA90: =SUM(AA82-AA52)/AA30 -> -11.495337 | AB90: =SUM(AB82-AB52)/AB30 -> -68.993861 | AC90: =SUM(AC82-AC52)/AC30 -> -16.212836 | AD90: =SUM(AD82-AD52)/AD30 -> -9.8862949 | AE90: =SUM(AE82-AE52)/AE30 -> -5.3136714 | ... AI90: =SUM(AI82-AI52)/AI30 -> 0.73332077
B91: LTM Interest Coverage | C91: =C30/-C35 -> -35.709395 | D91: =D30/-D35 -> -27.64797 | E91: =E30/-E35 -> -0.75066094 | F91: =F30/-F35 -> -39.443719 | K91: {=SUM(H30:K30)/SUM(-H35:K35)} -> -22.607065 | L91: {=SUM(I30:L30)/SUM(-I35:L35)} -> -18.371912 | M91: {=SUM(J30:M30)/SUM(-J35:M35)} -> -2.8201693 | N91: {=SUM(K30:N30)/SUM(-K35:N35)} -> -3.5808205 | O91: {=SUM(L30:O30)/SUM(-L35:O35)} -> -0.63212827 | P91: {=SUM(M30:P30)/SUM(-M35:P35)} -> -4.6718433 | Q91: {=SUM(N30:Q30)/SUM(-N35:Q35)} -> -7.6072352 | R91: {=SUM(O30:R30)/SUM(-O35:R35)} -> -13.657991 | ... V91: {=SUM(S30:V30)/SUM(-S35:V35)} -> 157.37224 | X91: =X30/-X35 -> -22.607065 | Y91: =Y30/-Y35 -> -18.371912 | Z91: =Z30/-Z35 -> -2.8201693 | AA91: =AA30/-AA35 -> -3.5808205 | AB91: =AB30/-AB35 -> -0.63212827 | AC91: =AC30/-AC35 -> -4.6718433 | AD91: =AD30/-AD35 -> -7.6072352 | AE91: =AE30/-AE35 -> -13.657991 | ... AI91: =AI30/-AI35 -> 157.37224
B92: LTM Debt Service Coverage | C92: {=SUM(C30+C33)/SUM(-C34:C35)} -> -122.4487 | D92: {=SUM(D30+D33)/SUM(-D34:D35)} -> -22.800874 | E92: {=SUM(E30+E33)/SUM(-E34:E35)} -> -27.061736 | F92: {=SUM(F30+F33)/SUM(-F34:F35)} -> -522.32704 | K92: {=SUM(H30:K30+H33:K33)/SUM(-H34:K35)} -> -7.4408684 | L92: {=SUM(I30:L30+I33:L33)/SUM(-I34:L35)} -> 6.4825826 | M92: {=SUM(J30:M30+J33:M33)/SUM(-J34:M35)} -> 1.8675886 | N92: {=SUM(K30:N30+K33:N33)/SUM(-K34:N35)} -> 2.9469314 | O92: {=SUM(L30:O30+L33:O33)/SUM(-L34:O35)} -> 3.8364171 | P92: {=SUM(M30:P30+M33:P33)/SUM(-M34:P35)} -> 16.630391 | Q92: {=SUM(N30:Q30+N33:Q33)/SUM(-N34:Q35)} -> 15.945051 | R92: {=SUM(O30:R30+O33:R33)/SUM(-O34:R35)} -> 11.920909 | ... V92: {=SUM(S30:V30+S33:V33)/SUM(-S34:V35)} -> -8.6203869 | X92: {=SUM(X30+X33)/SUM(-X34:X35)} -> -7.4408684 | Y92: {=SUM(Y30+Y33)/SUM(-Y34:Y35)} -> 6.4825826 | Z92: {=SUM(Z30+Z33)/SUM(-Z34:Z35)} -> 1.8675886 | AA92: {=SUM(AA30+AA33)/SUM(-AA34:AA35)} -> 2.9469314 | AB92: {=SUM(AB30+AB33)/SUM(-AB34:AB35)} -> 3.8364171 | AC92: {=SUM(AC30+AC33)/SUM(-AC34:AC35)} -> 16.630391 | AD92: {=SUM(AD30+AD33)/SUM(-AD34:AD35)} -> 15.945051 | AE92: {=SUM(AE30+AE33)/SUM(-AE34:AE35)} -> 11.920909 | ... AI92: {=SUM(AI30+AI33)/SUM(-AI34:AI35)} -> -8.6203869
B93: LTM Fixed Charge Coverage | C93: {=SUM(C30)/SUM(-C33:C35)} -> -0.27442079 | D93: {=SUM(D30)/SUM(-D33:D35)} -> -3.375926 | E93: {=SUM(E30)/SUM(-E33:E35)} -> -0.015656238 | F93: {=SUM(F30)/SUM(-F33:F35)} -> -0.079472756 | K93: {=SUM(H30:K30)/SUM(-H33:K35)} -> -2.4471586 | L93: {=SUM(I30:L30)/SUM(-I33:L35)} -> -19.680567 | M93: {=SUM(J30:M30)/SUM(-J33:M35)} -> -0.80900038 | N93: {=SUM(K30:N30)/SUM(-K33:N35)} -> -0.43102208 | O93: {=SUM(L30:O30)/SUM(-L33:O35)} -> -0.022097732 | P93: {=SUM(M30:P30)/SUM(-M33:P35)} -> -0.068070136 | Q93: {=SUM(N30:Q30)/SUM(-N33:Q35)} -> -0.10774575 | R93: {=SUM(O30:R30)/SUM(-O33:R35)} -> -0.16605796 | ... V93: {=SUM(S30:V30)/SUM(-S33:V35)} -> 0.27328489 | X93: {=SUM(X30)/SUM(-X33:X35)} -> -2.4471586 | Y93: {=SUM(Y30)/SUM(-Y33:Y35)} -> -19.680567 | Z93: {=SUM(Z30)/SUM(-Z33:Z35)} -> -0.80900038 | AA93: {=SUM(AA30)/SUM(-AA33:AA35)} -> -0.43102208 | AB93: {=SUM(AB30)/SUM(-AB33:AB35)} -> -0.022097732 | AC93: {=SUM(AC30)/SUM(-AC33:AC35)} -> -0.068070136 | AD93: {=SUM(AD30)/SUM(-AD33:AD35)} -> -0.10774575 | AE93: {=SUM(AE30)/SUM(-AE33:AE35)} -> -0.16605796 | ... AI93: {=SUM(AI30)/SUM(-AI33:AI35)} -> 0.27328489
B94: Debt-to-Book Capitalization | C94: =C85/C82 -> 1.454241 | D94: =D85/D82 -> 0.83892775 | E94: =E85/E82 -> 1.992147 | F94: =F85/F82 -> 3.5348732 | K94: =K85/K82 -> 0.83892775 | L94: =L85/L82 -> 1.2036892 | M94: =M85/M82 -> 1.3760917 | N94: =N85/N82 -> 1.3854956 | O94: =O85/O82 -> 1.992147 | P94: =P85/P82 -> 1.6744139 | Q94: =Q85/Q82 -> 1.7365984 | R94: =R85/R82 -> 1.8958307 | ... V94: =V85/V82 -> 8.1100731 | X94: =X85/X82 -> 0.83892775 | Y94: =Y85/Y82 -> 1.2036892 | Z94: =Z85/Z82 -> 1.3760917 | AA94: =AA85/AA82 -> 1.3854956 | AB94: =AB85/AB82 -> 1.992147 | AC94: =AC85/AC82 -> 1.6744139 | AD94: =AD85/AD82 -> 1.7365984 | AE94: =AE85/AE82 -> 1.8958307 | ... AI94: =AI85/AI82 -> 8.1100731
