Workbook

Sheet 3-Statement Model
B2: Microstrategy, Inc. (NASDAQ: MSTR) | C2: FYE | D2: FYE | H2: Quarterly | N2: Quarterly | Q2: Quarterly | W2: LTM | Z2: Variance
B3: 3-Statement Model | C3: 2021 | D3: 2022 | E3: 2023 | F3: 2024 | H3: 1Q22 | I3: 2Q22 | J3: 3Q22 | K3: 4Q22 | L3: 1Q23 | M3: 2Q23 | N3: 3Q23 | O3: 4Q23 | P3: 1Q24 | Q3: 2Q24 | R3: 3Q24 | S3: 4Q24 | T3: 1Q25 | U3: 2Q25 | W3: 3Q24 | X3: 3Q24
B4: ($ In Thousands) | C4: 44561 | D4: 44926 | E4: 45291 | F4: 45657 | H4: 44651 | I4: 44742 | J4: 44834 | K4: 44926 | L4: 45016 | M4: 45107 | N4: 45199 | O4: 45291 | P4: 45382 | Q4: 45473 | R4: 45565 | S4: 45657 | T4: 45747 | U4: 45838 | W4: 45565 | X4: 45565
A6: X | B6: Income Statement
B8: Product licenses | C8: 101804 | D8: 86498 | E8: 75351 | F8: 48567 | H8: 16513 | I8: 20129 | J8: 22286 | K8: =SUM(D8-SUM(H8:J8)) -> 27570 | L8: 17412 | M8: 15522 | N8: 24045 | O8: =SUM(E8-SUM(L8:N8)) -> 18372 | P8: 12938 | Q8: 9286 | R8: 11087 | S8: =SUM(F8-SUM(P8:R8)) -> 15256 | T8: 7270 | U8: 7177 | W8: =SUM(K8:N8) -> 84549 | X8: =SUM(O8:R8) -> 51683
B9: Subscription services | C9: 43069 | D9: 60746 | E9: 81179 | F9: 106776 | H9: 12845 | I9: 14017 | J9: 16414 | K9: =SUM(D9-SUM(H9:J9)) -> 17470 | L9: 18810 | M9: 19878 | N9: 20974 | O9: =SUM(E9-SUM(L9:N9)) -> 21517 | P9: 22966 | Q9: 24080 | R9: 27800 | S9: =SUM(F9-SUM(P9:R9)) -> 31930 | T9: 37103 | U9: 40824 | W9: =SUM(K9:N9) -> 77132 | X9: =SUM(O9:R9) -> 96363
B10: Total product licenses and subscription services | C10: =SUM(C8:C9) -> 144873 | D10: =SUM(D8:D9) -> 147244 | E10: =SUM(E8:E9) -> 156530 | F10: =SUM(F8:F9) -> 155343 | H10: =SUM(H8:H9) -> 29358 | I10: =SUM(I8:I9) -> 34146 | J10: =SUM(J8:J9) -> 38700 | K10: =SUM(K8:K9) -> 45040 | L10: =SUM(L8:L9) -> 36222 | M10: =SUM(M8:M9) -> 35400 | N10: =SUM(N8:N9) -> 45019 | O10: =SUM(O8:O9) -> 39889 | ... U10: =SUM(U8:U9) -> 48001 | W10: =SUM(W8:W9) -> 161681 | X10: =SUM(X8:X9) -> 148046
B11: Product support | C11: 281209 | D11: 266521 | E11: 263888 | F11: 243805 | H11: 67151 | I11: 66521 | J11: 66010 | K11: =SUM(D11-SUM(H11:J11)) -> 66839 | L11: 65481 | M11: 66081 | N11: 66860 | O11: =SUM(E11-SUM(L11:N11)) -> 65466 | P11: 62685 | Q11: 61740 | R11: 61015 | S11: =SUM(F11-SUM(P11:R11)) -> 58365 | T11: 52529 | U11: 52081 | W11: =SUM(K11:N11) -> 265261 | X11: =SUM(O11:R11) -> 250906
B12: Other services | C12: 84680 | D12: 85499 | E12: 75843 | F12: 64308 | H12: 22768 | I12: 21406 | J12: 20650 | K12: =SUM(D12-SUM(H12:J12)) -> 20675 | L12: 20212 | M12: 18919 | N12: 17583 | O12: =SUM(E12-SUM(L12:N12)) -> 19129 | P12: 16657 | Q12: 16336 | R12: 16169 | S12: =SUM(F12-SUM(P12:R12)) -> 15146 | T12: 14164 | U12: 14406 | W12: =SUM(K12:N12) -> 77389 | X12: =SUM(O12:R12) -> 68291
B13: Total Revenue | C13: =+C10+SUM(C11:C12) -> 510762 | D13: =+D10+SUM(D11:D12) -> 499264 | E13: =+E10+SUM(E11:E12) -> 496261 | F13: =+F10+SUM(F11:F12) -> 463456 | H13: =+H10+SUM(H11:H12) -> 119277 | I13: =+I10+SUM(I11:I12) -> 122073 | J13: =+J10+SUM(J11:J12) -> 125360 | K13: =+K10+SUM(K11:K12) -> 132554 | L13: =+L10+SUM(L11:L12) -> 121915 | M13: =+M10+SUM(M11:M12) -> 120400 | N13: =+N10+SUM(N11:N12) -> 129462 | O13: =+O10+SUM(O11:O12) -> 124484 | ... U13: =+U10+SUM(U11:U12) -> 114488 | W13: =+W10+SUM(W11:W12) -> 504331 | X13: =+X10+SUM(X11:X12) -> 467243
B15: Product licenses | C15: -1721 | D15: -1672 | E15: -1929 | F15: -3060 | H15: -477 | I15: -431 | J15: -406 | K15: =SUM(D15-SUM(H15:J15)) -> -358 | L15: -534 | M15: -444 | N15: -342 | O15: =SUM(E15-SUM(L15:N15)) -> -609 | P15: -567 | Q15: -794 | R15: -769 | S15: =SUM(F15-SUM(P15:R15)) -> -930 | T15: -964 | U15: -1169 | W15: =SUM(K15:N15) -> -1678 | X15: =SUM(O15:R15) -> -2739
B16: Subscription services | C16: -16901 | D16: -24770 | E16: -31776 | F16: -42440 | H16: -5410 | I16: -5498 | J16: -6395 | K16: =SUM(D16-SUM(H16:J16)) -> -7467 | L16: -7856 | M16: -7216 | N16: -8028 | O16: =SUM(E16-SUM(L16:N16)) -> -8676 | P16: -8604 | Q16: -9560 | R16: -11454 | S16: =SUM(F16-SUM(P16:R16)) -> -12822 | T16: -14429 | U16: -15906 | W16: =SUM(K16:N16) -> -30567 | X16: =SUM(O16:R16) -> -38294
B17: Total product licenses and subscription services | C17: =SUM(C15:C16) -> -18622 | D17: =SUM(D15:D16) -> -26442 | E17: =SUM(E15:E16) -> -33705 | F17: =SUM(F15:F16) -> -45500 | H17: =SUM(H15:H16) -> -5887 | I17: =SUM(I15:I16) -> -5929 | J17: =SUM(J15:J16) -> -6801 | K17: =SUM(K15:K16) -> -7825 | L17: =SUM(L15:L16) -> -8390 | M17: =SUM(M15:M16) -> -7660 | N17: =SUM(N15:N16) -> -8370 | O17: =SUM(O15:O16) -> -9285 | ... U17: =SUM(U15:U16) -> -17075 | W17: =SUM(W15:W16) -> -32245 | X17: =SUM(X15:X16) -> -41033
B18: Product support | C18: -19254 | D18: -21264 | E18: -22434 | F18: -33289 | H18: -5191 | I18: -5127 | J18: -5224 | K18: =SUM(D18-SUM(H18:J18)) -> -5722 | L18: -5768 | M18: -5816 | N18: -5531 | O18: =SUM(E18-SUM(L18:N18)) -> -5319 | P18: -8547 | Q18: -8193 | R18: -8572 | S18: =SUM(F18-SUM(P18:R18)) -> -7977 | T18: -7354 | U18: -7291 | W18: =SUM(K18:N18) -> -22837 | X18: =SUM(O18:R18) -> -30631
B19: Other services | C19: -54033 | D19: -55283 | E19: -53805 | F19: -50679 | H19: -14599 | I19: -14148 | J19: -13360 | K19: =SUM(D19-SUM(H19:J19)) -> -13176 | L19: -13783 | M19: -13645 | N19: -12760 | O19: =SUM(E19-SUM(L19:N19)) -> -13617 | P19: -12297 | Q19: -12388 | R19: -13554 | S19: =SUM(F19-SUM(P19:R19)) -> -12440 | T19: -11224 | U19: -11384 | W19: =SUM(K19:N19) -> -53364 | X19: =SUM(O19:R19) -> -51856
B20: Gross Profit | C20: =+SUM(C13+SUM(C17:C19)) -> 418853 | D20: =+SUM(D13+SUM(D17:D19)) -> 396275 | E20: =+SUM(E13+SUM(E17:E19)) -> 386317 | F20: =+SUM(F13+SUM(F17:F19)) -> 333988 | H20: =+SUM(H13+SUM(H17:H19)) -> 93600 | I20: =+SUM(I13+SUM(I17:I19)) -> 96869 | J20: =+SUM(J13+SUM(J17:J19)) -> 99975 | K20: =+SUM(K13+SUM(K17:K19)) -> 105831 | L20: =+SUM(L13+SUM(L17:L19)) -> 93974 | M20: =+SUM(M13+SUM(M17:M19)) -> 93279 | N20: =+SUM(N13+SUM(N17:N19)) -> 102801 | O20: =+SUM(O13+SUM(O17:O19)) -> 96263 | ... U20: =+SUM(U13+SUM(U17:U19)) -> 78738 | W20: =+SUM(W13+SUM(W17:W19)) -> 395885 | X20: =+SUM(X13+SUM(X17:X19)) -> 343723
B21: Gross Margin | C21: =C20/C13 -> 0.82005513 | D21: =D20/D13 -> 0.79371835 | E21: =E20/E13 -> 0.77845529 | F21: =F20/F13 -> 0.72064662 | H21: =H20/H13 -> 0.78472799 | I21: =I20/I13 -> 0.79353338 | J21: =J20/J13 -> 0.79750319 | K21: =K20/K13 -> 0.79839914 | L21: =L20/L13 -> 0.77081573 | M21: =M20/M13 -> 0.77474252 | N21: =N20/N13 -> 0.79406312 | O21: =O20/O13 -> 0.77329617 | ... U21: =U20/U13 -> 0.6877402 | W21: =W20/W13 -> 0.78497058 | X21: =X20/X13 -> 0.73564077
B23: Sales and marketing | C23: -160141 | D23: -146882 | E23: -149671 | F23: -138081 | H23: -33240 | I23: -36862 | J23: -35409 | K23: =SUM(D23-SUM(H23:J23)) -> -41371 | L23: -36106 | M23: -37660 | N23: -35606 | O23: =SUM(E23-SUM(L23:N23)) -> -40299 | P23: -33451 | Q23: -34251 | R23: -35414 | S23: =SUM(F23-SUM(P23:R23)) -> -34965 | T23: -27532 | U23: -33691 | W23: =SUM(K23:N23) -> -150743 | X23: =SUM(O23:R23) -> -143415
B24: Research and development | C24: -117117 | D24: -127428 | E24: -120530 | F24: -118486 | H24: -33523 | I24: -31790 | J24: -30498 | K24: =SUM(D24-SUM(H24:J24)) -> -31617 | L24: -31358 | M24: -29354 | N24: -29660 | O24: =SUM(E24-SUM(L24:N24)) -> -30158 | P24: -29183 | Q24: -30311 | R24: -33301 | S24: =SUM(F24-SUM(P24:R24)) -> -25691 | T24: -24423 | U24: =-24071 -> -24071 | W24: =SUM(K24:N24) -> -121989 | X24: =SUM(O24:R24) -> -122953
B25: General and administrative | C25: -95501 | D25: -111421 | E25: -115312 | F25: -140537 | H25: -26706 | I25: -28502 | J25: -27283 | K25: =SUM(D25-SUM(H25:J25)) -> -28930 | L25: -27906 | M25: -28830 | N25: -29223 | O25: =SUM(E25-SUM(L25:N25)) -> -29353 | P25: -34666 | Q25: -36129 | R25: -33505 | S25: =SUM(F25-SUM(P25:R25)) -> -36237 | T25: -40547 | U25: -36500 | W25: =SUM(K25:N25) -> -114889 | X25: =SUM(O25:R25) -> -133653
B26: Unrealized gain on digital assets | C26: 0 | D26: 0 | E26: 0 | F26: 0 | H26: 0 | I26: 0 | J26: 0 | K26: 0 | L26: 0 | M26: 0 | N26: 0 | O26: 0 | P26: 0 | Q26: 0 | R26: 0 | S26: 0 | T26: =-5906005 -> -5906005 | U26: 14047514
B27: Digital asset impairment gains (losses on sale), net | C27: -830621 | D27: -1286286 | E27: -115851 | F27: -1789862 | H27: -170091 | I27: -917838 | J27: -727 | K27: =SUM(D27-SUM(H27:J27)) -> -197630 | L27: -18911 | M27: -24143 | N27: -33559 | O27: =SUM(E27-SUM(L27:N27)) -> -39238 | P27: -191633 | Q27: -180090 | R27: -412084 | S27: =SUM(F27-SUM(P27:R27)) -> -1006055 | T27: 0 | U27: 0 | W27: =SUM(K27:N27) -> -274243 | X27: =SUM(O27:R27) -> -823045
B28: Profit From Operations | C28: =SUM(C20+SUM(C23:C27)) -> -784527 | D28: =SUM(D20+SUM(D23:D27)) -> -1275742 | E28: =SUM(E20+SUM(E23:E27)) -> -115047 | F28: =SUM(F20+SUM(F23:F27)) -> -1852978 | H28: =SUM(H20+SUM(H23:H27)) -> -169960 | I28: =SUM(I20+SUM(I23:I27)) -> -918123 | J28: =SUM(J20+SUM(J23:J27)) -> 6058 | K28: =SUM(K20+SUM(K23:K27)) -> -193717 | L28: =SUM(L20+SUM(L23:L27)) -> -20307 | M28: =SUM(M20+SUM(M23:M27)) -> -26708 | N28: =SUM(N20+SUM(N23:N27)) -> -25247 | O28: =SUM(O20+SUM(O23:O27)) -> -42785 | ... U28: =SUM(U20+SUM(U23:U27)) -> 14031990 | W28: =SUM(W20+SUM(W23:W27)) -> -265979 | X28: =SUM(X20+SUM(X23:X27)) -> -879343
B29: Operating Margin | C29: =C28/C13 -> -1.5359933 | D29: =D28/D13 -> -2.5552453 | E29: =E28/E13 -> -0.23182761 | F29: =F28/F13 -> -3.9981746 | H29: =H28/H13 -> -1.4249185 | I29: =I28/I13 -> -7.521098 | J29: =J28/J13 -> 0.048324825 | K29: =K28/K13 -> -1.4614195 | L29: =L28/L13 -> -0.16656687 | M29: =M28/M13 -> -0.22182724 | N29: =N28/N13 -> -0.19501475 | O29: =O28/O13 -> -0.34369879 | ... U29: =U28/U13 -> 122.56298 | W29: =W28/W13 -> -0.52738975 | X29: =X28/X13 -> -1.8819822
B31: Interest expense, net | C31: -29149 | D31: -53136 | E31: -48960 | F31: -61941 | H31: -11039 | I31: -13187 | J31: -14073 | K31: =SUM(D31-SUM(H31:J31)) -> -14837 | L31: -14930 | M31: -11095 | N31: -11006 | O31: =SUM(E31-SUM(L31:N31)) -> -11929 | P31: -11881 | Q31: -15466 | R31: -18129 | S31: =SUM(F31-SUM(P31:R31)) -> -16465 | T31: -17106 | U31: -17897 | W31: =SUM(K31:N31) -> -51868 | X31: =SUM(L31:O31) -> -48960
B32: Gain (Loss) on debt extinguishment | C32: 0 | D32: 0 | E32: 44686 | F32: -22933 | H32: 0 | I32: 0 | J32: 0 | K32: =SUM(D32-SUM(H32:J32)) -> 0 | L32: 44686 | M32: 0 | N32: 0 | O32: =SUM(E32-SUM(L32:N32)) -> 0 | P32: 0 | Q32: 0 | R32: -22933 | S32: =SUM(F32-SUM(P32:R32)) -> 0 | T32: 0 | U32: 0 | W32: =SUM(K32:N32) -> 44686 | X32: =SUM(L32:O32) -> 44686
B33: Other income (expense), net | C33: 2287 | D33: 6413 | E33: -5204 | F33: 3506 | H33: 2225 | I33: 5120 | J33: 4897 | K33: =SUM(D33-SUM(H33:J33)) -> -5829 | L33: -1443 | M33: -250 | N33: 2419 | O33: =SUM(E33-SUM(L33:N33)) -> -5930 | P33: 1696 | Q33: 694 | R33: -5034 | S33: =SUM(F33-SUM(P33:R33)) -> 6150 | T33: -3936 | U33: -8271 | W33: =SUM(K33:N33) -> -5103 | X33: =SUM(L33:O33) -> -5204
B34: Net loss before provision for income taxes | C34: =SUM(C31:C33)+C28 -> -811389 | D34: =SUM(D31:D33)+D28 -> -1322465 | E34: =SUM(E31:E33)+E28 -> -124525 | F34: =SUM(F31:F33)+F28 -> -1934346 | H34: =SUM(H31:H33)+H28 -> -178774 | I34: =SUM(I31:I33)+I28 -> -926190 | J34: =SUM(J31:J33)+J28 -> -3118 | K34: =SUM(K31:K33)+K28 -> -214383 | L34: =SUM(L31:L33)+L28 -> 8006 | M34: =SUM(M31:M33)+M28 -> -38053 | N34: =SUM(N31:N33)+N28 -> -33834 | O34: =SUM(O31:O33)+O28 -> -60644 | ... U34: =SUM(U31:U33)+U28 -> 14005822 | W34: =SUM(W31:W33)+W28 -> -278264 | X34: =SUM(X31:X33)+X28 -> -888821
B36: Benefit (Expense) from provision for income taxes | C36: 275909 | D36: -147332 | E36: 553646 | F36: 767685 | H36: 48023 | I36: -136108 | J36: -23961 | K36: -35286 | L36: 453187 | M36: 60296 | N36: -109607 | O36: =SUM(E36-SUM(L36:N36)) -> 149770 | P36: 160769 | Q36: 112487 | R36: 138504 | S36: =SUM(F36-SUM(P36:R36)) -> 355925 | T36: 1725084 | U36: -3984976 | W36: =SUM(K36:N36) -> 368590 | X36: =SUM(L36:O36) -> 553646
B37: Net loss | C37: =SUM(C34+C36) -> -535480 | D37: =SUM(D34+D36) -> -1469797 | E37: =SUM(E34+E36) -> 429121 | F37: =SUM(F34+F36) -> -1166661 | H37: =SUM(H34+H36) -> -130751 | I37: =SUM(I34+I36) -> -1062298 | J37: =SUM(J34+J36) -> -27079 | K37: =SUM(K34+K36) -> -249669 | L37: =SUM(L34+L36) -> 461193 | M37: =SUM(M34+M36) -> 22243 | N37: =SUM(N34+N36) -> -143441 | O37: =SUM(O34+O36) -> 89126 | ... U37: =SUM(U34+U36) -> 10020846 | W37: =SUM(W34+W36) -> 90326 | X37: =SUM(X34+X36) -> -335175
B38: Net Margin | C38: =C37/C13 -> -1.0483944 | D38: =D37/D13 -> -2.9439275 | E38: =E37/E13 -> 0.86470829 | F38: =F37/F13 -> -2.5173069 | H38: =H37/H13 -> -1.0961962 | I38: =I37/I13 -> -8.7021536 | J38: =J37/J13 -> -0.21600989 | K38: =K37/K13 -> -1.8835267 | L38: =L37/L13 -> 3.7829061 | M38: =M37/M13 -> 0.18474252 | N38: =N37/N13 -> -1.1079776 | O38: =O37/O13 -> 0.7159635 | ... U38: =U37/U13 -> 87.527479 | W38: =W37/W13 -> 0.17910063 | X38: =X37/X13 -> -0.71734622
A40: X | B40: Balance Sheet Statement
B42: Cash and cash equivalents | C42: 63356 | D42: 43835 | E42: 46817 | F42: 38117 | H42: 92677 | I42: 69386 | J42: 60390 | K42: =D42 -> 43835 | L42: 94311 | M42: 65968 | N42: 45009 | O42: =E42 -> 46817 | P42: 81326 | Q42: 66923 | R42: 46343 | S42: =F42 -> 38117 | T42: 60298 | U42: 50095 | W42: =SUM(K42:N42) -> 249123 | X42: =SUM(O42:R42) -> 241409
B43: Restricted cash | C43: 1078 | D43: 7033 | E43: 1856 | F43: 1780 | H43: 6265 | I43: 6155 | J43: 6578 | K43: =D43 -> 7033 | L43: 2153 | M43: 2085 | N43: 1865 | O43: =E43 -> 1856 | P43: 2402 | Q43: 1878 | R43: 1862 | S43: =F43 -> 1780 | T43: 1960 | U43: 2037 | W43: =SUM(K43:N43) -> 13136 | X43: =SUM(O43:R43) -> 7998
B44: Accounts receivable, net | C44: 189280 | D44: 189280 | E44: 183815 | F44: 181203 | H44: 126930 | I44: 118645 | J44: 109926 | K44: =D44 -> 189280 | L44: 139178 | M44: 121901 | N44: 128650 | O44: =E44 -> 183815 | P44: 115150 | Q44: 112234 | R44: 107169 | S44: =F44 -> 181203 | T44: 104585 | U44: 117870 | W44: =SUM(K44:N44) -> 579009 | X44: =SUM(O44:R44) -> 518368
B45: Prepaid expenses and other current assets | C45: 14251 | D45: 24418 | E45: 35407 | F45: 31224 | H45: 21116 | I45: 25496 | J45: 25399 | K45: =D45 -> 24418 | L45: 24034 | M45: 19680 | N45: 24041 | O45: =E45 -> 35407 | P45: 42714 | Q45: 27234 | R45: 30668 | S45: =F45 -> 31224 | T45: 36769 | U45: 43459 | W45: =SUM(K45:N45) -> 92173 | X45: =SUM(O45:R45) -> 136023
B46: Total Current Assets | C46: =SUM(C42:C45) -> 267965 | D46: =SUM(D42:D45) -> 264566 | E46: =SUM(E42:E45) -> 267895 | F46: =SUM(F42:F45) -> 252324 | H46: =SUM(H42:H45) -> 246988 | I46: =SUM(I42:I45) -> 219682 | J46: =SUM(J42:J45) -> 202293 | K46: =SUM(K42:K45) -> 264566 | L46: =SUM(L42:L45) -> 259676 | M46: =SUM(M42:M45) -> 209634 | N46: =SUM(N42:N45) -> 199565 | O46: =SUM(O42:O45) -> 267895 | ... U46: =SUM(U42:U45) -> 213461 | W46: =SUM(W42:W45) -> 933441 | X46: =SUM(X42:X45) -> 903798
B48: Digital assets | C48: 2850210 | D48: 1840028 | E48: 3626476 | F48: 23909373 | H48: 2895619 | I48: 1987781 | J48: 1993032 | K48: =D48 -> 1840028 | L48: 2000392 | M48: 2323252 | N48: 2451374 | O48: =E48 -> 3626476 | P48: 5074152 | Q48: 5687890 | R48: 6850879 | S48: =F48 -> 23909373 | T48: 43546079 | U48: 64362798 | W48: =SUM(K48:N48) -> 8615046 | X48: =SUM(O48:R48) -> 21239397
B49: Property and equipment, net | C49: 36587 | D49: 32311 | E49: 28941 | F49: 26327 | H49: 35680 | I49: 34580 | J49: 33033 | K49: =D49 -> 32311 | L49: 31338 | M49: 30507 | N49: 30192 | O49: =E49 -> 28941 | P49: 29108 | Q49: 28332 | R49: 27517 | S49: =F49 -> 26327 | T49: 28335 | U49: 30203 | W49: =SUM(K49:N49) -> 124348 | X49: =SUM(O49:R49) -> 113898
B50: Right-of-use assets | C50: 66760 | D50: 61299 | E50: 57343 | F50: 54560 | H50: 64637 | I50: 65169 | J50: 62902 | K50: =D50 -> 61299 | L50: 59655 | M50: 58264 | N50: 54542 | O50: =E50 -> 57343 | P50: 55093 | Q50: 53591 | R50: 55308 | S50: =F50 -> 54560 | T50: 53070 | U50: 51573 | W50: =SUM(K50:N50) -> 233760 | X50: =SUM(O50:R50) -> 221335
B51: Deposits and other assets | C51: 15820 | D51: 23916 | E51: 24300 | F51: 75794 | H51: 18181 | I51: 17786 | J51: 20992 | K51: =D51 -> 23916 | L51: 23825 | M51: 22421 | N51: 24156 | O51: =E51 -> 24300 | P51: 31757 | Q51: 43449 | R51: 51109 | S51: =F51 -> 75794 | T51: 83261 | U51: 109664 | W51: =SUM(K51:N51) -> 94318 | X51: =SUM(O51:R51) -> 150615
B52: Deferred tax assets, net | C52: 319782 | D52: 188152 | E52: 757573 | F52: 1525307 | H52: 377282 | I52: 243367 | J52: 233034 | K52: =D52 -> 188152 | L52: 651516 | M52: 719026 | N52: 614112 | O52: =E52 -> 757573 | P52: 919837 | Q52: 1031542 | R52: 1172726 | S52: =F52 -> 1525307 | T52: 5403 | U52: 5716 | W52: =SUM(K52:N52) -> 2172806 | X52: =SUM(O52:R52) -> 3881678
B53: Total Assets | C53: =SUM(C48:C52)+C46 -> 3557124 | D53: =SUM(D48:D52)+D46 -> 2410272 | E53: =SUM(E48:E52)+E46 -> 4762528 | F53: =SUM(F48:F52)+F46 -> 25843685 | H53: =SUM(H48:H52)+H46 -> 3638387 | I53: =SUM(I48:I52)+I46 -> 2568365 | J53: =SUM(J48:J52)+J46 -> 2545286 | K53: =SUM(K48:K52)+K46 -> 2410272 | L53: =SUM(L48:L52)+L46 -> 3026402 | M53: =SUM(M48:M52)+M46 -> 3363104 | N53: =SUM(N48:N52)+N46 -> 3373941 | O53: =SUM(O48:O52)+O46 -> 4762528 | ... U53: =SUM(U48:U52)+U46 -> 64773415 | W53: =SUM(W48:W52)+W46 -> 12173719 | X53: =SUM(X48:X52)+X46 -> 26510721
B55: Accounts payable, accrued expenses, and operating lease liabilities | C55: 46084 | D55: 42976 | E55: 43090 | F55: 52982 | H55: 44388 | I55: 35960 | J55: 36846 | K55: =D55 -> 42976 | L55: 50604 | M55: 33660 | N55: 34306 | O55: =I55 -> 35960 | P55: 41866 | Q55: 44188 | R55: 45714 | S55: =F55 -> 52982 | T55: 53716 | U55: 44220 | W55: =SUM(K55:N55) -> 161546 | X55: =SUM(O55:R55) -> 167728
B56: Accrued compensation and employee benefits | C56: 54548 | D56: 53716 | E56: 50045 | F56: 58362 | H56: 43726 | I56: 47773 | J56: 46346 | K56: =D56 -> 53716 | L56: 39199 | M56: 41492 | N56: 43405 | O56: =E56 -> 50045 | P56: 40617 | Q56: 46853 | R56: 51686 | S56: =F56 -> 58362 | T56: 32785 | U56: 50132 | W56: =SUM(K56:N56) -> 177812 | X56: =SUM(O56:R56) -> 189201
B57: Accrued interest | C57: 1493 | D57: 2829 | E57: 1493 | F57: 5549 | H57: 10544 | I57: 2269 | J57: 11394 | K57: =D57 -> 2829 | L57: 10368 | M57: 1493 | N57: 10368 | O57: =E57 -> 1493 | P57: 10878 | Q57: 5066 | R57: 5800 | S57: =F57 -> 5549 | T57: 5970 | U57: 5620 | W57: =SUM(K57:N57) -> 25058 | X57: =SUM(O57:R57) -> 23237
B58: Current portion of long-term debt, net | C58: 0 | D58: 454 | E58: 483 | F58: 517 | H58: 0 | I58: 0 | J58: 0 | K58: =D58 -> 454 | L58: 460 | M58: 468 | N58: 475 | O58: =E58 -> 483 | P58: 492 | Q58: 145119 | R58: 509 | S58: =F58 -> 517 | T58: 525 | U58: 349 | W58: =SUM(K58:N58) -> 1857 | X58: =SUM(O58:R58) -> 146603
B59: Deferred revenue and advance payments | C59: 209860 | D59: 217428 | E59: 228162 | F59: 237974 | H59: 206217 | I59: 188098 | J59: 165934 | K59: =D59 -> 217428 | L59: 211768 | M59: 195817 | N59: 179167 | O59: =E59 -> 228162 | P59: 215955 | Q59: 204837 | R59: 184402 | S59: =F59 -> 237974 | T59: 215693 | U59: 214251 | W59: =SUM(K59:N59) -> 804180 | X59: =SUM(O59:R59) -> 833356
B60: Total Current Liabilities | C60: =SUM(C55:C59) -> 311985 | D60: =SUM(D55:D59) -> 317403 | E60: =SUM(E55:E59) -> 323273 | F60: =SUM(F55:F59) -> 355384 | H60: =SUM(H55:H59) -> 304875 | I60: =SUM(I55:I59) -> 274100 | J60: =SUM(J55:J59) -> 260520 | K60: =SUM(K55:K59) -> 317403 | L60: =SUM(L55:L59) -> 312399 | M60: =SUM(M55:M59) -> 272930 | N60: =SUM(N55:N59) -> 267721 | O60: =SUM(O55:O59) -> 316143 | ... U60: =SUM(U55:U59) -> 314572 | W60: =SUM(W55:W59) -> 1170453 | X60: =SUM(X55:X59) -> 1360125
B62: Long-term debt, net | C62: 2155151 | D62: 2378560 | E62: 2182108 | F62: 7191158 | H62: 2361865 | I62: 2374863 | J62: 2376935 | K62: =D62 -> 2378560 | L62: 2175918 | M62: 2177974 | N62: 2180038 | O62: =I62 -> 2374863 | P62: 3558801 | Q62: 3703381 | R62: 4211949 | S62: =F62 -> 7191158 | T62: 8140156 | U62: 8162281 | W62: =SUM(K62:N62) -> 8912490 | X62: =SUM(O62:R62) -> 13848994
B63: Deferred revenue and advance payments | C63: 8089 | D63: 12763 | E63: 8524 | F63: 4970 | H63: 8236 | I63: 8497 | J63: 8754 | K63: =D63 -> 12763 | L63: 11646 | M63: 11244 | N63: 7638 | O63: =I63 -> 8497 | P63: 6486 | Q63: 5964 | R63: 6344 | S63: =F63 -> 4970 | T63: 3981 | U63: 4197 | W63: =SUM(K63:N63) -> 43291 | X63: =SUM(O63:R63) -> 27291
B64: Operating lease liabilities | C64: 76608 | D64: 67344 | E64: 61086 | F64: 56403 | H64: 73956 | I64: 72162 | J64: 69278 | K64: =D64 -> 67344 | L64: 65355 | M64: 63814 | N64: 59720 | O64: =I64 -> 72162 | P64: 58430 | Q64: 56544 | R64: 57495 | S64: =F64 -> 56403 | T64: 53691 | U64: 51218 | W64: =SUM(K64:N64) -> 256233 | X64: =SUM(O64:R64) -> 244631
B65: Other long-term liabilities | C65: 26224 | D65: 17124 | E65: 22208 | F65: 5379 | H65: 26347 | I65: 25706 | J65: 30088 | K65: =D65 -> 17124 | L65: 17675 | M65: 17826 | N65: 18231 | O65: =I65 -> 25706 | P65: 17552 | Q65: 5965 | R65: 5676 | S65: =F65 -> 5379 | T65: 4439 | U65: 4672 | W65: =SUM(K65:N65) -> 70856 | X65: =SUM(O65:R65) -> 54899
B66: Deferred tax liabilities | C66: 109 | D66: 198 | E66: 357 | F66: 407 | H66: 109 | I66: 105 | J66: 0 | K66: =D66 -> 198 | L66: 198 | M66: 198 | N66: 198 | O66: =I66 -> 105 | P66: 357 | Q66: 357 | R66: 357 | S66: =F66 -> 407 | T66: 1883071 | U66: 5865510 | W66: =SUM(K66:N66) -> 792 | X66: =SUM(O66:R66) -> 1176
B67: Total Liabilities | C67: =SUM(C62:C66)+C60 -> 2578166 | D67: =SUM(D62:D66)+D60 -> 2793392 | E67: =SUM(E62:E66)+E60 -> 2597556 | F67: =SUM(F62:F66)+F60 -> 7613701 | H67: =SUM(H62:H66)+H60 -> 2775388 | I67: =SUM(I62:I66)+I60 -> 2755433 | J67: =SUM(J62:J66)+J60 -> 2745575 | K67: =SUM(K62:K66)+K60 -> 2793392 | L67: =SUM(L62:L66)+L60 -> 2583191 | M67: =SUM(M62:M66)+M60 -> 2543986 | N67: =SUM(N62:N66)+N60 -> 2533546 | O67: =SUM(O62:O66)+O60 -> 2797476 | ... U67: =SUM(U62:U66)+U60 -> 14402450 | W67: =SUM(W62:W66)+W60 -> 10454115 | X67: =SUM(X62:X66)+X60 -> 15537116
B69: 8.00% Series A Perpetual Strike Preferred Stock | C69: 0 | D69: 0 | E69: 0 | F69: 0 | H69: 0 | I69: 0 | J69: 0 | K69: 0 | L69: 0 | M69: 0 | N69: 0 | O69: 0 | P69: 0 | Q69: 0 | R69: 0 | S69: 0 | T69: 593624 | U69: 1040394
B70: 10.00% Series A Perpetual Strife Preferred Stock | C70: 0 | D70: 0 | E70: 0 | F70: 0 | H70: 0 | I70: 0 | J70: 0 | K70: 0 | L70: 0 | M70: 0 | N70: 0 | O70: 0 | P70: 0 | Q70: 0 | R70: 0 | S70: 0 | T70: 710873 | U70: 874041
B71: 10.00% Series A Perpetual Stride Preferred Stock | C71: 0 | D71: 0 | E71: 0 | F71: 0 | H71: 0 | I71: 0 | J71: 0 | K71: 0 | L71: 0 | M71: 0 | N71: 0 | O71: 0 | P71: 0 | Q71: 0 | R71: 0 | S71: 0 | T71: 0 | U71: 979486
B72: Preferred Stock | C72: 0 | D72: 0 | E72: 0 | F72: 0 | H72: 0 | I72: 0 | J72: 0 | K72: =D72 -> 0 | L72: 0 | M72: 0 | N72: 0 | O72: =I72 -> 0 | P72: 0 | Q72: 0 | R72: 0 | S72: =F72 -> 0 | T72: 0 | U72: 0 | W72: =SUM(K72:N72) -> 0 | X72: =SUM(O72:R72) -> 0
B73: Class A Common Stock | C73: 18 | D73: 18 | E73: 24 | F73: 226 | H73: 18 | I73: 18 | J73: 18 | K73: =D73 -> 18 | L73: 20 | M73: 21 | N73: 21 | O73: =I73 -> 18 | P73: 24 | Q73: 26 | R73: 192 | S73: =F73 -> 226 | T73: 247 | U73: 261 | W73: =SUM(K73:N73) -> 80 | X73: =SUM(O73:R73) -> 260
B74: Class B Convertible Common Stock | C74: 2 | D74: 2 | E74: 2 | F74: 20 | H74: 2 | I74: 2 | J74: 2 | K74: =D74 -> 2 | L74: 2 | M74: 2 | N74: 2 | O74: =I74 -> 2 | P74: 2 | Q74: 2 | R74: 20 | S74: =F74 -> 20 | T74: 20 | U74: 20 | W74: =SUM(K74:N74) -> 8 | X74: =SUM(O74:R74) -> 26
B75: Additional paid-in capital | C75: 1727143 | D75: 1841120 | E75: 3957728 | F75: 20411998 | H75: 1743944 | I75: 1760288 | J75: 1778660 | K75: =D75 -> 1841120 | L75: 2205518 | M75: 2559268 | N75: 2726191 | O75: =I75 -> 1760288 | P75: 4247704 | Q75: 4785336 | R75: 6060206 | S75: =F75 -> 20411998 | T75: 25881089 | U75: 31158044 | W75: =SUM(K75:N75) -> 9332097 | X75: =SUM(O75:R75) -> 16853534
B76: Treasury stock, at cost; 8,684 shares and 8,684 shares, respectively | C76: -782104 | D76: -782104 | E76: -782104 | F76: 0 | H76: -782104 | I76: -782104 | J76: -782104 | K76: =D76 -> -782104 | L76: -782104 | M76: -782104 | N76: -782104 | O76: =I76 -> -782104 | P76: -782104 | Q76: -782104 | R76: -782104 | S76: =F76 -> 0 | T76: 0 | U76: 0 | W76: =SUM(K76:N76) -> -3128416 | X76: =SUM(O76:R76) -> -3128416
B77: Accumulated other comprehensive loss | C77: -7543 | D77: -13801 | E77: -11444 | F77: -15384 | H77: -9552 | I77: -13665 | J77: -18179 | K77: =D77 -> -13801 | L77: -13063 | M77: -13150 | N77: -15355 | O77: =I77 -> -13665 | P77: -13169 | Q77: -13550 | R77: -9580 | S77: =F77 -> -15384 | T77: -11967 | U77: -5020 | W77: =SUM(K77:N77) -> -55369 | X77: =SUM(O77:R77) -> -49964
B78: (Accumulated deficit) retained earnings | C78: 41442 | D78: -1428355 | E78: -999234 | F78: -2166876 | H78: -89309 | I78: -1151607 | J78: -1178686 | K78: =D78 -> -1428355 | L78: -967162 | M78: -944919 | N78: -1088360 | O78: =I78 -> -1151607 | P78: -1052352 | Q78: -1154911 | R78: -1495085 | S78: =F78 -> -2166876 | T78: 6351847 | U78: 16323739 | W78: =SUM(K78:N78) -> -4428796 | X78: =SUM(O78:R78) -> -4853955
B79: Total stockholders' equity | C79: =SUM(C72:C78) -> 978958 | D79: =SUM(D72:D78) -> -383120 | E79: =SUM(E72:E78) -> 2164972 | F79: =SUM(F72:F78) -> 18229984 | H79: =SUM(H72:H78) -> 862999 | I79: =SUM(I72:I78) -> -187068 | J79: =SUM(J72:J78) -> -200289 | K79: =SUM(K72:K78) -> -383120 | L79: =SUM(L72:L78) -> 443211 | M79: =SUM(M72:M78) -> 819118 | N79: =SUM(N72:N78) -> 840395 | O79: =SUM(O72:O78) -> -187068 | ... S79: =SUM(S72:S78) -> 18229984 | T79: =SUM(T69:T78) -> 33525733 | U79: =SUM(U69:U78) -> 50370965 | W79: =SUM(W72:W78) -> 1719604 | X79: =SUM(X72:X78) -> 8821485
B80: Total liabilities and stockholders' equity | C80: =SUM(C79+C67) -> 3557124 | D80: =SUM(D79+D67) -> 2410272 | E80: =SUM(E79+E67) -> 4762528 | F80: =SUM(F79+F67) -> 25843685 | H80: =SUM(H79+H67) -> 3638387 | I80: =SUM(I79+I67) -> 2568365 | J80: =SUM(J79+J67) -> 2545286 | K80: =SUM(K79+K67) -> 2410272 | L80: =SUM(L79+L67) -> 3026402 | M80: =SUM(M79+M67) -> 3363104 | N80: =SUM(N79+N67) -> 3373941 | O80: =SUM(O79+O67) -> 2610408 | ... U80: =SUM(U79+U67) -> 64773415 | W80: =SUM(W79+W67) -> 12173719 | X80: =SUM(X79+X67) -> 24358601
A82: X | B82: Cash-Flows Statement
B84: Cash-Flows From Operating Activities
B85: Net income (loss) | C85: -535480 | D85: -1469797 | E85: 429121 | F85: -1166661 | H85: -130751 | I85: =-1193049-H85 -> -1062298 | J85: =-1220128-I85-H85 -> -27079 | K85: =SUM(D85-SUM(H85:J85)) -> -249669 | L85: 461193 | M85: =483436-L85 -> 22243 | N85: =339995-M85-L85 -> -143441 | O85: =SUM(E85-SUM(L85:N85)) -> 89126 | P85: -53118 | Q85: =-155677-P85 -> -102559 | R85: =-495851-Q85-P85 -> -340174 | S85: =SUM(F85-SUM(P85:R85)) -> -670810 | T85: -4217370 | U85: =5803476-T85 -> 10020846 | W85: =SUM(K85:N85) -> 90326 | X85: =SUM(O85:R85) -> -406725
B87: Adjustments to reconcile net income (loss) to net cash used in operating activities:
B88: Depreciation and amortization | C88: 11358 | D88: 10874 | E88: 14527 | F88: 17808 | H88: 2691 | I88: =4767-H88 -> 2076 | J88: =6917-I88-H88 -> 2150 | K88: =SUM(D88-SUM(H88:J88)) -> 3957 | L88: 3431 | M88: =6661-L88 -> 3230 | N88: =9405-M88-L88 -> 2744 | O88: =SUM(E88-SUM(L88:N88)) -> 5122 | P88: 3050 | Q88: =6701-P88 -> 3651 | R88: =12679-Q88-P88 -> 5978 | S88: =SUM(F88-SUM(P88:R88)) -> 5129 | T88: 6575 | U88: =15693-T88 -> 9118 | W88: =SUM(K88:N88) -> 13362 | X88: =SUM(O88:R88) -> 17801
B89: Reduction in carrying amount of right-of-use assets | C89: 8189 | D89: 8072 | E89: 8643 | F89: 8475 | H89: 1994 | I89: =3990-H89 -> 1996 | J89: =6020-I89-H89 -> 2030 | K89: =SUM(D89-SUM(H89:J89)) -> 2052 | L89: 2124 | M89: =4320-L89 -> 2196 | N89: =6438-M89-L89 -> 2118 | O89: =SUM(E89-SUM(L89:N89)) -> 2205 | P89: 2110 | Q89: =4126-P89 -> 2016 | R89: =6228-Q89-P89 -> 2102 | S89: =SUM(F89-SUM(P89:R89)) -> 2247 | T89: 2240 | U89: =4526-T89 -> 2286 | W89: =SUM(K89:N89) -> 8490 | X89: =SUM(O89:R89) -> 8433
B90: Credit losses and sales allowances | C90: 1509 | D90: 939 | E90: 1387 | F90: 649 | H90: 272 | I90: =606-H90 -> 334 | J90: =1189-I90-H90 -> 583 | K90: =SUM(D90-SUM(H90:J90)) -> -250 | L90: 21 | M90: =438-L90 -> 417 | N90: =752-M90-L90 -> 314 | O90: =SUM(E90-SUM(L90:N90)) -> 635 | P90: 24 | Q90: =-44-P90 -> -68 | R90: =262-Q90-P90 -> 306 | S90: =SUM(F90-SUM(P90:R90)) -> 387 | T90: 0 | U90: 0 | W90: =SUM(K90:N90) -> 502 | X90: =SUM(O90:R90) -> 897
B91: Deferred taxes | C91: -284221 | D91: 131493 | E91: -568949 | F91: -774586 | H91: -57445 | I91: =76109-H91 -> 133554 | J91: =90166-I91-H91 -> 14057 | K91: =SUM(D91-SUM(H91:J91)) -> 41327 | L91: -460061 | M91: =-530628-L91 -> -70567 | N91: =-425986-M91-L91 -> 104642 | O91: =SUM(E91-SUM(L91:N91)) -> -142963 | P91: -161097 | Q91: =-278067-P91 -> -116970 | R91: =-419965-Q91-P91 -> -141898 | S91: =SUM(F91-SUM(P91:R91)) -> -354621 | T91: -1728363 | U91: =2254166-T91 -> 3982529 | W91: =SUM(K91:N91) -> -384659 | X91: =SUM(O91:R91) -> -562928
B92: Release of liabilities for unrecognized tax benefits | C92: -561 | D92: -360 | E92: -506 | F92: -1265 | H92: 0 | I92: 0 | J92: 0 | K92: =SUM(D92-SUM(H92:J92)) -> -360 | L92: -102 | M92: =-102-L92 -> 0 | N92: =-162-M92-L92 -> -60 | O92: =SUM(E92-SUM(L92:N92)) -> -344 | P92: -73 | Q92: =-73-P92 -> 0 | R92: =-73-Q92-P92 -> 0 | S92: =SUM(F92-SUM(P92:R92)) -> -1192 | T92: 0 | U92: 0 | W92: =SUM(K92:N92) -> -522 | X92: =SUM(O92:R92) -> -417
B93: Share-based compensation expense | C93: 44126 | D93: 63619 | E93: 69571 | F93: 77124 | H93: 14394 | I93: =29688-H93 -> 15294 | J93: =46587-I93-H93 -> 16899 | K93: =SUM(D93-SUM(H93:J93)) -> 17032 | L93: 17555 | M93: =33049-L93 -> 15494 | N93: =49855-M93-L93 -> 16806 | O93: =SUM(E93-SUM(L93:N93)) -> 19716 | P93: 17791 | Q93: =38412-P93 -> 20621 | R93: =57789-Q93-P1065 -> 37168 | S93: =SUM(F93-SUM(P93:R93)) -> 1544 | T93: 11819 | U93: =27561-T93 -> 15742 | W93: =SUM(K93:N93) -> 66887 | X93: =SUM(O93:R93) -> 95296
B94: Unrealized loss (gain) on digital assets | C94: 0 | D94: 0 | E94: 0 | F94: 0 | H94: 0 | I94: 0 | J94: 0 | K94: 0 | L94: 0 | M94: 0 | N94: 0 | O94: 0 | P94: 0 | Q94: 0 | R94: 0 | S94: 0 | T94: 5906005 | U94: =-8141509-T94 -> -14047514
B95: Digital asset impairment losses (gains on sale), net | C95: 830621 | D95: 1286286 | E95: 115851 | F95: 1789862 | H95: 170091 | I95: =1087929-H95 -> 917838 | J95: =1088656-I95-H95 -> 727 | K95: =SUM(D95-SUM(H95:J95)) -> 197630 | L95: 18911 | M95: =43054-L95 -> 24143 | N95: =76613-M95-L95 -> 33559 | O95: =SUM(E95-SUM(L95:N95)) -> 39238 | P95: 191633 | Q95: =371723-P95 -> 180090 | R95: =783807-Q95-P95 -> 412084 | S95: =SUM(F95-SUM(P95:R95)) -> 1006055 | T95: 0 | U95: 0 | W95: =SUM(K95:N95) -> 274243 | X95: =SUM(O95:R95) -> 823045
B96: Amortization of issuance costs on long-term debt | C96: 7201 | D96: 8694 | E96: 8808 | F96: 15336 | H96: 2129 | I96: =4297-H96 -> 2168 | J96: =6490-I96-H96 -> 2193 | K96: =SUM(D96-SUM(H96:J96)) -> 2204 | L96: 2210 | M96: =4400-L96 -> 2190 | N96: =6599-M96-L96 -> 2199 | O96: =SUM(E96-SUM(L96:N96)) -> 2209 | P96: 2557 | Q96: =6399-P96 -> 3842 | R96: =10231-Q96-P96 -> 3832 | S96: =SUM(F96-SUM(P96:R96)) -> 5105 | T96: 6048 | U96: =12445-T96 -> 6397 | W96: =SUM(K96:N96) -> 8803 | X96: =SUM(O96:R96) -> 12440
B97: Loss (Gain) on debt extinguishment | C97: 0 | D97: 0 | E97: -44686 | F97: 22933 | H97: 0 | I97: 0 | J97: 0 | K97: =SUM(D97-SUM(H97:J97)) -> 0 | L97: -44686 | M97: =-44686-L97 -> 0 | N97: =-44686-M97-L97 -> 0 | O97: =SUM(E97-SUM(L97:N97)) -> 0 | P97: 0 | Q97: =0-P97 -> 0 | R97: =22933-Q97-P97 -> 22933 | S97: =SUM(F97-SUM(P97:R97)) -> 0 | T97: 0 | U97: 0 | W97: =SUM(K97:N97) -> -44686 | X97: =SUM(O97:R97) -> 22933
B99: Changes in assets and liabilities, net of effect of acquisitions:
B100: Accounts receivable | C100: 2618 | D100: -5292 | E100: 10307 | F100: 5688 | H100: 8183 | I100: =9281-H100 -> 1098 | J100: =5586-I100-H100 -> -3695 | K100: =SUM(D100-SUM(H100:J100)) -> -10878 | L100: 10241 | M100: =17737-L100 -> 7496 | N100: =6627-M100-L100 -> -11110 | O100: =SUM(E100-SUM(L100:N100)) -> 3680 | P100: 12166 | Q100: =20119-P100 -> 7953 | R100: =27374-Q100-P100 -> 7255 | S100: =SUM(F100-SUM(P100:R100)) -> -21686 | T100: 10542 | U100: =14962-T100 -> 4420 | W100: =SUM(K100:N100) -> -4251 | X100: =SUM(O100:R100) -> 31054
B101: Prepaid expenses and other current assets | C101: -25 | D101: -6342 | E101: -11358 | F101: 3804 | H101: -2838 | I101: =-7077-H101 -> -4239 | J101: =-7837-I101-H101 -> -760 | K101: =SUM(D101-SUM(H101:J101)) -> 1495 | L101: 423 | M101: =4861-L101 -> 4438 | N101: =-99-M101-L101 -> -4960 | O101: =SUM(E101-SUM(L101:N101)) -> -11259 | P101: -6260 | Q101: =7914-P101 -> 14174 | R101: =4868-Q101-P101 -> -3046 | S101: =SUM(F101-SUM(P101:R101)) -> -1064 | T101: =-7835 -> -7835 | U101: =-16029-T101 -> -8194 | W101: =SUM(K101:N101) -> 1396 | X101: =SUM(O101:R101) -> -6391
B102: Deposits and other assets | C102: -1713 | D102: -7455 | E102: -632 | F102: -10668 | H102: -5801 | I102: =-6578-H102 -> -777 | J102: =-8314-I102-H102 -> -1736 | K102: =SUM(D102-SUM(H102:J102)) -> 859 | L102: -6 | M102: =1189-L102 -> 1195 | N102: =-321-M102-L102 -> -1510 | O102: =SUM(E102-SUM(L102:N102)) -> -311 | P102: -5339 | Q102: =-8163-P102 -> -2824 | R102: =-6748-Q102-P102 -> 1415 | S102: =SUM(F102-SUM(P102:R102)) -> -3920 | T102: -1519 | U102: =-2429-T102 -> -910 | W102: =SUM(K102:N102) -> 538 | X102: =SUM(O102:R102) -> -7059
B103: Accounts payable and accrued expenses | C103: 3749 | D103: -3521 | E103: -634 | F103: 1141 | H103: -2041 | I103: =-10216-H103 -> -8175 | J103: =-8880-I103-H103 -> 1336 | K103: =SUM(D103-SUM(H103:J103)) -> 5359 | L103: 4230 | M103: =-9400-L103 -> -13630 | N103: =-8005-M103-L103 -> 1395 | O103: =SUM(E103-SUM(L103:N103)) -> 7371 | P103: -2005 | Q103: =-8164-P103 -> -6159 | R103: =-8318-Q103-P103 -> -154 | S103: =SUM(F103-SUM(P103:R103)) -> 9459 | T103: -1431 | U103: =-3250-T103 -> -1819 | W103: =SUM(K103:N103) -> -2646 | X103: =SUM(O103:R103) -> -947
B104: Accrued compensation and employee benefits | C104: 2374 | D104: -12344 | E104: -12000 | F104: -34563 | H104: -12735 | I104: =-9802-H104 -> 2933 | J104: =-13105-I104-H104 -> -3303 | K104: =SUM(D104-SUM(H104:J104)) -> 761 | L104: -16327 | M104: =-15559-L104 -> 768 | N104: =-15186-M104-L104 -> 373 | O104: =SUM(E104-SUM(L104:N104)) -> 3186 | P104: -13279 | Q104: =-18059-P104 -> -4780 | R104: =-26383-Q104-P104 -> -8324 | S104: =SUM(F104-SUM(P104:R104)) -> -8180 | T104: -30385 | U104: =-28187-T104 -> 2198 | W104: =SUM(K104:N104) -> -14425 | X104: =SUM(O104:R104) -> -23197
B105: Accrued interest | C105: 1222 | D105: 1336 | E105: -1336 | F105: 4193 | H105: 9051 | I105: =776-H105 -> -8275 | J105: =9901-I105-H105 -> 9125 | K105: =SUM(D105-SUM(H105:J105)) -> -8565 | L105: 7539 | M105: =-1336-L105 -> -8875 | N105: =7539-M105-L105 -> 8875 | O105: =SUM(E105-SUM(L105:N105)) -> -8875 | P105: 9385 | Q105: =3641-P105 -> -5744 | R105: =4444-Q105-P105 -> 803 | S105: =SUM(F105-SUM(P105:R105)) -> -251 | T105: 421 | U105: =71-T105 -> -350 | W105: =SUM(K105:N105) -> -1026 | X105: =SUM(O105:R105) -> -4431
B106: Deferred revenue and advance payments | C106: 14710 | D106: 14839 | E106: 2362 | F106: 1049 | H106: 48895 | I106: =36945-H106 -> -11950 | J106: =25401-I106-H106 -> -11544 | K106: =SUM(D106-SUM(H106:J106)) -> -10562 | L106: 33352 | M106: =26952-L106 -> -6400 | N106: =9901-M106-L106 -> -17051 | O106: =SUM(E106-SUM(L106:N106)) -> -7539 | P106: 41560 | Q106: =24994-P106 -> -16566 | R106: =3484-Q106-P106 -> -21510 | S106: =SUM(F106-SUM(P106:R106)) -> -2435 | T106: 43289 | U106: =26095-T106 -> -17194 | W106: =SUM(K106:N106) -> -661 | X106: =SUM(O106:R106) -> -4055
B107: Operating lease liabilities | C107: -10222 | D107: -9634 | E107: -10218 | F107: -10510 | H107: -2382 | I107: =-4835-H107 -> -2453 | J107: =-7390-I107-H107 -> -2555 | K107: =SUM(D107-SUM(H107:J107)) -> -2244 | L107: -2594 | M107: =-5233-L107 -> -2639 | N107: =-7954-M107-L107 -> -2721 | O107: =SUM(E107-SUM(L107:N107)) -> -2264 | P107: -2896 | Q107: =-5467-P107 -> -2571 | R107: =-7832-Q107-P107 -> -2365 | S107: =SUM(F107-SUM(P107:R107)) -> -2678 | T107: -2618 | U107: =5308-T107 -> 7926 | W107: =SUM(K107:N107) -> -10198 | X107: =SUM(O107:R107) -> -10096
B108: Other long-term liabilities | C108: -1622 | D108: -8196 | E108: 2454 | F108: -2841 | H108: -25 | I108: =32-H108 -> 57 | J108: =150-I108-H108 -> 118 | K108: =SUM(D108-SUM(H108:J108)) -> -8346 | L108: -57 | M108: =-228-L108 -> -171 | N108: =203-M108-L108 -> 431 | O108: =SUM(E108-SUM(L108:N108)) -> 2251 | P108: -7622 | Q108: =-5057-P108 -> 2565 | R108: =-4637-Q108-P108 -> 420 | S108: =SUM(F108-SUM(P108:R108)) -> 1796 | T108: 193 | U108: =415-T108 -> 222 | W108: =SUM(K108:N108) -> -8143 | X108: =SUM(O108:R108) -> -2386
B109: Net cash used in operating activities | C109: =SUM(C85:C108) -> 93833 | D109: =SUM(D85:D108) -> 3211 | E109: =SUM(E85:E108) -> 12712 | F109: =SUM(F85:F108) -> -53032 | H109: =SUM(H85:H108) -> 43682 | I109: =SUM(I85:I108) -> -20819 | J109: =SUM(J85:J108) -> -1454 | K109: =SUM(K85:K108) -> -18198 | L109: =SUM(L85:L108) -> 37397 | M109: =SUM(M85:M108) -> -18472 | N109: =SUM(N85:N108) -> -7397 | O109: =SUM(O85:O108) -> 1184 | ... U109: =SUM(U85:U108) -> -24297 | W109: =SUM(W85:W108) -> -6670 | X109: =SUM(X85:X108) -> -16733
B111: Cash flows from investing activities:
B112: Purchases of digital assets | C112: -2626529 | D112: -287921 | E112: -1902299 | F112: -22072759 | H112: -215500 | I112: =-225500-H112 -> -10000 | J112: =-231478-I112-H112 -> -5978 | K112: =SUM(D112-SUM(H112:J112)) -> -56443 | L112: -179275 | M112: =-526278-L112 -> -347003 | N112: =-687959-M112-L112 -> -161681 | O112: =SUM(E112-SUM(L112:N112)) -> -1214340 | P112: -1639309 | Q112: =-2433137-P112 -> -793828 | R112: =-4008210-Q112-P112 -> -1575073 | S112: =SUM(F112-SUM(P112:R112)) -> -18064549 | T112: -7661663 | U112: =-14430868-T112 -> -6769205 | W112: =SUM(K112:N112) -> -744402 | X112: =SUM(O112:R112) -> -5222550
B113: Advance deposits on purchases of property and equipment | C113: 0 | D113: 0 | E113: 0 | F113: -10500 | H113: 0 | I113: 0 | J113: 0 | K113: 0 | L113: 0 | M113: 0 | N113: 0 | O113: 0 | P113: 0 | Q113: 0 | R113: 0 | S113: =SUM(F113-SUM(P113:R113)) -> -10500 | T113: -6000 | U113: =-22000-T113 -> -16000
B114: Purchases of property and equipment | C114: -2706 | D114: -2486 | E114: -2938 | F114: -2978 | H114: -641 | I114: =-1519-H114 -> -878 | J114: =-1851-I114-H114 -> -332 | K114: =SUM(D114-SUM(H114:J114)) -> -635 | L114: -499 | M114: =-1138-L114 -> -639 | N114: =-2591-M114-L114 -> -1453 | O114: =SUM(E114-SUM(L114:N114)) -> -347 | P114: -1545 | Q114: =-2268-P114 -> -723 | R114: =-2694-Q114-P114 -> -426 | S114: =SUM(F114-SUM(P114:R114)) -> -284 | T114: -2737 | U114: =-4831-T114 -> -2094 | W114: =SUM(K114:N114) -> -3226 | X114: =SUM(O114:R114) -> -3041
B115: Proceeds from sale of digital assets | C115: 0 | D115: 11817 | E115: 0 | F115: 0 | H115: 0 | I115: 0 | J115: 0 | K115: =SUM(D115-SUM(H115:J115)) -> 11817 | L115: 0 | M115: 0 | N115: 0 | O115: =SUM(E115-SUM(L115:N115)) -> 0 | P115: 0 | Q115: 0 | R115: 0 | S115: =SUM(F115-SUM(P115:R115)) -> 0 | T115: 0 | U115: 0 | W115: =SUM(K115:N115) -> 11817 | X115: =SUM(O115:R115) -> 0
B116: Net cash used in investing activities | C116: =SUM(C112:C115) -> -2629235 | D116: =SUM(D112:D115) -> -278590 | E116: =SUM(E112:E115) -> -1905237 | F116: =SUM(F112:F115) -> -22086237 | H116: =SUM(H112:H115) -> -216141 | I116: =SUM(I112:I115) -> -10878 | J116: =SUM(J112:J115) -> -6310 | K116: =SUM(K112:K115) -> -45261 | L116: =SUM(L112:L115) -> -179774 | M116: =SUM(M112:M115) -> -347642 | N116: =SUM(N112:N115) -> -163134 | O116: =SUM(O112:O115) -> -1214687 | ... U116: =SUM(U112:U115) -> -6787299 | W116: =SUM(W112:W115) -> -735811 | X116: =SUM(X112:X115) -> -5225591
B118: Cash flows from financing activities:
B119: Debt Financing - Convertible Notes
...

Sheet FCF Analysis
B2: Microstrategy, Inc. (NASDAQ: MSTR) | C2: FYE | D2: FYE | H2: Quarterly | P2: Quarterly | Q2: Quarterly | W2: LTM | AA2: LTM | AI2: Variance
B3: FCF Analysis | C3: 2021 | D3: 2022 | E3: 2023 | F3: 2024 | H3: 1Q22 | I3: 2Q22 | J3: 3Q22 | K3: 4Q22 | L3: 1Q23 | M3: 2Q23 | N3: 3Q23 | O3: 4Q23 | P3: 1Q24 | Q3: 2Q24 | R3: 3Q24 | S3: 4Q24 | T3: 1Q25 | U3: 2Q25 | W3: =K3 -> 4Q22 | X3: =L3 -> 1Q23 | Y3: =M3 -> 2Q23 | Z3: =N3 -> 3Q23 | AA3: =O3 -> 4Q23 | AB3: =P3 -> 1Q24 | AC3: =Q3 -> 2Q24 | AD3: =R3 -> 3Q24 | ... AG3: =U3 -> 2Q25
B4: ($ In Thousands) | C4: 44561 | D4: 44926 | E4: 45291 | F4: 45657 | H4: 44651 | I4: 44742 | J4: 44834 | K4: 44926 | L4: 45016 | M4: 45107 | N4: 45199 | O4: 45291 | P4: 45382 | Q4: 45473 | R4: 45565 | S4: 45657 | T4: 45747 | U4: 45838 | W4: =K4 -> 44926 | X4: =L4 -> 45016 | Y4: =M4 -> 45107 | Z4: =N4 -> 45199 | AA4: =O4 -> 45291 | AB4: =P4 -> 45382 | AC4: =Q4 -> 45473 | AD4: =R4 -> 45565 | ... AG4: =U4 -> 45838
B6: Product licenses | C6: ='3-Statement Model'!C8 -> 101804 | D6: ='3-Statement Model'!D8 -> 86498 | E6: ='3-Statement Model'!E8 -> 75351 | F6: ='3-Statement Model'!F8 -> 48567 | H6: ='3-Statement Model'!H8 -> 16513 | I6: ='3-Statement Model'!I8 -> 20129 | J6: ='3-Statement Model'!J8 -> 22286 | K6: ='3-Statement Model'!K8 -> 27570 | L6: ='3-Statement Model'!L8 -> 17412 | M6: ='3-Statement Model'!M8 -> 15522 | N6: ='3-Statement Model'!N8 -> 24045 | O6: ='3-Statement Model'!O8 -> 18372 | ... U6: ='3-Statement Model'!U8 -> 7177 | W6: =SUM(H6:K6) -> 86498 | X6: =SUM(I6:L6) -> 87397 | Y6: =SUM(J6:M6) -> 82790 | Z6: =SUM(K6:N6) -> 84549 | AA6: =SUM(L6:O6) -> 75351 | AB6: =SUM(M6:P6) -> 70877 | AC6: =SUM(N6:Q6) -> 64641 | AD6: =SUM(O6:R6) -> 51683 | ... AG6: =SUM(R6:U6) -> 40790 | AI6: =SUM(AG6/AC6)-1 -> -0.36897635
B7: Subscription services | C7: ='3-Statement Model'!C9 -> 43069 | D7: ='3-Statement Model'!D9 -> 60746 | E7: ='3-Statement Model'!E9 -> 81179 | F7: ='3-Statement Model'!F9 -> 106776 | H7: ='3-Statement Model'!H9 -> 12845 | I7: ='3-Statement Model'!I9 -> 14017 | J7: ='3-Statement Model'!J9 -> 16414 | K7: ='3-Statement Model'!K9 -> 17470 | L7: ='3-Statement Model'!L9 -> 18810 | M7: ='3-Statement Model'!M9 -> 19878 | N7: ='3-Statement Model'!N9 -> 20974 | O7: ='3-Statement Model'!O9 -> 21517 | ... U7: ='3-Statement Model'!U9 -> 40824 | W7: =SUM(H7:K7) -> 60746 | X7: =SUM(I7:L7) -> 66711 | Y7: =SUM(J7:M7) -> 72572 | Z7: =SUM(K7:N7) -> 77132 | AA7: =SUM(L7:O7) -> 81179 | AB7: =SUM(M7:P7) -> 85335 | AC7: =SUM(N7:Q7) -> 89537 | AD7: =SUM(O7:R7) -> 96363 | ... AG7: =SUM(R7:U7) -> 137657 | AI7: =SUM(AG7/AC7)-1 -> 0.53743145
B8: Product support | C8: ='3-Statement Model'!C11 -> 281209 | D8: ='3-Statement Model'!D11 -> 266521 | E8: ='3-Statement Model'!E11 -> 263888 | F8: ='3-Statement Model'!F11 -> 243805 | H8: ='3-Statement Model'!H11 -> 67151 | I8: ='3-Statement Model'!I11 -> 66521 | J8: ='3-Statement Model'!J11 -> 66010 | K8: ='3-Statement Model'!K11 -> 66839 | L8: ='3-Statement Model'!L11 -> 65481 | M8: ='3-Statement Model'!M11 -> 66081 | N8: ='3-Statement Model'!N11 -> 66860 | O8: ='3-Statement Model'!O11 -> 65466 | ... U8: ='3-Statement Model'!U11 -> 52081 | W8: =SUM(H8:K8) -> 266521 | X8: =SUM(I8:L8) -> 264851 | Y8: =SUM(J8:M8) -> 264411 | Z8: =SUM(K8:N8) -> 265261 | AA8: =SUM(L8:O8) -> 263888 | AB8: =SUM(M8:P8) -> 261092 | AC8: =SUM(N8:Q8) -> 256751 | AD8: =SUM(O8:R8) -> 250906 | ... AG8: =SUM(R8:U8) -> 223990 | AI8: =SUM(AG8/AC8)-1 -> -0.12759833
B9: Other services | C9: ='3-Statement Model'!C12 -> 84680 | D9: ='3-Statement Model'!D12 -> 85499 | E9: ='3-Statement Model'!E12 -> 75843 | F9: ='3-Statement Model'!F12 -> 64308 | H9: ='3-Statement Model'!H12 -> 22768 | I9: ='3-Statement Model'!I12 -> 21406 | J9: ='3-Statement Model'!J12 -> 20650 | K9: ='3-Statement Model'!K12 -> 20675 | L9: ='3-Statement Model'!L12 -> 20212 | M9: ='3-Statement Model'!M12 -> 18919 | N9: ='3-Statement Model'!N12 -> 17583 | O9: ='3-Statement Model'!O12 -> 19129 | ... U9: ='3-Statement Model'!U12 -> 14406 | W9: =SUM(H9:K9) -> 85499 | X9: =SUM(I9:L9) -> 82943 | Y9: =SUM(J9:M9) -> 80456 | Z9: =SUM(K9:N9) -> 77389 | AA9: =SUM(L9:O9) -> 75843 | AB9: =SUM(M9:P9) -> 72288 | AC9: =SUM(N9:Q9) -> 69705 | AD9: =SUM(O9:R9) -> 68291 | ... AG9: =SUM(R9:U9) -> 59885 | AI9: =SUM(AG9/AC9)-1 -> -0.14087942
B10: Total Revenue | C10: =SUM(C6:C9) -> 510762 | D10: =SUM(D6:D9) -> 499264 | E10: =SUM(E6:E9) -> 496261 | F10: =SUM(F6:F9) -> 463456 | H10: =SUM(H6:H9) -> 119277 | I10: =SUM(I6:I9) -> 122073 | J10: =SUM(J6:J9) -> 125360 | K10: =SUM(K6:K9) -> 132554 | L10: =SUM(L6:L9) -> 121915 | M10: =SUM(M6:M9) -> 120400 | N10: =SUM(N6:N9) -> 129462 | O10: =SUM(O6:O9) -> 124484 | ... U10: =SUM(U6:U9) -> 114488 | W10: =SUM(W6:W9) -> 499264 | X10: =SUM(X6:X9) -> 501902 | Y10: =SUM(Y6:Y9) -> 500229 | Z10: =SUM(Z6:Z9) -> 504331 | AA10: =SUM(AA6:AA9) -> 496261 | AB10: =SUM(AB6:AB9) -> 489592 | AC10: =SUM(AC6:AC9) -> 480634 | AD10: =SUM(AD6:AD9) -> 467243 | ... AG10: =SUM(AG6:AG9) -> 462322 | AI10: =SUM(AG10/AC10)-1 -> -0.038099677
B11: Y/Y Growth (%) | D11: =SUM(D10/C10)-1 -> -0.022511463 | E11: =SUM(E10/D10)-1 -> -0.0060148539 | F11: =SUM(F10/E10)-1 -> -0.066104328 | L11: =SUM(L10/H10)-1 -> 0.022116586 | M11: =SUM(M10/I10)-1 -> -0.013704914 | N11: =SUM(N10/J10)-1 -> 0.032721761 | O11: =SUM(O10/K10)-1 -> -0.060880849 | P11: =SUM(P10/L10)-1 -> -0.054702047 | Q11: =SUM(Q10/M10)-1 -> -0.074401993 | R11: =SUM(R10/N10)-1 -> -0.10343576 | S11: =SUM(S10/O10)-1 -> -0.03042158 | ... U11: =SUM(U10/Q10)-1 -> 0.027332604 | AA11: =SUM(AA10/W10)-1 -> -0.0060148539 | AB11: =SUM(AB10/X10)-1 -> -0.0245267 | AC11: =SUM(AC10/Y10)-1 -> -0.039172059 | AD11: =SUM(AD10/Z10)-1 -> -0.073539005 | AE11: =SUM(AE10/AA10)-1 -> -0.066104328 | AF11: =SUM(AF10/AB10)-1 -> -0.061920946 | AG11: =SUM(AG10/AC10)-1 -> -0.038099677 | AI11: =SUM(AG11-AC11)*10000 -> 10.723825
B12: Q/Q Growth (%) | C12: N/A | D12: N/A | E12: N/A | F12: N/A | I12: =SUM(I10/H10)-1 -> 0.023441233 | J12: =SUM(J10/I10)-1 -> 0.026926511 | K12: =SUM(K10/J10)-1 -> 0.057386726 | L12: =SUM(L10/K10)-1 -> -0.080261629 | M12: =SUM(M10/L10)-1 -> -0.012426691 | N12: =SUM(N10/M10)-1 -> 0.075265781 | O12: =SUM(O10/N10)-1 -> -0.038451437 | P12: =SUM(P10/O10)-1 -> -0.07421034 | ... U12: =SUM(U10/T10)-1 -> 0.030810509 | W12: N/A | X12: N/A | Y12: N/A | Z12: N/A | AA12: N/A | AB12: N/A | AC12: N/A | AD12: N/A | AE12: N/A | AF12: N/A | AG12: N/A
B14: (-) Product licenses | C14: ='3-Statement Model'!C15 -> -1721 | D14: ='3-Statement Model'!D15 -> -1672 | E14: ='3-Statement Model'!E15 -> -1929 | F14: ='3-Statement Model'!F15 -> -3060 | H14: ='3-Statement Model'!H15 -> -477 | I14: ='3-Statement Model'!I15 -> -431 | J14: ='3-Statement Model'!J15 -> -406 | K14: ='3-Statement Model'!K15 -> -358 | L14: ='3-Statement Model'!L15 -> -534 | M14: ='3-Statement Model'!M15 -> -444 | N14: ='3-Statement Model'!N15 -> -342 | O14: ='3-Statement Model'!O15 -> -609 | ... U14: ='3-Statement Model'!U15 -> -1169 | W14: =SUM(H14:K14) -> -1672 | X14: =SUM(I14:L14) -> -1729 | Y14: =SUM(J14:M14) -> -1742 | Z14: =SUM(K14:N14) -> -1678 | AA14: =SUM(L14:O14) -> -1929 | AB14: =SUM(M14:P14) -> -1962 | AC14: =SUM(N14:Q14) -> -2312 | AD14: =SUM(O14:R14) -> -2739 | ... AG14: =SUM(R14:U14) -> -3832 | AI14: =SUM(AG14/AC14)-1 -> 0.65743945
B15: (-) Subscription services | C15: ='3-Statement Model'!C16 -> -16901 | D15: ='3-Statement Model'!D16 -> -24770 | E15: ='3-Statement Model'!E16 -> -31776 | F15: ='3-Statement Model'!F16 -> -42440 | H15: ='3-Statement Model'!H16 -> -5410 | I15: ='3-Statement Model'!I16 -> -5498 | J15: ='3-Statement Model'!J16 -> -6395 | K15: ='3-Statement Model'!K16 -> -7467 | L15: ='3-Statement Model'!L16 -> -7856 | M15: ='3-Statement Model'!M16 -> -7216 | N15: ='3-Statement Model'!N16 -> -8028 | O15: ='3-Statement Model'!O16 -> -8676 | ... U15: ='3-Statement Model'!U16 -> -15906 | W15: =SUM(H15:K15) -> -24770 | X15: =SUM(I15:L15) -> -27216 | Y15: =SUM(J15:M15) -> -28934 | Z15: =SUM(K15:N15) -> -30567 | AA15: =SUM(L15:O15) -> -31776 | AB15: =SUM(M15:P15) -> -32524 | AC15: =SUM(N15:Q15) -> -34868 | AD15: =SUM(O15:R15) -> -38294 | ... AG15: =SUM(R15:U15) -> -54611 | AI15: =SUM(AG15/AC15)-1 -> 0.56622118
B16: (-) Product support | C16: ='3-Statement Model'!C18 -> -19254 | D16: ='3-Statement Model'!D18 -> -21264 | E16: ='3-Statement Model'!E18 -> -22434 | F16: ='3-Statement Model'!F18 -> -33289 | H16: ='3-Statement Model'!H18 -> -5191 | I16: ='3-Statement Model'!I18 -> -5127 | J16: ='3-Statement Model'!J18 -> -5224 | K16: ='3-Statement Model'!K18 -> -5722 | L16: ='3-Statement Model'!L18 -> -5768 | M16: ='3-Statement Model'!M18 -> -5816 | N16: ='3-Statement Model'!N18 -> -5531 | O16: ='3-Statement Model'!O18 -> -5319 | ... U16: ='3-Statement Model'!U18 -> -7291 | W16: =SUM(H16:K16) -> -21264 | X16: =SUM(I16:L16) -> -21841 | Y16: =SUM(J16:M16) -> -22530 | Z16: =SUM(K16:N16) -> -22837 | AA16: =SUM(L16:O16) -> -22434 | AB16: =SUM(M16:P16) -> -25213 | AC16: =SUM(N16:Q16) -> -27590 | AD16: =SUM(O16:R16) -> -30631 | ... AG16: =SUM(R16:U16) -> -31194 | AI16: =SUM(AG16/AC16)-1 -> 0.13062704
B17: (-) Other services | C17: ='3-Statement Model'!C19 -> -54033 | D17: ='3-Statement Model'!D19 -> -55283 | E17: ='3-Statement Model'!E19 -> -53805 | F17: ='3-Statement Model'!F19 -> -50679 | H17: ='3-Statement Model'!H19 -> -14599 | I17: ='3-Statement Model'!I19 -> -14148 | J17: ='3-Statement Model'!J19 -> -13360 | K17: ='3-Statement Model'!K19 -> -13176 | L17: ='3-Statement Model'!L19 -> -13783 | M17: ='3-Statement Model'!M19 -> -13645 | N17: ='3-Statement Model'!N19 -> -12760 | O17: ='3-Statement Model'!O19 -> -13617 | ... U17: ='3-Statement Model'!U19 -> -11384 | W17: =SUM(H17:K17) -> -55283 | X17: =SUM(I17:L17) -> -54467 | Y17: =SUM(J17:M17) -> -53964 | Z17: =SUM(K17:N17) -> -53364 | AA17: =SUM(L17:O17) -> -53805 | AB17: =SUM(M17:P17) -> -52319 | AC17: =SUM(N17:Q17) -> -51062 | AD17: =SUM(O17:R17) -> -51856 | ... AG17: =SUM(R17:U17) -> -48602 | AI17: =SUM(AG17/AC17)-1 -> -0.048176726
B18: (-) Cost of Sales | C18: =SUM(C14:C17) -> -91909 | D18: =SUM(D14:D17) -> -102989 | E18: =SUM(E14:E17) -> -109944 | F18: =SUM(F14:F17) -> -129468 | H18: =SUM(H14:H17) -> -25677 | I18: =SUM(I14:I17) -> -25204 | J18: =SUM(J14:J17) -> -25385 | K18: =SUM(K14:K17) -> -26723 | L18: =SUM(L14:L17) -> -27941 | M18: =SUM(M14:M17) -> -27121 | N18: =SUM(N14:N17) -> -26661 | O18: =SUM(O14:O17) -> -28221 | ... U18: =SUM(U14:U17) -> -35750 | W18: =SUM(H18:K18) -> -102989 | X18: =SUM(I18:L18) -> -105253 | Y18: =SUM(J18:M18) -> -107170 | Z18: =SUM(K18:N18) -> -108446 | AA18: =SUM(L18:O18) -> -109944 | AB18: =SUM(M18:P18) -> -112018 | AC18: =SUM(N18:Q18) -> -115832 | AD18: =SUM(O18:R18) -> -123520 | ... AG18: =SUM(R18:U18) -> -138239 | AI18: =SUM(AG18/AC18)-1 -> 0.19344395
B19: Gross Profit | C19: =+C10+C18 -> 418853 | D19: =+D10+D18 -> 396275 | E19: =+E10+E18 -> 386317 | F19: =+F10+F18 -> 333988 | H19: =+H10+H18 -> 93600 | I19: =+I10+I18 -> 96869 | J19: =+J10+J18 -> 99975 | K19: =+K10+K18 -> 105831 | L19: =+L10+L18 -> 93974 | M19: =+M10+M18 -> 93279 | N19: =+N10+N18 -> 102801 | O19: =+O10+O18 -> 96263 | ... U19: =+U10+U18 -> 78738 | W19: =+W10+W18 -> 396275 | X19: =+X10+X18 -> 396649 | Y19: =+Y10+Y18 -> 393059 | Z19: =+Z10+Z18 -> 395885 | AA19: =+AA10+AA18 -> 386317 | AB19: =+AB10+AB18 -> 377574 | AC19: =+AC10+AC18 -> 364802 | AD19: =+AD10+AD18 -> 343723 | ... AG19: =+AG10+AG18 -> 324083 | AI19: =SUM(AG19/AC19)-1 -> -0.11161945
B20: Gross Margin (%) | C20: =C19/C10 -> 0.82005513 | D20: =D19/D10 -> 0.79371835 | E20: =E19/E10 -> 0.77845529 | F20: =F19/F10 -> 0.72064662 | H20: =H19/H10 -> 0.78472799 | I20: =I19/I10 -> 0.79353338 | J20: =J19/J10 -> 0.79750319 | K20: =K19/K10 -> 0.79839914 | L20: =L19/L10 -> 0.77081573 | M20: =M19/M10 -> 0.77474252 | N20: =N19/N10 -> 0.79406312 | O20: =O19/O10 -> 0.77329617 | ... U20: =U19/U10 -> 0.6877402 | W20: =W19/W10 -> 0.79371835 | X20: =X19/X10 -> 0.79029173 | Y20: =Y19/Y10 -> 0.78575812 | Z20: =Z19/Z10 -> 0.78497058 | AA20: =AA19/AA10 -> 0.77845529 | AB20: =AB19/AB10 -> 0.77120133 | AC20: =AC19/AC10 -> 0.75900165 | AD20: =AD19/AD10 -> 0.73564077 | ... AG20: =AG19/AG10 -> 0.70098979 | AI20: =SUM(AG20-AC20)*10000 -> -580.11866
B22: (-) Sales and Marketing | C22: ='3-Statement Model'!C23 -> -160141 | D22: ='3-Statement Model'!D23 -> -146882 | E22: ='3-Statement Model'!E23 -> -149671 | F22: ='3-Statement Model'!F23 -> -138081 | G22: ='3-Statement Model'!G23 -> 0 | H22: ='3-Statement Model'!H23 -> -33240 | I22: ='3-Statement Model'!I23 -> -36862 | J22: ='3-Statement Model'!J23 -> -35409 | ... U22: ='3-Statement Model'!U23 -> -33691 | W22: =SUM(H22:K22) -> -146882 | X22: =SUM(I22:L22) -> -149748 | Y22: =SUM(J22:M22) -> -150546 | Z22: =SUM(K22:N22) -> -150743 | AA22: =SUM(L22:O22) -> -149671 | AB22: =SUM(M22:P22) -> -147016 | AC22: =SUM(N22:Q22) -> -143607 | AD22: =SUM(O22:R22) -> -143415 | ... AG22: =SUM(R22:U22) -> -131602 | AI22: =SUM(AG22/AC22)-1 -> -0.083596204
B23: (-) Research and Development | C23: ='3-Statement Model'!C24 -> -117117 | D23: ='3-Statement Model'!D24 -> -127428 | E23: ='3-Statement Model'!E24 -> -120530 | F23: ='3-Statement Model'!F24 -> -118486 | G23: ='3-Statement Model'!G24 -> 0 | H23: ='3-Statement Model'!H24 -> -33523 | I23: ='3-Statement Model'!I24 -> -31790 | J23: ='3-Statement Model'!J24 -> -30498 | ... U23: ='3-Statement Model'!U24 -> -24071 | W23: =SUM(H23:K23) -> -127428 | X23: =SUM(I23:L23) -> -125263 | Y23: =SUM(J23:M23) -> -122827 | Z23: =SUM(K23:N23) -> -121989 | AA23: =SUM(L23:O23) -> -120530 | AB23: =SUM(M23:P23) -> -118355 | AC23: =SUM(N23:Q23) -> -119312 | AD23: =SUM(O23:R23) -> -122953 | ... AG23: =SUM(R23:U23) -> -107486 | AI23: =SUM(AG23/AC23)-1 -> -0.099118278
B24: (-) General and Administrative | C24: ='3-Statement Model'!C25 -> -95501 | D24: ='3-Statement Model'!D25 -> -111421 | E24: ='3-Statement Model'!E25 -> -115312 | F24: ='3-Statement Model'!F25 -> -140537 | G24: ='3-Statement Model'!G25 -> 0 | H24: ='3-Statement Model'!H25 -> -26706 | I24: ='3-Statement Model'!I25 -> -28502 | J24: ='3-Statement Model'!J25 -> -27283 | ... U24: ='3-Statement Model'!U25 -> -36500 | W24: =SUM(H24:K24) -> -111421 | X24: =SUM(I24:L24) -> -112621 | Y24: =SUM(J24:M24) -> -112949 | Z24: =SUM(K24:N24) -> -114889 | AA24: =SUM(L24:O24) -> -115312 | AB24: =SUM(M24:P24) -> -122072 | AC24: =SUM(N24:Q24) -> -129371 | AD24: =SUM(O24:R24) -> -133653 | ... AG24: =SUM(R24:U24) -> -146789 | AI24: =SUM(AG24/AC24)-1 -> 0.13463605
B25: (-) Unrealized gain on digital assets | C25: ='3-Statement Model'!C26 -> 0 | D25: ='3-Statement Model'!D26 -> 0 | E25: ='3-Statement Model'!E26 -> 0 | F25: ='3-Statement Model'!F26 -> 0 | G25: ='3-Statement Model'!G26 -> 0 | H25: ='3-Statement Model'!H26 -> 0 | I25: ='3-Statement Model'!I26 -> 0 | J25: ='3-Statement Model'!J26 -> 0 | ... U25: ='3-Statement Model'!U26 -> 14047514 | AC25: =SUM(N25:Q25) -> 0 | AD25: =SUM(O25:R25) -> 0 | AE25: =SUM(P25:S25) -> 0 | AF25: =SUM(Q25:T25) -> -5906005 | AG25: =SUM(R25:U25) -> 8141509 | AI25: =SUM(AG25/AC25)-1 -> #DIV/0!
B26: (-) Digital asset impairment gains (losses on sale), net | C26: ='3-Statement Model'!C27 -> -830621 | D26: ='3-Statement Model'!D27 -> -1286286 | E26: ='3-Statement Model'!E27 -> -115851 | F26: ='3-Statement Model'!F27 -> -1789862 | G26: ='3-Statement Model'!G27 -> 0 | H26: ='3-Statement Model'!H27 -> -170091 | I26: ='3-Statement Model'!I27 -> -917838 | J26: ='3-Statement Model'!J27 -> -727 | ... U26: ='3-Statement Model'!U27 -> 0 | W26: =SUM(H26:K26) -> -1286286 | X26: =SUM(I26:L26) -> -1135106 | Y26: =SUM(J26:M26) -> -241411 | Z26: =SUM(K26:N26) -> -274243 | AA26: =SUM(L26:O26) -> -115851 | AB26: =SUM(M26:P26) -> -288573 | AC26: =SUM(N26:Q26) -> -444520 | AD26: =SUM(O26:R26) -> -823045 | ... AG26: =SUM(R26:U26) -> -1418139 | AI26: =SUM(AG26/AC26)-1 -> 2.1902704
B27: Earning before Interest & Taxes (EBIT) | C27: =SUM(C19+SUM(C22:C26)) -> -784527 | D27: =SUM(D19+SUM(D22:D26)) -> -1275742 | E27: =SUM(E19+SUM(E22:E26)) -> -115047 | F27: =SUM(F19+SUM(F22:F26)) -> -1852978 | H27: =SUM(H19+SUM(H22:H26)) -> -169960 | I27: =SUM(I19+SUM(I22:I26)) -> -918123 | J27: =SUM(J19+SUM(J22:J26)) -> 6058 | K27: =SUM(K19+SUM(K22:K26)) -> -193717 | L27: =SUM(L19+SUM(L22:L26)) -> -20307 | M27: =SUM(M19+SUM(M22:M26)) -> -26708 | N27: =SUM(N19+SUM(N22:N26)) -> -25247 | O27: =SUM(O19+SUM(O22:O26)) -> -42785 | ... U27: =SUM(U19+SUM(U22:U26)) -> 14031990 | W27: =SUM(W19+SUM(W22:W26)) -> -1275742 | X27: =SUM(X19+SUM(X22:X26)) -> -1126089 | Y27: =SUM(Y19+SUM(Y22:Y26)) -> -234674 | Z27: =SUM(Z19+SUM(Z22:Z26)) -> -265979 | AA27: =SUM(AA19+SUM(AA22:AA26)) -> -115047 | AB27: =SUM(AB19+SUM(AB22:AB26)) -> -298442 | AC27: =SUM(AC19+SUM(AC22:AC26)) -> -472008 | AD27: =SUM(AD19+SUM(AD22:AD26)) -> -879343 | ... AG27: =SUM(AG19+SUM(AG22:AG26)) -> 6661576 | AI27: =SUM(AG27/AC27)-1 -> -15.113269
B28: Operating Margin (%) | C28: =C27/C10 -> -1.5359933 | D28: =D27/D10 -> -2.5552453 | E28: =E27/E10 -> -0.23182761 | F28: =F27/F10 -> -3.9981746 | H28: =H27/H10 -> -1.4249185 | I28: =I27/I10 -> -7.521098 | J28: =J27/J10 -> 0.048324825 | K28: =K27/K10 -> -1.4614195 | L28: =L27/L10 -> -0.16656687 | M28: =M27/M10 -> -0.22182724 | N28: =N27/N10 -> -0.19501475 | O28: =O27/O10 -> -0.34369879 | ... U28: =U27/U10 -> 122.56298 | W28: =W27/W10 -> -2.5552453 | X28: =X27/X10 -> -2.2436432 | Y28: =Y27/Y10 -> -0.46913314 | Z28: =Z27/Z10 -> -0.52738975 | AA28: =AA27/AA10 -> -0.23182761 | AB28: =AB27/AB10 -> -0.60957287 | AC28: =AC27/AC10 -> -0.98205287 | AD28: =AD27/AD10 -> -1.8819822 | ... AG28: =AG27/AG10 -> 14.408953 | AI28: =SUM(AG28-AC28)*10000 -> 153910.06
B30: (+) Depreciation and Amortization | C30: ='3-Statement Model'!C88 -> 11358 | D30: ='3-Statement Model'!D88 -> 10874 | E30: ='3-Statement Model'!E88 -> 14527 | F30: ='3-Statement Model'!F88 -> 17808 | H30: ='3-Statement Model'!H88 -> 2691 | I30: ='3-Statement Model'!I88 -> 2076 | J30: ='3-Statement Model'!J88 -> 2150 | K30: ='3-Statement Model'!K88 -> 3957 | L30: ='3-Statement Model'!L88 -> 3431 | M30: ='3-Statement Model'!M88 -> 3230 | N30: ='3-Statement Model'!N88 -> 2744 | O30: ='3-Statement Model'!O88 -> 5122 | ... U30: ='3-Statement Model'!U88 -> 9118 | W30: =SUM(H30:K30) -> 10874 | X30: =SUM(I30:L30) -> 11614 | Y30: =SUM(J30:M30) -> 12768 | Z30: =SUM(K30:N30) -> 13362 | AA30: =SUM(L30:O30) -> 14527 | AB30: =SUM(M30:P30) -> 14146 | AC30: =SUM(N30:Q30) -> 14567 | AD30: =SUM(O30:R30) -> 17801 | ... AG30: =SUM(R30:U30) -> 26800 | AI30: =SUM(AG30/AC30)-1 -> 0.83977483
B31: EBITDA | C31: =SUM(C27+C30) -> -773169 | D31: =SUM(D27+D30) -> -1264868 | E31: =SUM(E27+E30) -> -100520 | F31: =SUM(F27+F30) -> -1835170 | H31: =SUM(H27+H30) -> -167269 | I31: =SUM(I27+I30) -> -916047 | J31: =SUM(J27+J30) -> 8208 | K31: =SUM(K27+K30) -> -189760 | L31: =SUM(L27+L30) -> -16876 | M31: =SUM(M27+M30) -> -23478 | N31: =SUM(N27+N30) -> -22503 | O31: =SUM(O27+O30) -> -37663 | ... U31: =SUM(U27+U30) -> 14041108 | W31: =SUM(W27+W30) -> -1264868 | X31: =SUM(X27+X30) -> -1114475 | Y31: =SUM(Y27+Y30) -> -221906 | Z31: =SUM(Z27+Z30) -> -252617 | AA31: =SUM(AA27+AA30) -> -100520 | AB31: =SUM(AB27+AB30) -> -284296 | AC31: =SUM(AC27+AC30) -> -457441 | AD31: =SUM(AD27+AD30) -> -861542 | ... AG31: =SUM(AG27+AG30) -> 6688376 | AI31: =SUM(AG31/AC31)-1 -> -15.621287
B32: EBITDA Margin (%) | C32: =C31/C10 -> -1.5137559 | D32: =D31/D10 -> -2.5334653 | E32: =E31/E10 -> -0.2025547 | F32: =F31/F10 -> -3.9597502 | H32: =H31/H10 -> -1.4023575 | I32: =I31/I10 -> -7.5040918 | J32: =J31/J10 -> 0.065475431 | K32: =K31/K10 -> -1.4315675 | L32: =L31/L10 -> -0.13842431 | M32: =M31/M10 -> -0.195 | N32: =N31/N10 -> -0.17381934 | O32: =O31/O10 -> -0.30255294 | ... U32: =U31/U10 -> 122.64262 | W32: =W31/W10 -> -2.5334653 | X32: =X31/X10 -> -2.2205032 | Y32: =Y31/Y10 -> -0.44360883 | Z32: =Z31/Z10 -> -0.50089525 | AA32: =AA31/AA10 -> -0.2025547 | AB32: =AB31/AB10 -> -0.58067942 | AC32: =AC31/AC10 -> -0.95174499 | AD32: =AD31/AD10 -> -1.8438842 | ... AG32: =AG31/AG10 -> 14.466921 | AI32: =SUM(AG32-AC32)*10000 -> 154186.66
B34: (+) Share-based Compensation | C34: ='3-Statement Model'!C96 -> 7201 | D34: ='3-Statement Model'!D96 -> 8694 | E34: ='3-Statement Model'!E96 -> 8808 | F34: ='3-Statement Model'!F96 -> 15336 | H34: ='3-Statement Model'!H96 -> 2129 | I34: ='3-Statement Model'!I96 -> 2168 | J34: ='3-Statement Model'!J96 -> 2193 | K34: ='3-Statement Model'!K96 -> 2204 | L34: ='3-Statement Model'!L96 -> 2210 | M34: ='3-Statement Model'!M96 -> 2190 | N34: ='3-Statement Model'!N96 -> 2199 | O34: ='3-Statement Model'!O96 -> 2209 | ... U34: ='3-Statement Model'!U96 -> 6397 | W34: =SUM(H34:K34) -> 8694 | X34: =SUM(I34:L34) -> 8775 | Y34: =SUM(J34:M34) -> 8797 | Z34: =SUM(K34:N34) -> 8803 | AA34: =SUM(L34:O34) -> 8808 | AB34: =SUM(M34:P34) -> 9155 | AC34: =SUM(N34:Q34) -> 10807 | AD34: =SUM(O34:R34) -> 12440 | ... AG34: =SUM(R34:U34) -> 21382 | AI34: =SUM(AG34/AC34)-1 -> 0.97853243
B35: (+/-) Digital asset impairment Losses (Gains), net | C35: =-C26 -> 830621 | D35: =-D26 -> 1286286 | E35: =-E26 -> 115851 | F35: =-F26 -> 1789862 | H35: =-H26 -> 170091 | I35: =-I26 -> 917838 | J35: =-J26 -> 727 | K35: =-K26 -> 197630 | L35: =-L26 -> 18911 | M35: =-M26 -> 24143 | N35: =-N26 -> 33559 | O35: =-O26 -> 39238 | ... U35: =-U26 -> 0 | W35: =SUM(H35:K35) -> 1286286 | X35: =SUM(I35:L35) -> 1135106 | Y35: =SUM(J35:M35) -> 241411 | Z35: =SUM(K35:N35) -> 274243 | AA35: =SUM(L35:O35) -> 115851 | AB35: =SUM(M35:P35) -> 288573 | AC35: =SUM(N35:Q35) -> 444520 | AD35: =SUM(O35:R35) -> 823045 | ... AG35: =SUM(R35:U35) -> 1418139 | AI35: =SUM(AG35/AC35)-1 -> 2.1902704
B36: (+/-) Unrealized Loss (Gain) on digital assets | C36: =-C25 -> 0 | D36: =-D25 -> 0 | E36: =-E25 -> 0 | F36: =-F25 -> 0 | G36: =-G25 -> 0 | H36: =-H25 -> 0 | I36: =-I25 -> 0 | J36: =-J25 -> 0 | ... U36: =-U25 -> -14047514 | AC36: =SUM(N36:Q36) -> 0 | AD36: =SUM(O36:R36) -> 0 | AE36: =SUM(P36:S36) -> 0 | AF36: =SUM(Q36:T36) -> 5906005 | AG36: =SUM(R36:U36) -> -8141509 | AI36: =SUM(AG36/AC36)-1 -> #DIV/0!
B37: Adj. EBITDA | C37: =+SUM(C31+SUM(C34:C36)) -> 64653 | D37: =+SUM(D31+SUM(D34:D36)) -> 30112 | E37: =+SUM(E31+SUM(E34:E36)) -> 24139 | F37: =+SUM(F31+SUM(F34:F36)) -> -29972 | H37: =+SUM(H31+SUM(H34:H36)) -> 4951 | I37: =+SUM(I31+SUM(I34:I36)) -> 3959 | J37: =+SUM(J31+SUM(J34:J36)) -> 11128 | K37: =+SUM(K31+SUM(K34:K36)) -> 10074 | L37: =+SUM(L31+SUM(L34:L36)) -> 4245 | M37: =+SUM(M31+SUM(M34:M36)) -> 2855 | N37: =+SUM(N31+SUM(N34:N36)) -> 13255 | O37: =+SUM(O31+SUM(O34:O36)) -> 3784 | ... U37: =+SUM(U31+SUM(U34:U36)) -> -9 | W37: =+SUM(W31+SUM(W34:W35)) -> 30112 | X37: =+SUM(X31+SUM(X34:X35)) -> 29406 | Y37: =+SUM(Y31+SUM(Y34:Y35)) -> 28302 | Z37: =+SUM(Z31+SUM(Z34:Z35)) -> 30429 | AA37: =+SUM(AA31+SUM(AA34:AA35)) -> 24139 | AB37: =+SUM(AB31+SUM(AB34:AB35)) -> 13432 | AC37: =+SUM(AC31+SUM(AC34:AC36)) -> -2114 | AD37: =+SUM(AD31+SUM(AD34:AD36)) -> -26057 | AE37: =+SUM(AE31+SUM(AE34:AE36)) -> -29972 | AF37: =+SUM(AF31+SUM(AF34:AF36)) -> -26294 | AG37: =+SUM(AG31+SUM(AG34:AG36)) -> -13612 | AI37: =SUM(AG37/AC37)-1 -> 5.4389782
B38: Adj. EBITDA Margin (%) | C38: =C37/C10 -> 0.12658146 | D38: =D37/D10 -> 0.06031278 | E38: =E37/E10 -> 0.048641743 | F38: =F37/F10 -> -0.064670648 | H38: =H37/H10 -> 0.041508422 | I38: =I37/I10 -> 0.032431414 | J38: =J37/J10 -> 0.088768347 | K38: =K37/K10 -> 0.075999215 | L38: =L37/L10 -> 0.034819341 | M38: =M37/M10 -> 0.023712625 | N38: =N37/N10 -> 0.10238526 | O38: =O37/O10 -> 0.030397481 | ... U38: =U37/U10 -> -7.8610859e-05 | W38: =W37/W10 -> 0.06031278 | X38: =X37/X10 -> 0.058589127 | Y38: =Y37/Y10 -> 0.056578087 | Z38: =Z37/Z10 -> 0.060335375 | AA38: =AA37/AA10 -> 0.048641743 | AB38: =AB37/AB10 -> 0.027435089 | AC38: =AC37/AC10 -> -0.0043983572 | AD38: =AD37/AD10 -> -0.055767556 | ... AG38: =AG37/AG10 -> -0.029442683 | AI38: =SUM(AG38-AC38)*10000 -> -250.44326
B40: (-) Capital Expenditures | C40: ='3-Statement Model'!C114 -> -2706 | D40: ='3-Statement Model'!D114 -> -2486 | E40: ='3-Statement Model'!E114 -> -2938 | F40: ='3-Statement Model'!F114 -> -2978 | H40: ='3-Statement Model'!H114 -> -641 | I40: ='3-Statement Model'!I114 -> -878 | J40: ='3-Statement Model'!J114 -> -332 | K40: ='3-Statement Model'!K114 -> -635 | L40: ='3-Statement Model'!L114 -> -499 | M40: ='3-Statement Model'!M114 -> -639 | N40: ='3-Statement Model'!N114 -> -1453 | O40: ='3-Statement Model'!O114 -> -347 | ... U40: ='3-Statement Model'!U114 -> -2094 | W40: =SUM(H40:K40) -> -2486 | X40: =SUM(I40:L40) -> -2344 | Y40: =SUM(J40:M40) -> -2105 | Z40: =SUM(K40:N40) -> -3226 | AA40: =SUM(L40:O40) -> -2938 | AB40: =SUM(M40:P40) -> -3984 | AC40: =SUM(N40:Q40) -> -4068 | AD40: =SUM(O40:R40) -> -3041 | ... AG40: =SUM(R40:U40) -> -5541 | AI40: =SUM(AG40/AC40)-1 -> 0.3620944
B41: (-) Cash Interest | C41: =-'3-Statement Model'!C134 -> -20416 | D41: =-'3-Statement Model'!D134 -> -43448 | E41: =-'3-Statement Model'!E134 -> -41229 | F41: =-'3-Statement Model'!F134 -> -44571 | H41: =SUM($D$41/4) -> -10862 | I41: =SUM($D$41/4) -> -10862 | J41: =SUM($D$41/4) -> -10862 | K41: =SUM($D$41/4) -> -10862 | L41: =SUM($E$41/4) -> -10307.25 | M41: =SUM($E$41/4) -> -10307.25 | N41: =SUM($E$41/4) -> -10307.25 | O41: =SUM($E$41/4) -> -10307.25 | P41: =SUM($F$41/4) -> -11142.75 | Q41: =SUM($F$41/4) -> -11142.75 | R41: =SUM($F$41/4) -> -11142.75 | S41: =SUM($F$41/4) -> -11142.75 | T41: =S41 -> -11142.75 | U41: =T41 -> -11142.75 | W41: =SUM(H41:K41) -> -43448 | X41: =SUM(I41:L41) -> -42893.25 | Y41: =SUM(J41:M41) -> -42338.5 | Z41: =SUM(K41:N41) -> -41783.75 | AA41: =SUM(L41:O41) -> -41229 | AB41: =SUM(M41:P41) -> -42064.5 | AC41: =SUM(N41:Q41) -> -42900 | AD41: =SUM(O41:R41) -> -43735.5 | ... AG41: =SUM(R41:U41) -> -44571 | AI41: =SUM(AG41/AC41)-1 -> 0.038951049
B42: (-) Cash Taxes | C42: =-'3-Statement Model'!C135 -> -7010 | D42: =-'3-Statement Model'!D135 -> -21973 | E42: =-'3-Statement Model'!E135 -> -30318 | F42: =-'3-Statement Model'!F135 -> -1059 | H42: =SUM($D$42/4) -> -5493.25 | I42: =SUM($D$42/4) -> -5493.25 | J42: =SUM($D$42/4) -> -5493.25 | K42: =SUM($D$42/4) -> -5493.25 | L42: =SUM($E$42/4) -> -7579.5 | M42: =SUM($E$42/4) -> -7579.5 | N42: =SUM($E$42/4) -> -7579.5 | O42: =SUM($E$42/4) -> -7579.5 | P42: =SUM($F$42/4) -> -264.75 | Q42: =SUM($F$42/4) -> -264.75 | R42: =SUM($F$42/4) -> -264.75 | S42: =SUM($F$42/4) -> -264.75 | T42: =S42 -> -264.75 | U42: =T42 -> -264.75 | W42: =SUM(H42:K42) -> -21973 | X42: =SUM(I42:L42) -> -24059.25 | Y42: =SUM(J42:M42) -> -26145.5 | Z42: =SUM(K42:N42) -> -28231.75 | AA42: =SUM(L42:O42) -> -30318 | AB42: =SUM(M42:P42) -> -23003.25 | AC42: =SUM(N42:Q42) -> -15688.5 | AD42: =SUM(O42:R42) -> -8373.75 | ... AG42: =SUM(R42:U42) -> -1059 | AI42: =SUM(AG42/AC42)-1 -> -0.93249833
B43: (-) Mandatory Amortization | C43: 0 | D43: 0 | E43: 0 | F43: 0 | H43: 0 | I43: 0 | J43: 0 | K43: 0 | L43: 0 | M43: 0 | N43: 0 | O43: 0 | P43: 0 | Q43: 0 | R43: 0 | S43: 0 | T43: 0 | U43: 0 | W43: =SUM(H43:K43) -> 0 | X43: =SUM(I43:L43) -> 0 | Y43: =SUM(J43:M43) -> 0 | Z43: =SUM(K43:N43) -> 0 | AA43: =SUM(L43:O43) -> 0 | AB43: =SUM(M43:P43) -> 0 | AC43: =SUM(N43:Q43) -> 0 | AD43: =SUM(O43:R43) -> 0 | ... AG43: =SUM(R43:U43) -> 0 | AI43: =SUM(AG43/AC43)-1 -> #DIV/0!
B44: (+/-) Changes in NWC | C44: =SUM('3-Statement Model'!C100:C108) -> 11091 | D44: =SUM('3-Statement Model'!D100:D108) -> -36609 | E44: =SUM('3-Statement Model'!E100:E108) -> -21055 | F44: =SUM('3-Statement Model'!F100:F108) -> -42707 | H44: =SUM('3-Statement Model'!H100:H108) -> 40307 | I44: =SUM('3-Statement Model'!I100:I108) -> -31781 | J44: =SUM('3-Statement Model'!J100:J108) -> -13014 | K44: =SUM('3-Statement Model'!K100:K108) -> -32121 | L44: =SUM('3-Statement Model'!L100:L108) -> 36801 | M44: =SUM('3-Statement Model'!M100:M108) -> -17818 | N44: =SUM('3-Statement Model'!N100:N108) -> -26278 | O44: =SUM('3-Statement Model'!O100:O108) -> -13760 | ... U44: =SUM('3-Statement Model'!U100:U108) -> -13701 | W44: =SUM(H44:K44) -> -36609 | X44: =SUM(I44:L44) -> -40115 | Y44: =SUM(J44:M44) -> -26152 | Z44: =SUM(K44:N44) -> -39416 | AA44: =SUM(L44:O44) -> -21055 | AB44: =SUM(M44:P44) -> -32146 | AC44: =SUM(N44:Q44) -> -28280 | AD44: =SUM(O44:R44) -> -27508 | ... AG44: =SUM(R44:U44) -> -57509 | AI44: =SUM(AG44/AC44)-1 -> 1.0335573
B45: Discretionary Cash-Flows | C45: =SUM(C37+SUM(C40:C44)) -> 45612 | D45: =SUM(D37+SUM(D40:D44)) -> -74404 | E45: =SUM(E37+SUM(E40:E44)) -> -71401 | F45: =SUM(F37+SUM(F40:F44)) -> -121287 | H45: =SUM(H37+SUM(H40:H44)) -> 28261.75 | I45: =SUM(I37+SUM(I40:I44)) -> -45055.25 | J45: =SUM(J37+SUM(J40:J44)) -> -18573.25 | K45: =SUM(K37+SUM(K40:K44)) -> -39037.25 | L45: =SUM(L37+SUM(L40:L44)) -> 22660.25 | M45: =SUM(M37+SUM(M40:M44)) -> -33488.75 | N45: =SUM(N37+SUM(N40:N44)) -> -32362.75 | O45: =SUM(O37+SUM(O40:O44)) -> -28209.75 | ... U45: =SUM(U37+SUM(U40:U44)) -> -27211.5 | W45: =SUM(W37+SUM(W40:W44)) -> -74404 | X45: =SUM(X37+SUM(X40:X44)) -> -80005.5 | Y45: =SUM(Y37+SUM(Y40:Y44)) -> -68439 | Z45: =SUM(Z37+SUM(Z40:Z44)) -> -82228.5 | AA45: =SUM(AA37+SUM(AA40:AA44)) -> -71401 | AB45: =SUM(AB37+SUM(AB40:AB44)) -> -87765.75 | AC45: =SUM(AC37+SUM(AC40:AC44)) -> -93050.5 | AD45: =SUM(AD37+SUM(AD40:AD44)) -> -108715.25 | ... AG45: =SUM(AG37+SUM(AG40:AG44)) -> -122292 | AI45: =SUM(AG45/AC45)-1 -> 0.31425409
B47: (+/-) Issuance / (Repayment) from convertible senior notes, net | C47: ='3-Statement Model'!C120 -> 1025204 | D47: ='3-Statement Model'!D120 -> 0 | E47: ='3-Statement Model'!E120 -> 0 | F47: ='3-Statement Model'!F120 -> 6132319 | H47: ='3-Statement Model'!H120 -> 0 | I47: ='3-Statement Model'!I120 -> 0 | J47: ='3-Statement Model'!J120 -> 0 | K47: ='3-Statement Model'!K120 -> 0 | L47: ='3-Statement Model'!L120 -> 0 | M47: ='3-Statement Model'!M120 -> 0 | N47: ='3-Statement Model'!N120 -> 0 | O47: ='3-Statement Model'!O120 -> 0 | ... U47: ='3-Statement Model'!U120 -> -646 | W47: =SUM(H47:K47) -> 0 | X47: =SUM(I47:L47) -> 0 | Y47: =SUM(J47:M47) -> 0 | Z47: =SUM(K47:N47) -> 0 | AA47: =SUM(L47:O47) -> 0 | AB47: =SUM(M47:P47) -> 1375679 | AC47: =SUM(N47:Q47) -> 2161698 | AD47: =SUM(O47:R47) -> 3159828 | ... AG47: =SUM(R47:U47) -> 5955699
B48: (+/-) Issuance / (Repayment) from senior secured notes, net | C48: ='3-Statement Model'!C121 -> 487208 | D48: ='3-Statement Model'!D121 -> 0 | E48: ='3-Statement Model'!E121 -> 0 | F48: ='3-Statement Model'!F121 -> 0 | H48: ='3-Statement Model'!H121 -> 0 | I48: ='3-Statement Model'!I121 -> 0 | J48: ='3-Statement Model'!J121 -> 0 | K48: ='3-Statement Model'!K121 -> 0 | L48: ='3-Statement Model'!L121 -> 0 | M48: ='3-Statement Model'!M121 -> 0 | N48: ='3-Statement Model'!N121 -> 0 | O48: ='3-Statement Model'!O121 -> 0 | ... U48: ='3-Statement Model'!U121 -> 0 | W48: =SUM(H48:K48) -> 0 | X48: =SUM(I48:L48) -> 0 | Y48: =SUM(J48:M48) -> 0 | Z48: =SUM(K48:N48) -> 0 | AA48: =SUM(L48:O48) -> 0 | AB48: =SUM(M48:P48) -> 0 | AC48: =SUM(N48:Q48) -> 0 | AD48: =SUM(O48:R48) -> 0 | ... AG48: =SUM(R48:U48) -> 0
B49: (+/-) Issuance / (Repayment) from secured term loan, net | C49: ='3-Statement Model'!C122 -> 0 | D49: ='3-Statement Model'!D122 -> 204586 | E49: ='3-Statement Model'!E122 -> -160033 | F49: ='3-Statement Model'!F122 -> -515414 | H49: ='3-Statement Model'!H122 -> 204693 | I49: ='3-Statement Model'!I122 -> -107 | J49: ='3-Statement Model'!J122 -> 0 | K49: ='3-Statement Model'!K122 -> 0 | L49: ='3-Statement Model'!L122 -> -159900 | M49: ='3-Statement Model'!M122 -> -133 | N49: ='3-Statement Model'!N122 -> 0 | O49: ='3-Statement Model'!O122 -> 0 | ... U49: ='3-Statement Model'!U122 -> 0 | W49: =SUM(H49:K49) -> 204586 | X49: =SUM(I49:L49) -> -160007 | Y49: =SUM(J49:M49) -> -160033 | Z49: =SUM(K49:N49) -> -160033 | AA49: =SUM(L49:O49) -> -160033 | AB49: =SUM(M49:P49) -> -133 | AC49: =SUM(N49:Q49) -> 0 | AD49: =SUM(O49:R49) -> -515325 | ... AG49: =SUM(R49:U49) -> -515414
B50: (+/-) Issuance / (Repayment) of other long-term secured debt, net | C50: ='3-Statement Model'!C123 -> 0 | D50: ='3-Statement Model'!D123 -> 10584 | E50: ='3-Statement Model'!E123 -> -513 | F50: ='3-Statement Model'!F123 -> -539 | H50: ='3-Statement Model'!H123 -> 0 | I50: ='3-Statement Model'!I123 -> 10926 | J50: ='3-Statement Model'!J123 -> 81 | K50: ='3-Statement Model'!K123 -> -423 | L50: ='3-Statement Model'!L123 -> -128 | M50: ='3-Statement Model'!M123 -> -126 | N50: ='3-Statement Model'!N123 -> -128 | O50: ='3-Statement Model'!O123 -> -131 | ... U50: ='3-Statement Model'!U123 -> 15859 | W50: =SUM(H50:K50) -> 10584 | X50: =SUM(I50:L50) -> 10456 | Y50: =SUM(J50:M50) -> -596 | Z50: =SUM(K50:N50) -> -805 | AA50: =SUM(L50:O50) -> -513 | AB50: =SUM(M50:P50) -> -518 | AC50: =SUM(N50:Q50) -> -525 | AD50: =SUM(O50:R50) -> -665 | ... AG50: =SUM(R50:U50) -> 15445
B51: (+/-) Net Equity Issuances / (Share Repurchases) | C51: =SUM('3-Statement Model'!C125:C129) -> 1029273 | D51: =SUM('3-Statement Model'!D125:D129) -> 50018 | E51: =SUM('3-Statement Model'!E125:E129) -> 2050432 | F51: =SUM('3-Statement Model'!F125:F129) -> 16516275 | H51: =SUM('3-Statement Model'!H125:H129) -> 2598 | I51: =SUM('3-Statement Model'!I125:I129) -> 377 | J51: =SUM('3-Statement Model'!J125:J129) -> 1725 | K51: =SUM('3-Statement Model'!K125:K129) -> 45318 | L51: =SUM('3-Statement Model'!L125:L129) -> 347650 | M51: =SUM('3-Statement Model'!M125:M129) -> 338548 | N51: =SUM('3-Statement Model'!N125:N129) -> 150242 | O51: =SUM('3-Statement Model'!O125:O129) -> 1213992 | ... U51: =SUM('3-Statement Model'!U125:U129) -> 6843896 | W51: =SUM(H51:K51) -> 50018 | X51: =SUM(I51:L51) -> 395070 | Y51: =SUM(J51:M51) -> 733241 | Z51: =SUM(K51:N51) -> 881758 | AA51: =SUM(L51:O51) -> 2050432 | AB51: =SUM(M51:P51) -> 1975636 | AC51: =SUM(N51:Q51) -> 1654633 | AD51: =SUM(O51:R51) -> 2615957 | ... AG51: =SUM(R51:U51) -> 28787682
B52: (+/-) Purchases / (Sale) of Digital Assets | C52: ='3-Statement Model'!C112+'3-Statement Model'!C115 -> -2626529 | D52: ='3-Statement Model'!D112+'3-Statement Model'!D115 -> -276104 | E52: ='3-Statement Model'!E112+'3-Statement Model'!E115 -> -1902299 | F52: ='3-Statement Model'!F112+'3-Statement Model'!F115 -> -22072759 | H52: ='3-Statement Model'!H112+'3-Statement Model'!H115 -> -215500 | I52: ='3-Statement Model'!I112+'3-Statement Model'!I115 -> -10000 | J52: ='3-Statement Model'!J112+'3-Statement Model'!J115 -> -5978 | K52: ='3-Statement Model'!K112+'3-Statement Model'!K115 -> -44626 | L52: ='3-Statement Model'!L112+'3-Statement Model'!L115 -> -179275 | M52: ='3-Statement Model'!M112+'3-Statement Model'!M115 -> -347003 | N52: ='3-Statement Model'!N112+'3-Statement Model'!N115 -> -161681 | O52: ='3-Statement Model'!O112+'3-Statement Model'!O115 -> -1214340 | ... U52: ='3-Statement Model'!U112+'3-Statement Model'!U115 -> -6769205 | W52: =SUM(H52:K52) -> -276104 | X52: =SUM(I52:L52) -> -239879 | Y52: =SUM(J52:M52) -> -576882 | Z52: =SUM(K52:N52) -> -732585 | AA52: =SUM(L52:O52) -> -1902299 | AB52: =SUM(M52:P52) -> -3362333 | AC52: =SUM(N52:Q52) -> -3809158 | AD52: =SUM(O52:R52) -> -5222550 | ... AG52: =SUM(R52:U52) -> -34070490
B53: (+/-) Dividends paid on preferred stock | C53: ='3-Statement Model'!C130 -> 0 | D53: ='3-Statement Model'!D130 -> 0 | E53: ='3-Statement Model'!E130 -> 0 | F53: ='3-Statement Model'!F130 -> 0 | H53: ='3-Statement Model'!H130 -> 0 | I53: ='3-Statement Model'!I130 -> 0 | J53: ='3-Statement Model'!J130 -> 0 | K53: ='3-Statement Model'!K130 -> 0 | L53: ='3-Statement Model'!L130 -> 0 | M53: ='3-Statement Model'!M130 -> 0 | N53: ='3-Statement Model'!N130 -> 0 | O53: ='3-Statement Model'!O130 -> 0 | ... U53: ='3-Statement Model'!U130 -> -48954 | AC53: =SUM(N53:Q53) -> 0 | AD53: =SUM(O53:R53) -> 0 | AE53: =SUM(P53:S53) -> 0 | AF53: =SUM(Q53:T53) -> -9188 | AG53: =SUM(R53:U53) -> -58142
B54: (+/-) Other Adjustments | D54: {=SUM(D59:D60-C59:C60)-SUM(D45:D52)} -> 71754 | E54: {=SUM(E59:E60-D59:D60)-SUM(E45:E52)} -> 81619 | F54: {=SUM(F59:F60-E59:E60)-SUM(F45:F52)} -> 52629 | I54: {=SUM(I59:I60-H59:H60)-SUM(I45:I52)} -> 20458.25 | J54: {=SUM(J59:J60-I59:I60)-SUM(J45:J52)} -> 14172.25 | K54: {=SUM(K59:K60-J59:J60)-SUM(K45:K52)} -> 22668.25 | L54: {=SUM(L59:L60-K59:K60)-SUM(L45:L52)} -> 14588.75 | M54: {=SUM(M59:M60-L59:L60)-SUM(M45:M52)} -> 13791.75 | N54: {=SUM(N59:N60-M59:M60)-SUM(N45:N52)} -> 22750.75 | O54: {=SUM(O59:O60-N59:N60)-SUM(O45:O52)} -> 30487.75 | P54: {=SUM(P59:P60-O59:O60)-SUM(P45:P52)} -> 19668.5 | ... U54: {=SUM(U59:U60-T59:T60)-SUM(U45:U52)} -> -72818.5 | W54: =SUM(H54:K54) -> 57298.75 | X54: =SUM(I54:L54) -> 71887.5 | Y54: =SUM(J54:M54) -> 65221 | Z54: =SUM(K54:N54) -> 73799.5 | AA54: =SUM(L54:O54) -> 81619 | AB54: =SUM(M54:P54) -> 86698.75 | AC54: =SUM(N54:Q54) -> 87150.5 | AD54: =SUM(O54:R54) -> 72801.25 | ... AG54: =SUM(R54:U54) -> -67299
B55: Free-Cash Flows | C55: =SUM(C45+SUM(C47:C54)) -> -39232 | D55: =SUM(D45+SUM(D47:D54)) -> -13566 | E55: =SUM(E45+SUM(E47:E54)) -> -2195 | F55: =SUM(F45+SUM(F47:F54)) -> -8776 | H55: =SUM(H45+SUM(H47:H54)) -> 20052.75 | I55: =SUM(I45+SUM(I47:I54)) -> -23401 | J55: =SUM(J45+SUM(J47:J54)) -> -8573 | K55: =SUM(K45+SUM(K47:K54)) -> -16100 | L55: =SUM(L45+SUM(L47:L54)) -> 45596 | M55: =SUM(M45+SUM(M47:M54)) -> -28411 | N55: =SUM(N45+SUM(N47:N54)) -> -21179 | O55: =SUM(O45+SUM(O47:O54)) -> 1799 | ... U55: =SUM(U45+SUM(U47:U54)) -> -59080 | W55: =SUM(W45+SUM(W47:W54)) -> -28021.25 | X55: =SUM(X45+SUM(X47:X54)) -> -2478 | Y55: =SUM(Y45+SUM(Y47:Y54)) -> -7488 | Z55: =SUM(Z45+SUM(Z47:Z54)) -> -20094 | AA55: =SUM(AA45+SUM(AA47:AA54)) -> -2195 | AB55: =SUM(AB45+SUM(AB47:AB54)) -> -12736 | AC55: =SUM(AC45+SUM(AC47:AC54)) -> 748 | AD55: =SUM(AD45+SUM(AD47:AD54)) -> 1331 | ... AG55: =SUM(AG45+SUM(AG47:AG54)) -> -74811
B57: Capitalization
B59: Cash & Cash Equivelants | C59: ='3-Statement Model'!C42 -> 63356 | D59: ='3-Statement Model'!D42 -> 43835 | E59: ='3-Statement Model'!E42 -> 46817 | F59: ='3-Statement Model'!F42 -> 38117 | H59: ='3-Statement Model'!H42 -> 92677 | I59: ='3-Statement Model'!I42 -> 69386 | J59: ='3-Statement Model'!J42 -> 60390 | K59: ='3-Statement Model'!K42 -> 43835 | L59: ='3-Statement Model'!L42 -> 94311 | M59: ='3-Statement Model'!M42 -> 65968 | N59: ='3-Statement Model'!N42 -> 45009 | O59: ='3-Statement Model'!O42 -> 46817 | ... U59: ='3-Statement Model'!U42 -> 50095 | W59: =K59 -> 43835 | X59: =L59 -> 94311 | Y59: =M59 -> 65968 | Z59: =N59 -> 45009 | AA59: =O59 -> 46817 | AB59: =P59 -> 81326 | AC59: =Q59 -> 66923 | AD59: =R59 -> 46343 | ... AG59: =U59 -> 50095
B60: Restricted Cash | C60: ='3-Statement Model'!C43 -> 1078 | D60: ='3-Statement Model'!D43 -> 7033 | E60: ='3-Statement Model'!E43 -> 1856 | F60: ='3-Statement Model'!F43 -> 1780 | H60: ='3-Statement Model'!H43 -> 6265 | I60: ='3-Statement Model'!I43 -> 6155 | J60: ='3-Statement Model'!J43 -> 6578 | K60: ='3-Statement Model'!K43 -> 7033 | L60: ='3-Statement Model'!L43 -> 2153 | M60: ='3-Statement Model'!M43 -> 2085 | N60: ='3-Statement Model'!N43 -> 1865 | O60: ='3-Statement Model'!O43 -> 1856 | ... U60: ='3-Statement Model'!U43 -> 2037 | W60: =K60 -> 7033 | X60: =L60 -> 2153 | Y60: =M60 -> 2085 | Z60: =N60 -> 1865 | AA60: =O60 -> 1856 | AB60: =P60 -> 2402 | AC60: =Q60 -> 1878 | AD60: =R60 -> 1862 | ... AG60: =U60 -> 2037
B61: Total Liquidity | C61: =SUM(C59:C60) -> 64434 | D61: =SUM(D59:D60) -> 50868 | E61: =SUM(E59:E60) -> 48673 | F61: =SUM(F59:F60) -> 39897 | H61: =SUM(H59:H60) -> 98942 | I61: =SUM(I59:I60) -> 75541 | J61: =SUM(J59:J60) -> 66968 | K61: =SUM(K59:K60) -> 50868 | L61: =SUM(L59:L60) -> 96464 | M61: =SUM(M59:M60) -> 68053 | N61: =SUM(N59:N60) -> 46874 | O61: =SUM(O59:O60) -> 48673 | ... U61: =SUM(U59:U60) -> 52132 | W61: =SUM(W59:W60) -> 50868 | X61: =SUM(X59:X60) -> 96464 | Y61: =SUM(Y59:Y60) -> 68053 | Z61: =SUM(Z59:Z60) -> 46874 | AA61: =SUM(AA59:AA60) -> 48673 | AB61: =SUM(AB59:AB60) -> 83728 | AC61: =SUM(AC59:AC60) -> 68801 | AD61: =SUM(AD59:AD60) -> 48205 | ... AG61: =SUM(AG59:AG60) -> 52132
B63: Digital Assets (Bitcoin Holdings) | C63: ='3-Statement Model'!C48 -> 2850210 | D63: ='3-Statement Model'!D48 -> 1840028 | E63: ='3-Statement Model'!E48 -> 3626476 | F63: ='3-Statement Model'!F48 -> 23909373 | H63: ='3-Statement Model'!H48 -> 2895619 | I63: ='3-Statement Model'!I48 -> 1987781 | J63: ='3-Statement Model'!J48 -> 1993032 | K63: ='3-Statement Model'!K48 -> 1840028 | L63: ='3-Statement Model'!L48 -> 2000392 | M63: ='3-Statement Model'!M48 -> 2323252 | N63: ='3-Statement Model'!N48 -> 2451374 | O63: ='3-Statement Model'!O48 -> 3626476 | ... U63: ='3-Statement Model'!U48 -> 64362798 | W63: =K63 -> 1840028 | X63: =L63 -> 2000392 | Y63: =M63 -> 2323252 | Z63: =N63 -> 2451374 | AA63: =O63 -> 3626476 | AB63: =P63 -> 5074152 | AC63: =Q63 -> 5687890 | AD63: =R63 -> 6850879 | ... AG63: =U63 -> 64362798
B64: Total Adj. Liquidity | C64: =SUM(C63:C63)+C61 -> 2914644 | D64: =SUM(D63:D63)+D61 -> 1890896 | E64: =SUM(E63:E63)+E61 -> 3675149 | F64: =SUM(F63:F63)+F61 -> 23949270 | H64: =SUM(H63:H63)+H61 -> 2994561 | I64: =SUM(I63:I63)+I61 -> 2063322 | J64: =SUM(J63:J63)+J61 -> 2060000 | K64: =SUM(K63:K63)+K61 -> 1890896 | L64: =SUM(L63:L63)+L61 -> 2096856 | M64: =SUM(M63:M63)+M61 -> 2391305 | N64: =SUM(N63:N63)+N61 -> 2498248 | O64: =SUM(O63:O63)+O61 -> 3675149 | ... U64: =SUM(U63:U63)+U61 -> 64414930 | W64: =SUM(W63:W63) -> 1840028 | X64: =SUM(X63:X63) -> 2000392 | Y64: =SUM(Y63:Y63) -> 2323252 | Z64: =SUM(Z63:Z63) -> 2451374 | AA64: =SUM(AA63:AA63) -> 3626476 | AB64: =SUM(AB63:AB63) -> 5074152 | AC64: =SUM(AC63:AC63) -> 5687890 | AD64: =SUM(AD63:AD63) -> 6850879 | ... AG64: =SUM(AG63:AG63) -> 64362798
B66: Balance Sheet Metrics:
B67: Accounts Receivable | C67: ='3-Statement Model'!C44 -> 189280 | D67: ='3-Statement Model'!D44 -> 189280 | E67: ='3-Statement Model'!E44 -> 183815 | F67: ='3-Statement Model'!F44 -> 181203 | H67: ='3-Statement Model'!H44 -> 126930 | I67: ='3-Statement Model'!I44 -> 118645 | J67: ='3-Statement Model'!J44 -> 109926 | K67: ='3-Statement Model'!K44 -> 189280 | L67: ='3-Statement Model'!L44 -> 139178 | M67: ='3-Statement Model'!M44 -> 121901 | N67: ='3-Statement Model'!N44 -> 128650 | O67: ='3-Statement Model'!O44 -> 183815 | ... U67: ='3-Statement Model'!U44 -> 117870 | W67: =K67 -> 189280 | X67: =L67 -> 139178 | Y67: =M67 -> 121901 | Z67: =N67 -> 128650 | AA67: =O67 -> 183815 | AB67: =P67 -> 115150 | AC67: =Q67 -> 112234 | AD67: =R67 -> 107169 | ... AG67: =U67 -> 117870
B68: Accounts Payable | C68: ='3-Statement Model'!C55 -> 46084 | D68: ='3-Statement Model'!D55 -> 42976 | E68: ='3-Statement Model'!E55 -> 43090 | F68: ='3-Statement Model'!F55 -> 52982 | H68: ='3-Statement Model'!H55 -> 44388 | I68: ='3-Statement Model'!I55 -> 35960 | J68: ='3-Statement Model'!J55 -> 36846 | K68: ='3-Statement Model'!K55 -> 42976 | L68: ='3-Statement Model'!L55 -> 50604 | M68: ='3-Statement Model'!M55 -> 33660 | N68: ='3-Statement Model'!N55 -> 34306 | O68: ='3-Statement Model'!O55 -> 35960 | ... U68: ='3-Statement Model'!U55 -> 44220 | W68: =K68 -> 42976 | X68: =L68 -> 50604 | Y68: =M68 -> 33660 | Z68: =N68 -> 34306 | AA68: =O68 -> 35960 | AB68: =P68 -> 41866 | AC68: =Q68 -> 44188 | AD68: =R68 -> 45714 | ... AG68: =U68 -> 44220
B69: Property Plant, and Equiptment | C69: ='3-Statement Model'!C49 -> 36587 | D69: ='3-Statement Model'!D49 -> 32311 | E69: ='3-Statement Model'!E49 -> 28941 | F69: ='3-Statement Model'!F49 -> 26327 | H69: ='3-Statement Model'!H49 -> 35680 | I69: ='3-Statement Model'!I49 -> 34580 | J69: ='3-Statement Model'!J49 -> 33033 | K69: ='3-Statement Model'!K49 -> 32311 | L69: ='3-Statement Model'!L49 -> 31338 | M69: ='3-Statement Model'!M49 -> 30507 | N69: ='3-Statement Model'!N49 -> 30192 | O69: ='3-Statement Model'!O49 -> 28941 | ... U69: ='3-Statement Model'!U49 -> 30203 | W69: =K69 -> 32311 | X69: =L69 -> 31338 | Y69: =M69 -> 30507 | Z69: =N69 -> 30192 | AA69: =O69 -> 28941 | AB69: =P69 -> 29108 | AC69: =Q69 -> 28332 | AD69: =R69 -> 27517 | ... AG69: =U69 -> 30203
B70: Current Liabilities | C70: ='3-Statement Model'!C60 -> 311985 | D70: ='3-Statement Model'!D60 -> 317403 | E70: ='3-Statement Model'!E60 -> 323273 | F70: ='3-Statement Model'!F60 -> 355384 | H70: ='3-Statement Model'!H60 -> 304875 | I70: ='3-Statement Model'!I60 -> 274100 | J70: ='3-Statement Model'!J60 -> 260520 | K70: ='3-Statement Model'!K60 -> 317403 | L70: ='3-Statement Model'!L60 -> 312399 | M70: ='3-Statement Model'!M60 -> 272930 | N70: ='3-Statement Model'!N60 -> 267721 | O70: ='3-Statement Model'!O60 -> 316143 | ... U70: ='3-Statement Model'!U60 -> 314572 | W70: =K70 -> 317403 | X70: =L70 -> 312399 | Y70: =M70 -> 272930 | Z70: =N70 -> 267721 | AA70: =O70 -> 316143 | AB70: =P70 -> 309808 | AC70: =Q70 -> 446063 | AD70: =R70 -> 288111 | ... AG70: =U70 -> 314572
B71: Total Liabilities | C71: ='3-Statement Model'!C67 -> 2578166 | D71: ='3-Statement Model'!D67 -> 2793392 | E71: ='3-Statement Model'!E67 -> 2597556 | F71: ='3-Statement Model'!F67 -> 7613701 | H71: ='3-Statement Model'!H67 -> 2775388 | I71: ='3-Statement Model'!I67 -> 2755433 | J71: ='3-Statement Model'!J67 -> 2745575 | K71: ='3-Statement Model'!K67 -> 2793392 | L71: ='3-Statement Model'!L67 -> 2583191 | M71: ='3-Statement Model'!M67 -> 2543986 | N71: ='3-Statement Model'!N67 -> 2533546 | O71: ='3-Statement Model'!O67 -> 2797476 | ... U71: ='3-Statement Model'!U67 -> 14402450 | W71: =K71 -> 2793392 | X71: =L71 -> 2583191 | Y71: =M71 -> 2543986 | Z71: =N71 -> 2533546 | AA71: =O71 -> 2797476 | AB71: =P71 -> 3951434 | AC71: =Q71 -> 4218274 | AD71: =R71 -> 4569932 | ... AG71: =U71 -> 14402450
B73: Summary Debt (BS):
B74: CPLTD | C74: ='3-Statement Model'!C58 -> 0 | D74: ='3-Statement Model'!D58 -> 454 | E74: ='3-Statement Model'!E58 -> 483 | F74: ='3-Statement Model'!F58 -> 517 | H74: ='3-Statement Model'!H58 -> 0 | I74: ='3-Statement Model'!I58 -> 0 | J74: ='3-Statement Model'!J58 -> 0 | K74: ='3-Statement Model'!K58 -> 454 | L74: ='3-Statement Model'!L58 -> 460 | M74: ='3-Statement Model'!M58 -> 468 | N74: ='3-Statement Model'!N58 -> 475 | O74: ='3-Statement Model'!O58 -> 483 | ... U74: ='3-Statement Model'!U58 -> 349 | W74: =K74 -> 454 | X74: =L74 -> 460 | Y74: =M74 -> 468 | Z74: =N74 -> 475 | AA74: =O74 -> 483 | AB74: =P74 -> 492 | AC74: =Q74 -> 145119 | AD74: =R74 -> 509 | ... AG74: =U74 -> 349
B75: LTD | C75: ='3-Statement Model'!C62 -> 2155151 | D75: ='3-Statement Model'!D62 -> 2378560 | E75: ='3-Statement Model'!E62 -> 2182108 | F75: ='3-Statement Model'!F62 -> 7191158 | H75: ='3-Statement Model'!H62 -> 2361865 | I75: ='3-Statement Model'!I62 -> 2374863 | J75: ='3-Statement Model'!J62 -> 2376935 | K75: ='3-Statement Model'!K62 -> 2378560 | L75: ='3-Statement Model'!L62 -> 2175918 | M75: ='3-Statement Model'!M62 -> 2177974 | N75: ='3-Statement Model'!N62 -> 2180038 | O75: ='3-Statement Model'!O62 -> 2374863 | ... U75: ='3-Statement Model'!U62 -> 8162281 | W75: =K75 -> 2378560 | X75: =L75 -> 2175918 | Y75: =M75 -> 2177974 | Z75: =N75 -> 2180038 | AA75: =O75 -> 2374863 | AB75: =P75 -> 3558801 | AC75: =Q75 -> 3703381 | AD75: =R75 -> 4211949 | ... AG75: =U75 -> 8162281
B77: $650MM 0.750% Sr. Unsecured Convertible Notes due 2025 | C77: 637882 | D77: 640888 | E77: 643931 | F77: 1041352 | H77: 638630 | I77: 639380 | J77: 640133 | K77: =D77 -> 640888 | L77: 641645 | M77: 642405 | N77: 643167 | O77: =E77 -> 643931 | P77: 644698 | Q77: 144618 | R77: 0 | S77: =F77 -> 1041352 | T77: 0 | U77: 0 | W77: =K77 -> 640888 | X77: =L77 -> 641645 | Y77: =M77 -> 642405 | Z77: =N77 -> 643167 | AA77: =O77 -> 643931 | AB77: =P77 -> 644698 | AC77: =Q77 -> 144618 | AD77: =R77 -> 0 | ... AG77: =U77 -> 0
B78: $1.050Bn 0.000% Sr. Unsecured Convertible Notes due 2027 | C78: 1029263 | D78: 1033277 | E78: 1037306 | F78: 998543 | H78: 1030265 | I78: 1031268 | J78: 1032272 | K78: =D78 -> 1033277 | L78: 1034283 | M78: 1035290 | N78: 1036298 | O78: =E78 -> 1037306 | P78: 1038316 | Q78: 1039327 | R78: 1040339 | S78: =F78 -> 998543 | T78: 0 | U78: 0 | W78: =K78 -> 1033277 | X78: =L78 -> 1034283 | Y78: =M78 -> 1035290 | Z78: =N78 -> 1036298 | AA78: =O78 -> 1037306 | AB78: =P78 -> 1038316 | AC78: =Q78 -> 1039327 | AD78: =R78 -> 1040339 | ... AG78: =U78 -> 0
B79: $1.010Bn 0.625% Sr. Unsecured Convertible Notes due 2028 | C79: 0 | D79: 0 | E79: 0 | F79: 2975037 | H79: 0 | I79: 0 | J79: 0 | K79: =D79 -> 0 | L79: 0 | M79: 0 | N79: 0 | O79: =E79 -> 0 | P79: 0 | Q79: 0 | R79: 997502 | S79: =F79 -> 2975037 | T79: 999587 | U79: 1000634 | W79: =K79 -> 0 | X79: =L79 -> 0 | Y79: =M79 -> 0 | Z79: =N79 -> 0 | AA79: =O79 -> 0 | AB79: =P79 -> 0 | AC79: =Q79 -> 0 | AD79: =R79 -> 997502 | ... AG79: =U79 -> 1000634
B80: $3.0Bn 0.000% Sr. Unsecured Convertible Notes due 2029 | C80: 0 | D80: 0 | E80: 0 | F80: 0 | H80: 0 | I80: 0 | J80: 0 | K80: 0 | L80: 0 | M80: 0 | N80: 0 | O80: 0 | P80: 0 | Q80: 0 | R80: 0 | S80: 0 | T80: 2976855 | U80: 2978675 | AF80: =T80 -> 2976855 | AG80: =U80 -> 2978675
B81: $800MM 0.625% Sr. Unsecured Convertible Notes due 2030 | C81: 0 | D81: 0 | E81: 0 | F81: 785172 | H81: 0 | I81: 0 | J81: 0 | K81: =D81 -> 0 | L81: 0 | M81: 0 | N81: 0 | O81: =E81 -> 0 | P81: 782248 | Q81: 783220 | R81: 784194 | S81: =F81 -> 785172 | T81: 786152 | U81: 787135 | W81: =K81 -> 0 | X81: =L81 -> 0 | Y81: =M81 -> 0 | Z81: =N81 -> 0 | AA81: =O81 -> 0 | AB81: =P81 -> 782248 | AC81: =Q81 -> 783220 | AD81: =R81 -> 784194 | ... AG81: =U81 -> 787135
B82: $800MM 0.000% Sr. Unsecured Convertible Notes due 2030 | T82: 1985365 | U82: 1986614 | AF82: =T82 -> 1985365 | AG82: =U82 -> 1986614
B83: $603.8MM 0.875% Sr. Unsecured Convertible Notes due 2031 | C83: 0 | D83: 0 | E83: 0 | F83: 594476 | H83: 0 | I83: 0 | J83: 0 | K83: =D83 -> 0 | L83: 0 | M83: 0 | N83: 0 | O83: =E83 -> 0 | P83: 592368 | Q83: 593259 | R83: 593867 | S83: =F83 -> 594476 | T83: 595087 | U83: 595613 | W83: =K83 -> 0 | X83: =L83 -> 0 | Y83: =M83 -> 0 | Z83: =N83 -> 0 | AA83: =O83 -> 0 | AB83: =P83 -> 592368 | AC83: =Q83 -> 593259 | AD83: =R83 -> 593867 | ... AG83: =U83 -> 595613
B84: $800MM 2.250% Sr. Unsecured Convertible Notes due 2032 | C84: 0 | D84: 0 | E84: 0 | F84: 787417 | H84: 0 | I84: 0 | J84: 0 | K84: =D84 -> 0 | L84: 0 | M84: 0 | N84: 0 | O84: =E84 -> 0 | P84: 0 | Q84: 786095 | R84: 786754 | S84: =F84 -> 787417 | T84: 788084 | U84: 788756 | W84: =K84 -> 0 | X84: =L84 -> 0 | Y84: =M84 -> 0 | Z84: =N84 -> 0 | AA84: =O84 -> 0 | AB84: =P84 -> 0 | AC84: =Q84 -> 786095 | AD84: =R84 -> 786754 | ... AG84: =U84 -> 788756
B85: $500MM 6.580% 2028 Sr. Secured Notes due 2028 | C85: 488006 | D85: 489547 | E85: 491193 | F85: 0 | H85: 488382 | I85: 488764 | J85: 489152 | K85: =D85 -> 489547 | L85: 489948 | M85: 490356 | N85: 490771 | O85: =E85 -> 491193 | P85: 491622 | Q85: 492057 | R85: 0 | S85: =F85 -> 0 | T85: 0 | U85: 0 | W85: =K85 -> 489547 | X85: =L85 -> 489948 | Y85: =M85 -> 490356 | Z85: =N85 -> 490771 | AA85: =O85 -> 491193 | AB85: =P85 -> 491622 | AC85: =Q85 -> 492057 | AD85: =R85 -> 0 | ... AG85: =U85 -> 0
B86: $205MM 3.870% 2025 Secured Term Loan | C86: 0 | D86: 204688 | E86: 0 | F86: 0 | H86: 204588 | I86: 204621 | J86: 204654 | K86: =D86 -> 204688 | L86: 0 | M86: 0 | N86: 0 | O86: =E86 -> 0 | P86: 0 | Q86: 0 | R86: 0 | S86: =F86 -> 0 | T86: 0 | U86: 0 | W86: =K86 -> 204688 | X86: =L86 -> 0 | Y86: =M86 -> 0 | Z86: =N86 -> 0 | AA86: =O86 -> 0 | AB86: =P86 -> 0 | AC86: =Q86 -> 0 | AD86: =R86 -> 0 | ... AG86: =U86 -> 0
B87: Other long-term secured debt | C87: 0 | D87: 10160 | E87: 9678 | F87: 9678 | H87: 0 | I87: 10830 | J87: 10724 | K87: =D87 -> 10160 | L87: 10042 | M87: 9923 | N87: 9802 | O87: =E87 -> 9678 | P87: 9549 | Q87: 9924 | R87: 9802 | S87: =F87 -> 9678 | T87: 9551 | U87: 25203 | W87: =K87 -> 10160 | X87: =L87 -> 10042 | Y87: =M87 -> 9923 | Z87: =N87 -> 9802 | AA87: =O87 -> 9678 | AB87: =P87 -> 9549 | AC87: =Q87 -> 9924 | AD87: =R87 -> 9802 | ... AG87: =U87 -> 25203
B88: Total Debt | C88: =SUM(C77:C85) -> 2155151 | D88: =SUM(D77:D85) -> 2163712 | E88: =SUM(E77:E87) -> 2182108 | F88: =SUM(F77:F87) -> 7191675 | H88: =SUM(H77:H87) -> 2361865 | I88: =SUM(I77:I87) -> 2374863 | J88: =SUM(J77:J87) -> 2376935 | K88: =SUM(K77:K87) -> 2378560 | L88: =SUM(L77:L87) -> 2175918 | M88: =SUM(M77:M87) -> 2177974 | N88: =SUM(N77:N87) -> 2180038 | O88: =SUM(O77:O87) -> 2182108 | ... U88: =SUM(U77:U87) -> 8162630 | W88: =SUM(W77:W87) -> 2378560 | X88: =SUM(X77:X87) -> 2175918 | Y88: =SUM(Y77:Y87) -> 2177974 | Z88: =SUM(Z77:Z87) -> 2180038 | AA88: =SUM(AA77:AA87) -> 2182108 | AB88: =SUM(AB77:AB87) -> 3558801 | AC88: =SUM(AC77:AC87) -> 3848500 | AD88: =SUM(AD77:AD87) -> 4212458 | ... AG88: =SUM(AG77:AG87) -> 8162630
B90: Total Shareholder Equity | C90: ='3-Statement Model'!C79 -> 978958 | D90: ='3-Statement Model'!D79 -> -383120 | E90: ='3-Statement Model'!E79 -> 2164972 | F90: ='3-Statement Model'!F79 -> 18229984 | H90: ='3-Statement Model'!H79 -> 862999 | I90: ='3-Statement Model'!I79 -> -187068 | J90: ='3-Statement Model'!J79 -> -200289 | K90: ='3-Statement Model'!K79 -> -383120 | L90: ='3-Statement Model'!L79 -> 443211 | M90: ='3-Statement Model'!M79 -> 819118 | N90: ='3-Statement Model'!N79 -> 840395 | O90: ='3-Statement Model'!O79 -> -187068 | ... U90: ='3-Statement Model'!U79 -> 50370965 | W90: =K90 -> -383120 | X90: =L90 -> 443211 | Y90: =M90 -> 819118 | Z90: =N90 -> 840395 | AA90: =O90 -> -187068 | AB90: =P90 -> 2400105 | AC90: =Q90 -> 2834799 | AD90: =R90 -> 3773649 | ... AG90: =U90 -> 50370965
B91: Total Book Capitalization | C91: =SUM(C88:C90) -> 3134109 | D91: =SUM(D88:D90) -> 1780592 | E91: =SUM(E88:E90) -> 4347080 | F91: =SUM(F88:F90) -> 25421659 | H91: =SUM(H88:H90) -> 3224864 | I91: =SUM(I88:I90) -> 2187795 | J91: =SUM(J88:J90) -> 2176646 | K91: =SUM(K88:K90) -> 1995440 | L91: =SUM(L88:L90) -> 2619129 | M91: =SUM(M88:M90) -> 2997092 | N91: =SUM(N88:N90) -> 3020433 | O91: =SUM(O88:O90) -> 1995040 | ... U91: =SUM(U88:U90) -> 58533595 | W91: =SUM(W88:W90) -> 1995440 | X91: =SUM(X88:X90) -> 2619129 | Y91: =SUM(Y88:Y90) -> 2997092 | Z91: =SUM(Z88:Z90) -> 3020433 | AA91: =SUM(AA88:AA90) -> 1995040 | AB91: =SUM(AB88:AB90) -> 5958906 | AC91: =SUM(AC88:AC90) -> 6683299 | AD91: =SUM(AD88:AD90) -> 7986107 | ... AG91: =SUM(AG88:AG90) -> 58533595
B93: Ratio Analysis
B95: Total Leverage | C95: =C88/C37 -> 33.334122 | D95: =D88/D37 -> 71.855473 | E95: =E88/E37 -> 90.397614 | F95: =F88/F37 -> -239.94645 | K95: =SUM(K88/SUM(H37:K37)) -> 78.990436 | L95: =SUM(L88/SUM(I37:L37)) -> 73.995715 | M95: =SUM(M88/SUM(J37:M37)) -> 76.954774 | N95: =SUM(N88/SUM(K37:N37)) -> 71.643432 | O95: =SUM(O88/SUM(L37:O37)) -> 90.397614 | P95: =SUM(P88/SUM(M37:P37)) -> 264.94945 | Q95: =SUM(Q88/SUM(N37:Q37)) -> -1820.4825 | R95: =SUM(R88/SUM(O37:R37)) -> -161.6632 | ... U95: =SUM(U88/SUM(R37:U37)) -> -599.66427 | W95: =W88/W37 -> 78.990436 | X95: =X88/X37 -> 73.995715 | Y95: =Y88/Y37 -> 76.954774 | Z95: =Z88/Z37 -> 71.643432 | AA95: =AA88/AA37 -> 90.397614 | AB95: =AB88/AB37 -> 264.94945 | AC95: =AC88/AC37 -> -1820.4825 | AD95: =AD88/AD37 -> -161.6632 | ... AG95: =AG88/AG37 -> -599.66427
B96: Net Leverage (C&CE) | C96: =SUM(C88-C59)/C37 -> 32.354183 | D96: =SUM(D88-D59)/D37 -> 70.399741 | E96: =SUM(E88-E59)/E37 -> 88.458138 | F96: =SUM(F88-F59)/F37 -> -238.6747 | K96: =SUM(K88-K59)/SUM(H37:K37) -> 77.534704 | L96: =SUM(L88-L59)/SUM(I37:L37) -> 70.788513 | M96: =SUM(M88-M59)/SUM(J37:M37) -> 74.623914 | N96: =SUM(N88-N59)/SUM(K37:N37) -> 70.164284 | O96: =SUM(O88-O59)/SUM(L37:O37) -> 88.458138 | P96: =SUM(P88-P59)/SUM(M37:P37) -> 258.8948 | Q96: =SUM(Q88-Q59)/SUM(N37:Q37) -> -1788.8254 | R96: =SUM(R88-R59)/SUM(O37:R37) -> -159.88468 | ... U96: =SUM(U88-U59)/SUM(R37:U37) -> -595.98406 | W96: =SUM(W88-W59)/W37 -> 77.534704 | X96: =SUM(X88-X59)/X37 -> 70.788513 | Y96: =SUM(Y88-Y59)/Y37 -> 74.623914 | Z96: =SUM(Z88-Z59)/Z37 -> 70.164284 | AA96: =SUM(AA88-AA59)/AA37 -> 88.458138 | AB96: =SUM(AB88-AB59)/AB37 -> 258.8948 | AC96: =SUM(AC88-AC59)/AC37 -> -1788.8254 | AD96: =SUM(AD88-AD59)/AD37 -> -159.88468 | ... AG96: =SUM(AG88-AG59)/AG37 -> -595.98406
B97: Net Leverage (C&CE + BTC Holdings) | C97: =SUM(C88-C59-C63)/C37 -> -11.730546 | D97: =SUM(D88-D59-D63)/D37 -> 9.2936039 | E97: =SUM(E88-E59-E63)/E37 -> -61.774929 | F97: =SUM(F88-F59-F63)/F37 -> 559.04895 | K97: =SUM(K88-K59-K63)/SUM(H37:K37) -> 16.428567 | L97: =SUM(L88-L59-L63)/SUM(I37:L37) -> 2.7618513 | M97: =SUM(M88-M59-M63)/SUM(J37:M37) -> -7.4639955 | N97: =SUM(N88-N59-N63)/SUM(K37:N37) -> -10.396168 | O97: =SUM(O88-O59-O63)/SUM(L37:O37) -> -61.774929 | P97: =SUM(P88-P59-P63)/SUM(M37:P37) -> -118.87113 | Q97: =SUM(Q88-Q59-Q63)/SUM(N37:Q37) -> 901.75639 | R97: =SUM(R88-R59-R63)/SUM(O37:R37) -> 103.03427 | ... U97: =SUM(U88-U59-U63)/SUM(R37:U37) -> 4132.4025 | W97: =SUM(W88-W59-W63)/W37 -> 16.428567 | X97: =SUM(X88-X59-X63)/X37 -> 2.7618513 | Y97: =SUM(Y88-Y59-Y63)/Y37 -> -7.4639955 | Z97: =SUM(Z88-Z59-Z63)/Z37 -> -10.396168 | AA97: =SUM(AA88-AA59-AA63)/AA37 -> -61.774929 | AB97: =SUM(AB88-AB59-AB63)/AB37 -> -118.87113 | AC97: =SUM(AC88-AC59-AC63)/AC37 -> 901.75639 | AD97: =SUM(AD88-AD59-AD63)/AD37 -> 103.03427 | ... AG97: =SUM(AG88-AG59-AG63)/AG37 -> 4132.4025
B99: Interest Coverage | C99: =C37/-C41 -> 3.166781 | D99: =D37/-D41 -> 0.69305837 | E99: =E37/-E41 -> 0.58548594 | F99: =F37/-F41 -> -0.67245518 | K99: {=SUM(H37:K37)/SUM(-H41:K41)} -> 0.69305837 | L99: {=SUM(I37:L37)/SUM(-I41:L41)} -> 0.68556241 | M99: {=SUM(J37:M37)/SUM(-J41:M41)} -> 0.6684696 | N99: {=SUM(K37:N37)/SUM(-K41:N41)} -> 0.72824962 | O99: {=SUM(L37:O37)/SUM(-L41:O41)} -> 0.58548594 | P99: {=SUM(M37:P37)/SUM(-M41:P41)} -> 0.31931914 | Q99: {=SUM(N37:Q37)/SUM(-N41:Q41)} -> -0.049277389 | R99: {=SUM(O37:R37)/SUM(-O41:R41)} -> -0.59578603 | ... U99: {=SUM(R37:U37)/SUM(-R41:U41)} -> -0.30540037 | W99: =W37/-W41 -> 0.69305837 | X99: =X37/-X41 -> 0.68556241 | Y99: =Y37/-Y41 -> 0.6684696 | Z99: =Z37/-Z41 -> 0.72824962 | AA99: =AA37/-AA41 -> 0.58548594 | AB99: =AB37/-AB41 -> 0.31931914 | AC99: =AC37/-AC41 -> -0.049277389 | AD99: =AD37/-AD41 -> -0.59578603 | ... AG99: =AG37/-AG41 -> -0.30540037
B100: Debt Service Coverage | C100: {=SUM(C37+C40)/SUM(-C41:C43)} -> 2.2586961 | D100: {=SUM(D37+D40)/SUM(-D41:D43)} -> 0.42228031 | E100: {=SUM(E37+E40)/SUM(-E41:E43)} -> 0.2963227 | F100: {=SUM(F37+F40)/SUM(-F41:F43)} -> -0.72211265 | K100: {=SUM(H37:K37+H40:K40)/SUM(-H41:K43)} -> 0.42228031 | L100: {=SUM(I37:L37+I40:L40)/SUM(-I41:L43)} -> 0.40419701 | M100: {=SUM(J37:M37+J40:M40)/SUM(-J41:M43)} -> 0.38252731 | N100: {=SUM(K37:N37+K40:N40)/SUM(-K41:N43)} -> 0.38852825 | O100: {=SUM(L37:O37+L40:O40)/SUM(-L41:O43)} -> 0.2963227 | P100: {=SUM(M37:P37+M40:P40)/SUM(-M41:P43)} -> 0.1452025 | Q100: {=SUM(N37:Q37+N40:Q40)/SUM(-N41:Q43)} -> -0.10551559 | R100: {=SUM(O37:R37+O40:R40)/SUM(-O41:R43)} -> -0.55840374 | ... U100: {=SUM(R37:U37+R40:U40)/SUM(-R41:U43)} -> -0.41974578 | W100: {=SUM(W37+W40)/SUM(-W41:W43)} -> 0.42228031 | X100: {=SUM(X37+X40)/SUM(-X41:X43)} -> 0.40419701 | Y100: {=SUM(Y37+Y40)/SUM(-Y41:Y43)} -> 0.38252731 | Z100: {=SUM(Z37+Z40)/SUM(-Z41:Z43)} -> 0.38852825 | AA100: {=SUM(AA37+AA40)/SUM(-AA41:AA43)} -> 0.2963227 | AB100: {=SUM(AB37+AB40)/SUM(-AB41:AB43)} -> 0.1452025 | AC100: {=SUM(AC37+AC40)/SUM(-AC41:AC43)} -> -0.10551559 | AD100: {=SUM(AD37+AD40)/SUM(-AD41:AD43)} -> -0.55840374 | ... AG100: {=SUM(AG37+AG40)/SUM(-AG41:AG43)} -> -0.41974578
B101: Fixed Charge Coverage | C101: {=SUM(C37)/SUM(-C40:C43)} -> 2.1456591 | D101: {=SUM(D37)/SUM(-D40:D43)} -> 0.44342999 | E101: {=SUM(E37)/SUM(-E40:E43)} -> 0.32407867 | F101: {=SUM(F37)/SUM(-F40:F43)} -> -0.61660632 | K101: {=SUM(H37:K37)/SUM(-H40:K43)} -> 0.44342999 | L101: {=SUM(I37:L37)/SUM(-I40:L43)} -> 0.42435044 | M101: {=SUM(J37:M37)/SUM(-J40:M43)} -> 0.40094066 | N101: {=SUM(K37:N37)/SUM(-K40:N43)} -> 0.41546118 | O101: {=SUM(L37:O37)/SUM(-L40:O43)} -> 0.32407867 | P101: {=SUM(M37:P37)/SUM(-M40:P43)} -> 0.19452078 | Q101: {=SUM(N37:Q37)/SUM(-N40:Q43)} -> -0.033739516 | R101: {=SUM(O37:R37)/SUM(-O40:R43)} -> -0.47247293 | ... U101: {=SUM(R37:U37)/SUM(-R40:U43)} -> -0.26601004 | W101: {=SUM(W37)/SUM(-W40:W43)} -> 0.44342999 | X101: {=SUM(X37)/SUM(-X40:X43)} -> 0.42435044 | Y101: {=SUM(Y37)/SUM(-Y40:Y43)} -> 0.40094066 | Z101: {=SUM(Z37)/SUM(-Z40:Z43)} -> 0.41546118 | AA101: {=SUM(AA37)/SUM(-AA40:AA43)} -> 0.32407867 | AB101: {=SUM(AB37)/SUM(-AB40:AB43)} -> 0.19452078 | AC101: {=SUM(AC37)/SUM(-AC40:AC43)} -> -0.033739516 | AD101: {=SUM(AD37)/SUM(-AD40:AD43)} -> -0.47247293 | ... AG101: {=SUM(AG37)/SUM(-AG40:AG43)} -> -0.26601004
B102: Debt-to-Book Capitalization | C102: =C91/C88 -> 1.454241 | D102: =D91/D88 -> 0.82293392 | E102: =E91/E88 -> 1.992147 | F102: =F91/F88 -> 3.5348732 | K102: =K91/K88 -> 0.83892775 | L102: =L91/L88 -> 1.2036892 | M102: =M91/M88 -> 1.3760917 | N102: =N91/N88 -> 1.3854956 | O102: =O91/O88 -> 0.91427189 | P102: =P91/P88 -> 1.6744139 | Q102: =Q91/Q88 -> 1.7365984 | R102: =R91/R88 -> 1.8958307 | ... U102: =U91/U88 -> 7.1709235 | W102: =W91/W88 -> 0.83892775 | X102: =X91/X88 -> 1.2036892 | Y102: =Y91/Y88 -> 1.3760917 | Z102: =Z91/Z88 -> 1.3854956 | AA102: =AA91/AA88 -> 0.91427189 | AB102: =AB91/AB88 -> 1.6744139 | AC102: =AC91/AC88 -> 1.7365984 | AD102: =AD91/AD88 -> 1.8958307 | ... AG102: =AG91/AG88 -> 7.1709235
