Workbook

Sheet Historical Financials
B2: Warner Bros Discovery Inc (NASDAQ: WBD)
B3: Historical Financials
B4: ($ In Millions, except EPS)
A6: X | B6: Income Statement | E6: FYE | I6: Quarterly | O6: Quarterly | X6: LTM | AD6: Variance
B7: Fiscal Period | C7: 2020 | D7: 2021 | E7: 2022 | F7: 2023 | G7: 2024 | I7: 1Q23 | J7: 2Q23 | K7: 3Q23 | L7: 4Q23 | M7: 1Q24 | N7: 2Q24 | O7: 3Q24 | P7: 4Q24 | Q7: 1Q25 | R7: 2Q25 | S7: 3Q25 | U7: =L7 -> 4Q23 | V7: =M7 -> 1Q24 | W7: =N7 -> 2Q24 | X7: =O7 -> 3Q24 | Y7: =P7 -> 4Q24 | Z7: =Q7 -> 1Q25 | AA7: =R7 -> 2Q25 | AB7: =S7 -> 3Q25
B8: Fiscal Period End Date | C8: 44196 | D8: 44561 | E8: 44926 | F8: 45291 | G8: 45657 | I8: 45016 | J8: 45107 | K8: 45199 | L8: =E8 -> 44926 | M8: 45382 | N8: 45473 | O8: 45565 | P8: =F8 -> 45291 | Q8: 45747 | R8: 45838 | S8: 45930 | U8: =L8 -> 44926 | V8: =M8 -> 45382 | W8: =N8 -> 45473 | X8: =O8 -> 45565 | Y8: =P8 -> 45291 | Z8: =Q8 -> 45747 | AA8: =R8 -> 45838 | AB8: =S8 -> 45930
B10: Consolidated Revenue | C10: 10671 | D10: 12191 | E10: 33817 | F10: 41321 | G10: 39321 | I10: 10700 | J10: 10358 | K10: 9979 | L10: =SUM(F10-SUM(I10:K10)) -> 10284 | M10: 9958 | N10: 9713 | O10: 9623 | P10: =SUM(G10-SUM(M10:O10)) -> 10027 | Q10: 8979 | R10: 9812 | S10: 9045 | U10: =SUM(I10:L10) -> 41321 | V10: =SUM(J10:M10) -> 40579 | W10: =SUM(K10:N10) -> 39934 | X10: =SUM(L10:O10) -> 39578 | Y10: =SUM(M10:P10) -> 39321 | Z10: =SUM(N10:Q10) -> 38342 | AA10: =SUM(O10:R10) -> 38441 | AB10: =SUM(P10:S10) -> 37863 | AD10: =SUM(AB10/X10)-1 -> -0.043332154
B11: Total Revenue | C11: =+SUM(C10:C10) -> 10671 | D11: =+SUM(D10:D10) -> 12191 | E11: =+SUM(E10:E10) -> 33817 | F11: =+SUM(F10:F10) -> 41321 | G11: =+SUM(G10:G10) -> 39321 | I11: =+SUM(I10:I10) -> 10700 | J11: =+SUM(J10:J10) -> 10358 | K11: =+SUM(K10:K10) -> 9979 | L11: =+SUM(L10:L10) -> 10284 | M11: =+SUM(M10:M10) -> 9958 | N11: =+SUM(N10:N10) -> 9713 | O11: =+SUM(O10:O10) -> 9623 | P11: =+SUM(P10:P10) -> 10027 | ... S11: =+SUM(S10:S10) -> 9045 | U11: =+SUM(U10:U10) -> 41321 | V11: =+SUM(V10:V10) -> 40579 | W11: =+SUM(W10:W10) -> 39934 | X11: =+SUM(X10:X10) -> 39578 | Y11: =+SUM(Y10:Y10) -> 39321 | Z11: =+SUM(Z10:Z10) -> 38342 | AA11: =+SUM(AA10:AA10) -> 38441 | AB11: =+SUM(AB10:AB10) -> 37863 | AD11: =SUM(AB11/X11)-1 -> -0.043332154
B13: Costs of revenues, excluding depreciation and amortization | C13: -3860 | D13: -4620 | E13: -20442 | F13: -24526 | G13: -22970 | I13: -6685 | J13: -6636 | K13: -5309 | L13: =SUM(F13-SUM(I13:K13)) -> -5896 | M13: -6058 | N13: -6204 | O13: -5181 | P13: =SUM(G13-SUM(M13:O13)) -> -5527 | Q13: -5131 | R13: -5967 | S13: -4564 | U13: =SUM(I13:L13) -> -24526 | V13: =SUM(J13:M13) -> -23899 | W13: =SUM(K13:N13) -> -23467 | X13: =SUM(L13:O13) -> -23339 | Y13: =SUM(M13:P13) -> -22970 | Z13: =SUM(N13:Q13) -> -22043 | AA13: =SUM(O13:R13) -> -21806 | AB13: =SUM(P13:S13) -> -21189 | AD13: =SUM(AB13/X13)-1 -> -0.092120485
B14: Gross Profit | C14: =SUM(C11+C13) -> 6811 | D14: =SUM(D11+D13) -> 7571 | E14: =SUM(E11+E13) -> 13375 | F14: =SUM(F11+F13) -> 16795 | G14: =SUM(G11+G13) -> 16351 | I14: =SUM(I11+I13) -> 4015 | J14: =SUM(J11+J13) -> 3722 | K14: =SUM(K11+K13) -> 4670 | L14: =SUM(L11+L13) -> 4388 | M14: =SUM(M11+M13) -> 3900 | N14: =SUM(N11+N13) -> 3509 | O14: =SUM(O11+O13) -> 4442 | P14: =SUM(P11+P13) -> 4500 | ... S14: =SUM(S11+S13) -> 4481 | U14: =SUM(U11+U13) -> 16795 | V14: =SUM(V11+V13) -> 16680 | W14: =SUM(W11+W13) -> 16467 | X14: =SUM(X11+X13) -> 16239 | Y14: =SUM(Y11+Y13) -> 16351 | Z14: =SUM(Z11+Z13) -> 16299 | AA14: =SUM(AA11+AA13) -> 16635 | AB14: =SUM(AB11+AB13) -> 16674 | AD14: =SUM(AB14/X14)-1 -> 0.026787364
B15: Gross Margin (%) | C15: =C14/C11 -> 0.63827195 | D15: =D14/D11 -> 0.62103191 | E15: =E14/E11 -> 0.39551113 | F15: =F14/F11 -> 0.40645193 | G15: =G14/G11 -> 0.41583378 | I15: =I14/I11 -> 0.37523364 | J15: =J14/J11 -> 0.35933578 | K15: =K14/K11 -> 0.46798276 | L15: =L14/L11 -> 0.42668222 | M15: =M14/M11 -> 0.39164491 | N15: =N14/N11 -> 0.3612684 | O15: =O14/O11 -> 0.46160241 | P15: =P14/P11 -> 0.44878827 | ... S15: =S14/S11 -> 0.49541183 | U15: =U14/U11 -> 0.40645193 | V15: =V14/V11 -> 0.41105005 | W15: =W14/W11 -> 0.41235539 | X15: =X14/X11 -> 0.4103037 | Y15: =Y14/Y11 -> 0.41583378 | Z15: =Z14/Z11 -> 0.4250952 | AA15: =AA14/AA11 -> 0.43274108 | AB15: =AB14/AB11 -> 0.44037715 | AD15: =SUM(AB15-X15)*1000 -> 30.073445
B17: Selling, general and administrative | C17: -2722 | D17: -4016 | E17: -9678 | F17: -9696 | G17: -9296 | I17: -2388 | J17: -2562 | K17: -2291 | L17: =SUM(F17-SUM(I17:K17)) -> -2455 | M17: -2232 | N17: -2461 | O17: -2385 | P17: =SUM(G17-SUM(M17:O17)) -> -2218 | Q17: -2194 | R17: -2477 | S17: -2361 | U17: =SUM(I17:L17) -> -9696 | V17: =SUM(J17:M17) -> -9540 | W17: =SUM(K17:N17) -> -9439 | X17: =SUM(L17:O17) -> -9533 | Y17: =SUM(M17:P17) -> -9296 | Z17: =SUM(N17:Q17) -> -9258 | AA17: =SUM(O17:R17) -> -9274 | AB17: =SUM(P17:S17) -> -9250 | AD17: =SUM(AB17/X17)-1 -> -0.029686353
B18: Depreciation and amortization | C18: -1359 | D18: -1582 | E18: -7193 | F18: -7985 | G18: -7037 | I18: -2058 | J18: -1914 | K18: -1989 | L18: =SUM(F18-SUM(I18:K18)) -> -2024 | M18: -1888 | N18: -1744 | O18: -1762 | P18: =SUM(G18-SUM(M18:O18)) -> -1643 | Q18: -1547 | R18: -1447 | S18: -1375 | U18: =SUM(I18:L18) -> -7985 | V18: =SUM(J18:M18) -> -7815 | W18: =SUM(K18:N18) -> -7645 | X18: =SUM(L18:O18) -> -7418 | Y18: =SUM(M18:P18) -> -7037 | Z18: =SUM(N18:Q18) -> -6696 | AA18: =SUM(O18:R18) -> -6399 | AB18: =SUM(P18:S18) -> -6012 | AD18: =SUM(AB18/X18)-1 -> -0.18953896
B19: Restructuring and other charges | C19: -91 | D19: -32 | E19: -3757 | F19: -585 | G19: -447 | I19: -95 | J19: -146 | K19: -269 | L19: =SUM(F19-SUM(I19:K19)) -> -75 | M19: -35 | N19: -117 | O19: -9 | P19: =SUM(G19-SUM(M19:O19)) -> -286 | Q19: -54 | R19: -80 | S19: -88 | U19: =SUM(I19:L19) -> -585 | V19: =SUM(J19:M19) -> -525 | W19: =SUM(K19:N19) -> -496 | X19: =SUM(L19:O19) -> -236 | Y19: =SUM(M19:P19) -> -447 | Z19: =SUM(N19:Q19) -> -466 | AA19: =SUM(O19:R19) -> -429 | AB19: =SUM(P19:S19) -> -508 | AD19: =SUM(AB19/X19)-1 -> 1.1525424
B20: Impairments and loss on dispositions | C20: -124 | D20: 71 | E20: -117 | F20: -77 | G20: -9603 | I20: -31 | J20: -6 | K20: -24 | L20: =SUM(F20-SUM(I20:K20)) -> -16 | M20: -12 | N20: -9395 | O20: -5 | P20: =SUM(G20-SUM(M20:O20)) -> -191 | Q20: -90 | R20: -26 | S20: -46 | U20: =SUM(I20:L20) -> -77 | V20: =SUM(J20:M20) -> -58 | W20: =SUM(K20:N20) -> -9447 | X20: =SUM(L20:O20) -> -9428 | Y20: =SUM(M20:P20) -> -9603 | Z20: =SUM(N20:Q20) -> -9681 | AA20: =SUM(O20:R20) -> -312 | AB20: =SUM(P20:S20) -> -353 | AD20: =SUM(AB20/X20)-1 -> -0.96255834
B21: Operating Profit | C21: =+SUM(C14+SUM(C17:C20)) -> 2515 | D21: =+SUM(D14+SUM(D17:D20)) -> 2012 | E21: =+SUM(E14+SUM(E17:E20)) -> -7370 | F21: =+SUM(F14+SUM(F17:F20)) -> -1548 | G21: =+SUM(G14+SUM(G17:G20)) -> -10032 | I21: =+SUM(I14+SUM(I17:I20)) -> -557 | J21: =+SUM(J14+SUM(J17:J20)) -> -906 | K21: =+SUM(K14+SUM(K17:K20)) -> 97 | L21: =+SUM(L14+SUM(L17:L20)) -> -182 | M21: =+SUM(M14+SUM(M17:M20)) -> -267 | N21: =+SUM(N14+SUM(N17:N20)) -> -10208 | O21: =+SUM(O14+SUM(O17:O20)) -> 281 | P21: =+SUM(P14+SUM(P17:P20)) -> 162 | ... S21: =+SUM(S14+SUM(S17:S20)) -> 611 | U21: =+SUM(U14+SUM(U17:U20)) -> -1548 | V21: =+SUM(V14+SUM(V17:V20)) -> -1258 | W21: =+SUM(W14+SUM(W17:W20)) -> -10560 | X21: =+SUM(X14+SUM(X17:X20)) -> -10376 | Y21: =+SUM(Y14+SUM(Y17:Y20)) -> -10032 | Z21: =+SUM(Z14+SUM(Z17:Z20)) -> -9802 | AA21: =+SUM(AA14+SUM(AA17:AA20)) -> 221 | AB21: =+SUM(AB14+SUM(AB17:AB20)) -> 551 | AD21: =SUM(AB21/X21)-1 -> -1.0531033
B22: Operating Margin (%) | C22: =C21/C11 -> 0.2356855 | D22: =D21/D11 -> 0.16503978 | E22: =E21/E11 -> -0.21793772 | F22: =F21/F11 -> -0.037462791 | G22: =G21/G11 -> -0.25513085 | I22: =I21/I11 -> -0.052056075 | J22: =J21/J11 -> -0.087468623 | K22: =K21/K11 -> 0.0097204129 | L22: =L21/L11 -> -0.017697394 | M22: =M21/M11 -> -0.026812613 | N22: =N21/N11 -> -1.0509626 | O22: =O21/O11 -> 0.029200873 | P22: =P21/P11 -> 0.016156378 | ... S22: =S21/S11 -> 0.067551133 | U22: =U21/U11 -> -0.037462791 | V22: =V21/V11 -> -0.031001257 | W22: =W21/W11 -> -0.26443632 | X22: =X21/X11 -> -0.26216585 | Y22: =Y21/Y11 -> -0.25513085 | Z22: =Z21/Z11 -> -0.25564655 | AA22: =AA21/AA11 -> 0.00574907 | AB22: =AB21/AB11 -> 0.014552465 | AD22: =SUM(AB22-X22)*1000 -> 276.71832
B24: Interest expense, net | C24: -648 | D24: -633 | E24: -1777 | F24: -2221 | G24: -2017 | I24: -571 | J24: -574 | K24: -574 | L24: =SUM(F24-SUM(I24:K24)) -> -502 | M24: -515 | N24: -518 | O24: -494 | P24: =SUM(G24-SUM(M24:O24)) -> -490 | Q24: -468 | R24: -463 | S24: -570 | U24: =SUM(I24:L24) -> -2221 | V24: =SUM(J24:M24) -> -2165 | W24: =SUM(K24:N24) -> -2109 | X24: =SUM(L24:O24) -> -2029 | Y24: =SUM(M24:P24) -> -2017 | Z24: =SUM(N24:Q24) -> -1970 | AA24: =SUM(O24:R24) -> -1915 | AB24: =SUM(P24:S24) -> -1991 | AD24: =SUM(AB24/X24)-1 -> -0.018728438
B25: Gain on extinguishment of debt | C25: 0 | D25: 0 | E25: 0 | F25: 17 | G25: 632 | I25: 0 | J25: -5 | K25: 22 | L25: =SUM(F25-SUM(I25:K25)) -> 0 | M25: 0 | N25: 542 | O25: 23 | P25: =SUM(G25-SUM(M25:O25)) -> 67 | Q25: -4 | R25: 2958 | S25: -1 | U25: =SUM(I25:L25) -> 17 | V25: =SUM(J25:M25) -> 17 | W25: =SUM(K25:N25) -> 564 | X25: =SUM(L25:O25) -> 565 | Y25: =SUM(M25:P25) -> 632 | Z25: =SUM(N25:Q25) -> 628 | AA25: =SUM(O25:R25) -> 3044 | AB25: =SUM(P25:S25) -> 3020 | AD25: =SUM(AB25/X25)-1 -> 4.3451327
B26: Loss from equity investees, net | C26: -105 | D26: -18 | E26: -160 | F26: -82 | G26: -121 | I26: -37 | J26: -22 | K26: -14 | L26: =SUM(F26-SUM(I26:K26)) -> -9 | M26: -48 | N26: -23 | O26: -18 | P26: =SUM(G26-SUM(M26:O26)) -> -32 | Q26: -7 | R26: 5 | S26: 17 | U26: =SUM(I26:L26) -> -82 | V26: =SUM(J26:M26) -> -93 | W26: =SUM(K26:N26) -> -94 | X26: =SUM(L26:O26) -> -98 | Y26: =SUM(M26:P26) -> -121 | Z26: =SUM(N26:Q26) -> -80 | AA26: =SUM(O26:R26) -> -52 | AB26: =SUM(P26:S26) -> -17 | AD26: =SUM(AB26/X26)-1 -> -0.82653061
B27: Other income (expense), net | C27: -34 | D27: 72 | E27: 347 | F27: -29 | G27: 150 | I27: -73 | J27: 27 | K27: -63 | L27: =SUM(F27-SUM(I27:K27)) -> 80 | M27: 11 | N27: 172 | O27: 30 | P27: =SUM(G27-SUM(M27:O27)) -> -63 | Q27: 82 | R27: 139 | S27: -30 | U27: =SUM(I27:L27) -> -29 | V27: =SUM(J27:M27) -> 55 | W27: =SUM(K27:N27) -> 200 | X27: =SUM(L27:O27) -> 293 | Y27: =SUM(M27:P27) -> 150 | Z27: =SUM(N27:Q27) -> 221 | AA27: =SUM(O27:R27) -> 188 | AB27: =SUM(P27:S27) -> 128 | AD27: =SUM(AB27/X27)-1 -> -0.56313993
B28: Loss before income taxes | C28: =SUM(C24:C27)+C21 -> 1728 | D28: =SUM(D24:D27)+D21 -> 1433 | E28: =SUM(E24:E27)+E21 -> -8960 | F28: =SUM(F24:F27)+F21 -> -3863 | G28: =SUM(G24:G27)+G21 -> -11388 | I28: =SUM(I24:I27)+I21 -> -1238 | J28: =SUM(J24:J27)+J21 -> -1480 | K28: =SUM(K24:K27)+K21 -> -532 | L28: =SUM(L24:L27)+L21 -> -613 | M28: =SUM(M24:M27)+M21 -> -819 | N28: =SUM(N24:N27)+N21 -> -10035 | O28: =SUM(O24:O27)+O21 -> -178 | P28: =SUM(P24:P27)+P21 -> -356 | ... S28: =SUM(S24:S27)+S21 -> 27 | U28: =SUM(U24:U27)+U21 -> -3863 | V28: =SUM(V24:V27)+V21 -> -3444 | W28: =SUM(W24:W27)+W21 -> -11999 | X28: =SUM(X24:X27)+X21 -> -11645 | Y28: =SUM(Y24:Y27)+Y21 -> -11388 | Z28: =SUM(Z24:Z27)+Z21 -> -11003 | AA28: =SUM(AA24:AA27)+AA21 -> 1486 | AB28: =SUM(AB24:AB27)+AB21 -> 1691 | AD28: =SUM(AB28/X28)-1 -> -1.1452125
B29: EBT Margin (%) | C29: =C28/C11 -> 0.16193421 | D29: =D28/D11 -> 0.11754573 | E29: =E28/E11 -> -0.2649555 | F29: =F28/F11 -> -0.093487573 | G29: =G28/G11 -> -0.28961624 | I29: =I28/I11 -> -0.11570093 | J29: =J28/J11 -> -0.14288473 | K29: =K28/K11 -> -0.053311955 | L29: =L28/L11 -> -0.059607157 | M29: =M28/M11 -> -0.082245431 | N29: =N28/N11 -> -1.0331514 | O29: =O28/O11 -> -0.01849735 | P29: =P28/P11 -> -0.035504139 | ... S29: =S28/S11 -> 0.0029850746 | U29: =U28/U11 -> -0.093487573 | V29: =V28/V11 -> -0.084871485 | W29: =W28/W11 -> -0.30047078 | X29: =X28/X11 -> -0.29422912 | Y29: =Y28/Y11 -> -0.28961624 | Z29: =Z28/Z11 -> -0.2869699 | AA29: =AA28/AA11 -> 0.038656643 | AB29: =AB28/AB11 -> 0.044661015 | AD29: =SUM(AB29-X29)*1000 -> 338.89013
B31: Income tax expense | C31: -373 | D31: -236 | E31: 1663 | F31: 784 | G31: -94 | I31: 178 | J31: 260 | K31: 125 | L31: =SUM(F31-SUM(I31:K31)) -> 221 | M31: -136 | N31: 7 | O31: 319 | P31: =SUM(G31-SUM(M31:O31)) -> -284 | Q31: -15 | R31: -866 | S31: -170 | U31: =SUM(I31:L31) -> 784 | V31: =SUM(J31:M31) -> 470 | W31: =SUM(K31:N31) -> 217 | X31: =SUM(L31:O31) -> 411 | Y31: =SUM(M31:P31) -> -94 | Z31: =SUM(N31:Q31) -> 27 | AA31: =SUM(O31:R31) -> -846 | AB31: =SUM(P31:S31) -> -1335 | AD31: =SUM(AB31/X31)-1 -> -4.2481752
B32: Net Income | C32: =SUM(C28+SUM(C31:C31)) -> 1355 | D32: =SUM(D28+SUM(D31:D31)) -> 1197 | E32: =SUM(E28+SUM(E31:E31)) -> -7297 | F32: =SUM(F28+SUM(F31:F31)) -> -3079 | G32: =SUM(G28+SUM(G31:G31)) -> -11482 | I32: =SUM(I28+SUM(I31:I31)) -> -1060 | J32: =SUM(J28+SUM(J31:J31)) -> -1220 | K32: =SUM(K28+SUM(K31:K31)) -> -407 | L32: =SUM(L28+SUM(L31:L31)) -> -392 | M32: =SUM(M28+SUM(M31:M31)) -> -955 | N32: =SUM(N28+SUM(N31:N31)) -> -10028 | O32: =SUM(O28+SUM(O31:O31)) -> 141 | P32: =SUM(P28+SUM(P31:P31)) -> -640 | ... S32: =SUM(S28+SUM(S31:S31)) -> -143 | U32: =SUM(U24+SUM(U31:U31)) -> -1437 | V32: =SUM(V24+SUM(V31:V31)) -> -1695 | W32: =SUM(W24+SUM(W31:W31)) -> -1892 | X32: =SUM(X24+SUM(X31:X31)) -> -1618 | Y32: =SUM(Y24+SUM(Y31:Y31)) -> -2111 | Z32: =SUM(Z24+SUM(Z31:Z31)) -> -1943 | AA32: =SUM(AA24+SUM(AA31:AA31)) -> -2761 | AB32: =SUM(AB24+SUM(AB31:AB31)) -> -3326 | AD32: =SUM(AB32/X32)-1 -> 1.0556242
B34: Net loss (income) attributable to noncontrolling interests | C34: -124 | D34: -138 | E34: -68 | F34: -38 | G34: 129 | I34: -8 | J34: -16 | K34: -8 | L34: =SUM(F34-SUM(I34:K34)) -> -6 | M34: -7 | N34: -10 | O34: -3 | P34: =SUM(G34-SUM(M34:O34)) -> 149 | Q34: -8 | R34: -7 | S34: -4 | U34: =SUM(I34:L34) -> -38 | V34: =SUM(J34:M34) -> -37 | W34: =SUM(K34:N34) -> -31 | X34: =SUM(L34:O34) -> -26 | Y34: =SUM(M34:P34) -> 129 | Z34: =SUM(N34:Q34) -> 128 | AA34: =SUM(O34:R34) -> 131 | AB34: =SUM(P34:S34) -> 130 | AD34: =SUM(AB34/X34)-1 -> -6
B35: Net loss (income) attributable to redeemable noncontrolling interests | C35: -12 | D35: -53 | E35: -6 | F35: -9 | G35: 42 | I35: -1 | J35: -4 | K35: -2 | L35: =SUM(F35-SUM(I35:K35)) -> -2 | M35: -4 | N35: 52 | O35: -3 | P35: =SUM(G35-SUM(M35:O35)) -> -3 | Q35: 4 | R35: -1 | S35: -1 | U35: =SUM(I35:L35) -> -9 | V35: =SUM(J35:M35) -> -12 | W35: =SUM(K35:N35) -> 44 | X35: =SUM(L35:O35) -> 43 | Y35: =SUM(M35:P35) -> 42 | Z35: =SUM(N35:Q35) -> 50 | AA35: =SUM(O35:R35) -> -3 | AB35: =SUM(P35:S35) -> -1
B36: Net loss available to Warner Bros. Discovery, Inc. | C36: =SUM(C32)+SUM(C34:C35) -> 1219 | D36: =SUM(D32)+SUM(D34:D35) -> 1006 | E36: =SUM(E32)+SUM(E34:E35) -> -7371 | F36: =SUM(F32)+SUM(F34:F35) -> -3126 | G36: =SUM(G32)+SUM(G34:G35) -> -11311 | I36: =SUM(I32)+SUM(I34:I35) -> -1069 | J36: =SUM(J32)+SUM(J34:J35) -> -1240 | K36: =SUM(K32)+SUM(K34:K35) -> -417 | L36: =SUM(L32)+SUM(L34:L35) -> -400 | M36: =SUM(M32)+SUM(M34:M35) -> -966 | N36: =SUM(N32)+SUM(N34:N35) -> -9986 | O36: =SUM(O32)+SUM(O34:O35) -> 135 | P36: =SUM(P32)+SUM(P34:P35) -> -494 | ... S36: =SUM(S32)+SUM(S34:S35) -> -148 | U36: =SUM(U32)+SUM(U34:U35) -> -1484 | V36: =SUM(V32)+SUM(V34:V35) -> -1744 | W36: =SUM(W32)+SUM(W34:W35) -> -1879 | X36: =SUM(X32)+SUM(X34:X35) -> -1601 | Y36: =SUM(Y32)+SUM(Y34:Y35) -> -1940 | Z36: =SUM(Z32)+SUM(Z34:Z35) -> -1765 | AA36: =SUM(AA32)+SUM(AA34:AA35) -> -2633 | AB36: =SUM(AB32)+SUM(AB34:AB35) -> -3197 | AD36: =SUM(AB36/X36)-1 -> 0.99687695
B38: Basic shares | C38: 599 | D38: 588 | E38: 1940 | F38: 2436 | G38: 2450 | I38: 2432 | J38: 2437 | K38: 2438 | L38: =F38 -> 2436 | M38: 2443 | N38: 2451 | O38: 2453 | P38: =G38 -> 2450 | Q38: 2462 | R38: 2477 | S38: 2479 | U38: =L38 -> 2436 | V38: =M38 -> 2443 | W38: =N38 -> 2451 | X38: =O38 -> 2453 | Y38: =P38 -> 2450 | Z38: =Q38 -> 2462 | AA38: =R38 -> 2477 | AB38: =S38 -> 2479 | AD38: =SUM(AB38/X38)-1 -> 0.010599266
B39: Basic EPS | C39: =C36/C38 -> 2.0350584 | D39: =D36/D38 -> 1.7108844 | E39: =E36/E38 -> -3.7994845 | F39: =F36/F38 -> -1.2832512 | G39: =G36/G38 -> -4.6167347 | I39: =I36/I38 -> -0.43955592 | J39: =J36/J38 -> -0.50882232 | K39: =K36/K38 -> -0.17104184 | L39: =L36/L38 -> -0.16420361 | M39: =M36/M38 -> -0.39541547 | N39: =N36/N38 -> -4.0742554 | O39: =O36/O38 -> 0.055034651 | P39: =P36/P38 -> -0.20163265 | ... S39: =S36/S38 -> -0.059701493 | U39: =U36/U38 -> -0.6091954 | V39: =V36/V38 -> -0.71387638 | W39: =W36/W38 -> -0.76662587 | X39: =X36/X38 -> -0.6526702 | Y39: =Y36/Y38 -> -0.79183673 | Z39: =Z36/Z38 -> -0.71689683 | AA39: =AA36/AA38 -> -1.0629794 | AB39: =AB36/AB38 -> -1.2896329 | AD39: =SUM(AB39/X39)-1 -> 0.97593351
B41: Fully Diluted Shares | C41: 672 | D41: 664 | E41: 1940 | F41: 2436 | G41: 2450 | I41: 2432 | J41: 2437 | K41: 2438 | L41: =F41 -> 2436 | M41: 2443 | N41: 2451 | O41: 2470 | P41: =G41 -> 2450 | Q41: 2462 | R41: 2499 | S41: 2479 | U41: =L41 -> 2436 | V41: =M41 -> 2443 | W41: =N41 -> 2451 | X41: =O41 -> 2470 | Y41: =P41 -> 2450 | Z41: =Q41 -> 2462 | AA41: =R41 -> 2499 | AB41: =S41 -> 2479 | AD41: =SUM(AB41/X41)-1 -> 0.0036437247
B42: Diluted EPS | C42: =C36/C41 -> 1.8139881 | D42: =D36/D41 -> 1.5150602 | E42: =E36/E41 -> -3.7994845 | F42: =F36/F41 -> -1.2832512 | G42: =G36/G41 -> -4.6167347 | I42: =I36/I41 -> -0.43955592 | J42: =J36/J41 -> -0.50882232 | K42: =K36/K41 -> -0.17104184 | L42: =L36/L41 -> -0.16420361 | M42: =M36/M41 -> -0.39541547 | N42: =N36/N41 -> -4.0742554 | O42: =O36/O41 -> 0.05465587 | P42: =P36/P41 -> -0.20163265 | ... S42: =S36/S41 -> -0.059701493 | U42: =U36/U41 -> -0.6091954 | V42: =V36/V41 -> -0.71387638 | W42: =W36/W41 -> -0.76662587 | X42: =X36/X41 -> -0.64817814 | Y42: =Y36/Y41 -> -0.79183673 | Z42: =Z36/Z41 -> -0.71689683 | AA42: =AA36/AA41 -> -1.0536214 | AB42: =AB36/AB41 -> -1.2896329 | AD42: =SUM(AB42/X42)-1 -> 0.9896273
A44: X | B44: Balance Sheet | C44: FYE | D44: FYE | O44: Quarterly | X44: LTM | AD44: Variance
B45: =B7 -> Fiscal Period | C45: =C7 -> 2020 | D45: =D7 -> 2021 | E45: =E7 -> 2022 | F45: =F7 -> 2023 | G45: =G7 -> 2024 | I45: =I7 -> 1Q23 | J45: =J7 -> 2Q23 | K45: =K7 -> 3Q23 | L45: =L7 -> 4Q23 | M45: =M7 -> 1Q24 | N45: =N7 -> 2Q24 | O45: =O7 -> 3Q24 | P45: =P7 -> 4Q24 | ... S45: =S7 -> 3Q25 | U45: =U7 -> 4Q23 | V45: =V7 -> 1Q24 | W45: =W7 -> 2Q24 | X45: =X7 -> 3Q24 | Y45: =Y7 -> 4Q24 | Z45: =Z7 -> 1Q25 | AA45: =AA7 -> 2Q25 | AB45: =AB7 -> 3Q25
B46: =B8 -> Fiscal Period End Date | C46: =C8 -> 44196 | D46: =D8 -> 44561 | E46: =E8 -> 44926 | F46: =F8 -> 45291 | G46: =G8 -> 45657 | I46: =I8 -> 45016 | J46: =J8 -> 45107 | K46: =K8 -> 45199 | L46: =L8 -> 44926 | M46: =M8 -> 45382 | N46: =N8 -> 45473 | O46: =O8 -> 45565 | P46: =P8 -> 45291 | ... S46: =S8 -> 45930 | U46: =U8 -> 44926 | V46: =V8 -> 45382 | W46: =W8 -> 45473 | X46: =X8 -> 45565 | Y46: =Y8 -> 45291 | Z46: =Z8 -> 45747 | AA46: =AA8 -> 45838 | AB46: =AB8 -> 45930
B48: Current Assets
B49: Cash and cash equivalents | C49: 2091 | D49: 3905 | E49: 3731 | F49: 3780 | G49: 5312 | I49: 2594 | J49: 3027 | K49: 2383 | L49: =F49 -> 3780 | M49: 2976 | N49: 3613 | O49: 3336 | P49: =G49 -> 5312 | Q49: 3868 | R49: 4888 | S49: 4294 | U49: =L49 -> 3780 | V49: =M49 -> 2976 | W49: =N49 -> 3613 | X49: =O49 -> 3336 | Y49: =P49 -> 5312 | Z49: =Q49 -> 3868 | AA49: =R49 -> 4888 | AB49: =S49 -> 4294 | AD49: =SUM(AB49/X49)-1 -> 0.28717026
B50: Receivables, net | C50: 2537 | D50: 2446 | E50: 6380 | F50: 6047 | G50: 4947 | I50: 6833 | J50: 6770 | K50: 6312 | L50: =F50 -> 6047 | M50: 6303 | N50: 6166 | O50: 5534 | P50: =G50 -> 4947 | Q50: 4664 | R50: 5383 | S50: 5128 | U50: =L50 -> 6047 | V50: =M50 -> 6303 | W50: =N50 -> 6166 | X50: =O50 -> 5534 | Y50: =P50 -> 4947 | Z50: =Q50 -> 4664 | AA50: =R50 -> 5383 | AB50: =S50 -> 5128 | AD50: =SUM(AB50/X50)-1 -> -0.073364655
B51: Prepaid expenses and other current assets | C51: =970+532 -> 1502 | D51: 913 | E51: 3888 | F51: 4391 | G51: 3819 | I51: 4300 | J51: 3976 | K51: 4136 | L51: =F51 -> 4391 | M51: 4623 | N51: 3651 | O51: 3635 | P51: =G51 -> 3819 | Q51: 4250 | R51: 3340 | S51: 3640 | U51: =L51 -> 4391 | V51: =M51 -> 4623 | W51: =N51 -> 3651 | X51: =O51 -> 3635 | Y51: =P51 -> 3819 | Z51: =Q51 -> 4250 | AA51: =R51 -> 3340 | AB51: =S51 -> 3640 | AD51: =SUM(AB51/X51)-1 -> 0.0013755158
B52: Total Current Assets | C52: =SUM(C49:C51) -> 6130 | D52: =SUM(D49:D51) -> 7264 | E52: =SUM(E49:E51) -> 13999 | F52: =SUM(F49:F51) -> 14218 | G52: =SUM(G49:G51) -> 14078 | I52: =SUM(I49:I51) -> 13727 | J52: =SUM(J49:J51) -> 13773 | K52: =SUM(K49:K51) -> 12831 | L52: =SUM(L49:L51) -> 14218 | M52: =SUM(M49:M51) -> 13902 | N52: =SUM(N49:N51) -> 13430 | O52: =SUM(O49:O51) -> 12505 | P52: =SUM(P49:P51) -> 14078 | ... S52: =SUM(S49:S51) -> 13062 | U52: =SUM(U49:U51) -> 14218 | V52: =SUM(V49:V51) -> 13902 | W52: =SUM(W49:W51) -> 13430 | X52: =SUM(X49:X51) -> 12505 | Y52: =SUM(Y49:Y51) -> 14078 | Z52: =SUM(Z49:Z51) -> 12782 | AA52: =SUM(AA49:AA51) -> 13611 | AB52: =SUM(AB49:AB51) -> 13062 | AD52: =SUM(AB52/X52)-1 -> 0.044542183
B54: Non-Current Assets
B55: Film and television content rights and games | C55: 3439 | D55: 3832 | E55: 26652 | F55: 21229 | G55: 19102 | I55: 25473 | J55: 24393 | K55: 22454 | L55: =F55 -> 21229 | M55: 20439 | N55: 20010 | O55: 20039 | P55: =G55 -> 19102 | Q55: 18821 | R55: 18817 | S55: 19104 | U55: =L55 -> 21229 | V55: =M55 -> 20439 | W55: =N55 -> 20010 | X55: =O55 -> 20039 | Y55: =P55 -> 19102 | Z55: =Q55 -> 18821 | AA55: =R55 -> 18817 | AB55: =S55 -> 19104 | AD55: =SUM(AB55/X55)-1 -> -0.046659015
B56: Property and equipment, net | C56: 1206 | D56: 1336 | E56: 5301 | F56: 5957 | G56: 6087 | I56: 5325 | J56: 5473 | K56: 5810 | L56: =F56 -> 5957 | M56: 5937 | N56: 6043 | O56: 6158 | P56: =G56 -> 6087 | Q56: 6211 | R56: 6413 | S56: 6517 | U56: =L56 -> 5957 | V56: =M56 -> 5937 | W56: =N56 -> 6043 | X56: =O56 -> 6158 | Y56: =P56 -> 6087 | Z56: =Q56 -> 6211 | AA56: =R56 -> 6413 | AB56: =S56 -> 6517 | AD56: =SUM(AB56/X56)-1 -> 0.058298149
B57: Goodwill | C57: 13070 | D57: 12912 | E57: 34438 | F57: 34969 | G57: 25667 | I57: 34658 | J57: 34911 | K57: 34727 | L57: =F57 -> 34969 | M57: 34891 | N57: 25740 | O57: 25869 | P57: =G57 -> 25667 | Q57: 25746 | R57: 25939 | S57: 25920 | U57: =L57 -> 34969 | V57: =M57 -> 34891 | W57: =N57 -> 25740 | X57: =O57 -> 25869 | Y57: =P57 -> 25667 | Z57: =Q57 -> 25746 | AA57: =R57 -> 25939 | AB57: =S57 -> 25920 | AD57: =SUM(AB57/X57)-1 -> 0.0019714716
B58: Intangible assets, net | C58: 7640 | D58: 6317 | E58: 44982 | F58: 38285 | G58: 32299 | I58: 43239 | J58: 41584 | K58: 39874 | L58: =F58 -> 38285 | M58: 36648 | N58: 35157 | O58: 33767 | P58: =G58 -> 32299 | Q58: 31033 | R58: 29906 | S58: 28789 | U58: =L58 -> 38285 | V58: =M58 -> 36648 | W58: =N58 -> 35157 | X58: =O58 -> 33767 | Y58: =P58 -> 32299 | Z58: =Q58 -> 31033 | AA58: =R58 -> 29906 | AB58: =S58 -> 28789 | AD58: =SUM(AB58/X58)-1 -> -0.14742204
B59: Other noncurrent assets | C59: =2095+507 -> 2602 | D59: 2766 | E59: 8629 | F59: 8099 | G59: 7327 | I59: 8162 | J59: 8484 | K59: 8053 | L59: =F59 -> 8099 | M59: 8002 | N59: 7649 | O59: 7995 | P59: =G59 -> 7327 | Q59: 7086 | R59: 7041 | S59: 7127 | U59: =L59 -> 8099 | V59: =M59 -> 8002 | W59: =N59 -> 7649 | X59: =O59 -> 7995 | Y59: =P59 -> 7327 | Z59: =Q59 -> 7086 | AA59: =R59 -> 7041 | AB59: =S59 -> 7127 | AD59: =SUM(AB59/X59)-1 -> -0.10856785
B60: Total Assets | C60: =SUM(C55:C59)+C52 -> 34087 | D60: =SUM(D55:D59)+D52 -> 34427 | E60: =SUM(E55:E59)+E52 -> 134001 | F60: =SUM(F55:F59)+F52 -> 122757 | G60: =SUM(G55:G59)+G52 -> 104560 | I60: =SUM(I55:I59)+I52 -> 130584 | J60: =SUM(J55:J59)+J52 -> 128618 | K60: =SUM(K55:K59)+K52 -> 123749 | L60: =SUM(L55:L59)+L52 -> 122757 | M60: =SUM(M55:M59)+M52 -> 119819 | N60: =SUM(N55:N59)+N52 -> 108029 | O60: =SUM(O55:O59)+O52 -> 106333 | P60: =SUM(P55:P59)+P52 -> 104560 | ... S60: =SUM(S55:S59)+S52 -> 100519 | U60: =SUM(U55:U59)+U52 -> 122757 | V60: =SUM(V55:V59)+V52 -> 119819 | W60: =SUM(W55:W59)+W52 -> 108029 | X60: =SUM(X55:X59)+X52 -> 106333 | Y60: =SUM(Y55:Y59)+Y52 -> 104560 | Z60: =SUM(Z55:Z59)+Z52 -> 101679 | AA60: =SUM(AA55:AA59)+AA52 -> 101727 | AB60: =SUM(AB55:AB59)+AB52 -> 100519 | AD60: =SUM(AB60/X60)-1 -> -0.054677287
B62: Current Liabilities
B63: Accounts payable | C63: 397 | D63: 412 | E63: 1454 | F63: 1260 | G63: 1055 | I63: 1123 | J63: 1689 | K63: 1329 | L63: =F63 -> 1260 | M63: 1245 | N63: 1151 | O63: 1120 | P63: =G63 -> 1055 | Q63: 1008 | R63: 1074 | S63: 1083 | U63: =L63 -> 1260 | V63: =M63 -> 1245 | W63: =N63 -> 1151 | X63: =O63 -> 1120 | Y63: =P63 -> 1055 | Z63: =Q63 -> 1008 | AA63: =R63 -> 1074 | AB63: =S63 -> 1083 | AD63: =SUM(AB63/X63)-1 -> -0.033035714
B64: Accrued liabilities | C64: 1793 | D64: 2230 | E64: 11504 | F64: 10368 | G64: 10438 | I64: 10158 | J64: 10668 | K64: 10040 | L64: =F64 -> 10368 | M64: 10288 | N64: 10926 | O64: 10002 | P64: =G64 -> 10438 | Q64: 9899 | R64: 10218 | S64: 9292 | U64: =L64 -> 10368 | V64: =M64 -> 10288 | W64: =N64 -> 10926 | X64: =O64 -> 10002 | Y64: =P64 -> 10438 | Z64: =Q64 -> 9899 | AA64: =R64 -> 10218 | AB64: =S64 -> 9292 | AD64: =SUM(AB64/X64)-1 -> -0.070985803
B65: Deferred revenues | C65: 557 | D65: 478 | E65: 1694 | F65: 1924 | G65: 1569 | I65: 1603 | J65: 1548 | K65: 1917 | L65: =F65 -> 1924 | M65: 1993 | N65: 2022 | O65: 1530 | P65: =G65 -> 1569 | Q65: 1600 | R65: 1527 | S65: 1649 | U65: =L65 -> 1924 | V65: =M65 -> 1993 | W65: =N65 -> 2022 | X65: =O65 -> 1530 | Y65: =P65 -> 1569 | Z65: =Q65 -> 1600 | AA65: =R65 -> 1527 | AB65: =S65 -> 1649 | AD65: =SUM(AB65/X65)-1 -> 0.077777778
B66: Current portion of debt | C66: 335 | D66: 339 | E66: 365 | F66: 1780 | G66: 2748 | I66: 3496 | J66: 3001 | K66: 1302 | L66: =F66 -> 1780 | M66: 3430 | N66: 3669 | O66: 3043 | P66: =G66 -> 2748 | Q66: 2779 | R66: 221 | S66: 139 | U66: =L66 -> 1780 | V66: =M66 -> 3430 | W66: =N66 -> 3669 | X66: =O66 -> 3043 | Y66: =P66 -> 2748 | Z66: =Q66 -> 2779 | AA66: =R66 -> 221 | AB66: =S66 -> 139 | AD66: =SUM(AB66/X66)-1 -> -0.95432139
B67: Total Current Liabilities | C67: =SUM(C63:C66) -> 3082 | D67: =SUM(D63:D66) -> 3459 | E67: =SUM(E63:E66) -> 15017 | F67: =SUM(F63:F66) -> 15332 | G67: =SUM(G63:G66) -> 15810 | I67: =SUM(I63:I66) -> 16380 | J67: =SUM(J63:J66) -> 16906 | K67: =SUM(K63:K66) -> 14588 | L67: =SUM(L63:L66) -> 15332 | M67: =SUM(M63:M66) -> 16956 | N67: =SUM(N63:N66) -> 17768 | O67: =SUM(O63:O66) -> 15695 | P67: =SUM(P63:P66) -> 15810 | ... S67: =SUM(S63:S66) -> 12163 | U67: =SUM(U63:U66) -> 15332 | V67: =SUM(V63:V66) -> 16956 | W67: =SUM(W63:W66) -> 17768 | X67: =SUM(X63:X66) -> 15695 | Y67: =SUM(Y63:Y66) -> 15810 | Z67: =SUM(Z63:Z66) -> 15286 | AA67: =SUM(AA63:AA66) -> 13040 | AB67: =SUM(AB63:AB66) -> 12163 | AD67: =SUM(AB67/X67)-1 -> -0.22503982
B69: Non-Current Liabilities
B70: Noncurrent portion of debt | C70: 15069 | D70: 14420 | E70: 48634 | F70: 41889 | G70: 36757 | I70: 45434 | J70: 44276 | K70: 43498 | L70: =F70 -> 41889 | M70: 39148 | N70: 37289 | O70: 37166 | P70: =G70 -> 36757 | Q70: 34647 | R70: 34411 | S70: 33382 | U70: =L70 -> 41889 | V70: =M70 -> 39148 | W70: =N70 -> 37289 | X70: =O70 -> 37166 | Y70: =P70 -> 36757 | Z70: =Q70 -> 34647 | AA70: =R70 -> 34411 | AB70: =S70 -> 33382 | AD70: =SUM(AB70/X70)-1 -> -0.10181349
B71: Deferred income taxes | C71: 1534 | D71: 1225 | E71: 11014 | F71: 8736 | G71: 6985 | I71: 10211 | J71: 9718 | K71: 9098 | L71: =F71 -> 8736 | M71: 8303 | N71: 7806 | O71: 7339 | P71: =G71 -> 6985 | Q71: 6714 | R71: 6494 | S71: 6708 | U71: =L71 -> 8736 | V71: =M71 -> 8303 | W71: =N71 -> 7806 | X71: =O71 -> 7339 | Y71: =P71 -> 6985 | Z71: =Q71 -> 6714 | AA71: =R71 -> 6494 | AB71: =S71 -> 6708 | AD71: =SUM(AB71/X71)-1 -> -0.085979016
B72: Other noncurrent liabilities | C72: 2019 | D72: 1927 | E72: 10669 | F72: 10328 | G72: 10070 | I72: 10717 | J72: 10933 | K72: 10423 | L72: =F72 -> 10328 | M72: 10118 | N72: 9751 | O72: 9959 | P72: =G72 -> 10070 | Q72: 9861 | R72: 10436 | S72: 10961 | U72: =L72 -> 10328 | V72: =M72 -> 10118 | W72: =N72 -> 9751 | X72: =O72 -> 9959 | Y72: =P72 -> 10070 | Z72: =Q72 -> 9861 | AA72: =R72 -> 10436 | AB72: =S72 -> 10961 | AD72: =SUM(AB72/X72)-1 -> 0.10061251
B73: Total Liabilities | C73: =SUM(C70:C72)+C67 -> 21704 | D73: =SUM(D70:D72)+D67 -> 21031 | E73: =SUM(E70:E72)+E67 -> 85334 | F73: =SUM(F70:F72)+F67 -> 76285 | G73: =SUM(G70:G72)+G67 -> 69622 | I73: =SUM(I70:I72)+I67 -> 82742 | J73: =SUM(J70:J72)+J67 -> 81833 | K73: =SUM(K70:K72)+K67 -> 77607 | L73: =SUM(L70:L72)+L67 -> 76285 | M73: =SUM(M70:M72)+M67 -> 74525 | N73: =SUM(N70:N72)+N67 -> 72614 | O73: =SUM(O70:O72)+O67 -> 70159 | P73: =SUM(P70:P72)+P67 -> 69622 | ... S73: =SUM(S70:S72)+S67 -> 63214 | U73: =SUM(U70:U72)+U67 -> 76285 | V73: =SUM(V70:V72)+V67 -> 74525 | W73: =SUM(W70:W72)+W67 -> 72614 | X73: =SUM(X70:X72)+X67 -> 70159 | Y73: =SUM(Y70:Y72)+Y67 -> 69622 | Z73: =SUM(Z70:Z72)+Z67 -> 66508 | AA73: =SUM(AA70:AA72)+AA67 -> 64381 | AB73: =SUM(AB70:AB72)+AB67 -> 63214 | AD73: =SUM(AB73/X73)-1 -> -0.098989438
B75: Mezzanine equity
B76: Redeemable noncontrolling interests | C76: 383 | D76: 363 | E76: 318 | F76: 165 | G76: 109 | I76: 309 | J76: 306 | K76: 281 | L76: =F76 -> 165 | M76: 179 | N76: 118 | O76: 117 | P76: =G76 -> 109 | Q76: 23 | R76: 23 | S76: 23 | U76: =L76 -> 165 | V76: =M76 -> 179 | W76: =N76 -> 118 | X76: =O76 -> 117 | Y76: =P76 -> 109 | Z76: =Q76 -> 23 | AA76: =R76 -> 23 | AB76: =S76 -> 23
B77: Total Mezzanine equity | C77: =SUM(C76) -> 383 | D77: =SUM(D76) -> 363 | E77: =SUM(E76) -> 318 | F77: =SUM(F76) -> 165 | G77: =SUM(G76) -> 109 | I77: =SUM(I76) -> 309 | J77: =SUM(J76) -> 306 | K77: =SUM(K76) -> 281 | L77: =SUM(L76) -> 165 | M77: =SUM(M76) -> 179 | N77: =SUM(N76) -> 118 | O77: =SUM(O76) -> 117 | P77: =SUM(P76) -> 109 | ... S77: =SUM(S76) -> 23 | U77: =SUM(U76) -> 165 | V77: =SUM(V76) -> 179 | W77: =SUM(W76) -> 118 | X77: =SUM(X76) -> 117 | Y77: =SUM(Y76) -> 109 | Z77: =SUM(Z76) -> 23 | AA77: =SUM(AA76) -> 23 | AB77: =SUM(AB76) -> 23
B79: Shareholder Equity
B80: Common Stock | C80: 7 | D80: 7 | E80: 27 | F80: 27 | G80: 27 | I80: 27 | J80: 27 | K80: 27 | L80: =F80 -> 27 | M80: 27 | N80: 27 | O80: 27 | P80: =G80 -> 27 | Q80: 27 | R80: 27 | S80: 27 | U80: =L80 -> 27 | V80: =M80 -> 27 | W80: =N80 -> 27 | X80: =O80 -> 27 | Y80: =P80 -> 27 | Z80: =Q80 -> 27 | AA80: =R80 -> 27 | AB80: =S80 -> 27 | AD80: =SUM(AB80/X80)-1 -> 0
B81: Preferred Stock | C81: 0 | D81: 0 | E81: 0 | F81: 0 | G81: 0 | I81: 0 | J81: 0 | K81: 0 | L81: =F81 -> 0 | M81: 0 | N81: 0 | O81: 0 | P81: =G81 -> 0 | Q81: 0 | R81: 0 | S81: 0 | U81: =L81 -> 0 | V81: =M81 -> 0 | W81: =N81 -> 0 | X81: =O81 -> 0 | Y81: =P81 -> 0 | Z81: =Q81 -> 0 | AA81: =R81 -> 0 | AB81: =S81 -> 0 | AD81: =SUM(AB81/X81)-1 -> #DIV/0!
B82: Additional paid-in capital | C82: 10809 | D82: 11086 | E82: 54630 | F82: 55112 | G82: 55560 | I82: 54685 | J82: 54816 | K82: 54944 | L82: =F82 -> 55112 | M82: 55175 | N82: 55332 | O82: 55463 | P82: =G82 -> 55560 | Q82: 55585 | R82: 55749 | S82: 55926 | U82: =L82 -> 55112 | V82: =M82 -> 55175 | W82: =N82 -> 55332 | X82: =O82 -> 55463 | Y82: =P82 -> 55560 | Z82: =Q82 -> 55585 | AA82: =R82 -> 55749 | AB82: =S82 -> 55926 | AD82: =SUM(AB82/X82)-1 -> 0.0083479076
B83: Treasury stock | C83: -8244 | D83: -8244 | E83: -8244 | F83: -8244 | G83: -8244 | I83: -8244 | J83: -8244 | K83: -8244 | L83: =F83 -> -8244 | M83: -8244 | N83: -8244 | O83: -8244 | P83: =G83 -> -8244 | Q83: -8244 | R83: -8244 | S83: -8244 | U83: =L83 -> -8244 | V83: =M83 -> -8244 | W83: =N83 -> -8244 | X83: =O83 -> -8244 | Y83: =P83 -> -8244 | Z83: =Q83 -> -8244 | AA83: =R83 -> -8244 | AB83: =S83 -> -8244 | AD83: =SUM(AB83/X83)-1 -> 0
B84: Accumulated deficit | C84: 8543 | D84: 9580 | E84: 2205 | F84: -928 | G84: -12239 | I84: 1133 | J84: -105 | K84: -526 | L84: =F84 -> -928 | M84: -1894 | N84: -11880 | O84: -11745 | P84: =G84 -> -12239 | Q84: -12692 | R84: -11112 | S84: -11260 | U84: =L84 -> -928 | V84: =M84 -> -1894 | W84: =N84 -> -11880 | X84: =O84 -> -11745 | Y84: =P84 -> -12239 | Z84: =Q84 -> -12692 | AA84: =R84 -> -11112 | AB84: =S84 -> -11260 | AD84: =SUM(AB84/X84)-1 -> -0.041294168
B85: Accumulated other comprehensive loss | C85: -651 | D85: -830 | E85: -1523 | F85: -741 | G85: -1067 | I85: -1105 | J85: -1042 | K85: -1427 | L85: =F85 -> -741 | M85: -913 | N85: -890 | O85: -401 | P85: =G85 -> -1067 | Q85: -840 | R85: -371 | S85: -431 | U85: =L85 -> -741 | V85: =M85 -> -913 | W85: =N85 -> -890 | X85: =O85 -> -401 | Y85: =P85 -> -1067 | Z85: =Q85 -> -840 | AA85: =R85 -> -371 | AB85: =S85 -> -431 | AD85: =SUM(AB85/X85)-1 -> 0.074812968
B86: Total Warner Bros. Discovery, Inc. stockholders' equity | C86: =SUM(C80:C85) -> 10464 | D86: =SUM(D80:D85) -> 11599 | E86: =SUM(E80:E85) -> 47095 | F86: =SUM(F80:F85) -> 45226 | G86: =SUM(G80:G85) -> 34037 | I86: =SUM(I80:I85) -> 46496 | J86: =SUM(J80:J85) -> 45452 | K86: =SUM(K80:K85) -> 44774 | L86: =SUM(L80:L85) -> 45226 | M86: =SUM(M80:M85) -> 44151 | N86: =SUM(N80:N85) -> 34345 | O86: =SUM(O80:O85) -> 35100 | P86: =SUM(P80:P85) -> 34037 | ... S86: =SUM(S80:S85) -> 36018 | U86: =SUM(U80:U85) -> 45226 | V86: =SUM(V80:V85) -> 44151 | W86: =SUM(W80:W85) -> 34345 | X86: =SUM(X80:X85) -> 35100 | Y86: =SUM(Y80:Y85) -> 34037 | Z86: =SUM(Z80:Z85) -> 33836 | AA86: =SUM(AA80:AA85) -> 36049 | AB86: =SUM(AB80:AB85) -> 36018 | AD86: =SUM(AB86/X86)-1 -> 0.026153846
B88: Noncontrolling interests | C88: 1536 | D88: 1434 | E88: 1254 | F88: 1081 | G88: 792 | I88: 1037 | J88: 1027 | K88: 1087 | L88: =F88 -> 1081 | M88: 964 | N88: 952 | O88: 957 | P88: =G88 -> 792 | Q88: 1312 | R88: 1274 | S88: 1264 | U88: =L88 -> 1081 | V88: =M88 -> 964 | W88: =N88 -> 952 | X88: =O88 -> 957 | Y88: =P88 -> 792 | Z88: =Q88 -> 1312 | AA88: =R88 -> 1274 | AB88: =S88 -> 1264
B89: Total Equity | C89: =SUM(C86+SUM(C88:C88)) -> 12000 | D89: =SUM(D86+SUM(D88:D88)) -> 13033 | E89: =SUM(E86+SUM(E88:E88)) -> 48349 | F89: =SUM(F86+SUM(F88:F88)) -> 46307 | G89: =SUM(G86+SUM(G88:G88)) -> 34829 | I89: =SUM(I86+SUM(I88:I88)) -> 47533 | J89: =SUM(J86+SUM(J88:J88)) -> 46479 | K89: =SUM(K86+SUM(K88:K88)) -> 45861 | L89: =SUM(L86+SUM(L88:L88)) -> 46307 | M89: =SUM(M86+SUM(M88:M88)) -> 45115 | N89: =SUM(N86+SUM(N88:N88)) -> 35297 | O89: =SUM(O86+SUM(O88:O88)) -> 36057 | P89: =SUM(P86+SUM(P88:P88)) -> 34829 | ... S89: =SUM(S86+SUM(S88:S88)) -> 37282 | U89: =SUM(U86+SUM(U88:U88)) -> 46307 | V89: =SUM(V86+SUM(V88:V88)) -> 45115 | W89: =SUM(W86+SUM(W88:W88)) -> 35297 | X89: =SUM(X86+SUM(X88:X88)) -> 36057 | Y89: =SUM(Y86+SUM(Y88:Y88)) -> 34829 | Z89: =SUM(Z86+SUM(Z88:Z88)) -> 35148 | AA89: =SUM(AA86+SUM(AA88:AA88)) -> 37323 | AB89: =SUM(AB86+SUM(AB88:AB88)) -> 37282
B90: Total liabilities and stockholders' equity | C90: =SUM(C89+C73+C77) -> 34087 | D90: =SUM(D89+D73+D77) -> 34427 | E90: =SUM(E89+E73+E77) -> 134001 | F90: =SUM(F89+F73+F77) -> 122757 | G90: =SUM(G89+G73+G77) -> 104560 | I90: =SUM(I89+I73+I77) -> 130584 | J90: =SUM(J89+J73+J77) -> 128618 | K90: =SUM(K89+K73+K77) -> 123749 | L90: =SUM(L89+L73+L77) -> 122757 | M90: =SUM(M89+M73+M77) -> 119819 | N90: =SUM(N89+N73+N77) -> 108029 | O90: =SUM(O89+O73+O77) -> 106333 | P90: =SUM(P89+P73+P77) -> 104560 | ... S90: =SUM(S89+S73+S77) -> 100519 | U90: =SUM(U89+U73+U77) -> 122757 | V90: =SUM(V89+V73+V77) -> 119819 | W90: =SUM(W89+W73+W77) -> 108029 | X90: =SUM(X89+X73+X77) -> 106333 | Y90: =SUM(Y89+Y73+Y77) -> 104560 | Z90: =SUM(Z89+Z73+Z77) -> 101679 | AA90: =SUM(AA89+AA73+AA77) -> 101727 | AB90: =SUM(AB89+AB73+AB77) -> 100519 | AD90: =SUM(AB90/X90)-1 -> -0.054677287
B92: Balance Check | C92: =C90-C60 -> 0 | D92: =D90-D60 -> 0 | E92: =E90-E60 -> 0 | F92: =F90-F60 -> 0 | G92: =G90-G60 -> 0 | I92: =I90-I60 -> 0 | J92: =J90-J60 -> 0 | K92: =K90-K60 -> 0 | L92: =L90-L60 -> 0 | M92: =M90-M60 -> 0 | N92: =N90-N60 -> 0 | O92: =O90-O60 -> 0 | P92: =P90-P60 -> 0 | ... S92: =S90-S60 -> 0 | U92: =U90-U60 -> 0 | V92: =V90-V60 -> 0 | W92: =W90-W60 -> 0 | X92: =X90-X60 -> 0 | Y92: =Y90-Y60 -> 0 | Z92: =Z90-Z60 -> 0 | AA92: =AA90-AA60 -> 0 | AB92: =AB90-AB60 -> 0
A95: X | B95: Cash-Flows Statement | C95: FYE | D95: FYE | O95: Quarterly | X95: LTM | AD95: Variance
B96: =B7 -> Fiscal Period | C96: =C7 -> 2020 | D96: =D7 -> 2021 | E96: =E7 -> 2022 | F96: =F7 -> 2023 | G96: =G7 -> 2024 | I96: =I7 -> 1Q23 | J96: =J7 -> 2Q23 | K96: =K7 -> 3Q23 | L96: =L7 -> 4Q23 | M96: =M7 -> 1Q24 | N96: =N7 -> 2Q24 | O96: =O7 -> 3Q24 | P96: =P7 -> 4Q24 | ... S96: =S7 -> 3Q25 | U96: =U7 -> 4Q23 | V96: =V7 -> 1Q24 | W96: =W7 -> 2Q24 | X96: =X7 -> 3Q24 | Y96: =Y7 -> 4Q24 | Z96: =Z7 -> 1Q25 | AA96: =AA7 -> 2Q25 | AB96: =AB7 -> 3Q25
B97: =B8 -> Fiscal Period End Date | C97: =C8 -> 44196 | D97: =D8 -> 44561 | E97: =E8 -> 44926 | F97: =F8 -> 45291 | G97: =G8 -> 45657 | I97: =I8 -> 45016 | J97: =J8 -> 45107 | K97: =K8 -> 45199 | L97: =L8 -> 44926 | M97: =M8 -> 45382 | N97: =N8 -> 45473 | O97: =O8 -> 45565 | P97: =P8 -> 45291 | ... S97: =S8 -> 45930 | U97: =U8 -> 44926 | V97: =V8 -> 45382 | W97: =W8 -> 45473 | X97: =X8 -> 45565 | Y97: =Y8 -> 45291 | Z97: =Z8 -> 45747 | AA97: =AA8 -> 45838 | AB97: =AB8 -> 45930
B99: Cash-Flows From Operating Activities
B100: Net loss | C100: =C32 -> 1355 | D100: =D32 -> 1197 | E100: =E32 -> -7297 | F100: =F32 -> -3079 | G100: =G32 -> -11482 | I100: =I32 -> -1060 | J100: =J32 -> -1220 | K100: =K32 -> -407 | L100: =L32 -> -392 | M100: =M32 -> -955 | N100: =N32 -> -10028 | O100: =O32 -> 141 | P100: =P32 -> -640 | ... S100: =S32 -> -143 | U100: =U32 -> -1437 | V100: =V32 -> -1695 | W100: =W32 -> -1892 | X100: =X32 -> -1618 | Y100: =Y32 -> -2111 | Z100: =Z32 -> -1943 | AA100: =AA32 -> -2761 | AB100: =AB32 -> -3326 | AD100: =SUM(AB100/X100)-1 -> 1.0556242
B102: Adjustments to reconcile net income:
B103: Content rights amortization and impairment | C103: 2956 | D103: 3501 | E103: 14161 | F103: 16024 | G103: 13946 | I103: 4723 | J103: =9361-I103 -> 4638 | K103: =12547-J103-I103 -> 3186 | L103: =SUM(F103-SUM(I103:K103)) -> 3477 | M103: 3827 | N103: =7747-M103 -> 3920 | O103: =10879-N103-M103 -> 3132 | P103: =SUM(G103-SUM(M103:O103)) -> 3067 | Q103: 3145 | R103: =6851-Q103 -> 3706 | S103: =9093-R103-Q103 -> 2242 | U103: =SUM(K103:N103) -> 14410 | V103: =SUM(L103:O103) -> 14356 | W103: =SUM(M103:P103) -> 13946 | X103: =SUM(N103:Q103) -> 13264 | Y103: =SUM(O103:R103) -> 13050 | Z103: =SUM(P103:S103) -> 12160 | AA103: =SUM(Q103:S103) -> 9093 | AB103: =SUM(R103:S103) -> 5948 | AD103: =SUM(AB103/X103)-1 -> -0.55156815
B104: Depreciation and amortization | C104: 1359 | D104: 1582 | E104: 7193 | F104: 7985 | G104: 7037 | I104: 2058 | J104: =3972-I104 -> 1914 | K104: =5961-J104-I104 -> 1989 | L104: =SUM(F104-SUM(I104:K104)) -> 2024 | M104: 1888 | N104: =3632-M104 -> 1744 | O104: =5394-N104-M104 -> 1762 | P104: =SUM(G104-SUM(M104:O104)) -> 1643 | Q104: 1547 | R104: =2994-Q104 -> 1447 | S104: =4369-R104-Q104 -> 1375 | U104: =SUM(K104:N104) -> 7645 | V104: =SUM(L104:O104) -> 7418 | W104: =SUM(M104:P104) -> 7037 | X104: =SUM(N104:Q104) -> 6696 | Y104: =SUM(O104:R104) -> 6399 | Z104: =SUM(P104:S104) -> 6012 | AA104: =SUM(Q104:S104) -> 4369 | AB104: =SUM(R104:S104) -> 2822 | AD104: =SUM(AB104/X104)-1 -> -0.57855436
B105: Deferred income taxes | C105: -186 | D105: -511 | E105: -2842 | F105: -2344 | G105: -1732 | I105: -669 | J105: =-1426-I105 -> -757 | K105: =-2071-J105-I105 -> -645 | L105: =SUM(F105-SUM(I105:K105)) -> -273 | M105: -399 | N105: =-889-M105 -> -490 | O105: =-1351-N105-M105 -> -462 | P105: =SUM(G105-SUM(M105:O105)) -> -381 | Q105: -312 | R105: =-471-Q105 -> -159 | S105: =-272-R105-Q105 -> 199 | U105: =SUM(K105:N105) -> -1807 | V105: =SUM(L105:O105) -> -1624 | W105: =SUM(M105:P105) -> -1732 | X105: =SUM(N105:Q105) -> -1645 | Y105: =SUM(O105:R105) -> -1314 | Z105: =SUM(P105:S105) -> -653 | AA105: =SUM(Q105:S105) -> -272 | AB105: =SUM(R105:S105) -> 40 | AD105: =SUM(AB105/X105)-1 -> -1.0243161
B106: Share-based compensation expense | C106: 110 | D106: 178 | E106: 412 | F106: 500 | G106: 557 | I106: 111 | J106: =248-I106 -> 137 | K106: =391-J106-I106 -> 143 | L106: =SUM(F106-SUM(I106:K106)) -> 109 | M106: 101 | N106: =260-M106 -> 159 | O106: =419-N106-M106 -> 159 | P106: =SUM(G106-SUM(M106:O106)) -> 138 | Q106: 123 | R106: =298-Q106 -> 175 | S106: =540-R106-Q106 -> 242 | U106: =SUM(K106:N106) -> 512 | V106: =SUM(L106:O106) -> 528 | W106: =SUM(M106:P106) -> 557 | X106: =SUM(N106:Q106) -> 579 | Y106: =SUM(O106:R106) -> 595 | Z106: =SUM(P106:S106) -> 678 | AA106: =SUM(Q106:S106) -> 540 | AB106: =SUM(R106:S106) -> 417 | AD106: =SUM(AB106/X106)-1 -> -0.27979275
B107: Equity in losses of equity method investee companies and cash distributions | C107: 167 | D107: 63 | E107: 211 | F107: 157 | G107: 167 | I107: 62 | J107: =112-I107 -> 50 | K107: =136-J107-I107 -> 24 | L107: =SUM(F107-SUM(I107:K107)) -> 21 | M107: 58 | N107: =83-M107 -> 25 | O107: =130-N107-M107 -> 47 | P107: =SUM(G107-SUM(M107:O107)) -> 37 | Q107: 0 | R107: =18-Q107 -> 18 | S107: =26-R107-Q107 -> 8 | U107: =SUM(K107:N107) -> 128 | V107: =SUM(L107:O107) -> 151 | W107: =SUM(M107:P107) -> 167 | X107: =SUM(N107:Q107) -> 109 | Y107: =SUM(O107:R107) -> 102 | Z107: =SUM(P107:S107) -> 63 | AA107: =SUM(Q107:S107) -> 26 | AB107: =SUM(R107:S107) -> 26 | AD107: =SUM(AB107/X107)-1 -> -0.76146789
B108: Gain on sale of investments | C108: -103 | D108: -19 | E108: -199 | F108: 0 | G108: -227 | I108: 0 | J108: 0 | K108: 0 | L108: =SUM(F108-SUM(I108:K108)) -> 0 | M108: 0 | N108: =-203-M108 -> -203 | O108: =-204-N108-M108 -> -1 | P108: =SUM(G108-SUM(M108:O108)) -> -23 | Q108: 0 | R108: =-6-Q108 -> -6 | S108: =-4-R108-Q108 -> 2 | U108: =SUM(K108:N108) -> -203 | V108: =SUM(L108:O108) -> -204 | W108: =SUM(M108:P108) -> -227 | X108: =SUM(N108:Q108) -> -227 | Y108: =SUM(O108:R108) -> -30 | Z108: =SUM(P108:S108) -> -27 | AA108: =SUM(Q108:S108) -> -4 | AB108: =SUM(R108:S108) -> -4 | AD108: =SUM(AB108/X108)-1 -> -0.98237885
B109: Loss (Gain) on extinguishment of debt | C109: 76 | D109: 0 | E109: 0 | F109: -17 | G109: -632 | I109: 0 | J109: =5-I109 -> 5 | K109: =-17-J109-I109 -> -22 | L109: =SUM(F109-SUM(I109:K109)) -> 0 | M109: 0 | N109: =-567-M109 -> -567 | O109: =-590-N109-M109 -> -23 | P109: =SUM(G109-SUM(M109:O109)) -> -42 | Q109: 0 | R109: =-2954-Q109 -> -2954 | S109: =-2953-R109-Q109 -> 1 | U109: =SUM(K109:N109) -> -589 | V109: =SUM(L109:O109) -> -590 | W109: =SUM(M109:P109) -> -632 | X109: =SUM(N109:Q109) -> -632 | Y109: =SUM(O109:R109) -> -3019 | Z109: =SUM(P109:S109) -> -2995 | AA109: =SUM(Q109:S109) -> -2953 | AB109: =SUM(R109:S109) -> -2953 | AD109: =SUM(AB109/X109)-1 -> 3.6724684
B110: Impairments and loss (Gain) on dispositions | C110: 126 | D110: -71 | E110: 116 | F110: 77 | G110: 9603 | I110: 0 | J110: =37-I110 -> 37 | K110: =61-J110-I110 -> 24 | L110: =SUM(F110-SUM(I110:K110)) -> 16 | M110: 0 | N110: =9407-M110 -> 9407 | O110: =9412-N110-M110 -> 5 | P110: =SUM(G110-SUM(M110:O110)) -> 191 | Q110: 90 | R110: =116-Q110 -> 26 | S110: =162-R110-Q110 -> 46 | U110: =SUM(K110:N110) -> 9447 | V110: =SUM(L110:O110) -> 9428 | W110: =SUM(M110:P110) -> 9603 | X110: =SUM(N110:Q110) -> 9693 | Y110: =SUM(O110:R110) -> 312 | Z110: =SUM(P110:S110) -> 353 | AA110: =SUM(Q110:S110) -> 162 | AB110: =SUM(R110:S110) -> 72 | AD110: =SUM(AB110/X110)-1 -> -0.99257196
B111: Loss (Gain) from derivative instruments, net | C111: -36 | D111: 49 | E111: -501 | F111: -151 | G111: -16 | I111: -23 | J111: =-111-I111 -> -88 | K111: =-100-J111-I111 -> 11 | L111: =SUM(F111-SUM(I111:K111)) -> -51 | M111: -43 | N111: =-33-M111 -> 10 | O111: =-41-N111-M111 -> -8 | P111: =SUM(G111-SUM(M111:O111)) -> 25 | Q111: 0 | R111: 0 | S111: 0 | U111: =SUM(K111:N111) -> -73 | V111: =SUM(L111:O111) -> -92 | W111: =SUM(M111:P111) -> -16 | X111: =SUM(N111:Q111) -> 27 | Y111: =SUM(O111:R111) -> 17 | Z111: =SUM(P111:S111) -> 25 | AA111: =SUM(Q111:S111) -> 0 | AB111: =SUM(R111:S111) -> 0 | AD111: =SUM(AB111/X111)-1 -> -1
B112: Other, net | C112: 14 | D112: 66 | E112: 435 | F112: 199 | G112: 115 | I112: 97 | J112: =129-I112 -> 32 | K112: =186-J112-I112 -> 57 | L112: =SUM(F112-SUM(I112:K112)) -> 13 | M112: 7 | N112: =58-M112 -> 51 | O112: =96-N112-M112 -> 38 | P112: =SUM(G112-SUM(M112:O112)) -> 19 | Q112: 17 | R112: =-97-Q112 -> -114 | S112: =-75-R112-Q112 -> 22 | U112: =SUM(K112:N112) -> 128 | V112: =SUM(L112:O112) -> 109 | W112: =SUM(M112:P112) -> 115 | X112: =SUM(N112:Q112) -> 125 | Y112: =SUM(O112:R112) -> -40 | Z112: =SUM(P112:S112) -> -56 | AA112: =SUM(Q112:S112) -> -75 | AB112: =SUM(R112:S112) -> -92 | AD112: =SUM(AB112/X112)-1 -> -1.736
B113: Content restructuring impairments and write-offs | C113: 0 | D113: 0 | E113: 2808 | F113: 115 | G113: 165 | I113: 0 | J113: 0 | K113: 0 | L113: =SUM(F113-SUM(I113:K113)) -> 115 | M113: 0 | N113: 0 | O113: 0 | P113: =SUM(G113-SUM(M113:O113)) -> 165 | Q113: 0 | R113: 0 | S113: 0 | U113: =SUM(K113:N113) -> 115 | V113: =SUM(L113:O113) -> 115 | W113: =SUM(M113:P113) -> 165 | X113: =SUM(N113:Q113) -> 165 | Y113: =SUM(O113:R113) -> 165 | Z113: =SUM(P113:S113) -> 165 | AA113: =SUM(Q113:S113) -> 0 | AB113: =SUM(R113:S113) -> 0 | AD113: =SUM(AB113/X113)-1 -> -1
B114: Preferred stock conversion premium | C114: 0 | D114: 0 | E114: 789 | F114: 0 | G114: 0 | I114: 0 | J114: 0 | K114: 0 | L114: =SUM(F114-SUM(I114:K114)) -> 0 | M114: 0 | N114: 0 | O114: 0 | P114: =SUM(G114-SUM(M114:O114)) -> 0 | Q114: 0 | R114: 0 | S114: 0 | U114: =SUM(K114:N114) -> 0 | V114: =SUM(L114:O114) -> 0 | W114: =SUM(M114:P114) -> 0 | X114: =SUM(N114:Q114) -> 0 | Y114: =SUM(O114:R114) -> 0 | Z114: =SUM(P114:S114) -> 0 | AA114: =SUM(Q114:S114) -> 0 | AB114: =SUM(R114:S114) -> 0 | AD114: =SUM(AB114/X114)-1 -> #DIV/0!
B115: Changes in assets and liabilities:
B116: Receivables, net | C116: 105 | D116: 47 | E116: 181 | F116: 312 | G116: 1012 | I116: -486 | J116: =-433-I116 -> 53 | K116: =-33-J116-I116 -> 400 | L116: =SUM(F116-SUM(I116:K116)) -> 345 | M116: -304 | N116: =-191-M116 -> 113 | O116: =517-N116-M116 -> 708 | P116: =SUM(G116-SUM(M116:O116)) -> 495 | Q116: 288 | R116: =-460-Q116 -> -748 | S116: =-200-R116-Q116 -> 260 | U116: =SUM(K116:N116) -> 554 | V116: =SUM(L116:O116) -> 862 | W116: =SUM(M116:P116) -> 1012 | X116: =SUM(N116:Q116) -> 1604 | Y116: =SUM(O116:R116) -> 743 | Z116: =SUM(P116:S116) -> 295 | AA116: =SUM(Q116:S116) -> -200 | AB116: =SUM(R116:S116) -> -488 | AD116: =SUM(AB116/X116)-1 -> -1.3042394
B117: Film and television content rights, games and production payables, net | C117: -3053 | D117: -3381 | E117: -12562 | F117: -12305 | G117: -12349 | I117: -4051 | J117: =-7656-I117 -> -3605 | K117: =-9853-J117-I117 -> -2197 | L117: =SUM(F117-SUM(I117:K117)) -> -2452 | M117: -2778 | N117: =-6351-M117 -> -3573 | O117: =-9506-N117-M117 -> -3155 | P117: =SUM(G117-SUM(M117:O117)) -> -2843 | Q117: -2846 | R117: =-6314-Q117 -> -3468 | S117: =-9096-R117-Q117 -> -2782 | U117: =SUM(K117:N117) -> -11000 | V117: =SUM(L117:O117) -> -11958 | W117: =SUM(M117:P117) -> -12349 | X117: =SUM(N117:Q117) -> -12417 | Y117: =SUM(O117:R117) -> -12312 | Z117: =SUM(P117:S117) -> -11939 | AA117: =SUM(Q117:S117) -> -9096 | AB117: =SUM(R117:S117) -> -6250 | AD117: =SUM(AB117/X117)-1 -> -0.49665781
B118: Accounts payable, accrued liabilities, deferred revenues and other noncurrent liabilities | C118: -131 | D118: 185 | E118: 1529 | F118: -820 | G118: -529 | I118: -1652 | J118: =-859-I118 -> 793 | K118: =-1245-J118-I118 -> -386 | L118: =SUM(F118-SUM(I118:K118)) -> 425 | M118: -753 | N118: =-132-M118 -> 621 | O118: =-1493-N118-M118 -> -1361 | P118: =SUM(G118-SUM(M118:O118)) -> 964 | Q118: -1026 | R118: =-141-Q118 -> 885 | S118: =-402-R118-Q118 -> -261 | U118: =SUM(K118:N118) -> -93 | V118: =SUM(L118:O118) -> -1068 | W118: =SUM(M118:P118) -> -529 | X118: =SUM(N118:Q118) -> -802 | Y118: =SUM(O118:R118) -> -538 | Z118: =SUM(P118:S118) -> 562 | AA118: =SUM(Q118:S118) -> -402 | AB118: =SUM(R118:S118) -> 624 | AD118: =SUM(AB118/X118)-1 -> -1.7780549
B119: Foreign currency, prepaid expenses and other assets, net | C119: -20 | D119: -88 | E119: -130 | F119: 824 | G119: -260 | I119: 259 | J119: =284-I119 -> 25 | K119: =623-J119-I119 -> 339 | L119: =SUM(F119-SUM(I119:K119)) -> 201 | M119: -64 | N119: =-25-M119 -> 39 | O119: =-160-N119-M119 -> -135 | P119: =SUM(G119-SUM(M119:O119)) -> -100 | Q119: -24 | R119: =563-Q119 -> 587 | S119: =331-R119-Q119 -> -232 | U119: =SUM(K119:N119) -> 515 | V119: =SUM(L119:O119) -> 41 | W119: =SUM(M119:P119) -> -260 | X119: =SUM(N119:Q119) -> -220 | Y119: =SUM(O119:R119) -> 328 | Z119: =SUM(P119:S119) -> 231 | AA119: =SUM(Q119:S119) -> 331 | AB119: =SUM(R119:S119) -> 355 | AD119: =SUM(AB119/X119)-1 -> -2.6136364
B120: Net cash used in operating activities | C120: =SUM(C100:C119) -> 2739 | D120: =SUM(D100:D119) -> 2798 | E120: =SUM(E100:E119) -> 4304 | F120: =SUM(F100:F119) -> 7477 | G120: =SUM(G100:G119) -> 5375 | I120: =SUM(I100:I119) -> -631 | J120: =SUM(J100:J119) -> 2014 | K120: =SUM(K100:K119) -> 2516 | L120: =SUM(L100:L119) -> 3578 | M120: =SUM(M100:M119) -> 585 | N120: =SUM(N100:N119) -> 1228 | O120: =SUM(O100:O119) -> 847 | P120: =SUM(P100:P119) -> 2715 | ... S120: =SUM(S100:S119) -> 979 | U120: =SUM(U100:U119) -> 18252 | V120: =SUM(V100:V119) -> 15777 | W120: =SUM(W100:W119) -> 14965 | X120: =SUM(X100:X119) -> 14701 | Y120: =SUM(Y100:Y119) -> 2347 | Z120: =SUM(Z100:Z119) -> 2931 | AA120: =SUM(AA100:AA119) -> -1242 | AB120: =SUM(AB100:AB119) -> -2809 | AD120: =SUM(AB120/X120)-1 -> -1.1910754
B122: Cash flows from investing activities:
B123: Purchases of property and equipment | C123: -402 | D123: -373 | E123: -987 | F123: -1316 | G123: -948 | I123: -299 | J123: =-591-I123 -> -292 | K123: =-1048-J123-I123 -> -457 | L123: =SUM(F123-SUM(I123:K123)) -> -268 | M123: -195 | N123: =-447-M123 -> -252 | O123: =-662-N123-M123 -> -215 | P123: =SUM(G123-SUM(M123:O123)) -> -286 | Q123: -251 | R123: =-532-Q123 -> -281 | S123: =-810-R123-Q123 -> -278 | U123: =SUM(K123:N123) -> -1172 | V123: =SUM(L123:O123) -> -930 | W123: =SUM(M123:P123) -> -948 | X123: =SUM(N123:Q123) -> -1004 | Y123: =SUM(O123:R123) -> -1033 | Z123: =SUM(P123:S123) -> -1096 | AA123: =SUM(Q123:S123) -> -810 | AB123: =SUM(R123:S123) -> -559 | AD123: =SUM(AB123/X123)-1 -> -0.44322709
B124: Divestitures / (Acquisitions) | C124: -39 | D124: -2 | E124: 3612 | F124: -50 | G124: 0 | I124: 0 | J124: 0 | K124: 0 | L124: =SUM(F124-SUM(I124:K124)) -> -50 | M124: 0 | N124: 0 | O124: 0 | P124: =SUM(G124-SUM(M124:O124)) -> 0 | Q124: 66 | R124: =66-Q124 -> 0 | S124: =0-R124-Q124 -> -66 | U124: =SUM(K124:N124) -> -50 | V124: =SUM(L124:O124) -> -50 | W124: =SUM(M124:P124) -> 0 | X124: =SUM(N124:Q124) -> 66 | Y124: =SUM(O124:R124) -> 66 | Z124: =SUM(P124:S124) -> 0 | AA124: =SUM(Q124:S124) -> 0 | AB124: =SUM(R124:S124) -> -66 | AD124: =SUM(AB124/X124)-1 -> -2
...

Sheet Revenue Segment Analysis
B2: ='Historical Financials'!B2 -> Warner Bros Discovery Inc (NASDAQ: WBD) | C2: FYE | D2: FYE | O2: Quarterly | X2: LTM
B3: Segment Anaysis | C3: ='Historical Financials'!C7 -> 2020 | D3: ='Historical Financials'!D7 -> 2021 | E3: ='Historical Financials'!E7 -> 2022 | F3: ='Historical Financials'!F7 -> 2023 | G3: ='Historical Financials'!G7 -> 2024 | I3: ='Historical Financials'!I7 -> 1Q23 | J3: ='Historical Financials'!J7 -> 2Q23 | K3: ='Historical Financials'!K7 -> 3Q23 | L3: ='Historical Financials'!L7 -> 4Q23 | M3: ='Historical Financials'!M7 -> 1Q24 | N3: ='Historical Financials'!N7 -> 2Q24 | O3: ='Historical Financials'!O7 -> 3Q24 | P3: ='Historical Financials'!P7 -> 4Q24 | ... S3: ='Historical Financials'!S7 -> 3Q25 | U3: =L3 -> 4Q23 | V3: =M3 -> 1Q24 | W3: =N3 -> 2Q24 | X3: =O3 -> 3Q24 | Y3: =P3 -> 4Q24 | Z3: =Q3 -> 1Q25 | AA3: =R3 -> 2Q25 | AB3: =S3 -> 3Q25
B4: ($ In Millions) | C4: ='Historical Financials'!C8 -> 44196 | D4: ='Historical Financials'!D8 -> 44561 | E4: ='Historical Financials'!E8 -> 44926 | F4: ='Historical Financials'!F8 -> 45291 | G4: ='Historical Financials'!G8 -> 45657 | I4: ='Historical Financials'!I8 -> 45016 | J4: ='Historical Financials'!J8 -> 45107 | K4: ='Historical Financials'!K8 -> 45199 | L4: ='Historical Financials'!L8 -> 44926 | M4: ='Historical Financials'!M8 -> 45382 | N4: ='Historical Financials'!N8 -> 45473 | O4: ='Historical Financials'!O8 -> 45565 | P4: ='Historical Financials'!P8 -> 45291 | ... S4: ='Historical Financials'!S8 -> 45930 | U4: =L4 -> 44926 | V4: =M4 -> 45382 | W4: =N4 -> 45473 | X4: =O4 -> 45565 | Y4: =P4 -> 45291 | Z4: =Q4 -> 45747 | AA4: =R4 -> 45838 | AB4: =S4 -> 45930
A6: X | B6: Revenue by reportable segment
A8: X | B8: Revenue by Type
B9: Distribution | C9: 5572 | D9: 5202 | E9: 16142 | F9: 20237 | G9: 19701 | I9: 5163 | J9: 5135 | K9: 5026 | L9: =SUM(F9-SUM(I9:K9)) -> 4913 | M9: 4985 | N9: 4879 | O9: 4920 | P9: =SUM(G9-SUM(M9:O9)) -> 4917 | Q9: 4886 | R9: 4885 | S9: 4702 | U9: =SUM(I9:L9) -> 20237 | V9: =SUM(J9:M9) -> 20059 | W9: =SUM(K9:N9) -> 19803 | X9: =SUM(L9:O9) -> 19697 | Y9: =SUM(M9:P9) -> 19701 | Z9: =SUM(N9:Q9) -> 19602 | AA9: =SUM(O9:R9) -> 19608 | AB9: =SUM(P9:S9) -> 19390
B10: Advertising | C10: 4686 | D10: 6194 | E10: 8524 | F10: 8700 | G10: 8090 | I10: 2298 | J10: 2519 | K10: 1796 | L10: =SUM(F10-SUM(I10:K10)) -> 2087 | M10: 2148 | N10: 2430 | O10: 1682 | P10: =SUM(G10-SUM(M10:O10)) -> 1830 | Q10: 1980 | R10: 2216 | S10: 1407 | U10: =SUM(I10:L10) -> 8700 | V10: =SUM(J10:M10) -> 8550 | W10: =SUM(K10:N10) -> 8461 | X10: =SUM(L10:O10) -> 8347 | Y10: =SUM(M10:P10) -> 8090 | Z10: =SUM(N10:Q10) -> 7922 | AA10: =SUM(O10:R10) -> 7708 | AB10: =SUM(P10:S10) -> 7433
B11: Content | C11: 355 | D11: 737 | E11: 8360 | F11: 11203 | G11: 10297 | I11: 2954 | J11: 2446 | K11: 2840 | L11: =SUM(F11-SUM(I11:K11)) -> 2963 | M11: 2558 | N11: 2109 | O11: 2721 | P11: =SUM(G11-SUM(M11:O11)) -> 2909 | Q11: 1866 | R11: 2471 | S11: 2649 | U11: =SUM(I11:L11) -> 11203 | V11: =SUM(J11:M11) -> 10807 | W11: =SUM(K11:N11) -> 10470 | X11: =SUM(L11:O11) -> 10351 | Y11: =SUM(M11:P11) -> 10297 | Z11: =SUM(N11:Q11) -> 9605 | AA11: =SUM(O11:R11) -> 9967 | AB11: =SUM(P11:S11) -> 9895
B12: Other | C12: 58 | D12: 58 | E12: 791 | F12: 1181 | G12: 1233 | I12: 285 | J12: 258 | K12: 317 | L12: =SUM(F12-SUM(I12:K12)) -> 321 | M12: 267 | N12: 295 | O12: 300 | P12: =SUM(G12-SUM(M12:O12)) -> 371 | Q12: 247 | R12: 240 | S12: 287 | U12: =SUM(I12:L12) -> 1181 | V12: =SUM(J12:M12) -> 1163 | W12: =SUM(K12:N12) -> 1200 | X12: =SUM(L12:O12) -> 1183 | Y12: =SUM(M12:P12) -> 1233 | Z12: =SUM(N12:Q12) -> 1213 | AA12: =SUM(O12:R12) -> 1158 | AB12: =SUM(P12:S12) -> 1145
B13: Total Net Revenue | C13: =SUM(C9:C12) -> 10671 | D13: =SUM(D9:D12) -> 12191 | E13: =SUM(E9:E12) -> 33817 | F13: =SUM(F9:F12) -> 41321 | G13: =SUM(G9:G12) -> 39321 | I13: =SUM(I9:I12) -> 10700 | J13: =SUM(J9:J12) -> 10358 | K13: =SUM(K9:K12) -> 9979 | L13: =SUM(L9:L12) -> 10284 | M13: =SUM(M9:M12) -> 9958 | N13: =SUM(N9:N12) -> 9713 | O13: =SUM(O9:O12) -> 9623 | P13: =SUM(P9:P12) -> 10027 | ... S13: =SUM(S9:S12) -> 9045 | U13: =SUM(U9:U12) -> 41321 | V13: =SUM(V9:V12) -> 40579 | W13: =SUM(W9:W12) -> 39934 | X13: =SUM(X9:X12) -> 39578 | Y13: =SUM(Y9:Y12) -> 39321 | Z13: =SUM(Z9:Z12) -> 38342 | AA13: =SUM(AA9:AA12) -> 38441 | AB13: =SUM(AB9:AB12) -> 37863
B14: Variance Check | C14: =+C13-'Historical Financials'!C11 -> 0 | D14: =+D13-'Historical Financials'!D11 -> 0 | E14: =+E13-'Historical Financials'!E11 -> 0 | F14: =+F13-'Historical Financials'!F11 -> 0 | G14: =+G13-'Historical Financials'!G11 -> 0 | I14: =+I13-'Historical Financials'!I11 -> 0 | J14: =+J13-'Historical Financials'!J11 -> 0 | K14: =+K13-'Historical Financials'!K11 -> 0 | L14: =+L13-'Historical Financials'!L11 -> 0 | M14: =+M13-'Historical Financials'!M11 -> 0 | N14: =+N13-'Historical Financials'!N11 -> 0 | O14: =+O13-'Historical Financials'!O11 -> 0 | P14: =+P13-'Historical Financials'!P11 -> 0 | ... S14: =+S13-'Historical Financials'!S11 -> 0 | U14: =+U13-'Historical Financials'!U11 -> 0 | V14: =+V13-'Historical Financials'!V11 -> 0 | W14: =+W13-'Historical Financials'!W11 -> 0 | X14: =+X13-'Historical Financials'!X11 -> 0 | Y14: =+Y13-'Historical Financials'!Y11 -> 0 | Z14: =+Z13-'Historical Financials'!Z11 -> 0 | AA14: =+AA13-'Historical Financials'!AA11 -> 0 | AB14: =+AB13-'Historical Financials'!AB11 -> 0
B16: =B9&"(%)" -> Distribution(%) | C16: =SUM(C9/C$13) -> 0.52216287 | D16: =SUM(D9/D$13) -> 0.42670823 | E16: =SUM(E9/E$13) -> 0.47733389 | F16: =SUM(F9/F$13) -> 0.48975097 | G16: =SUM(G9/G$13) -> 0.50102998 | I16: =SUM(I9/I$13) -> 0.48252336 | J16: =SUM(J9/J$13) -> 0.49575208 | K16: =SUM(K9/K$13) -> 0.50365768 | L16: =SUM(L9/L$13) -> 0.4777324 | M16: =SUM(M9/M$13) -> 0.50060253 | N16: =SUM(N9/N$13) -> 0.50231648 | O16: =SUM(O9/O$13) -> 0.51127507 | P16: =SUM(P9/P$13) -> 0.49037598 | ... S16: =SUM(S9/S$13) -> 0.51984522 | U16: =L16 -> 0.4777324 | V16: =M16 -> 0.50060253 | W16: =N16 -> 0.50231648 | X16: =O16 -> 0.51127507 | Y16: =P16 -> 0.49037598 | Z16: =Q16 -> 0.54415859 | AA16: =R16 -> 0.49785976 | AB16: =S16 -> 0.51984522
B17: =B10&"(%)" -> Advertising(%) | C17: =SUM(C10/C$13) -> 0.4391341 | D17: =SUM(D10/D$13) -> 0.50807973 | E17: =SUM(E10/E$13) -> 0.25206257 | F17: =SUM(F10/F$13) -> 0.2105467 | G17: =SUM(G10/G$13) -> 0.20574248 | I17: =SUM(I10/I$13) -> 0.21476636 | J17: =SUM(J10/J$13) -> 0.24319367 | K17: =SUM(K10/K$13) -> 0.17997795 | L17: =SUM(L10/L$13) -> 0.2029366 | M17: =SUM(M10/M$13) -> 0.21570597 | N17: =SUM(N10/N$13) -> 0.25018017 | O17: =SUM(O10/O$13) -> 0.17478957 | P17: =SUM(P10/P$13) -> 0.18250723 | ... S17: =SUM(S10/S$13) -> 0.15555556 | U17: =L17 -> 0.2029366 | V17: =M17 -> 0.21570597 | W17: =N17 -> 0.25018017 | X17: =O17 -> 0.17478957 | Y17: =P17 -> 0.18250723 | Z17: =Q17 -> 0.22051453 | AA17: =R17 -> 0.2258459 | AB17: =S17 -> 0.15555556
B18: =B11&"(%)" -> Content(%) | C18: =SUM(C11/C$13) -> 0.033267735 | D18: =SUM(D11/D$13) -> 0.060454434 | E18: =SUM(E11/E$13) -> 0.24721294 | F18: =SUM(F11/F$13) -> 0.27112122 | G18: =SUM(G11/G$13) -> 0.26187025 | I18: =SUM(I11/I$13) -> 0.27607477 | J18: =SUM(J11/J$13) -> 0.23614597 | K18: =SUM(K11/K$13) -> 0.28459766 | L18: =SUM(L11/L$13) -> 0.28811746 | M18: =SUM(M11/M$13) -> 0.25687889 | N18: =SUM(N11/N$13) -> 0.21713168 | O18: =SUM(O11/O$13) -> 0.28276005 | P18: =SUM(P11/P$13) -> 0.29011668 | ... S18: =SUM(S11/S$13) -> 0.29286899 | U18: =L18 -> 0.28811746 | V18: =M18 -> 0.25687889 | W18: =N18 -> 0.21713168 | X18: =O18 -> 0.28276005 | Y18: =P18 -> 0.29011668 | Z18: =Q18 -> 0.20781824 | AA18: =R18 -> 0.25183449 | AB18: =S18 -> 0.29286899
B19: =B12&"(%)" -> Other(%) | C19: =SUM(C12/C$13) -> 0.0054352919 | D19: =SUM(D12/D$13) -> 0.0047576081 | E19: =SUM(E12/E$13) -> 0.023390602 | F19: =SUM(F12/F$13) -> 0.028581109 | G19: =SUM(G12/G$13) -> 0.03135729 | I19: =SUM(I12/I$13) -> 0.026635514 | J19: =SUM(J12/J$13) -> 0.024908283 | K19: =SUM(K12/K$13) -> 0.03176671 | L19: =SUM(L12/L$13) -> 0.031213536 | M19: =SUM(M12/M$13) -> 0.026812613 | N19: =SUM(N12/N$13) -> 0.030371667 | O19: =SUM(O12/O$13) -> 0.031175309 | P19: =SUM(P12/P$13) -> 0.0370001 | ... S19: =SUM(S12/S$13) -> 0.031730238 | U19: =L19 -> 0.031213536 | V19: =M19 -> 0.026812613 | W19: =N19 -> 0.030371667 | X19: =O19 -> 0.031175309 | Y19: =P19 -> 0.0370001 | Z19: =Q19 -> 0.027508631 | AA19: =R19 -> 0.024459845 | AB19: =S19 -> 0.031730238
A22: X | B22: Revenue By End Market Channel
A24: X | B24: Revenue by End Market Channel
B25: Studios | C25: =C43 -> 12 | D25: =D43 -> 20 | E25: =E43 -> 9731 | F25: =F43 -> 12192 | G25: =G43 -> 11607 | I25: =I43 -> 3212 | J25: =J43 -> 2581 | K25: =K43 -> 3226 | L25: =SUM(F25-SUM(I25:K25)) -> 3173 | M25: =M43 -> 2821 | N25: =N43 -> 2449 | O25: =O43 -> 2680 | P25: =SUM(G25-SUM(M25:O25)) -> 3657 | Q25: =Q43 -> 2314 | R25: =R43 -> 3801 | S25: =S43 -> 3321 | U25: =SUM(I25:L25) -> 12192 | V25: =SUM(J25:M25) -> 11801 | W25: =SUM(K25:N25) -> 11669 | X25: =SUM(L25:O25) -> 11123 | Y25: =SUM(M25:P25) -> 11607 | Z25: =SUM(N25:Q25) -> 11100 | AA25: =SUM(O25:R25) -> 12452 | AB25: =SUM(P25:S25) -> 13093
B26: Networks | C26: =C85 -> 10439 | D26: =D85 -> 11311 | E26: =E85 -> 19348 | F26: =F85 -> 21244 | G26: =G85 -> 20175 | I26: =I85 -> 5581 | J26: =J85 -> 5758 | K26: =K85 -> 4868 | L26: =SUM(F26-SUM(I26:K26)) -> 5037 | M26: =M85 -> 5125 | N26: =N85 -> 5272 | O26: =O85 -> 5010 | P26: =SUM(G26-SUM(M26:O26)) -> 4768 | Q26: =Q85 -> 4774 | R26: =R85 -> 4803 | S26: =S85 -> 3883 | U26: =SUM(I26:L26) -> 21244 | V26: =SUM(J26:M26) -> 20788 | W26: =SUM(K26:N26) -> 20302 | X26: =SUM(L26:O26) -> 20444 | Y26: =SUM(M26:P26) -> 20175 | Z26: =SUM(N26:Q26) -> 19824 | AA26: =SUM(O26:R26) -> 19355 | AB26: =SUM(P26:S26) -> 18228
B27: Streaming | C27: =C124 -> 220 | D27: =D124 -> 860 | E27: =E124 -> 7274 | F27: =F124 -> 10154 | G27: =G124 -> 10313 | I27: =I124 -> 2455 | J27: =J124 -> 2732 | K27: =K124 -> 2438 | L27: =SUM(F27-SUM(I27:K27)) -> 2529 | M27: =M124 -> 2460 | N27: =N124 -> 2568 | O27: =O124 -> 2634 | P27: =SUM(G27-SUM(M27:O27)) -> 2651 | Q27: =Q124 -> 2656 | R27: =R124 -> 2793 | S27: =S124 -> 2633 | U27: =SUM(I27:L27) -> 10154 | V27: =SUM(J27:M27) -> 10159 | W27: =SUM(K27:N27) -> 9995 | X27: =SUM(L27:O27) -> 10191 | Y27: =SUM(M27:P27) -> 10313 | Z27: =SUM(N27:Q27) -> 10509 | AA27: =SUM(O27:R27) -> 10734 | AB27: =SUM(P27:S27) -> 10733
B28: Corporate and Inter-segment eliminations | C28: 0 | D28: 0 | E28: -2536 | F28: -2269 | G28: -2774 | I28: -548 | J28: -713 | K28: -553 | L28: =SUM(F28-SUM(I28:K28)) -> -455 | M28: -448 | N28: -576 | O28: -701 | P28: =SUM(G28-SUM(M28:O28)) -> -1049 | Q28: -765 | R28: -1585 | S28: -792 | U28: =SUM(I28:L28) -> -2269 | V28: =SUM(J28:M28) -> -2169 | W28: =SUM(K28:N28) -> -2032 | X28: =SUM(L28:O28) -> -2180 | Y28: =SUM(M28:P28) -> -2774 | Z28: =SUM(N28:Q28) -> -3091 | AA28: =SUM(O28:R28) -> -4100 | AB28: =SUM(P28:S28) -> -4191
B29: Total Net Revenue | C29: =SUM(C25:C28) -> 10671 | D29: =SUM(D25:D28) -> 12191 | E29: =SUM(E25:E28) -> 33817 | F29: =SUM(F25:F28) -> 41321 | G29: =SUM(G25:G28) -> 39321 | I29: =SUM(I25:I28) -> 10700 | J29: =SUM(J25:J28) -> 10358 | K29: =SUM(K25:K28) -> 9979 | L29: =SUM(L25:L28) -> 10284 | M29: =SUM(M25:M28) -> 9958 | N29: =SUM(N25:N28) -> 9713 | O29: =SUM(O25:O28) -> 9623 | P29: =SUM(P25:P28) -> 10027 | ... S29: =SUM(S25:S28) -> 9045 | U29: =SUM(U25:U28) -> 41321 | V29: =SUM(V25:V28) -> 40579 | W29: =SUM(W25:W28) -> 39934 | X29: =SUM(X25:X28) -> 39578 | Y29: =SUM(Y25:Y28) -> 39321 | Z29: =SUM(Z25:Z28) -> 38342 | AA29: =SUM(AA25:AA28) -> 38441 | AB29: =SUM(AB25:AB28) -> 37863
B30: Variance Check | C30: =+C29-C13 -> 0 | D30: =+D29-D13 -> 0 | E30: =+E29-E13 -> 0 | F30: =+F29-F13 -> 0 | G30: =+G29-G13 -> 0 | I30: =+I29-I13 -> 0 | J30: =+J29-J13 -> 0 | K30: =+K29-K13 -> 0 | L30: =+L29-L13 -> 0 | M30: =+M29-M13 -> 0 | N30: =+N29-N13 -> 0 | O30: =+O29-O13 -> 0 | P30: =+P29-P13 -> 0 | ... S30: =+S29-S13 -> 0 | U30: =+U29-U13 -> 0 | V30: =+V29-V13 -> 0 | W30: =+W29-W13 -> 0 | X30: =+X29-X13 -> 0 | Y30: =+Y29-Y13 -> 0 | Z30: =+Z29-Z13 -> 0 | AA30: =+AA29-AA13 -> 0 | AB30: =+AB29-AB13 -> 0
B32: =B25&"(%)" -> Studios(%) | C32: =SUM(C25/C$29) -> 0.0011245432 | D32: =SUM(D25/D$29) -> 0.0016405545 | E32: =SUM(E25/E$13) -> 0.28775468 | F32: =SUM(F25/F$13) -> 0.29505578 | G32: =SUM(G25/G$13) -> 0.29518578 | I32: =SUM(I25/I$13) -> 0.30018692 | J32: =SUM(J25/J$13) -> 0.24917938 | K32: =SUM(K25/K$13) -> 0.32327889 | L32: =SUM(L25/L$13) -> 0.30853753 | M32: =SUM(M25/M$13) -> 0.28328982 | N32: =SUM(N25/N$13) -> 0.25213631 | O32: =SUM(O25/O$13) -> 0.27849943 | P32: =SUM(P25/P$13) -> 0.36471527 | ... S32: =SUM(S25/S$13) -> 0.36716418 | U32: =L32 -> 0.30853753 | V32: =M32 -> 0.28328982 | W32: =N32 -> 0.25213631 | X32: =O32 -> 0.27849943 | Y32: =P32 -> 0.36471527 | Z32: =Q32 -> 0.25771244 | AA32: =R32 -> 0.3873828 | AB32: =S32 -> 0.36716418
B33: =B26&"(%)" -> Networks(%) | C33: =SUM(C26/C$29) -> 0.97825883 | D33: =SUM(D26/D$29) -> 0.9278156 | E33: =SUM(E26/E$13) -> 0.57213827 | F33: =SUM(F26/F$13) -> 0.51412115 | G33: =SUM(G26/G$13) -> 0.51308461 | I33: =SUM(I26/I$13) -> 0.52158879 | J33: =SUM(J26/J$13) -> 0.55589882 | K33: =SUM(K26/K$13) -> 0.48782443 | L33: =SUM(L26/L$13) -> 0.48978996 | M33: =SUM(M26/M$13) -> 0.51466158 | N33: =SUM(N26/N$13) -> 0.54277772 | O33: =SUM(O26/O$13) -> 0.52062766 | P33: =SUM(P26/P$13) -> 0.47551611 | ... S33: =SUM(S26/S$13) -> 0.42929795 | U33: =L33 -> 0.48978996 | V33: =M33 -> 0.51466158 | W33: =N33 -> 0.54277772 | X33: =O33 -> 0.52062766 | Y33: =P33 -> 0.47551611 | Z33: =Q33 -> 0.53168504 | AA33: =R33 -> 0.48950265 | AB33: =S33 -> 0.42929795
B34: =B27&"(%)" -> Streaming(%) | C34: =SUM(C27/C$29) -> 0.020616624 | D34: =SUM(D27/D$29) -> 0.070543844 | E34: =SUM(E27/E$13) -> 0.21509891 | F34: =SUM(F27/F$13) -> 0.24573461 | G34: =SUM(G27/G$13) -> 0.26227715 | I34: =SUM(I27/I$13) -> 0.22943925 | J34: =SUM(J27/J$13) -> 0.26375748 | K34: =SUM(K27/K$13) -> 0.24431306 | L34: =SUM(L27/L$13) -> 0.24591599 | M34: =SUM(M27/M$13) -> 0.24703756 | N34: =SUM(N27/N$13) -> 0.26438793 | O34: =SUM(O27/O$13) -> 0.27371921 | P34: =SUM(P27/P$13) -> 0.26438616 | ... S34: =SUM(S27/S$13) -> 0.29110006 | U34: =L34 -> 0.24591599 | V34: =M34 -> 0.24703756 | W34: =N34 -> 0.26438793 | X34: =O34 -> 0.27371921 | Y34: =P34 -> 0.26438616 | Z34: =Q34 -> 0.29580131 | AA34: =R34 -> 0.28465145 | AB34: =S34 -> 0.29110006
A36: X | B36: Studios Segment Analysis
A38: X | B38: Revenue by Type: Studios Segment
B39: Distribution | C39: 0 | D39: 0 | E39: 12 | F39: 17 | G39: 8 | I39: 3 | J39: 3 | K39: 13 | L39: =SUM(F39-SUM(I39:K39)) -> -2 | M39: 5 | N39: 3 | O39: 6 | P39: =SUM(G39-SUM(M39:O39)) -> -6 | Q39: 1 | R39: 1 | S39: 2 | U39: =SUM(I39:L39) -> 17 | V39: =SUM(J39:M39) -> 19 | W39: =SUM(K39:N39) -> 19 | X39: =SUM(L39:O39) -> 12 | Y39: =SUM(M39:P39) -> 8 | Z39: =SUM(N39:Q39) -> 4 | AA39: =SUM(O39:R39) -> 2 | AB39: =SUM(P39:S39) -> -2
B40: Advertising | C40: 0 | D40: 0 | E40: 15 | F40: 15 | G40: 5 | I40: 3 | J40: 4 | K40: 4 | L40: =SUM(F40-SUM(I40:K40)) -> 4 | M40: 4 | N40: 0 | O40: 1 | P40: =SUM(G40-SUM(M40:O40)) -> 0 | Q40: 1 | R40: 0 | S40: 0 | U40: =SUM(I40:L40) -> 15 | V40: =SUM(J40:M40) -> 16 | W40: =SUM(K40:N40) -> 12 | X40: =SUM(L40:O40) -> 9 | Y40: =SUM(M40:P40) -> 5 | Z40: =SUM(N40:Q40) -> 2 | AA40: =SUM(O40:R40) -> 2 | AB40: =SUM(P40:S40) -> 1
B41: Content | C41: 12 | D41: 20 | E41: 9156 | F41: 11358 | G41: 10717 | I41: 3027 | J41: 2398 | K41: 3000 | L41: =SUM(F41-SUM(I41:K41)) -> 2933 | M41: 2623 | N41: 2237 | O41: 2463 | P41: =SUM(G41-SUM(M41:O41)) -> 3394 | Q41: 2139 | R41: 3591 | S41: 3111 | U41: =SUM(I41:L41) -> 11358 | V41: =SUM(J41:M41) -> 10954 | W41: =SUM(K41:N41) -> 10793 | X41: =SUM(L41:O41) -> 10256 | Y41: =SUM(M41:P41) -> 10717 | Z41: =SUM(N41:Q41) -> 10233 | AA41: =SUM(O41:R41) -> 11587 | AB41: =SUM(P41:S41) -> 12235
B42: Other | C42: 0 | D42: 0 | E42: 548 | F42: 802 | G42: 877 | I42: 179 | J42: 176 | K42: 209 | L42: =SUM(F42-SUM(I42:K42)) -> 238 | M42: 189 | N42: 209 | O42: 210 | P42: =SUM(G42-SUM(M42:O42)) -> 269 | Q42: 173 | R42: 209 | S42: 208 | U42: =SUM(I42:L42) -> 802 | V42: =SUM(J42:M42) -> 812 | W42: =SUM(K42:N42) -> 845 | X42: =SUM(L42:O42) -> 846 | Y42: =SUM(M42:P42) -> 877 | Z42: =SUM(N42:Q42) -> 861 | AA42: =SUM(O42:R42) -> 861 | AB42: =SUM(P42:S42) -> 859
B43: Total Net Revenue from Studios Segment | C43: =SUM(C39:C42) -> 12 | D43: =SUM(D39:D42) -> 20 | E43: =SUM(E39:E42) -> 9731 | F43: =SUM(F39:F42) -> 12192 | G43: =SUM(G39:G42) -> 11607 | I43: =SUM(I39:I42) -> 3212 | J43: =SUM(J39:J42) -> 2581 | K43: =SUM(K39:K42) -> 3226 | L43: =SUM(L39:L42) -> 3173 | M43: =SUM(M39:M42) -> 2821 | N43: =SUM(N39:N42) -> 2449 | O43: =SUM(O39:O42) -> 2680 | P43: =SUM(P39:P42) -> 3657 | ... S43: =SUM(S39:S42) -> 3321 | U43: =SUM(U39:U42) -> 12192 | V43: =SUM(V39:V42) -> 11801 | W43: =SUM(W39:W42) -> 11669 | X43: =SUM(X39:X42) -> 11123 | Y43: =SUM(Y39:Y42) -> 11607 | Z43: =SUM(Z39:Z42) -> 11100 | AA43: =SUM(AA39:AA42) -> 12452 | AB43: =SUM(AB39:AB42) -> 13093
B44: Variance Check | C44: =+C43-C25 -> 0 | D44: =+D43-D25 -> 0 | E44: =+E43-E25 -> 0 | F44: =+F43-F25 -> 0 | G44: =+G43-G25 -> 0 | I44: =+I43-I25 -> 0 | J44: =+J43-J25 -> 0 | K44: =+K43-K25 -> 0 | L44: =+L43-L25 -> 0 | M44: =+M43-M25 -> 0 | N44: =+N43-N25 -> 0 | O44: =+O43-O25 -> 0 | P44: =+P43-P25 -> 0 | ... S44: =+S43-S25 -> 0 | U44: =+U43-U25 -> 0 | V44: =+V43-V25 -> 0 | W44: =+W43-W25 -> 0 | X44: =+X43-X25 -> 0 | Y44: =+Y43-Y25 -> 0 | Z44: =+Z43-Z25 -> 0 | AA44: =+AA43-AA25 -> 0 | AB44: =+AB43-AB25 -> 0
B46: =B39&"(%)" -> Distribution(%) | C46: =SUM(C39/C$43) -> 0 | D46: =SUM(D39/D$43) -> 0 | E46: =SUM(E39/E$43) -> 0.0012331723 | F46: =SUM(F39/F$43) -> 0.001394357 | G46: =SUM(G39/G$43) -> 0.00068923925 | I46: =SUM(I39/I$43) -> 0.00093399751 | J46: =SUM(J39/J$43) -> 0.0011623402 | K46: =SUM(K39/K$43) -> 0.0040297582 | L46: =SUM(L39/L$43) -> -0.00063031831 | M46: =SUM(M39/M$43) -> 0.0017724211 | N46: =SUM(N39/N$43) -> 0.0012249898 | O46: =SUM(O39/O$43) -> 0.002238806 | P46: =SUM(P39/P$43) -> -0.0016406891 | ... S46: =SUM(S39/S$43) -> 0.00060222824 | U46: =SUM(U39/U$43) -> 0.001394357 | V46: =SUM(V39/V$43) -> 0.001610033 | W46: =SUM(W39/W$43) -> 0.0016282458 | X46: =SUM(X39/X$43) -> 0.0010788456 | Y46: =SUM(Y39/Y$43) -> 0.00068923925 | Z46: =SUM(Z39/Z$43) -> 0.00036036036 | AA46: =SUM(AA39/AA$43) -> 0.00016061677 | AB46: =SUM(AB39/AB$43) -> -0.00015275338
B47: =B40&"(%)" -> Advertising(%) | C47: =SUM(C40/C$43) -> 0 | D47: =SUM(D40/D$43) -> 0 | E47: =SUM(E40/E$43) -> 0.0015414654 | F47: =SUM(F40/F$43) -> 0.001230315 | G47: =SUM(G40/G$43) -> 0.00043077453 | I47: =SUM(I40/I$43) -> 0.00093399751 | J47: =SUM(J40/J$43) -> 0.0015497869 | K47: =SUM(K40/K$43) -> 0.0012399256 | L47: =SUM(L40/L$43) -> 0.0012606366 | M47: =SUM(M40/M$43) -> 0.0014179369 | N47: =SUM(N40/N$43) -> 0 | O47: =SUM(O40/O$43) -> 0.00037313433 | P47: =SUM(P40/P$43) -> 0 | ... S47: =SUM(S40/S$43) -> 0 | U47: =SUM(U40/U$43) -> 0.001230315 | V47: =SUM(V40/V$43) -> 0.0013558173 | W47: =SUM(W40/W$43) -> 0.0010283658 | X47: =SUM(X40/X$43) -> 0.00080913423 | Y47: =SUM(Y40/Y$43) -> 0.00043077453 | Z47: =SUM(Z40/Z$43) -> 0.00018018018 | AA47: =SUM(AA40/AA$43) -> 0.00016061677 | AB47: =SUM(AB40/AB$43) -> 7.637669e-05
B48: =B41&"(%)" -> Content(%) | C48: =SUM(C41/C$43) -> 1 | D48: =SUM(D41/D$43) -> 1 | E48: =SUM(E41/E$43) -> 0.94091049 | F48: =SUM(F41/F$43) -> 0.93159449 | G48: =SUM(G41/G$43) -> 0.92332213 | I48: =SUM(I41/I$43) -> 0.94240349 | J48: =SUM(J41/J$43) -> 0.92909725 | K48: =SUM(K41/K$43) -> 0.9299442 | L48: =SUM(L41/L$43) -> 0.9243618 | M48: =SUM(M41/M$43) -> 0.92981212 | N48: =SUM(N41/N$43) -> 0.91343405 | O48: =SUM(O41/O$43) -> 0.91902985 | P48: =SUM(P41/P$43) -> 0.92808313 | ... S48: =SUM(S41/S$43) -> 0.93676603 | U48: =SUM(U41/U$43) -> 0.93159449 | V48: =SUM(V41/V$43) -> 0.92822642 | W48: =SUM(W41/W$43) -> 0.9249293 | X48: =SUM(X41/X$43) -> 0.9220534 | Y48: =SUM(Y41/Y$43) -> 0.92332213 | Z48: =SUM(Z41/Z$43) -> 0.92189189 | AA48: =SUM(AA41/AA$43) -> 0.93053325 | AB48: =SUM(AB41/AB$43) -> 0.9344688
B49: =B42&"(%)" -> Other(%) | C49: =SUM(C42/C$43) -> 0 | D49: =SUM(D42/D$43) -> 0 | E49: =SUM(E42/E$43) -> 0.05631487 | F49: =SUM(F42/F$43) -> 0.06578084 | G49: =SUM(G42/G$43) -> 0.075557853 | I49: =SUM(I42/I$43) -> 0.055728518 | J49: =SUM(J42/J$43) -> 0.068190624 | K49: =SUM(K42/K$43) -> 0.064786113 | L49: =SUM(L42/L$43) -> 0.075007879 | M49: =SUM(M42/M$43) -> 0.066997519 | N49: =SUM(N42/N$43) -> 0.085340955 | O49: =SUM(O42/O$43) -> 0.078358209 | P49: =SUM(P42/P$43) -> 0.073557561 | ... S49: =SUM(S42/S$43) -> 0.062631737 | U49: =SUM(U42/U$43) -> 0.06578084 | V49: =SUM(V42/V$43) -> 0.068807728 | W49: =SUM(W42/W$43) -> 0.072414089 | X49: =SUM(X42/X$43) -> 0.076058617 | Y49: =SUM(Y42/Y$43) -> 0.075557853 | Z49: =SUM(Z42/Z$43) -> 0.077567568 | AA49: =SUM(AA42/AA$43) -> 0.069145519 | AB49: =SUM(AB42/AB$43) -> 0.065607577
A51: X | B51: Studios Segment: Operating Income & Adj. EBITDA Analysis
B52: =B39 -> Distribution | C52: =C39 -> 0 | D52: =D39 -> 0 | E52: =E39 -> 12 | F52: =F39 -> 17 | G52: =G39 -> 8 | I52: =I39 -> 3 | J52: =J39 -> 3 | K52: =K39 -> 13 | L52: =SUM(F52-SUM(I52:K52)) -> -2 | M52: =M39 -> 5 | N52: =N39 -> 3 | O52: =O39 -> 6 | P52: =SUM(G52-SUM(M52:O52)) -> -6 | Q52: =Q39 -> 1 | R52: =R39 -> 1 | S52: =S39 -> 2 | U52: =SUM(I52:L52) -> 17 | V52: =SUM(J52:M52) -> 19 | W52: =SUM(K52:N52) -> 19 | X52: =SUM(L52:O52) -> 12 | Y52: =SUM(M52:P52) -> 8 | Z52: =SUM(N52:Q52) -> 4 | AA52: =SUM(O52:R52) -> 2 | AB52: =SUM(P52:S52) -> -2
B53: =B40 -> Advertising | C53: =C40 -> 0 | D53: =D40 -> 0 | E53: =E40 -> 15 | F53: =F40 -> 15 | G53: =G40 -> 5 | I53: =I40 -> 3 | J53: =J40 -> 4 | K53: =K40 -> 4 | L53: =SUM(F53-SUM(I53:K53)) -> 4 | M53: =M40 -> 4 | N53: =N40 -> 0 | O53: =O40 -> 1 | P53: =SUM(G53-SUM(M53:O53)) -> 0 | Q53: =Q40 -> 1 | R53: =R40 -> 0 | S53: =S40 -> 0 | U53: =SUM(I53:L53) -> 15 | V53: =SUM(J53:M53) -> 16 | W53: =SUM(K53:N53) -> 12 | X53: =SUM(L53:O53) -> 9 | Y53: =SUM(M53:P53) -> 5 | Z53: =SUM(N53:Q53) -> 2 | AA53: =SUM(O53:R53) -> 2 | AB53: =SUM(P53:S53) -> 1
B54: =B41 -> Content | C54: =C41 -> 12 | D54: =D41 -> 20 | E54: =E41 -> 9156 | F54: =F41 -> 11358 | G54: =G41 -> 10717 | I54: =I41 -> 3027 | J54: =J41 -> 2398 | K54: =K41 -> 3000 | L54: =SUM(F54-SUM(I54:K54)) -> 2933 | M54: =M41 -> 2623 | N54: =N41 -> 2237 | O54: =O41 -> 2463 | P54: =SUM(G54-SUM(M54:O54)) -> 3394 | Q54: =Q41 -> 2139 | R54: =R41 -> 3591 | S54: =S41 -> 3111 | U54: =SUM(I54:L54) -> 11358 | V54: =SUM(J54:M54) -> 10954 | W54: =SUM(K54:N54) -> 10793 | X54: =SUM(L54:O54) -> 10256 | Y54: =SUM(M54:P54) -> 10717 | Z54: =SUM(N54:Q54) -> 10233 | AA54: =SUM(O54:R54) -> 11587 | AB54: =SUM(P54:S54) -> 12235
B55: =B42 -> Other | C55: =C42 -> 0 | D55: =D42 -> 0 | E55: =E42 -> 548 | F55: =F42 -> 802 | G55: =G42 -> 877 | I55: =I42 -> 179 | J55: =J42 -> 176 | K55: =K42 -> 209 | L55: =SUM(F55-SUM(I55:K55)) -> 238 | M55: =M42 -> 189 | N55: =N42 -> 209 | O55: =O42 -> 210 | P55: =SUM(G55-SUM(M55:O55)) -> 269 | Q55: =Q42 -> 173 | R55: =R42 -> 209 | S55: =S42 -> 208 | U55: =SUM(I55:L55) -> 802 | V55: =SUM(J55:M55) -> 812 | W55: =SUM(K55:N55) -> 845 | X55: =SUM(L55:O55) -> 846 | Y55: =SUM(M55:P55) -> 877 | Z55: =SUM(N55:Q55) -> 861 | AA55: =SUM(O55:R55) -> 861 | AB55: =SUM(P55:S55) -> 859
B56: Total Revenue | C56: =SUM(C52:C55) -> 12 | D56: =SUM(D52:D55) -> 20 | E56: =SUM(E52:E55) -> 9731 | F56: =SUM(F52:F55) -> 12192 | G56: =SUM(G52:G55) -> 11607 | I56: =SUM(I52:I55) -> 3212 | J56: =SUM(J52:J55) -> 2581 | K56: =SUM(K52:K55) -> 3226 | L56: =SUM(L52:L55) -> 3173 | M56: =SUM(M52:M55) -> 2821 | N56: =SUM(N52:N55) -> 2449 | O56: =SUM(O52:O55) -> 2680 | P56: =SUM(P52:P55) -> 3657 | ... S56: =SUM(S52:S55) -> 3321 | U56: =SUM(U52:U55) -> 12192 | V56: =SUM(V52:V55) -> 11801 | W56: =SUM(W52:W55) -> 11669 | X56: =SUM(X52:X55) -> 11123 | Y56: =SUM(Y52:Y55) -> 11607 | Z56: =SUM(Z52:Z55) -> 11100 | AA56: =SUM(AA52:AA55) -> 12452 | AB56: =SUM(AB52:AB55) -> 13093
L57: =SUM(E57-SUM(I57:K57)) -> 0 | P57: =SUM(F57-SUM(M57:O57)) -> 0 | U57: =SUM(K57:N57) -> 0 | V57: =SUM(L57:O57) -> 0 | W57: =SUM(M57:P57) -> 0 | X57: =SUM(N57:Q57) -> 0 | Y57: =SUM(O57:R57) -> 0 | Z57: =SUM(P57:S57) -> 0 | AA57: =SUM(Q57:S57) -> 0 | AB57: =SUM(R57:S57) -> 0
B58: Costs of revenues, excluding depreciation and amortization | D58: -3 | E58: -6310 | F58: -7296 | G58: -7530 | I58: -1959 | J58: -1645 | K58: -1794 | L58: =SUM(F58-SUM(I58:K58)) -> -1898 | M58: -2019 | N58: -1601 | O58: -1736 | P58: =SUM(G58-SUM(M58:O58)) -> -2174 | Q58: -1413 | R58: -2215 | S58: -1897 | U58: =SUM(I58:L58) -> -7296 | V58: =SUM(J58:M58) -> -7356 | W58: =SUM(K58:N58) -> -7312 | X58: =SUM(L58:O58) -> -7254 | Y58: =SUM(M58:P58) -> -7530 | Z58: =SUM(N58:Q58) -> -6924 | AA58: =SUM(O58:R58) -> -7538 | AB58: =SUM(P58:S58) -> -7699
B59: Gross Profit | C59: =SUM(C56+C58) -> 12 | D59: =SUM(D56+D58) -> 17 | E59: =SUM(E56+E58) -> 3421 | F59: =SUM(F56+F58) -> 4896 | G59: =SUM(G56+G58) -> 4077 | I59: =SUM(I56+I58) -> 1253 | J59: =SUM(J56+J58) -> 936 | K59: =SUM(K56+K58) -> 1432 | L59: =SUM(L56+L58) -> 1275 | M59: =SUM(M56+M58) -> 802 | N59: =SUM(N56+N58) -> 848 | O59: =SUM(O56+O58) -> 944 | P59: =SUM(P56+P58) -> 1483 | ... S59: =SUM(S56+S58) -> 1424 | U59: =SUM(U56+U58) -> 4896 | V59: =SUM(V56+V58) -> 4445 | W59: =SUM(W56+W58) -> 4357 | X59: =SUM(X56+X58) -> 3869 | Y59: =SUM(Y56+Y58) -> 4077 | Z59: =SUM(Z56+Z58) -> 4176 | AA59: =SUM(AA56+AA58) -> 4914 | AB59: =SUM(AB56+AB58) -> 5394
B60: Gross Margin (%) | C60: =C59/C56 -> 1 | D60: =D59/D56 -> 0.85 | E60: =E59/E56 -> 0.35155688 | F60: =F59/F56 -> 0.4015748 | G60: =G59/G56 -> 0.35125355 | I60: =I59/I56 -> 0.39009963 | J60: =J59/J56 -> 0.36265014 | K60: =K59/K56 -> 0.44389337 | L60: =L59/L56 -> 0.40182792 | M60: =M59/M56 -> 0.28429635 | N60: =N59/N56 -> 0.34626378 | O60: =O59/O56 -> 0.35223881 | P60: =P59/P56 -> 0.40552365 | ... S60: =S59/S56 -> 0.42878651 | U60: =U59/U56 -> 0.4015748 | V60: =V59/V56 -> 0.37666299 | W60: =W59/W56 -> 0.37338247 | X60: =X59/X56 -> 0.34783781 | Y60: =Y59/Y56 -> 0.35125355 | Z60: =Z59/Z56 -> 0.37621622 | AA60: =AA59/AA56 -> 0.3946354 | AB60: =AB59/AB56 -> 0.41197586
L61: =SUM(E61-SUM(I61:K61)) -> 0 | P61: =SUM(F61-SUM(M61:O61)) -> 0 | U61: =SUM(K61:N61) -> 0 | V61: =SUM(L61:O61) -> 0 | W61: =SUM(M61:P61) -> 0 | X61: =SUM(N61:Q61) -> 0 | Y61: =SUM(O61:R61) -> 0 | Z61: =SUM(P61:S61) -> 0 | AA61: =SUM(Q61:S61) -> 0 | AB61: =SUM(R61:S61) -> 0
B62: Selling, general and administrative | D62: -3 | E62: -1649 | F62: -2713 | G62: -2425 | I62: -646 | J62: -630 | K62: -705 | L62: =SUM(F62-SUM(I62:K62)) -> -732 | M62: -618 | N62: -638 | O62: -636 | P62: =SUM(G62-SUM(M62:O62)) -> -533 | Q62: -642 | R62: -723 | S62: -729 | U62: =SUM(I62:L62) -> -2713 | V62: =SUM(J62:M62) -> -2685 | W62: =SUM(K62:N62) -> -2693 | X62: =SUM(L62:O62) -> -2624 | Y62: =SUM(M62:P62) -> -2425 | Z62: =SUM(N62:Q62) -> -2449 | AA62: =SUM(O62:R62) -> -2534 | AB62: =SUM(P62:S62) -> -2627
B63: Adjusted EBITDA | C63: =SUM(C59+C62) -> 12 | D63: =SUM(D59+D62) -> 14 | E63: =SUM(E59+E62) -> 1772 | F63: =SUM(F59+F62) -> 2183 | G63: =SUM(G59+G62) -> 1652 | I63: =SUM(I59+I62) -> 607 | J63: =SUM(J59+J62) -> 306 | K63: =SUM(K59+K62) -> 727 | L63: =SUM(L59+L62) -> 543 | M63: =SUM(M59+M62) -> 184 | N63: =SUM(N59+N62) -> 210 | O63: =SUM(O59+O62) -> 308 | P63: =SUM(P59+P62) -> 950 | ... S63: =SUM(S59+S62) -> 695 | U63: =SUM(U59+U62) -> 2183 | V63: =SUM(V59+V62) -> 1760 | W63: =SUM(W59+W62) -> 1664 | X63: =SUM(X59+X62) -> 1245 | Y63: =SUM(Y59+Y62) -> 1652 | Z63: =SUM(Z59+Z62) -> 1727 | AA63: =SUM(AA59+AA62) -> 2380 | AB63: =SUM(AB59+AB62) -> 2767
B64: Adjusted EBITDA Margin (%) | C64: =C63/C56 -> 1 | D64: =D63/D56 -> 0.7 | E64: =E63/E56 -> 0.18209845 | F64: =F63/F56 -> 0.17905184 | G64: =G63/G56 -> 0.14232791 | I64: =I63/I56 -> 0.18897883 | J64: =J63/J56 -> 0.1185587 | K64: =K63/K56 -> 0.22535648 | L64: =L63/L56 -> 0.17113142 | M64: =M63/M56 -> 0.065225097 | N64: =N63/N56 -> 0.085749285 | O64: =O63/O56 -> 0.11492537 | P64: =P63/P56 -> 0.25977577 | ... S64: =S63/S56 -> 0.20927431 | U64: =U63/U56 -> 0.17905184 | V64: =V63/V56 -> 0.1491399 | W64: =W63/W56 -> 0.14260005 | X64: =X63/X56 -> 0.11193023 | Y64: =Y63/Y56 -> 0.14232791 | Z64: =Z63/Z56 -> 0.15558559 | AA64: =AA63/AA56 -> 0.19113395 | AB64: =AB63/AB56 -> 0.2113343
B66: Depreciation and amortization | D66: 0 | E66: -501 | F66: -667 | G66: -702 | I66: -172 | J66: -143 | K66: -143 | L66: =SUM(F66-SUM(I66:K66)) -> -209 | M66: -186 | N66: -174 | O66: -171 | P66: =SUM(G66-SUM(M66:O66)) -> -171 | Q66: -170 | R66: -169 | S66: -170 | U66: =SUM(I66:L66) -> -667 | V66: =SUM(J66:M66) -> -681 | W66: =SUM(K66:N66) -> -712 | X66: =SUM(L66:O66) -> -740 | Y66: =SUM(M66:P66) -> -702 | Z66: =SUM(N66:Q66) -> -686 | AA66: =SUM(O66:R66) -> -681 | AB66: =SUM(P66:S66) -> -680
B67: Restructuring and other charges | D67: 0 | E67: -1050 | F67: -225 | G67: -263 | I67: -76 | J67: -10 | K67: -134 | L67: =SUM(F67-SUM(I67:K67)) -> -5 | M67: -11 | N67: -19 | O67: -2 | P67: =SUM(G67-SUM(M67:O67)) -> -231 | Q67: 5 | R67: 1 | S67: -12 | U67: =SUM(I67:L67) -> -225 | V67: =SUM(J67:M67) -> -160 | W67: =SUM(K67:N67) -> -169 | X67: =SUM(L67:O67) -> -37 | Y67: =SUM(M67:P67) -> -263 | Z67: =SUM(N67:Q67) -> -247 | AA67: =SUM(O67:R67) -> -227 | AB67: =SUM(P67:S67) -> -237
B68: Transaction and integration costs | D68: 0 | E68: -9 | F68: -7 | G68: -2 | I68: -2 | J68: -2 | K68: -1 | L68: =SUM(F68-SUM(I68:K68)) -> -2 | M68: -1 | N68: -1 | O68: 0 | P68: =SUM(G68-SUM(M68:O68)) -> 0 | Q68: 0 | R68: 0 | S68: 0 | U68: =SUM(I68:L68) -> -7 | V68: =SUM(J68:M68) -> -6 | W68: =SUM(K68:N68) -> -5 | X68: =SUM(L68:O68) -> -4 | Y68: =SUM(M68:P68) -> -2 | Z68: =SUM(N68:Q68) -> -1 | AA68: =SUM(O68:R68) -> 0 | AB68: =SUM(P68:S68) -> 0
B69: Facility consolidation costs | D69: 0 | E69: 0 | F69: 0 | G69: -1 | I69: 0 | J69: 0 | K69: 0 | L69: =SUM(F69-SUM(I69:K69)) -> 0 | M69: 0 | N69: -1 | O69: -1 | P69: =SUM(G69-SUM(M69:O69)) -> 1 | Q69: 0 | R69: 0 | S69: 0 | U69: =SUM(I69:L69) -> 0 | V69: =SUM(J69:M69) -> 0 | W69: =SUM(K69:N69) -> -1 | X69: =SUM(L69:O69) -> -2 | Y69: =SUM(M69:P69) -> -1 | Z69: =SUM(N69:Q69) -> -1 | AA69: =SUM(O69:R69) -> 0 | AB69: =SUM(P69:S69) -> 1
B70: Impairment and amortization of fair value step-up for content | D70: 0 | E70: -1370 | F70: -995 | G70: -96 | I70: -442 | J70: -271 | K70: -173 | L70: =SUM(F70-SUM(I70:K70)) -> -109 | M70: 72 | N70: -83 | O70: -34 | P70: =SUM(G70-SUM(M70:O70)) -> -51 | Q70: -36 | R70: -25 | S70: -33 | U70: =SUM(I70:L70) -> -995 | V70: =SUM(J70:M70) -> -481 | W70: =SUM(K70:N70) -> -293 | X70: =SUM(L70:O70) -> -154 | Y70: =SUM(M70:P70) -> -96 | Z70: =SUM(N70:Q70) -> -204 | AA70: =SUM(O70:R70) -> -146 | AB70: =SUM(P70:S70) -> -145
B71: Amortization of capitalized interest for content | D71: 0 | E71: 0 | F71: -46 | G71: -46 | I71: 0 | J71: -22 | K71: -12 | L71: =SUM(F71-SUM(I71:K71)) -> -12 | M71: -17 | N71: -13 | O71: -8 | P71: =SUM(G71-SUM(M71:O71)) -> -8 | Q71: -6 | R71: -3 | S71: -19 | U71: =SUM(I71:L71) -> -46 | V71: =SUM(J71:M71) -> -63 | W71: =SUM(K71:N71) -> -54 | X71: =SUM(L71:O71) -> -50 | Y71: =SUM(M71:P71) -> -46 | Z71: =SUM(N71:Q71) -> -35 | AA71: =SUM(O71:R71) -> -25 | AB71: =SUM(P71:S71) -> -36
B72: Impairments and loss on dispositions | D72: 0 | E72: -30 | F72: -1 | G72: -14 | I72: 0 | J72: 1 | K72: 0 | L72: =SUM(F72-SUM(I72:K72)) -> -2 | M72: 0 | N72: 1 | O72: 5 | P72: =SUM(G72-SUM(M72:O72)) -> -20 | Q72: 1 | R72: 0 | S72: 0 | U72: =SUM(I72:L72) -> -1 | V72: =SUM(J72:M72) -> -1 | W72: =SUM(K72:N72) -> -1 | X72: =SUM(L72:O72) -> 4 | Y72: =SUM(M72:P72) -> -14 | Z72: =SUM(N72:Q72) -> -13 | AA72: =SUM(O72:R72) -> -14 | AB72: =SUM(P72:S72) -> -19
B73: Inter-segment eliminations | D73: 0 | E73: -5 | F73: -31 | G73: 0 | I73: -1 | J73: 0 | K73: 0 | L73: =SUM(F73-SUM(I73:K73)) -> -30 | M73: 0 | N73: 0 | O73: 0 | P73: =SUM(G73-SUM(M73:O73)) -> 0 | Q73: 0 | R73: 0 | S73: 0 | U73: =SUM(I73:L73) -> -31 | V73: =SUM(J73:M73) -> -30 | W73: =SUM(K73:N73) -> -30 | X73: =SUM(L73:O73) -> -30 | Y73: =SUM(M73:P73) -> 0 | Z73: =SUM(N73:Q73) -> 0 | AA73: =SUM(O73:R73) -> 0 | AB73: =SUM(P73:S73) -> 0
B74: Employee share-based compensation | D74: 0 | E74: -1 | F74: 0 | G74: 1 | I74: 0 | J74: 0 | K74: 0 | L74: =SUM(F74-SUM(I74:K74)) -> 0 | M74: 1 | N74: 0 | O74: 0 | P74: =SUM(G74-SUM(M74:O74)) -> 0 | Q74: 0 | R74: 0 | S74: 0 | U74: =SUM(I74:L74) -> 0 | V74: =SUM(J74:M74) -> 1 | W74: =SUM(K74:N74) -> 1 | X74: =SUM(L74:O74) -> 1 | Y74: =SUM(M74:P74) -> 1 | Z74: =SUM(N74:Q74) -> 0 | AA74: =SUM(O74:R74) -> 0 | AB74: =SUM(P74:S74) -> 0
B75: Operating Income | C75: =SUM(C63+SUM(C66:C74)) -> 12 | D75: =SUM(D63+SUM(D66:D74)) -> 14 | E75: =SUM(E63+SUM(E66:E74)) -> -1194 | F75: =SUM(F63+SUM(F66:F74)) -> 211 | G75: =SUM(G63+SUM(G66:G74)) -> 529 | I75: =SUM(I63+SUM(I66:I74)) -> -86 | J75: =SUM(J63+SUM(J66:J74)) -> -141 | K75: =SUM(K63+SUM(K66:K74)) -> 264 | L75: =SUM(L63+SUM(L66:L74)) -> 174 | M75: =SUM(M63+SUM(M66:M74)) -> 42 | N75: =SUM(N63+SUM(N66:N74)) -> -80 | O75: =SUM(O63+SUM(O66:O74)) -> 97 | P75: =SUM(P63+SUM(P66:P74)) -> 470 | ... S75: =SUM(S63+SUM(S66:S74)) -> 461 | U75: =SUM(U63+SUM(U66:U74)) -> 211 | V75: =SUM(V63+SUM(V66:V74)) -> 339 | W75: =SUM(W63+SUM(W66:W74)) -> 400 | X75: =SUM(X63+SUM(X66:X74)) -> 233 | Y75: =SUM(Y63+SUM(Y66:Y74)) -> 529 | Z75: =SUM(Z63+SUM(Z66:Z74)) -> 540 | AA75: =SUM(AA63+SUM(AA66:AA74)) -> 1287 | AB75: =SUM(AB63+SUM(AB66:AB74)) -> 1651
B76: Operating Margin (%) | C76: =C75/C56 -> 1 | D76: =D75/D56 -> 0.7 | E76: =E75/E56 -> -0.12270065 | F76: =F75/F56 -> 0.01730643 | G76: =G75/G56 -> 0.045575946 | I76: =I75/I56 -> -0.026774595 | J76: =J75/J56 -> -0.054629988 | K76: =K75/K56 -> 0.08183509 | L76: =L75/L56 -> 0.054837693 | M76: =M75/M56 -> 0.014888337 | N76: =N75/N56 -> -0.032666394 | O76: =O75/O56 -> 0.03619403 | P76: =P75/P56 -> 0.12852065 | ... S76: =S75/S56 -> 0.13881361 | U76: =U75/U56 -> 0.01730643 | V76: =V75/V56 -> 0.028726379 | W76: =W75/W56 -> 0.034278859 | X76: =X75/X56 -> 0.020947586 | Y76: =Y75/Y56 -> 0.045575946 | Z76: =Z75/Z56 -> 0.048648649 | AA76: =AA75/AA56 -> 0.10335689 | AB76: =AB75/AB56 -> 0.12609791
A78: X | B78: Networks Segment Analysis
A80: X | B80: Revenue by Networks Segment
B81: Distribution | C81: 4496 | D81: 4486 | E81: 9759 | F81: 11521 | G81: 10680 | I81: 2995 | J81: 2941 | K81: 2833 | L81: =SUM(F81-SUM(I81:K81)) -> 2752 | M81: 2797 | N81: 2675 | O81: 2598 | P81: =SUM(G81-SUM(M81:O81)) -> 2610 | Q81: 2558 | R81: 2477 | S81: 2387 | U81: =SUM(I81:L81) -> 11521 | V81: =SUM(J81:M81) -> 11323 | W81: =SUM(K81:N81) -> 11057 | X81: =SUM(L81:O81) -> 10822 | Y81: =SUM(M81:P81) -> 10680 | Z81: =SUM(N81:Q81) -> 10441 | AA81: =SUM(O81:R81) -> 10243 | AB81: =SUM(P81:S81) -> 10032
B82: Advertising | C82: 5547 | D82: 6063 | E82: 8224 | F82: 8342 | G82: 7306 | I82: 2237 | J82: 2448 | K82: 1709 | L82: =SUM(F82-SUM(I82:K82)) -> 1948 | M82: 1987 | N82: 2214 | O82: 1490 | P82: =SUM(G82-SUM(M82:O82)) -> 1615 | Q82: 1758 | R82: 1953 | S82: 1186 | U82: =SUM(I82:L82) -> 8342 | V82: =SUM(J82:M82) -> 8092 | W82: =SUM(K82:N82) -> 7858 | X82: =SUM(L82:O82) -> 7639 | Y82: =SUM(M82:P82) -> 7306 | Z82: =SUM(N82:Q82) -> 7077 | AA82: =SUM(O82:R82) -> 6816 | AB82: =SUM(P82:S82) -> 6512
B83: Content | C83: 340 | D83: 706 | E83: 1120 | F83: 1005 | G83: 1848 | I83: 245 | J83: 284 | K83: 215 | L83: =SUM(F83-SUM(I83:K83)) -> 261 | M83: 264 | N83: 299 | O83: 833 | P83: =SUM(G83-SUM(M83:O83)) -> 452 | Q83: 380 | R83: 287 | S83: 217 | U83: =SUM(I83:L83) -> 1005 | V83: =SUM(J83:M83) -> 1024 | W83: =SUM(K83:N83) -> 1039 | X83: =SUM(L83:O83) -> 1657 | Y83: =SUM(M83:P83) -> 1848 | Z83: =SUM(N83:Q83) -> 1964 | AA83: =SUM(O83:R83) -> 1952 | AB83: =SUM(P83:S83) -> 1336
B84: Other | C84: 56 | D84: 56 | E84: 245 | F84: 376 | G84: 341 | I84: 104 | J84: 85 | K84: 111 | L84: =SUM(F84-SUM(I84:K84)) -> 76 | M84: 77 | N84: 84 | O84: 89 | P84: =SUM(G84-SUM(M84:O84)) -> 91 | Q84: 78 | R84: 86 | S84: 93 | U84: =SUM(I84:L84) -> 376 | V84: =SUM(J84:M84) -> 349 | W84: =SUM(K84:N84) -> 348 | X84: =SUM(L84:O84) -> 326 | Y84: =SUM(M84:P84) -> 341 | Z84: =SUM(N84:Q84) -> 342 | AA84: =SUM(O84:R84) -> 344 | AB84: =SUM(P84:S84) -> 348
B85: Total Revenue from Networks Segment | C85: =SUM(C81:C84) -> 10439 | D85: =SUM(D81:D84) -> 11311 | E85: =SUM(E81:E84) -> 19348 | F85: =SUM(F81:F84) -> 21244 | G85: =SUM(G81:G84) -> 20175 | I85: =SUM(I81:I84) -> 5581 | J85: =SUM(J81:J84) -> 5758 | K85: =SUM(K81:K84) -> 4868 | L85: =SUM(L81:L84) -> 5037 | M85: =SUM(M81:M84) -> 5125 | N85: =SUM(N81:N84) -> 5272 | O85: =SUM(O81:O84) -> 5010 | P85: =SUM(P81:P84) -> 4768 | ... S85: =SUM(S81:S84) -> 3883 | U85: =SUM(U81:U84) -> 21244 | V85: =SUM(V81:V84) -> 20788 | W85: =SUM(W81:W84) -> 20302 | X85: =SUM(X81:X84) -> 20444 | Y85: =SUM(Y81:Y84) -> 20175 | Z85: =SUM(Z81:Z84) -> 19824 | AA85: =SUM(AA81:AA84) -> 19355 | AB85: =SUM(AB81:AB84) -> 18228
B86: Variance Check | C86: =+C85-C26 -> 0 | D86: =+D85-D26 -> 0 | E86: =+E85-E26 -> 0 | F86: =+F85-F26 -> 0 | G86: =+G85-G26 -> 0 | I86: =+I85-I26 -> 0 | J86: =+J85-J26 -> 0 | K86: =+K85-K26 -> 0 | L86: =+L85-L26 -> 0 | M86: =+M85-M26 -> 0 | N86: =+N85-N26 -> 0 | O86: =+O85-O26 -> 0 | P86: =+P85-P26 -> 0 | ... S86: =+S85-S26 -> 0 | U86: =+U85-U26 -> 0 | V86: =+V85-V26 -> 0 | W86: =+W85-W26 -> 0 | X86: =+X85-X26 -> 0 | Y86: =+Y85-Y26 -> 0 | Z86: =+Z85-Z26 -> 0 | AA86: =+AA85-AA26 -> 0 | AB86: =+AB85-AB26 -> 0
B88: =B81&"(%)" -> Distribution(%) | C88: =C81/C$85 -> 0.4306926 | D88: =D81/D$85 -> 0.39660507 | E88: =E81/E$85 -> 0.50439322 | F88: =F81/F$85 -> 0.54231783 | G88: =G81/G$85 -> 0.52936803 | I88: =I81/I$85 -> 0.53664218 | J88: =J81/J$85 -> 0.51076763 | K88: =K81/K$85 -> 0.58196385 | L88: =L81/L$85 -> 0.54635696 | M88: =M81/M$85 -> 0.5457561 | N88: =N81/N$85 -> 0.50739757 | O88: =O81/O$85 -> 0.51856287 | P88: =P81/P$85 -> 0.54739933 | ... S88: =S81/S$85 -> 0.61473088 | U88: =U81/U$85 -> 0.54231783 | V88: =V81/V$85 -> 0.54468924 | W88: =W81/W$85 -> 0.54462615 | X88: =X81/X$85 -> 0.52934846 | Y88: =Y81/Y$85 -> 0.52936803 | Z88: =Z81/Z$85 -> 0.52668483 | AA88: =AA81/AA$85 -> 0.52921726 | AB88: =AB81/AB$85 -> 0.55036208
B89: =B82&"(%)" -> Advertising(%) | C89: =C82/C$85 -> 0.53137274 | D89: =D82/D$85 -> 0.53602688 | E89: =E82/E$85 -> 0.42505685 | F89: =F82/F$85 -> 0.39267558 | G89: =G82/G$85 -> 0.36213135 | I89: =I82/I$85 -> 0.40082423 | J89: =J82/J$85 -> 0.42514762 | K89: =K82/K$85 -> 0.3510682 | L89: =L82/L$85 -> 0.38673814 | M89: =M82/M$85 -> 0.38770732 | N89: =N82/N$85 -> 0.41995448 | O89: =O82/O$85 -> 0.29740519 | P89: =P82/P$85 -> 0.33871644 | ... S89: =S82/S$85 -> 0.30543394 | U89: =U82/U$85 -> 0.39267558 | V89: =V82/V$85 -> 0.38926304 | W89: =W82/W$85 -> 0.38705546 | X89: =X82/X$85 -> 0.37365486 | Y89: =Y82/Y$85 -> 0.36213135 | Z89: =Z82/Z$85 -> 0.35699153 | AA89: =AA82/AA$85 -> 0.35215707 | AB89: =AB82/AB$85 -> 0.35725258
B90: =B83&"(%)" -> Content(%) | C90: =C83/C$85 -> 0.03257017 | D90: =D83/D$85 -> 0.062417116 | E90: =E83/E$85 -> 0.05788712 | F90: =F83/F$85 -> 0.047307475 | G90: =G83/G$85 -> 0.091598513 | I90: =I83/I$85 -> 0.043898943 | J90: =J83/J$85 -> 0.049322681 | K90: =K83/K$85 -> 0.044165982 | L90: =L83/L$85 -> 0.051816557 | M90: =M83/M$85 -> 0.051512195 | N90: =N83/N$85 -> 0.056714719 | O90: =O83/O$85 -> 0.16626747 | P90: =P83/P$85 -> 0.094798658 | ... S90: =S83/S$85 -> 0.055884625 | U90: =U83/U$85 -> 0.047307475 | V90: =V83/V$85 -> 0.049259188 | W90: =W83/W$85 -> 0.051177224 | X90: =X83/X$85 -> 0.081050675 | Y90: =Y83/Y$85 -> 0.091598513 | Z90: =Z83/Z$85 -> 0.099071832 | AA90: =AA83/AA$85 -> 0.10085249 | AB90: =AB83/AB$85 -> 0.073293834
B91: =B84&"(%)" -> Other(%) | C91: =C84/C$85 -> 0.0053644985 | D91: =D84/D$85 -> 0.0049509327 | E91: =E84/E$85 -> 0.012662808 | F91: =F84/F$85 -> 0.017699115 | G91: =G84/G$85 -> 0.016902107 | I91: =I84/I$85 -> 0.018634653 | J91: =J84/J$85 -> 0.01476207 | K91: =K84/K$85 -> 0.022801972 | L91: =L84/L$85 -> 0.015088346 | M91: =M84/M$85 -> 0.01502439 | N91: =N84/N$85 -> 0.015933232 | O91: =O84/O$85 -> 0.017764471 | P91: =P84/P$85 -> 0.01908557 | ... S91: =S84/S$85 -> 0.023950554 | U91: =U84/U$85 -> 0.017699115 | V91: =V84/V$85 -> 0.016788532 | W91: =W84/W$85 -> 0.017141168 | X91: =X84/X$85 -> 0.015945999 | Y91: =Y84/Y$85 -> 0.016902107 | Z91: =Z84/Z$85 -> 0.017251816 | AA91: =AA84/AA$85 -> 0.017773185 | AB91: =AB84/AB$85 -> 0.019091508
A93: X | B93: Networks Segment: Operating Income & Adj. EBITDA Analysis
B94: =B81 -> Distribution | C94: =C81 -> 4496 | D94: =D81 -> 4486 | E94: =E81 -> 9759 | F94: =F81 -> 11521 | G94: =G81 -> 10680 | I94: =I81 -> 2995 | J94: =J81 -> 2941 | K94: =K81 -> 2833 | L94: =SUM(F94-SUM(I94:K94)) -> 2752 | M94: =M81 -> 2797 | N94: =N81 -> 2675 | O94: =O81 -> 2598 | P94: =SUM(G94-SUM(M94:O94)) -> 2610 | Q94: =Q81 -> 2558 | R94: =R81 -> 2477 | S94: =S81 -> 2387 | U94: =SUM(I94:L94) -> 11521 | V94: =SUM(J94:M94) -> 11323 | W94: =SUM(K94:N94) -> 11057 | X94: =SUM(L94:O94) -> 10822 | Y94: =SUM(M94:P94) -> 10680 | Z94: =SUM(N94:Q94) -> 10441 | AA94: =SUM(O94:R94) -> 10243 | AB94: =SUM(P94:S94) -> 10032
B95: =B82 -> Advertising | C95: =C82 -> 5547 | D95: =D82 -> 6063 | E95: =E82 -> 8224 | F95: =F82 -> 8342 | G95: =G82 -> 7306 | I95: =I82 -> 2237 | J95: =J82 -> 2448 | K95: =K82 -> 1709 | L95: =SUM(F95-SUM(I95:K95)) -> 1948 | M95: =M82 -> 1987 | N95: =N82 -> 2214 | O95: =O82 -> 1490 | P95: =SUM(G95-SUM(M95:O95)) -> 1615 | Q95: =Q82 -> 1758 | R95: =R82 -> 1953 | S95: =S82 -> 1186 | U95: =SUM(I95:L95) -> 8342 | V95: =SUM(J95:M95) -> 8092 | W95: =SUM(K95:N95) -> 7858 | X95: =SUM(L95:O95) -> 7639 | Y95: =SUM(M95:P95) -> 7306 | Z95: =SUM(N95:Q95) -> 7077 | AA95: =SUM(O95:R95) -> 6816 | AB95: =SUM(P95:S95) -> 6512
B96: =B83 -> Content | C96: =C83 -> 340 | D96: =D83 -> 706 | E96: =E83 -> 1120 | F96: =F83 -> 1005 | G96: =G83 -> 1848 | I96: =I83 -> 245 | J96: =J83 -> 284 | K96: =K83 -> 215 | L96: =SUM(F96-SUM(I96:K96)) -> 261 | M96: =M83 -> 264 | N96: =N83 -> 299 | O96: =O83 -> 833 | P96: =SUM(G96-SUM(M96:O96)) -> 452 | Q96: =Q83 -> 380 | R96: =R83 -> 287 | S96: =S83 -> 217 | U96: =SUM(I96:L96) -> 1005 | V96: =SUM(J96:M96) -> 1024 | W96: =SUM(K96:N96) -> 1039 | X96: =SUM(L96:O96) -> 1657 | Y96: =SUM(M96:P96) -> 1848 | Z96: =SUM(N96:Q96) -> 1964 | AA96: =SUM(O96:R96) -> 1952 | AB96: =SUM(P96:S96) -> 1336
B97: =B84 -> Other | C97: =C84 -> 56 | D97: =D84 -> 56 | E97: =E84 -> 245 | F97: =F84 -> 376 | G97: =G84 -> 341 | I97: =I84 -> 104 | J97: =J84 -> 85 | K97: =K84 -> 111 | L97: =SUM(F97-SUM(I97:K97)) -> 76 | M97: =M84 -> 77 | N97: =N84 -> 84 | O97: =O84 -> 89 | P97: =SUM(G97-SUM(M97:O97)) -> 91 | Q97: =Q84 -> 78 | R97: =R84 -> 86 | S97: =S84 -> 93 | U97: =SUM(I97:L97) -> 376 | V97: =SUM(J97:M97) -> 349 | W97: =SUM(K97:N97) -> 348 | X97: =SUM(L97:O97) -> 326 | Y97: =SUM(M97:P97) -> 341 | Z97: =SUM(N97:Q97) -> 342 | AA97: =SUM(O97:R97) -> 344 | AB97: =SUM(P97:S97) -> 348
B98: Total Revenue | C98: =SUM(C94:C97) -> 10439 | D98: =SUM(D94:D97) -> 11311 | E98: =SUM(E94:E97) -> 19348 | F98: =SUM(F94:F97) -> 21244 | G98: =SUM(G94:G97) -> 20175 | I98: =SUM(I94:I97) -> 5581 | J98: =SUM(J94:J97) -> 5758 | K98: =SUM(K94:K97) -> 4868 | L98: =SUM(L94:L97) -> 5037 | M98: =SUM(M94:M97) -> 5125 | N98: =SUM(N94:N97) -> 5272 | O98: =SUM(O94:O97) -> 5010 | P98: =SUM(P94:P97) -> 4768 | ... S98: =SUM(S94:S97) -> 3883 | U98: =SUM(U94:U97) -> 21244 | V98: =SUM(V94:V97) -> 20788 | W98: =SUM(W94:W97) -> 20302 | X98: =SUM(X94:X97) -> 20444 | Y98: =SUM(Y94:Y97) -> 20175 | Z98: =SUM(Z94:Z97) -> 19824 | AA98: =SUM(AA94:AA97) -> 19355 | AB98: =SUM(AB94:AB97) -> 18228
L99: =SUM(E99-SUM(I99:K99)) -> 0 | P99: =SUM(F99-SUM(M99:O99)) -> 0 | U99: =SUM(K99:N99) -> 0 | V99: =SUM(L99:O99) -> 0 | W99: =SUM(M99:P99) -> 0 | X99: =SUM(N99:Q99) -> 0 | Y99: =SUM(O99:R99) -> 0 | Z99: =SUM(P99:S99) -> 0 | AA99: =SUM(Q99:S99) -> 0 | AB99: =SUM(R99:S99) -> 0
B100: Costs of revenues, excluding depreciation and amortization | D100: -3926 | E100: -8006 | F100: -9342 | G100: -9238 | I100: -2594 | J100: -2849 | K100: -1800 | L100: =SUM(F100-SUM(I100:K100)) -> -2099 | M100: -2372 | N100: -2531 | O100: -2185 | P100: =SUM(G100-SUM(M100:O100)) -> -2150 | Q100: -2327 | R100: -2592 | S100: -1520 | U100: =SUM(I100:L100) -> -9342 | V100: =SUM(J100:M100) -> -9120 | W100: =SUM(K100:N100) -> -8802 | X100: =SUM(L100:O100) -> -9187 | Y100: =SUM(M100:P100) -> -9238 | Z100: =SUM(N100:Q100) -> -9193 | AA100: =SUM(O100:R100) -> -9254 | AB100: =SUM(P100:S100) -> -8589
B101: Gross Profit | C101: =SUM(C98+C100) -> 10439 | D101: =SUM(D98+D100) -> 7385 | E101: =SUM(E98+E100) -> 11342 | F101: =SUM(F98+F100) -> 11902 | G101: =SUM(G98+G100) -> 10937 | I101: =SUM(I98+I100) -> 2987 | J101: =SUM(J98+J100) -> 2909 | K101: =SUM(K98+K100) -> 3068 | L101: =SUM(L98+L100) -> 2938 | M101: =SUM(M98+M100) -> 2753 | N101: =SUM(N98+N100) -> 2741 | O101: =SUM(O98+O100) -> 2825 | P101: =SUM(P98+P100) -> 2618 | ... S101: =SUM(S98+S100) -> 2363 | U101: =SUM(U98+U100) -> 11902 | V101: =SUM(V98+V100) -> 11668 | W101: =SUM(W98+W100) -> 11500 | X101: =SUM(X98+X100) -> 11257 | Y101: =SUM(Y98+Y100) -> 10937 | Z101: =SUM(Z98+Z100) -> 10631 | AA101: =SUM(AA98+AA100) -> 10101 | AB101: =SUM(AB98+AB100) -> 9639
B102: Gross Margin (%) | C102: =C101/C98 -> 1 | D102: =D101/D98 -> 0.65290425 | E102: =E101/E98 -> 0.58621046 | F102: =F101/F98 -> 0.56025231 | G102: =G101/G98 -> 0.54210657 | I102: =I101/I98 -> 0.53520874 | J102: =J101/J98 -> 0.50521014 | K102: =K101/K98 -> 0.63023829 | L102: =L101/L98 -> 0.5832837 | M102: =M101/M98 -> 0.53717073 | N102: =N101/N98 -> 0.51991654 | O102: =O101/O98 -> 0.56387226 | P102: =P101/P98 -> 0.54907718 | ... S102: =S101/S98 -> 0.60855009 | U102: =U101/U98 -> 0.56025231 | V102: =V101/V98 -> 0.56128536 | W102: =W101/W98 -> 0.56644666 | X102: =X101/X98 -> 0.5506261 | Y102: =Y101/Y98 -> 0.54210657 | Z102: =Z101/Z98 -> 0.53626917 | AA102: =AA101/AA98 -> 0.52188065 | AB102: =AB101/AB98 -> 0.52880184
L103: =SUM(E103-SUM(I103:K103)) -> 0 | P103: =SUM(F103-SUM(M103:O103)) -> 0 | U103: =SUM(K103:N103) -> 0 | V103: =SUM(L103:O103) -> 0 | W103: =SUM(M103:P103) -> 0 | X103: =SUM(N103:Q103) -> 0 | Y103: =SUM(O103:R103) -> 0 | Z103: =SUM(P103:S103) -> 0 | AA103: =SUM(Q103:S103) -> 0 | AB103: =SUM(R103:S103) -> 0
B104: Selling, general and administrative | D104: -1852 | E104: -2617 | F104: -2839 | G104: -2788 | I104: -694 | J104: -743 | K104: -672 | L104: =SUM(F104-SUM(I104:K104)) -> -730 | M104: -634 | N104: -743 | O104: -710 | P104: =SUM(G104-SUM(M104:O104)) -> -701 | Q104: -654 | R104: -699 | S104: -661 | U104: =SUM(I104:L104) -> -2839 | V104: =SUM(J104:M104) -> -2779 | W104: =SUM(K104:N104) -> -2779 | X104: =SUM(L104:O104) -> -2817 | Y104: =SUM(M104:P104) -> -2788 | Z104: =SUM(N104:Q104) -> -2808 | AA104: =SUM(O104:R104) -> -2764 | AB104: =SUM(P104:S104) -> -2715
B105: Adjusted EBITDA | C105: =SUM(C101+C104) -> 10439 | D105: =SUM(D101+D104) -> 5533 | E105: =SUM(E101+E104) -> 8725 | F105: =SUM(F101+F104) -> 9063 | G105: =SUM(G101+G104) -> 8149 | I105: =SUM(I101+I104) -> 2293 | J105: =SUM(J101+J104) -> 2166 | K105: =SUM(K101+K104) -> 2396 | L105: =SUM(L101+L104) -> 2208 | M105: =SUM(M101+M104) -> 2119 | N105: =SUM(N101+N104) -> 1998 | O105: =SUM(O101+O104) -> 2115 | P105: =SUM(P101+P104) -> 1917 | ... S105: =SUM(S101+S104) -> 1702 | U105: =SUM(U101+U104) -> 9063 | V105: =SUM(V101+V104) -> 8889 | W105: =SUM(W101+W104) -> 8721 | X105: =SUM(X101+X104) -> 8440 | Y105: =SUM(Y101+Y104) -> 8149 | Z105: =SUM(Z101+Z104) -> 7823 | AA105: =SUM(AA101+AA104) -> 7337 | AB105: =SUM(AB101+AB104) -> 6924
B106: Adjusted EBITDA Margin (%) | C106: =C105/C98 -> 1 | D106: =D105/D98 -> 0.48916983 | E106: =E105/E98 -> 0.450951 | F106: =F105/F98 -> 0.42661457 | G106: =G105/G98 -> 0.40391574 | I106: =I105/I98 -> 0.41085827 | J106: =J105/J98 -> 0.37617228 | K106: =K105/K98 -> 0.49219392 | L106: =L105/L98 -> 0.43835616 | M106: =M105/M98 -> 0.41346341 | N106: =N105/N98 -> 0.37898331 | O106: =O105/O98 -> 0.42215569 | P106: =P105/P98 -> 0.40205537 | ... S106: =S105/S98 -> 0.43832089 | U106: =U105/U98 -> 0.42661457 | V106: =V105/V98 -> 0.42760246 | W106: =W105/W98 -> 0.42956359 | X106: =X105/X98 -> 0.41283506 | Y106: =Y105/Y98 -> 0.40391574 | Z106: =Z105/Z98 -> 0.39462268 | AA106: =AA105/AA98 -> 0.37907517 | AB106: =AB105/AB98 -> 0.37985517
B108: Depreciation and amortization | D108: -1212 | E108: -4687 | F108: -4961 | G108: -4172 | I108: -1304 | J108: -1262 | K108: -1202 | L108: =SUM(F108-SUM(I108:K108)) -> -1193 | M108: -1105 | N108: -1052 | O108: -1048 | P108: =SUM(G108-SUM(M108:O108)) -> -967 | Q108: -907 | R108: -829 | S108: -758 | U108: =SUM(I108:L108) -> -4961 | V108: =SUM(J108:M108) -> -4762 | W108: =SUM(K108:N108) -> -4552 | X108: =SUM(L108:O108) -> -4398 | Y108: =SUM(M108:P108) -> -4172 | Z108: =SUM(N108:Q108) -> -3974 | AA108: =SUM(O108:R108) -> -3751 | AB108: =SUM(P108:S108) -> -3461
B109: Restructuring and other charges | D109: -30 | E109: -1003 | F109: -201 | G109: -85 | I109: -3 | J109: -110 | K109: -48 | L109: =SUM(F109-SUM(I109:K109)) -> -40 | M109: -11 | N109: -42 | O109: -5 | P109: =SUM(G109-SUM(M109:O109)) -> -27 | Q109: -16 | R109: -25 | S109: -16 | U109: =SUM(I109:L109) -> -201 | V109: =SUM(J109:M109) -> -209 | W109: =SUM(K109:N109) -> -141 | X109: =SUM(L109:O109) -> -98 | Y109: =SUM(M109:P109) -> -85 | Z109: =SUM(N109:Q109) -> -90 | AA109: =SUM(O109:R109) -> -73 | AB109: =SUM(P109:S109) -> -84
B110: Transaction and integration costs | D110: -4 | E110: -2 | F110: -3 | G110: -2 | I110: -3 | J110: -8 | K110: 8 | L110: =SUM(F110-SUM(I110:K110)) -> 0 | M110: -1 | N110: 1 | O110: -3 | P110: =SUM(G110-SUM(M110:O110)) -> 1 | Q110: 0 | R110: 0 | S110: 0 | U110: =SUM(I110:L110) -> -3 | V110: =SUM(J110:M110) -> -1 | W110: =SUM(K110:N110) -> 8 | X110: =SUM(L110:O110) -> -3 | Y110: =SUM(M110:P110) -> -2 | Z110: =SUM(N110:Q110) -> -1 | AA110: =SUM(O110:R110) -> -2 | AB110: =SUM(P110:S110) -> 1
B111: Impairment and amortization of fair value step-up for content | D111: 0 | E111: -73 | F111: -473 | G111: -495 | I111: -121 | J111: -279 | K111: 0 | L111: =SUM(F111-SUM(I111:K111)) -> -73 | M111: -125 | N111: -294 | O111: 0 | P111: =SUM(G111-SUM(M111:O111)) -> -76 | Q111: -130 | R111: -310 | S111: 0 | U111: =SUM(I111:L111) -> -473 | V111: =SUM(J111:M111) -> -477 | W111: =SUM(K111:N111) -> -492 | X111: =SUM(L111:O111) -> -492 | Y111: =SUM(M111:P111) -> -495 | Z111: =SUM(N111:Q111) -> -500 | AA111: =SUM(O111:R111) -> -516 | AB111: =SUM(P111:S111) -> -516
B112: Inter-segment eliminations | D112: 0 | E112: -17 | F112: -90 | G112: 0 | I112: 7 | J112: -22 | K112: 10 | L112: =SUM(F112-SUM(I112:K112)) -> -85 | M112: 0 | N112: 0 | O112: 0 | P112: =SUM(G112-SUM(M112:O112)) -> 0 | Q112: 0 | R112: 0 | S112: 0 | U112: =SUM(I112:L112) -> -90 | V112: =SUM(J112:M112) -> -97 | W112: =SUM(K112:N112) -> -75 | X112: =SUM(L112:O112) -> -85 | Y112: =SUM(M112:P112) -> 0 | Z112: =SUM(N112:Q112) -> 0 | AA112: =SUM(O112:R112) -> 0 | AB112: =SUM(P112:S112) -> 0
B113: Impairments and Other Charges | D113: 72 | E113: -24 | F113: -13 | G113: -9154 | I113: -1 | J113: -4 | K113: -11 | L113: =SUM(F113-SUM(I113:K113)) -> 3 | M113: 0 | N113: -9154 | O113: -5 | P113: =SUM(G113-SUM(M113:O113)) -> 5 | Q113: =-1-2 -> -3 | R113: -1 | S113: -27 | U113: =SUM(I113:L113) -> -13 | V113: =SUM(J113:M113) -> -12 | W113: =SUM(K113:N113) -> -9162 | X113: =SUM(L113:O113) -> -9156 | Y113: =SUM(M113:P113) -> -9154 | Z113: =SUM(N113:Q113) -> -9157 | AA113: =SUM(O113:R113) -> -4 | AB113: =SUM(P113:S113) -> -26
B114: Operating Income | C114: =SUM(C105+SUM(C108:C113)) -> 10439 | D114: =SUM(D105+SUM(D108:D113)) -> 4359 | E114: =SUM(E105+SUM(E108:E113)) -> 2919 | F114: =SUM(F105+SUM(F108:F113)) -> 3322 | G114: =SUM(G105+SUM(G108:G113)) -> -5759 | I114: =SUM(I105+SUM(I108:I113)) -> 868 | J114: =SUM(J105+SUM(J108:J113)) -> 481 | K114: =SUM(K105+SUM(K108:K113)) -> 1153 | L114: =SUM(L105+SUM(L108:L113)) -> 820 | M114: =SUM(M105+SUM(M108:M113)) -> 877 | N114: =SUM(N105+SUM(N108:N113)) -> -8543 | O114: =SUM(O105+SUM(O108:O113)) -> 1054 | P114: =SUM(P105+SUM(P108:P113)) -> 853 | ... S114: =SUM(S105+SUM(S108:S113)) -> 901 | U114: =SUM(U105+SUM(U108:U113)) -> 3322 | V114: =SUM(V105+SUM(V108:V113)) -> 3331 | W114: =SUM(W105+SUM(W108:W113)) -> -5693 | X114: =SUM(X105+SUM(X108:X113)) -> -5792 | Y114: =SUM(Y105+SUM(Y108:Y113)) -> -5759 | Z114: =SUM(Z105+SUM(Z108:Z113)) -> -5899 | AA114: =SUM(AA105+SUM(AA108:AA113)) -> 2991 | AB114: =SUM(AB105+SUM(AB108:AB113)) -> 2838
B115: Operating Margin (%) | C115: =C114/C98 -> 1 | D115: =D114/D98 -> 0.38537707 | E115: =E114/E98 -> 0.15086831 | F115: =F114/F98 -> 0.15637356 | G115: =G114/G98 -> -0.28545229 | I115: =I114/I98 -> 0.15552768 | J115: =J114/J98 -> 0.08353595 | K115: =K114/K98 -> 0.23685292 | L115: =L114/L98 -> 0.16279531 | M115: =M114/M98 -> 0.17112195 | N115: =N114/N98 -> -1.6204476 | O115: =O114/O98 -> 0.21037924 | P115: =P114/P98 -> 0.17890101 | ... S115: =S114/S98 -> 0.23203708 | U115: =U114/U98 -> 0.15637356 | V115: =V114/V98 -> 0.16023668 | W115: =W114/W98 -> -0.28041572 | X115: =X114/X98 -> -0.28331051 | Y115: =Y114/Y98 -> -0.28545229 | Z115: =Z114/Z98 -> -0.2975686 | AA115: =AA114/AA98 -> 0.15453371 | AB115: =AB114/AB98 -> 0.15569454
A117: X | B117: Streaming Segment Analysis
A119: X | B119: Revenue by Streaming Segment
B120: Distribution | C120: 190 | D120: 716 | E120: 6371 | F120: 8703 | G120: 9022 | I120: 2165 | J120: 2192 | K120: 2179 | L120: =SUM(F120-SUM(I120:K120)) -> 2167 | M120: 2185 | N120: 2202 | O120: 2320 | P120: =SUM(G120-SUM(M120:O120)) -> 2315 | Q120: 2329 | R120: 2410 | S120: 2317 | U120: =SUM(I120:L120) -> 8703 | V120: =SUM(J120:M120) -> 8723 | W120: =SUM(K120:N120) -> 8733 | X120: =SUM(L120:O120) -> 8874 | Y120: =SUM(M120:P120) -> 9022 | Z120: =SUM(N120:Q120) -> 9166 | AA120: =SUM(O120:R120) -> 9374 | AB120: =SUM(P120:S120) -> 9371
...

Sheet FCF
B2: ='Historical Financials'!B2 -> Warner Bros Discovery Inc (NASDAQ: WBD) | E2: FYE | I2: Quarterly | S2: Quarterly | W2: LTM | X2: LTM | AD2: Variance
B3: FCF Analysis | C3: ='Historical Financials'!C7 -> 2020 | D3: ='Historical Financials'!D7 -> 2021 | E3: ='Historical Financials'!E7 -> 2022 | F3: ='Historical Financials'!F7 -> 2023 | G3: ='Historical Financials'!G7 -> 2024 | I3: ='Historical Financials'!I7 -> 1Q23 | J3: ='Historical Financials'!J7 -> 2Q23 | K3: ='Historical Financials'!K7 -> 3Q23 | L3: ='Historical Financials'!L7 -> 4Q23 | M3: ='Historical Financials'!M7 -> 1Q24 | N3: ='Historical Financials'!N7 -> 2Q24 | O3: ='Historical Financials'!O7 -> 3Q24 | P3: ='Historical Financials'!P7 -> 4Q24 | ... S3: ='Historical Financials'!S7 -> 3Q25 | U3: =L3 -> 4Q23 | V3: =M3 -> 1Q24 | W3: =N3 -> 2Q24 | X3: =O3 -> 3Q24 | Y3: =P3 -> 4Q24 | Z3: =Q3 -> 1Q25 | AA3: =R3 -> 2Q25 | AB3: =S3 -> 3Q25
B4: ($ In Millions) | C4: ='Historical Financials'!C8 -> 44196 | D4: ='Historical Financials'!D8 -> 44561 | E4: ='Historical Financials'!E8 -> 44926 | F4: ='Historical Financials'!F8 -> 45291 | G4: ='Historical Financials'!G8 -> 45657 | I4: ='Historical Financials'!I8 -> 45016 | J4: ='Historical Financials'!J8 -> 45107 | K4: ='Historical Financials'!K8 -> 45199 | L4: ='Historical Financials'!L8 -> 44926 | M4: ='Historical Financials'!M8 -> 45382 | N4: ='Historical Financials'!N8 -> 45473 | O4: ='Historical Financials'!O8 -> 45565 | P4: ='Historical Financials'!P8 -> 45291 | ... S4: ='Historical Financials'!S8 -> 45930 | U4: =L4 -> 44926 | V4: =M4 -> 45382 | W4: =N4 -> 45473 | X4: =O4 -> 45565 | Y4: =P4 -> 45291 | Z4: =Q4 -> 45747 | AA4: =R4 -> 45838 | AB4: =S4 -> 45930
B6: ='Revenue Segment Analysis'!B9 -> Distribution | C6: ='Revenue Segment Analysis'!C9 -> 5572 | D6: ='Revenue Segment Analysis'!D9 -> 5202 | E6: ='Revenue Segment Analysis'!E9 -> 16142 | F6: ='Revenue Segment Analysis'!F9 -> 20237 | G6: ='Revenue Segment Analysis'!G9 -> 19701 | I6: ='Revenue Segment Analysis'!I9 -> 5163 | J6: ='Revenue Segment Analysis'!J9 -> 5135 | K6: ='Revenue Segment Analysis'!K9 -> 5026 | L6: ='Revenue Segment Analysis'!L9 -> 4913 | M6: ='Revenue Segment Analysis'!M9 -> 4985 | N6: ='Revenue Segment Analysis'!N9 -> 4879 | O6: ='Revenue Segment Analysis'!O9 -> 4920 | P6: ='Revenue Segment Analysis'!P9 -> 4917 | ... S6: ='Revenue Segment Analysis'!S9 -> 4702 | T6: =SUM(H6:K6) -> 15324 | U6: =SUM(I6:L6) -> 20237 | V6: =SUM(J6:M6) -> 20059 | W6: =SUM(K6:N6) -> 19803 | X6: =SUM(L6:O6) -> 19697 | Y6: =SUM(M6:P6) -> 19701 | Z6: =SUM(N6:Q6) -> 19602 | AA6: =SUM(O6:R6) -> 19608 | AB6: =SUM(P6:S6) -> 19390 | AD6: =SUM(AB6/X6)-1 -> -0.01558613
B7: ='Revenue Segment Analysis'!B10 -> Advertising | C7: ='Revenue Segment Analysis'!C10 -> 4686 | D7: ='Revenue Segment Analysis'!D10 -> 6194 | E7: ='Revenue Segment Analysis'!E10 -> 8524 | F7: ='Revenue Segment Analysis'!F10 -> 8700 | G7: ='Revenue Segment Analysis'!G10 -> 8090 | I7: ='Revenue Segment Analysis'!I10 -> 2298 | J7: ='Revenue Segment Analysis'!J10 -> 2519 | K7: ='Revenue Segment Analysis'!K10 -> 1796 | L7: ='Revenue Segment Analysis'!L10 -> 2087 | M7: ='Revenue Segment Analysis'!M10 -> 2148 | N7: ='Revenue Segment Analysis'!N10 -> 2430 | O7: ='Revenue Segment Analysis'!O10 -> 1682 | P7: ='Revenue Segment Analysis'!P10 -> 1830 | ... S7: ='Revenue Segment Analysis'!S10 -> 1407 | T7: =SUM(H7:K7) -> 6613 | U7: =SUM(I7:L7) -> 8700 | V7: =SUM(J7:M7) -> 8550 | W7: =SUM(K7:N7) -> 8461 | X7: =SUM(L7:O7) -> 8347 | Y7: =SUM(M7:P7) -> 8090 | Z7: =SUM(N7:Q7) -> 7922 | AA7: =SUM(O7:R7) -> 7708 | AB7: =SUM(P7:S7) -> 7433 | AD7: =SUM(AB7/X7)-1 -> -0.10950042
B8: ='Revenue Segment Analysis'!B11 -> Content | C8: ='Revenue Segment Analysis'!C11 -> 355 | D8: ='Revenue Segment Analysis'!D11 -> 737 | E8: ='Revenue Segment Analysis'!E11 -> 8360 | F8: ='Revenue Segment Analysis'!F11 -> 11203 | G8: ='Revenue Segment Analysis'!G11 -> 10297 | I8: ='Revenue Segment Analysis'!I11 -> 2954 | J8: ='Revenue Segment Analysis'!J11 -> 2446 | K8: ='Revenue Segment Analysis'!K11 -> 2840 | L8: ='Revenue Segment Analysis'!L11 -> 2963 | M8: ='Revenue Segment Analysis'!M11 -> 2558 | N8: ='Revenue Segment Analysis'!N11 -> 2109 | O8: ='Revenue Segment Analysis'!O11 -> 2721 | P8: ='Revenue Segment Analysis'!P11 -> 2909 | ... S8: ='Revenue Segment Analysis'!S11 -> 2649 | T8: =SUM(H8:K8) -> 8240 | U8: =SUM(I8:L8) -> 11203 | V8: =SUM(J8:M8) -> 10807 | W8: =SUM(K8:N8) -> 10470 | X8: =SUM(L8:O8) -> 10351 | Y8: =SUM(M8:P8) -> 10297 | Z8: =SUM(N8:Q8) -> 9605 | AA8: =SUM(O8:R8) -> 9967 | AB8: =SUM(P8:S8) -> 9895 | AD8: =SUM(AB8/X8)-1 -> -0.044053715
B9: ='Revenue Segment Analysis'!B12 -> Other | C9: ='Revenue Segment Analysis'!C12 -> 58 | D9: ='Revenue Segment Analysis'!D12 -> 58 | E9: ='Revenue Segment Analysis'!E12 -> 791 | F9: ='Revenue Segment Analysis'!F12 -> 1181 | G9: ='Revenue Segment Analysis'!G12 -> 1233 | I9: ='Revenue Segment Analysis'!I12 -> 285 | J9: ='Revenue Segment Analysis'!J12 -> 258 | K9: ='Revenue Segment Analysis'!K12 -> 317 | L9: ='Revenue Segment Analysis'!L12 -> 321 | M9: ='Revenue Segment Analysis'!M12 -> 267 | N9: ='Revenue Segment Analysis'!N12 -> 295 | O9: ='Revenue Segment Analysis'!O12 -> 300 | P9: ='Revenue Segment Analysis'!P12 -> 371 | ... S9: ='Revenue Segment Analysis'!S12 -> 287 | T9: =SUM(H9:K9) -> 860 | U9: =SUM(I9:L9) -> 1181 | V9: =SUM(J9:M9) -> 1163 | W9: =SUM(K9:N9) -> 1200 | X9: =SUM(L9:O9) -> 1183 | Y9: =SUM(M9:P9) -> 1233 | Z9: =SUM(N9:Q9) -> 1213 | AA9: =SUM(O9:R9) -> 1158 | AB9: =SUM(P9:S9) -> 1145 | AD9: =SUM(AB9/X9)-1 -> -0.032121724
B10: Total Revenue | C10: =SUM(C6:C9) -> 10671 | D10: =SUM(D6:D9) -> 12191 | E10: =SUM(E6:E9) -> 33817 | F10: =SUM(F6:F9) -> 41321 | G10: =SUM(G6:G9) -> 39321 | I10: =SUM(I6:I9) -> 10700 | J10: =SUM(J6:J9) -> 10358 | K10: =SUM(K6:K9) -> 9979 | L10: =SUM(L6:L9) -> 10284 | M10: =SUM(M6:M9) -> 9958 | N10: =SUM(N6:N9) -> 9713 | O10: =SUM(O6:O9) -> 9623 | P10: =SUM(P6:P9) -> 10027 | ... S10: =SUM(S6:S9) -> 9045 | U10: =SUM(U6:U9) -> 41321 | V10: =SUM(V6:V9) -> 40579 | W10: =SUM(W6:W9) -> 39934 | X10: =SUM(X6:X9) -> 39578 | Y10: =SUM(Y6:Y9) -> 39321 | Z10: =SUM(Z6:Z9) -> 38342 | AA10: =SUM(AA6:AA9) -> 38441 | AB10: =SUM(AB6:AB9) -> 37863 | AD10: =SUM(AB10/X10)-1 -> -0.043332154
B11: Y/Y Growth (%) | D11: =SUM(D10/C10)-1 -> 0.14244213 | E11: =SUM(E10/D10)-1 -> 1.7739316 | F11: =SUM(F10/E10)-1 -> 0.22190023 | G11: =SUM(G10/F10)-1 -> -0.048401539 | M11: =SUM(M10/I10)-1 -> -0.069345794 | N11: =SUM(N10/J10)-1 -> -0.062270709 | O11: =SUM(O10/K10)-1 -> -0.035674917 | P11: =SUM(P10/L10)-1 -> -0.024990276 | Q11: =SUM(Q10/M10)-1 -> -0.098312914 | R11: =SUM(R10/N10)-1 -> 0.010192525 | S11: =SUM(S10/O10)-1 -> -0.060064429 | Y11: =SUM(Y10/U10)-1 -> -0.048401539 | Z11: =SUM(Z10/V10)-1 -> -0.055127036 | AA11: =SUM(AA10/W10)-1 -> -0.037386688 | AB11: =SUM(AB10/X10)-1 -> -0.043332154 | AD11: =SUM(AB11-X11)*10000 -> -433.32154
B12: Q/Q Growth (%) | C12: N/A | D12: N/A | E12: N/A | F12: N/A | G12: N/A | J12: =SUM(J10/I10)-1 -> -0.031962617 | K12: =SUM(K10/J10)-1 -> -0.036590075 | L12: =SUM(L10/K10)-1 -> 0.030564185 | M12: =SUM(M10/L10)-1 -> -0.031699728 | N12: =SUM(N10/M10)-1 -> -0.024603334 | O12: =SUM(O10/N10)-1 -> -0.0092659323 | P12: =SUM(P10/O10)-1 -> 0.04198275 | Q12: =SUM(Q10/P10)-1 -> -0.1045178 | ... S12: =SUM(S10/R10)-1 -> -0.078169588 | U12: N/A | V12: N/A | W12: N/A | X12: N/A | Y12: N/A | Z12: N/A | AA12: N/A | AB12: N/A
B14: (-) Cost of Sales | C14: ='Historical Financials'!C13 -> -3860 | D14: ='Historical Financials'!D13 -> -4620 | E14: ='Historical Financials'!E13 -> -20442 | F14: ='Historical Financials'!F13 -> -24526 | G14: ='Historical Financials'!G13 -> -22970 | I14: ='Historical Financials'!I13 -> -6685 | J14: ='Historical Financials'!J13 -> -6636 | K14: ='Historical Financials'!K13 -> -5309 | L14: ='Historical Financials'!L13 -> -5896 | M14: ='Historical Financials'!M13 -> -6058 | N14: ='Historical Financials'!N13 -> -6204 | O14: ='Historical Financials'!O13 -> -5181 | P14: ='Historical Financials'!P13 -> -5527 | ... S14: ='Historical Financials'!S13 -> -4564 | T14: =SUM(H14:K14) -> -18630 | U14: =SUM(I14:L14) -> -24526 | V14: =SUM(J14:M14) -> -23899 | W14: =SUM(K14:N14) -> -23467 | X14: =SUM(L14:O14) -> -23339 | Y14: =SUM(M14:P14) -> -22970 | Z14: =SUM(N14:Q14) -> -22043 | AA14: =SUM(O14:R14) -> -21806 | AB14: =SUM(P14:S14) -> -21189 | AD14: =SUM(AB14/X14)-1 -> -0.092120485
B15: Gross Profit | C15: =SUM(C10+SUM(C14:C14)) -> 6811 | D15: =SUM(D10+SUM(D14:D14)) -> 7571 | E15: =SUM(E10+SUM(E14:E14)) -> 13375 | F15: =SUM(F10+SUM(F14:F14)) -> 16795 | G15: =SUM(G10+SUM(G14:G14)) -> 16351 | I15: =SUM(I10+SUM(I14:I14)) -> 4015 | J15: =SUM(J10+SUM(J14:J14)) -> 3722 | K15: =SUM(K10+SUM(K14:K14)) -> 4670 | L15: =SUM(L10+SUM(L14:L14)) -> 4388 | M15: =SUM(M10+SUM(M14:M14)) -> 3900 | N15: =SUM(N10+SUM(N14:N14)) -> 3509 | O15: =SUM(O10+SUM(O14:O14)) -> 4442 | P15: =SUM(P10+SUM(P14:P14)) -> 4500 | ... S15: =SUM(S10+SUM(S14:S14)) -> 4481 | U15: =SUM(U10+SUM(U14:U14)) -> 16795 | V15: =SUM(V10+SUM(V14:V14)) -> 16680 | W15: =SUM(W10+SUM(W14:W14)) -> 16467 | X15: =SUM(X10+SUM(X14:X14)) -> 16239 | Y15: =SUM(Y10+SUM(Y14:Y14)) -> 16351 | Z15: =SUM(Z10+SUM(Z14:Z14)) -> 16299 | AA15: =SUM(AA10+SUM(AA14:AA14)) -> 16635 | AB15: =SUM(AB10+SUM(AB14:AB14)) -> 16674 | AD15: =SUM(AB15/X15)-1 -> 0.026787364
B16: Gross Margin (%) | C16: =C15/C10 -> 0.63827195 | D16: =D15/D10 -> 0.62103191 | E16: =E15/E10 -> 0.39551113 | F16: =F15/F10 -> 0.40645193 | G16: =G15/G10 -> 0.41583378 | I16: =I15/I10 -> 0.37523364 | J16: =J15/J10 -> 0.35933578 | K16: =K15/K10 -> 0.46798276 | L16: =L15/L10 -> 0.42668222 | M16: =M15/M10 -> 0.39164491 | N16: =N15/N10 -> 0.3612684 | O16: =O15/O10 -> 0.46160241 | P16: =P15/P10 -> 0.44878827 | ... S16: =S15/S10 -> 0.49541183 | U16: =U15/U10 -> 0.40645193 | V16: =V15/V10 -> 0.41105005 | W16: =W15/W10 -> 0.41235539 | X16: =X15/X10 -> 0.4103037 | Y16: =Y15/Y10 -> 0.41583378 | Z16: =Z15/Z10 -> 0.4250952 | AA16: =AA15/AA10 -> 0.43274108 | AB16: =AB15/AB10 -> 0.44037715 | AD16: =SUM(AB16-X16)*10000 -> 300.73445
B18: (-) Selling, general and administrative | C18: ='Historical Financials'!C17 -> -2722 | D18: ='Historical Financials'!D17 -> -4016 | E18: ='Historical Financials'!E17 -> -9678 | F18: ='Historical Financials'!F17 -> -9696 | G18: ='Historical Financials'!G17 -> -9296 | I18: ='Historical Financials'!I17 -> -2388 | J18: ='Historical Financials'!J17 -> -2562 | K18: ='Historical Financials'!K17 -> -2291 | L18: ='Historical Financials'!L17 -> -2455 | M18: ='Historical Financials'!M17 -> -2232 | N18: ='Historical Financials'!N17 -> -2461 | O18: ='Historical Financials'!O17 -> -2385 | P18: ='Historical Financials'!P17 -> -2218 | ... S18: ='Historical Financials'!S17 -> -2361 | T18: =SUM(H18:K18) -> -7241 | U18: =SUM(I18:L18) -> -9696 | V18: =SUM(J18:M18) -> -9540 | W18: =SUM(K18:N18) -> -9439 | X18: =SUM(L18:O18) -> -9533 | Y18: =SUM(M18:P18) -> -9296 | Z18: =SUM(N18:Q18) -> -9258 | AA18: =SUM(O18:R18) -> -9274 | AB18: =SUM(P18:S18) -> -9250 | AD18: =SUM(AB18/X18)-1 -> -0.029686353
B19: (-) Depreciation and amortization | C19: ='Historical Financials'!C18 -> -1359 | D19: ='Historical Financials'!D18 -> -1582 | E19: ='Historical Financials'!E18 -> -7193 | F19: ='Historical Financials'!F18 -> -7985 | G19: ='Historical Financials'!G18 -> -7037 | I19: ='Historical Financials'!I18 -> -2058 | J19: ='Historical Financials'!J18 -> -1914 | K19: ='Historical Financials'!K18 -> -1989 | L19: ='Historical Financials'!L18 -> -2024 | M19: ='Historical Financials'!M18 -> -1888 | N19: ='Historical Financials'!N18 -> -1744 | O19: ='Historical Financials'!O18 -> -1762 | P19: ='Historical Financials'!P18 -> -1643 | ... S19: ='Historical Financials'!S18 -> -1375 | T19: =SUM(H19:K19) -> -5961 | U19: =SUM(I19:L19) -> -7985 | V19: =SUM(J19:M19) -> -7815 | W19: =SUM(K19:N19) -> -7645 | X19: =SUM(L19:O19) -> -7418 | Y19: =SUM(M19:P19) -> -7037 | Z19: =SUM(N19:Q19) -> -6696 | AA19: =SUM(O19:R19) -> -6399 | AB19: =SUM(P19:S19) -> -6012 | AD19: =SUM(AB19/X19)-1 -> -0.18953896
B20: (-) Restructuring and other charges | C20: ='Historical Financials'!C19 -> -91 | D20: ='Historical Financials'!D19 -> -32 | E20: ='Historical Financials'!E19 -> -3757 | F20: ='Historical Financials'!F19 -> -585 | G20: ='Historical Financials'!G19 -> -447 | I20: ='Historical Financials'!I19 -> -95 | J20: ='Historical Financials'!J19 -> -146 | K20: ='Historical Financials'!K19 -> -269 | L20: ='Historical Financials'!L19 -> -75 | M20: ='Historical Financials'!M19 -> -35 | N20: ='Historical Financials'!N19 -> -117 | O20: ='Historical Financials'!O19 -> -9 | P20: ='Historical Financials'!P19 -> -286 | ... S20: ='Historical Financials'!S19 -> -88 | T20: =SUM(H20:K20) -> -510 | U20: =SUM(I20:L20) -> -585 | V20: =SUM(J20:M20) -> -525 | W20: =SUM(K20:N20) -> -496 | X20: =SUM(L20:O20) -> -236 | Y20: =SUM(M20:P20) -> -447 | Z20: =SUM(N20:Q20) -> -466 | AA20: =SUM(O20:R20) -> -429 | AB20: =SUM(P20:S20) -> -508 | AD20: =SUM(AB20/X20)-1 -> 1.1525424
B21: (-) Impairments and loss on dispositions | C21: ='Historical Financials'!C20 -> -124 | D21: ='Historical Financials'!D20 -> 71 | E21: ='Historical Financials'!E20 -> -117 | F21: ='Historical Financials'!F20 -> -77 | G21: ='Historical Financials'!G20 -> -9603 | I21: ='Historical Financials'!I20 -> -31 | J21: ='Historical Financials'!J20 -> -6 | K21: ='Historical Financials'!K20 -> -24 | L21: ='Historical Financials'!L20 -> -16 | M21: ='Historical Financials'!M20 -> -12 | N21: ='Historical Financials'!N20 -> -9395 | O21: ='Historical Financials'!O20 -> -5 | P21: ='Historical Financials'!P20 -> -191 | ... S21: ='Historical Financials'!S20 -> -46 | T21: =SUM(H21:K21) -> -61 | U21: =SUM(I21:L21) -> -77 | V21: =SUM(J21:M21) -> -58 | W21: =SUM(K21:N21) -> -9447 | X21: =SUM(L21:O21) -> -9428 | Y21: =SUM(M21:P21) -> -9603 | Z21: =SUM(N21:Q21) -> -9681 | AA21: =SUM(O21:R21) -> -312 | AB21: =SUM(P21:S21) -> -353 | AD21: =SUM(AB21/X21)-1 -> -0.96255834
B22: Earning before Interest & Taxes (EBIT) | C22: =SUM(C15+SUM(C18:C21)) -> 2515 | D22: =SUM(D15+SUM(D18:D21)) -> 2012 | E22: =SUM(E15+SUM(E18:E21)) -> -7370 | F22: =SUM(F15+SUM(F18:F21)) -> -1548 | G22: =SUM(G15+SUM(G18:G21)) -> -10032 | I22: =SUM(I15+SUM(I18:I21)) -> -557 | J22: =SUM(J15+SUM(J18:J21)) -> -906 | K22: =SUM(K15+SUM(K18:K21)) -> 97 | L22: =SUM(L15+SUM(L18:L21)) -> -182 | M22: =SUM(M15+SUM(M18:M21)) -> -267 | N22: =SUM(N15+SUM(N18:N21)) -> -10208 | O22: =SUM(O15+SUM(O18:O21)) -> 281 | P22: =SUM(P15+SUM(P18:P21)) -> 162 | ... S22: =SUM(S15+SUM(S18:S21)) -> 611 | U22: =SUM(U15+SUM(U18:U21)) -> -1548 | V22: =SUM(V15+SUM(V18:V21)) -> -1258 | W22: =SUM(W15+SUM(W18:W21)) -> -10560 | X22: =SUM(X15+SUM(X18:X21)) -> -10376 | Y22: =SUM(Y15+SUM(Y18:Y21)) -> -10032 | Z22: =SUM(Z15+SUM(Z18:Z21)) -> -9802 | AA22: =SUM(AA15+SUM(AA18:AA21)) -> 221 | AB22: =SUM(AB15+SUM(AB18:AB21)) -> 551 | AD22: =SUM(AB22/X22)-1 -> -1.0531033
B23: Operating Margin (%) | C23: =C22/C10 -> 0.2356855 | D23: =D22/D10 -> 0.16503978 | E23: =E22/E10 -> -0.21793772 | F23: =F22/F10 -> -0.037462791 | G23: =G22/G10 -> -0.25513085 | I23: =I22/I10 -> -0.052056075 | J23: =J22/J10 -> -0.087468623 | K23: =K22/K10 -> 0.0097204129 | L23: =L22/L10 -> -0.017697394 | M23: =M22/M10 -> -0.026812613 | N23: =N22/N10 -> -1.0509626 | O23: =O22/O10 -> 0.029200873 | P23: =P22/P10 -> 0.016156378 | ... S23: =S22/S10 -> 0.067551133 | U23: =U22/U10 -> -0.037462791 | V23: =V22/V10 -> -0.031001257 | W23: =W22/W10 -> -0.26443632 | X23: =X22/X10 -> -0.26216585 | Y23: =Y22/Y10 -> -0.25513085 | Z23: =Z22/Z10 -> -0.25564655 | AA23: =AA22/AA10 -> 0.00574907 | AB23: =AB22/AB10 -> 0.014552465 | AD23: =SUM(AB23-X23)*10000 -> 2767.1832
B25: (+) Depreciation and Amortization (D&A) | C25: =-C19 -> 1359 | D25: =-D19 -> 1582 | E25: =-E19 -> 7193 | F25: =-F19 -> 7985 | G25: =-G19 -> 7037 | I25: =-I19 -> 2058 | J25: =-J19 -> 1914 | K25: =-K19 -> 1989 | L25: =-L19 -> 2024 | M25: =-M19 -> 1888 | N25: =-N19 -> 1744 | O25: =-O19 -> 1762 | P25: =-P19 -> 1643 | ... S25: =-S19 -> 1375 | T25: =SUM(H25:K25) -> 5961 | U25: =SUM(I25:L25) -> 7985 | V25: =SUM(J25:M25) -> 7815 | W25: =SUM(K25:N25) -> 7645 | X25: =SUM(L25:O25) -> 7418 | Y25: =SUM(M25:P25) -> 7037 | Z25: =SUM(N25:Q25) -> 6696 | AA25: =SUM(O25:R25) -> 6399 | AB25: =SUM(P25:S25) -> 6012 | AD25: =SUM(AB25/X25)-1 -> -0.18953896
B26: EBITDA | C26: =SUM(C22+SUM(C25:C25)) -> 3874 | D26: =SUM(D22+SUM(D25:D25)) -> 3594 | E26: =SUM(E22+SUM(E25:E25)) -> -177 | F26: =SUM(F22+SUM(F25:F25)) -> 6437 | G26: =SUM(G22+SUM(G25:G25)) -> -2995 | I26: =SUM(I22+SUM(I25:I25)) -> 1501 | J26: =SUM(J22+SUM(J25:J25)) -> 1008 | K26: =SUM(K22+SUM(K25:K25)) -> 2086 | L26: =SUM(L22+SUM(L25:L25)) -> 1842 | M26: =SUM(M22+SUM(M25:M25)) -> 1621 | N26: =SUM(N22+SUM(N25:N25)) -> -8464 | O26: =SUM(O22+SUM(O25:O25)) -> 2043 | P26: =SUM(P22+SUM(P25:P25)) -> 1805 | ... S26: =SUM(S22+SUM(S25:S25)) -> 1986 | U26: =SUM(U22+SUM(U25:U25)) -> 6437 | V26: =SUM(V22+SUM(V25:V25)) -> 6557 | W26: =SUM(W22+SUM(W25:W25)) -> -2915 | X26: =SUM(X22+SUM(X25:X25)) -> -2958 | Y26: =SUM(Y22+SUM(Y25:Y25)) -> -2995 | Z26: =SUM(Z22+SUM(Z25:Z25)) -> -3106 | AA26: =SUM(AA22+SUM(AA25:AA25)) -> 6620 | AB26: =SUM(AB22+SUM(AB25:AB25)) -> 6563 | AD26: =SUM(AB26/X26)-1 -> -3.2187289
B27: EBITDA Margin (%) | C27: =C26/C10 -> 0.36304001 | D27: =D26/D10 -> 0.29480764 | E27: =E26/E10 -> -0.0052340539 | F27: =F26/F10 -> 0.15578035 | G27: =G26/G10 -> -0.076167951 | I27: =I26/I10 -> 0.14028037 | J27: =J26/J10 -> 0.097316084 | K27: =K26/K10 -> 0.20903898 | L27: =L26/L10 -> 0.17911319 | M27: =M26/M10 -> 0.16278369 | N27: =N26/N10 -> -0.87140945 | O27: =O26/O10 -> 0.21230386 | P27: =P26/P10 -> 0.18001396 | ... S27: =S26/S10 -> 0.21956882 | U27: =U26/U10 -> 0.15578035 | V27: =V26/V10 -> 0.16158604 | W27: =W26/W10 -> -0.072995442 | X27: =X26/X10 -> -0.074738491 | Y27: =Y26/Y10 -> -0.076167951 | Z27: =Z26/Z10 -> -0.081007772 | AA27: =AA26/AA10 -> 0.17221196 | AB27: =AB26/AB10 -> 0.17333545 | AD27: =SUM(AB27-X27)*10000 -> 2480.7394
B29: (+) Stock-Based Compensation (SBC) | C29: ='Historical Financials'!C106 -> 110 | D29: ='Historical Financials'!D106 -> 178 | E29: ='Historical Financials'!E106 -> 412 | F29: ='Historical Financials'!F106 -> 500 | G29: ='Historical Financials'!G106 -> 557 | I29: ='Historical Financials'!I106 -> 111 | J29: ='Historical Financials'!J106 -> 137 | K29: ='Historical Financials'!K106 -> 143 | L29: ='Historical Financials'!L106 -> 109 | M29: ='Historical Financials'!M106 -> 101 | N29: ='Historical Financials'!N106 -> 159 | O29: ='Historical Financials'!O106 -> 159 | P29: ='Historical Financials'!P106 -> 138 | ... S29: ='Historical Financials'!S106 -> 242 | T29: =SUM(H29:K29) -> 391 | U29: =SUM(I29:L29) -> 500 | V29: =SUM(J29:M29) -> 490 | W29: =SUM(K29:N29) -> 512 | X29: =SUM(L29:O29) -> 528 | Y29: =SUM(M29:P29) -> 557 | Z29: =SUM(N29:Q29) -> 579 | AA29: =SUM(O29:R29) -> 595 | AB29: =SUM(P29:S29) -> 678 | AD29: =SUM(AB29/X29)-1 -> 0.28409091
B30: (+) Restructuring and other charges | C30: =-C20 -> 91 | D30: =-D20 -> 32 | E30: =-E20 -> 3757 | F30: =-F20 -> 585 | G30: =-G20 -> 447 | I30: =-I20 -> 95 | J30: =-J20 -> 146 | K30: =-K20 -> 269 | L30: =-L20 -> 75 | M30: =-M20 -> 35 | N30: =-N20 -> 117 | O30: =-O20 -> 9 | P30: =-P20 -> 286 | ... S30: =-S20 -> 88 | T30: =SUM(H30:K30) -> 510 | U30: =SUM(I30:L30) -> 585 | V30: =SUM(J30:M30) -> 525 | W30: =SUM(K30:N30) -> 496 | X30: =SUM(L30:O30) -> 236 | Y30: =SUM(M30:P30) -> 447 | Z30: =SUM(N30:Q30) -> 466 | AA30: =SUM(O30:R30) -> 429 | AB30: =SUM(P30:S30) -> 508 | AD30: =SUM(AB30/X30)-1 -> 1.1525424
B31: (+) Impairments and loss on dispositions | C31: =-C21 -> 124 | D31: =-D21 -> -71 | E31: =-E21 -> 117 | F31: =-F21 -> 77 | G31: =-G21 -> 9603 | I31: =-I21 -> 31 | J31: =-J21 -> 6 | K31: =-K21 -> 24 | L31: =-L21 -> 16 | M31: =-M21 -> 12 | N31: =-N21 -> 9395 | O31: =-O21 -> 5 | P31: =-P21 -> 191 | ... S31: =-S21 -> 46 | T31: =SUM(H31:K31) -> 61 | U31: =SUM(I31:L31) -> 77 | V31: =SUM(J31:M31) -> 58 | W31: =SUM(K31:N31) -> 9447 | X31: =SUM(L31:O31) -> 9428 | Y31: =SUM(M31:P31) -> 9603 | Z31: =SUM(N31:Q31) -> 9681 | AA31: =SUM(O31:R31) -> 312 | AB31: =SUM(P31:S31) -> 353 | AD31: =SUM(AB31/X31)-1 -> -0.96255834
B32: Adj. EBITDA | C32: =+SUM(C26+SUM(C29:C31)) -> 4199 | D32: =+SUM(D26+SUM(D29:D31)) -> 3733 | E32: =+SUM(E26+SUM(E29:E31)) -> 4109 | F32: =+SUM(F26+SUM(F29:F31)) -> 7599 | G32: =+SUM(G26+SUM(G29:G31)) -> 7612 | I32: =+SUM(I26+SUM(I29:I31)) -> 1738 | J32: =+SUM(J26+SUM(J29:J31)) -> 1297 | K32: =+SUM(K26+SUM(K29:K31)) -> 2522 | L32: =+SUM(L26+SUM(L29:L31)) -> 2042 | M32: =+SUM(M26+SUM(M29:M31)) -> 1769 | N32: =+SUM(N26+SUM(N29:N31)) -> 1207 | O32: =+SUM(O26+SUM(O29:O31)) -> 2216 | P32: =+SUM(P26+SUM(P29:P31)) -> 2420 | ... S32: =+SUM(S26+SUM(S29:S31)) -> 2362 | U32: =+SUM(U26+SUM(U29:U31)) -> 7599 | V32: =+SUM(V26+SUM(V29:V31)) -> 7630 | W32: =+SUM(W26+SUM(W29:W31)) -> 7540 | X32: =+SUM(X26+SUM(X29:X31)) -> 7234 | Y32: =+SUM(Y26+SUM(Y29:Y31)) -> 7612 | Z32: =+SUM(Z26+SUM(Z29:Z31)) -> 7620 | AA32: =+SUM(AA26+SUM(AA29:AA31)) -> 7956 | AB32: =+SUM(AB26+SUM(AB29:AB31)) -> 8102 | AD32: =SUM(AB32/X32)-1 -> 0.11998894
B33: Adj. EBITDA Margin (%) | C33: =C32/C10 -> 0.39349639 | D33: =D32/D10 -> 0.3062095 | E33: =E32/E10 -> 0.12150693 | F33: =F32/F10 -> 0.18390165 | G33: =G32/G10 -> 0.19358612 | I33: =I32/I10 -> 0.16242991 | J33: =J32/J10 -> 0.12521722 | K33: =K32/K10 -> 0.25273073 | L33: =L32/L10 -> 0.19856087 | M33: =M32/M10 -> 0.17764611 | N33: =N32/N10 -> 0.12426645 | O33: =O32/O10 -> 0.23028162 | P33: =P32/P10 -> 0.24134836 | ... S33: =S32/S10 -> 0.26113875 | U33: =U32/U10 -> 0.18390165 | V33: =V32/V10 -> 0.18802829 | W33: =W32/W10 -> 0.18881154 | X33: =X32/X10 -> 0.18277831 | Y33: =Y32/Y10 -> 0.19358612 | Z33: =Z32/Z10 -> 0.19873768 | AA33: =AA32/AA10 -> 0.20696652 | AB33: =AB32/AB10 -> 0.21398199 | AD33: =SUM(AB33-X33)*10000 -> 312.03677
B35: (-) Capital Expenditures | C35: ='Historical Financials'!C123 -> -402 | D35: ='Historical Financials'!D123 -> -373 | E35: ='Historical Financials'!E123 -> -987 | F35: ='Historical Financials'!F123 -> -1316 | G35: ='Historical Financials'!G123 -> -948 | I35: ='Historical Financials'!I123 -> -299 | J35: ='Historical Financials'!J123 -> -292 | K35: ='Historical Financials'!K123 -> -457 | L35: ='Historical Financials'!L123 -> -268 | M35: ='Historical Financials'!M123 -> -195 | N35: ='Historical Financials'!N123 -> -252 | O35: ='Historical Financials'!O123 -> -215 | P35: ='Historical Financials'!P123 -> -286 | ... S35: ='Historical Financials'!S123 -> -278 | T35: =SUM(H35:K35) -> -1048 | U35: =SUM(I35:L35) -> -1316 | V35: =SUM(J35:M35) -> -1212 | W35: =SUM(K35:N35) -> -1172 | X35: =SUM(L35:O35) -> -930 | Y35: =SUM(M35:P35) -> -948 | Z35: =SUM(N35:Q35) -> -1004 | AA35: =SUM(O35:R35) -> -1033 | AB35: =SUM(P35:S35) -> -1096 | AD35: =SUM(AB35/X35)-1 -> 0.17849462
B36: (-) Cash Taxes | C36: =-'Historical Financials'!C150 -> -641 | D36: =-'Historical Financials'!D150 -> -643 | E36: =-'Historical Financials'!E150 -> -1027 | F36: =-'Historical Financials'!F150 -> -1440 | G36: =-'Historical Financials'!G150 -> -1113 | I36: =-'Historical Financials'!I150 -> -312 | J36: =-'Historical Financials'!J150 -> -518 | K36: =-'Historical Financials'!K150 -> -361 | L36: =-'Historical Financials'!L150 -> -249 | M36: =-'Historical Financials'!M150 -> -118 | N36: =-'Historical Financials'!N150 -> -366 | O36: =-'Historical Financials'!O150 -> -348 | P36: =-'Historical Financials'!P150 -> -281 | Q36: ='Historical Financials'!Q31 -> -15 | R36: ='Historical Financials'!R31 -> -866 | S36: ='Historical Financials'!S31 -> -170 | T36: =SUM(H36:K36) -> -1191 | U36: =SUM(I36:L36) -> -1440 | V36: =SUM(J36:M36) -> -1246 | W36: =SUM(K36:N36) -> -1094 | X36: =SUM(L36:O36) -> -1081 | Y36: =SUM(M36:P36) -> -1113 | Z36: =SUM(N36:Q36) -> -1010 | AA36: =SUM(O36:R36) -> -1510 | AB36: =SUM(P36:S36) -> -1332 | AD36: =SUM(AB36/X36)-1 -> 0.23219241
B37: (-) Cash Interest | C37: =-'Historical Financials'!C151 -> -673 | D37: =-'Historical Financials'!D151 -> -664 | E37: =-'Historical Financials'!E151 -> -1539 | F37: =-'Historical Financials'!F151 -> -2237 | G37: =-'Historical Financials'!G151 -> -1996 | I37: =-'Historical Financials'!I151 -> -920 | J37: =-'Historical Financials'!J151 -> -217 | K37: =-'Historical Financials'!K151 -> -928 | L37: =-'Historical Financials'!L151 -> -172 | M37: =-'Historical Financials'!M151 -> -867 | N37: =-'Historical Financials'!N151 -> -194 | O37: =-'Historical Financials'!O151 -> -812 | P37: =-'Historical Financials'!P151 -> -123 | Q37: ='Historical Financials'!Q24 -> -468 | R37: ='Historical Financials'!R24 -> -463 | S37: ='Historical Financials'!S24 -> -570 | T37: =SUM(H37:K37) -> -2065 | U37: =SUM(I37:L37) -> -2237 | V37: =SUM(J37:M37) -> -2184 | W37: =SUM(K37:N37) -> -2161 | X37: =SUM(L37:O37) -> -2045 | Y37: =SUM(M37:P37) -> -1996 | Z37: =SUM(N37:Q37) -> -1597 | AA37: =SUM(O37:R37) -> -1866 | AB37: =SUM(P37:S37) -> -1624 | AD37: =SUM(AB37/X37)-1 -> -0.20586797
B38: (-) Mandatory Outflows | T38: =SUM(H38:K38) -> 0 | U38: =SUM(I38:L38) -> 0 | V38: =SUM(J38:M38) -> 0 | W38: =SUM(K38:N38) -> 0 | X38: =SUM(L38:O38) -> 0 | Y38: =SUM(M38:P38) -> 0 | Z38: =SUM(N38:Q38) -> 0 | AA38: =SUM(O38:R38) -> 0 | AB38: =SUM(P38:S38) -> 0 | AD38: =SUM(AB38/X38)-1 -> #DIV/0!
B39: (+/-) Changes in NWC | C39: =SUM('Historical Financials'!C116:C119) -> -3099 | D39: =SUM('Historical Financials'!D116:D119) -> -3237 | E39: =SUM('Historical Financials'!E116:E119) -> -10982 | F39: =SUM('Historical Financials'!F116:F119) -> -11989 | G39: =SUM('Historical Financials'!G116:G119) -> -12126 | I39: =SUM('Historical Financials'!I116:I119) -> -5930 | J39: =SUM('Historical Financials'!J116:J119) -> -2734 | K39: =SUM('Historical Financials'!K116:K119) -> -1844 | L39: =SUM('Historical Financials'!L116:L119) -> -1481 | M39: =SUM('Historical Financials'!M116:M119) -> -3899 | N39: =SUM('Historical Financials'!N116:N119) -> -2800 | O39: =SUM('Historical Financials'!O116:O119) -> -3943 | P39: =SUM('Historical Financials'!P116:P119) -> -1484 | ... S39: =SUM('Historical Financials'!S116:S119) -> -3015 | T39: =SUM(H39:K39) -> -10508 | U39: =SUM(I39:L39) -> -11989 | V39: =SUM(J39:M39) -> -9958 | W39: =SUM(K39:N39) -> -10024 | X39: =SUM(L39:O39) -> -12123 | Y39: =SUM(M39:P39) -> -12126 | Z39: =SUM(N39:Q39) -> -11835 | AA39: =SUM(O39:R39) -> -11779 | AB39: =SUM(P39:S39) -> -10851 | AD39: =SUM(AB39/X39)-1 -> -0.10492452
B40: Discretionary Cash-Flows | C40: =SUM(C32+SUM(C35:C39)) -> -616 | D40: =SUM(D32+SUM(D35:D39)) -> -1184 | E40: =SUM(E32+SUM(E35:E39)) -> -10426 | F40: =SUM(F32+SUM(F35:F39)) -> -9383 | G40: =SUM(G32+SUM(G35:G39)) -> -8571 | I40: =SUM(I32+SUM(I35:I39)) -> -5723 | J40: =SUM(J32+SUM(J35:J39)) -> -2464 | K40: =SUM(K32+SUM(K35:K39)) -> -1068 | L40: =SUM(L32+SUM(L35:L39)) -> -128 | M40: =SUM(M32+SUM(M35:M39)) -> -3310 | N40: =SUM(N32+SUM(N35:N39)) -> -2405 | O40: =SUM(O32+SUM(O35:O39)) -> -3102 | P40: =SUM(P32+SUM(P35:P39)) -> 246 | ... S40: =SUM(S32+SUM(S35:S39)) -> -1671 | U40: =SUM(U32+SUM(U35:U39)) -> -9383 | V40: =SUM(V32+SUM(V35:V39)) -> -6970 | W40: =SUM(W32+SUM(W35:W39)) -> -6911 | X40: =SUM(X32+SUM(X35:X39)) -> -8945 | Y40: =SUM(Y32+SUM(Y35:Y39)) -> -8571 | Z40: =SUM(Z32+SUM(Z35:Z39)) -> -7826 | AA40: =SUM(AA32+SUM(AA35:AA39)) -> -8232 | AB40: =SUM(AB32+SUM(AB35:AB39)) -> -6801 | AD40: =SUM(AB40/X40)-1 -> -0.23968698
B42: (+/-) Divestitures / (Acquisitions) | C42: ='Historical Financials'!C124 -> -39 | D42: ='Historical Financials'!D124 -> -2 | E42: ='Historical Financials'!E124 -> 3612 | F42: ='Historical Financials'!F124 -> -50 | G42: ='Historical Financials'!G124 -> 0 | I42: ='Historical Financials'!I124 -> 0 | J42: ='Historical Financials'!J124 -> 0 | K42: ='Historical Financials'!K124 -> 0 | L42: ='Historical Financials'!L124 -> -50 | M42: ='Historical Financials'!M124 -> 0 | N42: ='Historical Financials'!N124 -> 0 | O42: ='Historical Financials'!O124 -> 0 | P42: ='Historical Financials'!P124 -> 0 | ... S42: ='Historical Financials'!S124 -> -66 | T42: =SUM(H42:K42) -> 0 | U42: =SUM(I42:L42) -> -50 | V42: =SUM(J42:M42) -> -50 | W42: =SUM(K42:N42) -> -50 | X42: =SUM(L42:O42) -> -50 | Y42: =SUM(M42:P42) -> 0 | Z42: =SUM(N42:Q42) -> 66 | AA42: =SUM(O42:R42) -> 66 | AB42: =SUM(P42:S42) -> 0
B43: (+/-) Proceeds from Investments / (Purchases) | C43: ='Historical Financials'!C125 -> -362 | D43: ='Historical Financials'!D125 -> 312 | E43: ='Historical Financials'!E125 -> 138 | F43: ='Historical Financials'!F125 -> -112 | G43: ='Historical Financials'!G125 -> 432 | I43: ='Historical Financials'!I125 -> -13 | J43: ='Historical Financials'!J125 -> -32 | K43: ='Historical Financials'!K125 -> -46 | L43: ='Historical Financials'!L125 -> -21 | M43: ='Historical Financials'!M125 -> -53 | N43: ='Historical Financials'!N125 -> 309 | O43: ='Historical Financials'!O125 -> -36 | P43: ='Historical Financials'!P125 -> 212 | ... S43: ='Historical Financials'!S125 -> -71 | T43: =SUM(H43:K43) -> -91 | U43: =SUM(I43:L43) -> -112 | V43: =SUM(J43:M43) -> -152 | W43: =SUM(K43:N43) -> 189 | X43: =SUM(L43:O43) -> 199 | Y43: =SUM(M43:P43) -> 432 | Z43: =SUM(N43:Q43) -> 482 | AA43: =SUM(O43:R43) -> 204 | AB43: =SUM(P43:S43) -> 169
B44: (+/-) Proceeds from Debt / (Repayment) | C44: ='Historical Financials'!C131 -> -214 | D44: ='Historical Financials'!D131 -> -574 | E44: ='Historical Financials'!E131 -> -7317 | F44: ='Historical Financials'!F131 -> -5371 | G44: ='Historical Financials'!G131 -> -3426 | I44: ='Historical Financials'!I131 -> -107 | J44: ='Historical Financials'!J131 -> -1656 | K44: ='Historical Financials'!K131 -> -2415 | L44: ='Historical Financials'!L131 -> -1193 | M44: ='Historical Financials'!M131 -> -1047 | N44: ='Historical Financials'!N131 -> -1039 | O44: ='Historical Financials'!O131 -> -847 | P44: ='Historical Financials'!P131 -> -493 | ... S44: ='Historical Financials'!S131 -> -1257 | T44: =SUM(H44:K44) -> -4178 | U44: =SUM(I44:L44) -> -5371 | V44: =SUM(J44:M44) -> -6311 | W44: =SUM(K44:N44) -> -5694 | X44: =SUM(L44:O44) -> -4126 | Y44: =SUM(M44:P44) -> -3426 | Z44: =SUM(N44:Q44) -> -4544 | AA44: =SUM(O44:R44) -> -3440 | AB44: =SUM(P44:S44) -> -3850
B45: (+/-) Changes in non-control. & redeemable interests | C45: ='Historical Financials'!C132 -> -254 | D45: ='Historical Financials'!D132 -> -251 | E45: ='Historical Financials'!E132 -> -300 | F45: ='Historical Financials'!F132 -> -350 | G45: ='Historical Financials'!G132 -> -193 | I45: ='Historical Financials'!I132 -> -237 | J45: ='Historical Financials'!J132 -> -32 | K45: ='Historical Financials'!K132 -> -13 | L45: ='Historical Financials'!L132 -> -68 | M45: ='Historical Financials'!M132 -> -130 | N45: ='Historical Financials'!N132 -> -31 | O45: ='Historical Financials'!O132 -> -11 | P45: ='Historical Financials'!P132 -> -21 | ... S45: ='Historical Financials'!S132 -> -14 | T45: =SUM(H45:K45) -> -282 | U45: =SUM(I45:L45) -> -350 | V45: =SUM(J45:M45) -> -243 | W45: =SUM(K45:N45) -> -242 | X45: =SUM(L45:O45) -> -240 | Y45: =SUM(M45:P45) -> -193 | Z45: =SUM(N45:Q45) -> -220 | AA45: =SUM(O45:R45) -> -206 | AB45: =SUM(P45:S45) -> -209
B46: (+/-) Changes in Content rights amortization and impairment | C46: ='Historical Financials'!C103 -> 2956 | D46: ='Historical Financials'!D103 -> 3501 | E46: ='Historical Financials'!E103 -> 14161 | F46: ='Historical Financials'!F103 -> 16024 | G46: ='Historical Financials'!G103 -> 13946 | I46: ='Historical Financials'!I103 -> 4723 | J46: ='Historical Financials'!J103 -> 4638 | K46: ='Historical Financials'!K103 -> 3186 | L46: ='Historical Financials'!L103 -> 3477 | M46: ='Historical Financials'!M103 -> 3827 | N46: ='Historical Financials'!N103 -> 3920 | O46: ='Historical Financials'!O103 -> 3132 | P46: ='Historical Financials'!P103 -> 3067 | ... S46: ='Historical Financials'!S103 -> 2242 | T46: =SUM(H46:K46) -> 12547 | U46: =SUM(I46:L46) -> 16024 | V46: =SUM(J46:M46) -> 15128 | W46: =SUM(K46:N46) -> 14410 | X46: =SUM(L46:O46) -> 14356 | Y46: =SUM(M46:P46) -> 13946 | Z46: =SUM(N46:Q46) -> 13264 | AA46: =SUM(O46:R46) -> 13050 | AB46: =SUM(P46:S46) -> 12160
B47: (+/-) Other | D47: =SUM(D52)-SUM(C52)-SUM(D40:D46) -> 12 | E47: =SUM(E52)-SUM(D52)-SUM(E40:E46) -> -42 | F47: =SUM(F52)-SUM(E52)-SUM(F40:F46) -> -709 | G47: =SUM(G52)-SUM(F52)-SUM(G40:G46) -> -656 | I47: =SUM(I52)-SUM(E52)-SUM(I40:I46) -> 220 | J47: =SUM(J52)-SUM(I52)-SUM(J40:J46) -> -21 | K47: =SUM(K52)-SUM(J52)-SUM(K40:K46) -> -288 | L47: =SUM(L52)-SUM(K52)-SUM(L40:L46) -> -620 | M47: =SUM(M52)-SUM(L52)-SUM(M40:M46) -> -91 | N47: =SUM(N52)-SUM(M52)-SUM(N40:N46) -> -117 | O47: =SUM(O52)-SUM(N52)-SUM(O40:O46) -> 587 | P47: =SUM(P52)-SUM(O52)-SUM(P40:P46) -> -1035 | Q47: =SUM(Q52)-SUM(P52)-SUM(Q40:Q46) -> 235 | ... S47: =SUM(S52)-SUM(R52)-SUM(S40:S46) -> 243 | T47: =SUM(H47:K47) -> -89 | U47: =SUM(I47:L47) -> -709 | V47: =SUM(J47:M47) -> -1020 | W47: =SUM(K47:N47) -> -1116 | X47: =SUM(L47:O47) -> -241 | Y47: =SUM(M47:P47) -> -656 | Z47: =SUM(N47:Q47) -> -330 | AA47: =SUM(O47:R47) -> -167 | AB47: =SUM(P47:S47) -> -511
B48: Free-Cash Flows | C48: =SUM(C40+SUM(C42:C47)) -> 1471 | D48: =SUM(D40+SUM(D42:D47)) -> 1814 | E48: =SUM(E40+SUM(E42:E47)) -> -174 | F48: =SUM(F40+SUM(F42:F47)) -> 49 | G48: =SUM(G40+SUM(G42:G47)) -> 1532 | I48: =SUM(I40+SUM(I42:I47)) -> -1137 | J48: =SUM(J40+SUM(J42:J47)) -> 433 | K48: =SUM(K40+SUM(K42:K47)) -> -644 | L48: =SUM(L40+SUM(L42:L47)) -> 1397 | M48: =SUM(M40+SUM(M42:M47)) -> -804 | N48: =SUM(N40+SUM(N42:N47)) -> 637 | O48: =SUM(O40+SUM(O42:O47)) -> -277 | P48: =SUM(P40+SUM(P42:P47)) -> 1976 | ... S48: =SUM(S40+SUM(S42:S47)) -> -594 | U48: =SUM(U40+SUM(U42:U47)) -> 49 | V48: =SUM(V40+SUM(V42:V47)) -> 382 | W48: =SUM(W40+SUM(W42:W47)) -> 586 | X48: =SUM(X40+SUM(X42:X47)) -> 953 | Y48: =SUM(Y40+SUM(Y42:Y47)) -> 1532 | Z48: =SUM(Z40+SUM(Z42:Z47)) -> 892 | AA48: =SUM(AA40+SUM(AA42:AA47)) -> 1275 | AB48: =SUM(AB40+SUM(AB42:AB47)) -> 958
B50: Capitalization
B52: Cash and Cash Equivalents | C52: ='Historical Financials'!C49 -> 2091 | D52: ='Historical Financials'!D49 -> 3905 | E52: ='Historical Financials'!E49 -> 3731 | F52: ='Historical Financials'!F49 -> 3780 | G52: ='Historical Financials'!G49 -> 5312 | I52: ='Historical Financials'!I49 -> 2594 | J52: ='Historical Financials'!J49 -> 3027 | K52: ='Historical Financials'!K49 -> 2383 | L52: ='Historical Financials'!L49 -> 3780 | M52: ='Historical Financials'!M49 -> 2976 | N52: ='Historical Financials'!N49 -> 3613 | O52: ='Historical Financials'!O49 -> 3336 | P52: ='Historical Financials'!P49 -> 5312 | ... S52: ='Historical Financials'!S49 -> 4294 | U52: =L52 -> 3780 | V52: =M52 -> 2976 | W52: =N52 -> 3613 | X52: =O52 -> 3336 | Y52: =P52 -> 5312 | Z52: =Q52 -> 3868 | AA52: =R52 -> 4888 | AB52: =S52 -> 4294
B53: $4.0Bn RCF | C53: 4000 | D53: 4000 | E53: 4000 | F53: 4000 | G53: 4000 | I53: 4000 | J53: 4000 | K53: 4000 | L53: =E53 -> 4000 | M53: 4000 | N53: 4000 | O53: 4000 | P53: =F53 -> 4000 | Q53: 4000 | R53: 4000 | S53: 4000 | U53: =N53 -> 4000 | V53: =O53 -> 4000 | W53: =P53 -> 4000 | X53: =O53 -> 4000 | Y53: =P53 -> 4000 | Z53: =Q53 -> 4000 | AA53: =R53 -> 4000 | AB53: =S53 -> 4000
B54: Total Liquidity | C54: =SUM(C52:C53) -> 6091 | D54: =SUM(D52:D53) -> 7905 | E54: =SUM(E52:E53) -> 7731 | F54: =SUM(F52:F53) -> 7780 | G54: =SUM(G52:G53) -> 9312 | I54: =SUM(I52:I53) -> 6594 | J54: =SUM(J52:J53) -> 7027 | K54: =SUM(K52:K53) -> 6383 | L54: =SUM(L52:L53) -> 7780 | M54: =SUM(M52:M53) -> 6976 | N54: =SUM(N52:N53) -> 7613 | O54: =SUM(O52:O53) -> 7336 | P54: =SUM(P52:P53) -> 9312 | ... S54: =SUM(S52:S53) -> 8294 | U54: =SUM(U52:U53) -> 7780 | V54: =SUM(V52:V53) -> 6976 | W54: =SUM(W52:W53) -> 7613 | X54: =SUM(X52:X53) -> 7336 | Y54: =SUM(Y52:Y53) -> 9312 | Z54: =SUM(Z52:Z53) -> 7868 | AA54: =SUM(AA52:AA53) -> 8888 | AB54: =SUM(AB52:AB53) -> 8294
B56: Balance Sheet Metrics:
B57: Receivables, net | C57: ='Historical Financials'!C50 -> 2537 | D57: ='Historical Financials'!D50 -> 2446 | E57: ='Historical Financials'!E50 -> 6380 | F57: ='Historical Financials'!F50 -> 6047 | G57: ='Historical Financials'!G50 -> 4947 | I57: ='Historical Financials'!I50 -> 6833 | J57: ='Historical Financials'!J50 -> 6770 | K57: ='Historical Financials'!K50 -> 6312 | L57: ='Historical Financials'!L50 -> 6047 | M57: ='Historical Financials'!M50 -> 6303 | N57: ='Historical Financials'!N50 -> 6166 | O57: ='Historical Financials'!O50 -> 5534 | P57: ='Historical Financials'!P50 -> 4947 | ... S57: ='Historical Financials'!S50 -> 5128 | U57: =N57 -> 6166 | V57: =O57 -> 5534 | W57: =P57 -> 4947 | X57: =O57 -> 5534 | Y57: =P57 -> 4947 | Z57: =Q57 -> 4664 | AA57: =R57 -> 5383 | AB57: =S57 -> 5128
B58: Film and television content rights and games | C58: ='Historical Financials'!C55 -> 3439 | D58: ='Historical Financials'!D55 -> 3832 | E58: ='Historical Financials'!E55 -> 26652 | F58: ='Historical Financials'!F55 -> 21229 | G58: ='Historical Financials'!G55 -> 19102 | I58: ='Historical Financials'!I55 -> 25473 | J58: ='Historical Financials'!J55 -> 24393 | K58: ='Historical Financials'!K55 -> 22454 | L58: ='Historical Financials'!L55 -> 21229 | M58: ='Historical Financials'!M55 -> 20439 | N58: ='Historical Financials'!N55 -> 20010 | O58: ='Historical Financials'!O55 -> 20039 | P58: ='Historical Financials'!P55 -> 19102 | ... S58: ='Historical Financials'!S55 -> 19104 | U58: =N58 -> 20010 | V58: =O58 -> 20039 | W58: =P58 -> 19102 | X58: =O58 -> 20039 | Y58: =P58 -> 19102 | Z58: =Q58 -> 18821 | AA58: =R58 -> 18817 | AB58: =S58 -> 19104
B59: Property and equipment, net | C59: ='Historical Financials'!C56 -> 1206 | D59: ='Historical Financials'!D56 -> 1336 | E59: ='Historical Financials'!E56 -> 5301 | F59: ='Historical Financials'!F56 -> 5957 | G59: ='Historical Financials'!G56 -> 6087 | I59: ='Historical Financials'!I56 -> 5325 | J59: ='Historical Financials'!J56 -> 5473 | K59: ='Historical Financials'!K56 -> 5810 | L59: ='Historical Financials'!L56 -> 5957 | M59: ='Historical Financials'!M56 -> 5937 | N59: ='Historical Financials'!N56 -> 6043 | O59: ='Historical Financials'!O56 -> 6158 | P59: ='Historical Financials'!P56 -> 6087 | ... S59: ='Historical Financials'!S56 -> 6517 | U59: =N59 -> 6043 | V59: =O59 -> 6158 | W59: =P59 -> 6087 | X59: =O59 -> 6158 | Y59: =P59 -> 6087 | Z59: =Q59 -> 6211 | AA59: =R59 -> 6413 | AB59: =S59 -> 6517
B60: Accounts payable | C60: ='Historical Financials'!C63 -> 397 | D60: ='Historical Financials'!D63 -> 412 | E60: ='Historical Financials'!E63 -> 1454 | F60: ='Historical Financials'!F63 -> 1260 | G60: ='Historical Financials'!G63 -> 1055 | I60: ='Historical Financials'!I63 -> 1123 | J60: ='Historical Financials'!J63 -> 1689 | K60: ='Historical Financials'!K63 -> 1329 | L60: ='Historical Financials'!L63 -> 1260 | M60: ='Historical Financials'!M63 -> 1245 | N60: ='Historical Financials'!N63 -> 1151 | O60: ='Historical Financials'!O63 -> 1120 | P60: ='Historical Financials'!P63 -> 1055 | ... S60: ='Historical Financials'!S63 -> 1083 | U60: =N60 -> 1151 | V60: =O60 -> 1120 | W60: =P60 -> 1055 | X60: =O60 -> 1120 | Y60: =P60 -> 1055 | Z60: =Q60 -> 1008 | AA60: =R60 -> 1074 | AB60: =S60 -> 1083
B61: Deferred revenues | C61: ='Historical Financials'!C65 -> 557 | D61: ='Historical Financials'!D65 -> 478 | E61: ='Historical Financials'!E65 -> 1694 | F61: ='Historical Financials'!F65 -> 1924 | G61: ='Historical Financials'!G65 -> 1569 | I61: ='Historical Financials'!I65 -> 1603 | J61: ='Historical Financials'!J65 -> 1548 | K61: ='Historical Financials'!K65 -> 1917 | L61: ='Historical Financials'!L65 -> 1924 | M61: ='Historical Financials'!M65 -> 1993 | N61: ='Historical Financials'!N65 -> 2022 | O61: ='Historical Financials'!O65 -> 1530 | P61: ='Historical Financials'!P65 -> 1569 | ... S61: ='Historical Financials'!S65 -> 1649 | U61: =N61 -> 2022 | V61: =O61 -> 1530 | W61: =P61 -> 1569 | X61: =O61 -> 1530 | Y61: =P61 -> 1569 | Z61: =Q61 -> 1600 | AA61: =R61 -> 1527 | AB61: =S61 -> 1649
B62: Current Liabilities | C62: ='Historical Financials'!C67 -> 3082 | D62: ='Historical Financials'!D67 -> 3459 | E62: ='Historical Financials'!E67 -> 15017 | F62: ='Historical Financials'!F67 -> 15332 | G62: ='Historical Financials'!G67 -> 15810 | I62: ='Historical Financials'!I67 -> 16380 | J62: ='Historical Financials'!J67 -> 16906 | K62: ='Historical Financials'!K67 -> 14588 | L62: ='Historical Financials'!L67 -> 15332 | M62: ='Historical Financials'!M67 -> 16956 | N62: ='Historical Financials'!N67 -> 17768 | O62: ='Historical Financials'!O67 -> 15695 | P62: ='Historical Financials'!P67 -> 15810 | ... S62: ='Historical Financials'!S67 -> 12163 | U62: =N62 -> 17768 | V62: =O62 -> 15695 | W62: =P62 -> 15810 | X62: =O62 -> 15695 | Y62: =P62 -> 15810 | Z62: =Q62 -> 15286 | AA62: =R62 -> 13040 | AB62: =S62 -> 12163
B63: Total Liabilities | C63: ='Historical Financials'!C73 -> 21704 | D63: ='Historical Financials'!D73 -> 21031 | E63: ='Historical Financials'!E73 -> 85334 | F63: ='Historical Financials'!F73 -> 76285 | G63: ='Historical Financials'!G73 -> 69622 | I63: ='Historical Financials'!I73 -> 82742 | J63: ='Historical Financials'!J73 -> 81833 | K63: ='Historical Financials'!K73 -> 77607 | L63: ='Historical Financials'!L73 -> 76285 | M63: ='Historical Financials'!M73 -> 74525 | N63: ='Historical Financials'!N73 -> 72614 | O63: ='Historical Financials'!O73 -> 70159 | P63: ='Historical Financials'!P73 -> 69622 | ... S63: ='Historical Financials'!S73 -> 63214 | U63: =N63 -> 72614 | V63: =O63 -> 70159 | W63: =P63 -> 69622 | X63: =O63 -> 70159 | Y63: =P63 -> 69622 | Z63: =Q63 -> 66508 | AA63: =R63 -> 64381 | AB63: =S63 -> 63214
B65: Summary Debt:
B66: CPLTD | C66: ='Historical Financials'!C66 -> 335 | D66: ='Historical Financials'!D66 -> 339 | E66: ='Historical Financials'!E66 -> 365 | F66: ='Historical Financials'!F66 -> 1780 | G66: ='Historical Financials'!G66 -> 2748 | I66: ='Historical Financials'!I66 -> 3496 | J66: ='Historical Financials'!J66 -> 3001 | K66: ='Historical Financials'!K66 -> 1302 | L66: ='Historical Financials'!L66 -> 1780 | M66: ='Historical Financials'!M66 -> 3430 | N66: ='Historical Financials'!N66 -> 3669 | O66: ='Historical Financials'!O66 -> 3043 | P66: ='Historical Financials'!P66 -> 2748 | ... S66: ='Historical Financials'!S66 -> 139 | U66: =N66 -> 3669 | V66: =O66 -> 3043 | W66: =P66 -> 2748 | X66: =O66 -> 3043 | Y66: =P66 -> 2748 | Z66: =Q66 -> 2779 | AA66: =R66 -> 221 | AB66: =S66 -> 139
B67: LTD | C67: ='Historical Financials'!C70 -> 15069 | D67: ='Historical Financials'!D70 -> 14420 | E67: ='Historical Financials'!E70 -> 48634 | F67: ='Historical Financials'!F70 -> 41889 | G67: ='Historical Financials'!G70 -> 36757 | I67: ='Historical Financials'!I70 -> 45434 | J67: ='Historical Financials'!J70 -> 44276 | K67: ='Historical Financials'!K70 -> 43498 | L67: ='Historical Financials'!L70 -> 41889 | M67: ='Historical Financials'!M70 -> 39148 | N67: ='Historical Financials'!N70 -> 37289 | O67: ='Historical Financials'!O70 -> 37166 | P67: ='Historical Financials'!P70 -> 36757 | ... S67: ='Historical Financials'!S70 -> 33382 | U67: =N67 -> 37289 | V67: =O67 -> 37166 | W67: =P67 -> 36757 | X67: =O67 -> 37166 | Y67: =P67 -> 36757 | Z67: =Q67 -> 34647 | AA67: =R67 -> 34411 | AB67: =S67 -> 33382
B69: Aggregate Debt Holdings | C69: =SUM(C66:C67) -> 15404 | D69: =SUM(D66:D67) -> 14759 | E69: =SUM(E66:E67) -> 48999 | F69: =SUM(F66:F67) -> 43669 | G69: =SUM(G66:G67) -> 39505 | I69: =SUM(I66:I67) -> 48930 | J69: =SUM(J66:J67) -> 47277 | K69: =SUM(K66:K67) -> 44800 | L69: =SUM(L66:L67) -> 43669 | M69: =SUM(M66:M67) -> 42578 | N69: =SUM(N66:N67) -> 40958 | O69: =SUM(O66:O67) -> 40209 | P69: =SUM(P66:P67) -> 39505 | ... S69: =SUM(S66:S67) -> 33521 | U69: =N69 -> 40958 | V69: =O69 -> 40209 | W69: =P69 -> 39505 | X69: =O69 -> 40209 | Y69: =P69 -> 39505 | Z69: =Q69 -> 37426 | AA69: =R69 -> 34632 | AB69: =S69 -> 33521
B70: Total Debt | C70: =SUM(C69:C69) -> 15404 | D70: =SUM(D69:D69) -> 14759 | E70: =SUM(E69:E69) -> 48999 | F70: =SUM(F69:F69) -> 43669 | G70: =SUM(G69:G69) -> 39505 | I70: =SUM(I69:I69) -> 48930 | J70: =SUM(J69:J69) -> 47277 | K70: =SUM(K69:K69) -> 44800 | L70: =SUM(L69:L69) -> 43669 | M70: =SUM(M69:M69) -> 42578 | N70: =SUM(N69:N69) -> 40958 | O70: =SUM(O69:O69) -> 40209 | P70: =SUM(P69:P69) -> 39505 | ... S70: =SUM(S69:S69) -> 33521 | U70: =SUM(U69:U69) -> 40958 | V70: =SUM(V69:V69) -> 40209 | W70: =SUM(W69:W69) -> 39505 | X70: =SUM(X69:X69) -> 40209 | Y70: =SUM(Y69:Y69) -> 39505 | Z70: =SUM(Z69:Z69) -> 37426 | AA70: =SUM(AA69:AA69) -> 34632 | AB70: =SUM(AB69:AB69) -> 33521
B72: Total Shareholder Equity | C72: ='Historical Financials'!C89 -> 12000 | D72: ='Historical Financials'!D89 -> 13033 | E72: ='Historical Financials'!E89 -> 48349 | F72: ='Historical Financials'!F89 -> 46307 | G72: ='Historical Financials'!G89 -> 34829 | I72: ='Historical Financials'!I89 -> 47533 | J72: ='Historical Financials'!J89 -> 46479 | K72: ='Historical Financials'!K89 -> 45861 | L72: ='Historical Financials'!L89 -> 46307 | M72: ='Historical Financials'!M89 -> 45115 | N72: ='Historical Financials'!N89 -> 35297 | O72: ='Historical Financials'!O89 -> 36057 | P72: ='Historical Financials'!P89 -> 34829 | ... S72: ='Historical Financials'!S89 -> 37282 | U72: =N72 -> 35297 | V72: =O72 -> 36057 | W72: =P72 -> 34829 | X72: =O72 -> 36057 | Y72: =P72 -> 34829 | Z72: =Q72 -> 35148 | AA72: =R72 -> 37323 | AB72: =S72 -> 37282
B73: Total Book Capitalization | C73: =SUM(C70:C72) -> 27404 | D73: =SUM(D70:D72) -> 27792 | E73: =SUM(E70:E72) -> 97348 | F73: =SUM(F70:F72) -> 89976 | G73: =SUM(G70:G72) -> 74334 | I73: =SUM(I70:I72) -> 96463 | J73: =SUM(J70:J72) -> 93756 | K73: =SUM(K70:K72) -> 90661 | L73: =SUM(L70:L72) -> 89976 | M73: =SUM(M70:M72) -> 87693 | N73: =SUM(N70:N72) -> 76255 | O73: =SUM(O70:O72) -> 76266 | P73: =SUM(P70:P72) -> 74334 | ... S73: =SUM(S70:S72) -> 70803 | U73: =SUM(U70:U72) -> 76255 | V73: =SUM(V70:V72) -> 76266 | W73: =SUM(W70:W72) -> 74334 | X73: =SUM(X70:X72) -> 76266 | Y73: =SUM(Y70:Y72) -> 74334 | Z73: =SUM(Z70:Z72) -> 72574 | AA73: =SUM(AA70:AA72) -> 71955 | AB73: =SUM(AB70:AB72) -> 70803
B75: Credit Metrics
B77: LTM Total Leverage | C77: =C70/C32 -> 3.6684925 | D77: =D70/D32 -> 3.9536566 | E77: =E70/E32 -> 11.924799 | F77: =F70/F32 -> 5.7466772 | G77: =G70/G32 -> 5.1898318 | L77: =SUM(L70/SUM(I32:L32)) -> 5.7466772 | M77: =SUM(M70/SUM(J32:M32)) -> 5.5803408 | N77: =SUM(N70/SUM(K32:N32)) -> 5.4320955 | O77: =SUM(O70/SUM(L32:O32)) -> 5.5583356 | P77: =SUM(P70/SUM(M32:P32)) -> 5.1898318 | Q77: =SUM(Q70/SUM(N32:Q32)) -> 4.9115486 | R77: =SUM(R70/SUM(O32:R32)) -> 4.3529412 | S77: =SUM(S70/SUM(P32:S32)) -> 4.1373735 | U77: =U70/U32 -> 5.3899197 | V77: =V70/V32 -> 5.2698558 | W77: =W70/W32 -> 5.2393899 | X77: =X70/X32 -> 5.5583356 | Y77: =Y70/Y32 -> 5.1898318 | Z77: =Z70/Z32 -> 4.9115486 | AA77: =AA70/AA32 -> 4.3529412 | AB77: =AB70/AB32 -> 4.1373735
B78: LTM Net Leverage | C78: =SUM(C70-C52)/C32 -> 3.1705168 | D78: =SUM(D70-D52)/D32 -> 2.907581 | E78: =SUM(E70-E52)/E32 -> 11.016792 | F78: =SUM(F70-F52)/F32 -> 5.2492433 | G78: =SUM(G70-G52)/G32 -> 4.4919863 | L78: =SUM(L70-L52)/SUM(I32:L32) -> 5.2492433 | M78: =SUM(M70-M52)/SUM(J32:M32) -> 5.1903014 | N78: =SUM(N70-N52)/SUM(K32:N32) -> 4.9529178 | O78: =SUM(O70-O52)/SUM(L32:O32) -> 5.09718 | P78: =SUM(P70-P52)/SUM(M32:P32) -> 4.4919863 | Q78: =SUM(Q70-Q52)/SUM(N32:Q32) -> 4.403937 | R78: =SUM(R70-R52)/SUM(O32:R32) -> 3.7385621 | S78: =SUM(S70-S52)/SUM(P32:S32) -> 3.6073809 | U78: =SUM(U70-U52)/U32 -> 4.8924859 | V78: =SUM(V70-V52)/V32 -> 4.8798165 | W78: =SUM(W70-W52)/W32 -> 4.7602122 | X78: =SUM(X70-X52)/X32 -> 5.09718 | Y78: =SUM(Y70-Y52)/Y32 -> 4.4919863 | Z78: =SUM(Z70-Z52)/Z32 -> 4.403937 | AA78: =SUM(AA70-AA52)/AA32 -> 3.7385621 | AB78: =SUM(AB70-AB52)/AB32 -> 3.6073809
B79: LTM Interest Coverage | C79: =C32/-C37 -> 6.2392273 | D79: =D32/-D37 -> 5.621988 | E79: =E32/-E37 -> 2.6699155 | F79: =F32/-F37 -> 3.3969602 | G79: =G32/-G37 -> 3.8136273 | L79: {=SUM(I32:L32)/SUM(-I37:L37)} -> 3.3969602 | M79: {=SUM(J32:M32)/SUM(-J37:M37)} -> 3.4935897 | N79: {=SUM(K32:N32)/SUM(-K37:N37)} -> 3.4891254 | O79: {=SUM(L32:O32)/SUM(-L37:O37)} -> 3.5374083 | P79: {=SUM(M32:P32)/SUM(-M37:P37)} -> 3.8136273 | Q79: {=SUM(N32:Q32)/SUM(-N37:Q37)} -> 4.7714465 | R79: {=SUM(O32:R32)/SUM(-O37:R37)} -> 4.2636656 | S79: {=SUM(P32:S32)/SUM(-P37:S37)} -> 4.9889163 | U79: =U32/-U37 -> 3.3969602 | V79: =V32/-V37 -> 3.4935897 | W79: =W32/-W37 -> 3.4891254 | X79: =X32/-X37 -> 3.5374083 | Y79: =Y32/-Y37 -> 3.8136273 | Z79: =Z32/-Z37 -> 4.7714465 | AA79: =AA32/-AA37 -> 4.2636656 | AB79: =AB32/-AB37 -> 4.9889163
B80: LTM Debt Service Coverage | C80: {=SUM(C32+C35)/SUM(-C36:C37)} -> 2.8896499 | D80: {=SUM(D32+D35)/SUM(-D36:D37)} -> 2.5707728 | E80: {=SUM(E32+E35)/SUM(-E36:E37)} -> 1.2166797 | F80: {=SUM(F32+F35)/SUM(-F36:F37)} -> 1.7087299 | G80: {=SUM(G32+G35)/SUM(-G36:G37)} -> 2.1434545 | L80: {=SUM(I32:L32+I35:L35)/SUM(-I36:L37)} -> 1.7087299 | M80: {=SUM(J32:M32+J35:M35)/SUM(-J36:M37)} -> 1.871137 | N80: {=SUM(K32:N32+K35:N35)/SUM(-K36:N37)} -> 1.9563748 | O80: {=SUM(L32:O32+L35:O35)/SUM(-L36:O37)} -> 2.0166347 | P80: {=SUM(M32:P32+M35:P35)/SUM(-M36:P37)} -> 2.1434545 | Q80: {=SUM(N32:Q32+N35:Q35)/SUM(-N36:Q37)} -> 2.5377829 | R80: {=SUM(O32:R32+O35:R35)/SUM(-O36:R37)} -> 2.0506517 | S80: {=SUM(P32:S32+P35:S35)/SUM(-P36:S37)} -> 2.3700947 | U80: {=SUM(U32+U35)/SUM(-U36:U37)} -> 1.7087299 | V80: {=SUM(V32+V35)/SUM(-V36:V37)} -> 1.871137 | W80: {=SUM(W32+W35)/SUM(-W36:W37)} -> 1.9563748 | X80: {=SUM(X32+X35)/SUM(-X36:X37)} -> 2.0166347 | Y80: {=SUM(Y32+Y35)/SUM(-Y36:Y37)} -> 2.1434545 | Z80: {=SUM(Z32+Z35)/SUM(-Z36:Z37)} -> 2.5377829 | AA80: {=SUM(AA32+AA35)/SUM(-AA36:AA37)} -> 2.0506517 | AB80: {=SUM(AB32+AB35)/SUM(-AB36:AB37)} -> 2.3700947
B81: LTM Fixed Charge Coverage | C81: {=SUM(C32)/SUM(-C35:C37)} -> 2.4469697 | D81: {=SUM(D32)/SUM(-D35:D37)} -> 2.2220238 | E81: {=SUM(E32)/SUM(-E35:E37)} -> 1.1564875 | F81: {=SUM(F32)/SUM(-F35:F37)} -> 1.5219307 | G81: {=SUM(G32)/SUM(-G35:G37)} -> 1.8762632 | L81: {=SUM(I32:L32)/SUM(-I35:L37)} -> 1.5219307 | M81: {=SUM(J32:M32)/SUM(-J35:M37)} -> 1.6436881 | N81: {=SUM(K32:N32)/SUM(-K35:N37)} -> 1.703185 | O81: {=SUM(L32:O32)/SUM(-L35:O37)} -> 1.7835306 | P81: {=SUM(M32:P32)/SUM(-M35:P37)} -> 1.8762632 | Q81: {=SUM(N32:Q32)/SUM(-N35:Q37)} -> 2.1102188 | R81: {=SUM(O32:R32)/SUM(-O35:R37)} -> 1.8044908 | S81: {=SUM(P32:S32)/SUM(-P35:S37)} -> 1.9995064 | U81: {=SUM(U32)/SUM(-U35:U37)} -> 1.5219307 | V81: {=SUM(V32)/SUM(-V35:V37)} -> 1.6436881 | W81: {=SUM(W32)/SUM(-W35:W37)} -> 1.703185 | X81: {=SUM(X32)/SUM(-X35:X37)} -> 1.7835306 | Y81: {=SUM(Y32)/SUM(-Y35:Y37)} -> 1.8762632 | Z81: {=SUM(Z32)/SUM(-Z35:Z37)} -> 2.1102188 | AA81: {=SUM(AA32)/SUM(-AA35:AA37)} -> 1.8044908 | AB81: {=SUM(AB32)/SUM(-AB35:AB37)} -> 1.9995064
B82: Debt-to-Book Capitalization | C82: =C73/C70 -> 1.7790184 | D82: =D73/D70 -> 1.8830544 | E82: =E73/E70 -> 1.9867344 | F82: =F73/F70 -> 2.060409 | G82: =G73/G70 -> 1.8816352 | L82: =L73/L70 -> 2.060409 | M82: =M73/M70 -> 2.0595848 | N82: =N73/N70 -> 1.8617852 | O82: =O73/O70 -> 1.8967395 | P82: =P73/P70 -> 1.8816352 | Q82: =Q73/Q70 -> 1.9391332 | R82: =R73/R70 -> 2.0777027 | S82: =S73/S70 -> 2.1121983 | U82: =U73/U70 -> 1.8617852 | V82: =V73/V70 -> 1.8967395 | W82: =W73/W70 -> 1.8816352 | X82: =X73/X70 -> 1.8967395 | Y82: =Y73/Y70 -> 1.8816352 | Z82: =Z73/Z70 -> 1.9391332 | AA82: =AA73/AA70 -> 2.0777027 | AB82: =AB73/AB70 -> 2.1121983
