Workbook

Sheet Historical Financials
B2: Paramount Global (NASDAQ: PARA)
B3: Historical Financials
B4: ($ In Millions, except EPS)
A6: X | B6: Income Statement | D6: FYE | H6: Quarterly | N6: Quarterly | U6: LTM | AA6: Variance
B7: Fiscal Period | C7: 2021 | D7: 2022 | E7: 2023 | F7: 2024 | H7: 1Q23 | I7: 2Q23 | J7: 3Q23 | K7: 4Q23 | L7: 1Q24 | M7: 2Q24 | N7: 3Q24 | O7: 4Q24 | P7: 1Q25 | Q7: 2Q25 | S7: =K7 -> 4Q23 | T7: =L7 -> 1Q24 | U7: =M7 -> 2Q24 | V7: =N7 -> 3Q24 | W7: =O7 -> 4Q24 | X7: =P7 -> 1Q25 | Y7: =Q7 -> 2Q25
B8: Fiscal Period End Date | C8: 44561 | D8: 44926 | E8: 45291 | F8: 45657 | H8: 45016 | I8: 45107 | J8: 45199 | K8: =D8 -> 44926 | L8: 45382 | M8: 45473 | N8: 45565 | O8: =E8 -> 45291 | P8: 45747 | Q8: 45838 | S8: =K8 -> 44926 | T8: =L8 -> 45382 | U8: =M8 -> 45473 | V8: =N8 -> 45565 | W8: =O8 -> 45291 | X8: =P8 -> 45747 | Y8: =Q8 -> 45838
B10: Consolidated Revenue | C10: 28586 | D10: 30154 | E10: 29652 | F10: 29213 | H10: 7265 | I10: 7616 | J10: 7133 | K10: =SUM(E10-SUM(H10:J10)) -> 7638 | L10: 7685 | M10: 6813 | N10: 6731 | O10: =SUM(F10-SUM(L10:N10)) -> 7984 | P10: 7192 | Q10: 6849 | S10: =SUM(H10:K10) -> 29652 | T10: =SUM(I10:L10) -> 30072 | U10: =SUM(J10:M10) -> 29269 | V10: =SUM(K10:N10) -> 28867 | W10: =SUM(L10:O10) -> 29213 | X10: =SUM(M10:P10) -> 28720 | Y10: =SUM(N10:Q10) -> 28756 | AA10: =SUM(Y10/U10)-1 -> -0.017527076
B11: Total Revenue | C11: =+SUM(C10:C10) -> 28586 | D11: =+SUM(D10:D10) -> 30154 | E11: =+SUM(E10:E10) -> 29652 | F11: =+SUM(F10:F10) -> 29213 | H11: =+SUM(H10:H10) -> 7265 | I11: =+SUM(I10:I10) -> 7616 | J11: =+SUM(J10:J10) -> 7133 | K11: =+SUM(K10:K10) -> 7638 | L11: =+SUM(L10:L10) -> 7685 | M11: =+SUM(M10:M10) -> 6813 | N11: =+SUM(N10:N10) -> 6731 | O11: =+SUM(O10:O10) -> 7984 | ... Q11: =+SUM(Q10:Q10) -> 6849 | S11: =+SUM(S10:S10) -> 29652 | T11: =+SUM(T10:T10) -> 30072 | U11: =+SUM(U10:U10) -> 29269 | V11: =+SUM(V10:V10) -> 28867 | W11: =+SUM(W10:W10) -> 29213 | X11: =+SUM(X10:X10) -> 28720 | Y11: =+SUM(Y10:Y10) -> 28756 | AA11: =SUM(Y11/U11)-1 -> -0.017527076
B13: Operating expenses | C13: -17744 | D13: -19845 | E13: -20017 | F13: -19437 | H13: -4964 | I13: -5227 | J13: -4681 | K13: =SUM(E13-SUM(H13:J13)) -> -5145 | L13: -5036 | M13: -4367 | N13: -4342 | O13: =SUM(F13-SUM(L13:N13)) -> -5692 | P13: -4961 | Q13: -4624 | S13: =SUM(H13:K13) -> -20017 | T13: =SUM(I13:L13) -> -20089 | U13: =SUM(J13:M13) -> -19229 | V13: =SUM(K13:N13) -> -18890 | W13: =SUM(L13:O13) -> -19437 | X13: =SUM(M13:P13) -> -19362 | Y13: =SUM(N13:Q13) -> -19619 | AA13: =SUM(Y13/U13)-1 -> 0.020281866
B14: Programming charges | C14: 0 | D14: 0 | E14: -2371 | F14: -1118 | H14: -1674 | I14: -697 | J14: 0 | K14: =SUM(E14-SUM(H14:J14)) -> 0 | L14: -1118 | M14: 0 | N14: 0 | O14: =SUM(F14-SUM(L14:N14)) -> 0 | P14: 0 | Q14: 0 | S14: =SUM(H14:K14) -> -2371 | T14: =SUM(I14:L14) -> -1815 | U14: =SUM(J14:M14) -> -1118 | V14: =SUM(K14:N14) -> -1118 | W14: =SUM(L14:O14) -> -1118 | X14: =SUM(M14:P14) -> 0 | Y14: =SUM(N14:Q14) -> 0 | AA14: =SUM(Y14/U14)-1 -> -1
B15: Selling, general and administrative | C15: -6398 | D15: -7033 | E15: -7245 | F15: -6658 | H15: -1753 | I15: -1783 | J15: -1736 | K15: =SUM(E15-SUM(H15:J15)) -> -1973 | L15: -1662 | M15: -1579 | N15: -1531 | O15: =SUM(F15-SUM(L15:N15)) -> -1886 | P15: -1543 | Q15: -1401 | S15: =SUM(H15:K15) -> -7245 | T15: =SUM(I15:L15) -> -7154 | U15: =SUM(J15:M15) -> -6950 | V15: =SUM(K15:N15) -> -6745 | W15: =SUM(L15:O15) -> -6658 | X15: =SUM(M15:P15) -> -6539 | Y15: =SUM(N15:Q15) -> -6361 | AA15: =SUM(Y15/U15)-1 -> -0.084748201
B16: Depreciation and amortization | C16: -390 | D16: -378 | E16: -418 | F16: -392 | H16: -100 | I16: -105 | J16: -105 | K16: =SUM(E16-SUM(H16:J16)) -> -108 | L16: -100 | M16: -101 | N16: -96 | O16: =SUM(F16-SUM(L16:N16)) -> -95 | P16: -88 | Q16: -87 | S16: =SUM(H16:K16) -> -418 | T16: =SUM(I16:L16) -> -418 | U16: =SUM(J16:M16) -> -414 | V16: =SUM(K16:N16) -> -405 | W16: =SUM(L16:O16) -> -392 | X16: =SUM(M16:P16) -> -380 | Y16: =SUM(N16:Q16) -> -366 | AA16: =SUM(Y16/U16)-1 -> -0.11594203
B17: Impairment charges | C17: 0 | D17: -27 | E17: -83 | F17: -6130 | H17: 0 | I17: 0 | J17: 0 | K17: =SUM(E17-SUM(H17:J17)) -> -83 | L17: -186 | M17: -5996 | N17: -104 | O17: =SUM(F17-SUM(L17:N17)) -> 156 | P17: 0 | Q17: -157 | S17: =SUM(H17:K17) -> -83 | T17: =SUM(I17:L17) -> -269 | U17: =SUM(J17:M17) -> -6265 | V17: =SUM(K17:N17) -> -6369 | W17: =SUM(L17:O17) -> -6130 | X17: =SUM(M17:P17) -> -5944 | Y17: =SUM(N17:Q17) -> -105 | AA17: =SUM(Y17/U17)-1 -> -0.98324022
B18: Restructuring, transaction-related items, and other corporate matters | C18: -100 | D18: -585 | E18: 31 | F18: -747 | H18: 0 | I18: -54 | J18: 10 | K18: =SUM(E18-SUM(H18:J18)) -> 75 | L18: 0 | M18: -88 | N18: -321 | O18: =SUM(F18-SUM(L18:N18)) -> -338 | P18: -85 | Q18: -181 | S18: =SUM(H18:K18) -> 31 | T18: =SUM(I18:L18) -> 31 | U18: =SUM(J18:M18) -> -3 | V18: =SUM(K18:N18) -> -334 | W18: =SUM(L18:O18) -> -747 | X18: =SUM(M18:P18) -> -832 | Y18: =SUM(N18:Q18) -> -925 | AA18: =SUM(Y18/U18)-1 -> 307.33333
B19: Gains on dispositions | C19: 2343 | D19: 56 | E19: 0 | F19: 0 | H19: 0 | I19: 0 | J19: 0 | K19: =SUM(E19-SUM(H19:J19)) -> 0 | L19: 0 | M19: 0 | N19: 0 | O19: =SUM(F19-SUM(L19:N19)) -> 0 | P19: 35 | Q19: 0 | S19: =SUM(H19:K19) -> 0 | T19: =SUM(I19:L19) -> 0 | U19: =SUM(J19:M19) -> 0 | V19: =SUM(K19:N19) -> 0 | W19: =SUM(L19:O19) -> 0 | X19: =SUM(M19:P19) -> 35 | Y19: =SUM(N19:Q19) -> 35 | AA19: =SUM(Y19/U19)-1 -> #DIV/0!
B20: Operating Profit | C20: =+SUM(C11+SUM(C13:C19)) -> 6297 | D20: =+SUM(D11+SUM(D13:D19)) -> 2342 | E20: =+SUM(E11+SUM(E13:E19)) -> -451 | F20: =+SUM(F11+SUM(F13:F19)) -> -5269 | H20: =+SUM(H11+SUM(H13:H19)) -> -1226 | I20: =+SUM(I11+SUM(I13:I19)) -> -250 | J20: =+SUM(J11+SUM(J13:J19)) -> 621 | K20: =+SUM(K11+SUM(K13:K19)) -> 404 | L20: =+SUM(L11+SUM(L13:L19)) -> -417 | M20: =+SUM(M11+SUM(M13:M19)) -> -5318 | N20: =+SUM(N11+SUM(N13:N19)) -> 337 | O20: =+SUM(O11+SUM(O13:O19)) -> 129 | ... Q20: =+SUM(Q11+SUM(Q13:Q19)) -> 399 | S20: =+SUM(S11+SUM(S13:S19)) -> -451 | T20: =+SUM(T11+SUM(T13:T19)) -> 358 | U20: =+SUM(U11+SUM(U13:U19)) -> -4710 | V20: =+SUM(V11+SUM(V13:V19)) -> -4994 | W20: =+SUM(W11+SUM(W13:W19)) -> -5269 | X20: =+SUM(X11+SUM(X13:X19)) -> -4302 | Y20: =+SUM(Y11+SUM(Y13:Y19)) -> 1415 | AA20: =SUM(Y20/U20)-1 -> -1.3004246
B21: Operating Margin (%) | C21: =C20/C11 -> 0.22028266 | D21: =D20/D11 -> 0.077667971 | E21: =E20/E11 -> -0.015209767 | F21: =F20/F11 -> -0.18036491 | H21: =H20/H11 -> -0.1687543 | I21: =I20/I11 -> -0.03282563 | J21: =J20/J11 -> 0.087060143 | K21: =K20/K11 -> 0.052893428 | L21: =L20/L11 -> -0.054261548 | M21: =M20/M11 -> -0.78056656 | N21: =N20/N11 -> 0.050066855 | O21: =O20/O11 -> 0.016157315 | ... Q21: =Q20/Q11 -> 0.05825668 | S21: =S20/S11 -> -0.015209767 | T21: =T20/T11 -> 0.011904762 | U21: =U20/U11 -> -0.16092111 | V21: =V20/V11 -> -0.17300031 | W21: =W20/W11 -> -0.18036491 | X21: =X20/X11 -> -0.14979109 | Y21: =Y20/Y11 -> 0.049207122 | AA21: =SUM(Y21-U21)*1000 -> 210.12823
B23: Interest expense | C23: -986 | D23: -931 | E23: -920 | F23: -860 | H23: -226 | I23: -240 | J23: -232 | K23: =SUM(E23-SUM(H23:J23)) -> -222 | L23: -221 | M23: -215 | N23: -209 | O23: =SUM(F23-SUM(L23:N23)) -> -215 | P23: -217 | Q23: -214 | S23: =SUM(H23:K23) -> -920 | T23: =SUM(I23:L23) -> -915 | U23: =SUM(J23:M23) -> -890 | V23: =SUM(K23:N23) -> -867 | W23: =SUM(L23:O23) -> -860 | X23: =SUM(M23:P23) -> -856 | Y23: =SUM(N23:Q23) -> -855 | AA23: =SUM(Y23/U23)-1 -> -0.039325843
B24: Interest income | C24: 53 | D24: 108 | E24: 137 | F24: 151 | H24: 35 | I24: 33 | J24: 29 | K24: =SUM(E24-SUM(H24:J24)) -> 40 | L24: 45 | M24: 35 | N24: 31 | O24: =SUM(F24-SUM(L24:N24)) -> 40 | P24: 38 | Q24: 32 | S24: =SUM(H24:K24) -> 137 | T24: =SUM(I24:L24) -> 147 | U24: =SUM(J24:M24) -> 149 | V24: =SUM(K24:N24) -> 151 | W24: =SUM(L24:O24) -> 151 | X24: =SUM(M24:P24) -> 144 | Y24: =SUM(N24:Q24) -> 141 | AA24: =SUM(Y24/U24)-1 -> -0.053691275
B25: Gain (loss) from investments | C25: 47 | D25: -9 | E25: 168 | F25: -17 | H25: 0 | I25: 168 | J25: 0 | K25: =SUM(E25-SUM(H25:J25)) -> 0 | L25: -4 | M25: 0 | N25: 0 | O25: =SUM(F25-SUM(L25:N25)) -> -13 | P25: 0 | Q25: 0 | S25: =SUM(H25:K25) -> 168 | T25: =SUM(I25:L25) -> 164 | U25: =SUM(J25:M25) -> -4 | V25: =SUM(K25:N25) -> -4 | W25: =SUM(L25:O25) -> -17 | X25: =SUM(M25:P25) -> -13 | Y25: =SUM(N25:Q25) -> -13 | AA25: =SUM(Y25/U25)-1 -> 2.25
B26: Gain (loss) on extinguishment of debt | C26: -128 | D26: -120 | E26: 29 | F26: 0 | H26: 0 | I26: 0 | J26: 0 | K26: =SUM(E26-SUM(H26:J26)) -> 29 | L26: 0 | M26: 0 | N26: 0 | O26: =SUM(F26-SUM(L26:N26)) -> 0 | P26: 0 | Q26: 0 | S26: =SUM(H26:K26) -> 29 | T26: =SUM(I26:L26) -> 29 | U26: =SUM(J26:M26) -> 29 | V26: =SUM(K26:N26) -> 29 | W26: =SUM(L26:O26) -> 0 | X26: =SUM(M26:P26) -> 0 | Y26: =SUM(N26:Q26) -> 0 | AA26: =SUM(Y26/U26)-1 -> -1
B27: Other items, net | C27: -77 | D27: -124 | E27: -216 | F27: -182 | H27: -46 | I27: -60 | J27: -42 | K27: =SUM(E27-SUM(H27:J27)) -> -68 | L27: -38 | M27: -49 | N27: -39 | O27: =SUM(F27-SUM(L27:N27)) -> -56 | P27: -37 | Q27: -39 | S27: =SUM(H27:K27) -> -216 | T27: =SUM(I27:L27) -> -208 | U27: =SUM(J27:M27) -> -197 | V27: =SUM(K27:N27) -> -194 | W27: =SUM(L27:O27) -> -182 | X27: =SUM(M27:P27) -> -181 | Y27: =SUM(N27:Q27) -> -171 | AA27: =SUM(Y27/U27)-1 -> -0.1319797
B28: Earnings (loss) from Continuing Operations before Taxes & Equity | C28: =SUM(C23:C27)+C20 -> 5206 | D28: =SUM(D23:D27)+D20 -> 1266 | E28: =SUM(E23:E27)+E20 -> -1253 | F28: =SUM(F23:F27)+F20 -> -6177 | H28: =SUM(H23:H27)+H20 -> -1463 | I28: =SUM(I23:I27)+I20 -> -349 | J28: =SUM(J23:J27)+J20 -> 376 | K28: =SUM(K23:K27)+K20 -> 183 | L28: =SUM(L23:L27)+L20 -> -635 | M28: =SUM(M23:M27)+M20 -> -5547 | N28: =SUM(N23:N27)+N20 -> 120 | O28: =SUM(O23:O27)+O20 -> -115 | ... Q28: =SUM(Q23:Q27)+Q20 -> 178 | S28: =SUM(S23:S27)+S20 -> -1253 | T28: =SUM(T23:T27)+T20 -> -425 | U28: =SUM(U23:U27)+U20 -> -5623 | V28: =SUM(V23:V27)+V20 -> -5879 | W28: =SUM(W23:W27)+W20 -> -6177 | X28: =SUM(X23:X27)+X20 -> -5208 | Y28: =SUM(Y23:Y27)+Y20 -> 517 | AA28: =SUM(Y28/U28)-1 -> -1.0919438
B29: EBT Margin (%) | C29: =C28/C11 -> 0.18211712 | D29: =D28/D11 -> 0.04198448 | E29: =E28/E11 -> -0.042256846 | F29: =F28/F11 -> -0.21144696 | H29: =H28/H11 -> -0.20137646 | I29: =I28/I11 -> -0.04582458 | J29: =J28/J11 -> 0.052712744 | K29: =K28/K11 -> 0.023959152 | L29: =L28/L11 -> -0.082628497 | M29: =M28/M11 -> -0.81417878 | N29: =N28/N11 -> 0.01782796 | O29: =O28/O11 -> -0.014403808 | ... Q29: =Q28/Q11 -> 0.025989196 | S29: =S28/S11 -> -0.042256846 | T29: =T28/T11 -> -0.014132748 | U29: =U28/U11 -> -0.19211452 | V29: =V28/V11 -> -0.20365816 | W29: =W28/W11 -> -0.21144696 | X29: =X28/X11 -> -0.18133705 | Y29: =Y28/Y11 -> 0.017978857 | AA29: =SUM(Y29-U29)*1000 -> 210.09338
B31: Income tax expense | C31: -646 | D31: -227 | E31: 361 | F31: 305 | H31: 381 | I31: 95 | J31: -40 | K31: =SUM(E31-SUM(H31:J31)) -> -75 | L31: 172 | M31: 215 | N31: -45 | O31: =SUM(F31-SUM(L31:N31)) -> -37 | P31: -100 | Q31: -50 | S31: =SUM(H31:K31) -> 361 | T31: =SUM(I31:L31) -> 152 | U31: =SUM(J31:M31) -> 272 | V31: =SUM(K31:N31) -> 267 | W31: =SUM(L31:O31) -> 305 | X31: =SUM(M31:P31) -> 33 | Y31: =SUM(N31:Q31) -> -232 | AA31: =SUM(Y31/U31)-1 -> -1.8529412
B32: Equity in loss of investee companies, net of tax | C32: -91 | D32: -204 | E32: -360 | F32: -291 | H32: -75 | I32: -109 | J32: -75 | K32: =SUM(E32-SUM(H32:J32)) -> -101 | L32: -90 | M32: -72 | N32: -59 | O32: =SUM(F32-SUM(L32:N32)) -> -70 | P32: -73 | Q32: -67 | S32: =SUM(H32:K32) -> -360 | T32: =SUM(I32:L32) -> -375 | U32: =SUM(J32:M32) -> -338 | V32: =SUM(K32:N32) -> -322 | W32: =SUM(L32:O32) -> -291 | X32: =SUM(M32:P32) -> -274 | Y32: =SUM(N32:Q32) -> -269
B33: Net earnings (loss) from continuing operations | C33: =SUM(C28+SUM(C31:C32)) -> 4469 | D33: =SUM(D28+SUM(D31:D32)) -> 835 | E33: =SUM(E28+SUM(E31:E32)) -> -1252 | F33: =SUM(F28+SUM(F31:F32)) -> -6163 | H33: =SUM(H28+SUM(H31:H32)) -> -1157 | I33: =SUM(I28+SUM(I31:I32)) -> -363 | J33: =SUM(J28+SUM(J31:J32)) -> 261 | K33: =SUM(K28+SUM(K31:K32)) -> 7 | L33: =SUM(L28+SUM(L31:L32)) -> -553 | M33: =SUM(M28+SUM(M31:M32)) -> -5404 | N33: =SUM(N28+SUM(N31:N32)) -> 16 | O33: =SUM(O28+SUM(O31:O32)) -> -222 | ... Q33: =SUM(Q28+SUM(Q31:Q32)) -> 61 | S33: =SUM(S23+SUM(S31:S32)) -> -919 | T33: =SUM(T23+SUM(T31:T32)) -> -1138 | U33: =SUM(U23+SUM(U31:U32)) -> -956 | V33: =SUM(V23+SUM(V31:V32)) -> -922 | W33: =SUM(W23+SUM(W31:W32)) -> -846 | X33: =SUM(X23+SUM(X31:X32)) -> -1097 | Y33: =SUM(Y23+SUM(Y31:Y32)) -> -1356 | AA33: =SUM(Y33/U33)-1 -> 0.41841004
B35: Net earnings from discontinued operations, net of tax | C35: 162 | D35: 379 | E35: 676 | F35: 14 | H35: 45 | I35: 73 | J35: 48 | K35: =SUM(E35-SUM(H35:J35)) -> 510 | L35: 9 | M35: 0 | N35: 5 | O35: =SUM(F35-SUM(L35:N35)) -> 0 | P35: 0 | Q35: 0 | S35: =SUM(H35:K35) -> 676 | T35: =SUM(I35:L35) -> 640 | U35: =SUM(J35:M35) -> 567 | V35: =SUM(K35:N35) -> 524 | W35: =SUM(L35:O35) -> 14 | X35: =SUM(M35:P35) -> 5 | Y35: =SUM(N35:Q35) -> 5 | AA35: =SUM(Y35/U35)-1 -> -0.99118166
B36: Net earnings (loss) (Paramount and noncontrolling interests) | C36: =SUM(C33)+SUM(C35:C35) -> 4631 | D36: =SUM(D33)+SUM(D35:D35) -> 1214 | E36: =SUM(E33)+SUM(E35:E35) -> -576 | F36: =SUM(F33)+SUM(F35:F35) -> -6149 | H36: =SUM(H33)+SUM(H35:H35) -> -1112 | I36: =SUM(I33)+SUM(I35:I35) -> -290 | J36: =SUM(J33)+SUM(J35:J35) -> 309 | K36: =SUM(K33)+SUM(K35:K35) -> 517 | L36: =SUM(L33)+SUM(L35:L35) -> -544 | M36: =SUM(M33)+SUM(M35:M35) -> -5404 | N36: =SUM(N33)+SUM(N35:N35) -> 21 | O36: =SUM(O33)+SUM(O35:O35) -> -222 | ... Q36: =SUM(Q33)+SUM(Q35:Q35) -> 61 | S36: =SUM(S33)+SUM(S35:S35) -> -243 | T36: =SUM(T33)+SUM(T35:T35) -> -498 | U36: =SUM(U33)+SUM(U35:U35) -> -389 | V36: =SUM(V33)+SUM(V35:V35) -> -398 | W36: =SUM(W33)+SUM(W35:W35) -> -832 | X36: =SUM(X33)+SUM(X35:X35) -> -1092 | Y36: =SUM(Y33)+SUM(Y35:Y35) -> -1351 | AA36: =SUM(Y36/U36)-1 -> 2.4730077
B38: Net earnings attributable to noncontrolling interests | C38: -88 | D38: -110 | E38: -32 | F38: -41 | H38: -6 | I38: -9 | J38: -14 | K38: =SUM(E38-SUM(H38:J38)) -> -3 | L38: -10 | M38: -9 | N38: -20 | O38: =SUM(F38-SUM(L38:N38)) -> -2 | P38: -9 | Q38: -4 | S38: =SUM(H38:K38) -> -32 | T38: =SUM(I38:L38) -> -36 | U38: =SUM(J38:M38) -> -36 | V38: =SUM(K38:N38) -> -42 | W38: =SUM(L38:O38) -> -41 | X38: =SUM(M38:P38) -> -40 | Y38: =SUM(N38:Q38) -> -35 | AA38: =SUM(Y38/U38)-1 -> -0.027777778
B39: Net earnings (loss) attributable to Paramount | C39: =SUM(C36+SUM(C38:C38)) -> 4543 | D39: =SUM(D36+SUM(D38:D38)) -> 1104 | E39: =SUM(E36+SUM(E38:E38)) -> -608 | F39: =SUM(F36+SUM(F38:F38)) -> -6190 | H39: =SUM(H36+SUM(H38:H38)) -> -1118 | I39: =SUM(I36+SUM(I38:I38)) -> -299 | J39: =SUM(J36+SUM(J38:J38)) -> 295 | K39: =SUM(K36+SUM(K38:K38)) -> 514 | L39: =SUM(L36+SUM(L38:L38)) -> -554 | M39: =SUM(M36+SUM(M38:M38)) -> -5413 | N39: =SUM(N36+SUM(N38:N38)) -> 1 | O39: =SUM(O36+SUM(O38:O38)) -> -224 | ... Q39: =SUM(Q36+SUM(Q38:Q38)) -> 57 | S39: =SUM(S36+SUM(S38:S38)) -> -275 | T39: =SUM(T36+SUM(T38:T38)) -> -534 | U39: =SUM(U36+SUM(U38:U38)) -> -425 | V39: =SUM(V36+SUM(V38:V38)) -> -440 | W39: =SUM(W36+SUM(W38:W38)) -> -873 | X39: =SUM(X36+SUM(X38:X38)) -> -1132 | Y39: =SUM(Y36+SUM(Y38:Y38)) -> -1386 | AA39: =SUM(Y39/U39)-1 -> 2.2611765
B40: Net Margin (%) | C40: =C39/C11 -> 0.15892395 | D40: =D39/D11 -> 0.036612058 | E40: =E39/E11 -> -0.020504519 | F40: =F39/F11 -> -0.21189197 | H40: =H39/H11 -> -0.15388851 | I40: =I39/I11 -> -0.039259454 | J40: =J39/J11 -> 0.041357073 | K40: =K39/K11 -> 0.067295103 | L40: =L39/L11 -> -0.072088484 | M40: =M39/M11 -> -0.79451049 | N40: =N39/N11 -> 0.00014856633 | O40: =O39/O11 -> -0.028056112 | ... Q40: =Q39/Q11 -> 0.0083223828 | S40: =S39/S11 -> -0.0092742479 | T40: =T39/T11 -> -0.017757382 | U40: =U39/U11 -> -0.014520482 | V40: =V39/V11 -> -0.015242318 | W40: =W39/W11 -> -0.029883956 | X40: =X39/X11 -> -0.039415042 | Y40: =Y39/Y11 -> -0.048198637 | AA40: =SUM(Y40-U40)*1000 -> -33.678154
B42: Basic shares | C42: 641 | D42: 649 | E42: 652 | F42: 664 | H42: 651 | I42: 651 | J42: 652 | K42: =E42 -> 652 | L42: 654 | M42: 667 | N42: 667 | O42: =F42 -> 664 | P42: 672 | Q42: 675 | S42: =K42 -> 652 | T42: =L42 -> 654 | U42: =M42 -> 667 | V42: =N42 -> 667 | W42: =O42 -> 664 | X42: =P42 -> 672 | Y42: =Q42 -> 675 | AA42: =SUM(Y42/U42)-1 -> 0.011994003
B43: Basic EPS | C43: =C39/C42 -> 7.0873635 | D43: =D39/D42 -> 1.7010786 | E43: =E39/E42 -> -0.93251534 | F43: =F39/F42 -> -9.3222892 | H43: =H39/H42 -> -1.7173579 | I43: =I39/I42 -> -0.45929339 | J43: =J39/J42 -> 0.45245399 | K43: =K39/K42 -> 0.78834356 | L43: =L39/L42 -> -0.8470948 | M43: =M39/M42 -> -8.1154423 | N43: =N39/N42 -> 0.0014992504 | O43: =O39/O42 -> -0.3373494 | ... Q43: =Q39/Q42 -> 0.084444444 | S43: =S39/S42 -> -0.42177914 | T43: =T39/T42 -> -0.81651376 | U43: =U39/U42 -> -0.63718141 | V43: =V39/V42 -> -0.65967016 | W43: =W39/W42 -> -1.314759 | X43: =X39/X42 -> -1.6845238 | Y43: =Y39/Y42 -> -2.0533333 | AA43: =SUM(Y43/U43)-1 -> 2.2225255
B45: Fully Diluted Shares | C45: 655 | D45: 650 | E45: 652 | F45: 664 | H45: 651 | I45: 651 | J45: 652 | K45: =E45 -> 652 | L45: 654 | M45: 667 | N45: 670 | O45: =F45 -> 664 | P45: 678 | Q45: 680 | S45: =K45 -> 652 | T45: =L45 -> 654 | U45: =M45 -> 667 | V45: =N45 -> 670 | W45: =O45 -> 664 | X45: =P45 -> 678 | Y45: =Q45 -> 680 | AA45: =SUM(Y45/U45)-1 -> 0.019490255
B46: Diluted EPS | C46: =C39/C45 -> 6.9358779 | D46: =D39/D45 -> 1.6984615 | E46: =E39/E45 -> -0.93251534 | F46: =F39/F45 -> -9.3222892 | H46: =H39/H45 -> -1.7173579 | I46: =I39/I45 -> -0.45929339 | J46: =J39/J45 -> 0.45245399 | K46: =K39/K45 -> 0.78834356 | L46: =L39/L45 -> -0.8470948 | M46: =M39/M45 -> -8.1154423 | N46: =N39/N45 -> 0.0014925373 | O46: =O39/O45 -> -0.3373494 | ... Q46: =Q39/Q45 -> 0.083823529 | S46: =S39/S45 -> -0.42177914 | T46: =T39/T45 -> -0.81651376 | U46: =U39/U45 -> -0.63718141 | V46: =V39/V45 -> -0.65671642 | W46: =W39/W45 -> -1.314759 | X46: =X39/X45 -> -1.6696165 | Y46: =Y39/Y45 -> -2.0382353 | AA46: =SUM(Y46/U46)-1 -> 2.1988304
A48: X | B48: Balance Sheet | C48: FYE | N48: Quarterly | U48: LTM | AA48: Variance
B49: =B7 -> Fiscal Period | C49: =C7 -> 2021 | D49: =D7 -> 2022 | E49: =E7 -> 2023 | F49: =F7 -> 2024 | H49: =H7 -> 1Q23 | I49: =I7 -> 2Q23 | J49: =J7 -> 3Q23 | K49: =K7 -> 4Q23 | L49: =L7 -> 1Q24 | M49: =M7 -> 2Q24 | N49: =N7 -> 3Q24 | O49: =O7 -> 4Q24 | ... Q49: =Q7 -> 2Q25 | S49: =S7 -> 4Q23 | T49: =T7 -> 1Q24 | U49: =U7 -> 2Q24 | V49: =V7 -> 3Q24 | W49: =W7 -> 4Q24 | X49: =X7 -> 1Q25 | Y49: =Y7 -> 2Q25
B50: =B8 -> Fiscal Period End Date | C50: =C8 -> 44561 | D50: =D8 -> 44926 | E50: =E8 -> 45291 | F50: =F8 -> 45657 | H50: =H8 -> 45016 | I50: =I8 -> 45107 | J50: =J8 -> 45199 | K50: =K8 -> 44926 | L50: =L8 -> 45382 | M50: =M8 -> 45473 | N50: =N8 -> 45565 | O50: =O8 -> 45291 | ... Q50: =Q8 -> 45838 | S50: =S8 -> 44926 | T50: =T8 -> 45382 | U50: =U8 -> 45473 | V50: =V8 -> 45565 | W50: =W8 -> 45291 | X50: =X8 -> 45747 | Y50: =Y8 -> 45838
B52: Current Assets
B53: Cash and cash equivalents | C53: 6267 | D53: 2885 | E53: 2460 | F53: 2661 | H53: 2109 | I53: 1714 | J53: 1804 | K53: =E53 -> 2460 | L53: 2384 | M53: 2315 | N53: 2443 | O53: =F53 -> 2661 | P53: 2673 | Q53: 2739 | S53: =K53 -> 2460 | T53: =L53 -> 2384 | U53: =M53 -> 2315 | V53: =N53 -> 2443 | W53: =O53 -> 2661 | X53: =P53 -> 2673 | Y53: =Q53 -> 2739 | AA53: =SUM(Y53/U53)-1 -> 0.18315335
B54: Receivables, net | C54: 6984 | D54: 7412 | E54: 7115 | F54: 6920 | H54: 7448 | I54: 7186 | J54: 6939 | K54: =E54 -> 7115 | L54: 7096 | M54: 6545 | N54: 6327 | O54: =F54 -> 6920 | P54: 6835 | Q54: 6291 | S54: =K54 -> 7115 | T54: =L54 -> 7096 | U54: =M54 -> 6545 | V54: =N54 -> 6327 | W54: =O54 -> 6920 | X54: =P54 -> 6835 | Y54: =Q54 -> 6291 | AA54: =SUM(Y54/U54)-1 -> -0.038808251
B55: Programming and other inventory | C55: 1504 | D55: 1342 | E55: 1414 | F55: 1429 | H55: 1085 | I55: 1533 | J55: 1754 | K55: =E55 -> 1414 | L55: 892 | M55: 1322 | N55: 1664 | O55: =F55 -> 1429 | P55: 1054 | Q55: 1519 | S55: =K55 -> 1414 | T55: =L55 -> 892 | U55: =M55 -> 1322 | V55: =N55 -> 1664 | W55: =O55 -> 1429 | X55: =P55 -> 1054 | Y55: =Q55 -> 1519 | AA55: =SUM(Y55/U55)-1 -> 0.14901664
B56: Prepaid expenses and other current assets | C56: =1176+745 -> 1921 | D56: =1308+787 -> 2095 | E56: =1677+37 -> 1714 | F56: 1532 | H56: =1364+651 -> 2015 | I56: =1458+568 -> 2026 | J56: =1536+678 -> 2214 | K56: =E56 -> 1714 | L56: =1511+49 -> 1560 | M56: 1497 | N56: =1484+7 -> 1491 | O56: =F56 -> 1532 | P56: 1411 | Q56: 1568 | S56: =K56 -> 1714 | T56: =L56 -> 1560 | U56: =M56 -> 1497 | V56: =N56 -> 1491 | W56: =O56 -> 1532 | X56: =P56 -> 1411 | Y56: =Q56 -> 1568 | AA56: =SUM(Y56/U56)-1 -> 0.04742819
B57: Total Current Assets | C57: =SUM(C53:C56) -> 16676 | D57: =SUM(D53:D56) -> 13734 | E57: =SUM(E53:E56) -> 12703 | F57: =SUM(F53:F56) -> 12542 | H57: =SUM(H53:H56) -> 12657 | I57: =SUM(I53:I56) -> 12459 | J57: =SUM(J53:J56) -> 12711 | K57: =SUM(K53:K56) -> 12703 | L57: =SUM(L53:L56) -> 11932 | M57: =SUM(M53:M56) -> 11679 | N57: =SUM(N53:N56) -> 11925 | O57: =SUM(O53:O56) -> 12542 | ... Q57: =SUM(Q53:Q56) -> 12117 | S57: =SUM(S53:S56) -> 12703 | T57: =SUM(T53:T56) -> 11932 | U57: =SUM(U53:U56) -> 11679 | V57: =SUM(V53:V56) -> 11925 | W57: =SUM(W53:W56) -> 12542 | X57: =SUM(X53:X56) -> 11973 | Y57: =SUM(Y53:Y56) -> 12117 | AA57: =SUM(Y57/U57)-1 -> 0.037503211
B59: Non-Current Assets
B60: Property and equipment, net | C60: 1736 | D60: 1762 | E60: 1666 | F60: 1566 | H60: 1718 | I60: 1689 | J60: 1668 | K60: =E60 -> 1666 | L60: 1612 | M60: 1567 | N60: 1545 | O60: =F60 -> 1566 | P60: 1519 | Q60: 1494 | S60: =K60 -> 1666 | T60: =L60 -> 1612 | U60: =M60 -> 1567 | V60: =N60 -> 1545 | W60: =O60 -> 1566 | X60: =P60 -> 1519 | Y60: =Q60 -> 1494 | AA60: =SUM(Y60/U60)-1 -> -0.046585833
B61: Programming and other inventory | C61: 13358 | D61: 16278 | E61: 13851 | F61: 13924 | H61: 15692 | I61: 14602 | J61: 13844 | K61: =E61 -> 13851 | L61: 13420 | M61: 13672 | N61: 13948 | O61: =F61 -> 13924 | P61: 14032 | Q61: 13812 | S61: =K61 -> 13851 | T61: =L61 -> 13420 | U61: =M61 -> 13672 | V61: =N61 -> 13948 | W61: =O61 -> 13924 | X61: =P61 -> 14032 | Y61: =Q61 -> 13812 | AA61: =SUM(Y61/U61)-1 -> 0.010239906
B62: Goodwill | C62: 16584 | D62: 16499 | E62: 16516 | F62: 10508 | H62: 16511 | I62: 16517 | J62: 16488 | K62: =E62 -> 16516 | L62: 16500 | M62: 10509 | N62: 10508 | O62: =F62 -> 10508 | P62: 10488 | Q62: 10488 | S62: =K62 -> 16516 | T62: =L62 -> 16500 | U62: =M62 -> 10509 | V62: =N62 -> 10508 | W62: =O62 -> 10508 | X62: =P62 -> 10488 | Y62: =Q62 -> 10488 | AA62: =SUM(Y62/U62)-1 -> -0.0019982872
B63: Intangible assets, net | C63: 2772 | D63: 2694 | E63: 2589 | F63: 2406 | H63: 2688 | I63: 2682 | J63: 2675 | K63: =E63 -> 2589 | L63: 2580 | M63: 2558 | N63: 2450 | O63: =F63 -> 2406 | P63: 2404 | Q63: 2249 | S63: =K63 -> 2589 | T63: =L63 -> 2580 | U63: =M63 -> 2558 | V63: =N63 -> 2450 | W63: =O63 -> 2406 | X63: =P63 -> 2404 | Y63: =Q63 -> 2249 | AA63: =SUM(Y63/U63)-1 -> -0.1207975
B64: Operating lease assets | C64: 1630 | D64: 1391 | E64: 1183 | F64: 1012 | H64: 1363 | I64: 1302 | J64: 1264 | K64: =E64 -> 1183 | L64: 1117 | M64: 1069 | N64: 1029 | O64: =F64 -> 1012 | P64: 945 | Q64: 922 | S64: =K64 -> 1183 | T64: =L64 -> 1117 | U64: =M64 -> 1069 | V64: =N64 -> 1029 | W64: =O64 -> 1012 | X64: =P64 -> 945 | Y64: =Q64 -> 922 | AA64: =SUM(Y64/U64)-1 -> -0.13751169
B65: Deferred income tax assets, net | C65: 1206 | D65: 1242 | E65: 1242 | F65: 1386 | H65: 1286 | I65: 1282 | J65: 1273 | K65: =E65 -> 1242 | L65: 1244 | M65: 1362 | N65: 1387 | O65: =F65 -> 1386 | P65: 1342 | Q65: 1354 | S65: =K65 -> 1242 | T65: =L65 -> 1244 | U65: =M65 -> 1362 | V65: =N65 -> 1387 | W65: =O65 -> 1386 | X65: =P65 -> 1342 | Y65: =Q65 -> 1354 | AA65: =SUM(Y65/U65)-1 -> -0.0058737151
B66: Other assets | C66: =3824+19+815 -> 4658 | D66: =3991+802 -> 4793 | E66: 3793 | F66: 2828 | H66: =3848+798 -> 4646 | I66: =4016+812 -> 4828 | J66: =3913+804 -> 4717 | K66: =E66 -> 3793 | L66: 3622 | M66: 3474 | N66: 3458 | O66: =F66 -> 2828 | P66: 2693 | Q66: 2490 | S66: =K66 -> 3793 | T66: =L66 -> 3622 | U66: =M66 -> 3474 | V66: =N66 -> 3458 | W66: =O66 -> 2828 | X66: =P66 -> 2693 | Y66: =Q66 -> 2490 | AA66: =SUM(Y66/U66)-1 -> -0.28324698
B67: Total Assets | C67: =SUM(C60:C66)+C57 -> 58620 | D67: =SUM(D60:D66)+D57 -> 58393 | E67: =SUM(E60:E66)+E57 -> 53543 | F67: =SUM(F60:F66)+F57 -> 46172 | H67: =SUM(H60:H66)+H57 -> 56561 | I67: =SUM(I60:I66)+I57 -> 55361 | J67: =SUM(J60:J66)+J57 -> 54640 | K67: =SUM(K60:K66)+K57 -> 53543 | L67: =SUM(L60:L66)+L57 -> 52027 | M67: =SUM(M60:M66)+M57 -> 45890 | N67: =SUM(N60:N66)+N57 -> 46250 | O67: =SUM(O60:O66)+O57 -> 46172 | ... Q67: =SUM(Q60:Q66)+Q57 -> 44926 | S67: =SUM(S60:S66)+S57 -> 53543 | T67: =SUM(T60:T66)+T57 -> 52027 | U67: =SUM(U60:U66)+U57 -> 45890 | V67: =SUM(V60:V66)+V57 -> 46250 | W67: =SUM(W60:W66)+W57 -> 46172 | X67: =SUM(X60:X66)+X57 -> 45396 | Y67: =SUM(Y60:Y66)+Y57 -> 44926 | AA67: =SUM(Y67/U67)-1 -> -0.021006755
B69: Current Liabilities
B70: Accounts payable | C70: 800 | D70: 1403 | E70: 1100 | F70: 953 | H70: 1235 | I70: 1210 | J70: 953 | K70: =E70 -> 1100 | L70: 787 | M70: 826 | N70: 826 | O70: =F70 -> 953 | P70: 735 | Q70: 822 | S70: =K70 -> 1100 | T70: =L70 -> 787 | U70: =M70 -> 826 | V70: =N70 -> 826 | W70: =O70 -> 953 | X70: =P70 -> 735 | Y70: =Q70 -> 822 | AA70: =SUM(Y70/U70)-1 -> -0.004842615
B71: Accrued expenses | C71: 2323 | D71: 2071 | E71: 2104 | F71: 2199 | H71: 1760 | I71: 1948 | J71: 2118 | K71: =E71 -> 2104 | L71: 1728 | M71: 1865 | N71: 1954 | O71: =F71 -> 2199 | P71: 1737 | Q71: 1727 | S71: =K71 -> 2104 | T71: =L71 -> 1728 | U71: =M71 -> 1865 | V71: =N71 -> 1954 | W71: =O71 -> 2199 | X71: =P71 -> 1737 | Y71: =Q71 -> 1727 | AA71: =SUM(Y71/U71)-1 -> -0.073994638
B72: Participants’ share and royalties payable | C72: 2159 | D72: 2416 | E72: 2702 | F72: 2574 | H72: 2421 | I72: 2470 | J72: 2731 | K72: =E72 -> 2702 | L72: 2625 | M72: 2462 | N72: 2485 | O72: =F72 -> 2574 | P72: 2585 | Q72: 2642 | S72: =K72 -> 2702 | T72: =L72 -> 2625 | U72: =M72 -> 2462 | V72: =N72 -> 2485 | W72: =O72 -> 2574 | X72: =P72 -> 2585 | Y72: =Q72 -> 2642 | AA72: =SUM(Y72/U72)-1 -> 0.073111292
B73: Accrued programming and production costs | C73: 1342 | D73: 2063 | E73: 1842 | F73: 1720 | H73: 2425 | I73: 2159 | J73: 1695 | K73: =E73 -> 1842 | L73: 1994 | M73: 1769 | N73: 1697 | O73: =F73 -> 1720 | P73: 1833 | Q73: 1381 | S73: =K73 -> 1842 | T73: =L73 -> 1994 | U73: =M73 -> 1769 | V73: =N73 -> 1697 | W73: =O73 -> 1720 | X73: =P73 -> 1833 | Y73: =Q73 -> 1381 | AA73: =SUM(Y73/U73)-1 -> -0.21933296
B74: Deferred revenues | C74: 1091 | D74: 973 | E74: 746 | F74: 825 | H74: 1092 | I74: 921 | J74: 848 | K74: =E74 -> 746 | L74: 671 | M74: 708 | N74: 824 | O74: =F74 -> 825 | P74: 765 | Q74: 753 | S74: =K74 -> 746 | T74: =L74 -> 671 | U74: =M74 -> 708 | V74: =N74 -> 824 | W74: =O74 -> 825 | X74: =P74 -> 765 | Y74: =Q74 -> 753 | AA74: =SUM(Y74/U74)-1 -> 0.063559322
B75: Debt | C75: 11 | D75: 239 | E75: 1 | F75: 0 | H75: 240 | I75: 180 | J75: 38 | K75: =E75 -> 1 | L75: 1 | M75: 126 | N75: 125 | O75: =F75 -> 0 | P75: 346 | Q75: 346 | S75: =K75 -> 1 | T75: =L75 -> 1 | U75: =M75 -> 126 | V75: =N75 -> 125 | W75: =O75 -> 0 | X75: =P75 -> 346 | Y75: =Q75 -> 346 | AA75: =SUM(Y75/U75)-1 -> 1.7460317
B76: Other current liabilities | C76: =1182+571 -> 1753 | D76: =1477+549 -> 2026 | E76: 1161 | F76: 1360 | H76: =1642+480 -> 2122 | I76: =1343+439 -> 1782 | J76: =1196+471 -> 1667 | K76: =E76 -> 1161 | L76: 1438 | M76: 1250 | N76: 1443 | O76: =F76 -> 1360 | P76: 1291 | Q76: 1059 | S76: =K76 -> 1161 | T76: =L76 -> 1438 | U76: =M76 -> 1250 | V76: =N76 -> 1443 | W76: =O76 -> 1360 | X76: =P76 -> 1291 | Y76: =Q76 -> 1059
B77: Total Current Liabilities | C77: =SUM(C70:C76) -> 9479 | D77: =SUM(D70:D76) -> 11191 | E77: =SUM(E70:E76) -> 9656 | F77: =SUM(F70:F76) -> 9631 | H77: =SUM(H70:H76) -> 11295 | I77: =SUM(I70:I76) -> 10670 | J77: =SUM(J70:J76) -> 10050 | K77: =SUM(K70:K76) -> 9656 | L77: =SUM(L70:L76) -> 9244 | M77: =SUM(M70:M76) -> 9006 | N77: =SUM(N70:N76) -> 9354 | O77: =SUM(O70:O76) -> 9631 | ... Q77: =SUM(Q70:Q76) -> 8730 | S77: =SUM(S70:S76) -> 9656 | T77: =SUM(T70:T76) -> 9244 | U77: =SUM(U70:U76) -> 9006 | V77: =SUM(V70:V76) -> 9354 | W77: =SUM(W70:W76) -> 9631 | X77: =SUM(X70:X76) -> 9292 | Y77: =SUM(Y70:Y76) -> 8730 | AA77: =SUM(Y77/U77)-1 -> -0.030646236
B79: Non-Current Liabilities
B80: Long-term debt | C80: 17698 | D80: 15607 | E80: 14601 | F80: 14501 | H80: 15613 | I80: 15620 | J80: 15627 | K80: =E80 -> 14601 | L80: 14607 | M80: 14488 | N80: 14495 | O80: =F80 -> 14501 | P80: 14161 | Q80: 14168 | S80: =K80 -> 14601 | T80: =L80 -> 14607 | U80: =M80 -> 14488 | V80: =N80 -> 14495 | W80: =O80 -> 14501 | X80: =P80 -> 14161 | Y80: =Q80 -> 14168 | AA80: =SUM(Y80/U80)-1 -> -0.022087245
B81: Participants’ share and royalties payable | C81: 1244 | D81: 1744 | E81: 1394 | F81: 1310 | H81: 1665 | I81: 1616 | J81: 1453 | K81: =E81 -> 1394 | L81: 1337 | M81: 1326 | N81: 1254 | O81: =F81 -> 1310 | P81: 1315 | Q81: 1247 | S81: =K81 -> 1394 | T81: =L81 -> 1337 | U81: =M81 -> 1326 | V81: =N81 -> 1254 | W81: =O81 -> 1310 | X81: =P81 -> 1315 | Y81: =Q81 -> 1247 | AA81: =SUM(Y81/U81)-1 -> -0.059577677
B82: Pension and postretirement benefit obligations | C82: 1946 | D82: 1458 | E82: 1337 | F82: 1226 | H82: 1454 | I82: 1463 | J82: 1436 | K82: =E82 -> 1337 | L82: 1332 | M82: 1329 | N82: 1322 | O82: =F82 -> 1226 | P82: 1108 | Q82: 1097 | S82: =K82 -> 1337 | T82: =L82 -> 1332 | U82: =M82 -> 1329 | V82: =N82 -> 1322 | W82: =O82 -> 1226 | X82: =P82 -> 1108 | Y82: =Q82 -> 1097 | AA82: =SUM(Y82/U82)-1 -> -0.17456734
B83: Deferred income tax liabilities, net | C83: 1063 | D83: 1077 | E83: 503 | F83: 34 | H83: 668 | I83: 516 | J83: 500 | K83: =E83 -> 503 | L83: 273 | M83: 35 | N83: 35 | O83: =F83 -> 34 | P83: 40 | Q83: 34 | S83: =K83 -> 503 | T83: =L83 -> 273 | U83: =M83 -> 35 | V83: =N83 -> 35 | W83: =O83 -> 34 | X83: =P83 -> 40 | Y83: =Q83 -> 34 | AA83: =SUM(Y83/U83)-1 -> -0.028571429
B84: Operating lease liabilities | C84: 1598 | D84: 1428 | E84: 1256 | F84: 1048 | H84: 1398 | I84: 1341 | J84: 1307 | K84: =E84 -> 1256 | L84: 1199 | M84: 1127 | N84: 1076 | O84: =F84 -> 1048 | P84: 1020 | Q84: 993 | S84: =K84 -> 1256 | T84: =L84 -> 1199 | U84: =M84 -> 1127 | V84: =N84 -> 1076 | W84: =O84 -> 1048 | X84: =P84 -> 1020 | Y84: =Q84 -> 993 | AA84: =SUM(Y84/U84)-1 -> -0.11889973
B85: Program rights obligations | C85: 404 | D85: 367 | E85: 204 | F85: 260 | H85: 326 | I85: 254 | J85: 209 | K85: =E85 -> 204 | L85: 204 | M85: 229 | N85: 208 | O85: =F85 -> 260 | P85: 221 | Q85: 183 | S85: =K85 -> 204 | T85: =L85 -> 204 | U85: =M85 -> 229 | V85: =N85 -> 208 | W85: =O85 -> 260 | X85: =P85 -> 221 | Y85: =Q85 -> 183 | AA85: =SUM(Y85/U85)-1 -> -0.20087336
B86: Other liabilities | C86: =1898+213+107 -> 2218 | D86: =1715+200 -> 1915 | E86: 1542 | F86: 1380 | H86: =1603+196 -> 1799 | I86: =1520+204 -> 1724 | J86: =1476+204 -> 1680 | K86: =E86 -> 1542 | L86: 1494 | M86: 1404 | N86: 1431 | O86: =F86 -> 1380 | P86: 1311 | Q86: 1363 | S86: =K86 -> 1542 | T86: =L86 -> 1494 | U86: =M86 -> 1404 | V86: =N86 -> 1431 | W86: =O86 -> 1380 | X86: =P86 -> 1311 | Y86: =Q86 -> 1363 | AA86: =SUM(Y86/U86)-1 -> -0.029202279
B87: Total Liabilities | C87: =SUM(C80:C86)+C77 -> 35650 | D87: =SUM(D80:D86)+D77 -> 34787 | E87: =SUM(E80:E86)+E77 -> 30493 | F87: =SUM(F80:F86)+F77 -> 29390 | H87: =SUM(H80:H86)+H77 -> 34218 | I87: =SUM(I80:I86)+I77 -> 33204 | J87: =SUM(J80:J86)+J77 -> 32262 | K87: =SUM(K80:K86)+K77 -> 30493 | L87: =SUM(L80:L86)+L77 -> 29690 | M87: =SUM(M80:M86)+M77 -> 28944 | N87: =SUM(N80:N86)+N77 -> 29175 | O87: =SUM(O80:O86)+O77 -> 29390 | ... Q87: =SUM(Q80:Q86)+Q77 -> 27815 | S87: =SUM(S80:S86)+S77 -> 30493 | T87: =SUM(T80:T86)+T77 -> 29690 | U87: =SUM(U80:U86)+U77 -> 28944 | V87: =SUM(V80:V86)+V77 -> 29175 | W87: =SUM(W80:W86)+W77 -> 29390 | X87: =SUM(X80:X86)+X77 -> 28468 | Y87: =SUM(Y80:Y86)+Y77 -> 27815 | AA87: =SUM(Y87/U87)-1 -> -0.039006357
B89: Common Stock | C89: 1 | D89: 1 | E89: 1 | F89: 1 | H89: 1 | I89: 1 | J89: 1 | K89: =E89 -> 1 | L89: 1 | M89: 1 | N89: 1 | O89: =F89 -> 1 | P89: 1 | Q89: 1 | S89: =K89 -> 1 | T89: =L89 -> 1 | U89: =M89 -> 1 | V89: =N89 -> 1 | W89: =O89 -> 1 | X89: =P89 -> 1 | Y89: =Q89 -> 1 | AA89: =SUM(Y89/U89)-1 -> 0
B90: Additional paid-in capital | C90: 32918 | D90: 33063 | E90: 33210 | F90: 33394 | H90: 33087 | I90: 33135 | J90: 33176 | K90: =E90 -> 33210 | L90: 33240 | M90: 33299 | N90: 33364 | O90: =F90 -> 33394 | P90: 33412 | Q90: 33455 | S90: =K90 -> 33210 | T90: =L90 -> 33240 | U90: =M90 -> 33299 | V90: =N90 -> 33364 | W90: =O90 -> 33394 | X90: =P90 -> 33412 | Y90: =Q90 -> 33455 | AA90: =SUM(Y90/U90)-1 -> 0.0046848254
B91: Treasury stock | C91: -22958 | D91: -22958 | E91: -22958 | F91: -22958 | H91: -22958 | I91: -22958 | J91: -22958 | K91: =E91 -> -22958 | L91: -22958 | M91: -22958 | N91: -22958 | O91: =F91 -> -22958 | P91: -22958 | Q91: -22958 | S91: =K91 -> -22958 | T91: =L91 -> -22958 | U91: =M91 -> -22958 | V91: =N91 -> -22958 | W91: =O91 -> -22958 | X91: =P91 -> -22958 | Y91: =Q91 -> -22958 | AA91: =SUM(Y91/U91)-1 -> 0
B92: Retained earnings | C92: 14343 | D92: 14737 | E92: 13829 | F92: 7487 | H92: 13463 | I92: 13116 | J92: 13363 | K92: =E92 -> 13829 | L92: 13226 | M92: 7779 | N92: 7745 | O92: =F92 -> 7487 | P92: 7604 | Q92: 7626 | S92: =K92 -> 13829 | T92: =L92 -> 13226 | U92: =M92 -> 7779 | V92: =N92 -> 7745 | W92: =O92 -> 7487 | X92: =P92 -> 7604 | Y92: =Q92 -> 7626 | AA92: =SUM(Y92/U92)-1 -> -0.019668338
B93: Accumulated other comprehensive loss | C93: -1902 | D93: -1807 | E93: -1556 | F93: -1604 | H93: -1742 | I93: -1639 | J93: -1718 | K93: =E93 -> -1556 | L93: -1615 | M93: -1624 | N93: -1524 | O93: =F93 -> -1604 | P93: -1521 | Q93: -1419 | S93: =K93 -> -1556 | T93: =L93 -> -1615 | U93: =M93 -> -1624 | V93: =N93 -> -1524 | W93: =O93 -> -1604 | X93: =P93 -> -1521 | Y93: =Q93 -> -1419 | AA93: =SUM(Y93/U93)-1 -> -0.12623153
B94: Total Paramount stockholders’ equity | C94: =SUM(C89:C93) -> 22402 | D94: =SUM(D89:D93) -> 23036 | E94: =SUM(E89:E93) -> 22526 | F94: =SUM(F89:F93) -> 16320 | H94: =SUM(H89:H93) -> 21851 | I94: =SUM(I89:I93) -> 21655 | J94: =SUM(J89:J93) -> 21864 | K94: =SUM(K89:K93) -> 22526 | L94: =SUM(L89:L93) -> 21894 | M94: =SUM(M89:M93) -> 16497 | N94: =SUM(N89:N93) -> 16628 | O94: =SUM(O89:O93) -> 16320 | ... Q94: =SUM(Q89:Q93) -> 16705 | S94: =SUM(S89:S93) -> 22526 | T94: =SUM(T89:T93) -> 21894 | U94: =SUM(U89:U93) -> 16497 | V94: =SUM(V89:V93) -> 16628 | W94: =SUM(W89:W93) -> 16320 | X94: =SUM(X89:X93) -> 16538 | Y94: =SUM(Y89:Y93) -> 16705 | AA94: =SUM(Y94/U94)-1 -> 0.012608353
B96: Noncontrolling interests | C96: =568 -> 568 | D96: 570 | E96: 524 | F96: 462 | H96: 492 | I96: 502 | J96: 514 | K96: =E96 -> 524 | L96: 443 | M96: 449 | N96: 447 | O96: =F96 -> 462 | P96: 390 | Q96: 406 | S96: =K96 -> 524 | T96: =L96 -> 443 | U96: =M96 -> 449 | V96: =N96 -> 447 | W96: =O96 -> 462 | X96: =P96 -> 390 | Y96: =Q96 -> 406
B97: Total Equity | C97: =SUM(C94+C96) -> 22970 | D97: =SUM(D94+D96) -> 23606 | E97: =SUM(E94+E96) -> 23050 | F97: =SUM(F94+F96) -> 16782 | H97: =SUM(H94+H96) -> 22343 | I97: =SUM(I94+I96) -> 22157 | J97: =SUM(J94+J96) -> 22378 | K97: =SUM(K94+K96) -> 23050 | L97: =SUM(L94+L96) -> 22337 | M97: =SUM(M94+M96) -> 16946 | N97: =SUM(N94+N96) -> 17075 | O97: =SUM(O94+O96) -> 16782 | ... Q97: =SUM(Q94+Q96) -> 17111 | S97: =SUM(S94+S96) -> 23050 | T97: =SUM(T94+T96) -> 22337 | U97: =SUM(U94+U96) -> 16946 | V97: =SUM(V94+V96) -> 17075 | W97: =SUM(W94+W96) -> 16782 | X97: =SUM(X94+X96) -> 16928 | Y97: =SUM(Y94+Y96) -> 17111
B98: Total liabilities and stockholders' equity | C98: =SUM(C97+C87) -> 58620 | D98: =SUM(D97+D87) -> 58393 | E98: =SUM(E97+E87) -> 53543 | F98: =SUM(F97+F87) -> 46172 | H98: =SUM(H97+H87) -> 56561 | I98: =SUM(I97+I87) -> 55361 | J98: =SUM(J97+J87) -> 54640 | K98: =SUM(K97+K87) -> 53543 | L98: =SUM(L97+L87) -> 52027 | M98: =SUM(M97+M87) -> 45890 | N98: =SUM(N97+N87) -> 46250 | O98: =SUM(O97+O87) -> 46172 | ... Q98: =SUM(Q97+Q87) -> 44926 | S98: =SUM(S97+S87) -> 53543 | T98: =SUM(T97+T87) -> 52027 | U98: =SUM(U97+U87) -> 45890 | V98: =SUM(V97+V87) -> 46250 | W98: =SUM(W97+W87) -> 46172 | X98: =SUM(X97+X87) -> 45396 | Y98: =SUM(Y97+Y87) -> 44926 | AA98: =SUM(Y98/U98)-1 -> -0.021006755
B100: Balance Check | C100: =C98-C67 -> 0 | D100: =D98-D67 -> 0 | E100: =E98-E67 -> 0 | F100: =F98-F67 -> 0 | H100: =H98-H67 -> 0 | I100: =I98-I67 -> 0 | J100: =J98-J67 -> 0 | K100: =K98-K67 -> 0 | L100: =L98-L67 -> 0 | M100: =M98-M67 -> 0 | N100: =N98-N67 -> 0 | O100: =O98-O67 -> 0 | ... Q100: =Q98-Q67 -> 0 | S100: =S98-S67 -> 0 | T100: =T98-T67 -> 0 | U100: =U98-U67 -> 0 | V100: =V98-V67 -> 0 | W100: =W98-W67 -> 0 | X100: =X98-X67 -> 0 | Y100: =Y98-Y67 -> 0
A103: X | B103: Cash-Flows Statement | C103: FYE | N103: Quarterly | U103: LTM | AA103: Variance
B104: =B7 -> Fiscal Period | C104: =C7 -> 2021 | D104: =D7 -> 2022 | E104: =E7 -> 2023 | F104: =F7 -> 2024 | H104: =H7 -> 1Q23 | I104: =I7 -> 2Q23 | J104: =J7 -> 3Q23 | K104: =K7 -> 4Q23 | L104: =L7 -> 1Q24 | M104: =M7 -> 2Q24 | N104: =N7 -> 3Q24 | O104: =O7 -> 4Q24 | ... Q104: =Q7 -> 2Q25 | S104: =S7 -> 4Q23 | T104: =T7 -> 1Q24 | U104: =U7 -> 2Q24 | V104: =V7 -> 3Q24 | W104: =W7 -> 4Q24 | X104: =X7 -> 1Q25 | Y104: =Y7 -> 2Q25
B105: =B8 -> Fiscal Period End Date | C105: =C8 -> 44561 | D105: =D8 -> 44926 | E105: =E8 -> 45291 | F105: =F8 -> 45657 | H105: =H8 -> 45016 | I105: =I8 -> 45107 | J105: =J8 -> 45199 | K105: =K8 -> 44926 | L105: =L8 -> 45382 | M105: =M8 -> 45473 | N105: =N8 -> 45565 | O105: =O8 -> 45291 | ... Q105: =Q8 -> 45838 | S105: =S8 -> 44926 | T105: =T8 -> 45382 | U105: =U8 -> 45473 | V105: =V8 -> 45565 | W105: =W8 -> 45291 | X105: =X8 -> 45747 | Y105: =Y8 -> 45838
B107: Cash-Flows From Operating Activities
B108: Net earnings (loss) from continuing operations | C108: =C33 -> 4469 | D108: =D33 -> 835 | E108: =E33 -> -1252 | F108: =F33 -> -6163 | H108: =H33 -> -1157 | I108: =I33 -> -363 | J108: =J33 -> 261 | K108: =K33 -> 7 | L108: =L33 -> -553 | M108: =M33 -> -5404 | N108: =N33 -> 16 | O108: =O33 -> -222 | ... Q108: =Q33 -> 61 | S108: =SUM(I108:L108) -> -648 | T108: =SUM(J108:M108) -> -5689 | U108: =SUM(K108:N108) -> -5934 | V108: =SUM(L108:O108) -> -6163 | W108: =SUM(M108:P108) -> -5449 | X108: =SUM(N108:Q108) -> 16 | Y108: =SUM(O108:Q108) -> 0 | AA108: =SUM(Y108/U108)-1 -> -1
B110: Adjustments to reconcile net income:
B111: Programming charges | C111: 0 | D111: 0 | E111: 2371 | F111: 1118 | H111: 1674 | I111: =2371-H111 -> 697 | J111: =2371-I111-H111 -> 0 | K111: =SUM(E111-SUM(H111:J111)) -> 0 | L111: 1118 | M111: =1118-L111 -> 0 | N111: =1118-M111-L111 -> 0 | O111: =SUM(F111-SUM(L111:N111)) -> 0 | P111: 0 | Q111: 0 | S111: =SUM(H111:K111) -> 2371 | T111: =SUM(I111:L111) -> 1815 | U111: =SUM(J111:M111) -> 1118 | V111: =SUM(K111:N111) -> 1118 | W111: =SUM(L111:O111) -> 1118 | X111: =SUM(M111:P111) -> 0 | Y111: =SUM(N111:Q111) -> 0 | AA111: =SUM(Y111/U111)-1 -> -1
B112: Depreciation and amortization | C112: 390 | D112: 378 | E112: 418 | F112: 392 | H112: 100 | I112: =205-H112 -> 105 | J112: =310-I112-H112 -> 105 | K112: =SUM(E112-SUM(H112:J112)) -> 108 | L112: 100 | M112: =201-L112 -> 101 | N112: =297-M112-L112 -> 96 | O112: =SUM(F112-SUM(L112:N112)) -> 95 | P112: 88 | Q112: =175-P112 -> 87 | S112: =SUM(H112:K112) -> 418 | T112: =SUM(I112:L112) -> 418 | U112: =SUM(J112:M112) -> 414 | V112: =SUM(K112:N112) -> 405 | W112: =SUM(L112:O112) -> 392 | X112: =SUM(M112:P112) -> 380 | Y112: =SUM(N112:Q112) -> 366 | AA112: =SUM(Y112/U112)-1 -> -0.11594203
B113: Impairment charges | C113: 0 | D113: 27 | E113: 83 | F113: 6130 | H113: 0 | I113: 0 | J113: 0 | K113: =SUM(E113-SUM(H113:J113)) -> 83 | L113: 0 | M113: =5996-L113 -> 5996 | N113: =6100-M113-L113 -> 104 | O113: =SUM(F113-SUM(L113:N113)) -> 30 | P113: 0 | Q113: =157-P113 -> 157 | S113: =SUM(H113:K113) -> 83 | T113: =SUM(I113:L113) -> 83 | U113: =SUM(J113:M113) -> 6079 | V113: =SUM(K113:N113) -> 6183 | W113: =SUM(L113:O113) -> 6130 | X113: =SUM(M113:P113) -> 6130 | Y113: =SUM(N113:Q113) -> 291 | AA113: =SUM(Y113/U113)-1 -> -0.95213028
B114: Amortization of content costs and participation and residuals expense | C114: 13649 | D114: 14951 | E114: 14713 | F114: 13888 | H114: 0 | I114: 0 | J114: 0 | K114: =SUM(E114-SUM(H114:J114)) -> 14713 | L114: 0 | M114: 0 | N114: 0 | O114: =SUM(F114-SUM(L114:N114)) -> 13888 | P114: 0 | Q114: 0 | S114: =SUM(H114:K114) -> 14713 | T114: =SUM(I114:L114) -> 14713 | U114: =SUM(J114:M114) -> 14713 | V114: =SUM(K114:N114) -> 14713 | W114: =SUM(L114:O114) -> 13888 | X114: =SUM(M114:P114) -> 13888 | Y114: =SUM(N114:Q114) -> 13888 | AA114: =SUM(Y114/U114)-1 -> -0.056072861
B115: Deferred tax benefit | C115: 90 | D115: -106 | E115: -650 | F115: -630 | H115: -436 | I115: =-586-H115 -> -150 | J115: =-592-I115-H115 -> -6 | K115: =SUM(E115-SUM(H115:J115)) -> -58 | L115: -231 | M115: =-593-L115 -> -362 | N115: =-622-M115-L115 -> -29 | O115: =SUM(F115-SUM(L115:N115)) -> -8 | P115: 45 | Q115: =21-P115 -> -24 | S115: =SUM(H115:K115) -> -650 | T115: =SUM(I115:L115) -> -445 | U115: =SUM(J115:M115) -> -657 | V115: =SUM(K115:N115) -> -680 | W115: =SUM(L115:O115) -> -630 | X115: =SUM(M115:P115) -> -354 | Y115: =SUM(N115:Q115) -> -16 | AA115: =SUM(Y115/U115)-1 -> -0.97564688
B116: Stock-based compensation | C116: 192 | D116: 172 | E116: 177 | F116: 245 | H116: 39 | I116: =88-H116 -> 49 | J116: =131-I116-H116 -> 43 | K116: =SUM(E116-SUM(H116:J116)) -> 46 | L116: 47 | M116: =109-L116 -> 62 | N116: =175-M116-L116 -> 66 | O116: =SUM(F116-SUM(L116:N116)) -> 70 | P116: 44 | Q116: =87-P116 -> 43 | S116: =SUM(H116:K116) -> 177 | T116: =SUM(I116:L116) -> 185 | U116: =SUM(J116:M116) -> 198 | V116: =SUM(K116:N116) -> 221 | W116: =SUM(L116:O116) -> 245 | X116: =SUM(M116:P116) -> 242 | Y116: =SUM(N116:Q116) -> 223 | AA116: =SUM(Y116/U116)-1 -> 0.12626263
B117: Gains on dispositions | C117: -2343 | D117: -56 | E117: 0 | F117: 0 | H117: 0 | I117: 0 | J117: 0 | K117: =SUM(E117-SUM(H117:J117)) -> 0 | L117: 0 | M117: 0 | N117: 0 | O117: =SUM(F117-SUM(L117:N117)) -> 0 | P117: -35 | Q117: =-35-P117 -> 0 | S117: =SUM(H117:K117) -> 0 | T117: =SUM(I117:L117) -> 0 | U117: =SUM(J117:M117) -> 0 | V117: =SUM(K117:N117) -> 0 | W117: =SUM(L117:O117) -> 0 | X117: =SUM(M117:P117) -> -35 | Y117: =SUM(N117:Q117) -> -35 | AA117: =SUM(Y117/U117)-1 -> #DIV/0!
B118: (Gain) loss from investments | C118: -47 | D118: 9 | E118: -168 | F118: 17 | H118: 0 | I118: =-168-H118 -> -168 | J118: =-168-I118-H118 -> 0 | K118: =SUM(E118-SUM(H118:J118)) -> 0 | L118: 4 | M118: =4-L118 -> 0 | N118: =4-M118-L118 -> 0 | O118: =SUM(F118-SUM(L118:N118)) -> 13 | P118: 0 | Q118: 0 | S118: =SUM(H118:K118) -> -168 | T118: =SUM(I118:L118) -> -164 | U118: =SUM(J118:M118) -> 4 | V118: =SUM(K118:N118) -> 4 | W118: =SUM(L118:O118) -> 17 | X118: =SUM(M118:P118) -> 13 | Y118: =SUM(N118:Q118) -> 13 | AA118: =SUM(Y118/U118)-1 -> 2.25
B119: (Gain) loss on extinguishment of debt | C119: 128 | D119: 120 | E119: -29 | F119: 0 | H119: 0 | I119: 0 | J119: 0 | K119: =SUM(E119-SUM(H119:J119)) -> -29 | L119: 0 | M119: 0 | N119: 0 | O119: =SUM(F119-SUM(L119:N119)) -> 0 | P119: 0 | Q119: 0 | S119: =SUM(H119:K119) -> -29 | T119: =SUM(I119:L119) -> -29 | U119: =SUM(J119:M119) -> -29 | V119: =SUM(K119:N119) -> -29 | W119: =SUM(L119:O119) -> 0 | X119: =SUM(M119:P119) -> 0 | Y119: =SUM(N119:Q119) -> 0 | AA119: =SUM(Y119/U119)-1 -> -1
B120: Equity in loss of investee companies, net of tax and distributions | C120: 96 | D120: 207 | E120: 363 | F120: 304 | H120: 75 | I120: =184-H120 -> 109 | J120: =259-I120-H120 -> 75 | K120: =SUM(E120-SUM(H120:J120)) -> 104 | L120: 90 | M120: =168-L120 -> 78 | N120: =228-M120-L120 -> 60 | O120: =SUM(F120-SUM(L120:N120)) -> 76 | P120: 73 | Q120: =141-P120 -> 68 | S120: =SUM(H120:K120) -> 363 | T120: =SUM(I120:L120) -> 378 | U120: =SUM(J120:M120) -> 347 | V120: =SUM(K120:N120) -> 332 | W120: =SUM(L120:O120) -> 304 | X120: =SUM(M120:P120) -> 287 | Y120: =SUM(N120:Q120) -> 277 | AA120: =SUM(Y120/U120)-1 -> -0.20172911
B121: Other, net | C121: -51 | D121: -159 | E121: -186 | F121: 227 | H121: 0 | I121: 0 | J121: 0 | K121: =SUM(E121-SUM(H121:J121)) -> -186 | L121: 0 | M121: 0 | N121: 0 | O121: =SUM(F121-SUM(L121:N121)) -> 227 | P121: 0 | Q121: 0 | S121: =SUM(H121:K121) -> -186 | T121: =SUM(I121:L121) -> -186 | U121: =SUM(J121:M121) -> -186 | V121: =SUM(K121:N121) -> -186 | W121: =SUM(L121:O121) -> 227 | X121: =SUM(M121:P121) -> 227 | Y121: =SUM(N121:Q121) -> 227 | AA121: =SUM(Y121/U121)-1 -> -2.2204301
B122: Net cash flow provided by operating activities from discontinued operations | C122: 118 | D122: 361 | E122: 91 | F122: 0 | H122: 105 | I122: =223-H122 -> 118 | J122: =205-I122-H122 -> -18 | K122: =SUM(E122-SUM(H122:J122)) -> -114 | L122: 0 | M122: 0 | N122: 0 | O122: =SUM(F122-SUM(L122:N122)) -> 0 | P122: 0 | Q122: 0 | S122: =SUM(H122:K122) -> 91 | T122: =SUM(I122:L122) -> -14 | U122: =SUM(J122:M122) -> -132 | V122: =SUM(K122:N122) -> -114 | W122: =SUM(L122:O122) -> 0 | X122: =SUM(M122:P122) -> 0 | Y122: =SUM(N122:Q122) -> 0
...

Sheet Revenue Drivers
B2: ='Historical Financials'!B2 -> Paramount Global (NASDAQ: PARA) | C2: FYE | N2: Quarterly | U2: LTM
B3: Segment Anaysis | C3: ='Historical Financials'!C7 -> 2021 | D3: ='Historical Financials'!D7 -> 2022 | E3: ='Historical Financials'!E7 -> 2023 | F3: ='Historical Financials'!F7 -> 2024 | H3: ='Historical Financials'!H7 -> 1Q23 | I3: ='Historical Financials'!I7 -> 2Q23 | J3: ='Historical Financials'!J7 -> 3Q23 | K3: ='Historical Financials'!K7 -> 4Q23 | L3: ='Historical Financials'!L7 -> 1Q24 | M3: ='Historical Financials'!M7 -> 2Q24 | N3: ='Historical Financials'!N7 -> 3Q24 | O3: ='Historical Financials'!O7 -> 4Q24 | ... Q3: ='Historical Financials'!Q7 -> 2Q25 | S3: =K3 -> 4Q23 | T3: =L3 -> 1Q24 | U3: =M3 -> 2Q24 | V3: =N3 -> 3Q24 | W3: =O3 -> 4Q24 | X3: =P3 -> 1Q25 | Y3: =Q3 -> 2Q25
B4: ($ In Millions) | C4: ='Historical Financials'!C8 -> 44561 | D4: ='Historical Financials'!D8 -> 44926 | E4: ='Historical Financials'!E8 -> 45291 | F4: ='Historical Financials'!F8 -> 45657 | H4: ='Historical Financials'!H8 -> 45016 | I4: ='Historical Financials'!I8 -> 45107 | J4: ='Historical Financials'!J8 -> 45199 | K4: ='Historical Financials'!K8 -> 44926 | L4: ='Historical Financials'!L8 -> 45382 | M4: ='Historical Financials'!M8 -> 45473 | N4: ='Historical Financials'!N8 -> 45565 | O4: ='Historical Financials'!O8 -> 45291 | ... Q4: ='Historical Financials'!Q8 -> 45838 | S4: =K4 -> 44926 | T4: =L4 -> 45382 | U4: =M4 -> 45473 | V4: =N4 -> 45565 | W4: =O4 -> 45291 | X4: =P4 -> 45747 | Y4: =Q4 -> 45838
A6: X | B6: Revenue by reportable segment
A8: X | B8: Revenue by Type
B9: Advertising | C9: 11412 | D9: 10890 | E9: 9989 | F9: 10295 | H9: 2651 | I9: 2395 | J9: 2133 | K9: =SUM(E9-SUM(H9:J9)) -> 2810 | L9: 3096 | M9: 2251 | N9: 2174 | O9: =SUM(F9-SUM(L9:N9)) -> 2774 | P9: 2513 | Q9: 2152 | S9: =SUM(H9:K9) -> 9989 | T9: =SUM(I9:L9) -> 10434 | U9: =SUM(J9:M9) -> 10290 | V9: =SUM(K9:N9) -> 10331 | W9: =SUM(L9:O9) -> 10295 | X9: =SUM(M9:P9) -> 9712 | Y9: =SUM(N9:Q9) -> 9613
B10: Affiliate and subscription | C10: 10442 | D10: 11551 | E10: 13018 | F10: 13153 | H10: 3179 | I10: 3235 | J10: 3262 | K10: =SUM(E10-SUM(H10:J10)) -> 3342 | L10: 3357 | M10: 3275 | N10: 3215 | O10: =SUM(F10-SUM(L10:N10)) -> 3306 | P10: 3397 | Q10: 3445 | S10: =SUM(H10:K10) -> 13018 | T10: =SUM(I10:L10) -> 13196 | U10: =SUM(J10:M10) -> 13236 | V10: =SUM(K10:N10) -> 13189 | W10: =SUM(L10:O10) -> 13153 | X10: =SUM(M10:P10) -> 13193 | Y10: =SUM(N10:Q10) -> 13363
B11: Theatrical | C11: 241 | D11: 1223 | E11: 813 | F11: 813 | H11: 127 | I11: 231 | J11: 377 | K11: =SUM(E11-SUM(H11:J11)) -> 78 | L11: 153 | M11: 138 | N11: 108 | O11: =SUM(F11-SUM(L11:N11)) -> 414 | P11: 148 | Q11: 254 | S11: =SUM(H11:K11) -> 813 | T11: =SUM(I11:L11) -> 839 | U11: =SUM(J11:M11) -> 746 | V11: =SUM(K11:N11) -> 477 | W11: =SUM(L11:O11) -> 813 | X11: =SUM(M11:P11) -> 808 | Y11: =SUM(N11:Q11) -> 924
B12: Licensing and other | C12: 6491 | D12: 6490 | E12: 5832 | F12: 4952 | H12: 1308 | I12: 1755 | J12: 1361 | K12: =SUM(E12-SUM(H12:J12)) -> 1408 | L12: 1079 | M12: 1149 | N12: 1234 | O12: =SUM(F12-SUM(L12:N12)) -> 1490 | P12: 1134 | Q12: 998 | S12: =SUM(H12:K12) -> 5832 | T12: =SUM(I12:L12) -> 5603 | U12: =SUM(J12:M12) -> 4997 | V12: =SUM(K12:N12) -> 4870 | W12: =SUM(L12:O12) -> 4952 | X12: =SUM(M12:P12) -> 5007 | Y12: =SUM(N12:Q12) -> 4856
B13: Total Net Revenue | C13: =SUM(C9:C12) -> 28586 | D13: =SUM(D9:D12) -> 30154 | E13: =SUM(E9:E12) -> 29652 | F13: =SUM(F9:F12) -> 29213 | H13: =SUM(H9:H12) -> 7265 | I13: =SUM(I9:I12) -> 7616 | J13: =SUM(J9:J12) -> 7133 | K13: =SUM(K9:K12) -> 7638 | L13: =SUM(L9:L12) -> 7685 | M13: =SUM(M9:M12) -> 6813 | N13: =SUM(N9:N12) -> 6731 | O13: =SUM(O9:O12) -> 7984 | ... Q13: =SUM(Q9:Q12) -> 6849 | S13: =SUM(S9:S12) -> 29652 | T13: =SUM(T9:T12) -> 30072 | U13: =SUM(U9:U12) -> 29269 | V13: =SUM(V9:V12) -> 28867 | W13: =SUM(W9:W12) -> 29213 | X13: =SUM(X9:X12) -> 28720 | Y13: =SUM(Y9:Y12) -> 28756
B14: Variance Check | C14: =+C13-'Historical Financials'!C11 -> 0 | D14: =+D13-'Historical Financials'!D11 -> 0 | E14: =+E13-'Historical Financials'!E11 -> 0 | F14: =+F13-'Historical Financials'!F11 -> 0 | H14: =+H13-'Historical Financials'!H11 -> 0 | I14: =+I13-'Historical Financials'!I11 -> 0 | J14: =+J13-'Historical Financials'!J11 -> 0 | K14: =+K13-'Historical Financials'!K11 -> 0 | L14: =+L13-'Historical Financials'!L11 -> 0 | M14: =+M13-'Historical Financials'!M11 -> 0 | N14: =+N13-'Historical Financials'!N11 -> 0 | O14: =+O13-'Historical Financials'!O11 -> 0 | ... Q14: =+Q13-'Historical Financials'!Q11 -> 0 | S14: =+S13-'Historical Financials'!S11 -> 0 | T14: =+T13-'Historical Financials'!T11 -> 0 | U14: =+U13-'Historical Financials'!U11 -> 0 | V14: =+V13-'Historical Financials'!V11 -> 0 | W14: =+W13-'Historical Financials'!W11 -> 0 | X14: =+X13-'Historical Financials'!X11 -> 0 | Y14: =+Y13-'Historical Financials'!Y11 -> 0
B16: =B9&"(%)" -> Advertising(%) | C16: =SUM(C9/C$13) -> 0.3992164 | D16: =SUM(D9/D$13) -> 0.36114612 | E16: =SUM(E9/E$13) -> 0.33687441 | F16: =SUM(F9/F$13) -> 0.3524116 | H16: =SUM(H9/H$13) -> 0.36490021 | I16: =SUM(I9/I$13) -> 0.31446954 | J16: =SUM(J9/J$13) -> 0.29903267 | K16: =SUM(K9/K$13) -> 0.36789736 | L16: =SUM(L9/L$13) -> 0.40286272 | M16: =SUM(M9/M$13) -> 0.33039777 | N16: =SUM(N9/N$13) -> 0.32298321 | O16: =SUM(O9/O$13) -> 0.34744489 | ... Q16: =SUM(Q9/Q$13) -> 0.31420645 | S16: =SUM(S9/S$13) -> 0.33687441 | T16: =SUM(T9/T$13) -> 0.34696728 | U16: =SUM(U9/U$13) -> 0.3515665 | V16: =SUM(V9/V$13) -> 0.3578827 | W16: =SUM(W9/W$13) -> 0.3524116 | X16: =SUM(X9/X$13) -> 0.33816156 | Y16: =SUM(Y9/Y$13) -> 0.33429545
B17: =B10&"(%)" -> Affiliate and subscription(%) | C17: =SUM(C10/C$13) -> 0.36528371 | D17: =SUM(D10/D$13) -> 0.38306692 | E17: =SUM(E10/E$13) -> 0.43902604 | F17: =SUM(F10/F$13) -> 0.45024475 | H17: =SUM(H10/H$13) -> 0.43757743 | I17: =SUM(I10/I$13) -> 0.42476366 | J17: =SUM(J10/J$13) -> 0.45731109 | K17: =SUM(K10/K$13) -> 0.4375491 | L17: =SUM(L10/L$13) -> 0.43682498 | M17: =SUM(M10/M$13) -> 0.48069866 | N17: =SUM(N10/N$13) -> 0.47764077 | O17: =SUM(O10/O$13) -> 0.41407816 | ... Q17: =SUM(Q10/Q$13) -> 0.50299314 | S17: =SUM(S10/S$13) -> 0.43902604 | T17: =SUM(T10/T$13) -> 0.43881351 | U17: =SUM(U10/U$13) -> 0.45221907 | V17: =SUM(V10/V$13) -> 0.45688849 | W17: =SUM(W10/W$13) -> 0.45024475 | X17: =SUM(X10/X$13) -> 0.4593663 | Y17: =SUM(Y10/Y$13) -> 0.46470302
B18: =B11&"(%)" -> Theatrical(%) | C18: =SUM(C11/C$13) -> 0.0084307003 | D18: =SUM(D11/D$13) -> 0.040558467 | E18: =SUM(E11/E$13) -> 0.027418049 | F18: =SUM(F11/F$13) -> 0.027830076 | H18: =SUM(H11/H$13) -> 0.017481074 | I18: =SUM(I11/I$13) -> 0.030330882 | J18: =SUM(J11/J$13) -> 0.052852937 | K18: =SUM(K11/K$13) -> 0.010212097 | L18: =SUM(L11/L$13) -> 0.019908913 | M18: =SUM(M11/M$13) -> 0.020255394 | N18: =SUM(N11/N$13) -> 0.016045164 | O18: =SUM(O11/O$13) -> 0.051853707 | ... Q18: =SUM(Q11/Q$13) -> 0.037085706 | S18: =SUM(S11/S$13) -> 0.027418049 | T18: =SUM(T11/T$13) -> 0.027899707 | U18: =SUM(U11/U$13) -> 0.025487717 | V18: =SUM(V11/V$13) -> 0.016524059 | W18: =SUM(W11/W$13) -> 0.027830076 | X18: =SUM(X11/X$13) -> 0.028133705 | Y18: =SUM(Y11/Y$13) -> 0.032132425
B19: =B12&"(%)" -> Licensing and other(%) | C19: =SUM(C12/C$13) -> 0.22706919 | D19: =SUM(D12/D$13) -> 0.21522849 | E19: =SUM(E12/E$13) -> 0.19668151 | F19: =SUM(F12/F$13) -> 0.16951357 | H19: =SUM(H12/H$13) -> 0.18004129 | I19: =SUM(I12/I$13) -> 0.23043592 | J19: =SUM(J12/J$13) -> 0.19080331 | K19: =SUM(K12/K$13) -> 0.18434145 | L19: =SUM(L12/L$13) -> 0.14040338 | M19: =SUM(M12/M$13) -> 0.16864817 | N19: =SUM(N12/N$13) -> 0.18333086 | O19: =SUM(O12/O$13) -> 0.18662325 | ... Q19: =SUM(Q12/Q$13) -> 0.1457147 | S19: =SUM(S12/S$13) -> 0.19668151 | T19: =SUM(T12/T$13) -> 0.1863195 | U19: =SUM(U12/U$13) -> 0.17072671 | V19: =SUM(V12/V$13) -> 0.16870475 | W19: =SUM(W12/W$13) -> 0.16951357 | X19: =SUM(X12/X$13) -> 0.17433844 | Y19: =SUM(Y12/Y$13) -> 0.16886911
A21: X | B21: Revenue by Type
B22: TV Media | C22: 22734 | D22: 21732 | E22: 20085 | F22: 18779 | H22: 5193 | I22: 5157 | J22: 4567 | K22: =SUM(E22-SUM(H22:J22)) -> 5168 | L22: 5231 | M22: 4271 | N22: 4298 | O22: =SUM(F22-SUM(L22:N22)) -> 4979 | P22: 4538 | Q22: 4011 | S22: =SUM(H22:K22) -> 20085 | T22: =SUM(I22:L22) -> 20123 | U22: =SUM(J22:M22) -> 19237 | V22: =SUM(K22:N22) -> 18968 | W22: =SUM(L22:O22) -> 18779 | X22: =SUM(M22:P22) -> 18086 | Y22: =SUM(N22:Q22) -> 17826
B23: Direct-to-Consumer | C23: 3327 | D23: 4904 | E23: 6736 | F23: 7632 | H23: 1510 | I23: 1665 | J23: 1692 | K23: =SUM(E23-SUM(H23:J23)) -> 1869 | L23: 1879 | M23: 1880 | N23: 1860 | O23: =SUM(F23-SUM(L23:N23)) -> 2013 | P23: 2044 | Q23: 2160 | S23: =SUM(H23:K23) -> 6736 | T23: =SUM(I23:L23) -> 7105 | U23: =SUM(J23:M23) -> 7320 | V23: =SUM(K23:N23) -> 7488 | W23: =SUM(L23:O23) -> 7632 | X23: =SUM(M23:P23) -> 7797 | Y23: =SUM(N23:Q23) -> 8077
B24: Filmed Entertainment | C24: 2687 | D24: 3706 | E24: 2957 | F24: 2955 | H24: 588 | I24: 831 | J24: 891 | K24: =SUM(E24-SUM(H24:J24)) -> 647 | L24: 605 | M24: 679 | N24: 590 | O24: =SUM(F24-SUM(L24:N24)) -> 1081 | P24: 627 | Q24: 690 | S24: =SUM(H24:K24) -> 2957 | T24: =SUM(I24:L24) -> 2974 | U24: =SUM(J24:M24) -> 2822 | V24: =SUM(K24:N24) -> 2521 | W24: =SUM(L24:O24) -> 2955 | X24: =SUM(M24:P24) -> 2977 | Y24: =SUM(N24:Q24) -> 2988
B25: Eliminations | C25: -162 | D25: -188 | E25: -126 | F25: -153 | H25: -26 | I25: -37 | J25: -17 | K25: =SUM(E25-SUM(H25:J25)) -> -46 | L25: -30 | M25: -17 | N25: -17 | O25: =SUM(F25-SUM(L25:N25)) -> -89 | P25: -17 | Q25: -12 | S25: =SUM(H25:K25) -> -126 | T25: =SUM(I25:L25) -> -130 | U25: =SUM(J25:M25) -> -110 | V25: =SUM(K25:N25) -> -110 | W25: =SUM(L25:O25) -> -153 | X25: =SUM(M25:P25) -> -140 | Y25: =SUM(N25:Q25) -> -135
B26: Total Net Revenue | C26: =SUM(C22:C25) -> 28586 | D26: =SUM(D22:D25) -> 30154 | E26: =SUM(E22:E25) -> 29652 | F26: =SUM(F22:F25) -> 29213 | H26: =SUM(H22:H25) -> 7265 | I26: =SUM(I22:I25) -> 7616 | J26: =SUM(J22:J25) -> 7133 | K26: =SUM(K22:K25) -> 7638 | L26: =SUM(L22:L25) -> 7685 | M26: =SUM(M22:M25) -> 6813 | N26: =SUM(N22:N25) -> 6731 | O26: =SUM(O22:O25) -> 7984 | ... Q26: =SUM(Q22:Q25) -> 6849 | S26: =SUM(S22:S25) -> 29652 | T26: =SUM(T22:T25) -> 30072 | U26: =SUM(U22:U25) -> 29269 | V26: =SUM(V22:V25) -> 28867 | W26: =SUM(W22:W25) -> 29213 | X26: =SUM(X22:X25) -> 28720 | Y26: =SUM(Y22:Y25) -> 28756
B27: Variance Check | C27: =+C26-C13 -> 0 | D27: =+D26-D13 -> 0 | E27: =+E26-E13 -> 0 | F27: =+F26-F13 -> 0 | H27: =+H26-H13 -> 0 | I27: =+I26-I13 -> 0 | J27: =+J26-J13 -> 0 | K27: =+K26-K13 -> 0 | L27: =+L26-L13 -> 0 | M27: =+M26-M13 -> 0 | N27: =+N26-N13 -> 0 | O27: =+O26-O13 -> 0 | ... Q27: =+Q26-Q13 -> 0 | S27: =+S26-S13 -> 0 | T27: =+T26-T13 -> 0 | U27: =+U26-U13 -> 0 | V27: =+V26-V13 -> 0 | W27: =+W26-W13 -> 0 | X27: =+X26-X13 -> 0 | Y27: =+Y26-Y13 -> 0
B29: =B22&"(%)" -> TV Media(%) | C29: =SUM(C22/C$26) -> 0.7952844 | D29: =SUM(D22/D$26) -> 0.7207004 | E29: =SUM(E22/E$26) -> 0.67735735 | F29: =SUM(F22/F$26) -> 0.64283025 | H29: =SUM(H22/H$26) -> 0.71479697 | I29: =SUM(I22/I$26) -> 0.6771271 | J29: =SUM(J22/J$26) -> 0.64026356 | K29: =SUM(K22/K$26) -> 0.67661692 | L29: =SUM(L22/L$26) -> 0.68067664 | M29: =SUM(M22/M$26) -> 0.62688977 | N29: =SUM(N22/N$26) -> 0.63853811 | O29: =SUM(O22/O$26) -> 0.62362224 | ... Q29: =SUM(Q22/Q$26) -> 0.58563294 | S29: =SUM(S22/S$26) -> 0.67735735 | T29: =SUM(T22/T$26) -> 0.66916068 | U29: =SUM(U22/U$26) -> 0.65724828 | V29: =SUM(V22/V$26) -> 0.65708248 | W29: =SUM(W22/W$26) -> 0.64283025 | X29: =SUM(X22/X$26) -> 0.62973538 | Y29: =SUM(Y22/Y$26) -> 0.61990541
B30: =B23&"(%)" -> Direct-to-Consumer(%) | C30: =SUM(C23/C$26) -> 0.11638564 | D30: =SUM(D23/D$26) -> 0.16263182 | E30: =SUM(E23/E$26) -> 0.22716849 | F30: =SUM(F23/F$26) -> 0.26125355 | H30: =SUM(H23/H$26) -> 0.20784584 | I30: =SUM(I23/I$26) -> 0.2186187 | J30: =SUM(J23/J$26) -> 0.23720735 | K30: =SUM(K23/K$26) -> 0.24469756 | L30: =SUM(L23/L$26) -> 0.24450228 | M30: =SUM(M23/M$26) -> 0.27594305 | N30: =SUM(N23/N$26) -> 0.27633338 | O30: =SUM(O23/O$26) -> 0.25212926 | ... Q30: =SUM(Q23/Q$26) -> 0.31537451 | S30: =SUM(S23/S$26) -> 0.22716849 | T30: =SUM(T23/T$26) -> 0.23626629 | U30: =SUM(U23/U$26) -> 0.25009396 | V30: =SUM(V23/V$26) -> 0.25939654 | W30: =SUM(W23/W$26) -> 0.26125355 | X30: =SUM(X23/X$26) -> 0.27148329 | Y30: =SUM(Y23/Y$26) -> 0.28088051
B31: =B24&"(%)" -> Filmed Entertainment(%) | C31: =SUM(C24/C$26) -> 0.093997061 | D31: =SUM(D24/D$26) -> 0.12290243 | E31: =SUM(E24/E$26) -> 0.099723459 | F31: =SUM(F24/F$26) -> 0.1011536 | H31: =SUM(H24/H$26) -> 0.080935994 | I31: =SUM(I24/I$26) -> 0.10911239 | J31: =SUM(J24/J$26) -> 0.12491238 | K31: =SUM(K24/K$26) -> 0.084708039 | L31: =SUM(L24/L$26) -> 0.078724789 | M31: =SUM(M24/M$26) -> 0.09966241 | N31: =SUM(N24/N$26) -> 0.087654138 | O31: =SUM(O24/O$26) -> 0.13539579 | ... Q31: =SUM(Q24/Q$26) -> 0.10074463 | S31: =SUM(S24/S$26) -> 0.099723459 | T31: =SUM(T24/T$26) -> 0.098895983 | U31: =SUM(U24/U$26) -> 0.096416003 | V31: =SUM(V24/V$26) -> 0.087331555 | W31: =SUM(W24/W$26) -> 0.1011536 | X31: =SUM(X24/X$26) -> 0.10365599 | Y31: =SUM(Y24/Y$26) -> 0.10390875
A33: X | B33: Revenue by product category: Revenue by TV Media
A35: X | B35: Revenue by TV Media
B36: Advertising | C36: 10105 | D36: 9350 | E36: 8188 | F36: 8180 | H36: 2256 | I36: 1946 | J36: 1703 | K36: =SUM(E36-SUM(H36:J36)) -> 2283 | L36: 2582 | M36: 1733 | N36: 1666 | O36: =SUM(F36-SUM(L36:N36)) -> 2199 | P36: 2038 | Q36: 1657 | S36: =SUM(H36:K36) -> 8188 | T36: =SUM(I36:L36) -> 8514 | U36: =SUM(J36:M36) -> 8301 | V36: =SUM(K36:N36) -> 8264 | W36: =SUM(L36:O36) -> 8180 | X36: =SUM(M36:P36) -> 7636 | Y36: =SUM(N36:Q36) -> 7560
B37: Affiliate and subscription | C37: 8413 | D37: 8180 | E37: 8085 | F37: 7647 | H37: 2067 | I37: 2011 | J37: 2004 | K37: =SUM(E37-SUM(H37:J37)) -> 2003 | L37: 1998 | M37: 1908 | N37: 1872 | O37: =SUM(F37-SUM(L37:N37)) -> 1869 | P37: 1826 | Q37: 1780 | S37: =SUM(H37:K37) -> 8085 | T37: =SUM(I37:L37) -> 8016 | U37: =SUM(J37:M37) -> 7913 | V37: =SUM(K37:N37) -> 7781 | W37: =SUM(L37:O37) -> 7647 | X37: =SUM(M37:P37) -> 7475 | Y37: =SUM(N37:Q37) -> 7347
B38: Licensing and other | C38: 4216 | D38: 4202 | E38: 3812 | F38: 2952 | H38: 870 | I38: 1200 | J38: 860 | K38: =SUM(E38-SUM(H38:J38)) -> 882 | L38: 651 | M38: 630 | N38: 760 | O38: =SUM(F38-SUM(L38:N38)) -> 911 | P38: 674 | Q38: 574 | S38: =SUM(H38:K38) -> 3812 | T38: =SUM(I38:L38) -> 3593 | U38: =SUM(J38:M38) -> 3023 | V38: =SUM(K38:N38) -> 2923 | W38: =SUM(L38:O38) -> 2952 | X38: =SUM(M38:P38) -> 2975 | Y38: =SUM(N38:Q38) -> 2919
B39: Total Revenue from TV Media | C39: =SUM(C36:C38) -> 22734 | D39: =SUM(D36:D38) -> 21732 | E39: =SUM(E36:E38) -> 20085 | F39: =SUM(F36:F38) -> 18779 | H39: =SUM(H36:H38) -> 5193 | I39: =SUM(I36:I38) -> 5157 | J39: =SUM(J36:J38) -> 4567 | K39: =SUM(K36:K38) -> 5168 | L39: =SUM(L36:L38) -> 5231 | M39: =SUM(M36:M38) -> 4271 | N39: =SUM(N36:N38) -> 4298 | O39: =SUM(O36:O38) -> 4979 | ... Q39: =SUM(Q36:Q38) -> 4011 | S39: =SUM(S36:S38) -> 20085 | T39: =SUM(T36:T38) -> 20123 | U39: =SUM(U36:U38) -> 19237 | V39: =SUM(V36:V38) -> 18968 | W39: =SUM(W36:W38) -> 18779 | X39: =SUM(X36:X38) -> 18086 | Y39: =SUM(Y36:Y38) -> 17826
B40: Variance Check | C40: =+C39-C22 -> 0 | D40: =+D39-D22 -> 0 | E40: =+E39-E22 -> 0 | F40: =+F39-F22 -> 0 | H40: =+H39-H22 -> 0 | I40: =+I39-I22 -> 0 | J40: =+J39-J22 -> 0 | K40: =+K39-K22 -> 0 | L40: =+L39-L22 -> 0 | M40: =+M39-M22 -> 0 | N40: =+N39-N22 -> 0 | O40: =+O39-O22 -> 0 | ... Q40: =+Q39-Q22 -> 0 | S40: =+S39-S22 -> 0 | T40: =+T39-T22 -> 0 | U40: =+U39-U22 -> 0 | V40: =+V39-V22 -> 0 | W40: =+W39-W22 -> 0 | X40: =+X39-X22 -> 0 | Y40: =+Y39-Y22 -> 0
B42: =B36&"(%)" -> Advertising(%) | C42: =C36/C$39 -> 0.44448843 | D42: =D36/D$39 -> 0.43024112 | E42: =E36/E$39 -> 0.40766741 | F42: =F36/F$39 -> 0.43559295 | H42: =H36/H$39 -> 0.43443096 | I42: =I36/I$39 -> 0.37735117 | J42: =J36/J$39 -> 0.37289249 | K42: =K36/K$39 -> 0.44175697 | L42: =L36/L$39 -> 0.49359587 | M42: =M36/M$39 -> 0.40575978 | N42: =N36/N$39 -> 0.38762215 | O42: =O36/O$39 -> 0.44165495 | ... Q42: =Q36/Q$39 -> 0.41311394 | S42: =S36/S$39 -> 0.40766741 | T42: =T36/T$39 -> 0.42309795 | U42: =U36/U$39 -> 0.43151219 | V42: =V36/V$39 -> 0.43568115 | W42: =W36/W$39 -> 0.43559295 | X42: =X36/X$39 -> 0.42220502 | Y42: =Y36/Y$39 -> 0.42409963
B43: =B37&"(%)" -> Affiliate and subscription(%) | C43: =C37/C$39 -> 0.37006246 | D43: =D37/D$39 -> 0.37640346 | E43: =E37/E$39 -> 0.40253921 | F43: =F37/F$39 -> 0.40721018 | H43: =H37/H$39 -> 0.39803582 | I43: =I37/I$39 -> 0.3899554 | J43: =J37/J$39 -> 0.43880009 | K43: =K37/K$39 -> 0.3875774 | L43: =L37/L$39 -> 0.38195374 | M43: =M37/M$39 -> 0.44673379 | N43: =N37/N$39 -> 0.43555142 | O43: =O37/O$39 -> 0.37537658 | ... Q43: =Q37/Q$39 -> 0.44377961 | S43: =S37/S$39 -> 0.40253921 | T43: =T37/T$39 -> 0.39835015 | U43: =U37/U$39 -> 0.41134272 | V43: =V37/V$39 -> 0.41021721 | W43: =W37/W$39 -> 0.40721018 | X43: =X37/X$39 -> 0.41330311 | Y43: =Y37/Y$39 -> 0.41215079
B44: =B38&"(%)" -> Licensing and other(%) | C44: =C38/C$39 -> 0.18544911 | D44: =D38/D$39 -> 0.19335542 | E44: =E38/E$39 -> 0.18979338 | F44: =F38/F$39 -> 0.15719687 | H44: =H38/H$39 -> 0.16753322 | I44: =I38/I$39 -> 0.23269343 | J44: =J38/J$39 -> 0.18830742 | K44: =K38/K$39 -> 0.17066563 | L44: =L38/L$39 -> 0.12445039 | M44: =M38/M$39 -> 0.14750644 | N44: =N38/N$39 -> 0.17682643 | O44: =O38/O$39 -> 0.18296847 | ... Q44: =Q38/Q$39 -> 0.14310646 | S44: =S38/S$39 -> 0.18979338 | T44: =T38/T$39 -> 0.17855191 | U44: =U38/U$39 -> 0.15714508 | V44: =V38/V$39 -> 0.15410164 | W44: =W38/W$39 -> 0.15719687 | X44: =X38/X$39 -> 0.16449187 | Y44: =Y38/Y$39 -> 0.16374958
A46: X | B46: Revenue by product category: Direct to Consumer
A48: X | B48: Revenue by Direct-to-Consumer
B49: Advertising | C49: 1298 | D49: 1533 | E49: 1795 | F49: 2114 | H49: 398 | I49: 441 | J49: 430 | K49: =SUM(E49-SUM(H49:J49)) -> 526 | L49: 520 | M49: 513 | N49: 507 | O49: =SUM(F49-SUM(L49:N49)) -> 574 | P49: 473 | Q49: 494 | S49: =SUM(H49:K49) -> 1795 | T49: =SUM(I49:L49) -> 1917 | U49: =SUM(J49:M49) -> 1989 | V49: =SUM(K49:N49) -> 2066 | W49: =SUM(L49:O49) -> 2114 | X49: =SUM(M49:P49) -> 2067 | Y49: =SUM(N49:Q49) -> 2048
B50: Subscription & Licensing | C50: 2029 | D50: 3371 | E50: =4933+8 -> 4941 | F50: =5506+12 -> 5518 | H50: 1112 | I50: 1224 | J50: =1258+4 -> 1262 | K50: =SUM(E50-SUM(H50:J50)) -> 1343 | L50: 1359 | M50: 1367 | N50: =1343+10 -> 1353 | O50: =SUM(F50-SUM(L50:N50)) -> 1439 | P50: 1571 | Q50: =1665+1 -> 1666 | S50: =SUM(H50:K50) -> 4941 | T50: =SUM(I50:L50) -> 5188 | U50: =SUM(J50:M50) -> 5331 | V50: =SUM(K50:N50) -> 5422 | W50: =SUM(L50:O50) -> 5518 | X50: =SUM(M50:P50) -> 5730 | Y50: =SUM(N50:Q50) -> 6029
B51: Total Revenue from Direct-to-Consumer | C51: =SUM(C49:C50) -> 3327 | D51: =SUM(D49:D50) -> 4904 | E51: =SUM(E49:E50) -> 6736 | F51: =SUM(F49:F50) -> 7632 | H51: =SUM(H49:H50) -> 1510 | I51: =SUM(I49:I50) -> 1665 | J51: =SUM(J49:J50) -> 1692 | K51: =SUM(K49:K50) -> 1869 | L51: =SUM(L49:L50) -> 1879 | M51: =SUM(M49:M50) -> 1880 | N51: =SUM(N49:N50) -> 1860 | O51: =SUM(O49:O50) -> 2013 | ... Q51: =SUM(Q49:Q50) -> 2160 | S51: =SUM(S49:S50) -> 6736 | T51: =SUM(T49:T50) -> 7105 | U51: =SUM(U49:U50) -> 7320 | V51: =SUM(V49:V50) -> 7488 | W51: =SUM(W49:W50) -> 7632 | X51: =SUM(X49:X50) -> 7797 | Y51: =SUM(Y49:Y50) -> 8077
B52: Variance Check | C52: =+C51-C23 -> 0 | D52: =+D51-D23 -> 0 | E52: =+E51-E23 -> 0 | F52: =+F51-F23 -> 0 | H52: =+H51-H23 -> 0 | I52: =+I51-I23 -> 0 | J52: =+J51-J23 -> 0 | K52: =+K51-K23 -> 0 | L52: =+L51-L23 -> 0 | M52: =+M51-M23 -> 0 | N52: =+N51-N23 -> 0 | O52: =+O51-O23 -> 0 | ... Q52: =+Q51-Q23 -> 0 | S52: =+S51-S23 -> 0 | T52: =+T51-T23 -> 0 | U52: =+U51-U23 -> 0 | V52: =+V51-V23 -> 0 | W52: =+W51-W23 -> 0 | X52: =+X51-X23 -> 0 | Y52: =+Y51-Y23 -> 0
B54: =B49&"(%)" -> Advertising(%) | C54: =C49/C$51 -> 0.39014127 | D54: =D49/D$51 -> 0.31260196 | E54: =E49/E$51 -> 0.26647862 | F54: =F49/F$51 -> 0.27699161 | H54: =H49/H$51 -> 0.26357616 | I54: =I49/I$51 -> 0.26486486 | J54: =J49/J$51 -> 0.25413712 | K54: =K49/K$51 -> 0.28143392 | L54: =L49/L$51 -> 0.27674295 | M54: =M49/M$51 -> 0.27287234 | N54: =N49/N$51 -> 0.27258065 | O54: =O49/O$51 -> 0.28514655 | ... Q54: =Q49/Q$51 -> 0.2287037 | S54: =S49/S$51 -> 0.26647862 | T54: =T49/T$51 -> 0.26980999 | U54: =U49/U$51 -> 0.27172131 | V54: =V49/V$51 -> 0.27590812 | W54: =W49/W$51 -> 0.27699161 | X54: =X49/X$51 -> 0.26510196 | Y54: =Y49/Y$51 -> 0.25355949
B55: =B50&"(%)" -> Subscription & Licensing(%) | C55: =C50/C$51 -> 0.60985873 | D55: =D50/D$51 -> 0.68739804 | E55: =E50/E$51 -> 0.73352138 | F55: =F50/F$51 -> 0.72300839 | H55: =H50/H$51 -> 0.73642384 | I55: =I50/I$51 -> 0.73513514 | J55: =J50/J$51 -> 0.74586288 | K55: =K50/K$51 -> 0.71856608 | L55: =L50/L$51 -> 0.72325705 | M55: =M50/M$51 -> 0.72712766 | N55: =N50/N$51 -> 0.72741935 | O55: =O50/O$51 -> 0.71485345 | ... Q55: =Q50/Q$51 -> 0.7712963 | S55: =S50/S$51 -> 0.73352138 | T55: =T50/T$51 -> 0.73019001 | U55: =U50/U$51 -> 0.72827869 | V55: =V50/V$51 -> 0.72409188 | W55: =W50/W$51 -> 0.72300839 | X55: =X50/X$51 -> 0.73489804 | Y55: =Y50/Y$51 -> 0.74644051
B57: Direct-to-Consumer KPIs
B59: Paramount+ (Global) Streaming Subscribers | C59: 32.8 | D59: 55.9 | E59: 67.5 | F59: 77.5 | H59: 60 | I59: 60.7 | J59: 63.4 | K59: =E59 -> 67.5 | L59: 71.2 | M59: 68.4 | N59: 71.9 | O59: =F59 -> 77.5 | P59: 79 | Q59: 77.7 | S59: =K59 -> 67.5 | T59: =L59 -> 71.2 | U59: =M59 -> 68.4 | V59: =N59 -> 71.9 | W59: =O59 -> 77.5 | X59: =P59 -> 79 | Y59: =Q59 -> 77.7
A61: X | B61: Paramount+ (Global) Streaming Revenue
B62: Paramount+ (Global) Streaming Revenue | C62: 1347 | D62: 2767 | E62: 4446 | F62: 5896 | H62: 965 | I62: 990 | J62: 1138 | K62: =SUM(E62-SUM(H62:J62)) -> 1353 | L62: 1459 | M62: 1445 | N62: 1428 | O62: =SUM(F62-SUM(L62:N62)) -> 1564 | P62: 1686 | Q62: 1771 | S62: =SUM(H62:K62) -> 4446 | T62: =SUM(I62:L62) -> 4940 | U62: =SUM(J62:M62) -> 5395 | V62: =SUM(K62:N62) -> 5685 | W62: =SUM(L62:O62) -> 5896 | X62: =SUM(M62:P62) -> 6123 | Y62: =SUM(N62:Q62) -> 6449
B63: Total Paramount+ (Global) Streaming Revenue | C63: =SUM(C62:C62) -> 1347 | D63: =SUM(D62:D62) -> 2767 | E63: =SUM(E62:E62) -> 4446 | F63: =SUM(F62:F62) -> 5896 | H63: =SUM(H62:H62) -> 965 | I63: =SUM(I62:I62) -> 990 | J63: =SUM(J62:J62) -> 1138 | K63: =SUM(K62:K62) -> 1353 | L63: =SUM(L62:L62) -> 1459 | M63: =SUM(M62:M62) -> 1445 | N63: =SUM(N62:N62) -> 1428 | O63: =SUM(O62:O62) -> 1564 | ... Q63: =SUM(Q62:Q62) -> 1771 | S63: =SUM(S62:S62) -> 4446 | T63: =SUM(T62:T62) -> 4940 | U63: =SUM(U62:U62) -> 5395 | V63: =SUM(V62:V62) -> 5685 | W63: =SUM(W62:W62) -> 5896 | X63: =SUM(X62:X62) -> 6123 | Y63: =SUM(Y62:Y62) -> 6449
A65: X | B65: Revenue by product category: Filmed Entertainment
A67: X | B67: Revenue by Filmed Entertainment
B68: Advertising | C68: 18 | D68: 23 | E68: 24 | F68: 16 | H68: 5 | I68: 11 | J68: 5 | K68: =SUM(E68-SUM(H68:J68)) -> 3 | L68: 1 | M68: 7 | N68: 2 | O68: =SUM(F68-SUM(L68:N68)) -> 6 | P68: 3 | Q68: 2 | S68: =SUM(H68:K68) -> 24 | T68: =SUM(I68:L68) -> 20 | U68: =SUM(J68:M68) -> 16 | V68: =SUM(K68:N68) -> 13 | W68: =SUM(L68:O68) -> 16 | X68: =SUM(M68:P68) -> 18 | Y68: =SUM(N68:Q68) -> 13
B69: Theatrical | C69: 241 | D69: 1223 | E69: 813 | F69: 813 | H69: 127 | I69: 231 | J69: 377 | K69: =SUM(E69-SUM(H69:J69)) -> 78 | L69: 153 | M69: 138 | N69: 108 | O69: =SUM(F69-SUM(L69:N69)) -> 414 | P69: 148 | Q69: 254 | S69: =SUM(H69:K69) -> 813 | T69: =SUM(I69:L69) -> 839 | U69: =SUM(J69:M69) -> 746 | V69: =SUM(K69:N69) -> 477 | W69: =SUM(L69:O69) -> 813 | X69: =SUM(M69:P69) -> 808 | Y69: =SUM(N69:Q69) -> 924
B70: Licensing and other | C70: 2428 | D70: 2460 | E70: 2120 | F70: 2126 | H70: 456 | I70: 589 | J70: 509 | K70: =SUM(E70-SUM(H70:J70)) -> 566 | L70: 451 | M70: 534 | N70: 480 | O70: =SUM(F70-SUM(L70:N70)) -> 661 | P70: 476 | Q70: 434 | S70: =SUM(H70:K70) -> 2120 | T70: =SUM(I70:L70) -> 2115 | U70: =SUM(J70:M70) -> 2060 | V70: =SUM(K70:N70) -> 2031 | W70: =SUM(L70:O70) -> 2126 | X70: =SUM(M70:P70) -> 2151 | Y70: =SUM(N70:Q70) -> 2051
B71: Total Revenue from Filmed Entertainment | C71: =SUM(C68:C70) -> 2687 | D71: =SUM(D68:D70) -> 3706 | E71: =SUM(E68:E70) -> 2957 | F71: =SUM(F68:F70) -> 2955 | H71: =SUM(H68:H70) -> 588 | I71: =SUM(I68:I70) -> 831 | J71: =SUM(J68:J70) -> 891 | K71: =SUM(K68:K70) -> 647 | L71: =SUM(L68:L70) -> 605 | M71: =SUM(M68:M70) -> 679 | N71: =SUM(N68:N70) -> 590 | O71: =SUM(O68:O70) -> 1081 | ... Q71: =SUM(Q68:Q70) -> 690 | S71: =SUM(S68:S70) -> 2957 | T71: =SUM(T68:T70) -> 2974 | U71: =SUM(U68:U70) -> 2822 | V71: =SUM(V68:V70) -> 2521 | W71: =SUM(W68:W70) -> 2955 | X71: =SUM(X68:X70) -> 2977 | Y71: =SUM(Y68:Y70) -> 2988
B72: Variance Check | C72: =+C71-C24 -> 0 | D72: =+D71-D24 -> 0 | E72: =+E71-E24 -> 0 | F72: =+F71-F24 -> 0 | H72: =+H71-H24 -> 0 | I72: =+I71-I24 -> 0 | J72: =+J71-J24 -> 0 | K72: =+K71-K24 -> 0 | L72: =+L71-L24 -> 0 | M72: =+M71-M24 -> 0 | N72: =+N71-N24 -> 0 | O72: =+O71-O24 -> 0 | ... Q72: =+Q71-Q24 -> 0 | S72: =+S71-S24 -> 0 | T72: =+T71-T24 -> 0 | U72: =+U71-U24 -> 0 | V72: =+V71-V24 -> 0 | W72: =+W71-W24 -> 0 | X72: =+X71-X24 -> 0 | Y72: =+Y71-Y24 -> 0
B74: =B68&"(%)" -> Advertising(%) | C74: =C68/C$39 -> 0.00079176564 | D74: =D68/D$39 -> 0.0010583471 | E74: =E68/E$39 -> 0.0011949216 | F74: =F68/F$39 -> 0.00085201555 | H74: =H68/H$39 -> 0.00096283459 | I74: =I68/I$39 -> 0.0021330231 | J74: =J68/J$39 -> 0.0010948106 | K74: =K68/K$39 -> 0.00058049536 | L74: =L68/L$39 -> 0.00019116804 | M74: =M68/M$39 -> 0.0016389604 | N74: =N68/N$39 -> 0.00046533271 | O74: =O68/O$39 -> 0.0012050613 | ... Q74: =Q68/Q$39 -> 0.00049862877 | S74: =S68/S$39 -> 0.0011949216 | T74: =T68/T$39 -> 0.00099388759 | U74: =U68/U$39 -> 0.00083173052 | V74: =V68/V$39 -> 0.00068536482 | W74: =W68/W$39 -> 0.00085201555 | X74: =X68/X$39 -> 0.00099524494 | Y74: =Y68/Y$39 -> 0.00072927185
B75: =B69&"(%)" -> Theatrical(%) | C75: =C69/C$39 -> 0.010600862 | D75: =D69/D$39 -> 0.056276459 | E75: =E69/E$39 -> 0.040477969 | F75: =F69/F$39 -> 0.04329304 | H75: =H69/H$39 -> 0.024455998 | I75: =I69/I$39 -> 0.044793485 | J75: =J69/J$39 -> 0.082548719 | K75: =K69/K$39 -> 0.015092879 | L75: =L69/L$39 -> 0.02924871 | M75: =M69/M$39 -> 0.032310934 | N75: =N69/N$39 -> 0.025127966 | O75: =O69/O$39 -> 0.083149227 | ... Q75: =Q69/Q$39 -> 0.063325854 | S75: =S69/S$39 -> 0.040477969 | T75: =T69/T$39 -> 0.041693584 | U75: =U69/U$39 -> 0.038779435 | V75: =V69/V$39 -> 0.025147617 | W75: =W69/W$39 -> 0.04329304 | X75: =X69/X$39 -> 0.04467544 | Y75: =Y69/Y$39 -> 0.051834399
B76: =B70&"(%)" -> Licensing and other(%) | C76: =C70/C$39 -> 0.10680039 | D76: =D70/D$39 -> 0.11319713 | E76: =E70/E$39 -> 0.10555141 | F76: =F70/F$39 -> 0.11321157 | H76: =H70/H$39 -> 0.087810514 | I76: =I70/I$39 -> 0.11421369 | J76: =J70/J$39 -> 0.11145172 | K76: =K70/K$39 -> 0.10952012 | L76: =L70/L$39 -> 0.086216785 | M76: =M70/M$39 -> 0.12502927 | N76: =N70/N$39 -> 0.11167985 | O76: =O70/O$39 -> 0.13275758 | ... Q76: =Q70/Q$39 -> 0.10820244 | S76: =S70/S$39 -> 0.10555141 | T76: =T70/T$39 -> 0.10510361 | U76: =U70/U$39 -> 0.1070853 | V76: =V70/V$39 -> 0.10707507 | W76: =W70/W$39 -> 0.11321157 | X76: =X70/X$39 -> 0.11893177 | Y76: =Y70/Y$39 -> 0.11505666

Sheet FCF
B2: ='Historical Financials'!B2 -> Paramount Global (NASDAQ: PARA) | D2: FYE | H2: Quarterly | T2: LTM | U2: LTM | AA2: Variance
B3: FCF Analysis | C3: ='Historical Financials'!C7 -> 2021 | D3: ='Historical Financials'!D7 -> 2022 | E3: ='Historical Financials'!E7 -> 2023 | F3: ='Historical Financials'!F7 -> 2024 | H3: ='Historical Financials'!H7 -> 1Q23 | I3: ='Historical Financials'!I7 -> 2Q23 | J3: ='Historical Financials'!J7 -> 3Q23 | K3: ='Historical Financials'!K7 -> 4Q23 | L3: ='Historical Financials'!L7 -> 1Q24 | M3: ='Historical Financials'!M7 -> 2Q24 | N3: ='Historical Financials'!N7 -> 3Q24 | O3: ='Historical Financials'!O7 -> 4Q24 | ... Q3: ='Historical Financials'!Q7 -> 2Q25 | S3: =K3 -> 4Q23 | T3: =L3 -> 1Q24 | U3: =M3 -> 2Q24 | V3: =N3 -> 3Q24 | W3: =O3 -> 4Q24 | X3: =P3 -> 1Q25 | Y3: =Q3 -> 2Q25
B4: ($ In Millions) | C4: ='Historical Financials'!C8 -> 44561 | D4: ='Historical Financials'!D8 -> 44926 | E4: ='Historical Financials'!E8 -> 45291 | F4: ='Historical Financials'!F8 -> 45657 | H4: ='Historical Financials'!H8 -> 45016 | I4: ='Historical Financials'!I8 -> 45107 | J4: ='Historical Financials'!J8 -> 45199 | K4: ='Historical Financials'!K8 -> 44926 | L4: ='Historical Financials'!L8 -> 45382 | M4: ='Historical Financials'!M8 -> 45473 | N4: ='Historical Financials'!N8 -> 45565 | O4: ='Historical Financials'!O8 -> 45291 | ... Q4: ='Historical Financials'!Q8 -> 45838 | S4: =K4 -> 44926 | T4: =L4 -> 45382 | U4: =M4 -> 45473 | V4: =N4 -> 45565 | W4: =O4 -> 45291 | X4: =P4 -> 45747 | Y4: =Q4 -> 45838
B6: ='Revenue Drivers'!B9 -> Advertising | C6: ='Revenue Drivers'!C9 -> 11412 | D6: ='Revenue Drivers'!D9 -> 10890 | E6: ='Revenue Drivers'!E9 -> 9989 | F6: ='Revenue Drivers'!F9 -> 10295 | H6: ='Revenue Drivers'!H9 -> 2651 | I6: ='Revenue Drivers'!I9 -> 2395 | J6: ='Revenue Drivers'!J9 -> 2133 | K6: ='Revenue Drivers'!K9 -> 2810 | L6: ='Revenue Drivers'!L9 -> 3096 | M6: ='Revenue Drivers'!M9 -> 2251 | N6: ='Revenue Drivers'!N9 -> 2174 | O6: ='Revenue Drivers'!O9 -> 2774 | ... Q6: ='Revenue Drivers'!Q9 -> 2152 | S6: =SUM(H6:K6) -> 9989 | T6: =SUM(I6:L6) -> 10434 | U6: =SUM(J6:M6) -> 10290 | V6: =SUM(K6:N6) -> 10331 | W6: =SUM(L6:O6) -> 10295 | X6: =SUM(M6:P6) -> 9712 | Y6: =SUM(N6:Q6) -> 9613 | AA6: =SUM(Y6/U6)-1 -> -0.065792031
B7: ='Revenue Drivers'!B10 -> Affiliate and subscription | C7: ='Revenue Drivers'!C10 -> 10442 | D7: ='Revenue Drivers'!D10 -> 11551 | E7: ='Revenue Drivers'!E10 -> 13018 | F7: ='Revenue Drivers'!F10 -> 13153 | H7: ='Revenue Drivers'!H10 -> 3179 | I7: ='Revenue Drivers'!I10 -> 3235 | J7: ='Revenue Drivers'!J10 -> 3262 | K7: ='Revenue Drivers'!K10 -> 3342 | L7: ='Revenue Drivers'!L10 -> 3357 | M7: ='Revenue Drivers'!M10 -> 3275 | N7: ='Revenue Drivers'!N10 -> 3215 | O7: ='Revenue Drivers'!O10 -> 3306 | ... Q7: ='Revenue Drivers'!Q10 -> 3445 | S7: =SUM(H7:K7) -> 13018 | T7: =SUM(I7:L7) -> 13196 | U7: =SUM(J7:M7) -> 13236 | V7: =SUM(K7:N7) -> 13189 | W7: =SUM(L7:O7) -> 13153 | X7: =SUM(M7:P7) -> 13193 | Y7: =SUM(N7:Q7) -> 13363 | AA7: =SUM(Y7/U7)-1 -> 0.0095950438
B8: ='Revenue Drivers'!B11 -> Theatrical | C8: ='Revenue Drivers'!C11 -> 241 | D8: ='Revenue Drivers'!D11 -> 1223 | E8: ='Revenue Drivers'!E11 -> 813 | F8: ='Revenue Drivers'!F11 -> 813 | H8: ='Revenue Drivers'!H11 -> 127 | I8: ='Revenue Drivers'!I11 -> 231 | J8: ='Revenue Drivers'!J11 -> 377 | K8: ='Revenue Drivers'!K11 -> 78 | L8: ='Revenue Drivers'!L11 -> 153 | M8: ='Revenue Drivers'!M11 -> 138 | N8: ='Revenue Drivers'!N11 -> 108 | O8: ='Revenue Drivers'!O11 -> 414 | ... Q8: ='Revenue Drivers'!Q11 -> 254 | S8: =SUM(H8:K8) -> 813 | T8: =SUM(I8:L8) -> 839 | U8: =SUM(J8:M8) -> 746 | V8: =SUM(K8:N8) -> 477 | W8: =SUM(L8:O8) -> 813 | X8: =SUM(M8:P8) -> 808 | Y8: =SUM(N8:Q8) -> 924 | AA8: =SUM(Y8/U8)-1 -> 0.2386059
B9: ='Revenue Drivers'!B12 -> Licensing and other | C9: ='Revenue Drivers'!C12 -> 6491 | D9: ='Revenue Drivers'!D12 -> 6490 | E9: ='Revenue Drivers'!E12 -> 5832 | F9: ='Revenue Drivers'!F12 -> 4952 | H9: ='Revenue Drivers'!H12 -> 1308 | I9: ='Revenue Drivers'!I12 -> 1755 | J9: ='Revenue Drivers'!J12 -> 1361 | K9: ='Revenue Drivers'!K12 -> 1408 | L9: ='Revenue Drivers'!L12 -> 1079 | M9: ='Revenue Drivers'!M12 -> 1149 | N9: ='Revenue Drivers'!N12 -> 1234 | O9: ='Revenue Drivers'!O12 -> 1490 | ... Q9: ='Revenue Drivers'!Q12 -> 998 | S9: =SUM(H9:K9) -> 5832 | T9: =SUM(I9:L9) -> 5603 | U9: =SUM(J9:M9) -> 4997 | V9: =SUM(K9:N9) -> 4870 | W9: =SUM(L9:O9) -> 4952 | X9: =SUM(M9:P9) -> 5007 | Y9: =SUM(N9:Q9) -> 4856 | AA9: =SUM(Y9/U9)-1 -> -0.02821693
B10: Total Revenue | C10: =SUM(C6:C9) -> 28586 | D10: =SUM(D6:D9) -> 30154 | E10: =SUM(E6:E9) -> 29652 | F10: =SUM(F6:F9) -> 29213 | H10: =SUM(H6:H9) -> 7265 | I10: =SUM(I6:I9) -> 7616 | J10: =SUM(J6:J9) -> 7133 | K10: =SUM(K6:K9) -> 7638 | L10: =SUM(L6:L9) -> 7685 | M10: =SUM(M6:M9) -> 6813 | N10: =SUM(N6:N9) -> 6731 | O10: =SUM(O6:O9) -> 7984 | ... Q10: =SUM(Q6:Q9) -> 6849 | S10: =SUM(S6:S9) -> 29652 | T10: =SUM(T6:T9) -> 30072 | U10: =SUM(U6:U9) -> 29269 | V10: =SUM(V6:V9) -> 28867 | W10: =SUM(W6:W9) -> 29213 | X10: =SUM(X6:X9) -> 28720 | Y10: =SUM(Y6:Y9) -> 28756 | AA10: =SUM(Y10/U10)-1 -> -0.017527076
B11: Y/Y Growth (%) | D11: =SUM(D10/C10)-1 -> 0.054852025 | E11: =SUM(E10/D10)-1 -> -0.016647874 | F11: =SUM(F10/E10)-1 -> -0.014805072 | L11: =SUM(L10/H10)-1 -> 0.057811425 | M11: =SUM(M10/I10)-1 -> -0.10543592 | N11: =SUM(N10/J10)-1 -> -0.056357774 | O11: =SUM(O10/K10)-1 -> 0.045299817 | P11: =SUM(P10/L10)-1 -> -0.064150943 | Q11: =SUM(Q10/M10)-1 -> 0.0052840159 | W11: =SUM(W10/S10)-1 -> -0.014805072 | X11: =SUM(X10/T10)-1 -> -0.044958766 | Y11: =SUM(Y10/U10)-1 -> -0.017527076 | AA11: =SUM(Y11-U11)*10000 -> -175.27076
B12: Q/Q Growth (%) | C12: N/A | D12: N/A | E12: N/A | F12: N/A | I12: =SUM(I10/H10)-1 -> 0.048313833 | J12: =SUM(J10/I10)-1 -> -0.063419118 | K12: =SUM(K10/J10)-1 -> 0.070797701 | L12: =SUM(L10/K10)-1 -> 0.0061534433 | M12: =SUM(M10/L10)-1 -> -0.11346779 | N12: =SUM(N10/M10)-1 -> -0.012035814 | O12: =SUM(O10/N10)-1 -> 0.18615362 | P12: =SUM(P10/O10)-1 -> -0.099198397 | Q12: =SUM(Q10/P10)-1 -> -0.04769188 | S12: N/A | T12: N/A | U12: N/A | V12: N/A | W12: N/A | X12: N/A | Y12: N/A
B14: (-) Operating Expenses | C14: ='Historical Financials'!C13 -> -17744 | D14: ='Historical Financials'!D13 -> -19845 | E14: ='Historical Financials'!E13 -> -20017 | F14: ='Historical Financials'!F13 -> -19437 | H14: ='Historical Financials'!H13 -> -4964 | I14: ='Historical Financials'!I13 -> -5227 | J14: ='Historical Financials'!J13 -> -4681 | K14: ='Historical Financials'!K13 -> -5145 | L14: ='Historical Financials'!L13 -> -5036 | M14: ='Historical Financials'!M13 -> -4367 | N14: ='Historical Financials'!N13 -> -4342 | O14: ='Historical Financials'!O13 -> -5692 | ... Q14: ='Historical Financials'!Q13 -> -4624 | S14: =SUM(H14:K14) -> -20017 | T14: =SUM(I14:L14) -> -20089 | U14: =SUM(J14:M14) -> -19229 | V14: =SUM(K14:N14) -> -18890 | W14: =SUM(L14:O14) -> -19437 | X14: =SUM(M14:P14) -> -19362 | Y14: =SUM(N14:Q14) -> -19619 | AA14: =SUM(Y14/U14)-1 -> 0.020281866
B15: (-) Programming charges | C15: ='Historical Financials'!C14 -> 0 | D15: ='Historical Financials'!D14 -> 0 | E15: ='Historical Financials'!E14 -> -2371 | F15: ='Historical Financials'!F14 -> -1118 | H15: ='Historical Financials'!H14 -> -1674 | I15: ='Historical Financials'!I14 -> -697 | J15: ='Historical Financials'!J14 -> 0 | K15: ='Historical Financials'!K14 -> 0 | L15: ='Historical Financials'!L14 -> -1118 | M15: ='Historical Financials'!M14 -> 0 | N15: ='Historical Financials'!N14 -> 0 | O15: ='Historical Financials'!O14 -> 0 | ... Q15: ='Historical Financials'!Q14 -> 0 | S15: =SUM(H15:K15) -> -2371 | T15: =SUM(I15:L15) -> -1815 | U15: =SUM(J15:M15) -> -1118 | V15: =SUM(K15:N15) -> -1118 | W15: =SUM(L15:O15) -> -1118 | X15: =SUM(M15:P15) -> 0 | Y15: =SUM(N15:Q15) -> 0 | AA15: =SUM(Y15/U15)-1 -> -1
B16: (-) Selling, general and administrative | C16: ='Historical Financials'!C15 -> -6398 | D16: ='Historical Financials'!D15 -> -7033 | E16: ='Historical Financials'!E15 -> -7245 | F16: ='Historical Financials'!F15 -> -6658 | H16: ='Historical Financials'!H15 -> -1753 | I16: ='Historical Financials'!I15 -> -1783 | J16: ='Historical Financials'!J15 -> -1736 | K16: ='Historical Financials'!K15 -> -1973 | L16: ='Historical Financials'!L15 -> -1662 | M16: ='Historical Financials'!M15 -> -1579 | N16: ='Historical Financials'!N15 -> -1531 | O16: ='Historical Financials'!O15 -> -1886 | ... Q16: ='Historical Financials'!Q15 -> -1401 | S16: =SUM(H16:K16) -> -7245 | T16: =SUM(I16:L16) -> -7154 | U16: =SUM(J16:M16) -> -6950 | V16: =SUM(K16:N16) -> -6745 | W16: =SUM(L16:O16) -> -6658 | X16: =SUM(M16:P16) -> -6539 | Y16: =SUM(N16:Q16) -> -6361 | AA16: =SUM(Y16/U16)-1 -> -0.084748201
B17: (-) Depreciation and amortization | C17: ='Historical Financials'!C16 -> -390 | D17: ='Historical Financials'!D16 -> -378 | E17: ='Historical Financials'!E16 -> -418 | F17: ='Historical Financials'!F16 -> -392 | H17: ='Historical Financials'!H16 -> -100 | I17: ='Historical Financials'!I16 -> -105 | J17: ='Historical Financials'!J16 -> -105 | K17: ='Historical Financials'!K16 -> -108 | L17: ='Historical Financials'!L16 -> -100 | M17: ='Historical Financials'!M16 -> -101 | N17: ='Historical Financials'!N16 -> -96 | O17: ='Historical Financials'!O16 -> -95 | ... Q17: ='Historical Financials'!Q16 -> -87 | S17: =SUM(H17:K17) -> -418 | T17: =SUM(I17:L17) -> -418 | U17: =SUM(J17:M17) -> -414 | V17: =SUM(K17:N17) -> -405 | W17: =SUM(L17:O17) -> -392 | X17: =SUM(M17:P17) -> -380 | Y17: =SUM(N17:Q17) -> -366 | AA17: =SUM(Y17/U17)-1 -> -0.11594203
B18: (-) Impairment charges | C18: ='Historical Financials'!C17 -> 0 | D18: ='Historical Financials'!D17 -> -27 | E18: ='Historical Financials'!E17 -> -83 | F18: ='Historical Financials'!F17 -> -6130 | H18: ='Historical Financials'!H17 -> 0 | I18: ='Historical Financials'!I17 -> 0 | J18: ='Historical Financials'!J17 -> 0 | K18: ='Historical Financials'!K17 -> -83 | L18: ='Historical Financials'!L17 -> -186 | M18: ='Historical Financials'!M17 -> -5996 | N18: ='Historical Financials'!N17 -> -104 | O18: ='Historical Financials'!O17 -> 156 | ... Q18: ='Historical Financials'!Q17 -> -157 | S18: =SUM(H18:K18) -> -83 | T18: =SUM(I18:L18) -> -269 | U18: =SUM(J18:M18) -> -6265 | V18: =SUM(K18:N18) -> -6369 | W18: =SUM(L18:O18) -> -6130 | X18: =SUM(M18:P18) -> -5944 | Y18: =SUM(N18:Q18) -> -105 | AA18: =SUM(Y18/U18)-1 -> -0.98324022
B19: (-) Restructuring, transaction-related items, and other corporate matters | C19: ='Historical Financials'!C18 -> -100 | D19: ='Historical Financials'!D18 -> -585 | E19: ='Historical Financials'!E18 -> 31 | F19: ='Historical Financials'!F18 -> -747 | H19: ='Historical Financials'!H18 -> 0 | I19: ='Historical Financials'!I18 -> -54 | J19: ='Historical Financials'!J18 -> 10 | K19: ='Historical Financials'!K18 -> 75 | L19: ='Historical Financials'!L18 -> 0 | M19: ='Historical Financials'!M18 -> -88 | N19: ='Historical Financials'!N18 -> -321 | O19: ='Historical Financials'!O18 -> -338 | ... Q19: ='Historical Financials'!Q18 -> -181 | S19: =SUM(H19:K19) -> 31 | T19: =SUM(I19:L19) -> 31 | U19: =SUM(J19:M19) -> -3 | V19: =SUM(K19:N19) -> -334 | W19: =SUM(L19:O19) -> -747 | X19: =SUM(M19:P19) -> -832 | Y19: =SUM(N19:Q19) -> -925 | AA19: =SUM(Y19/U19)-1 -> 307.33333
B20: (-) Gains on dispositions | C20: ='Historical Financials'!C19 -> 2343 | D20: ='Historical Financials'!D19 -> 56 | E20: ='Historical Financials'!E19 -> 0 | F20: ='Historical Financials'!F19 -> 0 | H20: ='Historical Financials'!H19 -> 0 | I20: ='Historical Financials'!I19 -> 0 | J20: ='Historical Financials'!J19 -> 0 | K20: ='Historical Financials'!K19 -> 0 | L20: ='Historical Financials'!L19 -> 0 | M20: ='Historical Financials'!M19 -> 0 | N20: ='Historical Financials'!N19 -> 0 | O20: ='Historical Financials'!O19 -> 0 | ... Q20: ='Historical Financials'!Q19 -> 0 | S20: =SUM(H20:K20) -> 0 | T20: =SUM(I20:L20) -> 0 | U20: =SUM(J20:M20) -> 0 | V20: =SUM(K20:N20) -> 0 | W20: =SUM(L20:O20) -> 0 | X20: =SUM(M20:P20) -> 35 | Y20: =SUM(N20:Q20) -> 35 | AA20: =SUM(Y20/U20)-1 -> #DIV/0!
B21: Earning before Interest & Taxes (EBIT) | C21: =SUM(C10+SUM(C14:C20)) -> 6297 | D21: =SUM(D10+SUM(D14:D20)) -> 2342 | E21: =SUM(E10+SUM(E14:E20)) -> -451 | F21: =SUM(F10+SUM(F14:F20)) -> -5269 | H21: =SUM(H10+SUM(H14:H20)) -> -1226 | I21: =SUM(I10+SUM(I14:I20)) -> -250 | J21: =SUM(J10+SUM(J14:J20)) -> 621 | K21: =SUM(K10+SUM(K14:K20)) -> 404 | L21: =SUM(L10+SUM(L14:L20)) -> -417 | M21: =SUM(M10+SUM(M14:M20)) -> -5318 | N21: =SUM(N10+SUM(N14:N20)) -> 337 | O21: =SUM(O10+SUM(O14:O20)) -> 129 | ... Q21: =SUM(Q10+SUM(Q14:Q20)) -> 399 | S21: =SUM(S10+SUM(S14:S20)) -> -451 | T21: =SUM(T10+SUM(T14:T20)) -> 358 | U21: =SUM(U10+SUM(U14:U20)) -> -4710 | V21: =SUM(V10+SUM(V14:V20)) -> -4994 | W21: =SUM(W10+SUM(W14:W20)) -> -5269 | X21: =SUM(X10+SUM(X14:X20)) -> -4302 | Y21: =SUM(Y10+SUM(Y14:Y20)) -> 1415 | AA21: =SUM(Y21/U21)-1 -> -1.3004246
B22: Operating Margin (%) | C22: =C21/C10 -> 0.22028266 | D22: =D21/D10 -> 0.077667971 | E22: =E21/E10 -> -0.015209767 | F22: =F21/F10 -> -0.18036491 | H22: =H21/H10 -> -0.1687543 | I22: =I21/I10 -> -0.03282563 | J22: =J21/J10 -> 0.087060143 | K22: =K21/K10 -> 0.052893428 | L22: =L21/L10 -> -0.054261548 | M22: =M21/M10 -> -0.78056656 | N22: =N21/N10 -> 0.050066855 | O22: =O21/O10 -> 0.016157315 | ... Q22: =Q21/Q10 -> 0.05825668 | S22: =S21/S10 -> -0.015209767 | T22: =T21/T10 -> 0.011904762 | U22: =U21/U10 -> -0.16092111 | V22: =V21/V10 -> -0.17300031 | W22: =W21/W10 -> -0.18036491 | X22: =X21/X10 -> -0.14979109 | Y22: =Y21/Y10 -> 0.049207122 | AA22: =SUM(Y22-U22)*10000 -> 2101.2823
B24: (+) Depreciation and Amortization (D&A) | C24: =-C17 -> 390 | D24: =-D17 -> 378 | E24: =-E17 -> 418 | F24: =-F17 -> 392 | H24: =-H17 -> 100 | I24: =-I17 -> 105 | J24: =-J17 -> 105 | K24: =-K17 -> 108 | L24: =-L17 -> 100 | M24: =-M17 -> 101 | N24: =-N17 -> 96 | O24: =-O17 -> 95 | ... Q24: =-Q17 -> 87 | S24: =SUM(H24:K24) -> 418 | T24: =SUM(I24:L24) -> 418 | U24: =SUM(J24:M24) -> 414 | V24: =SUM(K24:N24) -> 405 | W24: =SUM(L24:O24) -> 392 | X24: =SUM(M24:P24) -> 380 | Y24: =SUM(N24:Q24) -> 366 | AA24: =SUM(Y24/U24)-1 -> -0.11594203
B25: EBITDA | C25: =SUM(C21+SUM(C24:C24)) -> 6687 | D25: =SUM(D21+SUM(D24:D24)) -> 2720 | E25: =SUM(E21+SUM(E24:E24)) -> -33 | F25: =SUM(F21+SUM(F24:F24)) -> -4877 | H25: =SUM(H21+SUM(H24:H24)) -> -1126 | I25: =SUM(I21+SUM(I24:I24)) -> -145 | J25: =SUM(J21+SUM(J24:J24)) -> 726 | K25: =SUM(K21+SUM(K24:K24)) -> 512 | L25: =SUM(L21+SUM(L24:L24)) -> -317 | M25: =SUM(M21+SUM(M24:M24)) -> -5217 | N25: =SUM(N21+SUM(N24:N24)) -> 433 | O25: =SUM(O21+SUM(O24:O24)) -> 224 | ... Q25: =SUM(Q21+SUM(Q24:Q24)) -> 486 | S25: =SUM(S21+SUM(S24:S24)) -> -33 | T25: =SUM(T21+SUM(T24:T24)) -> 776 | U25: =SUM(U21+SUM(U24:U24)) -> -4296 | V25: =SUM(V21+SUM(V24:V24)) -> -4589 | W25: =SUM(W21+SUM(W24:W24)) -> -4877 | X25: =SUM(X21+SUM(X24:X24)) -> -3922 | Y25: =SUM(Y21+SUM(Y24:Y24)) -> 1781 | AA25: =SUM(Y25/U25)-1 -> -1.4145717
B26: EBITDA Margin (%) | C26: =C25/C10 -> 0.2339257 | D26: =D25/D10 -> 0.090203621 | E26: =E25/E10 -> -0.0011129098 | F26: =F25/F10 -> -0.16694622 | H26: =H25/H10 -> -0.15498968 | I26: =I25/I10 -> -0.019038866 | J26: =J25/J10 -> 0.10178046 | K26: =K25/K10 -> 0.067033255 | L26: =L25/L10 -> -0.041249187 | M26: =M25/M10 -> -0.76574196 | N26: =N25/N10 -> 0.064329223 | O26: =O25/O10 -> 0.028056112 | ... Q26: =Q25/Q10 -> 0.070959264 | S26: =S25/S10 -> -0.0011129098 | T26: =T25/T10 -> 0.025804735 | U26: =U25/U10 -> -0.14677645 | V26: =V25/V10 -> -0.15897045 | W26: =W25/W10 -> -0.16694622 | X26: =X25/X10 -> -0.13655989 | Y26: =Y25/Y10 -> 0.061934901 | AA26: =SUM(Y26-U26)*10000 -> 2087.1135
B28: (+) Stock-based compensation (SBC) | C28: ='Historical Financials'!C116 -> 192 | D28: ='Historical Financials'!D116 -> 172 | E28: ='Historical Financials'!E116 -> 177 | F28: ='Historical Financials'!F116 -> 245 | H28: ='Historical Financials'!H116 -> 39 | I28: ='Historical Financials'!I116 -> 49 | J28: ='Historical Financials'!J116 -> 43 | K28: ='Historical Financials'!K116 -> 46 | L28: ='Historical Financials'!L116 -> 47 | M28: ='Historical Financials'!M116 -> 62 | N28: ='Historical Financials'!N116 -> 66 | O28: ='Historical Financials'!O116 -> 70 | ... Q28: ='Historical Financials'!Q116 -> 43 | S28: =SUM(H28:K28) -> 177 | T28: =SUM(I28:L28) -> 185 | U28: =SUM(J28:M28) -> 198 | V28: =SUM(K28:N28) -> 221 | W28: =SUM(L28:O28) -> 245 | X28: =SUM(M28:P28) -> 242 | Y28: =SUM(N28:Q28) -> 223 | AA28: =SUM(Y28/U28)-1 -> 0.12626263
B29: (+) Impairment charges | C29: =-C18 -> 0 | D29: =-D18 -> 27 | E29: =-E18 -> 83 | F29: =-F18 -> 6130 | H29: =-H18 -> 0 | I29: =-I18 -> 0 | J29: =-J18 -> 0 | K29: =-K18 -> 83 | L29: =-L18 -> 186 | M29: =-M18 -> 5996 | N29: =-N18 -> 104 | O29: =-O18 -> -156 | ... Q29: =-Q18 -> 157 | S29: =SUM(H29:K29) -> 83 | T29: =SUM(I29:L29) -> 269 | U29: =SUM(J29:M29) -> 6265 | V29: =SUM(K29:N29) -> 6369 | W29: =SUM(L29:O29) -> 6130 | X29: =SUM(M29:P29) -> 5944 | Y29: =SUM(N29:Q29) -> 105 | AA29: =SUM(Y29/U29)-1 -> -0.98324022
B30: (+) Restructuring, transaction-related items, and other corporate matters | C30: =-C19 -> 100 | D30: =-D19 -> 585 | E30: =-E19 -> -31 | F30: =-F19 -> 747 | H30: =-H19 -> 0 | I30: =-I19 -> 54 | J30: =-J19 -> -10 | K30: =-K19 -> -75 | L30: =-L19 -> 0 | M30: =-M19 -> 88 | N30: =-N19 -> 321 | O30: =-O19 -> 338 | ... Q30: =-Q19 -> 181 | S30: =SUM(H30:K30) -> -31 | T30: =SUM(I30:L30) -> -31 | U30: =SUM(J30:M30) -> 3 | V30: =SUM(K30:N30) -> 334 | W30: =SUM(L30:O30) -> 747 | X30: =SUM(M30:P30) -> 832 | Y30: =SUM(N30:Q30) -> 925 | AA30: =SUM(Y30/U30)-1 -> 307.33333
B31: (+) Gains on dispositions | C31: =-C20 -> -2343 | D31: =-D20 -> -56 | E31: =-E20 -> 0 | F31: =-F20 -> 0 | H31: =-H20 -> 0 | I31: =-I20 -> 0 | J31: =-J20 -> 0 | K31: =-K20 -> 0 | L31: =-L20 -> 0 | M31: =-M20 -> 0 | N31: =-N20 -> 0 | O31: =-O20 -> 0 | ... Q31: =-Q20 -> 0 | S31: =SUM(H31:K31) -> 0 | T31: =SUM(I31:L31) -> 0 | U31: =SUM(J31:M31) -> 0 | V31: =SUM(K31:N31) -> 0 | W31: =SUM(L31:O31) -> 0 | X31: =SUM(M31:P31) -> -35 | Y31: =SUM(N31:Q31) -> -35 | AA31: =SUM(Y31/U31)-1 -> #DIV/0!
B32: Adj. EBITDA | C32: =+SUM(C25+SUM(C28:C28)) -> 6879 | D32: =+SUM(D25+SUM(D28:D28)) -> 2892 | E32: =+SUM(E25+SUM(E28:E28)) -> 144 | F32: =+SUM(F25+SUM(F28:F28)) -> -4632 | H32: =+SUM(H25+SUM(H28:H28)) -> -1087 | I32: =+SUM(I25+SUM(I28:I28)) -> -96 | J32: =+SUM(J25+SUM(J28:J28)) -> 769 | K32: =+SUM(K25+SUM(K28:K28)) -> 558 | L32: =+SUM(L25+SUM(L28:L28)) -> -270 | M32: =+SUM(M25+SUM(M28:M28)) -> -5155 | N32: =+SUM(N25+SUM(N28:N28)) -> 499 | O32: =+SUM(O25+SUM(O28:O28)) -> 294 | ... Q32: =+SUM(Q25+SUM(Q28:Q28)) -> 529 | S32: =+SUM(S25+SUM(S28:S28)) -> 144 | T32: =+SUM(T25+SUM(T28:T28)) -> 961 | U32: =+SUM(U25+SUM(U28:U28)) -> -4098 | V32: =+SUM(V25+SUM(V28:V28)) -> -4368 | W32: =+SUM(W25+SUM(W28:W28)) -> -4632 | X32: =+SUM(X25+SUM(X28:X28)) -> -3680 | Y32: =+SUM(Y25+SUM(Y28:Y28)) -> 2004 | AA32: =SUM(Y32/U32)-1 -> -1.489019
B33: Adj. EBITDA Margin (%) | C33: =C32/C10 -> 0.24064227 | D33: =D32/D10 -> 0.095907674 | E33: =E32/E10 -> 0.0048563335 | F33: =F32/F10 -> -0.15855955 | H33: =H32/H10 -> -0.14962147 | I33: =I32/I10 -> -0.012605042 | J33: =J32/J10 -> 0.10780878 | K33: =K32/K10 -> 0.073055774 | L33: =L32/L10 -> -0.035133377 | M33: =M32/M10 -> -0.75664171 | N33: =N32/N10 -> 0.074134601 | O33: =O32/O10 -> 0.036823647 | ... Q33: =Q32/Q10 -> 0.077237553 | S33: =S32/S10 -> 0.0048563335 | T33: =T32/T10 -> 0.031956637 | U33: =U32/U10 -> -0.14001162 | V33: =V32/V10 -> -0.15131465 | W33: =W32/W10 -> -0.15855955 | X33: =X32/X10 -> -0.1281337 | Y33: =Y32/Y10 -> 0.069689804 | AA33: =SUM(Y33-U33)*10000 -> 2097.0142
B35: (-) Capital Expenditures | C35: ='Historical Financials'!C128 -> -354 | D35: ='Historical Financials'!D128 -> -358 | E35: ='Historical Financials'!E128 -> -328 | F35: ='Historical Financials'!F128 -> -263 | H35: ='Historical Financials'!H128 -> -71 | I35: ='Historical Financials'!I128 -> -69 | J35: ='Historical Financials'!J128 -> -73 | K35: ='Historical Financials'!K128 -> -115 | L35: ='Historical Financials'!L128 -> -51 | M35: ='Historical Financials'!M128 -> -49 | N35: ='Historical Financials'!N128 -> -51 | O35: ='Historical Financials'!O128 -> -112 | ... Q35: ='Historical Financials'!Q128 -> -45 | S35: =SUM(H35:K35) -> -328 | T35: =SUM(I35:L35) -> -308 | U35: =SUM(J35:M35) -> -288 | V35: =SUM(K35:N35) -> -266 | W35: =SUM(L35:O35) -> -263 | X35: =SUM(M35:P35) -> -269 | Y35: =SUM(N35:Q35) -> -265 | AA35: =SUM(Y35/U35)-1 -> -0.079861111
B36: (-) Cash Taxes | C36: =-'Historical Financials'!C159 -> -334 | D36: =-'Historical Financials'!D159 -> -73 | E36: =-'Historical Financials'!E159 -> -107 | F36: =-'Historical Financials'!F159 -> -184 | H36: =-'Historical Financials'!H159 -> 6 | I36: =-'Historical Financials'!I159 -> -76 | J36: =-'Historical Financials'!J159 -> 68 | K36: =-'Historical Financials'!K159 -> -71 | L36: =-'Historical Financials'!L159 -> -27 | M36: =-'Historical Financials'!M159 -> -147 | N36: =-'Historical Financials'!N159 -> 106 | O36: =-'Historical Financials'!O159 -> -39 | ... Q36: =-'Historical Financials'!Q159 -> -153 | S36: =SUM(H36:K36) -> -73 | T36: =SUM(I36:L36) -> -106 | U36: =SUM(J36:M36) -> -177 | V36: =SUM(K36:N36) -> -139 | W36: =SUM(L36:O36) -> -107 | X36: =SUM(M36:P36) -> -107 | Y36: =SUM(N36:Q36) -> -113 | AA36: =SUM(Y36/U36)-1 -> -0.36158192
B37: (-) Cash Interest | C37: =-'Historical Financials'!C158 -> -970 | D37: =-'Historical Financials'!D158 -> -920 | E37: =-'Historical Financials'!E158 -> -901 | F37: =-'Historical Financials'!F158 -> -833 | H37: =-'Historical Financials'!H158 -> -275 | I37: =-'Historical Financials'!I158 -> -174 | J37: =-'Historical Financials'!J158 -> -247 | K37: =-'Historical Financials'!K158 -> -224 | L37: =-'Historical Financials'!L158 -> -229 | M37: =-'Historical Financials'!M158 -> -189 | N37: =-'Historical Financials'!N158 -> -258 | O37: =-'Historical Financials'!O158 -> -225 | ... Q37: =-'Historical Financials'!Q158 -> -147 | S37: =SUM(H37:K37) -> -920 | T37: =SUM(I37:L37) -> -874 | U37: =SUM(J37:M37) -> -889 | V37: =SUM(K37:N37) -> -900 | W37: =SUM(L37:O37) -> -901 | X37: =SUM(M37:P37) -> -936 | Y37: =SUM(N37:Q37) -> -894 | AA37: =SUM(Y37/U37)-1 -> 0.005624297
B38: (-) Common Dividends | C38: ='Historical Financials'!C137 -> -30 | D38: ='Historical Financials'!D137 -> -58 | E38: ='Historical Financials'!E137 -> -58 | F38: ='Historical Financials'!F137 -> -29 | H38: ='Historical Financials'!H137 -> -14 | I38: ='Historical Financials'!I137 -> -15 | J38: ='Historical Financials'!J137 -> -14 | K38: ='Historical Financials'!K137 -> -15 | L38: ='Historical Financials'!L137 -> -14 | M38: ='Historical Financials'!M137 -> -15 | N38: ='Historical Financials'!N137 -> 0 | O38: ='Historical Financials'!O137 -> 0 | ... Q38: ='Historical Financials'!Q137 -> 0 | S38: =SUM(H38:K38) -> -58 | T38: =SUM(I38:L38) -> -58 | U38: =SUM(J38:M38) -> -58 | V38: =SUM(K38:N38) -> -44 | W38: =SUM(L38:O38) -> -29 | X38: =SUM(M38:P38) -> -15 | Y38: =SUM(N38:Q38) -> 0
B39: (-) Preferred Dividends | C39: ='Historical Financials'!C138 -> -617 | D39: ='Historical Financials'!D138 -> -631 | E39: ='Historical Financials'!E138 -> -389 | F39: ='Historical Financials'!F138 -> -139 | H39: ='Historical Financials'!H138 -> -166 | I39: ='Historical Financials'!I138 -> -151 | J39: ='Historical Financials'!J138 -> -34 | K39: ='Historical Financials'!K138 -> -38 | L39: ='Historical Financials'!L138 -> -35 | M39: ='Historical Financials'!M138 -> -33 | N39: ='Historical Financials'!N138 -> -34 | O39: ='Historical Financials'!O138 -> -37 | ... Q39: ='Historical Financials'!Q138 -> -34 | S39: =SUM(H39:K39) -> -389 | T39: =SUM(I39:L39) -> -258 | U39: =SUM(J39:M39) -> -140 | V39: =SUM(K39:N39) -> -140 | W39: =SUM(L39:O39) -> -139 | X39: =SUM(M39:P39) -> -140 | Y39: =SUM(N39:Q39) -> -141 | AA39: =SUM(Y39/U39)-1 -> 0.0071428571
B40: (-) Payments to noncontrolling interests | C40: ='Historical Financials'!C140 -> -235 | D40: ='Historical Financials'!D140 -> -218 | E40: ='Historical Financials'!E140 -> -93 | F40: ='Historical Financials'!F140 -> -127 | H40: ='Historical Financials'!H140 -> -89 | I40: ='Historical Financials'!I140 -> -4 | J40: ='Historical Financials'!J140 -> -4 | K40: ='Historical Financials'!K140 -> 4 | L40: ='Historical Financials'!L140 -> -94 | M40: ='Historical Financials'!M140 -> -3 | N40: ='Historical Financials'!N140 -> -23 | O40: ='Historical Financials'!O140 -> -7 | ... Q40: ='Historical Financials'!Q140 -> 12 | S40: =SUM(H40:K40) -> -93 | T40: =SUM(I40:L40) -> -98 | U40: =SUM(J40:M40) -> -97 | V40: =SUM(K40:N40) -> -116 | W40: =SUM(L40:O40) -> -127 | X40: =SUM(M40:P40) -> -110 | Y40: =SUM(N40:Q40) -> -95 | AA40: =SUM(Y40/U40)-1 -> -0.020618557
B41: (+/-) Changes in NWC | C41: ='Historical Financials'!C123 -> -15738 | D41: ='Historical Financials'!D123 -> -16520 | E41: ='Historical Financials'!E123 -> -15456 | F41: ='Historical Financials'!F123 -> -14776 | H41: ='Historical Financials'!H123 -> -778 | I41: ='Historical Financials'!I123 -> -420 | J41: ='Historical Financials'!J123 -> -28 | K41: ='Historical Financials'!K123 -> -14230 | L41: ='Historical Financials'!L123 -> -315 | M41: ='Historical Financials'!M123 -> -412 | N41: ='Historical Financials'!N123 -> -48 | O41: ='Historical Financials'!O123 -> -14001 | ... Q41: ='Historical Financials'!Q123 -> -233 | S41: =SUM(H41:K41) -> -15456 | T41: =SUM(I41:L41) -> -14993 | U41: =SUM(J41:M41) -> -14985 | V41: =SUM(K41:N41) -> -15005 | W41: =SUM(L41:O41) -> -14776 | X41: =SUM(M41:P41) -> -14657 | Y41: =SUM(N41:Q41) -> -14478 | AA41: =SUM(Y41/U41)-1 -> -0.033833834
B42: Discretionary Cash-Flows | C42: =SUM(C32+SUM(C35:C41)) -> -11399 | D42: =SUM(D32+SUM(D35:D41)) -> -15886 | E42: =SUM(E32+SUM(E35:E41)) -> -17188 | F42: =SUM(F32+SUM(F35:F41)) -> -20983 | H42: =SUM(H32+SUM(H35:H41)) -> -2474 | I42: =SUM(I32+SUM(I35:I41)) -> -1005 | J42: =SUM(J32+SUM(J35:J41)) -> 437 | K42: =SUM(K32+SUM(K35:K41)) -> -14131 | L42: =SUM(L32+SUM(L35:L41)) -> -1035 | M42: =SUM(M32+SUM(M35:M41)) -> -6003 | N42: =SUM(N32+SUM(N35:N41)) -> 191 | O42: =SUM(O32+SUM(O35:O41)) -> -14127 | ... Q42: =SUM(Q32+SUM(Q35:Q41)) -> -71 | S42: =SUM(S32+SUM(S35:S41)) -> -17173 | T42: =SUM(T32+SUM(T35:T41)) -> -15734 | U42: =SUM(U32+SUM(U35:U41)) -> -20732 | V42: =SUM(V32+SUM(V35:V41)) -> -20978 | W42: =SUM(W32+SUM(W35:W41)) -> -20974 | X42: =SUM(X32+SUM(X35:X41)) -> -19914 | Y42: =SUM(Y32+SUM(Y35:Y41)) -> -13982 | AA42: =SUM(Y42/U42)-1 -> -0.32558364
B44: (+/-) Proceeds from Dispositions / (Acquisitions) | C44: ='Historical Financials'!C129 -> 2974 | D44: ='Historical Financials'!D129 -> 95 | E44: ='Historical Financials'!E129 -> 71 | F44: ='Historical Financials'!F129 -> 554 | H44: ='Historical Financials'!H129 -> 0 | I44: ='Historical Financials'!I129 -> 0 | J44: ='Historical Financials'!J129 -> 0 | K44: ='Historical Financials'!K129 -> 71 | L44: ='Historical Financials'!L129 -> 0 | M44: ='Historical Financials'!M129 -> 0 | N44: ='Historical Financials'!N129 -> 0 | O44: ='Historical Financials'!O129 -> 554 | ... Q44: ='Historical Financials'!Q129 -> 5 | S44: =SUM(H44:K44) -> 71 | T44: =SUM(I44:L44) -> 71 | U44: =SUM(J44:M44) -> 71 | V44: =SUM(K44:N44) -> 71 | W44: =SUM(L44:O44) -> 554 | X44: =SUM(M44:P44) -> 615 | Y44: =SUM(N44:Q44) -> 620
B45: (+/-) Equity in loss of investee companies, net of tax and distributions | C45: ='Historical Financials'!C120 -> 96 | D45: ='Historical Financials'!D120 -> 207 | E45: ='Historical Financials'!E120 -> 363 | F45: ='Historical Financials'!F120 -> 304 | H45: ='Historical Financials'!H120 -> 75 | I45: ='Historical Financials'!I120 -> 109 | J45: ='Historical Financials'!J120 -> 75 | K45: ='Historical Financials'!K120 -> 104 | L45: ='Historical Financials'!L120 -> 90 | M45: ='Historical Financials'!M120 -> 78 | N45: ='Historical Financials'!N120 -> 60 | O45: ='Historical Financials'!O120 -> 76 | ... Q45: ='Historical Financials'!Q120 -> 68 | S45: =SUM(H45:K45) -> 363 | T45: =SUM(I45:L45) -> 378 | U45: =SUM(J45:M45) -> 347 | V45: =SUM(K45:N45) -> 332 | W45: =SUM(L45:O45) -> 304 | X45: =SUM(M45:P45) -> 287 | Y45: =SUM(N45:Q45) -> 277
B46: (+/-) Amortization of content costs and participation and residuals expense | C46: ='Historical Financials'!C114 -> 13649 | D46: ='Historical Financials'!D114 -> 14951 | E46: ='Historical Financials'!E114 -> 14713 | F46: ='Historical Financials'!F114 -> 13888 | H46: ='Historical Financials'!H114 -> 0 | I46: ='Historical Financials'!I114 -> 0 | J46: ='Historical Financials'!J114 -> 0 | K46: ='Historical Financials'!K114 -> 14713 | L46: ='Historical Financials'!L114 -> 0 | M46: ='Historical Financials'!M114 -> 0 | N46: ='Historical Financials'!N114 -> 0 | O46: ='Historical Financials'!O114 -> 13888 | ... Q46: ='Historical Financials'!Q114 -> 0 | S46: =SUM(H46:K46) -> 14713 | T46: =SUM(I46:L46) -> 14713 | U46: =SUM(J46:M46) -> 14713 | V46: =SUM(K46:N46) -> 14713 | W46: =SUM(L46:O46) -> 13888 | X46: =SUM(M46:P46) -> 13888 | Y46: =SUM(N46:Q46) -> 13888
B47: (+/-) Issuances from Debt / (Repayment) | C47: =SUM('Historical Financials'!C135:C136) -> -2172 | D47: =SUM('Historical Financials'!D135:D136) -> -2002 | E47: =SUM('Historical Financials'!E135:E136) -> -1232 | F47: =SUM('Historical Financials'!F135:F136) -> -126 | H47: =SUM('Historical Financials'!H135:H136) -> 3 | I47: =SUM('Historical Financials'!I135:I136) -> -58 | J47: =SUM('Historical Financials'!J135:J136) -> -139 | K47: =SUM('Historical Financials'!K135:K136) -> -1038 | L47: =SUM('Historical Financials'!L135:L136) -> 0 | M47: =SUM('Historical Financials'!M135:M136) -> 0 | N47: =SUM('Historical Financials'!N135:N136) -> 0 | O47: =SUM('Historical Financials'!O135:O136) -> -126 | ... Q47: =SUM('Historical Financials'!Q135:Q136) -> 0 | S47: =SUM(H47:K47) -> -1232 | T47: =SUM(I47:L47) -> -1235 | U47: =SUM(J47:M47) -> -1177 | V47: =SUM(K47:N47) -> -1038 | W47: =SUM(L47:O47) -> -126 | X47: =SUM(M47:P47) -> -126 | Y47: =SUM(N47:Q47) -> -126
B48: (+/-) Net Equity Issuances / (Repurchases) | C48: ='Historical Financials'!C141 -> 3063 | D48: ='Historical Financials'!D141 -> 0 | E48: ='Historical Financials'!E141 -> 0 | F48: ='Historical Financials'!F141 -> 0 | H48: ='Historical Financials'!H141 -> 0 | I48: ='Historical Financials'!I141 -> 0 | J48: ='Historical Financials'!J141 -> 0 | K48: ='Historical Financials'!K141 -> 0 | L48: ='Historical Financials'!L141 -> 0 | M48: ='Historical Financials'!M141 -> 0 | N48: ='Historical Financials'!N141 -> 0 | O48: ='Historical Financials'!O141 -> 0 | ... Q48: ='Historical Financials'!Q141 -> 0 | S48: =SUM(H48:K48) -> 0 | T48: =SUM(I48:L48) -> 0 | U48: =SUM(J48:M48) -> 0 | V48: =SUM(K48:N48) -> 0 | W48: =SUM(L48:O48) -> 0 | X48: =SUM(M48:P48) -> 0 | Y48: =SUM(N48:Q48) -> 0
B49: (+/-) Other | D49: =SUM(D54)-SUM(C54)-SUM(D42:D48) -> -747 | E49: =SUM(E54)-SUM(D54)-SUM(E42:E48) -> 2848 | F49: =SUM(F54)-SUM(E54)-SUM(F42:F48) -> 6564 | H49: =SUM(H54)-SUM(D54)-SUM(H42:H48) -> 1620 | I49: =SUM(I54)-SUM(H54)-SUM(I42:I48) -> 559 | J49: =SUM(J54)-SUM(I54)-SUM(J42:J48) -> -283 | K49: =SUM(K54)-SUM(J54)-SUM(K42:K48) -> 937 | L49: =SUM(L54)-SUM(K54)-SUM(L42:L48) -> 869 | M49: =SUM(M54)-SUM(L54)-SUM(M42:M48) -> 5856 | N49: =SUM(N54)-SUM(M54)-SUM(N42:N48) -> -123 | O49: =SUM(O54)-SUM(N54)-SUM(O42:O48) -> -47 | P49: =SUM(P54)-SUM(O54)-SUM(P42:P48) -> -147 | Q49: =SUM(Q54)-SUM(P54)-SUM(Q42:Q48) -> 64 | S49: =SUM(H49:K49) -> 2833 | T49: =SUM(I49:L49) -> 2082 | U49: =SUM(J49:M49) -> 7379 | V49: =SUM(K49:N49) -> 7539 | W49: =SUM(L49:O49) -> 6555 | X49: =SUM(M49:P49) -> 5539 | Y49: =SUM(N49:Q49) -> -253
B50: Free-Cash Flows | C50: =SUM(C42+SUM(C44:C49)) -> 6211 | D50: =SUM(D42+SUM(D44:D49)) -> -3382 | E50: =SUM(E42+SUM(E44:E49)) -> -425 | F50: =SUM(F42+SUM(F44:F49)) -> 201 | H50: =SUM(H42+SUM(H44:H49)) -> -776 | I50: =SUM(I42+SUM(I44:I49)) -> -395 | J50: =SUM(J42+SUM(J44:J49)) -> 90 | K50: =SUM(K42+SUM(K44:K49)) -> 656 | L50: =SUM(L42+SUM(L44:L49)) -> -76 | M50: =SUM(M42+SUM(M44:M49)) -> -69 | N50: =SUM(N42+SUM(N44:N49)) -> 128 | O50: =SUM(O42+SUM(O44:O49)) -> 218 | ... Q50: =SUM(Q42+SUM(Q44:Q49)) -> 66 | S50: =SUM(S42+SUM(S44:S49)) -> -425 | T50: =SUM(T42+SUM(T44:T49)) -> 275 | U50: =SUM(U42+SUM(U44:U49)) -> 601 | V50: =SUM(V42+SUM(V44:V49)) -> 639 | W50: =SUM(W42+SUM(W44:W49)) -> 201 | X50: =SUM(X42+SUM(X44:X49)) -> 289 | Y50: =SUM(Y42+SUM(Y44:Y49)) -> 424
B52: Capitalization
B54: Cash & Cash Equivelants | C54: ='Historical Financials'!C53 -> 6267 | D54: ='Historical Financials'!D53 -> 2885 | E54: ='Historical Financials'!E53 -> 2460 | F54: ='Historical Financials'!F53 -> 2661 | H54: ='Historical Financials'!H53 -> 2109 | I54: ='Historical Financials'!I53 -> 1714 | J54: ='Historical Financials'!J53 -> 1804 | K54: ='Historical Financials'!K53 -> 2460 | L54: ='Historical Financials'!L53 -> 2384 | M54: ='Historical Financials'!M53 -> 2315 | N54: ='Historical Financials'!N53 -> 2443 | O54: ='Historical Financials'!O53 -> 2661 | ... Q54: ='Historical Financials'!Q53 -> 2739 | S54: =K54 -> 2460 | T54: =L54 -> 2384 | U54: =M54 -> 2315 | V54: =N54 -> 2443 | W54: =O54 -> 2661 | X54: =P54 -> 2673 | Y54: =Q54 -> 2739
B55: $3.5Bn RCF (CP Backstop) | C55: 3500 | D55: 3500 | E55: 3500 | F55: 3500 | H55: 3500 | I55: 3500 | J55: 3500 | K55: 3500 | L55: 3500 | M55: 3500 | N55: 3500 | O55: 3500 | P55: 3500 | Q55: 3500 | S55: =K55 -> 3500 | T55: =L55 -> 3500 | U55: =M55 -> 3500 | V55: =N55 -> 3500 | W55: =O55 -> 3500 | X55: =P55 -> 3500 | Y55: =Q55 -> 3500
B56: Total Liquidity | C56: =SUM(C54:C55) -> 9767 | D56: =SUM(D54:D55) -> 6385 | E56: =SUM(E54:E55) -> 5960 | F56: =SUM(F54:F55) -> 6161 | H56: =SUM(H54:H55) -> 5609 | I56: =SUM(I54:I55) -> 5214 | J56: =SUM(J54:J55) -> 5304 | K56: =SUM(K54:K55) -> 5960 | L56: =SUM(L54:L55) -> 5884 | M56: =SUM(M54:M55) -> 5815 | N56: =SUM(N54:N55) -> 5943 | O56: =SUM(O54:O55) -> 6161 | ... Q56: =SUM(Q54:Q55) -> 6239 | S56: =SUM(S54:S55) -> 5960 | T56: =SUM(T54:T55) -> 5884 | U56: =SUM(U54:U55) -> 5815 | V56: =SUM(V54:V55) -> 5943 | W56: =SUM(W54:W55) -> 6161 | X56: =SUM(X54:X55) -> 6173 | Y56: =SUM(Y54:Y55) -> 6239
B58: Balance Sheet Metrics:
B59: Receivables, net | C59: ='Historical Financials'!C54 -> 6984 | D59: ='Historical Financials'!D54 -> 7412 | E59: ='Historical Financials'!E54 -> 7115 | F59: ='Historical Financials'!F54 -> 6920 | H59: ='Historical Financials'!H54 -> 7448 | I59: ='Historical Financials'!I54 -> 7186 | J59: ='Historical Financials'!J54 -> 6939 | K59: ='Historical Financials'!K54 -> 7115 | L59: ='Historical Financials'!L54 -> 7096 | M59: ='Historical Financials'!M54 -> 6545 | N59: ='Historical Financials'!N54 -> 6327 | O59: ='Historical Financials'!O54 -> 6920 | ... Q59: ='Historical Financials'!Q54 -> 6291 | S59: =K59 -> 7115 | T59: =L59 -> 7096 | U59: =M59 -> 6545 | V59: =N59 -> 6327 | W59: =O59 -> 6920 | X59: =P59 -> 6835 | Y59: =Q59 -> 6291
B60: Programming and other inventory | C60: ='Historical Financials'!C55+'Historical Financials'!C61 -> 14862 | D60: ='Historical Financials'!D55+'Historical Financials'!D61 -> 17620 | E60: ='Historical Financials'!E55+'Historical Financials'!E61 -> 15265 | F60: ='Historical Financials'!F55+'Historical Financials'!F61 -> 15353 | H60: ='Historical Financials'!H55+'Historical Financials'!H61 -> 16777 | I60: ='Historical Financials'!I55+'Historical Financials'!I61 -> 16135 | J60: ='Historical Financials'!J55+'Historical Financials'!J61 -> 15598 | K60: ='Historical Financials'!K55+'Historical Financials'!K61 -> 15265 | L60: ='Historical Financials'!L55+'Historical Financials'!L61 -> 14312 | M60: ='Historical Financials'!M55+'Historical Financials'!M61 -> 14994 | N60: ='Historical Financials'!N55+'Historical Financials'!N61 -> 15612 | O60: ='Historical Financials'!O55+'Historical Financials'!O61 -> 15353 | ... Q60: ='Historical Financials'!Q55+'Historical Financials'!Q61 -> 15331 | S60: =K60 -> 15265 | T60: =L60 -> 14312 | U60: =M60 -> 14994 | V60: =N60 -> 15612 | W60: =O60 -> 15353 | X60: =P60 -> 15086 | Y60: =Q60 -> 15331
B61: Property and equipment, net | C61: ='Historical Financials'!C60 -> 1736 | D61: ='Historical Financials'!D60 -> 1762 | E61: ='Historical Financials'!E60 -> 1666 | F61: ='Historical Financials'!F60 -> 1566 | H61: ='Historical Financials'!H60 -> 1718 | I61: ='Historical Financials'!I60 -> 1689 | J61: ='Historical Financials'!J60 -> 1668 | K61: ='Historical Financials'!K60 -> 1666 | L61: ='Historical Financials'!L60 -> 1612 | M61: ='Historical Financials'!M60 -> 1567 | N61: ='Historical Financials'!N60 -> 1545 | O61: ='Historical Financials'!O60 -> 1566 | ... Q61: ='Historical Financials'!Q60 -> 1494 | S61: =K61 -> 1666 | T61: =L61 -> 1612 | U61: =M61 -> 1567 | V61: =N61 -> 1545 | W61: =O61 -> 1566 | X61: =P61 -> 1519 | Y61: =Q61 -> 1494
B62: Accounts payable | C62: ='Historical Financials'!C70 -> 800 | D62: ='Historical Financials'!D70 -> 1403 | E62: ='Historical Financials'!E70 -> 1100 | F62: ='Historical Financials'!F70 -> 953 | H62: ='Historical Financials'!H70 -> 1235 | I62: ='Historical Financials'!I70 -> 1210 | J62: ='Historical Financials'!J70 -> 953 | K62: ='Historical Financials'!K70 -> 1100 | L62: ='Historical Financials'!L70 -> 787 | M62: ='Historical Financials'!M70 -> 826 | N62: ='Historical Financials'!N70 -> 826 | O62: ='Historical Financials'!O70 -> 953 | ... Q62: ='Historical Financials'!Q70 -> 822 | S62: =K62 -> 1100 | T62: =L62 -> 787 | U62: =M62 -> 826 | V62: =N62 -> 826 | W62: =O62 -> 953 | X62: =P62 -> 735 | Y62: =Q62 -> 822
B63: Deferred revenues | C63: ='Historical Financials'!C74 -> 1091 | D63: ='Historical Financials'!D74 -> 973 | E63: ='Historical Financials'!E74 -> 746 | F63: ='Historical Financials'!F74 -> 825 | H63: ='Historical Financials'!H74 -> 1092 | I63: ='Historical Financials'!I74 -> 921 | J63: ='Historical Financials'!J74 -> 848 | K63: ='Historical Financials'!K74 -> 746 | L63: ='Historical Financials'!L74 -> 671 | M63: ='Historical Financials'!M74 -> 708 | N63: ='Historical Financials'!N74 -> 824 | O63: ='Historical Financials'!O74 -> 825 | ... Q63: ='Historical Financials'!Q74 -> 753 | S63: =K63 -> 746 | T63: =L63 -> 671 | U63: =M63 -> 708 | V63: =N63 -> 824 | W63: =O63 -> 825 | X63: =P63 -> 765 | Y63: =Q63 -> 753
B64: Current Liabilities | C64: ='Historical Financials'!C77 -> 9479 | D64: ='Historical Financials'!D77 -> 11191 | E64: ='Historical Financials'!E77 -> 9656 | F64: ='Historical Financials'!F77 -> 9631 | H64: ='Historical Financials'!H77 -> 11295 | I64: ='Historical Financials'!I77 -> 10670 | J64: ='Historical Financials'!J77 -> 10050 | K64: ='Historical Financials'!K77 -> 9656 | L64: ='Historical Financials'!L77 -> 9244 | M64: ='Historical Financials'!M77 -> 9006 | N64: ='Historical Financials'!N77 -> 9354 | O64: ='Historical Financials'!O77 -> 9631 | ... Q64: ='Historical Financials'!Q77 -> 8730 | S64: =K64 -> 9656 | T64: =L64 -> 9244 | U64: =M64 -> 9006 | V64: =N64 -> 9354 | W64: =O64 -> 9631 | X64: =P64 -> 9292 | Y64: =Q64 -> 8730
B65: Total Liabilities | C65: ='Historical Financials'!C87 -> 35650 | D65: ='Historical Financials'!D87 -> 34787 | E65: ='Historical Financials'!E87 -> 30493 | F65: ='Historical Financials'!F87 -> 29390 | H65: ='Historical Financials'!H87 -> 34218 | I65: ='Historical Financials'!I87 -> 33204 | J65: ='Historical Financials'!J87 -> 32262 | K65: ='Historical Financials'!K87 -> 30493 | L65: ='Historical Financials'!L87 -> 29690 | M65: ='Historical Financials'!M87 -> 28944 | N65: ='Historical Financials'!N87 -> 29175 | O65: ='Historical Financials'!O87 -> 29390 | ... Q65: ='Historical Financials'!Q87 -> 27815 | S65: =K65 -> 30493 | T65: =L65 -> 29690 | U65: =M65 -> 28944 | V65: =N65 -> 29175 | W65: =O65 -> 29390 | X65: =P65 -> 28468 | Y65: =Q65 -> 27815
B67: Summary Debt:
B68: CPLTD | C68: ='Historical Financials'!C75 -> 11 | D68: ='Historical Financials'!D75 -> 239 | E68: ='Historical Financials'!E75 -> 1 | F68: ='Historical Financials'!F75 -> 0 | H68: ='Historical Financials'!H75 -> 240 | I68: ='Historical Financials'!I75 -> 180 | J68: ='Historical Financials'!J75 -> 38 | K68: ='Historical Financials'!K75 -> 1 | L68: ='Historical Financials'!L75 -> 1 | M68: ='Historical Financials'!M75 -> 126 | N68: ='Historical Financials'!N75 -> 125 | O68: ='Historical Financials'!O75 -> 0 | ... Q68: ='Historical Financials'!Q75 -> 346 | S68: =K68 -> 1 | T68: =L68 -> 1 | U68: =M68 -> 126 | V68: =N68 -> 125 | W68: =O68 -> 0 | X68: =P68 -> 346 | Y68: =Q68 -> 346
B69: LTD | C69: ='Historical Financials'!C80 -> 17698 | D69: ='Historical Financials'!D80 -> 15607 | E69: ='Historical Financials'!E80 -> 14601 | F69: ='Historical Financials'!F80 -> 14501 | H69: ='Historical Financials'!H80 -> 15613 | I69: ='Historical Financials'!I80 -> 15620 | J69: ='Historical Financials'!J80 -> 15627 | K69: ='Historical Financials'!K80 -> 14601 | L69: ='Historical Financials'!L80 -> 14607 | M69: ='Historical Financials'!M80 -> 14488 | N69: ='Historical Financials'!N80 -> 14495 | O69: ='Historical Financials'!O80 -> 14501 | ... Q69: ='Historical Financials'!Q80 -> 14168 | S69: =K69 -> 14601 | T69: =L69 -> 14607 | U69: =M69 -> 14488 | V69: =N69 -> 14495 | W69: =O69 -> 14501 | X69: =P69 -> 14161 | Y69: =Q69 -> 14168
B71: Aggregate Debt Issuances | C71: =SUM(C68:C69) -> 17709 | D71: =SUM(D68:D69) -> 15846 | E71: =SUM(E68:E69) -> 14602 | F71: =SUM(F68:F69) -> 14501 | H71: =SUM(H68:H69) -> 15853 | I71: =SUM(I68:I69) -> 15800 | J71: =SUM(J68:J69) -> 15665 | K71: =SUM(K68:K69) -> 14602 | L71: =SUM(L68:L69) -> 14608 | M71: =SUM(M68:M69) -> 14614 | N71: =SUM(N68:N69) -> 14620 | O71: =SUM(O68:O69) -> 14501 | ... Q71: =SUM(Q68:Q69) -> 14514 | S71: =K71 -> 14602 | T71: =L71 -> 14608 | U71: =M71 -> 14614 | V71: =N71 -> 14620 | W71: =O71 -> 14501 | X71: =P71 -> 14507 | Y71: =Q71 -> 14514
B72: Total Debt | C72: =SUM(C71:C71) -> 17709 | D72: =SUM(D71:D71) -> 15846 | E72: =SUM(E71:E71) -> 14602 | F72: =SUM(F71:F71) -> 14501 | H72: =SUM(H71:H71) -> 15853 | I72: =SUM(I71:I71) -> 15800 | J72: =SUM(J71:J71) -> 15665 | K72: =SUM(K71:K71) -> 14602 | L72: =SUM(L71:L71) -> 14608 | M72: =SUM(M71:M71) -> 14614 | N72: =SUM(N71:N71) -> 14620 | O72: =SUM(O71:O71) -> 14501 | ... Q72: =SUM(Q71:Q71) -> 14514 | S72: =SUM(S71:S71) -> 14602 | T72: =SUM(T71:T71) -> 14608 | U72: =SUM(U71:U71) -> 14614 | V72: =SUM(V71:V71) -> 14620 | W72: =SUM(W71:W71) -> 14501 | X72: =SUM(X71:X71) -> 14507 | Y72: =SUM(Y71:Y71) -> 14514
B74: Total Shareholder Equity | C74: ='Historical Financials'!C97 -> 22970 | D74: ='Historical Financials'!D97 -> 23606 | E74: ='Historical Financials'!E97 -> 23050 | F74: ='Historical Financials'!F97 -> 16782 | H74: ='Historical Financials'!H97 -> 22343 | I74: ='Historical Financials'!I97 -> 22157 | J74: ='Historical Financials'!J97 -> 22378 | K74: ='Historical Financials'!K97 -> 23050 | L74: ='Historical Financials'!L97 -> 22337 | M74: ='Historical Financials'!M97 -> 16946 | N74: ='Historical Financials'!N97 -> 17075 | O74: ='Historical Financials'!O97 -> 16782 | ... Q74: ='Historical Financials'!Q97 -> 17111 | S74: =K74 -> 23050 | T74: =L74 -> 22337 | U74: =M74 -> 16946 | V74: =N74 -> 17075 | W74: =O74 -> 16782 | X74: =P74 -> 16928 | Y74: =Q74 -> 17111
B75: Total Book Capitalization | C75: =SUM(C72:C74) -> 40679 | D75: =SUM(D72:D74) -> 39452 | E75: =SUM(E72:E74) -> 37652 | F75: =SUM(F72:F74) -> 31283 | H75: =SUM(H72:H74) -> 38196 | I75: =SUM(I72:I74) -> 37957 | J75: =SUM(J72:J74) -> 38043 | K75: =SUM(K72:K74) -> 37652 | L75: =SUM(L72:L74) -> 36945 | M75: =SUM(M72:M74) -> 31560 | N75: =SUM(N72:N74) -> 31695 | O75: =SUM(O72:O74) -> 31283 | ... Q75: =SUM(Q72:Q74) -> 31625 | S75: =SUM(S72:S74) -> 37652 | T75: =SUM(T72:T74) -> 36945 | U75: =SUM(U72:U74) -> 31560 | V75: =SUM(V72:V74) -> 31695 | W75: =SUM(W72:W74) -> 31283 | X75: =SUM(X72:X74) -> 31435 | Y75: =SUM(Y72:Y74) -> 31625
B77: Credit Metrics
B79: LTM Total Leverage | C79: =C72/C32 -> 2.5743567 | D79: =D72/D32 -> 5.4792531 | E79: =E72/E32 -> 101.40278 | F79: =F72/F32 -> -3.1306131 | K79: =SUM(K72/SUM(H32:K32)) -> 101.40278 | L79: =SUM(L72/SUM(I32:L32)) -> 15.200832 | M79: =SUM(M72/SUM(J32:M32)) -> -3.5661298 | N79: =SUM(N72/SUM(K32:N32)) -> -3.3470696 | O79: =SUM(O72/SUM(L32:O32)) -> -3.1306131 | P79: =SUM(P72/SUM(M32:P32)) -> -3.9421196 | Q79: =SUM(Q72/SUM(N32:Q32)) -> 7.242515 | S79: =S72/S32 -> 101.40278 | T79: =T72/T32 -> 15.200832 | U79: =U72/U32 -> -3.5661298 | V79: =V72/V32 -> -3.3470696 | W79: =W72/W32 -> -3.1306131 | X79: =X72/X32 -> -3.9421196 | Y79: =Y72/Y32 -> 7.242515
B80: LTM Net Leverage | C80: =SUM(C72-C54)/C32 -> 1.6633232 | D80: =SUM(D72-D54)/D32 -> 4.4816736 | E80: =SUM(E72-E54)/E32 -> 84.319444 | F80: =SUM(F72-F54)/F32 -> -2.5561313 | K80: =SUM(K72-K54)/SUM(H32:K32) -> 84.319444 | L80: =SUM(L72-L54)/SUM(I32:L32) -> 12.720083 | M80: =SUM(M72-M54)/SUM(J32:M32) -> -3.0012201 | N80: =SUM(N72-N54)/SUM(K32:N32) -> -2.7877747 | O80: =SUM(O72-O54)/SUM(L32:O32) -> -2.5561313 | P80: =SUM(P72-P54)/SUM(M32:P32) -> -3.2157609 | Q80: =SUM(Q72-Q54)/SUM(N32:Q32) -> 5.8757485 | S80: =SUM(S72-S54)/S32 -> 84.319444 | T80: =SUM(T72-T54)/T32 -> 12.720083 | U80: =SUM(U72-U54)/U32 -> -3.0012201 | V80: =SUM(V72-V54)/V32 -> -2.7877747 | W80: =SUM(W72-W54)/W32 -> -2.5561313 | X80: =SUM(X72-X54)/X32 -> -3.2157609 | Y80: =SUM(Y72-Y54)/Y32 -> 5.8757485
B81: LTM Interest Coverage | C81: =C32/-C37 -> 7.0917526 | D81: =D32/-D37 -> 3.1434783 | E81: =E32/-E37 -> 0.15982242 | F81: =F32/-F37 -> -5.5606242 | K81: {=SUM(H32:K32)/SUM(-H37:K37)} -> 0.15652174 | L81: {=SUM(I32:L32)/SUM(-I37:L37)} -> 1.0995423 | M81: {=SUM(J32:M32)/SUM(-J37:M37)} -> -4.6096738 | N81: {=SUM(K32:N32)/SUM(-K37:N37)} -> -4.8533333 | O81: {=SUM(L32:O32)/SUM(-L37:O37)} -> -5.1409545 | P81: {=SUM(M32:P32)/SUM(-M37:P37)} -> -3.9316239 | Q81: {=SUM(N32:Q32)/SUM(-N37:Q37)} -> 2.2416107 | S81: =S32/-S37 -> 0.15652174 | T81: =T32/-T37 -> 1.0995423 | U81: =U32/-U37 -> -4.6096738 | V81: =V32/-V37 -> -4.8533333 | W81: =W32/-W37 -> -5.1409545 | X81: =X32/-X37 -> -3.9316239 | Y81: =Y32/-Y37 -> 2.2416107
B82: LTM Debt Service Coverage | C82: {=SUM(C32+C35)/SUM(-C36:C37)} -> 5.0038344 | D82: {=SUM(D32+D35)/SUM(-D36:D37)} -> 2.551863 | E82: {=SUM(E32+E35)/SUM(-E36:E37)} -> -0.18253968 | F82: {=SUM(F32+F35)/SUM(-F36:F37)} -> -4.813176 | K82: {=SUM(H32:K32+H35:K35)/SUM(-H36:K37)} -> -0.18529708 | L82: {=SUM(I32:L32+I35:L35)/SUM(-I36:L37)} -> 0.66632653 | M82: {=SUM(J32:M32+J35:M35)/SUM(-J36:M37)} -> -4.1144465 | N82: {=SUM(K32:N32+K35:N35)/SUM(-K36:N37)} -> -4.4600577 | O82: {=SUM(L32:O32+L35:O35)/SUM(-L36:O37)} -> -4.8561508 | P82: {=SUM(M32:P32+M35:P35)/SUM(-M36:P37)} -> -3.7861937 | Q82: {=SUM(N32:Q32+N35:Q35)/SUM(-N36:Q37)} -> 1.7269116 | S82: {=SUM(S32+S35)/SUM(-S36:S37)} -> -0.18529708 | T82: {=SUM(T32+T35)/SUM(-T36:T37)} -> 0.66632653 | U82: {=SUM(U32+U35)/SUM(-U36:U37)} -> -4.1144465 | V82: {=SUM(V32+V35)/SUM(-V36:V37)} -> -4.4600577 | W82: {=SUM(W32+W35)/SUM(-W36:W37)} -> -4.8561508 | X82: {=SUM(X32+X35)/SUM(-X36:X37)} -> -3.7861937 | Y82: {=SUM(Y32+Y35)/SUM(-Y36:Y37)} -> 1.7269116
B83: LTM Fixed Charge Coverage | C83: {=SUM(C32)/SUM(-C35:C37)} -> 4.1489747 | D83: {=SUM(D32)/SUM(-D35:D37)} -> 2.1406366 | E83: {=SUM(E32)/SUM(-E35:E37)} -> 0.10778443 | F83: {=SUM(F32)/SUM(-F35:F37)} -> -3.61875 | K83: {=SUM(H32:K32)/SUM(-H35:K37)} -> 0.10900833 | L83: {=SUM(I32:L32)/SUM(-I35:L37)} -> 0.74611801 | M83: {=SUM(J32:M32)/SUM(-J35:M37)} -> -3.0265879 | N83: {=SUM(K32:N32)/SUM(-K35:N37)} -> -3.3471264 | O83: {=SUM(L32:O32)/SUM(-L35:O37)} -> -3.6443745 | P83: {=SUM(M32:P32)/SUM(-M35:P37)} -> -2.804878 | Q83: {=SUM(N32:Q32)/SUM(-N35:Q37)} -> 1.5754717 | S83: {=SUM(S32)/SUM(-S35:S37)} -> 0.10900833 | T83: {=SUM(T32)/SUM(-T35:T37)} -> 0.74611801 | U83: {=SUM(U32)/SUM(-U35:U37)} -> -3.0265879 | V83: {=SUM(V32)/SUM(-V35:V37)} -> -3.3471264 | W83: {=SUM(W32)/SUM(-W35:W37)} -> -3.6443745 | X83: {=SUM(X32)/SUM(-X35:X37)} -> -2.804878 | Y83: {=SUM(Y32)/SUM(-Y35:Y37)} -> 1.5754717
B84: Debt-to-Book Capitalization | C84: =C75/C72 -> 2.2970806 | D84: =D75/D72 -> 2.4897135 | E84: =E75/E72 -> 2.5785509 | F84: =F75/F72 -> 2.1572995 | K84: =K75/K72 -> 2.5785509 | L84: =L75/L72 -> 2.5290936 | M84: =M75/M72 -> 2.159573 | N84: =N75/N72 -> 2.1679207 | O84: =O75/O72 -> 2.1572995 | P84: =P75/P72 -> 2.166885 | Q84: =Q75/Q72 -> 2.1789307 | S84: =S75/S72 -> 2.5785509 | T84: =T75/T72 -> 2.5290936 | U84: =U75/U72 -> 2.159573 | V84: =V75/V72 -> 2.1679207 | W84: =W75/W72 -> 2.1572995 | X84: =X75/X72 -> 2.166885 | Y84: =Y75/Y72 -> 2.1789307
