Workbook

Sheet Cover
C12: Netflix, Inc. (NASDAQ: NFLX) Company Summary
C13: January 2026
C15: Scope | I15: Model Outputs
C16: Forecast horizon: | G16: 2020A-3031F | I16: Case Assumption: | M16: Base case
C17: Methods: | G17: DCF, Peer Comparables | I17: Target Price: | M17: TBD
C18: Valuation Weights: | G18: 70% DCF, 30% Peer Comparables | I18: Recommendation: | M18: TBD
C20: Company Info | I20: Business Snapshot
C21: Ticker: | G21: NFLX | I21: Primary platforms: | M21: iOS, macOS, iPadOS, watchOS, tvOS, visionOS
C22: Industry: | G22: Media & Entertainment / Streaming | I22: Hardware products: | M22: iPhone, Mac, iPad, Apple Watch, AirPods
C23: Headquarters: | G23: Los Gatos, California | I23: Services ecosystem: | M23: Store, Music, TV+, Arcade, Pay, iCloud, AppleCare
C24: Founded: | G24: 1997 (DVD), Streaming 2007 | I24: Installed base: | M24: >2.2B active devices (2025 est.)
C25: CEO: | G25: Ted Sarandos & Greg Peters (Co-CEOs) | I25: Revenue mix (FY2025): | M25: Hardware ~78% / Services ~22%
C26: CFO: | G26: Spencer Neumann | I26: Geographic exposure: | M26: Americas largest; China strategic
C27: Fiscal year end: | G27: December 31
C28: Employees: | G28: ≈13,000 (FY2025) | I28: Financial Profile
C29: Credit Ratings: | G29: S&P: BB+ / Moody’s: Ba1 / Fitch: BB+ | I29: Revenue CAGR (5yr): | M29: High-single to low-double digits
C30: Capital Structure: | G30: Term debt + content obligations; buybacks | I30: Gross Margins: | M30: ~40–45% consolidated
C31: Dividend Policy: | G31: No dividend | I31: OpEx Structure: | M31: Content > Tech > G&A
C32: Legal structure: | G32: C-Corporation (Delaware) | I32: Capital Returns: | M32: Buybacks only
C33: Exchange Listing: | G33: NASDAQ Global Select Market | I33: FCF: | M33: High-yield FCF
C35: Supply Chain & Production | I35: Regulatory & Risks
C36: Model: | G36: Vertical studio + licensed catalog | I36: Antitrust: | M36: Low structural risk vs app stores
C37: Studios: | G37: LA, Vancouver, Seoul, Tokyo, Madrid | I37: Data Privacy: | M37: GDPR, CCPA compliance
C38: Risks: | G38: Strikes, FX, regional censorship | I38: Censorship: | M38: Local edits/bans in EMEA/APAC
C40: Strategic Positioning | I40: Competition
C41: Advantages: | G41: Global scale, algorithms, localized content, pricing power | I41: Streaming: | M41: Disney+/Hulu, Prime Video, Max, Apple TV+, Paramount+, Peacock
C42: Risks: | G42: Content inflation, churn, FX exposure, competitive saturation | I42: Indirect: | M42: YouTube, TikTok, Linear TV
C44: Segments
C45: Reporting Regions: | G45: UCAN, EMEA, LATAM, APAC
C46: Product Segments: | G46: Ad-Free, Ad-Supported, Gaming (immaterial revenue)

Sheet Summary Assumptions
C12: Netflix, Inc. (NASDAQ: NFLX) Financial Model Summary Assumptions
C13: January 2026
C15: DCF Assumptions | L15: Revenue Segment Assumptions
D16: 2025 | E16: 2026 | F16: 2027 | G16: 2028 | H16: 2029 | I16: 2030 | J16: 2031 | M16: 2025 | N16: 2026 | O16: 2027 | P16: 2028 | Q16: 2029 | R16: 2030 | S16: 2031
C17: Revenue | L17: iPhone Revenue
C18: Y/Y Growth (%) | E18: =SUM(E17/D17)-1 -> #DIV/0! | F18: =SUM(F17/E17)-1 -> #DIV/0! | G18: =SUM(G17/F17)-1 -> #DIV/0! | H18: =SUM(H17/G17)-1 -> #DIV/0! | I18: =SUM(I17/H17)-1 -> #DIV/0! | J18: =SUM(J17/I17)-1 -> #DIV/0! | L18: Y/Y Growth (%) | N18: =SUM(N17/M17)-1 -> #DIV/0! | O18: =SUM(O17/N17)-1 -> #DIV/0! | P18: =SUM(P17/O17)-1 -> #DIV/0! | Q18: =SUM(Q17/P17)-1 -> #DIV/0! | R18: =SUM(R17/Q17)-1 -> #DIV/0! | S18: =SUM(S17/R17)-1 -> #DIV/0!
C19: EBITDA | L19: Mac Revenue
C20: Y/Y Growth (%) | E20: =SUM(E19/D19)-1 -> #DIV/0! | F20: =SUM(F19/E19)-1 -> #DIV/0! | G20: =SUM(G19/F19)-1 -> #DIV/0! | H20: =SUM(H19/G19)-1 -> #DIV/0! | I20: =SUM(I19/H19)-1 -> #DIV/0! | J20: =SUM(J19/I19)-1 -> #DIV/0! | L20: Y/Y Growth (%) | N20: =SUM(N19/M19)-1 -> #DIV/0! | O20: =SUM(O19/N19)-1 -> #DIV/0! | P20: =SUM(P19/O19)-1 -> #DIV/0! | Q20: =SUM(Q19/P19)-1 -> #DIV/0! | R20: =SUM(R19/Q19)-1 -> #DIV/0! | S20: =SUM(S19/R19)-1 -> #DIV/0!
C21: EBIT | L21: iPad Revenue
C22: Y/Y Growth (%) | E22: =SUM(E21/D21)-1 -> #DIV/0! | F22: =SUM(F21/E21)-1 -> #DIV/0! | G22: =SUM(G21/F21)-1 -> #DIV/0! | H22: =SUM(H21/G21)-1 -> #DIV/0! | I22: =SUM(I21/H21)-1 -> #DIV/0! | J22: =SUM(J21/I21)-1 -> #DIV/0! | L22: Y/Y Growth (%) | N22: =SUM(N21/M21)-1 -> #DIV/0! | O22: =SUM(O21/N21)-1 -> #DIV/0! | P22: =SUM(P21/O21)-1 -> #DIV/0! | Q22: =SUM(Q21/P21)-1 -> #DIV/0! | R22: =SUM(R21/Q21)-1 -> #DIV/0! | S22: =SUM(S21/R21)-1 -> #DIV/0!
C23: NOPAT | L23: Services Revenue
C24: Y/Y Growth (%) | E24: =SUM(E23/D23)-1 -> #DIV/0! | F24: =SUM(F23/E23)-1 -> #DIV/0! | G24: =SUM(G23/F23)-1 -> #DIV/0! | H24: =SUM(H23/G23)-1 -> #DIV/0! | I24: =SUM(I23/H23)-1 -> #DIV/0! | J24: =SUM(J23/I23)-1 -> #DIV/0! | L24: Y/Y Growth (%) | N24: =SUM(N23/M23)-1 -> #DIV/0! | O24: =SUM(O23/N23)-1 -> #DIV/0! | P24: =SUM(P23/O23)-1 -> #DIV/0! | Q24: =SUM(Q23/P23)-1 -> #DIV/0! | R24: =SUM(R23/Q23)-1 -> #DIV/0! | S24: =SUM(S23/R23)-1 -> #DIV/0!
C25: UFCF | L25: Other
C26: Y/Y Growth (%) | E26: =SUM(E25/D25)-1 -> #DIV/0! | F26: =SUM(F25/E25)-1 -> #DIV/0! | G26: =SUM(G25/F25)-1 -> #DIV/0! | H26: =SUM(H25/G25)-1 -> #DIV/0! | I26: =SUM(I25/H25)-1 -> #DIV/0! | J26: =SUM(J25/I25)-1 -> #DIV/0! | L26: Y/Y Growth (%) | N26: =SUM(N25/M25)-1 -> #DIV/0! | O26: =SUM(O25/N25)-1 -> #DIV/0! | P26: =SUM(P25/O25)-1 -> #DIV/0! | Q26: =SUM(Q25/P25)-1 -> #DIV/0! | R26: =SUM(R25/Q25)-1 -> #DIV/0! | S26: =SUM(S25/R25)-1 -> #DIV/0!
C28: Unit Economics | L28: ASP Economics
D29: 2025 | E29: 2026 | F29: 2027 | G29: 2028 | H29: 2029 | I29: 2030 | J29: 2031 | M29: 2025 | N29: 2026 | O29: 2027 | P29: 2028 | Q29: 2029 | R29: 2030 | S29: 2031
C30: iPhone Units | L30: iPhone ASP
C31: Y/Y Growth (%) | E31: =SUM(E30/D30)-1 -> #DIV/0! | F31: =SUM(F30/E30)-1 -> #DIV/0! | G31: =SUM(G30/F30)-1 -> #DIV/0! | H31: =SUM(H30/G30)-1 -> #DIV/0! | I31: =SUM(I30/H30)-1 -> #DIV/0! | J31: =SUM(J30/I30)-1 -> #DIV/0! | L31: Y/Y Growth (%) | N31: =SUM(N30/M30)-1 -> #DIV/0! | O31: =SUM(O30/N30)-1 -> #DIV/0! | P31: =SUM(P30/O30)-1 -> #DIV/0! | Q31: =SUM(Q30/P30)-1 -> #DIV/0! | R31: =SUM(R30/Q30)-1 -> #DIV/0! | S31: =SUM(S30/R30)-1 -> #DIV/0!
C32: iPad Units | L32: iPad ASP
C33: Y/Y Growth (%) | E33: =SUM(E32/D32)-1 -> #DIV/0! | F33: =SUM(F32/E32)-1 -> #DIV/0! | G33: =SUM(G32/F32)-1 -> #DIV/0! | H33: =SUM(H32/G32)-1 -> #DIV/0! | I33: =SUM(I32/H32)-1 -> #DIV/0! | J33: =SUM(J32/I32)-1 -> #DIV/0! | L33: Y/Y Growth (%) | N33: =SUM(N32/M32)-1 -> #DIV/0! | O33: =SUM(O32/N32)-1 -> #DIV/0! | P33: =SUM(P32/O32)-1 -> #DIV/0! | Q33: =SUM(Q32/P32)-1 -> #DIV/0! | R33: =SUM(R32/Q32)-1 -> #DIV/0! | S33: =SUM(S32/R32)-1 -> #DIV/0!
C34: Mac Units | L34: Mac ASP
C35: Y/Y Growth (%) | E35: =SUM(E34/D34)-1 -> #DIV/0! | F35: =SUM(F34/E34)-1 -> #DIV/0! | G35: =SUM(G34/F34)-1 -> #DIV/0! | H35: =SUM(H34/G34)-1 -> #DIV/0! | I35: =SUM(I34/H34)-1 -> #DIV/0! | J35: =SUM(J34/I34)-1 -> #DIV/0! | L35: Y/Y Growth (%) | N35: =SUM(N34/M34)-1 -> #DIV/0! | O35: =SUM(O34/N34)-1 -> #DIV/0! | P35: =SUM(P34/O34)-1 -> #DIV/0! | Q35: =SUM(Q34/P34)-1 -> #DIV/0! | R35: =SUM(R34/Q34)-1 -> #DIV/0! | S35: =SUM(S34/R34)-1 -> #DIV/0!
C37: P/E Forecast | L37: EPS Forecast
D38: 2025 | E38: 2026 | F38: 2027 | G38: 2028 | H38: 2029 | I38: 2030 | J38: 2031 | M38: 2025 | N38: 2026 | O38: 2027 | P38: 2028 | Q38: 2029 | R38: 2030 | S38: 2031
C39: Basic P/E | L39: Basic EPS
C40: Y/Y Growth (%) | E40: =SUM(E39/D39)-1 -> #DIV/0! | F40: =SUM(F39/E39)-1 -> #DIV/0! | G40: =SUM(G39/F39)-1 -> #DIV/0! | H40: =SUM(H39/G39)-1 -> #DIV/0! | I40: =SUM(I39/H39)-1 -> #DIV/0! | J40: =SUM(J39/I39)-1 -> #DIV/0! | L40: Y/Y Growth (%) | N40: =SUM(N39/M39)-1 -> #DIV/0! | O40: =SUM(O39/N39)-1 -> #DIV/0! | P40: =SUM(P39/O39)-1 -> #DIV/0! | Q40: =SUM(Q39/P39)-1 -> #DIV/0! | R40: =SUM(R39/Q39)-1 -> #DIV/0! | S40: =SUM(S39/R39)-1 -> #DIV/0!
C41: Diluted P/E | L41: Diluted EPS
C42: Y/Y Growth (%) | E42: =SUM(E41/D41)-1 -> #DIV/0! | F42: =SUM(F41/E41)-1 -> #DIV/0! | G42: =SUM(G41/F41)-1 -> #DIV/0! | H42: =SUM(H41/G41)-1 -> #DIV/0! | I42: =SUM(I41/H41)-1 -> #DIV/0! | J42: =SUM(J41/I41)-1 -> #DIV/0! | L42: Y/Y Growth (%) | N42: =SUM(N41/M41)-1 -> #DIV/0! | O42: =SUM(O41/N41)-1 -> #DIV/0! | P42: =SUM(P41/O41)-1 -> #DIV/0! | Q42: =SUM(Q41/P41)-1 -> #DIV/0! | R42: =SUM(R41/Q41)-1 -> #DIV/0! | S42: =SUM(S41/R41)-1 -> #DIV/0!

Sheet Summary Valuation
C12: Netflix, Inc. (NASDAQ: NFLX) Football Field Estimates
C13: January 2026
C15: Summary Valuation
E16: Low | F16: Delta | G16: High | H16: Mid
D17: Comparable Trading Analysis | F17: =G17-E17 -> 0 | H17: =MEDIAN(G17,E17) -> #NUM!
D18: DCF Valuation Analysis: Perpetuity Method | F18: =G18-E18 -> 0 | H18: =MEDIAN(G18,E18) -> #NUM!
D19: DCF Valuation Analysis: Multiple Method | F19: =G19-E19 -> 0 | H19: =MEDIAN(G19,E19) -> #NUM!
D20: 52 Week Trading | F20: =G20-E20 -> 0 | H20: =MEDIAN(G20,E20) -> #NUM!
D21: Street Consensus | F21: =G21-E21 -> 0 | H21: =MEDIAN(G21,E21) -> #NUM!
C23: Valuation Weighting
C24: Intrinsic Valuation | D24: Valuation | F24: Bear | G24: Relative | H24: Base | I24: Relative | J24: Bull | K24: Relative | L24: Weighted
C25: Method | D25: Weight | F25: Case | G25: Weight | H25: Case | I25: Weight | J25: Case | K25: Weight | L25: Value
C27: DCF: Perpetuity Method | F27: =E18 -> 0 | H27: =H18 -> #NUM! | J27: =G18 -> 0 | L27: =F27*G27+H27*I27+J27*K27 -> #NUM!
C28: DCF: Multiple Method | F28: =E19 -> 0 | H28: =H19 -> #NUM! | J28: =G19 -> 0 | L28: =F28*G28+H28*I28+J28*K28 -> #NUM!
C30: Valuation Weighting
C31: Market Based | D31: Valuation | F31: Bear | G31: Relative | H31: Base | I31: Relative | J31: Bull | K31: Relative | L31: Weighted
C32: Valuation Method | D32: Weight | F32: Case | G32: Weight | H32: Case | I32: Weight | J32: Case | K32: Weight | L32: Value
C33: Comparable Trading Analysis | L33: =F33*G33+H33*I33+J33*K33 -> 0
C35: Summary Weighted Valuation
C36: Target Price | D36: =D33*L33+D27*L27+D28*L28 -> #NUM!
C37: Current Price
C38: Upside (Downside) | D38: =(D36/D37)-1 -> #NUM!

Sheet Historical Financials
B2: Netflix, Inc. (NASDAQ: NFLX)
B3: Historical Financials
B4: $ in thousands except per share
A6: X | B6: Income Statement | G6: FYE | O6: Quarterly | S6: Quarterly | Y6: Quarterly | AN6: LTM | AO6: LTM | AU6: Variance
B7: Fiscal Period | C7: 2018 | D7: 2019 | E7: 2020 | F7: 2021 | G7: 2022 | H7: 2023 | I7: 2024 | K7: 1Q21 | L7: 2Q21 | M7: 3Q21 | N7: 4Q21 | O7: 1Q22 | P7: 2Q22 | Q7: 3Q22 | R7: 4Q22 | S7: 1Q23 | T7: 2Q23 | U7: 3Q23 | V7: 4Q23 | W7: 1Q24 | X7: 2Q24 | Y7: 3Q24 | Z7: 4Q24 | AA7: 1Q25 | AB7: 2Q25 | AC7: 3Q25 | AE7: =O7 -> 1Q22 | AF7: =P7 -> 2Q22 | AG7: =Q7 -> 3Q22 | AH7: =R7 -> 4Q22 | AI7: =S7 -> 1Q23 | AJ7: =T7 -> 2Q23 | AK7: =U7 -> 3Q23 | AL7: =V7 -> 4Q23 | ... AS7: =AC7 -> 3Q25
B8: Fiscal Period End Date | C8: 43465 | D8: 43830 | E8: 44196 | F8: 44561 | G8: 44926 | H8: 45291 | I8: 45657 | K8: 44286 | L8: 44377 | M8: 44469 | N8: =F8 -> 44561 | O8: 44651 | P8: 44742 | Q8: 44834 | R8: =G8 -> 44926 | S8: 45016 | T8: 45107 | U8: 45199 | V8: =H8 -> 45291 | W8: 45382 | X8: 45473 | Y8: 45565 | Z8: =I8 -> 45657 | AA8: 45747 | AB8: 45838 | AC8: 45930 | AE8: =O8 -> 44651 | AF8: =P8 -> 44742 | AG8: =Q8 -> 44834 | AH8: =R8 -> 44926 | AI8: =S8 -> 45016 | AJ8: =T8 -> 45107 | AK8: =U8 -> 45199 | AL8: =V8 -> 45291 | ... AS8: =AC8 -> 45930
B10: Consolidated Revenue | C10: 15794.341 | D10: 20156.447 | E10: 24996.056 | F10: 29697.844 | G10: 31615.55 | H10: 33723.297 | I10: 39000.966 | K10: 7163.282 | L10: 7341.777 | M10: 7483.467 | N10: =SUM(F10-SUM(K10:M10)) -> 7709.318 | O10: 7867.767 | P10: 7970.141 | Q10: 7925.589 | R10: =SUM(G10-SUM(O10:Q10)) -> 7852.053 | S10: 8161.503 | T10: 8187.301 | U10: 8541.668 | V10: =SUM(H10-SUM(S10:U10)) -> 8832.825 | W10: 9370.44 | X10: 9559.31 | Y10: 9824.703 | Z10: =SUM(I10-SUM(W10:Y10)) -> 10246.513 | AA10: 10542.801 | AB10: 11079.166 | AC10: 11510.307 | AE10: =SUM(L10:O10) -> 30402.329 | AF10: =SUM(M10:P10) -> 31030.693 | AG10: =SUM(N10:Q10) -> 31472.815 | AH10: =SUM(O10:R10) -> 31615.55 | AI10: =SUM(P10:S10) -> 31909.286 | AJ10: =SUM(Q10:T10) -> 32126.446 | AK10: =SUM(R10:U10) -> 32742.525 | AL10: =SUM(S10:V10) -> 33723.297 | ... AS10: =SUM(Z10:AC10) -> 43378.787 | AU10: =SUM(AS10/AO10)-1 -> 0.15408163
B11: Total Revenue | C11: =+SUM(C10:C10) -> 15794.341 | D11: =+SUM(D10:D10) -> 20156.447 | E11: =+SUM(E10:E10) -> 24996.056 | F11: =+SUM(F10:F10) -> 29697.844 | G11: =+SUM(G10:G10) -> 31615.55 | H11: =+SUM(H10:H10) -> 33723.297 | I11: =+SUM(I10:I10) -> 39000.966 | K11: =+SUM(K10:K10) -> 7163.282 | L11: =+SUM(L10:L10) -> 7341.777 | M11: =+SUM(M10:M10) -> 7483.467 | N11: =+SUM(N10:N10) -> 7709.318 | O11: =+SUM(O10:O10) -> 7867.767 | P11: =+SUM(P10:P10) -> 7970.141 | Q11: =+SUM(Q10:Q10) -> 7925.589 | R11: =+SUM(R10:R10) -> 7852.053 | ... AC11: =+SUM(AC10:AC10) -> 11510.307 | AE11: =+SUM(AE10:AE10) -> 30402.329 | AF11: =+SUM(AF10:AF10) -> 31030.693 | AG11: =+SUM(AG10:AG10) -> 31472.815 | AH11: =+SUM(AH10:AH10) -> 31615.55 | AI11: =+SUM(AI10:AI10) -> 31909.286 | AJ11: =+SUM(AJ10:AJ10) -> 32126.446 | AK11: =+SUM(AK10:AK10) -> 32742.525 | AL11: =+SUM(AL10:AL10) -> 33723.297 | ... AS11: =+SUM(AS10:AS10) -> 43378.787 | AU11: =SUM(AS11/AO11)-1 -> 0.15408163
B13: Amortization of content assets | C13: -7532.088 | D13: -9216.247 | E13: -10806.912 | F13: -12230.367 | G13: -14026.132 | H13: -14197.437 | I13: -15301.517 | K13: -2719.196 | L13: -2806.803 | M13: -2963.051 | N13: =SUM(F13-SUM(K13:M13)) -> -3741.317 | O13: -3166.365 | P13: -3261.348 | Q13: -3653.592 | R13: =SUM(G13-SUM(O13:Q13)) -> -3944.827 | S13: -3459.984 | T13: -3410.021 | U13: -3573.353 | V13: =SUM(H13-SUM(S13:U13)) -> -3754.079 | W13: -3670.805 | X13: -3769.69 | Y13: -3699.521 | Z13: =SUM(I13-SUM(W13:Y13)) -> -4161.501 | AA13: -3823.112 | AB13: -3832.074 | AC13: -4002.744 | AE13: =SUM(L13:O13) -> -12677.536 | AF13: =SUM(M13:P13) -> -13132.081 | AG13: =SUM(N13:Q13) -> -13822.622 | AH13: =SUM(O13:R13) -> -14026.132 | AI13: =SUM(P13:S13) -> -14319.751 | AJ13: =SUM(Q13:T13) -> -14468.424 | AK13: =SUM(R13:U13) -> -14388.185 | AL13: =SUM(S13:V13) -> -14197.437 | ... AS13: =SUM(Z13:AC13) -> -15819.431 | AU13: =SUM(AS13/AO13)-1 -> 0.062127709
B14: Other Cost of Revenues | C14: =+C15-C13 -> -2435.45 | D14: =+D15-D13 -> -3223.966 | E14: =+E15-E13 -> -4469.407 | F14: =+F15-F13 -> -5102.316 | G14: =+G15-G13 -> -5142.153 | H14: =+H15-H13 -> -5517.931 | I14: =+I15-I13 -> -5736.947 | K14: =+K15-K13 -> -1149.315 | L14: =+L15-L13 -> -1211.205 | M14: =+M15-M13 -> -1243.538 | N14: =SUM(F14-SUM(K14:M14)) -> -1498.258 | O14: =+O15-O13 -> -1118.34 | P14: =+P15-P13 -> -1429.407 | Q14: =+Q15-Q13 -> -1135.073 | R14: =+R15-R13 -> -1459.333 | S14: =+S15-S13 -> -1343.641 | T14: =+T15-T13 -> -1263.449 | U14: =+U15-U13 -> -1357.435 | V14: =+V15-V13 -> -1553.406 | ... AC14: =+AC15-AC13 -> -2161.506 | AE14: =SUM(L14:O14) -> -5071.341 | AF14: =SUM(M14:P14) -> -5289.543 | AG14: =SUM(N14:Q14) -> -5181.078 | AH14: =SUM(O14:R14) -> -5142.153 | AI14: =SUM(P14:S14) -> -5367.454 | AJ14: =SUM(Q14:T14) -> -5201.496 | AK14: =SUM(R14:U14) -> -5423.858 | AL14: =SUM(S14:V14) -> -5517.931 | ... AS14: =SUM(Z14:AC14) -> -6700.641 | AU14: =SUM(AS14/AO14)-1 -> 0.17875852
B15: Total Cost of Revenue | C15: -9967.538 | D15: -12440.213 | E15: -15276.319 | F15: -17332.683 | G15: -19168.285 | H15: -19715.368 | I15: -21038.464 | K15: -3868.511 | L15: -4018.008 | M15: -4206.589 | N15: =SUM(F15-SUM(K15:M15)) -> -5239.575 | O15: -4284.705 | P15: -4690.755 | Q15: -4788.665 | R15: =SUM(G15-SUM(O15:Q15)) -> -5404.16 | S15: -4803.625 | T15: -4673.47 | U15: -4930.788 | V15: =SUM(H15-SUM(S15:U15)) -> -5307.485 | W15: -4977.073 | X15: -5174.143 | Y15: -5119.884 | Z15: =SUM(I15-SUM(W15:Y15)) -> -5767.364 | AA15: -5263.147 | AB15: -5325.311 | AC15: -6164.25 | AE15: =SUM(L15:O15) -> -17748.877 | AF15: =SUM(M15:P15) -> -18421.624 | AG15: =SUM(N15:Q15) -> -19003.7 | AH15: =SUM(O15:R15) -> -19168.285 | AI15: =SUM(P15:S15) -> -19687.205 | AJ15: =SUM(Q15:T15) -> -19669.92 | AK15: =SUM(R15:U15) -> -19812.043 | AL15: =SUM(S15:V15) -> -19715.368 | ... AS15: =SUM(Z15:AC15) -> -22520.072 | AU15: =SUM(AS15/AO15)-1 -> 0.094345019
B16: Gross Profit | C16: =+SUM(C11+SUM(C13:C14)) -> 5826.803 | D16: =+SUM(D11+SUM(D13:D14)) -> 7716.234 | E16: =+SUM(E11+SUM(E13:E14)) -> 9719.737 | F16: =+SUM(F11+SUM(F13:F14)) -> 12365.161 | G16: =+SUM(G11+SUM(G13:G14)) -> 12447.265 | H16: =+SUM(H11+SUM(H13:H14)) -> 14007.929 | I16: =+SUM(I11+SUM(I13:I14)) -> 17962.502 | K16: =+SUM(K11+SUM(K13:K14)) -> 3294.771 | L16: =+SUM(L11+SUM(L13:L14)) -> 3323.769 | M16: =+SUM(M11+SUM(M13:M14)) -> 3276.878 | N16: =+SUM(N11+SUM(N13:N14)) -> 2469.743 | O16: =+SUM(O11+SUM(O13:O14)) -> 3583.062 | P16: =+SUM(P11+SUM(P13:P14)) -> 3279.386 | Q16: =+SUM(Q11+SUM(Q13:Q14)) -> 3136.924 | R16: =+SUM(R11+SUM(R13:R14)) -> 2447.893 | ... AC16: =+SUM(AC11+SUM(AC13:AC14)) -> 5346.057 | AE16: =+SUM(AE11+SUM(AE13:AE14)) -> 12653.452 | AF16: =+SUM(AF11+SUM(AF13:AF14)) -> 12609.069 | AG16: =+SUM(AG11+SUM(AG13:AG14)) -> 12469.115 | AH16: =+SUM(AH11+SUM(AH13:AH14)) -> 12447.265 | AI16: =+SUM(AI11+SUM(AI13:AI14)) -> 12222.081 | AJ16: =+SUM(AJ11+SUM(AJ13:AJ14)) -> 12456.526 | AK16: =+SUM(AK11+SUM(AK13:AK14)) -> 12930.482 | AL16: =+SUM(AL11+SUM(AL13:AL14)) -> 14007.929 | ... AS16: =+SUM(AS11+SUM(AS13:AS14)) -> 20858.715 | AU16: =SUM(AS16/AO16)-1 -> 0.22635613
B17: Gross Margin (%) | C17: =C16/C11 -> 0.36891713 | D17: =D16/D11 -> 0.38281717 | E17: =E16/E11 -> 0.38885083 | F17: =F16/F11 -> 0.41636561 | G17: =G16/G11 -> 0.39370705 | H17: =H16/H11 -> 0.4153784 | I17: =I16/I11 -> 0.46056557 | K17: =K16/K11 -> 0.45995271 | L17: =L16/L11 -> 0.45271996 | M17: =M16/M11 -> 0.43788233 | N17: =N16/N11 -> 0.32035817 | O17: =O16/O11 -> 0.45541028 | P17: =P16/P11 -> 0.41145897 | Q17: =Q16/Q11 -> 0.39579696 | R17: =R16/R11 -> 0.31175197 | ... AC17: =AC16/AC11 -> 0.46445825 | AE17: =AE16/AE11 -> 0.41620009 | AF17: =AF16/AF11 -> 0.40634184 | AG17: =AG16/AG11 -> 0.39618684 | AH17: =AH16/AH11 -> 0.39370705 | AI17: =AI16/AI11 -> 0.38302584 | AJ17: =AJ16/AJ11 -> 0.38773433 | AK17: =AK16/AK11 -> 0.39491401 | AL17: =AL16/AL11 -> 0.4153784 | ... AS17: =AS16/AS11 -> 0.48085058 | AU17: =SUM(AS17-AO17)*1000 -> 28.338618
B19: Marketing | C19: -2369.469 | D19: -2652.462 | E19: -2228.362 | F19: -2545.146 | G19: -2530.502 | H19: -2657.883 | I19: -2917.554 | K19: -512.512 | L19: -603.973 | M19: -635.948 | N19: =SUM(F19-SUM(K19:M19)) -> -792.713 | O19: -555.978 | P19: -574.96 | Q19: -567.954 | R19: =SUM(G19-SUM(O19:Q19)) -> -831.61 | S19: -555.362 | T19: -627.168 | U19: -558.736 | V19: =SUM(H19-SUM(S19:U19)) -> -916.617 | W19: -654.34 | X19: -644.084 | Y19: -642.926 | Z19: =SUM(I19-SUM(W19:Y19)) -> -976.204 | AA19: -688.37 | AB19: -713.265 | AC19: -786.295 | AE19: =SUM(L19:O19) -> -2588.612 | AF19: =SUM(M19:P19) -> -2559.599 | AG19: =SUM(N19:Q19) -> -2491.605 | AH19: =SUM(O19:R19) -> -2530.502 | AI19: =SUM(P19:S19) -> -2529.886 | AJ19: =SUM(Q19:T19) -> -2582.094 | AK19: =SUM(R19:U19) -> -2572.876 | AL19: =SUM(S19:V19) -> -2657.883 | ... AS19: =SUM(Z19:AC19) -> -3164.134 | AU19: =SUM(AS19/AO19)-1 -> 0.10712755
B20: Technology and Development (T&D) | C20: -1221.814 | D20: -1545.149 | E20: -1829.6 | F20: -2273.885 | G20: -2711.041 | H20: -2675.758 | I20: -2925.295 | K20: -525.207 | L20: -537.321 | M20: -563.887 | N20: =SUM(F20-SUM(K20:M20)) -> -647.47 | O20: -657.53 | P20: -716.846 | Q20: -662.739 | R20: =SUM(G20-SUM(O20:Q20)) -> -673.926 | S20: -687.275 | T20: -657.983 | U20: -657.159 | V20: =SUM(H20-SUM(S20:U20)) -> -673.341 | W20: -702.473 | X20: -711.254 | Y20: -735.063 | Z20: =SUM(I20-SUM(W20:Y20)) -> -776.505 | AA20: -822.823 | AB20: -824.683 | AC20: -853.584 | AE20: =SUM(L20:O20) -> -2406.208 | AF20: =SUM(M20:P20) -> -2585.733 | AG20: =SUM(N20:Q20) -> -2684.585 | AH20: =SUM(O20:R20) -> -2711.041 | AI20: =SUM(P20:S20) -> -2740.786 | AJ20: =SUM(Q20:T20) -> -2681.923 | AK20: =SUM(R20:U20) -> -2676.343 | AL20: =SUM(S20:V20) -> -2675.758 | ... AS20: =SUM(Z20:AC20) -> -3277.595 | AU20: =SUM(AS20/AO20)-1 -> 0.1613901
B21: General and Administrative (G&A) | C21: -630.294 | D21: -914.369 | E21: -1076.486 | F21: -1351.621 | G21: -1572.891 | H21: -1720.285 | I21: -1702.039 | K21: -297.196 | L21: -334.845 | M21: -321.79 | N21: =SUM(F21-SUM(K21:M21)) -> -397.79 | O21: -397.928 | P21: -409.297 | Q21: -373.213 | R21: =SUM(G21-SUM(O21:Q21)) -> -392.453 | S21: -400.924 | T21: -401.497 | U21: -478.591 | V21: =SUM(H21-SUM(S21:U21)) -> -439.273 | W21: -404.02 | X21: -426.992 | Y21: -417.353 | Z21: =SUM(I21-SUM(W21:Y21)) -> -453.674 | AA21: -421.462 | AB21: -441.213 | AC21: -457.931 | AE21: =SUM(L21:O21) -> -1452.353 | AF21: =SUM(M21:P21) -> -1526.805 | AG21: =SUM(N21:Q21) -> -1578.228 | AH21: =SUM(O21:R21) -> -1572.891 | AI21: =SUM(P21:S21) -> -1575.887 | AJ21: =SUM(Q21:T21) -> -1568.087 | AK21: =SUM(R21:U21) -> -1673.465 | AL21: =SUM(S21:V21) -> -1720.285 | ... AS21: =SUM(Z21:AC21) -> -1774.28 | AU21: =SUM(AS21/AO21)-1 -> 0.051339209
B22: Operating Profit | C22: =+SUM(C16+SUM(C19:C21)) -> 1605.226 | D22: =+SUM(D16+SUM(D19:D21)) -> 2604.254 | E22: =+SUM(E16+SUM(E19:E21)) -> 4585.289 | F22: =+SUM(F16+SUM(F19:F21)) -> 6194.509 | G22: =+SUM(G16+SUM(G19:G21)) -> 5632.831 | H22: =+SUM(H16+SUM(H19:H21)) -> 6954.003 | I22: =+SUM(I16+SUM(I19:I21)) -> 10417.614 | K22: =+SUM(K16+SUM(K19:K21)) -> 1959.856 | L22: =+SUM(L16+SUM(L19:L21)) -> 1847.63 | M22: =+SUM(M16+SUM(M19:M21)) -> 1755.253 | N22: =+SUM(N16+SUM(N19:N21)) -> 631.77 | O22: =+SUM(O16+SUM(O19:O21)) -> 1971.626 | P22: =+SUM(P16+SUM(P19:P21)) -> 1578.283 | Q22: =+SUM(Q16+SUM(Q19:Q21)) -> 1533.018 | R22: =+SUM(R16+SUM(R19:R21)) -> 549.904 | ... AC22: =+SUM(AC16+SUM(AC19:AC21)) -> 3248.247 | AE22: =+SUM(AE16+SUM(AE19:AE21)) -> 6206.279 | AF22: =+SUM(AF16+SUM(AF19:AF21)) -> 5936.932 | AG22: =+SUM(AG16+SUM(AG19:AG21)) -> 5714.697 | AH22: =+SUM(AH16+SUM(AH19:AH21)) -> 5632.831 | AI22: =+SUM(AI16+SUM(AI19:AI21)) -> 5375.522 | AJ22: =+SUM(AJ16+SUM(AJ19:AJ21)) -> 5624.422 | AK22: =+SUM(AK16+SUM(AK19:AK21)) -> 6007.798 | AL22: =+SUM(AL16+SUM(AL19:AL21)) -> 6954.003 | ... AS22: =+SUM(AS16+SUM(AS19:AS21)) -> 12642.706 | AU22: =SUM(AS22/AO22)-1 -> 0.31135384
B23: Operating Margin (%) | C23: =C22/C11 -> 0.10163298 | D23: =D22/D11 -> 0.12920204 | E23: =E22/E11 -> 0.1834405 | F23: =F22/F11 -> 0.20858447 | G23: =G22/G11 -> 0.17816647 | H23: =H22/H11 -> 0.20620768 | I23: =I22/I11 -> 0.26711169 | K23: =K22/K11 -> 0.27359749 | L23: =L22/L11 -> 0.25165978 | M23: =M22/M11 -> 0.23455078 | N23: =N22/N11 -> 0.081948883 | O23: =O22/O11 -> 0.25059537 | P23: =P22/P11 -> 0.19802448 | Q23: =Q22/Q11 -> 0.19342638 | R23: =R22/R11 -> 0.070033149 | ... AC23: =AC22/AC11 -> 0.28220333 | AE23: =AE22/AE11 -> 0.20413828 | AF23: =AF22/AF11 -> 0.19132451 | AG23: =AG22/AG11 -> 0.18157566 | AH23: =AH22/AH11 -> 0.17816647 | AI23: =AI22/AI11 -> 0.16846262 | AJ23: =AJ22/AJ11 -> 0.1750714 | AK23: =AK22/AK11 -> 0.18348609 | AL23: =AL22/AL11 -> 0.20620768 | ... AS23: =AS22/AS11 -> 0.29144904 | AU23: =SUM(AS23-AO23)*1000 -> 34.953828
B25: Interest Income | C25: 0 | D25: 0 | E25: 0 | F25: 0 | G25: 60 | H25: 281 | I25: 294 | K25: 0 | L25: 0 | M25: 0 | N25: =SUM(F25-SUM(K25:M25)) -> 0 | O25: 0 | P25: 0 | Q25: 0 | R25: =SUM(G25-SUM(O25:Q25)) -> 60 | S25: 0 | T25: 0 | U25: 0 | V25: =SUM(H25-SUM(S25:U25)) -> 281 | W25: 67 | X25: 63 | Y25: 76 | Z25: =SUM(I25-SUM(W25:Y25)) -> 88 | AA25: 82 | AB25: 72 | AC25: 67 | AE25: =SUM(L25:O25) -> 0 | AF25: =SUM(M25:P25) -> 0 | AG25: =SUM(N25:Q25) -> 0 | AH25: =SUM(O25:R25) -> 60 | AI25: =SUM(P25:S25) -> 60 | AJ25: =SUM(Q25:T25) -> 60 | AK25: =SUM(R25:U25) -> 60 | AL25: =SUM(S25:V25) -> 281 | ... AS25: =SUM(Z25:AC25) -> 309 | AU25: =SUM(AS25/AO25)-1 -> -0.36550308
B26: Interest Expense | C26: -420.493 | D26: -626.023 | E26: -767.499 | F26: -765.62 | G26: -706.212 | H26: -699.826 | I26: -718.733 | K26: -194.44 | L26: -191.322 | M26: -190.429 | N26: =SUM(F26-SUM(K26:M26)) -> -189.429 | O26: -187.579 | P26: -175.455 | Q26: -172.575 | R26: =SUM(G26-SUM(O26:Q26)) -> -170.603 | S26: -174.239 | T26: -174.812 | U26: -175.563 | V26: =SUM(H26-SUM(S26:U26)) -> -175.212 | W26: -173.314 | X26: -167.986 | Y26: -184.83 | Z26: =SUM(I26-SUM(W26:Y26)) -> -192.603 | AA26: -184.172 | AB26: -182.649 | AC26: -175.294 | AE26: =SUM(L26:O26) -> -758.759 | AF26: =SUM(M26:P26) -> -742.892 | AG26: =SUM(N26:Q26) -> -725.038 | AH26: =SUM(O26:R26) -> -706.212 | AI26: =SUM(P26:S26) -> -692.872 | AJ26: =SUM(Q26:T26) -> -692.229 | AK26: =SUM(R26:U26) -> -695.217 | AL26: =SUM(S26:V26) -> -699.826 | ... AS26: =SUM(Z26:AC26) -> -734.718 | AU26: =SUM(AS26/AO26)-1 -> 0.047588766
B27: Other Income & Expenses | C27: 41.725 | D27: 84 | E27: -618.441 | F27: 411.214 | G27: =(337.31-G25) -> 277.31 | H27: =(-48.772-H25) -> -329.772 | I27: =(266.776-I25) -> -27.224 | K27: 269.086 | L27: -62.519 | M27: 96.135 | N27: =SUM(F27-SUM(K27:M27)) -> 108.512 | O27: 195.645 | P27: 220.226 | Q27: 261.404 | R27: =SUM(G27-SUM(O27:Q27)) -> -399.965 | S27: -71.204 | T27: 26.961 | U27: 168.218 | V27: =SUM(H27-SUM(S27:U27)) -> -453.747 | W27: =155.359-W25 -> 88.359 | X27: =79.005-X25 -> 16.005 | Y27: =-21.693-Y25 -> -97.693 | Z27: =SUM(I27-SUM(W27:Y27)) -> -33.895 | AA27: =50.899-AA25 -> -31.101 | AB27: =39.63-AB25 -> -32.37 | AC27: =36.457-AC25 -> -30.543 | AE27: =SUM(L27:O27) -> 337.773 | AF27: =SUM(M27:P27) -> 620.518 | AG27: =SUM(N27:Q27) -> 785.787 | AH27: =SUM(O27:R27) -> 277.31 | AI27: =SUM(P27:S27) -> 10.461 | AJ27: =SUM(Q27:T27) -> -182.804 | AK27: =SUM(R27:U27) -> -275.99 | AL27: =SUM(S27:V27) -> -329.772 | ... AS27: =SUM(Z27:AC27) -> -127.909 | AU27: =SUM(AS27/AO27)-1 -> -0.71389876
B28: Earning Before Taxes | C28: =SUM(C22+SUM(C25:C27)) -> 1226.458 | D28: =SUM(D22+SUM(D25:D27)) -> 2062.231 | E28: =SUM(E22+SUM(E25:E27)) -> 3199.349 | F28: =SUM(F22+SUM(F25:F27)) -> 5840.103 | G28: =SUM(G22+SUM(G25:G27)) -> 5263.929 | H28: =SUM(H22+SUM(H25:H27)) -> 6205.405 | I28: =SUM(I22+SUM(I25:I27)) -> 9965.657 | K28: =SUM(K22+SUM(K25:K27)) -> 2034.502 | L28: =SUM(L22+SUM(L25:L27)) -> 1593.789 | M28: =SUM(M22+SUM(M25:M27)) -> 1660.959 | N28: =SUM(N22+SUM(N25:N27)) -> 550.853 | O28: =SUM(O22+SUM(O25:O27)) -> 1979.692 | P28: =SUM(P22+SUM(P25:P27)) -> 1623.054 | Q28: =SUM(Q22+SUM(Q25:Q27)) -> 1621.847 | R28: =SUM(R22+SUM(R25:R27)) -> 39.336 | ... AC28: =SUM(AC22+SUM(AC25:AC27)) -> 3109.41 | AE28: =SUM(AE22+SUM(AE25:AE27)) -> 5785.293 | AF28: =SUM(AF22+SUM(AF25:AF27)) -> 5814.558 | AG28: =SUM(AG22+SUM(AG25:AG27)) -> 5775.446 | AH28: =SUM(AH22+SUM(AH25:AH27)) -> 5263.929 | AI28: =SUM(AI22+SUM(AI25:AI27)) -> 4753.111 | AJ28: =SUM(AJ22+SUM(AJ25:AJ27)) -> 4809.389 | AK28: =SUM(AK22+SUM(AK25:AK27)) -> 5096.591 | AL28: =SUM(AL22+SUM(AL25:AL27)) -> 6205.405 | ... AS28: =SUM(AS22+SUM(AS25:AS27)) -> 12089.079 | AU28: =SUM(AS28/AO28)-1 -> 0.34629172
B29: EBT Margin (%) | C29: =C28/C11 -> 0.077651736 | D29: =D28/D11 -> 0.10231124 | E29: =E28/E11 -> 0.12799415 | F29: =F28/F11 -> 0.19665074 | G29: =G28/G11 -> 0.1664981 | H29: =H28/H11 -> 0.18400944 | I29: =I28/I11 -> 0.25552334 | K29: =K28/K11 -> 0.28401814 | L29: =L28/L11 -> 0.21708491 | M29: =M28/M11 -> 0.22195047 | N29: =N28/N11 -> 0.071452883 | O29: =O28/O11 -> 0.25162057 | P29: =P28/P11 -> 0.20364182 | Q29: =Q28/Q11 -> 0.20463425 | R29: =R28/R11 -> 0.0050096452 | ... AC29: =AC28/AC11 -> 0.27014136 | AE29: =AE28/AE11 -> 0.19029111 | AF29: =AF28/AF11 -> 0.18738086 | AG29: =AG28/AG11 -> 0.18350586 | AH29: =AH28/AH11 -> 0.1664981 | AI29: =AI28/AI11 -> 0.14895698 | AJ29: =AJ28/AJ11 -> 0.14970187 | AK29: =AK28/AK11 -> 0.15565663 | AL29: =AL28/AL11 -> 0.18400944 | ... AS29: =AS28/AS11 -> 0.27868642 | AU29: =SUM(AS29-AO29)*1000 -> 39.788065
B31: Provision for taxes | C31: -15.216 | D31: -195.315 | E31: -437.954 | F31: -723.875 | G31: -772.005 | H31: -797.415 | I31: -1254.026 | K31: -327.787 | L31: -240.776 | M31: -211.888 | N31: =SUM(F31-SUM(K31:M31)) -> 56.576 | O31: -382.245 | P31: -182.103 | Q31: -223.605 | R31: =SUM(G31-SUM(O31:Q31)) -> 15.948 | S31: -163.754 | T31: -191.722 | U31: -231.627 | V31: =SUM(H31-SUM(S31:U31)) -> -210.312 | W31: -282.37 | X31: -366.55 | Y31: -339.445 | Z31: =SUM(I31-SUM(W31:Y31)) -> -265.661 | AA31: -323.375 | AB31: -506.262 | AC31: -562.494 | AE31: =SUM(L31:O31) -> -778.333 | AF31: =SUM(M31:P31) -> -719.66 | AG31: =SUM(N31:Q31) -> -731.377 | AH31: =SUM(O31:R31) -> -772.005 | AI31: =SUM(P31:S31) -> -553.514 | AJ31: =SUM(Q31:T31) -> -563.133 | AK31: =SUM(R31:U31) -> -571.155 | AL31: =SUM(S31:V31) -> -797.415 | ... AS31: =SUM(Z31:AC31) -> -1657.792 | AU31: =SUM(AS31/AO31)-1 -> 0.38301811
B32: Net loss | C32: =SUM(C28+SUM(C31:C31)) -> 1211.242 | D32: =SUM(D28+SUM(D31:D31)) -> 1866.916 | E32: =SUM(E28+SUM(E31:E31)) -> 2761.395 | F32: =SUM(F28+SUM(F31:F31)) -> 5116.228 | G32: =SUM(G28+SUM(G31:G31)) -> 4491.924 | H32: =SUM(H28+SUM(H31:H31)) -> 5407.99 | I32: =SUM(I28+SUM(I31:I31)) -> 8711.631 | K32: =SUM(K28+SUM(K31:K31)) -> 1706.715 | L32: =SUM(L28+SUM(L31:L31)) -> 1353.013 | M32: =SUM(M28+SUM(M31:M31)) -> 1449.071 | N32: =SUM(N28+SUM(N31:N31)) -> 607.429 | O32: =SUM(O28+SUM(O31:O31)) -> 1597.447 | P32: =SUM(P28+SUM(P31:P31)) -> 1440.951 | Q32: =SUM(Q28+SUM(Q31:Q31)) -> 1398.242 | R32: =SUM(R28+SUM(R31:R31)) -> 55.284 | ... AC32: =SUM(AC28+SUM(AC31:AC31)) -> 2546.916 | AE32: =SUM(AE28+SUM(AE31:AE31)) -> 5006.96 | AF32: =SUM(AF28+SUM(AF31:AF31)) -> 5094.898 | AG32: =SUM(AG28+SUM(AG31:AG31)) -> 5044.069 | AH32: =SUM(AH28+SUM(AH31:AH31)) -> 4491.924 | AI32: =SUM(AI28+SUM(AI31:AI31)) -> 4199.597 | AJ32: =SUM(AJ28+SUM(AJ31:AJ31)) -> 4246.256 | AK32: =SUM(AK28+SUM(AK31:AK31)) -> 4525.436 | AL32: =SUM(AL28+SUM(AL31:AL31)) -> 5407.99 | ... AS32: =SUM(AS28+SUM(AS31:AS31)) -> 10431.287 | AU32: =SUM(AS32/AO32)-1 -> 0.34063385
B33: Net Margin (%) | C33: =C32/C11 -> 0.076688353 | D33: =D32/D11 -> 0.092621284 | E33: =E32/E11 -> 0.11047323 | F33: =F32/F11 -> 0.17227607 | G33: =G32/G11 -> 0.14207958 | H33: =H32/H11 -> 0.16036362 | I33: =I32/I11 -> 0.22336962 | K33: =K32/K11 -> 0.2382588 | L33: =L32/L11 -> 0.18428958 | M33: =M32/M11 -> 0.19363632 | N33: =N32/N11 -> 0.078791535 | O33: =O32/O11 -> 0.2030369 | P33: =P32/P11 -> 0.18079366 | Q33: =Q32/Q11 -> 0.17642121 | R33: =R32/R11 -> 0.0070407064 | ... AC33: =AC32/AC11 -> 0.22127264 | AE33: =AE32/AE11 -> 0.16469001 | AF33: =AF32/AF11 -> 0.16418899 | AG33: =AG32/AG11 -> 0.16026749 | AH33: =AH32/AH11 -> 0.14207958 | AI33: =AI32/AI11 -> 0.1316105 | AJ33: =AJ32/AJ11 -> 0.13217323 | AK33: =AK32/AK11 -> 0.1382128 | AL33: =AL32/AL11 -> 0.16036362 | ... AS33: =AS32/AS11 -> 0.24046977 | AU33: =SUM(AS33-AO33)*1000 -> 33.461911
B35: Basic Shares | E35: 440.922 | F35: 443.155 | G35: 444.698 | H35: 441.571 | I35: =(429519)/1000 -> 429.519 | K35: 443.224 | L35: 443.159 | M35: 442.778 | N35: =F35 -> 443.155 | O35: 444.146 | P35: 444.557 | Q35: 444.878 | R35: =G35 -> 444.698 | S35: 445.244 | T35: 443.881 | U35: 441.537 | V35: =K35 -> 443.224 | W35: 432.09 | X35: 430.065 | Y35: 428.239 | Z35: =I35 -> 429.519 | AA35: 427.27 | AB35: 425.211 | AC35: 424.455 | AE35: =O35 -> 444.146 | AF35: =P35 -> 444.557 | AG35: =Q35 -> 444.878 | AH35: =R35 -> 444.698 | AI35: =S35 -> 445.244 | AJ35: =T35 -> 443.881 | AK35: =U35 -> 441.537 | AL35: =V35 -> 443.224 | ... AS35: =AC35 -> 424.455 | AU35: =SUM(AS35/AO35)-1 -> -0.0088361873
B36: Basic EPS | E36: =E32/E35 -> 6.2627744 | F36: =F32/F35 -> 11.545008 | G36: =G32/G35 -> 10.101066 | H36: =H32/H35 -> 12.247158 | I36: =I32/I35 -> 20.282295 | K36: =K32/K35 -> 3.8506827 | L36: =L32/L35 -> 3.0531096 | M36: =M32/M35 -> 3.2726807 | N36: =N32/N35 -> 1.370692 | O36: =O32/O35 -> 3.5966709 | P36: =P32/P35 -> 3.2413189 | Q36: =Q32/Q35 -> 3.1429785 | R36: =R32/R35 -> 0.12431808 | ... AC36: =AC32/AC35 -> 6.0004382 | AE36: =AE32/AE35 -> 11.27323 | AF36: =AF32/AF35 -> 11.460618 | AG36: =AG32/AG35 -> 11.338095 | AH36: =AH32/AH35 -> 10.101066 | AI36: =AI32/AI35 -> 9.4321249 | AJ36: =AJ32/AJ35 -> 9.5662036 | AK36: =AK32/AK35 -> 10.249279 | AL36: =AL32/AL35 -> 12.201483 | ... AS36: =AS32/AS35 -> 24.575719 | AU36: =SUM(AS36/AO36)-1 -> 0.35258555
B38: Fully Diluted Shares | E38: 454.208 | F38: 455.372 | G38: 451.29 | H38: 449.498 | I38: 439.261 | K38: 455.641 | L38: 455.129 | M38: 454.925 | N38: =F38 -> 455.372 | O38: 452.984 | P38: 450.169 | Q38: 450.344 | R38: =G38 -> 451.29 | S38: 452.417 | T38: 451.572 | U38: 450.011 | V38: =K38 -> 455.641 | W38: 441.654 | X38: 439.739 | Y38: 437.898 | Z38: =I38 -> 439.261 | AA38: 436.962 | AB38: 434.883 | AC38: 434.039 | AE38: =O38 -> 452.984 | AF38: =P38 -> 450.169 | AG38: =Q38 -> 450.344 | AH38: =R38 -> 451.29 | AI38: =S38 -> 452.417 | AJ38: =T38 -> 451.572 | AK38: =U38 -> 450.011 | AL38: =V38 -> 455.641 | ... AS38: =AC38 -> 434.039 | AU38: =SUM(AS38/AO38)-1 -> -0.0088125545
B39: Fully Diluted EPS | E39: =E32/E38 -> 6.0795825 | F39: =F32/F38 -> 11.235271 | G39: =G32/G38 -> 9.9535199 | H39: =H32/H38 -> 12.031177 | I39: =I32/I38 -> 19.832471 | K39: =K32/K38 -> 3.745745 | L39: =L32/L38 -> 2.9728121 | M39: =M32/M38 -> 3.1852965 | N39: =N32/N38 -> 1.3339182 | O39: =O32/O38 -> 3.5264976 | P39: =P32/P38 -> 3.2009112 | Q39: =Q32/Q38 -> 3.104831 | R39: =R32/R38 -> 0.12250216 | ... AC39: =AC32/AC38 -> 5.8679427 | AE39: =AE32/AE38 -> 11.053282 | AF39: =AF32/AF38 -> 11.317745 | AG39: =AG32/AG38 -> 11.20048 | AH39: =AH32/AH38 -> 9.9535199 | AI39: =AI32/AI38 -> 9.28258 | AJ39: =AJ32/AJ38 -> 9.4032757 | AK39: =AK32/AK38 -> 10.056279 | AL39: =AL32/AL38 -> 11.868971 | ... AS39: =AS32/AS38 -> 24.033064 | AU39: =SUM(AS39/AO39)-1 -> 0.3525533
A41: X | B41: Balance Sheet | AN41: LTM | AU41: Variance
B42: =B7 -> Fiscal Period | C42: =C7 -> 2018 | D42: =D7 -> 2019 | E42: =E7 -> 2020 | F42: =F7 -> 2021 | G42: =G7 -> 2022 | H42: =H7 -> 2023 | I42: =I7 -> 2024 | K42: =K7 -> 1Q21 | L42: =L7 -> 2Q21 | M42: =M7 -> 3Q21 | N42: =N7 -> 4Q21 | O42: =O7 -> 1Q22 | P42: =P7 -> 2Q22 | Q42: =Q7 -> 3Q22 | R42: =R7 -> 4Q22 | ... AC42: =AC7 -> 3Q25 | AE42: =AE7 -> 1Q22 | AF42: =AF7 -> 2Q22 | AG42: =AG7 -> 3Q22 | AH42: =AH7 -> 4Q22 | AI42: =AI7 -> 1Q23 | AJ42: =AJ7 -> 2Q23 | AK42: =AK7 -> 3Q23 | AL42: =AL7 -> 4Q23 | ... AS42: =AS7 -> 3Q25
B43: =B8 -> Fiscal Period End Date | C43: =C8 -> 43465 | D43: =D8 -> 43830 | E43: =E8 -> 44196 | F43: =F8 -> 44561 | G43: =G8 -> 44926 | H43: =H8 -> 45291 | I43: =I8 -> 45657 | K43: =K8 -> 44286 | L43: =L8 -> 44377 | M43: =M8 -> 44469 | N43: =N8 -> 44561 | O43: =O8 -> 44651 | P43: =P8 -> 44742 | Q43: =Q8 -> 44834 | R43: =R8 -> 44926 | ... AC43: =AC8 -> 45930 | AE43: =AE8 -> 44651 | AF43: =AF8 -> 44742 | AG43: =AG8 -> 44834 | AH43: =AH8 -> 44926 | AI43: =AI8 -> 45016 | AJ43: =AJ8 -> 45107 | AK43: =AK8 -> 45199 | AL43: =AL8 -> 45291 | ... AS43: =AS8 -> 45930
B45: Current Assets
B46: Cash and cash equivalents | C46: 3794.483 | D46: 5018.437 | E46: 8205.55 | F46: 6027.804 | G46: 5147.176 | H46: 7116.913 | I46: 7804.733 | K46: 8403.705 | L46: 7777.53 | M46: 7526.681 | N46: =F46 -> 6027.804 | O46: 6008.946 | P46: 5819.449 | Q46: 6113.733 | R46: =G46 -> 5147.176 | S46: 6714.594 | T46: 7662.788 | U46: 7353.245 | V46: =H46 -> 7116.913 | W46: 7024.766 | X46: 6624.939 | Y46: 7457.025 | Z46: =I46 -> 7804.733 | AA46: 7199.848 | AB46: 8177.405 | AC46: 9287.287 | AE46: =O46 -> 6008.946 | AF46: =P46 -> 5819.449 | AG46: =Q46 -> 6113.733 | AH46: =R46 -> 5147.176 | AI46: =S46 -> 6714.594 | AJ46: =T46 -> 7662.788 | AK46: =U46 -> 7353.245 | AL46: =V46 -> 7116.913 | ... AS46: =AC46 -> 9287.287 | AU46: =SUM(AS46/AO46)-1 -> 0.24544131
B47: Other current assets | C47: 748.466 | D47: 1160.067 | E47: 1556.03 | F47: 2042.021 | G47: 3208.021 | H47: 2780.247 | I47: 3516.64 | K47: 1703.803 | L47: 1826.746 | M47: 1889.106 | N47: =F47 -> 2042.021 | O47: 2089.069 | P47: 2021.329 | Q47: 2703.17 | R47: =G47 -> 3208.021 | S47: 2655.119 | T47: 2929.347 | U47: 2912.028 | V47: =H47 -> 2780.247 | W47: 2875.574 | X47: 2959.641 | Y47: 2905.172 | Z47: =I47 -> 3516.64 | AA47: 3326.642 | AB47: 3602.586 | AC47: 3638.543 | AE47: =O47 -> 2089.069 | AF47: =P47 -> 2021.329 | AG47: =Q47 -> 2703.17 | AH47: =R47 -> 3208.021 | AI47: =S47 -> 2655.119 | AJ47: =T47 -> 2929.347 | AK47: =U47 -> 2912.028 | AL47: =V47 -> 2780.247 | ... AS47: =AC47 -> 3638.543 | AU47: =SUM(AS47/AO47)-1 -> 0.25243634
B48: Short-term investments | C48: 0 | D48: 0 | E48: 0 | F48: 0 | G48: 911.276 | H48: 20.973 | I48: 1779.006 | K48: 0 | L48: 0 | M48: 0 | N48: =F48 -> 0 | O48: 0 | P48: 0 | Q48: 0 | R48: =G48 -> 911.276 | S48: 1112.91 | T48: 914.201 | U48: 514.201 | V48: =H48 -> 20.973 | W48: 20.973 | X48: 30.973 | Y48: 1766.902 | Z48: =I48 -> 1779.006 | AA48: 1171.142 | AB48: 213.115 | AC48: 37.105 | AE48: =O48 -> 0 | AF48: =P48 -> 0 | AG48: =Q48 -> 0 | AH48: =R48 -> 911.276 | AI48: =S48 -> 1112.91 | AJ48: =T48 -> 914.201 | AK48: =U48 -> 514.201 | AL48: =V48 -> 20.973 | ... AS48: =AC48 -> 37.105 | AU48: =SUM(AS48/AO48)-1 -> -0.97899997
B49: Total Current Assets | C49: =SUM(C46:C48) -> 4542.949 | D49: =SUM(D46:D48) -> 6178.504 | E49: =SUM(E46:E48) -> 9761.58 | F49: =SUM(F46:F48) -> 8069.825 | G49: =SUM(G46:G48) -> 9266.473 | H49: =SUM(H46:H48) -> 9918.133 | I49: =SUM(I46:I48) -> 13100.379 | K49: =SUM(K46:K48) -> 10107.508 | L49: =SUM(L46:L48) -> 9604.276 | M49: =SUM(M46:M48) -> 9415.787 | N49: =SUM(N46:N48) -> 8069.825 | O49: =SUM(O46:O48) -> 8098.015 | P49: =SUM(P46:P48) -> 7840.778 | Q49: =SUM(Q46:Q48) -> 8816.903 | R49: =SUM(R46:R48) -> 9266.473 | ... AC49: =SUM(AC46:AC48) -> 12962.935 | AE49: =SUM(AE46:AE48) -> 8098.015 | AF49: =SUM(AF46:AF48) -> 7840.778 | AG49: =SUM(AG46:AG48) -> 8816.903 | AH49: =SUM(AH46:AH48) -> 9266.473 | AI49: =SUM(AI46:AI48) -> 10482.623 | AJ49: =SUM(AJ46:AJ48) -> 11506.336 | AK49: =SUM(AK46:AK48) -> 10779.474 | AL49: =SUM(AL46:AL48) -> 9918.133 | ... AS49: =SUM(AS46:AS48) -> 12962.935 | AU49: =SUM(AS49/AO49)-1 -> 0.068746739
B51: Non-Current Assets
B52: Content assets, net | C52: 20102.327 | D52: 24504.567 | E52: 25383.95 | F52: 30919.539 | G52: 32736.713 | H52: 31658.056 | I52: 32452.462 | K52: 26043.991 | L52: 27291.64 | M52: 28974.045 | N52: =F52 -> 30919.539 | O52: 31191.92 | P52: 32533.199 | Q52: 32777.34 | R52: =G52 -> 32736.713 | S52: 32349.184 | T52: 32520.774 | U52: 31749.861 | V52: =H52 -> 31658.056 | W52: 31662.1 | X52: 31927.355 | Y52: 32175.382 | Z52: =I52 -> 32452.462 | AA52: 32040.839 | AB52: 32089.394 | AC52: 32639.879 | AE52: =O52 -> 31191.92 | AF52: =P52 -> 32533.199 | AG52: =Q52 -> 32777.34 | AH52: =R52 -> 32736.713 | AI52: =S52 -> 32349.184 | AJ52: =T52 -> 32520.774 | AK52: =U52 -> 31749.861 | AL52: =V52 -> 31658.056 | ... AS52: =AC52 -> 32639.879 | AU52: =SUM(AS52/AO52)-1 -> 0.01443641
B53: Property and equipment, net | C53: 418.281 | D53: 565.221 | E53: 960.183 | F53: 1323.453 | G53: 1398.257 | H53: 1491.444 | I53: 1593.756 | K53: 1015.419 | L53: 1107.437 | M53: 1220.114 | N53: =F53 -> 1323.453 | O53: 1383.763 | P53: 1361.92 | Q53: 1372.754 | R53: =G53 -> 1398.257 | S53: 1413.094 | T53: 1471.968 | U53: 1498.391 | V53: =H53 -> 1491.444 | W53: 1501.168 | X53: 1510.958 | Y53: 1568.212 | Z53: =I53 -> 1593.756 | AA53: 1644.346 | AB53: 1743.566 | AC53: 1837.889 | AE53: =O53 -> 1383.763 | AF53: =P53 -> 1361.92 | AG53: =Q53 -> 1372.754 | AH53: =R53 -> 1398.257 | AI53: =S53 -> 1413.094 | AJ53: =T53 -> 1471.968 | AK53: =U53 -> 1498.391 | AL53: =V53 -> 1491.444 | ... AS53: =AC53 -> 1837.889 | AU53: =SUM(AS53/AO53)-1 -> 0.17196463
B54: Other non-current assets | C54: 910.843 | D54: 2727.42 | E54: 3174.646 | F54: 4271.846 | G54: 5193.325 | H54: 5664.359 | I54: 6483.777 | K54: 2956.096 | L54: 2967.616 | M54: 3129.911 | N54: =F54 -> 4271.846 | O54: 4657.206 | P54: 4615.038 | Q54: 4595.19 | R54: =G54 -> 5193.325 | S54: 5245.444 | T54: 5318.395 | U54: 5474.06 | V54: =H54 -> 5664.359 | W54: 5743.14 | X54: 6045.029 | Y54: 6409.151 | Z54: =I54 -> 6483.777 | AA54: 6704.827 | AB54: 7273.598 | AC54: 7494.132 | AE54: =O54 -> 4657.206 | AF54: =P54 -> 4615.038 | AG54: =Q54 -> 4595.19 | AH54: =R54 -> 5193.325 | AI54: =S54 -> 5245.444 | AJ54: =T54 -> 5318.395 | AK54: =U54 -> 5474.06 | AL54: =V54 -> 5664.359 | ... AS54: =AC54 -> 7494.132 | AU54: =SUM(AS54/AO54)-1 -> 0.16928623
B55: Total Assets | C55: =SUM(C52:C54)+C49 -> 25974.4 | D55: =SUM(D52:D54)+D49 -> 33975.712 | E55: =SUM(E52:E54)+E49 -> 39280.359 | F55: =SUM(F52:F54)+F49 -> 44584.663 | G55: =SUM(G52:G54)+G49 -> 48594.768 | H55: =SUM(H52:H54)+H49 -> 48731.992 | I55: =SUM(I52:I54)+I49 -> 53630.374 | K55: =SUM(K52:K54)+K49 -> 40123.014 | L55: =SUM(L52:L54)+L49 -> 40970.969 | M55: =SUM(M52:M54)+M49 -> 42739.857 | N55: =SUM(N52:N54)+N49 -> 44584.663 | O55: =SUM(O52:O54)+O49 -> 45330.904 | P55: =SUM(P52:P54)+P49 -> 46350.935 | Q55: =SUM(Q52:Q54)+Q49 -> 47562.187 | R55: =SUM(R52:R54)+R49 -> 48594.768 | ... AC55: =SUM(AC52:AC54)+AC49 -> 54934.835 | AE55: =SUM(AE52:AE54)+AE49 -> 45330.904 | AF55: =SUM(AF52:AF54)+AF49 -> 46350.935 | AG55: =SUM(AG52:AG54)+AG49 -> 47562.187 | AH55: =SUM(AH52:AH54)+AH49 -> 48594.768 | AI55: =SUM(AI52:AI54)+AI49 -> 49490.345 | AJ55: =SUM(AJ52:AJ54)+AJ49 -> 50817.473 | AK55: =SUM(AK52:AK54)+AK49 -> 49501.786 | AL55: =SUM(AL52:AL54)+AL49 -> 48731.992 | ... AS55: =SUM(AS52:AS54)+AS49 -> 54934.835 | AU55: =SUM(AS55/AO55)-1 -> 0.050744021
B57: Current Liabilities
B58: Current content liabilities | C58: 4681.562 | D58: 4413.561 | E58: 4429.536 | F58: 4292.967 | G58: 4480.15 | H58: 4466.47 | I58: 4393.681 | K58: 4297.957 | L58: 4197.874 | M58: 4110.962 | N58: =F58 -> 4292.967 | O58: 4066.289 | P58: 4174.966 | Q58: 4225.89 | R58: =G58 -> 4480.15 | S58: 4344.58 | T58: 4440.412 | U58: 4259.582 | V58: =H58 -> 4466.47 | W58: 4436.021 | X58: 4391.437 | Y58: 4489.971 | Z58: =I58 -> 4393.681 | AA58: 4128.905 | AB58: 4091.77 | AC58: 4102.64 | AE58: =O58 -> 4066.289 | AF58: =P58 -> 4174.966 | AG58: =Q58 -> 4225.89 | AH58: =R58 -> 4480.15 | AI58: =S58 -> 4344.58 | AJ58: =T58 -> 4440.412 | AK58: =U58 -> 4259.582 | AL58: =V58 -> 4466.47 | ... AS58: =AC58 -> 4102.64 | AU58: =SUM(AS58/AO58)-1 -> -0.086265813
B59: Accounts payable | C59: 562.985 | D59: 674.347 | E59: 656.183 | F59: 837.483 | G59: 671.513 | H59: 747.412 | I59: 899.909 | K59: 532.942 | L59: 622.931 | M59: 643.059 | N59: =F59 -> 837.483 | O59: 617.202 | P59: 504.278 | Q59: 560.156 | R59: =G59 -> 671.513 | S59: 591.987 | T59: 615.374 | U59: 534.429 | V59: =H59 -> 747.412 | W59: 607.348 | X59: 598.557 | Y59: 641.953 | Z59: =I59 -> 899.909 | AA59: 614.489 | AB59: 632.718 | AC59: 793.233 | AE59: =O59 -> 617.202 | AF59: =P59 -> 504.278 | AG59: =Q59 -> 560.156 | AH59: =R59 -> 671.513 | AI59: =S59 -> 591.987 | AJ59: =T59 -> 615.374 | AK59: =U59 -> 534.429 | AL59: =V59 -> 747.412 | ... AS59: =AC59 -> 793.233 | AU59: =SUM(AS59/AO59)-1 -> 0.23565588
B60: Accrued expenses and other liabilities | C60: 481.874 | D60: 843.043 | E60: 1102.196 | F60: 1449.351 | G60: 1514.65 | H60: 1803.96 | I60: 2156.544 | K60: 1291.812 | L60: 1125.591 | M60: 1413.12 | N60: =F60 -> 1449.351 | O60: 1817.117 | P60: 1596.035 | Q60: 1803.555 | R60: =G60 -> 1514.65 | S60: 1718.069 | T60: 1908.714 | U60: 1838.908 | V60: =H60 -> 1803.96 | W60: 1977.428 | X60: 1876.244 | Y60: 2241.758 | Z60: =I60 -> 2156.544 | AA60: 2359.518 | AB60: 2489.486 | AC60: 3111.311 | AE60: =O60 -> 1817.117 | AF60: =P60 -> 1596.035 | AG60: =Q60 -> 1803.555 | AH60: =R60 -> 1514.65 | AI60: =S60 -> 1718.069 | AJ60: =T60 -> 1908.714 | AK60: =U60 -> 1838.908 | AL60: =V60 -> 1803.96 | ... AS60: =AC60 -> 3111.311 | AU60: =SUM(AS60/AO60)-1 -> 0.38788888
B61: Deferred revenue | C61: 760.899 | D61: 924.745 | E61: 1117.992 | F61: 1209.342 | G61: 1264.661 | H61: 1442.969 | I61: 1520.813 | K61: 1140.271 | L61: 1187.364 | M61: 1182.632 | N61: =F61 -> 1209.342 | O61: 1239.048 | P61: 1224.743 | Q61: 1176.323 | R61: =G61 -> 1264.661 | S61: 1262.271 | T61: 1311.918 | U61: 1306.185 | V61: =H61 -> 1442.969 | W61: 1469.484 | X61: 1473.72 | Y61: 1513.048 | Z61: =I61 -> 1520.813 | AA61: 1609.726 | AB61: 1728.361 | AC61: 1724.675 | AE61: =O61 -> 1239.048 | AF61: =P61 -> 1224.743 | AG61: =Q61 -> 1176.323 | AH61: =R61 -> 1264.661 | AI61: =S61 -> 1262.271 | AJ61: =T61 -> 1311.918 | AK61: =U61 -> 1306.185 | AL61: =V61 -> 1442.969 | ... AS61: =AC61 -> 1724.675 | AU61: =SUM(AS61/AO61)-1 -> 0.139868
B62: Short-term debt | C62: 0 | D62: 0 | E62: 499.878 | F62: 699.823 | G62: 0 | H62: 399.844 | I62: 1784.453 | K62: 698.788 | L62: 699.128 | M62: 699.473 | N62: =F62 -> 699.823 | O62: 0 | P62: 0 | Q62: 0 | R62: =G62 -> 0 | S62: 399.163 | T62: 399.387 | U62: 399.614 | V62: =H62 -> 399.844 | W62: 798.936 | X62: 1800.041 | Y62: 1820.396 | Z62: =I62 -> 1784.453 | AA62: 1005.881 | AB62: 0 | AC62: 0 | AE62: =O62 -> 0 | AF62: =P62 -> 0 | AG62: =Q62 -> 0 | AH62: =R62 -> 0 | AI62: =S62 -> 399.163 | AJ62: =T62 -> 399.387 | AK62: =U62 -> 399.614 | AL62: =V62 -> 399.844 | ... AS62: =AC62 -> 0 | AU62: =SUM(AS62/AO62)-1 -> -1
B63: Total Current Liabilities | C63: =SUM(C58:C62) -> 6487.32 | D63: =SUM(D58:D62) -> 6855.696 | E63: =SUM(E58:E62) -> 7805.785 | F63: =SUM(F58:F62) -> 8488.966 | G63: =SUM(G58:G62) -> 7930.974 | H63: =SUM(H58:H62) -> 8860.655 | I63: =SUM(I58:I62) -> 10755.4 | K63: =SUM(K58:K62) -> 7961.77 | L63: =SUM(L58:L62) -> 7832.888 | M63: =SUM(M58:M62) -> 8049.246 | N63: =SUM(N58:N62) -> 8488.966 | O63: =SUM(O58:O62) -> 7739.656 | P63: =SUM(P58:P62) -> 7500.022 | Q63: =SUM(Q58:Q62) -> 7765.924 | R63: =SUM(R58:R62) -> 7930.974 | ... AC63: =SUM(AC58:AC62) -> 9731.859 | AE63: =SUM(AE58:AE62) -> 7739.656 | AF63: =SUM(AF58:AF62) -> 7500.022 | AG63: =SUM(AG58:AG62) -> 7765.924 | AH63: =SUM(AH58:AH62) -> 7930.974 | AI63: =SUM(AI58:AI62) -> 8316.07 | AJ63: =SUM(AJ58:AJ62) -> 8675.805 | AK63: =SUM(AK58:AK62) -> 8338.718 | AL63: =SUM(AL58:AL62) -> 8860.655 | ... AS63: =SUM(AS58:AS62) -> 9731.859 | AU63: =SUM(AS63/AO63)-1 -> -0.091085787
B65: Non-Current Liabilities
B66: Non-current content liabilities | C66: 3759.026 | D66: 3334.323 | E66: 2618.084 | F66: 3094.213 | G66: 3081.277 | H66: 2578.173 | I66: 1780.806 | K66: 2465.626 | L66: 2265.286 | M66: 2301.026 | N66: =F66 -> 3094.213 | O66: 2945.221 | P66: 2989.961 | Q66: 2955.368 | R66: =G66 -> 3081.277 | S66: 2908.029 | T66: 2849.387 | U66: 2668.472 | V66: =H66 -> 2578.173 | W66: 2370.692 | X66: 2028.782 | Y66: 1918.089 | Z66: =I66 -> 1780.806 | AA66: 1696.662 | AB66: 1606.404 | AC66: 1591.973 | AE66: =O66 -> 2945.221 | AF66: =P66 -> 2989.961 | AG66: =Q66 -> 2955.368 | AH66: =R66 -> 3081.277 | AI66: =S66 -> 2908.029 | AJ66: =T66 -> 2849.387 | AK66: =U66 -> 2668.472 | AL66: =V66 -> 2578.173 | ... AS66: =AC66 -> 1591.973 | AU66: =SUM(AS66/AO66)-1 -> -0.17002131
B67: Long-term debt | C67: 10360.058 | D67: 14759.26 | E67: 15809.095 | F67: 14693.072 | G67: 14353.076 | H67: 14143.417 | I67: 13798.351 | K67: 14860.552 | L67: 14926.889 | M67: 14793.691 | N67: =F67 -> 14693.072 | O67: 14534.561 | P67: 14233.303 | Q67: 13888.117 | R67: =G67 -> 14353.076 | S67: 14037.965 | T67: 14070.151 | U67: 13900.754 | V67: =H67 -> 14143.417 | W67: 13217.038 | X67: 12180.024 | Y67: 14160.932 | Z67: =I67 -> 13798.351 | AA67: 14011.037 | AB67: 14453.206 | AC67: 14463.02 | AE67: =O67 -> 14534.561 | AF67: =P67 -> 14233.303 | AG67: =Q67 -> 13888.117 | AH67: =R67 -> 14353.076 | AI67: =S67 -> 14037.965 | AJ67: =T67 -> 14070.151 | AK67: =U67 -> 13900.754 | AL67: =V67 -> 14143.417 | ... AS67: =AC67 -> 14463.02 | AU67: =SUM(AS67/AO67)-1 -> 0.021332494
B68: Other non-current liabilities | C68: 129.231 | D68: 1444.276 | E68: 1982.155 | F68: 2459.164 | G68: 2452.04 | H68: 2561.434 | I68: 2552.25 | K68: 1950.986 | L68: 2082.035 | M68: 2281.277 | N68: =F68 -> 2459.164 | O68: 2567.427 | P68: 2551.675 | Q68: 2424.637 | R68: =G68 -> 2452.04 | S68: 2400.085 | T68: 2389.915 | U68: 2486.215 | V68: =H68 -> 2561.434 | W68: 2585.364 | X68: 2637.397 | Y68: 2774.961 | Z68: =I68 -> 2552.25 | AA68: 2633.353 | AB68: 3145.82 | AC68: 3193.948 | AE68: =O68 -> 2567.427 | AF68: =P68 -> 2551.675 | AG68: =Q68 -> 2424.637 | AH68: =R68 -> 2452.04 | AI68: =S68 -> 2400.085 | AJ68: =T68 -> 2389.915 | AK68: =U68 -> 2486.215 | AL68: =V68 -> 2561.434 | ... AS68: =AC68 -> 3193.948 | AU68: =SUM(AS68/AO68)-1 -> 0.15098843
B69: Total Liabilities | C69: =SUM(C66:C68)+C63 -> 20735.635 | D69: =SUM(D66:D68)+D63 -> 26393.555 | E69: =SUM(E66:E68)+E63 -> 28215.119 | F69: =SUM(F66:F68)+F63 -> 28735.415 | G69: =SUM(G66:G68)+G63 -> 27817.367 | H69: =SUM(H66:H68)+H63 -> 28143.679 | I69: =SUM(I66:I68)+I63 -> 28886.807 | K69: =SUM(K66:K68)+K63 -> 27238.934 | L69: =SUM(L66:L68)+L63 -> 27107.098 | M69: =SUM(M66:M68)+M63 -> 27425.24 | N69: =SUM(N66:N68)+N63 -> 28735.415 | O69: =SUM(O66:O68)+O63 -> 27786.865 | P69: =SUM(P66:P68)+P63 -> 27274.961 | Q69: =SUM(Q66:Q68)+Q63 -> 27034.046 | R69: =SUM(R66:R68)+R63 -> 27817.367 | ... AC69: =SUM(AC66:AC68)+AC63 -> 28980.8 | AE69: =SUM(AE66:AE68)+AE63 -> 27786.865 | AF69: =SUM(AF66:AF68)+AF63 -> 27274.961 | AG69: =SUM(AG66:AG68)+AG63 -> 27034.046 | AH69: =SUM(AH66:AH68)+AH63 -> 27817.367 | AI69: =SUM(AI66:AI68)+AI63 -> 27662.149 | AJ69: =SUM(AJ66:AJ68)+AJ63 -> 27985.258 | AK69: =SUM(AK66:AK68)+AK63 -> 27394.159 | AL69: =SUM(AL66:AL68)+AL63 -> 28143.679 | ... AS69: =SUM(AS66:AS68)+AS63 -> 28980.8 | AU69: =SUM(AS69/AO69)-1 -> -0.019630793
B71: Common stock | C71: 2315.988 | D71: 2793.929 | E71: 3447.698 | F71: 4024.561 | G71: 4637.601 | H71: 5145.172 | I71: 6252.126 | K71: 3600.084 | L71: 3721.246 | M71: 3852.531 | N71: =F71 -> 4024.561 | O71: 4155.58 | P71: 4316.87 | Q71: 4473.962 | R71: =G71 -> 4637.601 | S71: 4762.395 | T71: 4874.208 | U71: 5011.427 | V71: =H71 -> 5145.172 | W71: 5489.85 | X71: 5680.061 | Y71: 5887.903 | Z71: =I71 -> 6252.126 | AA71: 6677.469 | AB71: 6932.828 | AC71: 7080.325 | AE71: =O71 -> 4155.58 | AF71: =P71 -> 4316.87 | AG71: =Q71 -> 4473.962 | AH71: =R71 -> 4637.601 | AI71: =S71 -> 4762.395 | AJ71: =T71 -> 4874.208 | AK71: =U71 -> 5011.427 | AL71: =V71 -> 5145.172 | ... AS71: =AC71 -> 7080.325 | AU71: =SUM(AS71/AO71)-1 -> 0.20252066
B72: Treasury stock at cost | C72: 0 | D72: 0 | E72: 0 | F72: -824.19 | G72: -824.19 | H72: -6922.2 | I72: -13171.638 | K72: 0 | L72: -500.022 | M72: -600.022 | N72: =F72 -> -824.19 | O72: -824.19 | P72: -824.19 | Q72: -824.19 | R72: =G72 -> -824.19 | S72: -1228.92 | T72: -1876.753 | U72: -4399.677 | V72: =H72 -> -6922.2 | W72: -8934.056 | X72: -10547.055 | Y72: -12254.855 | Z72: =I72 -> -13171.638 | AA72: -16754.929 | AB72: -18392.942 | AC72: -20270.631 | AE72: =O72 -> -824.19 | AF72: =P72 -> -824.19 | AG72: =Q72 -> -824.19 | AH72: =R72 -> -824.19 | AI72: =S72 -> -1228.92 | AJ72: =T72 -> -1876.753 | AK72: =U72 -> -4399.677 | AL72: =V72 -> -6922.2 | ... AS72: =AC72 -> -20270.631 | AU72: =SUM(AS72/AO72)-1 -> 0.65408983
B73: Accumulated other comprehensive income (loss) | C73: -19.582 | D73: -23.521 | E73: 44.398 | F73: -40.495 | G73: -217.306 | H73: -223.945 | I73: 362.162 | K73: 4.137 | L73: 9.775 | M73: -19.835 | N73: =F73 -> -40.495 | O73: -74.17 | P73: -144.476 | Q73: -247.643 | R73: =G73 -> -217.306 | S73: -191.695 | T73: -139.266 | U73: -155.571 | V73: =H73 -> -223.945 | W73: -111.879 | X73: -89.114 | Y73: -344.622 | Z73: =I73 -> 362.162 | AA73: -85.735 | AB73: -904.668 | AC73: -719.256 | AE73: =O73 -> -74.17 | AF73: =P73 -> -144.476 | AG73: =Q73 -> -247.643 | AH73: =R73 -> -217.306 | AI73: =S73 -> -191.695 | AJ73: =T73 -> -139.266 | AK73: =U73 -> -155.571 | AL73: =V73 -> -223.945 | ... AS73: =AC73 -> -719.256 | AU73: =SUM(AS73/AO73)-1 -> 1.0870867
B74: Retained earnings | C74: 2942.359 | D74: 4811.749 | E74: 7573.144 | F74: 12689.372 | G74: 17181.296 | H74: 22589.286 | I74: 31300.917 | K74: 9279.859 | L74: 10632.872 | M74: 12081.943 | N74: =F74 -> 12689.372 | O74: 14286.819 | P74: 15727.77 | Q74: 17126.012 | R74: =G74 -> 17181.296 | S74: 18486.416 | T74: 19974.026 | U74: 21651.448 | V74: =H74 -> 22589.286 | W74: 24921.495 | X74: 27068.801 | Y74: 29432.31 | Z74: =I74 -> 31300.917 | AA74: 34191.268 | AB74: 37316.681 | AC74: 39863.597 | AE74: =O74 -> 14286.819 | AF74: =P74 -> 15727.77 | AG74: =Q74 -> 17126.012 | AH74: =R74 -> 17181.296 | AI74: =S74 -> 18486.416 | AJ74: =T74 -> 19974.026 | AK74: =U74 -> 21651.448 | AL74: =V74 -> 22589.286 | ... AS74: =AC74 -> 39863.597 | AU74: =SUM(AS74/AO74)-1 -> 0.35441618
B75: Total stockholders' equity | C75: =SUM(C71:C74) -> 5238.765 | D75: =SUM(D71:D74) -> 7582.157 | E75: =SUM(E71:E74) -> 11065.24 | F75: =SUM(F71:F74) -> 15849.248 | G75: =SUM(G71:G74) -> 20777.401 | H75: =SUM(H71:H74) -> 20588.313 | I75: =SUM(I71:I74) -> 24743.567 | K75: =SUM(K71:K74) -> 12884.08 | L75: =SUM(L71:L74) -> 13863.871 | M75: =SUM(M71:M74) -> 15314.617 | N75: =SUM(N71:N74) -> 15849.248 | O75: =SUM(O71:O74) -> 17544.039 | P75: =SUM(P71:P74) -> 19075.974 | Q75: =SUM(Q71:Q74) -> 20528.141 | R75: =SUM(R71:R74) -> 20777.401 | ... AC75: =SUM(AC71:AC74) -> 25954.035 | AE75: =SUM(AE71:AE74) -> 17544.039 | AF75: =SUM(AF71:AF74) -> 19075.974 | AG75: =SUM(AG71:AG74) -> 20528.141 | AH75: =SUM(AH71:AH74) -> 20777.401 | AI75: =SUM(AI71:AI74) -> 21828.196 | AJ75: =SUM(AJ71:AJ74) -> 22832.215 | AK75: =SUM(AK71:AK74) -> 22107.627 | AL75: =SUM(AL71:AL74) -> 20588.313 | ... AS75: =SUM(AS71:AS74) -> 25954.035 | AU75: =SUM(AS75/AO75)-1 -> 0.14230609
B76: Total liabilities and stockholders' equity | C76: =SUM(C75+C69) -> 25974.4 | D76: =SUM(D75+D69) -> 33975.712 | E76: =SUM(E75+E69) -> 39280.359 | F76: =SUM(F75+F69) -> 44584.663 | G76: =SUM(G75+G69) -> 48594.768 | H76: =SUM(H75+H69) -> 48731.992 | I76: =SUM(I75+I69) -> 53630.374 | K76: =SUM(K75+K69) -> 40123.014 | L76: =SUM(L75+L69) -> 40970.969 | M76: =SUM(M75+M69) -> 42739.857 | N76: =SUM(N75+N69) -> 44584.663 | O76: =SUM(O75+O69) -> 45330.904 | P76: =SUM(P75+P69) -> 46350.935 | Q76: =SUM(Q75+Q69) -> 47562.187 | R76: =SUM(R75+R69) -> 48594.768 | ... AC76: =SUM(AC75+AC69) -> 54934.835 | AE76: =SUM(AE75+AE69) -> 45330.904 | AF76: =SUM(AF75+AF69) -> 46350.935 | AG76: =SUM(AG75+AG69) -> 47562.187 | AH76: =SUM(AH75+AH69) -> 48594.768 | AI76: =SUM(AI75+AI69) -> 49490.345 | AJ76: =SUM(AJ75+AJ69) -> 50817.473 | AK76: =SUM(AK75+AK69) -> 49501.786 | AL76: =SUM(AL75+AL69) -> 48731.992 | ... AS76: =SUM(AS75+AS69) -> 54934.835 | AU76: =SUM(AS76/AO76)-1 -> 0.050744021
B78: Balance Check | C78: =C76-C55 -> 0 | D78: =D76-D55 -> 0 | E78: =E76-E55 -> 0 | F78: =F76-F55 -> 0 | G78: =G76-G55 -> 0 | H78: =H76-H55 -> 0 | I78: =I76-I55 -> 0 | K78: =K76-K55 -> 0 | L78: =L76-L55 -> 0 | M78: =M76-M55 -> 0 | N78: =N76-N55 -> 0 | O78: =O76-O55 -> 0 | P78: =P76-P55 -> 0 | Q78: =Q76-Q55 -> 0 | R78: =R76-R55 -> 0 | ... AC78: =AC76-AC55 -> 0 | AE78: =AE76-AE55 -> 0 | AF78: =AF76-AF55 -> 0 | AG78: =AG76-AG55 -> 0 | AH78: =AH76-AH55 -> 0 | AI78: =AI76-AI55 -> 0 | AJ78: =AJ76-AJ55 -> 0 | AK78: =AK76-AK55 -> 0 | AL78: =AL76-AL55 -> 0 | ... AS78: =AS76-AS55 -> 0
A81: X | B81: Cash-Flows Statement | AN81: LTM | AU81: Variance
B82: =B7 -> Fiscal Period | C82: =C7 -> 2018 | D82: =D7 -> 2019 | E82: =E7 -> 2020 | F82: =F7 -> 2021 | G82: =G7 -> 2022 | H82: =H7 -> 2023 | I82: =I7 -> 2024 | K82: =K7 -> 1Q21 | L82: =L7 -> 2Q21 | M82: =M7 -> 3Q21 | N82: =N7 -> 4Q21 | O82: =O7 -> 1Q22 | P82: =P7 -> 2Q22 | Q82: =Q7 -> 3Q22 | R82: =R7 -> 4Q22 | ... AC82: =AC7 -> 3Q25 | AE82: =AE7 -> 1Q22 | AF82: =AF7 -> 2Q22 | AG82: =AG7 -> 3Q22 | AH82: =AH7 -> 4Q22 | AI82: =AI7 -> 1Q23 | AJ82: =AJ7 -> 2Q23 | AK82: =AK7 -> 3Q23 | AL82: =AL7 -> 4Q23 | ... AS82: =AS7 -> 3Q25
B83: =B8 -> Fiscal Period End Date | C83: =C8 -> 43465 | D83: =D8 -> 43830 | E83: =E8 -> 44196 | F83: =F8 -> 44561 | G83: =G8 -> 44926 | H83: =H8 -> 45291 | I83: =I8 -> 45657 | K83: =K8 -> 44286 | L83: =L8 -> 44377 | M83: =M8 -> 44469 | N83: =N8 -> 44561 | O83: =O8 -> 44651 | P83: =P8 -> 44742 | Q83: =Q8 -> 44834 | R83: =R8 -> 44926 | ... AC83: =AC8 -> 45930 | AE83: =AE8 -> 44651 | AF83: =AF8 -> 44742 | AG83: =AG8 -> 44834 | AH83: =AH8 -> 44926 | AI83: =AI8 -> 45016 | AJ83: =AJ8 -> 45107 | AK83: =AK8 -> 45199 | AL83: =AL8 -> 45291 | ... AS83: =AS8 -> 45930
B85: Cash-Flows From Operating Activities
B86: Net income (loss) | C86: =C32 -> 1211.242 | D86: =D32 -> 1866.916 | E86: =E32 -> 2761.395 | F86: =F32 -> 5116.228 | G86: =G32 -> 4491.924 | H86: =H32 -> 5407.99 | I86: =I32 -> 8711.631 | K86: =K32 -> 1706.715 | L86: =L32 -> 1353.013 | M86: =M32 -> 1449.071 | N86: =N32 -> 607.429 | O86: =O32 -> 1597.447 | P86: =P32 -> 1440.951 | Q86: =Q32 -> 1398.242 | R86: =R32 -> 55.284 | ... AC86: =AC32 -> 2546.916 | AE86: =SUM(L86:O86) -> 5006.96 | AF86: =SUM(M86:P86) -> 5094.898 | AG86: =SUM(N86:Q86) -> 5044.069 | AH86: =SUM(O86:R86) -> 4491.924 | AI86: =SUM(P86:S86) -> 4199.597 | AJ86: =SUM(Q86:T86) -> 4246.256 | AK86: =SUM(R86:U86) -> 4525.436 | AL86: =SUM(S86:V86) -> 5407.99 | ... AS86: =SUM(Z86:AC86) -> 10431.287 | AU86: =SUM(AS86/AO86)-1 -> 0.34063385
B88: Adjustments to reconcile net income:
B89: Additions to content assets | C89: -13043.437 | D89: -13916.683 | E89: -11779.284 | F89: -17702.202 | G89: -16839.038 | H89: -12554.703 | I89: -16223.617 | K89: -3284.576 | L89: -4096.75 | M89: -4666.237 | N89: =SUM(F89-SUM(K89:M89)) -> -5654.639 | O89: -3584.164 | P89: -4687.011 | Q89: -4582.671 | R89: =SUM(G89-SUM(O89:Q89)) -> -3985.192 | S89: -2458.666 | T89: -3683.007 | U89: -2883.839 | V89: =SUM(H89-SUM(S89:U89)) -> -3529.191 | W89: -3728.967 | X89: -4048.852 | Y89: -4016.396 | Z89: =SUM(I89-SUM(W89:Y89)) -> -4429.402 | AA89: -3549.657 | AB89: -3835.813 | AC89: -4653.935 | AE89: =SUM(L89:O89) -> -18001.79 | AF89: =SUM(M89:P89) -> -18592.051 | AG89: =SUM(N89:Q89) -> -18508.485 | AH89: =SUM(O89:R89) -> -16839.038 | AI89: =SUM(P89:S89) -> -15713.54 | AJ89: =SUM(Q89:T89) -> -14709.536 | AK89: =SUM(R89:U89) -> -13010.704 | AL89: =SUM(S89:V89) -> -12554.703 | ... AS89: =SUM(Z89:AC89) -> -16468.807 | AU89: =SUM(AS89/AO89)-1 -> 0.07474846
B90: Change in content liabilities | C90: 999.88 | D90: -694.011 | E90: -757.433 | F90: 232.898 | G90: 179.31 | H90: -585.602 | I90: -779.135 | K90: -266.04 | L90: -312.208 | M90: -29.246 | N90: =SUM(F90-SUM(K90:M90)) -> 840.392 | O90: -347.149 | P90: 191.228 | Q90: 60.867 | R90: =SUM(G90-SUM(O90:Q90)) -> 274.364 | S90: -354.791 | T90: 46.119 | U90: -325.989 | V90: =SUM(H90-SUM(S90:U90)) -> 49.059 | W90: -189.441 | X90: -366.572 | Y90: -83.585 | Z90: =SUM(I90-SUM(W90:Y90)) -> -139.537 | AA90: -411.253 | AB90: -214.052 | AC90: 24.262 | AE90: =SUM(L90:O90) -> 151.789 | AF90: =SUM(M90:P90) -> 655.225 | AG90: =SUM(N90:Q90) -> 745.338 | AH90: =SUM(O90:R90) -> 179.31 | AI90: =SUM(P90:S90) -> 171.668 | AJ90: =SUM(Q90:T90) -> 26.559 | AK90: =SUM(R90:U90) -> -360.297 | AL90: =SUM(S90:V90) -> -585.602 | ... AS90: =SUM(Z90:AC90) -> -740.58 | AU90: =SUM(AS90/AO90)-1 -> 0.25407467
B91: Amortization of content assets | C91: 7532.088 | D91: 9216.247 | E91: 10806.912 | F91: 12230.367 | G91: 14026.132 | H91: 14197.437 | I91: 15301.517 | K91: 2719.196 | L91: 2806.803 | M91: 2963.051 | N91: =SUM(F91-SUM(K91:M91)) -> 3741.317 | O91: 3166.365 | P91: 3261.348 | Q91: 3653.592 | R91: =SUM(G91-SUM(O91:Q91)) -> 3944.827 | S91: 3459.984 | T91: 3410.021 | U91: 3573.353 | V91: =SUM(H91-SUM(S91:U91)) -> 3754.079 | W91: 3670.805 | X91: 3769.69 | Y91: 3699.521 | Z91: =SUM(I91-SUM(W91:Y91)) -> 4161.501 | AA91: 3823.112 | AB91: 3832.074 | AC91: 4002.744 | AE91: =SUM(L91:O91) -> 12677.536 | AF91: =SUM(M91:P91) -> 13132.081 | AG91: =SUM(N91:Q91) -> 13822.622 | AH91: =SUM(O91:R91) -> 14026.132 | AI91: =SUM(P91:S91) -> 14319.751 | AJ91: =SUM(Q91:T91) -> 14468.424 | AK91: =SUM(R91:U91) -> 14388.185 | AL91: =SUM(S91:V91) -> 14197.437 | ... AS91: =SUM(Z91:AC91) -> 15819.431 | AU91: =SUM(AS91/AO91)-1 -> 0.062127709
B92: Depreciation and amortization of property, equipment and intangibles | C92: 83.157 | D92: 103.579 | E92: 115.71 | F92: 208.412 | G92: 336.682 | H92: 356.947 | I92: 328.914 | K92: 35.741 | L92: 38.434 | M92: 70.253 | N92: =SUM(F92-SUM(K92:M92)) -> 63.984 | O92: 74.602 | P92: 83.505 | Q92: 85.188 | R92: =SUM(G92-SUM(O92:Q92)) -> 93.387 | S92: 90.335 | T92: 89.385 | U92: 90.66 | V92: =SUM(H92-SUM(S92:U92)) -> 86.567 | W92: 87.234 | X92: 81.227 | Y92: 80.914 | Z92: =SUM(I92-SUM(W92:Y92)) -> 79.539 | AA92: 80.067 | AB92: 80.013 | AC92: 87.326 | AE92: =SUM(L92:O92) -> 247.273 | AF92: =SUM(M92:P92) -> 292.344 | AG92: =SUM(N92:Q92) -> 307.279 | AH92: =SUM(O92:R92) -> 336.682 | AI92: =SUM(P92:S92) -> 352.415 | AJ92: =SUM(Q92:T92) -> 358.295 | AK92: =SUM(R92:U92) -> 363.767 | AL92: =SUM(S92:V92) -> 356.947 | ... AS92: =SUM(Z92:AC92) -> 326.945 | AU92: =SUM(AS92/AO92)-1 -> -0.026781409
B93: Stock-based compensation expense | C93: 320.657 | D93: 405.376 | E93: 415.18 | F93: 403.22 | G93: 575.452 | H93: 339.368 | I93: 272.588 | K93: 107.23 | L93: 101.583 | M93: 95.078 | N93: =SUM(F93-SUM(K93:M93)) -> 99.329 | O93: 119.209 | P93: 150.392 | Q93: 152.062 | R93: =SUM(G93-SUM(O93:Q93)) -> 153.789 | S93: 99.099 | T93: 78.03 | U93: 79.72 | V93: =SUM(H93-SUM(S93:U93)) -> 82.519 | W93: 76.345 | X93: 68.766 | Y93: 65.65 | Z93: =SUM(I93-SUM(W93:Y93)) -> 61.827 | AA93: 71.977 | AB93: 80.862 | AC93: 80.986 | AE93: =SUM(L93:O93) -> 415.199 | AF93: =SUM(M93:P93) -> 464.008 | AG93: =SUM(N93:Q93) -> 520.992 | AH93: =SUM(O93:R93) -> 575.452 | AI93: =SUM(P93:S93) -> 555.342 | AJ93: =SUM(Q93:T93) -> 482.98 | AK93: =SUM(R93:U93) -> 410.638 | AL93: =SUM(S93:V93) -> 339.368 | ... AS93: =SUM(Z93:AC93) -> 295.652 | AU93: =SUM(AS93/AO93)-1 -> 0.0080878342
B94: Foreign currency remeasurement loss (gain) on debt | C94: -73.953 | D94: -45.576 | E94: 533.278 | F94: -430.661 | G94: -353.111 | H94: 176.296 | I94: -121.539 | K94: -253.33 | L94: 63.074 | M94: -136.488 | N94: =SUM(F94-SUM(K94:M94)) -> -103.917 | O94: -161.821 | P94: -304.513 | Q94: -348.458 | R94: =SUM(G94-SUM(O94:Q94)) -> 461.681 | S94: 80.651 | T94: 28.952 | U94: -172.678 | V94: =SUM(H94-SUM(S94:U94)) -> 239.371 | W94: -130.801 | X94: -42.692 | Y94: 104.809 | Z94: =SUM(I94-SUM(W94:Y94)) -> -52.855 | AA94: 28.547 | AB94: 55.238 | AC94: -1.707 | AE94: =SUM(L94:O94) -> -339.152 | AF94: =SUM(M94:P94) -> -706.739 | AG94: =SUM(N94:Q94) -> -918.709 | AH94: =SUM(O94:R94) -> -353.111 | AI94: =SUM(P94:S94) -> -110.639 | AJ94: =SUM(Q94:T94) -> 222.826 | AK94: =SUM(R94:U94) -> 398.606 | AL94: =SUM(S94:V94) -> 176.296 | ... AS94: =SUM(Z94:AC94) -> 29.223 | AU94: =SUM(AS94/AO94)-1 -> -0.82879188
B95: Other non-cash items | C95: 81.64 | D95: 228.23 | E95: 293.126 | F95: 376.777 | G95: 533.543 | H95: 512.075 | I95: 494.778 | K95: 72.657 | L95: 108.103 | M95: 102.211 | N95: =SUM(F95-SUM(K95:M95)) -> 93.806 | O95: 101.968 | P95: 205.374 | Q95: 102.513 | R95: =SUM(G95-SUM(O95:Q95)) -> 123.688 | S95: 120.008 | T95: 121.483 | U95: 115.688 | V95: =SUM(H95-SUM(S95:U95)) -> 154.896 | W95: 97.181 | X95: 138.588 | Y95: 128.082 | Z95: =SUM(I95-SUM(W95:Y95)) -> 130.927 | AA95: 114.73 | AB95: 120.139 | AC95: 142.293 | AE95: =SUM(L95:O95) -> 406.088 | AF95: =SUM(M95:P95) -> 503.359 | AG95: =SUM(N95:Q95) -> 503.661 | AH95: =SUM(O95:R95) -> 533.543 | AI95: =SUM(P95:S95) -> 551.583 | AJ95: =SUM(Q95:T95) -> 467.692 | AK95: =SUM(R95:U95) -> 480.867 | AL95: =SUM(S95:V95) -> 512.075 | ... AS95: =SUM(Z95:AC95) -> 508.089 | AU95: =SUM(AS95/AO95)-1 -> -0.020545661
B96: Deferred income taxes | C96: -85.52 | D96: -94.443 | E96: 70.066 | F96: 199.548 | G96: -166.55 | H96: -459.359 | I96: -590.698 | K96: 159.733 | L96: 51.127 | M96: 50.967 | N96: =SUM(F96-SUM(K96:M96)) -> -62.279 | O96: -68.906 | P96: -115.82 | Q96: -57.797 | R96: =SUM(G96-SUM(O96:Q96)) -> 75.973 | S96: -98.782 | T96: -103.172 | U96: -86.277 | V96: =SUM(H96-SUM(S96:U96)) -> -171.128 | W96: -107.077 | X96: -209.387 | Y96: -200.982 | Z96: =SUM(I96-SUM(W96:Y96)) -> -73.252 | AA96: -163.928 | AB96: -135.755 | AC96: 20.539 | AE96: =SUM(L96:O96) -> -29.091 | AF96: =SUM(M96:P96) -> -196.038 | AG96: =SUM(N96:Q96) -> -304.802 | AH96: =SUM(O96:R96) -> -166.55 | AI96: =SUM(P96:S96) -> -196.426 | AJ96: =SUM(Q96:T96) -> -183.778 | AK96: =SUM(R96:U96) -> -212.258 | AL96: =SUM(S96:V96) -> -459.359 | ... AS96: =SUM(Z96:AC96) -> -352.396 | AU96: =SUM(AS96/AO96)-1 -> -0.48822349
B97: Changes in assets and liabilities:
B98: Other current assets | C98: -200.192 | D98: -252.113 | E98: -187.623 | F98: -369.681 | G98: -353.834 | H98: -181.003 | I98: 22.18 | K98: -221.555 | L98: -52.373 | M98: -95.145 | N98: =SUM(F98-SUM(K98:M98)) -> -0.608 | O98: 41.157 | P98: 123.399 | Q98: -120.071 | R98: =SUM(G98-SUM(O98:Q98)) -> -398.319 | S98: -88.522 | T98: -183.049 | U98: 103.766 | V98: =SUM(H98-SUM(S98:U98)) -> -13.198 | W98: 38.049 | X98: -28.959 | Y98: 54.956 | Z98: =SUM(I98-SUM(W98:Y98)) -> -41.866 | AA98: -131.367 | AB98: -176.683 | AC98: -169.597 | AE98: =SUM(L98:O98) -> -106.969 | AF98: =SUM(M98:P98) -> 68.803 | AG98: =SUM(N98:Q98) -> 43.877 | AH98: =SUM(O98:R98) -> -353.834 | AI98: =SUM(P98:S98) -> -483.513 | AJ98: =SUM(Q98:T98) -> -789.961 | AK98: =SUM(R98:U98) -> -566.124 | AL98: =SUM(S98:V98) -> -181.003 | ... AS98: =SUM(Z98:AC98) -> -519.513 | AU98: =SUM(AS98/AO98)-1 -> -11.21698
B99: Accounts payable | C99: 199.198 | D99: 96.063 | E99: -41.605 | F99: 145.115 | G99: -158.543 | H99: 93.502 | I99: 121.353 | K99: -137.313 | L99: 72.313 | M99: 24.836 | N99: =SUM(F99-SUM(K99:M99)) -> 185.279 | O99: -215.444 | P99: -122.048 | Q99: 53.875 | R99: =SUM(G99-SUM(O99:Q99)) -> 125.074 | S99: -89.668 | T99: 38.332 | U99: -68.39 | V99: =SUM(H99-SUM(S99:U99)) -> 213.228 | W99: -145.265 | X99: -19.358 | Y99: 30.597 | Z99: =SUM(I99-SUM(W99:Y99)) -> 255.379 | AA99: -276.426 | AB99: 11.046 | AC99: 139.451 | AE99: =SUM(L99:O99) -> 66.984 | AF99: =SUM(M99:P99) -> -127.377 | AG99: =SUM(N99:Q99) -> -98.338 | AH99: =SUM(O99:R99) -> -158.543 | AI99: =SUM(P99:S99) -> -32.767 | AJ99: =SUM(Q99:T99) -> 127.613 | AK99: =SUM(R99:U99) -> 5.348 | AL99: =SUM(S99:V99) -> 93.502 | ... AS99: =SUM(Z99:AC99) -> 129.45 | AU99: =SUM(AS99/AO99)-1 -> 0.63442842
B100: Accrued expenses and other liabilities | C100: 150.422 | D100: 157.778 | E100: 198.183 | F100: 180.338 | G100: -55.513 | H100: 103.565 | I100: 191.899 | K100: 177.897 | L100: -171.43 | M100: 269.774 | N100: =SUM(F100-SUM(K100:M100)) -> -95.903 | O100: 350.763 | P100: -238.719 | Q100: 212.072 | R100: =SUM(G100-SUM(O100:Q100)) -> -379.629 | S100: 185.299 | T100: 177.831 | U100: -65.029 | V100: =SUM(H100-SUM(S100:U100)) -> -194.536 | W100: 251.782 | X100: -114.303 | Y100: 179.011 | Z100: =SUM(I100-SUM(W100:Y100)) -> -124.591 | AA100: 306.413 | AB100: -267.235 | AC100: 707.151 | AE100: =SUM(L100:O100) -> 353.204 | AF100: =SUM(M100:P100) -> 285.915 | AG100: =SUM(N100:Q100) -> 228.213 | AH100: =SUM(O100:R100) -> -55.513 | AI100: =SUM(P100:S100) -> -220.977 | AJ100: =SUM(Q100:T100) -> 195.573 | AK100: =SUM(R100:U100) -> -81.528 | AL100: =SUM(S100:V100) -> 103.565 | ... AS100: =SUM(Z100:AC100) -> 621.738 | AU100: =SUM(AS100/AO100)-1 -> 4.0981354
B101: Deferred revenue | C101: 142.277 | D101: 163.846 | E101: 193.247 | F101: 91.35 | G101: 27.356 | H101: 178.708 | I101: 77.844 | K101: 22.279 | L101: 47.093 | M101: -4.732 | N101: =SUM(F101-SUM(K101:M101)) -> 26.71 | O101: 16.743 | P101: -10.376 | Q101: -48.42 | R101: =SUM(G101-SUM(O101:Q101)) -> 69.409 | S101: -2.39 | T101: 49.647 | U101: -5.733 | V101: =SUM(H101-SUM(S101:U101)) -> 137.184 | W101: 26.515 | X101: 4.236 | Y101: 39.328 | Z101: =SUM(I101-SUM(W101:Y101)) -> 7.765 | AA101: 88.913 | AB101: 118.635 | AC101: -3.686 | AE101: =SUM(L101:O101) -> 85.814 | AF101: =SUM(M101:P101) -> 28.345 | AG101: =SUM(N101:Q101) -> -15.343 | AH101: =SUM(O101:R101) -> 27.356 | AI101: =SUM(P101:S101) -> 8.223 | AJ101: =SUM(Q101:T101) -> 68.246 | AK101: =SUM(R101:U101) -> 110.933 | AL101: =SUM(S101:V101) -> 178.708 | ... AS101: =SUM(Z101:AC101) -> 211.627 | AU101: =SUM(AS101/AO101)-1 -> 0.021055374
B102: Other non-current assets and liabilities | C102: 2.062 | D102: -122.531 | E102: -194.075 | F102: -289.099 | G102: -217.553 | H102: -310.92 | I102: -446.351 | K102: -61.368 | L102: -72.543 | M102: -11.014 | N102: =SUM(F102-SUM(K102:M102)) -> -144.174 | O102: -167.931 | P102: 125.04 | Q102: -4.184 | R102: =SUM(G102-SUM(O102:Q102)) -> -170.478 | S102: -68.937 | T102: -117.95 | U102: -40.359 | V102: =SUM(H102-SUM(S102:U102)) -> -83.674 | W102: -66.047 | X102: -88.843 | Y102: -124.313 | Z102: =SUM(I102-SUM(W102:Y102)) -> -167.148 | AA102: -82.28 | AB102: -370.624 | AC102: -97.569 | AE102: =SUM(L102:O102) -> -395.662 | AF102: =SUM(M102:P102) -> -198.079 | AG102: =SUM(N102:Q102) -> -191.249 | AH102: =SUM(O102:R102) -> -217.553 | AI102: =SUM(P102:S102) -> -118.559 | AJ102: =SUM(Q102:T102) -> -361.549 | AK102: =SUM(R102:U102) -> -397.724 | AL102: =SUM(S102:V102) -> -310.92 | ... AS102: =SUM(Z102:AC102) -> -717.621 | AU102: =SUM(AS102/AO102)-1 -> 0.97758745
B103: Net cash used in operating activities | C103: =SUM(C86:C102) -> -2680.479 | D103: =SUM(D86:D102) -> -2887.322 | E103: =SUM(E86:E102) -> 2427.077 | F103: =SUM(F86:F102) -> 392.61 | G103: =SUM(G86:G102) -> 2026.257 | H103: =SUM(H86:H102) -> 7274.301 | I103: =SUM(I86:I102) -> 7361.364 | K103: =SUM(K86:K102) -> 777.266 | L103: =SUM(L86:L102) -> -63.761 | M103: =SUM(M86:M102) -> 82.379 | N103: =SUM(N86:N102) -> -403.274 | O103: =SUM(O86:O102) -> 922.839 | P103: =SUM(P86:P102) -> 102.75 | Q103: =SUM(Q86:Q102) -> 556.81 | R103: =SUM(R86:R102) -> 443.858 | ... AC103: =SUM(AC86:AC102) -> 2825.174 | AE103: =SUM(AE86:AE102) -> 538.183 | AF103: =SUM(AF86:AF102) -> 704.694 | AG103: =SUM(AG86:AG102) -> 1179.125 | AH103: =SUM(AH86:AH102) -> 2026.257 | AI103: =SUM(AI86:AI102) -> 3282.158 | AJ103: =SUM(AJ86:AJ102) -> 4619.64 | AK103: =SUM(AK86:AK102) -> 6055.145 | AL103: =SUM(AL86:AL102) -> 7274.301 | ... AS103: =SUM(AS86:AS102) -> 9574.525 | AU103: =SUM(AS103/AO103)-1 -> 0.27873729
B105: Cash flows from investing activities:
B106: Purchases of property and equipment | C106: -173.946 | D106: -253.035 | E106: -497.923 | F106: -524.585 | G106: -407.729 | H106: -348.552 | I106: -439.538 | K106: -81.001 | L106: -110.278 | M106: -167.327 | N106: =SUM(F106-SUM(K106:M106)) -> -165.979 | O106: -121.158 | P106: -90.018 | Q106: -84.96 | R106: =SUM(G106-SUM(O106:Q106)) -> -111.593 | S106: -62.019 | T106: -100.972 | U106: -103.929 | V106: =SUM(H106-SUM(S106:U106)) -> -81.632 | W106: -75.714 | X106: -78.287 | Y106: -126.863 | Z106: =SUM(I106-SUM(W106:Y106)) -> -158.674 | AA106: -128.277 | AB106: -155.889 | AC106: -164.719 | AE106: =SUM(L106:O106) -> -564.742 | AF106: =SUM(M106:P106) -> -544.482 | AG106: =SUM(N106:Q106) -> -462.115 | AH106: =SUM(O106:R106) -> -407.729 | AI106: =SUM(P106:S106) -> -348.59 | AJ106: =SUM(Q106:T106) -> -359.544 | AK106: =SUM(R106:U106) -> -378.513 | AL106: =SUM(S106:V106) -> -348.552 | ... AS106: =SUM(Z106:AC106) -> -607.559 | AU106: =SUM(AS106/AO106)-1 -> 0.67604332
B107: Change in other assets | C107: -165.174 | D107: -134.029 | E107: -7.431 | F107: -26.919 | G107: 0 | H107: 0 | I107: 0 | K107: -4.615 | L107: -1 | M107: -21.304 | N107: =SUM(F107-SUM(K107:M107)) -> -3.5527137e-15 | O107: 0 | P107: 0 | Q107: 0 | R107: =SUM(G107-SUM(O107:Q107)) -> 0 | S107: 0 | T107: 0 | U107: 0 | V107: =SUM(H107-SUM(S107:U107)) -> 0 | W107: 0 | X107: 0 | Y107: 0 | Z107: =SUM(I107-SUM(W107:Y107)) -> 0 | AA107: 0 | AB107: 0 | AC107: 0 | AE107: =SUM(L107:O107) -> -22.304 | AF107: =SUM(M107:P107) -> -21.304 | AG107: =SUM(N107:Q107) -> -3.5527137e-15 | AH107: =SUM(O107:R107) -> 0 | AI107: =SUM(P107:S107) -> 0 | AJ107: =SUM(Q107:T107) -> 0 | AK107: =SUM(R107:U107) -> 0 | AL107: =SUM(S107:V107) -> 0 | ... AS107: =SUM(Z107:AC107) -> 0 | AU107: =SUM(AS107/AO107)-1 -> #DIV/0!
B108: Acquisitions | C108: 0 | D108: 0 | E108: 0 | F108: -788.349 | G108: -757.387 | H108: 0 | I108: 0 | K108: 0 | L108: 0 | M108: 0 | N108: =SUM(F108-SUM(K108:M108)) -> -788.349 | O108: -124.521 | P108: -68.876 | Q108: 0 | R108: =SUM(G108-SUM(O108:Q108)) -> -563.99 | S108: 0 | T108: 0 | U108: 0 | V108: =SUM(H108-SUM(S108:U108)) -> 0 | W108: 0 | X108: 0 | Y108: 0 | Z108: =SUM(I108-SUM(W108:Y108)) -> 0 | AA108: 0 | AB108: -36.19 | AC108: 36.19 | AE108: =SUM(L108:O108) -> -912.87 | AF108: =SUM(M108:P108) -> -981.746 | AG108: =SUM(N108:Q108) -> -981.746 | AH108: =SUM(O108:R108) -> -757.387 | AI108: =SUM(P108:S108) -> -632.866 | AJ108: =SUM(Q108:T108) -> -563.99 | AK108: =SUM(R108:U108) -> -563.99 | AL108: =SUM(S108:V108) -> 0 | ... AS108: =SUM(Z108:AC108) -> 0 | AU108: =SUM(AS108/AO108)-1 -> #DIV/0!
B109: Purchases of short-term investments | C109: 0 | D109: 0 | E109: 0 | F109: 0 | G109: -911.276 | H109: -504.862 | I109: -1742.246 | K109: 0 | L109: 0 | M109: 0 | N109: =SUM(F109-SUM(K109:M109)) -> 0 | O109: 0 | P109: 0 | Q109: 0 | R109: =SUM(G109-SUM(O109:Q109)) -> -911.276 | S109: -201.634 | T109: -303.228 | U109: 0 | V109: =SUM(H109-SUM(S109:U109)) -> -5.6843419e-14 | W109: 0 | X109: 0 | Y109: -1742.246 | Z109: =SUM(I109-SUM(W109:Y109)) -> 0 | AA109: -156.015 | AB109: -1.65 | AC109: -3.85 | AE109: =SUM(L109:O109) -> 0 | AF109: =SUM(M109:P109) -> 0 | AG109: =SUM(N109:Q109) -> 0 | AH109: =SUM(O109:R109) -> -911.276 | AI109: =SUM(P109:S109) -> -1112.91 | AJ109: =SUM(Q109:T109) -> -1416.138 | AK109: =SUM(R109:U109) -> -1416.138 | AL109: =SUM(S109:V109) -> -504.862 | ... AS109: =SUM(Z109:AC109) -> -161.515 | AU109: =SUM(AS109/AO109)-1 -> -0.90729495
B110: Proceeds from maturities of short-term investments | C110: 0 | D110: 0 | E110: 0 | F110: 0 | G110: 0 | H110: 1395.165 | I110: 0 | K110: 0 | L110: 0 | M110: 0 | N110: =SUM(F110-SUM(K110:M110)) -> 0 | O110: 0 | P110: 0 | Q110: 0 | R110: =SUM(G110-SUM(O110:Q110)) -> 0 | S110: 0 | T110: 501.937 | U110: 400 | V110: =SUM(H110-SUM(S110:U110)) -> 493.228 | W110: 0 | X110: 0 | Y110: 0 | Z110: =SUM(I110-SUM(W110:Y110)) -> 0 | AA110: 769.954 | AB110: 962.413 | AC110: 176.25 | AE110: =SUM(L110:O110) -> 0 | AF110: =SUM(M110:P110) -> 0 | AG110: =SUM(N110:Q110) -> 0 | AH110: =SUM(O110:R110) -> 0 | AI110: =SUM(P110:S110) -> 0 | AJ110: =SUM(Q110:T110) -> 501.937 | AK110: =SUM(R110:U110) -> 901.937 | AL110: =SUM(S110:V110) -> 1395.165 | ... AS110: =SUM(Z110:AC110) -> 1908.617 | AU110: =SUM(AS110/AO110)-1 -> 2.8696445
B111: Net cash used in investing activities | C111: =SUM(C106:C110) -> -339.12 | D111: =SUM(D106:D110) -> -387.064 | E111: =SUM(E106:E110) -> -505.354 | F111: =SUM(F106:F110) -> -1339.853 | G111: =SUM(G106:G110) -> -2076.392 | H111: =SUM(H106:H110) -> 541.751 | I111: =SUM(I106:I110) -> -2181.784 | K111: =SUM(K106:K110) -> -85.616 | L111: =SUM(L106:L110) -> -111.278 | M111: =SUM(M106:M110) -> -188.631 | N111: =SUM(N106:N110) -> -954.328 | O111: =SUM(O106:O110) -> -245.679 | P111: =SUM(P106:P110) -> -158.894 | Q111: =SUM(Q106:Q110) -> -84.96 | R111: =SUM(R106:R110) -> -1586.859 | ... AC111: =SUM(AC106:AC110) -> 43.871 | AE111: =SUM(AE106:AE110) -> -1499.916 | AF111: =SUM(AF106:AF110) -> -1547.532 | AG111: =SUM(AG106:AG110) -> -1443.861 | AH111: =SUM(AH106:AH110) -> -2076.392 | AI111: =SUM(AI106:AI110) -> -2094.366 | AJ111: =SUM(AJ106:AJ110) -> -1837.735 | AK111: =SUM(AK106:AK110) -> -1456.704 | AL111: =SUM(AL106:AL110) -> 541.751 | ... AS111: =SUM(AS106:AS110) -> 1139.543 | AU111: =SUM(AS111/AO111)-1 -> -1.7071257
B113: Cash flows from financing activities:
B114: Proceeds from issuance of debt | C114: 3961.852 | D114: 4469.306 | E114: 1009.464 | F114: 0 | G114: 0 | H114: 0 | I114: 1794.46 | K114: 0 | L114: 0 | M114: 0 | N114: =SUM(F114-SUM(K114:M114)) -> 0 | O114: 0 | P114: 0 | Q114: 0 | R114: =SUM(G114-SUM(O114:Q114)) -> 0 | S114: 0 | T114: 0 | U114: 0 | V114: =SUM(H114-SUM(S114:U114)) -> 0 | W114: 0 | X114: 0 | Y114: 1794.46 | Z114: =SUM(I114-SUM(W114:Y114)) -> 0 | AA114: 0 | AB114: 0 | AC114: 0 | AE114: =SUM(L114:O114) -> 0 | AF114: =SUM(M114:P114) -> 0 | AG114: =SUM(N114:Q114) -> 0 | AH114: =SUM(O114:R114) -> 0 | AI114: =SUM(P114:S114) -> 0 | AJ114: =SUM(Q114:T114) -> 0 | AK114: =SUM(R114:U114) -> 0 | AL114: =SUM(S114:V114) -> 0 | ... AS114: =SUM(Z114:AC114) -> 0 | AU114: =SUM(AS114/AO114)-1 -> -1
B115: Debt issuance costs | C115: -35.871 | D115: -36.134 | E115: -7.559 | F115: 0 | G115: 0 | H115: 0 | I115: 0 | K115: 0 | L115: 0 | M115: 0 | N115: =SUM(F115-SUM(K115:M115)) -> 0 | O115: 0 | P115: 0 | Q115: 0 | R115: =SUM(G115-SUM(O115:Q115)) -> 0 | S115: 0 | T115: 0 | U115: 0 | V115: =SUM(H115-SUM(S115:U115)) -> 0 | W115: 0 | X115: 0 | Y115: 0 | Z115: =SUM(I115-SUM(W115:Y115)) -> 0 | AA115: 0 | AB115: 0 | AC115: 0 | AE115: =SUM(L115:O115) -> 0 | AF115: =SUM(M115:P115) -> 0 | AG115: =SUM(N115:Q115) -> 0 | AH115: =SUM(O115:R115) -> 0 | AI115: =SUM(P115:S115) -> 0 | AJ115: =SUM(Q115:T115) -> 0 | AK115: =SUM(R115:U115) -> 0 | AL115: =SUM(S115:V115) -> 0 | ... AS115: =SUM(Z115:AC115) -> 0 | AU115: =SUM(AS115/AO115)-1 -> #DIV/0!
B116: Repayments of debt | C116: 0 | D116: 0 | E116: 0 | F116: -500 | G116: -700 | H116: 0 | I116: -400 | K116: -500 | L116: 0 | M116: 0 | N116: =SUM(F116-SUM(K116:M116)) -> 0 | O116: -700 | P116: 0 | Q116: 0 | R116: =SUM(G116-SUM(O116:Q116)) -> 0 | S116: 0 | T116: 0 | U116: 0 | V116: =SUM(H116-SUM(S116:U116)) -> 0 | W116: -400 | X116: 0 | Y116: 0 | Z116: =SUM(I116-SUM(W116:Y116)) -> 0 | AA116: -800 | AB116: -1033.45 | AC116: 0 | AE116: =SUM(L116:O116) -> -700 | AF116: =SUM(M116:P116) -> -700 | AG116: =SUM(N116:Q116) -> -700 | AH116: =SUM(O116:R116) -> -700 | AI116: =SUM(P116:S116) -> 0 | AJ116: =SUM(Q116:T116) -> 0 | AK116: =SUM(R116:U116) -> 0 | AL116: =SUM(S116:V116) -> 0 | ... AS116: =SUM(Z116:AC116) -> -1833.45 | AU116: =SUM(AS116/AO116)-1 -> 3.583625
B117: Proceeds from issuance of common stock | C117: 124.502 | D117: 72.49 | E117: 235.406 | F117: 174.414 | G117: 35.746 | H117: 169.99 | I117: 832.887 | K117: 48.071 | L117: 19.749 | M117: 18.445 | N117: =SUM(F117-SUM(K117:M117)) -> 88.149 | O117: 13.678 | P117: 11.25 | Q117: 4.113 | R117: =SUM(G117-SUM(O117:Q117)) -> 6.705 | S117: 26.028 | T117: 34.717 | U117: 57.818 | V117: =SUM(H117-SUM(S117:U117)) -> 51.427 | W117: 268.881 | X117: 118.75 | Y117: 143.244 | Z117: =SUM(I117-SUM(W117:Y117)) -> 302.012 | AA117: 351.602 | AB117: 169.066 | AC117: 70.215 | AE117: =SUM(L117:O117) -> 140.021 | AF117: =SUM(M117:P117) -> 131.522 | AG117: =SUM(N117:Q117) -> 117.19 | AH117: =SUM(O117:R117) -> 35.746 | AI117: =SUM(P117:S117) -> 48.096 | AJ117: =SUM(Q117:T117) -> 71.563 | AK117: =SUM(R117:U117) -> 125.268 | AL117: =SUM(S117:V117) -> 169.99 | ... AS117: =SUM(Z117:AC117) -> 892.895 | AU117: =SUM(AS117/AO117)-1 -> 0.53338817
B118: Repurchases of common stock | C118: 0 | D118: 0 | E118: 0 | F118: -600.022 | G118: 0 | H118: -6045.347 | I118: -6263.746 | K118: 0 | L118: -500.022 | M118: -100 | N118: =SUM(F118-SUM(K118:M118)) -> -1.1368684e-13 | O118: 0 | P118: 0 | Q118: 0 | R118: =SUM(G118-SUM(O118:Q118)) -> 0 | S118: -400.101 | T118: -645.146 | U118: -2500.1 | V118: =SUM(H118-SUM(S118:U118)) -> -2500 | W118: -2000 | X118: -1599.998 | Y118: -1700 | Z118: =SUM(I118-SUM(W118:Y118)) -> -963.748 | AA118: -3536.396 | AB118: -1654.327 | AC118: -1856.885 | AE118: =SUM(L118:O118) -> -600.022 | AF118: =SUM(M118:P118) -> -100 | AG118: =SUM(N118:Q118) -> -1.1368684e-13 | AH118: =SUM(O118:R118) -> 0 | AI118: =SUM(P118:S118) -> -400.101 | AJ118: =SUM(Q118:T118) -> -1045.247 | AK118: =SUM(R118:U118) -> -3545.347 | AL118: =SUM(S118:V118) -> -6045.347 | ... AS118: =SUM(Z118:AC118) -> -8011.356 | AU118: =SUM(AS118/AO118)-1 -> 0.027097186
B119: Taxes paid related to net share settlement of equity awards | C119: 0 | D119: 0 | E119: 0 | F119: -224.168 | G119: 0 | H119: 0 | I119: -8.285 | K119: 0 | L119: 0 | M119: 0 | N119: =SUM(F119-SUM(K119:M119)) -> -224.168 | O119: 0 | P119: 0 | Q119: 0 | R119: =SUM(G119-SUM(O119:Q119)) -> 0 | S119: 0 | T119: 0 | U119: 0 | V119: =SUM(H119-SUM(S119:U119)) -> 0 | W119: -1.825 | X119: -1.883 | Y119: -2.024 | Z119: =SUM(I119-SUM(W119:Y119)) -> -2.553 | AA119: -27.87 | AB119: -6.114 | AC119: -6.196 | AE119: =SUM(L119:O119) -> -224.168 | AF119: =SUM(M119:P119) -> -224.168 | AG119: =SUM(N119:Q119) -> -224.168 | AH119: =SUM(O119:R119) -> 0 | AI119: =SUM(P119:S119) -> 0 | AJ119: =SUM(Q119:T119) -> 0 | AK119: =SUM(R119:U119) -> 0 | AL119: =SUM(S119:V119) -> 0 | ... AS119: =SUM(Z119:AC119) -> -42.733 | AU119: =SUM(AS119/AO119)-1 -> 6.455164
B120: Other financing activities | C120: -1.956 | D120: 0 | E120: 0 | F120: 0 | G120: 0 | H120: -75.446 | I120: -29.743 | K120: 0 | L120: 0 | M120: 0 | N120: =SUM(F120-SUM(K120:M120)) -> 0 | O120: 0 | P120: 0 | Q120: 0 | R120: =SUM(G120-SUM(O120:Q120)) -> 0 | S120: 0 | T120: -38.92 | U120: -32.826 | V120: =SUM(H120-SUM(S120:U120)) -> -3.7 | W120: 0 | X120: -6.25 | Y120: -9.084 | Z120: =SUM(I120-SUM(W120:Y120)) -> -14.409 | AA120: -15.652 | AB120: 21.957 | AC120: 55.837 | AE120: =SUM(L120:O120) -> 0 | AF120: =SUM(M120:P120) -> 0 | AG120: =SUM(N120:Q120) -> 0 | AH120: =SUM(O120:R120) -> 0 | AI120: =SUM(P120:S120) -> 0 | AJ120: =SUM(Q120:T120) -> -38.92 | AK120: =SUM(R120:U120) -> -71.746 | AL120: =SUM(S120:V120) -> -75.446 | ... AS120: =SUM(Z120:AC120) -> 47.733 | AU120: =SUM(AS120/AO120)-1 -> -3.5077756
B121: Net cash provided by financing activities | C121: =SUM(C114:C120) -> 4048.527 | D121: =SUM(D114:D120) -> 4505.662 | E121: =SUM(E114:E120) -> 1237.311 | F121: =SUM(F114:F120) -> -1149.776 | G121: =SUM(G114:G120) -> -664.254 | H121: =SUM(H114:H120) -> -5950.803 | I121: =SUM(I114:I120) -> -4074.427 | K121: =SUM(K114:K120) -> -451.929 | L121: =SUM(L114:L120) -> -480.273 | M121: =SUM(M114:M120) -> -81.555 | N121: =SUM(N114:N120) -> -136.019 | O121: =SUM(O114:O120) -> -686.322 | P121: =SUM(P114:P120) -> 11.25 | Q121: =SUM(Q114:Q120) -> 4.113 | R121: =SUM(R114:R120) -> 6.705 | ... AC121: =SUM(AC114:AC120) -> -1737.029 | AE121: =SUM(AE114:AE120) -> -1384.169 | AF121: =SUM(AF114:AF120) -> -892.646 | AG121: =SUM(AG114:AG120) -> -806.978 | AH121: =SUM(AH114:AH120) -> -664.254 | AI121: =SUM(AI114:AI120) -> -352.005 | AJ121: =SUM(AJ114:AJ120) -> -1012.604 | AK121: =SUM(AK114:AK120) -> -3491.825 | AL121: =SUM(AL114:AL120) -> -5950.803 | ... AS121: =SUM(AS114:AS120) -> -8946.911 | AU121: =SUM(AS121/AO121)-1 -> 0.52990902
B124: Unrestricted Cash BOP | C124: 2822.795 | D124: =C131 -> 3794.483 | E124: =D131 -> 5018.437 | F124: =E131 -> 8205.55 | G124: =F131 -> 6027.804 | H124: =G131 -> 5147.176 | I124: =H131 -> 7116.913 | K124: =E131 -> 8205.55 | L124: =K131 -> 8403.705 | M124: =L131 -> 7777.53 | N124: =M131 -> 7526.681 | O124: =N131 -> 6027.804 | P124: =O131 -> 6008.946 | Q124: =P131 -> 5819.449 | R124: =Q131 -> 6113.733 | S124: =R131 -> 5147.176 | ... AC124: =AB131 -> 8177.405 | AE124: =K131 -> 8403.705 | AF124: =L131 -> 7777.53 | AG124: =M131 -> 7526.681 | AH124: =N131 -> 6027.804 | AI124: =O131 -> 6008.946 | AJ124: =P131 -> 5819.449 | AK124: =Q131 -> 6113.733 | AL124: =R131 -> 5147.176 | ... AS124: =Y131 -> 7457.025
...

Sheet Revenue Drivers
B2: Netflix, Inc. (NASDAQ: NFLX) | C2: FYE | G2: FYE | K2: Quarterly | S2: Quarterly | T2: Quarterly | AA2: LTM | AE2: LTM | AG2: LTM | AM2: Variance
B3: Segment Anaysis | C3: ='Historical Financials'!C7 -> 2018 | D3: ='Historical Financials'!D7 -> 2019 | E3: ='Historical Financials'!E7 -> 2020 | F3: ='Historical Financials'!F7 -> 2021 | G3: ='Historical Financials'!G7 -> 2022 | H3: ='Historical Financials'!H7 -> 2023 | I3: ='Historical Financials'!I7 -> 2024 | K3: ='Historical Financials'!O7 -> 1Q22 | L3: ='Historical Financials'!P7 -> 2Q22 | M3: ='Historical Financials'!Q7 -> 3Q22 | N3: ='Historical Financials'!R7 -> 4Q22 | O3: ='Historical Financials'!S7 -> 1Q23 | P3: ='Historical Financials'!T7 -> 2Q23 | Q3: ='Historical Financials'!U7 -> 3Q23 | R3: ='Historical Financials'!V7 -> 4Q23 | ... Y3: ='Historical Financials'!AC7 -> 3Q25 | AA3: =O3 -> 1Q23 | AB3: =P3 -> 2Q23 | AC3: =Q3 -> 3Q23 | AD3: =R3 -> 4Q23 | AE3: =S3 -> 1Q24 | AF3: =T3 -> 2Q24 | AG3: =U3 -> 3Q24 | AH3: =V3 -> 4Q24 | ... AK3: =Y3 -> 3Q25
B4: $ in thousands except per share | C4: ='Historical Financials'!C8 -> 43465 | D4: ='Historical Financials'!D8 -> 43830 | E4: ='Historical Financials'!E8 -> 44196 | F4: ='Historical Financials'!F8 -> 44561 | G4: ='Historical Financials'!G8 -> 44926 | H4: ='Historical Financials'!H8 -> 45291 | I4: ='Historical Financials'!I8 -> 45657 | K4: ='Historical Financials'!O8 -> 44651 | L4: ='Historical Financials'!P8 -> 44742 | M4: ='Historical Financials'!Q8 -> 44834 | N4: ='Historical Financials'!R8 -> 44926 | O4: ='Historical Financials'!S8 -> 45016 | P4: ='Historical Financials'!T8 -> 45107 | Q4: ='Historical Financials'!U8 -> 45199 | R4: ='Historical Financials'!V8 -> 45291 | ... Y4: ='Historical Financials'!AC8 -> 45930 | AA4: =O4 -> 45016 | AB4: =P4 -> 45107 | AC4: =Q4 -> 45199 | AD4: =R4 -> 45291 | AE4: =S4 -> 45382 | AF4: =T4 -> 45473 | AG4: =U4 -> 45565 | AH4: =V4 -> 45657 | ... AK4: =Y4 -> 45930
A6: X | B6: Offerings Drivers
B8: Disaggregated Revenues
B9: UCAN Revenue | C9: 8281.532 | D9: 10051.208 | E9: 11455.396 | F9: 12972.1 | G9: 14084.643 | H9: 14873.783 | I9: 17359.369 | K9: 3350.424 | L9: 3537.863 | M9: 3601.565 | N9: =SUM(G9-SUM(K9:M9)) -> 3594.791 | O9: 3608.645 | P9: 3599.448 | Q9: 3735.133 | R9: =SUM(H9-SUM(O9:Q9)) -> 3930.557 | S9: 4224.315 | T9: 4295.56 | U9: 4322.476 | V9: =SUM(I9-SUM(S9:U9)) -> 4517.018 | W9: 4617.098 | X9: 4929.003 | Y9: 5071.781 | AA9: =SUM(L9:O9) -> 14342.864 | AB9: =SUM(M9:P9) -> 14404.449 | AC9: =SUM(N9:Q9) -> 14538.017 | AD9: =SUM(O9:R9) -> 14873.783 | AE9: =SUM(P9:S9) -> 15489.453 | AF9: =SUM(Q9:T9) -> 16185.565 | AG9: =SUM(R9:U9) -> 16772.908 | AH9: =SUM(S9:V9) -> 17359.369 | ... AK9: =SUM(V9:Y9) -> 19134.9 | AM9: =SUM(AK9/AG9)-1 -> 0.14082185
B10: EMEA Revenue | C10: 3963.707 | D10: 5543.067 | E10: 7772.252 | F10: 9699.819 | G10: 9745.015 | H10: 10556.487 | I10: 12387.035 | K10: 2561.831 | L10: 2457.235 | M10: 2375.814 | N10: =SUM(G10-SUM(K10:M10)) -> 2350.135 | O10: 2517.641 | P10: 2562.17 | Q10: 2693.146 | R10: =SUM(H10-SUM(O10:Q10)) -> 2783.53 | S10: 2958.193 | T10: 3007.772 | U10: 3133.466 | V10: =SUM(I10-SUM(S10:U10)) -> 3287.604 | W10: 3404.676 | X10: 3538.175 | Y10: 3699.052 | AG10: =SUM(R10:U10) -> 11882.961 | AH10: =SUM(S10:V10) -> 12387.035 | AI10: =SUM(T10:W10) -> 12833.518 | AJ10: =SUM(U10:X10) -> 13363.921 | AK10: =SUM(V10:Y10) -> 13929.507 | AM10: =SUM(AK10/AG10)-1 -> 0.17222526
B11: LATAM Revenue | C11: 2237.697 | D11: 2795.434 | E11: 3156.727 | F11: 3576.976 | G11: 4069.973 | H11: 4446.461 | I11: 4839.816 | K11: 998.948 | L11: 1030.234 | M11: 1023.945 | N11: =SUM(G11-SUM(K11:M11)) -> 1016.846 | O11: 1070.192 | P11: 1077.435 | Q11: 1142.811 | R11: =SUM(H11-SUM(O11:Q11)) -> 1156.023 | S11: 1165.008 | T11: 1204.145 | U11: 1240.892 | V11: =SUM(I11-SUM(S11:U11)) -> 1229.771 | W11: 1261.934 | X11: 1306.735 | Y11: 1370.913 | AG11: =SUM(R11:U11) -> 4766.068 | AH11: =SUM(S11:V11) -> 4839.816 | AI11: =SUM(T11:W11) -> 4936.742 | AJ11: =SUM(U11:X11) -> 5039.332 | AK11: =SUM(V11:Y11) -> 5169.353 | AM11: =SUM(AK11/AG11)-1 -> 0.084615872
B12: APAC Revenue | C12: 945.816 | D12: 1469.521 | E12: 2372.3 | F12: 3266.601 | G12: 3570.221 | H12: 3763.727 | I12: 4414.746 | K12: 916.754 | L12: 907.719 | M12: 889.037 | N12: =SUM(G12-SUM(K12:M12)) -> 856.711 | O12: 933.523 | P12: 919.273 | Q12: 948.216 | R12: =SUM(H12-SUM(O12:Q12)) -> 962.715 | S12: 1022.924 | T12: 1051.833 | U12: 1127.869 | V12: =SUM(I12-SUM(S12:U12)) -> 1212.12 | W12: 1259.093 | X12: 1305.253 | Y12: 1368.561 | AG12: =SUM(R12:U12) -> 4165.341 | AH12: =SUM(S12:V12) -> 4414.746 | AI12: =SUM(T12:W12) -> 4650.915 | AJ12: =SUM(U12:X12) -> 4904.335 | AK12: =SUM(V12:Y12) -> 5145.027 | AM12: =SUM(AK12/AG12)-1 -> 0.23519947
B13: Domestic DVD Revenue | C13: 365.589 | D13: 297.217 | E13: 239.381 | F13: 182.348 | G13: 145.698 | H13: 82.839 | I13: 0 | K13: 39.81 | L13: 37.09 | M13: 35.228 | N13: =SUM(G13-SUM(K13:M13)) -> 33.57 | O13: 31.502 | P13: 28.975 | Q13: 22.362 | R13: =SUM(H13-SUM(O13:Q13)) -> 0 | S13: 0 | T13: 0 | U13: 0 | V13: =SUM(I13-SUM(S13:U13)) -> 0 | W13: 0 | X13: 0 | Y13: 0 | AG13: =SUM(R13:U13) -> 0 | AH13: =SUM(S13:V13) -> 0 | AI13: =SUM(T13:W13) -> 0 | AJ13: =SUM(U13:X13) -> 0 | AK13: =SUM(V13:Y13) -> 0 | AM13: =SUM(AK13/AG13)-1 -> #DIV/0!
B14: Total Net Revenue | C14: =SUM(C9:C13) -> 15794.341 | D14: =SUM(D9:D13) -> 20156.447 | E14: =SUM(E9:E13) -> 24996.056 | F14: =SUM(F9:F13) -> 29697.844 | G14: =SUM(G9:G13) -> 31615.55 | H14: =SUM(H9:H13) -> 33723.297 | I14: =SUM(I9:I13) -> 39000.966 | K14: =SUM(K9:K13) -> 7867.767 | L14: =SUM(L9:L13) -> 7970.141 | M14: =SUM(M9:M13) -> 7925.589 | N14: =SUM(N9:N13) -> 7852.053 | O14: =SUM(O9:O13) -> 8161.503 | P14: =SUM(P9:P13) -> 8187.301 | Q14: =SUM(Q9:Q13) -> 8541.668 | R14: =SUM(R9:R13) -> 8832.825 | ... Y14: =SUM(Y9:Y13) -> 11510.307 | AA14: =SUM(AA9:AA13) -> 14342.864 | AB14: =SUM(AB9:AB13) -> 14404.449 | AC14: =SUM(AC9:AC13) -> 14538.017 | AD14: =SUM(AD9:AD13) -> 14873.783 | AE14: =SUM(AE9:AE13) -> 15489.453 | AF14: =SUM(AF9:AF13) -> 16185.565 | AG14: =SUM(AG9:AG13) -> 37587.278 | AH14: =SUM(AH9:AH13) -> 39000.966 | ... AK14: =SUM(AK9:AK13) -> 43378.787 | AM14: =SUM(AK14/AG14)-1 -> 0.15408163
B15: Variance Check | C15: =+C14-'Historical Financials'!C11 -> 0 | D15: =+D14-'Historical Financials'!D11 -> 0 | E15: =+E14-'Historical Financials'!E11 -> 0 | F15: =+F14-'Historical Financials'!F11 -> 0 | G15: =+G14-'Historical Financials'!G11 -> 0 | H15: =+H14-'Historical Financials'!H11 -> 0 | I15: =+I14-'Historical Financials'!I11 -> 0 | K15: =K14-'Historical Financials'!O11 -> 0 | L15: =L14-'Historical Financials'!P11 -> 0 | M15: =M14-'Historical Financials'!Q11 -> 0 | N15: =N14-'Historical Financials'!R11 -> 0 | O15: =O14-'Historical Financials'!S11 -> 0 | P15: =P14-'Historical Financials'!T11 -> 0 | Q15: =Q14-'Historical Financials'!U11 -> 0 | R15: =R14-'Historical Financials'!V11 -> 0 | ... Y15: =Y14-'Historical Financials'!AC11 -> 0 | AA15: =+AA14-'Historical Financials'!AI11 -> -17566.422 | AB15: =+AB14-'Historical Financials'!AJ11 -> -17721.997 | AC15: =+AC14-'Historical Financials'!AK11 -> -18204.508 | AD15: =+AD14-'Historical Financials'!AL11 -> -18849.514 | AE15: =+AE14-'Historical Financials'!AM11 -> -19442.781 | AF15: =+AF14-'Historical Financials'!AN11 -> -20118.678 | AG15: =+AG14-'Historical Financials'!AO11 -> 0 | AH15: =+AH14-'Historical Financials'!AP11 -> 0 | ... AJ15: =+AJ14-'Historical Financials'!AR11 -> 0 | AK15: =AK14-'Historical Financials'!AS11 -> 0

Sheet FCF
B2: ='Historical Financials'!B2 -> Netflix, Inc. (NASDAQ: NFLX) | C2: FYE | E2: FYE | I2: Quarterly | M2: Quarterly | S2: Quarterly | Y2: LTM | AF2: LTM | AG2: LTM | AM2: Variance
B3: FCF Analysis | C3: ='Historical Financials'!E7 -> 2020 | D3: ='Historical Financials'!F7 -> 2021 | E3: ='Historical Financials'!G7 -> 2022 | F3: ='Historical Financials'!H7 -> 2023 | G3: ='Historical Financials'!I7 -> 2024 | I3: ='Historical Financials'!O7 -> 1Q22 | J3: ='Historical Financials'!P7 -> 2Q22 | K3: ='Historical Financials'!Q7 -> 3Q22 | L3: ='Historical Financials'!R7 -> 4Q22 | M3: ='Historical Financials'!S7 -> 1Q23 | N3: ='Historical Financials'!T7 -> 2Q23 | O3: ='Historical Financials'!U7 -> 3Q23 | P3: ='Historical Financials'!V7 -> 4Q23 | ... W3: ='Historical Financials'!AC7 -> 3Q25 | Y3: =K3 -> 3Q22 | Z3: =L3 -> 4Q22 | AA3: =M3 -> 1Q23 | AB3: =N3 -> 2Q23 | AC3: =O3 -> 3Q23 | AD3: =P3 -> 4Q23 | AE3: =Q3 -> 1Q24 | AF3: =R3 -> 2Q24 | ... AK3: =W3 -> 3Q25
B4: $ mm except per share | C4: ='Historical Financials'!E8 -> 44196 | D4: ='Historical Financials'!F8 -> 44561 | E4: ='Historical Financials'!G8 -> 44926 | F4: ='Historical Financials'!H8 -> 45291 | G4: ='Historical Financials'!I8 -> 45657 | I4: ='Historical Financials'!O8 -> 44651 | J4: ='Historical Financials'!P8 -> 44742 | K4: ='Historical Financials'!Q8 -> 44834 | L4: ='Historical Financials'!R8 -> 44926 | M4: ='Historical Financials'!S8 -> 45016 | N4: ='Historical Financials'!T8 -> 45107 | O4: ='Historical Financials'!U8 -> 45199 | P4: ='Historical Financials'!V8 -> 45291 | ... W4: ='Historical Financials'!AC8 -> 45930 | Y4: =K4 -> 44834 | Z4: =L4 -> 44926 | AA4: =M4 -> 45016 | AB4: =N4 -> 45107 | AC4: =O4 -> 45199 | AD4: =P4 -> 45291 | AE4: =Q4 -> 45382 | AF4: =R4 -> 45473 | ... AK4: =W4 -> 45930
B6: ='Revenue Drivers'!B9 -> UCAN Revenue | C6: =('Revenue Drivers'!E9) -> 11455.396 | D6: =('Revenue Drivers'!F9) -> 12972.1 | E6: =('Revenue Drivers'!G9) -> 14084.643 | F6: =('Revenue Drivers'!H9) -> 14873.783 | G6: =('Revenue Drivers'!I9) -> 17359.369 | I6: =('Revenue Drivers'!K9) -> 3350.424 | J6: =('Revenue Drivers'!L9) -> 3537.863 | K6: =('Revenue Drivers'!M9) -> 3601.565 | L6: =('Revenue Drivers'!N9) -> 3594.791 | M6: =('Revenue Drivers'!O9) -> 3608.645 | N6: =('Revenue Drivers'!P9) -> 3599.448 | O6: =('Revenue Drivers'!Q9) -> 3735.133 | P6: =('Revenue Drivers'!R9) -> 3930.557 | ... W6: =('Revenue Drivers'!Y9) -> 5071.781 | Y6: =SUM(H6:K6) -> 10489.852 | Z6: =SUM(I6:L6) -> 14084.643 | AA6: =SUM(J6:M6) -> 14342.864 | AB6: =SUM(K6:N6) -> 14404.449 | AC6: =SUM(L6:O6) -> 14538.017 | AD6: =SUM(M6:P6) -> 14873.783 | AE6: =SUM(N6:Q6) -> 15489.453 | AF6: =SUM(O6:R6) -> 16185.565 | ... AK6: =SUM(T6:W6) -> 19134.9 | AM6: =SUM(AK6/AG6)-1 -> 0.14082185
B7: ='Revenue Drivers'!B10 -> EMEA Revenue | C7: =('Revenue Drivers'!E10) -> 7772.252 | D7: =('Revenue Drivers'!F10) -> 9699.819 | E7: =('Revenue Drivers'!G10) -> 9745.015 | F7: =('Revenue Drivers'!H10) -> 10556.487 | G7: =('Revenue Drivers'!I10) -> 12387.035 | I7: =('Revenue Drivers'!K10) -> 2561.831 | J7: =('Revenue Drivers'!L10) -> 2457.235 | K7: =('Revenue Drivers'!M10) -> 2375.814 | L7: =('Revenue Drivers'!N10) -> 2350.135 | M7: =('Revenue Drivers'!O10) -> 2517.641 | N7: =('Revenue Drivers'!P10) -> 2562.17 | O7: =('Revenue Drivers'!Q10) -> 2693.146 | P7: =('Revenue Drivers'!R10) -> 2783.53 | ... W7: =('Revenue Drivers'!Y10) -> 3699.052 | AG7: =SUM(P7:S7) -> 11882.961 | AH7: =SUM(Q7:T7) -> 12387.035 | AI7: =SUM(R7:U7) -> 12833.518 | AJ7: =SUM(S7:V7) -> 13363.921 | AK7: =SUM(T7:W7) -> 13929.507 | AM7: =SUM(AK7/AG7)-1 -> 0.17222526
B8: ='Revenue Drivers'!B11 -> LATAM Revenue | C8: =('Revenue Drivers'!E11) -> 3156.727 | D8: =('Revenue Drivers'!F11) -> 3576.976 | E8: =('Revenue Drivers'!G11) -> 4069.973 | F8: =('Revenue Drivers'!H11) -> 4446.461 | G8: =('Revenue Drivers'!I11) -> 4839.816 | I8: =('Revenue Drivers'!K11) -> 998.948 | J8: =('Revenue Drivers'!L11) -> 1030.234 | K8: =('Revenue Drivers'!M11) -> 1023.945 | L8: =('Revenue Drivers'!N11) -> 1016.846 | M8: =('Revenue Drivers'!O11) -> 1070.192 | N8: =('Revenue Drivers'!P11) -> 1077.435 | O8: =('Revenue Drivers'!Q11) -> 1142.811 | P8: =('Revenue Drivers'!R11) -> 1156.023 | ... W8: =('Revenue Drivers'!Y11) -> 1370.913 | AG8: =SUM(P8:S8) -> 4766.068 | AH8: =SUM(Q8:T8) -> 4839.816 | AI8: =SUM(R8:U8) -> 4936.742 | AJ8: =SUM(S8:V8) -> 5039.332 | AK8: =SUM(T8:W8) -> 5169.353 | AM8: =SUM(AK8/AG8)-1 -> 0.084615872
B9: ='Revenue Drivers'!B12 -> APAC Revenue | C9: =('Revenue Drivers'!E12) -> 2372.3 | D9: =('Revenue Drivers'!F12) -> 3266.601 | E9: =('Revenue Drivers'!G12) -> 3570.221 | F9: =('Revenue Drivers'!H12) -> 3763.727 | G9: =('Revenue Drivers'!I12) -> 4414.746 | I9: =('Revenue Drivers'!K12) -> 916.754 | J9: =('Revenue Drivers'!L12) -> 907.719 | K9: =('Revenue Drivers'!M12) -> 889.037 | L9: =('Revenue Drivers'!N12) -> 856.711 | M9: =('Revenue Drivers'!O12) -> 933.523 | N9: =('Revenue Drivers'!P12) -> 919.273 | O9: =('Revenue Drivers'!Q12) -> 948.216 | P9: =('Revenue Drivers'!R12) -> 962.715 | ... W9: =('Revenue Drivers'!Y12) -> 1368.561 | AG9: =SUM(P9:S9) -> 4165.341 | AH9: =SUM(Q9:T9) -> 4414.746 | AI9: =SUM(R9:U9) -> 4650.915 | AJ9: =SUM(S9:V9) -> 4904.335 | AK9: =SUM(T9:W9) -> 5145.027 | AM9: =SUM(AK9/AG9)-1 -> 0.23519947
B10: ='Revenue Drivers'!B13 -> Domestic DVD Revenue | C10: =('Revenue Drivers'!E13) -> 239.381 | D10: =('Revenue Drivers'!F13) -> 182.348 | E10: =('Revenue Drivers'!G13) -> 145.698 | F10: =('Revenue Drivers'!H13) -> 82.839 | G10: =('Revenue Drivers'!I13) -> 0 | I10: =('Revenue Drivers'!K13) -> 39.81 | J10: =('Revenue Drivers'!L13) -> 37.09 | K10: =('Revenue Drivers'!M13) -> 35.228 | L10: =('Revenue Drivers'!N13) -> 33.57 | M10: =('Revenue Drivers'!O13) -> 31.502 | N10: =('Revenue Drivers'!P13) -> 28.975 | O10: =('Revenue Drivers'!Q13) -> 22.362 | P10: =('Revenue Drivers'!R13) -> 0 | ... W10: =('Revenue Drivers'!Y13) -> 0 | AG10: =SUM(P10:S10) -> 0 | AH10: =SUM(Q10:T10) -> 0 | AI10: =SUM(R10:U10) -> 0 | AJ10: =SUM(S10:V10) -> 0 | AK10: =SUM(T10:W10) -> 0 | AM10: =SUM(AK10/AG10)-1 -> #DIV/0!
B11: Total Revenue | C11: =SUM(C6:C10) -> 24996.056 | D11: =SUM(D6:D10) -> 29697.844 | E11: =SUM(E6:E10) -> 31615.55 | F11: =SUM(F6:F10) -> 33723.297 | G11: =SUM(G6:G10) -> 39000.966 | I11: =SUM(I6:I10) -> 7867.767 | J11: =SUM(J6:J10) -> 7970.141 | K11: =SUM(K6:K10) -> 7925.589 | L11: =SUM(L6:L10) -> 7852.053 | M11: =SUM(M6:M10) -> 8161.503 | N11: =SUM(N6:N10) -> 8187.301 | O11: =SUM(O6:O10) -> 8541.668 | P11: =SUM(P6:P10) -> 8832.825 | ... W11: =SUM(W6:W10) -> 11510.307 | Y11: =SUM(Y6:Y10) -> 10489.852 | Z11: =SUM(Z6:Z10) -> 14084.643 | AA11: =SUM(AA6:AA10) -> 14342.864 | AB11: =SUM(AB6:AB10) -> 14404.449 | AC11: =SUM(AC6:AC10) -> 14538.017 | AD11: =SUM(AD6:AD10) -> 14873.783 | AE11: =SUM(AE6:AE10) -> 15489.453 | AF11: =SUM(AF6:AF10) -> 16185.565 | ... AK11: =SUM(AK6:AK10) -> 43378.787 | AM11: =SUM(AK11/AG11)-1 -> 0.15408163
B12: Y/Y Growth (%) | D12: =SUM(D11/C11)-1 -> 0.18810119 | E12: =SUM(E11/D11)-1 -> 0.064573913 | F12: =SUM(F11/E11)-1 -> 0.066668048 | G12: =SUM(G11/F11)-1 -> 0.1564992 | M12: =SUM(M11/I11)-1 -> 0.0373341 | N12: =SUM(N11/J11)-1 -> 0.027246695 | O12: =SUM(O11/K11)-1 -> 0.077732898 | P12: =SUM(P11/L11)-1 -> 0.12490644 | Q12: =SUM(Q11/M11)-1 -> 0.14812676 | R12: =SUM(R11/N11)-1 -> 0.16757769 | S12: =SUM(S11/O11)-1 -> 0.15020895 | T12: =SUM(T11/P11)-1 -> 0.16004936 | ... W12: =SUM(W11/S11)-1 -> 0.17156793 | AC12: =SUM(AC11/Y11)-1 -> 0.3859125 | AD12: =SUM(AD11/Z11)-1 -> 0.056028399 | AE12: =SUM(AE11/AA11)-1 -> 0.079941426 | AF12: =SUM(AF11/AB11)-1 -> 0.12365041 | AG12: =SUM(AG11/AC11)-1 -> 1.5854474 | AH12: =SUM(AH11/AD11)-1 -> 1.6221282 | AI12: =SUM(AI11/AE11)-1 -> 1.5935924 | AJ12: =SUM(AJ11/AF11)-1 -> 1.5759486 | AK12: =SUM(AK11/AG11)-1 -> 0.15408163 | AM12: =SUM(AK12-AG12)*10000 -> -14313.658
B13: Q/Q Growth (%) | C13: N/A | D13: N/A | E13: N/A | F13: N/A | G13: N/A | J13: =SUM(J11/I11)-1 -> 0.013011824 | K13: =SUM(K11/J11)-1 -> -0.0055898635 | L13: =SUM(L11/K11)-1 -> -0.009278301 | M13: =SUM(M11/L11)-1 -> 0.039410075 | N13: =SUM(N11/M11)-1 -> 0.0031609374 | O13: =SUM(O11/N11)-1 -> 0.043282518 | P13: =SUM(P11/O11)-1 -> 0.034086668 | Q13: =SUM(Q11/P11)-1 -> 0.060865578 | ... W13: =SUM(W11/V11)-1 -> 0.038914572 | Y13: N/A | Z13: N/A | AA13: N/A | AB13: N/A | AC13: N/A | AD13: N/A | AE13: N/A | AF13: N/A | AG13: N/A | AH13: N/A | AI13: N/A | AJ13: N/A | AK13: N/A
B15: (-) Amortization of content assets | C15: =('Historical Financials'!E13) -> -10806.912 | D15: =('Historical Financials'!F13) -> -12230.367 | E15: =('Historical Financials'!G13) -> -14026.132 | F15: =('Historical Financials'!H13) -> -14197.437 | G15: =('Historical Financials'!I13) -> -15301.517 | I15: =('Historical Financials'!O13) -> -3166.365 | J15: =('Historical Financials'!P13) -> -3261.348 | K15: =('Historical Financials'!Q13) -> -3653.592 | L15: =('Historical Financials'!R13) -> -3944.827 | M15: =('Historical Financials'!S13) -> -3459.984 | N15: =('Historical Financials'!T13) -> -3410.021 | O15: =('Historical Financials'!U13) -> -3573.353 | P15: =('Historical Financials'!V13) -> -3754.079 | ... W15: =('Historical Financials'!AC13) -> -4002.744 | Y15: =SUM(H15:K15) -> -10081.305 | Z15: =SUM(I15:L15) -> -14026.132 | AA15: =SUM(J15:M15) -> -14319.751 | AB15: =SUM(K15:N15) -> -14468.424 | AC15: =SUM(L15:O15) -> -14388.185 | AD15: =SUM(M15:P15) -> -14197.437 | AE15: =SUM(N15:Q15) -> -14408.258 | AF15: =SUM(O15:R15) -> -14767.927 | ... AK15: =SUM(T15:W15) -> -15819.431 | AM15: =SUM(AK15/AG15)-1 -> 0.062127709
B16: (-) Other Cost of Revenues | C16: =('Historical Financials'!E14) -> -4469.407 | D16: =('Historical Financials'!F14) -> -5102.316 | E16: =('Historical Financials'!G14) -> -5142.153 | F16: =('Historical Financials'!H14) -> -5517.931 | G16: =('Historical Financials'!I14) -> -5736.947 | I16: =('Historical Financials'!O14) -> -1118.34 | J16: =('Historical Financials'!P14) -> -1429.407 | K16: =('Historical Financials'!Q14) -> -1135.073 | L16: =('Historical Financials'!R14) -> -1459.333 | M16: =('Historical Financials'!S14) -> -1343.641 | N16: =('Historical Financials'!T14) -> -1263.449 | O16: =('Historical Financials'!U14) -> -1357.435 | P16: =('Historical Financials'!V14) -> -1553.406 | ... W16: =('Historical Financials'!AC14) -> -2161.506 | AG16: =SUM(P16:S16) -> -5684.49 | AH16: =SUM(Q16:T16) -> -5736.947 | AI16: =SUM(R16:U16) -> -5870.714 | AJ16: =SUM(S16:V16) -> -5959.498 | AK16: =SUM(T16:W16) -> -6700.641
B17: Gross Profit | C17: =SUM(C11+SUM(C15:C16)) -> 9719.737 | D17: =SUM(D11+SUM(D15:D16)) -> 12365.161 | E17: =SUM(E11+SUM(E15:E16)) -> 12447.265 | F17: =SUM(F11+SUM(F15:F16)) -> 14007.929 | G17: =SUM(G11+SUM(G15:G16)) -> 17962.502 | I17: =SUM(I11+SUM(I15:I16)) -> 3583.062 | J17: =SUM(J11+SUM(J15:J16)) -> 3279.386 | K17: =SUM(K11+SUM(K15:K16)) -> 3136.924 | L17: =SUM(L11+SUM(L15:L16)) -> 2447.893 | M17: =SUM(M11+SUM(M15:M16)) -> 3357.878 | N17: =SUM(N11+SUM(N15:N16)) -> 3513.831 | O17: =SUM(O11+SUM(O15:O16)) -> 3610.88 | P17: =SUM(P11+SUM(P15:P16)) -> 3525.34 | ... W17: =SUM(W11+SUM(W15:W16)) -> 5346.057 | Y17: =SUM(Y11+SUM(Y15:Y16)) -> 408.547 | Z17: =SUM(Z11+SUM(Z15:Z16)) -> 58.511 | AA17: =SUM(AA11+SUM(AA15:AA16)) -> 23.113 | AB17: =SUM(AB11+SUM(AB15:AB16)) -> -63.975 | AC17: =SUM(AC11+SUM(AC15:AC16)) -> 149.832 | AD17: =SUM(AD11+SUM(AD15:AD16)) -> 676.346 | AE17: =SUM(AE11+SUM(AE15:AE16)) -> 1081.195 | AF17: =SUM(AF11+SUM(AF15:AF16)) -> 1417.638 | ... AK17: =SUM(AK11+SUM(AK15:AK16)) -> 20858.715 | AM17: =SUM(AK17/AG17)-1 -> 0.22635613
B18: Gross Margin (%) | C18: =C17/C11 -> 0.38885083 | D18: =D17/D11 -> 0.41636561 | E18: =E17/E11 -> 0.39370705 | F18: =F17/F11 -> 0.4153784 | G18: =G17/G11 -> 0.46056557 | I18: =I17/I11 -> 0.45541028 | J18: =J17/J11 -> 0.41145897 | K18: =K17/K11 -> 0.39579696 | L18: =L17/L11 -> 0.31175197 | M18: =M17/M11 -> 0.41142888 | N18: =N17/N11 -> 0.42918063 | O18: =O17/O11 -> 0.4227371 | P18: =P17/P11 -> 0.39911806 | ... W18: =W17/W11 -> 0.46445825 | Y18: =Y17/Y11 -> 0.038946879 | Z18: =Z17/Z11 -> 0.0041542409 | AA18: =AA17/AA11 -> 0.0016114634 | AB18: =AB17/AB11 -> -0.0044413361 | AC18: =AC17/AC11 -> 0.01030622 | AD18: =AD17/AD11 -> 0.045472359 | AE18: =AE17/AE11 -> 0.069802013 | AF18: =AF17/AF11 -> 0.087586562 | ... AK18: =AK17/AK11 -> 0.48085058 | AM18: =SUM(AK18-AG18)*10000 -> 283.38618
B20: (-) Marketing | C20: =('Historical Financials'!E19) -> -2228.362 | D20: =('Historical Financials'!F19) -> -2545.146 | E20: =('Historical Financials'!G19) -> -2530.502 | F20: =('Historical Financials'!H19) -> -2657.883 | G20: =('Historical Financials'!I19) -> -2917.554 | I20: =('Historical Financials'!O19) -> -555.978 | J20: =('Historical Financials'!P19) -> -574.96 | K20: =('Historical Financials'!Q19) -> -567.954 | L20: =('Historical Financials'!R19) -> -831.61 | M20: =('Historical Financials'!S19) -> -555.362 | N20: =('Historical Financials'!T19) -> -627.168 | O20: =('Historical Financials'!U19) -> -558.736 | P20: =('Historical Financials'!V19) -> -916.617 | ... W20: =('Historical Financials'!AC19) -> -786.295 | Y20: =SUM(H20:K20) -> -1698.892 | Z20: =SUM(I20:L20) -> -2530.502 | AA20: =SUM(J20:M20) -> -2529.886 | AB20: =SUM(K20:N20) -> -2582.094 | AC20: =SUM(L20:O20) -> -2572.876 | AD20: =SUM(M20:P20) -> -2657.883 | AE20: =SUM(N20:Q20) -> -2756.861 | AF20: =SUM(O20:R20) -> -2773.777 | ... AK20: =SUM(T20:W20) -> -3164.134 | AM20: =SUM(AK20/AG20)-1 -> 0.10712755
B21: (-) Technology and Development (T&D) | C21: =('Historical Financials'!E20) -> -1829.6 | D21: =('Historical Financials'!F20) -> -2273.885 | E21: =('Historical Financials'!G20) -> -2711.041 | F21: =('Historical Financials'!H20) -> -2675.758 | G21: =('Historical Financials'!I20) -> -2925.295 | I21: =('Historical Financials'!O20) -> -657.53 | J21: =('Historical Financials'!P20) -> -716.846 | K21: =('Historical Financials'!Q20) -> -662.739 | L21: =('Historical Financials'!R20) -> -673.926 | M21: =('Historical Financials'!S20) -> -687.275 | N21: =('Historical Financials'!T20) -> -657.983 | O21: =('Historical Financials'!U20) -> -657.159 | P21: =('Historical Financials'!V20) -> -673.341 | ... W21: =('Historical Financials'!AC20) -> -853.584 | Y21: =SUM(H21:K21) -> -2037.115 | Z21: =SUM(I21:L21) -> -2711.041 | AA21: =SUM(J21:M21) -> -2740.786 | AB21: =SUM(K21:N21) -> -2681.923 | AC21: =SUM(L21:O21) -> -2676.343 | AD21: =SUM(M21:P21) -> -2675.758 | AE21: =SUM(N21:Q21) -> -2690.956 | AF21: =SUM(O21:R21) -> -2744.227 | ... AK21: =SUM(T21:W21) -> -3277.595 | AM21: =SUM(AK21/AG21)-1 -> 0.1613901
B22: (-) General and Administrative (G&A) | C22: =('Historical Financials'!E21) -> -1076.486 | D22: =('Historical Financials'!F21) -> -1351.621 | E22: =('Historical Financials'!G21) -> -1572.891 | F22: =('Historical Financials'!H21) -> -1720.285 | G22: =('Historical Financials'!I21) -> -1702.039 | I22: =('Historical Financials'!O21) -> -397.928 | J22: =('Historical Financials'!P21) -> -409.297 | K22: =('Historical Financials'!Q21) -> -373.213 | L22: =('Historical Financials'!R21) -> -392.453 | M22: =('Historical Financials'!S21) -> -400.924 | N22: =('Historical Financials'!T21) -> -401.497 | O22: =('Historical Financials'!U21) -> -478.591 | P22: =('Historical Financials'!V21) -> -439.273 | ... W22: =('Historical Financials'!AC21) -> -457.931 | Y22: =SUM(H22:K22) -> -1180.438 | Z22: =SUM(I22:L22) -> -1572.891 | AA22: =SUM(J22:M22) -> -1575.887 | AB22: =SUM(K22:N22) -> -1568.087 | AC22: =SUM(L22:O22) -> -1673.465 | AD22: =SUM(M22:P22) -> -1720.285 | AE22: =SUM(N22:Q22) -> -1723.381 | AF22: =SUM(O22:R22) -> -1748.876 | ... AK22: =SUM(T22:W22) -> -1774.28 | AM22: =SUM(AK22/AG22)-1 -> 0.051339209
B23: Earning before Interest & Taxes (EBIT) | C23: =SUM(C17+SUM(C20:C22)) -> 4585.289 | D23: =SUM(D17+SUM(D20:D22)) -> 6194.509 | E23: =SUM(E17+SUM(E20:E22)) -> 5632.831 | F23: =SUM(F17+SUM(F20:F22)) -> 6954.003 | G23: =SUM(G17+SUM(G20:G22)) -> 10417.614 | I23: =SUM(I17+SUM(I20:I22)) -> 1971.626 | J23: =SUM(J17+SUM(J20:J22)) -> 1578.283 | K23: =SUM(K17+SUM(K20:K22)) -> 1533.018 | L23: =SUM(L17+SUM(L20:L22)) -> 549.904 | M23: =SUM(M17+SUM(M20:M22)) -> 1714.317 | N23: =SUM(N17+SUM(N20:N22)) -> 1827.183 | O23: =SUM(O17+SUM(O20:O22)) -> 1916.394 | P23: =SUM(P17+SUM(P20:P22)) -> 1496.109 | ... W23: =SUM(W17+SUM(W20:W22)) -> 3248.247 | Y23: =SUM(Y17+SUM(Y20:Y22)) -> -4507.898 | Z23: =SUM(Z17+SUM(Z20:Z22)) -> -6755.923 | AA23: =SUM(AA17+SUM(AA20:AA22)) -> -6823.446 | AB23: =SUM(AB17+SUM(AB20:AB22)) -> -6896.079 | AC23: =SUM(AC17+SUM(AC20:AC22)) -> -6772.852 | AD23: =SUM(AD17+SUM(AD20:AD22)) -> -6377.58 | AE23: =SUM(AE17+SUM(AE20:AE22)) -> -6090.003 | AF23: =SUM(AF17+SUM(AF20:AF22)) -> -5849.242 | ... AK23: =SUM(AK17+SUM(AK20:AK22)) -> 12642.706 | AM23: =SUM(AK23/AG23)-1 -> 0.31135384
B24: Operating Margin (%) | C24: =C23/C11 -> 0.1834405 | D24: =D23/D11 -> 0.20858447 | E24: =E23/E11 -> 0.17816647 | F24: =F23/F11 -> 0.20620768 | G24: =G23/G11 -> 0.26711169 | I24: =I23/I11 -> 0.25059537 | J24: =J23/J11 -> 0.19802448 | K24: =K23/K11 -> 0.19342638 | L24: =L23/L11 -> 0.070033149 | M24: =M23/M11 -> 0.21004918 | N24: =N23/N11 -> 0.22317281 | O24: =O23/O11 -> 0.22435829 | P24: =P23/P11 -> 0.16938058 | ... W24: =W23/W11 -> 0.28220333 | Y24: =Y23/Y11 -> -0.42973895 | Z24: =Z23/Z11 -> -0.4796659 | AA24: =AA23/AA11 -> -0.47573804 | AB24: =AB23/AB11 -> -0.47874646 | AC24: =AC23/AC11 -> -0.46587179 | AD24: =AD23/AD11 -> -0.42877995 | AE24: =AE23/AE11 -> -0.39317095 | AF24: =AF23/AF11 -> -0.36138633 | ... AK24: =AK23/AK11 -> 0.29144904 | AM24: =SUM(AK24-AG24)*10000 -> 349.53828
B26: (+) Depreciation and amortization of PP&E and intangibles | C26: =('Historical Financials'!E92) -> 115.71 | D26: =('Historical Financials'!F92) -> 208.412 | E26: =('Historical Financials'!G92) -> 336.682 | F26: =('Historical Financials'!H92) -> 356.947 | G26: =('Historical Financials'!I92) -> 328.914 | I26: =('Historical Financials'!O92) -> 74.602 | J26: =('Historical Financials'!P92) -> 83.505 | K26: =('Historical Financials'!Q92) -> 85.188 | L26: =('Historical Financials'!R92) -> 93.387 | M26: =('Historical Financials'!S92) -> 90.335 | N26: =('Historical Financials'!T92) -> 89.385 | O26: =('Historical Financials'!U92) -> 90.66 | P26: =('Historical Financials'!V92) -> 86.567 | ... W26: =('Historical Financials'!AC92) -> 87.326 | Y26: =SUM(H26:K26) -> 243.295 | Z26: =SUM(I26:L26) -> 336.682 | AA26: =SUM(J26:M26) -> 352.415 | AB26: =SUM(K26:N26) -> 358.295 | AC26: =SUM(L26:O26) -> 363.767 | AD26: =SUM(M26:P26) -> 356.947 | AE26: =SUM(N26:Q26) -> 353.846 | AF26: =SUM(O26:R26) -> 345.688 | ... AK26: =SUM(T26:W26) -> 326.945 | AM26: =SUM(AK26/AG26)-1 -> -0.026781409
B27: (+) Amortization of content assets | C27: =-C15 -> 10806.912 | D27: =-D15 -> 12230.367 | E27: =-E15 -> 14026.132 | F27: =-F15 -> 14197.437 | G27: =-G15 -> 15301.517 | I27: =-I15 -> 3166.365 | J27: =-J15 -> 3261.348 | K27: =-K15 -> 3653.592 | L27: =-L15 -> 3944.827 | M27: =-M15 -> 3459.984 | N27: =-N15 -> 3410.021 | O27: =-O15 -> 3573.353 | P27: =-P15 -> 3754.079 | ... W27: =-W15 -> 4002.744 | Y27: =-Y15 -> 10081.305 | Z27: =-Z15 -> 14026.132 | AA27: =-AA15 -> 14319.751 | AB27: =-AB15 -> 14468.424 | AC27: =-AC15 -> 14388.185 | AD27: =-AD15 -> 14197.437 | AE27: =-AE15 -> 14408.258 | AF27: =-AF15 -> 14767.927 | ... AK27: =-AK15 -> 15819.431
B28: EBITDA | C28: =SUM(C23+SUM(C26:C27)) -> 15507.911 | D28: =SUM(D23+SUM(D26:D27)) -> 18633.288 | E28: =SUM(E23+SUM(E26:E27)) -> 19995.645 | F28: =SUM(F23+SUM(F26:F27)) -> 21508.387 | G28: =SUM(G23+SUM(G26:G27)) -> 26048.045 | I28: =SUM(I23+SUM(I26:I27)) -> 5212.593 | J28: =SUM(J23+SUM(J26:J27)) -> 4923.136 | K28: =SUM(K23+SUM(K26:K27)) -> 5271.798 | L28: =SUM(L23+SUM(L26:L27)) -> 4588.118 | M28: =SUM(M23+SUM(M26:M27)) -> 5264.636 | N28: =SUM(N23+SUM(N26:N27)) -> 5326.589 | O28: =SUM(O23+SUM(O26:O27)) -> 5580.407 | P28: =SUM(P23+SUM(P26:P27)) -> 5336.755 | ... W28: =SUM(W23+SUM(W26:W27)) -> 7338.317 | Y28: =SUM(Y23+SUM(Y26:Y27)) -> 5816.702 | Z28: =SUM(Z23+SUM(Z26:Z27)) -> 7606.891 | AA28: =SUM(AA23+SUM(AA26:AA27)) -> 7848.72 | AB28: =SUM(AB23+SUM(AB26:AB27)) -> 7930.64 | AC28: =SUM(AC23+SUM(AC26:AC27)) -> 7979.1 | AD28: =SUM(AD23+SUM(AD26:AD27)) -> 8176.804 | AE28: =SUM(AE23+SUM(AE26:AE27)) -> 8672.101 | AF28: =SUM(AF23+SUM(AF26:AF27)) -> 9264.373 | ... AK28: =SUM(AK23+SUM(AK26:AK27)) -> 28789.082 | AM28: =SUM(AK28/AG28)-1 -> 0.15753645
B29: EBITDA Margin (%) | C29: =C28/C11 -> 0.62041432 | D29: =D28/D11 -> 0.62742898 | E29: =E28/E11 -> 0.63246235 | F29: =F28/F11 -> 0.63779016 | G29: =G28/G11 -> 0.66788205 | I29: =I28/I11 -> 0.66252508 | J29: =J28/J11 -> 0.61769748 | K29: =K28/K11 -> 0.66516167 | L29: =L28/L11 -> 0.58432081 | M29: =M28/M11 -> 0.64505717 | N29: =N28/N11 -> 0.65059157 | O29: =O28/O11 -> 0.65331584 | P29: =P28/P11 -> 0.60419571 | ... W29: =W28/W11 -> 0.63754312 | Y29: =Y28/Y11 -> 0.55450754 | Z29: =Z28/Z11 -> 0.54008405 | AA29: =AA28/AA11 -> 0.54722125 | AB29: =AB28/AB11 -> 0.55056879 | AC29: =AC28/AC11 -> 0.54884377 | AD29: =AD28/AD11 -> 0.54974609 | AE29: =AE28/AE11 -> 0.55987135 | AF29: =AF28/AF11 -> 0.5723849 | ... AK29: =AK28/AK11 -> 0.66366729 | AM29: =SUM(AK29-AG29)*10000 -> 19.80801
B31: (+) Share-based Compensation | C31: =('Historical Financials'!E93) -> 415.18 | D31: =('Historical Financials'!F93) -> 403.22 | E31: =('Historical Financials'!G93) -> 575.452 | F31: =('Historical Financials'!H93) -> 339.368 | G31: =('Historical Financials'!I93) -> 272.588 | I31: =('Historical Financials'!O93) -> 119.209 | J31: =('Historical Financials'!P93) -> 150.392 | K31: =('Historical Financials'!Q93) -> 152.062 | L31: =('Historical Financials'!R93) -> 153.789 | M31: =('Historical Financials'!S93) -> 99.099 | N31: =('Historical Financials'!T93) -> 78.03 | O31: =('Historical Financials'!U93) -> 79.72 | P31: =('Historical Financials'!V93) -> 82.519 | ... W31: =('Historical Financials'!AC93) -> 80.986 | Y31: =SUM(H31:K31) -> 421.663 | Z31: =SUM(I31:L31) -> 575.452 | AA31: =SUM(J31:M31) -> 555.342 | AB31: =SUM(K31:N31) -> 482.98 | AC31: =SUM(L31:O31) -> 410.638 | AD31: =SUM(M31:P31) -> 339.368 | AE31: =SUM(N31:Q31) -> 316.614 | AF31: =SUM(O31:R31) -> 307.35 | ... AK31: =SUM(T31:W31) -> 295.652 | AM31: =SUM(AK31/AG31)-1 -> 0.0080878342
B32: Adj. EBITDA | C32: =+SUM(C28+SUM(C31:C31)) -> 15923.091 | D32: =+SUM(D28+SUM(D31:D31)) -> 19036.508 | E32: =+SUM(E28+SUM(E31:E31)) -> 20571.097 | F32: =+SUM(F28+SUM(F31:F31)) -> 21847.755 | G32: =+SUM(G28+SUM(G31:G31)) -> 26320.633 | I32: =+SUM(I28+SUM(I31:I31)) -> 5331.802 | J32: =+SUM(J28+SUM(J31:J31)) -> 5073.528 | K32: =+SUM(K28+SUM(K31:K31)) -> 5423.86 | L32: =+SUM(L28+SUM(L31:L31)) -> 4741.907 | M32: =+SUM(M28+SUM(M31:M31)) -> 5363.735 | N32: =+SUM(N28+SUM(N31:N31)) -> 5404.619 | O32: =+SUM(O28+SUM(O31:O31)) -> 5660.127 | P32: =+SUM(P28+SUM(P31:P31)) -> 5419.274 | ... W32: =+SUM(W28+SUM(W31:W31)) -> 7419.303 | Y32: =+SUM(Y28+SUM(Y31:Y31)) -> 6238.365 | Z32: =+SUM(Z28+SUM(Z31:Z31)) -> 8182.343 | AA32: =+SUM(AA28+SUM(AA31:AA31)) -> 8404.062 | AB32: =+SUM(AB28+SUM(AB31:AB31)) -> 8413.62 | AC32: =+SUM(AC28+SUM(AC31:AC31)) -> 8389.738 | AD32: =+SUM(AD28+SUM(AD31:AD31)) -> 8516.172 | AE32: =+SUM(AE28+SUM(AE31:AE31)) -> 8988.715 | AF32: =+SUM(AF28+SUM(AF31:AF31)) -> 9571.723 | ... AK32: =+SUM(AK28+SUM(AK31:AK31)) -> 29084.734 | AM32: =SUM(AK32/AG32)-1 -> 0.15579468
B33: Adj. EBITDA Margin (%) | C33: =C32/C11 -> 0.63702414 | D33: =D32/D11 -> 0.6410064 | E33: =E32/E11 -> 0.6506639 | F33: =F32/F11 -> 0.64785347 | G33: =G32/G11 -> 0.67487131 | I33: =I32/I11 -> 0.67767665 | J33: =J32/J11 -> 0.63656691 | K33: =K32/K11 -> 0.68434788 | L33: =L32/L11 -> 0.60390665 | M33: =M32/M11 -> 0.65719942 | N33: =N32/N11 -> 0.66012218 | O33: =O32/O11 -> 0.66264891 | P33: =P32/P11 -> 0.61353802 | ... W33: =W32/W11 -> 0.64457907 | Y33: =Y32/Y11 -> 0.59470477 | Z33: =Z32/Z11 -> 0.58094075 | AA33: =AA32/AA11 -> 0.5859403 | AB33: =AB32/AB11 -> 0.5840987 | AC33: =AC32/AC11 -> 0.57708957 | AD33: =AD32/AD11 -> 0.57256261 | AE33: =AE32/AE11 -> 0.58031197 | AF33: =AF32/AF11 -> 0.59137404 | ... AK33: =AK32/AK11 -> 0.67048288 | AM33: =SUM(AK33-AG33)*10000 -> 9.9375037
B35: (-) Capital Expenditures | C35: =('Historical Financials'!E106) -> -497.923 | D35: =('Historical Financials'!F106) -> -524.585 | E35: =('Historical Financials'!G106) -> -407.729 | F35: =('Historical Financials'!H106) -> -348.552 | G35: =('Historical Financials'!I106) -> -439.538 | I35: =('Historical Financials'!O106) -> -121.158 | J35: =('Historical Financials'!P106) -> -90.018 | K35: =('Historical Financials'!Q106) -> -84.96 | L35: =('Historical Financials'!R106) -> -111.593 | M35: =('Historical Financials'!S106) -> -62.019 | N35: =('Historical Financials'!T106) -> -100.972 | O35: =('Historical Financials'!U106) -> -103.929 | P35: =('Historical Financials'!V106) -> -81.632 | ... W35: =('Historical Financials'!AC106) -> -164.719 | Y35: =SUM(H35:K35) -> -296.136 | Z35: =SUM(I35:L35) -> -407.729 | AA35: =SUM(J35:M35) -> -348.59 | AB35: =SUM(K35:N35) -> -359.544 | AC35: =SUM(L35:O35) -> -378.513 | AD35: =SUM(M35:P35) -> -348.552 | AE35: =SUM(N35:Q35) -> -362.247 | AF35: =SUM(O35:R35) -> -339.562 | ... AK35: =SUM(T35:W35) -> -607.559 | AM35: =SUM(AK35/AG35)-1 -> 0.67604332
B36: (-) Cash Taxes | C36: =-('Historical Financials'!E136) -> -291.582 | D36: =-('Historical Financials'!F136) -> -509.265 | E36: =-('Historical Financials'!G136) -> -811.72 | F36: =-('Historical Financials'!H136) -> -1154.973 | G36: =-('Historical Financials'!I136) -> -1641.53 | I36: =('Historical Financials'!O31) -> -382.245 | J36: =('Historical Financials'!P31) -> -182.103 | K36: =('Historical Financials'!Q31) -> -223.605 | L36: =('Historical Financials'!R31) -> 15.948 | M36: =('Historical Financials'!S31) -> -163.754 | N36: =('Historical Financials'!T31) -> -191.722 | O36: =('Historical Financials'!U31) -> -231.627 | P36: =('Historical Financials'!V31) -> -210.312 | ... W36: =('Historical Financials'!AC31) -> -562.494 | Y36: =SUM(H36:K36) -> -787.953 | Z36: =SUM(I36:L36) -> -772.005 | AA36: =SUM(J36:M36) -> -553.514 | AB36: =SUM(K36:N36) -> -563.133 | AC36: =SUM(L36:O36) -> -571.155 | AD36: =SUM(M36:P36) -> -797.415 | AE36: =SUM(N36:Q36) -> -916.031 | AF36: =SUM(O36:R36) -> -1090.859 | ... AK36: =SUM(T36:W36) -> -1657.792 | AM36: =SUM(AK36/AG36)-1 -> 0.38301811
B37: (-) Cash Interest | C37: =-('Historical Financials'!E137) -> -762.904 | D37: =-('Historical Financials'!F137) -> -763.432 | E37: =-('Historical Financials'!G137) -> -701.693 | F37: =-('Historical Financials'!H137) -> -684.504 | G37: =-('Historical Financials'!I137) -> -674.502 | I37: =('Historical Financials'!O26) -> -187.579 | J37: =('Historical Financials'!P26) -> -175.455 | K37: =('Historical Financials'!Q26) -> -172.575 | L37: =('Historical Financials'!R26) -> -170.603 | M37: =('Historical Financials'!S26) -> -174.239 | N37: =('Historical Financials'!T26) -> -174.812 | O37: =('Historical Financials'!U26) -> -175.563 | P37: =('Historical Financials'!V26) -> -175.212 | ... W37: =('Historical Financials'!AC26) -> -175.294 | Y37: =SUM(H37:K37) -> -535.609 | Z37: =SUM(I37:L37) -> -706.212 | AA37: =SUM(J37:M37) -> -692.872 | AB37: =SUM(K37:N37) -> -692.229 | AC37: =SUM(L37:O37) -> -695.217 | AD37: =SUM(M37:P37) -> -699.826 | AE37: =SUM(N37:Q37) -> -698.901 | AF37: =SUM(O37:R37) -> -692.075 | ... AK37: =SUM(T37:W37) -> -734.718 | AM37: =SUM(AK37/AG37)-1 -> 0.047588766
B38: (+/-) Changes in NWC | C38: =SUM('Historical Financials'!E98:E102) -> -31.873 | D38: =SUM('Historical Financials'!F98:F102) -> -241.977 | E38: =SUM('Historical Financials'!G98:G102) -> -758.087 | F38: =SUM('Historical Financials'!H98:H102) -> -116.148 | G38: =SUM('Historical Financials'!I98:I102) -> -33.075 | I38: =SUM('Historical Financials'!O98:O102) -> 25.288 | J38: =SUM('Historical Financials'!P98:P102) -> -122.704 | K38: =SUM('Historical Financials'!Q98:Q102) -> 93.272 | L38: =SUM('Historical Financials'!R98:R102) -> -753.943 | M38: =SUM('Historical Financials'!S98:S102) -> -64.218 | N38: =SUM('Historical Financials'!T98:T102) -> -35.189 | O38: =SUM('Historical Financials'!U98:U102) -> -75.745 | P38: =SUM('Historical Financials'!V98:V102) -> 59.004 | ... W38: =SUM('Historical Financials'!AC98:AC102) -> 575.75 | Y38: =SUM(H38:K38) -> -4.144 | Z38: =SUM(I38:L38) -> -758.087 | AA38: =SUM(J38:M38) -> -847.593 | AB38: =SUM(K38:N38) -> -760.078 | AC38: =SUM(L38:O38) -> -929.095 | AD38: =SUM(M38:P38) -> -116.148 | AE38: =SUM(N38:Q38) -> 53.104 | AF38: =SUM(O38:R38) -> -158.934 | ... AK38: =SUM(T38:W38) -> -274.319 | AM38: =SUM(AK38/AG38)-1 -> -3.845928
B39: Discretionary Cash-Flows | C39: =SUM(C32+SUM(C35:C38)) -> 14338.809 | D39: =SUM(D32+SUM(D35:D38)) -> 16997.249 | E39: =SUM(E32+SUM(E35:E38)) -> 17891.868 | F39: =SUM(F32+SUM(F35:F38)) -> 19543.578 | G39: =SUM(G32+SUM(G35:G38)) -> 23531.988 | I39: =SUM(I32+SUM(I35:I38)) -> 4666.108 | J39: =SUM(J32+SUM(J35:J38)) -> 4503.248 | K39: =SUM(K32+SUM(K35:K38)) -> 5035.992 | L39: =SUM(L32+SUM(L35:L38)) -> 3721.716 | M39: =SUM(M32+SUM(M35:M38)) -> 4899.505 | N39: =SUM(N32+SUM(N35:N38)) -> 4901.924 | O39: =SUM(O32+SUM(O35:O38)) -> 5073.263 | P39: =SUM(P32+SUM(P35:P38)) -> 5011.122 | ... W39: =SUM(W32+SUM(W35:W38)) -> 7092.546 | Y39: =SUM(Y32+SUM(Y35:Y38)) -> 4614.523 | Z39: =SUM(Z32+SUM(Z35:Z38)) -> 5538.31 | AA39: =SUM(AA32+SUM(AA35:AA38)) -> 5961.493 | AB39: =SUM(AB32+SUM(AB35:AB38)) -> 6038.636 | AC39: =SUM(AC32+SUM(AC35:AC38)) -> 5815.758 | AD39: =SUM(AD32+SUM(AD35:AD38)) -> 6554.231 | AE39: =SUM(AE32+SUM(AE35:AE38)) -> 7064.64 | AF39: =SUM(AF32+SUM(AF35:AF38)) -> 7290.293 | ... AK39: =SUM(AK32+SUM(AK35:AK38)) -> 25810.346 | AM39: =SUM(AK39/AG39)-1 -> 0.12227928
B41: (+/-) Proceeds / (Purchases) of ST Investments | C41: =SUM('Historical Financials'!E109:E110) -> 0 | D41: =SUM('Historical Financials'!F109:F110) -> 0 | E41: =SUM('Historical Financials'!G109:G110) -> -911.276 | F41: =SUM('Historical Financials'!H109:H110) -> 890.303 | G41: =SUM('Historical Financials'!I109:I110) -> -1742.246 | I41: =SUM('Historical Financials'!O109:O110) -> 0 | J41: =SUM('Historical Financials'!P109:P110) -> 0 | K41: =SUM('Historical Financials'!Q109:Q110) -> 0 | L41: =SUM('Historical Financials'!R109:R110) -> -911.276 | M41: =SUM('Historical Financials'!S109:S110) -> -201.634 | N41: =SUM('Historical Financials'!T109:T110) -> 198.709 | O41: =SUM('Historical Financials'!U109:U110) -> 400 | P41: =SUM('Historical Financials'!V109:V110) -> 493.228 | ... W41: =SUM('Historical Financials'!AC109:AC110) -> 172.4 | Y41: =SUM(H41:K41) -> 0 | Z41: =SUM(I41:L41) -> -911.276 | AA41: =SUM(J41:M41) -> -1112.91 | AB41: =SUM(K41:N41) -> -914.201 | AC41: =SUM(L41:O41) -> -514.201 | AD41: =SUM(M41:P41) -> 890.303 | AE41: =SUM(N41:Q41) -> 1091.937 | AF41: =SUM(O41:R41) -> 893.228 | ... AK41: =SUM(T41:W41) -> 1747.102
B42: (+/-) Divestiture / Acquisitions | C42: =('Historical Financials'!E108) -> 0 | D42: =('Historical Financials'!F108) -> -788.349 | E42: =('Historical Financials'!G108) -> -757.387 | F42: =('Historical Financials'!H108) -> 0 | G42: =('Historical Financials'!I108) -> 0 | I42: =('Historical Financials'!O108) -> -124.521 | J42: =('Historical Financials'!P108) -> -68.876 | K42: =('Historical Financials'!Q108) -> 0 | L42: =('Historical Financials'!R108) -> -563.99 | M42: =('Historical Financials'!S108) -> 0 | N42: =('Historical Financials'!T108) -> 0 | O42: =('Historical Financials'!U108) -> 0 | P42: =('Historical Financials'!V108) -> 0 | ... W42: =('Historical Financials'!AC108) -> 36.19 | Y42: =SUM(H42:K42) -> -193.397 | Z42: =SUM(I42:L42) -> -757.387 | AA42: =SUM(J42:M42) -> -632.866 | AB42: =SUM(K42:N42) -> -563.99 | AC42: =SUM(L42:O42) -> -563.99 | AD42: =SUM(M42:P42) -> 0 | AE42: =SUM(N42:Q42) -> 0 | AF42: =SUM(O42:R42) -> 0 | ... AK42: =SUM(T42:W42) -> 0
B43: (-) Proceeds From Equity Issuances / (Share Repurchases) | C43: =SUM('Historical Financials'!E117:E118) -> 235.406 | D43: =SUM('Historical Financials'!F117:F118) -> -425.608 | E43: =SUM('Historical Financials'!G117:G118) -> 35.746 | F43: =SUM('Historical Financials'!H117:H118) -> -5875.357 | G43: =SUM('Historical Financials'!I117:I118) -> -5430.859 | I43: =SUM('Historical Financials'!O117:O118) -> 13.678 | J43: =SUM('Historical Financials'!P117:P118) -> 11.25 | K43: =SUM('Historical Financials'!Q117:Q118) -> 4.113 | L43: =SUM('Historical Financials'!R117:R118) -> 6.705 | M43: =SUM('Historical Financials'!S117:S118) -> -374.073 | N43: =SUM('Historical Financials'!T117:T118) -> -610.429 | O43: =SUM('Historical Financials'!U117:U118) -> -2442.282 | P43: =SUM('Historical Financials'!V117:V118) -> -2448.573 | ... W43: =SUM('Historical Financials'!AC117:AC118) -> -1786.67 | AG43: =SUM(P43:S43) -> -7217.696 | AH43: =SUM(Q43:T43) -> -5430.859 | AI43: =SUM(R43:U43) -> -6884.534 | AJ43: =SUM(S43:V43) -> -6888.547 | AK43: =SUM(T43:W43) -> -7118.461
B44: (-) 'Proceeds from issuance of Debt / (Repayment), net | C44: =SUM('Historical Financials'!E114:E116) -> 1001.905 | D44: =SUM('Historical Financials'!F114:F116) -> -500 | E44: =SUM('Historical Financials'!G114:G116) -> -700 | F44: =SUM('Historical Financials'!H114:H116) -> 0 | G44: =SUM('Historical Financials'!I114:I116) -> 1394.46 | I44: =SUM('Historical Financials'!O114:O116) -> -700 | J44: =SUM('Historical Financials'!P114:P116) -> 0 | K44: =SUM('Historical Financials'!Q114:Q116) -> 0 | L44: =SUM('Historical Financials'!R114:R116) -> 0 | M44: =SUM('Historical Financials'!S114:S116) -> 0 | N44: =SUM('Historical Financials'!T114:T116) -> 0 | O44: =SUM('Historical Financials'!U114:U116) -> 0 | P44: =SUM('Historical Financials'!V114:V116) -> 0 | ... W44: =SUM('Historical Financials'!AC114:AC116) -> 0 | AG44: =SUM(P44:S44) -> 1394.46 | AH44: =SUM(Q44:T44) -> 1394.46 | AI44: =SUM(R44:U44) -> 994.46 | AJ44: =SUM(S44:V44) -> -38.99 | AK44: =SUM(T44:W44) -> -1833.45
B45: (+/-) Changes in Additions to content assets | C45: =SUM('Historical Financials'!E89:E90) -> -12536.717 | D45: =SUM('Historical Financials'!F89:F90) -> -17469.304 | E45: =SUM('Historical Financials'!G89:G90) -> -16659.728 | F45: =SUM('Historical Financials'!H89:H90) -> -13140.305 | G45: =SUM('Historical Financials'!I89:I90) -> -17002.752 | I45: =SUM('Historical Financials'!O89:O90) -> -3931.313 | J45: =SUM('Historical Financials'!P89:P90) -> -4495.783 | K45: =SUM('Historical Financials'!Q89:Q90) -> -4521.804 | L45: =SUM('Historical Financials'!R89:R90) -> -3710.828 | M45: =SUM('Historical Financials'!S89:S90) -> -2813.457 | N45: =SUM('Historical Financials'!T89:T90) -> -3636.888 | O45: =SUM('Historical Financials'!U89:U90) -> -3209.828 | P45: =SUM('Historical Financials'!V89:V90) -> -3480.132 | ... W45: =SUM('Historical Financials'!AC89:AC90) -> -4629.673 | AF45: =SUM(O45:R45) -> -15023.792 | AG45: =SUM(P45:S45) -> -15913.945 | AH45: =SUM(Q45:T45) -> -17002.752 | AI45: =SUM(R45:U45) -> -17045.254 | AJ45: =SUM(S45:V45) -> -16679.695 | AK45: =SUM(T45:W45) -> -17209.387
B46: (+/-) Changes in Other Financing Activities | C46: =SUM('Historical Financials'!E119:E120) -> 0 | D46: =SUM('Historical Financials'!F119:F120) -> -224.168 | E46: =SUM('Historical Financials'!G119:G120) -> 0 | F46: =SUM('Historical Financials'!H119:H120) -> -75.446 | G46: =SUM('Historical Financials'!I119:I120) -> -38.028 | I46: =SUM('Historical Financials'!O119:O120) -> 0 | J46: =SUM('Historical Financials'!P119:P120) -> 0 | K46: =SUM('Historical Financials'!Q119:Q120) -> 0 | L46: =SUM('Historical Financials'!R119:R120) -> 0 | M46: =SUM('Historical Financials'!S119:S120) -> 0 | N46: =SUM('Historical Financials'!T119:T120) -> -38.92 | O46: =SUM('Historical Financials'!U119:U120) -> -32.826 | P46: =SUM('Historical Financials'!V119:V120) -> -3.7 | ... W46: =SUM('Historical Financials'!AC119:AC120) -> 49.641 | AG46: =SUM(P46:S46) -> -24.766 | AH46: =SUM(Q46:T46) -> -38.028 | AI46: =SUM(R46:U46) -> -79.725 | AJ46: =SUM(S46:V46) -> -55.749 | AK46: =SUM(T46:W46) -> 5
B47: (+/-) Other | D47: =SUM(D52-C52)-SUM(D39:D45) -> 8.266 | E47: =SUM(E52-D52)-SUM(E39:E45) -> 220.149 | F47: =SUM(F52-E52)-SUM(F39:F45) -> 551.518 | G47: =SUM(G52-F52)-SUM(G39:G46) -> -24.743 | I47: =SUM(I52-D52)-SUM(I39:I46) -> 57.19 | J47: =SUM(J52-I52)-SUM(J39:J46) -> -139.336 | K47: =SUM(K52-J52)-SUM(K39:K46) -> -224.017 | L47: =SUM(L52-K52)-SUM(L39:L46) -> 491.116 | M47: =SUM(M52-L52)-SUM(M39:M46) -> 57.077 | N47: =SUM(N52-M52)-SUM(N39:N46) -> 133.798 | O47: =SUM(O52-N52)-SUM(O39:O46) -> -97.87 | P47: =SUM(P52-O52)-SUM(P39:P46) -> 191.723 | Q47: =SUM(Q52-P52)-SUM(Q39:Q46) -> -81.349 | ... W47: =SUM(W52-V52)-SUM(W39:W46) -> 175.448 | Y47: =SUM(H47:K47) -> -306.163 | Z47: =SUM(I47:L47) -> 184.953 | AA47: =SUM(J47:M47) -> 184.84 | AB47: =SUM(K47:N47) -> 457.974 | AC47: =SUM(L47:O47) -> 584.121 | AD47: =SUM(M47:P47) -> 284.728 | AE47: =SUM(N47:Q47) -> 146.302 | AF47: =SUM(O47:R47) -> -144.988 | ... AK47: =SUM(T47:W47) -> 429.112
B48: Free-Cash Flows | C48: =SUM(C39+SUM(C41:C47)) -> 3039.403 | D48: =SUM(D39+SUM(D41:D47)) -> -2401.914 | E48: =SUM(E39+SUM(E41:E47)) -> -880.628 | F48: =SUM(F39+SUM(F41:F47)) -> 1894.291 | G48: =SUM(G39+SUM(G41:G47)) -> 687.82 | I48: =SUM(I39+SUM(I41:I47)) -> -18.858 | J48: =SUM(J39+SUM(J41:J47)) -> -189.497 | K48: =SUM(K39+SUM(K41:K47)) -> 294.284 | L48: =SUM(L39+SUM(L41:L47)) -> -966.557 | M48: =SUM(M39+SUM(M41:M47)) -> 1567.418 | N48: =SUM(N39+SUM(N41:N47)) -> 948.194 | O48: =SUM(O39+SUM(O41:O47)) -> -309.543 | P48: =SUM(P39+SUM(P41:P47)) -> -236.332 | ... W48: =SUM(W39+SUM(W41:W47)) -> 1109.882 | Y48: =SUM(Y39+SUM(Y41:Y47)) -> 4114.963 | Z48: =SUM(Z39+SUM(Z41:Z47)) -> 4054.6 | AA48: =SUM(AA39+SUM(AA41:AA47)) -> 4400.557 | AB48: =SUM(AB39+SUM(AB41:AB47)) -> 5018.419 | AC48: =SUM(AC39+SUM(AC41:AC47)) -> 5321.688 | AD48: =SUM(AD39+SUM(AD41:AD47)) -> 7729.262 | AE48: =SUM(AE39+SUM(AE41:AE47)) -> 8302.879 | AF48: =SUM(AF39+SUM(AF41:AF47)) -> -6985.259 | ... AK48: =SUM(AK39+SUM(AK41:AK47)) -> 1830.262
B50: Capitalization
B52: Cash & Cash Equivelants | C52: =('Historical Financials'!E46) -> 8205.55 | D52: =('Historical Financials'!F46) -> 6027.804 | E52: =('Historical Financials'!G46) -> 5147.176 | F52: =('Historical Financials'!H46) -> 7116.913 | G52: =('Historical Financials'!I46) -> 7804.733 | I52: =('Historical Financials'!O46) -> 6008.946 | J52: =('Historical Financials'!P46) -> 5819.449 | K52: =('Historical Financials'!Q46) -> 6113.733 | L52: =('Historical Financials'!R46) -> 5147.176 | M52: =('Historical Financials'!S46) -> 6714.594 | N52: =('Historical Financials'!T46) -> 7662.788 | O52: =('Historical Financials'!U46) -> 7353.245 | P52: =('Historical Financials'!V46) -> 7116.913 | ... W52: =('Historical Financials'!AC46) -> 9287.287 | Y52: =K52 -> 6113.733 | Z52: =L52 -> 5147.176 | AA52: =M52 -> 6714.594 | AB52: =N52 -> 7662.788 | AC52: =O52 -> 7353.245 | AD52: =P52 -> 7116.913 | AE52: =Q52 -> 7024.766 | AF52: =R52 -> 6624.939 | ... AK52: =W52 -> 9287.287
B53: Marketable Securities | C53: =('Historical Financials'!E48) -> 0 | D53: =('Historical Financials'!F48) -> 0 | E53: =('Historical Financials'!G48) -> 911.276 | F53: =('Historical Financials'!H48) -> 20.973 | G53: =('Historical Financials'!I48) -> 1779.006 | I53: =('Historical Financials'!O48) -> 0 | J53: =('Historical Financials'!P48) -> 0 | K53: =('Historical Financials'!Q48) -> 0 | L53: =('Historical Financials'!R48) -> 911.276 | M53: =('Historical Financials'!S48) -> 1112.91 | N53: =('Historical Financials'!T48) -> 914.201 | O53: =('Historical Financials'!U48) -> 514.201 | P53: =('Historical Financials'!V48) -> 20.973 | ... W53: =('Historical Financials'!AC48) -> 37.105 | AG53: =S53 -> 1766.902 | AH53: =T53 -> 1779.006 | AI53: =U53 -> 1171.142 | AJ53: =V53 -> 213.115 | AK53: =W53 -> 37.105
B54: $3Bn RCF due April 2025, April 2029 (CP Backstop) | C54: 750 | D54: 1000 | E54: 1000 | F54: 1000 | G54: 3000 | I54: 1000 | J54: 1000 | K54: 1000 | L54: =E54 -> 1000 | M54: 1000 | N54: 1000 | O54: 1000 | P54: =F54 -> 1000 | Q54: 3000 | R54: 3000 | S54: 3000 | T54: =G54 -> 3000 | U54: 3000 | V54: 3000 | W54: 3000 | AG54: =S54 -> 3000 | AH54: =T54 -> 3000 | AI54: =U54 -> 3000 | AJ54: =V54 -> 3000 | AK54: =W54 -> 3000
B55: Total Liquidity | C55: =SUM(C52:C54) -> 8955.55 | D55: =SUM(D52:D54) -> 7027.804 | E55: =SUM(E52:E54) -> 7058.452 | F55: =SUM(F52:F54) -> 8137.886 | G55: =SUM(G52:G54) -> 12583.739 | I55: =SUM(I52:I54) -> 7008.946 | J55: =SUM(J52:J54) -> 6819.449 | K55: =SUM(K52:K54) -> 7113.733 | L55: =SUM(L52:L54) -> 7058.452 | M55: =SUM(M52:M54) -> 8827.504 | N55: =SUM(N52:N54) -> 9576.989 | O55: =SUM(O52:O54) -> 8867.446 | P55: =SUM(P52:P54) -> 8137.886 | ... W55: =SUM(W52:W54) -> 12324.392 | Y55: =SUM(Y52:Y52) -> 6113.733 | Z55: =SUM(Z52:Z52) -> 5147.176 | AA55: =SUM(AA52:AA52) -> 6714.594 | AB55: =SUM(AB52:AB52) -> 7662.788 | AC55: =SUM(AC52:AC52) -> 7353.245 | AD55: =SUM(AD52:AD52) -> 7116.913 | AE55: =SUM(AE52:AE52) -> 7024.766 | AF55: =SUM(AF52:AF52) -> 6624.939 | AG55: =SUM(AG52:AG54) -> 12223.927 | AH55: =SUM(AH52:AH54) -> 12583.739 | AI55: =SUM(AI52:AI54) -> 11370.99 | AJ55: =SUM(AJ52:AJ54) -> 11390.52 | AK55: =SUM(AK52:AK54) -> 12324.392
B57: Balance Sheet Metrics:
B58: Property and Equipment, net | C58: =('Historical Financials'!E53) -> 960.183 | D58: =('Historical Financials'!F53) -> 1323.453 | E58: =('Historical Financials'!G53) -> 1398.257 | F58: =('Historical Financials'!H53) -> 1491.444 | G58: =('Historical Financials'!I53) -> 1593.756 | I58: =('Historical Financials'!O53) -> 1383.763 | J58: =('Historical Financials'!P53) -> 1361.92 | K58: =('Historical Financials'!Q53) -> 1372.754 | L58: =('Historical Financials'!R53) -> 1398.257 | M58: =('Historical Financials'!S53) -> 1413.094 | N58: =('Historical Financials'!T53) -> 1471.968 | O58: =('Historical Financials'!U53) -> 1498.391 | P58: =('Historical Financials'!V53) -> 1491.444 | ... W58: =('Historical Financials'!AC53) -> 1837.889 | Y58: =K58 -> 1372.754 | Z58: =L58 -> 1398.257 | AA58: =M58 -> 1413.094 | AB58: =N58 -> 1471.968 | AC58: =O58 -> 1498.391 | AD58: =P58 -> 1491.444 | AE58: =Q58 -> 1501.168 | AF58: =R58 -> 1510.958 | ... AK58: =W58 -> 1837.889
B59: Content Liabilities | C59: =('Historical Financials'!E58) -> 4429.536 | D59: =('Historical Financials'!F58) -> 4292.967 | E59: =('Historical Financials'!G58) -> 4480.15 | F59: =('Historical Financials'!H58) -> 4466.47 | G59: =('Historical Financials'!I58) -> 4393.681 | I59: =('Historical Financials'!O58) -> 4066.289 | J59: =('Historical Financials'!P58) -> 4174.966 | K59: =('Historical Financials'!Q58) -> 4225.89 | L59: =('Historical Financials'!R58) -> 4480.15 | M59: =('Historical Financials'!S58) -> 4344.58 | N59: =('Historical Financials'!T58) -> 4440.412 | O59: =('Historical Financials'!U58) -> 4259.582 | P59: =('Historical Financials'!V58) -> 4466.47 | ... W59: =('Historical Financials'!AC58) -> 4102.64 | Y59: =K59 -> 4225.89 | Z59: =L59 -> 4480.15 | AA59: =M59 -> 4344.58 | AB59: =N59 -> 4440.412 | AC59: =O59 -> 4259.582 | AD59: =P59 -> 4466.47 | AE59: =Q59 -> 4436.021 | AF59: =R59 -> 4391.437 | ... AK59: =W59 -> 4102.64
B60: Accounts Payable | C60: =('Historical Financials'!E59) -> 656.183 | D60: =('Historical Financials'!F59) -> 837.483 | E60: =('Historical Financials'!G59) -> 671.513 | F60: =('Historical Financials'!H59) -> 747.412 | G60: =('Historical Financials'!I59) -> 899.909 | I60: =('Historical Financials'!O59) -> 617.202 | J60: =('Historical Financials'!P59) -> 504.278 | K60: =('Historical Financials'!Q59) -> 560.156 | L60: =('Historical Financials'!R59) -> 671.513 | M60: =('Historical Financials'!S59) -> 591.987 | N60: =('Historical Financials'!T59) -> 615.374 | O60: =('Historical Financials'!U59) -> 534.429 | P60: =('Historical Financials'!V59) -> 747.412 | ... W60: =('Historical Financials'!AC59) -> 793.233 | AG60: =S60 -> 641.953 | AH60: =T60 -> 899.909 | AI60: =U60 -> 614.489 | AJ60: =V60 -> 632.718 | AK60: =W60 -> 793.233
B61: Deferred Revenue | C61: =('Historical Financials'!E61) -> 1117.992 | D61: =('Historical Financials'!F61) -> 1209.342 | E61: =('Historical Financials'!G61) -> 1264.661 | F61: =('Historical Financials'!H61) -> 1442.969 | G61: =('Historical Financials'!I61) -> 1520.813 | I61: =('Historical Financials'!O61) -> 1239.048 | J61: =('Historical Financials'!P61) -> 1224.743 | K61: =('Historical Financials'!Q61) -> 1176.323 | L61: =('Historical Financials'!R61) -> 1264.661 | M61: =('Historical Financials'!S61) -> 1262.271 | N61: =('Historical Financials'!T61) -> 1311.918 | O61: =('Historical Financials'!U61) -> 1306.185 | P61: =('Historical Financials'!V61) -> 1442.969 | ... W61: =('Historical Financials'!AC61) -> 1724.675 | AG61: =S61 -> 1513.048 | AH61: =T61 -> 1520.813 | AI61: =U61 -> 1609.726 | AJ61: =V61 -> 1728.361 | AK61: =W61 -> 1724.675
B62: Current Liabilities | C62: =('Historical Financials'!E63) -> 7805.785 | D62: =('Historical Financials'!F63) -> 8488.966 | E62: =('Historical Financials'!G63) -> 7930.974 | F62: =('Historical Financials'!H63) -> 8860.655 | G62: =('Historical Financials'!I63) -> 10755.4 | I62: =('Historical Financials'!O63) -> 7739.656 | J62: =('Historical Financials'!P63) -> 7500.022 | K62: =('Historical Financials'!Q63) -> 7765.924 | L62: =('Historical Financials'!R63) -> 7930.974 | M62: =('Historical Financials'!S63) -> 8316.07 | N62: =('Historical Financials'!T63) -> 8675.805 | O62: =('Historical Financials'!U63) -> 8338.718 | P62: =('Historical Financials'!V63) -> 8860.655 | ... W62: =('Historical Financials'!AC63) -> 9731.859 | Y62: =K62 -> 7765.924 | Z62: =L62 -> 7930.974 | AA62: =M62 -> 8316.07 | AB62: =N62 -> 8675.805 | AC62: =O62 -> 8338.718 | AD62: =P62 -> 8860.655 | AE62: =Q62 -> 9289.217 | AF62: =R62 -> 10139.999 | ... AK62: =W62 -> 9731.859
B63: Total Liabilities | C63: =('Historical Financials'!E69) -> 28215.119 | D63: =('Historical Financials'!F69) -> 28735.415 | E63: =('Historical Financials'!G69) -> 27817.367 | F63: =('Historical Financials'!H69) -> 28143.679 | G63: =('Historical Financials'!I69) -> 28886.807 | I63: =('Historical Financials'!O69) -> 27786.865 | J63: =('Historical Financials'!P69) -> 27274.961 | K63: =('Historical Financials'!Q69) -> 27034.046 | L63: =('Historical Financials'!R69) -> 27817.367 | M63: =('Historical Financials'!S69) -> 27662.149 | N63: =('Historical Financials'!T69) -> 27985.258 | O63: =('Historical Financials'!U69) -> 27394.159 | P63: =('Historical Financials'!V69) -> 28143.679 | ... W63: =('Historical Financials'!AC69) -> 28980.8 | Y63: =K63 -> 27034.046 | Z63: =L63 -> 27817.367 | AA63: =M63 -> 27662.149 | AB63: =N63 -> 27985.258 | AC63: =O63 -> 27394.159 | AD63: =P63 -> 28143.679 | AE63: =Q63 -> 27462.311 | AF63: =R63 -> 26986.202 | ... AK63: =W63 -> 28980.8
B65: Summary Debt:
B66: CPLTD | C66: =('Historical Financials'!E62) -> 499.878 | D66: =('Historical Financials'!F62) -> 699.823 | E66: =('Historical Financials'!G62) -> 0 | F66: =('Historical Financials'!H62) -> 399.844 | G66: =('Historical Financials'!I62) -> 1784.453 | I66: =('Historical Financials'!O62) -> 0 | J66: =('Historical Financials'!P62) -> 0 | K66: =('Historical Financials'!Q62) -> 0 | L66: =('Historical Financials'!R62) -> 0 | M66: =('Historical Financials'!S62) -> 399.163 | N66: =('Historical Financials'!T62) -> 399.387 | O66: =('Historical Financials'!U62) -> 399.614 | P66: =('Historical Financials'!V62) -> 399.844 | ... W66: =('Historical Financials'!AC62) -> 0 | AG66: =S66 -> 1820.396 | AH66: =T66 -> 1784.453 | AI66: =U66 -> 1005.881 | AJ66: =V66 -> 0 | AK66: =W66 -> 0
B67: LTD | C67: =('Historical Financials'!E67) -> 15809.095 | D67: =('Historical Financials'!F67) -> 14693.072 | E67: =('Historical Financials'!G67) -> 14353.076 | F67: =('Historical Financials'!H67) -> 14143.417 | G67: =('Historical Financials'!I67) -> 13798.351 | I67: =('Historical Financials'!O67) -> 14534.561 | J67: =('Historical Financials'!P67) -> 14233.303 | K67: =('Historical Financials'!Q67) -> 13888.117 | L67: =('Historical Financials'!R67) -> 14353.076 | M67: =('Historical Financials'!S67) -> 14037.965 | N67: =('Historical Financials'!T67) -> 14070.151 | O67: =('Historical Financials'!U67) -> 13900.754 | P67: =('Historical Financials'!V67) -> 14143.417 | ... W67: =('Historical Financials'!AC67) -> 14463.02 | AG67: =S67 -> 14160.932 | AH67: =T67 -> 13798.351 | AI67: =U67 -> 14011.037 | AJ67: =V67 -> 14453.206 | AK67: =W67 -> 14463.02
B69: $3Bn Commercial Paper Program | C69: 0 | D69: 0 | E69: 0 | F69: 0 | G69: 0 | I69: 0 | J69: 0 | K69: 0 | L69: =E69 -> 0 | M69: 0 | N69: 0 | O69: 0 | P69: =F69 -> 0 | Q69: 0 | R69: 0 | S69: 0 | T69: =G69 -> 0 | U69: 0 | V69: 0 | W69: 0 | Y69: =K69 -> 0 | Z69: =L69 -> 0 | AA69: =M69 -> 0 | AB69: =N69 -> 0 | AC69: =O69 -> 0 | AD69: =P69 -> 0 | AE69: =Q69 -> 0 | AF69: =R69 -> 0 | ... AK69: =W69 -> 0
B70: Consolidated Sr. Notes | C70: ='Debt Schedule'!C25 -> 16416 | D70: ='Debt Schedule'!D25 -> 15485 | E70: ='Debt Schedule'!E25 -> 14432 | F70: ='Debt Schedule'!F25 -> 14608 | G70: ='Debt Schedule'!G25 -> 15653 | I70: ='Debt Schedule'!I25 -> 14623 | J70: ='Debt Schedule'!J25 -> 14318 | K70: ='Debt Schedule'!K25 -> 13970 | L70: ='Debt Schedule'!L25 -> 14432 | M70: ='Debt Schedule'!M25 -> 14513 | N70: ='Debt Schedule'!N25 -> 14542 | O70: ='Debt Schedule'!O25 -> 14368 | P70: ='Debt Schedule'!P25 -> 14608 | ... W70: ='Debt Schedule'!W25 -> 14523 | Y70: =K70 -> 13970 | Z70: =L70 -> 14432 | AA70: =M70 -> 14513 | AB70: =N70 -> 14542 | AC70: =O70 -> 14368 | AD70: =P70 -> 14608 | AE70: =Q70 -> 14077 | AF70: =R70 -> 14038 | ... AK70: =W70 -> 14523
B71: Total Debt | C71: =SUM(C70:C70) -> 16416 | D71: =SUM(D70:D70) -> 15485 | E71: =SUM(E70:E70) -> 14432 | F71: =SUM(F70:F70) -> 14608 | G71: =SUM(G70:G70) -> 15653 | I71: =SUM(I70:I70) -> 14623 | J71: =SUM(J70:J70) -> 14318 | K71: =SUM(K70:K70) -> 13970 | L71: =SUM(L70:L70) -> 14432 | M71: =SUM(M70:M70) -> 14513 | N71: =SUM(N70:N70) -> 14542 | O71: =SUM(O70:O70) -> 14368 | P71: =SUM(P70:P70) -> 14608 | ... W71: =SUM(W70:W70) -> 14523 | Y71: =SUM(Y70:Y70) -> 13970 | Z71: =SUM(Z70:Z70) -> 14432 | AA71: =SUM(AA70:AA70) -> 14513 | AB71: =SUM(AB70:AB70) -> 14542 | AC71: =SUM(AC70:AC70) -> 14368 | AD71: =SUM(AD70:AD70) -> 14608 | AE71: =SUM(AE70:AE70) -> 14077 | AF71: =SUM(AF70:AF70) -> 14038 | ... AK71: =SUM(AK70:AK70) -> 14523
B73: Total Shareholder Equity | C73: =('Historical Financials'!E75) -> 11065.24 | D73: =('Historical Financials'!F75) -> 15849.248 | E73: =('Historical Financials'!G75) -> 20777.401 | F73: =('Historical Financials'!H75) -> 20588.313 | G73: =('Historical Financials'!I75) -> 24743.567 | I73: =('Historical Financials'!O75) -> 17544.039 | J73: =('Historical Financials'!P75) -> 19075.974 | K73: =('Historical Financials'!Q75) -> 20528.141 | L73: =('Historical Financials'!R75) -> 20777.401 | M73: =('Historical Financials'!S75) -> 21828.196 | N73: =('Historical Financials'!T75) -> 22832.215 | O73: =('Historical Financials'!U75) -> 22107.627 | P73: =('Historical Financials'!V75) -> 20588.313 | ... W73: =('Historical Financials'!AC75) -> 25954.035 | Y73: =K73 -> 20528.141 | Z73: =L73 -> 20777.401 | AA73: =M73 -> 21828.196 | AB73: =N73 -> 22832.215 | AC73: =O73 -> 22107.627 | AD73: =P73 -> 20588.313 | AE73: =Q73 -> 21365.41 | AF73: =R73 -> 22112.693 | ... AK73: =W73 -> 25954.035
B74: Total Book Capitalization | C74: =SUM(C71:C73) -> 27481.24 | D74: =SUM(D71:D73) -> 31334.248 | E74: =SUM(E71:E73) -> 35209.401 | F74: =SUM(F71:F73) -> 35196.313 | G74: =SUM(G71:G73) -> 40396.567 | I74: =SUM(I71:I73) -> 32167.039 | J74: =SUM(J71:J73) -> 33393.974 | K74: =SUM(K71:K73) -> 34498.141 | L74: =SUM(L71:L73) -> 35209.401 | M74: =SUM(M71:M73) -> 36341.196 | N74: =SUM(N71:N73) -> 37374.215 | O74: =SUM(O71:O73) -> 36475.627 | P74: =SUM(P71:P73) -> 35196.313 | ... W74: =SUM(W71:W73) -> 40477.035 | Y74: =SUM(Y71:Y73) -> 34498.141 | Z74: =SUM(Z71:Z73) -> 35209.401 | AA74: =SUM(AA71:AA73) -> 36341.196 | AB74: =SUM(AB71:AB73) -> 37374.215 | AC74: =SUM(AC71:AC73) -> 36475.627 | AD74: =SUM(AD71:AD73) -> 35196.313 | AE74: =SUM(AE71:AE73) -> 35442.41 | AF74: =SUM(AF71:AF73) -> 36150.693 | ... AK74: =SUM(AK71:AK73) -> 40477.035
B76: Credit Metrics
B78: LTM Total Leverage | C78: =C71/C32 -> 1.0309556 | D78: =D71/D32 -> 0.813437 | E78: =E71/E32 -> 0.70156686 | F78: =F71/F32 -> 0.66862705 | G78: =G71/G32 -> 0.59470454 | L78: =SUM(L71/SUM(I32:L32)) -> 0.70156686 | M78: =SUM(M71/SUM(J32:M32)) -> 0.70441095 | N78: =SUM(N71/SUM(K32:N32)) -> 0.69465539 | O78: =SUM(O71/SUM(L32:O32)) -> 0.67868383 | P78: =SUM(P71/SUM(M32:P32)) -> 0.66862705 | Q78: =SUM(Q71/SUM(N32:Q32)) -> 0.61335184 | R78: =SUM(R71/SUM(O32:R32)) -> 0.58324375 | S78: =SUM(S71/SUM(P32:S32)) -> 0.63800768 | ... W78: =SUM(W71/SUM(T32:W32)) -> 0.49933412 | Y78: =Y71/Y32 -> 2.2393688 | Z78: =Z71/Z32 -> 1.763798 | AA78: =AA71/AA32 -> 1.726903 | AB78: =AB71/AB32 -> 1.728388 | AC78: =AC71/AC32 -> 1.7125684 | AD78: =AD71/AD32 -> 1.7153247 | AE78: =AE71/AE32 -> 1.5660748 | AF78: =AF71/AF32 -> 1.4666116 | ... AK78: =AK71/AK32 -> 0.49933412
B79: LTM Net Leverage | C79: =SUM(C71-C52)/C32 -> 0.51563167 | D79: =SUM(D71-D52)/D32 -> 0.49679258 | E79: =SUM(E71-E52)/E32 -> 0.45135289 | F79: =SUM(F71-F52)/F32 -> 0.34287674 | G79: =SUM(G71-G52)/G32 -> 0.29817926 | L79: =SUM(L71-L52)/SUM(I32:L32) -> 0.45135289 | M79: =SUM(M71-M52)/SUM(J32:M32) -> 0.37850772 | N79: =SUM(N71-N52)/SUM(K32:N32) -> 0.32861241 | O79: =SUM(O71-O52)/SUM(L32:O32) -> 0.33134749 | P79: =SUM(P71-P52)/SUM(M32:P32) -> 0.34287674 | Q79: =SUM(Q71-Q52)/SUM(N32:Q32) -> 0.30727433 | R79: =SUM(R71-R52)/SUM(O32:R32) -> 0.30799412 | S79: =SUM(S71-S52)/SUM(P32:S32) -> 0.34167387 | ... W79: =SUM(W71-W52)/SUM(T32:W32) -> 0.18001585 | Y79: =SUM(Y71-Y52)/Y32 -> 1.2593471 | Z79: =SUM(Z71-Z52)/Z32 -> 1.134739 | AA79: =SUM(AA71-AA52)/AA32 -> 0.92793294 | AB79: =SUM(AB71-AB52)/AB32 -> 0.81762808 | AC79: =SUM(AC71-AC52)/AC32 -> 0.83611133 | AD79: =SUM(AD71-AD52)/AD32 -> 0.87963078 | AE79: =SUM(AE71-AE52)/AE32 -> 0.78456531 | AF79: =SUM(AF71-AF52)/AF32 -> 0.77447509 | ... AK79: =SUM(AK71-AK52)/AK32 -> 0.18001585
B80: LTM Interest Coverage | C80: =C32/-C37 -> 20.871684 | D80: =D32/-D37 -> 24.935434 | E80: =E32/-E37 -> 29.316378 | F80: =F32/-F37 -> 31.917644 | G80: =G32/-G37 -> 39.02232 | L80: {=SUM(I32:L32)/SUM(-I37:L37)} -> 29.128784 | M80: {=SUM(J32:M32)/SUM(-J37:M37)} -> 29.735694 | N80: {=SUM(K32:N32)/SUM(-K37:N37)} -> 30.241612 | O80: {=SUM(L32:O32)/SUM(-L37:O37)} -> 30.451482 | P80: {=SUM(M32:P32)/SUM(-M37:P37)} -> 31.218839 | Q80: {=SUM(N32:Q32)/SUM(-N37:Q37)} -> 32.838611 | R80: {=SUM(O32:R32)/SUM(-O37:R37)} -> 34.77779 | S80: {=SUM(P32:S32)/SUM(-P37:S37)} -> 35.880175 | ... W80: {=SUM(T32:W32)/SUM(-T37:W37)} -> 39.586255 | Y80: =Y32/-Y37 -> 11.647237 | Z80: =Z32/-Z37 -> 11.586242 | AA80: =AA32/-AA37 -> 12.129314 | AB80: =AB32/-AB37 -> 12.154388 | AC80: =AC32/-AC37 -> 12.067798 | AD80: =AD32/-AD37 -> 12.168985 | AE80: =AE32/-AE37 -> 12.861214 | AF80: =AF32/-AF37 -> 13.830471 | ... AK80: =AK32/-AK37 -> 39.586255
B81: LTM Debt Service Coverage | C81: {=SUM(C32+C35)/SUM(-C36:C37)} -> 14.628139 | D81: {=SUM(D32+D35)/SUM(-D36:D37)} -> 14.545428 | E81: {=SUM(E32+E35)/SUM(-E36:E37)} -> 13.32311 | F81: {=SUM(F32+F35)/SUM(-F36:F37)} -> 11.687672 | G81: {=SUM(G32+G35)/SUM(-G36:G37)} -> 11.174757 | L81: {=SUM(I32:L32+I35:L35)/SUM(-I36:L37)} -> 13.64033 | M81: {=SUM(J32:M32+J35:M35)/SUM(-J36:M37)} -> 16.250536 | N81: {=SUM(K32:N32+K35:N35)/SUM(-K36:N37)} -> 16.389358 | O81: {=SUM(L32:O32+L35:O35)/SUM(-L36:O37)} -> 16.418458 | P81: {=SUM(M32:P32+M35:P35)/SUM(-M36:P37)} -> 14.359213 | Q81: {=SUM(N32:Q32+N35:Q35)/SUM(-N36:Q37)} -> 13.987395 | R81: {=SUM(O32:R32+O35:R35)/SUM(-O36:R37)} -> 13.309117 | S81: {=SUM(P32:S32+P35:S35)/SUM(-P36:S37)} -> 13.053437 | ... W81: {=SUM(T32:W32+T35:W35)/SUM(-T36:W37)} -> 11.902636 | Y81: {=SUM(Y32+Y35)/SUM(-Y36:Y37)} -> 4.4895736 | Z81: {=SUM(Z32+Z35)/SUM(-Z36:Z37)} -> 5.2594538 | AA81: {=SUM(AA32+AA35)/SUM(-AA36:AA37)} -> 6.4630636 | AB81: {=SUM(AB32+AB35)/SUM(-AB36:AB37)} -> 6.4157398 | AC81: {=SUM(AC32+AC35)/SUM(-AC36:AC37)} -> 6.326123 | AD81: {=SUM(AD32+AD35)/SUM(-AD36:AD37)} -> 5.4551138 | AE81: {=SUM(AE32+AE35)/SUM(-AE36:AE37)} -> 5.3416912 | AF81: {=SUM(AF32+AF35)/SUM(-AF36:AF37)} -> 5.1780722 | ... AK81: {=SUM(AK32+AK35)/SUM(-AK36:AK37)} -> 11.902636
B82: LTM Fixed Charge Coverage | C82: {=SUM(C32)/SUM(-C35:C37)} -> 10.257021 | D82: {=SUM(D32)/SUM(-D35:D37)} -> 10.591831 | E82: {=SUM(E32)/SUM(-E35:E37)} -> 10.707744 | F82: {=SUM(F32)/SUM(-F35:F37)} -> 9.9851305 | G82: {=SUM(G32)/SUM(-G35:G37)} -> 9.5517926 | L82: {=SUM(I32:L32)/SUM(-I35:L37)} -> 10.907575 | M82: {=SUM(J32:M32)/SUM(-J35:M37)} -> 12.917455 | N82: {=SUM(K32:N32)/SUM(-K35:N37)} -> 12.963059 | O82: {=SUM(L32:O32)/SUM(-L35:O37)} -> 12.870437 | P82: {=SUM(M32:P32)/SUM(-M35:P37)} -> 11.836514 | Q82: {=SUM(N32:Q32)/SUM(-N35:Q37)} -> 11.607921 | R82: {=SUM(O32:R32)/SUM(-O35:R37)} -> 11.339875 | S82: {=SUM(P32:S32)/SUM(-P35:S37)} -> 11.122257 | ... W82: {=SUM(T32:W32)/SUM(-T35:W37)} -> 9.6946884 | Y82: {=SUM(Y32)/SUM(-Y35:Y37)} -> 3.8515606 | Z82: {=SUM(Z32)/SUM(-Z35:Z37)} -> 4.3385882 | AA82: {=SUM(AA32)/SUM(-AA35:AA37)} -> 5.2690837 | AB82: {=SUM(AB32)/SUM(-AB35:AB37)} -> 5.2099751 | AC82: {=SUM(AC32)/SUM(-AC35:AC37)} -> 5.1005013 | AD82: {=SUM(AD32)/SUM(-AD35:AD37)} -> 4.6138283 | AE82: {=SUM(AE32)/SUM(-AE35:AE37)} -> 4.5462323 | AF82: {=SUM(AF32)/SUM(-AF35:AF37)} -> 4.5096542 | ... AK82: {=SUM(AK32)/SUM(-AK35:AK37)} -> 9.6946884
B83: Debt-to-Book Capitalization | C83: =C74/C71 -> 1.6740521 | D83: =D74/D71 -> 2.0235226 | E83: =E74/E71 -> 2.4396758 | F83: =F74/F71 -> 2.4093862 | G83: =G74/G71 -> 2.5807556 | L83: =L74/L71 -> 2.4396758 | M83: =M74/M71 -> 2.5040444 | N83: =N74/N71 -> 2.5700877 | O83: =O74/O71 -> 2.5386711 | P83: =P74/P71 -> 2.4093862 | Q83: =Q74/Q71 -> 2.5177531 | R83: =R74/R71 -> 2.5752025 | S83: =S74/S71 -> 2.4151813 | ... W83: =W74/W71 -> 2.7870987 | Y83: =Y74/Y71 -> 2.4694446 | Z83: =Z74/Z71 -> 2.4396758 | AA83: =AA74/AA71 -> 2.5040444 | AB83: =AB74/AB71 -> 2.5700877 | AC83: =AC74/AC71 -> 2.5386711 | AD83: =AD74/AD71 -> 2.4093862 | AE83: =AE74/AE71 -> 2.5177531 | AF83: =AF74/AF71 -> 2.5752025 | ... AK83: =AK74/AK71 -> 2.7870987

Sheet Debt Schedule
B2: ='Historical Financials'!B2 -> Netflix, Inc. (NASDAQ: NFLX) | C2: FYE | E2: FYE | I2: Quarterly | M2: Quarterly | S2: Quarterly | Y2: LTM | AF2: LTM | AG2: LTM
B3: Debt Schedule | C3: ='Historical Financials'!E7 -> 2020 | D3: ='Historical Financials'!F7 -> 2021 | E3: ='Historical Financials'!G7 -> 2022 | F3: ='Historical Financials'!H7 -> 2023 | G3: ='Historical Financials'!I7 -> 2024 | I3: ='Historical Financials'!O7 -> 1Q22 | J3: ='Historical Financials'!P7 -> 2Q22 | K3: ='Historical Financials'!Q7 -> 3Q22 | L3: ='Historical Financials'!R7 -> 4Q22 | M3: ='Historical Financials'!S7 -> 1Q23 | N3: ='Historical Financials'!T7 -> 2Q23 | O3: ='Historical Financials'!U7 -> 3Q23 | P3: ='Historical Financials'!V7 -> 4Q23 | ... W3: ='Historical Financials'!AC7 -> 3Q25 | Y3: =K3 -> 3Q22 | Z3: =L3 -> 4Q22 | AA3: =M3 -> 1Q23 | AB3: =N3 -> 2Q23 | AC3: =O3 -> 3Q23 | AD3: =P3 -> 4Q23 | AE3: =Q3 -> 1Q24 | AF3: =R3 -> 2Q24 | ... AK3: =W3 -> 3Q25
B4: ($ in Millions) | C4: ='Historical Financials'!E8 -> 44196 | D4: ='Historical Financials'!F8 -> 44561 | E4: ='Historical Financials'!G8 -> 44926 | F4: ='Historical Financials'!H8 -> 45291 | G4: ='Historical Financials'!I8 -> 45657 | I4: ='Historical Financials'!O8 -> 44651 | J4: ='Historical Financials'!P8 -> 44742 | K4: ='Historical Financials'!Q8 -> 44834 | L4: ='Historical Financials'!R8 -> 44926 | M4: ='Historical Financials'!S8 -> 45016 | N4: ='Historical Financials'!T8 -> 45107 | O4: ='Historical Financials'!U8 -> 45199 | P4: ='Historical Financials'!V8 -> 45291 | ... W4: ='Historical Financials'!AC8 -> 45930 | Y4: =K4 -> 44834 | Z4: =L4 -> 44926 | AA4: =M4 -> 45016 | AB4: =N4 -> 45107 | AC4: =O4 -> 45199 | AD4: =P4 -> 45291 | AE4: =Q4 -> 45382 | AF4: =R4 -> 45473 | ... AK4: =W4 -> 45930
B6: Total Senior Notes
B7: 5.375% Senior Notes due February 2021 | C7: 500 | D7: 0 | E7: 0 | F7: 0 | G7: 0 | I7: 0 | J7: 0 | K7: 0 | L7: =E7 -> 0 | M7: 0 | N7: 0 | O7: 0 | P7: =F7 -> 0 | Q7: 0 | R7: 0 | S7: 0 | T7: =G7 -> 0 | U7: 0 | V7: 0 | W7: 0 | Y7: =K7 -> 0 | Z7: =L7 -> 0 | AA7: =M7 -> 0 | AB7: =N7 -> 0 | AC7: =O7 -> 0 | AD7: =P7 -> 0 | AE7: =Q7 -> 0 | AF7: =R7 -> 0 | ... AK7: =W7 -> 0
B8: 5.500% Senior Notes due February 2022 | C8: 700 | D8: 700 | E8: 0 | F8: 0 | G8: 0 | I8: 0 | J8: 0 | K8: 0 | L8: =E8 -> 0 | M8: 0 | N8: 0 | O8: 0 | P8: =F8 -> 0 | Q8: 0 | R8: 0 | S8: 0 | T8: =G8 -> 0 | U8: 0 | V8: 0 | W8: 0 | Y8: =K8 -> 0 | Z8: =L8 -> 0 | AA8: =M8 -> 0 | AB8: =N8 -> 0 | AC8: =O8 -> 0 | AD8: =P8 -> 0 | AE8: =Q8 -> 0 | AF8: =R8 -> 0 | ... AK8: =W8 -> 0
B9: 5.750% Senior Notes due March 2024 | C9: 400 | D9: 400 | E9: 400 | F9: 400 | G9: 0 | I9: 400 | J9: 400 | K9: 400 | L9: =E9 -> 400 | M9: 400 | N9: 400 | O9: 400 | P9: =F9 -> 400 | Q9: 0 | R9: 0 | S9: 0 | T9: =G9 -> 0 | U9: 0 | V9: 0 | W9: 0 | Y9: =K9 -> 400 | Z9: =L9 -> 400 | AA9: =M9 -> 400 | AB9: =N9 -> 400 | AC9: =O9 -> 400 | AD9: =P9 -> 400 | AE9: =Q9 -> 0 | AF9: =R9 -> 0 | ... AK9: =W9 -> 0
B10: 5.875% Senior Notes due February 2025 | C10: 800 | D10: 800 | E10: 800 | F10: 800 | G10: 800 | I10: 800 | J10: 800 | K10: 800 | L10: =E10 -> 800 | M10: 800 | N10: 800 | O10: 800 | P10: =F10 -> 800 | Q10: 800 | R10: 800 | S10: 800 | T10: =G10 -> 800 | U10: 0 | V10: 0 | W10: 0 | Y10: =K10 -> 800 | Z10: =L10 -> 800 | AA10: =M10 -> 800 | AB10: =N10 -> 800 | AC10: =O10 -> 800 | AD10: =P10 -> 800 | AE10: =Q10 -> 800 | AF10: =R10 -> 800 | ... AK10: =W10 -> 0
B11: 3.000% Senior Notes due June 2025 (1) | C11: 574 | D11: 535 | E11: 503 | F11: 519 | G11: 487 | I11: 520 | J11: 492 | K11: 460 | L11: =E11 -> 503 | M11: 510 | N11: 513 | O11: 497 | P11: =F11 -> 519 | Q11: 507 | R11: 503 | S11: 523 | T11: =G11 -> 487 | U11: 508 | V11: 0 | W11: 0 | Y11: =K11 -> 460 | Z11: =L11 -> 503 | AA11: =M11 -> 510 | AB11: =N11 -> 513 | AC11: =O11 -> 497 | AD11: =P11 -> 519 | AE11: =Q11 -> 507 | AF11: =R11 -> 503 | ... AK11: =W11 -> 0
B12: 3.625% Senior Notes due June 2025 | C12: 500 | D12: 500 | E12: 500 | F12: 500 | G12: 500 | I12: 500 | J12: 500 | K12: 500 | L12: =E12 -> 500 | M12: 500 | N12: 500 | O12: 500 | P12: =F12 -> 500 | Q12: 500 | R12: 500 | S12: 500 | T12: =G12 -> 500 | U12: 500 | V12: 0 | W12: 0 | Y12: =K12 -> 500 | Z12: =L12 -> 500 | AA12: =M12 -> 500 | AB12: =N12 -> 500 | AC12: =O12 -> 500 | AD12: =P12 -> 500 | AE12: =Q12 -> 500 | AF12: =R12 -> 500 | ... AK12: =W12 -> 0
B13: 4.375% Senior Notes due November 2026 | C13: 1000 | D13: 1000 | E13: 1000 | F13: 1000 | G13: 1000 | I13: 1000 | J13: 1000 | K13: 1000 | L13: =E13 -> 1000 | M13: 1000 | N13: 1000 | O13: 1000 | P13: =F13 -> 1000 | Q13: 1000 | R13: 1000 | S13: 1000 | T13: =G13 -> 1000 | U13: 1000 | V13: 1000 | W13: 1000 | Y13: =K13 -> 1000 | Z13: =L13 -> 1000 | AA13: =M13 -> 1000 | AB13: =N13 -> 1000 | AC13: =O13 -> 1000 | AD13: =P13 -> 1000 | AE13: =Q13 -> 1000 | AF13: =R13 -> 1000 | ... AK13: =W13 -> 1000
B14: 3.625% Senior Notes due May 2027 (1) | C14: 1588 | D14: 1480 | E14: 1391 | F14: 1434 | G14: 1346 | I14: 1439 | J14: 1362 | K14: 1275 | L14: =E14 -> 1391 | M14: 1412 | N14: 1419 | O14: 1375 | P14: =F14 -> 1434 | Q14: 1401 | R14: 1394 | S14: 1446 | T14: =G14 -> 1346 | U14: 1404 | V14: 1525 | W14: 1528 | Y14: =K14 -> 1275 | Z14: =L14 -> 1391 | AA14: =M14 -> 1412 | AB14: =N14 -> 1419 | AC14: =O14 -> 1375 | AD14: =P14 -> 1434 | AE14: =Q14 -> 1401 | AF14: =R14 -> 1394 | ... AK14: =W14 -> 1528
B15: 4.875% Senior Notes due April 2028 | C15: 1600 | D15: 1600 | E15: 1600 | F15: 1600 | G15: 1600 | I15: 1600 | J15: 1600 | K15: 1600 | L15: =E15 -> 1600 | M15: 1600 | N15: 1600 | O15: 1600 | P15: =F15 -> 1600 | Q15: 1600 | R15: 1600 | S15: 1600 | T15: =G15 -> 1600 | U15: 1600 | V15: 1600 | W15: 1600 | Y15: =K15 -> 1600 | Z15: =L15 -> 1600 | AA15: =M15 -> 1600 | AB15: =N15 -> 1600 | AC15: =O15 -> 1600 | AD15: =P15 -> 1600 | AE15: =Q15 -> 1600 | AF15: =R15 -> 1600 | ... AK15: =W15 -> 1600
B16: 5.875% Senior Notes due November 2028 | C16: 1900 | D16: 1900 | E16: 1900 | F16: 1900 | G16: 1900 | I16: 1900 | J16: 1900 | K16: 1900 | L16: =E16 -> 1900 | M16: 1900 | N16: 1900 | O16: 1900 | P16: =F16 -> 1900 | Q16: 1900 | R16: 1900 | S16: 1900 | T16: =G16 -> 1900 | U16: 1900 | V16: 1900 | W16: 1900 | Y16: =K16 -> 1900 | Z16: =L16 -> 1900 | AA16: =M16 -> 1900 | AB16: =N16 -> 1900 | AC16: =O16 -> 1900 | AD16: =P16 -> 1900 | AE16: =Q16 -> 1900 | AF16: =R16 -> 1900 | ... AK16: =W16 -> 1900
B17: 4.625% Senior Notes due May 2029 (1) | C17: 1344 | D17: 1252 | E17: 1177 | F17: 1215 | G17: 1139 | I17: 1218 | J17: 1153 | K17: 1079 | L17: =E17 -> 1177 | M17: 1194 | N17: 1200 | O17: 1163 | P17: =F17 -> 1215 | Q17: 1187 | R17: 1178 | S17: 1225 | T17: =G17 -> 1139 | U17: 1188 | V17: 1291 | W17: 1293 | Y17: =K17 -> 1079 | Z17: =L17 -> 1177 | AA17: =M17 -> 1194 | AB17: =N17 -> 1200 | AC17: =O17 -> 1163 | AD17: =P17 -> 1215 | AE17: =Q17 -> 1187 | AF17: =R17 -> 1178 | ... AK17: =W17 -> 1293
B18: 6.375% Senior Notes due May 2029 | C18: 800 | D18: 800 | E18: 800 | F18: 800 | G18: 800 | I18: 800 | J18: 800 | K18: 800 | L18: =E18 -> 800 | M18: 800 | N18: 800 | O18: 800 | P18: =F18 -> 800 | Q18: 800 | R18: 800 | S18: 800 | T18: =G18 -> 800 | U18: 800 | V18: 800 | W18: 800 | Y18: =K18 -> 800 | Z18: =L18 -> 800 | AA18: =M18 -> 800 | AB18: =N18 -> 800 | AC18: =O18 -> 800 | AD18: =P18 -> 800 | AE18: =Q18 -> 800 | AF18: =R18 -> 800 | ... AK18: =W18 -> 800
... B24: 5.400% Senior Notes due August 2054 | C24: 0 | D24: 0 | E24: 0 | F24: 0 | G24: 800 | I24: 0 | J24: 0 | K24: 0 | L24: =E24 -> 0 | M24: 0 | N24: 0 | O24: 0 | P24: =F24 -> 0 | Q24: 0 | R24: 0 | S24: 800 | T24: =G24 -> 800 | U24: 800 | V24: 800 | W24: 800 | Y24: =K24 -> 0 | Z24: =L24 -> 0 | AA24: =M24 -> 0 | AB24: =N24 -> 0 | AC24: =O24 -> 0 | AD24: =P24 -> 0 | AE24: =Q24 -> 0 | AF24: =R24 -> 0 | ... AK24: =W24 -> 800
B25: Total Debt | C25: =SUM(C7:C24) -> 16416 | D25: =SUM(D7:D24) -> 15485 | E25: =SUM(E7:E24) -> 14432 | F25: =SUM(F7:F24) -> 14608 | G25: =SUM(G7:G24) -> 15653 | I25: =SUM(I7:I24) -> 14623 | J25: =SUM(J7:J24) -> 14318 | K25: =SUM(K7:K24) -> 13970 | L25: =SUM(L7:L24) -> 14432 | M25: =SUM(M7:M24) -> 14513 | N25: =SUM(N7:N24) -> 14542 | O25: =SUM(O7:O24) -> 14368 | P25: =SUM(P7:P24) -> 14608 | ... W25: =SUM(W7:W24) -> 14523 | Y25: =SUM(Y7:Y24) -> 13970 | Z25: =SUM(Z7:Z24) -> 14432 | AA25: =SUM(AA7:AA24) -> 14513 | AB25: =SUM(AB7:AB24) -> 14542 | AC25: =SUM(AC7:AC24) -> 14368 | AD25: =SUM(AD7:AD24) -> 14608 | AE25: =SUM(AE7:AE24) -> 14077 | AF25: =SUM(AF7:AF24) -> 14038 | ... AK25: =SUM(AK7:AK24) -> 14523
B27: 1) The following Senior Notes have a principal amount denominated in euros: 3.000% Senior Notes for €470 million, 3.625% Senior Notes for €1,300 million, 4.625% Senior Notes for €1,100 million, 3.875% Senior Notes for €1,200 million, and 3.625% Senior Notes for €1,100 million.

Sheet Revenue Projections & Cases
B2: ='Historical Financials'!B2 -> Netflix, Inc. (NASDAQ: NFLX)
B3: Revenue Build Projections
B4: ($ in Millions)
B6: Operating Scenario: | D6: Base case
B8: Apple Inc. (NASDAQ: AAPL) | C8: Actuals | I8: CAGR | J8: Forecast | P8: CAGR
B9: Revenue Build Projections | C9: ='[1]3 Statement Model'!C16 -> 2020 | D9: ='[1]3 Statement Model'!D16 -> 2021 | E9: ='[1]3 Statement Model'!E16 -> 2022 | F9: ='[1]3 Statement Model'!F16 -> 2023 | G9: ='[1]3 Statement Model'!G16 -> 2024 | H9: ='[1]3 Statement Model'!H16 -> 2025 | I9: 6-Year(A) | J9: ='[1]3 Statement Model'!L16 -> 2026 | K9: ='[1]3 Statement Model'!M16 -> 2027 | L9: ='[1]3 Statement Model'!N16 -> 2028 | M9: ='[1]3 Statement Model'!O16 -> 2029 | N9: ='[1]3 Statement Model'!P16 -> 2030 | O9: ='[1]3 Statement Model'!Q16 -> 2031 | P9: 6-Year(F)
B10: ($ in Millions) | C10: ='[1]3 Statement Model'!C17 -> 44104 | D10: ='[1]3 Statement Model'!D17 -> 44469 | E10: ='[1]3 Statement Model'!E17 -> 44834 | F10: ='[1]3 Statement Model'!F17 -> 45192 | G10: ='[1]3 Statement Model'!G17 -> 45559 | H10: ='[1]3 Statement Model'!H17 -> 45927 | I10: =H10 -> 45927 | J10: ='[1]3 Statement Model'!L17 -> 46295 | K10: ='[1]3 Statement Model'!M17 -> 46660 | L10: ='[1]3 Statement Model'!N17 -> 47026 | M10: ='[1]3 Statement Model'!O17 -> 47391 | N10: ='[1]3 Statement Model'!P17 -> 47756 | O10: ='[1]3 Statement Model'!Q17 -> 48121 | P10: =O10 -> 48121
B12: iPhone Revenue | I12: =((H12/C12)^(1/COUNT(D12:H12))-1) -> #DIV/0! | J12: =(J27*J35)/1000 -> 0 | K12: =(K27*K35)/1000 -> 0 | L12: =(L27*L35)/1000 -> 0 | M12: =(M27*M35)/1000 -> 0 | N12: =(N27*N35)/1000 -> 0 | O12: =(O27*O35)/1000 -> 0 | P12: =((O12/J12)^(1/COUNT(K12:O12))-1) -> #DIV/0!
B13: Mac Revenue | I13: =((H13/C13)^(1/COUNT(D13:H13))-1) -> #DIV/0! | J13: =(J29*J37)/1000 -> 0 | K13: =(K29*K37)/1000 -> 0 | L13: =(L29*L37)/1000 -> 0 | M13: =(M29*M37)/1000 -> 0 | N13: =(N29*N37)/1000 -> 0 | O13: =(O29*O37)/1000 -> 0 | P13: =((O13/J13)^(1/COUNT(K13:O13))-1) -> #DIV/0!
B14: iPad Revenue | I14: =((H14/C14)^(1/COUNT(D14:H14))-1) -> #DIV/0! | J14: =(J28*J36)/1000 -> 0 | K14: =(K28*K36)/1000 -> 0 | L14: =(L28*L36)/1000 -> 0 | M14: =(M28*M36)/1000 -> 0 | N14: =(N28*N36)/1000 -> 0 | O14: =(O28*O36)/1000 -> 0 | P14: =((O14/J14)^(1/COUNT(K14:O14))-1) -> #DIV/0!
B15: Services Revenue | I15: =((H15/C15)^(1/COUNT(D15:H15))-1) -> #DIV/0! | J15: =J53 -> 0 | K15: =K53 -> 0 | L15: =L53 -> 0 | M15: =M53 -> 0 | N15: =N53 -> 0 | O15: =O53 -> 0 | P15: =((O15/J15)^(1/COUNT(K15:O15))-1) -> #DIV/0!
B16: Wearables, Home, and Accessories Revenue | I16: =((H16/C16)^(1/COUNT(D16:H16))-1) -> #DIV/0! | J16: =J54 -> 0 | K16: =K54 -> 0 | L16: =L54 -> 0 | M16: =M54 -> 0 | N16: =N54 -> 0 | O16: =O54 -> 0 | P16: =((O16/J16)^(1/COUNT(K16:O16))-1) -> #DIV/0!
B17: Total revenue | C17: =SUM(C12:C16) -> 0 | D17: =SUM(D12:D16) -> 0 | E17: =SUM(E12:E16) -> 0 | F17: =SUM(F12:F16) -> 0 | G17: =SUM(G12:G16) -> 0 | H17: =SUM(H12:H16) -> 0 | I17: =((H17/C17)^(1/COUNT(D17:H17))-1) -> #DIV/0! | J17: =SUM(J12:J16) -> 0 | K17: =SUM(K12:K16) -> 0 | L17: =SUM(L12:L16) -> 0 | M17: =SUM(M12:M16) -> 0 | N17: =SUM(N12:N16) -> 0 | O17: =SUM(O12:O16) -> 0 | P17: =((O17/J17)^(1/COUNT(K17:O17))-1) -> #DIV/0!
B19: Y/Y Revenue Growth Assumptions
B20: Total Revenue | C20: N/A | D20: =SUM(D17/C17)-1 -> #DIV/0! | E20: =SUM(E17/D17)-1 -> #DIV/0! | F20: =SUM(F17/E17)-1 -> #DIV/0! | G20: =SUM(G17/F17)-1 -> #DIV/0! | H20: =SUM(H17/G17)-1 -> #DIV/0! | J20: =SUM(J17/H17)-1 -> #DIV/0! | K20: =SUM(K17/J17)-1 -> #DIV/0! | L20: =SUM(L17/K17)-1 -> #DIV/0! | M20: =SUM(M17/L17)-1 -> #DIV/0! | N20: =SUM(N17/M17)-1 -> #DIV/0! | O20: =SUM(O17/N17)-1 -> #DIV/0!
B21: =B12&"(%)" -> iPhone Revenue(%) | C21: N/A | D21: =SUM(D12/C12)-1 -> #DIV/0! | E21: =SUM(E12/D12)-1 -> #DIV/0! | F21: =SUM(F12/E12)-1 -> #DIV/0! | G21: =SUM(G12/F12)-1 -> #DIV/0! | H21: =SUM(H12/G12)-1 -> #DIV/0! | J21: =SUM(J12/H12)-1 -> #DIV/0! | K21: =SUM(K12/J12)-1 -> #DIV/0! | L21: =SUM(L12/K12)-1 -> #DIV/0! | M21: =SUM(M12/L12)-1 -> #DIV/0! | N21: =SUM(N12/M12)-1 -> #DIV/0! | O21: =SUM(O12/N12)-1 -> #DIV/0!
B22: =B13&"(%)" -> Mac Revenue(%) | C22: N/A | D22: =SUM(D13/C13)-1 -> #DIV/0! | E22: =SUM(E13/D13)-1 -> #DIV/0! | F22: =SUM(F13/E13)-1 -> #DIV/0! | G22: =SUM(G13/F13)-1 -> #DIV/0! | H22: =SUM(H13/G13)-1 -> #DIV/0! | J22: =SUM(J13/H13)-1 -> #DIV/0! | K22: =SUM(K13/J13)-1 -> #DIV/0! | L22: =SUM(L13/K13)-1 -> #DIV/0! | M22: =SUM(M13/L13)-1 -> #DIV/0! | N22: =SUM(N13/M13)-1 -> #DIV/0! | O22: =SUM(O13/N13)-1 -> #DIV/0!
B23: =B14&"(%)" -> iPad Revenue(%) | C23: N/A | D23: =SUM(D14/C14)-1 -> #DIV/0! | E23: =SUM(E14/D14)-1 -> #DIV/0! | F23: =SUM(F14/E14)-1 -> #DIV/0! | G23: =SUM(G14/F14)-1 -> #DIV/0! | H23: =SUM(H14/G14)-1 -> #DIV/0! | J23: =SUM(J14/H14)-1 -> #DIV/0! | K23: =SUM(K14/J14)-1 -> #DIV/0! | L23: =SUM(L14/K14)-1 -> #DIV/0! | M23: =SUM(M14/L14)-1 -> #DIV/0! | N23: =SUM(N14/M14)-1 -> #DIV/0! | O23: =SUM(O14/N14)-1 -> #DIV/0!
B24: =B15&"(%)" -> Services Revenue(%) | C24: N/A | D24: =SUM(D15/C15)-1 -> #DIV/0! | E24: =SUM(E15/D15)-1 -> #DIV/0! | F24: =SUM(F15/E15)-1 -> #DIV/0! | G24: =SUM(G15/F15)-1 -> #DIV/0! | H24: =SUM(H15/G15)-1 -> #DIV/0! | J24: =SUM(J15/H15)-1 -> #DIV/0! | K24: =SUM(K15/J15)-1 -> #DIV/0! | L24: =SUM(L15/K15)-1 -> #DIV/0! | M24: =SUM(M15/L15)-1 -> #DIV/0! | N24: =SUM(N15/M15)-1 -> #DIV/0! | O24: =SUM(O15/N15)-1 -> #DIV/0!
B25: =B16&"(%)" -> Wearables, Home, and Accessories Revenue(%) | C25: N/A | D25: =SUM(D16/C16)-1 -> #DIV/0! | E25: =SUM(E16/D16)-1 -> #DIV/0! | F25: =SUM(F16/E16)-1 -> #DIV/0! | G25: =SUM(G16/F16)-1 -> #DIV/0! | H25: =SUM(H16/G16)-1 -> #DIV/0! | J25: =SUM(J16/H16)-1 -> #DIV/0! | K25: =SUM(K16/J16)-1 -> #DIV/0! | L25: =SUM(L16/K16)-1 -> #DIV/0! | M25: =SUM(M16/L16)-1 -> #DIV/0! | N25: =SUM(N16/M16)-1 -> #DIV/0! | O25: =SUM(O16/N16)-1 -> #DIV/0!
B26: Unit Economics
B27: iPhone | J27: =J48 -> 0 | K27: =K48 -> 0 | L27: =L48 -> 0 | M27: =M48 -> 0 | N27: =N48 -> 0 | O27: =O48 -> 0
B28: iPad | J28: =J50 -> 0 | K28: =K50 -> 0 | L28: =L50 -> 0 | M28: =M50 -> 0 | N28: =N50 -> 0 | O28: =O50 -> 0
B29: Mac | J29: =J52 -> 0 | K29: =K52 -> 0 | L29: =L52 -> 0 | M29: =M52 -> 0 | N29: =N52 -> 0 | O29: =O52 -> 0
B30: Y/Y Unit Economics Growth Assumptions
B31: iPhone | C31: N/A | D31: =SUM(D27/C27)-1 -> #DIV/0! | E31: =SUM(E27/D27)-1 -> #DIV/0! | F31: =SUM(F27/E27)-1 -> #DIV/0! | G31: =SUM(G27/F27)-1 -> #DIV/0! | H31: =SUM(H27/G27)-1 -> #DIV/0! | J31: =SUM(J27/H27)-1 -> #DIV/0! | K31: =SUM(K27/J27)-1 -> #DIV/0! | L31: =SUM(L27/K27)-1 -> #DIV/0! | M31: =SUM(M27/L27)-1 -> #DIV/0! | N31: =SUM(N27/M27)-1 -> #DIV/0! | O31: =SUM(O27/N27)-1 -> #DIV/0!
B32: iPad | C32: N/A | D32: =SUM(D28/C28)-1 -> #DIV/0! | E32: =SUM(E28/D28)-1 -> #DIV/0! | F32: =SUM(F28/E28)-1 -> #DIV/0! | G32: =SUM(G28/F28)-1 -> #DIV/0! | H32: =SUM(H28/G28)-1 -> #DIV/0! | J32: =SUM(J28/H28)-1 -> #DIV/0! | K32: =SUM(K28/J28)-1 -> #DIV/0! | L32: =SUM(L28/K28)-1 -> #DIV/0! | M32: =SUM(M28/L28)-1 -> #DIV/0! | N32: =SUM(N28/M28)-1 -> #DIV/0! | O32: =SUM(O28/N28)-1 -> #DIV/0!
B33: Mac | C33: N/A | D33: =SUM(D29/C29)-1 -> #DIV/0! | E33: =SUM(E29/D29)-1 -> #DIV/0! | F33: =SUM(F29/E29)-1 -> #DIV/0! | G33: =SUM(G29/F29)-1 -> #DIV/0! | H33: =SUM(H29/G29)-1 -> #DIV/0! | J33: =SUM(J29/H29)-1 -> #DIV/0! | K33: =SUM(K29/J29)-1 -> #DIV/0! | L33: =SUM(L29/K29)-1 -> #DIV/0! | M33: =SUM(M29/L29)-1 -> #DIV/0! | N33: =SUM(N29/M29)-1 -> #DIV/0! | O33: =SUM(O29/N29)-1 -> #DIV/0!
B34: ASP
B35: iPhone | J35: =J47 -> 0 | K35: =K47 -> 0 | L35: =L47 -> 0 | M35: =M47 -> 0 | N35: =N47 -> 0 | O35: =O47 -> 0
B36: iPad | J36: =J49 -> 0 | K36: =K49 -> 0 | L36: =L49 -> 0 | M36: =M49 -> 0 | N36: =N49 -> 0 | O36: =O49 -> 0
B37: Mac | J37: =J51 -> 0 | K37: =K51 -> 0 | L37: =L51 -> 0 | M37: =M51 -> 0 | N37: =N51 -> 0 | O37: =O51 -> 0
B38: Y/Y ASP Growth Assumptions
B39: iPhone | C39: N/A | D39: =SUM(D35/C35)-1 -> #DIV/0! | E39: =SUM(E35/D35)-1 -> #DIV/0! | F39: =SUM(F35/E35)-1 -> #DIV/0! | G39: =SUM(G35/F35)-1 -> #DIV/0! | H39: =SUM(H35/G35)-1 -> #DIV/0! | J39: =SUM(J35/H35)-1 -> #DIV/0! | K39: =SUM(K35/J35)-1 -> #DIV/0! | L39: =SUM(L35/K35)-1 -> #DIV/0! | M39: =SUM(M35/L35)-1 -> #DIV/0! | N39: =SUM(N35/M35)-1 -> #DIV/0! | O39: =SUM(O35/N35)-1 -> #DIV/0!
B40: iPad | C40: N/A | D40: =SUM(D36/C36)-1 -> #DIV/0! | E40: =SUM(E36/D36)-1 -> #DIV/0! | F40: =SUM(F36/E36)-1 -> #DIV/0! | G40: =SUM(G36/F36)-1 -> #DIV/0! | H40: =SUM(H36/G36)-1 -> #DIV/0! | J40: =SUM(J36/H36)-1 -> #DIV/0! | K40: =SUM(K36/J36)-1 -> #DIV/0! | L40: =SUM(L36/K36)-1 -> #DIV/0! | M40: =SUM(M36/L36)-1 -> #DIV/0! | N40: =SUM(N36/M36)-1 -> #DIV/0! | O40: =SUM(O36/N36)-1 -> #DIV/0!
B41: Mac | C41: N/A | D41: =SUM(D37/C37)-1 -> #DIV/0! | E41: =SUM(E37/D37)-1 -> #DIV/0! | F41: =SUM(F37/E37)-1 -> #DIV/0! | G41: =SUM(G37/F37)-1 -> #DIV/0! | H41: =SUM(H37/G37)-1 -> #DIV/0! | J41: =SUM(J37/H37)-1 -> #DIV/0! | K41: =SUM(K37/J37)-1 -> #DIV/0! | L41: =SUM(L37/K37)-1 -> #DIV/0! | M41: =SUM(M37/L37)-1 -> #DIV/0! | N41: =SUM(N37/M37)-1 -> #DIV/0! | O41: =SUM(O37/N37)-1 -> #DIV/0!
B43: Case Scenarios
B45: Active case: | C45: =D6 -> Base case | I45: Var. from | J45: ='[1]3 Statement Model'!L16 -> 2026 | K45: ='[1]3 Statement Model'!M16 -> 2027 | L45: ='[1]3 Statement Model'!N16 -> 2028 | M45: ='[1]3 Statement Model'!O16 -> 2029 | N45: ='[1]3 Statement Model'!P16 -> 2030 | O45: ='[1]3 Statement Model'!Q16 -> 2031
I46: base case | J46: ='[1]3 Statement Model'!L17 -> 46295 | K46: ='[1]3 Statement Model'!M17 -> 46660 | L46: ='[1]3 Statement Model'!N17 -> 47026 | M46: ='[1]3 Statement Model'!O17 -> 47391 | N46: ='[1]3 Statement Model'!P17 -> 47756 | O46: ='[1]3 Statement Model'!Q17 -> 48121
B47: iPhone ASP | I47: =OFFSET(I$58,MATCH($B47,$B$58:$B$101,0)+MATCH($C$45,$B$59:$B$61,0)-1,0) -> NM | J47: =OFFSET(J$58,MATCH($B47,$B$58:$B$101,0)+MATCH($C$45,$B$59:$B$61,0)-1,0) -> 0 | K47: =OFFSET(K$58,MATCH($B47,$B$58:$B$101,0)+MATCH($C$45,$B$59:$B$61,0)-1,0) -> 0 | L47: =OFFSET(L$58,MATCH($B47,$B$58:$B$101,0)+MATCH($C$45,$B$59:$B$61,0)-1,0) -> 0 | M47: =OFFSET(M$58,MATCH($B47,$B$58:$B$101,0)+MATCH($C$45,$B$59:$B$61,0)-1,0) -> 0 | N47: =OFFSET(N$58,MATCH($B47,$B$58:$B$101,0)+MATCH($C$45,$B$59:$B$61,0)-1,0) -> 0 | O47: =OFFSET(O$58,MATCH($B47,$B$58:$B$101,0)+MATCH($C$45,$B$59:$B$61,0)-1,0) -> 0
B48: iPhone Units | I48: =OFFSET(I$58,MATCH($B48,$B$58:$B$101,0)+MATCH($C$45,$B$59:$B$61,0)-1,0) -> NM | J48: =OFFSET(J$58,MATCH($B48,$B$58:$B$101,0)+MATCH($C$45,$B$59:$B$61,0)-1,0) -> 0 | K48: =OFFSET(K$58,MATCH($B48,$B$58:$B$101,0)+MATCH($C$45,$B$59:$B$61,0)-1,0) -> 0 | L48: =OFFSET(L$58,MATCH($B48,$B$58:$B$101,0)+MATCH($C$45,$B$59:$B$61,0)-1,0) -> 0 | M48: =OFFSET(M$58,MATCH($B48,$B$58:$B$101,0)+MATCH($C$45,$B$59:$B$61,0)-1,0) -> 0 | N48: =OFFSET(N$58,MATCH($B48,$B$58:$B$101,0)+MATCH($C$45,$B$59:$B$61,0)-1,0) -> 0 | O48: =OFFSET(O$58,MATCH($B48,$B$58:$B$101,0)+MATCH($C$45,$B$59:$B$61,0)-1,0) -> 0
B49: iPad ASP | I49: =OFFSET(I$58,MATCH($B49,$B$58:$B$101,0)+MATCH($C$45,$B$59:$B$61,0)-1,0) -> NM | J49: =OFFSET(J$58,MATCH($B49,$B$58:$B$101,0)+MATCH($C$45,$B$59:$B$61,0)-1,0) -> 0 | K49: =OFFSET(K$58,MATCH($B49,$B$58:$B$101,0)+MATCH($C$45,$B$59:$B$61,0)-1,0) -> 0 | L49: =OFFSET(L$58,MATCH($B49,$B$58:$B$101,0)+MATCH($C$45,$B$59:$B$61,0)-1,0) -> 0 | M49: =OFFSET(M$58,MATCH($B49,$B$58:$B$101,0)+MATCH($C$45,$B$59:$B$61,0)-1,0) -> 0 | N49: =OFFSET(N$58,MATCH($B49,$B$58:$B$101,0)+MATCH($C$45,$B$59:$B$61,0)-1,0) -> 0 | O49: =OFFSET(O$58,MATCH($B49,$B$58:$B$101,0)+MATCH($C$45,$B$59:$B$61,0)-1,0) -> 0
B50: iPad Units | I50: =OFFSET(I$58,MATCH($B50,$B$58:$B$101,0)+MATCH($C$45,$B$59:$B$61,0)-1,0) -> NM | J50: =OFFSET(J$58,MATCH($B50,$B$58:$B$101,0)+MATCH($C$45,$B$59:$B$61,0)-1,0) -> 0 | K50: =OFFSET(K$58,MATCH($B50,$B$58:$B$101,0)+MATCH($C$45,$B$59:$B$61,0)-1,0) -> 0 | L50: =OFFSET(L$58,MATCH($B50,$B$58:$B$101,0)+MATCH($C$45,$B$59:$B$61,0)-1,0) -> 0 | M50: =OFFSET(M$58,MATCH($B50,$B$58:$B$101,0)+MATCH($C$45,$B$59:$B$61,0)-1,0) -> 0 | N50: =OFFSET(N$58,MATCH($B50,$B$58:$B$101,0)+MATCH($C$45,$B$59:$B$61,0)-1,0) -> 0 | O50: =OFFSET(O$58,MATCH($B50,$B$58:$B$101,0)+MATCH($C$45,$B$59:$B$61,0)-1,0) -> 0
B51: Mac ASP | I51: =OFFSET(I$58,MATCH($B51,$B$58:$B$101,0)+MATCH($C$45,$B$59:$B$61,0)-1,0) -> NM | J51: =OFFSET(J$58,MATCH($B51,$B$58:$B$101,0)+MATCH($C$45,$B$59:$B$61,0)-1,0) -> 0 | K51: =OFFSET(K$58,MATCH($B51,$B$58:$B$101,0)+MATCH($C$45,$B$59:$B$61,0)-1,0) -> 0 | L51: =OFFSET(L$58,MATCH($B51,$B$58:$B$101,0)+MATCH($C$45,$B$59:$B$61,0)-1,0) -> 0 | M51: =OFFSET(M$58,MATCH($B51,$B$58:$B$101,0)+MATCH($C$45,$B$59:$B$61,0)-1,0) -> 0 | N51: =OFFSET(N$58,MATCH($B51,$B$58:$B$101,0)+MATCH($C$45,$B$59:$B$61,0)-1,0) -> 0 | O51: =OFFSET(O$58,MATCH($B51,$B$58:$B$101,0)+MATCH($C$45,$B$59:$B$61,0)-1,0) -> 0
B52: Mac Units | I52: =OFFSET(I$58,MATCH($B52,$B$58:$B$101,0)+MATCH($C$45,$B$59:$B$61,0)-1,0) -> NM | J52: =OFFSET(J$58,MATCH($B52,$B$58:$B$101,0)+MATCH($C$45,$B$59:$B$61,0)-1,0) -> 0 | K52: =OFFSET(K$58,MATCH($B52,$B$58:$B$101,0)+MATCH($C$45,$B$59:$B$61,0)-1,0) -> 0 | L52: =OFFSET(L$58,MATCH($B52,$B$58:$B$101,0)+MATCH($C$45,$B$59:$B$61,0)-1,0) -> 0 | M52: =OFFSET(M$58,MATCH($B52,$B$58:$B$101,0)+MATCH($C$45,$B$59:$B$61,0)-1,0) -> 0 | N52: =OFFSET(N$58,MATCH($B52,$B$58:$B$101,0)+MATCH($C$45,$B$59:$B$61,0)-1,0) -> 0 | O52: =OFFSET(O$58,MATCH($B52,$B$58:$B$101,0)+MATCH($C$45,$B$59:$B$61,0)-1,0) -> 0
B53: Services Revenue | I53: =OFFSET(I$58,MATCH($B53,$B$58:$B$101,0)+MATCH($C$45,$B$59:$B$61,0)-1,0) -> NM | J53: =OFFSET(J$58,MATCH($B53,$B$58:$B$101,0)+MATCH($C$45,$B$59:$B$61,0)-1,0) -> 0 | K53: =OFFSET(K$58,MATCH($B53,$B$58:$B$101,0)+MATCH($C$45,$B$59:$B$61,0)-1,0) -> 0 | L53: =OFFSET(L$58,MATCH($B53,$B$58:$B$101,0)+MATCH($C$45,$B$59:$B$61,0)-1,0) -> 0 | M53: =OFFSET(M$58,MATCH($B53,$B$58:$B$101,0)+MATCH($C$45,$B$59:$B$61,0)-1,0) -> 0 | N53: =OFFSET(N$58,MATCH($B53,$B$58:$B$101,0)+MATCH($C$45,$B$59:$B$61,0)-1,0) -> 0 | O53: =OFFSET(O$58,MATCH($B53,$B$58:$B$101,0)+MATCH($C$45,$B$59:$B$61,0)-1,0) -> 0
B54: Wearables, Home, and Accessories Revenue | I54: =OFFSET(I$58,MATCH($B54,$B$58:$B$101,0)+MATCH($C$45,$B$59:$B$61,0)-1,0) -> NM | J54: =OFFSET(J$58,MATCH($B54,$B$58:$B$101,0)+MATCH($C$45,$B$59:$B$61,0)-1,0) -> 0 | K54: =OFFSET(K$58,MATCH($B54,$B$58:$B$101,0)+MATCH($C$45,$B$59:$B$61,0)-1,0) -> 0 | L54: =OFFSET(L$58,MATCH($B54,$B$58:$B$101,0)+MATCH($C$45,$B$59:$B$61,0)-1,0) -> 0 | M54: =OFFSET(M$58,MATCH($B54,$B$58:$B$101,0)+MATCH($C$45,$B$59:$B$61,0)-1,0) -> 0 | N54: =OFFSET(N$58,MATCH($B54,$B$58:$B$101,0)+MATCH($C$45,$B$59:$B$61,0)-1,0) -> 0 | O54: =OFFSET(O$58,MATCH($B54,$B$58:$B$101,0)+MATCH($C$45,$B$59:$B$61,0)-1,0) -> 0
B55: Gross profit margin | I55: =OFFSET(I$58,MATCH($B55,$B$58:$B$101,0)+MATCH($C$45,$B$59:$B$61,0)-1,0) -> NM | J55: =OFFSET(J$58,MATCH($B55,$B$58:$B$101,0)+MATCH($C$45,$B$59:$B$61,0)-1,0) -> 0 | K55: =OFFSET(K$58,MATCH($B55,$B$58:$B$101,0)+MATCH($C$45,$B$59:$B$61,0)-1,0) -> 0 | L55: =OFFSET(L$58,MATCH($B55,$B$58:$B$101,0)+MATCH($C$45,$B$59:$B$61,0)-1,0) -> 0 | M55: =OFFSET(M$58,MATCH($B55,$B$58:$B$101,0)+MATCH($C$45,$B$59:$B$61,0)-1,0) -> 0 | N55: =OFFSET(N$58,MATCH($B55,$B$58:$B$101,0)+MATCH($C$45,$B$59:$B$61,0)-1,0) -> 0 | O55: =OFFSET(O$58,MATCH($B55,$B$58:$B$101,0)+MATCH($C$45,$B$59:$B$61,0)-1,0) -> 0
B56: R&D % of sales | I56: =OFFSET(I$58,MATCH($B56,$B$58:$B$101,0)+MATCH($C$45,$B$59:$B$61,0)-1,0) -> NM | J56: =OFFSET(J$58,MATCH($B56,$B$58:$B$101,0)+MATCH($C$45,$B$59:$B$61,0)-1,0) -> 0 | K56: =OFFSET(K$58,MATCH($B56,$B$58:$B$101,0)+MATCH($C$45,$B$59:$B$61,0)-1,0) -> 0 | L56: =OFFSET(L$58,MATCH($B56,$B$58:$B$101,0)+MATCH($C$45,$B$59:$B$61,0)-1,0) -> 0 | M56: =OFFSET(M$58,MATCH($B56,$B$58:$B$101,0)+MATCH($C$45,$B$59:$B$61,0)-1,0) -> 0 | N56: =OFFSET(N$58,MATCH($B56,$B$58:$B$101,0)+MATCH($C$45,$B$59:$B$61,0)-1,0) -> 0 | O56: =OFFSET(O$58,MATCH($B56,$B$58:$B$101,0)+MATCH($C$45,$B$59:$B$61,0)-1,0) -> 0
B57: SG&A % of sales | I57: =OFFSET(I$58,MATCH($B57,$B$58:$B$101,0)+MATCH($C$45,$B$59:$B$61,0)-1,0) -> NM | J57: =OFFSET(J$58,MATCH($B57,$B$58:$B$101,0)+MATCH($C$45,$B$59:$B$61,0)-1,0) -> 0 | K57: =OFFSET(K$58,MATCH($B57,$B$58:$B$101,0)+MATCH($C$45,$B$59:$B$61,0)-1,0) -> 0 | L57: =OFFSET(L$58,MATCH($B57,$B$58:$B$101,0)+MATCH($C$45,$B$59:$B$61,0)-1,0) -> 0 | M57: =OFFSET(M$58,MATCH($B57,$B$58:$B$101,0)+MATCH($C$45,$B$59:$B$61,0)-1,0) -> 0 | N57: =OFFSET(N$58,MATCH($B57,$B$58:$B$101,0)+MATCH($C$45,$B$59:$B$61,0)-1,0) -> 0 | O57: =OFFSET(O$58,MATCH($B57,$B$58:$B$101,0)+MATCH($C$45,$B$59:$B$61,0)-1,0) -> 0
B58: iPhone ASP
B59: Best case | I59: 100 | J59: =J60+$I$59 -> 100 | K59: =K60+$I$59 -> 100 | L59: =L60+$I$59 -> 100 | M59: =M60+$I$59 -> 100 | N59: =N60+$I$59 -> 100 | O59: =O60+$I$59 -> 100
B60: Base case | I60: NM | P60: Consensus Estimates - Median
B61: Weak case | I61: -100 | J61: =J60+$I$61 -> -100 | K61: =K60+$I$61 -> -100 | L61: =L60+$I$61 -> -100 | M61: =M60+$I$61 -> -100 | N61: =N60+$I$61 -> -100 | O61: =O60+$I$61 -> -100
B62: iPhone Units
B63: Best case | I63: 15000 | J63: =J64+$I$63 -> 15000 | K63: =K64+$I$63 -> 15000 | L63: =L64+$I$63 -> 15000 | M63: =M64+$I$63 -> 15000 | N63: =N64+$I$63 -> 15000 | O63: =O64+$I$63 -> 15000
B64: Base case | I64: NM | P64: Consensus Estimates - Average
B65: Weak case | I65: -15000 | J65: =J64+$I$65 -> -15000 | K65: =K64+$I$65 -> -15000 | L65: =L64+$I$65 -> -15000 | M65: =M64+$I$65 -> -15000 | N65: =N64+$I$65 -> -15000 | O65: =O64+$I$65 -> -15000
B66: iPad ASP
B67: Best case | I67: 100 | J67: =J68+$I$67 -> 100 | K67: =K68+$I$67 -> 100 | L67: =L68+$I$67 -> 100 | M67: =M68+$I$67 -> 100 | N67: =N68+$I$67 -> 100 | O67: =O68+$I$67 -> 100
B68: Base case | I68: NM | P68: Consensus Estimates - Average
B69: Weak case | I69: -100 | J69: =J68+$I$69 -> -100 | K69: =K68+$I$69 -> -100 | L69: =L68+$I$69 -> -100 | M69: =M68+$I$69 -> -100 | N69: =N68+$I$69 -> -100 | O69: =O68+$I$69 -> -100
B70: iPad Units
B71: Best case | I71: 6000 | J71: =J72+$I$71 -> 6000 | K71: =K72+$I$71 -> 6000 | L71: =L72+$I$71 -> 6000 | M71: =M72+$I$71 -> 6000 | N71: =N72+$I$71 -> 6000 | O71: =O72+$I$71 -> 6000
B72: Base case | I72: NM | P72: Consensus Estimates - Average
B73: Weak case | I73: -6000 | J73: =J72+$I$73 -> -6000 | K73: =K72+$I$73 -> -6000 | L73: =L72+$I$73 -> -6000 | M73: =M72+$I$73 -> -6000 | N73: =N72+$I$73 -> -6000 | O73: =O72+$I$73 -> -6000
B74: Mac ASP
B75: Best case | I75: 200 | J75: =J76+$I$75 -> 200 | K75: =K76+$I$75 -> 200 | L75: =L76+$I$75 -> 200 | M75: =M76+$I$75 -> 200 | N75: =N76+$I$75 -> 200 | O75: =O76+$I$75 -> 200
B76: Base case | I76: NM | P76: Consensus Estimates - Average
B77: Weak case | I77: -200 | J77: =J76+$I$77 -> -200 | K77: =K76+$I$77 -> -200 | L77: =L76+$I$77 -> -200 | M77: =M76+$I$77 -> -200 | N77: =N76+$I$77 -> -200 | O77: =O76+$I$77 -> -200
B78: Mac Units
B79: Best case | I79: 500 | J79: =J80+$I$79 -> 500 | K79: =K80+$I$79 -> 500 | L79: =L80+$I$79 -> 500 | M79: =M80+$I$79 -> 500 | N79: =N80+$I$79 -> 500 | O79: =O80+$I$79 -> 500
B80: Base case | I80: NM | P80: Consensus Estimates - Bull Case
B81: Weak case | I81: -500 | J81: =J80+$I$81 -> -500 | K81: =K80+$I$81 -> -500 | L81: =L80+$I$81 -> -500 | M81: =M80+$I$81 -> -500 | N81: =N80+$I$81 -> -500 | O81: =O80+$I$81 -> -500
B82: Services Revenue
B83: Best case | I83: 0.05 | J83: =SUM(J84*$I$83)+J84 -> 0 | K83: =SUM(K84*$I$83)+K84 -> 0 | L83: =SUM(L84*$I$83)+L84 -> 0 | M83: =SUM(M84*$I$83)+M84 -> 0 | N83: =SUM(N84*$I$83)+N84 -> 0 | O83: =SUM(O84*$I$83)+O84 -> 0
B84: Base case | I84: NM | P84: Consensus Estimates - Bull Case
B85: Weak case | I85: -0.05 | J85: =SUM(J84*$I$85)+J84 -> 0 | K85: =SUM(K84*$I$85)+K84 -> 0 | L85: =SUM(L84*$I$85)+L84 -> 0 | M85: =SUM(M84*$I$85)+M84 -> 0 | N85: =SUM(N84*$I$85)+N84 -> 0 | O85: =SUM(O84*$I$85)+O84 -> 0
B86: Wearables, Home, and Accessories Revenue
B87: Best case | I87: 0.05 | J87: =SUM(J88*$I$87)+J88 -> 0 | K87: =SUM(K88*$I$87)+K88 -> 0 | L87: =SUM(L88*$I$87)+L88 -> 0 | M87: =SUM(M88*$I$87)+M88 -> 0 | N87: =SUM(N88*$I$87)+N88 -> 0 | O87: =SUM(O88*$I$87)+O88 -> 0
B88: Base case | I88: NM | P88: Consensus Estimates - Median
B89: Weak case | I89: -0.05 | J89: =SUM(J88*$I$89)+J88 -> 0 | K89: =SUM(K88*$I$89)+K88 -> 0 | L89: =SUM(L88*$I$89)+L88 -> 0 | M89: =SUM(M88*$I$89)+M88 -> 0 | N89: =SUM(N88*$I$89)+N88 -> 0 | O89: =SUM(O88*$I$89)+O88 -> 0
B90: Gross Profit Margin
B91: Best case | I91: 0.01 | J91: =J92+$I$91 -> 0.01 | K91: =K92+$I$91 -> 0.01 | L91: =L92+$I$91 -> 0.01 | M91: =M92+$I$91 -> 0.01 | N91: =N92+$I$91 -> 0.01 | O91: =O92+$I$91 -> 0.01
B92: Base case | I92: NM | P92: Consensus Estimates - Average
B93: Weak case | I93: -0.01 | J93: =J92+$I$93 -> -0.01 | K93: =K92+$I$93 -> -0.01 | L93: =L92+$I$93 -> -0.01 | M93: =M92+$I$93 -> -0.01 | N93: =N92+$I$93 -> -0.01 | O93: =O92+$I$93 -> -0.01
B94: R&D % of sales
B95: Best case | I95: -0.01 | J95: =J96+$I$95 -> -0.01 | K95: =K96+$I$95 -> -0.01 | L95: =L96+$I$95 -> -0.01 | M95: =M96+$I$95 -> -0.01 | N95: =N96+$I$95 -> -0.01 | O95: =O96+$I$95 -> -0.01
B96: Base case | I96: NM | P96: Consensus Estimates - Average
B97: Weak case | I97: 0.01 | J97: =J96+$I$97 -> 0.01 | K97: =K96+$I$97 -> 0.01 | L97: =L96+$I$97 -> 0.01 | M97: =M96+$I$97 -> 0.01 | N97: =N96+$I$97 -> 0.01 | O97: =O96+$I$97 -> 0.01
B98: SG&A % of sales
B99: Best case | I99: -0.01 | J99: =J100+$I$99 -> -0.01 | K99: =K100+$I$99 -> -0.01 | L99: =L100+$I$99 -> -0.01 | M99: =M100+$I$99 -> -0.01 | N99: =N100+$I$99 -> -0.01 | O99: =O100+$I$99 -> -0.01
B100: Base case | I100: NM | P100: Consensus Estimates - Average
B101: Weak case | I101: 0.01 | J101: =J100+$I$101 -> 0.01 | K101: =K100+$I$101 -> 0.01 | L101: =L100+$I$101 -> 0.01 | M101: =M100+$I$101 -> 0.01 | N101: =N100+$I$101 -> 0.01 | O101: =O100+$I$101 -> 0.01

Sheet 3 Statement Model
B2: ='Historical Financials'!B2 -> Netflix, Inc. (NASDAQ: NFLX)
B3: 3-Statement Model
B4: $ mm except per share
B6: Company name
B7: Ticker
B8: Circ break 1=off, 0=on | C8: 0
B9: Latest closing share price
B10: Latest closing share price date
B11: Latest fiscal year end date
B12: Case active: | C12: ='[2]Revenue Projections & Cases'!D6 -> Base case
B13: Shares outstanding (millions)
B15: Income Statement | C15: Actuals | J15: CAGR | L15: Forecast | S15: CAGR
B16: Fiscal year | C16: ='[2]Historical Financials'!G7 -> 2020 | D16: ='[2]Historical Financials'!H7 -> 2021 | E16: ='[2]Historical Financials'!I7 -> 2022 | F16: ='[2]Historical Financials'!J7 -> 2023 | G16: ='[2]Historical Financials'!K7 -> 2024 | H16: ='[2]Historical Financials'!L7 -> 2025 | J16: 6-Year(A) | L16: =H16+1 -> 2026 | M16: =+L16+1 -> 2027 | N16: =+M16+1 -> 2028 | O16: =+N16+1 -> 2029 | P16: =+O16+1 -> 2030 | Q16: =+P16+1 -> 2031 | S16: 6-Year(F)
B17: Fiscal year end date | C17: ='[2]Historical Financials'!G8 -> 44104 | D17: ='[2]Historical Financials'!H8 -> 44469 | E17: ='[2]Historical Financials'!I8 -> 44834 | F17: ='[2]Historical Financials'!J8 -> 45192 | G17: ='[2]Historical Financials'!K8 -> 45559 | H17: ='[2]Historical Financials'!L8 -> 45927 | J17: =H17 -> 45927 | L17: =EOMONTH(H17,12) -> 46295 | M17: =EOMONTH(L17,12) -> 46660 | N17: =EOMONTH(M17,12) -> 47026 | O17: =EOMONTH(N17,12) -> 47391 | P17: =EOMONTH(O17,12) -> 47756 | Q17: =EOMONTH(P17,12) -> 48121 | S17: =Q17 -> 48121
B19: ='[2]Revenue Drivers'!B9 -> iPhone Revenue | S19: =((Q19/L19)^(1/COUNT(M19:Q19))-1) -> #DIV/0! | T19: See Revenue Projections & Cases
B20: ='[2]Revenue Drivers'!B10 -> Mac Revenue | S20: =((Q20/L20)^(1/COUNT(M20:Q20))-1) -> #DIV/0! | T20: See Revenue Projections & Cases
B21: ='[2]Revenue Drivers'!B11 -> iPad Revenue | S21: =((Q21/L21)^(1/COUNT(M21:Q21))-1) -> #DIV/0! | T21: See Revenue Projections & Cases
B22: ='[2]Revenue Drivers'!B12 -> Services Revenue | S22: =((Q22/L22)^(1/COUNT(M22:Q22))-1) -> #DIV/0! | T22: See Revenue Projections & Cases
B23: ='[2]Revenue Drivers'!B13 -> Wearables, Home, and Accessories Revenue | S23: =((Q23/L23)^(1/COUNT(M23:Q23))-1) -> #DIV/0! | T23: See Revenue Projections & Cases
B24: Total Revenue | C24: =SUM(C19:C23) -> 0 | D24: =SUM(D19:D23) -> 0 | E24: =SUM(E19:E23) -> 0 | F24: =SUM(F19:F23) -> 0 | G24: =SUM(G19:G23) -> 0 | H24: =SUM(H19:H23) -> 0 | J24: =((H24/C24)^(1/COUNT(D24:H24))-1) -> #DIV/0! | L24: =SUM(L19:L23) -> 0 | M24: =SUM(M19:M23) -> 0 | N24: =SUM(N19:N23) -> 0 | O24: =SUM(O19:O23) -> 0 | P24: =SUM(P19:P23) -> 0 | Q24: =SUM(Q19:Q23) -> 0 | S24: =((Q24/L24)^(1/COUNT(M24:Q24))-1) -> #DIV/0!
B26: Cost of sales | J26: =((H26/C26)^(1/COUNT(D26:H26))-1) -> #DIV/0! | L26: =L27-L24 -> 0 | M26: =M27-M24 -> 0 | N26: =N27-N24 -> 0 | O26: =O27-O24 -> 0 | P26: =P27-P24 -> 0 | Q26: =Q27-Q24 -> 0 | S26: =((Q26/L26)^(1/COUNT(M26:Q26))-1) -> #DIV/0!
B27: Gross Profit | C27: =+C26+C24 -> 0 | D27: =+D26+D24 -> 0 | E27: =+E26+E24 -> 0 | F27: =+F26+F24 -> 0 | G27: =+G26+G24 -> 0 | H27: =+H26+H24 -> 0 | J27: =((H27/C27)^(1/COUNT(D27:H27))-1) -> #DIV/0! | L27: =L58*L24 -> 0 | M27: =M58*M24 -> 0 | N27: =N58*N24 -> 0 | O27: =O58*O24 -> 0 | P27: =P58*P24 -> 0 | Q27: =Q58*Q24 -> 0 | S27: =((Q27/L27)^(1/COUNT(M27:Q27))-1) -> #DIV/0!
B29: Research & Development (R&D) | J29: =((H29/C29)^(1/COUNT(D29:H29))-1) -> #DIV/0! | L29: =-(L24*L70) -> 0 | M29: =-(M24*M70) -> 0 | N29: =-(N24*N70) -> 0 | O29: =-(O24*O70) -> 0 | P29: =-(P24*P70) -> 0 | Q29: =-(Q24*Q70) -> 0 | S29: =((Q29/L29)^(1/COUNT(M29:Q29))-1) -> #DIV/0!
B30: Selling, General and Administrative (SG&A) | J30: =((H30/C30)^(1/COUNT(D30:H30))-1) -> #DIV/0! | L30: =-(L24*L71) -> 0 | M30: =-(M24*M71) -> 0 | N30: =-(N24*N71) -> 0 | O30: =-(O24*O71) -> 0 | P30: =-(P24*P71) -> 0 | Q30: =-(Q24*Q71) -> 0 | S30: =((Q30/L30)^(1/COUNT(M30:Q30))-1) -> #DIV/0!
B31: Operating profit (EBIT) | C31: =SUM(C29:C30)+C27 -> 0 | D31: =SUM(D29:D30)+D27 -> 0 | E31: =SUM(E29:E30)+E27 -> 0 | F31: =SUM(F29:F30)+F27 -> 0 | G31: =SUM(G29:G30)+G27 -> 0 | H31: =SUM(H29:H30)+H27 -> 0 | J31: =((H31/C31)^(1/COUNT(D31:H31))-1) -> #DIV/0! | L31: =SUM(L29:L30)+L27 -> 0 | M31: =SUM(M29:M30)+M27 -> 0 | N31: =SUM(N29:N30)+N27 -> 0 | O31: =SUM(O29:O30)+O27 -> 0 | P31: =SUM(P29:P30)+P27 -> 0 | Q31: =SUM(Q29:Q30)+Q27 -> 0 | S31: =((Q31/L31)^(1/COUNT(M31:Q31))-1) -> #DIV/0!
B33: Interest Income | J33: =((H33/C33)^(1/COUNT(D33:H33))-1) -> #DIV/0! | L33: =L207 -> 0 | M33: =M207 -> 0 | N33: =N207 -> 0 | O33: =O207 -> 0 | P33: =P207 -> 0 | Q33: =Q207 -> 0 | S33: =((Q33/L33)^(1/COUNT(M33:Q33))-1) -> #DIV/0! | T33: See interest on cash schedule
B34: Interest Expense | J34: =((H34/C34)^(1/COUNT(D34:H34))-1) -> #DIV/0! | L34: =-L193 -> #DIV/0! | M34: =-M193 -> #DIV/0! | N34: =-N193 -> #DIV/0! | O34: =-O193 -> #DIV/0! | P34: =-P193 -> #DIV/0! | Q34: =-Q193 -> #DIV/0! | S34: =((Q34/L34)^(1/COUNT(M34:Q34))-1) -> #DIV/0! | T34: See interest expense schedule
B35: Other Income/Gains (Expenses/Losses) | J35: =((H35/C35)^(1/COUNT(D35:H35))-1) -> #DIV/0! | L35: =AVERAGE(F35:H35) -> #DIV/0! | M35: =L35 -> #DIV/0! | N35: =M35 -> #DIV/0! | O35: =N35 -> #DIV/0! | P35: =O35 -> #DIV/0! | Q35: =P35 -> #DIV/0! | S35: =((Q35/L35)^(1/COUNT(M35:Q35))-1) -> #DIV/0! | T35: 3-Year Average
B36: Pretax profit | C36: =SUM(C33:C35)+C31 -> 0 | D36: =SUM(D33:D35)+D31 -> 0 | E36: =SUM(E33:E35)+E31 -> 0 | F36: =SUM(F33:F35)+F31 -> 0 | G36: =SUM(G33:G35)+G31 -> 0 | H36: =SUM(H33:H35)+H31 -> 0 | J36: =((H36/C36)^(1/COUNT(D36:H36))-1) -> #DIV/0! | L36: =SUM(L33:L35)+L31 -> #DIV/0! | M36: =SUM(M33:M35)+M31 -> #DIV/0! | N36: =SUM(N33:N35)+N31 -> #DIV/0! | O36: =SUM(O33:O35)+O31 -> #DIV/0! | P36: =SUM(P33:P35)+P31 -> #DIV/0! | Q36: =SUM(Q33:Q35)+Q31 -> #DIV/0! | S36: =((Q36/L36)^(1/COUNT(M36:Q36))-1) -> #DIV/0!
B38: Taxes | J38: =((H38/C38)^(1/COUNT(D38:H38))-1) -> #DIV/0! | L38: =-(L36*L60) -> #DIV/0! | M38: =-(M36*M60) -> #DIV/0! | N38: =-(N36*N60) -> #DIV/0! | O38: =-(O36*O60) -> #DIV/0! | P38: =-(P36*P60) -> #DIV/0! | Q38: =-(Q36*Q60) -> #DIV/0! | S38: =((Q38/L38)^(1/COUNT(M38:Q38))-1) -> #DIV/0!
B39: Net income | C39: =+C36+C38 -> 0 | D39: =+D36+D38 -> 0 | E39: =+E36+E38 -> 0 | F39: =+F36+F38 -> 0 | G39: =+G36+G38 -> 0 | H39: =+H36+H38 -> 0 | J39: =((H39/C39)^(1/COUNT(D39:H39))-1) -> #DIV/0! | L39: =+L36+L38 -> #DIV/0! | M39: =+M36+M38 -> #DIV/0! | N39: =+N36+N38 -> #DIV/0! | O39: =+O36+O38 -> #DIV/0! | P39: =+P36+P38 -> #DIV/0! | Q39: =+Q36+Q38 -> #DIV/0! | S39: =((Q39/L39)^(1/COUNT(M39:Q39))-1) -> #DIV/0!
B41: Depreciation & Amortization | J41: =((H41/C41)^(1/COUNT(D41:H41))-1) -> #DIV/0! | L41: =L163 -> #DIV/0! | M41: =M163 -> #DIV/0! | N41: =N163 -> #DIV/0! | O41: =O163 -> #DIV/0! | P41: =P163 -> #DIV/0! | Q41: =Q163 -> #DIV/0! | S41: =((Q41/L41)^(1/COUNT(M41:Q41))-1) -> #DIV/0! | T41: See D&A schedule
B42: EBITDA | C42: =+C31+C41 -> 0 | D42: =+D31+D41 -> 0 | E42: =+E31+E41 -> 0 | F42: =+F31+F41 -> 0 | G42: =+G31+G41 -> 0 | H42: =+H31+H41 -> 0 | J42: =((H42/C42)^(1/COUNT(D42:H42))-1) -> #DIV/0! | L42: =+L31+L41 -> #DIV/0! | M42: =+M31+M41 -> #DIV/0! | N42: =+N31+N41 -> #DIV/0! | O42: =+O31+O41 -> #DIV/0! | P42: =+P31+P41 -> #DIV/0! | Q42: =+Q31+Q41 -> #DIV/0! | S42: =((Q42/L42)^(1/COUNT(M42:Q42))-1) -> #DIV/0!
B44: Stock Based Compensation | J44: =((H44/C44)^(1/COUNT(D44:H44))-1) -> #DIV/0! | L44: =(L50*H44)+H44 -> 0 | M44: =(M50*L44)+L44 -> 0 | N44: =(N50*M44)+M44 -> 0 | O44: =(O50*N44)+N44 -> 0 | P44: =(P50*O44)+O44 -> 0 | Q44: =(Q50*P44)+P44 -> 0 | S44: =((Q44/L44)^(1/COUNT(M44:Q44))-1) -> #DIV/0! | T44: Growth in-line with revenue
B45: Adj. EBITDA | C45: =+C42+C44 -> 0 | D45: =+D42+D44 -> 0 | E45: =+E42+E44 -> 0 | F45: =+F42+F44 -> 0 | G45: =+G42+G44 -> 0 | H45: =+H42+H44 -> 0 | J45: =((H45/C45)^(1/COUNT(D45:H45))-1) -> #DIV/0! | L45: =+L42+L44 -> #DIV/0! | M45: =+M42+M44 -> #DIV/0! | N45: =+N42+N44 -> #DIV/0! | O45: =+O42+O44 -> #DIV/0! | P45: =+P42+P44 -> #DIV/0! | Q45: =+Q42+Q44 -> #DIV/0! | S45: =((Q45/L45)^(1/COUNT(M45:Q45))-1) -> #DIV/0!
B47: Growth rates & margins
B49: Revenue growth
B50: Consolidated Revenue growth | C50: N/A | D50: =SUM(D24/C24)-1 -> #DIV/0! | E50: =SUM(E24/D24)-1 -> #DIV/0! | F50: =SUM(F24/E24)-1 -> #DIV/0! | G50: =SUM(G24/F24)-1 -> #DIV/0! | H50: =SUM(H24/G24)-1 -> #DIV/0! | T50: See Revenue Projections & Cases
B51: =B19 -> iPhone Revenue | C51: N/A | D51: =SUM(D19/C19)-1 -> #DIV/0! | E51: =SUM(E19/D19)-1 -> #DIV/0! | F51: =SUM(F19/E19)-1 -> #DIV/0! | G51: =SUM(G19/F19)-1 -> #DIV/0! | H51: =SUM(H19/G19)-1 -> #DIV/0! | T51: See Revenue Projections & Cases
B52: =B20 -> Mac Revenue | C52: N/A | D52: =SUM(D20/C20)-1 -> #DIV/0! | E52: =SUM(E20/D20)-1 -> #DIV/0! | F52: =SUM(F20/E20)-1 -> #DIV/0! | G52: =SUM(G20/F20)-1 -> #DIV/0! | H52: =SUM(H20/G20)-1 -> #DIV/0! | T52: See Revenue Projections & Cases
B53: =B21 -> iPad Revenue | C53: N/A | D53: =SUM(D21/C21)-1 -> #DIV/0! | E53: =SUM(E21/D21)-1 -> #DIV/0! | F53: =SUM(F21/E21)-1 -> #DIV/0! | G53: =SUM(G21/F21)-1 -> #DIV/0! | H53: =SUM(H21/G21)-1 -> #DIV/0! | T53: See Revenue Projections & Cases
B54: =B22 -> Services Revenue | C54: N/A | D54: =SUM(D22/C22)-1 -> #DIV/0! | E54: =SUM(E22/D22)-1 -> #DIV/0! | F54: =SUM(F22/E22)-1 -> #DIV/0! | G54: =SUM(G22/F22)-1 -> #DIV/0! | H54: =SUM(H22/G22)-1 -> #DIV/0! | T54: See Revenue Projections & Cases
B55: =B23 -> Wearables, Home, and Accessories Revenue | C55: N/A | D55: =SUM(D23/C23)-1 -> #DIV/0! | E55: =SUM(E23/D23)-1 -> #DIV/0! | F55: =SUM(F23/E23)-1 -> #DIV/0! | G55: =SUM(G23/F23)-1 -> #DIV/0! | H55: =SUM(H23/G23)-1 -> #DIV/0! | T55: See Revenue Projections & Cases
B57: Margins
B58: Gross Margin | C58: =C27/C24 -> #DIV/0! | D58: =D27/D24 -> #DIV/0! | E58: =E27/E24 -> #DIV/0! | F58: =F27/F24 -> #DIV/0! | G58: =G27/G24 -> #DIV/0! | H58: =H27/H24 -> #DIV/0! | T58: See Revenue Projections & Cases
B59: EBIT Margin | C59: =C31/C24 -> #DIV/0! | D59: =D31/D24 -> #DIV/0! | E59: =E31/E24 -> #DIV/0! | F59: =F31/F24 -> #DIV/0! | G59: =G31/G24 -> #DIV/0! | H59: =H31/H24 -> #DIV/0! | T59: Consensus Estimate - Average
B60: Tax Rate | C60: =-C38/C36 -> #DIV/0! | D60: =-D38/D36 -> #DIV/0! | E60: =-E38/E36 -> #DIV/0! | F60: =-F38/F36 -> #DIV/0! | G60: =-G38/G36 -> #DIV/0! | H60: =-H38/H36 -> #DIV/0! | T60: Consensus Estimate - Average
B61: EBITDA Margin | C61: =C42/C24 -> #DIV/0! | D61: =D42/D24 -> #DIV/0! | E61: =E42/E24 -> #DIV/0! | F61: =F42/F24 -> #DIV/0! | G61: =G42/G24 -> #DIV/0! | H61: =H42/H24 -> #DIV/0! | L61: =L42/L24 -> #DIV/0! | M61: =M42/M24 -> #DIV/0! | N61: =N42/N24 -> #DIV/0! | O61: =O42/O24 -> #DIV/0! | P61: =P42/P24 -> #DIV/0! | Q61: =Q42/Q24 -> #DIV/0!
B62: Adj. EBITDA Margin | C62: =C45/C24 -> #DIV/0! | D62: =D45/D24 -> #DIV/0! | E62: =E45/E24 -> #DIV/0! | F62: =F45/F24 -> #DIV/0! | G62: =G45/G24 -> #DIV/0! | H62: =H45/H24 -> #DIV/0! | L62: =L45/L24 -> #DIV/0! | M62: =M45/M24 -> #DIV/0! | N62: =N45/N24 -> #DIV/0! | O62: =O45/O24 -> #DIV/0! | P62: =P45/P24 -> #DIV/0! | Q62: =Q45/Q24 -> #DIV/0!
B64: Growth Rates
B65: Cost of Sales | C65: N/A | D65: =SUM(D26/C26)-1 -> #DIV/0! | E65: =SUM(E26/D26)-1 -> #DIV/0! | F65: =SUM(F26/E26)-1 -> #DIV/0! | G65: =SUM(G26/F26)-1 -> #DIV/0! | H65: =SUM(H26/G26)-1 -> #DIV/0! | L65: =SUM(L26/H26)-1 -> #DIV/0! | M65: =SUM(M26/L26)-1 -> #DIV/0! | N65: =SUM(N26/M26)-1 -> #DIV/0! | O65: =SUM(O26/N26)-1 -> #DIV/0! | P65: =SUM(P26/O26)-1 -> #DIV/0! | Q65: =SUM(Q26/P26)-1 -> #DIV/0!
B66: R&D Growth (%) | C66: N/A | D66: =SUM(D29/C29)-1 -> #DIV/0! | E66: =SUM(E29/D29)-1 -> #DIV/0! | F66: =SUM(F29/E29)-1 -> #DIV/0! | G66: =SUM(G29/F29)-1 -> #DIV/0! | H66: =SUM(H29/G29)-1 -> #DIV/0! | L66: =SUM(L29/H29)-1 -> #DIV/0! | M66: =SUM(M29/L29)-1 -> #DIV/0! | N66: =SUM(N29/M29)-1 -> #DIV/0! | O66: =SUM(O29/N29)-1 -> #DIV/0! | P66: =SUM(P29/O29)-1 -> #DIV/0! | Q66: =SUM(Q29/P29)-1 -> #DIV/0!
B67: SG&A Growth (%) | C67: N/A | D67: =SUM(D30/C30)-1 -> #DIV/0! | E67: =SUM(E30/D30)-1 -> #DIV/0! | F67: =SUM(F30/E30)-1 -> #DIV/0! | G67: =SUM(G30/F30)-1 -> #DIV/0! | H67: =SUM(H30/G30)-1 -> #DIV/0! | L67: =SUM(L30/H30)-1 -> #DIV/0! | M67: =SUM(M30/L30)-1 -> #DIV/0! | N67: =SUM(N30/M30)-1 -> #DIV/0! | O67: =SUM(O30/N30)-1 -> #DIV/0! | P67: =SUM(P30/O30)-1 -> #DIV/0! | Q67: =SUM(Q30/P30)-1 -> #DIV/0!
B69: % of Sales
B70: R&D as a % of Sales | C70: =-C29/C24 -> #DIV/0! | D70: =-D29/D24 -> #DIV/0! | E70: =-E29/E24 -> #DIV/0! | F70: =-F29/F24 -> #DIV/0! | G70: =-G29/G24 -> #DIV/0! | H70: =-H29/H24 -> #DIV/0! | T70: See Revenue Projections & Cases
B71: SG&A as a % of Sales | C71: =-C30/C24 -> #DIV/0! | D71: =-D30/D24 -> #DIV/0! | E71: =-E30/E24 -> #DIV/0! | F71: =-F30/F24 -> #DIV/0! | G71: =-G30/G24 -> #DIV/0! | H71: =-H30/H24 -> #DIV/0! | T71: See Revenue Projections & Cases
B72: D&A as a % of Sales | C72: =C41/C24 -> #DIV/0! | D72: =D41/D24 -> #DIV/0! | E72: =E41/E24 -> #DIV/0! | F72: =F41/F24 -> #DIV/0! | G72: =G41/G24 -> #DIV/0! | H72: =H41/H24 -> #DIV/0! | L72: =L41/L24 -> #DIV/0! | M72: =M41/M24 -> #DIV/0! | N72: =N41/N24 -> #DIV/0! | O72: =O41/O24 -> #DIV/0! | P72: =P41/P24 -> #DIV/0! | Q72: =Q41/Q24 -> #DIV/0!
B73: SBC as a % of Sales | C73: =C44/C24 -> #DIV/0! | D73: =D44/D24 -> #DIV/0! | E73: =E44/E24 -> #DIV/0! | F73: =F44/F24 -> #DIV/0! | G73: =G44/G24 -> #DIV/0! | H73: =H44/H24 -> #DIV/0! | L73: =L44/L24 -> #DIV/0! | M73: =M44/M24 -> #DIV/0! | N73: =N44/N24 -> #DIV/0! | O73: =O44/O24 -> #DIV/0! | P73: =P44/P24 -> #DIV/0! | Q73: =Q44/Q24 -> #DIV/0!
A75: X | B75: Balance Sheet | C75: Actuals | J75: CAGR | K75: =K22 -> 0 | L75: Forecast | S75: CAGR
B76: =B16 -> Fiscal year | C76: =C16 -> 2020 | D76: =D16 -> 2021 | E76: =E16 -> 2022 | F76: =F16 -> 2023 | G76: =G16 -> 2024 | H76: =H16 -> 2025 | J76: =J16 -> 6-Year(A) | L76: =L16 -> 2026 | M76: =M16 -> 2027 | N76: =N16 -> 2028 | O76: =O16 -> 2029 | P76: =P16 -> 2030 | Q76: =Q16 -> 2031 | S76: =S16 -> 6-Year(F)
B77: =B17 -> Fiscal year end date | C77: =C17 -> 44104 | D77: =D17 -> 44469 | E77: =E17 -> 44834 | F77: =F17 -> 45192 | G77: =G17 -> 45559 | H77: =H17 -> 45927 | J77: =J17 -> 45927 | L77: =L17 -> 46295 | M77: =M17 -> 46660 | N77: =N17 -> 47026 | O77: =O17 -> 47391 | P77: =P17 -> 47756 | Q77: =Q17 -> 48121 | S77: =S17 -> 48121
B79: Total Assets
B80: Cash & equivalents, ST and LT marketable securities | J80: =((H80/C80)^(1/COUNT(D80:H80))-1) -> #DIV/0! | L80: =H80+L127 -> #DIV/0! | M80: =+L80+M127 -> #DIV/0! | N80: =+M80+N127 -> #DIV/0! | O80: =+N80+O127 -> #DIV/0! | P80: =+O80+P127 -> #DIV/0! | Q80: =+P80+Q127 -> #DIV/0! | S80: =((Q80/L80)^(1/COUNT(M80:Q80))-1) -> #DIV/0! | T80: Net change in cash' line on the cash flow statement
B81: Accounts receivable | J81: =((H81/C81)^(1/COUNT(D81:H81))-1) -> #DIV/0! | L81: =H81*L50+H81 -> 0 | M81: =L81*M50+L81 -> 0 | N81: =M81*N50+M81 -> 0 | O81: =N81*O50+N81 -> 0 | P81: =O81*P50+O81 -> 0 | Q81: =P81*Q50+P81 -> 0 | S81: =((Q81/L81)^(1/COUNT(M81:Q81))-1) -> #DIV/0! | T81: Growth in-line with revenue
B82: Inventories | J82: =((H82/C82)^(1/COUNT(D82:H82))-1) -> #DIV/0! | L82: =H82*L26/H26 -> #DIV/0! | M82: =L82*M26/L26 -> #DIV/0! | N82: =M82*N26/M26 -> #DIV/0! | O82: =N82*O26/N26 -> #DIV/0! | P82: =O82*P26/O26 -> #DIV/0! | Q82: =P82*Q26/P26 -> #DIV/0! | S82: =((Q82/L82)^(1/COUNT(M82:Q82))-1) -> #DIV/0! | T82: Growth in-line with cost of sales
B83: Other current assets | J83: =((H83/C83)^(1/COUNT(D83:H83))-1) -> #DIV/0! | L83: =SUM(H83*L50)+H83 -> 0 | M83: =L83*M50+L83 -> 0 | N83: =M83*N50+M83 -> 0 | O83: =N83*O50+N83 -> 0 | P83: =O83*P50+O83 -> 0 | Q83: =P83*Q50+P83 -> 0 | S83: =((Q83/L83)^(1/COUNT(M83:Q83))-1) -> #DIV/0! | T83: Growth in-line with revenue
B84: Property, plant & equipment | J84: =((H84/C84)^(1/COUNT(D84:H84))-1) -> #DIV/0! | L84: =L137 -> 0 | M84: =M137 -> 0 | N84: =N137 -> 0 | O84: =O137 -> 0 | P84: =P137 -> 0 | Q84: =Q137 -> 0 | S84: =((Q84/L84)^(1/COUNT(M84:Q84))-1) -> #DIV/0! | T84: See PP&E schedule
B85: Other non current assets | J85: =((H85/C85)^(1/COUNT(D85:H85))-1) -> #DIV/0! | L85: =SUM(H85*L50)+H85 -> 0 | M85: =L85*M50+L85 -> 0 | N85: =M85*N50+M85 -> 0 | O85: =N85*O50+N85 -> 0 | P85: =O85*P50+O85 -> 0 | Q85: =P85*Q50+P85 -> 0 | S85: =((Q85/L85)^(1/COUNT(M85:Q85))-1) -> #DIV/0! | T85: Growth in-line with revenue
B86: Total Assets | C86: =SUM(C80:C85) -> 0 | D86: =SUM(D80:D85) -> 0 | E86: =SUM(E80:E85) -> 0 | F86: =SUM(F80:F85) -> 0 | G86: =SUM(G80:G85) -> 0 | H86: =SUM(H80:H85) -> 0 | J86: =((H86/C86)^(1/COUNT(D86:H86))-1) -> #DIV/0! | L86: =SUM(L80:L85) -> #DIV/0! | M86: =SUM(M80:M85) -> #DIV/0! | N86: =SUM(N80:N85) -> #DIV/0! | O86: =SUM(O80:O85) -> #DIV/0! | P86: =SUM(P80:P85) -> #DIV/0! | Q86: =SUM(Q80:Q85) -> #DIV/0! | S86: =((Q86/L86)^(1/COUNT(M86:Q86))-1) -> #DIV/0!
B88: Total Liabilities
B89: Accounts payable | J89: =((H89/C89)^(1/COUNT(D89:H89))-1) -> #DIV/0! | L89: =H89*L26/H26 -> #DIV/0! | M89: =L89*M26/L26 -> #DIV/0! | N89: =M89*N26/M26 -> #DIV/0! | O89: =N89*O26/N26 -> #DIV/0! | P89: =O89*P26/O26 -> #DIV/0! | Q89: =P89*Q26/P26 -> #DIV/0! | S89: =((Q89/L89)^(1/COUNT(M89:Q89))-1) -> #DIV/0! | T89: Growth in-line with cost of sales
B90: Other current liabilities | J90: =((H90/C90)^(1/COUNT(D90:H90))-1) -> #DIV/0! | L90: =H90*L50+H90 -> 0 | M90: =L90*M50+L90 -> 0 | N90: =M90*N50+M90 -> 0 | O90: =N90*O50+N90 -> 0 | P90: =O90*P50+O90 -> 0 | Q90: =P90*Q50+P90 -> 0 | S90: =((Q90/L90)^(1/COUNT(M90:Q90))-1) -> #DIV/0! | T90: Growth in-line with revenue
B91: Deferred revenue (current) | J91: =((H91/C91)^(1/COUNT(D91:H91))-1) -> #DIV/0! | L91: =SUM(H91*L50)+H91 -> 0 | M91: =L91*M50+L91 -> 0 | N91: =M91*N50+M91 -> 0 | O91: =N91*O50+N91 -> 0 | P91: =O91*P50+O91 -> 0 | Q91: =P91*Q50+P91 -> 0 | S91: =((Q91/L91)^(1/COUNT(M91:Q91))-1) -> #DIV/0! | T91: Growth in-line with revenue
B92: Commercial paper / revolver | J92: =((H92/C92)^(1/COUNT(D92:H92))-1) -> #DIV/0! | L92: =L189 -> #DIV/0! | M92: =M189 -> #DIV/0! | N92: =N189 -> #DIV/0! | O92: =O189 -> #DIV/0! | P92: =P189 -> #DIV/0! | Q92: =Q189 -> #DIV/0! | S92: =((Q92/L92)^(1/COUNT(M92:Q92))-1) -> #DIV/0! | T92: See EOP balance from CP/revolver schedule
B93: Long term debt (includes current portion) | J93: =((H93/C93)^(1/COUNT(D93:H93))-1) -> #DIV/0! | L93: =H93 -> 0 | M93: =L93 -> 0 | N93: =M93 -> 0 | O93: =N93 -> 0 | P93: =O93 -> 0 | Q93: =P93 -> 0 | S93: =((Q93/L93)^(1/COUNT(M93:Q93))-1) -> #DIV/0! | T93: Straight-line
B94: Other non current liabilities | J94: =((H94/C94)^(1/COUNT(D94:H94))-1) -> #DIV/0! | L94: =SUM(H94*L50)+H94 -> 0 | M94: =L94*M50+L94 -> 0 | N94: =M94*N50+M94 -> 0 | O94: =N94*O50+N94 -> 0 | P94: =O94*P50+O94 -> 0 | Q94: =P94*Q50+P94 -> 0 | S94: =((Q94/L94)^(1/COUNT(M94:Q94))-1) -> #DIV/0! | T94: Growth in-line with revenue
B95: Total Liabilities | C95: =SUM(C89:C94) -> 0 | D95: =SUM(D89:D94) -> 0 | E95: =SUM(E89:E94) -> 0 | F95: =SUM(F89:F94) -> 0 | G95: =SUM(G89:G94) -> 0 | H95: =SUM(H89:H94) -> 0 | J95: =((H95/C95)^(1/COUNT(D95:H95))-1) -> #DIV/0! | L95: =SUM(L89:L94) -> #DIV/0! | M95: =SUM(M89:M94) -> #DIV/0! | N95: =SUM(N89:N94) -> #DIV/0! | O95: =SUM(O89:O94) -> #DIV/0! | P95: =SUM(P89:P94) -> #DIV/0! | Q95: =SUM(Q89:Q94) -> #DIV/0! | S95: =((Q95/L95)^(1/COUNT(M95:Q95))-1) -> #DIV/0!
B97: Stockholders' Equity
B98: Common stock | J98: =((H98/C98)^(1/COUNT(D98:H98))-1) -> #DIV/0! | L98: =H98+L44 -> 0 | M98: =L98+M44 -> 0 | N98: =M98+N44 -> 0 | O98: =N98+O44 -> 0 | P98: =O98+P44 -> 0 | Q98: =P98+Q44 -> 0 | S98: =((Q98/L98)^(1/COUNT(M98:Q98))-1) -> #DIV/0! | T98: Increase by stock-based compensation forecasted in the I/S section
B99: Retained earnings | J99: =((H99/C99)^(1/COUNT(D99:H99))-1) -> #DIV/0! | L99: =L176 -> #DIV/0! | M99: =M176 -> #DIV/0! | N99: =N176 -> #DIV/0! | O99: =O176 -> #DIV/0! | P99: =P176 -> #DIV/0! | Q99: =Q176 -> #DIV/0! | S99: =((Q99/L99)^(1/COUNT(M99:Q99))-1) -> #DIV/0! | T99: Reference from Retained Earnings schedule
B100: Other comprehensive income | J100: =((H100/C100)^(1/COUNT(D100:H100))-1) -> #DIV/0! | L100: =H100 -> 0 | M100: =L100 -> 0 | N100: =M100 -> 0 | O100: =N100 -> 0 | P100: =O100 -> 0 | Q100: =P100 -> 0 | S100: =((Q100/L100)^(1/COUNT(M100:Q100))-1) -> #DIV/0! | T100: straight-line
B101: Total Stockholders' Equity | C101: =SUM(C98:C100) -> 0 | D101: =SUM(D98:D100) -> 0 | E101: =SUM(E98:E100) -> 0 | F101: =SUM(F98:F100) -> 0 | G101: =SUM(G98:G100) -> 0 | H101: =SUM(H98:H100) -> 0 | J101: =((H101/C101)^(1/COUNT(D101:H101))-1) -> #DIV/0! | L101: =SUM(L98:L100) -> #DIV/0! | M101: =SUM(M98:M100) -> #DIV/0! | N101: =SUM(N98:N100) -> #DIV/0! | O101: =SUM(O98:O100) -> #DIV/0! | P101: =SUM(P98:P100) -> #DIV/0! | Q101: =SUM(Q98:Q100) -> #DIV/0! | S101: =((Q101/L101)^(1/COUNT(M101:Q101))-1) -> #DIV/0!
B103: Balance check | C103: =+C101+C95-C86 -> 0 | D103: =+D101+D95-D86 -> 0 | E103: =+E101+E95-E86 -> 0 | F103: =+F101+F95-F86 -> 0 | G103: =+G101+G95-G86 -> 0 | H103: =+H101+H95-H86 -> 0 | L103: =+L101+L95-L86 -> #DIV/0! | M103: =+M101+M95-M86 -> #DIV/0! | N103: =+N101+N95-N86 -> #DIV/0! | O103: =+O101+O95-O86 -> #DIV/0! | P103: =+P101+P95-P86 -> #DIV/0! | Q103: =+Q101+Q95-Q86 -> #DIV/0!
A105: X | B105: Cash-Flows Statement | C105: Actuals | J105: CAGR | L105: Forecast | S105: CAGR
B106: =B16 -> Fiscal year | C106: =C76 -> 2020 | D106: =D76 -> 2021 | E106: =E76 -> 2022 | F106: =F76 -> 2023 | G106: =G76 -> 2024 | H106: =H76 -> 2025 | J106: =J76 -> 6-Year(A) | L106: =L76 -> 2026 | M106: =M76 -> 2027 | N106: =N76 -> 2028 | O106: =O76 -> 2029 | P106: =P76 -> 2030 | Q106: =Q76 -> 2031 | S106: =S76 -> 6-Year(F)
B107: =B17 -> Fiscal year end date | C107: =C77 -> 44104 | D107: =D77 -> 44469 | E107: =E77 -> 44834 | F107: =F77 -> 45192 | G107: =G77 -> 45559 | H107: =H77 -> 45927 | J107: =J77 -> 45927 | L107: =L77 -> 46295 | M107: =M77 -> 46660 | N107: =N77 -> 47026 | O107: =O77 -> 47391 | P107: =P77 -> 47756 | Q107: =Q77 -> 48121 | S107: =S77 -> 48121
B109: Net income | C109: =C39 -> 0 | D109: =D39 -> 0 | E109: =E39 -> 0 | F109: =F39 -> 0 | G109: =G39 -> 0 | H109: =H39 -> 0 | J109: =((H109/C109)^(1/COUNT(D109:H109))-1) -> #DIV/0! | L109: =L39 -> #DIV/0! | M109: =M39 -> #DIV/0! | N109: =N39 -> #DIV/0! | O109: =O39 -> #DIV/0! | P109: =P39 -> #DIV/0! | Q109: =Q39 -> #DIV/0! | S109: =((Q109/L109)^(1/COUNT(M109:Q109))-1) -> #DIV/0! | T109: Reference from the I/S
B110: Depreciation and amortization | C110: =C41 -> 0 | D110: =D41 -> 0 | E110: =E41 -> 0 | F110: =F41 -> 0 | G110: =G41 -> 0 | H110: =H41 -> 0 | J110: =((H110/C110)^(1/COUNT(D110:H110))-1) -> #DIV/0! | L110: =L41 -> #DIV/0! | M110: =M41 -> #DIV/0! | N110: =N41 -> #DIV/0! | O110: =O41 -> #DIV/0! | P110: =P41 -> #DIV/0! | Q110: =Q41 -> #DIV/0! | S110: =((Q110/L110)^(1/COUNT(M110:Q110))-1) -> #DIV/0! | T110: Reference from the I/S
B111: Stock based compensation | C111: =C44 -> 0 | D111: =D44 -> 0 | E111: =E44 -> 0 | F111: =F44 -> 0 | G111: =G44 -> 0 | H111: =H44 -> 0 | J111: =((H111/C111)^(1/COUNT(D111:H111))-1) -> #DIV/0! | L111: =L44 -> 0 | M111: =M44 -> 0 | N111: =N44 -> 0 | O111: =O44 -> 0 | P111: =P44 -> 0 | Q111: =Q44 -> 0 | S111: =((Q111/L111)^(1/COUNT(M111:Q111))-1) -> #DIV/0! | T111: Reference from the I/S
