Workbook

Sheet Historical Financials
B2: Qualcomm (NASDAQ: QCOM)
B3: Historical Financials
B4: $ in thousands except per share
A6: X | B6: Income Statement | E6: FYE | I6: Quarterly | M6: Quarterly | S6: Quarterly | AH6: LTM | AI6: LTM | AO6: Variance
B7: Fiscal Period | C7: 2020 | D7: 2021 | E7: 2022 | F7: 2023 | G7: 2024 | I7: 1Q22 | J7: 2Q22 | K7: 3Q22 | L7: 4Q22 | M7: 1Q23 | N7: 2Q23 | O7: 3Q23 | P7: 4Q23 | Q7: 1Q24 | R7: 2Q24 | S7: 3Q24 | T7: 4Q24 | U7: 1Q25 | V7: 2Q25 | W7: 3Q25 | Y7: =I7 -> 1Q22 | Z7: =J7 -> 2Q22 | AA7: =K7 -> 3Q22 | AB7: =L7 -> 4Q22 | AC7: =M7 -> 1Q23 | AD7: =N7 -> 2Q23 | AE7: =O7 -> 3Q23 | AF7: =P7 -> 4Q23 | ... AM7: =W7 -> 3Q25
B8: Fiscal Period End Date | C8: 44196 | D8: 44561 | E8: 44926 | F8: 45291 | G8: 45657 | I8: 44651 | J8: 44742 | K8: 44834 | L8: =E8 -> 44926 | M8: 45016 | N8: 45107 | O8: 45199 | P8: =F8 -> 45291 | Q8: 45382 | R8: 45473 | S8: 45565 | T8: =G8 -> 45657 | U8: 45747 | V8: 45838 | W8: 45930 | Y8: =I8 -> 44651 | Z8: =J8 -> 44742 | AA8: =K8 -> 44834 | AB8: =L8 -> 44926 | AC8: =M8 -> 45016 | AD8: =N8 -> 45107 | AE8: =O8 -> 45199 | AF8: =P8 -> 45291 | ... AM8: =W8 -> 45930
B10: Consolidated Revenue | C10: 23531 | D10: 33566 | E10: 44200 | F10: 35820 | G10: 38962 | I10: 10705 | J10: 11164 | K10: 10936 | L10: =SUM(E10-SUM(I10:K10)) -> 11395 | M10: 9463 | N10: 9275 | O10: 8451 | P10: =SUM(F10-SUM(M10:O10)) -> 8631 | Q10: 9935 | R10: 9389 | S10: 9393 | T10: =SUM(G10-SUM(Q10:S10)) -> 10245 | Y10: =SUM(I10:I10) -> 10705 | Z10: =SUM(I10:J10) -> 21869 | AA10: =SUM(I10:K10) -> 32805 | AB10: =SUM(I10:L10) -> 44200 | AC10: =SUM(J10:M10) -> 42958 | AD10: =SUM(K10:N10) -> 41069 | AE10: =SUM(L10:O10) -> 38584 | AF10: =SUM(M10:P10) -> 35820 | AG10: =SUM(N10:Q10) -> 36292 | AH10: =SUM(O10:R10) -> 36406 | AI10: =SUM(P10:S10) -> 37348 | ... AM10: =SUM(T10:W10) -> 10245 | AO10: =SUM(AM10/AI10)-1 -> -0.72568812
B11: Total Revenue | C11: =+SUM(C10:C10) -> 23531 | D11: =+SUM(D10:D10) -> 33566 | E11: =+SUM(E10:E10) -> 44200 | F11: =+SUM(F10:F10) -> 35820 | G11: =+SUM(G10:G10) -> 38962 | I11: =+SUM(I10:I10) -> 10705 | J11: =+SUM(J10:J10) -> 11164 | K11: =+SUM(K10:K10) -> 10936 | L11: =+SUM(L10:L10) -> 11395 | M11: =+SUM(M10:M10) -> 9463 | N11: =+SUM(N10:N10) -> 9275 | O11: =+SUM(O10:O10) -> 8451 | P11: =+SUM(P10:P10) -> 8631 | ... W11: =+SUM(W10:W10) -> 0 | Y11: =+SUM(Y10:Y10) -> 10705 | Z11: =+SUM(Z10:Z10) -> 21869 | AA11: =+SUM(AA10:AA10) -> 32805 | AB11: =+SUM(AB10:AB10) -> 44200 | AC11: =+SUM(AC10:AC10) -> 42958 | AD11: =+SUM(AD10:AD10) -> 41069 | AE11: =+SUM(AE10:AE10) -> 38584 | AF11: =+SUM(AF10:AF10) -> 35820 | ... AM11: =+SUM(AM10:AM10) -> 10245 | AO11: =SUM(AM11/AI11)-1 -> -0.72568812
B13: Cost of revenue | C13: -9255 | D13: -14262 | E13: -18635 | F13: -15869 | G13: -17060 | I13: -4303 | J13: -4648 | K13: -4816 | L13: =SUM(E13-SUM(I13:K13)) -> -4868 | M13: -4044 | N13: -4153 | O13: -3792 | P13: =SUM(F13-SUM(M13:O13)) -> -3880 | Q13: -4312 | R13: -4106 | S13: -4174 | T13: =SUM(G13-SUM(Q13:S13)) -> -4468 | Y13: =SUM(I13:I13) -> -4303 | Z13: =SUM(I13:J13) -> -8951 | AA13: =SUM(I13:K13) -> -13767 | AB13: =SUM(I13:L13) -> -18635 | AC13: =SUM(J13:M13) -> -18376 | AD13: =SUM(K13:N13) -> -17881 | AE13: =SUM(L13:O13) -> -16857 | AF13: =SUM(M13:P13) -> -15869 | AG13: =SUM(N13:Q13) -> -16137 | AH13: =SUM(O13:R13) -> -16090 | AI13: =SUM(P13:S13) -> -16472 | ... AM13: =SUM(T13:W13) -> -4468 | AO13: =SUM(AM13/AI13)-1 -> -0.72875182
B14: Gross Profit | C14: =+SUM(C11+SUM(C13:C13)) -> 14276 | D14: =+SUM(D11+SUM(D13:D13)) -> 19304 | E14: =+SUM(E11+SUM(E13:E13)) -> 25565 | F14: =+SUM(F11+SUM(F13:F13)) -> 19951 | G14: =+SUM(G11+SUM(G13:G13)) -> 21902 | I14: =+SUM(I11+SUM(I13:I13)) -> 6402 | J14: =+SUM(J11+SUM(J13:J13)) -> 6516 | K14: =+SUM(K11+SUM(K13:K13)) -> 6120 | L14: =+SUM(L11+SUM(L13:L13)) -> 6527 | M14: =+SUM(M11+SUM(M13:M13)) -> 5419 | N14: =+SUM(N11+SUM(N13:N13)) -> 5122 | O14: =+SUM(O11+SUM(O13:O13)) -> 4659 | P14: =+SUM(P11+SUM(P13:P13)) -> 4751 | ... W14: =+SUM(W11+SUM(W13:W13)) -> 0 | Y14: =+SUM(Y11+SUM(Y13:Y13)) -> 6402 | Z14: =+SUM(Z11+SUM(Z13:Z13)) -> 12918 | AA14: =+SUM(AA11+SUM(AA13:AA13)) -> 19038 | AB14: =+SUM(AB11+SUM(AB13:AB13)) -> 25565 | AC14: =+SUM(AC11+SUM(AC13:AC13)) -> 24582 | AD14: =+SUM(AD11+SUM(AD13:AD13)) -> 23188 | AE14: =+SUM(AE11+SUM(AE13:AE13)) -> 21727 | AF14: =+SUM(AF11+SUM(AF13:AF13)) -> 19951 | ... AM14: =+SUM(AM11+SUM(AM13:AM13)) -> 5777 | AO14: =SUM(AM14/AI14)-1 -> -0.72327074
B15: Gross Margin (%) | C15: =C14/C11 -> 0.60668905 | D15: =D14/D11 -> 0.57510576 | E15: =E14/E11 -> 0.57839367 | F15: =F14/F11 -> 0.55697934 | G15: =G14/G11 -> 0.56213747 | I15: =I14/I11 -> 0.5980383 | J15: =J14/J11 -> 0.58366177 | K15: =K14/K11 -> 0.5596196 | L15: =L14/L11 -> 0.57279509 | M15: =M14/M11 -> 0.57265138 | N15: =N14/N11 -> 0.5522372 | O15: =O14/O11 -> 0.5512957 | P15: =P14/P11 -> 0.55045765 | ... W15: =W14/W11 -> #DIV/0! | Y15: =Y14/Y11 -> 0.5980383 | Z15: =Z14/Z11 -> 0.59069916 | AA15: =AA14/AA11 -> 0.58033836 | AB15: =AB14/AB11 -> 0.57839367 | AC15: =AC14/AC11 -> 0.57223334 | AD15: =AD14/AD11 -> 0.56461078 | AE15: =AE14/AE11 -> 0.56310906 | AF15: =AF14/AF11 -> 0.55697934 | ... AM15: =AM14/AM11 -> 0.56388482 | AO15: =SUM(AM15-AI15)*1000 -> 4.9258415
B17: Research and development | C17: -5975 | D17: -7176 | E17: -8194 | F17: -8818 | G17: -8893 | I17: -1930 | J17: -2034 | K17: -2052 | L17: =SUM(E17-SUM(I17:K17)) -> -2178 | M17: -2251 | N17: -2210 | O17: -2222 | P17: =SUM(F17-SUM(M17:O17)) -> -2135 | Q17: -2096 | R17: -2236 | S17: -2259 | T17: =SUM(G17-SUM(Q17:S17)) -> -2302 | Y17: =SUM(I17:I17) -> -1930 | Z17: =SUM(I17:J17) -> -3964 | AA17: =SUM(I17:K17) -> -6016 | AB17: =SUM(I17:L17) -> -8194 | AC17: =SUM(J17:M17) -> -8515 | AD17: =SUM(K17:N17) -> -8691 | AE17: =SUM(L17:O17) -> -8861 | AF17: =SUM(M17:P17) -> -8818 | AG17: =SUM(N17:Q17) -> -8663 | AH17: =SUM(O17:R17) -> -8689 | AI17: =SUM(P17:S17) -> -8726 | ... AM17: =SUM(T17:W17) -> -2302 | AO17: =SUM(AM17/AI17)-1 -> -0.73619069
B18: Selling, general and administrative | C18: -2074 | D18: -2339 | E18: -2570 | F18: -2483 | G18: -2759 | I18: -608 | J18: -624 | K18: -655 | L18: =SUM(E18-SUM(I18:K18)) -> -683 | M18: -623 | N18: -614 | O18: -618 | P18: =SUM(F18-SUM(M18:O18)) -> -628 | Q18: -627 | R18: -707 | S18: -664 | T18: =SUM(G18-SUM(Q18:S18)) -> -761 | Y18: =SUM(I18:I18) -> -608 | Z18: =SUM(I18:J18) -> -1232 | AA18: =SUM(I18:K18) -> -1887 | AB18: =SUM(I18:L18) -> -2570 | AC18: =SUM(J18:M18) -> -2585 | AD18: =SUM(K18:N18) -> -2575 | AE18: =SUM(L18:O18) -> -2538 | AF18: =SUM(M18:P18) -> -2483 | AG18: =SUM(N18:Q18) -> -2487 | AH18: =SUM(O18:R18) -> -2580 | AI18: =SUM(P18:S18) -> -2626 | ... AM18: =SUM(T18:W18) -> -761 | AO18: =SUM(AM18/AI18)-1 -> -0.71020564
B19: Other Expenses | C19: 28 | D19: 0 | E19: 1059 | F19: -862 | G19: -179 | I19: 0 | J19: 0 | K19: 1059 | L19: =SUM(E19-SUM(I19:K19)) -> 0 | M19: -80 | N19: -208 | O19: 4 | P19: =SUM(F19-SUM(M19:O19)) -> -578 | Q19: 28 | R19: 0 | S19: -75 | T19: =SUM(G19-SUM(Q19:S19)) -> -132 | Y19: =SUM(I19:I19) -> 0 | Z19: =SUM(I19:J19) -> 0 | AA19: =SUM(I19:K19) -> 1059 | AB19: =SUM(I19:L19) -> 1059 | AC19: =SUM(J19:M19) -> 979 | AD19: =SUM(K19:N19) -> 771 | AE19: =SUM(L19:O19) -> -284 | AF19: =SUM(M19:P19) -> -862 | AG19: =SUM(N19:Q19) -> -754 | AH19: =SUM(O19:R19) -> -546 | AI19: =SUM(P19:S19) -> -625 | ... AM19: =SUM(T19:W19) -> -132 | AO19: =SUM(AM19/AI19)-1 -> -0.7888
B20: Operating Profit | C20: =+SUM(C14+SUM(C17:C19)) -> 6255 | D20: =+SUM(D14+SUM(D17:D19)) -> 9789 | E20: =+SUM(E14+SUM(E17:E19)) -> 15860 | F20: =+SUM(F14+SUM(F17:F19)) -> 7788 | G20: =+SUM(G14+SUM(G17:G19)) -> 10071 | I20: =+SUM(I14+SUM(I17:I19)) -> 3864 | J20: =+SUM(J14+SUM(J17:J19)) -> 3858 | K20: =+SUM(K14+SUM(K17:K19)) -> 4472 | L20: =+SUM(L14+SUM(L17:L19)) -> 3666 | M20: =+SUM(M14+SUM(M17:M19)) -> 2465 | N20: =+SUM(N14+SUM(N17:N19)) -> 2090 | O20: =+SUM(O14+SUM(O17:O19)) -> 1823 | P20: =+SUM(P14+SUM(P17:P19)) -> 1410 | ... W20: =+SUM(W14+SUM(W17:W19)) -> 0 | Y20: =+SUM(Y14+SUM(Y17:Y19)) -> 3864 | Z20: =+SUM(Z14+SUM(Z17:Z19)) -> 7722 | AA20: =+SUM(AA14+SUM(AA17:AA19)) -> 12194 | AB20: =+SUM(AB14+SUM(AB17:AB19)) -> 15860 | AC20: =+SUM(AC14+SUM(AC17:AC19)) -> 14461 | AD20: =+SUM(AD14+SUM(AD17:AD19)) -> 12693 | AE20: =+SUM(AE14+SUM(AE17:AE19)) -> 10044 | AF20: =+SUM(AF14+SUM(AF17:AF19)) -> 7788 | ... AM20: =+SUM(AM14+SUM(AM17:AM19)) -> 2582 | AO20: =SUM(AM20/AI20)-1 -> -0.70985504
B21: Operating Margin (%) | C21: =C20/C11 -> 0.26581956 | D21: =D20/D11 -> 0.29163439 | E21: =E20/E11 -> 0.35882353 | F21: =F20/F11 -> 0.21742044 | G21: =G20/G11 -> 0.25848262 | I21: =I20/I11 -> 0.36095283 | J21: =J20/J11 -> 0.34557506 | K21: =K20/K11 -> 0.40892465 | L21: =L20/L11 -> 0.32172005 | M21: =M20/M11 -> 0.26048822 | N21: =N20/N11 -> 0.22533693 | O21: =O20/O11 -> 0.21571412 | P21: =P20/P11 -> 0.16336462 | ... W21: =W20/W11 -> #DIV/0! | Y21: =Y20/Y11 -> 0.36095283 | Z21: =Z20/Z11 -> 0.35310257 | AA21: =AA20/AA11 -> 0.37171163 | AB21: =AB20/AB11 -> 0.35882353 | AC21: =AC20/AC11 -> 0.33663113 | AD21: =AD20/AD11 -> 0.30906523 | AE21: =AE20/AE11 -> 0.26031516 | AF21: =AF20/AF11 -> 0.21742044 | ... AM21: =AM20/AM11 -> 0.25202538 | AO21: =SUM(AM21-AI21)*1000 -> 13.752914
B23: Interest expense | C23: -602 | D23: -559 | E23: -490 | F23: -694 | G23: -697 | I23: -139 | J23: -137 | K23: -70 | L23: =SUM(E23-SUM(I23:K23)) -> -144 | M23: -170 | N23: -179 | O23: -172 | P23: =SUM(F23-SUM(M23:O23)) -> -173 | Q23: -178 | R23: -172 | S23: -168 | T23: =SUM(G23-SUM(Q23:S23)) -> -179 | Y23: =SUM(I23:I23) -> -139 | Z23: =SUM(I23:J23) -> -276 | AA23: =SUM(I23:K23) -> -346 | AB23: =SUM(I23:L23) -> -490 | AC23: =SUM(J23:M23) -> -521 | AD23: =SUM(K23:N23) -> -563 | AE23: =SUM(L23:O23) -> -665 | AF23: =SUM(M23:P23) -> -694 | AG23: =SUM(N23:Q23) -> -702 | AH23: =SUM(O23:R23) -> -695 | AI23: =SUM(P23:S23) -> -691 | ... AM23: =SUM(T23:W23) -> -179 | AO23: =SUM(AM23/AI23)-1 -> -0.74095514
B24: Interest and dividend income | C24: 156 | D24: 83 | E24: 91 | F24: 313 | G24: 675 | I24: 17 | J24: 20 | K24: 22 | L24: =SUM(E24-SUM(I24:K24)) -> 32 | M24: 55 | N24: 59 | O24: 79 | P24: =SUM(F24-SUM(M24:O24)) -> 120 | Q24: 149 | R24: 160 | S24: 182 | T24: =SUM(G24-SUM(Q24:S24)) -> 184 | Y24: =SUM(I24:I24) -> 17 | Z24: =SUM(I24:J24) -> 37 | AA24: =SUM(I24:K24) -> 59 | AB24: =SUM(I24:L24) -> 91 | AC24: =SUM(J24:M24) -> 129 | AD24: =SUM(K24:N24) -> 168 | AE24: =SUM(L24:O24) -> 225 | AF24: =SUM(M24:P24) -> 313 | AG24: =SUM(N24:Q24) -> 407 | AH24: =SUM(O24:R24) -> 508 | AI24: =SUM(P24:S24) -> 611 | ... AM24: =SUM(T24:W24) -> 184 | AO24: =SUM(AM24/AI24)-1 -> -0.69885434
B25: Investment and other income (expense), net | C25: -90 | D25: 961 | E25: -463 | F25: 36 | G25: 287 | I25: 123 | J25: -318 | K25: -185 | L25: =SUM(E25-SUM(I25:K25)) -> -83 | M25: 21 | N25: -75 | O25: 27 | P25: =SUM(F25-SUM(M25:O25)) -> 63 | Q25: 63 | R25: 170 | S25: 44 | T25: =SUM(G25-SUM(Q25:S25)) -> 10 | Y25: =SUM(I25:I25) -> 123 | Z25: =SUM(I25:J25) -> -195 | AA25: =SUM(I25:K25) -> -380 | AB25: =SUM(I25:L25) -> -463 | AC25: =SUM(J25:M25) -> -565 | AD25: =SUM(K25:N25) -> -322 | AE25: =SUM(L25:O25) -> -110 | AF25: =SUM(M25:P25) -> 36 | AG25: =SUM(N25:Q25) -> 78 | AH25: =SUM(O25:R25) -> 323 | AI25: =SUM(P25:S25) -> 340 | ... AM25: =SUM(T25:W25) -> 10 | AO25: =SUM(AM25/AI25)-1 -> -0.97058824
B26: Earning Before Taxes | C26: =SUM(C20+SUM(C23:C25)) -> 5719 | D26: =SUM(D20+SUM(D23:D25)) -> 10274 | E26: =SUM(E20+SUM(E23:E25)) -> 14998 | F26: =SUM(F20+SUM(F23:F25)) -> 7443 | G26: =SUM(G20+SUM(G23:G25)) -> 10336 | I26: =SUM(I20+SUM(I23:I25)) -> 3865 | J26: =SUM(J20+SUM(J23:J25)) -> 3423 | K26: =SUM(K20+SUM(K23:K25)) -> 4239 | L26: =SUM(L20+SUM(L23:L25)) -> 3471 | M26: =SUM(M20+SUM(M23:M25)) -> 2371 | N26: =SUM(N20+SUM(N23:N25)) -> 1895 | O26: =SUM(O20+SUM(O23:O25)) -> 1757 | P26: =SUM(P20+SUM(P23:P25)) -> 1420 | ... W26: =SUM(W20+SUM(W23:W25)) -> 0 | Y26: =SUM(Y20+SUM(Y23:Y25)) -> 3865 | Z26: =SUM(Z20+SUM(Z23:Z25)) -> 7288 | AA26: =SUM(AA20+SUM(AA23:AA25)) -> 11527 | AB26: =SUM(AB20+SUM(AB23:AB25)) -> 14998 | AC26: =SUM(AC20+SUM(AC23:AC25)) -> 13504 | AD26: =SUM(AD20+SUM(AD23:AD25)) -> 11976 | AE26: =SUM(AE20+SUM(AE23:AE25)) -> 9494 | AF26: =SUM(AF20+SUM(AF23:AF25)) -> 7443 | ... AM26: =SUM(AM20+SUM(AM23:AM25)) -> 2597 | AO26: =SUM(AM26/AI26)-1 -> -0.71645376
B27: EBT Margin (%) | C27: =C26/C11 -> 0.24304109 | D27: =D26/D11 -> 0.30608354 | E27: =E26/E11 -> 0.33932127 | F27: =F26/F11 -> 0.20778894 | G27: =G26/G11 -> 0.26528412 | I27: =I26/I11 -> 0.36104624 | J27: =J26/J11 -> 0.30661053 | K27: =K26/K11 -> 0.38761887 | L27: =L26/L11 -> 0.30460728 | M27: =M26/M11 -> 0.25055479 | N27: =N26/N11 -> 0.20431267 | O27: =O26/O11 -> 0.20790439 | P27: =P26/P11 -> 0.16452323 | ... W27: =W26/W11 -> #DIV/0! | Y27: =Y26/Y11 -> 0.36104624 | Z27: =Z26/Z11 -> 0.33325712 | AA27: =AA26/AA11 -> 0.35137936 | AB27: =AB26/AB11 -> 0.33932127 | AC27: =AC26/AC11 -> 0.31435355 | AD27: =AD26/AD11 -> 0.29160681 | AE27: =AE26/AE11 -> 0.24606054 | AF27: =AF26/AF11 -> 0.20778894 | ... AM27: =AM26/AM11 -> 0.25348951 | AO27: =SUM(AM27-AI27)*1000 -> 8.2554919
B29: Provision for taxes | C29: -521 | D29: -1231 | E29: -2012 | F29: -104 | G29: -226 | I29: -466 | J29: -489 | K29: -509 | L29: =SUM(E29-SUM(I29:K29)) -> -548 | M29: -98 | N29: -193 | O29: -22 | P29: =SUM(F29-SUM(M29:O29)) -> 209 | Q29: -151 | R29: -223 | S29: -171 | T29: =SUM(G29-SUM(Q29:S29)) -> 319 | Y29: =SUM(I29:I29) -> -466 | Z29: =SUM(I29:J29) -> -955 | AA29: =SUM(I29:K29) -> -1464 | AB29: =SUM(I29:L29) -> -2012 | AC29: =SUM(J29:M29) -> -1644 | AD29: =SUM(K29:N29) -> -1348 | AE29: =SUM(L29:O29) -> -861 | AF29: =SUM(M29:P29) -> -104 | AG29: =SUM(N29:Q29) -> -157 | AH29: =SUM(O29:R29) -> -187 | AI29: =SUM(P29:S29) -> -336 | ... AM29: =SUM(T29:W29) -> 319 | AO29: =SUM(AM29/AI29)-1 -> -1.9494048
B30: Income from continuing operations | C30: =SUM(C26+SUM(C29:C29)) -> 5198 | D30: =SUM(D26+SUM(D29:D29)) -> 9043 | E30: =SUM(E26+SUM(E29:E29)) -> 12986 | F30: =SUM(F26+SUM(F29:F29)) -> 7339 | G30: =SUM(G26+SUM(G29:G29)) -> 10110 | I30: =SUM(I26+SUM(I29:I29)) -> 3399 | J30: =SUM(J26+SUM(J29:J29)) -> 2934 | K30: =SUM(K26+SUM(K29:K29)) -> 3730 | L30: =SUM(L26+SUM(L29:L29)) -> 2923 | M30: =SUM(M26+SUM(M29:M29)) -> 2273 | N30: =SUM(N26+SUM(N29:N29)) -> 1702 | O30: =SUM(O26+SUM(O29:O29)) -> 1735 | P30: =SUM(P26+SUM(P29:P29)) -> 1629 | ... W30: =SUM(W26+SUM(W29:W29)) -> 0 | Y30: =SUM(Y26+SUM(Y29:Y29)) -> 3399 | Z30: =SUM(Z26+SUM(Z29:Z29)) -> 6333 | AA30: =SUM(AA26+SUM(AA29:AA29)) -> 10063 | AB30: =SUM(AB26+SUM(AB29:AB29)) -> 12986 | AC30: =SUM(AC26+SUM(AC29:AC29)) -> 11860 | AD30: =SUM(AD26+SUM(AD29:AD29)) -> 10628 | AE30: =SUM(AE26+SUM(AE29:AE29)) -> 8633 | AF30: =SUM(AF26+SUM(AF29:AF29)) -> 7339 | ... AM30: =SUM(AM26+SUM(AM29:AM29)) -> 2916 | AO30: =SUM(AM30/AI30)-1 -> -0.66950017
B31: Net Margin (%) | C31: =C30/C11 -> 0.22090009 | D31: =D30/D11 -> 0.26940952 | E31: =E30/E11 -> 0.2938009 | F31: =F30/F11 -> 0.20488554 | G31: =G30/G11 -> 0.2594836 | I31: =I30/I11 -> 0.31751518 | J31: =J30/J11 -> 0.26280903 | K31: =K30/K11 -> 0.34107535 | L31: =L30/L11 -> 0.25651602 | M31: =M30/M11 -> 0.24019867 | N31: =N30/N11 -> 0.18350404 | O31: =O30/O11 -> 0.20530115 | P31: =P30/P11 -> 0.18873827 | ... W31: =W30/W11 -> #DIV/0! | Y31: =Y30/Y11 -> 0.31751518 | Z31: =Z30/Z11 -> 0.289588 | AA31: =AA30/AA11 -> 0.30675202 | AB31: =AB30/AB11 -> 0.2938009 | AC31: =AC30/AC11 -> 0.27608362 | AD31: =AD30/AD11 -> 0.258784 | AE31: =AE30/AE11 -> 0.22374559 | AF31: =AF30/AF11 -> 0.20488554 | ... AM31: =AM30/AM11 -> 0.28462665 | AO31: =SUM(AM31-AI31)*1000 -> 48.389098
B33: Discontinued operations, net of income taxes | C33: 0 | D33: 0 | E33: -50 | F33: -107 | G33: 32 | I33: 0 | J33: 0 | K33: 0 | L33: =SUM(E33-SUM(I33:K33)) -> -50 | M33: -38 | N33: 2 | O33: 68 | P33: =SUM(F33-SUM(M33:O33)) -> -139 | Q33: -44 | R33: 51 | S33: 21 | T33: =SUM(G33-SUM(Q33:S33)) -> 4
B34: Net Income | C34: =SUM(C30+SUM(C33:C33)) -> 5198 | D34: =SUM(D30+SUM(D33:D33)) -> 9043 | E34: =SUM(E30+SUM(E33:E33)) -> 12936 | F34: =SUM(F30+SUM(F33:F33)) -> 7232 | G34: =SUM(G30+SUM(G33:G33)) -> 10142 | I34: =SUM(I30+SUM(I33:I33)) -> 3399 | J34: =SUM(J30+SUM(J33:J33)) -> 2934 | K34: =SUM(K30+SUM(K33:K33)) -> 3730 | L34: =SUM(L30+SUM(L33:L33)) -> 2873 | M34: =SUM(M30+SUM(M33:M33)) -> 2235 | N34: =SUM(N30+SUM(N33:N33)) -> 1704 | O34: =SUM(O30+SUM(O33:O33)) -> 1803 | P34: =SUM(P30+SUM(P33:P33)) -> 1490 | ... W34: =SUM(W30+SUM(W33:W33)) -> 0 | Y34: =SUM(Y29+SUM(Y33:Y33)) -> -466 | Z34: =SUM(Z29+SUM(Z33:Z33)) -> -955 | AA34: =SUM(AA29+SUM(AA33:AA33)) -> -1464 | AB34: =SUM(AB29+SUM(AB33:AB33)) -> -2012 | AC34: =SUM(AC29+SUM(AC33:AC33)) -> -1644 | AD34: =SUM(AD29+SUM(AD33:AD33)) -> -1348 | AE34: =SUM(AE29+SUM(AE33:AE33)) -> -861 | AF34: =SUM(AF29+SUM(AF33:AF33)) -> -104 | ... AM34: =SUM(AM29+SUM(AM33:AM33)) -> 319 | AO34: =SUM(AM34/AI34)-1 -> -1.9494048
B35: Net Margin (%) | C35: =C34/C11 -> 0.22090009 | D35: =D34/D11 -> 0.26940952 | E35: =E34/E11 -> 0.29266968 | F35: =F34/F11 -> 0.20189838 | G35: =G34/G11 -> 0.26030491 | I35: =I34/I11 -> 0.31751518 | J35: =J34/J11 -> 0.26280903 | K35: =K34/K11 -> 0.34107535 | L35: =L34/L11 -> 0.25212813 | M35: =M34/M11 -> 0.23618303 | N35: =N34/N11 -> 0.18371968 | O35: =O34/O11 -> 0.21334753 | P35: =P34/P11 -> 0.17263353 | ... W35: =W34/W11 -> #DIV/0! | Y35: =Y34/Y14 -> -0.072789753 | Z35: =Z34/Z14 -> -0.073927853 | AA35: =AA34/AA14 -> -0.076898834 | AB35: =AB34/AB14 -> -0.07870135 | AC35: =AC34/AC14 -> -0.066878204 | AD35: =AD34/AD14 -> -0.058133517 | AE35: =AE34/AE14 -> -0.039628112 | AF35: =AF34/AF14 -> -0.0052127713 | ... AM35: =AM34/AM14 -> 0.055218972 | AO35: =SUM(AM35-AI35)*1000 -> 71.314009
B37: Basic Shares | L37: =E37 -> 0 | P37: =F37 -> 0 | T37: =G37 -> 0 | Y37: =I37 -> 0 | Z37: =J37 -> 0 | AA37: =K37 -> 0 | AB37: =L37 -> 0 | AC37: =M37 -> 0 | AD37: =N37 -> 0 | AE37: =O37 -> 0 | AF37: =P37 -> 0 | ... AM37: =W37 -> 0 | AO37: =SUM(AM37/AI37)-1 -> #DIV/0!
B38: Basic EPS | C38: =C30/C37 -> #DIV/0! | D38: =D30/D37 -> #DIV/0! | E38: =E30/E37 -> #DIV/0! | F38: =F30/F37 -> #DIV/0! | G38: =G30/G37 -> #DIV/0! | I38: =I30/I37 -> #DIV/0! | J38: =J30/J37 -> #DIV/0! | K38: =K30/K37 -> #DIV/0! | L38: =L30/L37 -> #DIV/0! | M38: =M30/M37 -> #DIV/0! | N38: =N30/N37 -> #DIV/0! | O38: =O30/O37 -> #DIV/0! | P38: =P30/P37 -> #DIV/0! | ... W38: =W30/W37 -> #DIV/0! | Y38: =Y30/Y37 -> #DIV/0! | Z38: =Z30/Z37 -> #DIV/0! | AA38: =AA30/AA37 -> #DIV/0! | AB38: =AB30/AB37 -> #DIV/0! | AC38: =AC30/AC37 -> #DIV/0! | AD38: =AD30/AD37 -> #DIV/0! | AE38: =AE30/AE37 -> #DIV/0! | AF38: =AF30/AF37 -> #DIV/0! | ... AM38: =AM30/AM37 -> #DIV/0! | AO38: =SUM(AM38/AI38)-1 -> #DIV/0!
B40: Fully Diluted Shares | C40: 1149 | D40: 1149 | E40: 1137 | F40: 1126 | G40: 1130 | I40: 1142 | J40: 1140 | K40: 1134 | L40: =E40 -> 1137 | M40: 1131 | N40: 1123 | O40: 1124 | P40: =F40 -> 1126 | Q40: 1127 | R40: 1130 | S40: 1134 | T40: =G40 -> 1130 | Y40: =I40 -> 1142 | Z40: =J40 -> 1140 | AA40: =K40 -> 1134 | AB40: =L40 -> 1137 | AC40: =M40 -> 1131 | AD40: =N40 -> 1123 | AE40: =O40 -> 1124 | AF40: =P40 -> 1126 | ... AM40: =W40 -> 0 | AO40: =SUM(AM40/AI40)-1 -> -1
B41: Fully Diluted EPS | C41: =C34/C40 -> 4.5239339 | D41: =D34/D40 -> 7.870322 | E41: =E34/E40 -> 11.377309 | F41: =F34/F40 -> 6.4227353 | G41: =G34/G40 -> 8.9752212 | I41: =I30/I40 -> 2.9763573 | J41: =J30/J40 -> 2.5736842 | K41: =K30/K40 -> 3.2892416 | L41: =L30/L40 -> 2.5708004 | M41: =M30/M40 -> 2.0097259 | N41: =N30/N40 -> 1.5155833 | O41: =O30/O40 -> 1.5435943 | P41: =P30/P40 -> 1.446714 | ... W41: =W30/W40 -> #DIV/0! | Y41: =Y30/Y40 -> 2.9763573 | Z41: =Z30/Z40 -> 5.5552632 | AA41: =AA30/AA40 -> 8.8738977 | AB41: =AB30/AB40 -> 11.421284 | AC41: =AC30/AC40 -> 10.486295 | AD41: =AD30/AD40 -> 9.4639359 | AE41: =AE30/AE40 -> 7.680605 | AF41: =AF30/AF40 -> 6.517762 | ... AM41: =AM30/AM40 -> #DIV/0! | AO41: =SUM(AM41/AI41)-1 -> #DIV/0!
A43: X | B43: Balance Sheet | AH43: LTM | AO43: Variance
B44: =B7 -> Fiscal Period | C44: =C7 -> 2020 | D44: =D7 -> 2021 | E44: =E7 -> 2022 | F44: =F7 -> 2023 | G44: =G7 -> 2024 | I44: =I7 -> 1Q22 | J44: =J7 -> 2Q22 | K44: =K7 -> 3Q22 | L44: =L7 -> 4Q22 | M44: =M7 -> 1Q23 | N44: =N7 -> 2Q23 | O44: =O7 -> 3Q23 | P44: =P7 -> 4Q23 | ... W44: =W7 -> 3Q25 | Y44: =Y7 -> 1Q22 | Z44: =Z7 -> 2Q22 | AA44: =AA7 -> 3Q22 | AB44: =AB7 -> 4Q22 | AC44: =AC7 -> 1Q23 | AD44: =AD7 -> 2Q23 | AE44: =AE7 -> 3Q23 | AF44: =AF7 -> 4Q23 | ... AM44: =AM7 -> 3Q25
B45: =B8 -> Fiscal Period End Date | C45: =C8 -> 44196 | D45: =D8 -> 44561 | E45: =E8 -> 44926 | F45: =F8 -> 45291 | G45: =G8 -> 45657 | I45: =I8 -> 44651 | J45: =J8 -> 44742 | K45: =K8 -> 44834 | L45: =L8 -> 44926 | M45: =M8 -> 45016 | N45: =N8 -> 45107 | O45: =O8 -> 45199 | P45: =P8 -> 45291 | ... W45: =W8 -> 45930 | Y45: =Y8 -> 44651 | Z45: =Z8 -> 44742 | AA45: =AA8 -> 44834 | AB45: =AB8 -> 44926 | AC45: =AC8 -> 45016 | AD45: =AD8 -> 45107 | AE45: =AE8 -> 45199 | AF45: =AF8 -> 45291 | ... AM45: =AM8 -> 45930
B47: Current Assets
B48: Cash and cash equivalents | C48: 6707 | D48: 7116 | E48: 2773 | F48: 8450 | G48: 7849 | I48: 6607 | J48: 7173 | K48: 2676 | L48: =E48 -> 2773 | M48: 4808 | N48: 3488 | O48: 6087 | P48: =F48 -> 8450 | Q48: 8133 | R48: 9219 | S48: 7770 | T48: =G48 -> 7849 | Y48: =I48 -> 6607 | Z48: =J48 -> 7173 | AA48: =K48 -> 2676 | AB48: =L48 -> 2773 | AC48: =M48 -> 4808 | AD48: =N48 -> 3488 | AE48: =O48 -> 6087 | AF48: =P48 -> 8450 | ... AM48: =W48 -> 0 | AO48: =SUM(AM48/AI48)-1 -> -1
B49: Marketable securities | C49: 4507 | D49: 5298 | E49: 3609 | F49: 2874 | G49: 5451 | I49: 4703 | J49: 4373 | K49: 4172 | L49: =E49 -> 3609 | M49: 3430 | N49: 3188 | O49: 2544 | P49: =F49 -> 2874 | Q49: 3921 | R49: 4632 | S49: 5262 | T49: =G49 -> 5451
B50: Accounts receivable, net | C50: 4003 | D50: 3579 | E50: 5643 | F50: 3183 | G50: 3929 | I50: 4032 | J50: 4084 | K50: 3804 | L50: =E50 -> 5643 | M50: 3960 | N50: 3691 | O50: 3850 | P50: =F50 -> 3183 | Q50: 3513 | R50: 3054 | S50: 2948 | T50: =G50 -> 3929
B51: Inventories | C51: 2598 | D51: 3228 | E51: 6341 | F51: 6422 | G51: 6423 | I51: 3861 | J51: 4555 | K51: 5418 | L51: =E51 -> 6341 | M51: 6932 | N51: 6858 | O51: 6628 | P51: =F51 -> 6422 | Q51: 6247 | R51: 6087 | S51: 6020 | T51: =G51 -> 6423
B52: Held for sale assets | C52: 0 | D52: 0 | E52: 733 | F52: 341 | G52: 0 | I52: 0 | J52: 0 | K52: 950 | L52: =E52 -> 733 | M52: 721 | N52: 816 | O52: 317 | P52: =F52 -> 341 | Q52: 337 | R52: 0 | S52: 0 | T52: =G52 -> 0
B53: Other current assets | C53: 704 | D53: 854 | E53: 1625 | F53: 1194 | G53: 1579 | I53: 1019 | J53: 1425 | K53: 1979 | L53: =E53 -> 1625 | M53: 1247 | N53: 1032 | O53: 1050 | P53: =F53 -> 1194 | Q53: 1288 | R53: 1240 | S53: 1332 | T53: =G53 -> 1579
B54: Total Current Assets | C54: =SUM(C48:C53) -> 18519 | D54: =SUM(D48:D53) -> 20075 | E54: =SUM(E48:E53) -> 20724 | F54: =SUM(F48:F53) -> 22464 | G54: =SUM(G48:G53) -> 25231 | I54: =SUM(I48:I53) -> 20222 | J54: =SUM(J48:J53) -> 21610 | K54: =SUM(K48:K53) -> 18999 | L54: =SUM(L48:L53) -> 20724 | M54: =SUM(M48:M53) -> 21098 | N54: =SUM(N48:N53) -> 19073 | O54: =SUM(O48:O53) -> 20476 | P54: =SUM(P48:P53) -> 22464 | ... W54: =SUM(W48:W53) -> 0 | Y54: =SUM(Y48:Y53) -> 6607 | Z54: =SUM(Z48:Z53) -> 7173 | AA54: =SUM(AA48:AA53) -> 2676 | AB54: =SUM(AB48:AB53) -> 2773 | AC54: =SUM(AC48:AC53) -> 4808 | AD54: =SUM(AD48:AD53) -> 3488 | AE54: =SUM(AE48:AE53) -> 6087 | AF54: =SUM(AF48:AF53) -> 8450 | ... AM54: =SUM(AM48:AM53) -> 0 | AO54: =SUM(AM54/AI54)-1 -> -1
B56: Non-Current Assets
B57: Deferred tax assets | C57: 1351 | D57: 1591 | E57: 1803 | F57: 3310 | G57: 5162 | I57: 1454 | J57: 1545 | K57: 1778 | L57: =E57 -> 1803 | M57: 2092 | N57: 2477 | O57: 2773 | P57: =F57 -> 3310 | Q57: 3579 | R57: 3978 | S57: 4420 | T57: =G57 -> 5162 | Y57: =I57 -> 1454 | Z57: =J57 -> 1545 | AA57: =K57 -> 1778 | AB57: =L57 -> 1803 | AC57: =M57 -> 2092 | AD57: =N57 -> 2477 | AE57: =O57 -> 2773 | AF57: =P57 -> 3310 | ... AM57: =W57 -> 0 | AO57: =SUM(AM57/AI57)-1 -> -1
B58: Property, plant and equipment, net | C58: 3711 | D58: 4559 | E58: 5168 | F58: 5042 | G58: 4665 | I58: 4723 | J58: 4893 | K58: 5038 | L58: =E58 -> 5168 | M58: 5215 | N58: 5281 | O58: 5216 | P58: =F58 -> 5042 | Q58: 4907 | R58: 4724 | S58: 4744 | T58: =G58 -> 4665
B59: Goodwill | C59: 6323 | D59: 7246 | E59: 10508 | F59: 10642 | G59: 10799 | I59: 7264 | J59: 7261 | K59: 10719 | L59: =E59 -> 10508 | M59: 10566 | N59: 10579 | O59: 10591 | P59: =F59 -> 10642 | Q59: 10722 | R59: 10760 | S59: 10770 | T59: =G59 -> 10799
B60: Other intangible assets, net | C60: 1653 | D60: 1458 | E60: 1882 | F60: 1408 | G60: 1244 | I60: 1373 | J60: 1258 | K60: 1954 | L60: =E60 -> 1882 | M60: 1796 | N60: 1727 | O60: 1618 | P60: =F60 -> 1408 | Q60: 1387 | R60: 1331 | S60: 1296 | T60: =G60 -> 1244
B61: Held for sale assets | C61: 0 | D61: 0 | E61: 1200 | F61: 88 | G61: 0 | I61: 0 | J61: 0 | K61: 916 | L61: =E61 -> 1200 | M61: 1199 | N61: 1251 | O61: 218 | P61: =F61 -> 88 | Q61: 69 | R61: 0 | S61: 0 | T61: =G61 -> 0
B62: Other assets | C62: 4037 | D62: 6311 | E62: 7729 | F62: 8086 | G62: 8053 | I62: 7784 | J62: 7735 | K62: 7616 | L62: =E62 -> 7729 | M62: 8048 | N62: 7974 | O62: 8110 | P62: =F62 -> 8086 | Q62: 8032 | R62: 8142 | S62: 8179 | T62: =G62 -> 8053
B63: Total Assets | C63: =SUM(C57:C62)+C54 -> 35594 | D63: =SUM(D57:D62)+D54 -> 41240 | E63: =SUM(E57:E62)+E54 -> 49014 | F63: =SUM(F57:F62)+F54 -> 51040 | G63: =SUM(G57:G62)+G54 -> 55154 | I63: =SUM(I57:I62)+I54 -> 42820 | J63: =SUM(J57:J62)+J54 -> 44302 | K63: =SUM(K57:K62)+K54 -> 47020 | L63: =SUM(L57:L62)+L54 -> 49014 | M63: =SUM(M57:M62)+M54 -> 50014 | N63: =SUM(N57:N62)+N54 -> 48362 | O63: =SUM(O57:O62)+O54 -> 49002 | P63: =SUM(P57:P62)+P54 -> 51040 | ... W63: =SUM(W57:W62)+W54 -> 0 | Y63: =SUM(Y57:Y62)+Y54 -> 8061 | Z63: =SUM(Z57:Z62)+Z54 -> 8718 | AA63: =SUM(AA57:AA62)+AA54 -> 4454 | AB63: =SUM(AB57:AB62)+AB54 -> 4576 | AC63: =SUM(AC57:AC62)+AC54 -> 6900 | AD63: =SUM(AD57:AD62)+AD54 -> 5965 | AE63: =SUM(AE57:AE62)+AE54 -> 8860 | AF63: =SUM(AF57:AF62)+AF54 -> 11760 | ... AM63: =SUM(AM57:AM62)+AM54 -> 0 | AO63: =SUM(AM63/AI63)-1 -> -1
B65: Current Liabilities
B66: Trade accounts payable | C66: 2248 | D66: 2750 | E66: 3796 | F66: 1912 | G66: 2584 | I66: 3526 | J66: 3724 | K66: 3752 | L66: =E66 -> 3796 | M66: 2562 | N66: 1430 | O66: 1744 | P66: =F66 -> 1912 | Q66: 2147 | R66: 2314 | S66: 2586 | T66: =G66 -> 2584 | Y66: =I66 -> 3526 | Z66: =J66 -> 3724 | AA66: =K66 -> 3752 | AB66: =L66 -> 3796 | AC66: =M66 -> 2562 | AD66: =N66 -> 1430 | AE66: =O66 -> 1744 | AF66: =P66 -> 1912 | ... AM66: =W66 -> 0 | AO66: =SUM(AM66/AI66)-1 -> -1
B67: Payroll and other benefits related liabilities | C67: 1053 | D67: 1531 | E67: 1486 | F67: 1685 | G67: 1834 | I67: 1440 | J67: 1124 | K67: 1578 | L67: =E67 -> 1486 | M67: 1460 | N67: 1227 | O67: 1546 | P67: =F67 -> 1685 | Q67: 1757 | R67: 1253 | S67: 1780 | T67: =G67 -> 1834
B68: Unearned revenues | C68: 568 | D68: 612 | E68: 369 | F68: 293 | G68: 297 | I68: 604 | J68: 534 | K68: 463 | L68: =E68 -> 369 | M68: 289 | N68: 277 | O68: 249 | P68: =F68 -> 293 | Q68: 210 | R68: 253 | S68: 263 | T68: =G68 -> 297 | Y68: =I68 -> 604 | Z68: =J68 -> 534 | AA68: =K68 -> 463 | AB68: =L68 -> 369 | AC68: =M68 -> 289 | AD68: =N68 -> 277 | AE68: =O68 -> 249 | AF68: =P68 -> 293 | ... AM68: =W68 -> 0 | AO68: =SUM(AM68/AI68)-1 -> -1
B69: Short-term debt | C69: 500 | D69: 2044 | E69: 1945 | F69: 914 | G69: 1364 | I69: 2042 | J69: 3485 | K69: 1945 | L69: =E69 -> 1945 | M69: 1446 | N69: 499 | O69: 914 | P69: =F69 -> 914 | Q69: 914 | R69: 914 | S69: 1364 | T69: =G69 -> 1364 | Y69: =I69 -> 2042 | Z69: =J69 -> 3485 | AA69: =K69 -> 1945 | AB69: =L69 -> 1945 | AC69: =M69 -> 1446 | AD69: =N69 -> 499 | AE69: =O69 -> 914 | AF69: =P69 -> 914 | ... AM69: =W69 -> 0 | AO69: =SUM(AM69/AI69)-1 -> -1
B70: Held for sale liabilities | C70: 0 | D70: 0 | E70: 581 | F70: 333 | G70: 0 | I70: 0 | J70: 0 | K70: 677 | L70: =E70 -> 581 | M70: 646 | N70: 648 | O70: 300 | P70: =F70 -> 333 | Q70: 336 | R70: 0 | S70: 0 | T70: =G70 -> 0 | Y70: =I70 -> 0 | Z70: =J70 -> 0 | AA70: =K70 -> 677 | AB70: =L70 -> 581 | AC70: =M70 -> 646 | AD70: =N70 -> 648 | AE70: =O70 -> 300 | AF70: =P70 -> 333 | ... AM70: =W70 -> 0 | AO70: =SUM(AM70/AI70)-1 -> #DIV/0!
B71: Other current liabilities | C71: 4303 | D71: 5014 | E71: 3689 | F71: 4491 | G71: 4425 | I71: 4661 | J71: 4565 | K71: 3414 | L71: =E71 -> 3689 | M71: 3678 | N71: 3785 | O71: 3710 | P71: =F71 -> 4491 | Q71: 3805 | R71: 4409 | S71: 3754 | T71: =G71 -> 4425 | Y71: =I71 -> 4661 | Z71: =J71 -> 4565 | AA71: =K71 -> 3414 | AB71: =L71 -> 3689 | AC71: =M71 -> 3678 | AD71: =N71 -> 3785 | AE71: =O71 -> 3710 | AF71: =P71 -> 4491 | ... AM71: =W71 -> 0 | AO71: =SUM(AM71/AI71)-1 -> -1
B72: Total Current Liabilities | C72: =SUM(C66:C71) -> 8672 | D72: =SUM(D66:D71) -> 11951 | E72: =SUM(E66:E71) -> 11866 | F72: =SUM(F66:F71) -> 9628 | G72: =SUM(G66:G71) -> 10504 | I72: =SUM(I66:I71) -> 12273 | J72: =SUM(J66:J71) -> 13432 | K72: =SUM(K66:K71) -> 11829 | L72: =SUM(L66:L71) -> 11866 | M72: =SUM(M66:M71) -> 10081 | N72: =SUM(N66:N71) -> 7866 | O72: =SUM(O66:O71) -> 8463 | P72: =SUM(P66:P71) -> 9628 | ... W72: =SUM(W66:W71) -> 0 | Y72: =SUM(Y66:Y71) -> 10833 | Z72: =SUM(Z66:Z71) -> 12308 | AA72: =SUM(AA66:AA71) -> 10251 | AB72: =SUM(AB66:AB71) -> 10380 | AC72: =SUM(AC66:AC71) -> 8621 | AD72: =SUM(AD66:AD71) -> 6639 | AE72: =SUM(AE66:AE71) -> 6917 | AF72: =SUM(AF66:AF71) -> 7943 | ... AM72: =SUM(AM66:AM71) -> 0 | AO72: =SUM(AM72/AI72)-1 -> -1
B74: Non-Current Liabilities
B75: Unearned revenues | C75: 761 | D75: 364 | E75: 144 | F75: 99 | G75: 88 | I75: 257 | J75: 228 | K75: 180 | L75: =E75 -> 144 | M75: 105 | N75: 104 | O75: 92 | P75: =F75 -> 99 | Q75: 93 | R75: 135 | S75: 108 | T75: =G75 -> 88 | Y75: =I75 -> 257 | Z75: =J75 -> 228 | AA75: =K75 -> 180 | AB75: =L75 -> 144 | AC75: =M75 -> 105 | AD75: =N75 -> 104 | AE75: =O75 -> 92 | AF75: =P75 -> 99 | ... AM75: =W75 -> 0 | AO75: =SUM(AM75/AI75)-1 -> -1
B76: Income taxes payable | C76: 1872 | D76: 1713 | E76: 1472 | F76: 0 | G76: 0 | I76: 1687 | J76: 1479 | K76: 1480 | L76: =E76 -> 1472 | M76: 1472 | N76: 1084 | O76: 1098 | P76: =F76 -> 0 | Q76: 1056 | R76: 526 | S76: 526 | T76: =G76 -> 0
B77: Long-term debt | C77: 15226 | D77: 13701 | E77: 13537 | F77: 14484 | G77: 13270 | I77: 13708 | J77: 12195 | K77: 13600 | L77: =E77 -> 13537 | M77: 15431 | N77: 15486 | O77: 14530 | P77: =F77 -> 14484 | Q77: 14566 | R77: 14543 | S77: 13190 | T77: =G77 -> 13270
B78: Held for sale liabilities | C78: 0 | D78: 0 | E78: 119 | F78: 38 | G78: 0 | I78: 0 | J78: 0 | K78: 128 | L78: =E78 -> 119 | M78: 111 | N78: 116 | O78: 36 | P78: =F78 -> 38 | Q78: 43 | R78: 0 | S78: 0 | T78: =G78 -> 0
B79: Other liabilities | C79: 2986 | D79: 3561 | E79: 3863 | F79: 5210 | G79: 5018 | I79: 3562 | J79: 3640 | K79: 3755 | L79: =E79 -> 3863 | M79: 4004 | N79: 4008 | O79: 4113 | P79: =F79 -> 5210 | Q79: 4150 | R79: 4351 | S79: 4500 | T79: =G79 -> 5018 | Y79: =I79 -> 3562 | Z79: =J79 -> 3640 | AA79: =K79 -> 3755 | AB79: =L79 -> 3863 | AC79: =M79 -> 4004 | AD79: =N79 -> 4008 | AE79: =O79 -> 4113 | AF79: =P79 -> 5210 | ... AM79: =W79 -> 0 | AO79: =SUM(AM79/AI79)-1 -> -1
B80: Total Liabilities | C80: =SUM(C75:C79)+C72 -> 29517 | D80: =SUM(D75:D79)+D72 -> 31290 | E80: =SUM(E75:E79)+E72 -> 31001 | F80: =SUM(F75:F79)+F72 -> 29459 | G80: =SUM(G75:G79)+G72 -> 28880 | I80: =SUM(I75:I79)+I72 -> 31487 | J80: =SUM(J75:J79)+J72 -> 30974 | K80: =SUM(K75:K79)+K72 -> 30972 | L80: =SUM(L75:L79)+L72 -> 31001 | M80: =SUM(M75:M79)+M72 -> 31204 | N80: =SUM(N75:N79)+N72 -> 28664 | O80: =SUM(O75:O79)+O72 -> 28332 | P80: =SUM(P75:P79)+P72 -> 29459 | ... W80: =SUM(W75:W79)+W72 -> 0 | Y80: =SUM(Y75:Y79)+Y72 -> 14652 | Z80: =SUM(Z75:Z79)+Z72 -> 16176 | AA80: =SUM(AA75:AA79)+AA72 -> 14186 | AB80: =SUM(AB75:AB79)+AB72 -> 14387 | AC80: =SUM(AC75:AC79)+AC72 -> 12730 | AD80: =SUM(AD75:AD79)+AD72 -> 10751 | AE80: =SUM(AE75:AE79)+AE72 -> 11122 | AF80: =SUM(AF75:AF79)+AF72 -> 13252 | ... AM80: =SUM(AM75:AM79)+AM72 -> 0 | AO80: =SUM(AM80/AI80)-1 -> -1
B82: Preferred stock | C82: 0 | D82: 0 | E82: 0 | F82: 0 | G82: 0 | I82: 0 | J82: 0 | K82: 0 | L82: =E82 -> 0 | M82: 0 | N82: 0 | O82: 0 | P82: =F82 -> 0 | Q82: 0 | R82: 0 | S82: 0 | T82: =G82 -> 0 | Y82: =I82 -> 0 | Z82: =J82 -> 0 | AA82: =K82 -> 0 | AB82: =L82 -> 0 | AC82: =M82 -> 0 | AD82: =N82 -> 0 | AE82: =O82 -> 0 | AF82: =P82 -> 0 | ... AM82: =W82 -> 0 | AO82: =SUM(AM82/AI82)-1 -> #DIV/0!
B83: Common stock | C83: 586 | D83: 0 | E83: 195 | F83: 490 | G83: 0 | I83: 0 | J83: 0 | K83: 0 | L83: =E83 -> 195 | M83: 0 | N83: 0 | O83: 77 | P83: =F83 -> 490 | Q83: 0 | R83: 66 | S83: 0 | T83: =G83 -> 0 | Y83: =I83 -> 0 | Z83: =J83 -> 0 | AA83: =K83 -> 0 | AB83: =L83 -> 195 | AC83: =M83 -> 0 | AD83: =N83 -> 0 | AE83: =O83 -> 77 | AF83: =P83 -> 490 | ... AM83: =W83 -> 0 | AO83: =SUM(AM83/AI83)-1 -> #DIV/0!
B84: Retained earnings | C84: 5284 | D84: 9822 | E84: 17840 | F84: 20733 | G84: 25687 | I84: 11275 | J84: 13113 | K84: 15830 | L84: =E84 -> 17840 | M84: 18517 | N84: 19280 | O84: 20163 | P84: =F84 -> 20733 | Q84: 22565 | R84: 23965 | S84: 24273 | T84: =G84 -> 25687 | Y84: =I84 -> 11275 | Z84: =J84 -> 13113 | AA84: =K84 -> 15830 | AB84: =L84 -> 17840 | AC84: =M84 -> 18517 | AD84: =N84 -> 19280 | AE84: =O84 -> 20163 | AF84: =P84 -> 20733 | ... AM84: =W84 -> 0 | AO84: =SUM(AM84/AI84)-1 -> -1
B85: Accumulated other comprehensive income | C85: 207 | D85: 128 | E85: -22 | F85: 358 | G85: 587 | I85: 58 | J85: 215 | K85: 218 | L85: =E85 -> -22 | M85: 293 | N85: 418 | O85: 430 | P85: =F85 -> 358 | Q85: 493 | R85: 438 | S85: 397 | T85: =G85 -> 587 | Y85: =I85 -> 58 | Z85: =J85 -> 215 | AA85: =K85 -> 218 | AB85: =L85 -> -22 | AC85: =M85 -> 293 | AD85: =N85 -> 418 | AE85: =O85 -> 430 | AF85: =P85 -> 358 | ... AM85: =W85 -> 0 | AO85: =SUM(AM85/AI85)-1 -> -1
B86: Total stockholders' equity | C86: =SUM(C82:C85) -> 6077 | D86: =SUM(D82:D85) -> 9950 | E86: =SUM(E82:E85) -> 18013 | F86: =SUM(F82:F85) -> 21581 | G86: =SUM(G82:G85) -> 26274 | I86: =SUM(I82:I85) -> 11333 | J86: =SUM(J82:J85) -> 13328 | K86: =SUM(K82:K85) -> 16048 | L86: =SUM(L82:L85) -> 18013 | M86: =SUM(M82:M85) -> 18810 | N86: =SUM(N82:N85) -> 19698 | O86: =SUM(O82:O85) -> 20670 | P86: =SUM(P82:P85) -> 21581 | ... W86: =SUM(W82:W85) -> 0 | Y86: =SUM(Y82:Y85) -> 11333 | Z86: =SUM(Z82:Z85) -> 13328 | AA86: =SUM(AA82:AA85) -> 16048 | AB86: =SUM(AB82:AB85) -> 18013 | AC86: =SUM(AC82:AC85) -> 18810 | AD86: =SUM(AD82:AD85) -> 19698 | AE86: =SUM(AE82:AE85) -> 20670 | AF86: =SUM(AF82:AF85) -> 21581 | ... AM86: =SUM(AM82:AM85) -> 0 | AO86: =SUM(AM86/AI86)-1 -> -1
B87: Total liabilities and stockholders' equity | C87: =SUM(C86+C80) -> 35594 | D87: =SUM(D86+D80) -> 41240 | E87: =SUM(E86+E80) -> 49014 | F87: =SUM(F86+F80) -> 51040 | G87: =SUM(G86+G80) -> 55154 | I87: =SUM(I86+I80) -> 42820 | J87: =SUM(J86+J80) -> 44302 | K87: =SUM(K86+K80) -> 47020 | L87: =SUM(L86+L80) -> 49014 | M87: =SUM(M86+M80) -> 50014 | N87: =SUM(N86+N80) -> 48362 | O87: =SUM(O86+O80) -> 49002 | P87: =SUM(P86+P80) -> 51040 | ... W87: =SUM(W86+W80) -> 0 | Y87: =SUM(Y86+Y80) -> 25985 | Z87: =SUM(Z86+Z80) -> 29504 | AA87: =SUM(AA86+AA80) -> 30234 | AB87: =SUM(AB86+AB80) -> 32400 | AC87: =SUM(AC86+AC80) -> 31540 | AD87: =SUM(AD86+AD80) -> 30449 | AE87: =SUM(AE86+AE80) -> 31792 | AF87: =SUM(AF86+AF80) -> 34833 | ... AM87: =SUM(AM86+AM80) -> 0 | AO87: =SUM(AM87/AI87)-1 -> -1
B89: Balance Check | C89: =C87-C63 -> 0 | D89: =D87-D63 -> 0 | E89: =E87-E63 -> 0 | F89: =F87-F63 -> 0 | G89: =G87-G63 -> 0 | I89: =I87-I63 -> 0 | J89: =J87-J63 -> 0 | K89: =K87-K63 -> 0 | L89: =L87-L63 -> 0 | M89: =M87-M63 -> 0 | N89: =N87-N63 -> 0 | O89: =O87-O63 -> 0 | P89: =P87-P63 -> 0 | ... W89: =W87-W63 -> 0 | Y89: =Y87-Y63 -> 17924 | Z89: =Z87-Z63 -> 20786 | AA89: =AA87-AA63 -> 25780 | AB89: =AB87-AB63 -> 27824 | AC89: =AC87-AC63 -> 24640 | AD89: =AD87-AD63 -> 24484 | AE89: =AE87-AE63 -> 22932 | AF89: =AF87-AF63 -> 23073 | ... AM89: =AM87-AM63 -> 0
A92: X | B92: Cash-Flows Statement | AH92: LTM | AO92: Variance
B93: =B7 -> Fiscal Period | C93: =C7 -> 2020 | D93: =D7 -> 2021 | E93: =E7 -> 2022 | F93: =F7 -> 2023 | G93: =G7 -> 2024 | I93: =I7 -> 1Q22 | J93: =J7 -> 2Q22 | K93: =K7 -> 3Q22 | L93: =L7 -> 4Q22 | M93: =M7 -> 1Q23 | N93: =N7 -> 2Q23 | O93: =O7 -> 3Q23 | P93: =P7 -> 4Q23 | ... W93: =W7 -> 3Q25 | Y93: =Y7 -> 1Q22 | Z93: =Z7 -> 2Q22 | AA93: =AA7 -> 3Q22 | AB93: =AB7 -> 4Q22 | AC93: =AC7 -> 1Q23 | AD93: =AD7 -> 2Q23 | AE93: =AE7 -> 3Q23 | AF93: =AF7 -> 4Q23 | ... AM93: =AM7 -> 3Q25
B94: =B8 -> Fiscal Period End Date | C94: =C8 -> 44196 | D94: =D8 -> 44561 | E94: =E8 -> 44926 | F94: =F8 -> 45291 | G94: =G8 -> 45657 | I94: =I8 -> 44651 | J94: =J8 -> 44742 | K94: =K8 -> 44834 | L94: =L8 -> 44926 | M94: =M8 -> 45016 | N94: =N8 -> 45107 | O94: =O8 -> 45199 | P94: =P8 -> 45291 | ... W94: =W8 -> 45930 | Y94: =Y8 -> 44651 | Z94: =Z8 -> 44742 | AA94: =AA8 -> 44834 | AB94: =AB8 -> 44926 | AC94: =AC8 -> 45016 | AD94: =AD8 -> 45107 | AE94: =AE8 -> 45199 | AF94: =AF8 -> 45291 | ... AM94: =AM8 -> 45930
B96: Cash-Flows From Operating Activities
B97: Net income (loss) | C97: =C30 -> 5198 | D97: =D30 -> 9043 | E97: =E30 -> 12986 | F97: =F30 -> 7339 | G97: =G30 -> 10110 | I97: =I30 -> 3399 | J97: =J30 -> 2934 | K97: =K30 -> 3730 | L97: =L30 -> 2923 | M97: =M30 -> 2273 | N97: =N30 -> 1702 | O97: =O30 -> 1735 | P97: =P30 -> 1629 | ... W97: =W30 -> 0 | Y97: =SUM(I97:I97) -> 3399 | Z97: =SUM(I97:J97) -> 6333 | AA97: =SUM(I97:K97) -> 10063 | AB97: =SUM(I97:L97) -> 12986 | AC97: =SUM(J97:M97) -> 11860 | AD97: =SUM(K97:N97) -> 10628 | AE97: =SUM(L97:O97) -> 8633 | AF97: =SUM(M97:P97) -> 7339 | AG97: =SUM(N97:Q97) -> 7877 | AH97: =SUM(O97:R97) -> 8450 | AI97: =SUM(P97:S97) -> 8823 | ... AM97: =SUM(T97:W97) -> 2916 | AO97: =SUM(AM97/AI97)-1 -> -0.66950017
B99: Adjustments to reconcile net income:
B100: Depreciation and amortization expense | C100: 1393 | D100: 1582 | E100: 1762 | F100: 1809 | G100: 1706 | I100: 406 | J100: =834-I100 -> 428 | K100: 1272 | L100: =SUM(E100-SUM(I100:K100)) -> -344 | M100: 398 | N100: =868-M100 -> 470 | O100: =1347-N100-M100 -> 479 | P100: =SUM(F100-SUM(M100:O100)) -> 462 | Q100: 437 | R100: =848-Q100 -> 411 | S100: =1267-R100-Q100 -> 419 | T100: =SUM(G100-SUM(Q100:S100)) -> 439 | Y100: =SUM(I100:I100) -> 406 | Z100: =SUM(I100:J100) -> 834 | AA100: =SUM(I100:K100) -> 2106 | AB100: =SUM(I100:L100) -> 1762 | AC100: =SUM(J100:M100) -> 1754 | AD100: =SUM(K100:N100) -> 1796 | AE100: =SUM(L100:O100) -> 1003 | AF100: =SUM(M100:P100) -> 1809 | AG100: =SUM(N100:Q100) -> 1848 | AH100: =SUM(O100:R100) -> 1789 | AI100: =SUM(P100:S100) -> 1729 | ... AM100: =SUM(T100:W100) -> 439 | AO100: =SUM(AM100/AI100)-1 -> -0.74609601
B101: Indefinite and long-lived asset impairment charges | C101: 0 | D101: 0 | E101: 2 | F101: 182 | G101: 7 | I101: 0 | J101: =0-I101 -> 0 | K101: 0 | L101: =SUM(E101-SUM(I101:K101)) -> 2 | M101: 0 | N101: =0-M101 -> 0 | O101: 0 | P101: =SUM(F101-SUM(M101:O101)) -> 182 | R101: =0-Q101 -> 0 | S101: =0-R101-Q101 -> 0 | T101: =SUM(G101-SUM(Q101:S101)) -> 7 | Y101: =SUM(I101:I101) -> 0 | Z101: =SUM(I101:J101) -> 0 | AA101: =SUM(I101:K101) -> 0 | AB101: =SUM(I101:L101) -> 2 | AC101: =SUM(J101:M101) -> 2 | AD101: =SUM(K101:N101) -> 2 | AE101: =SUM(L101:O101) -> 2 | AF101: =SUM(M101:P101) -> 182 | AG101: =SUM(N101:Q101) -> 182 | AH101: =SUM(O101:R101) -> 182 | AI101: =SUM(P101:S101) -> 182 | ... AM101: =SUM(T101:W101) -> 7 | AO101: =SUM(AM101/AI101)-1 -> -0.96153846
B102: Income tax provision less than income tax payments | C102: -309 | D102: -245 | E102: -138 | F102: -1269 | G102: -3064 | I102: 272 | J102: =-403-I102 -> -675 | K102: -234 | L102: =SUM(E102-SUM(I102:K102)) -> 499 | M102: -120 | N102: =-631-M102 -> -511 | O102: =-836-N102-M102 -> -205 | P102: =SUM(F102-SUM(M102:O102)) -> -433 | Q102: -1012 | R102: =-1764-Q102 -> -752 | S102: =-2538-R102-Q102 -> -774 | T102: =SUM(G102-SUM(Q102:S102)) -> -526 | Y102: =SUM(I102:I102) -> 272 | Z102: =SUM(I102:J102) -> -403 | AA102: =SUM(I102:K102) -> -637 | AB102: =SUM(I102:L102) -> -138 | AC102: =SUM(J102:M102) -> -530 | AD102: =SUM(K102:N102) -> -366 | AE102: =SUM(L102:O102) -> -337 | AF102: =SUM(M102:P102) -> -1269 | AG102: =SUM(N102:Q102) -> -2161 | AH102: =SUM(O102:R102) -> -2402 | AI102: =SUM(P102:S102) -> -2971 | ... AM102: =SUM(T102:W102) -> -526 | AO102: =SUM(AM102/AI102)-1 -> -0.82295523
B103: Share-based compensation expense | C103: 1212 | D103: 1663 | E103: 2031 | F103: 2484 | G103: 2648 | I103: 496 | J103: =994-I103 -> 498 | K103: 1510 | L103: =SUM(E103-SUM(I103:K103)) -> -473 | M103: 634 | N103: =1262-M103 -> 628 | O103: =1876-N103-M103 -> 614 | P103: =SUM(F103-SUM(M103:O103)) -> 608 | Q103: 602 | R103: =1307-Q103 -> 705 | S103: =1951-R103-Q103 -> 644 | T103: =SUM(G103-SUM(Q103:S103)) -> 697 | Y103: =SUM(I103:I103) -> 496 | Z103: =SUM(I103:J103) -> 994 | AA103: =SUM(I103:K103) -> 2504 | AB103: =SUM(I103:L103) -> 2031 | AC103: =SUM(J103:M103) -> 2169 | AD103: =SUM(K103:N103) -> 2299 | AE103: =SUM(L103:O103) -> 1403 | AF103: =SUM(M103:P103) -> 2484 | AG103: =SUM(N103:Q103) -> 2452 | AH103: =SUM(O103:R103) -> 2529 | AI103: =SUM(P103:S103) -> 2559 | ... AM103: =SUM(T103:W103) -> 697 | AO103: =SUM(AM103/AI103)-1 -> -0.72762798
B104: Net (gains) losses on marketable securities and other investments | C104: -336 | D104: -1002 | E104: 432 | F104: -152 | G104: -349 | I104: -103 | J104: =213-I104 -> 316 | K104: 374 | L104: =SUM(E104-SUM(I104:K104)) -> -155 | M104: -25 | N104: =-45-M104 -> -20 | O104: =-84-N104-M104 -> -39 | P104: =SUM(F104-SUM(M104:O104)) -> -68 | Q104: -71 | R104: =-273-Q104 -> -202 | S104: =-314-R104-Q104 -> -41 | T104: =SUM(G104-SUM(Q104:S104)) -> -35 | Y104: =SUM(I104:I104) -> -103 | Z104: =SUM(I104:J104) -> 213 | AA104: =SUM(I104:K104) -> 587 | AB104: =SUM(I104:L104) -> 432 | AC104: =SUM(J104:M104) -> 510 | AD104: =SUM(K104:N104) -> 174 | AE104: =SUM(L104:O104) -> -239 | AF104: =SUM(M104:P104) -> -152 | AG104: =SUM(N104:Q104) -> -198 | AH104: =SUM(O104:R104) -> -380 | AI104: =SUM(P104:S104) -> -382 | ... AM104: =SUM(T104:W104) -> -35 | AO104: =SUM(AM104/AI104)-1 -> -0.90837696
B105: Impairment losses on other investments | C105: 405 | D105: 33 | E105: 47 | F105: 132 | G105: 79 | I105: 0 | J105: =0-I105 -> 0 | K105: 0 | L105: =SUM(E105-SUM(I105:K105)) -> 47 | M105: 0 | N105: =101-M105 -> 101 | O105: =120-N105-M105 -> 19 | P105: =SUM(F105-SUM(M105:O105)) -> 12 | R105: =62-Q105 -> 62 | S105: =66-R105-Q105 -> 4 | T105: =SUM(G105-SUM(Q105:S105)) -> 13 | Y105: =SUM(I105:I105) -> 0 | Z105: =SUM(I105:J105) -> 0 | AA105: =SUM(I105:K105) -> 0 | AB105: =SUM(I105:L105) -> 47 | AC105: =SUM(J105:M105) -> 47 | AD105: =SUM(K105:N105) -> 148 | AE105: =SUM(L105:O105) -> 167 | AF105: =SUM(M105:P105) -> 132 | AG105: =SUM(N105:Q105) -> 132 | AH105: =SUM(O105:R105) -> 93 | AI105: =SUM(P105:S105) -> 78 | ... AM105: =SUM(T105:W105) -> 13 | AO105: =SUM(AM105/AI105)-1 -> -0.83333333
B106: Other items, net | C106: -142 | D106: -77 | E106: -56 | F106: 25 | G106: -67 | I106: -25 | J106: =-35-I106 -> -10 | K106: 0 | L106: =SUM(E106-SUM(I106:K106)) -> -21 | M106: -33 | N106: =16-M106 -> 49 | O106: =23-N106-M106 -> 7 | P106: =SUM(F106-SUM(M106:O106)) -> 2 | Q106: 9 | R106: =-30-Q106 -> -39 | S106: =-63-R106-Q106 -> -33 | T106: =SUM(G106-SUM(Q106:S106)) -> -4 | Y106: =SUM(I106:I106) -> -25 | Z106: =SUM(I106:J106) -> -35 | AA106: =SUM(I106:K106) -> -35 | AB106: =SUM(I106:L106) -> -56 | AC106: =SUM(J106:M106) -> -64 | AD106: =SUM(K106:N106) -> -5 | AE106: =SUM(L106:O106) -> 2 | AF106: =SUM(M106:P106) -> 25 | AG106: =SUM(N106:Q106) -> 67 | AH106: =SUM(O106:R106) -> -21 | AI106: =SUM(P106:S106) -> -61 | ... AM106: =SUM(T106:W106) -> -4 | AO106: =SUM(AM106/AI106)-1 -> -0.93442623
B107: Net cash used by operating activities from discontinued operations | C107: 0 | D107: 0 | E107: -170 | F107: -399 | G107: -91 | I107: 0 | J107: 0 | K107: 0 | L107: =SUM(E107-SUM(I107:K107)) -> -170 | M107: -28 | N107: -33 | O107: -333 | P107: =SUM(F107-SUM(M107:O107)) -> -5 | Q107: =-91-P107 -> -86 | R107: =-91-Q107-P107 -> 0 | S107: =SUM(F107-SUM(P107:R107)) -> -308 | T107: =SUM(G107-SUM(Q107:S107)) -> 303
B108: Changes in assets and liabilities:
B109: Accounts receivable, net | C109: -1529 | D109: 426 | E109: -2066 | F109: 2472 | G109: -768 | I109: -454 | J109: =-501-I109 -> -47 | K109: -216 | L109: =SUM(E109-SUM(I109:K109)) -> -1349 | M109: 1694 | N109: =1964-M109 -> 270 | O109: =1807-N109-M109 -> -157 | P109: =SUM(F109-SUM(M109:O109)) -> 665 | Q109: -325 | R109: =92-Q109 -> 417 | S109: =221-R109-Q109 -> 129 | T109: =SUM(G109-SUM(Q109:S109)) -> -989 | Y109: =SUM(I109:I109) -> -454 | Z109: =SUM(I109:J109) -> -501 | AA109: =SUM(I109:K109) -> -717 | AB109: =SUM(I109:L109) -> -2066 | AC109: =SUM(J109:M109) -> 82 | AD109: =SUM(K109:N109) -> 399 | AE109: =SUM(L109:O109) -> 458 | AF109: =SUM(M109:P109) -> 2472 | AG109: =SUM(N109:Q109) -> 453 | AH109: =SUM(O109:R109) -> 600 | AI109: =SUM(P109:S109) -> 886 | ... AM109: =SUM(T109:W109) -> -989 | AO109: =SUM(AM109/AI109)-1 -> -2.1162528
B110: Inventories | C110: -1157 | D110: -622 | E110: -3137 | F110: 8 | G110: 13 | I110: -638 | J110: =-1337-I110 -> -699 | K110: -2201 | L110: =SUM(E110-SUM(I110:K110)) -> 401 | M110: -476 | N110: =-396-M110 -> 80 | O110: =-192-N110-M110 -> 204 | P110: =SUM(F110-SUM(M110:O110)) -> 200 | Q110: 165 | R110: =328-Q110 -> 163 | S110: =397-R110-Q110 -> 69 | T110: =SUM(G110-SUM(Q110:S110)) -> -384
B111: Other assets | C111: -110 | D111: -1649 | E111: -2266 | F111: 603 | G111: 230 | I111: -1504 | J111: =-1812-I111 -> -308 | K111: -2360 | L111: =SUM(E111-SUM(I111:K111)) -> 1906 | M111: 409 | N111: =615-M111 -> 206 | O111: =604-N111-M111 -> -11 | P111: =SUM(F111-SUM(M111:O111)) -> -1 | Q111: 115 | R111: =221-Q111 -> 106 | S111: =120-R111-Q111 -> -101 | T111: =SUM(G111-SUM(Q111:S111)) -> 110
B112: Trade accounts payable | C112: 907 | D112: 495 | E112: 1036 | F112: -1880 | G112: 682 | I112: 781 | J112: =979-I112 -> 198 | K112: 948 | L112: =SUM(E112-SUM(I112:K112)) -> -891 | M112: -1264 | N112: =-2358-M112 -> -1094 | O112: =-2052-N112-M112 -> 306 | P112: =SUM(F112-SUM(M112:O112)) -> 172 | Q112: 241 | R112: =420-Q112 -> 179 | S112: =691-R112-Q112 -> 271 | T112: =SUM(G112-SUM(Q112:S112)) -> -9 | Y112: =SUM(I112:I112) -> 781 | Z112: =SUM(I112:J112) -> 979 | AA112: =SUM(I112:K112) -> 1927 | AB112: =SUM(I112:L112) -> 1036 | AC112: =SUM(J112:M112) -> -1009 | AD112: =SUM(K112:N112) -> -2301 | AE112: =SUM(L112:O112) -> -2943 | AF112: =SUM(M112:P112) -> -1880 | AG112: =SUM(N112:Q112) -> -375 | AH112: =SUM(O112:R112) -> 898 | AI112: =SUM(P112:S112) -> 863 | ... AM112: =SUM(T112:W112) -> -9 | AO112: =SUM(AM112/AI112)-1 -> -1.0104287
B113: Payroll, benefits and other liabilities | C113: 528 | D113: 1091 | E113: -1043 | F113: 1 | G113: 1046 | I113: -495 | J113: =-371-I113 -> 124 | K113: -1274 | L113: =SUM(E113-SUM(I113:K113)) -> 602 | M113: -286 | N113: =-672-M113 -> -386 | O113: =-604-N113-M113 -> 68 | P113: =SUM(F113-SUM(M113:O113)) -> 605 | Q113: 74 | R113: =286-Q113 -> 212 | S113: =654-R113-Q113 -> 368 | T113: =SUM(G113-SUM(Q113:S113)) -> 392 | Y113: =SUM(I113:I113) -> -495 | Z113: =SUM(I113:J113) -> -371 | AA113: =SUM(I113:K113) -> -1645 | AB113: =SUM(I113:L113) -> -1043 | AC113: =SUM(J113:M113) -> -834 | AD113: =SUM(K113:N113) -> -1344 | AE113: =SUM(L113:O113) -> -2 | AF113: =SUM(M113:P113) -> 1 | AG113: =SUM(N113:Q113) -> 361 | AH113: =SUM(O113:R113) -> 959 | AI113: =SUM(P113:S113) -> 1259 | ... AM113: =SUM(T113:W113) -> 392 | AO113: =SUM(AM113/AI113)-1 -> -0.68864178
B114: Unearned revenues | C114: -246 | D114: -202 | E114: -324 | F114: -56 | G114: 20 | I114: -78 | J114: =-139-I114 -> -61 | K114: -232 | L114: =SUM(E114-SUM(I114:K114)) -> 47 | M114: -81 | N114: =-86-M114 -> -5 | O114: =-116-N114-M114 -> -30 | P114: =SUM(F114-SUM(M114:O114)) -> 60 | Q114: -81 | R114: =10-Q114 -> 91 | S114: =-1-R114-Q114 -> -11 | T114: =SUM(G114-SUM(Q114:S114)) -> 21 | Y114: =SUM(I114:I114) -> -78 | Z114: =SUM(I114:J114) -> -139 | AA114: =SUM(I114:K114) -> -371 | AB114: =SUM(I114:L114) -> -324 | AC114: =SUM(J114:M114) -> -327 | AD114: =SUM(K114:N114) -> -271 | AE114: =SUM(L114:O114) -> -69 | AF114: =SUM(M114:P114) -> -56 | AG114: =SUM(N114:Q114) -> -56 | AH114: =SUM(O114:R114) -> 40 | AI114: =SUM(P114:S114) -> 59 | ... AM114: =SUM(T114:W114) -> 21 | AO114: =SUM(AM114/AI114)-1 -> -0.6440678
B115: Net cash used in operating activities | C115: =SUM(C97:C114) -> 5814 | D115: =SUM(D97:D114) -> 10536 | E115: =SUM(E97:E114) -> 9096 | F115: =SUM(F97:F114) -> 11299 | G115: =SUM(G97:G114) -> 12202 | I115: =SUM(I97:I114) -> 2057 | J115: =SUM(J97:J114) -> 2698 | K115: =SUM(K97:K114) -> 1317 | L115: =SUM(L97:L114) -> 3024 | M115: =SUM(M97:M114) -> 3095 | N115: =SUM(N97:N114) -> 1457 | O115: =SUM(O97:O114) -> 2657 | P115: =SUM(P97:P114) -> 4090 | ... W115: =SUM(W97:W114) -> 0 | Y115: =SUM(Y97:Y114) -> 4199 | Z115: =SUM(Z97:Z114) -> 7904 | AA115: =SUM(AA97:AA114) -> 13782 | AB115: =SUM(AB97:AB114) -> 14669 | AC115: =SUM(AC97:AC114) -> 13660 | AD115: =SUM(AD97:AD114) -> 11159 | AE115: =SUM(AE97:AE114) -> 8078 | AF115: =SUM(AF97:AF114) -> 11087 | ... AM115: =SUM(AM97:AM114) -> 2922 | AO115: =SUM(AM115/AI115)-1 -> -0.77564496
B117: Cash flows from investing activities:
B118: Capital expenditures | C118: -1407 | D118: -1888 | E118: -2262 | F118: -1450 | G118: -1041 | I118: -583 | J118: =-1074-I118 -> -491 | K118: -1628 | L118: =SUM(E118-SUM(I118:K118)) -> 440 | M118: -398 | N118: =-851-M118 -> -453 | O118: =-1157-N118-M118 -> -306 | P118: =SUM(F118-SUM(M118:O118)) -> -293 | Q118: -214 | R118: -398 | S118: =-785-R118-Q118 -> -173 | T118: =SUM(G118-SUM(Q118:S118)) -> -256 | Y118: =SUM(I118:I118) -> -583 | Z118: =SUM(I118:J118) -> -1074 | AA118: =SUM(I118:K118) -> -2702 | AB118: =SUM(I118:L118) -> -2262 | AC118: =SUM(J118:M118) -> -2077 | AD118: =SUM(K118:N118) -> -2039 | AE118: =SUM(L118:O118) -> -717 | AF118: =SUM(M118:P118) -> -1450 | AG118: =SUM(N118:Q118) -> -1266 | AH118: =SUM(O118:R118) -> -1211 | AI118: =SUM(P118:S118) -> -1078 | ... AM118: =SUM(T118:W118) -> -256 | AO118: =SUM(AM118/AI118)-1 -> -0.76252319
B119: Purchases of debt and equity marketable securities | C119: -6213 | D119: -5907 | E119: -1414 | F119: -668 | G119: -5069 | I119: -517 | J119: =-936-I119 -> -419 | K119: -1269 | L119: =SUM(E119-SUM(I119:K119)) -> 791 | M119: -22 | N119: =-22-M119 -> 0 | O119: =-22-N119-M119 -> 0 | P119: =SUM(F119-SUM(M119:O119)) -> -646 | Q119: -1452 | R119: -2842 | S119: =-4156-R119-Q119 -> 138 | T119: =SUM(G119-SUM(Q119:S119)) -> -913 | Y119: =SUM(I119:I119) -> -517 | Z119: =SUM(I119:J119) -> -936 | AA119: =SUM(I119:K119) -> -2205 | AB119: =SUM(I119:L119) -> -1414 | AC119: =SUM(J119:M119) -> -919 | AD119: =SUM(K119:N119) -> -500 | AE119: =SUM(L119:O119) -> 769 | AF119: =SUM(M119:P119) -> -668 | AG119: =SUM(N119:Q119) -> -2098 | AH119: =SUM(O119:R119) -> -4940 | AI119: =SUM(P119:S119) -> -4802 | ... AM119: =SUM(T119:W119) -> -913 | AO119: =SUM(AM119/AI119)-1 -> -0.80987089
B120: Proceeds from sales and maturities of debt and equity marketable securities | C120: 2399 | D120: 5555 | E120: 2622 | F120: 1566 | G120: 2677 | I120: 1133 | J120: =1563-I120 -> 430 | K120: 1960 | L120: =SUM(E120-SUM(I120:K120)) -> -901 | M120: 219 | N120: =491-M120 -> 272 | O120: =1119-N120-M120 -> 628 | P120: =SUM(F120-SUM(M120:O120)) -> 447 | Q120: 463 | R120: 1178 | S120: =1895-R120-Q120 -> 254 | T120: =SUM(G120-SUM(Q120:S120)) -> 782
B121: Acquisitions and other investments, net of cash acquired | C121: -185 | D121: -1377 | E121: -4912 | F121: -235 | G121: -254 | I121: -238 | J121: =-288-I121 -> -50 | K121: -4743 | L121: =SUM(E121-SUM(I121:K121)) -> 119 | M121: -29 | N121: =-61-M121 -> -32 | O121: =-107-N121-M121 -> -46 | P121: =SUM(F121-SUM(M121:O121)) -> -128 | Q121: -60 | R121: -165 | S121: =-234-R121-Q121 -> -9 | T121: =SUM(G121-SUM(Q121:S121)) -> -20
B122: Proceeds from sales of property, plant and equipment | C122: 0 | D122: 0 | E122: 5 | F122: 127 | G122: 10 | I122: 0 | J122: =0-I122 -> 0 | K122: 0 | L122: =SUM(E122-SUM(I122:K122)) -> 5 | M122: 111 | N122: =121-M122 -> 10 | O122: =121-N122-M122 -> 0 | P122: =SUM(F122-SUM(M122:O122)) -> 6 | Q122: 5 | R122: 8 | S122: =10-R122-Q122 -> -3 | T122: =SUM(G122-SUM(Q122:S122)) -> 0
...

Sheet Revenue Drivers
B2: ='Historical Financials'!B2 -> Qualcomm (NASDAQ: QCOM) | E2: FYE | I2: Quarterly | Q2: Quarterly | R2: Quarterly | Y2: LTM | AC2: LTM | AE2: LTM | AK2: Variance
B3: Segment Anaysis | C3: ='Historical Financials'!C7 -> 2020 | D3: ='Historical Financials'!D7 -> 2021 | E3: ='Historical Financials'!E7 -> 2022 | F3: ='Historical Financials'!F7 -> 2023 | G3: ='Historical Financials'!G7 -> 2024 | I3: ='Historical Financials'!I7 -> 1Q22 | J3: ='Historical Financials'!J7 -> 2Q22 | K3: ='Historical Financials'!K7 -> 3Q22 | L3: ='Historical Financials'!L7 -> 4Q22 | M3: ='Historical Financials'!M7 -> 1Q23 | N3: ='Historical Financials'!N7 -> 2Q23 | O3: ='Historical Financials'!O7 -> 3Q23 | P3: ='Historical Financials'!P7 -> 4Q23 | ... W3: ='Historical Financials'!W7 -> 3Q25 | Y3: =M3 -> 1Q23 | Z3: =N3 -> 2Q23 | AA3: =O3 -> 3Q23 | AB3: =P3 -> 4Q23 | AC3: =Q3 -> 1Q24 | AD3: =R3 -> 2Q24 | AE3: =S3 -> 3Q24 | AF3: =T3 -> 4Q24 | ... AI3: =W3 -> 3Q25
B4: $ in thousands except per share | C4: ='Historical Financials'!C8 -> 44196 | D4: ='Historical Financials'!D8 -> 44561 | E4: ='Historical Financials'!E8 -> 44926 | F4: ='Historical Financials'!F8 -> 45291 | G4: ='Historical Financials'!G8 -> 45657 | I4: ='Historical Financials'!I8 -> 44651 | J4: ='Historical Financials'!J8 -> 44742 | K4: ='Historical Financials'!K8 -> 44834 | L4: ='Historical Financials'!L8 -> 44926 | M4: ='Historical Financials'!M8 -> 45016 | N4: ='Historical Financials'!N8 -> 45107 | O4: ='Historical Financials'!O8 -> 45199 | P4: ='Historical Financials'!P8 -> 45291 | ... W4: ='Historical Financials'!W8 -> 45930 | Y4: =M4 -> 45016 | Z4: =N4 -> 45107 | AA4: =O4 -> 45199 | AB4: =P4 -> 45291 | AC4: =Q4 -> 45382 | AD4: =R4 -> 45473 | AE4: =S4 -> 45565 | AF4: =T4 -> 45657 | ... AI4: =W4 -> 45930
A6: X | B6: Offerings Drivers
Y9: =SUM(J9:M9) -> 0 | Z9: =SUM(K9:N9) -> 0 | AA9: =SUM(L9:O9) -> 0 | AB9: =SUM(M9:P9) -> 0 | AC9: =SUM(N9:Q9) -> 0 | AD9: =SUM(O9:R9) -> 0 | AE9: =SUM(P9:S9) -> 0 | AF9: =SUM(Q9:T9) -> 0 | ... AI9: =SUM(T9:W9) -> 0 | AK9: =SUM(AI9/AE9)-1 -> #DIV/0!
AE10: =SUM(P10:S10) -> 0 | AF10: =SUM(Q10:T10) -> 0 | AG10: =SUM(R10:U10) -> 0 | AH10: =SUM(S10:V10) -> 0 | AI10: =SUM(T10:W10) -> 0 | AK10: =SUM(AI10/AE10)-1 -> #DIV/0!
B11: Total Net Revenue | C11: =SUM(C9:C10) -> 0 | D11: =SUM(D9:D10) -> 0 | E11: =SUM(E9:E10) -> 0 | F11: =SUM(F9:F10) -> 0 | G11: =SUM(G9:G10) -> 0 | I11: =SUM(I9:I10) -> 0 | J11: =SUM(J9:J10) -> 0 | K11: =SUM(K9:K10) -> 0 | L11: =SUM(L9:L10) -> 0 | M11: =SUM(M9:M10) -> 0 | N11: =SUM(N9:N10) -> 0 | O11: =SUM(O9:O10) -> 0 | P11: =SUM(P9:P10) -> 0 | ... W11: =SUM(W9:W10) -> 0 | Y11: =SUM(Y9:Y10) -> 0 | Z11: =SUM(Z9:Z10) -> 0 | AA11: =SUM(AA9:AA10) -> 0 | AB11: =SUM(AB9:AB10) -> 0 | AC11: =SUM(AC9:AC10) -> 0 | AD11: =SUM(AD9:AD10) -> 0 | AE11: =SUM(AE9:AE10) -> 0 | AF11: =SUM(AF9:AF10) -> 0 | ... AI11: =SUM(AI9:AI10) -> 0 | AK11: =SUM(AI11/AE11)-1 -> #DIV/0!
B12: Variance Check | C12: =+C11-'Historical Financials'!C11 -> -23531 | D12: =+D11-'Historical Financials'!D11 -> -33566 | E12: =+E11-'Historical Financials'!E11 -> -44200 | F12: =+F11-'Historical Financials'!F11 -> -35820 | G12: =+G11-'Historical Financials'!G11 -> -38962 | I12: =I11-'Historical Financials'!I11 -> -10705 | J12: =J11-'Historical Financials'!J11 -> -11164 | K12: =K11-'Historical Financials'!K11 -> -10936 | L12: =L11-'Historical Financials'!L11 -> -11395 | M12: =M11-'Historical Financials'!M11 -> -9463 | N12: =N11-'Historical Financials'!N11 -> -9275 | O12: =O11-'Historical Financials'!O11 -> -8451 | P12: =P11-'Historical Financials'!P11 -> -8631 | ... W12: =W11-'Historical Financials'!W11 -> 0 | Y12: =+Y11-'Historical Financials'!AC11 -> -42958 | Z12: =+Z11-'Historical Financials'!AD11 -> -41069 | AA12: =+AA11-'Historical Financials'!AE11 -> -38584 | AB12: =+AB11-'Historical Financials'!AF11 -> -35820 | AC12: =+AC11-'Historical Financials'!AG11 -> -36292 | AD12: =+AD11-'Historical Financials'!AH11 -> -36406 | AE12: =+AE11-'Historical Financials'!AI11 -> -37348 | AF12: =+AF11-'Historical Financials'!AJ11 -> -38962 | ... AH12: =+AH11-'Historical Financials'!AL11 -> -19638 | AI12: =AI11-'Historical Financials'!AM11 -> -10245

Sheet FCF
B2: ='Historical Financials'!B2 -> Qualcomm (NASDAQ: QCOM) | C2: FYE | E2: FYE | I2: Quarterly | M2: Quarterly | S2: Quarterly | Y2: LTM | AF2: LTM | AG2: LTM | AM2: Variance
B3: FCF Analysis | C3: ='Historical Financials'!C7 -> 2020 | D3: ='Historical Financials'!D7 -> 2021 | E3: ='Historical Financials'!E7 -> 2022 | F3: ='Historical Financials'!F7 -> 2023 | G3: ='Historical Financials'!G7 -> 2024 | I3: ='Historical Financials'!I7 -> 1Q22 | J3: ='Historical Financials'!J7 -> 2Q22 | K3: ='Historical Financials'!K7 -> 3Q22 | L3: ='Historical Financials'!L7 -> 4Q22 | M3: ='Historical Financials'!M7 -> 1Q23 | N3: ='Historical Financials'!N7 -> 2Q23 | O3: ='Historical Financials'!O7 -> 3Q23 | P3: ='Historical Financials'!P7 -> 4Q23 | ... W3: ='Historical Financials'!W7 -> 3Q25 | Y3: =K3 -> 3Q22 | Z3: =L3 -> 4Q22 | AA3: =M3 -> 1Q23 | AB3: =N3 -> 2Q23 | AC3: =O3 -> 3Q23 | AD3: =P3 -> 4Q23 | AE3: =Q3 -> 1Q24 | AF3: =R3 -> 2Q24 | ... AK3: =W3 -> 3Q25
B4: $ mm except per share | C4: ='Historical Financials'!C8 -> 44196 | D4: ='Historical Financials'!D8 -> 44561 | E4: ='Historical Financials'!E8 -> 44926 | F4: ='Historical Financials'!F8 -> 45291 | G4: ='Historical Financials'!G8 -> 45657 | I4: ='Historical Financials'!I8 -> 44651 | J4: ='Historical Financials'!J8 -> 44742 | K4: ='Historical Financials'!K8 -> 44834 | L4: ='Historical Financials'!L8 -> 44926 | M4: ='Historical Financials'!M8 -> 45016 | N4: ='Historical Financials'!N8 -> 45107 | O4: ='Historical Financials'!O8 -> 45199 | P4: ='Historical Financials'!P8 -> 45291 | ... W4: ='Historical Financials'!W8 -> 45930 | Y4: =K4 -> 44834 | Z4: =L4 -> 44926 | AA4: =M4 -> 45016 | AB4: =N4 -> 45107 | AC4: =O4 -> 45199 | AD4: =P4 -> 45291 | AE4: =Q4 -> 45382 | AF4: =R4 -> 45473 | ... AK4: =W4 -> 45930
B6: ='Revenue Drivers'!B9 -> 0 | C6: =('Revenue Drivers'!C9)/1000 -> 0 | D6: =('Revenue Drivers'!D9)/1000 -> 0 | E6: =('Revenue Drivers'!E9)/1000 -> 0 | F6: =('Revenue Drivers'!F9)/1000 -> 0 | G6: =('Revenue Drivers'!G9)/1000 -> 0 | I6: =('Revenue Drivers'!I9)/1000 -> 0 | J6: =('Revenue Drivers'!J9)/1000 -> 0 | K6: =('Revenue Drivers'!K9)/1000 -> 0 | L6: =('Revenue Drivers'!L9)/1000 -> 0 | M6: =('Revenue Drivers'!M9)/1000 -> 0 | N6: =('Revenue Drivers'!N9)/1000 -> 0 | O6: =('Revenue Drivers'!O9)/1000 -> 0 | P6: =('Revenue Drivers'!P9)/1000 -> 0 | ... W6: =('Revenue Drivers'!W9)/1000 -> 0 | Y6: =SUM(H6:K6) -> 0 | Z6: =SUM(I6:L6) -> 0 | AA6: =SUM(J6:M6) -> 0 | AB6: =SUM(K6:N6) -> 0 | AC6: =SUM(L6:O6) -> 0 | AD6: =SUM(M6:P6) -> 0 | AE6: =SUM(N6:Q6) -> 0 | AF6: =SUM(O6:R6) -> 0 | ... AK6: =SUM(T6:W6) -> 0 | AM6: =SUM(AK6/AG6)-1 -> #DIV/0!
B7: ='Revenue Drivers'!B10 -> 0 | C7: =('Revenue Drivers'!C10)/1000 -> 0 | D7: =('Revenue Drivers'!D10)/1000 -> 0 | E7: =('Revenue Drivers'!E10)/1000 -> 0 | F7: =('Revenue Drivers'!F10)/1000 -> 0 | G7: =('Revenue Drivers'!G10)/1000 -> 0 | I7: =('Revenue Drivers'!I10)/1000 -> 0 | J7: =('Revenue Drivers'!J10)/1000 -> 0 | K7: =('Revenue Drivers'!K10)/1000 -> 0 | L7: =('Revenue Drivers'!L10)/1000 -> 0 | M7: =('Revenue Drivers'!M10)/1000 -> 0 | N7: =('Revenue Drivers'!N10)/1000 -> 0 | O7: =('Revenue Drivers'!O10)/1000 -> 0 | P7: =('Revenue Drivers'!P10)/1000 -> 0 | ... W7: =('Revenue Drivers'!W10)/1000 -> 0 | AG7: =SUM(P7:S7) -> 0 | AH7: =SUM(Q7:T7) -> 0 | AI7: =SUM(R7:U7) -> 0 | AJ7: =SUM(S7:V7) -> 0 | AK7: =SUM(T7:W7) -> 0 | AM7: =SUM(AK7/AG7)-1 -> #DIV/0!
B8: ='Revenue Drivers'!#REF! -> #REF! | C8: =('Revenue Drivers'!#REF!)/1000 -> #REF! | D8: =('Revenue Drivers'!#REF!)/1000 -> #REF! | E8: =('Revenue Drivers'!#REF!)/1000 -> #REF! | F8: =('Revenue Drivers'!#REF!)/1000 -> #REF! | G8: =('Revenue Drivers'!#REF!)/1000 -> #REF! | I8: =('Revenue Drivers'!#REF!)/1000 -> #REF! | J8: =('Revenue Drivers'!#REF!)/1000 -> #REF! | K8: =('Revenue Drivers'!#REF!)/1000 -> #REF! | L8: =('Revenue Drivers'!#REF!)/1000 -> #REF! | M8: =('Revenue Drivers'!#REF!)/1000 -> #REF! | N8: =('Revenue Drivers'!#REF!)/1000 -> #REF! | O8: =('Revenue Drivers'!#REF!)/1000 -> #REF! | P8: =('Revenue Drivers'!#REF!)/1000 -> #REF! | ... W8: =('Revenue Drivers'!#REF!)/1000 -> #REF! | AG8: =SUM(P8:S8) -> #REF! | AH8: =SUM(Q8:T8) -> #REF! | AI8: =SUM(R8:U8) -> #REF! | AJ8: =SUM(S8:V8) -> #REF! | AK8: =SUM(T8:W8) -> #REF! | AM8: =SUM(AK8/AG8)-1 -> #REF!
B9: ='Revenue Drivers'!#REF! -> #REF! | C9: =('Revenue Drivers'!#REF!)/1000 -> #REF! | D9: =('Revenue Drivers'!#REF!)/1000 -> #REF! | E9: =('Revenue Drivers'!#REF!)/1000 -> #REF! | F9: =('Revenue Drivers'!#REF!)/1000 -> #REF! | G9: =('Revenue Drivers'!#REF!)/1000 -> #REF! | I9: =('Revenue Drivers'!#REF!)/1000 -> #REF! | J9: =('Revenue Drivers'!#REF!)/1000 -> #REF! | K9: =('Revenue Drivers'!#REF!)/1000 -> #REF! | L9: =('Revenue Drivers'!#REF!)/1000 -> #REF! | M9: =('Revenue Drivers'!#REF!)/1000 -> #REF! | N9: =('Revenue Drivers'!#REF!)/1000 -> #REF! | O9: =('Revenue Drivers'!#REF!)/1000 -> #REF! | P9: =('Revenue Drivers'!#REF!)/1000 -> #REF! | ... W9: =('Revenue Drivers'!#REF!)/1000 -> #REF! | AG9: =SUM(P9:S9) -> #REF! | AH9: =SUM(Q9:T9) -> #REF! | AI9: =SUM(R9:U9) -> #REF! | AJ9: =SUM(S9:V9) -> #REF! | AK9: =SUM(T9:W9) -> #REF! | AM9: =SUM(AK9/AG9)-1 -> #REF!
B10: ='Revenue Drivers'!#REF! -> #REF! | C10: =('Revenue Drivers'!#REF!)/1000 -> #REF! | D10: =('Revenue Drivers'!#REF!)/1000 -> #REF! | E10: =('Revenue Drivers'!#REF!)/1000 -> #REF! | F10: =('Revenue Drivers'!#REF!)/1000 -> #REF! | G10: =('Revenue Drivers'!#REF!)/1000 -> #REF! | I10: =('Revenue Drivers'!#REF!)/1000 -> #REF! | J10: =('Revenue Drivers'!#REF!)/1000 -> #REF! | K10: =('Revenue Drivers'!#REF!)/1000 -> #REF! | L10: =('Revenue Drivers'!#REF!)/1000 -> #REF! | M10: =('Revenue Drivers'!#REF!)/1000 -> #REF! | N10: =('Revenue Drivers'!#REF!)/1000 -> #REF! | O10: =('Revenue Drivers'!#REF!)/1000 -> #REF! | P10: =('Revenue Drivers'!#REF!)/1000 -> #REF! | ... W10: =('Revenue Drivers'!#REF!)/1000 -> #REF! | AG10: =SUM(P10:S10) -> #REF! | AH10: =SUM(Q10:T10) -> #REF! | AI10: =SUM(R10:U10) -> #REF! | AJ10: =SUM(S10:V10) -> #REF! | AK10: =SUM(T10:W10) -> #REF! | AM10: =SUM(AK10/AG10)-1 -> #REF!
B11: Total Revenue | C11: =SUM(C6:C10) -> #REF! | D11: =SUM(D6:D10) -> #REF! | E11: =SUM(E6:E10) -> #REF! | F11: =SUM(F6:F10) -> #REF! | G11: =SUM(G6:G10) -> #REF! | I11: =SUM(I6:I10) -> #REF! | J11: =SUM(J6:J10) -> #REF! | K11: =SUM(K6:K10) -> #REF! | L11: =SUM(L6:L10) -> #REF! | M11: =SUM(M6:M10) -> #REF! | N11: =SUM(N6:N10) -> #REF! | O11: =SUM(O6:O10) -> #REF! | P11: =SUM(P6:P10) -> #REF! | ... W11: =SUM(W6:W10) -> #REF! | Y11: =SUM(Y6:Y10) -> 0 | Z11: =SUM(Z6:Z10) -> 0 | AA11: =SUM(AA6:AA10) -> 0 | AB11: =SUM(AB6:AB10) -> 0 | AC11: =SUM(AC6:AC10) -> 0 | AD11: =SUM(AD6:AD10) -> 0 | AE11: =SUM(AE6:AE10) -> 0 | AF11: =SUM(AF6:AF10) -> 0 | ... AK11: =SUM(AK6:AK10) -> #REF! | AM11: =SUM(AK11/AG11)-1 -> #REF!
B12: Y/Y Growth (%) | D12: =SUM(D11/C11)-1 -> #REF! | E12: =SUM(E11/D11)-1 -> #REF! | F12: =SUM(F11/E11)-1 -> #REF! | G12: =SUM(G11/F11)-1 -> #REF! | M12: =SUM(M11/I11)-1 -> #REF! | N12: =SUM(N11/J11)-1 -> #REF! | O12: =SUM(O11/K11)-1 -> #REF! | P12: =SUM(P11/L11)-1 -> #REF! | Q12: =SUM(Q11/M11)-1 -> #REF! | R12: =SUM(R11/N11)-1 -> #REF! | S12: =SUM(S11/O11)-1 -> #REF! | T12: =SUM(T11/P11)-1 -> #REF! | ... W12: =SUM(W11/S11)-1 -> #REF! | AC12: =SUM(AC11/Y11)-1 -> #DIV/0! | AD12: =SUM(AD11/Z11)-1 -> #DIV/0! | AE12: =SUM(AE11/AA11)-1 -> #DIV/0! | AF12: =SUM(AF11/AB11)-1 -> #DIV/0! | AG12: =SUM(AG11/AC11)-1 -> #REF! | AH12: =SUM(AH11/AD11)-1 -> #REF! | AI12: =SUM(AI11/AE11)-1 -> #REF! | AJ12: =SUM(AJ11/AF11)-1 -> #REF! | AK12: =SUM(AK11/AG11)-1 -> #REF! | AM12: =SUM(AK12-AG12)*10000 -> #REF!
B13: Q/Q Growth (%) | C13: N/A | D13: N/A | E13: N/A | F13: N/A | G13: N/A | J13: =SUM(J11/I11)-1 -> #REF! | K13: =SUM(K11/J11)-1 -> #REF! | L13: =SUM(L11/K11)-1 -> #REF! | M13: =SUM(M11/L11)-1 -> #REF! | N13: =SUM(N11/M11)-1 -> #REF! | O13: =SUM(O11/N11)-1 -> #REF! | P13: =SUM(P11/O11)-1 -> #REF! | Q13: =SUM(Q11/P11)-1 -> #REF! | ... W13: =SUM(W11/V11)-1 -> #REF! | Y13: N/A | Z13: N/A | AA13: N/A | AB13: N/A | AC13: N/A | AD13: N/A | AE13: N/A | AF13: N/A | AG13: N/A | AH13: N/A | AI13: N/A | AJ13: N/A | AK13: N/A
B15: (-) Amortization of content assets | C15: =('Historical Financials'!C13)/1000 -> -9.255 | D15: =('Historical Financials'!D13)/1000 -> -14.262 | E15: =('Historical Financials'!E13)/1000 -> -18.635 | F15: =('Historical Financials'!F13)/1000 -> -15.869 | G15: =('Historical Financials'!G13)/1000 -> -17.06 | I15: =('Historical Financials'!I13)/1000 -> -4.303 | J15: =('Historical Financials'!J13)/1000 -> -4.648 | K15: =('Historical Financials'!K13)/1000 -> -4.816 | L15: =('Historical Financials'!L13)/1000 -> -4.868 | M15: =('Historical Financials'!M13)/1000 -> -4.044 | N15: =('Historical Financials'!N13)/1000 -> -4.153 | O15: =('Historical Financials'!O13)/1000 -> -3.792 | P15: =('Historical Financials'!P13)/1000 -> -3.88 | ... W15: =('Historical Financials'!W13)/1000 -> 0 | Y15: =SUM(H15:K15) -> -13.767 | Z15: =SUM(I15:L15) -> -18.635 | AA15: =SUM(J15:M15) -> -18.376 | AB15: =SUM(K15:N15) -> -17.881 | AC15: =SUM(L15:O15) -> -16.857 | AD15: =SUM(M15:P15) -> -15.869 | AE15: =SUM(N15:Q15) -> -16.137 | AF15: =SUM(O15:R15) -> -16.09 | ... AK15: =SUM(T15:W15) -> -4.468 | AM15: =SUM(AK15/AG15)-1 -> -0.72875182
B16: (-) Other Cost of Revenues | C16: =('Historical Financials'!#REF!)/1000 -> #REF! | D16: =('Historical Financials'!#REF!)/1000 -> #REF! | E16: =('Historical Financials'!#REF!)/1000 -> #REF! | F16: =('Historical Financials'!#REF!)/1000 -> #REF! | G16: =('Historical Financials'!#REF!)/1000 -> #REF! | I16: =('Historical Financials'!#REF!)/1000 -> #REF! | J16: =('Historical Financials'!#REF!)/1000 -> #REF! | K16: =('Historical Financials'!#REF!)/1000 -> #REF! | L16: =('Historical Financials'!#REF!)/1000 -> #REF! | M16: =('Historical Financials'!#REF!)/1000 -> #REF! | N16: =('Historical Financials'!#REF!)/1000 -> #REF! | O16: =('Historical Financials'!#REF!)/1000 -> #REF! | P16: =('Historical Financials'!#REF!)/1000 -> #REF! | ... W16: =('Historical Financials'!#REF!)/1000 -> #REF! | AG16: =SUM(P16:S16) -> #REF! | AH16: =SUM(Q16:T16) -> #REF! | AI16: =SUM(R16:U16) -> #REF! | AJ16: =SUM(S16:V16) -> #REF! | AK16: =SUM(T16:W16) -> #REF!
B17: Gross Profit | C17: =SUM(C11+SUM(C15:C16)) -> #REF! | D17: =SUM(D11+SUM(D15:D16)) -> #REF! | E17: =SUM(E11+SUM(E15:E16)) -> #REF! | F17: =SUM(F11+SUM(F15:F16)) -> #REF! | G17: =SUM(G11+SUM(G15:G16)) -> #REF! | I17: =SUM(I11+SUM(I15:I16)) -> #REF! | J17: =SUM(J11+SUM(J15:J16)) -> #REF! | K17: =SUM(K11+SUM(K15:K16)) -> #REF! | L17: =SUM(L11+SUM(L15:L16)) -> #REF! | M17: =SUM(M11+SUM(M15:M16)) -> #REF! | N17: =SUM(N11+SUM(N15:N16)) -> #REF! | O17: =SUM(O11+SUM(O15:O16)) -> #REF! | P17: =SUM(P11+SUM(P15:P16)) -> #REF! | ... W17: =SUM(W11+SUM(W15:W16)) -> #REF! | Y17: =SUM(Y11+SUM(Y15:Y16)) -> -13.767 | Z17: =SUM(Z11+SUM(Z15:Z16)) -> -18.635 | AA17: =SUM(AA11+SUM(AA15:AA16)) -> -18.376 | AB17: =SUM(AB11+SUM(AB15:AB16)) -> -17.881 | AC17: =SUM(AC11+SUM(AC15:AC16)) -> -16.857 | AD17: =SUM(AD11+SUM(AD15:AD16)) -> -15.869 | AE17: =SUM(AE11+SUM(AE15:AE16)) -> -16.137 | AF17: =SUM(AF11+SUM(AF15:AF16)) -> -16.09 | ... AK17: =SUM(AK11+SUM(AK15:AK16)) -> #REF! | AM17: =SUM(AK17/AG17)-1 -> #REF!
B18: Gross Margin (%) | C18: =C17/C11 -> #REF! | D18: =D17/D11 -> #REF! | E18: =E17/E11 -> #REF! | F18: =F17/F11 -> #REF! | G18: =G17/G11 -> #REF! | I18: =I17/I11 -> #REF! | J18: =J17/J11 -> #REF! | K18: =K17/K11 -> #REF! | L18: =L17/L11 -> #REF! | M18: =M17/M11 -> #REF! | N18: =N17/N11 -> #REF! | O18: =O17/O11 -> #REF! | P18: =P17/P11 -> #REF! | ... W18: =W17/W11 -> #REF! | Y18: =Y17/Y11 -> #DIV/0! | Z18: =Z17/Z11 -> #DIV/0! | AA18: =AA17/AA11 -> #DIV/0! | AB18: =AB17/AB11 -> #DIV/0! | AC18: =AC17/AC11 -> #DIV/0! | AD18: =AD17/AD11 -> #DIV/0! | AE18: =AE17/AE11 -> #DIV/0! | AF18: =AF17/AF11 -> #DIV/0! | ... AK18: =AK17/AK11 -> #REF! | AM18: =SUM(AK18-AG18)*10000 -> #REF!
B20: (-) Marketing | C20: =('Historical Financials'!C17)/1000 -> -5.975 | D20: =('Historical Financials'!D17)/1000 -> -7.176 | E20: =('Historical Financials'!E17)/1000 -> -8.194 | F20: =('Historical Financials'!F17)/1000 -> -8.818 | G20: =('Historical Financials'!G17)/1000 -> -8.893 | I20: =('Historical Financials'!I17)/1000 -> -1.93 | J20: =('Historical Financials'!J17)/1000 -> -2.034 | K20: =('Historical Financials'!K17)/1000 -> -2.052 | L20: =('Historical Financials'!L17)/1000 -> -2.178 | M20: =('Historical Financials'!M17)/1000 -> -2.251 | N20: =('Historical Financials'!N17)/1000 -> -2.21 | O20: =('Historical Financials'!O17)/1000 -> -2.222 | P20: =('Historical Financials'!P17)/1000 -> -2.135 | ... W20: =('Historical Financials'!W17)/1000 -> 0 | Y20: =SUM(H20:K20) -> -6.016 | Z20: =SUM(I20:L20) -> -8.194 | AA20: =SUM(J20:M20) -> -8.515 | AB20: =SUM(K20:N20) -> -8.691 | AC20: =SUM(L20:O20) -> -8.861 | AD20: =SUM(M20:P20) -> -8.818 | AE20: =SUM(N20:Q20) -> -8.663 | AF20: =SUM(O20:R20) -> -8.689 | ... AK20: =SUM(T20:W20) -> -2.302 | AM20: =SUM(AK20/AG20)-1 -> -0.73619069
B21: (-) Technology and Development (T&D) | C21: =('Historical Financials'!C18)/1000 -> -2.074 | D21: =('Historical Financials'!D18)/1000 -> -2.339 | E21: =('Historical Financials'!E18)/1000 -> -2.57 | F21: =('Historical Financials'!F18)/1000 -> -2.483 | G21: =('Historical Financials'!G18)/1000 -> -2.759 | I21: =('Historical Financials'!I18)/1000 -> -0.608 | J21: =('Historical Financials'!J18)/1000 -> -0.624 | K21: =('Historical Financials'!K18)/1000 -> -0.655 | L21: =('Historical Financials'!L18)/1000 -> -0.683 | M21: =('Historical Financials'!M18)/1000 -> -0.623 | N21: =('Historical Financials'!N18)/1000 -> -0.614 | O21: =('Historical Financials'!O18)/1000 -> -0.618 | P21: =('Historical Financials'!P18)/1000 -> -0.628 | ... W21: =('Historical Financials'!W18)/1000 -> 0 | Y21: =SUM(H21:K21) -> -1.887 | Z21: =SUM(I21:L21) -> -2.57 | AA21: =SUM(J21:M21) -> -2.585 | AB21: =SUM(K21:N21) -> -2.575 | AC21: =SUM(L21:O21) -> -2.538 | AD21: =SUM(M21:P21) -> -2.483 | AE21: =SUM(N21:Q21) -> -2.487 | AF21: =SUM(O21:R21) -> -2.58 | ... AK21: =SUM(T21:W21) -> -0.761 | AM21: =SUM(AK21/AG21)-1 -> -0.71020564
B22: (-) General and Administrative (G&A) | C22: =('Historical Financials'!C19)/1000 -> 0.028 | D22: =('Historical Financials'!D19)/1000 -> 0 | E22: =('Historical Financials'!E19)/1000 -> 1.059 | F22: =('Historical Financials'!F19)/1000 -> -0.862 | G22: =('Historical Financials'!G19)/1000 -> -0.179 | I22: =('Historical Financials'!I19)/1000 -> 0 | J22: =('Historical Financials'!J19)/1000 -> 0 | K22: =('Historical Financials'!K19)/1000 -> 1.059 | L22: =('Historical Financials'!L19)/1000 -> 0 | M22: =('Historical Financials'!M19)/1000 -> -0.08 | N22: =('Historical Financials'!N19)/1000 -> -0.208 | O22: =('Historical Financials'!O19)/1000 -> 0.004 | P22: =('Historical Financials'!P19)/1000 -> -0.578 | ... W22: =('Historical Financials'!W19)/1000 -> 0 | Y22: =SUM(H22:K22) -> 1.059 | Z22: =SUM(I22:L22) -> 1.059 | AA22: =SUM(J22:M22) -> 0.979 | AB22: =SUM(K22:N22) -> 0.771 | AC22: =SUM(L22:O22) -> -0.284 | AD22: =SUM(M22:P22) -> -0.862 | AE22: =SUM(N22:Q22) -> -0.754 | AF22: =SUM(O22:R22) -> -0.546 | ... AK22: =SUM(T22:W22) -> -0.132 | AM22: =SUM(AK22/AG22)-1 -> -0.7888
B23: Earning before Interest & Taxes (EBIT) | C23: =SUM(C17+SUM(C20:C22)) -> #REF! | D23: =SUM(D17+SUM(D20:D22)) -> #REF! | E23: =SUM(E17+SUM(E20:E22)) -> #REF! | F23: =SUM(F17+SUM(F20:F22)) -> #REF! | G23: =SUM(G17+SUM(G20:G22)) -> #REF! | I23: =SUM(I17+SUM(I20:I22)) -> #REF! | J23: =SUM(J17+SUM(J20:J22)) -> #REF! | K23: =SUM(K17+SUM(K20:K22)) -> #REF! | L23: =SUM(L17+SUM(L20:L22)) -> #REF! | M23: =SUM(M17+SUM(M20:M22)) -> #REF! | N23: =SUM(N17+SUM(N20:N22)) -> #REF! | O23: =SUM(O17+SUM(O20:O22)) -> #REF! | P23: =SUM(P17+SUM(P20:P22)) -> #REF! | ... W23: =SUM(W17+SUM(W20:W22)) -> #REF! | Y23: =SUM(Y17+SUM(Y20:Y22)) -> -20.611 | Z23: =SUM(Z17+SUM(Z20:Z22)) -> -28.34 | AA23: =SUM(AA17+SUM(AA20:AA22)) -> -28.497 | AB23: =SUM(AB17+SUM(AB20:AB22)) -> -28.376 | AC23: =SUM(AC17+SUM(AC20:AC22)) -> -28.54 | AD23: =SUM(AD17+SUM(AD20:AD22)) -> -28.032 | AE23: =SUM(AE17+SUM(AE20:AE22)) -> -28.041 | AF23: =SUM(AF17+SUM(AF20:AF22)) -> -27.905 | ... AK23: =SUM(AK17+SUM(AK20:AK22)) -> #REF! | AM23: =SUM(AK23/AG23)-1 -> #REF!
B24: Operating Margin (%) | C24: =C23/C11 -> #REF! | D24: =D23/D11 -> #REF! | E24: =E23/E11 -> #REF! | F24: =F23/F11 -> #REF! | G24: =G23/G11 -> #REF! | I24: =I23/I11 -> #REF! | J24: =J23/J11 -> #REF! | K24: =K23/K11 -> #REF! | L24: =L23/L11 -> #REF! | M24: =M23/M11 -> #REF! | N24: =N23/N11 -> #REF! | O24: =O23/O11 -> #REF! | P24: =P23/P11 -> #REF! | ... W24: =W23/W11 -> #REF! | Y24: =Y23/Y11 -> #DIV/0! | Z24: =Z23/Z11 -> #DIV/0! | AA24: =AA23/AA11 -> #DIV/0! | AB24: =AB23/AB11 -> #DIV/0! | AC24: =AC23/AC11 -> #DIV/0! | AD24: =AD23/AD11 -> #DIV/0! | AE24: =AE23/AE11 -> #DIV/0! | AF24: =AF23/AF11 -> #DIV/0! | ... AK24: =AK23/AK11 -> #REF! | AM24: =SUM(AK24-AG24)*10000 -> #REF!
B26: (+) Depreciation and amortization of PP&E and intangibles | C26: =('Historical Financials'!C103)/1000 -> 1.212 | D26: =('Historical Financials'!D103)/1000 -> 1.663 | E26: =('Historical Financials'!E103)/1000 -> 2.031 | F26: =('Historical Financials'!F103)/1000 -> 2.484 | G26: =('Historical Financials'!G103)/1000 -> 2.648 | I26: =('Historical Financials'!I103)/1000 -> 0.496 | J26: =('Historical Financials'!J103)/1000 -> 0.498 | K26: =('Historical Financials'!K103)/1000 -> 1.51 | L26: =('Historical Financials'!L103)/1000 -> -0.473 | M26: =('Historical Financials'!M103)/1000 -> 0.634 | N26: =('Historical Financials'!N103)/1000 -> 0.628 | O26: =('Historical Financials'!O103)/1000 -> 0.614 | P26: =('Historical Financials'!P103)/1000 -> 0.608 | ... W26: =('Historical Financials'!W103)/1000 -> 0 | Y26: =SUM(H26:K26) -> 2.504 | Z26: =SUM(I26:L26) -> 2.031 | AA26: =SUM(J26:M26) -> 2.169 | AB26: =SUM(K26:N26) -> 2.299 | AC26: =SUM(L26:O26) -> 1.403 | AD26: =SUM(M26:P26) -> 2.484 | AE26: =SUM(N26:Q26) -> 2.452 | AF26: =SUM(O26:R26) -> 2.529 | ... AK26: =SUM(T26:W26) -> 0.697 | AM26: =SUM(AK26/AG26)-1 -> -0.72762798
B27: (+) Amortization of content assets | C27: =-C15 -> 9.255 | D27: =-D15 -> 14.262 | E27: =-E15 -> 18.635 | F27: =-F15 -> 15.869 | G27: =-G15 -> 17.06 | I27: =-I15 -> 4.303 | J27: =-J15 -> 4.648 | K27: =-K15 -> 4.816 | L27: =-L15 -> 4.868 | M27: =-M15 -> 4.044 | N27: =-N15 -> 4.153 | O27: =-O15 -> 3.792 | P27: =-P15 -> 3.88 | ... W27: =-W15 -> 0 | Y27: =-Y15 -> 13.767 | Z27: =-Z15 -> 18.635 | AA27: =-AA15 -> 18.376 | AB27: =-AB15 -> 17.881 | AC27: =-AC15 -> 16.857 | AD27: =-AD15 -> 15.869 | AE27: =-AE15 -> 16.137 | AF27: =-AF15 -> 16.09 | ... AK27: =-AK15 -> 4.468
B28: EBITDA | C28: =SUM(C23+SUM(C26:C27)) -> #REF! | D28: =SUM(D23+SUM(D26:D27)) -> #REF! | E28: =SUM(E23+SUM(E26:E27)) -> #REF! | F28: =SUM(F23+SUM(F26:F27)) -> #REF! | G28: =SUM(G23+SUM(G26:G27)) -> #REF! | I28: =SUM(I23+SUM(I26:I27)) -> #REF! | J28: =SUM(J23+SUM(J26:J27)) -> #REF! | K28: =SUM(K23+SUM(K26:K27)) -> #REF! | L28: =SUM(L23+SUM(L26:L27)) -> #REF! | M28: =SUM(M23+SUM(M26:M27)) -> #REF! | N28: =SUM(N23+SUM(N26:N27)) -> #REF! | O28: =SUM(O23+SUM(O26:O27)) -> #REF! | P28: =SUM(P23+SUM(P26:P27)) -> #REF! | ... W28: =SUM(W23+SUM(W26:W27)) -> #REF! | Y28: =SUM(Y23+SUM(Y26:Y27)) -> -4.34 | Z28: =SUM(Z23+SUM(Z26:Z27)) -> -7.674 | AA28: =SUM(AA23+SUM(AA26:AA27)) -> -7.952 | AB28: =SUM(AB23+SUM(AB26:AB27)) -> -8.196 | AC28: =SUM(AC23+SUM(AC26:AC27)) -> -10.28 | AD28: =SUM(AD23+SUM(AD26:AD27)) -> -9.679 | AE28: =SUM(AE23+SUM(AE26:AE27)) -> -9.452 | AF28: =SUM(AF23+SUM(AF26:AF27)) -> -9.286 | ... AK28: =SUM(AK23+SUM(AK26:AK27)) -> #REF! | AM28: =SUM(AK28/AG28)-1 -> #REF!
B29: EBITDA Margin (%) | C29: =C28/C11 -> #REF! | D29: =D28/D11 -> #REF! | E29: =E28/E11 -> #REF! | F29: =F28/F11 -> #REF! | G29: =G28/G11 -> #REF! | I29: =I28/I11 -> #REF! | J29: =J28/J11 -> #REF! | K29: =K28/K11 -> #REF! | L29: =L28/L11 -> #REF! | M29: =M28/M11 -> #REF! | N29: =N28/N11 -> #REF! | O29: =O28/O11 -> #REF! | P29: =P28/P11 -> #REF! | ... W29: =W28/W11 -> #REF! | Y29: =Y28/Y11 -> #DIV/0! | Z29: =Z28/Z11 -> #DIV/0! | AA29: =AA28/AA11 -> #DIV/0! | AB29: =AB28/AB11 -> #DIV/0! | AC29: =AC28/AC11 -> #DIV/0! | AD29: =AD28/AD11 -> #DIV/0! | AE29: =AE28/AE11 -> #DIV/0! | AF29: =AF28/AF11 -> #DIV/0! | ... AK29: =AK28/AK11 -> #REF! | AM29: =SUM(AK29-AG29)*10000 -> #REF!
B31: (+) Share-based Compensation | C31: =('Historical Financials'!C104)/1000 -> -0.336 | D31: =('Historical Financials'!D104)/1000 -> -1.002 | E31: =('Historical Financials'!E104)/1000 -> 0.432 | F31: =('Historical Financials'!F104)/1000 -> -0.152 | G31: =('Historical Financials'!G104)/1000 -> -0.349 | I31: =('Historical Financials'!I104)/1000 -> -0.103 | J31: =('Historical Financials'!J104)/1000 -> 0.316 | K31: =('Historical Financials'!K104)/1000 -> 0.374 | L31: =('Historical Financials'!L104)/1000 -> -0.155 | M31: =('Historical Financials'!M104)/1000 -> -0.025 | N31: =('Historical Financials'!N104)/1000 -> -0.02 | O31: =('Historical Financials'!O104)/1000 -> -0.039 | P31: =('Historical Financials'!P104)/1000 -> -0.068 | ... W31: =('Historical Financials'!W104)/1000 -> 0 | Y31: =SUM(H31:K31) -> 0.587 | Z31: =SUM(I31:L31) -> 0.432 | AA31: =SUM(J31:M31) -> 0.51 | AB31: =SUM(K31:N31) -> 0.174 | AC31: =SUM(L31:O31) -> -0.239 | AD31: =SUM(M31:P31) -> -0.152 | AE31: =SUM(N31:Q31) -> -0.198 | AF31: =SUM(O31:R31) -> -0.38 | ... AK31: =SUM(T31:W31) -> -0.035 | AM31: =SUM(AK31/AG31)-1 -> -0.90837696
B32: Adj. EBITDA | C32: =+SUM(C28+SUM(C31:C31)) -> #REF! | D32: =+SUM(D28+SUM(D31:D31)) -> #REF! | E32: =+SUM(E28+SUM(E31:E31)) -> #REF! | F32: =+SUM(F28+SUM(F31:F31)) -> #REF! | G32: =+SUM(G28+SUM(G31:G31)) -> #REF! | I32: =+SUM(I28+SUM(I31:I31)) -> #REF! | J32: =+SUM(J28+SUM(J31:J31)) -> #REF! | K32: =+SUM(K28+SUM(K31:K31)) -> #REF! | L32: =+SUM(L28+SUM(L31:L31)) -> #REF! | M32: =+SUM(M28+SUM(M31:M31)) -> #REF! | N32: =+SUM(N28+SUM(N31:N31)) -> #REF! | O32: =+SUM(O28+SUM(O31:O31)) -> #REF! | P32: =+SUM(P28+SUM(P31:P31)) -> #REF! | ... W32: =+SUM(W28+SUM(W31:W31)) -> #REF! | Y32: =+SUM(Y28+SUM(Y31:Y31)) -> -3.753 | Z32: =+SUM(Z28+SUM(Z31:Z31)) -> -7.242 | AA32: =+SUM(AA28+SUM(AA31:AA31)) -> -7.442 | AB32: =+SUM(AB28+SUM(AB31:AB31)) -> -8.022 | AC32: =+SUM(AC28+SUM(AC31:AC31)) -> -10.519 | AD32: =+SUM(AD28+SUM(AD31:AD31)) -> -9.831 | AE32: =+SUM(AE28+SUM(AE31:AE31)) -> -9.65 | AF32: =+SUM(AF28+SUM(AF31:AF31)) -> -9.666 | ... AK32: =+SUM(AK28+SUM(AK31:AK31)) -> #REF! | AM32: =SUM(AK32/AG32)-1 -> #REF!
B33: Adj. EBITDA Margin (%) | C33: =C32/C11 -> #REF! | D33: =D32/D11 -> #REF! | E33: =E32/E11 -> #REF! | F33: =F32/F11 -> #REF! | G33: =G32/G11 -> #REF! | I33: =I32/I11 -> #REF! | J33: =J32/J11 -> #REF! | K33: =K32/K11 -> #REF! | L33: =L32/L11 -> #REF! | M33: =M32/M11 -> #REF! | N33: =N32/N11 -> #REF! | O33: =O32/O11 -> #REF! | P33: =P32/P11 -> #REF! | ... W33: =W32/W11 -> #REF! | Y33: =Y32/Y11 -> #DIV/0! | Z33: =Z32/Z11 -> #DIV/0! | AA33: =AA32/AA11 -> #DIV/0! | AB33: =AB32/AB11 -> #DIV/0! | AC33: =AC32/AC11 -> #DIV/0! | AD33: =AD32/AD11 -> #DIV/0! | AE33: =AE32/AE11 -> #DIV/0! | AF33: =AF32/AF11 -> #DIV/0! | ... AK33: =AK32/AK11 -> #REF! | AM33: =SUM(AK33-AG33)*10000 -> #REF!
B35: (-) Capital Expenditures | C35: =('Historical Financials'!C118)/1000 -> -1.407 | D35: =('Historical Financials'!D118)/1000 -> -1.888 | E35: =('Historical Financials'!E118)/1000 -> -2.262 | F35: =('Historical Financials'!F118)/1000 -> -1.45 | G35: =('Historical Financials'!G118)/1000 -> -1.041 | I35: =('Historical Financials'!I118)/1000 -> -0.583 | J35: =('Historical Financials'!J118)/1000 -> -0.491 | K35: =('Historical Financials'!K118)/1000 -> -1.628 | L35: =('Historical Financials'!L118)/1000 -> 0.44 | M35: =('Historical Financials'!M118)/1000 -> -0.398 | N35: =('Historical Financials'!N118)/1000 -> -0.453 | O35: =('Historical Financials'!O118)/1000 -> -0.306 | P35: =('Historical Financials'!P118)/1000 -> -0.293 | ... W35: =('Historical Financials'!W118)/1000 -> 0 | Y35: =SUM(H35:K35) -> -2.702 | Z35: =SUM(I35:L35) -> -2.262 | AA35: =SUM(J35:M35) -> -2.077 | AB35: =SUM(K35:N35) -> -2.039 | AC35: =SUM(L35:O35) -> -0.717 | AD35: =SUM(M35:P35) -> -1.45 | AE35: =SUM(N35:Q35) -> -1.266 | AF35: =SUM(O35:R35) -> -1.211 | ... AK35: =SUM(T35:W35) -> -0.256 | AM35: =SUM(AK35/AG35)-1 -> -0.76252319
B36: (-) Cash Taxes | C36: =-('Historical Financials'!C155)/1000 -> 0 | D36: =-('Historical Financials'!D155)/1000 -> 0 | E36: =-('Historical Financials'!E155)/1000 -> 0 | F36: =-('Historical Financials'!F155)/1000 -> 0 | G36: =-('Historical Financials'!G155)/1000 -> 0 | I36: =('Historical Financials'!I29)/1000 -> -0.466 | J36: =('Historical Financials'!J29)/1000 -> -0.489 | K36: =('Historical Financials'!K29)/1000 -> -0.509 | L36: =('Historical Financials'!L29)/1000 -> -0.548 | M36: =('Historical Financials'!M29)/1000 -> -0.098 | N36: =('Historical Financials'!N29)/1000 -> -0.193 | O36: =('Historical Financials'!O29)/1000 -> -0.022 | P36: =('Historical Financials'!P29)/1000 -> 0.209 | ... W36: =('Historical Financials'!W29)/1000 -> 0 | Y36: =SUM(H36:K36) -> -1.464 | Z36: =SUM(I36:L36) -> -2.012 | AA36: =SUM(J36:M36) -> -1.644 | AB36: =SUM(K36:N36) -> -1.348 | AC36: =SUM(L36:O36) -> -0.861 | AD36: =SUM(M36:P36) -> -0.104 | AE36: =SUM(N36:Q36) -> -0.157 | AF36: =SUM(O36:R36) -> -0.187 | ... AK36: =SUM(T36:W36) -> 0.319 | AM36: =SUM(AK36/AG36)-1 -> -1.9494048
B37: (-) Cash Interest | C37: =-('Historical Financials'!C156)/1000 -> 0 | D37: =-('Historical Financials'!D156)/1000 -> 0 | E37: =-('Historical Financials'!E156)/1000 -> 0 | F37: =-('Historical Financials'!F156)/1000 -> 0 | G37: =-('Historical Financials'!G156)/1000 -> 0 | I37: =('Historical Financials'!I24)/1000 -> 0.017 | J37: =('Historical Financials'!J24)/1000 -> 0.02 | K37: =('Historical Financials'!K24)/1000 -> 0.022 | L37: =('Historical Financials'!L24)/1000 -> 0.032 | M37: =('Historical Financials'!M24)/1000 -> 0.055 | N37: =('Historical Financials'!N24)/1000 -> 0.059 | O37: =('Historical Financials'!O24)/1000 -> 0.079 | P37: =('Historical Financials'!P24)/1000 -> 0.12 | ... W37: =('Historical Financials'!W24)/1000 -> 0 | Y37: =SUM(H37:K37) -> 0.059 | Z37: =SUM(I37:L37) -> 0.091 | AA37: =SUM(J37:M37) -> 0.129 | AB37: =SUM(K37:N37) -> 0.168 | AC37: =SUM(L37:O37) -> 0.225 | AD37: =SUM(M37:P37) -> 0.313 | AE37: =SUM(N37:Q37) -> 0.407 | AF37: =SUM(O37:R37) -> 0.508 | ... AK37: =SUM(T37:W37) -> 0.184 | AM37: =SUM(AK37/AG37)-1 -> -0.69885434
B38: (+/-) Changes in NWC | C38: =SUM('Historical Financials'!C109:C114)/1000 -> -1.607 | D38: =SUM('Historical Financials'!D109:D114)/1000 -> -0.461 | E38: =SUM('Historical Financials'!E109:E114)/1000 -> -7.8 | F38: =SUM('Historical Financials'!F109:F114)/1000 -> 1.148 | G38: =SUM('Historical Financials'!G109:G114)/1000 -> 1.223 | I38: =SUM('Historical Financials'!I109:I114)/1000 -> -2.388 | J38: =SUM('Historical Financials'!J109:J114)/1000 -> -0.793 | K38: =SUM('Historical Financials'!K109:K114)/1000 -> -5.335 | L38: =SUM('Historical Financials'!L109:L114)/1000 -> 0.716 | M38: =SUM('Historical Financials'!M109:M114)/1000 -> -0.004 | N38: =SUM('Historical Financials'!N109:N114)/1000 -> -0.929 | O38: =SUM('Historical Financials'!O109:O114)/1000 -> 0.38 | P38: =SUM('Historical Financials'!P109:P114)/1000 -> 1.701 | ... W38: =SUM('Historical Financials'!W109:W114)/1000 -> 0 | Y38: =SUM(H38:K38) -> -8.516 | Z38: =SUM(I38:L38) -> -7.8 | AA38: =SUM(J38:M38) -> -5.416 | AB38: =SUM(K38:N38) -> -5.552 | AC38: =SUM(L38:O38) -> 0.163 | AD38: =SUM(M38:P38) -> 1.148 | AE38: =SUM(N38:Q38) -> 1.341 | AF38: =SUM(O38:R38) -> 3.438 | ... AK38: =SUM(T38:W38) -> -0.859 | AM38: =SUM(AK38/AG38)-1 -> -1.2270685
B39: Discretionary Cash-Flows | C39: =SUM(C32+SUM(C35:C38)) -> #REF! | D39: =SUM(D32+SUM(D35:D38)) -> #REF! | E39: =SUM(E32+SUM(E35:E38)) -> #REF! | F39: =SUM(F32+SUM(F35:F38)) -> #REF! | G39: =SUM(G32+SUM(G35:G38)) -> #REF! | I39: =SUM(I32+SUM(I35:I38)) -> #REF! | J39: =SUM(J32+SUM(J35:J38)) -> #REF! | K39: =SUM(K32+SUM(K35:K38)) -> #REF! | L39: =SUM(L32+SUM(L35:L38)) -> #REF! | M39: =SUM(M32+SUM(M35:M38)) -> #REF! | N39: =SUM(N32+SUM(N35:N38)) -> #REF! | O39: =SUM(O32+SUM(O35:O38)) -> #REF! | P39: =SUM(P32+SUM(P35:P38)) -> #REF! | ... W39: =SUM(W32+SUM(W35:W38)) -> #REF! | Y39: =SUM(Y32+SUM(Y35:Y38)) -> -16.376 | Z39: =SUM(Z32+SUM(Z35:Z38)) -> -19.225 | AA39: =SUM(AA32+SUM(AA35:AA38)) -> -16.45 | AB39: =SUM(AB32+SUM(AB35:AB38)) -> -16.793 | AC39: =SUM(AC32+SUM(AC35:AC38)) -> -11.709 | AD39: =SUM(AD32+SUM(AD35:AD38)) -> -9.924 | AE39: =SUM(AE32+SUM(AE35:AE38)) -> -9.325 | AF39: =SUM(AF32+SUM(AF35:AF38)) -> -7.118 | ... AK39: =SUM(AK32+SUM(AK35:AK38)) -> #REF! | AM39: =SUM(AK39/AG39)-1 -> #REF!
B41: (+/-) Proceeds / (Purchases) of ST Investments | C41: =SUM('Historical Financials'!C125:C125)/1000 -> 0 | D41: =SUM('Historical Financials'!D125:D125)/1000 -> 0 | E41: =SUM('Historical Financials'!E125:E125)/1000 -> -0.016 | F41: =SUM('Historical Financials'!F125:F125)/1000 -> 1.383 | G41: =SUM('Historical Financials'!G125:G125)/1000 -> 0.002 | I41: =SUM('Historical Financials'!I125:I125)/1000 -> 0 | J41: =SUM('Historical Financials'!J125:J125)/1000 -> 0 | K41: =SUM('Historical Financials'!K125:K125)/1000 -> 0 | L41: =SUM('Historical Financials'!L125:L125)/1000 -> -0.016 | M41: =SUM('Historical Financials'!M125:M125)/1000 -> 0 | N41: =SUM('Historical Financials'!N125:N125)/1000 -> -0.042 | O41: =SUM('Historical Financials'!O125:O125)/1000 -> 1.437 | P41: =SUM('Historical Financials'!P125:P125)/1000 -> -0.012 | ... W41: =SUM('Historical Financials'!W125:W125)/1000 -> 0 | Y41: =SUM(H41:K41) -> 0 | Z41: =SUM(I41:L41) -> -0.016 | AA41: =SUM(J41:M41) -> -0.016 | AB41: =SUM(K41:N41) -> -0.058 | AC41: =SUM(L41:O41) -> 1.379 | AD41: =SUM(M41:P41) -> 1.383 | AE41: =SUM(N41:Q41) -> 1.383 | AF41: =SUM(O41:R41) -> 1.425 | ... AK41: =SUM(T41:W41) -> 0.004
B42: (+/-) Divestiture / Acquisitions | C42: =('Historical Financials'!C124)/1000 -> 0.043 | D42: =('Historical Financials'!D124)/1000 -> -0.059 | E42: =('Historical Financials'!E124)/1000 -> 0.041 | F42: =('Historical Financials'!F124)/1000 -> 0.019 | G42: =('Historical Financials'!G124)/1000 -> -0.036 | I42: =('Historical Financials'!I124)/1000 -> 0 | J42: =('Historical Financials'!J124)/1000 -> 0 | K42: =('Historical Financials'!K124)/1000 -> 0.041 | L42: =('Historical Financials'!L124)/1000 -> 0 | M42: =('Historical Financials'!M124)/1000 -> -0.018 | N42: =('Historical Financials'!N124)/1000 -> 0.014 | O42: =('Historical Financials'!O124)/1000 -> 0.022 | P42: =('Historical Financials'!P124)/1000 -> 0.001 | ... W42: =('Historical Financials'!W124)/1000 -> 0 | Y42: =SUM(H42:K42) -> 0.041 | Z42: =SUM(I42:L42) -> 0.041 | AA42: =SUM(J42:M42) -> 0.023 | AB42: =SUM(K42:N42) -> 0.037 | AC42: =SUM(L42:O42) -> 0.018 | AD42: =SUM(M42:P42) -> 0.019 | AE42: =SUM(N42:Q42) -> 0.039 | AF42: =SUM(O42:R42) -> -0.013 | ... AK42: =SUM(T42:W42) -> 0
B43: (-) Proceeds From Equity Issuances / (Share Repurchases) | C43: =SUM('Historical Financials'!#REF!)/1000 -> #REF! | D43: =SUM('Historical Financials'!#REF!)/1000 -> #REF! | E43: =SUM('Historical Financials'!#REF!)/1000 -> #REF! | F43: =SUM('Historical Financials'!#REF!)/1000 -> #REF! | G43: =SUM('Historical Financials'!#REF!)/1000 -> #REF! | I43: =SUM('Historical Financials'!#REF!)/1000 -> #REF! | J43: =SUM('Historical Financials'!#REF!)/1000 -> #REF! | K43: =SUM('Historical Financials'!#REF!)/1000 -> #REF! | L43: =SUM('Historical Financials'!#REF!)/1000 -> #REF! | M43: =SUM('Historical Financials'!#REF!)/1000 -> #REF! | N43: =SUM('Historical Financials'!#REF!)/1000 -> #REF! | O43: =SUM('Historical Financials'!#REF!)/1000 -> #REF! | P43: =SUM('Historical Financials'!#REF!)/1000 -> #REF! | ... W43: =SUM('Historical Financials'!#REF!)/1000 -> #REF! | AG43: =SUM(P43:S43) -> #REF! | AH43: =SUM(Q43:T43) -> #REF! | AI43: =SUM(R43:U43) -> #REF! | AJ43: =SUM(S43:V43) -> #REF! | AK43: =SUM(T43:W43) -> #REF!
B44: (-) 'Proceeds from issuance of Debt / (Repayment), net | C44: =SUM('Historical Financials'!C129:C131)/1000 -> 0.002 | D44: =SUM('Historical Financials'!D129:D131)/1000 -> 0.001 | E44: =SUM('Historical Financials'!E129:E131)/1000 -> -0.352 | F44: =SUM('Historical Financials'!F129:F131)/1000 -> -0.498 | G44: =SUM('Historical Financials'!G129:G131)/1000 -> 0 | I44: =SUM('Historical Financials'!I129:I131)/1000 -> 0 | J44: =SUM('Historical Financials'!J129:J131)/1000 -> 0 | K44: =SUM('Historical Financials'!K129:K131)/1000 -> -0.35 | L44: =SUM('Historical Financials'!L129:L131)/1000 -> -0.002 | M44: =SUM('Historical Financials'!M129:M131)/1000 -> -0.497 | N44: =SUM('Historical Financials'!N129:N131)/1000 -> 0.497 | O44: =SUM('Historical Financials'!O129:O131)/1000 -> -0.498 | P44: =SUM('Historical Financials'!P129:P131)/1000 -> 0 | ... W44: =SUM('Historical Financials'!W129:W131)/1000 -> 0 | AG44: =SUM(P44:S44) -> 0 | AH44: =SUM(Q44:T44) -> 0 | AI44: =SUM(R44:U44) -> 0 | AJ44: =SUM(S44:V44) -> 0 | AK44: =SUM(T44:W44) -> 0
B45: (+/-) Changes in Additions to content assets | C45: =SUM('Historical Financials'!C100:C101)/1000 -> 1.393 | D45: =SUM('Historical Financials'!D100:D101)/1000 -> 1.582 | E45: =SUM('Historical Financials'!E100:E101)/1000 -> 1.764 | F45: =SUM('Historical Financials'!F100:F101)/1000 -> 1.991 | G45: =SUM('Historical Financials'!G100:G101)/1000 -> 1.713 | I45: =SUM('Historical Financials'!I100:I101)/1000 -> 0.406 | J45: =SUM('Historical Financials'!J100:J101)/1000 -> 0.428 | K45: =SUM('Historical Financials'!K100:K101)/1000 -> 1.272 | L45: =SUM('Historical Financials'!L100:L101)/1000 -> -0.342 | M45: =SUM('Historical Financials'!M100:M101)/1000 -> 0.398 | N45: =SUM('Historical Financials'!N100:N101)/1000 -> 0.47 | O45: =SUM('Historical Financials'!O100:O101)/1000 -> 0.479 | P45: =SUM('Historical Financials'!P100:P101)/1000 -> 0.644 | ... W45: =SUM('Historical Financials'!W100:W101)/1000 -> 0 | AF45: =SUM(O45:R45) -> 1.971 | AG45: =SUM(P45:S45) -> 1.911 | AH45: =SUM(Q45:T45) -> 1.713 | AI45: =SUM(R45:U45) -> 1.276 | AJ45: =SUM(S45:V45) -> 0.865 | AK45: =SUM(T45:W45) -> 0.446
B46: (+/-) Changes in Other Financing Activities | C46: =SUM('Historical Financials'!#REF!)/1000 -> #REF! | D46: =SUM('Historical Financials'!#REF!)/1000 -> #REF! | E46: =SUM('Historical Financials'!#REF!)/1000 -> #REF! | F46: =SUM('Historical Financials'!#REF!)/1000 -> #REF! | G46: =SUM('Historical Financials'!#REF!)/1000 -> #REF! | I46: =SUM('Historical Financials'!#REF!)/1000 -> #REF! | J46: =SUM('Historical Financials'!#REF!)/1000 -> #REF! | K46: =SUM('Historical Financials'!#REF!)/1000 -> #REF! | L46: =SUM('Historical Financials'!#REF!)/1000 -> #REF! | M46: =SUM('Historical Financials'!#REF!)/1000 -> #REF! | N46: =SUM('Historical Financials'!#REF!)/1000 -> #REF! | O46: =SUM('Historical Financials'!#REF!)/1000 -> #REF! | P46: =SUM('Historical Financials'!#REF!)/1000 -> #REF! | ... W46: =SUM('Historical Financials'!#REF!)/1000 -> #REF! | AG46: =SUM(P46:S46) -> #REF! | AH46: =SUM(Q46:T46) -> #REF! | AI46: =SUM(R46:U46) -> #REF! | AJ46: =SUM(S46:V46) -> #REF! | AK46: =SUM(T46:W46) -> #REF!
B47: (+/-) Other | D47: =SUM(D52-C52)-SUM(D39:D45) -> #REF! | E47: =SUM(E52-D52)-SUM(E39:E45) -> #REF! | F47: =SUM(F52-E52)-SUM(F39:F45) -> #REF! | G47: =SUM(G52-F52)-SUM(G39:G46) -> #REF! | I47: =SUM(I52-D52)-SUM(I39:I46) -> #REF! | J47: =SUM(J52-I52)-SUM(J39:J46) -> #REF! | K47: =SUM(K52-J52)-SUM(K39:K46) -> #REF! | L47: =SUM(L52-K52)-SUM(L39:L46) -> #REF! | M47: =SUM(M52-L52)-SUM(M39:M46) -> #REF! | N47: =SUM(N52-M52)-SUM(N39:N46) -> #REF! | O47: =SUM(O52-N52)-SUM(O39:O46) -> #REF! | P47: =SUM(P52-O52)-SUM(P39:P46) -> #REF! | Q47: =SUM(Q52-P52)-SUM(Q39:Q46) -> #REF! | ... W47: =SUM(W52-V52)-SUM(W39:W46) -> #REF! | Y47: =SUM(H47:K47) -> #REF! | Z47: =SUM(I47:L47) -> #REF! | AA47: =SUM(J47:M47) -> #REF! | AB47: =SUM(K47:N47) -> #REF! | AC47: =SUM(L47:O47) -> #REF! | AD47: =SUM(M47:P47) -> #REF! | AE47: =SUM(N47:Q47) -> #REF! | AF47: =SUM(O47:R47) -> #REF! | ... AK47: =SUM(T47:W47) -> #REF!
B48: Free-Cash Flows | C48: =SUM(C39+SUM(C41:C47)) -> #REF! | D48: =SUM(D39+SUM(D41:D47)) -> #REF! | E48: =SUM(E39+SUM(E41:E47)) -> #REF! | F48: =SUM(F39+SUM(F41:F47)) -> #REF! | G48: =SUM(G39+SUM(G41:G47)) -> #REF! | I48: =SUM(I39+SUM(I41:I47)) -> #REF! | J48: =SUM(J39+SUM(J41:J47)) -> #REF! | K48: =SUM(K39+SUM(K41:K47)) -> #REF! | L48: =SUM(L39+SUM(L41:L47)) -> #REF! | M48: =SUM(M39+SUM(M41:M47)) -> #REF! | N48: =SUM(N39+SUM(N41:N47)) -> #REF! | O48: =SUM(O39+SUM(O41:O47)) -> #REF! | P48: =SUM(P39+SUM(P41:P47)) -> #REF! | ... W48: =SUM(W39+SUM(W41:W47)) -> #REF! | Y48: =SUM(Y39+SUM(Y41:Y47)) -> #REF! | Z48: =SUM(Z39+SUM(Z41:Z47)) -> #REF! | AA48: =SUM(AA39+SUM(AA41:AA47)) -> #REF! | AB48: =SUM(AB39+SUM(AB41:AB47)) -> #REF! | AC48: =SUM(AC39+SUM(AC41:AC47)) -> #REF! | AD48: =SUM(AD39+SUM(AD41:AD47)) -> #REF! | AE48: =SUM(AE39+SUM(AE41:AE47)) -> #REF! | AF48: =SUM(AF39+SUM(AF41:AF47)) -> #REF! | ... AK48: =SUM(AK39+SUM(AK41:AK47)) -> #REF!
B50: Capitalization
B52: Cash & Cash Equivelants | C52: =('Historical Financials'!C48)/1000 -> 6.707 | D52: =('Historical Financials'!D48)/1000 -> 7.116 | E52: =('Historical Financials'!E48)/1000 -> 2.773 | F52: =('Historical Financials'!F48)/1000 -> 8.45 | G52: =('Historical Financials'!G48)/1000 -> 7.849 | I52: =('Historical Financials'!I48)/1000 -> 6.607 | J52: =('Historical Financials'!J48)/1000 -> 7.173 | K52: =('Historical Financials'!K48)/1000 -> 2.676 | L52: =('Historical Financials'!L48)/1000 -> 2.773 | M52: =('Historical Financials'!M48)/1000 -> 4.808 | N52: =('Historical Financials'!N48)/1000 -> 3.488 | O52: =('Historical Financials'!O48)/1000 -> 6.087 | P52: =('Historical Financials'!P48)/1000 -> 8.45 | ... W52: =('Historical Financials'!W48)/1000 -> 0 | Y52: =K52 -> 2.676 | Z52: =L52 -> 2.773 | AA52: =M52 -> 4.808 | AB52: =N52 -> 3.488 | AC52: =O52 -> 6.087 | AD52: =P52 -> 8.45 | AE52: =Q52 -> 8.133 | AF52: =R52 -> 9.219 | ... AK52: =W52 -> 0
B53: Marketable Securities | C53: =('Historical Financials'!#REF!)/1000 -> #REF! | D53: =('Historical Financials'!#REF!)/1000 -> #REF! | E53: =('Historical Financials'!#REF!)/1000 -> #REF! | F53: =('Historical Financials'!#REF!)/1000 -> #REF! | G53: =('Historical Financials'!#REF!)/1000 -> #REF! | I53: =('Historical Financials'!#REF!)/1000 -> #REF! | J53: =('Historical Financials'!#REF!)/1000 -> #REF! | K53: =('Historical Financials'!#REF!)/1000 -> #REF! | L53: =('Historical Financials'!#REF!)/1000 -> #REF! | M53: =('Historical Financials'!#REF!)/1000 -> #REF! | N53: =('Historical Financials'!#REF!)/1000 -> #REF! | O53: =('Historical Financials'!#REF!)/1000 -> #REF! | P53: =('Historical Financials'!#REF!)/1000 -> #REF! | ... W53: =('Historical Financials'!#REF!)/1000 -> #REF! | AG53: =S53 -> #REF! | AH53: =T53 -> #REF! | AI53: =U53 -> #REF! | AJ53: =V53 -> #REF! | AK53: =W53 -> #REF!
B54: $3Bn RCF due April 2025, April 2029 (CP Backstop) | C54: 750 | D54: 1000 | E54: 1000 | F54: 1000 | G54: 3000 | I54: 1000 | J54: 1000 | K54: 1000 | L54: =E54 -> 1000 | M54: 1000 | N54: 1000 | O54: 1000 | P54: =F54 -> 1000 | Q54: 3000 | R54: 3000 | S54: 3000 | T54: =G54 -> 3000 | U54: 3000 | V54: 3000 | W54: 3000 | AG54: =S54 -> 3000 | AH54: =T54 -> 3000 | AI54: =U54 -> 3000 | AJ54: =V54 -> 3000 | AK54: =W54 -> 3000
B55: Total Liquidity | C55: =SUM(C52:C54) -> #REF! | D55: =SUM(D52:D54) -> #REF! | E55: =SUM(E52:E54) -> #REF! | F55: =SUM(F52:F54) -> #REF! | G55: =SUM(G52:G54) -> #REF! | I55: =SUM(I52:I54) -> #REF! | J55: =SUM(J52:J54) -> #REF! | K55: =SUM(K52:K54) -> #REF! | L55: =SUM(L52:L54) -> #REF! | M55: =SUM(M52:M54) -> #REF! | N55: =SUM(N52:N54) -> #REF! | O55: =SUM(O52:O54) -> #REF! | P55: =SUM(P52:P54) -> #REF! | ... W55: =SUM(W52:W54) -> #REF! | Y55: =SUM(Y52:Y52) -> 2.676 | Z55: =SUM(Z52:Z52) -> 2.773 | AA55: =SUM(AA52:AA52) -> 4.808 | AB55: =SUM(AB52:AB52) -> 3.488 | AC55: =SUM(AC52:AC52) -> 6.087 | AD55: =SUM(AD52:AD52) -> 8.45 | AE55: =SUM(AE52:AE52) -> 8.133 | AF55: =SUM(AF52:AF52) -> 9.219 | AG55: =SUM(AG52:AG54) -> #REF! | AH55: =SUM(AH52:AH54) -> #REF! | AI55: =SUM(AI52:AI54) -> #REF! | AJ55: =SUM(AJ52:AJ54) -> #REF! | AK55: =SUM(AK52:AK54) -> #REF!
B57: Balance Sheet Metrics:
B58: Property and Equipment, net | C58: =('Historical Financials'!#REF!)/1000 -> #REF! | D58: =('Historical Financials'!#REF!)/1000 -> #REF! | E58: =('Historical Financials'!#REF!)/1000 -> #REF! | F58: =('Historical Financials'!#REF!)/1000 -> #REF! | G58: =('Historical Financials'!#REF!)/1000 -> #REF! | I58: =('Historical Financials'!#REF!)/1000 -> #REF! | J58: =('Historical Financials'!#REF!)/1000 -> #REF! | K58: =('Historical Financials'!#REF!)/1000 -> #REF! | L58: =('Historical Financials'!#REF!)/1000 -> #REF! | M58: =('Historical Financials'!#REF!)/1000 -> #REF! | N58: =('Historical Financials'!#REF!)/1000 -> #REF! | O58: =('Historical Financials'!#REF!)/1000 -> #REF! | P58: =('Historical Financials'!#REF!)/1000 -> #REF! | ... W58: =('Historical Financials'!#REF!)/1000 -> #REF! | Y58: =K58 -> #REF! | Z58: =L58 -> #REF! | AA58: =M58 -> #REF! | AB58: =N58 -> #REF! | AC58: =O58 -> #REF! | AD58: =P58 -> #REF! | AE58: =Q58 -> #REF! | AF58: =R58 -> #REF! | ... AK58: =W58 -> #REF!
B59: Content Liabilities | C59: =('Historical Financials'!C66)/1000 -> 2.248 | D59: =('Historical Financials'!D66)/1000 -> 2.75 | E59: =('Historical Financials'!E66)/1000 -> 3.796 | F59: =('Historical Financials'!F66)/1000 -> 1.912 | G59: =('Historical Financials'!G66)/1000 -> 2.584 | I59: =('Historical Financials'!I66)/1000 -> 3.526 | J59: =('Historical Financials'!J66)/1000 -> 3.724 | K59: =('Historical Financials'!K66)/1000 -> 3.752 | L59: =('Historical Financials'!L66)/1000 -> 3.796 | M59: =('Historical Financials'!M66)/1000 -> 2.562 | N59: =('Historical Financials'!N66)/1000 -> 1.43 | O59: =('Historical Financials'!O66)/1000 -> 1.744 | P59: =('Historical Financials'!P66)/1000 -> 1.912 | ... W59: =('Historical Financials'!W66)/1000 -> 0 | Y59: =K59 -> 3.752 | Z59: =L59 -> 3.796 | AA59: =M59 -> 2.562 | AB59: =N59 -> 1.43 | AC59: =O59 -> 1.744 | AD59: =P59 -> 1.912 | AE59: =Q59 -> 2.147 | AF59: =R59 -> 2.314 | ... AK59: =W59 -> 0
B60: Accounts Payable | C60: =('Historical Financials'!C68)/1000 -> 0.568 | D60: =('Historical Financials'!D68)/1000 -> 0.612 | E60: =('Historical Financials'!E68)/1000 -> 0.369 | F60: =('Historical Financials'!F68)/1000 -> 0.293 | G60: =('Historical Financials'!G68)/1000 -> 0.297 | I60: =('Historical Financials'!I68)/1000 -> 0.604 | J60: =('Historical Financials'!J68)/1000 -> 0.534 | K60: =('Historical Financials'!K68)/1000 -> 0.463 | L60: =('Historical Financials'!L68)/1000 -> 0.369 | M60: =('Historical Financials'!M68)/1000 -> 0.289 | N60: =('Historical Financials'!N68)/1000 -> 0.277 | O60: =('Historical Financials'!O68)/1000 -> 0.249 | P60: =('Historical Financials'!P68)/1000 -> 0.293 | ... W60: =('Historical Financials'!W68)/1000 -> 0 | AG60: =S60 -> 0.263 | AH60: =T60 -> 0.297 | AI60: =U60 -> 0 | AJ60: =V60 -> 0 | AK60: =W60 -> 0
B61: Deferred Revenue | C61: =('Historical Financials'!C70)/1000 -> 0 | D61: =('Historical Financials'!D70)/1000 -> 0 | E61: =('Historical Financials'!E70)/1000 -> 0.581 | F61: =('Historical Financials'!F70)/1000 -> 0.333 | G61: =('Historical Financials'!G70)/1000 -> 0 | I61: =('Historical Financials'!I70)/1000 -> 0 | J61: =('Historical Financials'!J70)/1000 -> 0 | K61: =('Historical Financials'!K70)/1000 -> 0.677 | L61: =('Historical Financials'!L70)/1000 -> 0.581 | M61: =('Historical Financials'!M70)/1000 -> 0.646 | N61: =('Historical Financials'!N70)/1000 -> 0.648 | O61: =('Historical Financials'!O70)/1000 -> 0.3 | P61: =('Historical Financials'!P70)/1000 -> 0.333 | ... W61: =('Historical Financials'!W70)/1000 -> 0 | AG61: =S61 -> 0 | AH61: =T61 -> 0 | AI61: =U61 -> 0 | AJ61: =V61 -> 0 | AK61: =W61 -> 0
B62: Current Liabilities | C62: =('Historical Financials'!C72)/1000 -> 8.672 | D62: =('Historical Financials'!D72)/1000 -> 11.951 | E62: =('Historical Financials'!E72)/1000 -> 11.866 | F62: =('Historical Financials'!F72)/1000 -> 9.628 | G62: =('Historical Financials'!G72)/1000 -> 10.504 | I62: =('Historical Financials'!I72)/1000 -> 12.273 | J62: =('Historical Financials'!J72)/1000 -> 13.432 | K62: =('Historical Financials'!K72)/1000 -> 11.829 | L62: =('Historical Financials'!L72)/1000 -> 11.866 | M62: =('Historical Financials'!M72)/1000 -> 10.081 | N62: =('Historical Financials'!N72)/1000 -> 7.866 | O62: =('Historical Financials'!O72)/1000 -> 8.463 | P62: =('Historical Financials'!P72)/1000 -> 9.628 | ... W62: =('Historical Financials'!W72)/1000 -> 0 | Y62: =K62 -> 11.829 | Z62: =L62 -> 11.866 | AA62: =M62 -> 10.081 | AB62: =N62 -> 7.866 | AC62: =O62 -> 8.463 | AD62: =P62 -> 9.628 | AE62: =Q62 -> 9.169 | AF62: =R62 -> 9.143 | ... AK62: =W62 -> 0
B63: Total Liabilities | C63: =('Historical Financials'!C80)/1000 -> 29.517 | D63: =('Historical Financials'!D80)/1000 -> 31.29 | E63: =('Historical Financials'!E80)/1000 -> 31.001 | F63: =('Historical Financials'!F80)/1000 -> 29.459 | G63: =('Historical Financials'!G80)/1000 -> 28.88 | I63: =('Historical Financials'!I80)/1000 -> 31.487 | J63: =('Historical Financials'!J80)/1000 -> 30.974 | K63: =('Historical Financials'!K80)/1000 -> 30.972 | L63: =('Historical Financials'!L80)/1000 -> 31.001 | M63: =('Historical Financials'!M80)/1000 -> 31.204 | N63: =('Historical Financials'!N80)/1000 -> 28.664 | O63: =('Historical Financials'!O80)/1000 -> 28.332 | P63: =('Historical Financials'!P80)/1000 -> 29.459 | ... W63: =('Historical Financials'!W80)/1000 -> 0 | Y63: =K63 -> 30.972 | Z63: =L63 -> 31.001 | AA63: =M63 -> 31.204 | AB63: =N63 -> 28.664 | AC63: =O63 -> 28.332 | AD63: =P63 -> 29.459 | AE63: =Q63 -> 29.077 | AF63: =R63 -> 28.698 | ... AK63: =W63 -> 0
B65: Summary Debt:
B66: CPLTD | C66: =('Historical Financials'!C71)/1000 -> 4.303 | D66: =('Historical Financials'!D71)/1000 -> 5.014 | E66: =('Historical Financials'!E71)/1000 -> 3.689 | F66: =('Historical Financials'!F71)/1000 -> 4.491 | G66: =('Historical Financials'!G71)/1000 -> 4.425 | I66: =('Historical Financials'!I71)/1000 -> 4.661 | J66: =('Historical Financials'!J71)/1000 -> 4.565 | K66: =('Historical Financials'!K71)/1000 -> 3.414 | L66: =('Historical Financials'!L71)/1000 -> 3.689 | M66: =('Historical Financials'!M71)/1000 -> 3.678 | N66: =('Historical Financials'!N71)/1000 -> 3.785 | O66: =('Historical Financials'!O71)/1000 -> 3.71 | P66: =('Historical Financials'!P71)/1000 -> 4.491 | ... W66: =('Historical Financials'!W71)/1000 -> 0 | AG66: =S66 -> 3.754 | AH66: =T66 -> 4.425 | AI66: =U66 -> 0 | AJ66: =V66 -> 0 | AK66: =W66 -> 0
B67: LTD | C67: =('Historical Financials'!C79)/1000 -> 2.986 | D67: =('Historical Financials'!D79)/1000 -> 3.561 | E67: =('Historical Financials'!E79)/1000 -> 3.863 | F67: =('Historical Financials'!F79)/1000 -> 5.21 | G67: =('Historical Financials'!G79)/1000 -> 5.018 | I67: =('Historical Financials'!I79)/1000 -> 3.562 | J67: =('Historical Financials'!J79)/1000 -> 3.64 | K67: =('Historical Financials'!K79)/1000 -> 3.755 | L67: =('Historical Financials'!L79)/1000 -> 3.863 | M67: =('Historical Financials'!M79)/1000 -> 4.004 | N67: =('Historical Financials'!N79)/1000 -> 4.008 | O67: =('Historical Financials'!O79)/1000 -> 4.113 | P67: =('Historical Financials'!P79)/1000 -> 5.21 | ... W67: =('Historical Financials'!W79)/1000 -> 0 | AG67: =S67 -> 4.5 | AH67: =T67 -> 5.018 | AI67: =U67 -> 0 | AJ67: =V67 -> 0 | AK67: =W67 -> 0
B69: $3Bn Commercial Paper Program | C69: 0 | D69: 0 | E69: 0 | F69: 0 | G69: 0 | I69: 0 | J69: 0 | K69: 0 | L69: =E69 -> 0 | M69: 0 | N69: 0 | O69: 0 | P69: =F69 -> 0 | Q69: 0 | R69: 0 | S69: 0 | T69: =G69 -> 0 | U69: 0 | V69: 0 | W69: 0 | Y69: =K69 -> 0 | Z69: =L69 -> 0 | AA69: =M69 -> 0 | AB69: =N69 -> 0 | AC69: =O69 -> 0 | AD69: =P69 -> 0 | AE69: =Q69 -> 0 | AF69: =R69 -> 0 | ... AK69: =W69 -> 0
B70: Consolidated Sr. Notes | C70: ='Debt Schedule'!C25 -> 16416 | D70: ='Debt Schedule'!D25 -> 15485 | E70: ='Debt Schedule'!E25 -> 14432 | F70: ='Debt Schedule'!F25 -> 14608 | G70: ='Debt Schedule'!G25 -> 15653 | I70: ='Debt Schedule'!I25 -> 14623 | J70: ='Debt Schedule'!J25 -> 14318 | K70: ='Debt Schedule'!K25 -> 13970 | L70: ='Debt Schedule'!L25 -> 14432 | M70: ='Debt Schedule'!M25 -> 14513 | N70: ='Debt Schedule'!N25 -> 14542 | O70: ='Debt Schedule'!O25 -> 14368 | P70: ='Debt Schedule'!P25 -> 14608 | ... W70: ='Debt Schedule'!W25 -> 14523 | Y70: =K70 -> 13970 | Z70: =L70 -> 14432 | AA70: =M70 -> 14513 | AB70: =N70 -> 14542 | AC70: =O70 -> 14368 | AD70: =P70 -> 14608 | AE70: =Q70 -> 14077 | AF70: =R70 -> 14038 | ... AK70: =W70 -> 14523
B71: Total Debt | C71: =SUM(C70:C70) -> 16416 | D71: =SUM(D70:D70) -> 15485 | E71: =SUM(E70:E70) -> 14432 | F71: =SUM(F70:F70) -> 14608 | G71: =SUM(G70:G70) -> 15653 | I71: =SUM(I70:I70) -> 14623 | J71: =SUM(J70:J70) -> 14318 | K71: =SUM(K70:K70) -> 13970 | L71: =SUM(L70:L70) -> 14432 | M71: =SUM(M70:M70) -> 14513 | N71: =SUM(N70:N70) -> 14542 | O71: =SUM(O70:O70) -> 14368 | P71: =SUM(P70:P70) -> 14608 | ... W71: =SUM(W70:W70) -> 14523 | Y71: =SUM(Y70:Y70) -> 13970 | Z71: =SUM(Z70:Z70) -> 14432 | AA71: =SUM(AA70:AA70) -> 14513 | AB71: =SUM(AB70:AB70) -> 14542 | AC71: =SUM(AC70:AC70) -> 14368 | AD71: =SUM(AD70:AD70) -> 14608 | AE71: =SUM(AE70:AE70) -> 14077 | AF71: =SUM(AF70:AF70) -> 14038 | ... AK71: =SUM(AK70:AK70) -> 14523
B73: Total Shareholder Equity | C73: =('Historical Financials'!C86)/1000 -> 6.077 | D73: =('Historical Financials'!D86)/1000 -> 9.95 | E73: =('Historical Financials'!E86)/1000 -> 18.013 | F73: =('Historical Financials'!F86)/1000 -> 21.581 | G73: =('Historical Financials'!G86)/1000 -> 26.274 | I73: =('Historical Financials'!I86)/1000 -> 11.333 | J73: =('Historical Financials'!J86)/1000 -> 13.328 | K73: =('Historical Financials'!K86)/1000 -> 16.048 | L73: =('Historical Financials'!L86)/1000 -> 18.013 | M73: =('Historical Financials'!M86)/1000 -> 18.81 | N73: =('Historical Financials'!N86)/1000 -> 19.698 | O73: =('Historical Financials'!O86)/1000 -> 20.67 | P73: =('Historical Financials'!P86)/1000 -> 21.581 | ... W73: =('Historical Financials'!W86)/1000 -> 0 | Y73: =K73 -> 16.048 | Z73: =L73 -> 18.013 | AA73: =M73 -> 18.81 | AB73: =N73 -> 19.698 | AC73: =O73 -> 20.67 | AD73: =P73 -> 21.581 | AE73: =Q73 -> 23.058 | AF73: =R73 -> 24.469 | ... AK73: =W73 -> 0
B74: Total Book Capitalization | C74: =SUM(C71:C73) -> 16422.077 | D74: =SUM(D71:D73) -> 15494.95 | E74: =SUM(E71:E73) -> 14450.013 | F74: =SUM(F71:F73) -> 14629.581 | G74: =SUM(G71:G73) -> 15679.274 | I74: =SUM(I71:I73) -> 14634.333 | J74: =SUM(J71:J73) -> 14331.328 | K74: =SUM(K71:K73) -> 13986.048 | L74: =SUM(L71:L73) -> 14450.013 | M74: =SUM(M71:M73) -> 14531.81 | N74: =SUM(N71:N73) -> 14561.698 | O74: =SUM(O71:O73) -> 14388.67 | P74: =SUM(P71:P73) -> 14629.581 | ... W74: =SUM(W71:W73) -> 14523 | Y74: =SUM(Y71:Y73) -> 13986.048 | Z74: =SUM(Z71:Z73) -> 14450.013 | AA74: =SUM(AA71:AA73) -> 14531.81 | AB74: =SUM(AB71:AB73) -> 14561.698 | AC74: =SUM(AC71:AC73) -> 14388.67 | AD74: =SUM(AD71:AD73) -> 14629.581 | AE74: =SUM(AE71:AE73) -> 14100.058 | AF74: =SUM(AF71:AF73) -> 14062.469 | ... AK74: =SUM(AK71:AK73) -> 14523
B76: Credit Metrics
B78: LTM Total Leverage | C78: =C71/C32 -> #REF! | D78: =D71/D32 -> #REF! | E78: =E71/E32 -> #REF! | F78: =F71/F32 -> #REF! | G78: =G71/G32 -> #REF! | L78: =SUM(L71/SUM(I32:L32)) -> #REF! | M78: =SUM(M71/SUM(J32:M32)) -> #REF! | N78: =SUM(N71/SUM(K32:N32)) -> #REF! | O78: =SUM(O71/SUM(L32:O32)) -> #REF! | P78: =SUM(P71/SUM(M32:P32)) -> #REF! | Q78: =SUM(Q71/SUM(N32:Q32)) -> #REF! | R78: =SUM(R71/SUM(O32:R32)) -> #REF! | S78: =SUM(S71/SUM(P32:S32)) -> #REF! | ... W78: =SUM(W71/SUM(T32:W32)) -> #REF! | Y78: =Y71/Y32 -> -3722.3554 | Z78: =Z71/Z32 -> -1992.8197 | AA78: =AA71/AA32 -> -1950.1478 | AB78: =AB71/AB32 -> -1812.7649 | AC78: =AC71/AC32 -> -1365.9093 | AD78: =AD71/AD32 -> -1485.9119 | AE78: =AE71/AE32 -> -1458.7565 | AF78: =AF71/AF32 -> -1452.3071 | ... AK78: =AK71/AK32 -> #REF!
B79: LTM Net Leverage | C79: =SUM(C71-C52)/C32 -> #REF! | D79: =SUM(D71-D52)/D32 -> #REF! | E79: =SUM(E71-E52)/E32 -> #REF! | F79: =SUM(F71-F52)/F32 -> #REF! | G79: =SUM(G71-G52)/G32 -> #REF! | L79: =SUM(L71-L52)/SUM(I32:L32) -> #REF! | M79: =SUM(M71-M52)/SUM(J32:M32) -> #REF! | N79: =SUM(N71-N52)/SUM(K32:N32) -> #REF! | O79: =SUM(O71-O52)/SUM(L32:O32) -> #REF! | P79: =SUM(P71-P52)/SUM(M32:P32) -> #REF! | Q79: =SUM(Q71-Q52)/SUM(N32:Q32) -> #REF! | R79: =SUM(R71-R52)/SUM(O32:R32) -> #REF! | S79: =SUM(S71-S52)/SUM(P32:S32) -> #REF! | ... W79: =SUM(W71-W52)/SUM(T32:W32) -> #REF! | Y79: =SUM(Y71-Y52)/Y32 -> -3721.6424 | Z79: =SUM(Z71-Z52)/Z32 -> -1992.4368 | AA79: =SUM(AA71-AA52)/AA32 -> -1949.5017 | AB79: =SUM(AB71-AB52)/AB32 -> -1812.3301 | AC79: =SUM(AC71-AC52)/AC32 -> -1365.3306 | AD79: =SUM(AD71-AD52)/AD32 -> -1485.0524 | AE79: =SUM(AE71-AE52)/AE32 -> -1457.9137 | AF79: =SUM(AF71-AF52)/AF32 -> -1451.3533 | ... AK79: =SUM(AK71-AK52)/AK32 -> #REF!
B80: LTM Interest Coverage | C80: =C32/-C37 -> #REF! | D80: =D32/-D37 -> #REF! | E80: =E32/-E37 -> #REF! | F80: =F32/-F37 -> #REF! | G80: =G32/-G37 -> #REF! | L80: {=SUM(I32:L32)/SUM(-I37:L37)} -> #REF! | M80: {=SUM(J32:M32)/SUM(-J37:M37)} -> #REF! | N80: {=SUM(K32:N32)/SUM(-K37:N37)} -> #REF! | O80: {=SUM(L32:O32)/SUM(-L37:O37)} -> #REF! | P80: {=SUM(M32:P32)/SUM(-M37:P37)} -> #REF! | Q80: {=SUM(N32:Q32)/SUM(-N37:Q37)} -> #REF! | R80: {=SUM(O32:R32)/SUM(-O37:R37)} -> #REF! | S80: {=SUM(P32:S32)/SUM(-P37:S37)} -> #REF! | ... W80: {=SUM(T32:W32)/SUM(-T37:W37)} -> #REF! | Y80: =Y32/-Y37 -> 63.610169 | Z80: =Z32/-Z37 -> 79.582418 | AA80: =AA32/-AA37 -> 57.689922 | AB80: =AB32/-AB37 -> 47.75 | AC80: =AC32/-AC37 -> 46.751111 | AD80: =AD32/-AD37 -> 31.408946 | AE80: =AE32/-AE37 -> 23.710074 | AF80: =AF32/-AF37 -> 19.027559 | ... AK80: =AK32/-AK37 -> #REF!
B81: LTM Debt Service Coverage | C81: {=SUM(C32+C35)/SUM(-C36:C37)} -> #REF! | D81: {=SUM(D32+D35)/SUM(-D36:D37)} -> #REF! | E81: {=SUM(E32+E35)/SUM(-E36:E37)} -> #REF! | F81: {=SUM(F32+F35)/SUM(-F36:F37)} -> #REF! | G81: {=SUM(G32+G35)/SUM(-G36:G37)} -> #REF! | L81: {=SUM(I32:L32+I35:L35)/SUM(-I36:L37)} -> #REF! | M81: {=SUM(J32:M32+J35:M35)/SUM(-J36:M37)} -> #REF! | N81: {=SUM(K32:N32+K35:N35)/SUM(-K36:N37)} -> #REF! | O81: {=SUM(L32:O32+L35:O35)/SUM(-L36:O37)} -> #REF! | P81: {=SUM(M32:P32+M35:P35)/SUM(-M36:P37)} -> #REF! | Q81: {=SUM(N32:Q32+N35:Q35)/SUM(-N36:Q37)} -> #REF! | R81: {=SUM(O32:R32+O35:R35)/SUM(-O36:R37)} -> #REF! | S81: {=SUM(P32:S32+P35:S35)/SUM(-P36:S37)} -> #REF! | ... W81: {=SUM(T32:W32+T35:W35)/SUM(-T36:W37)} -> #REF! | Y81: {=SUM(Y32+Y35)/SUM(-Y36:Y37)} -> -4.594306 | Z81: {=SUM(Z32+Z35)/SUM(-Z36:Z37)} -> -4.9474232 | AA81: {=SUM(AA32+AA35)/SUM(-AA36:AA37)} -> -6.2831683 | AB81: {=SUM(AB32+AB35)/SUM(-AB36:AB37)} -> -8.5262712 | AC81: {=SUM(AC32+AC35)/SUM(-AC36:AC37)} -> -17.666667 | AD81: {=SUM(AD32+AD35)/SUM(-AD36:AD37)} -> 53.976077 | AE81: {=SUM(AE32+AE35)/SUM(-AE36:AE37)} -> 43.664 | AF81: {=SUM(AF32+AF35)/SUM(-AF36:AF37)} -> 33.884735 | ... AK81: {=SUM(AK32+AK35)/SUM(-AK36:AK37)} -> #REF!
B82: LTM Fixed Charge Coverage | C82: {=SUM(C32)/SUM(-C35:C37)} -> #REF! | D82: {=SUM(D32)/SUM(-D35:D37)} -> #REF! | E82: {=SUM(E32)/SUM(-E35:E37)} -> #REF! | F82: {=SUM(F32)/SUM(-F35:F37)} -> #REF! | G82: {=SUM(G32)/SUM(-G35:G37)} -> #REF! | L82: {=SUM(I32:L32)/SUM(-I35:L37)} -> #REF! | M82: {=SUM(J32:M32)/SUM(-J35:M37)} -> #REF! | N82: {=SUM(K32:N32)/SUM(-K35:N37)} -> #REF! | O82: {=SUM(L32:O32)/SUM(-L35:O37)} -> #REF! | P82: {=SUM(M32:P32)/SUM(-M35:P37)} -> #REF! | Q82: {=SUM(N32:Q32)/SUM(-N35:Q37)} -> #REF! | R82: {=SUM(O32:R32)/SUM(-O35:R37)} -> #REF! | S82: {=SUM(P32:S32)/SUM(-P35:S37)} -> #REF! | ... W82: {=SUM(T32:W32)/SUM(-T35:W37)} -> #REF! | Y82: {=SUM(Y32)/SUM(-Y35:Y37)} -> -0.9138057 | Z82: {=SUM(Z32)/SUM(-Z35:Z37)} -> -1.7312933 | AA82: {=SUM(AA32)/SUM(-AA35:AA37)} -> -2.0718263 | AB82: {=SUM(AB32)/SUM(-AB35:AB37)} -> -2.4920783 | AC82: {=SUM(AC32)/SUM(-AC35:AC37)} -> -7.774575 | AD82: {=SUM(AD32)/SUM(-AD35:AD37)} -> -7.9218372 | AE82: {=SUM(AE32)/SUM(-AE35:AE37)} -> -9.4980315 | AF82: {=SUM(AF32)/SUM(-AF35:AF37)} -> -10.860674 | ... AK82: {=SUM(AK32)/SUM(-AK35:AK37)} -> #REF!
B83: Debt-to-Book Capitalization | C83: =C74/C71 -> 1.0003702 | D83: =D74/D71 -> 1.0006426 | E83: =E74/E71 -> 1.0012481 | F83: =F74/F71 -> 1.0014773 | G83: =G74/G71 -> 1.0016785 | L83: =L74/L71 -> 1.0012481 | M83: =M74/M71 -> 1.0012961 | N83: =N74/N71 -> 1.0013546 | O83: =O74/O71 -> 1.0014386 | P83: =P74/P71 -> 1.0014773 | Q83: =Q74/Q71 -> 1.001638 | R83: =R74/R71 -> 1.0017431 | S83: =S74/S71 -> 1.0015366 | ... W83: =W74/W71 -> 1 | Y83: =Y74/Y71 -> 1.0011487 | Z83: =Z74/Z71 -> 1.0012481 | AA83: =AA74/AA71 -> 1.0012961 | AB83: =AB74/AB71 -> 1.0013546 | AC83: =AC74/AC71 -> 1.0014386 | AD83: =AD74/AD71 -> 1.0014773 | AE83: =AE74/AE71 -> 1.001638 | AF83: =AF74/AF71 -> 1.0017431 | ... AK83: =AK74/AK71 -> 1

Sheet Debt Schedule
B2: ='Historical Financials'!B2 -> Qualcomm (NASDAQ: QCOM) | C2: FYE | E2: FYE | I2: Quarterly | M2: Quarterly | S2: Quarterly | Y2: LTM | AF2: LTM | AG2: LTM
B3: Debt Schedule | C3: ='Historical Financials'!C7 -> 2020 | D3: ='Historical Financials'!D7 -> 2021 | E3: ='Historical Financials'!E7 -> 2022 | F3: ='Historical Financials'!F7 -> 2023 | G3: ='Historical Financials'!G7 -> 2024 | I3: ='Historical Financials'!I7 -> 1Q22 | J3: ='Historical Financials'!J7 -> 2Q22 | K3: ='Historical Financials'!K7 -> 3Q22 | L3: ='Historical Financials'!L7 -> 4Q22 | M3: ='Historical Financials'!M7 -> 1Q23 | N3: ='Historical Financials'!N7 -> 2Q23 | O3: ='Historical Financials'!O7 -> 3Q23 | P3: ='Historical Financials'!P7 -> 4Q23 | ... W3: ='Historical Financials'!W7 -> 3Q25 | Y3: =K3 -> 3Q22 | Z3: =L3 -> 4Q22 | AA3: =M3 -> 1Q23 | AB3: =N3 -> 2Q23 | AC3: =O3 -> 3Q23 | AD3: =P3 -> 4Q23 | AE3: =Q3 -> 1Q24 | AF3: =R3 -> 2Q24 | ... AK3: =W3 -> 3Q25
B4: ($ in Millions) | C4: ='Historical Financials'!C8 -> 44196 | D4: ='Historical Financials'!D8 -> 44561 | E4: ='Historical Financials'!E8 -> 44926 | F4: ='Historical Financials'!F8 -> 45291 | G4: ='Historical Financials'!G8 -> 45657 | I4: ='Historical Financials'!I8 -> 44651 | J4: ='Historical Financials'!J8 -> 44742 | K4: ='Historical Financials'!K8 -> 44834 | L4: ='Historical Financials'!L8 -> 44926 | M4: ='Historical Financials'!M8 -> 45016 | N4: ='Historical Financials'!N8 -> 45107 | O4: ='Historical Financials'!O8 -> 45199 | P4: ='Historical Financials'!P8 -> 45291 | ... W4: ='Historical Financials'!W8 -> 45930 | Y4: =K4 -> 44834 | Z4: =L4 -> 44926 | AA4: =M4 -> 45016 | AB4: =N4 -> 45107 | AC4: =O4 -> 45199 | AD4: =P4 -> 45291 | AE4: =Q4 -> 45382 | AF4: =R4 -> 45473 | ... AK4: =W4 -> 45930
B6: Total Senior Notes
B7: 5.375% Senior Notes due February 2021 | C7: 500 | D7: 0 | E7: 0 | F7: 0 | G7: 0 | I7: 0 | J7: 0 | K7: 0 | L7: =E7 -> 0 | M7: 0 | N7: 0 | O7: 0 | P7: =F7 -> 0 | Q7: 0 | R7: 0 | S7: 0 | T7: =G7 -> 0 | U7: 0 | V7: 0 | W7: 0 | Y7: =K7 -> 0 | Z7: =L7 -> 0 | AA7: =M7 -> 0 | AB7: =N7 -> 0 | AC7: =O7 -> 0 | AD7: =P7 -> 0 | AE7: =Q7 -> 0 | AF7: =R7 -> 0 | ... AK7: =W7 -> 0
B8: 5.500% Senior Notes due February 2022 | C8: 700 | D8: 700 | E8: 0 | F8: 0 | G8: 0 | I8: 0 | J8: 0 | K8: 0 | L8: =E8 -> 0 | M8: 0 | N8: 0 | O8: 0 | P8: =F8 -> 0 | Q8: 0 | R8: 0 | S8: 0 | T8: =G8 -> 0 | U8: 0 | V8: 0 | W8: 0 | Y8: =K8 -> 0 | Z8: =L8 -> 0 | AA8: =M8 -> 0 | AB8: =N8 -> 0 | AC8: =O8 -> 0 | AD8: =P8 -> 0 | AE8: =Q8 -> 0 | AF8: =R8 -> 0 | ... AK8: =W8 -> 0
B9: 5.750% Senior Notes due March 2024 | C9: 400 | D9: 400 | E9: 400 | F9: 400 | G9: 0 | I9: 400 | J9: 400 | K9: 400 | L9: =E9 -> 400 | M9: 400 | N9: 400 | O9: 400 | P9: =F9 -> 400 | Q9: 0 | R9: 0 | S9: 0 | T9: =G9 -> 0 | U9: 0 | V9: 0 | W9: 0 | Y9: =K9 -> 400 | Z9: =L9 -> 400 | AA9: =M9 -> 400 | AB9: =N9 -> 400 | AC9: =O9 -> 400 | AD9: =P9 -> 400 | AE9: =Q9 -> 0 | AF9: =R9 -> 0 | ... AK9: =W9 -> 0
B10: 5.875% Senior Notes due February 2025 | C10: 800 | D10: 800 | E10: 800 | F10: 800 | G10: 800 | I10: 800 | J10: 800 | K10: 800 | L10: =E10 -> 800 | M10: 800 | N10: 800 | O10: 800 | P10: =F10 -> 800 | Q10: 800 | R10: 800 | S10: 800 | T10: =G10 -> 800 | U10: 0 | V10: 0 | W10: 0 | Y10: =K10 -> 800 | Z10: =L10 -> 800 | AA10: =M10 -> 800 | AB10: =N10 -> 800 | AC10: =O10 -> 800 | AD10: =P10 -> 800 | AE10: =Q10 -> 800 | AF10: =R10 -> 800 | ... AK10: =W10 -> 0
B11: 3.000% Senior Notes due June 2025 (1) | C11: 574 | D11: 535 | E11: 503 | F11: 519 | G11: 487 | I11: 520 | J11: 492 | K11: 460 | L11: =E11 -> 503 | M11: 510 | N11: 513 | O11: 497 | P11: =F11 -> 519 | Q11: 507 | R11: 503 | S11: 523 | T11: =G11 -> 487 | U11: 508 | V11: 0 | W11: 0 | Y11: =K11 -> 460 | Z11: =L11 -> 503 | AA11: =M11 -> 510 | AB11: =N11 -> 513 | AC11: =O11 -> 497 | AD11: =P11 -> 519 | AE11: =Q11 -> 507 | AF11: =R11 -> 503 | ... AK11: =W11 -> 0
B12: 3.625% Senior Notes due June 2025 | C12: 500 | D12: 500 | E12: 500 | F12: 500 | G12: 500 | I12: 500 | J12: 500 | K12: 500 | L12: =E12 -> 500 | M12: 500 | N12: 500 | O12: 500 | P12: =F12 -> 500 | Q12: 500 | R12: 500 | S12: 500 | T12: =G12 -> 500 | U12: 500 | V12: 0 | W12: 0 | Y12: =K12 -> 500 | Z12: =L12 -> 500 | AA12: =M12 -> 500 | AB12: =N12 -> 500 | AC12: =O12 -> 500 | AD12: =P12 -> 500 | AE12: =Q12 -> 500 | AF12: =R12 -> 500 | ... AK12: =W12 -> 0
B13: 4.375% Senior Notes due November 2026 | C13: 1000 | D13: 1000 | E13: 1000 | F13: 1000 | G13: 1000 | I13: 1000 | J13: 1000 | K13: 1000 | L13: =E13 -> 1000 | M13: 1000 | N13: 1000 | O13: 1000 | P13: =F13 -> 1000 | Q13: 1000 | R13: 1000 | S13: 1000 | T13: =G13 -> 1000 | U13: 1000 | V13: 1000 | W13: 1000 | Y13: =K13 -> 1000 | Z13: =L13 -> 1000 | AA13: =M13 -> 1000 | AB13: =N13 -> 1000 | AC13: =O13 -> 1000 | AD13: =P13 -> 1000 | AE13: =Q13 -> 1000 | AF13: =R13 -> 1000 | ... AK13: =W13 -> 1000
B14: 3.625% Senior Notes due May 2027 (1) | C14: 1588 | D14: 1480 | E14: 1391 | F14: 1434 | G14: 1346 | I14: 1439 | J14: 1362 | K14: 1275 | L14: =E14 -> 1391 | M14: 1412 | N14: 1419 | O14: 1375 | P14: =F14 -> 1434 | Q14: 1401 | R14: 1394 | S14: 1446 | T14: =G14 -> 1346 | U14: 1404 | V14: 1525 | W14: 1528 | Y14: =K14 -> 1275 | Z14: =L14 -> 1391 | AA14: =M14 -> 1412 | AB14: =N14 -> 1419 | AC14: =O14 -> 1375 | AD14: =P14 -> 1434 | AE14: =Q14 -> 1401 | AF14: =R14 -> 1394 | ... AK14: =W14 -> 1528
B15: 4.875% Senior Notes due April 2028 | C15: 1600 | D15: 1600 | E15: 1600 | F15: 1600 | G15: 1600 | I15: 1600 | J15: 1600 | K15: 1600 | L15: =E15 -> 1600 | M15: 1600 | N15: 1600 | O15: 1600 | P15: =F15 -> 1600 | Q15: 1600 | R15: 1600 | S15: 1600 | T15: =G15 -> 1600 | U15: 1600 | V15: 1600 | W15: 1600 | Y15: =K15 -> 1600 | Z15: =L15 -> 1600 | AA15: =M15 -> 1600 | AB15: =N15 -> 1600 | AC15: =O15 -> 1600 | AD15: =P15 -> 1600 | AE15: =Q15 -> 1600 | AF15: =R15 -> 1600 | ... AK15: =W15 -> 1600
B16: 5.875% Senior Notes due November 2028 | C16: 1900 | D16: 1900 | E16: 1900 | F16: 1900 | G16: 1900 | I16: 1900 | J16: 1900 | K16: 1900 | L16: =E16 -> 1900 | M16: 1900 | N16: 1900 | O16: 1900 | P16: =F16 -> 1900 | Q16: 1900 | R16: 1900 | S16: 1900 | T16: =G16 -> 1900 | U16: 1900 | V16: 1900 | W16: 1900 | Y16: =K16 -> 1900 | Z16: =L16 -> 1900 | AA16: =M16 -> 1900 | AB16: =N16 -> 1900 | AC16: =O16 -> 1900 | AD16: =P16 -> 1900 | AE16: =Q16 -> 1900 | AF16: =R16 -> 1900 | ... AK16: =W16 -> 1900
B17: 4.625% Senior Notes due May 2029 (1) | C17: 1344 | D17: 1252 | E17: 1177 | F17: 1215 | G17: 1139 | I17: 1218 | J17: 1153 | K17: 1079 | L17: =E17 -> 1177 | M17: 1194 | N17: 1200 | O17: 1163 | P17: =F17 -> 1215 | Q17: 1187 | R17: 1178 | S17: 1225 | T17: =G17 -> 1139 | U17: 1188 | V17: 1291 | W17: 1293 | Y17: =K17 -> 1079 | Z17: =L17 -> 1177 | AA17: =M17 -> 1194 | AB17: =N17 -> 1200 | AC17: =O17 -> 1163 | AD17: =P17 -> 1215 | AE17: =Q17 -> 1187 | AF17: =R17 -> 1178 | ... AK17: =W17 -> 1293
B18: 6.375% Senior Notes due May 2029 | C18: 800 | D18: 800 | E18: 800 | F18: 800 | G18: 800 | I18: 800 | J18: 800 | K18: 800 | L18: =E18 -> 800 | M18: 800 | N18: 800 | O18: 800 | P18: =F18 -> 800 | Q18: 800 | R18: 800 | S18: 800 | T18: =G18 -> 800 | U18: 800 | V18: 800 | W18: 800 | Y18: =K18 -> 800 | Z18: =L18 -> 800 | AA18: =M18 -> 800 | AB18: =N18 -> 800 | AC18: =O18 -> 800 | AD18: =P18 -> 800 | AE18: =Q18 -> 800 | AF18: =R18 -> 800 | ... AK18: =W18 -> 800
... B24: 5.400% Senior Notes due August 2054 | C24: 0 | D24: 0 | E24: 0 | F24: 0 | G24: 800 | I24: 0 | J24: 0 | K24: 0 | L24: =E24 -> 0 | M24: 0 | N24: 0 | O24: 0 | P24: =F24 -> 0 | Q24: 0 | R24: 0 | S24: 800 | T24: =G24 -> 800 | U24: 800 | V24: 800 | W24: 800 | Y24: =K24 -> 0 | Z24: =L24 -> 0 | AA24: =M24 -> 0 | AB24: =N24 -> 0 | AC24: =O24 -> 0 | AD24: =P24 -> 0 | AE24: =Q24 -> 0 | AF24: =R24 -> 0 | ... AK24: =W24 -> 800
B25: Total Debt | C25: =SUM(C7:C24) -> 16416 | D25: =SUM(D7:D24) -> 15485 | E25: =SUM(E7:E24) -> 14432 | F25: =SUM(F7:F24) -> 14608 | G25: =SUM(G7:G24) -> 15653 | I25: =SUM(I7:I24) -> 14623 | J25: =SUM(J7:J24) -> 14318 | K25: =SUM(K7:K24) -> 13970 | L25: =SUM(L7:L24) -> 14432 | M25: =SUM(M7:M24) -> 14513 | N25: =SUM(N7:N24) -> 14542 | O25: =SUM(O7:O24) -> 14368 | P25: =SUM(P7:P24) -> 14608 | ... W25: =SUM(W7:W24) -> 14523 | Y25: =SUM(Y7:Y24) -> 13970 | Z25: =SUM(Z7:Z24) -> 14432 | AA25: =SUM(AA7:AA24) -> 14513 | AB25: =SUM(AB7:AB24) -> 14542 | AC25: =SUM(AC7:AC24) -> 14368 | AD25: =SUM(AD7:AD24) -> 14608 | AE25: =SUM(AE7:AE24) -> 14077 | AF25: =SUM(AF7:AF24) -> 14038 | ... AK25: =SUM(AK7:AK24) -> 14523
B27: 1) The following Senior Notes have a principal amount denominated in euros: 3.000% Senior Notes for €470 million, 3.625% Senior Notes for €1,300 million, 4.625% Senior Notes for €1,100 million, 3.875% Senior Notes for €1,200 million, and 3.625% Senior Notes for €1,100 million.
