Workbook

Sheet Historical Financials
B2: Beyond Meat, Inc. (NASDAQ: BYND)
B3: Historical Financials
B4: $ mm except per share
A6: X | B6: Income Statement | G6: FYE | K6: Quarterly | AV6: LTM | BB6: Variance
B7: Fiscal Period | C7: 2018 | D7: 2019 | E7: 2020 | F7: 2021 | G7: 2022 | H7: 2023 | I7: 2024 | K7: 1Q18 | L7: 2Q18 | M7: 3Q18 | N7: 4Q18 | O7: 1Q19 | P7: 2Q19 | Q7: 3Q19 | R7: 4Q19 | S7: 1Q20 | T7: 2Q20 | U7: 3Q20 | V7: 4Q20 | W7: 1Q21 | X7: 2Q21 | Y7: 3Q21 | Z7: 4Q21 | AA7: 1Q22 | AB7: 2Q22 | AC7: 3Q22 | AD7: 4Q22 | AE7: 1Q23 | AF7: 2Q23 | AG7: 3Q23 | AH7: 4Q23 | AI7: 1Q24 | AJ7: 2Q24 | AK7: 3Q24 | AL7: 4Q24 | AM7: 1Q25 | AN7: 2Q25 | AP7: =AD7 -> 4Q22 | AQ7: =AE7 -> 1Q23 | AR7: =AF7 -> 2Q23 | AS7: =AG7 -> 3Q23 | AT7: =AH7 -> 4Q23 | AU7: =AI7 -> 1Q24 | AV7: =AJ7 -> 2Q24 | AW7: =AK7 -> 3Q24 | ... AZ7: =AN7 -> 2Q25
B8: Fiscal Period End Date | C8: 43465 | D8: 43830 | E8: 44196 | F8: 44561 | G8: 44926 | H8: 45291 | I8: 45657 | K8: 43190 | L8: 43281 | M8: 43372 | N8: 43465 | O8: 43554 | P8: 43645 | Q8: 43736 | R8: 43830 | S8: 43918 | T8: 44009 | U8: 44100 | V8: 44196 | W8: 44289 | X8: 44380 | Y8: 44471 | Z8: 44561 | AA8: 44653 | AB8: 44744 | AC8: 44835 | AD8: 44926 | AE8: 45017 | AF8: 45108 | AG8: 45199 | AH8: 45291 | AI8: 45381 | AJ8: 45472 | AK8: 45563 | AL8: 45657 | AM8: 45745 | AN8: 45836 | AP8: =AD8 -> 44926 | AQ8: =AE8 -> 45017 | AR8: =AF8 -> 45108 | AS8: =AG8 -> 45199 | AT8: =AH8 -> 45291 | AU8: =AI8 -> 45381 | AV8: =AJ8 -> 45472 | AW8: =AK8 -> 45563 | ... AZ8: =AN8 -> 45836
B10: Consolidated Revenue | C10: 87934 | D10: 297897 | E10: 406785 | F10: 464700 | G10: 418933 | H10: 343376 | I10: 326452 | K10: 12776 | L10: 17367 | M10: 26277 | N10: =SUM(C10-SUM(K10:M10)) -> 31514 | O10: 40206 | P10: 67251 | Q10: 91961 | R10: =SUM(D10-SUM(O10:Q10)) -> 98479 | S10: 97074 | T10: 113338 | U10: 94436 | V10: =SUM(E10-SUM(S10:U10)) -> 101937 | W10: 108164 | X10: 149426 | Y10: 106432 | Z10: =SUM(F10-SUM(W10:Y10)) -> 100678 | AA10: 109455 | AB10: 147040 | AC10: 82500 | AD10: =SUM(G10-SUM(AA10:AC10)) -> 79938 | AE10: 92236 | AF10: 102149 | AG10: 75312 | AH10: =SUM(H10-SUM(AE10:AG10)) -> 73679 | AI10: 75603 | AJ10: 93185 | AK10: 81006 | AL10: =SUM(I10-SUM(AI10:AK10)) -> 76658 | AM10: 68731 | AN10: 74958 | AP10: =SUM(AA10:AD10) -> 418933 | AQ10: =SUM(AB10:AE10) -> 401714 | AR10: =SUM(AC10:AF10) -> 356823 | AS10: =SUM(AD10:AG10) -> 349635 | AT10: =SUM(AE10:AH10) -> 343376 | AU10: =SUM(AF10:AI10) -> 326743 | AV10: =SUM(AG10:AJ10) -> 317779 | AW10: =SUM(AH10:AK10) -> 323473 | ... AZ10: =SUM(AK10:AN10) -> 301353 | BB10: =SUM(AZ10/AV10)-1 -> -0.051690011
B11: Total Revenue | C11: =+SUM(C10:C10) -> 87934 | D11: =+SUM(D10:D10) -> 297897 | E11: =+SUM(E10:E10) -> 406785 | F11: =+SUM(F10:F10) -> 464700 | G11: =+SUM(G10:G10) -> 418933 | H11: =+SUM(H10:H10) -> 343376 | I11: =+SUM(I10:I10) -> 326452 | K11: =+SUM(K10:K10) -> 12776 | L11: =+SUM(L10:L10) -> 17367 | M11: =+SUM(M10:M10) -> 26277 | N11: =+SUM(N10:N10) -> 31514 | O11: =+SUM(O10:O10) -> 40206 | P11: =+SUM(P10:P10) -> 67251 | Q11: =+SUM(Q10:Q10) -> 91961 | R11: =+SUM(R10:R10) -> 98479 | ... AN11: =+SUM(AN10:AN10) -> 74958 | AP11: =+SUM(AP10:AP10) -> 418933 | AQ11: =+SUM(AQ10:AQ10) -> 401714 | AR11: =+SUM(AR10:AR10) -> 356823 | AS11: =+SUM(AS10:AS10) -> 349635 | AT11: =+SUM(AT10:AT10) -> 343376 | AU11: =+SUM(AU10:AU10) -> 326743 | AV11: =+SUM(AV10:AV10) -> 317779 | AW11: =+SUM(AW10:AW10) -> 323473 | ... AZ11: =+SUM(AZ10:AZ10) -> 301353 | BB11: =SUM(AZ11/AV11)-1 -> -0.051690011
B13: Cost of Sales | C13: -70360 | D13: -198141 | E13: -284510 | F13: -347419 | G13: -442676 | H13: -426031 | I13: -284753 | K13: -10719 | L13: -14755 | M13: -21235 | N13: =SUM(C13-SUM(K13:M13)) -> -23651 | O13: -29435 | P13: -44510 | Q13: -59178 | R13: =SUM(D13-SUM(O13:Q13)) -> -65018 | S13: -59383 | T13: -79687 | U13: -68908 | V13: =SUM(E13-SUM(S13:U13)) -> -76532 | W13: -75456 | X13: -102074 | Y13: -83456 | Z13: =SUM(F13-SUM(W13:Y13)) -> -86433 | AA13: -109265 | AB13: -153202 | AC13: -97340 | AD13: =SUM(G13-SUM(AA13:AC13)) -> -82869 | AE13: -86051 | AF13: -99876 | AG13: -82566 | AH13: =SUM(H13-SUM(AE13:AG13)) -> -157538 | AI13: -71935 | AJ13: -79468 | AK13: -66698 | AL13: =SUM(I13-SUM(AI13:AK13)) -> -66652 | AM13: -69796 | AN13: -66367 | AP13: =SUM(AA13:AD13) -> -442676 | AQ13: =SUM(AB13:AE13) -> -419462 | AR13: =SUM(AC13:AF13) -> -366136 | AS13: =SUM(AD13:AG13) -> -351362 | AT13: =SUM(AE13:AH13) -> -426031 | AU13: =SUM(AF13:AI13) -> -411915 | AV13: =SUM(AG13:AJ13) -> -391507 | AW13: =SUM(AH13:AK13) -> -375639 | ... AZ13: =SUM(AK13:AN13) -> -269513 | BB13: =SUM(AZ13/AV13)-1 -> -0.31160107
B14: Gross Profit | C14: =+SUM(C11+SUM(C13:C13)) -> 17574 | D14: =+SUM(D11+SUM(D13:D13)) -> 99756 | E14: =+SUM(E11+SUM(E13:E13)) -> 122275 | F14: =+SUM(F11+SUM(F13:F13)) -> 117281 | G14: =+SUM(G11+SUM(G13:G13)) -> -23743 | H14: =+SUM(H11+SUM(H13:H13)) -> -82655 | I14: =+SUM(I11+SUM(I13:I13)) -> 41699 | K14: =+SUM(K11+SUM(K13:K13)) -> 2057 | L14: =+SUM(L11+SUM(L13:L13)) -> 2612 | M14: =+SUM(M11+SUM(M13:M13)) -> 5042 | N14: =+SUM(N11+SUM(N13:N13)) -> 7863 | O14: =+SUM(O11+SUM(O13:O13)) -> 10771 | P14: =+SUM(P11+SUM(P13:P13)) -> 22741 | Q14: =+SUM(Q11+SUM(Q13:Q13)) -> 32783 | R14: =+SUM(R11+SUM(R13:R13)) -> 33461 | ... AN14: =+SUM(AN11+SUM(AN13:AN13)) -> 8591 | AP14: =+SUM(AP11+SUM(AP13:AP13)) -> -23743 | AQ14: =+SUM(AQ11+SUM(AQ13:AQ13)) -> -17748 | AR14: =+SUM(AR11+SUM(AR13:AR13)) -> -9313 | AS14: =+SUM(AS11+SUM(AS13:AS13)) -> -1727 | AT14: =+SUM(AT11+SUM(AT13:AT13)) -> -82655 | AU14: =+SUM(AU11+SUM(AU13:AU13)) -> -85172 | AV14: =+SUM(AV11+SUM(AV13:AV13)) -> -73728 | AW14: =+SUM(AW11+SUM(AW13:AW13)) -> -52166 | ... AZ14: =+SUM(AZ11+SUM(AZ13:AZ13)) -> 31840 | BB14: =SUM(AZ14/AV14)-1 -> -1.4318576
B15: Gross Margin (%) | C15: =C14/C11 -> 0.19985444 | D15: =D14/D11 -> 0.33486742 | E15: =E14/E11 -> 0.30058876 | F15: =F14/F11 -> 0.25238003 | G15: =G14/G11 -> -0.056674934 | H15: =H14/H11 -> -0.2407128 | I15: =I14/I11 -> 0.12773394 | K15: =K14/K11 -> 0.16100501 | L15: =L14/L11 -> 0.15040018 | M15: =M14/M11 -> 0.19187883 | N15: =N14/N11 -> 0.24950816 | O15: =O14/O11 -> 0.26789534 | P15: =P14/P11 -> 0.33815111 | Q15: =Q14/Q11 -> 0.35648808 | R15: =R14/R11 -> 0.33977802 | ... AN15: =AN14/AN11 -> 0.11461085 | AP15: =AP14/AP11 -> -0.056674934 | AQ15: =AQ14/AQ11 -> -0.044180686 | AR15: =AR14/AR11 -> -0.026099775 | AS15: =AS14/AS11 -> -0.0049394368 | AT15: =AT14/AT11 -> -0.2407128 | AU15: =AU14/AU11 -> -0.2606697 | AV15: =AV14/AV11 -> -0.2320103 | AW15: =AW14/AW11 -> -0.16126848 | ... AZ15: =AZ14/AZ11 -> 0.10565682 | BB15: =SUM(AZ15-AV15)*1000 -> 337.66712
B17: Selling, General & Administrative | C17: -34461 | D17: -74726 | E17: -133655 | F17: -209474 | G17: -239505 | H17: -220344 | I17: -169674 | K17: -5737 | L17: -7043 | M17: -10353 | N17: =SUM(C17-SUM(K17:M17)) -> -11328 | O17: -11177 | P17: -15515 | Q17: -20944 | R17: =SUM(D17-SUM(O17:Q17)) -> -27090 | S17: -27315 | T17: -34292 | U17: -33560 | V17: =SUM(E17-SUM(S17:U17)) -> -38488 | W17: -38954 | X17: -48286 | Y17: -56362 | Z17: =SUM(F17-SUM(W17:Y17)) -> -65872 | AA17: -75114 | AB17: -63015 | AC17: -54495 | AD17: =SUM(G17-SUM(AA17:AC17)) -> -46881 | AE17: -51900 | AF17: -47455 | AG17: -53252 | AH17: =SUM(H17-SUM(AE17:AG17)) -> -67737 | AI17: -47282 | AJ17: -42163 | AK17: -39084 | AL17: =SUM(I17-SUM(AI17:AK17)) -> -41145 | AM17: -47672 | AN17: -37696 | AP17: =SUM(AA17:AD17) -> -239505 | AQ17: =SUM(AB17:AE17) -> -216291 | AR17: =SUM(AC17:AF17) -> -200731 | AS17: =SUM(AD17:AG17) -> -199488 | AT17: =SUM(AE17:AH17) -> -220344 | AU17: =SUM(AF17:AI17) -> -215726 | AV17: =SUM(AG17:AJ17) -> -210434 | AW17: =SUM(AH17:AK17) -> -196266 | ... AZ17: =SUM(AK17:AN17) -> -165597 | BB17: =SUM(AZ17/AV17)-1 -> -0.21306918
B18: Research & Development | C18: -9587 | D18: -20650 | E18: -31535 | F18: -66946 | G18: -62264 | H18: -39530 | I18: -28149 | K18: -1605 | L18: -2497 | M18: -2165 | N18: =SUM(C18-SUM(K18:M18)) -> -3320 | O18: -4498 | P18: -4212 | Q18: -5951 | R18: =SUM(D18-SUM(O18:Q18)) -> -5989 | S18: -6194 | T18: -6016 | U18: -8278 | V18: =SUM(E18-SUM(S18:U18)) -> -11047 | W18: -15925 | X18: -13823 | Y18: -14862 | Z18: =SUM(F18-SUM(W18:Y18)) -> -22336 | AA18: -19678 | AB18: -16202 | AC18: -13413 | AD18: =SUM(G18-SUM(AA18:AC18)) -> -12971 | AE18: -12432 | AF18: -8773 | AG18: -9118 | AH18: =SUM(H18-SUM(AE18:AG18)) -> -9207 | AI18: -9860 | AJ18: -5485 | AK18: -6133 | AL18: =SUM(I18-SUM(AI18:AK18)) -> -6671 | AM18: -7462 | AN18: -5807 | AP18: =SUM(AA18:AD18) -> -62264 | AQ18: =SUM(AB18:AE18) -> -55018 | AR18: =SUM(AC18:AF18) -> -47589 | AS18: =SUM(AD18:AG18) -> -43294 | AT18: =SUM(AE18:AH18) -> -39530 | AU18: =SUM(AF18:AI18) -> -36958 | AV18: =SUM(AG18:AJ18) -> -33670 | AW18: =SUM(AH18:AK18) -> -30685 | ... AZ18: =SUM(AK18:AN18) -> -26073 | BB18: =SUM(AZ18/AV18)-1 -> -0.22563113
B19: Operating Profit | C19: =+SUM(C14+SUM(C17:C18)) -> -26474 | D19: =+SUM(D14+SUM(D17:D18)) -> 4380 | E19: =+SUM(E14+SUM(E17:E18)) -> -42915 | F19: =+SUM(F14+SUM(F17:F18)) -> -159139 | G19: =+SUM(G14+SUM(G17:G18)) -> -325512 | H19: =+SUM(H14+SUM(H17:H18)) -> -342529 | I19: =+SUM(I14+SUM(I17:I18)) -> -156124 | K19: =+SUM(K14+SUM(K17:K18)) -> -5285 | L19: =+SUM(L14+SUM(L17:L18)) -> -6928 | M19: =+SUM(M14+SUM(M17:M18)) -> -7476 | N19: =+SUM(N14+SUM(N17:N18)) -> -6785 | O19: =+SUM(O14+SUM(O17:O18)) -> -4904 | P19: =+SUM(P14+SUM(P17:P18)) -> 3014 | Q19: =+SUM(Q14+SUM(Q17:Q18)) -> 5888 | R19: =+SUM(R14+SUM(R17:R18)) -> 382 | ... AN19: =+SUM(AN14+SUM(AN17:AN18)) -> -34912 | AP19: =+SUM(AP14+SUM(AP17:AP18)) -> -325512 | AQ19: =+SUM(AQ14+SUM(AQ17:AQ18)) -> -289057 | AR19: =+SUM(AR14+SUM(AR17:AR18)) -> -257633 | AS19: =+SUM(AS14+SUM(AS17:AS18)) -> -244509 | AT19: =+SUM(AT14+SUM(AT17:AT18)) -> -342529 | AU19: =+SUM(AU14+SUM(AU17:AU18)) -> -337856 | AV19: =+SUM(AV14+SUM(AV17:AV18)) -> -317832 | AW19: =+SUM(AW14+SUM(AW17:AW18)) -> -279117 | ... AZ19: =+SUM(AZ14+SUM(AZ17:AZ18)) -> -159830 | BB19: =SUM(AZ19/AV19)-1 -> -0.49712427
B20: Operating Margin (%) | C20: =C19/C11 -> -0.30106671 | D20: =D19/D11 -> 0.014703069 | E20: =E19/E11 -> -0.10549799 | F20: =F19/F11 -> -0.34245535 | G20: =G19/G11 -> -0.77700253 | H20: =H19/H11 -> -0.99753332 | I20: =I19/I11 -> -0.47824489 | K20: =K19/K11 -> -0.41366625 | L20: =L19/L11 -> -0.39891749 | M20: =M19/M11 -> -0.28450736 | N20: =N19/N11 -> -0.21530114 | O20: =O19/O11 -> -0.12197184 | P20: =P19/P11 -> 0.044817177 | Q20: =Q19/Q11 -> 0.064027142 | R20: =R19/R11 -> 0.0038789996 | ... AN20: =AN19/AN11 -> -0.46575416 | AP20: =AP19/AP11 -> -0.77700253 | AQ20: =AQ19/AQ11 -> -0.71955919 | AR20: =AR19/AR11 -> -0.72201904 | AS20: =AS19/AS11 -> -0.69932644 | AT20: =AT19/AT11 -> -0.99753332 | AU20: =AU19/AU11 -> -1.0340114 | AV20: =AV19/AV11 -> -1.0001668 | AW20: =AW19/AW11 -> -0.86287573 | ... AZ20: =AZ19/AZ11 -> -0.53037468
B22: Restructuring Expenses | C22: -1515 | D22: -4869 | E22: -6430 | F22: 0 | G22: 0 | H22: 0 | I22: 0 | K22: -294 | L22: -348 | M22: -528 | N22: =SUM(C22-SUM(K22:M22)) -> -345 | O22: -394 | P22: -847 | Q22: -2319 | R22: =SUM(D22-SUM(O22:Q22)) -> -1309 | S22: -2373 | T22: -1509 | U22: -2146 | V22: =SUM(E22-SUM(S22:U22)) -> -402 | W22: -2474 | X22: -3844 | Y22: -5750 | Z22: =SUM(F22-SUM(W22:Y22)) -> 12068 | AA22: -3026 | AB22: -4302 | AC22: -6993 | AD22: =SUM(G22-SUM(AA22:AC22)) -> 14321 | AE22: 426 | AF22: 201 | AG22: 4 | AH22: =SUM(H22-SUM(AE22:AG22)) -> -631 | AI22: 0 | AJ22: 0 | AK22: 0 | AL22: =SUM(I22-SUM(AI22:AK22)) -> 0 | AM22: 0 | AN22: 0 | AP22: =SUM(AA22:AD22) -> 0 | AQ22: =SUM(AB22:AE22) -> 3452 | AR22: =SUM(AC22:AF22) -> 7955 | AS22: =SUM(AD22:AG22) -> 14952 | AT22: =SUM(AE22:AH22) -> 0 | AU22: =SUM(AF22:AI22) -> -426 | AV22: =SUM(AG22:AJ22) -> -627 | AW22: =SUM(AH22:AK22) -> -631 | ... AZ22: =SUM(AK22:AN22) -> 0 | BB22: =SUM(AZ22/AV22)-1 -> -1
B23: Restructuring Income/expense | C23: -1128 | D23: 0 | E23: 0 | F23: -15794 | G23: -17259 | H23: 631 | I23: 0 | K23: -47 | L23: -28 | M23: -313 | N23: =SUM(C23-SUM(K23:M23)) -> -740 | O23: -733 | P23: -741 | Q23: -855 | R23: =SUM(D23-SUM(O23:Q23)) -> 2329 | S23: 0 | T23: 0 | U23: 0 | V23: =SUM(E23-SUM(S23:U23)) -> 0 | W23: 0 | X23: 0 | Y23: 0 | Z23: =SUM(F23-SUM(W23:Y23)) -> -15794 | AA23: 0 | AB23: 0 | AC23: 0 | AD23: =SUM(G23-SUM(AA23:AC23)) -> -17259 | AE23: 0 | AF23: 0 | AG23: 0 | AH23: =SUM(H23-SUM(AE23:AG23)) -> 631 | AI23: 0 | AJ23: 0 | AK23: 0 | AL23: =SUM(I23-SUM(AI23:AK23)) -> 0 | AM23: 0 | AN23: 0 | AP23: =SUM(AA23:AD23) -> -17259 | AQ23: =SUM(AB23:AE23) -> -17259 | AR23: =SUM(AC23:AF23) -> -17259 | AS23: =SUM(AD23:AG23) -> -17259 | AT23: =SUM(AE23:AH23) -> 631 | AU23: =SUM(AF23:AI23) -> 631 | AV23: =SUM(AG23:AJ23) -> 631 | AW23: =SUM(AH23:AK23) -> 631 | ... AZ23: =SUM(AK23:AN23) -> 0 | BB23: =SUM(AZ23/AV23)-1 -> -1
B24: Interest Expense | C24: 352 | D24: -3071 | E24: -2576 | F24: -3648 | G24: -3966 | H24: -3955 | I24: -4097 | K24: -70 | L24: 38 | M24: -31 | N24: =SUM(C24-SUM(K24:M24)) -> 415 | O24: 141 | P24: 898 | Q24: 0 | R24: =SUM(D24-SUM(O24:Q24)) -> -4110 | S24: -705 | T24: -569 | U24: -689 | V24: =SUM(E24-SUM(S24:U24)) -> -613 | W24: -629 | X24: -1022 | Y24: -1005 | Z24: =SUM(F24-SUM(W24:Y24)) -> -992 | AA24: -1025 | AB24: -1108 | AC24: -1040 | AD24: =SUM(G24-SUM(AA24:AC24)) -> -793 | AE24: -989 | AF24: -989 | AG24: -989 | AH24: =SUM(H24-SUM(AE24:AG24)) -> -988 | AI24: -1015 | AJ24: -1029 | AK24: -1028 | AL24: =SUM(I24-SUM(AI24:AK24)) -> -1025 | AM24: -1024 | AN24: -2002 | AP24: =SUM(AA24:AD24) -> -3966 | AQ24: =SUM(AB24:AE24) -> -3930 | AR24: =SUM(AC24:AF24) -> -3811 | AS24: =SUM(AD24:AG24) -> -3760 | AT24: =SUM(AE24:AH24) -> -3955 | AU24: =SUM(AF24:AI24) -> -3981 | AV24: =SUM(AG24:AJ24) -> -4021 | AW24: =SUM(AH24:AK24) -> -4060 | ... AZ24: =SUM(AK24:AN24) -> -5079 | BB24: =SUM(AZ24/AV24)-1 -> 0.26311863
B25: Other, Net | C25: -1120 | D25: 3629 | E25: -759 | F25: -487 | G25: -420 | H25: 11616 | I25: -10 | K25: 0 | L25: 0 | M25: 0 | N25: =SUM(C25-SUM(K25:M25)) -> -1120 | O25: 0 | P25: 0 | Q25: 1385 | R25: =SUM(D25-SUM(O25:Q25)) -> 2244 | S25: 0 | T25: 0 | U25: 0 | V25: =SUM(E25-SUM(S25:U25)) -> -759 | W25: 0 | X25: 0 | Y25: 0 | Z25: =SUM(F25-SUM(W25:Y25)) -> -487 | AA25: 0 | AB25: 0 | AC25: 0 | AD25: =SUM(G25-SUM(AA25:AC25)) -> -420 | AE25: 0 | AF25: 0 | AG25: 0 | AH25: =SUM(H25-SUM(AE25:AG25)) -> 11616 | AI25: 0 | AJ25: 0 | AK25: 0 | AL25: =SUM(I25-SUM(AI25:AK25)) -> -10 | AM25: 0 | AN25: 0 | AP25: =SUM(AA25:AD25) -> -420 | AQ25: =SUM(AB25:AE25) -> -420 | AR25: =SUM(AC25:AF25) -> -420 | AS25: =SUM(AD25:AG25) -> -420 | AT25: =SUM(AE25:AH25) -> 11616 | AU25: =SUM(AF25:AI25) -> 11616 | AV25: =SUM(AG25:AJ25) -> 11616 | AW25: =SUM(AH25:AK25) -> 11616 | ... AZ25: =SUM(AK25:AN25) -> -10 | BB25: =SUM(AZ25/AV25)-1 -> -1.0008609
B26: Remeasurement of Warrant Liability | C26: 0 | D26: -12503 | E26: 0 | F26: 0 | G26: 0 | H26: 0 | I26: 0 | K26: 0 | L26: -130 | M26: -994 | N26: =SUM(C26-SUM(K26:M26)) -> 1124 | O26: -759 | P26: -11744 | Q26: 0 | R26: =SUM(D26-SUM(O26:Q26)) -> 0 | S26: 710 | T26: -1454 | U26: -85 | V26: =SUM(E26-SUM(S26:U26)) -> 829 | W26: -1570 | X26: 180 | Y26: 759 | Z26: =SUM(F26-SUM(W26:Y26)) -> 631 | AA26: -1124 | AB26: -4902 | AC26: -2151 | AD26: =SUM(G26-SUM(AA26:AC26)) -> 8177 | AE26: 2908 | AF26: 1746 | AG26: 243 | AH26: =SUM(H26-SUM(AE26:AG26)) -> -4897 | AI26: 123 | AJ26: 477 | AK26: 5405 | AL26: =SUM(I26-SUM(AI26:AK26)) -> -6005 | AM26: 4318 | AN26: 7731 | AP26: =SUM(AA26:AD26) -> 0 | AQ26: =SUM(AB26:AE26) -> 4032 | AR26: =SUM(AC26:AF26) -> 10680 | AS26: =SUM(AD26:AG26) -> 13074 | AT26: =SUM(AE26:AH26) -> 0 | AU26: =SUM(AF26:AI26) -> -2785 | AV26: =SUM(AG26:AJ26) -> -4054 | AW26: =SUM(AH26:AK26) -> 1108 | ... AZ26: =SUM(AK26:AN26) -> 11449 | BB26: =SUM(AZ26/AV26)-1 -> -3.8241243
B27: Equity in Losses of Unconsolidated Joint Venture | C27: 0 | D27: 0 | E27: 0 | F27: -2977 | G27: -18948 | H27: -3902 | I27: -73 | K27: 0 | L27: 0 | M27: 0 | N27: NA | O27: 0 | P27: 0 | Q27: 0 | R27: NA | S27: 0 | T27: 0 | U27: 0 | V27: NA | W27: -374 | X27: -207 | Y27: -595 | Z27: -1801 | AA27: -671 | AB27: -1432 | AC27: -8746 | AD27: -8099 | AE27: -3235 | AF27: -503 | AG27: -126 | AH27: -38 | AI27: 7 | AJ27: -30 | AK27: -38 | AL27: -12 | AM27: 0 | AN27: -59 | AP27: =SUM(AA27:AD27) -> -18948 | AQ27: =SUM(AB27:AE27) -> -21512 | AR27: =SUM(AC27:AF27) -> -20583 | AS27: =SUM(AD27:AG27) -> -11963 | AT27: =SUM(AE27:AH27) -> -3902 | AU27: =SUM(AF27:AI27) -> -660 | AV27: =SUM(AG27:AJ27) -> -187 | AW27: =SUM(AH27:AK27) -> -99 | ... AZ27: =SUM(AK27:AN27) -> -109
B28: Earning Before Taxes | C28: =SUM(C19+SUM(C22:C27)) -> -29885 | D28: =SUM(D19+SUM(D22:D27)) -> -12434 | E28: =SUM(E19+SUM(E22:E27)) -> -52680 | F28: =SUM(F19+SUM(F22:F27)) -> -182045 | G28: =SUM(G19+SUM(G22:G27)) -> -366105 | H28: =SUM(H19+SUM(H22:H27)) -> -338139 | I28: =SUM(I19+SUM(I22:I27)) -> -160304 | K28: =SUM(K19+SUM(K22:K27)) -> -5696 | L28: =SUM(L19+SUM(L22:L27)) -> -7396 | M28: =SUM(M19+SUM(M22:M27)) -> -9342 | N28: =SUM(N19+SUM(N22:N27)) -> -7451 | O28: =SUM(O19+SUM(O22:O27)) -> -6649 | P28: =SUM(P19+SUM(P22:P27)) -> -9420 | Q28: =SUM(Q19+SUM(Q22:Q27)) -> 4099 | R28: =SUM(R19+SUM(R22:R27)) -> -464 | ... AN28: =SUM(AN19+SUM(AN22:AN27)) -> -29242 | AP28: =SUM(AP19+SUM(AP22:AP27)) -> -366105 | AQ28: =SUM(AQ19+SUM(AQ22:AQ27)) -> -324694 | AR28: =SUM(AR19+SUM(AR22:AR27)) -> -281071 | AS28: =SUM(AS19+SUM(AS22:AS27)) -> -249885 | AT28: =SUM(AT19+SUM(AT22:AT27)) -> -338139 | AU28: =SUM(AU19+SUM(AU22:AU27)) -> -333461 | AV28: =SUM(AV19+SUM(AV22:AV27)) -> -314474 | AW28: =SUM(AW19+SUM(AW22:AW27)) -> -270552 | ... AZ28: =SUM(AZ19+SUM(AZ22:AZ27)) -> -153579 | BB28: =SUM(AZ28/AV28)-1 -> -0.51163212
B29: EBT Margin (%) | C29: =C28/C11 -> -0.33985717 | D29: =D28/D11 -> -0.041739259 | E29: =E28/E11 -> -0.1295033 | F29: =F28/F11 -> -0.39174736 | G29: =G28/G11 -> -0.87389869 | H29: =H28/H11 -> -0.9847485 | I29: =I28/I11 -> -0.49104922 | K29: =K28/K11 -> -0.44583594 | L29: =L28/L11 -> -0.42586515 | M29: =M28/M11 -> -0.35552004 | N29: =N28/N11 -> -0.2364346 | O29: =O28/O11 -> -0.16537333 | P29: =P28/P11 -> -0.14007227 | Q29: =Q28/Q11 -> 0.044573243 | R29: =R28/R11 -> -0.0047116644 | ... AN29: =AN28/AN11 -> -0.3901118 | AP29: =AP28/AP11 -> -0.87389869 | AQ29: =AQ28/AQ11 -> -0.80827156 | AR29: =AR28/AR11 -> -0.78770427 | AS29: =AS28/AS11 -> -0.71470248 | AT29: =AT28/AT11 -> -0.9847485 | AU29: =AU28/AU11 -> -1.0205605 | AV29: =AV28/AV11 -> -0.98959969 | AW29: =AW28/AW11 -> -0.83639747 | ... AZ29: =AZ28/AZ11 -> -0.50963156 | BB29: =SUM(AZ29-AV29)*1000 -> 479.96813
B31: Provision for taxes | C31: -1 | D31: -9 | E31: -72 | F31: -60 | G31: -32 | H31: -5 | I31: 26 | K31: 0 | L31: 0 | M31: 0 | N31: =SUM(C31-SUM(K31:M31)) -> -1 | O31: 0 | P31: -21 | Q31: 0 | R31: =SUM(D31-SUM(O31:Q31)) -> 12 | S31: 1 | T31: -16 | U31: -55 | V31: =SUM(E31-SUM(S31:U31)) -> -2 | W31: -48 | X31: -2 | Y31: 23 | Z31: =SUM(F31-SUM(W31:Y31)) -> -33 | AA31: -10 | AB31: -11 | AC31: 0 | AD31: =SUM(G31-SUM(AA31:AC31)) -> -11 | AE31: 0 | AF31: -5 | AG31: 0 | AH31: =SUM(H31-SUM(AE31:AG31)) -> 0 | AI31: -2 | AJ31: 34 | AK31: -6 | AL31: =SUM(I31-SUM(AI31:AK31)) -> 0 | AM31: 0 | AN31: 0 | AP31: =SUM(AA31:AD31) -> -32 | AQ31: =SUM(AB31:AE31) -> -22 | AR31: =SUM(AC31:AF31) -> -16 | AS31: =SUM(AD31:AG31) -> -16 | AT31: =SUM(AE31:AH31) -> -5 | AU31: =SUM(AF31:AI31) -> -7 | AV31: =SUM(AG31:AJ31) -> 32 | AW31: =SUM(AH31:AK31) -> 26 | ... AZ31: =SUM(AK31:AN31) -> -6 | BB31: =SUM(AZ31/AV31)-1 -> -1.1875
B32: Net loss | C32: =SUM(C28+C31) -> -29886 | D32: =SUM(D28+D31) -> -12443 | E32: =SUM(E28+E31) -> -52752 | F32: =SUM(F28+F31) -> -182105 | G32: =SUM(G28+G31) -> -366137 | H32: =SUM(H28+H31) -> -338144 | I32: =SUM(I28+I31) -> -160278 | K32: =SUM(K28+K31) -> -5696 | L32: =SUM(L28+L31) -> -7396 | M32: =SUM(M28+M31) -> -9342 | N32: =SUM(N28+N31) -> -7452 | O32: =SUM(O28+O31) -> -6649 | P32: =SUM(P28+P31) -> -9441 | Q32: =SUM(Q28+Q31) -> 4099 | R32: =SUM(R28+R31) -> -452 | ... AN32: =SUM(AN28+AN31) -> -29242 | AP32: =SUM(AP28+AP31) -> -366137 | AQ32: =SUM(AQ28+AQ31) -> -324716 | AR32: =SUM(AR28+AR31) -> -281087 | AS32: =SUM(AS28+AS31) -> -249901 | AT32: =SUM(AT28+AT31) -> -338144 | AU32: =SUM(AU28+AU31) -> -333468 | AV32: =SUM(AV28+AV31) -> -314442 | AW32: =SUM(AW28+AW31) -> -270526 | ... AZ32: =SUM(AZ28+AZ31) -> -153585 | BB32: =SUM(AZ32/AV32)-1 -> -0.51156334
B33: Net Margin (%) | C33: =C32/C11 -> -0.33986854 | D33: =D32/D11 -> -0.041769471 | E33: =E32/E11 -> -0.1296803 | F33: =F32/F11 -> -0.39187648 | G33: =G32/G11 -> -0.87397507 | H33: =H32/H11 -> -0.98476306 | I33: =I32/I11 -> -0.49096958 | K33: =K32/K11 -> -0.44583594 | L33: =L32/L11 -> -0.42586515 | M33: =M32/M11 -> -0.35552004 | N33: =N32/N11 -> -0.23646633 | O33: =O32/O11 -> -0.16537333 | P33: =P32/P11 -> -0.14038453 | Q33: =Q32/Q11 -> 0.044573243 | R33: =R32/R11 -> -0.004589811 | ... AN33: =AN32/AN11 -> -0.3901118 | AP33: =AP32/AP11 -> -0.87397507 | AQ33: =AQ32/AQ11 -> -0.80832632 | AR33: =AR32/AR11 -> -0.78774911 | AS33: =AS32/AS11 -> -0.71474824 | AT33: =AT32/AT11 -> -0.98476306 | AU33: =AU32/AU11 -> -1.0205819 | AV33: =AV32/AV11 -> -0.98949899 | AW33: =AW32/AW11 -> -0.8363171 | ... AZ33: =AZ32/AZ11 -> -0.50965147 | BB33: =SUM(AZ33-AV33)*1000 -> 479.84752
B35: Basic shares | N35: =D35 -> 0 | R35: =H35 -> 0 | V35: =L35 -> 0 | Z35: =P35 -> 0 | AD35: =T35 -> 0 | AH35: =X35 -> 0 | AL35: =AB35 -> 0 | AP35: =AD35 -> 0 | AQ35: =AE35 -> 0 | AR35: =AF35 -> 0 | AS35: =AG35 -> 0 | AT35: =AH35 -> 0 | AU35: =AI35 -> 0 | AV35: =AJ35 -> 0 | AW35: =AK35 -> 0 | ... AZ35: =AN35 -> 0
B36: Basic EPS | C36: =C32/C35 -> #DIV/0! | D36: =D32/D35 -> #DIV/0! | E36: =E32/E35 -> #DIV/0! | F36: =F32/F35 -> #DIV/0! | G36: =G32/G35 -> #DIV/0! | H36: =H32/H35 -> #DIV/0! | I36: =I32/I35 -> #DIV/0! | K36: =K32/K35 -> #DIV/0! | L36: =L32/L35 -> #DIV/0! | M36: =M32/M35 -> #DIV/0! | N36: =N32/N35 -> #DIV/0! | O36: =O32/O35 -> #DIV/0! | P36: =P32/P35 -> #DIV/0! | Q36: =Q32/Q35 -> #DIV/0! | R36: =R32/R35 -> #DIV/0! | ... AN36: =AN32/AN35 -> #DIV/0! | AP36: =AP32/AP35 -> #DIV/0! | AQ36: =AQ32/AQ35 -> #DIV/0! | AR36: =AR32/AR35 -> #DIV/0! | AS36: =AS32/AS35 -> #DIV/0! | AT36: =AT32/AT35 -> #DIV/0! | AU36: =AU32/AU35 -> #DIV/0! | AV36: =AV32/AV35 -> #DIV/0! | AW36: =AW32/AW35 -> #DIV/0! | ... AZ36: =AZ32/AZ35 -> #DIV/0! | BB36: =SUM(AZ36/AV36)-1 -> #DIV/0!
B38: Fully Diluted Shares | C38: 6287.172 | D38: 42274.777 | N38: =D38 -> 42274.777 | R38: =H38 -> 0 | V38: =L38 -> 0 | Z38: =P38 -> 0 | AD38: =T38 -> 0 | AH38: =X38 -> 0 | AL38: =AB38 -> 0 | AP38: =AD38 -> 0 | AQ38: =AE38 -> 0 | AR38: =AF38 -> 0 | AS38: =AG38 -> 0 | AT38: =AH38 -> 0 | AU38: =AI38 -> 0 | AV38: =AJ38 -> 0 | AW38: =AK38 -> 0 | ... AZ38: =AN38 -> 0
B39: Diluted EPS | C39: =C32/C38 -> -4.7534885 | D39: =D32/D38 -> -0.29433627 | E39: =E32/E38 -> #DIV/0! | F39: =F32/F38 -> #DIV/0! | G39: =G32/G38 -> #DIV/0! | H39: =H32/H38 -> #DIV/0! | I39: =I32/I38 -> #DIV/0! | K39: =K32/K38 -> #DIV/0! | L39: =L32/L38 -> #DIV/0! | M39: =M32/M38 -> #DIV/0! | N39: =N32/N38 -> -0.17627532 | O39: =O32/O38 -> #DIV/0! | P39: =P32/P38 -> #DIV/0! | Q39: =Q32/Q38 -> #DIV/0! | R39: =R32/R38 -> #DIV/0! | ... AN39: =AN32/AN38 -> #DIV/0! | AP39: =AP32/AP38 -> #DIV/0! | AQ39: =AQ32/AQ38 -> #DIV/0! | AR39: =AR32/AR38 -> #DIV/0! | AS39: =AS32/AS38 -> #DIV/0! | AT39: =AT32/AT38 -> #DIV/0! | AU39: =AU32/AU38 -> #DIV/0! | AV39: =AV32/AV38 -> #DIV/0! | AW39: =AW32/AW38 -> #DIV/0! | ... AZ39: =AZ32/AZ38 -> #DIV/0! | BB39: =SUM(AZ39/AV39)-1 -> #DIV/0!
A41: X | B41: Balance Sheet | K41: Quarterly | AV41: LTM | BB41: Variance
B42: =B7 -> Fiscal Period | C42: =C7 -> 2018 | D42: =D7 -> 2019 | E42: =E7 -> 2020 | F42: =F7 -> 2021 | G42: =G7 -> 2022 | H42: =H7 -> 2023 | I42: =I7 -> 2024 | K42: =K7 -> 1Q18 | L42: =L7 -> 2Q18 | M42: =M7 -> 3Q18 | N42: =N7 -> 4Q18 | O42: =O7 -> 1Q19 | P42: =P7 -> 2Q19 | Q42: =Q7 -> 3Q19 | R42: =R7 -> 4Q19 | ... AN42: =AN7 -> 2Q25 | AP42: =AP7 -> 4Q22 | AQ42: =AQ7 -> 1Q23 | AR42: =AR7 -> 2Q23 | AS42: =AS7 -> 3Q23 | AT42: =AT7 -> 4Q23 | AU42: =AU7 -> 1Q24 | AV42: =AV7 -> 2Q24 | AW42: =AW7 -> 3Q24 | ... AZ42: =AZ7 -> 2Q25
B43: =B8 -> Fiscal Period End Date | C43: =C8 -> 43465 | D43: =D8 -> 43830 | E43: =E8 -> 44196 | F43: =F8 -> 44561 | G43: =G8 -> 44926 | H43: =H8 -> 45291 | I43: =I8 -> 45657 | K43: =K8 -> 43190 | L43: =L8 -> 43281 | M43: =M8 -> 43372 | N43: =N8 -> 43465 | O43: =O8 -> 43554 | P43: =P8 -> 43645 | Q43: =Q8 -> 43736 | R43: =R8 -> 43830 | ... AN43: =AN8 -> 45836 | AP43: =AP8 -> 44926 | AQ43: =AQ8 -> 45017 | AR43: =AR8 -> 45108 | AS43: =AS8 -> 45199 | AT43: =AT8 -> 45291 | AU43: =AU8 -> 45381 | AV43: =AV8 -> 45472 | AW43: =AW8 -> 45563 | ... AZ43: =AZ8 -> 45836
B45: Current Assets
B46: Cash and Cash Equivalents | C46: 54271 | D46: 275988 | E46: 159127 | F46: 733294 | G46: 309922 | H46: 190505 | I46: 131913 | K46: 29047 | L46: 23489 | M46: 49780 | N46: =C46 -> 54271 | O46: 35409 | P46: 276987 | Q46: 312451 | R46: =D46 -> 275988 | S46: 246410 | T46: 222334 | U46: 214615 | V46: =E46 -> 159127 | W46: 1125017 | X46: 1009337 | Y46: 886442 | Z46: =F46 -> 733294 | AA46: 547858 | AB46: 454674 | AC46: 390176 | AD46: =G46 -> 309922 | AE46: 258566 | AF46: 210781 | AG46: 217545 | AH46: =H46 -> 190505 | AI46: 157913 | AJ46: 144873 | AK46: 121732 | AL46: =I46 -> 131913 | AM46: 102143 | AN46: 103497 | AP46: =AD46 -> 309922 | AQ46: =AE46 -> 258566 | AR46: =AF46 -> 210781 | AS46: =AG46 -> 217545 | AT46: =AH46 -> 190505 | AU46: =AI46 -> 157913 | AV46: =AJ46 -> 144873 | AW46: =AK46 -> 121732 | ... AZ46: =AN46 -> 103497 | BB46: =SUM(AZ46/AV46)-1 -> -0.28560187
B47: Restricted Cash | C47: 0 | D47: 0 | E47: 0 | F47: 0 | G47: 0 | H47: 2830 | I47: 1041 | N47: =C47 -> 0 | O47: 0 | P47: 0 | Q47: 0 | R47: =D47 -> 0 | S47: 0 | T47: 0 | U47: 0 | V47: =E47 -> 0 | W47: 0 | X47: 0 | Y47: 0 | Z47: =F47 -> 0 | AA47: 0 | AB47: 0 | AC47: 0 | AD47: =G47 -> 0 | AE47: 2426 | AF47: 2552 | AG47: 2689 | AH47: =H47 -> 2830 | AI47: 2971 | AJ47: 536 | AK47: 558 | AL47: =I47 -> 1041 | AM47: 1083 | AN47: 1172 | AP47: =AD47 -> 0 | AQ47: =AE47 -> 2426 | AR47: =AF47 -> 2552 | AS47: =AG47 -> 2689 | AT47: =AH47 -> 2830 | AU47: =AI47 -> 2971 | AV47: =AJ47 -> 536 | AW47: =AK47 -> 558 | ... AZ47: =AN47 -> 1172
B48: Accounts Receivables | C48: 12626 | D48: 40080 | E48: 35975 | F48: 43806 | G48: 34198 | H48: 31730 | I48: 26862 | N48: =C48 -> 12626 | O48: 16194 | P48: 34388 | Q48: 34482 | R48: =D48 -> 40080 | S48: 36333 | T48: 45986 | U48: 29760 | V48: =E48 -> 35975 | W48: 36653 | X48: 63369 | Y48: 48849 | Z48: =F48 -> 43806 | AA48: 52675 | AB48: 77154 | AC48: 34949 | AD48: =G48 -> 34198 | AE48: 42395 | AF48: 50821 | AG48: 35763 | AH48: =H48 -> 31730 | AI48: 35648 | AJ48: 34463 | AK48: 34674 | AL48: =I48 -> 26862 | AM48: 33267 | AN48: 37338 | AP48: =AD48 -> 34198 | AQ48: =AE48 -> 42395 | AR48: =AF48 -> 50821 | AS48: =AG48 -> 35763 | AT48: =AH48 -> 31730 | AU48: =AI48 -> 35648 | AV48: =AJ48 -> 34463 | AW48: =AK48 -> 34674 | ... AZ48: =AN48 -> 37338 | BB48: =SUM(AZ48/AV48)-1 -> 0.083422801
B49: Inventory | C49: 30257 | D49: 81596 | E49: 121717 | F49: 241870 | G49: 235696 | H49: 130336 | I49: 113444 | N49: =C49 -> 30257 | O49: 34281 | P49: 42695 | Q49: 60270 | R49: =D49 -> 81596 | S49: 120702 | T49: 143033 | U49: 132359 | V49: =E49 -> 121717 | W49: 145524 | X49: 165746 | Y49: 193490 | Z49: =F49 -> 241870 | AA49: 283754 | AB49: 254653 | AC49: 246987 | AD49: =G49 -> 235696 | AE49: 222370 | AF49: 207138 | AG49: 194570 | AH49: =H49 -> 130336 | AI49: 122538 | AJ49: 119532 | AK49: 125158 | AL49: =I49 -> 113444 | AM49: 100068 | AN49: 110868 | AP49: =AD49 -> 235696 | AQ49: =AE49 -> 222370 | AR49: =AF49 -> 207138 | AS49: =AG49 -> 194570 | AT49: =AH49 -> 130336 | AU49: =AI49 -> 122538 | AV49: =AJ49 -> 119532 | AW49: =AK49 -> 125158 | ... AZ49: =AN49 -> 110868
B50: Prepaid Expenses and Other Current Assets (1) | C50: 5672 | D50: 5930 | E50: 15407 | F50: 33078 | G50: =20700+5943 -> 26643 | H50: =12904+4539 -> 17443 | I50: =11332+1864 -> 13196 | N50: =C50 -> 5672 | O50: 6525 | P50: 7726 | Q50: 11742 | R50: =D50 -> 5930 | S50: 12498 | T50: 17990 | U50: 14195 | V50: =E50 -> 15407 | W50: 17788 | X50: 25630 | Y50: 24341 | Z50: =F50 -> 33078 | AA50: 33010 | AB50: 33029 | AC50: 23868 | AD50: =G50 -> 26643 | AE50: =16561+4737 -> 21298 | AF50: =26051+98 -> 26149 | AG50: =20938+118 -> 21056 | AH50: =H50 -> 17443 | AI50: =15032+2401 -> 17433 | AJ50: =15538+2323 -> 17861 | AK50: =13016+2275 -> 15291 | AL50: =I50 -> 13196 | AM50: =19135+1576 -> 20711 | AN50: =42596+1664 -> 44260 | AP50: =AD50 -> 26643 | AQ50: =AE50 -> 21298 | AR50: =AF50 -> 26149 | AS50: =AG50 -> 21056 | AT50: =AH50 -> 17443 | AU50: =AI50 -> 17433 | AV50: =AJ50 -> 17861 | AW50: =AK50 -> 15291 | ... AZ50: =AN50 -> 44260
B51: Total Current Assets | C51: =SUM(C46:C50) -> 102826 | D51: =SUM(D46:D50) -> 403594 | E51: =SUM(E46:E50) -> 332226 | F51: =SUM(F46:F50) -> 1052048 | G51: =SUM(G46:G50) -> 606459 | H51: =SUM(H46:H50) -> 372844 | I51: =SUM(I46:I50) -> 286456 | K51: =SUM(K46:K50) -> 29047 | L51: =SUM(L46:L50) -> 23489 | M51: =SUM(M46:M50) -> 49780 | N51: =SUM(N46:N50) -> 102826 | O51: =SUM(O46:O50) -> 92409 | P51: =SUM(P46:P50) -> 361796 | Q51: =SUM(Q46:Q50) -> 418945 | R51: =SUM(R46:R50) -> 403594 | ... AN51: =SUM(AN46:AN50) -> 297135 | AP51: =SUM(AP46:AP50) -> 606459 | AQ51: =SUM(AQ46:AQ50) -> 547055 | AR51: =SUM(AR46:AR50) -> 497441 | AS51: =SUM(AS46:AS50) -> 471623 | AT51: =SUM(AT46:AT50) -> 372844 | AU51: =SUM(AU46:AU50) -> 336503 | AV51: =SUM(AV46:AV50) -> 317265 | AW51: =SUM(AW46:AW50) -> 297413 | ... AZ51: =SUM(AZ46:AZ50) -> 297135 | BB51: =SUM(AZ51/AV51)-1 -> -0.063448537
B53: Non-Current Assets | BB53: =SUM(AZ53/AV53)-1 -> #DIV/0!
B54: Restricted Cash, Non-Current | C54: 0 | D54: 0 | E54: 0 | F54: 0 | G54: 12627 | H54: 12600 | I54: 12600 | N54: =C54 -> 0 | O54: 0 | P54: 0 | Q54: 0 | R54: 0 | S54: 0 | T54: 0 | U54: 0 | V54: =E54 -> 0 | W54: 0 | X54: 0 | Y54: 0 | Z54: =F54 -> 0 | AA54: 0 | AB54: 0 | AC54: 0 | AD54: =G54 -> 12627 | AE54: 12600 | AF54: 12600 | AG54: 12600 | AH54: =H54 -> 12600 | AI54: 12600 | AJ54: 12600 | AK54: 12600 | AL54: =I54 -> 12600 | AM54: 12600 | AN54: 12600 | AP54: =AD54 -> 12627 | AQ54: =AE54 -> 12600 | AR54: =AF54 -> 12600 | AS54: =AG54 -> 12600 | AT54: =AH54 -> 12600 | AU54: =AI54 -> 12600 | AV54: =AJ54 -> 12600 | AW54: =AK54 -> 12600 | ... AZ54: =AN54 -> 12600
B55: Operating Lease Right-of-use Assets | C55: 396 | D55: 855 | E55: 14570 | F55: 26815 | G55: 87595 | H55: 130460 | I55: 123975 | N55: =C55 -> 396 | O55: 887 | P55: 792 | Q55: 846 | R55: =D55 -> 855 | S55: 12431 | T55: 13793 | U55: 13736 | V55: =E55 -> 14570 | W55: 13938 | X55: 14672 | Y55: 25444 | Z55: =F55 -> 26815 | AA55: 25692 | AB55: 25464 | AC55: 88335 | AD55: =G55 -> 87595 | AE55: 75056 | AF55: 136264 | AG55: 132671 | AH55: =H55 -> 130460 | AI55: 129379 | AJ55: 127679 | AK55: 126092 | AL55: =I55 -> 123975 | AM55: 121131 | AN55: 6527 | AP55: =AD55 -> 87595 | AQ55: =AE55 -> 75056 | AR55: =AF55 -> 136264 | AS55: =AG55 -> 132671 | AT55: =AH55 -> 130460 | AU55: =AI55 -> 129379 | AV55: =AJ55 -> 127679 | AW55: =AK55 -> 126092 | ... AZ55: =AN55 -> 6527
B56: Property, Plant and Equipment, Net | C56: 30527 | D56: 47474 | E56: 115299 | F56: 226489 | G56: 257002 | H56: 194046 | I56: 184887 | N56: =C56 -> 30527 | O56: 31861 | P56: 34473 | Q56: 35050 | R56: =D56 -> 47474 | S56: 61758 | T56: 70286 | U56: 77002 | V56: =E56 -> 115299 | W56: 132094 | X56: 157449 | Y56: 197290 | Z56: =F56 -> 226489 | AA56: 241389 | AB56: 258075 | AC56: 262595 | AD56: =G56 -> 257002 | AE56: 251218 | AF56: 250335 | AG56: 245373 | AH56: =H56 -> 194046 | AI56: 190896 | AJ56: 186584 | AK56: 188115 | AL56: =I56 -> 184887 | AM56: 180781 | AN56: 320988 | AP56: =AD56 -> 257002 | AQ56: =AE56 -> 251218 | AR56: =AF56 -> 250335 | AS56: =AG56 -> 245373 | AT56: =AH56 -> 194046 | AU56: =AI56 -> 190896 | AV56: =AJ56 -> 186584 | AW56: =AK56 -> 188115 | ... AZ56: =AN56 -> 320988
B57: Investments in Unconsolidated Joint Ventures | C57: 0 | D57: 0 | E57: 0 | F57: 8023 | G57: 2325 | H57: 1673 | I57: 1601 | N57: =C57 -> 0 | O57: 0 | P57: 0 | Q57: 0 | R57: 0 | S57: 0 | T57: 0 | U57: 0 | V57: =E57 -> 0 | W57: 0 | X57: 0 | Y57: 0 | Z57: =F57 -> 8023 | AA57: 7353 | AB57: 5920 | AC57: 7174 | AD57: =G57 -> 2325 | AE57: 2340 | AF57: 1837 | AG57: 1711 | AH57: =H57 -> 1673 | AI57: 1680 | AJ57: 1650 | AK57: 1612 | AL57: =I57 -> 1601 | AM57: 1589 | AN57: 1531 | AP57: =AD57 -> 2325 | AQ57: =AE57 -> 2340 | AR57: =AF57 -> 1837 | AS57: =AG57 -> 1711 | AT57: =AH57 -> 1673 | AU57: =AI57 -> 1680 | AV57: =AJ57 -> 1650 | AW57: =AK57 -> 1612 | ... AZ57: =AN57 -> 1531
B58: Prepaid lease Costs, non-current | C58: 0 | D58: 0 | E58: 0 | F58: 59188 | G58: 85472 | H58: 61635 | I58: 68005 | N58: =C58 -> 0 | O58: 0 | P58: 0 | Q58: 0 | R58: 0 | S58: 0 | T58: 0 | U58: 0 | V58: =E58 -> 0 | W58: 0 | X58: 26578 | Y58: 49456 | Z58: =F58 -> 59188 | AA58: 96166 | AB58: 102839 | AC58: 80533 | AD58: =G58 -> 85472 | AE58: 88035 | AF58: 60794 | AG58: 60680 | AH58: =H58 -> 61635 | AI58: 63264 | AJ58: 64822 | AK58: 66444 | AL58: =I58 -> 68005 | AM58: 69814 | AN58: 52272 | AP58: =AD58 -> 85472 | AQ58: =AE58 -> 88035 | AR58: =AF58 -> 60794 | AS58: =AG58 -> 60680 | AT58: =AH58 -> 61635 | AU58: =AI58 -> 63264 | AV58: =AJ58 -> 64822 | AW58: =AK58 -> 66444 | ... AZ58: =AN58 -> 52272
B59: Other Non-current Assets (Net) | C59: 0 | D59: 0 | E59: 5911 | F59: 6836 | G59: 10744 | H59: 1192 | I59: 622 | N59: =C59 -> 0 | O59: 0 | P59: 0 | Q59: 0 | R59: 0 | S59: 1501 | T59: 4552 | U59: 4970 | V59: =E59 -> 5911 | W59: 4505 | X59: 3739 | Y59: 7062 | Z59: =F59 -> 6836 | AA59: 6613 | AB59: 6301 | AC59: 6670 | AD59: =G59 -> 10744 | AE59: 10273 | AF59: 9314 | AG59: 4550 | AH59: =H59 -> 1192 | AI59: 704 | AJ59: 634 | AK59: 662 | AL59: =I59 -> 622 | AM59: 643 | AN59: 688 | AP59: =AD59 -> 10744 | AQ59: =AE59 -> 10273 | AR59: =AF59 -> 9314 | AS59: =AG59 -> 4550 | AT59: =AH59 -> 1192 | AU59: =AI59 -> 704 | AV59: =AJ59 -> 634 | AW59: =AK59 -> 662 | ... AZ59: =AN59 -> 688
B60: Total Assets | C60: =SUM(C54:C59)+C51 -> 133749 | D60: =SUM(D54:D59)+D51 -> 451923 | E60: =SUM(E54:E59)+E51 -> 468006 | F60: =SUM(F54:F59)+F51 -> 1379399 | G60: =SUM(G54:G59)+G51 -> 1062224 | H60: =SUM(H54:H59)+H51 -> 774450 | I60: =SUM(I54:I59)+I51 -> 678146 | K60: =SUM(K54:K59)+K51 -> 29047 | L60: =SUM(L54:L59)+L51 -> 23489 | M60: =SUM(M54:M59)+M51 -> 49780 | N60: =SUM(N54:N59)+N51 -> 133749 | O60: =SUM(O54:O59)+O51 -> 125157 | P60: =SUM(P54:P59)+P51 -> 397061 | Q60: =SUM(Q54:Q59)+Q51 -> 454841 | R60: =SUM(R54:R59)+R51 -> 451923 | ... AN60: =SUM(AN54:AN59)+AN51 -> 691741 | AP60: =SUM(AP54:AP59)+AP51 -> 1062224 | AQ60: =SUM(AQ54:AQ59)+AQ51 -> 986577 | AR60: =SUM(AR54:AR59)+AR51 -> 968585 | AS60: =SUM(AS54:AS59)+AS51 -> 929208 | AT60: =SUM(AT54:AT59)+AT51 -> 774450 | AU60: =SUM(AU54:AU59)+AU51 -> 735026 | AV60: =SUM(AV54:AV59)+AV51 -> 711234 | AW60: =SUM(AW54:AW59)+AW51 -> 692938 | ... AZ60: =SUM(AZ54:AZ59)+AZ51 -> 691741 | BB60: =SUM(AZ60/AV60)-1 -> -0.027407295
B62: Current Liabilities
B63: Accounts Payable | C63: 17247 | D63: 26923 | E63: 53071 | F63: 69040 | G63: 55300 | H63: 56032 | I63: 37571 | N63: =C63 -> 17247 | O63: 11663 | P63: 27383 | Q63: 38348 | R63: =D63 -> 26923 | S63: 48219 | T63: 51567 | U63: 30531 | V63: =E63 -> 53071 | W63: 51456 | X63: 49951 | Y63: 45387 | Z63: =F63 -> 69040 | AA63: 67387 | AB63: 74430 | AC63: 68676 | AD63: =G63 -> 55300 | AE63: 41131 | AF63: 39508 | AG63: 61861 | AH63: =H63 -> 56032 | AI63: 55836 | AJ63: 59449 | AK63: 59633 | AL63: =I63 -> 37571 | AM63: 50512 | AN63: 68837 | AP63: =AD63 -> 55300 | AQ63: =AE63 -> 41131 | AR63: =AF63 -> 39508 | AS63: =AG63 -> 61861 | AT63: =AH63 -> 56032 | AU63: =AI63 -> 55836 | AV63: =AJ63 -> 59449 | AW63: =AK63 -> 59633 | ... AZ63: =AN63 -> 68837
B64: Accrued Expenses, Other Current Liabilities, and Other Payables (2) | C64: =2391+2312+1918+1255 -> 7876 | D64: =3805+4129+1768-D66 -> 9630 | E64: =4830+57+2843-E66 -> 7659 | F64: =20226+128+155-F66 -> 20327 | G64: =16729-G66 -> 16505 | H64: =9855+4790-H66 -> 14449 | I64: =11925+582+7250-I66 -> 18906 | N64: =C64 -> 7876 | O64: =3094+3387+2677+1085 -> 10243 | P64: =3622+2157+1208 -> 6987 | Q64: =4113+3181+1433 -> 8727 | R64: =D64 -> 9630 | S64: =5297+723+1949 -> 7969 | T64: =8829+1416+2024 -> 12269 | U64: =10241+43+2289 -> 12573 | V64: =E64 -> 7659 | W64: =11903+2565+3899 -> 18367 | X64: =14369+2696+648 -> 17713 | Y64: =19091+1400+4269 -> 24760 | Z64: =F64 -> 20327 | AA64: =22807+2754+3406 -> 28967 | AB64: =22975+4333+2984 -> 30292 | AC64: =14693+148+2348 -> 17189 | AD64: =G64 -> 16505 | AE64: =15826-AE66 -> 15580 | AF64: =12009-AF66 -> 11791 | AG64: =13914-AG66 -> 13705 | AH64: =H64 -> 14449 | AI64: =10665+822+7500-AI66 -> 18224 | AJ64: =12051+393+7500-AJ66 -> 18939 | AK64: =15260+345+7250-AK66 -> 21715 | AL64: =I64 -> 18906 | AM64: =14199+7250-AM66 -> 20620 | AN64: =15618 -> 15618 | AP64: =AD64 -> 16505 | AQ64: =AE64 -> 15580 | AR64: =AF64 -> 11791 | AS64: =AG64 -> 13705 | AT64: =AH64 -> 14449 | AU64: =AI64 -> 18224 | AV64: =AJ64 -> 18939 | AW64: =AK64 -> 21715 | ... AZ64: =AN64 -> 15618
B65: Current Portion of Operating Lease Liabilities | C65: 0 | D65: 0 | E65: 3095 | F65: 4458 | G65: 3812 | H65: 3677 | I65: 4125 | N65: =C65 -> 0 | O65: 0 | P65: 0 | Q65: 0 | R65: =D65 -> 0 | S65: 1628 | T65: 2367 | U65: 2481 | V65: =E65 -> 3095 | W65: 3101 | X65: 3651 | Y65: 3962 | Z65: =F65 -> 4458 | AA65: 4454 | AB65: 4595 | AC65: 4585 | AD65: =G65 -> 3812 | AE65: 2960 | AF65: 3127 | AG65: 3083 | AH65: =H65 -> 3677 | AI65: 3976 | AJ65: 4125 | AK65: 4103 | AL65: =I65 -> 4125 | AM65: 3941 | AN65: 1798 | AP65: =AD65 -> 3812 | AQ65: =AE65 -> 2960 | AR65: =AF65 -> 3127 | AS65: =AG65 -> 3083 | AT65: =AH65 -> 3677 | AU65: =AI65 -> 3976 | AV65: =AJ65 -> 4125 | AW65: =AK65 -> 4103 | ... AZ65: =AN65 -> 1798
B66: Current Portion of Finance Lease Liabilities | C66: 44 | D66: 72 | E66: 71 | F66: 182 | G66: 224 | H66: 196 | I66: 851 | N66: =C66 -> 44 | O66: 36 | P66: 33 | Q66: 30 | R66: =D66 -> 72 | S66: 73 | T66: 72 | U66: 72 | V66: =E66 -> 71 | W66: 185 | X66: 184 | Y66: 183 | Z66: =F66 -> 182 | AA66: 183 | AB66: 210 | AC66: 226 | AD66: =G66 -> 224 | AE66: 246 | AF66: 218 | AG66: 209 | AH66: =H66 -> 196 | AI66: 763 | AJ66: 1005 | AK66: 1140 | AL66: =I66 -> 851 | AM66: 829 | AN66: 3934 | AP66: =AD66 -> 224 | AQ66: =AE66 -> 246 | AR66: =AF66 -> 218 | AS66: =AG66 -> 209 | AT66: =AH66 -> 196 | AU66: =AI66 -> 763 | AV66: =AJ66 -> 1005 | AW66: =AK66 -> 1140 | ... AZ66: =AN66 -> 3934
B67: Consolidated Short-Term Borrowings (3) | C67: 0 | D67: =11000+72 -> 11072 | E67: =25000+71 -> 25071 | F67: 182 | G67: 0 | H67: 0 | I67: 0 | N67: =C67 -> 0 | O67: 0 | P67: =6000 -> 6000 | Q67: =9087 -> 9087 | R67: =D67 -> 11072 | S67: =14094 -> 14094 | T67: 0 | U67: 0 | V67: =E67 -> 25071 | W67: 0 | X67: 0 | Y67: 0 | Z67: =F67 -> 182 | AA67: 0 | AB67: 0 | AC67: 0 | AD67: =G67 -> 0 | AE67: 0 | AF67: 0 | AG67: 0 | AH67: =H67 -> 0 | AI67: 0 | AJ67: 0 | AK67: 0 | AL67: =I67 -> 0 | AM67: 0 | AN67: 0 | AP67: =AD67 -> 0 | AQ67: =AE67 -> 0 | AR67: =AF67 -> 0 | AS67: =AG67 -> 0 | AT67: =AH67 -> 0 | AU67: =AI67 -> 0 | AV67: =AJ67 -> 0 | AW67: =AK67 -> 0 | ... AZ67: =AN67 -> 0
B68: Total Current Liabilities | C68: =SUM(C63:C67) -> 25167 | D68: =SUM(D63:D67) -> 47697 | E68: =SUM(E63:E67) -> 88967 | F68: =SUM(F63:F67) -> 94189 | G68: =SUM(G63:G67) -> 75841 | H68: =SUM(H63:H67) -> 74354 | I68: =SUM(I63:I67) -> 61453 | K68: =SUM(K63:K67) -> 0 | L68: =SUM(L63:L67) -> 0 | M68: =SUM(M63:M67) -> 0 | N68: =SUM(N63:N67) -> 25167 | O68: =SUM(O63:O67) -> 21942 | P68: =SUM(P63:P67) -> 40403 | Q68: =SUM(Q63:Q67) -> 56192 | R68: =SUM(R63:R67) -> 47697 | ... AN68: =SUM(AN63:AN67) -> 90187 | AP68: =SUM(AP63:AP67) -> 75841 | AQ68: =SUM(AQ63:AQ67) -> 59917 | AR68: =SUM(AR63:AR67) -> 54644 | AS68: =SUM(AS63:AS67) -> 78858 | AT68: =SUM(AT63:AT67) -> 74354 | AU68: =SUM(AU63:AU67) -> 78799 | AV68: =SUM(AV63:AV67) -> 83518 | AW68: =SUM(AW63:AW67) -> 86591 | ... AZ68: =SUM(AZ63:AZ67) -> 90187 | BB68: =SUM(AZ68/AV68)-1 -> 0.07985105
B70: Non-Current Liabilities
B71: Convertible Senior Notes, Net | C71: 0 | D71: 0 | E71: 0 | F71: 1129674 | G71: 1133608 | H71: 1137542 | I71: 1141476 | N71: =C71 -> 0 | O71: 0 | P71: 0 | Q71: 0 | R71: =D71 -> 0 | S71: 0 | T71: 0 | U71: 0 | V71: =E71 -> 0 | W71: 1126723 | X71: 1127707 | Y71: 1128690 | Z71: =F71 -> 1129674 | AA71: 1130657 | AB71: 1131641 | AC71: 1132624 | AD71: =G71 -> 1133608 | AE71: 1134591 | AF71: 1135575 | AG71: 1136558 | AH71: =H71 -> 1137542 | AI71: 1138525 | AJ71: 1139509 | AK71: 1140492 | AL71: =I71 -> 1141476 | AM71: 1142459 | AN71: 1143443 | AP71: =AD71 -> 1133608 | AQ71: =AE71 -> 1134591 | AR71: =AF71 -> 1135575 | AS71: =AG71 -> 1136558 | AT71: =AH71 -> 1137542 | AU71: =AI71 -> 1138525 | AV71: =AJ71 -> 1139509 | AW71: =AK71 -> 1140492 | ... AZ71: =AN71 -> 1143443
B72: Consolidated Other Long-Term Borrowings (4) | C72: =6000+19388+5000 -> 30388 | D72: =4932+14637 -> 19569 | E72: 0 | F72: 0 | G72: 0 | H72: 0 | I72: 0 | N72: =C72 -> 30388 | O72: =4914+19533+6000 -> 30447 | P72: =4924+19543 -> 24467 | Q72: =4922+16503 -> 21425 | R72: =D72 -> 19569 | S72: =12185+4347 -> 16532 | T72: 50000 | U72: 50000 | V72: =E72 -> 0 | W72: 0 | X72: 0 | Y72: 0 | Z72: =F72 -> 0 | AA72: 0 | AB72: 0 | AC72: 0 | AD72: =G72 -> 0 | AE72: 0 | AF72: 0 | AG72: 0 | AH72: =H72 -> 0 | AI72: 0 | AJ72: 0 | AK72: 0 | AL72: =I72 -> 0 | AM72: 0 | AN72: =30525+20143 -> 50668 | AP72: =AD72 -> 0 | AQ72: =AE72 -> 0 | AR72: =AF72 -> 0 | AS72: =AG72 -> 0 | AT72: =AH72 -> 0 | AU72: =AI72 -> 0 | AV72: =AJ72 -> 0 | AW72: =AK72 -> 0 | ... AZ72: =AN72 -> 50668
B73: Finance Lease Obligations and Other Long-term Liabilities | C73: 404 | D73: 567 | E73: 149 | F73: 442 | G73: 469 | H73: 274 | I73: 2812 | N73: =C73 -> 404 | O73: 406 | P73: 406 | Q73: 396 | R73: =D73 -> 567 | S73: 202 | T73: 185 | U73: 167 | V73: =E73 -> 149 | W73: 579 | X73: 533 | Y73: 488 | Z73: =F73 -> 442 | AA73: 396 | AB73: 3739 | AC73: 3547 | AD73: =G73 -> 469 | AE73: 416 | AF73: 362 | AG73: 316 | AH73: =H73 -> 274 | AI73: 3623 | AJ73: 3348 | AK73: 3273 | AL73: =I73 -> 2812 | AM73: 2853 | AN73: =80025 -> 80025 | AP73: =AD73 -> 469 | AQ73: =AE73 -> 416 | AR73: =AF73 -> 362 | AS73: =AG73 -> 316 | AT73: =AH73 -> 274 | AU73: =AI73 -> 3623 | AV73: =AJ73 -> 3348 | AW73: =AK73 -> 3273 | ... AZ73: =AN73 -> 80025
B74: Operating Lease Liabilities, Net of Current Portion | C74: 0 | D74: 0 | E74: 11793 | F74: 22599 | G74: 55854 | H74: 75648 | I74: 73613 | N74: =C74 -> 0 | O74: 0 | P74: 0 | Q74: 0 | R74: =D74 -> 0 | S74: 10935 | T74: 11604 | U74: 11413 | V74: =E74 -> 11793 | W74: 11061 | X74: 11300 | Y74: 21799 | Z74: =F74 -> 22599 | AA74: 21485 | AB74: 21143 | AC74: 56484 | AD74: =G74 -> 55854 | AE74: 44787 | AF74: 77122 | AG74: 76382 | AH74: =H74 -> 75648 | AI74: 75490 | AJ74: 74884 | AK74: 74506 | AL74: =I74 -> 73613 | AM74: 72147 | AN74: 4441 | AP74: =AD74 -> 55854 | AQ74: =AE74 -> 44787 | AR74: =AF74 -> 77122 | AS74: =AG74 -> 76382 | AT74: =AH74 -> 75648 | AU74: =AI74 -> 75490 | AV74: =AJ74 -> 74884 | AW74: =AK74 -> 74506 | ... AZ74: =AN74 -> 4441 | BB74: =SUM(AZ74/AV74)-1 -> -0.94069494
B75: Total Liabilities | C75: =SUM(C71:C74)+C68 -> 55959 | D75: =SUM(D71:D74)+D68 -> 67833 | E75: =SUM(E71:E74)+E68 -> 100909 | F75: =SUM(F71:F74)+F68 -> 1246904 | G75: =SUM(G71:G74)+G68 -> 1265772 | H75: =SUM(H71:H74)+H68 -> 1287818 | I75: =SUM(I71:I74)+I68 -> 1279354 | K75: =SUM(K71:K74)+K68 -> 0 | L75: =SUM(L71:L74)+L68 -> 0 | M75: =SUM(M71:M74)+M68 -> 0 | N75: =SUM(N71:N74)+N68 -> 55959 | O75: =SUM(O71:O74)+O68 -> 52795 | P75: =SUM(P71:P74)+P68 -> 65276 | Q75: =SUM(Q71:Q74)+Q68 -> 78013 | R75: =SUM(R71:R74)+R68 -> 67833 | ... AN75: =SUM(AN71:AN74)+AN68 -> 1368764 | AP75: =SUM(AP71:AP74)+AP68 -> 1265772 | AQ75: =SUM(AQ71:AQ74)+AQ68 -> 1239711 | AR75: =SUM(AR71:AR74)+AR68 -> 1267703 | AS75: =SUM(AS71:AS74)+AS68 -> 1292114 | AT75: =SUM(AT71:AT74)+AT68 -> 1287818 | AU75: =SUM(AU71:AU74)+AU68 -> 1296437 | AV75: =SUM(AV71:AV74)+AV68 -> 1301259 | AW75: =SUM(AW71:AW74)+AW68 -> 1304862 | ... AZ75: =SUM(AZ71:AZ74)+AZ68 -> 1368764 | BB75: =SUM(AZ75/AV75)-1 -> 0.051876683
B77: Preferred Stock Convertible | C77: =2000+4999+14882+24948+17214+29840+55658+49999 -> 199540 | D77: 0 | E77: 0 | F77: 0 | G77: 0 | H77: 0 | I77: 0 | N77: =C77 -> 199540 | O77: =2000+4999+14882+24948+17214+29840+55658+49999 -> 199540 | P77: 0 | Q77: 0 | R77: =D77 -> 0 | S77: 0 | T77: 0 | U77: 0 | V77: =E77 -> 0 | W77: 0 | X77: 0 | Y77: 0 | Z77: =F77 -> 0 | AA77: 0 | AB77: 0 | AC77: 0 | AD77: 0 | AE77: 0 | AF77: 0 | AG77: 0 | AH77: =H77 -> 0 | AI77: 0 | AJ77: 0 | AK77: 0 | AL77: =I77 -> 0 | AM77: 0 | AN77: 0 | AP77: =AD77 -> 0 | AQ77: =AE77 -> 0 | AR77: =AF77 -> 0 | AS77: =AG77 -> 0 | AT77: =AH77 -> 0 | AU77: =AI77 -> 0 | AV77: =AJ77 -> 0 | AW77: =AK77 -> 0 | ... AZ77: =AN77 -> 0
B78: Common Stock - Par Value | C78: 1 | D78: 6 | E78: 6 | F78: 6 | G78: 6 | H78: 6 | I78: 8 | N78: =C78 -> 1 | O78: 1 | P78: 6 | Q78: 6 | R78: =D78 -> 6 | S78: 6 | T78: 6 | U78: 6 | V78: =E78 -> 6 | W78: 6 | X78: 6 | Y78: 6 | Z78: =F78 -> 6 | AA78: 6 | AB78: 6 | AC78: 6 | AD78: 6 | AE78: 6 | AF78: 6 | AG78: 6 | AH78: =H78 -> 6 | AI78: 6 | AJ78: 6 | AK78: 6 | AL78: =I78 -> 8 | AM78: 8 | AN78: 8 | AP78: =AD78 -> 6 | AQ78: =AE78 -> 6 | AR78: =AF78 -> 6 | AS78: =AG78 -> 6 | AT78: =AH78 -> 6 | AU78: =AI78 -> 6 | AV78: =AJ78 -> 6 | AW78: =AK78 -> 6 | ... AZ78: =AN78 -> 8
B79: Additional Paid in Capital | C79: 7921 | D79: 526199 | E79: 560210 | F79: 510014 | G79: 544357 | H79: 573128 | I79: 644004 | N79: =C79 -> 7921 | O79: 9142 | P79: 477541 | Q79: 518485 | R79: =D79 -> 526199 | S79: 532275 | T79: 540576 | U79: 548706 | V79: =E79 -> 560210 | W79: 485684 | X79: 496210 | Y79: 503690 | Z79: =F79 -> 510014 | AA79: 519681 | AB79: 530152 | AC79: 539399 | AD79: 544357 | AE79: 553805 | AF79: 561484 | AG79: 567927 | AH79: =H79 -> 573128 | AI79: 578773 | AJ79: 584441 | AK79: 590282 | AL79: =I79 -> 644004 | AM79: 649637 | AN79: 653855 | AP79: =AD79 -> 544357 | AQ79: =AE79 -> 553805 | AR79: =AF79 -> 561484 | AS79: =AG79 -> 567927 | AT79: =AH79 -> 573128 | AU79: =AI79 -> 578773 | AV79: =AJ79 -> 584441 | AW79: =AK79 -> 590282 | ... AZ79: =AN79 -> 653855
B80: Accumulated Deficit | C80: -129672 | D80: -142115 | E80: -194867 | F80: -376972 | G80: -743109 | H80: -1081253 | I80: -1241531 | N80: =C80 -> -129672 | O80: -136321 | P80: -145762 | Q80: -141663 | R80: =D80 -> -142115 | S80: -140300 | T80: -150505 | U80: -169790 | V80: =E80 -> -194867 | W80: -222133 | X80: -241785 | Y80: -296601 | Z80: =F80 -> -376972 | AA80: -477430 | AB80: -574564 | AC80: -676242 | AD80: -743109 | AE80: -802146 | AF80: -855651 | AG80: -926143 | AH80: =H80 -> -1081253 | AI80: -1135614 | AJ80: -1170093 | AK80: -1196669 | AL80: =I80 -> -1241531 | AM80: -1294447 | AN80: -1323689 | AP80: =AD80 -> -743109 | AQ80: =AE80 -> -802146 | AR80: =AF80 -> -855651 | AS80: =AG80 -> -926143 | AT80: =AH80 -> -1081253 | AU80: =AI80 -> -1135614 | AV80: =AJ80 -> -1170093 | AW80: =AK80 -> -1196669 | ... AZ80: =AN80 -> -1323689
B81: Accumulated Other Comprehensive (Loss) income | C81: 0 | D81: 0 | E81: 1748 | F81: -553 | G81: -4802 | H81: -5249 | I81: -3689 | N81: =C81 -> 0 | O81: 0 | P81: 0 | R81: =D81 -> 0 | S81: 0 | T81: -167 | U81: 478 | V81: =E81 -> 1748 | W81: 490 | X81: 1050 | Y81: 10 | Z81: =F81 -> -553 | AA81: -1276 | AB81: -3535 | AC81: -5207 | AD81: -4802 | AE81: -4799 | AF81: -4957 | AG81: -4696 | AH81: =H81 -> -5249 | AI81: -4576 | AJ81: -4379 | AK81: -5543 | AL81: =I81 -> -3689 | AM81: -4729 | AN81: -7197 | AP81: =AD81 -> -4802 | AQ81: =AE81 -> -4799 | AR81: =AF81 -> -4957 | AS81: =AG81 -> -4696 | AT81: =AH81 -> -5249 | AU81: =AI81 -> -4576 | AV81: =AJ81 -> -4379 | AW81: =AK81 -> -5543 | ... AZ81: =AN81 -> -7197
B82: Total stockholders' equity | C82: =SUM(C77:C81) -> 77790 | D82: =SUM(D77:D81) -> 384090 | E82: =SUM(E77:E81) -> 367097 | F82: =SUM(F77:F81) -> 132495 | G82: =SUM(G77:G81) -> -203548 | H82: =SUM(H77:H81) -> -513368 | I82: =SUM(I77:I81) -> -601208 | K82: =SUM(K77:K81) -> 0 | L82: =SUM(L77:L81) -> 0 | M82: =SUM(M77:M81) -> 0 | N82: =SUM(N77:N81) -> 77790 | O82: =SUM(O77:O81) -> 72362 | P82: =SUM(P77:P81) -> 331785 | Q82: =SUM(Q77:Q81) -> 376828 | R82: =SUM(R77:R81) -> 384090 | ... AN82: =SUM(AN77:AN81) -> -677023 | AP82: =SUM(AP77:AP81) -> -203548 | AQ82: =SUM(AQ77:AQ81) -> -253134 | AR82: =SUM(AR77:AR81) -> -299118 | AS82: =SUM(AS77:AS81) -> -362906 | AT82: =SUM(AT77:AT81) -> -513368 | AU82: =SUM(AU77:AU81) -> -561411 | AV82: =SUM(AV77:AV81) -> -590025 | AW82: =SUM(AW77:AW81) -> -611924 | ... AZ82: =SUM(AZ77:AZ81) -> -677023 | BB82: =SUM(AZ82/AV82)-1 -> 0.14744799
B83: Total liabilities and stockholders' equity | C83: =SUM(C82+C75) -> 133749 | D83: =SUM(D82+D75) -> 451923 | E83: =SUM(E82+E75) -> 468006 | F83: =SUM(F82+F75) -> 1379399 | G83: =SUM(G82+G75) -> 1062224 | H83: =SUM(H82+H75) -> 774450 | I83: =SUM(I82+I75) -> 678146 | K83: =SUM(K82+K75) -> 0 | L83: =SUM(L82+L75) -> 0 | M83: =SUM(M82+M75) -> 0 | N83: =SUM(N82+N75) -> 133749 | O83: =SUM(O82+O75) -> 125157 | P83: =SUM(P82+P75) -> 397061 | Q83: =SUM(Q82+Q75) -> 454841 | R83: =SUM(R82+R75) -> 451923 | ... AN83: =SUM(AN82+AN75) -> 691741 | AP83: =SUM(AP82+AP75) -> 1062224 | AQ83: =SUM(AQ82+AQ75) -> 986577 | AR83: =SUM(AR82+AR75) -> 968585 | AS83: =SUM(AS82+AS75) -> 929208 | AT83: =SUM(AT82+AT75) -> 774450 | AU83: =SUM(AU82+AU75) -> 735026 | AV83: =SUM(AV82+AV75) -> 711234 | AW83: =SUM(AW82+AW75) -> 692938 | ... AZ83: =SUM(AZ82+AZ75) -> 691741 | BB83: =SUM(AZ83/AV83)-1 -> -0.027407295
B85: Balance Check | C85: =C83-C60 -> 0 | D85: =D83-D60 -> 0 | E85: =E83-E60 -> 0 | F85: =F83-F60 -> 0 | G85: =G83-G60 -> 0 | H85: =H83-H60 -> 0 | I85: =I83-I60 -> 0 | N85: =N83-N60 -> 0 | O85: =O83-O60 -> 0 | P85: =P83-P60 -> 0 | Q85: =Q83-Q60 -> 0 | R85: =R83-R60 -> 0 | S85: =S83-S60 -> 0 | T85: =T83-T60 -> 0 | U85: =U83-U60 -> 0 | ... AN85: =AN83-AN60 -> 0 | AP85: =AP83-AP60 -> 0 | AQ85: =AQ83-AQ60 -> 0 | AR85: =AR83-AR60 -> 0 | AS85: =AS83-AS60 -> 0 | AT85: =AT83-AT60 -> 0 | AU85: =AU83-AU60 -> 0 | AV85: =AV83-AV60 -> 0 | AW85: =AW83-AW60 -> 0 | ... AZ85: =AZ83-AZ60 -> 0
B87: 1) Prepaid Expenses and Other Current Assets consists of: Prepaid Expenses and Other Current Assets + Asset Held for Sale.
B88: 2) Accrued Expenses, Other Current Liabilities, and Other Payables consists of: Accrued Expenses and Other Current Liabilities + Accrued Bonus + Stock warrant liability + Accrued Litigation Settlement + Wages Payable.
B89: 3) Consolidated Short-Term Borrowings consists of: Short-term borrowings under revolving credit Facility + Short-term borrowings under revolving credit line and bank term loan + Short-term Finance Lease Liabilities.
B90: 4) Consolidated Other Long-Term Borrowings consists of: Revolving Credit Line + Long-term Portion of Bank Term Loan, Net + Equipment loan, net + Delayed draw term loan, net + Delayed draw term loan warrants.
A92: X | B92: Cash-Flows Statement | K92: Quarterly | AV92: LTM | BB92: Variance
B93: =B7 -> Fiscal Period | C93: =C7 -> 2018 | D93: =D7 -> 2019 | E93: =E7 -> 2020 | F93: =F7 -> 2021 | G93: =G7 -> 2022 | H93: =H7 -> 2023 | I93: =I7 -> 2024 | K93: =K7 -> 1Q18 | L93: =L7 -> 2Q18 | M93: =M7 -> 3Q18 | N93: =N7 -> 4Q18 | O93: =O7 -> 1Q19 | P93: =P7 -> 2Q19 | Q93: =Q7 -> 3Q19 | R93: =R7 -> 4Q19 | ... AN93: =AN7 -> 2Q25 | AP93: =AP7 -> 4Q22 | AQ93: =AQ7 -> 1Q23 | AR93: =AR7 -> 2Q23 | AS93: =AS7 -> 3Q23 | AT93: =AT7 -> 4Q23 | AU93: =AU7 -> 1Q24 | AV93: =AV7 -> 2Q24 | AW93: =AW7 -> 3Q24 | ... AZ93: =AZ7 -> 2Q25
B94: =B8 -> Fiscal Period End Date | C94: =C8 -> 43465 | D94: =D8 -> 43830 | E94: =E8 -> 44196 | F94: =F8 -> 44561 | G94: =G8 -> 44926 | H94: =H8 -> 45291 | I94: =I8 -> 45657 | K94: =K8 -> 43190 | L94: =L8 -> 43281 | M94: =M8 -> 43372 | N94: =N8 -> 43465 | O94: =O8 -> 43554 | P94: =P8 -> 43645 | Q94: =Q8 -> 43736 | R94: =R8 -> 43830 | ... AN94: =AN8 -> 45836 | AP94: =AP8 -> 44926 | AQ94: =AQ8 -> 45017 | AR94: =AR8 -> 45108 | AS94: =AS8 -> 45199 | AT94: =AT8 -> 45291 | AU94: =AU8 -> 45381 | AV94: =AV8 -> 45472 | AW94: =AW8 -> 45563 | ... AZ94: =AZ8 -> 45836
B96: Cash-Flows From Operating Activities
B97: Net income (loss) | C97: =C32 -> -29886 | D97: =D32 -> -12443 | E97: =E32 -> -52752 | F97: =F32 -> -182105 | G97: =G32 -> -366137 | H97: =H32 -> -338144 | I97: =I32 -> -160278 | K97: =K32 -> -5696 | L97: =L32 -> -7396 | M97: =M32 -> -9342 | N97: =N32 -> -7452 | O97: =O32 -> -6649 | P97: =P32 -> -9441 | Q97: =Q32 -> 4099 | R97: =SUM(D97-SUM(O97:Q97)) -> -452 | S97: =S32 -> 1815 | T97: =T32 -> -10205 | U97: =U32 -> -19285 | V97: =SUM(E97-SUM(S97:U97)) -> -25077 | W97: =W32 -> -27266 | X97: =X32 -> -19652 | Y97: =Y32 -> -54816 | Z97: =SUM(F97-SUM(W97:Y97)) -> -80371 | AA97: =AA32 -> -100458 | AB97: =AB32 -> -97134 | AC97: =AC32 -> -101678 | AD97: =SUM(G97-SUM(AA97:AC97)) -> -66867 | AE97: =AE32 -> -59037 | AF97: =AF32 -> -53505 | AG97: =AG32 -> -70492 | AH97: =AH32 -> -155110 | AI97: =AI32 -> -54361 | AJ97: =AJ32 -> -34479 | AK97: =AK32 -> -26576 | AL97: =AL32 -> -44862 | ... AN97: =AN32 -> -29242 | AP97: =SUM(AA97:AD97) -> -366137 | AQ97: =SUM(AB97:AE97) -> -324716 | AR97: =SUM(AC97:AF97) -> -281087 | AS97: =SUM(AD97:AG97) -> -249901 | AT97: =SUM(AE97:AH97) -> -338144 | AU97: =SUM(AF97:AI97) -> -333468 | AV97: =SUM(AG97:AJ97) -> -314442 | AW97: =SUM(AH97:AK97) -> -270526 | ... AZ97: =SUM(AK97:AN97) -> -153585 | BB97: =SUM(AZ97/AV97)-1 -> -0.51156334
B99: Adjustments to reconcile net income: | BB99: =SUM(AZ99/AV99)-1 -> #DIV/0!
B100: Depreciation and Amortization | C100: 4921 | D100: 8106 | E100: 13299 | F100: 21663 | G100: 32582 | H100: 48094 | I100: 23121 | K100: 733 | L100: =1620-K100 -> 887 | M100: =3046-L100-K100 -> 1426 | N100: =SUM(C100-SUM(K100:M100)) -> 1875 | O100: 1905 | P100: =3957-O100 -> 2052 | Q100: =5980-P100-O100 -> 2023 | R100: =SUM(D100-SUM(O100:Q100)) -> 2126 | S100: 2583 | T100: =5855-S100 -> 3272 | U100: =9276-T100-S100 -> 3421 | V100: =SUM(E100-SUM(S100:U100)) -> 4023 | W100: 4326 | X100: =9207-W100 -> 4881 | Y100: =14910-X100-W100 -> 5703 | Z100: =SUM(F100-SUM(W100:Y100)) -> 6753 | AA100: 7091 | AB100: =14820-AA100 -> 7729 | AC100: =23255-AB100-AA100 -> 8435 | AD100: =SUM(G100-SUM(AA100:AC100)) -> 9327 | AE100: 6049 | AF100: =11928-AE100 -> 5879 | AG100: =17707-AF100-AE100 -> 5779 | AH100: =SUM(H100-SUM(AE100:AG100)) -> 30387 | AI100: 6969 | AJ100: =12182-AI100 -> 5213 | AK100: =17464-AJ100-AI100 -> 5282 | AL100: =SUM(I100-SUM(AI100:AK100)) -> 5657 | AM100: 7416 | AN100: =15682-AM100 -> 8266 | AP100: =SUM(AA100:AD100) -> 32582 | AQ100: =SUM(AB100:AE100) -> 31540 | AR100: =SUM(AC100:AF100) -> 29690 | AS100: =SUM(AD100:AG100) -> 27034 | AT100: =SUM(AE100:AH100) -> 48094 | AU100: =SUM(AF100:AI100) -> 49014 | AV100: =SUM(AG100:AJ100) -> 48348 | AW100: =SUM(AH100:AK100) -> 47851 | ... AZ100: =SUM(AK100:AN100) -> 26621 | BB100: =SUM(AZ100/AV100)-1 -> -0.44938777
B101: Share-based Compensation Expense | C101: 2241 | D101: 12807 | E101: 27279 | F101: 27698 | G101: 33857 | H101: 29098 | I101: 23923 | K101: 260 | L101: =710-K101 -> 450 | M101: =1090-L101-K101 -> 380 | N101: =SUM(C101-SUM(K101:M101)) -> 1151 | O101: 855 | P101: =2678-O101 -> 1823 | Q101: =5807-P101-O101 -> 3129 | R101: =SUM(D101-SUM(O101:Q101)) -> 7000 | S101: 5949 | T101: =13535-S101 -> 7586 | U101: =20377-T101-S101 -> 6842 | V101: =SUM(E101-SUM(S101:U101)) -> 6902 | W101: 7376 | X101: =15239-W101 -> 7863 | Y101: =21624-X101-W101 -> 6385 | Z101: =SUM(F101-SUM(W101:Y101)) -> 6074 | AA101: 9292 | AB101: =19598-AA101 -> 10306 | AC101: =28848-AB101-AA101 -> 9250 | AD101: =SUM(G101-SUM(AA101:AC101)) -> 5009 | AE101: 9565 | AF101: =17313-AE101 -> 7748 | AG101: =23791-AF101-AE101 -> 6478 | AH101: =SUM(H101-SUM(AE101:AG101)) -> 5307 | AI101: 6075 | AJ101: =11848-AI101 -> 5773 | AK101: =17753-AJ101-AI101 -> 5905 | AL101: =SUM(I101-SUM(AI101:AK101)) -> 6170 | AM101: 5853 | AN101: =10157-AM101 -> 4304 | AP101: =SUM(AA101:AD101) -> 33857 | AQ101: =SUM(AB101:AE101) -> 34130 | AR101: =SUM(AC101:AF101) -> 31572 | AS101: =SUM(AD101:AG101) -> 28800 | AT101: =SUM(AE101:AH101) -> 29098 | AU101: =SUM(AF101:AI101) -> 25608 | AV101: =SUM(AG101:AJ101) -> 23633 | AW101: =SUM(AH101:AK101) -> 23060 | ... AZ101: =SUM(AK101:AN101) -> 22232
B102: Non-cash Lease Expense | C102: 0 | D102: 0 | E102: 2341 | F102: 3418 | G102: 5167 | H102: 8140 | I102: 8279 | K102: 0 | L102: 0 | M102: 0 | N102: =SUM(C102-SUM(K102:M102)) -> 0 | O102: 0 | P102: 0 | Q102: 0 | R102: =SUM(D102-SUM(O102:Q102)) -> 0 | S102: 445 | T102: =1193-S102 -> 748 | U102: =1573-T102-S102 -> 380 | V102: =SUM(E102-SUM(S102:U102)) -> 768 | W102: 724 | X102: =1580-W102 -> 856 | Y102: =2351-X102-W102 -> 771 | Z102: =SUM(F102-SUM(W102:Y102)) -> 1067 | AA102: 1118 | AB102: =2091-AA102 -> 973 | AC102: =3389-AB102-AA102 -> 1298 | AD102: =SUM(G102-SUM(AA102:AC102)) -> 1778 | AE102: 1783 | AF102: =3613-AE102 -> 1830 | AG102: =5997-AF102-AE102 -> 2384 | AH102: =SUM(H102-SUM(AE102:AG102)) -> 2143 | AI102: 2074 | AJ102: =4130-AI102 -> 2056 | AK102: =6198-AJ102-AI102 -> 2068 | AL102: =SUM(I102-SUM(AI102:AK102)) -> 2081 | AM102: 2079 | AN102: =2889-AM102 -> 810 | AP102: =SUM(AA102:AD102) -> 5167 | AQ102: =SUM(AB102:AE102) -> 5832 | AR102: =SUM(AC102:AF102) -> 6689 | AS102: =SUM(AD102:AG102) -> 7775 | AT102: =SUM(AE102:AH102) -> 8140 | AU102: =SUM(AF102:AI102) -> 8431 | AV102: =SUM(AG102:AJ102) -> 8657 | AW102: =SUM(AH102:AK102) -> 8341 | ... AZ102: =SUM(AK102:AN102) -> 7038
B103: Provision for doubtful accounts | C103: 0 | D103: 0 | E103: 0 | F103: 0 | G103: 0 | H103: 0 | I103: 0 | K103: 0 | L103: 0 | M103: 0 | N103: =SUM(C103-SUM(K103:M103)) -> 0 | O103: 0 | P103: 0 | Q103: 0 | R103: =SUM(D103-SUM(O103:Q103)) -> 0 | S103: 0 | T103: 0 | U103: 0 | V103: =SUM(E103-SUM(S103:U103)) -> 0 | W103: 0 | X103: 0 | Y103: 0 | Z103: =SUM(F103-SUM(W103:Y103)) -> 0 | AA103: 0 | AB103: 0 | AC103: 0 | AD103: =SUM(G103-SUM(AA103:AC103)) -> 0 | AE103: 0 | AF103: 0 | AG103: 0 | AH103: =SUM(H103-SUM(AE103:AG103)) -> 0 | AI103: 0 | AJ103: 232 | AK103: =232-AJ103-AI103 -> 0 | AL103: =SUM(I103-SUM(AI103:AK103)) -> -232 | AM103: 0 | AN103: 0
B104: Loss on Sale of Fixed Assets | C104: 76 | D104: 93 | E104: 222 | F104: 199 | G104: 486 | H104: 20515 | I104: 809 | K104: 0 | L104: 0 | M104: =76-L104-K104 -> 76 | N104: =SUM(C104-SUM(K104:M104)) -> 0 | O104: 0 | P104: 0 | Q104: 0 | R104: =SUM(D104-SUM(O104:Q104)) -> 93 | S104: 0 | T104: =183-S104 -> 183 | U104: =218-T104-S104 -> 35 | V104: =SUM(E104-SUM(S104:U104)) -> 4 | W104: 3 | X104: =111-W104 -> 108 | Y104: =199-X104-W104 -> 88 | Z104: =SUM(F104-SUM(W104:Y104)) -> 0 | AA104: 315 | AB104: =400-AA104 -> 85 | AC104: =946-AB104-AA104 -> 546 | AD104: =SUM(G104-SUM(AA104:AC104)) -> -460 | AE104: 3907 | AF104: =3804-AE104 -> -103 | AG104: =3876-AF104-AE104 -> 72 | AH104: =SUM(H104-SUM(AE104:AG104)) -> 16639 | AI104: 183 | AJ104: =363-AI104 -> 180 | AK104: =493-AJ104-AI104 -> 130 | AL104: =SUM(I104-SUM(AI104:AK104)) -> 316 | AM104: 98 | AN104: =223-AM104 -> 125 | AP104: =SUM(AA104:AD104) -> 486 | AQ104: =SUM(AB104:AE104) -> 4078 | AR104: =SUM(AC104:AF104) -> 3890 | AS104: =SUM(AD104:AG104) -> 3416 | AT104: =SUM(AE104:AH104) -> 20515 | AU104: =SUM(AF104:AI104) -> 16791 | AV104: =SUM(AG104:AJ104) -> 17074 | AW104: =SUM(AH104:AK104) -> 17132 | ... AZ104: =SUM(AK104:AN104) -> 669
B105: Amortization of Debt Issuance Costs | C105: 109 | D105: 181 | E105: 256 | F105: 3322 | G105: 3934 | H105: 3934 | I105: 3934 | K105: 9 | L105: =35-K105 -> 26 | M105: =51-L105-K105 -> 16 | N105: =SUM(C105-SUM(K105:M105)) -> 58 | O105: 58 | P105: =78-O105 -> 20 | Q105: =124-P105-O105 -> 46 | R105: =SUM(D105-SUM(O105:Q105)) -> 57 | S105: 57 | T105: =93-S105 -> 36 | U105: =195-T105-S105 -> 102 | V105: =SUM(E105-SUM(S105:U105)) -> 61 | W105: 369 | X105: =1352-W105 -> 983 | Y105: =2338-X105-W105 -> 986 | Z105: =SUM(F105-SUM(W105:Y105)) -> 984 | AA105: 984 | AB105: =1967-AA105 -> 983 | AC105: =2951-AB105-AA105 -> 984 | AD105: =SUM(G105-SUM(AA105:AC105)) -> 983 | AE105: 984 | AF105: =1967-AE105 -> 983 | AG105: =2951-AF105-AE105 -> 984 | AH105: =SUM(H105-SUM(AE105:AG105)) -> 983 | AI105: 984 | AJ105: =1967-AI105 -> 983 | AK105: =2951-AJ105-AI105 -> 984 | AL105: =SUM(I105-SUM(AI105:AK105)) -> 983 | AM105: 984 | AN105: =1970-AM105 -> 986 | AP105: =SUM(AA105:AD105) -> 3934 | AQ105: =SUM(AB105:AE105) -> 3934 | AR105: =SUM(AC105:AF105) -> 3934 | AS105: =SUM(AD105:AG105) -> 3934 | AT105: =SUM(AE105:AH105) -> 3934 | AU105: =SUM(AF105:AI105) -> 3934 | AV105: =SUM(AG105:AJ105) -> 3934 | AW105: =SUM(AH105:AK105) -> 3934 | ... AZ105: =SUM(AK105:AN105) -> 3937
B106: Loss on Extinguishment of Debt | C106: 0 | D106: 0 | E106: 1538 | F106: 1037 | G106: 0 | H106: 0 | I106: 0 | K106: 0 | L106: 0 | M106: 0 | N106: =SUM(C106-SUM(K106:M106)) -> 0 | O106: 0 | P106: 0 | Q106: 0 | R106: =SUM(D106-SUM(O106:Q106)) -> 0 | S106: 0 | T106: =1538-S106 -> 1538 | U106: =1538-T106-S106 -> 0 | V106: =SUM(E106-SUM(S106:U106)) -> 0 | W106: 1037 | X106: =1037-W106 -> 0 | Y106: =1037-X106-W106 -> 0 | Z106: =SUM(F106-SUM(W106:Y106)) -> 0 | AA106: 671 | AB106: =0-AA106 -> -671 | AC106: =0-AB106-AA106 -> 0 | AD106: =SUM(G106-SUM(AA106:AC106)) -> 0 | AE106: 0 | AF106: 0 | AG106: 0 | AH106: =SUM(H106-SUM(AE106:AG106)) -> 0 | AI106: 0 | AJ106: 0 | AK106: 0 | AL106: =SUM(I106-SUM(AI106:AK106)) -> 0 | AM106: 0 | AN106: 0 | AP106: =SUM(AA106:AD106) -> 0 | AQ106: =SUM(AB106:AE106) -> -671 | AR106: =SUM(AC106:AF106) -> 0 | AS106: =SUM(AD106:AG106) -> 0 | AT106: =SUM(AE106:AH106) -> 0 | AU106: =SUM(AF106:AI106) -> 0 | AV106: =SUM(AG106:AJ106) -> 0 | AW106: =SUM(AH106:AK106) -> 0 | ... AZ106: =SUM(AK106:AN106) -> 0
B107: Equity in Losses of Unconsolidated Joint Ventures | C107: 0 | D107: 0 | E107: 0 | F107: 2977 | G107: 18948 | H107: 3902 | I107: 73 | K107: 0 | L107: 0 | M107: 0 | N107: =SUM(C107-SUM(K107:M107)) -> 0 | O107: 0 | P107: 0 | Q107: 0 | R107: =SUM(D107-SUM(O107:Q107)) -> 0 | S107: 0 | T107: 0 | U107: 0 | V107: =SUM(E107-SUM(S107:U107)) -> 0 | W107: 374 | X107: =581-W107 -> 207 | Y107: =1176-X107-W107 -> 595 | Z107: =SUM(F107-SUM(W107:Y107)) -> 1801 | AA107: 0 | AB107: =2103-AA107 -> 2103 | AC107: =10849-AB107-AA107 -> 8746 | AD107: =SUM(G107-SUM(AA107:AC107)) -> 8099 | AE107: 3235 | AF107: =3738-AE107 -> 503 | AG107: =3864-AF107-AE107 -> 126 | AH107: =SUM(H107-SUM(AE107:AG107)) -> 38 | AI107: -7 | AJ107: =23-AI107 -> 30 | AK107: =61-AJ107-AI107 -> 38 | AL107: =SUM(I107-SUM(AI107:AK107)) -> 12 | AM107: 11 | AN107: =70-AM107 -> 59 | AP107: =SUM(AA107:AD107) -> 18948 | AQ107: =SUM(AB107:AE107) -> 22183 | AR107: =SUM(AC107:AF107) -> 20583 | AS107: =SUM(AD107:AG107) -> 11963 | AT107: =SUM(AE107:AH107) -> 3902 | AU107: =SUM(AF107:AI107) -> 660 | AV107: =SUM(AG107:AJ107) -> 187 | AW107: =SUM(AH107:AK107) -> 99 | ... AZ107: =SUM(AK107:AN107) -> 120
B108: Write-down of Notes Receivable | C108: 0 | D108: 0 | E108: 0 | F108: 0 | G108: 0 | H108: 3795 | I108: 0 | K108: 0 | L108: 0 | M108: 0 | N108: =SUM(C108-SUM(K108:M108)) -> 0 | O108: 0 | P108: 0 | Q108: 0 | R108: =SUM(D108-SUM(O108:Q108)) -> 0 | S108: 0 | T108: 0 | U108: 0 | V108: =SUM(E108-SUM(S108:U108)) -> 0 | W108: 0 | X108: 0 | Y108: 0 | Z108: =SUM(F108-SUM(W108:Y108)) -> 0 | AA108: 0 | AB108: 0 | AC108: 0 | AD108: =SUM(G108-SUM(AA108:AC108)) -> 0 | AE108: 0 | AF108: 0 | AG108: =3795-AF108-AE108 -> 3795 | AH108: =SUM(H108-SUM(AE108:AG108)) -> 0 | AI108: 0 | AJ108: 0 | AK108: 0 | AL108: =SUM(I108-SUM(AI108:AK108)) -> 0 | AM108: 0 | AN108: 0 | AP108: =SUM(AA108:AD108) -> 0 | AQ108: =SUM(AB108:AE108) -> 0 | AR108: =SUM(AC108:AF108) -> 0 | AS108: =SUM(AD108:AG108) -> 3795 | AT108: =SUM(AE108:AH108) -> 3795 | AU108: =SUM(AF108:AI108) -> 3795 | AV108: =SUM(AG108:AJ108) -> 3795 | AW108: =SUM(AH108:AK108) -> 0 | ... AZ108: =SUM(AK108:AN108) -> 0
B109: Unrealized Gain/loss on Foreign Currency Transactions | C109: 0 | D109: 0 | E109: 0 | F109: 0 | G109: 5106 | H109: -1822 | I109: 5113 | K109: 0 | L109: 0 | M109: 0 | N109: =SUM(C109-SUM(K109:M109)) -> 0 | O109: 0 | P109: 0 | Q109: 0 | R109: =SUM(D109-SUM(O109:Q109)) -> 0 | S109: 0 | T109: 0 | U109: 0 | V109: =SUM(E109-SUM(S109:U109)) -> 0 | W109: 0 | X109: 0 | Y109: 0 | Z109: =SUM(F109-SUM(W109:Y109)) -> 0 | AA109: 0 | AB109: =7076-AA109 -> 7076 | AC109: =11160-AB109-AA109 -> 4084 | AD109: =SUM(G109-SUM(AA109:AC109)) -> -6054 | AE109: -731 | AF109: =213-AE109 -> 944 | AG109: =2740-AF109-AE109 -> 2527 | AH109: =SUM(H109-SUM(AE109:AG109)) -> -4562 | AI109: 2173 | AJ109: =2671-AI109 -> 498 | AK109: =-1118-AJ109-AI109 -> -3789 | AL109: =SUM(I109-SUM(AI109:AK109)) -> 6231 | AM109: -3571 | AN109: =-11161-AM109 -> -7590 | AP109: =SUM(AA109:AD109) -> 5106 | AQ109: =SUM(AB109:AE109) -> 4375 | AR109: =SUM(AC109:AF109) -> -1757 | AS109: =SUM(AD109:AG109) -> -3314 | AT109: =SUM(AE109:AH109) -> -1822 | AU109: =SUM(AF109:AI109) -> 1082 | AV109: =SUM(AG109:AJ109) -> 636 | AW109: =SUM(AH109:AK109) -> -5680 | ... AZ109: =SUM(AK109:AN109) -> -8719
B110: Change in Preferred and Common Stock Warrant Liabilities | C110: 1120 | D110: 12503 | E110: 0 | F110: 0 | G110: 0 | H110: 0 | I110: 0 | K110: 129 | L110: =259-K110 -> 130 | M110: =1253-L110-K110 -> 994 | N110: =SUM(C110-SUM(K110:M110)) -> -133 | O110: 759 | P110: =12503-O110 -> 11744 | Q110: =12503-P110-O110 -> 0 | R110: =SUM(D110-SUM(O110:Q110)) -> 0 | S110: 0 | T110: 0 | U110: 0 | V110: =SUM(E110-SUM(S110:U110)) -> 0 | W110: 0 | X110: 0 | Y110: 0 | Z110: =SUM(F110-SUM(W110:Y110)) -> 0 | AA110: 0 | AB110: 0 | AC110: 0 | AD110: =SUM(G110-SUM(AA110:AC110)) -> 0 | AE110: 0 | AF110: 0 | AG110: 0 | AH110: =SUM(H110-SUM(AE110:AG110)) -> 0 | AI110: 0 | AJ110: 0 | AK110: 0 | AL110: =SUM(I110-SUM(AI110:AK110)) -> 0 | AM110: 0 | AN110: 0 | AP110: =SUM(AA110:AD110) -> 0 | AQ110: =SUM(AB110:AE110) -> 0 | AR110: =SUM(AC110:AF110) -> 0 | AS110: =SUM(AD110:AG110) -> 0 | AT110: =SUM(AE110:AH110) -> 0 | AU110: =SUM(AF110:AI110) -> 0 | AV110: =SUM(AG110:AJ110) -> 0 | AW110: =SUM(AH110:AK110) -> 0 | ... AZ110: =SUM(AK110:AN110) -> 0
B111: Provision for Credit Losses | C111: 0 | D111: 0 | E111: 0 | F111: 0 | G111: 0 | H111: 0 | I111: 221 | K111: 0 | L111: 0 | M111: 0 | N111: =SUM(C111-SUM(K111:M111)) -> 0 | O111: 0 | P111: 0 | Q111: 0 | R111: =SUM(D111-SUM(O111:Q111)) -> 0 | S111: 0 | T111: 0 | U111: 0 | V111: =SUM(E111-SUM(S111:U111)) -> 0 | W111: 0 | X111: 0 | Y111: 0 | Z111: =SUM(F111-SUM(W111:Y111)) -> 0 | AA111: 0 | AB111: 0 | AC111: 0 | AD111: =SUM(G111-SUM(AA111:AC111)) -> 0 | AE111: 0 | AF111: 0 | AG111: 0 | AH111: =SUM(H111-SUM(AE111:AG111)) -> 0 | AI111: 0 | AJ111: 0 | AK111: 0 | AL111: =SUM(I111-SUM(AI111:AK111)) -> 221 | AM111: 0 | AN111: 0 | AP111: =SUM(AA111:AD111) -> 0 | AQ111: =SUM(AB111:AE111) -> 0 | AR111: =SUM(AC111:AF111) -> 0 | AS111: =SUM(AD111:AG111) -> 0 | AT111: =SUM(AE111:AH111) -> 0 | AU111: =SUM(AF111:AI111) -> 0 | AV111: =SUM(AG111:AJ111) -> 0 | AW111: =SUM(AH111:AK111) -> 0 | ... AZ111: =SUM(AK111:AN111) -> 221
B113: Changes in assets and liabilities: | BB113: =SUM(AZ113/AV113)-1 -> #DIV/0!
B114: Accounts Receivable | C114: -9045 | D114: -27454 | E114: 4516 | F114: -8463 | G114: 9063 | H114: 2717 | I114: 4193 | K114: -991 | L114: =-2788-K114 -> -1797 | M114: =-8499-L114-K114 -> -5711 | N114: =SUM(C114-SUM(K114:M114)) -> -546 | O114: -3568 | P114: =-21762-O114 -> -18194 | Q114: =-21856-P114-O114 -> -94 | R114: =SUM(D114-SUM(O114:Q114)) -> -5598 | S114: 3746 | T114: =-5907-S114 -> -9653 | U114: =10365-T114-S114 -> 16272 | V114: =SUM(E114-SUM(S114:U114)) -> -5849 | W114: -963 | X114: =-27713-W114 -> -26750 | Y114: =-13495-X114-W114 -> 14218 | Z114: =SUM(F114-SUM(W114:Y114)) -> 5032 | AA114: -9108 | AB114: =-30158-AA114 -> -21050 | AC114: =7703-AB114-AA114 -> 37861 | AD114: =SUM(G114-SUM(AA114:AC114)) -> 1360 | AE114: -8078 | AF114: =-16462-AE114 -> -8384 | AG114: =-1806-AF114-AE114 -> 14656 | AH114: =SUM(H114-SUM(AE114:AG114)) -> 4523 | AI114: -4143 | AJ114: =-3273-AI114 -> 870 | AK114: =-2977-AJ114-AI114 -> 296 | AL114: =SUM(I114-SUM(AI114:AK114)) -> 7170 | AM114: -6038 | AN114: =-9291-AM114 -> -3253 | AP114: =SUM(AA114:AD114) -> 9063 | AQ114: =SUM(AB114:AE114) -> 10093 | AR114: =SUM(AC114:AF114) -> 22759 | AS114: =SUM(AD114:AG114) -> -446 | AT114: =SUM(AE114:AH114) -> 2717 | AU114: =SUM(AF114:AI114) -> 6652 | AV114: =SUM(AG114:AJ114) -> 15906 | AW114: =SUM(AH114:AK114) -> 1546 | ... AZ114: =SUM(AK114:AN114) -> -1825 | BB114: =SUM(AZ114/AV114)-1 -> -1.1147366
B115: Inventories | C115: -22113 | D115: -51339 | E115: -38863 | F115: -122666 | G115: 2572 | H115: 106087 | I115: 15576 | K115: -1144 | L115: =-6178-K115 -> -5034 | M115: =-9627-L115-K115 -> -3449 | N115: =SUM(C115-SUM(K115:M115)) -> -12486 | O115: -4025 | P115: =-12438-O115 -> -8413 | Q115: =-30013-P115-O115 -> -17575 | R115: =SUM(D115-SUM(O115:Q115)) -> -21326 | S115: -39106 | T115: =-61437-S115 -> -22331 | U115: =-50263-T115-S115 -> 11174 | V115: =SUM(E115-SUM(S115:U115)) -> 11400 | W115: -24729 | X115: =-44741-W115 -> -20012 | Y115: =-73557-X115-W115 -> -28816 | Z115: =SUM(F115-SUM(W115:Y115)) -> -49109 | AA115: -43043 | AB115: =-17036-AA115 -> 26007 | AC115: =-12411-AB115-AA115 -> 4625 | AD115: =SUM(G115-SUM(AA115:AC115)) -> 14983 | AE115: 13779 | AF115: =28975-AE115 -> 15196 | AG115: =40470-AF115-AE115 -> 11495 | AH115: =SUM(H115-SUM(AE115:AG115)) -> 65617 | AI115: 7162 | AJ115: =10005-AI115 -> 2843 | AK115: =5361-AJ115-AI115 -> -4644 | AL115: =SUM(I115-SUM(AI115:AK115)) -> 10215 | AM115: 14113 | AN115: =4709-AM115 -> -9404 | AP115: =SUM(AA115:AD115) -> 2572 | AQ115: =SUM(AB115:AE115) -> 59394 | AR115: =SUM(AC115:AF115) -> 48583 | AS115: =SUM(AD115:AG115) -> 55453 | AT115: =SUM(AE115:AH115) -> 106087 | AU115: =SUM(AF115:AI115) -> 99470 | AV115: =SUM(AG115:AJ115) -> 87117 | AW115: =SUM(AH115:AK115) -> 70978 | ... AZ115: =SUM(AK115:AN115) -> 10280
B116: Prepaid Expense and Other Assets | C116: 325 | D116: -2362 | E116: -9699 | F116: -21414 | G116: 11595 | H116: 12873 | I116: 2013 | K116: 60 | L116: =-154-K116 -> -214 | M116: =-615-L116-K116 -> -461 | N116: =SUM(C116-SUM(K116:M116)) -> 940 | O116: 122 | P116: =-2131-O116 -> -2253 | Q116: =-1878-P116-O116 -> 253 | R116: =SUM(D116-SUM(O116:Q116)) -> -484 | S116: -6255 | T116: =-12192-S116 -> -5937 | U116: =-9444-T116-S116 -> 2748 | V116: =SUM(E116-SUM(S116:U116)) -> -255 | W116: -2877 | X116: =-9943-W116 -> -7066 | Y116: =-13249-X116-W116 -> -3306 | Z116: =SUM(F116-SUM(W116:Y116)) -> -8165 | AA116: -213 | AB116: =-992-AA116 -> -779 | AC116: =7802-AB116-AA116 -> 8794 | AD116: =SUM(G116-SUM(AA116:AC116)) -> 3793 | AE116: 3926 | AF116: =-4705-AE116 -> -8631 | AG116: =1282-AF116-AE116 -> 5987 | AH116: =SUM(H116-SUM(AE116:AG116)) -> 11591 | AI116: 410 | AJ116: =-2450-AI116 -> -2860 | AK116: =144-AJ116-AI116 -> 2594 | AL116: =SUM(I116-SUM(AI116:AK116)) -> 1869 | AM116: -4425 | AN116: =-8473-AM116 -> -4048 | AP116: =SUM(AA116:AD116) -> 11595 | AQ116: =SUM(AB116:AE116) -> 15734 | AR116: =SUM(AC116:AF116) -> 7882 | AS116: =SUM(AD116:AG116) -> 5075 | AT116: =SUM(AE116:AH116) -> 12873 | AU116: =SUM(AF116:AI116) -> 9357 | AV116: =SUM(AG116:AJ116) -> 15128 | AW116: =SUM(AH116:AK116) -> 11735 | ... AZ116: =SUM(AK116:AN116) -> -4010
B117: Accounts Payable | C117: 10455 | D117: 10149 | E117: 16027 | F117: 21665 | G117: -10826 | H117: 3004 | I117: -20564 | K117: 1845 | L117: =6623-K117 -> 4778 | M117: =7670-L117-K117 -> 1047 | N117: =SUM(C117-SUM(K117:M117)) -> 2785 | O117: -4349 | P117: =9799-O117 -> 14148 | Q117: =20206-P117-O117 -> 10407 | R117: =SUM(D117-SUM(O117:Q117)) -> -10057 | S117: 16651 | T117: =21564-S117 -> 4913 | U117: =2442-T117-S117 -> -19122 | V117: =SUM(E117-SUM(S117:U117)) -> 13585 | W117: 1098 | X117: =-2197-W117 -> -3295 | Y117: =965-X117-W117 -> 3162 | Z117: =SUM(F117-SUM(W117:Y117)) -> 20700 | AA117: -2295 | AB117: =-206-AA117 -> 2089 | AC117: =-2922-AB117-AA117 -> -2716 | AD117: =SUM(G117-SUM(AA117:AC117)) -> -7904 | AE117: -13271 | AF117: =-14177-AE117 -> -906 | AG117: =8335-AF117-AE117 -> 22512 | AH117: =SUM(H117-SUM(AE117:AG117)) -> -5331 | AI117: 214 | AJ117: =3633-AI117 -> 3419 | AK117: =-797-AJ117-AI117 -> -4430 | AL117: =SUM(I117-SUM(AI117:AK117)) -> -19767 | AM117: 13976 | AN117: =25710-AM117 -> 11734 | AP117: =SUM(AA117:AD117) -> -10826 | AQ117: =SUM(AB117:AE117) -> -21802 | AR117: =SUM(AC117:AF117) -> -24797 | AS117: =SUM(AD117:AG117) -> 431 | AT117: =SUM(AE117:AH117) -> 3004 | AU117: =SUM(AF117:AI117) -> 16489 | AV117: =SUM(AG117:AJ117) -> 20814 | AW117: =SUM(AH117:AK117) -> -6128 | ... AZ117: =SUM(AK117:AN117) -> 1513
B118: Accrued Expenses and Other Current Liabilities | C118: 3798 | D118: 2743 | E118: -1965 | F118: 13961 | G118: -7148 | H118: -2492 | I118: 4511 | K118: -133 | L118: =259-K118 -> 392 | M118: =3573-L118-K118 -> 3314 | N118: =SUM(C118-SUM(K118:M118)) -> 225 | O118: 1608 | P118: =1028-O118 -> -580 | Q118: =2768-P118-O118 -> 1740 | R118: =SUM(D118-SUM(O118:Q118)) -> -25 | S118: -2608 | T118: =818-S118 -> 3426 | U118: =245-T118-S118 -> -573 | V118: =SUM(E118-SUM(S118:U118)) -> -2210 | W118: 10689 | X118: =10157-W118 -> -532 | Y118: =18176-X118-W118 -> 8019 | Z118: =SUM(F118-SUM(W118:Y118)) -> -4215 | AA118: 8527 | AB118: =7949-AA118 -> -578 | AC118: =-3429-AB118-AA118 -> -11378 | AD118: =SUM(G118-SUM(AA118:AC118)) -> -3719 | AE118: -528 | AF118: =-4852-AE118 -> -4324 | AG118: =-2752-AF118-AE118 -> 2100 | AH118: =SUM(H118-SUM(AE118:AG118)) -> 260 | AI118: 2953 | AJ118: =4557-AI118 -> 1604 | AK118: =7135-AJ118-AI118 -> 2578 | AL118: =SUM(I118-SUM(AI118:AK118)) -> -2624 | AM118: -1031 | AN118: =-3638-AM118 -> -2607 | AP118: =SUM(AA118:AD118) -> -7148 | AQ118: =SUM(AB118:AE118) -> -16203 | AR118: =SUM(AC118:AF118) -> -19949 | AS118: =SUM(AD118:AG118) -> -6471 | AT118: =SUM(AE118:AH118) -> -2492 | AU118: =SUM(AF118:AI118) -> 989 | AV118: =SUM(AG118:AJ118) -> 6917 | AW118: =SUM(AH118:AK118) -> 7395 | ... AZ118: =SUM(AK118:AN118) -> -3684 | BB118: =SUM(AZ118/AV118)-1 -> -1.5326008
B119: Prepaid lease costs, non-current | C119: 0 | D119: 0 | E119: 0 | F119: -59188 | G119: -55110 | H119: -4245 | I119: -6502 | K119: 0 | L119: 0 | M119: 0 | N119: =SUM(C119-SUM(K119:M119)) -> 0 | O119: 0 | P119: 0 | Q119: 0 | R119: =SUM(D119-SUM(O119:Q119)) -> 0 | S119: 0 | T119: 0 | U119: 0 | V119: =SUM(E119-SUM(S119:U119)) -> 0 | W119: 0 | X119: =-26578-W119 -> -26578 | Y119: =-49456-X119-W119 -> -22878 | Z119: =SUM(F119-SUM(W119:Y119)) -> -9732 | AA119: -36978 | AB119: =-43651-AA119 -> -6673 | AC119: =-49063-AB119-AA119 -> -5412 | AD119: =SUM(G119-SUM(AA119:AC119)) -> -6047 | AE119: -3082 | AF119: =-4593-AE119 -> -1511 | AG119: =-3254-AF119-AE119 -> 1339 | AH119: =SUM(H119-SUM(AE119:AG119)) -> -991 | AI119: -1669 | AJ119: =-3236-AI119 -> -1567 | AK119: =-4933-AJ119-AI119 -> -1697 | AL119: =SUM(I119-SUM(AI119:AK119)) -> -1569 | AM119: -1768 | AN119: =-3888-AM119 -> -2120 | AP119: =SUM(AA119:AD119) -> -55110 | AQ119: =SUM(AB119:AE119) -> -21214 | AR119: =SUM(AC119:AF119) -> -16052 | AS119: =SUM(AD119:AG119) -> -9301 | AT119: =SUM(AE119:AH119) -> -4245 | AU119: =SUM(AF119:AI119) -> -2832 | AV119: =SUM(AG119:AJ119) -> -2888 | AW119: =SUM(AH119:AK119) -> -5924 | ... AZ119: =SUM(AK119:AN119) -> -7154 | BB119: =SUM(AZ119/AV119)-1 -> 1.4771468
B120: Operating Lease Liabilities | C120: 0 | D120: 0 | E120: -2194 | F120: -3474 | G120: -4333 | H120: -3281 | I120: -3235 | K120: 0 | L120: 0 | M120: 0 | N120: =SUM(C120-SUM(K120:M120)) -> 0 | O120: 0 | P120: 0 | Q120: 0 | R120: =SUM(D120-SUM(O120:Q120)) -> 0 | S120: -479 | T120: =-1188-S120 -> -709 | U120: =-1584-T120-S120 -> -396 | V120: =SUM(E120-SUM(S120:U120)) -> -610 | W120: -818 | X120: =-1619-W120 -> -801 | Y120: =-2332-X120-W120 -> -713 | Z120: =SUM(F120-SUM(W120:Y120)) -> -1142 | AA120: -1113 | AB120: =-2059-AA120 -> -946 | AC120: =-3177-AB120-AA120 -> -1118 | AD120: =SUM(G120-SUM(AA120:AC120)) -> -1156 | AE120: -678 | AF120: =-2556-AE120 -> -1878 | AG120: =-3244-AF120-AE120 -> -688 | AH120: =SUM(H120-SUM(AE120:AG120)) -> -37 | AI120: -822 | AJ120: =-1626-AI120 -> -804 | AK120: =-2412-AJ120-AI120 -> -786 | AL120: =SUM(I120-SUM(AI120:AK120)) -> -823 | AM120: -927 | AN120: =-2156-AM120 -> -1229 | AP120: =SUM(AA120:AD120) -> -4333 | AQ120: =SUM(AB120:AE120) -> -3898 | AR120: =SUM(AC120:AF120) -> -4830 | AS120: =SUM(AD120:AG120) -> -4400 | AT120: =SUM(AE120:AH120) -> -3281 | AU120: =SUM(AF120:AI120) -> -3425 | AV120: =SUM(AG120:AJ120) -> -2351 | AW120: =SUM(AH120:AK120) -> -2449 | ... AZ120: =SUM(AK120:AN120) -> -3765 | BB120: =SUM(AZ120/AV120)-1 -> 0.60144619
B121: Long-term Liabilities | C121: 278 | D121: 21 | E121: 0 | F121: 0 | G121: 0 | H121: 0 | I121: 0 | K121: 40 | L121: =39-K121 -> -1 | M121: =39-L121-K121 -> 0 | N121: =SUM(C121-SUM(K121:M121)) -> 239 | O121: 4 | P121: =12-O121 -> 8 | Q121: =11-P121-O121 -> -1 | R121: =SUM(D121-SUM(O121:Q121)) -> 10 | S121: 0 | T121: 0 | U121: 0 | V121: =SUM(E121-SUM(S121:U121)) -> 0 | W121: 0 | X121: 0 | Y121: 0 | Z121: =SUM(F121-SUM(W121:Y121)) -> 0 | AA121: 0 | AB121: 0 | AC121: =3022-AB121-AA121 -> 3022 | AD121: =SUM(G121-SUM(AA121:AC121)) -> -3022 | AE121: 0 | AF121: 0 | AG121: 0 | AH121: =SUM(H121-SUM(AE121:AG121)) -> 0 | AI121: 0 | AJ121: 0 | AK121: 0 | AL121: =SUM(I121-SUM(AI121:AK121)) -> 0 | AM121: 0 | AN121: 0 | AP121: =SUM(AA121:AD121) -> 0 | AQ121: =SUM(AB121:AE121) -> 0 | AR121: =SUM(AC121:AF121) -> 0 | AS121: =SUM(AD121:AG121) -> -3022 | AT121: =SUM(AE121:AH121) -> 0 | AU121: =SUM(AF121:AI121) -> 0 | AV121: =SUM(AG121:AJ121) -> 0 | AW121: =SUM(AH121:AK121) -> 0 | ... AZ121: =SUM(AK121:AN121) -> 0 | BB121: =SUM(AZ121/AV121)-1 -> #DIV/0!
...

Sheet Revenue Drivers
B2: Beyond Meat, Inc. (NASDAQ: BYND) | C2: FYE | K2: Quarterly | S2: Quarterly | T2: Quarterly | Z2: LTM | AD2: LTM | AL2: Variance
B3: Segment Anaysis | C3: ='Historical Financials'!C7 -> 2018 | D3: ='Historical Financials'!D7 -> 2019 | E3: ='Historical Financials'!E7 -> 2020 | F3: ='Historical Financials'!F7 -> 2021 | G3: ='Historical Financials'!G7 -> 2022 | H3: ='Historical Financials'!H7 -> 2023 | I3: ='Historical Financials'!I7 -> 2024 | K3: 1Q22 | L3: 2Q22 | M3: 3Q22 | N3: 4Q22 | O3: 1Q23 | P3: 2Q23 | Q3: 3Q23 | R3: 4Q23 | S3: 1Q24 | T3: 2Q24 | U3: 3Q24 | V3: 4Q24 | W3: 1Q25 | X3: 2Q25 | Z3: 1Q23 | AA3: 2Q23 | AB3: 3Q23 | AC3: 4Q23 | AD3: 1Q24 | AE3: 2Q24 | AF3: 3Q24 | AG3: 4Q24 | AH3: 1Q25 | AI3: 2Q25 | AJ3: 3Q25
B4: $ mm except per share | C4: ='Historical Financials'!C8 -> 43465 | D4: ='Historical Financials'!D8 -> 43830 | E4: ='Historical Financials'!E8 -> 44196 | F4: ='Historical Financials'!F8 -> 44561 | G4: ='Historical Financials'!G8 -> 44926 | H4: ='Historical Financials'!H8 -> 45291 | I4: ='Historical Financials'!I8 -> 45657 | K4: 44653 | L4: 44744 | M4: 44835 | N4: 44926 | O4: 45017 | P4: 45108 | Q4: 45199 | R4: 45291 | S4: 45381 | T4: 45472 | U4: 45563 | V4: 45657 | W4: 45745 | X4: 45836 | Z4: 44917 | AA4: 45008 | AB4: 45100 | AC4: 45192 | AD4: 45283 | AE4: 45375 | AF4: 45467 | AG4: 45559 | AH4: 45650 | AI4: 45741 | AJ4: 45833
A6: X | B6: Net Revenues by Channel
B7: Retail | C7: =+C13+C18 -> 50779 | D7: =+D13+D18 -> 144809 | E7: =+E13+E18 -> 300583 | F7: =+F13+F18 -> 324843 | G7: =+G13+G18 -> 295651 | H7: =+H13+H18 -> 216963 | I7: =+I13+I18 -> 210595 | K7: =+K13+K18 -> 84397 | L7: =+L13+L18 -> 102553 | M7: =+M13+M18 -> 56372 | N7: =+N13+N18 -> 52329 | O7: =+O13+O18 -> 58448 | P7: =+P13+P18 -> 68485 | Q7: =+Q13+Q18 -> 44671 | R7: =+R13+R18 -> 45359 | ... X7: =+X13+X18 -> 48776 | Z7: =SUM(L7:O7) -> 269702 | AA7: =SUM(M7:P7) -> 235634 | AB7: =SUM(N7:Q7) -> 223933 | AC7: =SUM(O7:R7) -> 216963 | AD7: =SUM(P7:S7) -> 208181 | AE7: =SUM(Q7:T7) -> 202150 | AF7: =SUM(R7:U7) -> 209013 | AG7: =SUM(S7:V7) -> 210595 | ... AI7: =SUM(U7:X7) -> 191293 | AJ7: =SUM(V7:X7) -> 139759 | AL7: =SUM(AJ7/AF7)-1 -> -0.33133824
B8: Foodservice | C8: =+C14+C19 -> 37155 | D8: =+D14+D19 -> 153088 | E8: =+E14+E19 -> 106202 | F8: =+F14+F19 -> 139857 | G8: =+G14+G19 -> 123282 | H8: =+H14+H19 -> 126413 | I8: =+I14+I19 -> 115857 | K8: =+K14+K19 -> 25058 | L8: =+L14+L19 -> 44487 | M8: =+M14+M19 -> 26128 | N8: =+N14+N19 -> 27609 | O8: =+O14+O19 -> 33788 | P8: =+P14+P19 -> 33664 | Q8: =+Q14+Q19 -> 30641 | R8: =+R14+R19 -> 28320 | ... X8: =+X14+X19 -> 26182 | Z8: =SUM(L8:O8) -> 132012 | AA8: =SUM(M8:P8) -> 121189 | AB8: =SUM(N8:Q8) -> 125702 | AC8: =SUM(O8:R8) -> 126413 | AD8: =SUM(P8:S8) -> 118562 | AE8: =SUM(Q8:T8) -> 115629 | AF8: =SUM(R8:U8) -> 114460 | AG8: =SUM(S8:V8) -> 115857 | ... AI8: =SUM(U8:X8) -> 110060 | AJ8: =SUM(V8:X8) -> 80588 | AL8: =SUM(AJ8/AF8)-1 -> -0.29592871
B9: Total Net Revenue | C9: =SUM(C7:C8) -> 87934 | D9: =SUM(D7:D8) -> 297897 | E9: =SUM(E7:E8) -> 406785 | F9: =SUM(F7:F8) -> 464700 | G9: =SUM(G7:G8) -> 418933 | H9: =SUM(H7:H8) -> 343376 | I9: =SUM(I7:I8) -> 326452 | K9: =SUM(K7:K8) -> 109455 | L9: =SUM(L7:L8) -> 147040 | M9: =SUM(M7:M8) -> 82500 | N9: =SUM(N7:N8) -> 79938 | O9: =SUM(O7:O8) -> 92236 | P9: =SUM(P7:P8) -> 102149 | Q9: =SUM(Q7:Q8) -> 75312 | R9: =SUM(R7:R8) -> 73679 | ... X9: =SUM(X7:X8) -> 74958 | Z9: =SUM(Z7:Z8) -> 401714 | AA9: =SUM(AA7:AA8) -> 356823 | AB9: =SUM(AB7:AB8) -> 349635 | AC9: =SUM(AC7:AC8) -> 343376 | AD9: =SUM(AD7:AD8) -> 326743 | AE9: =SUM(AE7:AE8) -> 317779 | AF9: =SUM(AF7:AF8) -> 323473 | AG9: =SUM(AG7:AG8) -> 326452 | ... AJ9: =SUM(AJ7:AJ8) -> 220347 | AL9: =SUM(AJ9/AF9)-1 -> -0.31880868
B10: Balance Check | C10: =+C9-'Historical Financials'!C11 -> 0 | D10: =+D9-'Historical Financials'!D11 -> 0 | E10: =+E9-'Historical Financials'!E11 -> 0 | F10: =+F9-'Historical Financials'!F11 -> 0 | G10: =+G9-'Historical Financials'!G11 -> 0 | H10: =+H9-'Historical Financials'!H11 -> 0 | I10: =+I9-'Historical Financials'!I11 -> 0 | K10: =K9-'Historical Financials'!AA11 -> 0 | L10: =L9-'Historical Financials'!AB11 -> 0 | M10: =M9-'Historical Financials'!AC11 -> 0 | N10: =N9-'Historical Financials'!AD11 -> 0 | O10: =O9-'Historical Financials'!AE11 -> 0 | P10: =P9-'Historical Financials'!AF11 -> 0 | Q10: =Q9-'Historical Financials'!AG11 -> 0 | R10: =R9-'Historical Financials'!AH11 -> 0 | ... X10: =X9-'Historical Financials'!AN11 -> 0 | Z10: =Z9-'Historical Financials'!AP11 -> -17219 | AA10: =AA9-'Historical Financials'!AQ11 -> -44891 | AB10: =AB9-'Historical Financials'!AR11 -> -7188 | AC10: =AC9-'Historical Financials'!AS11 -> -6259 | AD10: =AD9-'Historical Financials'!AT11 -> -16633 | AE10: =AE9-'Historical Financials'!AU11 -> -8964 | AF10: =AF9-'Historical Financials'!AV11 -> 5694 | AG10: =AG9-'Historical Financials'!AW11 -> 2979 | ... AJ10: =AJ9-'Historical Financials'!AZ11 -> -81006
A12: X | B12: Revenue by Channel: U.S
B13: Retail | C13: 49772 | D13: 129383 | E13: 264111 | F13: 243360 | G13: 234744 | H13: 155240 | I13: 150812 | K13: 68260 | L13: 78861 | M13: 46177 | N13: =SUM(G13-SUM(K13:M13)) -> 41446 | O13: 44159 | P13: 48490 | Q13: 30518 | R13: =SUM(H13-SUM(O13:Q13)) -> 32073 | S13: 37088 | T13: 44869 | U13: 34969 | V13: =SUM(I13-SUM(S13:U13)) -> 33886 | W13: 31360 | X13: 32909 | Z13: =SUM(L13:O13) -> 210643 | AA13: =SUM(M13:P13) -> 180272 | AB13: =SUM(N13:Q13) -> 164613 | AC13: =SUM(O13:R13) -> 155240 | AD13: =SUM(P13:S13) -> 148169 | AE13: =SUM(Q13:T13) -> 144548 | AF13: =SUM(R13:U13) -> 148999 | AG13: =SUM(S13:V13) -> 150812 | ... AI13: =SUM(U13:X13) -> 133124 | AJ13: =SUM(V13:X13) -> 98155 | AL13: =SUM(AJ13/AF13)-1 -> -0.34123719
B14: Foodservice | C14: 20717 | D14: 70372 | E14: 60763 | F14: 76475 | G14: 69289 | H14: 50647 | I14: 47584 | K14: 15493 | L14: 23389 | M14: 15994 | N14: =SUM(G14-SUM(K14:M14)) -> 14413 | O14: 14675 | P14: 12764 | Q14: 12535 | R14: =SUM(H14-SUM(O14:Q14)) -> 10673 | S14: 12304 | T14: 10350 | U14: 14478 | V14: =SUM(I14-SUM(S14:U14)) -> 10452 | W14: 9413 | X14: 11055 | Z14: =SUM(L14:O14) -> 68471 | AA14: =SUM(M14:P14) -> 57846 | AB14: =SUM(N14:Q14) -> 54387 | AC14: =SUM(O14:R14) -> 50647 | AD14: =SUM(P14:S14) -> 48276 | AE14: =SUM(Q14:T14) -> 45862 | AF14: =SUM(R14:U14) -> 47805 | AG14: =SUM(S14:V14) -> 47584 | ... AI14: =SUM(U14:X14) -> 45398 | AJ14: =SUM(V14:X14) -> 30920 | AL14: =SUM(AJ14/AF14)-1 -> -0.35320573
B15: Total Net U.S Revenue | C15: =SUM(C13:C14) -> 70489 | D15: =SUM(D13:D14) -> 199755 | E15: =SUM(E13:E14) -> 324874 | F15: =SUM(F13:F14) -> 319835 | G15: =SUM(G13:G14) -> 304033 | H15: =SUM(H13:H14) -> 205887 | I15: =SUM(I13:I14) -> 198396 | K15: =SUM(K13:K14) -> 83753 | L15: =SUM(L13:L14) -> 102250 | M15: =SUM(M13:M14) -> 62171 | N15: =SUM(N13:N14) -> 55859 | O15: =SUM(O13:O14) -> 58834 | P15: =SUM(P13:P14) -> 61254 | Q15: =SUM(Q13:Q14) -> 43053 | R15: =SUM(R13:R14) -> 42746 | ... X15: =SUM(X13:X14) -> 43964 | Z15: =SUM(Z13:Z14) -> 279114 | AA15: =SUM(AA13:AA14) -> 238118 | AB15: =SUM(AB13:AB14) -> 219000 | AC15: =SUM(AC13:AC14) -> 205887 | AD15: =SUM(AD13:AD14) -> 196445 | AE15: =SUM(AE13:AE14) -> 190410 | AF15: =SUM(AF13:AF14) -> 196804 | AG15: =SUM(AG13:AG14) -> 198396 | ... AJ15: =SUM(AJ13:AJ14) -> 129075 | AL15: =SUM(AJ15/AF15)-1 -> -0.34414443
A17: X | B17: Revenue by Channel: International
B18: Retail | C18: 1007 | D18: 15426 | E18: 36472 | F18: 81483 | G18: 60907 | H18: 61723 | I18: 59783 | K18: 16137 | L18: 23692 | M18: 10195 | N18: =SUM(G18-SUM(K18:M18)) -> 10883 | O18: 14289 | P18: 19995 | Q18: 14153 | R18: =SUM(H18-SUM(O18:Q18)) -> 13286 | S18: 12578 | T18: 17585 | U18: 16565 | V18: =SUM(I18-SUM(S18:U18)) -> 13055 | W18: 12682 | X18: 15867 | Z18: =SUM(L18:O18) -> 59059 | AA18: =SUM(M18:P18) -> 55362 | AB18: =SUM(N18:Q18) -> 59320 | AC18: =SUM(O18:R18) -> 61723 | AD18: =SUM(P18:S18) -> 60012 | AE18: =SUM(Q18:T18) -> 57602 | AF18: =SUM(R18:U18) -> 60014 | AG18: =SUM(S18:V18) -> 59783 | ... AI18: =SUM(U18:X18) -> 58169 | AJ18: =SUM(V18:X18) -> 41604 | AL18: =SUM(AJ18/AF18)-1 -> -0.30676176
B19: Foodservice | C19: 16438 | D19: 82716 | E19: 45439 | F19: 63382 | G19: 53993 | H19: 75766 | I19: 68273 | K19: 9565 | L19: 21098 | M19: 10134 | N19: =SUM(G19-SUM(K19:M19)) -> 13196 | O19: 19113 | P19: 20900 | Q19: 18106 | R19: =SUM(H19-SUM(O19:Q19)) -> 17647 | S19: 13633 | T19: 20381 | U19: 14994 | V19: =SUM(I19-SUM(S19:U19)) -> 19265 | W19: 15276 | X19: 15127 | Z19: =SUM(L19:O19) -> 63541 | AA19: =SUM(M19:P19) -> 63343 | AB19: =SUM(N19:Q19) -> 71315 | AC19: =SUM(O19:R19) -> 75766 | AD19: =SUM(P19:S19) -> 70286 | AE19: =SUM(Q19:T19) -> 69767 | AF19: =SUM(R19:U19) -> 66655 | AG19: =SUM(S19:V19) -> 68273 | ... AI19: =SUM(U19:X19) -> 64662 | AJ19: =SUM(V19:X19) -> 49668 | AL19: =SUM(AJ19/AF19)-1 -> -0.2548496
B20: Total Net International Revenue | C20: =SUM(C18:C19) -> 17445 | D20: =SUM(D18:D19) -> 98142 | E20: =SUM(E18:E19) -> 81911 | F20: =SUM(F18:F19) -> 144865 | G20: =SUM(G18:G19) -> 114900 | H20: =SUM(H18:H19) -> 137489 | I20: =SUM(I18:I19) -> 128056 | K20: =SUM(K18:K19) -> 25702 | L20: =SUM(L18:L19) -> 44790 | M20: =SUM(M18:M19) -> 20329 | N20: =SUM(N18:N19) -> 24079 | O20: =SUM(O18:O19) -> 33402 | P20: =SUM(P18:P19) -> 40895 | Q20: =SUM(Q18:Q19) -> 32259 | R20: =SUM(R18:R19) -> 30933 | ... X20: =SUM(X18:X19) -> 30994 | Z20: =SUM(Z18:Z19) -> 122600 | AA20: =SUM(AA18:AA19) -> 118705 | AB20: =SUM(AB18:AB19) -> 130635 | AC20: =SUM(AC18:AC19) -> 137489 | AD20: =SUM(AD18:AD19) -> 130298 | AE20: =SUM(AE18:AE19) -> 127369 | AF20: =SUM(AF18:AF19) -> 126669 | AG20: =SUM(AG18:AG19) -> 128056 | ... AJ20: =SUM(AJ18:AJ19) -> 91272 | AL20: =SUM(AJ20/AF20)-1 -> -0.27944485

Sheet FCF
B2: Beyond Meat, Inc. (NASDAQ: BYND) | C2: FYE | E2: FYE | I2: Quarterly | Q2: Quarterly | R2: Quarterly | X2: LTM | AE2: LTM | AK2: Variance
B3: FCF Analysis | C3: ='Historical Financials'!E7 -> 2020 | D3: ='Historical Financials'!F7 -> 2021 | E3: ='Historical Financials'!G7 -> 2022 | F3: ='Historical Financials'!H7 -> 2023 | G3: ='Historical Financials'!I7 -> 2024 | I3: ='Historical Financials'!AA7 -> 1Q22 | J3: ='Historical Financials'!AB7 -> 2Q22 | K3: ='Historical Financials'!AC7 -> 3Q22 | L3: ='Historical Financials'!AD7 -> 4Q22 | M3: ='Historical Financials'!AE7 -> 1Q23 | N3: ='Historical Financials'!AF7 -> 2Q23 | O3: ='Historical Financials'!AG7 -> 3Q23 | P3: ='Historical Financials'!AH7 -> 4Q23 | ... V3: ='Historical Financials'!AN7 -> 2Q25 | X3: =K3 -> 3Q22 | Y3: =L3 -> 4Q22 | Z3: =M3 -> 1Q23 | AA3: =N3 -> 2Q23 | AB3: =O3 -> 3Q23 | AC3: =P3 -> 4Q23 | AD3: =Q3 -> 1Q24 | AE3: =R3 -> 2Q24 | ... AI3: =V3 -> 2Q25
B4: $ mm except per share | C4: ='Historical Financials'!E8 -> 44196 | D4: ='Historical Financials'!F8 -> 44561 | E4: ='Historical Financials'!G8 -> 44926 | F4: ='Historical Financials'!H8 -> 45291 | G4: ='Historical Financials'!I8 -> 45657 | I4: ='Historical Financials'!AA8 -> 44653 | J4: ='Historical Financials'!AB8 -> 44744 | K4: ='Historical Financials'!AC8 -> 44835 | L4: ='Historical Financials'!AD8 -> 44926 | M4: ='Historical Financials'!AE8 -> 45017 | N4: ='Historical Financials'!AF8 -> 45108 | O4: ='Historical Financials'!AG8 -> 45199 | P4: ='Historical Financials'!AH8 -> 45291 | ... V4: ='Historical Financials'!AN8 -> 45836 | X4: =K4 -> 44835 | Y4: =L4 -> 44926 | Z4: =M4 -> 45017 | AA4: =N4 -> 45108 | AB4: =O4 -> 45199 | AC4: =P4 -> 45291 | AD4: =Q4 -> 45381 | AE4: =R4 -> 45472 | ... AI4: =V4 -> 45836
B6: ='Revenue Drivers'!B7 -> Retail | C6: ='Revenue Drivers'!E7 -> 300583 | D6: ='Revenue Drivers'!F7 -> 324843 | E6: ='Revenue Drivers'!G7 -> 295651 | F6: ='Revenue Drivers'!H7 -> 216963 | G6: ='Revenue Drivers'!I7 -> 210595 | I6: ='Revenue Drivers'!K7 -> 84397 | J6: ='Revenue Drivers'!L7 -> 102553 | K6: ='Revenue Drivers'!M7 -> 56372 | L6: ='Revenue Drivers'!N7 -> 52329 | M6: ='Revenue Drivers'!O7 -> 58448 | N6: ='Revenue Drivers'!P7 -> 68485 | O6: ='Revenue Drivers'!Q7 -> 44671 | P6: ='Revenue Drivers'!R7 -> 45359 | ... V6: ='Revenue Drivers'!X7 -> 48776 | X6: =SUM(H6:K6) -> 243322 | Y6: =SUM(I6:L6) -> 295651 | Z6: =SUM(J6:M6) -> 269702 | AA6: =SUM(K6:N6) -> 235634 | AB6: =SUM(L6:O6) -> 223933 | AC6: =SUM(M6:P6) -> 216963 | AD6: =SUM(N6:Q6) -> 208181 | AE6: =SUM(O6:R6) -> 202150 | ... AI6: =SUM(S6:V6) -> 191293 | AK6: =SUM(AI6/AE6)-1 -> -0.053707643
B7: ='Revenue Drivers'!B8 -> Foodservice | C7: ='Revenue Drivers'!E8 -> 106202 | D7: ='Revenue Drivers'!F8 -> 139857 | E7: ='Revenue Drivers'!G8 -> 123282 | F7: ='Revenue Drivers'!H8 -> 126413 | G7: ='Revenue Drivers'!I8 -> 115857 | I7: ='Revenue Drivers'!K8 -> 25058 | J7: ='Revenue Drivers'!L8 -> 44487 | K7: ='Revenue Drivers'!M8 -> 26128 | L7: ='Revenue Drivers'!N8 -> 27609 | M7: ='Revenue Drivers'!O8 -> 33788 | N7: ='Revenue Drivers'!P8 -> 33664 | O7: ='Revenue Drivers'!Q8 -> 30641 | P7: ='Revenue Drivers'!R8 -> 28320 | ... V7: ='Revenue Drivers'!X8 -> 26182 | X7: =SUM(H7:K7) -> 95673 | Y7: =SUM(I7:L7) -> 123282 | Z7: =SUM(J7:M7) -> 132012 | AA7: =SUM(K7:N7) -> 121189 | AB7: =SUM(L7:O7) -> 125702 | AC7: =SUM(M7:P7) -> 126413 | AD7: =SUM(N7:Q7) -> 118562 | AE7: =SUM(O7:R7) -> 115629 | ... AI7: =SUM(S7:V7) -> 110060 | AK7: =SUM(AI7/AE7)-1 -> -0.048162658
B8: Total Revenue | C8: =SUM(C6:C7) -> 406785 | D8: =SUM(D6:D7) -> 464700 | E8: =SUM(E6:E7) -> 418933 | F8: =SUM(F6:F7) -> 343376 | G8: =SUM(G6:G7) -> 326452 | I8: =SUM(I6:I7) -> 109455 | J8: =SUM(J6:J7) -> 147040 | K8: =SUM(K6:K7) -> 82500 | L8: =SUM(L6:L7) -> 79938 | M8: =SUM(M6:M7) -> 92236 | N8: =SUM(N6:N7) -> 102149 | O8: =SUM(O6:O7) -> 75312 | P8: =SUM(P6:P7) -> 73679 | ... V8: =SUM(V6:V7) -> 74958 | X8: =SUM(X6:X7) -> 338995 | Y8: =SUM(Y6:Y7) -> 418933 | Z8: =SUM(Z6:Z7) -> 401714 | AA8: =SUM(AA6:AA7) -> 356823 | AB8: =SUM(AB6:AB7) -> 349635 | AC8: =SUM(AC6:AC7) -> 343376 | AD8: =SUM(AD6:AD7) -> 326743 | AE8: =SUM(AE6:AE7) -> 317779 | ... AI8: =SUM(AI6:AI7) -> 301353 | AK8: =SUM(AI8/AE8)-1 -> -0.051690011
B9: Y/Y Growth (%) | D9: =SUM(D8/C8)-1 -> 0.14237251 | E9: =SUM(E8/D8)-1 -> -0.098487196 | F9: =SUM(F8/E8)-1 -> -0.18035581 | G9: =SUM(G8/F8)-1 -> -0.049287079 | M9: =SUM(M8/I8)-1 -> -0.15731579 | N9: =SUM(N8/J8)-1 -> -0.30529788 | O9: =SUM(O8/K8)-1 -> -0.087127273 | P9: =SUM(P8/L8)-1 -> -0.078298181 | Q9: =SUM(Q8/M8)-1 -> -0.18033089 | R9: =SUM(R8/N8)-1 -> -0.087754163 | S9: =SUM(S8/O8)-1 -> 0.075605481 | T9: =SUM(T8/P8)-1 -> 0.040432145 | ... V9: =SUM(V8/R8)-1 -> -0.19560015 | AB9: =SUM(AB8/X8)-1 -> 0.031386894 | AC9: =SUM(AC8/Y8)-1 -> -0.18035581 | AD9: =SUM(AD8/Z8)-1 -> -0.1866278 | AE9: =SUM(AE8/AA8)-1 -> -0.1094212 | AF9: =SUM(AF8/AB8)-1 -> -0.074826605 | AG9: =SUM(AG8/AC8)-1 -> -0.049287079 | AH9: =SUM(AH8/AD8)-1 -> -0.021922428 | AI9: =SUM(AI8/AE8)-1 -> -0.051690011 | AK9: =SUM(AI9-AE9)*10000 -> 577.31187
B10: Q/Q Growth (%) | C10: N/A | D10: N/A | E10: N/A | F10: N/A | G10: N/A | J10: =SUM(J8/I8)-1 -> 0.34338313 | K10: =SUM(K8/J8)-1 -> -0.43892818 | L10: =SUM(L8/K8)-1 -> -0.031054545 | M10: =SUM(M8/L8)-1 -> 0.15384423 | N10: =SUM(N8/M8)-1 -> 0.10747431 | O10: =SUM(O8/N8)-1 -> -0.26272406 | P10: =SUM(P8/O8)-1 -> -0.021683132 | Q10: =SUM(Q8/P8)-1 -> 0.026113275 | ... V10: =SUM(V8/U8)-1 -> 0.090599584 | X10: N/A | Y10: N/A | Z10: N/A | AA10: N/A | AB10: N/A | AC10: N/A | AD10: N/A | AE10: N/A | AF10: N/A | AG10: N/A | AH10: N/A | AI10: N/A
B12: (-) Cost of Sales | C12: ='Historical Financials'!E13 -> -284510 | D12: ='Historical Financials'!F13 -> -347419 | E12: ='Historical Financials'!G13 -> -442676 | F12: ='Historical Financials'!H13 -> -426031 | G12: ='Historical Financials'!I13 -> -284753 | I12: ='Historical Financials'!AA13 -> -109265 | J12: ='Historical Financials'!AB13 -> -153202 | K12: ='Historical Financials'!AC13 -> -97340 | L12: ='Historical Financials'!AD13 -> -82869 | M12: ='Historical Financials'!AE13 -> -86051 | N12: ='Historical Financials'!AF13 -> -99876 | O12: ='Historical Financials'!AG13 -> -82566 | P12: ='Historical Financials'!AH13 -> -157538 | ... V12: ='Historical Financials'!AN13 -> -66367 | X12: =SUM(H12:K12) -> -359807 | Y12: =SUM(I12:L12) -> -442676 | Z12: =SUM(J12:M12) -> -419462 | AA12: =SUM(K12:N12) -> -366136 | AB12: =SUM(L12:O12) -> -351362 | AC12: =SUM(M12:P12) -> -426031 | AD12: =SUM(N12:Q12) -> -411915 | AE12: =SUM(O12:R12) -> -391507 | ... AI12: =SUM(S12:V12) -> -269513 | AK12: =SUM(AI12/AE12)-1 -> -0.31160107
B13: Gross Profit | C13: =+C8+C12 -> 122275 | D13: =+D8+D12 -> 117281 | E13: =+E8+E12 -> -23743 | F13: =+F8+F12 -> -82655 | G13: =+G8+G12 -> 41699 | I13: =+I8+I12 -> 190 | J13: =+J8+J12 -> -6162 | K13: =+K8+K12 -> -14840 | L13: =+L8+L12 -> -2931 | M13: =+M8+M12 -> 6185 | N13: =+N8+N12 -> 2273 | O13: =+O8+O12 -> -7254 | P13: =+P8+P12 -> -83859 | ... V13: =+V8+V12 -> 8591 | X13: =+X8+X12 -> -20812 | Y13: =+Y8+Y12 -> -23743 | Z13: =+Z8+Z12 -> -17748 | AA13: =+AA8+AA12 -> -9313 | AB13: =+AB8+AB12 -> -1727 | AC13: =+AC8+AC12 -> -82655 | AD13: =+AD8+AD12 -> -85172 | AE13: =+AE8+AE12 -> -73728 | ... AI13: =+AI8+AI12 -> 31840 | AK13: =SUM(AI13/AE13)-1 -> -1.4318576
B14: Gross Margin (%) | C14: =C13/C8 -> 0.30058876 | D14: =D13/D8 -> 0.25238003 | E14: =E13/E8 -> -0.056674934 | F14: =F13/F8 -> -0.2407128 | G14: =G13/G8 -> 0.12773394 | I14: =I13/I8 -> 0.0017358732 | J14: =J13/J8 -> -0.041906964 | K14: =K13/K8 -> -0.17987879 | L14: =L13/L8 -> -0.036665916 | M14: =M13/M8 -> 0.067056247 | N14: =N13/N8 -> 0.022251809 | O14: =O13/O8 -> -0.096319312 | P14: =P13/P8 -> -1.1381669 | ... V14: =V13/V8 -> 0.11461085 | X14: =X13/X8 -> -0.061393236 | Y14: =Y13/Y8 -> -0.056674934 | Z14: =Z13/Z8 -> -0.044180686 | AA14: =AA13/AA8 -> -0.026099775 | AB14: =AB13/AB8 -> -0.0049394368 | AC14: =AC13/AC8 -> -0.2407128 | AD14: =AD13/AD8 -> -0.2606697 | AE14: =AE13/AE8 -> -0.2320103 | ... AI14: =AI13/AI8 -> 0.10565682 | AK14: =SUM(AI14-AE14)*10000 -> 3376.6712
B16: (-) Selling, General & Administrative (SG&A) | C16: ='Historical Financials'!E17 -> -133655 | D16: ='Historical Financials'!F17 -> -209474 | E16: ='Historical Financials'!G17 -> -239505 | F16: ='Historical Financials'!H17 -> -220344 | G16: ='Historical Financials'!I17 -> -169674 | I16: ='Historical Financials'!AA17 -> -75114 | J16: ='Historical Financials'!AB17 -> -63015 | K16: ='Historical Financials'!AC17 -> -54495 | L16: ='Historical Financials'!AD17 -> -46881 | M16: ='Historical Financials'!AE17 -> -51900 | N16: ='Historical Financials'!AF17 -> -47455 | O16: ='Historical Financials'!AG17 -> -53252 | P16: ='Historical Financials'!AH17 -> -67737 | ... V16: ='Historical Financials'!AN17 -> -37696 | X16: =SUM(H16:K16) -> -192624 | Y16: =SUM(I16:L16) -> -239505 | Z16: =SUM(J16:M16) -> -216291 | AA16: =SUM(K16:N16) -> -200731 | AB16: =SUM(L16:O16) -> -199488 | AC16: =SUM(M16:P16) -> -220344 | AD16: =SUM(N16:Q16) -> -215726 | AE16: =SUM(O16:R16) -> -210434 | ... AI16: =SUM(S16:V16) -> -165597 | AK16: =SUM(AI16/AE16)-1 -> -0.21306918
B17: (-) Research and Development (R&D) | C17: ='Historical Financials'!E18 -> -31535 | D17: ='Historical Financials'!F18 -> -66946 | E17: ='Historical Financials'!G18 -> -62264 | F17: ='Historical Financials'!H18 -> -39530 | G17: ='Historical Financials'!I18 -> -28149 | I17: ='Historical Financials'!AA18 -> -19678 | J17: ='Historical Financials'!AB18 -> -16202 | K17: ='Historical Financials'!AC18 -> -13413 | L17: ='Historical Financials'!AD18 -> -12971 | M17: ='Historical Financials'!AE18 -> -12432 | N17: ='Historical Financials'!AF18 -> -8773 | O17: ='Historical Financials'!AG18 -> -9118 | P17: ='Historical Financials'!AH18 -> -9207 | ... V17: ='Historical Financials'!AN18 -> -5807 | X17: =SUM(H17:K17) -> -49293 | Y17: =SUM(I17:L17) -> -62264 | Z17: =SUM(J17:M17) -> -55018 | AA17: =SUM(K17:N17) -> -47589 | AB17: =SUM(L17:O17) -> -43294 | AC17: =SUM(M17:P17) -> -39530 | AD17: =SUM(N17:Q17) -> -36958 | AE17: =SUM(O17:R17) -> -33670 | ... AI17: =SUM(S17:V17) -> -26073 | AK17: =SUM(AI17/AE17)-1 -> -0.22563113
B18: Earning before Interest & Taxes (EBIT) | C18: =SUM(C13+SUM(C16:C17)) -> -42915 | D18: =SUM(D13+SUM(D16:D17)) -> -159139 | E18: =SUM(E13+SUM(E16:E17)) -> -325512 | F18: =SUM(F13+SUM(F16:F17)) -> -342529 | G18: =SUM(G13+SUM(G16:G17)) -> -156124 | I18: =SUM(I13+SUM(I16:I17)) -> -94602 | J18: =SUM(J13+SUM(J16:J17)) -> -85379 | K18: =SUM(K13+SUM(K16:K17)) -> -82748 | L18: =SUM(L13+SUM(L16:L17)) -> -62783 | M18: =SUM(M13+SUM(M16:M17)) -> -58147 | N18: =SUM(N13+SUM(N16:N17)) -> -53955 | O18: =SUM(O13+SUM(O16:O17)) -> -69624 | P18: =SUM(P13+SUM(P16:P17)) -> -160803 | ... V18: =SUM(V13+SUM(V16:V17)) -> -34912 | X18: =SUM(X13+SUM(X16:X17)) -> -262729 | Y18: =SUM(Y13+SUM(Y16:Y17)) -> -325512 | Z18: =SUM(Z13+SUM(Z16:Z17)) -> -289057 | AA18: =SUM(AA13+SUM(AA16:AA17)) -> -257633 | AB18: =SUM(AB13+SUM(AB16:AB17)) -> -244509 | AC18: =SUM(AC13+SUM(AC16:AC17)) -> -342529 | AD18: =SUM(AD13+SUM(AD16:AD17)) -> -337856 | AE18: =SUM(AE13+SUM(AE16:AE17)) -> -317832 | ... AI18: =SUM(AI13+SUM(AI16:AI17)) -> -159830 | AK18: =SUM(AI18/AE18)-1 -> -0.49712427
B19: Operating Margin (%) | C19: =C18/C8 -> -0.10549799 | D19: =D18/D8 -> -0.34245535 | E19: =E18/E8 -> -0.77700253 | F19: =F18/F8 -> -0.99753332 | G19: =G18/G8 -> -0.47824489 | I19: =I18/I8 -> -0.8643004 | J19: =J18/J8 -> -0.58065152 | K19: =K18/K8 -> -1.0030061 | L19: =L18/L8 -> -0.78539618 | M19: =M18/M8 -> -0.63041546 | N19: =N18/N8 -> -0.528199 | O19: =O18/O8 -> -0.92447419 | P19: =P18/P8 -> -2.1824808 | ... V19: =V18/V8 -> -0.46575416 | X19: =X18/X8 -> -0.77502323 | Y19: =Y18/Y8 -> -0.77700253 | Z19: =Z18/Z8 -> -0.71955919 | AA19: =AA18/AA8 -> -0.72201904 | AB19: =AB18/AB8 -> -0.69932644 | AC19: =AC18/AC8 -> -0.99753332 | AD19: =AD18/AD8 -> -1.0340114 | AE19: =AE18/AE8 -> -1.0001668 | ... AI19: =AI18/AI8 -> -0.53037468 | AK19: =SUM(AI19-AE19)*10000 -> 4697.9211
B21: (+) Depreciation and Amortization | C21: ='Historical Financials'!E100 -> 13299 | D21: ='Historical Financials'!F100 -> 21663 | E21: ='Historical Financials'!G100 -> 32582 | F21: ='Historical Financials'!H100 -> 48094 | G21: ='Historical Financials'!I100 -> 23121 | I21: ='Historical Financials'!AA100 -> 7091 | J21: ='Historical Financials'!AB100 -> 7729 | K21: ='Historical Financials'!AC100 -> 8435 | L21: ='Historical Financials'!AD100 -> 9327 | M21: ='Historical Financials'!AE100 -> 6049 | N21: ='Historical Financials'!AF100 -> 5879 | O21: ='Historical Financials'!AG100 -> 5779 | P21: ='Historical Financials'!AH100 -> 30387 | ... V21: ='Historical Financials'!AN100 -> 8266 | X21: =SUM(H21:K21) -> 23255 | Y21: =SUM(I21:L21) -> 32582 | Z21: =SUM(J21:M21) -> 31540 | AA21: =SUM(K21:N21) -> 29690 | AB21: =SUM(L21:O21) -> 27034 | AC21: =SUM(M21:P21) -> 48094 | AD21: =SUM(N21:Q21) -> 49014 | AE21: =SUM(O21:R21) -> 48348 | ... AI21: =SUM(S21:V21) -> 26621 | AK21: =SUM(AI21/AE21)-1 -> -0.44938777
B22: EBITDA | C22: =SUM(C18+C21) -> -29616 | D22: =SUM(D18+D21) -> -137476 | E22: =SUM(E18+E21) -> -292930 | F22: =SUM(F18+F21) -> -294435 | G22: =SUM(G18+G21) -> -133003 | I22: =SUM(I18+I21) -> -87511 | J22: =SUM(J18+J21) -> -77650 | K22: =SUM(K18+K21) -> -74313 | L22: =SUM(L18+L21) -> -53456 | M22: =SUM(M18+M21) -> -52098 | N22: =SUM(N18+N21) -> -48076 | O22: =SUM(O18+O21) -> -63845 | P22: =SUM(P18+P21) -> -130416 | ... V22: =SUM(V18+V21) -> -26646 | X22: =SUM(X18+X21) -> -239474 | Y22: =SUM(Y18+Y21) -> -292930 | Z22: =SUM(Z18+Z21) -> -257517 | AA22: =SUM(AA18+AA21) -> -227943 | AB22: =SUM(AB18+AB21) -> -217475 | AC22: =SUM(AC18+AC21) -> -294435 | AD22: =SUM(AD18+AD21) -> -288842 | AE22: =SUM(AE18+AE21) -> -269484 | ... AI22: =SUM(AI18+AI21) -> -133209 | AK22: =SUM(AI22/AE22)-1 -> -0.50568865
B23: EBITDA Margin (%) | C23: =C22/C8 -> -0.072805044 | D23: =D22/D8 -> -0.29583818 | E23: =E22/E8 -> -0.69922875 | F23: =F22/F8 -> -0.85747111 | G23: =G22/G8 -> -0.40741977 | I23: =I22/I8 -> -0.79951578 | J23: =J22/J8 -> -0.5280876 | K23: =K22/K8 -> -0.90076364 | L23: =L22/L8 -> -0.66871826 | M23: =M22/M8 -> -0.56483369 | N23: =N22/N8 -> -0.47064582 | O23: =O22/O8 -> -0.84774007 | P23: =P22/P8 -> -1.7700566 | ... V23: =V22/V8 -> -0.35547907 | X23: =X22/X8 -> -0.7064234 | Y23: =Y22/Y8 -> -0.69922875 | Z23: =Z22/Z8 -> -0.64104562 | AA23: =AA22/AA8 -> -0.63881252 | AB23: =AB22/AB8 -> -0.62200581 | AC23: =AC22/AC8 -> -0.85747111 | AD23: =AD22/AD8 -> -0.88400364 | AE23: =AE22/AE8 -> -0.84802331 | ... AI23: =AI22/AI8 -> -0.44203642 | AK23: =SUM(AI23-AE23)*10000 -> 4059.869
B25: (+) Share-based Compensation | C25: ='Historical Financials'!E101 -> 27279 | D25: ='Historical Financials'!F101 -> 27698 | E25: ='Historical Financials'!G101 -> 33857 | F25: ='Historical Financials'!H101 -> 29098 | G25: ='Historical Financials'!I101 -> 23923 | I25: ='Historical Financials'!AA101 -> 9292 | J25: ='Historical Financials'!AB101 -> 10306 | K25: ='Historical Financials'!AC101 -> 9250 | L25: ='Historical Financials'!AD101 -> 5009 | M25: ='Historical Financials'!AE101 -> 9565 | N25: ='Historical Financials'!AF101 -> 7748 | O25: ='Historical Financials'!AG101 -> 6478 | P25: ='Historical Financials'!AH101 -> 5307 | ... V25: ='Historical Financials'!AN101 -> 4304 | X25: =SUM(H25:K25) -> 28848 | Y25: =SUM(I25:L25) -> 33857 | Z25: =SUM(J25:M25) -> 34130 | AA25: =SUM(K25:N25) -> 31572 | AB25: =SUM(L25:O25) -> 28800 | AC25: =SUM(M25:P25) -> 29098 | AD25: =SUM(N25:Q25) -> 25608 | AE25: =SUM(O25:R25) -> 23633 | ... AI25: =SUM(S25:V25) -> 22232 | AK25: =SUM(AI25/AE25)-1 -> -0.059281513
B26: (+) Restructuring Expenses | C26: 6430 | D26: 21663 | E26: 17259 | F26: -631 | G26: 0 | I26: 3026 | J26: 4302 | K26: 6993 | L26: =SUM(E26-SUM(I26:K26)) -> 2938 | M26: 426 | N26: -201 | O26: -4 | P26: =SUM(F26-SUM(M26:O26)) -> -852 | Q26: 0 | R26: 0 | S26: 0 | T26: =SUM(G26-SUM(Q26:S26)) -> 0 | U26: 0 | V26: 0 | AE26: =SUM(O26:R26) -> -856 | AF26: =SUM(P26:S26) -> -852 | AG26: =SUM(Q26:T26) -> 0 | AH26: =SUM(R26:U26) -> 0 | AI26: =SUM(S26:V26) -> 0
B27: (+) Accrued litigation settlement costs | C27: 0 | D27: 0 | E27: 0 | F27: 0 | G27: 7500 | I27: 0 | J27: 0 | K27: 0 | L27: =SUM(E27-SUM(I27:K27)) -> 0 | M27: 0 | N27: 0 | O27: 0 | P27: =SUM(F27-SUM(M27:O27)) -> 0 | Q27: 7500 | R27: 0 | S27: 0 | T27: =SUM(G27-SUM(Q27:S27)) -> 0 | U27: 0 | V27: 0 | AE27: =SUM(O27:R27) -> 7500 | AF27: =SUM(P27:S27) -> 7500 | AG27: =SUM(Q27:T27) -> 7500 | AH27: =SUM(R27:U27) -> 0 | AI27: =SUM(S27:V27) -> 0
B28: (+) Other | C28: 0 | D28: 0 | E28: 0 | F28: 0 | G28: 0 | I28: 0 | J28: 0 | K28: 0 | L28: =SUM(E28-SUM(I28:K28)) -> 0 | M28: 0 | N28: 0 | O28: 0 | P28: =SUM(F28-SUM(M28:O28)) -> 0 | Q28: 0 | R28: 0 | S28: 0 | T28: =SUM(G28-SUM(Q28:S28)) -> 0 | U28: 2083 | V28: 1739 | AE28: =SUM(O28:R28) -> 0 | AF28: =SUM(P28:S28) -> 0 | AG28: =SUM(Q28:T28) -> 0 | AH28: =SUM(R28:U28) -> 2083 | AI28: =SUM(S28:V28) -> 3822
B29: Adj. EBITDA | C29: =+SUM(C22+SUM(C25:C28)) -> 4093 | D29: =+SUM(D22+SUM(D25:D28)) -> -88115 | E29: =+SUM(E22+SUM(E25:E28)) -> -241814 | F29: =+SUM(F22+SUM(F25:F28)) -> -265968 | G29: =+SUM(G22+SUM(G25:G28)) -> -101580 | I29: =+SUM(I22+SUM(I25:I28)) -> -75193 | J29: =+SUM(J22+SUM(J25:J28)) -> -63042 | K29: =+SUM(K22+SUM(K25:K28)) -> -58070 | L29: =+SUM(L22+SUM(L25:L28)) -> -45509 | M29: =+SUM(M22+SUM(M25:M28)) -> -42107 | N29: =+SUM(N22+SUM(N25:N28)) -> -40529 | O29: =+SUM(O22+SUM(O25:O28)) -> -57371 | P29: =+SUM(P22+SUM(P25:P28)) -> -125961 | ... V29: =+SUM(V22+SUM(V25:V28)) -> -20603 | X29: =+SUM(X22+SUM(X25:X28)) -> -210626 | Y29: =+SUM(Y22+SUM(Y25:Y28)) -> -259073 | Z29: =+SUM(Z22+SUM(Z25:Z28)) -> -223387 | AA29: =+SUM(AA22+SUM(AA25:AA28)) -> -196371 | AB29: =+SUM(AB22+SUM(AB25:AB28)) -> -188675 | AC29: =+SUM(AC22+SUM(AC25:AC28)) -> -265337 | AD29: =+SUM(AD22+SUM(AD25:AD28)) -> -263234 | AE29: =+SUM(AE22+SUM(AE25:AE28)) -> -239207 | ... AI29: =+SUM(AI22+SUM(AI25:AI28)) -> -107155 | AK29: =SUM(AI29/AE29)-1 -> -0.5520407
B30: Adj. EBITDA Margin (%) | C30: =C29/C8 -> 0.010061826 | D30: =D29/D8 -> -0.18961696 | E30: =E29/E8 -> -0.57721402 | F30: =F29/F8 -> -0.77456782 | G30: =G29/G8 -> -0.31116366 | I30: =I29/I8 -> -0.68697638 | J30: =J29/J8 -> -0.42874048 | K30: =K29/K8 -> -0.70387879 | L30: =L29/L8 -> -0.56930371 | M30: =M29/M8 -> -0.45651373 | N30: =N29/N8 -> -0.39676355 | O30: =O29/O8 -> -0.76177767 | P30: =P29/P8 -> -1.7095916 | ... V30: =V29/V8 -> -0.27486059 | X30: =X29/X8 -> -0.6213248 | Y30: =Y29/Y8 -> -0.61841154 | Z30: =Z29/Z8 -> -0.55608468 | AA30: =AA29/AA8 -> -0.55033168 | AB30: =AB29/AB8 -> -0.53963419 | AC30: =AC29/AC8 -> -0.77273018 | AD30: =AD29/AD8 -> -0.80563011 | AE30: =AE29/AE8 -> -0.75274641 | ... AI30: =AI29/AI8 -> -0.35557967 | AK30: =SUM(AI30-AE30)*10000 -> 3971.6674
B32: (-) Capital Expenditures | C32: ='Historical Financials'!E125 -> -57696 | D32: ='Historical Financials'!F125 -> -135961 | E32: ='Historical Financials'!G125 -> -70475 | F32: ='Historical Financials'!H125 -> -10564 | G32: ='Historical Financials'!I125 -> -11015 | I32: ='Historical Financials'!AA125 -> -21548 | J32: ='Historical Financials'!AB125 -> -20417 | K32: ='Historical Financials'!AC125 -> -17987 | L32: ='Historical Financials'!AD125 -> -10523 | M32: ='Historical Financials'!AE125 -> -5302 | N32: ='Historical Financials'!AF125 -> -1837 | O32: ='Historical Financials'!AG125 -> -1428 | P32: ='Historical Financials'!AH125 -> -1997 | ... V32: ='Historical Financials'!AN125 -> -1938 | X32: =SUM(H32:K32) -> -59952 | Y32: =SUM(I32:L32) -> -70475 | Z32: =SUM(J32:M32) -> -54229 | AA32: =SUM(K32:N32) -> -35649 | AB32: =SUM(L32:O32) -> -19090 | AC32: =SUM(M32:P32) -> -10564 | AD32: =SUM(N32:Q32) -> -6459 | AE32: =SUM(O32:R32) -> -5945 | ... AI32: =SUM(S32:V32) -> -14918 | AK32: =SUM(AI32/AE32)-1 -> 1.5093356
B33: (-) Cash Taxes | C33: =-'Historical Financials'!E160 -> -18 | D33: =-'Historical Financials'!F160 -> 10 | E33: =-'Historical Financials'!G160 -> -38 | F33: =-'Historical Financials'!H160 -> 1 | G33: =-'Historical Financials'!I160 -> -6 | I33: =-'Historical Financials'!AA160 -> -52 | J33: =-'Historical Financials'!AB160 -> 31 | K33: =-'Historical Financials'!AC160 -> 0 | L33: =-'Historical Financials'!AD160 -> -17 | M33: =-'Historical Financials'!AE160 -> 0 | N33: =-'Historical Financials'!AF160 -> -9 | O33: =-'Historical Financials'!AG160 -> 0 | P33: =-'Historical Financials'!AH160 -> 10 | ... V33: =-'Historical Financials'!AN160 -> -2 | X33: =SUM(H33:K33) -> -21 | Y33: =SUM(I33:L33) -> -38 | Z33: =SUM(J33:M33) -> 14 | AA33: =SUM(K33:N33) -> -26 | AB33: =SUM(L33:O33) -> -26 | AC33: =SUM(M33:P33) -> 1 | AD33: =SUM(N33:Q33) -> -1 | AE33: =SUM(O33:R33) -> -6 | ... AI33: =SUM(S33:V33) -> 8 | AK33: =SUM(AI33/AE33)-1 -> -2.3333333
B34: (-) Cash Interest | C34: =-'Historical Financials'!E161 -> -2564 | D34: =-'Historical Financials'!F161 -> -348 | E34: =-'Historical Financials'!G161 -> -10 | F34: =-'Historical Financials'!H161 -> 0 | G34: =-'Historical Financials'!I161 -> 0 | I34: =-'Historical Financials'!AA161 -> -17 | J34: =-'Historical Financials'!AB161 -> -136 | K34: =-'Historical Financials'!AC161 -> 150 | L34: =-'Historical Financials'!AD161 -> -7 | M34: =-'Historical Financials'!AE161 -> 0 | N34: =-'Historical Financials'!AF161 -> 0 | O34: =-'Historical Financials'!AG161 -> 0 | P34: =-'Historical Financials'!AH161 -> 0 | ... V34: =-'Historical Financials'!AN161 -> 0 | X34: =SUM(H34:K34) -> -3 | Y34: =SUM(I34:L34) -> -10 | Z34: =SUM(J34:M34) -> 7 | AA34: =SUM(K34:N34) -> 143 | AB34: =SUM(L34:O34) -> -7 | AC34: =SUM(M34:P34) -> 0 | AD34: =SUM(N34:Q34) -> 0 | AE34: =SUM(O34:R34) -> 0 | ... AI34: =SUM(S34:V34) -> 0 | AK34: =SUM(AI34/AE34)-1 -> #DIV/0!
B35: (+/-) Changes in NWC | C35: =SUM('Historical Financials'!E114:E121) -> -32178 | D35: =SUM('Historical Financials'!F114:F121) -> -179579 | E35: =SUM('Historical Financials'!G114:G121) -> -54187 | F35: =SUM('Historical Financials'!H114:H121) -> 114663 | G35: =SUM('Historical Financials'!I114:I121) -> -4008 | I35: =SUM('Historical Financials'!AA114:AA121) -> -84223 | J35: =SUM('Historical Financials'!AB114:AB121) -> -1930 | K35: =SUM('Historical Financials'!AC114:AC121) -> 33678 | L35: =SUM('Historical Financials'!AD114:AD121) -> -1712 | M35: =SUM('Historical Financials'!AE114:AE121) -> -7932 | N35: =SUM('Historical Financials'!AF114:AF121) -> -10438 | O35: =SUM('Historical Financials'!AG114:AG121) -> 57401 | P35: =SUM('Historical Financials'!AH114:AH121) -> 75632 | ... V35: =SUM('Historical Financials'!AN114:AN121) -> -10927 | X35: =SUM(H35:K35) -> -52475 | Y35: =SUM(I35:L35) -> -54187 | Z35: =SUM(J35:M35) -> 22104 | AA35: =SUM(K35:N35) -> 13596 | AB35: =SUM(L35:O35) -> 37319 | AC35: =SUM(M35:P35) -> 114663 | AD35: =SUM(N35:Q35) -> 126700 | AE35: =SUM(O35:R35) -> 140643 | ... AI35: =SUM(S35:V35) -> -8645 | AK35: =SUM(AI35/AE35)-1 -> -1.0614677
B36: Discretionary Cash-Flows | C36: =SUM(C29+SUM(C32:C35)) -> -88363 | D36: =SUM(D29+SUM(D32:D35)) -> -403993 | E36: =SUM(E29+SUM(E32:E35)) -> -366524 | F36: =SUM(F29+SUM(F32:F35)) -> -161868 | G36: =SUM(G29+SUM(G32:G35)) -> -116609 | I36: =SUM(I29+SUM(I32:I35)) -> -181033 | J36: =SUM(J29+SUM(J32:J35)) -> -85494 | K36: =SUM(K29+SUM(K32:K35)) -> -42229 | L36: =SUM(L29+SUM(L32:L35)) -> -57768 | M36: =SUM(M29+SUM(M32:M35)) -> -55341 | N36: =SUM(N29+SUM(N32:N35)) -> -52813 | O36: =SUM(O29+SUM(O32:O35)) -> -1398 | P36: =SUM(P29+SUM(P32:P35)) -> -52316 | ... V36: =SUM(V29+SUM(V32:V35)) -> -33470 | X36: =SUM(X29+SUM(X32:X35)) -> -323077 | Y36: =SUM(Y29+SUM(Y32:Y35)) -> -383783 | Z36: =SUM(Z29+SUM(Z32:Z35)) -> -255491 | AA36: =SUM(AA29+SUM(AA32:AA35)) -> -218307 | AB36: =SUM(AB29+SUM(AB32:AB35)) -> -170479 | AC36: =SUM(AC29+SUM(AC32:AC35)) -> -161237 | AD36: =SUM(AD29+SUM(AD32:AD35)) -> -142994 | AE36: =SUM(AE29+SUM(AE32:AE35)) -> -104515 | ... AI36: =SUM(AI29+SUM(AI32:AI35)) -> -130710 | AK36: =SUM(AI36/AE36)-1 -> 0.25063388
B38: (+/-) Proceeds / (Purchases) of Equity, net | C38: =SUM('Historical Financials'!E137:E141) -> 25732 | D38: =SUM('Historical Financials'!F137:F141) -> 1046104 | E38: =SUM('Historical Financials'!G137:G141) -> 486 | F38: =SUM('Historical Financials'!H137:H141) -> -327 | G38: =SUM('Historical Financials'!I137:I141) -> 46954 | I38: =SUM('Historical Financials'!AA137:AA141) -> 376 | J38: =SUM('Historical Financials'!AB137:AB141) -> 164 | K38: =SUM('Historical Financials'!AC137:AC141) -> -3 | L38: =SUM('Historical Financials'!AD137:AD141) -> -51 | M38: =SUM('Historical Financials'!AE137:AE141) -> -116 | N38: =SUM('Historical Financials'!AF137:AF141) -> -69 | O38: =SUM('Historical Financials'!AG137:AG141) -> -35 | P38: =SUM('Historical Financials'!AH137:AH141) -> -107 | ... V38: =SUM('Historical Financials'!AN137:AN141) -> -86 | X38: =SUM(H38:K38) -> 537 | Y38: =SUM(I38:L38) -> 486 | Z38: =SUM(J38:M38) -> -6 | AA38: =SUM(K38:N38) -> -239 | AB38: =SUM(L38:O38) -> -271 | AC38: =SUM(M38:P38) -> -327 | AD38: =SUM(N38:Q38) -> -641 | AE38: =SUM(O38:R38) -> -676 | ... AI38: =SUM(S38:V38) -> 47182
B39: (+/-) Issuance / (Repayment) of Debt, net | C39: =SUM('Historical Financials'!E143:E145) -> -27424 | D39: =SUM('Historical Financials'!F143:F145) -> -23605 | E39: =SUM('Historical Financials'!G143:G145) -> 0 | F39: =SUM('Historical Financials'!H143:H145) -> 0 | G39: =SUM('Historical Financials'!I143:I145) -> 0 | I39: =SUM('Historical Financials'!AA143:AA145) -> 0 | J39: =SUM('Historical Financials'!AB143:AB145) -> 0 | K39: =SUM('Historical Financials'!AC143:AC145) -> 0 | L39: =SUM('Historical Financials'!AD143:AD145) -> 0 | M39: =SUM('Historical Financials'!AE143:AE145) -> 0 | N39: =SUM('Historical Financials'!AF143:AF145) -> 0 | O39: =SUM('Historical Financials'!AG143:AG145) -> 0 | P39: =SUM('Historical Financials'!AH143:AH145) -> 0 | ... V39: =SUM('Historical Financials'!AN143:AN145) -> 35008 | X39: =SUM(H39:K39) -> 0 | Y39: =SUM(I39:L39) -> 0 | Z39: =SUM(J39:M39) -> 0 | AA39: =SUM(K39:N39) -> 0 | AB39: =SUM(L39:O39) -> 0 | AC39: =SUM(M39:P39) -> 0 | AD39: =SUM(N39:Q39) -> 0 | AE39: =SUM(O39:R39) -> 0 | ... AI39: =SUM(S39:V39) -> 34883
B40: (+/-) Payments of Capital Lease Obligations | C40: ='Historical Financials'!E142 -> -70 | D40: ='Historical Financials'!F142 -> -177 | E40: ='Historical Financials'!G142 -> -210 | F40: ='Historical Financials'!H142 -> -223 | G40: ='Historical Financials'!I142 -> -1177 | I40: ='Historical Financials'!AA142 -> -45 | J40: ='Historical Financials'!AB142 -> 2 | K40: ='Historical Financials'!AC142 -> -109 | L40: ='Historical Financials'!AD142 -> -58 | M40: ='Historical Financials'!AE142 -> -33 | N40: ='Historical Financials'!AF142 -> -82 | O40: ='Historical Financials'!AG142 -> -53 | P40: ='Historical Financials'!AH142 -> -55 | ... V40: ='Historical Financials'!AN142 -> -693 | X40: =SUM(H40:K40) -> -152 | Y40: =SUM(I40:L40) -> -210 | Z40: =SUM(J40:M40) -> -198 | AA40: =SUM(K40:N40) -> -282 | AB40: =SUM(L40:O40) -> -226 | AC40: =SUM(M40:P40) -> -223 | AD40: =SUM(N40:Q40) -> -701 | AE40: =SUM(O40:R40) -> -622 | ... AI40: =SUM(S40:V40) -> -1600
B41: (+/-) Other Financing Activities | C41: =SUM('Historical Financials'!E126:E133) -> -17204 | D41: =SUM('Historical Financials'!F126:F133) -> -11518 | E41: =SUM('Historical Financials'!G126:G133) -> -17052 | F41: =SUM('Historical Financials'!H126:H133) -> 1073 | G41: =SUM('Historical Financials'!I126:I133) -> 4783 | I41: =SUM('Historical Financials'!AA126:AA133) -> 49 | J41: =SUM('Historical Financials'!AB126:AB133) -> -72 | K41: =SUM('Historical Financials'!AC126:AC133) -> -10729 | L41: =SUM('Historical Financials'!AD126:AD133) -> -6300 | M41: =SUM('Historical Financials'!AE126:AE133) -> -1000 | N41: =SUM('Historical Financials'!AF126:AF133) -> 66 | O41: =SUM('Historical Financials'!AG126:AG133) -> 161 | P41: =SUM('Historical Financials'!AH126:AH133) -> 1846 | ... V41: =SUM('Historical Financials'!AN126:AN133) -> 0 | AE41: =SUM(O41:R41) -> 5696 | AF41: =SUM(P41:S41) -> 6376 | AG41: =SUM(Q41:T41) -> 4783 | AH41: =SUM(R41:U41) -> 4236 | AI41: =SUM(S41:V41) -> 1442
B42: (+/-) Other | D42: =SUM(D47-C47)-SUM(D36:D41) -> -32644 | E42: =SUM(E47-D47)-SUM(E36:E41) -> -40072 | F42: =SUM(F47-E47)-SUM(F36:F41) -> 41928 | G42: =SUM(G47-F47)-SUM(G36:G41) -> 7457 | I42: =SUM(I47-D47)-SUM(I36:I41) -> -4783 | J42: =SUM(J47-I47)-SUM(J36:J41) -> -7784 | K42: =SUM(K47-J47)-SUM(K36:K41) -> -11428 | L42: =SUM(L47-K47)-SUM(L36:L41) -> -16077 | M42: =SUM(M47-L47)-SUM(M36:M41) -> 5134 | N42: =SUM(N47-M47)-SUM(N36:N41) -> 5113 | O42: =SUM(O47-N47)-SUM(O36:O41) -> 8089 | P42: =SUM(P47-O47)-SUM(P36:P41) -> 23592 | Q42: =SUM(Q47-P47)-SUM(Q36:Q41) -> -2522 | ... V42: =SUM(V47-U47)-SUM(V36:V41) -> 595 | X42: =SUM(H42:K42) -> -23995 | Y42: =SUM(I42:L42) -> -40072 | Z42: =SUM(J42:M42) -> -30155 | AA42: =SUM(K42:N42) -> -17258 | AB42: =SUM(L42:O42) -> 2259 | AC42: =SUM(M42:P42) -> 41928 | AD42: =SUM(N42:Q42) -> 34272 | AE42: =SUM(O42:R42) -> 34209 | ... AI42: =SUM(S42:V42) -> 7427
B43: Free-Cash Flows | C43: =SUM(C36+SUM(C38:C42)) -> -107329 | D43: =SUM(D36+SUM(D38:D42)) -> 574167 | E43: =SUM(E36+SUM(E38:E42)) -> -423372 | F43: =SUM(F36+SUM(F38:F42)) -> -119417 | G43: =SUM(G36+SUM(G38:G42)) -> -58592 | I43: =SUM(I36+SUM(I38:I42)) -> -185436 | J43: =SUM(J36+SUM(J38:J42)) -> -93184 | K43: =SUM(K36+SUM(K38:K42)) -> -64498 | L43: =SUM(L36+SUM(L38:L42)) -> -80254 | M43: =SUM(M36+SUM(M38:M42)) -> -51356 | N43: =SUM(N36+SUM(N38:N42)) -> -47785 | O43: =SUM(O36+SUM(O38:O42)) -> 6764 | P43: =SUM(P36+SUM(P38:P42)) -> -27040 | ... V43: =SUM(V36+SUM(V38:V42)) -> 1354 | X43: =SUM(X36+SUM(X38:X42)) -> -346687 | Y43: =SUM(Y36+SUM(Y38:Y42)) -> -423579 | Z43: =SUM(Z36+SUM(Z38:Z42)) -> -285850 | AA43: =SUM(AA36+SUM(AA38:AA42)) -> -236086 | AB43: =SUM(AB36+SUM(AB38:AB42)) -> -168717 | AC43: =SUM(AC36+SUM(AC38:AC42)) -> -119859 | AD43: =SUM(AD36+SUM(AD38:AD42)) -> -110064 | AE43: =SUM(AE36+SUM(AE38:AE42)) -> -65908 | ... AI43: =SUM(AI36+SUM(AI38:AI42)) -> -41376
B45: Capitalization
B47: Cash & Cash Equivelants | C47: ='Historical Financials'!E46 -> 159127 | D47: ='Historical Financials'!F46 -> 733294 | E47: ='Historical Financials'!G46 -> 309922 | F47: ='Historical Financials'!H46 -> 190505 | G47: ='Historical Financials'!I46 -> 131913 | I47: ='Historical Financials'!AA46 -> 547858 | J47: ='Historical Financials'!AB46 -> 454674 | K47: ='Historical Financials'!AC46 -> 390176 | L47: ='Historical Financials'!AD46 -> 309922 | M47: ='Historical Financials'!AE46 -> 258566 | N47: ='Historical Financials'!AF46 -> 210781 | O47: ='Historical Financials'!AG46 -> 217545 | P47: ='Historical Financials'!AH46 -> 190505 | ... V47: ='Historical Financials'!AN46 -> 103497 | X47: =K47 -> 390176 | Y47: =L47 -> 309922 | Z47: =M47 -> 258566 | AA47: =N47 -> 210781 | AB47: =O47 -> 217545 | AC47: =P47 -> 190505 | AD47: =Q47 -> 157913 | AE47: =R47 -> 144873 | ... AI47: =V47 -> 103497
B48: Restricted Cash, Current | C48: ='Historical Financials'!E47 -> 0 | D48: ='Historical Financials'!F47 -> 0 | E48: ='Historical Financials'!G47 -> 0 | F48: ='Historical Financials'!H47 -> 2830 | G48: ='Historical Financials'!I47 -> 1041 | I48: ='Historical Financials'!AA47 -> 0 | J48: ='Historical Financials'!AB47 -> 0 | K48: ='Historical Financials'!AC47 -> 0 | L48: ='Historical Financials'!AD47 -> 0 | M48: ='Historical Financials'!AE47 -> 2426 | N48: ='Historical Financials'!AF47 -> 2552 | O48: ='Historical Financials'!AG47 -> 2689 | P48: ='Historical Financials'!AH47 -> 2830 | ... V48: ='Historical Financials'!AN47 -> 1172 | X48: =K48 -> 0 | Y48: =L48 -> 0 | Z48: =M48 -> 2426 | AA48: =N48 -> 2552 | AB48: =O48 -> 2689 | AC48: =P48 -> 2830 | AD48: =Q48 -> 2971 | AE48: =R48 -> 536 | ... AI48: =V48 -> 1172
B49: Restricted Cash, Non-Current | C49: ='Historical Financials'!E54 -> 0 | D49: ='Historical Financials'!F54 -> 0 | E49: ='Historical Financials'!G54 -> 12627 | F49: ='Historical Financials'!H54 -> 12600 | G49: ='Historical Financials'!I54 -> 12600 | I49: ='Historical Financials'!AA54 -> 0 | J49: ='Historical Financials'!AB54 -> 0 | K49: ='Historical Financials'!AC54 -> 0 | L49: ='Historical Financials'!AD54 -> 12627 | M49: ='Historical Financials'!AE54 -> 12600 | N49: ='Historical Financials'!AF54 -> 12600 | O49: ='Historical Financials'!AG54 -> 12600 | P49: ='Historical Financials'!AH54 -> 12600 | ... V49: ='Historical Financials'!AN54 -> 12600 | X49: =K49 -> 0 | Y49: =L49 -> 12627 | Z49: =M49 -> 12600 | AA49: =N49 -> 12600 | AB49: =O49 -> 12600 | AC49: =P49 -> 12600 | AD49: =Q49 -> 12600 | AE49: =R49 -> 12600 | ... AI49: =V49 -> 12600
B50: $150MM Sr. Secured 3.500% RCF due April 21, 2025 (Terminated) | C50: =150000-C66-C52 -> 112500 | D50: 0 | E50: 0 | F50: 0 | G50: 0 | I50: 0 | J50: 0 | K50: 0 | L50: =E50 -> 0 | M50: 0 | N50: 0 | O50: 0 | P50: =F50 -> 0 | Q50: 0 | R50: 0 | S50: 0 | T50: =G50 -> 0 | U50: 0 | V50: 0 | X50: =K50 -> 0 | Y50: =L50 -> 0 | Z50: =M50 -> 0 | AA50: =N50 -> 0 | AB50: =O50 -> 0 | AC50: =P50 -> 0 | AD50: =Q50 -> 0 | AE50: =R50 -> 0 | ... AI50: =V50 -> 0
B51: Total Liquidity | C51: =SUM(C47:C50) -> 271627 | D51: =SUM(D47:D50) -> 733294 | E51: =SUM(E47:E50) -> 322549 | F51: =SUM(F47:F50) -> 205935 | G51: =SUM(G47:G50) -> 145554 | I51: =SUM(I47:I50) -> 547858 | J51: =SUM(J47:J50) -> 454674 | K51: =SUM(K47:K50) -> 390176 | L51: =SUM(L47:L50) -> 322549 | M51: =SUM(M47:M50) -> 273592 | N51: =SUM(N47:N50) -> 225933 | O51: =SUM(O47:O50) -> 232834 | P51: =SUM(P47:P50) -> 205935 | ... V51: =SUM(V47:V50) -> 117269 | X51: =SUM(X47:X49) -> 390176 | Y51: =SUM(Y47:Y49) -> 322549 | Z51: =SUM(Z47:Z49) -> 273592 | AA51: =SUM(AA47:AA49) -> 225933 | AB51: =SUM(AB47:AB49) -> 232834 | AC51: =SUM(AC47:AC49) -> 205935 | AD51: =SUM(AD47:AD49) -> 173484 | AE51: =SUM(AE47:AE49) -> 158009 | ... AI51: =SUM(AI47:AI49) -> 117269
B52: Outstanding L/Cs | C52: 12500 | D52: N/A | E52: N/A | F52: N/A | G52: N/A | I52: N/A | J52: N/A | K52: N/A | L52: N/A | M52: N/A | N52: N/A | O52: N/A | P52: N/A | Q52: N/A | R52: N/A | S52: N/A | T52: N/A | U52: N/A | V52: N/A | X52: N/A | Y52: N/A | Z52: N/A | AA52: N/A | AB52: N/A | AC52: N/A | AD52: N/A | AE52: N/A | AF52: N/A | AG52: N/A | AH52: N/A | AI52: N/A
B54: Balance Sheet Metrics:
B55: Accounts Receivable | C55: ='Historical Financials'!E48 -> 35975 | D55: ='Historical Financials'!F48 -> 43806 | E55: ='Historical Financials'!G48 -> 34198 | F55: ='Historical Financials'!H48 -> 31730 | G55: ='Historical Financials'!I48 -> 26862 | I55: ='Historical Financials'!AA48 -> 52675 | J55: ='Historical Financials'!AB48 -> 77154 | K55: ='Historical Financials'!AC48 -> 34949 | L55: ='Historical Financials'!AD48 -> 34198 | M55: ='Historical Financials'!AE48 -> 42395 | N55: ='Historical Financials'!AF48 -> 50821 | O55: ='Historical Financials'!AG48 -> 35763 | P55: ='Historical Financials'!AH48 -> 31730 | ... V55: ='Historical Financials'!AN48 -> 37338 | X55: =K55 -> 34949 | Y55: =L55 -> 34198 | Z55: =M55 -> 42395 | AA55: =N55 -> 50821 | AB55: =O55 -> 35763 | AC55: =P55 -> 31730 | AD55: =Q55 -> 35648 | AE55: =R55 -> 34463 | ... AI55: =V55 -> 37338
B56: Accounts Payable | C56: ='Historical Financials'!E63 -> 53071 | D56: ='Historical Financials'!F63 -> 69040 | E56: ='Historical Financials'!G63 -> 55300 | F56: ='Historical Financials'!H63 -> 56032 | G56: ='Historical Financials'!I63 -> 37571 | I56: ='Historical Financials'!AA63 -> 67387 | J56: ='Historical Financials'!AB63 -> 74430 | K56: ='Historical Financials'!AC63 -> 68676 | L56: ='Historical Financials'!AD63 -> 55300 | M56: ='Historical Financials'!AE63 -> 41131 | N56: ='Historical Financials'!AF63 -> 39508 | O56: ='Historical Financials'!AG63 -> 61861 | P56: ='Historical Financials'!AH63 -> 56032 | ... V56: ='Historical Financials'!AN63 -> 68837 | X56: =K56 -> 68676 | Y56: =L56 -> 55300 | Z56: =M56 -> 41131 | AA56: =N56 -> 39508 | AB56: =O56 -> 61861 | AC56: =P56 -> 56032 | AD56: =Q56 -> 55836 | AE56: =R56 -> 59449 | ... AI56: =V56 -> 68837
B57: Inventories | C57: ='Historical Financials'!E49 -> 121717 | D57: ='Historical Financials'!F49 -> 241870 | E57: ='Historical Financials'!G49 -> 235696 | F57: ='Historical Financials'!H49 -> 130336 | G57: ='Historical Financials'!I49 -> 113444 | I57: ='Historical Financials'!AA49 -> 283754 | J57: ='Historical Financials'!AB49 -> 254653 | K57: ='Historical Financials'!AC49 -> 246987 | L57: ='Historical Financials'!AD49 -> 235696 | M57: ='Historical Financials'!AE49 -> 222370 | N57: ='Historical Financials'!AF49 -> 207138 | O57: ='Historical Financials'!AG49 -> 194570 | P57: ='Historical Financials'!AH49 -> 130336 | ... V57: ='Historical Financials'!AN49 -> 110868 | X57: =K57 -> 246987 | Y57: =L57 -> 235696 | Z57: =M57 -> 222370 | AA57: =N57 -> 207138 | AB57: =O57 -> 194570 | AC57: =P57 -> 130336 | AD57: =Q57 -> 122538 | AE57: =R57 -> 119532 | ... AI57: =V57 -> 110868
B58: Property Plant, and Equiptment | C58: ='Historical Financials'!E56 -> 115299 | D58: ='Historical Financials'!F56 -> 226489 | E58: ='Historical Financials'!G56 -> 257002 | F58: ='Historical Financials'!H56 -> 194046 | G58: ='Historical Financials'!I56 -> 184887 | I58: ='Historical Financials'!AA56 -> 241389 | J58: ='Historical Financials'!AB56 -> 258075 | K58: ='Historical Financials'!AC56 -> 262595 | L58: ='Historical Financials'!AD56 -> 257002 | M58: ='Historical Financials'!AE56 -> 251218 | N58: ='Historical Financials'!AF56 -> 250335 | O58: ='Historical Financials'!AG56 -> 245373 | P58: ='Historical Financials'!AH56 -> 194046 | ... V58: ='Historical Financials'!AN56 -> 320988 | X58: =K58 -> 262595 | Y58: =L58 -> 257002 | Z58: =M58 -> 251218 | AA58: =N58 -> 250335 | AB58: =O58 -> 245373 | AC58: =P58 -> 194046 | AD58: =Q58 -> 190896 | AE58: =R58 -> 186584 | ... AI58: =V58 -> 320988
B59: Current Liabilities | C59: ='Historical Financials'!E51 -> 332226 | D59: ='Historical Financials'!F51 -> 1052048 | E59: ='Historical Financials'!G51 -> 606459 | F59: ='Historical Financials'!H51 -> 372844 | G59: ='Historical Financials'!I51 -> 286456 | I59: ='Historical Financials'!AA51 -> 917297 | J59: ='Historical Financials'!AB51 -> 819510 | K59: ='Historical Financials'!AC51 -> 695980 | L59: ='Historical Financials'!AD51 -> 606459 | M59: ='Historical Financials'!AE51 -> 547055 | N59: ='Historical Financials'!AF51 -> 497441 | O59: ='Historical Financials'!AG51 -> 471623 | P59: ='Historical Financials'!AH51 -> 372844 | ... V59: ='Historical Financials'!AN51 -> 297135 | X59: =K59 -> 695980 | Y59: =L59 -> 606459 | Z59: =M59 -> 547055 | AA59: =N59 -> 497441 | AB59: =O59 -> 471623 | AC59: =P59 -> 372844 | AD59: =Q59 -> 336503 | AE59: =R59 -> 317265 | ... AI59: =V59 -> 297135
B60: Total Liabilities | C60: ='Historical Financials'!E75 -> 100909 | D60: ='Historical Financials'!F75 -> 1246904 | E60: ='Historical Financials'!G75 -> 1265772 | F60: ='Historical Financials'!H75 -> 1287818 | G60: ='Historical Financials'!I75 -> 1279354 | I60: ='Historical Financials'!AA75 -> 1253529 | J60: ='Historical Financials'!AB75 -> 1266050 | K60: ='Historical Financials'!AC75 -> 1283331 | L60: ='Historical Financials'!AD75 -> 1265772 | M60: ='Historical Financials'!AE75 -> 1239711 | N60: ='Historical Financials'!AF75 -> 1267703 | O60: ='Historical Financials'!AG75 -> 1292114 | P60: ='Historical Financials'!AH75 -> 1287818 | ... V60: ='Historical Financials'!AN75 -> 1368764 | X60: =K60 -> 1283331 | Y60: =L60 -> 1265772 | Z60: =M60 -> 1239711 | AA60: =N60 -> 1267703 | AB60: =O60 -> 1292114 | AC60: =P60 -> 1287818 | AD60: =Q60 -> 1296437 | AE60: =R60 -> 1301259 | ... AI60: =V60 -> 1368764
B62: Summary Debt (BS):
B63: CPLTD | C63: =+'Historical Financials'!E66+'Historical Financials'!E67 -> 25142 | D63: =+'Historical Financials'!F66+'Historical Financials'!F67 -> 364 | E63: =+'Historical Financials'!G66+'Historical Financials'!G67 -> 224 | F63: =+'Historical Financials'!H66+'Historical Financials'!H67 -> 196 | G63: =+'Historical Financials'!I66+'Historical Financials'!I67 -> 851 | I63: =+'Historical Financials'!AA66+'Historical Financials'!AA67 -> 183 | J63: =+'Historical Financials'!AB66+'Historical Financials'!AB67 -> 210 | K63: =+'Historical Financials'!AC66+'Historical Financials'!AC67 -> 226 | L63: =+'Historical Financials'!AD66+'Historical Financials'!AD67 -> 224 | M63: =+'Historical Financials'!AE66+'Historical Financials'!AE67 -> 246 | N63: =+'Historical Financials'!AF66+'Historical Financials'!AF67 -> 218 | O63: =+'Historical Financials'!AG66+'Historical Financials'!AG67 -> 209 | P63: =+'Historical Financials'!AH66+'Historical Financials'!AH67 -> 196 | ... V63: =+'Historical Financials'!AN66+'Historical Financials'!AN67 -> 3934 | X63: =K63 -> 226 | Y63: =L63 -> 224 | Z63: =M63 -> 246 | AA63: =N63 -> 218 | AB63: =O63 -> 209 | AC63: =P63 -> 196 | AD63: =Q63 -> 763 | AE63: =R63 -> 1005 | ... AI63: =V63 -> 3934
B64: LTD | C64: =+'Historical Financials'!E71+'Historical Financials'!E72+'Historical Financials'!E73 -> 149 | D64: =+'Historical Financials'!F71+'Historical Financials'!F72+'Historical Financials'!F73 -> 1130116 | E64: =+'Historical Financials'!G71+'Historical Financials'!G72+'Historical Financials'!G73 -> 1134077 | F64: =+'Historical Financials'!H71+'Historical Financials'!H72+'Historical Financials'!H73 -> 1137816 | G64: =+'Historical Financials'!I71+'Historical Financials'!I72+'Historical Financials'!I73 -> 1144288 | I64: =+'Historical Financials'!AA71+'Historical Financials'!AA72+'Historical Financials'!AA73 -> 1131053 | J64: =+'Historical Financials'!AB71+'Historical Financials'!AB72+'Historical Financials'!AB73 -> 1135380 | K64: =+'Historical Financials'!AC71+'Historical Financials'!AC72+'Historical Financials'!AC73 -> 1136171 | L64: =+'Historical Financials'!AD71+'Historical Financials'!AD72+'Historical Financials'!AD73 -> 1134077 | M64: =+'Historical Financials'!AE71+'Historical Financials'!AE72+'Historical Financials'!AE73 -> 1135007 | N64: =+'Historical Financials'!AF71+'Historical Financials'!AF72+'Historical Financials'!AF73 -> 1135937 | O64: =+'Historical Financials'!AG71+'Historical Financials'!AG72+'Historical Financials'!AG73 -> 1136874 | P64: =+'Historical Financials'!AH71+'Historical Financials'!AH72+'Historical Financials'!AH73 -> 1137816 | ... V64: =+'Historical Financials'!AN71+'Historical Financials'!AN72+'Historical Financials'!AN73 -> 1274136 | X64: =K64 -> 1136171 | Y64: =L64 -> 1134077 | Z64: =M64 -> 1135007 | AA64: =N64 -> 1135937 | AB64: =O64 -> 1136874 | AC64: =P64 -> 1137816 | AD64: =Q64 -> 1142148 | AE64: =R64 -> 1142857 | ... AI64: =V64 -> 1274136
B66: $150MM Sr. Secured 3.500% RCF due April 21, 2025 (Terminated) | C66: 25000 | D66: 0 | E66: 0 | F66: 0 | G66: 0 | I66: 0 | J66: 0 | K66: 0 | L66: =E66 -> 0 | M66: 0 | N66: 0 | O66: 0 | P66: =F66 -> 0 | Q66: 0 | R66: 0 | S66: 0 | T66: =G66 -> 0 | U66: 0 | V66: 0 | X66: =K66 -> 0 | Y66: =L66 -> 0 | Z66: =M66 -> 0 | AA66: =N66 -> 0 | AB66: =O66 -> 0 | AC66: =P66 -> 0 | AD66: =Q66 -> 0 | AE66: =R66 -> 0 | ... AI66: =V66 -> 0
B67: $1.0Bn 0.00% Convertible Senior Notes due March 15, 2027 | C67: 0 | D67: 1129674 | E67: 1133608 | F67: 1137542 | G67: 1141476 | I67: 1130657 | J67: 1131641 | K67: 1132624 | L67: =E67 -> 1133608 | M67: 1134591 | N67: 1135575 | O67: 1136558 | P67: =F67 -> 1137542 | Q67: 1138525 | R67: 1139509 | S67: 1140493 | T67: =G67 -> 1141476 | U67: 1142460 | V67: 1143443 | X67: =K67 -> 1132624 | Y67: =L67 -> 1133608 | Z67: =M67 -> 1134591 | AA67: =N67 -> 1135575 | AB67: =O67 -> 1136558 | AC67: =P67 -> 1137542 | AD67: =Q67 -> 1138525 | AE67: =R67 -> 1139509 | ... AI67: =V67 -> 1143443
B68: $100MM Delayed Draw Term Loan | C68: 0 | D68: 0 | E68: 0 | F68: 0 | G68: 0 | I68: 0 | J68: 0 | K68: 0 | L68: =E68 -> 0 | M68: 0 | N68: 0 | O68: 0 | P68: =F68 -> 0 | Q68: 0 | R68: 0 | S68: 0 | T68: =G68 -> 0 | U68: 0 | V68: 30525 | X68: =K68 -> 0 | Y68: =L68 -> 0 | Z68: =M68 -> 0 | AA68: =N68 -> 0 | AB68: =O68 -> 0 | AC68: =P68 -> 0 | AD68: =Q68 -> 0 | AE68: =R68 -> 0 | ... AI68: =V68 -> 30525
B69: Finance Lease Obligations | C69: =+'Historical Financials'!E66+'Historical Financials'!E73 -> 220 | D69: =+'Historical Financials'!F66+'Historical Financials'!F73 -> 624 | E69: =+'Historical Financials'!G66+'Historical Financials'!G73 -> 693 | F69: =+'Historical Financials'!H66+'Historical Financials'!H73 -> 470 | G69: =+'Historical Financials'!I66+'Historical Financials'!I73 -> 3663 | I69: =+'Historical Financials'!AA66+'Historical Financials'!AA73 -> 579 | J69: =+'Historical Financials'!AB66+'Historical Financials'!AB73 -> 3949 | K69: =+'Historical Financials'!AC66+'Historical Financials'!AC73 -> 3773 | L69: =+'Historical Financials'!AD66+'Historical Financials'!AD73 -> 693 | M69: =+'Historical Financials'!AE66+'Historical Financials'!AE73 -> 662 | N69: =+'Historical Financials'!AF66+'Historical Financials'!AF73 -> 580 | O69: =+'Historical Financials'!AG66+'Historical Financials'!AG73 -> 525 | P69: =+'Historical Financials'!AH66+'Historical Financials'!AH73 -> 470 | ... W69: =+'Historical Financials'!AO66+'Historical Financials'!AO73 -> 0 | X69: =K69 -> 3773 | Y69: =L69 -> 693 | Z69: =M69 -> 662 | AA69: =N69 -> 580 | AB69: =O69 -> 525 | AC69: =P69 -> 470 | AD69: =Q69 -> 4386 | AE69: =R69 -> 4353 | ... AI69: =V69 -> 83959
B70: Total Debt | C70: =SUM(C66:C69) -> 25220 | D70: =SUM(D66:D69) -> 1130298 | E70: =SUM(E66:E69) -> 1134301 | F70: =SUM(F66:F69) -> 1138012 | G70: =SUM(G66:G69) -> 1145139 | I70: =SUM(I66:I69) -> 1131236 | J70: =SUM(J66:J69) -> 1135590 | K70: =SUM(K66:K69) -> 1136397 | L70: =SUM(L66:L69) -> 1134301 | M70: =SUM(M66:M69) -> 1135253 | N70: =SUM(N66:N69) -> 1136155 | O70: =SUM(O66:O69) -> 1137083 | P70: =SUM(P66:P69) -> 1138012 | ... V70: =SUM(V66:V69) -> 1257927 | X70: =SUM(X66:X69) -> 1136397 | Y70: =SUM(Y66:Y69) -> 1134301 | Z70: =SUM(Z66:Z69) -> 1135253 | AA70: =SUM(AA66:AA69) -> 1136155 | AB70: =SUM(AB66:AB69) -> 1137083 | AC70: =SUM(AC66:AC69) -> 1138012 | AD70: =SUM(AD66:AD69) -> 1142911 | AE70: =SUM(AE66:AE69) -> 1143862 | ... AI70: =SUM(AI66:AI69) -> 1257927
B72: Total Shareholder Equity | C72: ='Historical Financials'!E82 -> 367097 | D72: ='Historical Financials'!F82 -> 132495 | E72: ='Historical Financials'!G82 -> -203548 | F72: ='Historical Financials'!H82 -> -513368 | G72: ='Historical Financials'!I82 -> -601208 | I72: ='Historical Financials'!AA82 -> 40981 | J72: ='Historical Financials'!AB82 -> -47941 | K72: ='Historical Financials'!AC82 -> -142044 | L72: ='Historical Financials'!AD82 -> -203548 | M72: ='Historical Financials'!AE82 -> -253134 | N72: ='Historical Financials'!AF82 -> -299118 | O72: ='Historical Financials'!AG82 -> -362906 | P72: ='Historical Financials'!AH82 -> -513368 | ... V72: ='Historical Financials'!AN82 -> -677023 | X72: =K72 -> -142044 | Y72: =L72 -> -203548 | Z72: =M72 -> -253134 | AA72: =N72 -> -299118 | AB72: =O72 -> -362906 | AC72: =P72 -> -513368 | AD72: =Q72 -> -561411 | AE72: =R72 -> -590025 | ... AI72: =V72 -> -677023
B73: Total Book Capitalization | C73: =SUM(C70:C72) -> 392317 | D73: =SUM(D70:D72) -> 1262793 | E73: =SUM(E70:E72) -> 930753 | F73: =SUM(F70:F72) -> 624644 | G73: =SUM(G70:G72) -> 543931 | I73: =SUM(I70:I72) -> 1172217 | J73: =SUM(J70:J72) -> 1087649 | K73: =SUM(K70:K72) -> 994353 | L73: =SUM(L70:L72) -> 930753 | M73: =SUM(M70:M72) -> 882119 | N73: =SUM(N70:N72) -> 837037 | O73: =SUM(O70:O72) -> 774177 | P73: =SUM(P70:P72) -> 624644 | ... V73: =SUM(V70:V72) -> 580904 | X73: =SUM(X70:X72) -> 994353 | Y73: =SUM(Y70:Y72) -> 930753 | Z73: =SUM(Z70:Z72) -> 882119 | AA73: =SUM(AA70:AA72) -> 837037 | AB73: =SUM(AB70:AB72) -> 774177 | AC73: =SUM(AC70:AC72) -> 624644 | AD73: =SUM(AD70:AD72) -> 581500 | AE73: =SUM(AE70:AE72) -> 553837 | ... AI73: =SUM(AI70:AI72) -> 580904
B75: Credit Metrics
B77: Total Leverage | C77: =C70/C29 -> 6.1617396 | D77: =D70/D29 -> -12.827532 | E77: =E70/E29 -> -4.6907995 | F77: =F70/F29 -> -4.2787553 | G77: =G70/G29 -> -11.273272 | L77: =SUM(L70/SUM(I29:L29)) -> -4.6907995 | M77: =SUM(M70/SUM(J29:M29)) -> -5.4389109 | N77: =SUM(N70/SUM(K29:N29)) -> -6.1013076 | O77: =SUM(O70/SUM(L29:O29)) -> -6.1292988 | P77: =SUM(P70/SUM(M29:P29)) -> -4.2787553 | Q77: =SUM(Q70/SUM(N29:Q29)) -> -4.450744 | R77: =SUM(R70/SUM(O29:R29)) -> -4.7818918 | S77: =SUM(S70/SUM(P29:S29)) -> -5.6802806 | ... V77: =SUM(V70/SUM(S29:V29)) -> -11.739322 | X77: =X70/X29 -> -5.3953311 | Y77: =Y70/Y29 -> -4.3783065 | Z77: =Z70/Z29 -> -5.0820012 | AA77: =AA70/AA29 -> -5.7857576 | AB77: =AB70/AB29 -> -6.0266755 | AC77: =AC70/AC29 -> -4.2889307 | AD77: =AD70/AD29 -> -4.3418061 | AE77: =AE70/AE29 -> -4.7818918 | ... AI77: =AI70/AI29 -> -11.739322
B78: Net Leverage (C&CE) | C78: =SUM(C70-C47)/C29 -> -32.716101 | D78: =SUM(D70-D47)/D29 -> -4.5055212 | E78: =SUM(E70-E47)/E29 -> -3.409145 | F78: =SUM(F70-F47)/F29 -> -3.562485 | G78: =SUM(G70-G47)/G29 -> -9.9746604 | L78: =SUM(L70-L47)/SUM(I29:L29) -> -3.409145 | M78: =SUM(M70-M47)/SUM(J29:M29) -> -4.2001409 | N78: =SUM(N70-N47)/SUM(K29:N29) -> -4.9693849 | O78: =SUM(O70-O47)/SUM(L29:O29) -> -4.9566506 | P78: =SUM(P70-P47)/SUM(M29:P29) -> -3.562485 | Q78: =SUM(Q70-Q47)/SUM(N29:Q29) -> -3.8357964 | R78: =SUM(R70-R47)/SUM(O29:R29) -> -4.1762532 | S78: =SUM(S70-S47)/SUM(P29:S29) -> -5.0763254 | ... V78: =SUM(V70-V47)/SUM(S29:V29) -> -10.773459 | X78: =SUM(X70-X47)/X29 -> -3.5428722 | Y78: =SUM(Y70-Y47)/Y29 -> -3.1820336 | Z78: =SUM(Z70-Z47)/Z29 -> -3.9245211 | AA78: =SUM(AA70-AA47)/AA29 -> -4.7123761 | AB78: =SUM(AB70-AB47)/AB29 -> -4.8736611 | AC78: =SUM(AC70-AC47)/AC29 -> -3.5709569 | AD78: =SUM(AD70-AD47)/AD29 -> -3.7419102 | AE78: =SUM(AE70-AE47)/AE29 -> -4.1762532 | ... AI78: =SUM(AI70-AI47)/AI29 -> -10.773459
B79: Interest Coverage | C79: =C29/-C34 -> 1.5963339 | D79: =D29/-D34 -> -253.20402 | E79: =E29/-E34 -> -24181.4 | F79: =F29/-F34 -> #DIV/0! | G79: =G29/-G34 -> #DIV/0! | L79: {=SUM(I29:L29)/SUM(-I34:L34)} -> -24181.4 | M79: {=SUM(J29:M29)/SUM(-J34:M34)} -> 29818.286 | N79: {=SUM(K29:N29)/SUM(-K34:N34)} -> 1302.2028 | O79: {=SUM(L29:O29)/SUM(-L34:O34)} -> -26502.286 | P79: {=SUM(M29:P29)/SUM(-M34:P34)} -> #DIV/0! | Q79: {=SUM(N29:Q29)/SUM(-N34:Q34)} -> #DIV/0! | R79: {=SUM(O29:R29)/SUM(-O34:R34)} -> #DIV/0! | S79: {=SUM(P29:S29)/SUM(-P34:S34)} -> #DIV/0! | ... V79: {=SUM(S29:V29)/SUM(-S34:V34)} -> #DIV/0! | X79: =X29/-X34 -> -70208.667 | Y79: =Y29/-Y34 -> -25907.3 | Z79: =Z29/-Z34 -> 31912.429 | AA79: =AA29/-AA34 -> 1373.2238 | AB79: =AB29/-AB34 -> -26953.571 | AC79: =AC29/-AC34 -> #DIV/0! | AD79: =AD29/-AD34 -> #DIV/0! | AE79: =AE29/-AE34 -> #DIV/0! | ... AI79: =AI29/-AI34 -> #DIV/0!
B80: Debt Service Coverage | C80: {=SUM(C29+C32)/SUM(-C33:C34)} -> -20.760263 | D80: {=SUM(D29+D32)/SUM(-D33:D34)} -> -662.94675 | E80: {=SUM(E29+E32)/SUM(-E33:E34)} -> -6506.0208 | F80: {=SUM(F29+F32)/SUM(-F33:F34)} -> 276532 | G80: {=SUM(G29+G32)/SUM(-G33:G34)} -> -18765.833 | L80: {=SUM(I29:L29+I32:L32)/SUM(-I33:L34)} -> -6506.0208 | M80: {=SUM(J29:M29+J32:M32)/SUM(-J33:M34)} -> 12521.762 | N80: {=SUM(K29:N29+K32:N32)/SUM(-K33:N34)} -> 1896.2735 | O80: {=SUM(L29:O29+L32:O32)/SUM(-L33:O34)} -> -6200.1818 | P80: {=SUM(M29:P29+M32:P32)/SUM(-M33:P34)} -> 276532 | Q80: {=SUM(N29:Q29+N32:Q32)/SUM(-N33:Q34)} -> -263250 | R80: {=SUM(O29:R29+O32:R32)/SUM(-O33:R34)} -> -40858.667 | S80: {=SUM(P29:S29+P32:S32)/SUM(-P33:S34)} -> -34682.5 | ... V80: {=SUM(S29:V29+S32:V32)/SUM(-S33:V34)} -> 15259.125 | X80: {=SUM(X29+X32)/SUM(-X33:X34)} -> -11274.083 | Y80: {=SUM(Y29+Y32)/SUM(-Y33:Y34)} -> -6865.5833 | Z80: {=SUM(Z29+Z32)/SUM(-Z33:Z34)} -> 13219.81 | AA80: {=SUM(AA29+AA32)/SUM(-AA33:AA34)} -> 1983.0769 | AB80: {=SUM(AB29+AB32)/SUM(-AB33:AB34)} -> -6295.9091 | AC80: {=SUM(AC29+AC32)/SUM(-AC33:AC34)} -> 275901 | AD80: {=SUM(AD29+AD32)/SUM(-AD33:AD34)} -> -269693 | AE80: {=SUM(AE29+AE32)/SUM(-AE33:AE34)} -> -40858.667 | ... AI80: {=SUM(AI29+AI32)/SUM(-AI33:AI34)} -> 15259.125
B81: Fixed Charge Coverage | C81: {=SUM(C29)/SUM(-C32:C34)} -> 0.067902054 | D81: {=SUM(D29)/SUM(-D32:D34)} -> -0.6464831 | E81: {=SUM(E29)/SUM(-E32:E34)} -> -3.4288672 | F81: {=SUM(F29)/SUM(-F32:F34)} -> -25.17921 | G81: {=SUM(G29)/SUM(-G32:G34)} -> -9.2169495 | L81: {=SUM(I29:L29)/SUM(-I32:L34)} -> -3.4288672 | M81: {=SUM(J29:M29)/SUM(-J32:M34)} -> -3.8505018 | N81: {=SUM(K29:N29)/SUM(-K32:N34)} -> -5.2407689 | O81: {=SUM(L29:O29)/SUM(-L32:O34)} -> -9.7011975 | P81: {=SUM(M29:P29)/SUM(-M32:P34)} -> -25.17921 | Q81: {=SUM(N29:Q29)/SUM(-N32:Q34)} -> -39.750929 | R81: {=SUM(O29:R29)/SUM(-O32:R34)} -> -40.196101 | S81: {=SUM(P29:S29)/SUM(-P32:S34)} -> -30.805135 | ... V81: {=SUM(S29:V29)/SUM(-S32:V34)} -> -7.1867874 | X81: {=SUM(X29)/SUM(-X32:X34)} -> -3.5118381 | Y81: {=SUM(Y29)/SUM(-Y32:Y34)} -> -3.6735958 | Z81: {=SUM(Z29)/SUM(-Z32:Z34)} -> -4.1209231 | AA81: {=SUM(AA29)/SUM(-AA32:AA34)} -> -5.5265957 | AB81: {=SUM(AB29)/SUM(-AB32:AB34)} -> -9.8663913 | AC81: {=SUM(AC29)/SUM(-AC32:AC34)} -> -25.119474 | AD81: {=SUM(AD29)/SUM(-AD32:AD34)} -> -40.748297 | AE81: {=SUM(AE29)/SUM(-AE32:AE34)} -> -40.196101 | ... AI81: {=SUM(AI29)/SUM(-AI32:AI34)} -> -7.1867874
B82: Debt-to-Book Capitalization | C82: =C73/C70 -> 15.555789 | D82: =D73/D70 -> 1.1172213 | E82: =E73/E70 -> 0.82055204 | F82: =F73/F70 -> 0.54889052 | G82: =G73/G70 -> 0.47499125 | L82: =L73/L70 -> 0.82055204 | M82: =M73/M70 -> 0.77702415 | N82: =N73/N70 -> 0.73672782 | O82: =O73/O70 -> 0.68084476 | P82: =P73/P70 -> 0.54889052 | Q82: =Q73/Q70 -> 0.50878852 | R82: =R73/R70 -> 0.48418166 | S82: =S73/S70 -> 0.46552468 | ... V82: =V73/V70 -> 0.46179468 | X82: =X73/X70 -> 0.87500495 | Y82: =Y73/Y70 -> 0.82055204 | Z82: =Z73/Z70 -> 0.77702415 | AA82: =AA73/AA70 -> 0.73672782 | AB82: =AB73/AB70 -> 0.68084476 | AC82: =AC73/AC70 -> 0.54889052 | AD82: =AD73/AD70 -> 0.50878852 | AE82: =AE73/AE70 -> 0.48418166 | ... AI82: =AI73/AI70 -> 0.46179468

Sheet 3-Statement Model
B2: =C6&"(NASDAQ: BYND)" -> Beyond Meat, Inc.(NASDAQ: BYND)
B3: 3-Statement Model
B4: $ mm except per share
B6: Company name | C6: Beyond Meat, Inc. | I6: Select an operating scenario: | K6: Base case
B7: Ticker | C7: BYND
B8: Circ break 1=off, 0=on | C8: 1
B9: Latest closing share price | C9: 262.82
B10: Latest closing share price date | C10: =NOW() -> 45966.75
B11: Latest fiscal year end date | C11: ='Historical Financials'!I8 -> 45657
B12: Shares outstanding (millions) | C12: 4443.265
A14: X | B14: Income Statement | C14: Actuals | G14: Forecast
B15: Fiscal year | C15: =D15-1 -> 2021 | D15: =E15-1 -> 2022 | E15: =F15-1 -> 2023 | F15: =YEAR(C11) -> 2024 | G15: =F15+1 -> 2025 | H15: =G15+1 -> 2026 | I15: =H15+1 -> 2027 | J15: =I15+1 -> 2028 | K15: =J15+1 -> 2029
B16: Fiscal year end date | C16: =EOMONTH(D16,-12) -> 44561 | D16: =EOMONTH(E16,-12) -> 44926 | E16: =EOMONTH(F16,-12) -> 45291 | F16: =C11 -> 45657 | G16: =EOMONTH(F16,12) -> 46022 | H16: =EOMONTH(G16,12) -> 46387 | I16: =EOMONTH(H16,12) -> 46752 | J16: =EOMONTH(I16,12) -> 47118 | K16: =EOMONTH(J16,12) -> 47483 | M16: Commentary
B18: ='Revenue Drivers'!B7 -> Retail | C18: ='Revenue Drivers'!F7 -> 324843 | D18: ='Revenue Drivers'!G7 -> 295651 | E18: ='Revenue Drivers'!H7 -> 216963 | F18: ='Revenue Drivers'!I7 -> 210595 | G18: =F18*(1+G52) -> #DIV/0! | H18: =G18*(1+H52) -> #DIV/0! | I18: =H18*(1+I52) -> #DIV/0! | J18: =I18*(1+J52) -> #DIV/0! | K18: =J18*(1+K52) -> #DIV/0! | M18: Previous year's revenues x (1+revenue growth rate)
B19: ='Revenue Drivers'!B8 -> Foodservice | C19: ='Revenue Drivers'!F8 -> 139857 | D19: ='Revenue Drivers'!G8 -> 123282 | E19: ='Revenue Drivers'!H8 -> 126413 | F19: ='Revenue Drivers'!I8 -> 115857 | G19: =F19*(1+G53) -> #REF! | H19: =G19*(1+H53) -> #REF! | I19: =H19*(1+I53) -> #REF! | J19: =I19*(1+J53) -> #REF! | K19: =J19*(1+K53) -> #REF!
B20: Total Net Revenue | C20: =SUM(C18:C19) -> 464700 | D20: =SUM(D18:D19) -> 418933 | E20: =SUM(E18:E19) -> 343376 | F20: =SUM(F18:F19) -> 326452 | G20: =SUM(G18:G19) -> #DIV/0! | H20: =SUM(H18:H19) -> #DIV/0! | I20: =SUM(I18:I19) -> #DIV/0! | J20: =SUM(J18:J19) -> #DIV/0! | K20: =SUM(K18:K19) -> #DIV/0!
B21: Y/Y Growth (%) | D21: =SUM(D20/C20)-1 -> -0.098487196 | E21: =SUM(E20/D20)-1 -> -0.18035581 | F21: =SUM(F20/E20)-1 -> -0.049287079 | G21: =SUM(G20/F20)-1 -> #DIV/0! | H21: =SUM(H20/G20)-1 -> #DIV/0! | I21: =SUM(I20/H20)-1 -> #DIV/0! | J21: =SUM(J20/I20)-1 -> #DIV/0! | K21: =SUM(K20/J20)-1 -> #DIV/0!
B23: Cost of Sales | G23: =+G24-G20 -> #DIV/0! | H23: =+H24-H20 -> #DIV/0! | I23: =+I24-I20 -> #DIV/0! | J23: =+J24-J20 -> #DIV/0! | K23: =+K24-K20 -> #DIV/0! | M23: Plug = Revenue - Gross Profit
B24: Gross Profit | C24: =+C23+C20 -> 464700 | D24: =+D23+D20 -> 418933 | E24: =+E23+E20 -> 343376 | F24: =+F23+F20 -> 326452 | G24: =G55*G20 -> #DIV/0! | H24: =H55*H20 -> #DIV/0! | I24: =I55*I20 -> #DIV/0! | J24: =J55*J20 -> #DIV/0! | K24: =K55*K20 -> #DIV/0! | M24: Revenue x Gross Profit Margin forecast
B25: Margin (%) | C25: =C24/C20 -> 1 | D25: =D24/D20 -> 1 | E25: =E24/E20 -> 1 | F25: =F24/F20 -> 1 | G25: =G24/G20 -> #DIV/0! | H25: =H24/H20 -> #DIV/0! | I25: =I24/I20 -> #DIV/0! | J25: =J24/J20 -> #DIV/0! | K25: =K24/K20 -> #DIV/0!
B27: Research & Development (R&D) | G27: =-G56*G18 -> #DIV/0! | H27: =-H56*H18 -> #DIV/0! | I27: =-I56*I18 -> #DIV/0! | J27: =-J56*J18 -> #DIV/0! | K27: =-K56*K18 -> #DIV/0! | M27: Revenue x R&D % of sales forecast
B28: Selling, General & Administrative (SG&A) | G28: =-G18*G57 -> #DIV/0! | H28: =-H18*H57 -> #DIV/0! | I28: =-I18*I57 -> #DIV/0! | J28: =-J18*J57 -> #DIV/0! | K28: =-K18*K57 -> #DIV/0! | M28: Revenue x SG&A % of sales forecast
B29: Operating profit (EBIT) | C29: =C24+C27+C28 -> 464700 | D29: =D24+D27+D28 -> 418933 | E29: =E24+E27+E28 -> 343376 | F29: =+SUM(F24+SUM(F27:F28)) -> 326452 | G29: =G24+G27+G28 -> #DIV/0! | H29: =H24+H27+H28 -> #DIV/0! | I29: =I24+I27+I28 -> #DIV/0! | J29: =J24+J27+J28 -> #DIV/0! | K29: =K24+K27+K28 -> #DIV/0! | M29: Gross Profit - R&D - SG&A
B30: Margin (%) | C30: =C29/C20 -> 1 | D30: =D29/D20 -> 1 | E30: =E29/E20 -> 1 | F30: =F29/F20 -> 1 | G30: =G29/G20 -> #DIV/0! | H30: =H29/H20 -> #DIV/0! | I30: =I29/I20 -> #DIV/0! | J30: =J29/J20 -> #DIV/0! | K30: =K29/K20 -> #DIV/0!
B32: Interest Income | M32: Reference from interest on cash schedule; Area of Model Mess Up
B33: Interest expense | M33: Reference from interest expense schedule
B34: Other expense, net | G34: =F34 -> 0 | H34: =G34 -> 0 | I34: =H34 -> 0 | J34: =I34 -> 0 | K34: =J34 -> 0 | M34: Straight-line
B35: Pretax profit | C35: =SUM(C29:C34) -> 464701 | D35: =SUM(D29:D34) -> 418934 | E35: =SUM(E29:E34) -> 343377 | F35: =SUM(F29:F34) -> 326453 | G35: =SUM(G29:G34) -> #DIV/0! | H35: =SUM(H29:H34) -> #DIV/0! | I35: =SUM(I29:I34) -> #DIV/0! | J35: =SUM(J29:J34) -> #DIV/0! | K35: =SUM(K29:K34) -> #DIV/0! | M35: EBIT + interest income less interest expense less other expense
B37: Taxes | M37: Pre-tax Profit x Tax Rate forecast
B38: Net income | C38: =SUM(C35:C37) -> 464701 | D38: =SUM(D35:D37) -> 418934 | E38: =SUM(E35:E37) -> 343377 | F38: =SUM(F35:F37) -> 326453 | G38: =SUM(G35:G37) -> #DIV/0! | H38: =SUM(H35:H37) -> #DIV/0! | I38: =SUM(I35:I37) -> #DIV/0! | J38: =SUM(J35:J37) -> #DIV/0! | K38: =SUM(K35:K37) -> #DIV/0! | M38: Pre-tax Profit less taxes
B39: Margin (%) | C39: =C38/C20 -> 1.0000022 | D39: =D38/D20 -> 1.0000024 | E39: =E38/E20 -> 1.0000029 | F39: =F38/F20 -> 1.0000031 | G39: =G38/G20 -> #DIV/0! | H39: =H38/H20 -> #DIV/0! | I39: =I38/I20 -> #DIV/0! | J39: =J38/J20 -> #DIV/0! | K39: =K38/K20 -> #DIV/0!
B41: Depreciation & amortization | M41: Reference from D&A schedule
B42: EBITDA | C42: =C29+C41 -> 464700 | D42: =D29+D41 -> 418933 | E42: =E29+E41 -> 343376 | F42: =F29+F41 -> 326452 | G42: =G29+G41 -> #DIV/0! | H42: =H29+H41 -> #DIV/0! | I42: =I29+I41 -> #DIV/0! | J42: =J29+J41 -> #DIV/0! | K42: =K29+K41 -> #DIV/0! | M42: EBIT + D&A
B43: Margin (%) | C43: =C42/C20 -> 1 | D43: =D42/D20 -> 1 | E43: =E42/E20 -> 1 | F43: =F42/F20 -> 1 | G43: =G42/G20 -> #DIV/0! | H43: =H42/H20 -> #DIV/0! | I43: =I42/I20 -> #DIV/0! | J43: =J42/J20 -> #DIV/0! | K43: =K42/K20 -> #DIV/0!
B45: Stock based compensation | M45: WSP assumption: grow SBC in-line with revenue growth
B46: Adjusted EBITDA | C46: =SUM(C42:C45) -> 464701 | D46: =SUM(D42:D45) -> 418934 | E46: =SUM(E42:E45) -> 343377 | F46: =SUM(F42:F45) -> 326453 | G46: =SUM(G42:G45) -> #DIV/0! | H46: =SUM(H42:H45) -> #DIV/0! | I46: =SUM(I42:I45) -> #DIV/0! | J46: =SUM(J42:J45) -> #DIV/0! | K46: =SUM(K42:K45) -> #DIV/0! | M46: EBITDA + Stock-based compensation
B47: Margin (%) | C47: =C46/C20 -> 1.0000022 | D47: =D46/D20 -> 1.0000024 | E47: =E46/E20 -> 1.0000029 | F47: =F46/F20 -> 1.0000031 | G47: =G46/G20 -> #DIV/0! | H47: =H46/H20 -> #DIV/0! | I47: =I46/I20 -> #DIV/0! | J47: =J46/J20 -> #DIV/0! | K47: =K46/K20 -> #DIV/0!
B49: Growth rates & margins
B51: Revenue growth | D51: =D20/C20-1 -> -0.098487196 | E51: =E20/D20-1 -> -0.18035581 | F51: =F20/E20-1 -> -0.049287079 | H51: ='Street Consensus'!M48 -> 0.062821839 | I51: ='Street Consensus'!N48 -> 0.068996967 | J51: ='Street Consensus'!O48 -> 0.053095052 | K51: ='Street Consensus'!P48 -> 0.06098213 | M51: Consensus estimates through 2030
B52: iPhone Revenue | D52: =SUM(D18/C18)-1 -> -0.08986495 | E52: =SUM(E18/D18)-1 -> -0.26615165 | F52: =SUM(F18/E18)-1 -> -0.029350627 | G52: ='Street Consensus'!L61 -> #DIV/0! | H52: ='Street Consensus'!M61 -> 0.056362565 | I52: ='Street Consensus'!N61 -> 0.056705375 | J52: ='Street Consensus'!O61 -> 0.039855672 | K52: ='Street Consensus'!P61 -> 0.039855672 | M52: Consensus estimates through 2030
B53: Mac Revenue | D53: =SUM(D19/C19)-1 -> -0.11851391 | E53: =SUM(E19/D19)-1 -> 0.025397057 | F53: =SUM(F19/E19)-1 -> -0.08350407 | G53: ='Street Consensus'!L87 -> #REF! | H53: ='Street Consensus'!M87 -> 0.030647887 | I53: ='Street Consensus'!N87 -> 0.037322528 | J53: ='Street Consensus'!O87 -> 0.042385208 | K53: ='Street Consensus'!P87 -> 0.042385208 | M53: Consensus estimates through 2030
B55: Gross profit margin | C55: =C24/C20 -> 1 | D55: =D24/D20 -> 1 | E55: =E24/E20 -> 1 | F55: =F24/F20 -> 1 | G55: ='Street Consensus'!L130 -> 0.46708323 | H55: ='Street Consensus'!M130 -> 0.471 | I55: ='Street Consensus'!N130 -> 0.477 | J55: ='Street Consensus'!O130 -> 0.482 | K55: ='Street Consensus'!P130 -> 0.482 | M55: Consensus estimates through 2030
B56: R&D % of sales | C56: =-C27/C18 -> 0 | D56: =-D27/D18 -> 0 | E56: =-E27/E18 -> 0 | F56: =-F27/F18 -> 0 | G56: ='Street Consensus'!L143 -> 0.12356686 | H56: ='Street Consensus'!M143 -> 0.12667184 | I56: ='Street Consensus'!N143 -> 0.1302502 | J56: ='Street Consensus'!O143 -> 0.13438286 | K56: ='Street Consensus'!P143 -> 0.13188286 | M56: Consensus estimates through 2030
B57: SG&A % of sales | C57: =-C28/C18 -> 0 | D57: =-D28/D18 -> 0 | E57: =-E28/E18 -> 0 | F57: =-F28/F18 -> 0 | G57: ='Street Consensus'!L156 -> 0.066929088 | H57: ='Street Consensus'!M156 -> 0.068371495 | I57: ='Street Consensus'!N156 -> 0.069180674 | J57: ='Street Consensus'!O156 -> 0.070901908 | K57: ='Street Consensus'!P156 -> 0.069101623 | M57: Consensus estimates through 2030
B58: Tax rate | C58: =-(C37/C35) -> 0 | D58: =-(D37/D35) -> 0 | E58: =-(E37/E35) -> 0 | F58: =-(F37/F35) -> 0 | G58: ='Street Consensus'!L171 -> 0.158 | H58: ='Street Consensus'!M171 -> 0.16 | I58: ='Street Consensus'!N171 -> 0.16 | J58: ='Street Consensus'!O171 -> 0.16 | K58: ='Street Consensus'!P171 -> 0.16 | M58: Consensus estimates through 2030
B60: D&A | D60: =D41/C41-1 -> #DIV/0! | E60: =E41/D41-1 -> #DIV/0! | F60: =F41/E41-1 -> #DIV/0! | G60: ='Street Consensus'!L186 -> #DIV/0! | H60: ='Street Consensus'!M186 -> 0.14078064 | I60: ='Street Consensus'!N186 -> 0.073981337 | J60: ='Street Consensus'!O186 -> 0.073981337 | K60: ='Street Consensus'!P186 -> 0.09151634 | M60: Consensus estimates through 2030
B61: SBC | D61: =D45/C45-1 -> #DIV/0! | E61: =E45/D45-1 -> #DIV/0! | F61: =F45/E45-1 -> #DIV/0! | G61: ='Street Consensus'!L197 -> #DIV/0! | H61: ='Street Consensus'!M197 -> 0.068349635 | I61: ='Street Consensus'!N197 -> 0.077013518 | J61: ='Street Consensus'!O197 -> 0.050342858 | K61: ='Street Consensus'!P197 -> 0.044944268 | M61: Consensus estimates through 2030
A63: X | B63: Balance Sheet | C63: Actuals | G63: Forecast
B64: =B15 -> Fiscal year | C64: =C15 -> 2021 | D64: =D15 -> 2022 | E64: =E15 -> 2023 | F64: =F15 -> 2024 | G64: =G15 -> 2025 | H64: =H15 -> 2026 | I64: =I15 -> 2027 | ... K64: =K15 -> 2029
B65: =B16 -> Fiscal year end date | C65: =C16 -> 44561 | D65: =D16 -> 44926 | E65: =E16 -> 45291 | F65: =F16 -> 45657 | G65: =G16 -> 46022 | H65: =H16 -> 46387 | I65: =I16 -> 46752 | ... K65: =K16 -> 47483
B67: Cash & equivalents, ST and LT marketable securities | G67: =+F67+G112 -> #DIV/0! | H67: =+G67+H112 -> #DIV/0! | I67: =+H67+I112 -> #DIV/0! | J67: =+I67+J112 -> #DIV/0! | K67: =+J67+K112 -> #DIV/0! | M67: Reference from 'net change in cash' line on the cash flow statement
B68: Accounts receivable | G68: =F68*(1+G51) -> 0 | H68: =G68*(1+H51) -> 0 | I68: =H68*(1+I51) -> 0 | J68: =I68*(1+J51) -> 0 | K68: =J68*(1+K51) -> 0 | M68: Grow in-line with revenue growth
B69: Inventories | G69: =F69*G23/F23 -> #DIV/0! | H69: =G69*H23/G23 -> #DIV/0! | I69: =H69*I23/H23 -> #DIV/0! | J69: =I69*J23/I23 -> #DIV/0! | K69: =J69*K23/J23 -> #DIV/0! | M69: Grow in-line with cost of sales growth
B70: Other current assets | G70: =F70*(1+G51) -> 0 | H70: =G70*(1+H51) -> 0 | I70: =H70*(1+I51) -> 0 | J70: =I70*(1+J51) -> 0 | K70: =J70*(1+K51) -> 0 | M70: Grow in-line with revenue growth
B71: Property, plant & equipment | M71: Reference from PP&E schedule
B72: Other non current assets | G72: =F72*(1+G51) -> 0 | H72: =G72*(1+H51) -> 0 | I72: =H72*(1+I51) -> 0 | J72: =I72*(1+J51) -> 0 | K72: =J72*(1+K51) -> 0 | M72: Grow in-line with revenue growth
B73: Total Assets | C73: =SUM(C67:C72) -> 0 | D73: =SUM(D67:D72) -> 0 | E73: =SUM(E67:E72) -> 0 | F73: =SUM(F67:F72) -> 0 | G73: =SUM(G67:G72) -> #DIV/0! | H73: =SUM(H67:H72) -> #DIV/0! | I73: =SUM(I67:I72) -> #DIV/0! | J73: =SUM(J67:J72) -> #DIV/0! | K73: =SUM(K67:K72) -> #DIV/0!
B75: Accounts payable | G75: =F75*G23/F23 -> #DIV/0! | H75: =G75*H23/G23 -> #DIV/0! | I75: =H75*I23/H23 -> #DIV/0! | J75: =I75*J23/I23 -> #DIV/0! | K75: =J75*K23/J23 -> #DIV/0! | M75: Grow in-line with cost of sales growth
B76: Other current liabilities | G76: =F76*(1+G51) -> 0 | H76: =G76*(1+H51) -> 0 | I76: =H76*(1+I51) -> 0 | J76: =I76*(1+J51) -> 0 | K76: =J76*(1+K51) -> 0 | M76: Grow in-line with revenue growth
B77: Deferred revenue (current) | G77: =F77*(1+G51) -> 0 | H77: =G77*(1+H51) -> 0 | I77: =H77*(1+I51) -> 0 | J77: =I77*(1+J51) -> 0 | K77: =J77*(1+K51) -> 0 | M77: Grow in-line with revenue growth
B78: Commercial paper / revolver | G78: =G162 -> #DIV/0! | H78: =H162 -> #DIV/0! | I78: =I162 -> #DIV/0! | J78: =J162 -> #DIV/0! | K78: =K162 -> #DIV/0! | M78: Reference EOP balance from CP/revolver schedule
B79: Long term debt (includes current portion) | G79: =F79 -> 0 | H79: =G79 -> 0 | I79: =H79 -> 0 | J79: =I79 -> 0 | K79: =J79 -> 0 | M79: WSP assumption: straight-line
B80: Other non current liabilities | G80: =F80*(1+G51) -> 0 | H80: =G80*(1+H51) -> 0 | I80: =H80*(1+I51) -> 0 | J80: =I80*(1+J51) -> 0 | K80: =J80*(1+K51) -> 0 | M80: Grow in-line with revenue growth
B81: Total liabilities | C81: =SUM(C75:C80) -> 0 | D81: =SUM(D75:D80) -> 0 | E81: =SUM(E75:E80) -> 0 | F81: =SUM(F75:F80) -> 0 | G81: =SUM(G75:G80) -> #DIV/0! | H81: =SUM(H75:H80) -> #DIV/0! | I81: =SUM(I75:I80) -> #DIV/0! | J81: =SUM(J75:J80) -> #DIV/0! | K81: =SUM(K75:K80) -> #DIV/0!
B83: Common stock | G83: =F83+G45 -> 0 | H83: =G83+H45 -> 0 | I83: =H83+I45 -> 0 | J83: =I83+J45 -> 0 | K83: =J83+K45 -> 0 | M83: Increase by stock-based compensation forecasted in the I/S section
B84: Retained earnings | M84: Reference from Retained Earnings schedule
B85: Other comprehensive income | G85: =F85 -> 0 | H85: =G85 -> 0 | I85: =H85 -> 0 | J85: =I85 -> 0 | K85: =J85 -> 0 | M85: WSP assumption: straight-line
B86: Total equity | C86: =SUM(C83:C85) -> 0 | D86: =SUM(D83:D85) -> 0 | E86: =SUM(E83:E85) -> 0 | F86: =SUM(F83:F85) -> 0 | G86: =SUM(G83:G85) -> 0 | H86: =SUM(H83:H85) -> 0 | I86: =SUM(I83:I85) -> 0 | J86: =SUM(J83:J85) -> 0 | K86: =SUM(K83:K85) -> 0
B87: Balance check | C87: =ROUND(C73-C81-C86,3) -> 0 | D87: =ROUND(D73-D81-D86,3) -> 0 | E87: =ROUND(E73-E81-E86,3) -> 0 | F87: =ROUND(F73-F81-F86,3) -> 0 | G87: =ROUND(G73-G81-G86,3) -> #DIV/0! | H87: =ROUND(H73-H81-H86,3) -> #DIV/0! | I87: =ROUND(I73-I81-I86,3) -> #DIV/0! | J87: =ROUND(J73-J81-J86,3) -> #DIV/0! | K87: =ROUND(K73-K81-K86,3) -> #DIV/0!
A89: X | B89: Cash-Flows Statement | C89: Actuals | G89: Forecast
B90: =B15 -> Fiscal year | C90: =C64 -> 2021 | D90: =D64 -> 2022 | E90: =E64 -> 2023 | F90: =F64 -> 2024 | G90: =G15 -> 2025 | H90: =H15 -> 2026 | I90: =I15 -> 2027 | J90: =J15 -> 2028 | K90: =K15 -> 2029
B91: =B16 -> Fiscal year end date | C91: =C65 -> 44561 | D91: =D65 -> 44926 | E91: =E65 -> 45291 | F91: =F65 -> 45657 | G91: =G16 -> 46022 | H91: =H16 -> 46387 | I91: =I16 -> 46752 | J91: =J16 -> 47118 | K91: =K16 -> 47483
B93: Net income | D93: =D38 -> 418934 | E93: =E38 -> 343377 | F93: =F38 -> 326453 | G93: =G38 -> #DIV/0! | H93: =H38 -> #DIV/0! | I93: =I38 -> #DIV/0! | J93: =J38 -> #DIV/0! | K93: =K38 -> #DIV/0! | M93: Reference from the I/S
B94: Depreciation and amortization | D94: =D41 -> 0 | E94: =E41 -> 0 | F94: =F41 -> 0 | G94: =G41 -> 0 | H94: =H41 -> 0 | I94: =I41 -> 0 | J94: =J41 -> 0 | K94: =K41 -> 0 | M94: Reference from the I/S
B95: Stock based compensation | D95: =D45 -> 0 | E95: =E45 -> 0 | F95: =F45 -> 0 | G95: =G45 -> 0 | H95: =H45 -> 0 | I95: =I45 -> 0 | J95: =J45 -> 0 | K95: =K45 -> 0
B96: Decreases / (Increases) in working capital assets | D96: =SUM(C68:C70)-SUM(D68:D70) -> 0 | E96: =SUM(D68:D70)-SUM(E68:E70) -> 0 | F96: =SUM(E68:E70)-SUM(F68:F70) -> 0 | G96: =SUM(F68:F70)-SUM(G68:G70) -> #DIV/0! | H96: =SUM(G68:G70)-SUM(H68:H70) -> #DIV/0! | I96: =SUM(H68:H70)-SUM(I68:I70) -> #DIV/0! | J96: =SUM(I68:I70)-SUM(J68:J70) -> #DIV/0! | K96: =SUM(J68:J70)-SUM(K68:K70) -> #DIV/0!
B97: Increases / (Decreases) in working capital liabilities | D97: =SUM(D75:D77)-SUM(C75:C77) -> 0 | E97: =SUM(E75:E77)-SUM(D75:D77) -> 0 | F97: =SUM(F75:F77)-SUM(E75:E77) -> 0 | G97: =SUM(G75:G77)-SUM(F75:F77) -> #DIV/0! | H97: =SUM(H75:H77)-SUM(G75:G77) -> #DIV/0! | I97: =SUM(I75:I77)-SUM(H75:H77) -> #DIV/0! | J97: =SUM(J75:J77)-SUM(I75:I77) -> #DIV/0! | K97: =SUM(K75:K77)-SUM(J75:J77) -> #DIV/0!
B98: Other non current assets | D98: =-D138 -> 0 | E98: =-E138 -> 0 | F98: =-F138 -> 0 | G98: =-G138 -> #DIV/0! | H98: =-H138 -> #DIV/0! | I98: =-I138 -> #DIV/0! | J98: =-J138 -> #DIV/0! | K98: =-K138 -> #DIV/0! | M98: Reference from schedule NOT the B/S: Only include 'Additions' (as outflow)
B99: Other non current liabilities | D99: =D80-C80 -> 0 | E99: =E80-D80 -> 0 | F99: =F80-E80 -> 0 | G99: =G80-F80 -> 0 | H99: =H80-G80 -> 0 | I99: =I80-H80 -> 0 | J99: =J80-I80 -> 0 | K99: =K80-J80 -> 0
B100: Cash from Operating Activities | D100: =SUM(D93:D99) -> 418934 | E100: =SUM(E93:E99) -> 343377 | F100: =SUM(F93:F99) -> 326453 | G100: =SUM(G93:G99) -> #DIV/0! | H100: =SUM(H93:H99) -> #DIV/0! | I100: =SUM(I93:I99) -> #DIV/0! | J100: =SUM(J93:J99) -> #DIV/0! | K100: =SUM(K93:K99) -> #DIV/0!
B102: Capital Expenditures | D102: =-(D123) -> 0 | E102: =-(E123) -> 0 | F102: =-(F123) -> 0 | G102: =-(G123) -> 0 | H102: =-(H123) -> 0 | I102: =-(I123) -> 0 | J102: =-(J123) -> 0 | K102: =-(K123) -> 0 | M102: Reference from PP&E schedule
B103: Cash from Investing Activities | D103: =IFERROR(D102,"NA") -> 0 | E103: =IFERROR(E102,"NA") -> 0 | F103: =IFERROR(F102,"NA") -> 0 | G103: =IFERROR(G102,"NA") -> 0 | H103: =IFERROR(H102,"NA") -> 0 | I103: =IFERROR(I102,"NA") -> 0 | J103: =IFERROR(J102,"NA") -> 0 | K103: =IFERROR(K102,"NA") -> 0
B105: Long term debt | D105: =D79-C79 -> 0 | E105: =E79-D79 -> 0 | F105: =F79-E79 -> 0 | G105: =G79-F79 -> 0 | H105: =H79-G79 -> 0 | I105: =I79-H79 -> 0 | J105: =J79-I79 -> 0 | K105: =K79-J79 -> 0
B106: Commercial paper/ Revolver | D106: =D78-C78 -> 0 | E106: =E78-D78 -> 0 | F106: =F78-E78 -> 0 | G106: =G78-F78 -> #DIV/0! | H106: =H78-G78 -> #DIV/0! | I106: =I78-H78 -> #DIV/0! | J106: =J78-I78 -> #DIV/0! | K106: =K78-J78 -> #DIV/0! | M106: Reference from B/S
B107: Share repurchases | D107: =D145 -> 0 | E107: =E145 -> 0 | F107: =F145 -> 0 | G107: =G145 -> 0 | H107: =H145 -> 0 | I107: =I145 -> 0 | J107: =J145 -> 0 | K107: =K145 -> 0 | M107: Reference from Retained Earnings schedule
B108: Common dividends | D108: =D144 -> 0 | E108: =E144 -> 0 | F108: =F144 -> 0 | G108: =G144 -> #DIV/0! | H108: =H144 -> #DIV/0! | I108: =I144 -> #DIV/0! | J108: =J144 -> #DIV/0! | K108: =K144 -> #DIV/0! | M108: Reference from Retained Earnings schedule
B109: Common dividends | D109: =D145 -> 0 | E109: =E145 -> 0 | F109: =F145 -> 0 | G109: =G145 -> 0 | H109: =H145 -> 0 | I109: =I145 -> 0 | J109: =J145 -> 0 | K109: =K145 -> 0 | M109: Reference from Retained Earnings schedule
B110: Cash from Financing Activities | D110: =SUM(D105:D108) -> 0 | E110: =SUM(E105:E108) -> 0 | F110: =SUM(F105:F108) -> 0 | G110: =SUM(G105:G108) -> #DIV/0! | H110: =SUM(H105:H108) -> #DIV/0! | I110: =SUM(I105:I108) -> #DIV/0! | J110: =SUM(J105:J108) -> #DIV/0! | K110: =SUM(K105:K108) -> #DIV/0!
B112: Net change in cash during period | D112: =D100+D103+D110 -> 418934 | E112: =E100+E103+E110 -> 343377 | F112: =F100+F103+F110 -> 326453 | G112: =G100+G103+G110 -> #DIV/0! | H112: =H100+H103+H110 -> #DIV/0! | I112: =I100+I103+I110 -> #DIV/0! | J112: =J100+J103+J110 -> #DIV/0! | K112: =K100+K103+K110 -> #DIV/0!
A114: X | B114: Supporting Schedules | C114: Actuals | G114: Forecast
B115: Fiscal year | C115: 2021 | D115: 2022 | E115: 2023 | F115: 2024 | G115: 2025 | H115: 2026 | I115: 2027 | J115: 2028 | K115: 2029
B116: Fiscal year end date | C116: 44469 | D116: 44834 | E116: 45199 | F116: 45559 | G116: 45930 | H116: 46295 | I116: 46660 | J116: 47026 | K116: 47391
A118: X | B118: PROPERTY, PLANT & EQUIPMENT
B119: =B15 -> Fiscal year | D119: =D15 -> 2022 | E119: =E15 -> 2023 | F119: =F15 -> 2024 | G119: =G15 -> 2025 | H119: =H15 -> 2026 | I119: =I15 -> 2027 | J119: =J15 -> 2028 | K119: =K15 -> 2029
B120: =B16 -> Fiscal year end date | D120: =D16 -> 44926 | E120: =E16 -> 45291 | F120: =F16 -> 45657 | G120: =G16 -> 46022 | H120: =H16 -> 46387 | I120: =I16 -> 46752 | J120: =J16 -> 47118 | K120: =K16 -> 47483
G121: Forecast
B122: Beginning of period | D122: =C125 -> 0 | E122: =D125 -> 0 | F122: =E125 -> 0 | G122: =F125 -> 0 | H122: =G125 -> #DIV/0! | I122: =H125 -> #DIV/0! | J122: =I125 -> #DIV/0! | K122: =J125 -> #DIV/0! | M122: BOP = Previous year EOP
B123: Plus: Capital expenditures | M123: First two years - consensus estimates, then grow with revenue
B124: Less: Depreciation | G124: =-(G127*G123) -> #DIV/0! | H124: =-(H127*H123) -> #DIV/0! | I124: =-(I127*I123) -> #DIV/0! | J124: =-(J127*J123) -> #DIV/0! | K124: =-(K127*K123) -> #DIV/0! | M124: Capex x 'D&A related to PP&E as a % of capex' ratio (below)
B125: End of period | C125: =C71 -> 0 | D125: =D71 -> 0 | E125: =E71 -> 0 | F125: =F71 -> 0 | G125: =SUM(G122:G124) -> #DIV/0! | H125: =SUM(H122:H124) -> #DIV/0! | I125: =SUM(I122:I124) -> #DIV/0! | J125: =SUM(J122:J124) -> #DIV/0! | K125: =SUM(K122:K124) -> #DIV/0! | M125: BOP + Capex - Depreciation
...

Sheet DCF
B2: ='3-Statement Model'!C6&"(NASDAQ: AAPL)" -> Beyond Meat, Inc.(NASDAQ: AAPL)
B3: Discounted Cash Flow Valuation
B4: $ and shares in millions, except per share data
B6: Most recent fiscal year end | C6: ='Historical Financials'!I8 -> 45657 | F6: Discount rate (WACC) | H6: =WACC!E23 -> 0.055928884 | I6: Link from WACC
B7: End of first fiscal year | C7: =EOMONTH(C6,12) -> 46022 | F7: Share price (Public Co) | H7: 262.82 | I7: Source: CIQ
B8: Most recent quarter end date | C8: ='Historical Financials'!#REF! -> #REF! | F8: Share price date | H8: 45956
B9: Valuation date | C9: 45956 | F9: Midyear adjustment? | H9: 1
B10: Portion of First Year Cash Flows | C10: =YEARFRAC(C9,C7) -> 0.18055556 | F10: Case active: | H10: ='3-Statement Model'!K6 -> Base case
B12: Unlevered Free Cash Flows
C13: LTM | D13: Actual | E13: Forecasts
B14: Fiscal year ended | C14: =C9 -> 45956 | D14: =C6 -> 45657 | E14: =EOMONTH(D14,12) -> 46022 | F14: =EOMONTH(E14,12) -> 46387 | G14: =EOMONTH(F14,12) -> 46752 | H14: =EOMONTH(G14,12) -> 47118 | I14: =EOMONTH(H14,12) -> 47483
B16: Revenue | C16: =FCF!AI8 -> 301353 | D16: =FCF!G8 -> 326452 | E16: ='3-Statement Model'!G18 -> #DIV/0! | F16: ='3-Statement Model'!H18 -> #DIV/0! | G16: ='3-Statement Model'!I18 -> #DIV/0! | H16: ='3-Statement Model'!J18 -> #DIV/0! | I16: ='3-Statement Model'!K18 -> #DIV/0!
B17: % growth | E17: =SUM(E16/D16)-1 -> #DIV/0! | F17: =SUM(F16/E16)-1 -> #DIV/0! | G17: =SUM(G16/F16)-1 -> #DIV/0! | H17: =SUM(H16/G16)-1 -> #DIV/0! | I17: =SUM(I16/H16)-1 -> #DIV/0!
B18: EBITDA | C18: =FCF!AI22 -> -133209 | D18: =FCF!G22 -> -133003 | E18: ='3-Statement Model'!G42 -> #DIV/0! | F18: ='3-Statement Model'!H42 -> #DIV/0! | G18: ='3-Statement Model'!I42 -> #DIV/0! | H18: ='3-Statement Model'!J42 -> #DIV/0! | I18: ='3-Statement Model'!K42 -> #DIV/0!
B19: % margin | D19: =D18/D16 -> -0.40741977 | E19: =E18/E16 -> #DIV/0! | F19: =F18/F16 -> #DIV/0! | G19: =G18/G16 -> #DIV/0! | H19: =H18/H16 -> #DIV/0! | I19: =I18/I16 -> #DIV/0!
B20: EBIT | C20: =FCF!AI18 -> -159830 | D20: =FCF!G18 -> -156124 | E20: ='3-Statement Model'!G29 -> #DIV/0! | F20: ='3-Statement Model'!H29 -> #DIV/0! | G20: ='3-Statement Model'!I29 -> #DIV/0! | H20: ='3-Statement Model'!J29 -> #DIV/0! | I20: ='3-Statement Model'!K29 -> #DIV/0!
B21: % margin | D21: =D20/D16 -> -0.47824489 | E21: =E20/E16 -> #DIV/0! | F21: =F20/F16 -> #DIV/0! | G21: =G20/G16 -> #DIV/0! | H21: =H20/H16 -> #DIV/0! | I21: =I20/I16 -> #DIV/0!
B23: Tax on EBIT | D23: ='3-Statement Model'!F37 -> 0 | E23: =+E20*E24 -> #DIV/0! | F23: =+F20*F24 -> #DIV/0! | G23: =+G20*G24 -> #DIV/0! | H23: =+H20*H24 -> #DIV/0! | I23: =+I20*I24 -> #DIV/0!
B24: Tax rate | D24: =D23/D20 -> 0 | E24: ='3-Statement Model'!G58 -> 0.158 | F24: ='3-Statement Model'!H58 -> 0.16 | G24: ='3-Statement Model'!I58 -> 0.16 | H24: ='3-Statement Model'!J58 -> 0.16 | I24: ='3-Statement Model'!K58 -> 0.16
B25: NOPAT (aka EBIAT) | D25: =+D23+D20 -> -156124 | E25: =E20*(1-E24) -> #DIV/0! | F25: =F20*(1-F24) -> #DIV/0! | G25: =G20*(1-G24) -> #DIV/0! | H25: =H20*(1-H24) -> #DIV/0! | I25: =I20*(1-I24) -> #DIV/0!
B27: Depreciation & amortization | D27: ='3-Statement Model'!F41 -> 0 | E27: ='3-Statement Model'!G41 -> 0 | F27: ='3-Statement Model'!H41 -> 0 | G27: ='3-Statement Model'!I41 -> 0 | H27: ='3-Statement Model'!J41 -> 0 | I27: ='3-Statement Model'!K41 -> 0
B28: Changes in net working capital | E28: =D34-E34 -> #DIV/0! | F28: =E34-F34 -> #DIV/0! | G28: =F34-G34 -> #DIV/0! | H28: =G34-H34 -> #DIV/0! | I28: =H34-I34 -> #DIV/0!
B29: Capital expenditures | E29: =-'3-Statement Model'!G102 -> 0 | F29: =-'3-Statement Model'!H102 -> 0 | G29: =-'3-Statement Model'!I102 -> 0 | H29: =-'3-Statement Model'!J102 -> 0 | I29: =-'3-Statement Model'!K102 -> 0
B30: as % of revenue | E30: =E29/E16 -> #DIV/0! | F30: =F29/F16 -> #DIV/0! | G30: =G29/G16 -> #DIV/0! | H30: =H29/H16 -> #DIV/0! | I30: =I29/I16 -> #DIV/0!
B32: Unlevered free cash flows (UFCF) | E32: =+E25+E27+E28+E29 -> #DIV/0! | F32: =+F25+F27+F28+F29 -> #DIV/0! | G32: =+G25+G27+G28+G29 -> #DIV/0! | H32: =+H25+H27+H28+H29 -> #DIV/0! | I32: =+I25+I27+I28+I29 -> #DIV/0!
B34: Net working capital (WC Assets - WC liabilities) | D34: =SUM('3-Statement Model'!F97)-SUM('3-Statement Model'!F96) -> 0 | E34: =SUM('3-Statement Model'!G97)-SUM('3-Statement Model'!G96) -> #DIV/0! | F34: =SUM('3-Statement Model'!H97)-SUM('3-Statement Model'!H96) -> #DIV/0! | G34: =SUM('3-Statement Model'!I97)-SUM('3-Statement Model'!I96) -> #DIV/0! | H34: =SUM('3-Statement Model'!J97)-SUM('3-Statement Model'!J96) -> #DIV/0! | I34: =SUM('3-Statement Model'!K97)-SUM('3-Statement Model'!K96) -> #DIV/0!
B35: as % of revenue | E35: =+E34/E16 -> #DIV/0! | F35: =+F34/F16 -> #DIV/0! | G35: =+G34/G16 -> #DIV/0! | H35: =+H34/H16 -> #DIV/0! | I35: =+I34/I16 -> #DIV/0!
B37: ="Present value of UFCF on "&TEXT(C9,"mmm dd, yyyy")&" valuation date" -> Present value of UFCF on Oct 26, 2025 valuation date
D39: Val date | E39: Yr 1 - Stub | F39: Year 2 | G39: Year 3 | H39: Year 4 | I39: Year 5
B40: Date for discounting cash flows | D40: =C9 -> 45956 | E40: =IF($H$9=1,AVERAGE(E14,D40),E14) -> 45989 | F40: =IF($H$9=1,AVERAGE(F14,E14),F14) -> 46204.5 | G40: =IF($H$9=1,AVERAGE(G14,F14),G14) -> 46569.5 | H40: =IF($H$9=1,AVERAGE(H14,G14),H14) -> 46935 | I40: =IF($H$9=1,AVERAGE(I14,H14),I14) -> 47300.5
B41: Unlevered free cash flows (UFCF) stub adjusted | C41: =C10 -> 0.18055556 | E41: =E32*C41 -> #DIV/0! | F41: =F32 -> #DIV/0! | G41: =G32 -> #DIV/0! | H41: =H32 -> #DIV/0! | I41: =I32 -> #DIV/0! | K41: <-Stub year counts first year cash flows starting at the valuation date
B42: Present value of of unlevered free cash flows | E42: =E41/(1+$H$6)^((E40-$C$9)/365) -> #DIV/0! | F42: =F41/(1+$H$6)^((F40-$C$9)/365) -> #DIV/0! | G42: =G41/(1+$H$6)^((G40-$C$9)/365) -> #DIV/0! | H42: =H41/(1+$H$6)^((H40-$C$9)/365) -> #DIV/0! | I42: =I41/(1+$H$6)^((I40-$C$9)/365) -> #DIV/0!
B44: Terminal value - growth in perpetuity approach | E44: Terminal value - EBITDA multiple approach
B46: Long term growth rate | C46: 0.03 | E46: Terminal year EBITDA | I46: =I18 -> #DIV/0!
B47: =YEAR(I14)&" FCF x (1+g)" -> 2029 FCF x (1+g) | C47: =I41*(1+C46) -> #DIV/0! | E47: EBITDA multiple | I47: 16.2
B48: ="Terminal value in "&YEAR(I14) -> Terminal value in 2029 | C48: =C47/(H6-C46) -> #DIV/0! | E48: ="Terminal value in "&YEAR(I14) -> Terminal value in 2029 | I48: =I46*I47 -> #DIV/0!
B49: Present value of terminal value | C49: =C48/(1+H6)^((I40-$D$40)/365) -> #DIV/0! | E49: Present value of terminal value | I49: =I48/(1+H6)^((I40-D40)/365) -> #DIV/0!
B50: Present value of stage 1 cash flows | C50: =SUM(E42:I42) -> #DIV/0! | E50: Present value of stage 1 cash flows | I50: =C50 -> #DIV/0!
B51: Total enterprise value (TEV) | C51: =C50+C49 -> #DIV/0! | E51: Enterprise value (stage 1 + 2) | I51: =SUM(I49:I50) -> #DIV/0!
B53: Terminal value as % of TEV | C53: =C49/$C$51 -> #DIV/0! | E53: Terminal value as % of TEV | I53: =+I49/I51 -> #DIV/0!
B54: Stage 1 cash flows as % of TEV | C54: =1-C53 -> #DIV/0! | E54: Cash flows as % of TEV | I54: =1-I53 -> #DIV/0!
B55: Implied TV exit EBITDA multiple | C55: =(C48/I18) -> #DIV/0! | E55: Implied terminal growth rate | I55: =(H6-I41/I48)/(1+I41/I48) -> #DIV/0!
B57: Net debt | E57: Shares outstanding
B58: Source doc | C58: 3Q25 10Q
B59: Source date | C59: =C8 -> #REF! | G59: Source doc | H59: Date | I59: Shares
B60: Gross debt and equivalents | E60: Basic shares | G60: Capital IQ | H60: =NOW() -> 45966.75 | I60: 14840.39
B61: Debt | C61: =FCF!AI70 -> 1257927 | E61: Restricted stock / RSUs | G61: 3Q25 10Q | H61: 45833 | I61: 149.976
B62: Convertible debt | C62: =[1]Shares!E25+[1]Shares!E31 -> 0 | E62: Options / warrants | G62: 3Q25 10Q | H62: 45833 | I62: =Shares!E19 -> 0
B63: Preferred stock | C63: =[1]Shares!E34+[1]Shares!E41 -> 0 | E63: Convertible debt | G63: 3Q25 10Q | H63: 45833 | I63: =0 -> 0
B64: Noncontrolling (minority) interests | C64: 0 | E64: Convertible preferred stock | G64: 3Q25 10Q | H64: 45833 | I64: 0
B65: Nonoperating assets | E65: Net diluted shares outstanding | I65: =SUM(I60:I64) -> 14990.366
B66: Cash | C66: =FCF!AI51 -> 117269
B67: Equity investments | C67: 0
B68: Net debt | C68: =SUM(C61:C64)-SUM(C66:C67) -> 1140658
B70: Valuation
C72: Perpetuity | D72: EBITDA
B73: Enterprise value | C73: =C51 -> #DIV/0! | D73: =I51 -> #DIV/0!
B74: Net debt | C74: =$C$68 -> 1140658 | D74: =C74 -> 1140658
B75: Equity value | C75: =C73-C74 -> #DIV/0! | D75: =D73-D74 -> #DIV/0!
B76: Shares outstanding | C76: =$I$65 -> 14990.366 | D76: =C76 -> 14990.366
B77: Equity value per share | C77: =C75/C76 -> #DIV/0! | D77: =D75/D76 -> #DIV/0!
C79: Last twelve months (LTM)
C80: Perpetuity | D80: EBITDA
B81: EV / Revenue | C81: =C$73/$C$16 -> #DIV/0! | D81: =D$73/$C$16 -> #DIV/0!
B82: EV / EBITDA | C82: =C73/$C$18 -> #DIV/0! | D82: =D73/$C$18 -> #DIV/0!
B83: EV / EBIT | C83: =C73/$C$20 -> #DIV/0! | D83: =D73/$C$20 -> #DIV/0!
C84: Year 1
C85: Perpetuity | D85: EBITDA
B86: EV / Revenue | C86: =C73/$E$16 -> #DIV/0! | D86: =D73/$E$16 -> #DIV/0!
B87: EV / EBITDA | C87: =C73/$E$18 -> #DIV/0! | D87: =D73/$E$18 -> #DIV/0!
B88: EV / EBIT | C88: =C73/$E$20 -> #DIV/0! | D88: =D73/$E$20 -> #DIV/0!
B90: Outputs
D92: Equity value per share | L92: LTM EBITDA multiple
E93: Long term growth rate (g):
D94: =C77 -> #DIV/0! | E94: =F94-0.005 -> 0.02 | F94: =G94-0.005 -> 0.025 | G94: 0.03 | H94: =G94+0.005 -> 0.035 | I94: =H94+0.005 -> 0.04 | L94: =C82 -> #DIV/0! | M94: =N94-0.005 -> 0.02 | N94: =O94-0.005 -> 0.025 | O94: 0.03 | P94: =O94+0.005 -> 0.035 | Q94: =P94+0.005 -> 0.04
D95: =D96+0.01 -> 0.11 | E95: 20.680633 | F95: 20.680633 | G95: 20.680633 | H95: 20.680633 | I95: 20.680633 | L95: =L96+0.01 -> 0.11 | M95: #DIV/0! | N95: #DIV/0! | O95: #DIV/0! | P95: #DIV/0! | Q95: #DIV/0!
D96: =D97+0.01 -> 0.1 | E96: 20.680633 | F96: 20.680633 | G96: 20.680633 | H96: 20.680633 | I96: 20.680633 | L96: =L97+0.01 -> 0.1 | M96: #DIV/0! | N96: #DIV/0! | O96: #DIV/0! | P96: #DIV/0! | Q96: #DIV/0!
C97: WACC: | D97: 0.09 | E97: 20.680633 | F97: 20.680633 | G97: 20.680633 | H97: 20.680633 | I97: 20.680633 | K97: WACC: | L97: 0.09 | M97: #DIV/0! | N97: #DIV/0! | O97: #DIV/0! | P97: #DIV/0! | Q97: #DIV/0!
D98: =D97-0.01 -> 0.08 | E98: 20.680633 | F98: 20.680633 | G98: 20.680633 | H98: 20.680633 | I98: 20.680633 | L98: =L97-0.01 -> 0.08 | M98: #DIV/0! | N98: #DIV/0! | O98: #DIV/0! | P98: #DIV/0! | Q98: #DIV/0!
B99: Data | D99: =D98-0.01 -> 0.07 | E99: 20.680633 | F99: 20.680633 | G99: 20.680633 | H99: 20.680633 | I99: 20.680633 | L99: =L98-0.01 -> 0.07 | M99: #DIV/0! | N99: #DIV/0! | O99: #DIV/0! | P99: #DIV/0! | Q99: #DIV/0!
B100: Tables
D101: Equity value per share | L101: LTM EBITDA multiple
E102: Exit EBITDA Multiple | M102: Exit EBITDA Multiple
D103: =D77 -> #DIV/0! | E103: =F103-1 -> 11 | F103: =G103-1 -> 12 | G103: 13 | H103: =G103+1 -> 14 | I103: =H103+1 -> 15 | L103: =D82 -> #DIV/0! | M103: =N103-1 -> 11 | N103: =O103-1 -> 12 | O103: 13 | P103: =O103+1 -> 14 | Q103: =P103+1 -> 15
D104: =D105+0.01 -> 0.11 | E104: 20.680633 | F104: 20.680633 | G104: 20.680633 | H104: 20.680633 | I104: 20.680633 | L104: =L105+0.01 -> 0.11 | M104: #DIV/0! | N104: #DIV/0! | O104: #DIV/0! | P104: #DIV/0! | Q104: #DIV/0!
D105: =D106+0.01 -> 0.1 | E105: 20.680633 | F105: 20.680633 | G105: 20.680633 | H105: 20.680633 | I105: 20.680633 | L105: =L106+0.01 -> 0.1 | M105: #DIV/0! | N105: #DIV/0! | O105: #DIV/0! | P105: #DIV/0! | Q105: #DIV/0!
C106: WACC: | D106: 0.09 | E106: 20.680633 | F106: 20.680633 | G106: 20.680633 | H106: 20.680633 | I106: 20.680633 | K106: WACC: | L106: 0.09 | M106: #DIV/0! | N106: #DIV/0! | O106: #DIV/0! | P106: #DIV/0! | Q106: #DIV/0!
D107: =D106-0.01 -> 0.08 | E107: 20.680633 | F107: 20.680633 | G107: 20.680633 | H107: 20.680633 | I107: 20.680633 | L107: =L106-0.01 -> 0.08 | M107: #DIV/0! | N107: #DIV/0! | O107: #DIV/0! | P107: #DIV/0! | Q107: #DIV/0!
D108: =D107-0.01 -> 0.07 | E108: 20.680633 | F108: 20.680633 | G108: 20.680633 | H108: 20.680633 | I108: 20.680633 | L108: =L107-0.01 -> 0.07 | M108: #DIV/0! | N108: #DIV/0! | O108: #DIV/0! | P108: #DIV/0! | Q108: #DIV/0!
B110: Equity value range | G110: Football field
C131: Low | D131: Diff. | E131: High | O131: Low | P131: Diff. | Q131: High
B132: ="DCF Value at "&TEXT(E103,"0.0x")&"-"&TEXT(I103,"0.0x")&" Exit EBITDA Range at "&TEXT(D106,"0.0%")&" WACC" -> DCF Value at 11.0x-15.0x Exit EBITDA Range at 9.0% WACC | C132: =E106 -> 20.680633 | D132: =E132-C132 -> 0 | E132: =I106 -> 20.680633 | G132: ="LTM EBITDA Purchase Multiple at "&TEXT(M94,"0.0%")&"-"&TEXT(Q94,"0.0%")&" Perpetuity Growth at "&TEXT(L97,"0.0%")&" WACC" -> LTM EBITDA Purchase Multiple at 2.0%-4.0% Perpetuity Growth at 9.0% WACC | O132: =M97 -> #DIV/0! | P132: =Q132-O132 -> #DIV/0! | Q132: =Q97 -> #DIV/0!
B133: ="DCF Value at "&TEXT(E94,"0.0%")&"-"&TEXT(I94,"0.0%")&" Perpetuity Range at "&TEXT(D106,"0.0%")&" WACC" -> DCF Value at 2.0%-4.0% Perpetuity Range at 9.0% WACC | C133: =E97 -> 20.680633 | D133: =E133-C133 -> 0 | E133: =I97 -> 20.680633 | G133: ="LTM EBITDA Purchase Multiple at "&TEXT(M106,"0.0x")&"-"&TEXT(Q106,"0.0x")&" Exit EBITDA Multiple at "&TEXT(L106,"0.0%")&" WACC" -> #DIV/0! | O133: =M106 -> #DIV/0! | P133: =Q133-O133 -> #DIV/0! | Q133: =Q106 -> #DIV/0!
B134: 52 Week Market High/Low | C134: 169.5 | D134: =E134-C134 -> 158.35 | E134: 327.85 | G134: ="LTM EBITDA Purchase Multiple at "&TEXT(L108,"0.0%")&"-"&TEXT(L104,"0.0%")&" WACC at "&TEXT(O103,"0.0x")&" Exit EBITDA" -> LTM EBITDA Purchase Multiple at 7.0%-11.0% WACC at 13.0x Exit EBITDA | O134: =O104 -> #DIV/0! | P134: =Q134-O134 -> #DIV/0! | Q134: =O108 -> #DIV/0!

Sheet Street Consensus
B2: Apple Inc. (NASDAQ: AAPL) | C2: Actuals | J2: CAGR | L2: Forecast | S2: CAGR
B3: Street Outlook | C3: 2019 | D3: 2020 | E3: 2021 | F3: 2022 | G3: 2023 | H3: 2024 | J3: 5-Year(A) | L3: 2025 | M3: 2026 | N3: 2027 | O3: 2028 | P3: 2029 | Q3: 2030 | S3: 5-Year(F)
B4: $ mm except per share | C4: 43737 | D4: 44104 | E4: 44469 | F4: 44834 | G4: 45192 | H4: 45559 | J4: =H4 -> 45559 | L4: 45930 | M4: 46295 | N4: 46660 | O4: 47026 | P4: 47391 | Q4: 47756 | S4: =Q4 -> 47756
B6: iPhone Revenue | J6: =((H6/C6)^(1/COUNT(D6:H6))-1) -> #DIV/0! | L6: =(H6*L61)+H6 -> #DIV/0! | M6: =(L6*M61)+L6 -> #DIV/0! | N6: =(M6*N61)+M6 -> #DIV/0! | O6: =(N6*O61)+N6 -> #DIV/0! | P6: =(O6*P61)+O6 -> #DIV/0! | Q6: =(P6*Q61)+P6 -> #DIV/0! | S6: =((Q6/H6)^(1/COUNT(L6:Q6))-1) -> #DIV/0!
B7: iPad Revenue | J7: =((H7/C7)^(1/COUNT(D7:H7))-1) -> #DIV/0! | L7: =(H7*L74)+H7 -> #DIV/0! | M7: =(L7*M74)+L7 -> #DIV/0! | N7: =(M7*N74)+M7 -> #DIV/0! | O7: =(N7*O74)+N7 -> #DIV/0! | P7: =(O7*P74)+O7 -> #DIV/0! | Q7: =(P7*Q74)+P7 -> #DIV/0! | S7: =((Q7/H7)^(1/COUNT(L7:Q7))-1) -> #DIV/0!
B8: Total Revenue | C8: =SUM(C6:C7) -> 0 | D8: =SUM(D6:D7) -> 0 | E8: =SUM(E6:E7) -> 0 | F8: =SUM(F6:F7) -> 0 | G8: =SUM(G6:G7) -> 0 | H8: =SUM(H6:H7) -> 0 | J8: =((H8/C8)^(1/COUNT(D8:H8))-1) -> #DIV/0! | L8: =SUM(L6:L7) -> #DIV/0! | M8: =SUM(M6:M7) -> #DIV/0! | N8: =SUM(N6:N7) -> #DIV/0! | O8: =SUM(O6:O7) -> #DIV/0! | P8: =SUM(P6:P7) -> #DIV/0! | Q8: =SUM(Q6:Q7) -> #DIV/0! | S8: =((Q8/H8)^(1/COUNT(L8:Q8))-1) -> #DIV/0!
B10: Cost of sales | J10: =((H10/C10)^(1/COUNT(D10:H10))-1) -> #DIV/0! | L10: =-(L8-L11) -> #DIV/0! | M10: =-(M8-M11) -> #DIV/0! | N10: =-(N8-N11) -> #DIV/0! | O10: =-(O8-O11) -> #DIV/0! | P10: =-(P8-P11) -> #DIV/0! | Q10: =-(Q8-Q11) -> #DIV/0! | S10: =((Q10/L10)^(1/COUNT(M10:Q10))-1) -> #DIV/0!
B11: Gross Profit | C11: =+C10+C8 -> 0 | D11: =+D10+D8 -> 0 | E11: =+E10+E8 -> 0 | F11: =+F10+F8 -> 0 | G11: =+G10+G8 -> 0 | H11: =+H10+H8 -> 0 | J11: =((H11/C11)^(1/COUNT(D11:H11))-1) -> #DIV/0! | L11: =L8*L130 -> #DIV/0! | M11: =M8*M130 -> #DIV/0! | N11: =N8*N130 -> #DIV/0! | O11: =O8*O130 -> #DIV/0! | P11: =P8*P130 -> #DIV/0! | Q11: =Q8*Q130 -> #DIV/0! | S11: =((Q11/L11)^(1/COUNT(M11:Q11))-1) -> #DIV/0!
B13: Research & Development | J13: =((H13/C13)^(1/COUNT(D13:H13))-1) -> #DIV/0! | L13: =-(L143*L8) -> #DIV/0! | M13: =-(M143*M8) -> #DIV/0! | N13: =-(N143*N8) -> #DIV/0! | O13: =-(O143*O8) -> #DIV/0! | P13: =-(P143*P8) -> #DIV/0! | Q13: =-(Q143*Q8) -> #DIV/0! | S13: =((Q13/L13)^(1/COUNT(M13:Q13))-1) -> #DIV/0!
B14: Selling, General & Administrative | J14: =((H14/C14)^(1/COUNT(D14:H14))-1) -> #DIV/0! | L14: =-(L156*L8) -> #DIV/0! | M14: =-(M156*M8) -> #DIV/0! | N14: =-(N156*N8) -> #DIV/0! | O14: =-(O156*O8) -> #DIV/0! | P14: =-(P156*P8) -> #DIV/0! | Q14: =-(Q156*Q8) -> #DIV/0! | S14: =((Q14/L14)^(1/COUNT(M14:Q14))-1) -> #DIV/0!
B15: Operating profit (EBIT) | C15: =SUM(C13:C14)+C11 -> 0 | D15: =SUM(D13:D14)+D11 -> 0 | E15: =SUM(E13:E14)+E11 -> 0 | F15: =SUM(F13:F14)+F11 -> 0 | G15: =SUM(G13:G14)+G11 -> 0 | H15: =SUM(H13:H14)+H11 -> 0 | J15: =((H15/C15)^(1/COUNT(D15:H15))-1) -> #DIV/0! | L15: =SUM(L13:L14)+L11 -> #DIV/0! | M15: =SUM(M13:M14)+M11 -> #DIV/0! | N15: =SUM(N13:N14)+N11 -> #DIV/0! | O15: =SUM(O13:O14)+O11 -> #DIV/0! | P15: =SUM(P13:P14)+P11 -> #DIV/0! | Q15: =SUM(Q13:Q14)+Q11 -> #DIV/0! | S15: =((Q15/L15)^(1/COUNT(M15:Q15))-1) -> #DIV/0!
B17: Interest income | J17: =((H17/C17)^(1/COUNT(D17:H17))-1) -> #DIV/0! | L17: =+(H17*L48)+H17 -> #DIV/0! | M17: =+(L17*M48)+L17 -> #DIV/0! | N17: =+(M17*N48)+M17 -> #DIV/0! | O17: =+(N17*O48)+N17 -> #DIV/0! | P17: =+(O17*P48)+O17 -> #DIV/0! | Q17: =+(P17*Q48)+P17 -> #DIV/0! | S17: =((Q17/L17)^(1/COUNT(M17:Q17))-1) -> #DIV/0!
B18: Interest expense | J18: =((H18/C18)^(1/COUNT(D18:H18))-1) -> #DIV/0! | L18: =H18 -> 0 | M18: =L18 -> 0 | N18: =M18 -> 0 | O18: =N18 -> 0 | P18: =O18 -> 0 | Q18: =P18 -> 0 | S18: =((Q18/L18)^(1/COUNT(M18:Q18))-1) -> #DIV/0!
B19: Other expense, net | J19: =((H19/C19)^(1/COUNT(D19:H19))-1) -> #DIV/0! | L19: =H19 -> 0 | M19: =L19 -> 0 | N19: =M19 -> 0 | O19: =N19 -> 0 | P19: =O19 -> 0 | Q19: =P19 -> 0 | S19: =((Q19/L19)^(1/COUNT(M19:Q19))-1) -> #DIV/0!
B20: Pretax profit | C20: =SUM(C17:C19)+C15 -> 0 | D20: =SUM(D17:D19)+D15 -> 0 | E20: =SUM(E17:E19)+E15 -> 0 | F20: =SUM(F17:F19)+F15 -> 0 | G20: =SUM(G17:G19)+G15 -> 0 | H20: =SUM(H17:H19)+H15 -> 0 | J20: =((H20/C20)^(1/COUNT(D20:H20))-1) -> #DIV/0! | L20: =SUM(L17:L19)+L15 -> #DIV/0! | M20: =SUM(M17:M19)+M15 -> #DIV/0! | N20: =SUM(N17:N19)+N15 -> #DIV/0! | O20: =SUM(O17:O19)+O15 -> #DIV/0! | P20: =SUM(P17:P19)+P15 -> #DIV/0! | Q20: =SUM(Q17:Q19)+Q15 -> #DIV/0! | S20: =((Q20/L20)^(1/COUNT(M20:Q20))-1) -> #DIV/0!
B22: Taxes | J22: =((H22/C22)^(1/COUNT(D22:H22))-1) -> #DIV/0! | L22: =+(H22*L171)+H22 -> 0 | M22: =+(L22*M171)+L22 -> 0 | N22: =+(M22*N171)+M22 -> 0 | O22: =+(N22*O171)+N22 -> 0 | P22: =+(O22*P171)+O22 -> 0 | Q22: =+(P22*Q171)+P22 -> 0 | S22: =((Q22/L22)^(1/COUNT(M22:Q22))-1) -> #DIV/0!
B23: Net income | C23: =+C20+C22 -> 0 | D23: =+D20+D22 -> 0 | E23: =+E20+E22 -> 0 | F23: =+F20+F22 -> 0 | G23: =+G20+G22 -> 0 | H23: =+H20+H22 -> 0 | J23: =((H23/C23)^(1/COUNT(D23:H23))-1) -> #DIV/0! | L23: =+L20+L22 -> #DIV/0! | M23: =+M20+M22 -> #DIV/0! | N23: =+N20+N22 -> #DIV/0! | O23: =+O20+O22 -> #DIV/0! | P23: =+P20+P22 -> #DIV/0! | Q23: =+Q20+Q22 -> #DIV/0! | S23: =((Q23/L23)^(1/COUNT(M23:Q23))-1) -> #DIV/0!
B25: Depreciation & Amortization | J25: =((H25/C25)^(1/COUNT(D25:H25))-1) -> #DIV/0! | L25: =+(H25*L186)+H25 -> #DIV/0! | M25: =+(L25*M186)+L25 -> #DIV/0! | N25: =+(M25*N186)+M25 -> #DIV/0! | O25: =+(N25*O186)+N25 -> #DIV/0! | P25: =+(O25*P186)+O25 -> #DIV/0! | Q25: =+(P25*Q186)+P25 -> #DIV/0! | S25: =((Q25/L25)^(1/COUNT(M25:Q25))-1) -> #DIV/0!
B26: EBITDA | C26: =+C15+C25 -> 0 | D26: =+D15+D25 -> 0 | E26: =+E15+E25 -> 0 | F26: =+F15+F25 -> 0 | G26: =+G15+G25 -> 0 | H26: =+H15+H25 -> 0 | J26: =((H26/C26)^(1/COUNT(D26:H26))-1) -> #DIV/0! | L26: =+L15+L25 -> #DIV/0! | M26: =+M15+M25 -> #DIV/0! | N26: =+N15+N25 -> #DIV/0! | O26: =+O15+O25 -> #DIV/0! | P26: =+P15+P25 -> #DIV/0! | Q26: =+Q15+Q25 -> #DIV/0! | S26: =((Q26/L26)^(1/COUNT(M26:Q26))-1) -> #DIV/0!
B28: Stock Based Compensation | J28: =((H28/C28)^(1/COUNT(D28:H28))-1) -> #DIV/0! | L28: =+(H28*L197)+H28 -> #DIV/0! | M28: =+(L28*M197)+L28 -> #DIV/0! | N28: =+(M28*N197)+M28 -> #DIV/0! | O28: =+(N28*O197)+N28 -> #DIV/0! | P28: =+(O28*P197)+O28 -> #DIV/0! | Q28: =+(P28*Q197)+P28 -> #DIV/0! | S28: =((Q28/L28)^(1/COUNT(M28:Q28))-1) -> #DIV/0!
B29: Adj. EBITDA | C29: =+C26+C28 -> 0 | D29: =+D26+D28 -> 0 | E29: =+E26+E28 -> 0 | F29: =+F26+F28 -> 0 | G29: =+G26+G28 -> 0 | H29: =+H26+H28 -> 0 | J29: =((H29/C29)^(1/COUNT(D29:H29))-1) -> #DIV/0! | L29: =+L26+L28 -> #DIV/0! | M29: =+M26+M28 -> #DIV/0! | N29: =+N26+N28 -> #DIV/0! | O29: =+O26+O28 -> #DIV/0! | P29: =+P26+P28 -> #DIV/0! | Q29: =+Q26+Q28 -> #DIV/0! | S29: =((Q29/L29)^(1/COUNT(M29:Q29))-1) -> #DIV/0!
B32: Revenue Drivers | J32: Consensus
A34: X | B34: iPhone Revenue | D34: =SUM(D6/C6)-1 -> #DIV/0! | E34: =SUM(E6/D6)-1 -> #DIV/0! | F34: =SUM(F6/E6)-1 -> #DIV/0! | G34: =SUM(G6/F6)-1 -> #DIV/0! | H34: =SUM(H6/G6)-1 -> #DIV/0! | J34: Total Revenue
B35: (%) of Total Revenue | C35: =C6/C$8 -> #DIV/0! | D35: =D6/D$8 -> #DIV/0! | E35: =E6/E$8 -> #DIV/0! | F35: =F6/F$8 -> #DIV/0! | G35: =G6/G$8 -> #DIV/0! | H35: =H6/H$8 -> #DIV/0! | J35: BofA | L35: =+L52+L65+L91+L104+L78 -> 416040.4 | M35: =+M52+M65+M91+M104+M78 -> 447778.31 | N35: =+N52+N65+N91+N104+N78 -> 482123.51 | O35: =+O52+O65+O91+O104+O78 -> 482123.51 | P35: =+P52+P65+P91+P104+P78 -> 482123.51 | Q35: =+Q52+Q65+Q91+Q104+Q78 -> 482123.51
B36: iPad Revenue | D36: =SUM(D7/C7)-1 -> #DIV/0! | E36: =SUM(E7/D7)-1 -> #DIV/0! | F36: =SUM(F7/E7)-1 -> #DIV/0! | G36: =SUM(G7/F7)-1 -> #DIV/0! | H36: =SUM(H7/G7)-1 -> #DIV/0! | J36: Y/Y Growth (%) | L36: =SUM(L35/$H$8)-1 -> #DIV/0! | M36: =SUM(M35/L35)-1 -> 0.076285632 | N36: =SUM(N35/M35)-1 -> 0.076701364 | O36: =N36 -> 0.076701364 | P36: =O36 -> 0.076701364 | Q36: =P36 -> 0.076701364
B37: (%) of Total Revenue | C37: =C7/C$8 -> #DIV/0! | D37: =D7/D$8 -> #DIV/0! | E37: =E7/E$8 -> #DIV/0! | F37: =F7/F$8 -> #DIV/0! | G37: =G7/G$8 -> #DIV/0! | H37: =H7/H$8 -> #DIV/0! | J37: JP Morgan | L37: =+L54+L67+L93+L106+L80 -> 416621 | M37: =+M54+M67+M93+M106+M80 -> 445334 | N37: =+N54+N67+N93+N106+N80 -> 489169 | O37: =+O54+O67+O93+O106+O80 -> 500680 | P37: =+P54+P67+P93+P106+P80 -> 500680 | Q37: =+Q54+Q67+Q93+Q106+Q80 -> 500680
B38: Mac Revenue | D38: =SUM(#REF!/#REF!)-1 -> #REF! | E38: =SUM(#REF!/#REF!)-1 -> #REF! | F38: =SUM(#REF!/#REF!)-1 -> #REF! | G38: =SUM(#REF!/#REF!)-1 -> #REF! | H38: =SUM(#REF!/#REF!)-1 -> #REF! | J38: Y/Y Growth (%) | L38: =SUM(L37/$H$8)-1 -> #DIV/0! | M38: =SUM(M37/L37)-1 -> 0.068918753 | N38: =SUM(N37/M37)-1 -> 0.098431739 | O38: =SUM(O37/N37)-1 -> 0.023531745 | P38: =O38 -> 0.023531745 | Q38: =P38 -> 0.023531745
J39: Barclays | L39: 414847 | M39: 438656 | N39: 465270 | O39: =N39 -> 465270 | P39: =O39 -> 465270 | Q39: =P39 -> 465270
J40: Y/Y Growth (%) | L40: =SUM(L39/$H$8)-1 -> #DIV/0! | M40: =SUM(M39/L39)-1 -> 0.057392243 | N40: =SUM(N39/M39)-1 -> 0.060671688 | O40: =N40 -> 0.060671688 | P40: =O40 -> 0.060671688 | Q40: =P40 -> 0.060671688
J41: Jefferies | L41: 410074 | M41: 425207 | N41: 464555 | O41: 478922 | P41: 535341 | Q41: 569147
J42: Y/Y Growth (%) | L42: =SUM(L41/$H$8)-1 -> #DIV/0! | M42: =SUM(M41/L41)-1 -> 0.036903096 | N42: =SUM(N41/M41)-1 -> 0.092538458 | O42: =SUM(O41/N41)-1 -> 0.03092637 | P42: =SUM(P41/O41)-1 -> 0.11780415 | Q42: =SUM(Q41/P41)-1 -> 0.063148535
B43: (%) of Total Revenue | C43: =#REF!/C$8 -> #REF! | D43: =#REF!/D$8 -> #REF! | E43: =#REF!/E$8 -> #REF! | F43: =#REF!/F$8 -> #REF! | G43: =#REF!/G$8 -> #REF! | H43: =#REF!/H$8 -> #REF! | J43: Morgan Stanley | L43: =+L56+L69+L95+L108+L82 -> 414913 | M43: =+M56+M69+M95+M108+M82 -> 441848 | N43: =+N56+N69+N95+N108+N82 -> 468930 | O43: =+O56+O69+O95+O108+O82 -> 468930 | P43: =+P56+P69+P95+P108+P82 -> 468930 | Q43: =+Q56+Q69+Q95+Q108+Q82 -> 468930
B44: Wearables, Home, and Accessories Revenue | D44: =SUM(#REF!/#REF!)-1 -> #REF! | E44: =SUM(#REF!/#REF!)-1 -> #REF! | F44: =SUM(#REF!/#REF!)-1 -> #REF! | G44: =SUM(#REF!/#REF!)-1 -> #REF! | H44: =SUM(#REF!/#REF!)-1 -> #REF! | J44: Y/Y Growth (%) | L44: =SUM(L43/$H$8)-1 -> #DIV/0! | M44: =SUM(M43/L43)-1 -> 0.064917224 | N44: =SUM(N43/M43)-1 -> 0.061292571 | O44: =N44 -> 0.061292571 | P44: =O44 -> 0.061292571 | Q44: =P44 -> 0.061292571
B45: (%) of Total Revenue | C45: =#REF!/C$8 -> #REF! | D45: =#REF!/D$8 -> #REF! | E45: =#REF!/E$8 -> #REF! | F45: =#REF!/F$8 -> #REF! | G45: =#REF!/G$8 -> #REF! | H45: =#REF!/H$8 -> #REF! | J45: Wells Fargo | L45: =+L58+L71+L97+L110+L84 -> 415305 | M45: =+M58+M71+M97+M110+M84 -> 440525 | N45: =+N58+N71+N97+N110+N84 -> 460577 | O45: =+O58+O71+O97+O110+O84 -> 460577 | P45: =+P58+P71+P97+P110+P84 -> 460577 | Q45: =+Q58+Q71+Q97+Q110+Q84 -> 460577
B46: Services Revenue | D46: =SUM(#REF!/#REF!)-1 -> #REF! | E46: =SUM(#REF!/#REF!)-1 -> #REF! | F46: =SUM(#REF!/#REF!)-1 -> #REF! | G46: =SUM(#REF!/#REF!)-1 -> #REF! | H46: =SUM(#REF!/#REF!)-1 -> #REF! | J46: Y/Y Growth (%) | L46: =SUM(L45/$H$8)-1 -> #DIV/0! | M46: =SUM(M45/L45)-1 -> 0.060726454 | N46: =SUM(N45/M45)-1 -> 0.045518416 | O46: =N46 -> 0.045518416 | P46: =O46 -> 0.045518416 | Q46: =P46 -> 0.045518416
B47: (%) of Total Revenue | C47: =#REF!/C$8 -> #REF! | D47: =#REF!/D$8 -> #REF! | E47: =#REF!/E$8 -> #REF! | F47: =#REF!/F$8 -> #REF! | G47: =#REF!/G$8 -> #REF! | H47: =#REF!/H$8 -> #REF!
J48: Median (%) | L48: =MEDIAN(L$46,L$36,L$44,L$38,L$42,L$40) -> #DIV/0! | M48: =MEDIAN(M$46,M$36,M$44,M$38,M$42,M$40) -> 0.062821839 | N48: =MEDIAN(N$46,N$36,N$44,N$38,N$42,N$40) -> 0.068996967 | O48: =MEDIAN(O$46,O$36,O$44,O$38,O$42,O$40) -> 0.053095052 | P48: =MEDIAN(P$46,P$36,P$44,P$38,P$42,P$40) -> 0.06098213 | Q48: =MEDIAN(Q$46,Q$36,Q$44,Q$38,Q$42,Q$40) -> 0.06098213
J49: Average (%) | L49: =AVERAGE(L$46,L$36,L$44,L$38,L$42,L$40) -> #DIV/0! | M49: =AVERAGE(M$46,M$36,M$44,M$38,M$42,M$40) -> 0.060857234 | N49: =AVERAGE(N$46,N$36,N$44,N$38,N$42,N$40) -> 0.072525706 | O49: =AVERAGE(O$46,O$36,O$44,O$38,O$42,O$40) -> 0.049773692 | P49: =AVERAGE(P$46,P$36,P$44,P$38,P$42,P$40) -> 0.064253322 | Q49: =AVERAGE(Q$46,Q$36,Q$44,Q$38,Q$42,Q$40) -> 0.055144053
A51: X | B51: Revenue: iPhone Revenue | J51: Revenue: iPhone Revenue
J52: BofA | L52: 210271 | M52: 224197.5 | N52: 237444 | O52: =N52 -> 237444 | P52: =O52 -> 237444 | Q52: =P52 -> 237444
J53: Y/Y Growth (%) | L53: =SUM(L52/$H$6)-1 -> #DIV/0! | M53: =SUM(M52/L52)-1 -> 0.066231197 | N53: =SUM(N52/M52)-1 -> 0.059084067 | O53: =N53 -> 0.059084067 | P53: =O53 -> 0.059084067 | Q53: =P53 -> 0.059084067
J54: JP Morgan | L54: 210893 | M54: 223122 | N54: 249550 | O54: 240721 | P54: =O54 -> 240721 | Q54: =P54 -> 240721
J55: Y/Y Growth (%) | L55: =SUM(L54/$H$6)-1 -> #DIV/0! | M55: =SUM(M54/L54)-1 -> 0.057986752 | N55: =SUM(N54/M54)-1 -> 0.11844641 | O55: =SUM(O54/N54)-1 -> -0.035379683 | P55: =SUM(P54/O54)-1 -> 0 | Q55: =SUM(Q54/P54)-1 -> 0
J56: Morgan Stanley | L56: 209597 | M56: 221070 | N56: 233080 | O56: =N56 -> 233080 | P56: =O56 -> 233080 | Q56: =P56 -> 233080
J57: Y/Y Growth (%) | L57: =SUM(L56/$H$6)-1 -> #DIV/0! | M57: =SUM(M56/L56)-1 -> 0.054738379 | N57: =SUM(N56/M56)-1 -> 0.054326684 | O57: =N57 -> 0.054326684 | P57: =O57 -> 0.054326684 | Q57: =P57 -> 0.054326684
J58: Wells Fargo | L58: 209723 | M58: 221039 | N58: 226650 | O58: =N58 -> 226650 | P58: =O58 -> 226650 | Q58: =P58 -> 226650
J59: Y/Y Growth (%) | L59: =SUM(L58/$H$6)-1 -> #DIV/0! | M59: =SUM(M58/L58)-1 -> 0.053956886 | N59: =SUM(N58/M58)-1 -> 0.025384661 | O59: =N59 -> 0.025384661 | P59: =O59 -> 0.025384661 | Q59: =P59 -> 0.025384661
J61: Median (%) | L61: =MEDIAN(L$59,L$53,L$57,L$55) -> #DIV/0! | M61: =MEDIAN(M$59,M$53,M$57,M$55) -> 0.056362565 | N61: =MEDIAN(N$59,N$53,N$57,N$55) -> 0.056705375 | O61: =MEDIAN(O$59,O$53,O$57,O$55) -> 0.039855672 | P61: =MEDIAN(P$59,P$53,P$57,P$55) -> 0.039855672 | Q61: =MEDIAN(Q$59,Q$53,Q$57,Q$55) -> 0.039855672
J62: Average (%) | L62: =AVERAGE(L$59,L$53,L$57,L$55) -> #DIV/0! | M62: =AVERAGE(M$59,M$53,M$57,M$55) -> 0.058228303 | N62: =AVERAGE(N$59,N$53,N$57,N$55) -> 0.064310455 | O62: =AVERAGE(O$59,O$53,O$57,O$55) -> 0.025853932 | P62: =AVERAGE(P$59,P$53,P$57,P$55) -> 0.034698853 | Q62: =AVERAGE(Q$59,Q$53,Q$57,Q$55) -> 0.034698853
A64: X | B64: Revenue: iPad Revenue | J64: Revenue: iPad Revenue
J65: BofA | L65: 28208.285 | M65: 29955.43 | N65: 32016.946 | O65: =N65 -> 32016.946 | P65: =O65 -> 32016.946 | Q65: =P65 -> 32016.946
J66: Y/Y Growth (%) | L66: =SUM(L65/$H$7)-1 -> #DIV/0! | M66: =SUM(M65/L65)-1 -> 0.061937309 | N66: =SUM(N65/M65)-1 -> 0.068819444 | O66: =N66 -> 0.068819444 | P66: =O66 -> 0.068819444 | Q66: =P66 -> 0.068819444
J67: JP Morgan | L67: 28399 | M67: 29159 | N67: 30040 | O67: 31253 | P67: =O67 -> 31253 | Q67: =P67 -> 31253
J68: Y/Y Growth (%) | L68: =SUM(L67/$H$7)-1 -> #DIV/0! | M68: =SUM(M67/L67)-1 -> 0.026761506 | N68: =SUM(N67/M67)-1 -> 0.030213656 | O68: =SUM(O67/N67)-1 -> 0.040379494 | P68: =O68 -> 0.040379494 | Q68: =P68 -> 0.040379494
J69: Morgan Stanley | L69: 27523 | M69: 28295 | N69: 28599 | O69: =N69 -> 28599 | P69: =O69 -> 28599 | Q69: =P69 -> 28599
J70: Y/Y Growth (%) | L70: =SUM(L69/$H$7)-1 -> #DIV/0! | M70: =SUM(M69/L69)-1 -> 0.028049268 | N70: =SUM(N69/M69)-1 -> 0.010743948 | O70: =N70 -> 0.010743948 | P70: =O70 -> 0.010743948 | Q70: =P70 -> 0.010743948
J71: Wells Fargo | L71: 27567 | M71: 25036 | N71: 24466 | O71: =N71 -> 24466 | P71: =O71 -> 24466 | Q71: =P71 -> 24466
J72: Y/Y Growth (%) | L72: =SUM(L71/$H$7)-1 -> #DIV/0! | M72: =SUM(M71/L71)-1 -> -0.091812675 | N72: =SUM(N71/M71)-1 -> -0.022767215 | O72: 0 | P72: =O72 -> 0 | Q72: =P72 -> 0
J74: Median (%) | L74: =MEDIAN(L$72,L$66,L$70,L$68) -> #DIV/0! | M74: =MEDIAN(M$72,M$66,M$70,M$68) -> 0.027405387 | N74: =MEDIAN(N$72,N$66,N$70,N$68) -> 0.020478802 | O74: =MEDIAN(O$72,O$66,O$70,O$68) -> 0.025561721 | P74: =MEDIAN(P$72,P$66,P$70,P$68) -> 0.025561721 | Q74: =MEDIAN(Q$72,Q$66,Q$70,Q$68) -> 0.025561721
J75: Average (%) | L75: =AVERAGE(L$72,L$66,L$70,L$68) -> #DIV/0! | M75: =AVERAGE(M$72,M$66,M$70,M$68) -> 0.0062338519 | N75: =AVERAGE(N$72,N$66,N$70,N$68) -> 0.021752458 | O75: =AVERAGE(O$72,O$66,O$70,O$68) -> 0.029985721 | P75: =AVERAGE(P$72,P$66,P$70,P$68) -> 0.029985721 | Q75: =AVERAGE(Q$72,Q$66,Q$70,Q$68) -> 0.029985721
A77: X | B77: Revenue: Mac Revenue | J77: Revenue: Mac Revenue
J78: BofA | L78: 33477.452 | M78: 34521.796 | N78: 35879.893 | O78: =N78 -> 35879.893 | P78: =O78 -> 35879.893 | Q78: =P78 -> 35879.893
J79: Y/Y Growth (%) | L79: =SUM(L78/#REF!)-1 -> #REF! | M79: =SUM(M78/L78)-1 -> 0.031195439 | N79: =SUM(N78/M78)-1 -> 0.03934027 | O79: =N79 -> 0.03934027 | P79: =O79 -> 0.03934027 | Q79: =P79 -> 0.03934027
J80: JP Morgan | L80: 33189 | M80: 34188 | N80: 35395 | O80: 37003 | P80: =O80 -> 37003 | Q80: =P80 -> 37003
J81: Y/Y Growth (%) | L81: =SUM(L80/#REF!)-1 -> #REF! | M81: =SUM(M80/L80)-1 -> 0.030100334 | N81: =SUM(N80/M80)-1 -> 0.035304785 | O81: =SUM(O80/N80)-1 -> 0.045430146 | P81: =O81 -> 0.045430146 | Q81: =P81 -> 0.045430146
J82: Morgan Stanley | L82: 34302 | M82: 34888 | N82: 35155 | O82: =N82 -> 35155 | P82: =O82 -> 35155 | Q82: =P82 -> 35155
J83: Y/Y Growth (%) | L83: =SUM(L82/#REF!)-1 -> #REF! | M83: =SUM(M82/L82)-1 -> 0.017083552 | N83: =SUM(N82/M82)-1 -> 0.0076530612 | O83: =N83 -> 0.0076530612 | P83: =O83 -> 0.0076530612 | Q83: =P83 -> 0.0076530612
J84: Wells Fargo | L84: 34644 | M84: 37934 | N84: 40252 | O84: =N84 -> 40252 | P84: =O84 -> 40252 | Q84: =P84 -> 40252
J85: Y/Y Growth (%) | L85: =SUM(L84/#REF!)-1 -> #REF! | M85: =SUM(M84/L84)-1 -> 0.094965939 | N85: =SUM(N84/M84)-1 -> 0.061106132 | O85: =N85 -> 0.061106132 | P85: =O85 -> 0.061106132 | Q85: =P85 -> 0.061106132
J87: Median (%) | L87: =MEDIAN(L$85,L$79,L$83,L$81) -> #REF! | M87: =MEDIAN(M$85,M$79,M$83,M$81) -> 0.030647887 | N87: =MEDIAN(N$85,N$79,N$83,N$81) -> 0.037322528 | O87: =MEDIAN(O$85,O$79,O$83,O$81) -> 0.042385208 | P87: =MEDIAN(P$85,P$79,P$83,P$81) -> 0.042385208 | Q87: =MEDIAN(Q$85,Q$79,Q$83,Q$81) -> 0.042385208
J88: Average (%) | L88: =AVERAGE(L$85,L$79,L$83,L$81) -> #REF! | M88: =AVERAGE(M$85,M$79,M$83,M$81) -> 0.043336316 | N88: =AVERAGE(N$85,N$79,N$83,N$81) -> 0.035851062 | O88: =AVERAGE(O$85,O$79,O$83,O$81) -> 0.038382402 | P88: =AVERAGE(P$85,P$79,P$83,P$81) -> 0.038382402 | Q88: =AVERAGE(Q$85,Q$79,Q$83,Q$81) -> 0.038382402
A90: X | B90: Revenue: Wearables, Home and Accessories Revenue | J90: Revenue: Wearables, Home and Accessories Revenue
J91: BofA | L91: 35207.584 | M91: 37162.37 | N91: 39913.511 | O91: =N91 -> 39913.511 | P91: =O91 -> 39913.511 | Q91: =P91 -> 39913.511
J92: Y/Y Growth (%) | L92: =SUM(L91/#REF!)-1 -> #REF! | M92: =SUM(M91/L91)-1 -> 0.055521733 | N92: =SUM(N91/M91)-1 -> 0.07403028 | O92: =N92 -> 0.07403028 | P92: =O92 -> 0.07403028 | Q92: =P92 -> 0.07403028
J93: JP Morgan | L93: 35441 | M93: 36050 | N93: 36689 | O93: 38120 | P93: =O93 -> 38120 | Q93: =P93 -> 38120
J94: Y/Y Growth (%) | L94: =SUM(L93/#REF!)-1 -> #REF! | M94: =SUM(M93/L93)-1 -> 0.017183488 | N94: =SUM(N93/M93)-1 -> 0.017725381 | O94: =SUM(O93/N93)-1 -> 0.039003516 | P94: =O94 -> 0.039003516 | Q94: =P94 -> 0.039003516
J95: Morgan Stanley | L95: 34801 | M95: 35867 | N95: 37348 | O95: =N95 -> 37348 | P95: =O95 -> 37348 | Q95: =P95 -> 37348
J96: Y/Y Growth (%) | L96: =SUM(L95/#REF!)-1 -> #REF! | M96: =SUM(M95/L95)-1 -> 0.030631304 | N96: =SUM(N95/M95)-1 -> 0.041291438 | O96: =N96 -> 0.041291438 | P96: =O96 -> 0.041291438 | Q96: =P96 -> 0.041291438
J97: Wells Fargo | L97: 34854 | M97: 37710 | N97: 41279 | O97: =N97 -> 41279 | P97: =O97 -> 41279 | Q97: =P97 -> 41279
J98: Y/Y Growth (%) | L98: =SUM(L97/#REF!)-1 -> #REF! | M98: =SUM(M97/L97)-1 -> 0.081941814 | N98: =SUM(N97/M97)-1 -> 0.094643331 | O98: =N98 -> 0.094643331 | P98: =O98 -> 0.094643331 | Q98: =P98 -> 0.094643331
J100: Median (%) | L100: =MEDIAN(L$98,L$92,L$96,L$94) -> #REF! | M100: =MEDIAN(M$98,M$92,M$96,M$94) -> 0.043076518 | N100: =MEDIAN(N$98,N$92,N$96,N$94) -> 0.057660859 | O100: =MEDIAN(O$98,O$92,O$96,O$94) -> 0.057660859 | P100: =MEDIAN(P$98,P$92,P$96,P$94) -> 0.057660859 | Q100: =MEDIAN(Q$98,Q$92,Q$96,Q$94) -> 0.057660859
J101: Average (%) | L101: =AVERAGE(L$98,L$92,L$96,L$94) -> #REF! | M101: =AVERAGE(M$98,M$92,M$96,M$94) -> 0.046319585 | N101: =AVERAGE(N$98,N$92,N$96,N$94) -> 0.056922608 | O101: =AVERAGE(O$98,O$92,O$96,O$94) -> 0.062242141 | P101: =AVERAGE(P$98,P$92,P$96,P$94) -> 0.062242141 | Q101: =AVERAGE(Q$98,Q$92,Q$96,Q$94) -> 0.062242141
A103: X | B103: Revenue: Services Revenue | J103: Revenue: Services Revenue
J104: BofA | L104: 108876.08 | M104: 121941.21 | N104: 136869.16 | O104: =N104 -> 136869.16 | P104: =O104 -> 136869.16 | Q104: =P104 -> 136869.16
J105: Y/Y Growth (%) | L105: =SUM(L104/#REF!)-1 -> #REF! | M105: =SUM(M104/L104)-1 -> 0.12 | N105: =SUM(N104/M104)-1 -> 0.12241926 | O105: =N105 -> 0.12241926 | P105: =O105 -> 0.12241926 | Q105: =P105 -> 0.12241926
J106: JP Morgan | L106: 108699 | M106: 122815 | N106: 137495 | O106: 153583 | P106: =O106 -> 153583 | Q106: =P106 -> 153583
J107: Y/Y Growth (%) | L107: =SUM(L106/#REF!)-1 -> #REF! | M107: =SUM(M106/L106)-1 -> 0.1298632 | N107: =SUM(N106/M106)-1 -> 0.11952937 | O107: =SUM(O106/N106)-1 -> 0.11700789 | P107: =O107 -> 0.11700789 | Q107: =P107 -> 0.11700789
J108: Morgan Stanley | L108: 108690 | M108: 121728 | N108: 134748 | O108: =N108 -> 134748 | P108: =O108 -> 134748 | Q108: =P108 -> 134748
J109: Y/Y Growth (%) | L109: =SUM(L108/#REF!)-1 -> #REF! | M109: =SUM(M108/L108)-1 -> 0.11995584 | N109: =SUM(N108/M108)-1 -> 0.10695978 | O109: =N109 -> 0.10695978 | P109: =O109 -> 0.10695978 | Q109: =P109 -> 0.10695978
J110: Wells Fargo | L110: 108517 | M110: 118806 | N110: 127930 | O110: =N110 -> 127930 | P110: =O110 -> 127930 | Q110: =P110 -> 127930
J111: Y/Y Growth (%) | L111: =SUM(L110/#REF!)-1 -> #REF! | M111: =SUM(M110/L110)-1 -> 0.094814637 | N111: =SUM(N110/M110)-1 -> 0.076797468 | O111: =N111 -> 0.076797468 | P111: =O111 -> 0.076797468 | Q111: =P111 -> 0.076797468
J113: Median (%) | L113: =MEDIAN(L$111,L$105,L$109,L$107) -> #REF! | M113: =MEDIAN(M$111,M$105,M$109,M$107) -> 0.11997792 | N113: =MEDIAN(N$111,N$105,N$109,N$107) -> 0.11324458 | O113: =MEDIAN(O$111,O$105,O$109,O$107) -> 0.11198384 | P113: =MEDIAN(P$111,P$105,P$109,P$107) -> 0.11198384 | Q113: =MEDIAN(Q$111,Q$105,Q$109,Q$107) -> 0.11198384
J114: Average (%) | L114: =AVERAGE(L$111,L$105,L$109,L$107) -> #REF! | M114: =AVERAGE(M$111,M$105,M$109,M$107) -> 0.11615842 | N114: =AVERAGE(N$111,N$105,N$109,N$107) -> 0.10642647 | O114: =AVERAGE(O$111,O$105,O$109,O$107) -> 0.1057961 | P114: =AVERAGE(P$111,P$105,P$109,P$107) -> 0.1057961 | Q114: =AVERAGE(Q$111,Q$105,Q$109,Q$107) -> 0.1057961
J116: Operating Drivers
A118: X | B118: Gross Profit | J118: Gross Profit
J119: BofA | L119: 197662.79 | M119: 213719.63 | N119: 230225.59 | O119: 243949.19 | P119: 260139.85 | Q119: 279241.89
J120: Margin (%) | L120: =L119/L35 -> 0.47510481 | M120: =M119/M35 -> 0.47728892 | N120: =N119/N35 -> 0.47752408 | O120: =O119/O35 -> 0.505989 | P120: =P119/P35 -> 0.53957096 | Q120: =Q119/Q35 -> 0.5791916
J121: JP Morgan | L121: =L122*L37 -> 194562.01 | M121: =M122*M37 -> 209752.31 | N121: =N122*N37 -> 232844.44 | O121: =O122*O37 -> 241327.76 | P121: =O121 -> 241327.76 | Q121: =P121 -> 241327.76
J122: Margin (%) | L122: 0.467 | M122: 0.471 | N122: 0.476 | O122: 0.482 | P122: =O122 -> 0.482 | Q122: =P122 -> 0.482
J123: Jefferies | L123: 191480 | M123: 205455 | N123: 224639 | O123: 235586 | P123: 265911 | Q123: 288739
...

Sheet WACC
B2: ='3-Statement Model'!C6&"(NASDAQ: AAPL)" -> Beyond Meat, Inc.(NASDAQ: AAPL)
B3: WACC Buildup
B4: $ and shares in millions, except per share data
B6: Cost of capital assumptions | E6: Source
B8: Cost of debt | C8: 0.022 | E8: Bloomberg - YTM on 2.2% 9/29 Bond
B9: Tax rate | C9: ='[1]Simple DCF Done'!I22 -> 0.173 | E9: From terminal year of UFCF forecast
B10: Cost of debt (after tax) | C10: =C8*(1-C9) -> 0.018194 | E10: Cost of debt x (1 - tax rate)
B12: Risk free rate | C12: 0.03979 | E12: WSJ: 10 Year US Treasury Yield
B13: Beta | C13: =IF(C34="Observed",C36,C37) -> 1.099 | E13: Bloomberg 2 year weekly adjusted beta
B14: Market risk premium | C14: 0.05 | E14: Market risk premium from D&P May 1, 2019
B15: Cost of equity | C15: =C12+C13*C14 -> 0.09474 | E15: RfR + Beta x MRP
B17: Capital weights (capital structure)
D18: Target
C19: Current | D19: (override) | E19: % of total
B20: Equity | C20: ='[1]Simple DCF Done'!H5*'[1]Simple DCF Done'!I61 -> 1223044.7 | E20: =IF(D20,D20,C20/(C20+C21)) -> 0.49297003
B21: Debt | C21: =DCF!C61 -> 1257927 | D21: =1-D20 -> 1 | E21: =1-E20 -> 0.50702997
B23: Cost of capital (WACC) | E23: =C10*E21+C15*E20 -> 0.055928884
B25: WACC sensitivity to MRP and Beta
D26: Beta
C27: =E23 -> 0.055928884 | D27: =E27-0.1 -> 0.999 | E27: 1.099 | F27: =E27+0.1 -> 1.199
C28: =C29-0.005 -> 0.045 | D28: 0.061013495 | E28: 0.065908826 | F28: 0.070804156
B29: Market | C29: =C30-0.005 -> 0.05 | D29: 0.066447312 | E29: 0.071886568 | F29: 0.077325824
B30: Risk | C30: 0.055 | D30: 0.071881129 | E30: 0.077864311 | F30: 0.083847492
B31: Premium | C31: =C30+0.005 -> 0.06 | D31: 0.077314946 | E31: 0.083842053 | F31: 0.090369161
