Workbook

Sheet Historical Financials
B2: Build-A-Bear Workshop, Inc (NYSE: BBW)
B3: Historical Financials
B4: ($ In Millions, except EPS)
A6: X | B6: Income Statement | C6: FYE | G6: Quarterly | M6: Quarterly | X6: LTM | AD6: Variance
B7: Fiscal Period | C7: 2022 | D7: 2023 | E7: 2024 | G7: 1Q23 | H7: 2Q23 | I7: 3Q23 | J7: 4Q23 | K7: 1Q24 | L7: 2Q24 | M7: 3Q24 | N7: 4Q24 | O7: 1Q25 | P7: 2Q25 | Q7: 3Q25 | S7: =J7 -> 4Q23 | T7: =K7 -> 1Q24 | U7: =L7 -> 2Q24 | V7: =M7 -> 3Q24 | W7: =N7 -> 4Q24 | X7: =O7 -> 1Q25 | Y7: =P7 -> 2Q25 | Z7: =Q7 -> 3Q25 | AA7: =#REF! -> #REF! | AB7: =#REF! -> #REF!
B8: Fiscal Period End Date | C8: 44954 | D8: 45325 | E8: 45689 | G8: 45045 | H8: 45136 | I8: 45227 | J8: =D8 -> 45325 | K8: 45416 | L8: 45507 | M8: 45598 | N8: =E8 -> 45689 | O8: 45780 | P8: 45871 | Q8: 45962 | S8: =J8 -> 45325 | T8: =K8 -> 45416 | U8: =L8 -> 45507 | V8: =M8 -> 45598 | W8: =N8 -> 45689 | X8: =O8 -> 45780 | Y8: =P8 -> 45871 | Z8: =Q8 -> 45962 | AA8: =#REF! -> #REF! | AB8: =#REF! -> #REF!
B10: Consolidated Revenue | C10: 467937 | D10: 486114 | E10: 496404 | G10: 120050 | J10: =SUM(D10-SUM(G10:I10)) -> 366064 | K10: 114730 | N10: =SUM(E10-SUM(K10:M10)) -> 381674 | S10: =SUM(G10:J10) -> 486114 | T10: =SUM(H10:K10) -> 480794 | U10: =SUM(I10:L10) -> 480794 | V10: =SUM(J10:M10) -> 480794 | W10: =SUM(K10:N10) -> 496404 | X10: =SUM(L10:O10) -> 381674 | Y10: =SUM(M10:P10) -> 381674 | Z10: =SUM(N10:Q10) -> 381674 | AA10: =SUM(O10:Q10) -> 0 | AB10: =SUM(P10:Q10) -> 0 | AD10: =SUM(AB10/X10)-1 -> -1
B11: Total Revenue | C11: =+SUM(C10:C10) -> 467937 | D11: =+SUM(D10:D10) -> 486114 | E11: =+SUM(E10:E10) -> 496404 | G11: =+SUM(G10:G10) -> 120050 | H11: =+SUM(H10:H10) -> 0 | I11: =+SUM(I10:I10) -> 0 | J11: =+SUM(J10:J10) -> 366064 | K11: =+SUM(K10:K10) -> 114730 | L11: =+SUM(L10:L10) -> 0 | M11: =+SUM(M10:M10) -> 0 | N11: =+SUM(N10:N10) -> 381674 | ... Q11: =+SUM(Q10:Q10) -> 0 | S11: =+SUM(S10:S10) -> 486114 | T11: =+SUM(T10:T10) -> 480794 | U11: =+SUM(U10:U10) -> 480794 | V11: =+SUM(V10:V10) -> 480794 | W11: =+SUM(W10:W10) -> 496404 | X11: =+SUM(X10:X10) -> 381674 | Y11: =+SUM(Y10:Y10) -> 381674 | Z11: =+SUM(Z10:Z10) -> 381674 | ... AB11: =+SUM(AB10:AB10) -> 0 | AD11: =SUM(AB11/X11)-1 -> -1
B13: Cost of merchandise sold - retail | C13: -211489 | D13: -206815 | E13: -207200 | G13: -50904 | J13: =SUM(D13-SUM(G13:I13)) -> -155911 | K13: -49415 | N13: =SUM(E13-SUM(K13:M13)) -> -157785 | S13: =SUM(G13:J13) -> -206815 | T13: =SUM(H13:K13) -> -205326 | U13: =SUM(I13:L13) -> -205326 | V13: =SUM(J13:M13) -> -205326 | W13: =SUM(K13:N13) -> -207200 | X13: =SUM(L13:O13) -> -157785 | Y13: =SUM(M13:P13) -> -157785 | Z13: =SUM(N13:Q13) -> -157785 | AA13: =SUM(O13:Q13) -> 0 | AB13: =SUM(P13:Q13) -> 0 | AD13: =SUM(AB13/X13)-1 -> -1
B14: Cost of merchandise sold - commercial | C14: -8591 | D14: -12091 | E14: -13439 | G14: -3358 | J14: =SUM(D14-SUM(G14:I14)) -> -8733 | K14: -2533 | N14: =SUM(E14-SUM(K14:M14)) -> -10906 | S14: =SUM(G14:J14) -> -12091 | T14: =SUM(H14:K14) -> -11266 | U14: =SUM(I14:L14) -> -11266 | V14: =SUM(J14:M14) -> -11266 | W14: =SUM(K14:N14) -> -13439 | X14: =SUM(L14:O14) -> -10906 | Y14: =SUM(M14:P14) -> -10906 | Z14: =SUM(N14:Q14) -> -10906 | AA14: =SUM(O14:Q14) -> 0 | AB14: =SUM(P14:Q14) -> 0 | AD14: =SUM(AB14/X14)-1 -> -1
B15: Cost of merchandise sold - international franchising | C15: -1985 | D15: -2816 | E15: -3247 | G15: -885 | J15: =SUM(D15-SUM(G15:I15)) -> -1931 | K15: -617 | N15: =SUM(E15-SUM(K15:M15)) -> -2630 | S15: =SUM(G15:J15) -> -2816 | T15: =SUM(H15:K15) -> -2548 | U15: =SUM(I15:L15) -> -2548 | V15: =SUM(J15:M15) -> -2548 | W15: =SUM(K15:N15) -> -3247 | X15: =SUM(L15:O15) -> -2630 | Y15: =SUM(M15:P15) -> -2630 | Z15: =SUM(N15:Q15) -> -2630 | AA15: =SUM(O15:Q15) -> 0 | AB15: =SUM(P15:Q15) -> 0 | AD15: =SUM(AB15/X15)-1 -> -1
B16: Gross Profit | C16: =+SUM(C11+SUM(C13:C15)) -> 245872 | D16: =+SUM(D11+SUM(D13:D15)) -> 264392 | E16: =+SUM(E11+SUM(E13:E15)) -> 272518 | G16: =+SUM(G11+SUM(G13:G15)) -> 64903 | H16: =+SUM(H11+SUM(H13:H15)) -> 0 | I16: =+SUM(I11+SUM(I13:I15)) -> 0 | J16: =+SUM(J11+SUM(J13:J15)) -> 199489 | K16: =+SUM(K11+SUM(K13:K15)) -> 62165 | L16: =+SUM(L11+SUM(L13:L15)) -> 0 | M16: =+SUM(M11+SUM(M13:M15)) -> 0 | N16: =+SUM(N11+SUM(N13:N15)) -> 210353 | ... Q16: =+SUM(Q11+SUM(Q13:Q15)) -> 0 | S16: =+SUM(S11+SUM(S13:S15)) -> 264392 | T16: =+SUM(T11+SUM(T13:T15)) -> 261654 | U16: =+SUM(U11+SUM(U13:U15)) -> 261654 | V16: =+SUM(V11+SUM(V13:V15)) -> 261654 | W16: =+SUM(W11+SUM(W13:W15)) -> 272518 | X16: =+SUM(X11+SUM(X13:X15)) -> 210353 | Y16: =+SUM(Y11+SUM(Y13:Y15)) -> 210353 | Z16: =+SUM(Z11+SUM(Z13:Z15)) -> 210353 | ... AB16: =+SUM(AB11+SUM(AB13:AB15)) -> 0 | AD16: =SUM(AB16/X16)-1 -> -1
B17: Gross Margin (%) | C17: =C16/C11 -> 0.52543825 | D17: =D16/D11 -> 0.54388888 | E17: =E16/E11 -> 0.5489843 | G17: =G16/G11 -> 0.54063307 | H17: =H16/H11 -> #DIV/0! | I17: =I16/I11 -> #DIV/0! | J17: =J16/J11 -> 0.54495662 | K17: =K16/K11 -> 0.54183736 | L17: =L16/L11 -> #DIV/0! | M17: =M16/M11 -> #DIV/0! | N17: =N16/N11 -> 0.55113264 | ... Q17: =Q16/Q11 -> #DIV/0! | S17: =S16/S11 -> 0.54388888 | T17: =T16/T11 -> 0.54421228 | U17: =U16/U11 -> 0.54421228 | V17: =V16/V11 -> 0.54421228 | W17: =W16/W11 -> 0.5489843 | X17: =X16/X11 -> 0.55113264 | Y17: =Y16/Y11 -> 0.55113264 | Z17: =Z16/Z11 -> 0.55113264 | ... AB17: =AB16/AB11 -> #DIV/0! | AD17: =SUM(AB17-X17)*1000 -> #DIV/0!
B19: Selling, general and administrative expense | C19: -183929 | D19: -198992 | E19: -206238 | G19: -45626 | J19: =SUM(D19-SUM(G19:I19)) -> -153366 | K19: -47562 | N19: =SUM(E19-SUM(K19:M19)) -> -158676 | S19: =SUM(G19:J19) -> -198992 | T19: =SUM(H19:K19) -> -200928 | U19: =SUM(I19:L19) -> -200928 | V19: =SUM(J19:M19) -> -200928 | W19: =SUM(K19:N19) -> -206238 | X19: =SUM(L19:O19) -> -158676 | Y19: =SUM(M19:P19) -> -158676 | Z19: =SUM(N19:Q19) -> -158676 | AA19: =SUM(O19:Q19) -> 0 | AB19: =SUM(P19:Q19) -> 0 | AD19: =SUM(AB19/X19)-1 -> -1
B20: Operating Profit | C20: =+SUM(C16+SUM(C19:C19)) -> 61943 | D20: =+SUM(D16+SUM(D19:D19)) -> 65400 | E20: =+SUM(E16+SUM(E19:E19)) -> 66280 | G20: =+SUM(G16+SUM(G19:G19)) -> 19277 | H20: =+SUM(H16+SUM(H19:H19)) -> 0 | I20: =+SUM(I16+SUM(I19:I19)) -> 0 | J20: =+SUM(J16+SUM(J19:J19)) -> 46123 | K20: =+SUM(K16+SUM(K19:K19)) -> 14603 | L20: =+SUM(L16+SUM(L19:L19)) -> 0 | M20: =+SUM(M16+SUM(M19:M19)) -> 0 | N20: =+SUM(N16+SUM(N19:N19)) -> 51677 | ... Q20: =+SUM(Q16+SUM(Q19:Q19)) -> 0 | S20: =+SUM(S16+SUM(S19:S19)) -> 65400 | T20: =+SUM(T16+SUM(T19:T19)) -> 60726 | U20: =+SUM(U16+SUM(U19:U19)) -> 60726 | V20: =+SUM(V16+SUM(V19:V19)) -> 60726 | W20: =+SUM(W16+SUM(W19:W19)) -> 66280 | X20: =+SUM(X16+SUM(X19:X19)) -> 51677 | Y20: =+SUM(Y16+SUM(Y19:Y19)) -> 51677 | Z20: =+SUM(Z16+SUM(Z19:Z19)) -> 51677 | ... AB20: =+SUM(AB16+SUM(AB19:AB19)) -> 0 | AD20: =SUM(AB20/X20)-1 -> -1
B21: Operating Margin (%) | C21: =C20/C11 -> 0.13237466 | D21: =D20/D11 -> 0.13453634 | E21: =E20/E11 -> 0.13352028 | G21: =G20/G11 -> 0.16057476 | H21: =H20/H11 -> #DIV/0! | I21: =I20/I11 -> #DIV/0! | J21: =J20/J11 -> 0.12599709 | K21: =K20/K11 -> 0.12728144 | L21: =L20/L11 -> #DIV/0! | M21: =M20/M11 -> #DIV/0! | N21: =N20/N11 -> 0.13539565 | ... Q21: =Q20/Q11 -> #DIV/0! | S21: =S20/S11 -> 0.13453634 | T21: =T20/T11 -> 0.12630357 | U21: =U20/U11 -> 0.12630357 | V21: =V20/V11 -> 0.12630357 | W21: =W20/W11 -> 0.13352028 | X21: =X20/X11 -> 0.13539565 | Y21: =Y20/Y11 -> 0.13539565 | Z21: =Z20/Z11 -> 0.13539565 | ... AB21: =AB20/AB11 -> #DIV/0! | AD21: =SUM(AB21-X21)*1000 -> #DIV/0!
B23: Interest income (expense), net | C23: -19 | D23: 929 | E23: 861 | G23: 76 | J23: =SUM(D23-SUM(G23:I23)) -> 853 | K23: 426 | N23: =SUM(E23-SUM(K23:M23)) -> 435 | S23: =SUM(G23:J23) -> 929 | T23: =SUM(H23:K23) -> 1279 | U23: =SUM(I23:L23) -> 1279 | V23: =SUM(J23:M23) -> 1279 | W23: =SUM(K23:N23) -> 861 | X23: =SUM(L23:O23) -> 435 | Y23: =SUM(M23:P23) -> 435 | Z23: =SUM(N23:Q23) -> 435 | AA23: =SUM(O23:Q23) -> 0 | AB23: =SUM(P23:Q23) -> 0 | AD23: =SUM(AB23/X23)-1 -> -1
B24: Earnings before Taxes | C24: =SUM(C23:C23)+C20 -> 61924 | D24: =SUM(D23:D23)+D20 -> 66329 | E24: =SUM(E23:E23)+E20 -> 67141 | G24: =SUM(G23:G23)+G20 -> 19353 | H24: =SUM(H23:H23)+H20 -> 0 | I24: =SUM(I23:I23)+I20 -> 0 | J24: =SUM(J23:J23)+J20 -> 46976 | K24: =SUM(K23:K23)+K20 -> 15029 | L24: =SUM(L23:L23)+L20 -> 0 | M24: =SUM(M23:M23)+M20 -> 0 | N24: =SUM(N23:N23)+N20 -> 52112 | ... Q24: =SUM(Q23:Q23)+Q20 -> 0 | S24: =SUM(S23:S23)+S20 -> 66329 | T24: =SUM(T23:T23)+T20 -> 62005 | U24: =SUM(U23:U23)+U20 -> 62005 | V24: =SUM(V23:V23)+V20 -> 62005 | W24: =SUM(W23:W23)+W20 -> 67141 | X24: =SUM(X23:X23)+X20 -> 52112 | Y24: =SUM(Y23:Y23)+Y20 -> 52112 | Z24: =SUM(Z23:Z23)+Z20 -> 52112 | ... AB24: =SUM(AB23:AB23)+AB20 -> 0 | AD24: =SUM(AB24/X24)-1 -> -1
B25: EBT Margin (%) | C25: =C24/C11 -> 0.13233405 | D25: =D24/D11 -> 0.13644742 | E25: =E24/E11 -> 0.13525475 | G25: =G24/G11 -> 0.16120783 | H25: =H24/H11 -> #DIV/0! | I25: =I24/I11 -> #DIV/0! | J25: =J24/J11 -> 0.12832729 | K25: =K24/K11 -> 0.13099451 | L25: =L24/L11 -> #DIV/0! | M25: =M24/M11 -> #DIV/0! | N25: =N24/N11 -> 0.13653537 | ... Q25: =Q24/Q11 -> #DIV/0! | S25: =S24/S11 -> 0.13644742 | T25: =T24/T11 -> 0.12896376 | U25: =U24/U11 -> 0.12896376 | V25: =V24/V11 -> 0.12896376 | W25: =W24/W11 -> 0.13525475 | X25: =X24/X11 -> 0.13653537 | Y25: =Y24/Y11 -> 0.13653537 | Z25: =Z24/Z11 -> 0.13653537 | ... AB25: =AB24/AB11 -> #DIV/0! | AD25: =SUM(AB25-X25)*1000 -> #DIV/0!
B27: Income tax expense | C27: -13939 | D27: -13524 | E27: -15356 | G27: -4745 | J27: =SUM(D27-SUM(G27:I27)) -> -8779 | K27: -3570 | N27: =SUM(E27-SUM(K27:M27)) -> -11786 | S27: =SUM(G27:J27) -> -13524 | T27: =SUM(H27:K27) -> -12349 | U27: =SUM(I27:L27) -> -12349 | V27: =SUM(J27:M27) -> -12349 | W27: =SUM(K27:N27) -> -15356 | X27: =SUM(L27:O27) -> -11786 | Y27: =SUM(M27:P27) -> -11786 | Z27: =SUM(N27:Q27) -> -11786 | AA27: =SUM(O27:Q27) -> 0 | AB27: =SUM(P27:Q27) -> 0 | AD27: =SUM(AB27/X27)-1 -> -1
B28: Net loss | C28: =SUM(C24+SUM(C27:C27)) -> 47985 | D28: =SUM(D24+SUM(D27:D27)) -> 52805 | E28: =SUM(E24+SUM(E27:E27)) -> 51785 | G28: =SUM(G24+SUM(G27:G27)) -> 14608 | H28: =SUM(H24+SUM(H27:H27)) -> 0 | I28: =SUM(I24+SUM(I27:I27)) -> 0 | J28: =SUM(J24+SUM(J27:J27)) -> 38197 | K28: =SUM(K24+SUM(K27:K27)) -> 11459 | L28: =SUM(L24+SUM(L27:L27)) -> 0 | M28: =SUM(M24+SUM(M27:M27)) -> 0 | N28: =SUM(N24+SUM(N27:N27)) -> 40326 | ... Q28: =SUM(Q24+SUM(Q27:Q27)) -> 0 | S28: =SUM(S24+SUM(S27:S27)) -> 52805 | T28: =SUM(T24+SUM(T27:T27)) -> 49656 | U28: =SUM(U24+SUM(U27:U27)) -> 49656 | V28: =SUM(V24+SUM(V27:V27)) -> 49656 | W28: =SUM(W24+SUM(W27:W27)) -> 51785 | X28: =SUM(X24+SUM(X27:X27)) -> 40326 | Y28: =SUM(Y24+SUM(Y27:Y27)) -> 40326 | Z28: =SUM(Z24+SUM(Z27:Z27)) -> 40326 | ... AB28: =SUM(AB24+SUM(AB27:AB27)) -> 0 | AD28: =SUM(AB28/X28)-1 -> -1
B29: Net Margin (%) | C29: =C28/C11 -> 0.10254586 | D29: =D28/D11 -> 0.10862678 | E29: =E28/E11 -> 0.10432027 | G29: =G28/G11 -> 0.12168263 | H29: =H28/H11 -> #DIV/0! | I29: =I28/I11 -> #DIV/0! | J29: =J28/J11 -> 0.10434514 | K29: =K28/K11 -> 0.099877974 | L29: =L28/L11 -> #DIV/0! | M29: =M28/M11 -> #DIV/0! | N29: =N28/N11 -> 0.10565561 | ... Q29: =Q28/Q11 -> #DIV/0! | S29: =S28/S11 -> 0.10862678 | T29: =T28/T11 -> 0.10327916 | U29: =U28/U11 -> 0.10327916 | V29: =V28/V11 -> 0.10327916 | W29: =W28/W11 -> 0.10432027 | X29: =X28/X11 -> 0.10565561 | Y29: =Y28/Y11 -> 0.10565561 | Z29: =Z28/Z11 -> 0.10565561 | ... AB29: =AB28/AB11 -> #DIV/0! | AD29: =SUM(AB29-X29)*1000 -> #DIV/0!
B31: Basic shares | C31: 14940.77 | D31: 14342.931 | E31: 13578.587 | G31: 14457.858 | J31: =D31 -> 14342.931 | K31: 13925.957 | N31: =E31 -> 13578.587 | S31: =J31 -> 14342.931 | T31: =K31 -> 13925.957 | U31: =L31 -> 0 | V31: =M31 -> 0 | W31: =N31 -> 13578.587 | X31: =O31 -> 0 | Y31: =P31 -> 0 | Z31: =Q31 -> 0 | AA31: =#REF! -> #REF! | AB31: =#REF! -> #REF! | AD31: =SUM(AB31/X31)-1 -> #REF!
B32: Basic EPS | C32: =C28/C31 -> 3.2116819 | D32: =D28/D31 -> 3.6816045 | E32: =E28/E31 -> 3.8137252 | G32: =G28/G31 -> 1.0103848 | H32: =H28/H31 -> #DIV/0! | I32: =I28/I31 -> #DIV/0! | J32: =J28/J31 -> 2.6631237 | K32: =K28/K31 -> 0.82285189 | L32: =L28/L31 -> #DIV/0! | M32: =M28/M31 -> #DIV/0! | N32: =N28/N31 -> 2.969823 | ... Q32: =Q28/Q31 -> #DIV/0! | S32: =S28/S31 -> 3.6816045 | T32: =T28/T31 -> 3.5657154 | U32: =U28/U31 -> #DIV/0! | V32: =V28/V31 -> #DIV/0! | W32: =W28/W31 -> 3.8137252 | X32: =X28/X31 -> #DIV/0! | Y32: =Y28/Y31 -> #DIV/0! | Z32: =Z28/Z31 -> #DIV/0! | ... AB32: =AB28/AB31 -> #REF! | AD32: =SUM(AB32/X32)-1 -> #REF!
B34: Fully Diluted Shares | C34: 15249.819 | D34: 14471.875 | E34: 13621.075 | G34: 14974.93 | J34: =D34 -> 14471.875 | K34: 14006.4 | N34: =E34 -> 13621.075 | S34: =J34 -> 14471.875 | T34: =K34 -> 14006.4 | U34: =L34 -> 0 | V34: =M34 -> 0 | W34: =N34 -> 13621.075 | X34: =O34 -> 0 | Y34: =P34 -> 0 | Z34: =Q34 -> 0 | AA34: =#REF! -> #REF! | AB34: =#REF! -> #REF! | AD34: =SUM(AB34/X34)-1 -> #REF!
B35: Diluted EPS | C35: =C28/C34 -> 3.1465947 | D35: =D28/D34 -> 3.6488016 | E35: =E28/E34 -> 3.8018292 | G35: =G28/G34 -> 0.97549705 | H35: =H28/H34 -> #DIV/0! | I35: =I28/I34 -> #DIV/0! | J35: =J28/J34 -> 2.6393954 | K35: =K28/K34 -> 0.818126 | L35: =L28/L34 -> #DIV/0! | M35: =M28/M34 -> #DIV/0! | N35: =N28/N34 -> 2.9605593 | ... Q35: =Q28/Q34 -> #DIV/0! | S35: =S28/S34 -> 3.6488016 | T35: =T28/T34 -> 3.5452365 | U35: =U28/U34 -> #DIV/0! | V35: =V28/V34 -> #DIV/0! | W35: =W28/W34 -> 3.8018292 | X35: =X28/X34 -> #DIV/0! | Y35: =Y28/Y34 -> #DIV/0! | Z35: =Z28/Z34 -> #DIV/0! | ... AB35: =AB28/AB34 -> #REF! | AD35: =SUM(AB35/X35)-1 -> #REF!
A37: X | B37: Balance Sheet | M37: Quarterly | X37: LTM | AD37: Variance
B38: =B7 -> Fiscal Period | C38: =C7 -> 2022 | D38: =D7 -> 2023 | E38: =E7 -> 2024 | G38: =G7 -> 1Q23 | H38: =H7 -> 2Q23 | I38: =I7 -> 3Q23 | J38: =J7 -> 4Q23 | K38: =K7 -> 1Q24 | L38: =L7 -> 2Q24 | M38: =M7 -> 3Q24 | N38: =N7 -> 4Q24 | ... Q38: =Q7 -> 3Q25 | S38: =S7 -> 4Q23 | T38: =T7 -> 1Q24 | U38: =U7 -> 2Q24 | V38: =V7 -> 3Q24 | W38: =W7 -> 4Q24 | X38: =X7 -> 1Q25 | Y38: =Y7 -> 2Q25 | Z38: =Z7 -> 3Q25 | ... AB38: =AB7 -> #REF!
B39: =B8 -> Fiscal Period End Date | C39: =C8 -> 44954 | D39: =D8 -> 45325 | E39: =E8 -> 45689 | G39: =G8 -> 45045 | H39: =H8 -> 45136 | I39: =I8 -> 45227 | J39: =J8 -> 45325 | K39: =K8 -> 45416 | L39: =L8 -> 45507 | M39: =M8 -> 45598 | N39: =N8 -> 45689 | ... Q39: =Q8 -> 45962 | S39: =S8 -> 45325 | T39: =T8 -> 45416 | U39: =U8 -> 45507 | V39: =V8 -> 45598 | W39: =W8 -> 45689 | X39: =X8 -> 45780 | Y39: =Y8 -> 45871 | Z39: =Z8 -> 45962 | ... AB39: =AB8 -> #REF!
B41: Current Assets
B42: Cash, cash equivalents and restricted cash | C42: 42198 | D42: 44327 | E42: 27758 | G42: 32819 | J42: =D42 -> 44327 | K42: 38233 | N42: =E42 -> 27758 | S42: =J42 -> 44327 | T42: =K42 -> 38233 | U42: =L42 -> 0 | V42: =M42 -> 0 | W42: =N42 -> 27758 | X42: =O42 -> 0 | Y42: =P42 -> 0 | Z42: =Q42 -> 0 | AA42: =#REF! -> #REF! | AB42: =#REF! -> #REF! | AD42: =SUM(AB42/X42)-1 -> #REF!
B43: Inventories, net | C43: 70485 | D43: 63499 | E43: 69775 | G43: 66489 | J43: =D43 -> 63499 | K43: 64024 | N43: =E43 -> 69775 | S43: =J43 -> 63499 | T43: =K43 -> 64024 | U43: =L43 -> 0 | V43: =M43 -> 0 | W43: =N43 -> 69775 | X43: =O43 -> 0 | Y43: =P43 -> 0 | Z43: =Q43 -> 0 | AA43: =#REF! -> #REF! | AB43: =#REF! -> #REF! | AD43: =SUM(AB43/X43)-1 -> #REF!
B44: Receivables, net | C44: 15374 | D44: 8569 | E44: 16096 | G44: 13307 | J44: =D44 -> 8569 | K44: 9547 | N44: =E44 -> 16096 | S44: =J44 -> 8569 | T44: =K44 -> 9547 | U44: =L44 -> 0 | V44: =M44 -> 0 | W44: =N44 -> 16096 | X44: =O44 -> 0 | Y44: =P44 -> 0 | Z44: =Q44 -> 0 | AA44: =#REF! -> #REF! | AB44: =#REF! -> #REF! | AD44: =SUM(AB44/X44)-1 -> #REF!
B45: Prepaid expenses and other current assets | C45: 19374 | D45: 11377 | E45: 12669 | G45: 13503 | J45: =D45 -> 11377 | K45: 12046 | N45: =E45 -> 12669 | S45: =J45 -> 11377 | T45: =K45 -> 12046 | U45: =L45 -> 0 | V45: =M45 -> 0 | W45: =N45 -> 12669 | X45: =O45 -> 0 | Y45: =P45 -> 0 | Z45: =Q45 -> 0 | AA45: =#REF! -> #REF! | AB45: =#REF! -> #REF! | AD45: =SUM(AB45/X45)-1 -> #REF!
B46: Total Current Assets | C46: =SUM(C42:C45) -> 147431 | D46: =SUM(D42:D45) -> 127772 | E46: =SUM(E42:E45) -> 126298 | G46: =SUM(G42:G45) -> 126118 | H46: =SUM(H42:H45) -> 0 | I46: =SUM(I42:I45) -> 0 | J46: =SUM(J42:J45) -> 127772 | K46: =SUM(K42:K45) -> 123850 | L46: =SUM(L42:L45) -> 0 | M46: =SUM(M42:M45) -> 0 | N46: =SUM(N42:N45) -> 126298 | ... Q46: =SUM(Q42:Q45) -> 0 | S46: =SUM(S42:S45) -> 127772 | T46: =SUM(T42:T45) -> 123850 | U46: =SUM(U42:U45) -> 0 | V46: =SUM(V42:V45) -> 0 | W46: =SUM(W42:W45) -> 126298 | X46: =SUM(X42:X45) -> 0 | Y46: =SUM(Y42:Y45) -> 0 | Z46: =SUM(Z42:Z45) -> 0 | ... AB46: =SUM(AB42:AB45) -> #REF! | AD46: =SUM(AB46/X46)-1 -> #REF!
B48: Non-Current Assets
B49: Operating lease right-of-use asset | C49: 71791 | D49: 73443 | E49: 90200 | G49: 73780 | J49: =D49 -> 73443 | K49: 72783 | N49: =E49 -> 90200 | S49: =J49 -> 73443 | T49: =K49 -> 72783 | U49: =L49 -> 0 | V49: =M49 -> 0 | W49: =N49 -> 90200 | X49: =O49 -> 0 | Y49: =P49 -> 0 | Z49: =Q49 -> 0 | AA49: =#REF! -> #REF! | AB49: =#REF! -> #REF! | AD49: =SUM(AB49/X49)-1 -> #REF!
B50: Property and equipment, net | C50: 50759 | D50: 55262 | E50: 59761 | G50: 50385 | J50: =D50 -> 55262 | K50: 53897 | N50: =E50 -> 59761 | S50: =J50 -> 55262 | T50: =K50 -> 53897 | U50: =L50 -> 0 | V50: =M50 -> 0 | W50: =N50 -> 59761 | X50: =O50 -> 0 | Y50: =P50 -> 0 | Z50: =Q50 -> 0 | AA50: =#REF! -> #REF! | AB50: =#REF! -> #REF! | AD50: =SUM(AB50/X50)-1 -> #REF!
B51: Deferred tax assets | C51: 6592 | D51: 8682 | E51: 7596 | G51: 6642 | J51: =D51 -> 8682 | K51: 8672 | N51: =E51 -> 7596 | S51: =J51 -> 8682 | T51: =K51 -> 8672 | U51: =L51 -> 0 | V51: =M51 -> 0 | W51: =N51 -> 7596 | X51: =O51 -> 0 | Y51: =P51 -> 0 | Z51: =Q51 -> 0 | AA51: =#REF! -> #REF! | AB51: =#REF! -> #REF! | AD51: =SUM(AB51/X51)-1 -> #REF!
B52: Other assets, net | C52: 4221 | D52: 7166 | E52: 6101 | G52: 4785 | J52: =D52 -> 7166 | K52: 6074 | N52: =E52 -> 6101 | S52: =J52 -> 7166 | T52: =K52 -> 6074 | U52: =L52 -> 0 | V52: =M52 -> 0 | W52: =N52 -> 6101 | X52: =O52 -> 0 | Y52: =P52 -> 0 | Z52: =Q52 -> 0 | AA52: =#REF! -> #REF! | AB52: =#REF! -> #REF! | AD52: =SUM(AB52/X52)-1 -> #REF!
B53: Total Assets | C53: =SUM(C49:C52)+C46 -> 280794 | D53: =SUM(D49:D52)+D46 -> 272325 | E53: =SUM(E49:E52)+E46 -> 289956 | G53: =SUM(G49:G52)+G46 -> 261710 | H53: =SUM(H49:H52)+H46 -> 0 | I53: =SUM(I49:I52)+I46 -> 0 | J53: =SUM(J49:J52)+J46 -> 272325 | K53: =SUM(K49:K52)+K46 -> 265276 | L53: =SUM(L49:L52)+L46 -> 0 | M53: =SUM(M49:M52)+M46 -> 0 | N53: =SUM(N49:N52)+N46 -> 289956 | ... Q53: =SUM(Q49:Q52)+Q46 -> 0 | S53: =SUM(S49:S52)+S46 -> 272325 | T53: =SUM(T49:T52)+T46 -> 265276 | U53: =SUM(U49:U52)+U46 -> 0 | V53: =SUM(V49:V52)+V46 -> 0 | W53: =SUM(W49:W52)+W46 -> 289956 | X53: =SUM(X49:X52)+X46 -> 0 | Y53: =SUM(Y49:Y52)+Y46 -> 0 | Z53: =SUM(Z49:Z52)+Z46 -> 0 | ... AB53: =SUM(AB49:AB52)+AB46 -> #REF! | AD53: =SUM(AB53/X53)-1 -> #REF!
B55: Current Liabilities
B56: Accounts payable | C56: 10286 | D56: 16170 | E56: 16538 | G56: 13686 | J56: =D56 -> 16170 | K56: 14793 | N56: =E56 -> 16538 | S56: =J56 -> 16170 | T56: =K56 -> 14793 | U56: =L56 -> 0 | V56: =M56 -> 0 | W56: =N56 -> 16538 | X56: =O56 -> 0 | Y56: =P56 -> 0 | Z56: =Q56 -> 0 | AA56: =#REF! -> #REF! | AB56: =#REF! -> #REF! | AD56: =SUM(AB56/X56)-1 -> #REF!
B57: Accrued expenses | C57: 37358 | D57: 19954 | E57: 16209 | G57: 27272 | J57: =D57 -> 19954 | K57: 19552 | N57: =E57 -> 16209 | S57: =J57 -> 19954 | T57: =K57 -> 19552 | U57: =L57 -> 0 | V57: =M57 -> 0 | W57: =N57 -> 16209 | X57: =O57 -> 0 | Y57: =P57 -> 0 | Z57: =Q57 -> 0 | AA57: =#REF! -> #REF! | AB57: =#REF! -> #REF! | AD57: =SUM(AB57/X57)-1 -> #REF!
B58: Operating lease liability short term | C58: 27436 | D58: 25961 | E58: 26841 | G58: 27843 | J58: =D58 -> 25961 | K58: 24276 | N58: =E58 -> 26841 | S58: =J58 -> 25961 | T58: =K58 -> 24276 | U58: =L58 -> 0 | V58: =M58 -> 0 | W58: =N58 -> 26841 | X58: =O58 -> 0 | Y58: =P58 -> 0 | Z58: =Q58 -> 0 | AA58: =#REF! -> #REF! | AB58: =#REF! -> #REF! | AD58: =SUM(AB58/X58)-1 -> #REF!
B59: Gift cards and customer deposits | C59: 19425 | D59: 18134 | E59: 15791 | G59: 18637 | J59: =D59 -> 18134 | K59: 16620 | N59: =E59 -> 15791 | S59: =J59 -> 18134 | T59: =K59 -> 16620 | U59: =L59 -> 0 | V59: =M59 -> 0 | W59: =N59 -> 15791 | X59: =O59 -> 0 | Y59: =P59 -> 0 | Z59: =Q59 -> 0 | AA59: =#REF! -> #REF! | AB59: =#REF! -> #REF! | AD59: =SUM(AB59/X59)-1 -> #REF!
B60: Deferred revenue and other | C60: 6646 | D60: 3514 | E60: 4015 | G60: 5010 | J60: =D60 -> 3514 | K60: 3432 | N60: =E60 -> 4015 | S60: =J60 -> 3514 | T60: =K60 -> 3432 | U60: =L60 -> 0 | V60: =M60 -> 0 | W60: =N60 -> 4015 | X60: =O60 -> 0 | Y60: =P60 -> 0 | Z60: =Q60 -> 0 | AA60: =#REF! -> #REF! | AB60: =#REF! -> #REF!
B61: Total Current Liabilities | C61: =SUM(C56:C60) -> 101151 | D61: =SUM(D56:D60) -> 83733 | E61: =SUM(E56:E60) -> 79394 | G61: =SUM(G56:G60) -> 92448 | H61: =SUM(H56:H60) -> 0 | I61: =SUM(I56:I60) -> 0 | J61: =SUM(J56:J60) -> 83733 | K61: =SUM(K56:K60) -> 78673 | L61: =SUM(L56:L60) -> 0 | M61: =SUM(M56:M60) -> 0 | N61: =SUM(N56:N60) -> 79394 | ... Q61: =SUM(Q56:Q60) -> 0 | S61: =SUM(S56:S60) -> 83733 | T61: =SUM(T56:T60) -> 78673 | U61: =SUM(U56:U60) -> 0 | V61: =SUM(V56:V60) -> 0 | W61: =SUM(W56:W60) -> 79394 | X61: =SUM(X56:X60) -> 0 | Y61: =SUM(Y56:Y60) -> 0 | Z61: =SUM(Z56:Z60) -> 0 | ... AB61: =SUM(AB56:AB60) -> #REF! | AD61: =SUM(AB61/X61)-1 -> #REF!
B63: Non-Current Liabilities
B64: Operating lease liability long term | C64: 59080 | D64: 57609 | E64: 70155 | G64: 59030 | J64: =D64 -> 57609 | K64: 56906 | N64: =E64 -> 70155 | S64: =J64 -> 57609 | T64: =K64 -> 56906 | U64: =L64 -> 0 | V64: =M64 -> 0 | W64: =N64 -> 70155 | X64: =O64 -> 0 | Y64: =P64 -> 0 | Z64: =Q64 -> 0 | AA64: =#REF! -> #REF! | AB64: =#REF! -> #REF! | AD64: =SUM(AB64/X64)-1 -> #REF!
B65: Other long-term liabilities | C65: 1446 | D65: 1321 | E65: 1325 | G65: 1260 | J65: =D65 -> 1321 | K65: 1356 | N65: =E65 -> 1325 | S65: =J65 -> 1321 | T65: =K65 -> 1356 | U65: =L65 -> 0 | V65: =M65 -> 0 | W65: =N65 -> 1325 | X65: =O65 -> 0 | Y65: =P65 -> 0 | Z65: =Q65 -> 0 | AA65: =#REF! -> #REF! | AB65: =#REF! -> #REF! | AD65: =SUM(AB65/X65)-1 -> #REF!
B66: Total Liabilities | C66: =SUM(C64:C65)+C61 -> 161677 | D66: =SUM(D64:D65)+D61 -> 142663 | E66: =SUM(E64:E65)+E61 -> 150874 | G66: =SUM(G64:G65)+G61 -> 152738 | H66: =SUM(H64:H65)+H61 -> 0 | I66: =SUM(I64:I65)+I61 -> 0 | J66: =SUM(J64:J65)+J61 -> 142663 | K66: =SUM(K64:K65)+K61 -> 136935 | L66: =SUM(L64:L65)+L61 -> 0 | M66: =SUM(M64:M65)+M61 -> 0 | N66: =SUM(N64:N65)+N61 -> 150874 | ... Q66: =SUM(Q64:Q65)+Q61 -> 0 | S66: =SUM(S64:S65)+S61 -> 142663 | T66: =SUM(T64:T65)+T61 -> 136935 | U66: =SUM(U64:U65)+U61 -> 0 | V66: =SUM(V64:V65)+V61 -> 0 | W66: =SUM(W64:W65)+W61 -> 150874 | X66: =SUM(X64:X65)+X61 -> 0 | Y66: =SUM(Y64:Y65)+Y61 -> 0 | Z66: =SUM(Z64:Z65)+Z61 -> 0 | ... AB66: =SUM(AB64:AB65)+AB61 -> #REF! | AD66: =SUM(AB66/X66)-1 -> #REF!
B68: Preferred stock | C68: 0 | D68: - | E68: - | G68: - | H68: - | I68: - | J68: =D68 -> - | K68: - | L68: - | M68: - | N68: =E68 -> - | O68: - | P68: - | Q68: - | S68: =J68 -> - | T68: =K68 -> - | U68: =L68 -> - | V68: =M68 -> - | W68: =N68 -> - | X68: =O68 -> - | Y68: =P68 -> - | Z68: =Q68 -> - | AA68: =#REF! -> #REF! | AB68: =#REF! -> #REF! | AD68: =SUM(AB68/X68)-1 -> #REF!
B69: Common stock | C69: 148 | D69: 142 | E69: 133 | G69: 149 | J69: =D69 -> 142 | K69: 139 | N69: =E69 -> 133 | S69: =J69 -> 142 | T69: =K69 -> 139 | U69: =L69 -> 0 | V69: =M69 -> 0 | W69: =N69 -> 133 | X69: =O69 -> 0 | Y69: =P69 -> 0 | Z69: =Q69 -> 0 | AA69: =#REF! -> #REF! | AB69: =#REF! -> #REF! | AD69: =SUM(AB69/X69)-1 -> #REF!
B70: Additional paid-in capital | C70: 69868 | D70: 66330 | E70: 61987 | G70: 70324 | J70: =D70 -> 66330 | K70: 64065 | N70: =E70 -> 61987 | S70: =J70 -> 66330 | T70: =K70 -> 64065 | U70: =L70 -> 0 | V70: =M70 -> 0 | W70: =N70 -> 61987 | X70: =O70 -> 0 | Y70: =P70 -> 0 | Z70: =Q70 -> 0 | AA70: =#REF! -> #REF! | AB70: =#REF! -> #REF! | AD70: =SUM(AB70/X70)-1 -> #REF!
B71: Accumulated other comprehensive loss | C71: -12274 | D71: -12082 | E71: -12554 | G71: -12177 | J71: =D71 -> -12082 | K71: -12153 | N71: =E71 -> -12554 | S71: =J71 -> -12082 | T71: =K71 -> -12153 | U71: =L71 -> 0 | V71: =M71 -> 0 | W71: =N71 -> -12554 | X71: =O71 -> 0 | Y71: =P71 -> 0 | Z71: =Q71 -> 0 | AA71: =#REF! -> #REF! | AB71: =#REF! -> #REF! | AD71: =SUM(AB71/X71)-1 -> #REF!
B72: Retained earnings | C72: 61375 | D72: 75272 | E72: 89516 | G72: 50676 | J72: =D72 -> 75272 | K72: 76290 | N72: =E72 -> 89516 | S72: =J72 -> 75272 | T72: =K72 -> 76290 | U72: =L72 -> 0 | V72: =M72 -> 0 | W72: =N72 -> 89516 | X72: =O72 -> 0 | Y72: =P72 -> 0 | Z72: =Q72 -> 0 | AA72: =#REF! -> #REF! | AB72: =#REF! -> #REF! | AD72: =SUM(AB72/X72)-1 -> #REF!
B73: Total stockholders' equity | C73: =SUM(C68:C72) -> 119117 | D73: =SUM(D68:D72) -> 129662 | E73: =SUM(E68:E72) -> 139082 | G73: =SUM(G68:G72) -> 108972 | H73: =SUM(H68:H72) -> 0 | I73: =SUM(I68:I72) -> 0 | J73: =SUM(J68:J72) -> 129662 | K73: =SUM(K68:K72) -> 128341 | L73: =SUM(L68:L72) -> 0 | M73: =SUM(M68:M72) -> 0 | N73: =SUM(N68:N72) -> 139082 | ... Q73: =SUM(Q68:Q72) -> 0 | S73: =SUM(S68:S72) -> 129662 | T73: =SUM(T68:T72) -> 128341 | U73: =SUM(U68:U72) -> 0 | V73: =SUM(V68:V72) -> 0 | W73: =SUM(W68:W72) -> 139082 | X73: =SUM(X68:X72) -> 0 | Y73: =SUM(Y68:Y72) -> 0 | Z73: =SUM(Z68:Z72) -> 0 | ... AB73: =SUM(AB68:AB72) -> #REF! | AD73: =SUM(AB73/X73)-1 -> #REF!
B74: Total liabilities and stockholders' equity | C74: =SUM(C73+C66) -> 280794 | D74: =SUM(D73+D66) -> 272325 | E74: =SUM(E73+E66) -> 289956 | G74: =SUM(G73+G66) -> 261710 | H74: =SUM(H73+H66) -> 0 | I74: =SUM(I73+I66) -> 0 | J74: =SUM(J73+J66) -> 272325 | K74: =SUM(K73+K66) -> 265276 | L74: =SUM(L73+L66) -> 0 | M74: =SUM(M73+M66) -> 0 | N74: =SUM(N73+N66) -> 289956 | ... Q74: =SUM(Q73+Q66) -> 0 | S74: =SUM(S73+S66) -> 272325 | T74: =SUM(T73+T66) -> 265276 | U74: =SUM(U73+U66) -> 0 | V74: =SUM(V73+V66) -> 0 | W74: =SUM(W73+W66) -> 289956 | X74: =SUM(X73+X66) -> 0 | Y74: =SUM(Y73+Y66) -> 0 | Z74: =SUM(Z73+Z66) -> 0 | ... AB74: =SUM(AB73+AB66) -> #REF! | AD74: =SUM(AB74/X74)-1 -> #REF!
B76: Balance Check | C76: =C74-C53 -> 0 | D76: =D74-D53 -> 0 | E76: =E74-E53 -> 0 | G76: =G74-G53 -> 0 | H76: =H74-H53 -> 0 | I76: =I74-I53 -> 0 | J76: =J74-J53 -> 0 | K76: =K74-K53 -> 0 | L76: =L74-L53 -> 0 | M76: =M74-M53 -> 0 | N76: =N74-N53 -> 0 | ... Q76: =Q74-Q53 -> 0 | S76: =S74-S53 -> 0 | T76: =T74-T53 -> 0 | U76: =U74-U53 -> 0 | V76: =V74-V53 -> 0 | W76: =W74-W53 -> 0 | X76: =X74-X53 -> 0 | Y76: =Y74-Y53 -> 0 | Z76: =Z74-Z53 -> 0 | ... AB76: =AB74-AB53 -> #REF!
A79: X | B79: Cash-Flows Statement | M79: Quarterly | X79: LTM | AD79: Variance
B80: =B7 -> Fiscal Period | C80: =C7 -> 2022 | D80: =D7 -> 2023 | E80: =E7 -> 2024 | G80: =G7 -> 1Q23 | H80: =H7 -> 2Q23 | I80: =I7 -> 3Q23 | J80: =J7 -> 4Q23 | K80: =K7 -> 1Q24 | L80: =L7 -> 2Q24 | M80: =M7 -> 3Q24 | N80: =N7 -> 4Q24 | ... Q80: =Q7 -> 3Q25 | S80: =S7 -> 4Q23 | T80: =T7 -> 1Q24 | U80: =U7 -> 2Q24 | V80: =V7 -> 3Q24 | W80: =W7 -> 4Q24 | X80: =X7 -> 1Q25 | Y80: =Y7 -> 2Q25 | Z80: =Z7 -> 3Q25 | ... AB80: =AB7 -> #REF!
B81: =B8 -> Fiscal Period End Date | C81: =C8 -> 44954 | D81: =D8 -> 45325 | E81: =E8 -> 45689 | G81: =G8 -> 45045 | H81: =H8 -> 45136 | I81: =I8 -> 45227 | J81: =J8 -> 45325 | K81: =K8 -> 45416 | L81: =L8 -> 45507 | M81: =M8 -> 45598 | N81: =N8 -> 45689 | ... Q81: =Q8 -> 45962 | S81: =S8 -> 45325 | T81: =T8 -> 45416 | U81: =U8 -> 45507 | V81: =V8 -> 45598 | W81: =W8 -> 45689 | X81: =X8 -> 45780 | Y81: =Y8 -> 45871 | Z81: =Z8 -> 45962 | ... AB81: =AB8 -> #REF!
B83: Cash-Flows From Operating Activities
B84: Net income (loss) | C84: =C28 -> 47985 | D84: =D28 -> 52805 | E84: =E28 -> 51785 | G84: =G28 -> 14608 | H84: =H28 -> 0 | I84: =I28 -> 0 | J84: =J28 -> 38197 | K84: =K28 -> 11459 | L84: =L28 -> 0 | M84: =M28 -> 0 | N84: =N28 -> 40326 | ... Q84: =Q28 -> 0 | S84: =S28 -> 52805 | T84: =T28 -> 49656 | U84: =U28 -> 49656 | V84: =V28 -> 49656 | W84: =W28 -> 51785 | X84: =X28 -> 40326 | Y84: =Y28 -> 40326 | Z84: =Z28 -> 40326 | ... AB84: =AB28 -> 0 | AD84: =SUM(AB84/X84)-1 -> -1
B86: Adjustments to reconcile net income:
B87: Depreciation and amortization | C87: 12482 | D87: 13657 | E87: 14772 | G87: 3080 | J87: =SUM(D87-SUM(G87:I87)) -> 10577 | K87: 3658 | N87: =SUM(E87-SUM(K87:M87)) -> 11114 | S87: =SUM(G87:J87) -> 13657 | T87: =SUM(H87:K87) -> 14235 | U87: =SUM(I87:L87) -> 14235 | V87: =SUM(J87:M87) -> 14235 | W87: =SUM(K87:N87) -> 14772 | X87: =SUM(L87:O87) -> 11114 | Y87: =SUM(M87:P87) -> 11114 | Z87: =SUM(N87:Q87) -> 11114 | AA87: =SUM(O87:Q87) -> 0 | AB87: =SUM(P87:Q87) -> 0 | AD87: =SUM(AB87/X87)-1 -> -1
B88: Share-based and performance-based stock compensation | C88: 2559 | D88: 2089 | E88: 2175 | G88: 1052 | J88: =SUM(D88-SUM(G88:I88)) -> 1037 | K88: 412 | N88: =SUM(E88-SUM(K88:M88)) -> 1763 | S88: =SUM(G88:J88) -> 2089 | T88: =SUM(H88:K88) -> 1449 | U88: =SUM(I88:L88) -> 1449 | V88: =SUM(J88:M88) -> 1449 | W88: =SUM(K88:N88) -> 2175 | X88: =SUM(L88:O88) -> 1763 | Y88: =SUM(M88:P88) -> 1763 | Z88: =SUM(N88:Q88) -> 1763 | AA88: =SUM(O88:Q88) -> 0 | AB88: =SUM(P88:Q88) -> 0 | AD88: =SUM(AB88/X88)-1 -> -1
B89: Deferred taxes | C89: 992 | D89: -1893 | E89: 1060 | G89: -53 | J89: =SUM(D89-SUM(G89:I89)) -> -1840 | K89: - | N89: =SUM(E89-SUM(K89:M89)) -> 1060 | S89: =SUM(G89:J89) -> -1893 | T89: =SUM(H89:K89) -> -1840 | U89: =SUM(I89:L89) -> -1840 | V89: =SUM(J89:M89) -> -1840 | W89: =SUM(K89:N89) -> 1060 | X89: =SUM(L89:O89) -> 1060 | Y89: =SUM(M89:P89) -> 1060 | Z89: =SUM(N89:Q89) -> 1060 | AA89: =SUM(O89:Q89) -> 0 | AB89: =SUM(P89:Q89) -> 0 | AD89: =SUM(AB89/X89)-1 -> -1
B90: Provision/(adjustments) for doubtful accounts | C90: -820 | D90: 251 | E90: 187 | G90: -316 | J90: =SUM(D90-SUM(G90:I90)) -> 567 | K90: -78 | N90: =SUM(E90-SUM(K90:M90)) -> 265 | S90: =SUM(G90:J90) -> 251 | T90: =SUM(H90:K90) -> 489 | U90: =SUM(I90:L90) -> 489 | V90: =SUM(J90:M90) -> 489 | W90: =SUM(K90:N90) -> 187 | X90: =SUM(L90:O90) -> 265 | Y90: =SUM(M90:P90) -> 265 | Z90: =SUM(N90:Q90) -> 265 | AA90: =SUM(O90:Q90) -> 0 | AB90: =SUM(P90:Q90) -> 0 | AD90: =SUM(AB90/X90)-1 -> -1
B91: Loss on disposal of property and equipment | C91: 110 | D91: 121 | E91: 290 | G91: 21 | J91: =SUM(D91-SUM(G91:I91)) -> 100 | K91: 139 | N91: =SUM(E91-SUM(K91:M91)) -> 151 | S91: =SUM(G91:J91) -> 121 | T91: =SUM(H91:K91) -> 239 | U91: =SUM(I91:L91) -> 239 | V91: =SUM(J91:M91) -> 239 | W91: =SUM(K91:N91) -> 290 | X91: =SUM(L91:O91) -> 151 | Y91: =SUM(M91:P91) -> 151 | Z91: =SUM(N91:Q91) -> 151 | AA91: =SUM(O91:Q91) -> 0 | AB91: =SUM(P91:Q91) -> 0 | AD91: =SUM(AB91/X91)-1 -> -1
B92: Net change in film costs and advances | C92: -2453 | D92: -1913 | E92: 513 | J92: =SUM(D92-SUM(G92:I92)) -> -1913 | N92: =SUM(E92-SUM(K92:M92)) -> 513 | S92: =SUM(G92:J92) -> -1913 | T92: =SUM(H92:K92) -> -1913 | U92: =SUM(I92:L92) -> -1913 | V92: =SUM(J92:M92) -> -1913 | W92: =SUM(K92:N92) -> 513 | X92: =SUM(L92:O92) -> 513 | Y92: =SUM(M92:P92) -> 513 | Z92: =SUM(N92:Q92) -> 513 | AA92: =SUM(O92:Q92) -> 0 | AB92: =SUM(P92:Q92) -> 0 | AD92: =SUM(AB92/X92)-1 -> -1
B93: Changes in Working Capital:
B94: Inventories, net | C94: 357 | D94: 7102 | E94: -6550 | G94: 4077 | J94: =SUM(D94-SUM(G94:I94)) -> 3025 | K94: -593 | N94: =SUM(E94-SUM(K94:M94)) -> -5957 | S94: =SUM(G94:J94) -> 7102 | T94: =SUM(H94:K94) -> 2432 | U94: =SUM(I94:L94) -> 2432 | V94: =SUM(J94:M94) -> 2432 | W94: =SUM(K94:N94) -> -6550 | X94: =SUM(L94:O94) -> -5957 | Y94: =SUM(M94:P94) -> -5957 | Z94: =SUM(N94:Q94) -> -5957 | AA94: =SUM(O94:Q94) -> 0 | AB94: =SUM(P94:Q94) -> 0 | AD94: =SUM(AB94/X94)-1 -> -1
B95: Receivables, net | C95: -3045 | D95: 5870 | E95: -7742 | G95: 1626 | J95: =SUM(D95-SUM(G95:I95)) -> 4244 | K95: -901 | N95: =SUM(E95-SUM(K95:M95)) -> -6841 | S95: =SUM(G95:J95) -> 5870 | T95: =SUM(H95:K95) -> 3343 | U95: =SUM(I95:L95) -> 3343 | V95: =SUM(J95:M95) -> 3343 | W95: =SUM(K95:N95) -> -7742 | X95: =SUM(L95:O95) -> -6841 | Y95: =SUM(M95:P95) -> -6841 | Z95: =SUM(N95:Q95) -> -6841 | AA95: =SUM(O95:Q95) -> 0 | AB95: =SUM(P95:Q95) -> 0 | AD95: =SUM(AB95/X95)-1 -> -1
B96: Prepaid expenses and other assets | C96: -6067 | D96: 6776 | E96: -750 | G96: 5264 | J96: =SUM(D96-SUM(G96:I96)) -> 1512 | K96: 407 | N96: =SUM(E96-SUM(K96:M96)) -> -1157 | S96: =SUM(G96:J96) -> 6776 | T96: =SUM(H96:K96) -> 1919 | U96: =SUM(I96:L96) -> 1919 | V96: =SUM(J96:M96) -> 1919 | W96: =SUM(K96:N96) -> -750 | X96: =SUM(L96:O96) -> -1157 | Y96: =SUM(M96:P96) -> -1157 | Z96: =SUM(N96:Q96) -> -1157 | AA96: =SUM(O96:Q96) -> 0 | AB96: =SUM(P96:Q96) -> 0 | AD96: =SUM(AB96/X96)-1 -> -1
B97: Accounts payable and accrued expenses | C97: -335 | D97: -11083 | E97: -3480 | G97: -6265 | J97: =SUM(D97-SUM(G97:I97)) -> -4818 | K97: -810 | N97: =SUM(E97-SUM(K97:M97)) -> -2670 | S97: =SUM(G97:J97) -> -11083 | T97: =SUM(H97:K97) -> -5628 | U97: =SUM(I97:L97) -> -5628 | V97: =SUM(J97:M97) -> -5628 | W97: =SUM(K97:N97) -> -3480 | X97: =SUM(L97:O97) -> -2670 | Y97: =SUM(M97:P97) -> -2670 | Z97: =SUM(N97:Q97) -> -2670 | AA97: =SUM(O97:Q97) -> 0 | AB97: =SUM(P97:Q97) -> 0 | AD97: =SUM(AB97/X97)-1 -> -1
B98: Operating leases | C98: -5899 | D98: -5175 | E98: -3302 | G98: -1840 | J98: =SUM(D98-SUM(G98:I98)) -> -3335 | K98: -1716 | N98: =SUM(E98-SUM(K98:M98)) -> -1586 | S98: =SUM(G98:J98) -> -5175 | T98: =SUM(H98:K98) -> -5051 | U98: =SUM(I98:L98) -> -5051 | V98: =SUM(J98:M98) -> -5051 | W98: =SUM(K98:N98) -> -3302 | X98: =SUM(L98:O98) -> -1586 | Y98: =SUM(M98:P98) -> -1586 | Z98: =SUM(N98:Q98) -> -1586 | AA98: =SUM(O98:Q98) -> 0 | AB98: =SUM(P98:Q98) -> 0 | AD98: =SUM(AB98/X98)-1 -> -1
B99: Gift cards and customer deposits | C99: -1485 | D99: -1310 | E99: -2298 | G99: -799 | J99: =SUM(D99-SUM(G99:I99)) -> -511 | K99: -1502 | N99: =SUM(E99-SUM(K99:M99)) -> -796 | S99: =SUM(G99:J99) -> -1310 | T99: =SUM(H99:K99) -> -2013 | U99: =SUM(I99:L99) -> -2013 | V99: =SUM(J99:M99) -> -2013 | W99: =SUM(K99:N99) -> -2298 | X99: =SUM(L99:O99) -> -796 | Y99: =SUM(M99:P99) -> -796 | Z99: =SUM(N99:Q99) -> -796 | AA99: =SUM(O99:Q99) -> 0 | AB99: =SUM(P99:Q99) -> 0 | AD99: =SUM(AB99/X99)-1 -> -1
B100: Deferred revenue | C100: 2895 | D100: -2987 | E100: 427 | G100: -1669 | J100: =SUM(D100-SUM(G100:I100)) -> -1318 | K100: -110 | N100: =SUM(E100-SUM(K100:M100)) -> 537 | S100: =SUM(G100:J100) -> -2987 | T100: =SUM(H100:K100) -> -1428 | U100: =SUM(I100:L100) -> -1428 | V100: =SUM(J100:M100) -> -1428 | W100: =SUM(K100:N100) -> 427 | X100: =SUM(L100:O100) -> 537 | Y100: =SUM(M100:P100) -> 537 | Z100: =SUM(N100:Q100) -> 537 | AA100: =SUM(O100:Q100) -> 0 | AB100: =SUM(P100:Q100) -> 0 | AD100: =SUM(AB100/X100)-1 -> -1
B101: Net cash used in operating activities | C101: =SUM(C84:C100) -> 47276 | D101: =SUM(D84:D100) -> 64310 | E101: =SUM(E84:E100) -> 47087 | G101: =SUM(G84:G100) -> 18786 | H101: =SUM(H84:H100) -> 0 | I101: =SUM(I84:I100) -> 0 | J101: =SUM(J84:J100) -> 45524 | K101: =SUM(K84:K100) -> 10365 | L101: =SUM(L84:L100) -> 0 | M101: =SUM(M84:M100) -> 0 | N101: =SUM(N84:N100) -> 36722 | ... Q101: =SUM(Q84:Q100) -> 0 | S101: =SUM(S84:S100) -> 64310 | T101: =SUM(T84:T100) -> 55889 | U101: =SUM(U84:U100) -> 55889 | V101: =SUM(V84:V100) -> 55889 | W101: =SUM(W84:W100) -> 47087 | X101: =SUM(X84:X100) -> 36722 | Y101: =SUM(Y84:Y100) -> 36722 | Z101: =SUM(Z84:Z100) -> 36722 | ... AB101: =SUM(AB84:AB100) -> 0 | AD101: =SUM(AB101/X101)-1 -> -1
B103: Cash flows from investing activities:
B104: Capital expenditures | C104: -13634 | D104: -18295 | E104: -19317 | G104: -3065 | J104: =SUM(D104-SUM(G104:I104)) -> -15230 | K104: -2430 | N104: =SUM(E104-SUM(K104:M104)) -> -16887 | S104: =SUM(G104:J104) -> -18295 | T104: =SUM(H104:K104) -> -17660 | U104: =SUM(I104:L104) -> -17660 | V104: =SUM(J104:M104) -> -17660 | W104: =SUM(K104:N104) -> -19317 | X104: =SUM(L104:O104) -> -16887 | Y104: =SUM(M104:P104) -> -16887 | Z104: =SUM(N104:Q104) -> -16887 | AA104: =SUM(O104:Q104) -> 0 | AB104: =SUM(P104:Q104) -> 0 | AD104: =SUM(AB104/X104)-1 -> -1
B105: Net cash used in investing activities | C105: =SUM(C104:C104) -> -13634 | D105: =SUM(D104:D104) -> -18295 | E105: =SUM(E104:E104) -> -19317 | G105: =SUM(G104:G104) -> -3065 | H105: =SUM(H104:H104) -> 0 | I105: =SUM(I104:I104) -> 0 | J105: =SUM(J104:J104) -> -15230 | K105: =SUM(K104:K104) -> -2430 | L105: =SUM(L104:L104) -> 0 | M105: =SUM(M104:M104) -> 0 | N105: =SUM(N104:N104) -> -16887 | ... Q105: =SUM(Q104:Q104) -> 0 | S105: =SUM(S104:S104) -> -18295 | T105: =SUM(T104:T104) -> -17660 | U105: =SUM(U104:U104) -> -17660 | V105: =SUM(V104:V104) -> -17660 | W105: =SUM(W104:W104) -> -19317 | X105: =SUM(X104:X104) -> -16887 | Y105: =SUM(Y104:Y104) -> -16887 | Z105: =SUM(Z104:Z104) -> -16887 | ... AB105: =SUM(AB104:AB104) -> 0 | AD105: =SUM(AB105/X105)-1 -> -1
B107: Cash flows from financing activities:
B108: Proceeds from exercise of employee equity awards, net of tax | C108: -592 | D108: -1339 | E108: -1869 | G108: 94 | J108: =SUM(D108-SUM(G108:I108)) -> -1433 | K108: -1869 | N108: =SUM(E108-SUM(K108:M108)) -> 0 | S108: =SUM(G108:J108) -> -1339 | T108: =SUM(H108:K108) -> -3302 | U108: =SUM(I108:L108) -> -3302 | V108: =SUM(J108:M108) -> -3302 | W108: =SUM(K108:N108) -> -1869 | X108: =SUM(L108:O108) -> 0 | Y108: =SUM(M108:P108) -> 0 | Z108: =SUM(N108:Q108) -> 0 | AA108: =SUM(O108:Q108) -> 0 | AB108: =SUM(P108:Q108) -> 0 | AD108: =SUM(AB108/X108)-1 -> #DIV/0!
B109: Purchases of Company's common stock | C109: -24172 | D109: -20500 | E109: -31266 | G109: -3099 | J109: =SUM(D109-SUM(G109:I109)) -> -17401 | K109: -9198 | N109: =SUM(E109-SUM(K109:M109)) -> -22068 | S109: =SUM(G109:J109) -> -20500 | T109: =SUM(H109:K109) -> -26599 | U109: =SUM(I109:L109) -> -26599 | V109: =SUM(J109:M109) -> -26599 | W109: =SUM(K109:N109) -> -31266 | X109: =SUM(L109:O109) -> -22068 | Y109: =SUM(M109:P109) -> -22068 | Z109: =SUM(N109:Q109) -> -22068 | AA109: =SUM(O109:Q109) -> 0 | AB109: =SUM(P109:Q109) -> 0 | AD109: =SUM(AB109/X109)-1 -> -1
B110: Cash dividends paid on vested participating securities | C110: -292 | D110: -22062 | E110: -11024 | G110: -22098 | J110: =SUM(D110-SUM(G110:I110)) -> 36 | K110: -2911 | N110: =SUM(E110-SUM(K110:M110)) -> -8113 | S110: =SUM(G110:J110) -> -22062 | T110: =SUM(H110:K110) -> -2875 | U110: =SUM(I110:L110) -> -2875 | V110: =SUM(J110:M110) -> -2875 | W110: =SUM(K110:N110) -> -11024 | X110: =SUM(L110:O110) -> -8113 | Y110: =SUM(M110:P110) -> -8113 | Z110: =SUM(N110:Q110) -> -8113 | AA110: =SUM(O110:Q110) -> 0 | AB110: =SUM(P110:Q110) -> 0 | AD110: =SUM(AB110/X110)-1 -> -1
B111: Net cash provided by financing activities | C111: =SUM(C108:C110) -> -25056 | D111: =SUM(D108:D110) -> -43901 | E111: =SUM(E108:E110) -> -44159 | G111: =SUM(G108:G110) -> -25103 | H111: =SUM(H108:H110) -> 0 | I111: =SUM(I108:I110) -> 0 | J111: =SUM(J108:J110) -> -18798 | K111: =SUM(K108:K110) -> -13978 | L111: =SUM(L108:L110) -> 0 | M111: =SUM(M108:M110) -> 0 | N111: =SUM(N108:N110) -> -30181 | ... Q111: =SUM(Q108:Q110) -> 0 | S111: =SUM(S108:S110) -> -43901 | T111: =SUM(T108:T110) -> -32776 | U111: =SUM(U108:U110) -> -32776 | V111: =SUM(V108:V110) -> -32776 | W111: =SUM(W108:W110) -> -44159 | X111: =SUM(X108:X110) -> -30181 | Y111: =SUM(Y108:Y110) -> -30181 | Z111: =SUM(Z108:Z110) -> -30181 | ... AB111: =SUM(AB108:AB110) -> 0 | AD111: =SUM(AB111/X111)-1 -> -1
B114: Unrestricted Cash BOP | C114: 32845 | D114: =C121 -> 42198 | E114: =D121 -> 44327 | G114: =D114 -> 42198 | H114: =G121 -> 32819 | I114: =H121 -> 32819 | J114: =I121 -> 32819 | K114: =J121 -> 44327 | L114: =K121 -> 38233 | M114: =L121 -> 38233 | N114: =M121 -> 38233 | O114: =N121 -> 27758 | ... Q114: =P121 -> 27758 | S114: =J114 -> 32819 | T114: =S121 -> 44327 | U114: =T121 -> 38233 | V114: =U121 -> 38233 | W114: =V121 -> 38233 | X114: =W121 -> 27758 | Y114: =X121 -> 27758 | Z114: =Y121 -> 27758 | AA114: =Z121 -> 27758 | AB114: =AA121 -> #REF!
B115: BOP Restricted Cash Adjustment | C115: 0 | D115: =-C119 -> 0 | E115: =-D119 -> 0 | G115: =D115 -> 0 | H115: =-G119 -> 0 | I115: =-H119 -> 0 | J115: =-I119 -> 0 | K115: =-J119 -> 0 | L115: =-K119 -> 0 | M115: =-L119 -> 0 | N115: =-M119 -> 0 | O115: =-N119 -> 0 | ... Q115: =-P119 -> 0 | S115: =J115 -> 0 | T115: =-S119 -> 0 | U115: =-T119 -> 0 | V115: =-U119 -> 0 | W115: =-V119 -> 0 | X115: =-W119 -> 0 | Y115: =-X119 -> 0 | Z115: =-Y119 -> 0 | AA115: =-Z119 -> 0 | AB115: =-AA119 -> #REF!
B116: Adjusted Cash Position BOP | C116: =SUM(C114:C115) -> 32845 | D116: =SUM(D114:D115) -> 42198 | E116: =SUM(E114:E115) -> 44327 | G116: =SUM(G114:G115) -> 42198 | H116: =SUM(H114:H115) -> 32819 | I116: =SUM(I114:I115) -> 32819 | J116: =SUM(J114:J115) -> 32819 | K116: =SUM(K114:K115) -> 44327 | L116: =SUM(L114:L115) -> 38233 | M116: =SUM(M114:M115) -> 38233 | N116: =SUM(N114:N115) -> 38233 | ... Q116: =SUM(Q114:Q115) -> 27758 | S116: =SUM(S114:S115) -> 32819 | T116: =SUM(T114:T115) -> 44327 | U116: =SUM(U114:U115) -> 38233 | V116: =SUM(V114:V115) -> 38233 | W116: =SUM(W114:W115) -> 38233 | X116: =SUM(X114:X115) -> 27758 | Y116: =SUM(Y114:Y115) -> 27758 | Z116: =SUM(Z114:Z115) -> 27758 | ... AB116: =SUM(AB114:AB115) -> #REF!
B118: EOP FX Adjustment | C118: 767 | D118: 15 | E118: -180 | G118: 3 | J118: =SUM(D118-SUM(G118:I118)) -> 12 | K118: -51 | N118: =SUM(E118-SUM(K118:M118)) -> -129 | S118: =J118 -> 12 | T118: =K118 -> -51 | U118: =L118 -> 0 | V118: =M118 -> 0 | W118: =N118 -> -129 | X118: =O118 -> 0 | Y118: =P118 -> 0 | Z118: =Q118 -> 0 | AA118: =#REF! -> #REF! | AB118: =#REF! -> #REF!
B119: EOP Restricted Cash Adjustment | C119: 0 | D119: 0 | E119: 0 | J119: =D119 -> 0 | N119: =E119 -> 0 | S119: =J119 -> 0 | T119: =K119 -> 0 | U119: =L119 -> 0 | V119: =M119 -> 0 | W119: =N119 -> 0 | X119: =O119 -> 0 | Y119: =P119 -> 0 | Z119: =Q119 -> 0 | AA119: =#REF! -> #REF! | AB119: =#REF! -> #REF!
B120: Net Change in Cash | C120: =+C111+C105+C101 -> 8586 | D120: =+D111+D105+D101 -> 2114 | E120: =+E111+E105+E101 -> -16389 | G120: =+G111+G105+G101 -> -9382 | H120: =+H111+H105+H101 -> 0 | I120: =+I111+I105+I101 -> 0 | J120: =+J111+J105+J101 -> 11496 | K120: =+K111+K105+K101 -> -6043 | L120: =+L111+L105+L101 -> 0 | M120: =+M111+M105+M101 -> 0 | N120: =+N111+N105+N101 -> -10346 | ... Q120: =+Q111+Q105+Q101 -> 0 | S120: =J120 -> 11496 | T120: =K120 -> -6043 | U120: =L120 -> 0 | V120: =M120 -> 0 | W120: =N120 -> -10346 | X120: =O120 -> 0 | Y120: =P120 -> 0 | Z120: =Q120 -> 0 | AA120: =#REF! -> #REF! | AB120: =#REF! -> #REF!
B121: Adjusted Cash Position EOP | C121: =SUM(C116:C120) -> 42198 | D121: =SUM(D116:D120) -> 44327 | E121: =SUM(E116:E120) -> 27758 | G121: =SUM(G116:G120) -> 32819 | H121: =SUM(H116:H120) -> 32819 | I121: =SUM(I116:I120) -> 32819 | J121: =SUM(J116:J120) -> 44327 | K121: =SUM(K116:K120) -> 38233 | L121: =SUM(L116:L120) -> 38233 | M121: =SUM(M116:M120) -> 38233 | N121: =SUM(N116:N120) -> 27758 | ... Q121: =SUM(Q116:Q120) -> 27758 | S121: =SUM(S116:S120) -> 44327 | T121: =SUM(T116:T120) -> 38233 | U121: =SUM(U116:U120) -> 38233 | V121: =SUM(V116:V120) -> 38233 | W121: =SUM(W116:W120) -> 27758 | X121: =SUM(X116:X120) -> 27758 | Y121: =SUM(Y116:Y120) -> 27758 | Z121: =SUM(Z116:Z120) -> 27758 | ... AB121: =SUM(AB116:AB120) -> #REF!
B123: Balance Check | C123: =C121-C42 -> 0 | D123: =D121-D42 -> 0 | E123: =E121-E42 -> 0 | G123: =G121-G42 -> 0 | H123: =H121-H42 -> 32819 | I123: =I121-I42 -> 32819 | J123: =J121-J42 -> 0 | K123: =K121-K42 -> 0 | L123: =L121-L42 -> 38233 | M123: =M121-M42 -> 38233 | N123: =N121-N42 -> 0 | ... Q123: =Q121-Q42 -> 27758 | S123: =S121-S42 -> 0 | T123: =T121-T42 -> 0 | U123: =U121-U42 -> 38233 | V123: =V121-V42 -> 38233 | W123: =W121-W42 -> 0 | X123: =X121-X42 -> 27758 | Y123: =Y121-Y42 -> 27758 | Z123: =Z121-Z42 -> 27758 | ... AB123: =AB121-AB42 -> #REF!
B125: Supplemental disclosures of other cash flow information:
B126: Interest paid | C126: 0 | D126: 0 | E126: 0 | G126: 0 | H126: 0 | I126: 0 | J126: =SUM(C126-SUM(G126:I126)) -> 0 | K126: 0 | L126: 0 | M126: 0 | N126: =SUM(D126-SUM(K126:M126)) -> 0 | O126: 0 | P126: 0 | Q126: 0 | S126: =SUM(I126:L126) -> 0 | T126: =SUM(J126:M126) -> 0 | U126: =SUM(K126:N126) -> 0 | V126: =SUM(L126:O126) -> 0 | W126: =SUM(M126:P126) -> 0 | X126: =SUM(N126:Q126) -> 0 | Y126: =SUM(O126:Q126) -> 0 | Z126: =SUM(P126:Q126) -> 0 | AA126: =SUM(Q126:Q126) -> 0 | AB126: =SUM(#REF!) -> #REF!
B127: Income taxes paid | C127: 10327 | D127: 17364 | E127: 16693 | G127: 646 | J127: =SUM(C127-SUM(G127:I127)) -> 9681 | K127: 210 | N127: =SUM(D127-SUM(K127:M127)) -> 17154 | S127: =SUM(I127:L127) -> 9891 | T127: =SUM(J127:M127) -> 9891 | U127: =SUM(K127:N127) -> 17364 | V127: =SUM(L127:O127) -> 17154 | W127: =SUM(M127:P127) -> 17154 | X127: =SUM(N127:Q127) -> 17154 | Y127: =SUM(O127:Q127) -> 0 | Z127: =SUM(P127:Q127) -> 0 | AA127: =SUM(Q127:Q127) -> 0 | AB127: =SUM(#REF!) -> #REF!

Sheet Revenue Drivers
B2: ='Historical Financials'!B2 -> Build-A-Bear Workshop, Inc (NYSE: BBW) | M2: Quarterly | X2: LTM
B3: Segment Anaysis | C3: ='Historical Financials'!C7 -> 2022 | D3: ='Historical Financials'!D7 -> 2023 | E3: ='Historical Financials'!E7 -> 2024 | G3: ='Historical Financials'!G7 -> 1Q23 | H3: ='Historical Financials'!H7 -> 2Q23 | I3: ='Historical Financials'!I7 -> 3Q23 | J3: ='Historical Financials'!J7 -> 4Q23 | K3: ='Historical Financials'!K7 -> 1Q24 | L3: ='Historical Financials'!L7 -> 2Q24 | M3: ='Historical Financials'!M7 -> 3Q24 | N3: ='Historical Financials'!N7 -> 4Q24 | ... Q3: ='Historical Financials'!Q7 -> 3Q25 | S3: =J3 -> 4Q23 | T3: =K3 -> 1Q24 | U3: =L3 -> 2Q24 | V3: =M3 -> 3Q24 | W3: =N3 -> 4Q24 | X3: =O3 -> 1Q25 | Y3: =P3 -> 2Q25 | Z3: =Q3 -> 3Q25 | AA3: =#REF! -> #REF! | AB3: =#REF! -> #REF!
B4: ($ In Millions) | C4: ='Historical Financials'!C8 -> 44954 | D4: ='Historical Financials'!D8 -> 45325 | E4: ='Historical Financials'!E8 -> 45689 | G4: ='Historical Financials'!G8 -> 45045 | H4: ='Historical Financials'!H8 -> 45136 | I4: ='Historical Financials'!I8 -> 45227 | J4: ='Historical Financials'!J8 -> 45325 | K4: ='Historical Financials'!K8 -> 45416 | L4: ='Historical Financials'!L8 -> 45507 | M4: ='Historical Financials'!M8 -> 45598 | N4: ='Historical Financials'!N8 -> 45689 | ... Q4: ='Historical Financials'!Q8 -> 45962 | S4: =J4 -> 45325 | T4: =K4 -> 45416 | U4: =L4 -> 45507 | V4: =M4 -> 45598 | W4: =N4 -> 45689 | X4: =O4 -> 45780 | Y4: =P4 -> 45871 | Z4: =Q4 -> 45962 | AA4: =#REF! -> #REF! | AB4: =#REF! -> #REF!
A6: X | B6: Revenue by reportable segment
A8: X | B8: Revenue Segment Anaysis
B9: Net retail sales | C9: 446181 | D9: 456163 | E9: 460325 | G9: 112096 | J9: =SUM(C9-SUM(G9:I9)) -> 334085 | K9: 107868 | N9: =SUM(D9-SUM(K9:M9)) -> 348295 | S9: =SUM(G9:J9) -> 446181 | T9: =SUM(H9:K9) -> 441953 | U9: =SUM(I9:L9) -> 441953 | V9: =SUM(J9:M9) -> 441953 | W9: =SUM(K9:N9) -> 456163 | X9: =SUM(L9:O9) -> 348295 | Y9: =SUM(M9:P9) -> 348295 | Z9: =SUM(N9:Q9) -> 348295 | AA9: =SUM(O9:Q9) -> 0 | AB9: =SUM(P9:Q9) -> 0
B10: Commercial revenue | C10: 18523 | D10: 25413 | E10: 31387 | G10: 6688 | J10: =SUM(C10-SUM(G10:I10)) -> 11835 | K10: 5985 | N10: =SUM(D10-SUM(K10:M10)) -> 19428
B11: International franchising | C11: 3233 | D11: 4538 | E11: 4692 | G11: 1266 | J11: =SUM(C11-SUM(G11:I11)) -> 1967 | K11: 877 | N11: =SUM(D11-SUM(K11:M11)) -> 3661 | S11: =SUM(G11:J11) -> 3233 | T11: =SUM(H11:K11) -> 2844 | U11: =SUM(I11:L11) -> 2844 | V11: =SUM(J11:M11) -> 2844 | W11: =SUM(K11:N11) -> 4538 | X11: =SUM(L11:O11) -> 3661 | Y11: =SUM(M11:P11) -> 3661 | Z11: =SUM(N11:Q11) -> 3661 | AA11: =SUM(O11:Q11) -> 0 | AB11: =SUM(P11:Q11) -> 0
B12: Total Net Revenue | C12: =SUM(C9:C11) -> 467937 | D12: =SUM(D9:D11) -> 486114 | E12: =SUM(E9:E11) -> 496404 | G12: =SUM(G9:G11) -> 120050 | H12: =SUM(H9:H11) -> 0 | I12: =SUM(I9:I11) -> 0 | J12: =SUM(J9:J11) -> 347887 | K12: =SUM(K9:K11) -> 114730 | L12: =SUM(L9:L11) -> 0 | M12: =SUM(M9:M11) -> 0 | N12: =SUM(N9:N11) -> 371384 | ... Q12: =SUM(Q9:Q11) -> 0 | S12: =SUM(S9:S11) -> 449414 | T12: =SUM(T9:T11) -> 444797 | U12: =SUM(U9:U11) -> 444797 | V12: =SUM(V9:V11) -> 444797 | W12: =SUM(W9:W11) -> 460701 | X12: =SUM(X9:X11) -> 351956 | Y12: =SUM(Y9:Y11) -> 351956 | Z12: =SUM(Z9:Z11) -> 351956 | ... AB12: =SUM(AB9:AB11) -> 0
B13: Balance Check | C13: =+C12-'Historical Financials'!C11 -> 0 | D13: =+D12-'Historical Financials'!D11 -> 0 | E13: =+E12-'Historical Financials'!E11 -> 0 | G13: =+G12-'Historical Financials'!G11 -> 0 | H13: =+H12-'Historical Financials'!H11 -> 0 | I13: =+I12-'Historical Financials'!I11 -> 0 | J13: =+J12-'Historical Financials'!J11 -> -18177 | K13: =+K12-'Historical Financials'!K11 -> 0 | L13: =+L12-'Historical Financials'!L11 -> 0 | M13: =+M12-'Historical Financials'!M11 -> 0 | N13: =+N12-'Historical Financials'!N11 -> -10290 | ... Q13: =+Q12-'Historical Financials'!Q11 -> 0 | S13: =+S12-'Historical Financials'!S11 -> -36700 | T13: =+T12-'Historical Financials'!T11 -> -35997 | U13: =+U12-'Historical Financials'!U11 -> -35997 | V13: =+V12-'Historical Financials'!V11 -> -35997 | W13: =+W12-'Historical Financials'!W11 -> -35703 | X13: =+X12-'Historical Financials'!X11 -> -29718 | Y13: =+Y12-'Historical Financials'!Y11 -> -29718 | Z13: =+Z12-'Historical Financials'!Z11 -> -29718 | ... AB13: =+AB12-'Historical Financials'!AB11 -> 0
B15: =B9&"(%)" -> Net retail sales (%) | C15: =SUM(C9/C$12) -> 0.95350656 | D15: =SUM(D9/D$12) -> 0.93838688 | E15: =SUM(E9/E$12) -> 0.92731928 | G15: =SUM(G9/G$12) -> 0.93374427 | H15: =SUM(H9/H$12) -> #DIV/0! | I15: =SUM(I9/I$12) -> #DIV/0! | J15: =SUM(J9/J$12) -> 0.9603262 | K15: =SUM(K9/K$12) -> 0.94019001 | L15: =SUM(L9/L$12) -> #DIV/0! | M15: =SUM(M9/M$12) -> #DIV/0! | N15: =SUM(N9/N$12) -> 0.93782985 | ... Q15: =SUM(Q9/Q$12) -> #DIV/0! | S15: =H15 -> #DIV/0! | T15: =I15 -> #DIV/0! | U15: =J15 -> 0.9603262 | V15: =K15 -> 0.94019001 | W15: =L15 -> #DIV/0! | X15: =M15 -> #DIV/0! | Y15: =N15 -> 0.93782985 | Z15: =O15 -> #DIV/0! | ... AB15: =Q15 -> #DIV/0!
B16: =B10&"(%)" -> Commercial revenue (%) | C16: =SUM(C10/C$12) -> 0.039584388 | D16: =SUM(D10/D$12) -> 0.052277861 | E16: =SUM(E10/E$12) -> 0.063228741 | G16: =SUM(G10/G$12) -> 0.055710121 | H16: =SUM(H10/H$12) -> #DIV/0! | I16: =SUM(I10/I$12) -> #DIV/0! | J16: =SUM(J10/J$12) -> 0.034019667 | K16: =SUM(K10/K$12) -> 0.052165955 | L16: =SUM(L10/L$12) -> #DIV/0! | M16: =SUM(M10/M$12) -> #DIV/0! | N16: =SUM(N10/N$12) -> 0.052312431 | ... Q16: =SUM(Q10/Q$12) -> #DIV/0! | S16: =H16 -> #DIV/0! | T16: =I16 -> #DIV/0! | U16: =J16 -> 0.034019667 | V16: =K16 -> 0.052165955 | W16: =L16 -> #DIV/0! | X16: =M16 -> #DIV/0! | Y16: =N16 -> 0.052312431 | Z16: =O16 -> #DIV/0! | ... AB16: =Q16 -> #DIV/0!
B17: =B11&"(%)" -> International franchising (%) | C17: =SUM(C11/C$12) -> 0.0069090497 | D17: =SUM(D11/D$12) -> 0.0093352588 | E17: =SUM(E11/E$12) -> 0.0094519786 | G17: =SUM(G11/G$12) -> 0.010545606 | H17: =SUM(H11/H$12) -> #DIV/0! | I17: =SUM(I11/I$12) -> #DIV/0! | J17: =SUM(J11/J$12) -> 0.0056541348 | K17: =SUM(K11/K$12) -> 0.0076440338 | L17: =SUM(L11/L$12) -> #DIV/0! | M17: =SUM(M11/M$12) -> #DIV/0! | N17: =SUM(N11/N$12) -> 0.0098577214 | ... Q17: =SUM(Q11/Q$12) -> #DIV/0! | S17: =H17 -> #DIV/0! | T17: =I17 -> #DIV/0! | U17: =J17 -> 0.0056541348 | V17: =K17 -> 0.0076440338 | W17: =L17 -> #DIV/0! | X17: =M17 -> #DIV/0! | Y17: =N17 -> 0.0098577214 | Z17: =O17 -> #DIV/0! | ... AB17: =Q17 -> #DIV/0!
A19: X | B19: Revenue by product category
A21: X | B21: Revenue by XXX
B22: XXX | J22: =SUM(C22-SUM(G22:I22)) -> 0 | N22: =SUM(D22-SUM(K22:M22)) -> 0 | S22: =SUM(G22:J22) -> 0 | T22: =SUM(H22:K22) -> 0 | U22: =SUM(I22:L22) -> 0 | V22: =SUM(J22:M22) -> 0 | W22: =SUM(K22:N22) -> 0 | X22: =SUM(L22:O22) -> 0 | Y22: =SUM(M22:P22) -> 0 | Z22: =SUM(N22:Q22) -> 0 | AA22: =SUM(O22:Q22) -> 0 | AB22: =SUM(P22:Q22) -> 0
B23: XXX | J23: =SUM(C23-SUM(G23:I23)) -> 0 | N23: =SUM(D23-SUM(K23:M23)) -> 0 | S23: =SUM(G23:J23) -> 0 | T23: =SUM(H23:K23) -> 0 | U23: =SUM(I23:L23) -> 0 | V23: =SUM(J23:M23) -> 0 | W23: =SUM(K23:N23) -> 0 | X23: =SUM(L23:O23) -> 0 | Y23: =SUM(M23:P23) -> 0 | Z23: =SUM(N23:Q23) -> 0 | AA23: =SUM(O23:Q23) -> 0 | AB23: =SUM(P23:Q23) -> 0
B24: XXX | J24: =SUM(C24-SUM(G24:I24)) -> 0 | N24: =SUM(D24-SUM(K24:M24)) -> 0 | S24: =SUM(G24:J24) -> 0 | T24: =SUM(H24:K24) -> 0 | U24: =SUM(I24:L24) -> 0 | V24: =SUM(J24:M24) -> 0 | W24: =SUM(K24:N24) -> 0 | X24: =SUM(L24:O24) -> 0 | Y24: =SUM(M24:P24) -> 0 | Z24: =SUM(N24:Q24) -> 0 | AA24: =SUM(O24:Q24) -> 0 | AB24: =SUM(P24:Q24) -> 0
B25: XXX | J25: =SUM(C25-SUM(G25:I25)) -> 0 | N25: =SUM(D25-SUM(K25:M25)) -> 0 | S25: =SUM(G25:J25) -> 0 | T25: =SUM(H25:K25) -> 0 | U25: =SUM(I25:L25) -> 0 | V25: =SUM(J25:M25) -> 0 | W25: =SUM(K25:N25) -> 0 | X25: =SUM(L25:O25) -> 0 | Y25: =SUM(M25:P25) -> 0 | Z25: =SUM(N25:Q25) -> 0 | AA25: =SUM(O25:Q25) -> 0 | AB25: =SUM(P25:Q25) -> 0
B26: XXX | J26: =SUM(C26-SUM(G26:I26)) -> 0 | N26: =SUM(D26-SUM(K26:M26)) -> 0 | S26: =SUM(G26:J26) -> 0 | T26: =SUM(H26:K26) -> 0 | U26: =SUM(I26:L26) -> 0 | V26: =SUM(J26:M26) -> 0 | W26: =SUM(K26:N26) -> 0 | X26: =SUM(L26:O26) -> 0 | Y26: =SUM(M26:P26) -> 0 | Z26: =SUM(N26:Q26) -> 0 | AA26: =SUM(O26:Q26) -> 0 | AB26: =SUM(P26:Q26) -> 0
B27: XXX | J27: =SUM(C27-SUM(G27:I27)) -> 0 | N27: =SUM(D27-SUM(K27:M27)) -> 0 | S27: =SUM(G27:J27) -> 0 | T27: =SUM(H27:K27) -> 0 | U27: =SUM(I27:L27) -> 0 | V27: =SUM(J27:M27) -> 0 | W27: =SUM(K27:N27) -> 0 | X27: =SUM(L27:O27) -> 0 | Y27: =SUM(M27:P27) -> 0 | Z27: =SUM(N27:Q27) -> 0 | AA27: =SUM(O27:Q27) -> 0 | AB27: =SUM(P27:Q27) -> 0
B28: Total Revenue | C28: =SUM(C22:C27) -> 0 | D28: =SUM(D22:D27) -> 0 | E28: =SUM(E22:E27) -> 0 | G28: =SUM(G22:G27) -> 0 | H28: =SUM(H22:H27) -> 0 | I28: =SUM(I22:I27) -> 0 | J28: =SUM(J22:J27) -> 0 | K28: =SUM(K22:K27) -> 0 | L28: =SUM(L22:L27) -> 0 | M28: =SUM(M22:M27) -> 0 | N28: =SUM(N22:N27) -> 0 | ... Q28: =SUM(Q22:Q27) -> 0 | S28: =SUM(S22:S27) -> 0 | T28: =SUM(T22:T27) -> 0 | U28: =SUM(U22:U27) -> 0 | V28: =SUM(V22:V27) -> 0 | W28: =SUM(W22:W27) -> 0 | X28: =SUM(X22:X27) -> 0 | Y28: =SUM(Y22:Y27) -> 0 | Z28: =SUM(Z22:Z27) -> 0 | ... AB28: =SUM(AB22:AB27) -> 0
B29: Balance Check | C29: =+C28-C12 -> -467937 | D29: =+D28-D12 -> -486114 | E29: =+E28-E12 -> -496404 | G29: =+G28-G12 -> -120050 | H29: =+H28-H12 -> 0 | I29: =+I28-I12 -> 0 | J29: =+J28-J12 -> -347887 | K29: =+K28-K12 -> -114730 | L29: =+L28-L12 -> 0 | M29: =+M28-M12 -> 0 | N29: =+N28-N12 -> -371384 | ... Q29: =+Q28-Q12 -> 0 | S29: =+S28-S12 -> -449414 | T29: =+T28-T12 -> -444797 | U29: =+U28-U12 -> -444797 | V29: =+V28-V12 -> -444797 | W29: =+W28-W12 -> -460701 | X29: =+X28-X12 -> -351956 | Y29: =+Y28-Y12 -> -351956 | Z29: =+Z28-Z12 -> -351956 | ... AB29: =+AB28-AB12 -> 0
B31: =B22&"(%)" -> XXX(%) | C31: =C22/C$28 -> #DIV/0! | D31: =D22/D$28 -> #DIV/0! | E31: =E22/E$28 -> #DIV/0! | G31: =G22/G$28 -> #DIV/0! | H31: =H22/H$28 -> #DIV/0! | I31: =I22/I$28 -> #DIV/0! | J31: =J22/J$28 -> #DIV/0! | K31: =K22/K$28 -> #DIV/0! | L31: =L22/L$28 -> #DIV/0! | M31: =M22/M$28 -> #DIV/0! | N31: =N22/N$28 -> #DIV/0! | ... Q31: =Q22/Q$28 -> #DIV/0! | S31: =S22/S$28 -> #DIV/0! | T31: =T22/T$28 -> #DIV/0! | U31: =U22/U$28 -> #DIV/0! | V31: =V22/V$28 -> #DIV/0! | W31: =W22/W$28 -> #DIV/0! | X31: =X22/X$28 -> #DIV/0! | Y31: =Y22/Y$28 -> #DIV/0! | Z31: =Z22/Z$28 -> #DIV/0! | ... AB31: =AB22/AB$28 -> #DIV/0!
B32: =B23&"(%)" -> XXX(%) | C32: =C23/C$28 -> #DIV/0! | D32: =D23/D$28 -> #DIV/0! | E32: =E23/E$28 -> #DIV/0! | G32: =G23/G$28 -> #DIV/0! | H32: =H23/H$28 -> #DIV/0! | I32: =I23/I$28 -> #DIV/0! | J32: =J23/J$28 -> #DIV/0! | K32: =K23/K$28 -> #DIV/0! | L32: =L23/L$28 -> #DIV/0! | M32: =M23/M$28 -> #DIV/0! | N32: =N23/N$28 -> #DIV/0! | ... Q32: =Q23/Q$28 -> #DIV/0! | S32: =S23/S$28 -> #DIV/0! | T32: =T23/T$28 -> #DIV/0! | U32: =U23/U$28 -> #DIV/0! | V32: =V23/V$28 -> #DIV/0! | W32: =W23/W$28 -> #DIV/0! | X32: =X23/X$28 -> #DIV/0! | Y32: =Y23/Y$28 -> #DIV/0! | Z32: =Z23/Z$28 -> #DIV/0! | ... AB32: =AB23/AB$28 -> #DIV/0!
B33: =B24&"(%)" -> XXX(%) | C33: =C24/C$28 -> #DIV/0! | D33: =D24/D$28 -> #DIV/0! | E33: =E24/E$28 -> #DIV/0! | G33: =G24/G$28 -> #DIV/0! | H33: =H24/H$28 -> #DIV/0! | I33: =I24/I$28 -> #DIV/0! | J33: =J24/J$28 -> #DIV/0! | K33: =K24/K$28 -> #DIV/0! | L33: =L24/L$28 -> #DIV/0! | M33: =M24/M$28 -> #DIV/0! | N33: =N24/N$28 -> #DIV/0! | ... Q33: =Q24/Q$28 -> #DIV/0! | S33: =S24/S$28 -> #DIV/0! | T33: =T24/T$28 -> #DIV/0! | U33: =U24/U$28 -> #DIV/0! | V33: =V24/V$28 -> #DIV/0! | W33: =W24/W$28 -> #DIV/0! | X33: =X24/X$28 -> #DIV/0! | Y33: =Y24/Y$28 -> #DIV/0! | Z33: =Z24/Z$28 -> #DIV/0! | ... AB33: =AB24/AB$28 -> #DIV/0!
B34: =B25&"(%)" -> XXX(%) | C34: =C25/C$28 -> #DIV/0! | D34: =D25/D$28 -> #DIV/0! | E34: =E25/E$28 -> #DIV/0! | G34: =G25/G$28 -> #DIV/0! | H34: =H25/H$28 -> #DIV/0! | I34: =I25/I$28 -> #DIV/0! | J34: =J25/J$28 -> #DIV/0! | K34: =K25/K$28 -> #DIV/0! | L34: =L25/L$28 -> #DIV/0! | M34: =M25/M$28 -> #DIV/0! | N34: =N25/N$28 -> #DIV/0! | ... Q34: =Q25/Q$28 -> #DIV/0! | S34: =S25/S$28 -> #DIV/0! | T34: =T25/T$28 -> #DIV/0! | U34: =U25/U$28 -> #DIV/0! | V34: =V25/V$28 -> #DIV/0! | W34: =W25/W$28 -> #DIV/0! | X34: =X25/X$28 -> #DIV/0! | Y34: =Y25/Y$28 -> #DIV/0! | Z34: =Z25/Z$28 -> #DIV/0! | ... AB34: =AB25/AB$28 -> #DIV/0!
B35: =B26&"(%)" -> XXX(%) | C35: =C26/C$28 -> #DIV/0! | D35: =D26/D$28 -> #DIV/0! | E35: =E26/E$28 -> #DIV/0! | G35: =G26/G$28 -> #DIV/0! | H35: =H26/H$28 -> #DIV/0! | I35: =I26/I$28 -> #DIV/0! | J35: =J26/J$28 -> #DIV/0! | K35: =K26/K$28 -> #DIV/0! | L35: =L26/L$28 -> #DIV/0! | M35: =M26/M$28 -> #DIV/0! | N35: =N26/N$28 -> #DIV/0! | ... Q35: =Q26/Q$28 -> #DIV/0! | S35: =S26/S$28 -> #DIV/0! | T35: =T26/T$28 -> #DIV/0! | U35: =U26/U$28 -> #DIV/0! | V35: =V26/V$28 -> #DIV/0! | W35: =W26/W$28 -> #DIV/0! | X35: =X26/X$28 -> #DIV/0! | Y35: =Y26/Y$28 -> #DIV/0! | Z35: =Z26/Z$28 -> #DIV/0! | ... AB35: =AB26/AB$28 -> #DIV/0!
B36: =B27&"(%)" -> XXX(%) | C36: =C27/C$28 -> #DIV/0! | D36: =D27/D$28 -> #DIV/0! | E36: =E27/E$28 -> #DIV/0! | G36: =G27/G$28 -> #DIV/0! | H36: =H27/H$28 -> #DIV/0! | I36: =I27/I$28 -> #DIV/0! | J36: =J27/J$28 -> #DIV/0! | K36: =K27/K$28 -> #DIV/0! | L36: =L27/L$28 -> #DIV/0! | M36: =M27/M$28 -> #DIV/0! | N36: =N27/N$28 -> #DIV/0! | ... Q36: =Q27/Q$28 -> #DIV/0! | S36: =S27/S$28 -> #DIV/0! | T36: =T27/T$28 -> #DIV/0! | U36: =U27/U$28 -> #DIV/0! | V36: =V27/V$28 -> #DIV/0! | W36: =W27/W$28 -> #DIV/0! | X36: =X27/X$28 -> #DIV/0! | Y36: =Y27/Y$28 -> #DIV/0! | Z36: =Z27/Z$28 -> #DIV/0! | ... AB36: =AB27/AB$28 -> #DIV/0!

Sheet FCF
B2: ='Historical Financials'!B2 -> Build-A-Bear Workshop, Inc (NYSE: BBW) | D2: FYE | H2: Quarterly | R2: Quarterly | Z2: LTM | AA2: LTM | AG2: Variance
B3: FCF Analysis | C3: ='Historical Financials'!#REF! -> #REF! | D3: ='Historical Financials'!C7 -> 2022 | E3: ='Historical Financials'!D7 -> 2023 | F3: ='Historical Financials'!E7 -> 2024 | H3: ='Historical Financials'!G7 -> 1Q23 | I3: ='Historical Financials'!H7 -> 2Q23 | J3: ='Historical Financials'!I7 -> 3Q23 | K3: ='Historical Financials'!J7 -> 4Q23 | L3: ='Historical Financials'!K7 -> 1Q24 | M3: ='Historical Financials'!L7 -> 2Q24 | N3: ='Historical Financials'!M7 -> 3Q24 | O3: ='Historical Financials'!N7 -> 4Q24 | ... R3: ='Historical Financials'!Q7 -> 3Q25 | S3: ='Historical Financials'!#REF! -> #REF! | T3: ='Historical Financials'!#REF! -> #REF! | V3: =K3 -> 4Q23 | W3: =L3 -> 1Q24 | X3: =M3 -> 2Q24 | Y3: =N3 -> 3Q24 | Z3: =O3 -> 4Q24 | AA3: =P3 -> 1Q25 | AB3: =Q3 -> 2Q25 | AC3: =R3 -> 3Q25 | ... AE3: =T3 -> #REF!
B4: ($ In Millions) | C4: ='Historical Financials'!#REF! -> #REF! | D4: ='Historical Financials'!C8 -> 44954 | E4: ='Historical Financials'!D8 -> 45325 | F4: ='Historical Financials'!E8 -> 45689 | H4: ='Historical Financials'!G8 -> 45045 | I4: ='Historical Financials'!H8 -> 45136 | J4: ='Historical Financials'!I8 -> 45227 | K4: ='Historical Financials'!J8 -> 45325 | L4: ='Historical Financials'!K8 -> 45416 | M4: ='Historical Financials'!L8 -> 45507 | N4: ='Historical Financials'!M8 -> 45598 | O4: ='Historical Financials'!N8 -> 45689 | ... R4: ='Historical Financials'!Q8 -> 45962 | S4: ='Historical Financials'!#REF! -> #REF! | T4: ='Historical Financials'!#REF! -> #REF! | V4: =K4 -> 45325 | W4: =L4 -> 45416 | X4: =M4 -> 45507 | Y4: =N4 -> 45598 | Z4: =O4 -> 45689 | AA4: =P4 -> 45780 | AB4: =Q4 -> 45871 | AC4: =R4 -> 45962 | ... AE4: =T4 -> #REF!
B6: XXX | V6: =SUM(H6:K6) -> 0 | W6: =SUM(I6:L6) -> 0 | X6: =SUM(J6:M6) -> 0 | Y6: =SUM(K6:N6) -> 0 | Z6: =SUM(L6:O6) -> 0 | AA6: =SUM(M6:P6) -> 0 | AB6: =SUM(N6:Q6) -> 0 | AC6: =SUM(O6:R6) -> 0 | ... AE6: =SUM(Q6:T6) -> 0 | AG6: =SUM(AE6/AA6)-1 -> #DIV/0!
B7: XXX | V7: =SUM(H7:K7) -> 0 | W7: =SUM(I7:L7) -> 0 | X7: =SUM(J7:M7) -> 0 | Y7: =SUM(K7:N7) -> 0 | Z7: =SUM(L7:O7) -> 0 | AA7: =SUM(M7:P7) -> 0 | AB7: =SUM(N7:Q7) -> 0 | AC7: =SUM(O7:R7) -> 0 | ... AE7: =SUM(Q7:T7) -> 0 | AG7: =SUM(AE7/AA7)-1 -> #DIV/0!
B8: XXX | V8: =SUM(H8:K8) -> 0 | W8: =SUM(I8:L8) -> 0 | X8: =SUM(J8:M8) -> 0 | Y8: =SUM(K8:N8) -> 0 | Z8: =SUM(L8:O8) -> 0 | AA8: =SUM(M8:P8) -> 0 | AB8: =SUM(N8:Q8) -> 0 | AC8: =SUM(O8:R8) -> 0 | ... AE8: =SUM(Q8:T8) -> 0 | AG8: =SUM(AE8/AA8)-1 -> #DIV/0!
B9: XXX | V9: =SUM(H9:K9) -> 0 | W9: =SUM(I9:L9) -> 0 | X9: =SUM(J9:M9) -> 0 | Y9: =SUM(K9:N9) -> 0 | Z9: =SUM(L9:O9) -> 0 | AA9: =SUM(M9:P9) -> 0 | AB9: =SUM(N9:Q9) -> 0 | AC9: =SUM(O9:R9) -> 0 | ... AE9: =SUM(Q9:T9) -> 0 | AG9: =SUM(AE9/AA9)-1 -> #DIV/0!
B10: XXX | V10: =SUM(H10:K10) -> 0 | W10: =SUM(I10:L10) -> 0 | X10: =SUM(J10:M10) -> 0 | Y10: =SUM(K10:N10) -> 0 | Z10: =SUM(L10:O10) -> 0 | AA10: =SUM(M10:P10) -> 0 | AB10: =SUM(N10:Q10) -> 0 | AC10: =SUM(O10:R10) -> 0 | ... AE10: =SUM(Q10:T10) -> 0 | AG10: =SUM(AE10/AA10)-1 -> #DIV/0!
B11: XXX | V11: =SUM(H11:K11) -> 0 | W11: =SUM(I11:L11) -> 0 | X11: =SUM(J11:M11) -> 0 | Y11: =SUM(K11:N11) -> 0 | Z11: =SUM(L11:O11) -> 0 | AA11: =SUM(M11:P11) -> 0 | AB11: =SUM(N11:Q11) -> 0 | AC11: =SUM(O11:R11) -> 0 | ... AE11: =SUM(Q11:T11) -> 0 | AG11: =SUM(AE11/AA11)-1 -> #DIV/0!
B12: Total Revenue | C12: =SUM(C6:C11) -> 0 | D12: =SUM(D6:D11) -> 0 | E12: =SUM(E6:E11) -> 0 | F12: =SUM(F6:F11) -> 0 | H12: =SUM(H6:H11) -> 0 | I12: =SUM(I6:I11) -> 0 | J12: =SUM(J6:J11) -> 0 | K12: =SUM(K6:K11) -> 0 | L12: =SUM(L6:L11) -> 0 | M12: =SUM(M6:M11) -> 0 | N12: =SUM(N6:N11) -> 0 | O12: =SUM(O6:O11) -> 0 | ... T12: =SUM(T6:T11) -> 0 | V12: =SUM(V6:V11) -> 0 | W12: =SUM(W6:W11) -> 0 | X12: =SUM(X6:X11) -> 0 | Y12: =SUM(Y6:Y11) -> 0 | Z12: =SUM(Z6:Z11) -> 0 | AA12: =SUM(AA6:AA11) -> 0 | AB12: =SUM(AB6:AB11) -> 0 | AC12: =SUM(AC6:AC11) -> 0 | ... AE12: =SUM(AE6:AE11) -> 0 | AG12: =SUM(AE12/AA12)-1 -> #DIV/0!
B13: Y/Y Growth (%) | C13: =SUM(C12/#REF!)-1 -> #REF! | D13: =SUM(D12/C12)-1 -> #DIV/0! | E13: =SUM(E12/D12)-1 -> #DIV/0! | F13: =SUM(F12/E12)-1 -> #DIV/0! | L13: =SUM(L12/H12)-1 -> #DIV/0! | M13: =SUM(M12/I12)-1 -> #DIV/0! | N13: =SUM(N12/J12)-1 -> #DIV/0! | O13: =SUM(O12/K12)-1 -> #DIV/0! | P13: =SUM(P12/L12)-1 -> #DIV/0! | Q13: =SUM(Q12/M12)-1 -> #DIV/0! | R13: =SUM(R12/N12)-1 -> #DIV/0! | S13: =SUM(S12/O12)-1 -> #DIV/0! | T13: =SUM(T12/P12)-1 -> #DIV/0! | Z13: =SUM(Z12/V12)-1 -> #DIV/0! | AA13: =SUM(AA12/W12)-1 -> #DIV/0! | AB13: =SUM(AB12/X12)-1 -> #DIV/0! | AC13: =SUM(AC12/Y12)-1 -> #DIV/0! | AD13: =SUM(AD12/Z12)-1 -> #DIV/0! | AE13: =SUM(AE12/AA12)-1 -> #DIV/0! | AG13: =SUM(AE13-AA13)*10000 -> #DIV/0!
B14: Q/Q Growth (%) | C14: N/A | D14: N/A | E14: N/A | F14: N/A | I14: =SUM(I12/H12)-1 -> #DIV/0! | J14: =SUM(J12/I12)-1 -> #DIV/0! | K14: =SUM(K12/J12)-1 -> #DIV/0! | L14: =SUM(L12/K12)-1 -> #DIV/0! | M14: =SUM(M12/L12)-1 -> #DIV/0! | N14: =SUM(N12/M12)-1 -> #DIV/0! | O14: =SUM(O12/N12)-1 -> #DIV/0! | P14: =SUM(P12/O12)-1 -> #DIV/0! | ... T14: =SUM(T12/S12)-1 -> #DIV/0! | V14: N/A | W14: N/A | X14: N/A | Y14: N/A | Z14: N/A | AA14: N/A | AB14: N/A | AC14: N/A | AD14: N/A | AE14: N/A
B16: (-) Cost of Sales | V16: =SUM(H16:K16) -> 0 | W16: =SUM(I16:L16) -> 0 | X16: =SUM(J16:M16) -> 0 | Y16: =SUM(K16:N16) -> 0 | Z16: =SUM(L16:O16) -> 0 | AA16: =SUM(M16:P16) -> 0 | AB16: =SUM(N16:Q16) -> 0 | AC16: =SUM(O16:R16) -> 0 | ... AE16: =SUM(Q16:T16) -> 0 | AG16: =SUM(AE16/AA16)-1 -> #DIV/0!
B17: Gross Profit | C17: =SUM(C12+SUM(C16:C16)) -> 0 | D17: =SUM(D12+SUM(D16:D16)) -> 0 | E17: =SUM(E12+SUM(E16:E16)) -> 0 | F17: =SUM(F12+SUM(F16:F16)) -> 0 | H17: =SUM(H12+SUM(H16:H16)) -> 0 | I17: =SUM(I12+SUM(I16:I16)) -> 0 | J17: =SUM(J12+SUM(J16:J16)) -> 0 | K17: =SUM(K12+SUM(K16:K16)) -> 0 | L17: =SUM(L12+SUM(L16:L16)) -> 0 | M17: =SUM(M12+SUM(M16:M16)) -> 0 | N17: =SUM(N12+SUM(N16:N16)) -> 0 | O17: =SUM(O12+SUM(O16:O16)) -> 0 | ... T17: =SUM(T12+SUM(T16:T16)) -> 0 | V17: =SUM(V12+SUM(V16:V16)) -> 0 | W17: =SUM(W12+SUM(W16:W16)) -> 0 | X17: =SUM(X12+SUM(X16:X16)) -> 0 | Y17: =SUM(Y12+SUM(Y16:Y16)) -> 0 | Z17: =SUM(Z12+SUM(Z16:Z16)) -> 0 | AA17: =SUM(AA12+SUM(AA16:AA16)) -> 0 | AB17: =SUM(AB12+SUM(AB16:AB16)) -> 0 | AC17: =SUM(AC12+SUM(AC16:AC16)) -> 0 | ... AE17: =SUM(AE12+SUM(AE16:AE16)) -> 0 | AG17: =SUM(AE17/AA17)-1 -> #DIV/0!
B18: Gross Margin (%) | C18: =C17/C12 -> #DIV/0! | D18: =D17/D12 -> #DIV/0! | E18: =E17/E12 -> #DIV/0! | F18: =F17/F12 -> #DIV/0! | H18: =H17/H12 -> #DIV/0! | I18: =I17/I12 -> #DIV/0! | J18: =J17/J12 -> #DIV/0! | K18: =K17/K12 -> #DIV/0! | L18: =L17/L12 -> #DIV/0! | M18: =M17/M12 -> #DIV/0! | N18: =N17/N12 -> #DIV/0! | O18: =O17/O12 -> #DIV/0! | ... T18: =T17/T12 -> #DIV/0! | V18: =V17/V12 -> #DIV/0! | W18: =W17/W12 -> #DIV/0! | X18: =X17/X12 -> #DIV/0! | Y18: =Y17/Y12 -> #DIV/0! | Z18: =Z17/Z12 -> #DIV/0! | AA18: =AA17/AA12 -> #DIV/0! | AB18: =AB17/AB12 -> #DIV/0! | AC18: =AC17/AC12 -> #DIV/0! | ... AE18: =AE17/AE12 -> #DIV/0! | AG18: =SUM(AE18-AA18)*10000 -> #DIV/0!
B20: (-) XXX | V20: =SUM(H20:K20) -> 0 | W20: =SUM(I20:L20) -> 0 | X20: =SUM(J20:M20) -> 0 | Y20: =SUM(K20:N20) -> 0 | Z20: =SUM(L20:O20) -> 0 | AA20: =SUM(M20:P20) -> 0 | AB20: =SUM(N20:Q20) -> 0 | AC20: =SUM(O20:R20) -> 0 | ... AE20: =SUM(Q20:T20) -> 0 | AG20: =SUM(AE20/AA20)-1 -> #DIV/0!
B21: (-) XXX | V21: =SUM(H21:K21) -> 0 | W21: =SUM(I21:L21) -> 0 | X21: =SUM(J21:M21) -> 0 | Y21: =SUM(K21:N21) -> 0 | Z21: =SUM(L21:O21) -> 0 | AA21: =SUM(M21:P21) -> 0 | AB21: =SUM(N21:Q21) -> 0 | AC21: =SUM(O21:R21) -> 0 | ... AE21: =SUM(Q21:T21) -> 0 | AG21: =SUM(AE21/AA21)-1 -> #DIV/0!
B22: (-) XXX | V22: =SUM(H22:K22) -> 0 | W22: =SUM(I22:L22) -> 0 | X22: =SUM(J22:M22) -> 0 | Y22: =SUM(K22:N22) -> 0 | Z22: =SUM(L22:O22) -> 0 | AA22: =SUM(M22:P22) -> 0 | AB22: =SUM(N22:Q22) -> 0 | AC22: =SUM(O22:R22) -> 0 | ... AE22: =SUM(Q22:T22) -> 0 | AG22: =SUM(AE22/AA22)-1 -> #DIV/0!
B23: (-) XXX | V23: =SUM(H23:K23) -> 0 | W23: =SUM(I23:L23) -> 0 | X23: =SUM(J23:M23) -> 0 | Y23: =SUM(K23:N23) -> 0 | Z23: =SUM(L23:O23) -> 0 | AA23: =SUM(M23:P23) -> 0 | AB23: =SUM(N23:Q23) -> 0 | AC23: =SUM(O23:R23) -> 0 | ... AE23: =SUM(Q23:T23) -> 0 | AG23: =SUM(AE23/AA23)-1 -> #DIV/0!
B24: (-) XXX | V24: =SUM(H24:K24) -> 0 | W24: =SUM(I24:L24) -> 0 | X24: =SUM(J24:M24) -> 0 | Y24: =SUM(K24:N24) -> 0 | Z24: =SUM(L24:O24) -> 0 | AA24: =SUM(M24:P24) -> 0 | AB24: =SUM(N24:Q24) -> 0 | AC24: =SUM(O24:R24) -> 0 | ... AE24: =SUM(Q24:T24) -> 0 | AG24: =SUM(AE24/AA24)-1 -> #DIV/0!
B25: Earning before Interest & Taxes (EBIT) | C25: =SUM(C17+SUM(C20:C24)) -> 0 | D25: =SUM(D17+SUM(D20:D24)) -> 0 | E25: =SUM(E17+SUM(E20:E24)) -> 0 | F25: =SUM(F17+SUM(F20:F24)) -> 0 | H25: =SUM(H17+SUM(H20:H24)) -> 0 | I25: =SUM(I17+SUM(I20:I24)) -> 0 | J25: =SUM(J17+SUM(J20:J24)) -> 0 | K25: =SUM(K17+SUM(K20:K24)) -> 0 | L25: =SUM(L17+SUM(L20:L24)) -> 0 | M25: =SUM(M17+SUM(M20:M24)) -> 0 | N25: =SUM(N17+SUM(N20:N24)) -> 0 | O25: =SUM(O17+SUM(O20:O24)) -> 0 | ... T25: =SUM(T17+SUM(T20:T24)) -> 0 | V25: =SUM(V17+SUM(V20:V24)) -> 0 | W25: =SUM(W17+SUM(W20:W24)) -> 0 | X25: =SUM(X17+SUM(X20:X24)) -> 0 | Y25: =SUM(Y17+SUM(Y20:Y24)) -> 0 | Z25: =SUM(Z17+SUM(Z20:Z24)) -> 0 | AA25: =SUM(AA17+SUM(AA20:AA24)) -> 0 | AB25: =SUM(AB17+SUM(AB20:AB24)) -> 0 | AC25: =SUM(AC17+SUM(AC20:AC24)) -> 0 | ... AE25: =SUM(AE17+SUM(AE20:AE24)) -> 0 | AG25: =SUM(AE25/AA25)-1 -> #DIV/0!
B26: Operating Margin (%) | C26: =C25/C12 -> #DIV/0! | D26: =D25/D12 -> #DIV/0! | E26: =E25/E12 -> #DIV/0! | F26: =F25/F12 -> #DIV/0! | H26: =H25/H12 -> #DIV/0! | I26: =I25/I12 -> #DIV/0! | J26: =J25/J12 -> #DIV/0! | K26: =K25/K12 -> #DIV/0! | L26: =L25/L12 -> #DIV/0! | M26: =M25/M12 -> #DIV/0! | N26: =N25/N12 -> #DIV/0! | O26: =O25/O12 -> #DIV/0! | ... T26: =T25/T12 -> #DIV/0! | V26: =V25/V12 -> #DIV/0! | W26: =W25/W12 -> #DIV/0! | X26: =X25/X12 -> #DIV/0! | Y26: =Y25/Y12 -> #DIV/0! | Z26: =Z25/Z12 -> #DIV/0! | AA26: =AA25/AA12 -> #DIV/0! | AB26: =AB25/AB12 -> #DIV/0! | AC26: =AC25/AC12 -> #DIV/0! | ... AE26: =AE25/AE12 -> #DIV/0! | AG26: =SUM(AE26-AA26)*10000 -> #DIV/0!
B28: (+) Depreciation and Amortization (D&A) | V28: =SUM(H28:K28) -> 0 | W28: =SUM(I28:L28) -> 0 | X28: =SUM(J28:M28) -> 0 | Y28: =SUM(K28:N28) -> 0 | Z28: =SUM(L28:O28) -> 0 | AA28: =SUM(M28:P28) -> 0 | AB28: =SUM(N28:Q28) -> 0 | AC28: =SUM(O28:R28) -> 0 | ... AE28: =SUM(Q28:T28) -> 0 | AG28: =SUM(AE28/AA28)-1 -> #DIV/0!
B29: EBITDA | C29: =SUM(C25+SUM(C28:C28)) -> 0 | D29: =SUM(D25+SUM(D28:D28)) -> 0 | E29: =SUM(E25+SUM(E28:E28)) -> 0 | F29: =SUM(F25+SUM(F28:F28)) -> 0 | H29: =SUM(H25+SUM(H28:H28)) -> 0 | I29: =SUM(I25+SUM(I28:I28)) -> 0 | J29: =SUM(J25+SUM(J28:J28)) -> 0 | K29: =SUM(K25+SUM(K28:K28)) -> 0 | L29: =SUM(L25+SUM(L28:L28)) -> 0 | M29: =SUM(M25+SUM(M28:M28)) -> 0 | N29: =SUM(N25+SUM(N28:N28)) -> 0 | O29: =SUM(O25+SUM(O28:O28)) -> 0 | ... T29: =SUM(T25+SUM(T28:T28)) -> 0 | V29: =SUM(V25+SUM(V28:V28)) -> 0 | W29: =SUM(W25+SUM(W28:W28)) -> 0 | X29: =SUM(X25+SUM(X28:X28)) -> 0 | Y29: =SUM(Y25+SUM(Y28:Y28)) -> 0 | Z29: =SUM(Z25+SUM(Z28:Z28)) -> 0 | AA29: =SUM(AA25+SUM(AA28:AA28)) -> 0 | AB29: =SUM(AB25+SUM(AB28:AB28)) -> 0 | AC29: =SUM(AC25+SUM(AC28:AC28)) -> 0 | ... AE29: =SUM(AE25+SUM(AE28:AE28)) -> 0 | AG29: =SUM(AE29/AA29)-1 -> #DIV/0!
B30: EBITDA Margin (%) | C30: =C29/C12 -> #DIV/0! | D30: =D29/D12 -> #DIV/0! | E30: =E29/E12 -> #DIV/0! | F30: =F29/F12 -> #DIV/0! | H30: =H29/H12 -> #DIV/0! | I30: =I29/I12 -> #DIV/0! | J30: =J29/J12 -> #DIV/0! | K30: =K29/K12 -> #DIV/0! | L30: =L29/L12 -> #DIV/0! | M30: =M29/M12 -> #DIV/0! | N30: =N29/N12 -> #DIV/0! | O30: =O29/O12 -> #DIV/0! | ... T30: =T29/T12 -> #DIV/0! | V30: =V29/V12 -> #DIV/0! | W30: =W29/W12 -> #DIV/0! | X30: =X29/X12 -> #DIV/0! | Y30: =Y29/Y12 -> #DIV/0! | Z30: =Z29/Z12 -> #DIV/0! | AA30: =AA29/AA12 -> #DIV/0! | AB30: =AB29/AB12 -> #DIV/0! | AC30: =AC29/AC12 -> #DIV/0! | ... AE30: =AE29/AE12 -> #DIV/0! | AG30: =SUM(AE30-AA30)*10000 -> #DIV/0!
B32: (+) Stock-Based Compensation (SBC) | V32: =SUM(H32:K32) -> 0 | W32: =SUM(I32:L32) -> 0 | X32: =SUM(J32:M32) -> 0 | Y32: =SUM(K32:N32) -> 0 | Z32: =SUM(L32:O32) -> 0 | AA32: =SUM(M32:P32) -> 0 | AB32: =SUM(N32:Q32) -> 0 | AC32: =SUM(O32:R32) -> 0 | ... AE32: =SUM(Q32:T32) -> 0 | AG32: =SUM(AE32/AA32)-1 -> #DIV/0!
B33: (+) XXX | V33: =SUM(H33:K33) -> 0 | W33: =SUM(I33:L33) -> 0 | X33: =SUM(J33:M33) -> 0 | Y33: =SUM(K33:N33) -> 0 | Z33: =SUM(L33:O33) -> 0 | AA33: =SUM(M33:P33) -> 0 | AB33: =SUM(N33:Q33) -> 0 | AC33: =SUM(O33:R33) -> 0 | ... AE33: =SUM(Q33:T33) -> 0 | AG33: =SUM(AE33/AA33)-1 -> #DIV/0!
B34: Adj. EBITDA | C34: =+SUM(C29+SUM(C32:C32)) -> 0 | D34: =+SUM(D29+SUM(D32:D32)) -> 0 | E34: =+SUM(E29+SUM(E32:E32)) -> 0 | F34: =+SUM(F29+SUM(F32:F32)) -> 0 | H34: =+SUM(H29+SUM(H32:H32)) -> 0 | I34: =+SUM(I29+SUM(I32:I32)) -> 0 | J34: =+SUM(J29+SUM(J32:J32)) -> 0 | K34: =+SUM(K29+SUM(K32:K32)) -> 0 | L34: =+SUM(L29+SUM(L32:L32)) -> 0 | M34: =+SUM(M29+SUM(M32:M32)) -> 0 | N34: =+SUM(N29+SUM(N32:N32)) -> 0 | O34: =+SUM(O29+SUM(O32:O32)) -> 0 | ... T34: =+SUM(T29+SUM(T32:T32)) -> 0 | V34: =+SUM(V29+SUM(V32:V32)) -> 0 | W34: =+SUM(W29+SUM(W32:W32)) -> 0 | X34: =+SUM(X29+SUM(X32:X32)) -> 0 | Y34: =+SUM(Y29+SUM(Y32:Y32)) -> 0 | Z34: =+SUM(Z29+SUM(Z32:Z32)) -> 0 | AA34: =+SUM(AA29+SUM(AA32:AA32)) -> 0 | AB34: =+SUM(AB29+SUM(AB32:AB32)) -> 0 | AC34: =+SUM(AC29+SUM(AC32:AC32)) -> 0 | ... AE34: =+SUM(AE29+SUM(AE32:AE32)) -> 0 | AG34: =SUM(AE34/AA34)-1 -> #DIV/0!
B35: Adj. EBITDA Margin (%) | C35: =C34/C12 -> #DIV/0! | D35: =D34/D12 -> #DIV/0! | E35: =E34/E12 -> #DIV/0! | F35: =F34/F12 -> #DIV/0! | H35: =H34/H12 -> #DIV/0! | I35: =I34/I12 -> #DIV/0! | J35: =J34/J12 -> #DIV/0! | K35: =K34/K12 -> #DIV/0! | L35: =L34/L12 -> #DIV/0! | M35: =M34/M12 -> #DIV/0! | N35: =N34/N12 -> #DIV/0! | O35: =O34/O12 -> #DIV/0! | ... T35: =T34/T12 -> #DIV/0! | V35: =V34/V12 -> #DIV/0! | W35: =W34/W12 -> #DIV/0! | X35: =X34/X12 -> #DIV/0! | Y35: =Y34/Y12 -> #DIV/0! | Z35: =Z34/Z12 -> #DIV/0! | AA35: =AA34/AA12 -> #DIV/0! | AB35: =AB34/AB12 -> #DIV/0! | AC35: =AC34/AC12 -> #DIV/0! | ... AE35: =AE34/AE12 -> #DIV/0! | AG35: =SUM(AE35-AA35)*10000 -> #DIV/0!
B37: (-) Capital Expenditures | V37: =SUM(H37:K37) -> 0 | W37: =SUM(I37:L37) -> 0 | X37: =SUM(J37:M37) -> 0 | Y37: =SUM(K37:N37) -> 0 | Z37: =SUM(L37:O37) -> 0 | AA37: =SUM(M37:P37) -> 0 | AB37: =SUM(N37:Q37) -> 0 | AC37: =SUM(O37:R37) -> 0 | ... AE37: =SUM(Q37:T37) -> 0 | AG37: =SUM(AE37/AA37)-1 -> #DIV/0!
B38: (-) Cash Taxes | V38: =SUM(H38:K38) -> 0 | W38: =SUM(I38:L38) -> 0 | X38: =SUM(J38:M38) -> 0 | Y38: =SUM(K38:N38) -> 0 | Z38: =SUM(L38:O38) -> 0 | AA38: =SUM(M38:P38) -> 0 | AB38: =SUM(N38:Q38) -> 0 | AC38: =SUM(O38:R38) -> 0 | ... AE38: =SUM(Q38:T38) -> 0 | AG38: =SUM(AE38/AA38)-1 -> #DIV/0!
B39: (-) Cash Interest | V39: =SUM(H39:K39) -> 0 | W39: =SUM(I39:L39) -> 0 | X39: =SUM(J39:M39) -> 0 | Y39: =SUM(K39:N39) -> 0 | Z39: =SUM(L39:O39) -> 0 | AA39: =SUM(M39:P39) -> 0 | AB39: =SUM(N39:Q39) -> 0 | AC39: =SUM(O39:R39) -> 0 | ... AE39: =SUM(Q39:T39) -> 0 | AG39: =SUM(AE39/AA39)-1 -> #DIV/0!
B40: (-) Mandatory Outflows | V40: =SUM(H40:K40) -> 0 | W40: =SUM(I40:L40) -> 0 | X40: =SUM(J40:M40) -> 0 | Y40: =SUM(K40:N40) -> 0 | Z40: =SUM(L40:O40) -> 0 | AA40: =SUM(M40:P40) -> 0 | AB40: =SUM(N40:Q40) -> 0 | AC40: =SUM(O40:R40) -> 0 | ... AE40: =SUM(Q40:T40) -> 0 | AG40: =SUM(AE40/AA40)-1 -> #DIV/0!
B41: (+/-) Changes in NWC | V41: =SUM(H41:K41) -> 0 | W41: =SUM(I41:L41) -> 0 | X41: =SUM(J41:M41) -> 0 | Y41: =SUM(K41:N41) -> 0 | Z41: =SUM(L41:O41) -> 0 | AA41: =SUM(M41:P41) -> 0 | AB41: =SUM(N41:Q41) -> 0 | AC41: =SUM(O41:R41) -> 0 | ... AE41: =SUM(Q41:T41) -> 0 | AG41: =SUM(AE41/AA41)-1 -> #DIV/0!
B42: Discretionary Cash-Flows | C42: =SUM(C34+SUM(C37:C41)) -> 0 | D42: =SUM(D34+SUM(D37:D41)) -> 0 | E42: =SUM(E34+SUM(E37:E41)) -> 0 | F42: =SUM(F34+SUM(F37:F41)) -> 0 | H42: =SUM(H34+SUM(H37:H41)) -> 0 | I42: =SUM(I34+SUM(I37:I41)) -> 0 | J42: =SUM(J34+SUM(J37:J41)) -> 0 | K42: =SUM(K34+SUM(K37:K41)) -> 0 | L42: =SUM(L34+SUM(L37:L41)) -> 0 | M42: =SUM(M34+SUM(M37:M41)) -> 0 | N42: =SUM(N34+SUM(N37:N41)) -> 0 | O42: =SUM(O34+SUM(O37:O41)) -> 0 | ... T42: =SUM(T34+SUM(T37:T41)) -> 0 | V42: =SUM(V34+SUM(V37:V41)) -> 0 | W42: =SUM(W34+SUM(W37:W41)) -> 0 | X42: =SUM(X34+SUM(X37:X41)) -> 0 | Y42: =SUM(Y34+SUM(Y37:Y41)) -> 0 | Z42: =SUM(Z34+SUM(Z37:Z41)) -> 0 | AA42: =SUM(AA34+SUM(AA37:AA41)) -> 0 | AB42: =SUM(AB34+SUM(AB37:AB41)) -> 0 | AC42: =SUM(AC34+SUM(AC37:AC41)) -> 0 | ... AE42: =SUM(AE34+SUM(AE37:AE41)) -> 0 | AG42: =SUM(AE42/AA42)-1 -> #DIV/0!
B44: (+/-) XXX | V44: =SUM(H44:K44) -> 0 | W44: =SUM(I44:L44) -> 0 | X44: =SUM(J44:M44) -> 0 | Y44: =SUM(K44:N44) -> 0 | Z44: =SUM(L44:O44) -> 0 | AA44: =SUM(M44:P44) -> 0 | AB44: =SUM(N44:Q44) -> 0 | AC44: =SUM(O44:R44) -> 0 | ... AE44: =SUM(Q44:T44) -> 0
B45: (+/-) XXX | V45: =SUM(H45:K45) -> 0 | W45: =SUM(I45:L45) -> 0 | X45: =SUM(J45:M45) -> 0 | Y45: =SUM(K45:N45) -> 0 | Z45: =SUM(L45:O45) -> 0 | AA45: =SUM(M45:P45) -> 0 | AB45: =SUM(N45:Q45) -> 0 | AC45: =SUM(O45:R45) -> 0 | ... AE45: =SUM(Q45:T45) -> 0
B46: (+/-) XXX | V46: =SUM(H46:K46) -> 0 | W46: =SUM(I46:L46) -> 0 | X46: =SUM(J46:M46) -> 0 | Y46: =SUM(K46:N46) -> 0 | Z46: =SUM(L46:O46) -> 0 | AA46: =SUM(M46:P46) -> 0 | AB46: =SUM(N46:Q46) -> 0 | AC46: =SUM(O46:R46) -> 0 | ... AE46: =SUM(Q46:T46) -> 0
B47: (+/-) XXX | V47: =SUM(H47:K47) -> 0 | W47: =SUM(I47:L47) -> 0 | X47: =SUM(J47:M47) -> 0 | Y47: =SUM(K47:N47) -> 0 | Z47: =SUM(L47:O47) -> 0 | AA47: =SUM(M47:P47) -> 0 | AB47: =SUM(N47:Q47) -> 0 | AC47: =SUM(O47:R47) -> 0 | ... AE47: =SUM(Q47:T47) -> 0
B48: (+/-) XXX | V48: =SUM(H48:K48) -> 0 | W48: =SUM(I48:L48) -> 0 | X48: =SUM(J48:M48) -> 0 | Y48: =SUM(K48:N48) -> 0 | Z48: =SUM(L48:O48) -> 0 | AA48: =SUM(M48:P48) -> 0 | AB48: =SUM(N48:Q48) -> 0 | AC48: =SUM(O48:R48) -> 0 | ... AE48: =SUM(Q48:T48) -> 0
B49: (+/-) Other | D49: =SUM(D54)-SUM(C54)-SUM(D42:D48) -> 0 | E49: =SUM(E54)-SUM(D54)-SUM(E42:E48) -> 0 | F49: =SUM(F54)-SUM(E54)-SUM(F42:F48) -> 0 | H49: =SUM(H54)-SUM(C54)-SUM(H42:H48) -> 0 | I49: =SUM(I54)-SUM(H54)-SUM(I42:I48) -> 0 | J49: =SUM(J54)-SUM(I54)-SUM(J42:J48) -> 0 | K49: =SUM(K54)-SUM(J54)-SUM(K42:K48) -> 44327 | L49: =SUM(L54)-SUM(K54)-SUM(L42:L48) -> -44327 | M49: =SUM(M54)-SUM(L54)-SUM(M42:M48) -> 0 | N49: =SUM(N54)-SUM(M54)-SUM(N42:N48) -> 0 | O49: =SUM(O54)-SUM(N54)-SUM(O42:O48) -> 27758 | P49: =SUM(P54)-SUM(O54)-SUM(P42:P48) -> -27758 | ... T49: =SUM(T54)-SUM(S54)-SUM(T42:T48) -> #REF! | V49: =SUM(H49:K49) -> 44327 | W49: =SUM(I49:L49) -> 0 | X49: =SUM(J49:M49) -> 0 | Y49: =SUM(K49:N49) -> 0 | Z49: =SUM(L49:O49) -> -16569 | AA49: =SUM(M49:P49) -> 0 | AB49: =SUM(N49:Q49) -> 0 | AC49: =SUM(O49:R49) -> 0 | ... AE49: =SUM(Q49:T49) -> #REF!
B50: Free-Cash Flows | C50: =SUM(C42+SUM(C44:C49)) -> 0 | D50: =SUM(D42+SUM(D44:D49)) -> 0 | E50: =SUM(E42+SUM(E44:E49)) -> 0 | F50: =SUM(F42+SUM(F44:F49)) -> 0 | H50: =SUM(H42+SUM(H44:H49)) -> 0 | I50: =SUM(I42+SUM(I44:I49)) -> 0 | J50: =SUM(J42+SUM(J44:J49)) -> 0 | K50: =SUM(K42+SUM(K44:K49)) -> 44327 | L50: =SUM(L42+SUM(L44:L49)) -> -44327 | M50: =SUM(M42+SUM(M44:M49)) -> 0 | N50: =SUM(N42+SUM(N44:N49)) -> 0 | O50: =SUM(O42+SUM(O44:O49)) -> 27758 | ... T50: =SUM(T42+SUM(T44:T49)) -> #REF! | V50: =SUM(V42+SUM(V44:V49)) -> 44327 | W50: =SUM(W42+SUM(W44:W49)) -> 0 | X50: =SUM(X42+SUM(X44:X49)) -> 0 | Y50: =SUM(Y42+SUM(Y44:Y49)) -> 0 | Z50: =SUM(Z42+SUM(Z44:Z49)) -> -16569 | AA50: =SUM(AA42+SUM(AA44:AA49)) -> 0 | AB50: =SUM(AB42+SUM(AB44:AB49)) -> 0 | AC50: =SUM(AC42+SUM(AC44:AC49)) -> 0 | ... AE50: =SUM(AE42+SUM(AE44:AE49)) -> #REF!
B52: Capitalization
B54: Cash & Cash Equivelants | K54: ='Historical Financials'!J42 -> 44327 | O54: ='Historical Financials'!N42 -> 27758 | S54: ='Historical Financials'!#REF! -> #REF! | V54: =K54 -> 44327 | W54: =L54 -> 0 | X54: =M54 -> 0 | Y54: =N54 -> 0 | Z54: =O54 -> 27758 | AA54: =P54 -> 0 | AB54: =Q54 -> 0 | AC54: =R54 -> 0 | ... AE54: =T54 -> 0
B55: XXX | K55: ='Historical Financials'!J43 -> 63499 | O55: ='Historical Financials'!N43 -> 69775 | S55: ='Historical Financials'!#REF! -> #REF! | V55: =K55 -> 63499 | W55: =L55 -> 0 | X55: =M55 -> 0 | Y55: =N55 -> 0 | Z55: =O55 -> 69775 | AA55: =P55 -> 0 | AB55: =Q55 -> 0 | AC55: =R55 -> 0 | ... AE55: =T55 -> 0
B56: XXX | K56: =D56 -> 0 | O56: =E56 -> 0 | S56: =F56 -> 0 | V56: =K56 -> 0 | W56: =L56 -> 0 | X56: =M56 -> 0 | Y56: =N56 -> 0 | Z56: =O56 -> 0 | AA56: =P56 -> 0 | AB56: =Q56 -> 0 | AC56: =R56 -> 0 | ... AE56: =T56 -> 0
B57: Total Liquidity | C57: =SUM(C54:C56) -> 0 | D57: =SUM(D54:D56) -> 0 | E57: =SUM(E54:E56) -> 0 | F57: =SUM(F54:F56) -> 0 | H57: =SUM(H54:H56) -> 0 | I57: =SUM(I54:I56) -> 0 | J57: =SUM(J54:J56) -> 0 | K57: =SUM(K54:K56) -> 107826 | L57: =SUM(L54:L56) -> 0 | M57: =SUM(M54:M56) -> 0 | N57: =SUM(N54:N56) -> 0 | O57: =SUM(O54:O56) -> 97533 | ... T57: =SUM(T54:T56) -> 0 | V57: =SUM(V54:V56) -> 107826 | W57: =SUM(W54:W56) -> 0 | X57: =SUM(X54:X56) -> 0 | Y57: =SUM(Y54:Y56) -> 0 | Z57: =SUM(Z54:Z56) -> 97533 | AA57: =SUM(AA54:AA56) -> 0 | AB57: =SUM(AB54:AB56) -> 0 | AC57: =SUM(AC54:AC56) -> 0 | ... AE57: =SUM(AE54:AE56) -> 0
B59: Balance Sheet Metrics:
B60: XXX | V60: =K60 -> 0 | W60: =L60 -> 0 | X60: =M60 -> 0 | Y60: =N60 -> 0 | Z60: =O60 -> 0 | AA60: =P60 -> 0 | AB60: =Q60 -> 0 | AC60: =R60 -> 0 | ... AE60: =T60 -> 0
B61: XXX | V61: =K61 -> 0 | W61: =L61 -> 0 | X61: =M61 -> 0 | Y61: =N61 -> 0 | Z61: =O61 -> 0 | AA61: =P61 -> 0 | AB61: =Q61 -> 0 | AC61: =R61 -> 0 | ... AE61: =T61 -> 0
B62: XXX | V62: =K62 -> 0 | W62: =L62 -> 0 | X62: =M62 -> 0 | Y62: =N62 -> 0 | Z62: =O62 -> 0 | AA62: =P62 -> 0 | AB62: =Q62 -> 0 | AC62: =R62 -> 0 | ... AE62: =T62 -> 0
B63: XXX | V63: =K63 -> 0 | W63: =L63 -> 0 | X63: =M63 -> 0 | Y63: =N63 -> 0 | Z63: =O63 -> 0 | AA63: =P63 -> 0 | AB63: =Q63 -> 0 | AC63: =R63 -> 0 | ... AE63: =T63 -> 0
B64: XXX | V64: =K64 -> 0 | W64: =L64 -> 0 | X64: =M64 -> 0 | Y64: =N64 -> 0 | Z64: =O64 -> 0 | AA64: =P64 -> 0 | AB64: =Q64 -> 0 | AC64: =R64 -> 0 | ... AE64: =T64 -> 0
B65: XXX | V65: =K65 -> 0 | W65: =L65 -> 0 | X65: =M65 -> 0 | Y65: =N65 -> 0 | Z65: =O65 -> 0 | AA65: =P65 -> 0 | AB65: =Q65 -> 0 | AC65: =R65 -> 0 | ... AE65: =T65 -> 0
B66: XXX | V66: =K66 -> 0 | W66: =L66 -> 0 | X66: =M66 -> 0 | Y66: =N66 -> 0 | Z66: =O66 -> 0 | AA66: =P66 -> 0 | AB66: =Q66 -> 0 | AC66: =R66 -> 0 | ... AE66: =T66 -> 0
B68: Summary Debt:
B69: CPLTD | V69: =K69 -> 0 | W69: =L69 -> 0 | X69: =M69 -> 0 | Y69: =N69 -> 0 | Z69: =O69 -> 0 | AA69: =P69 -> 0 | AB69: =Q69 -> 0 | AC69: =R69 -> 0 | ... AE69: =T69 -> 0
B70: LTD | V70: =K70 -> 0 | W70: =L70 -> 0 | X70: =M70 -> 0 | Y70: =N70 -> 0 | Z70: =O70 -> 0 | AA70: =P70 -> 0 | AB70: =Q70 -> 0 | AC70: =R70 -> 0 | ... AE70: =T70 -> 0
B72: XXX | K72: =D72 -> 0 | O72: =E72 -> 0 | S72: =F72 -> 0 | V72: =K72 -> 0 | W72: =L72 -> 0 | X72: =M72 -> 0 | Y72: =N72 -> 0 | Z72: =O72 -> 0 | AA72: =P72 -> 0 | AB72: =Q72 -> 0 | AC72: =R72 -> 0 | ... AE72: =T72 -> 0
B73: XXX | K73: =D73 -> 0 | O73: =E73 -> 0 | S73: =F73 -> 0 | V73: =K73 -> 0 | W73: =L73 -> 0 | X73: =M73 -> 0 | Y73: =N73 -> 0 | Z73: =O73 -> 0 | AA73: =P73 -> 0 | AB73: =Q73 -> 0 | AC73: =R73 -> 0 | ... AE73: =T73 -> 0
B74: XXX | K74: =D74 -> 0 | O74: =E74 -> 0 | S74: =F74 -> 0 | V74: =K74 -> 0 | W74: =L74 -> 0 | X74: =M74 -> 0 | Y74: =N74 -> 0 | Z74: =O74 -> 0 | AA74: =P74 -> 0 | AB74: =Q74 -> 0 | AC74: =R74 -> 0 | ... AE74: =T74 -> 0
B75: XXX | K75: ='Historical Financials'!J60+'Historical Financials'!#REF! -> #REF! | O75: ='Historical Financials'!N60+'Historical Financials'!#REF! -> #REF! | S75: ='Historical Financials'!#REF!+'Historical Financials'!#REF! -> #REF! | V75: =K75 -> #REF! | W75: =L75 -> 0 | X75: =M75 -> 0 | Y75: =N75 -> 0 | Z75: =O75 -> #REF! | AA75: =P75 -> 0 | AB75: =Q75 -> 0 | AC75: =R75 -> 0 | ... AE75: =T75 -> 0
B76: Total Debt | C76: =SUM(C72:C75) -> 0 | D76: =SUM(D72:D75) -> 0 | E76: =SUM(E72:E75) -> 0 | F76: =SUM(F72:F75) -> 0 | H76: =SUM(H72:H75) -> 0 | I76: =SUM(I72:I75) -> 0 | J76: =SUM(J72:J75) -> 0 | K76: =SUM(K72:K75) -> #REF! | L76: =SUM(L72:L75) -> 0 | M76: =SUM(M72:M75) -> 0 | N76: =SUM(N72:N75) -> 0 | O76: =SUM(O72:O75) -> #REF! | ... T76: =SUM(T72:T75) -> 0 | V76: =SUM(V72:V75) -> #REF! | W76: =SUM(W72:W75) -> 0 | X76: =SUM(X72:X75) -> 0 | Y76: =SUM(Y72:Y75) -> 0 | Z76: =SUM(Z72:Z75) -> #REF! | AA76: =SUM(AA72:AA75) -> 0 | AB76: =SUM(AB72:AB75) -> 0 | AC76: =SUM(AC72:AC75) -> 0 | ... AE76: =SUM(AE72:AE75) -> 0
B78: Total Shareholder Equity | V78: =K78 -> 0 | W78: =L78 -> 0 | X78: =M78 -> 0 | Y78: =N78 -> 0 | Z78: =O78 -> 0 | AA78: =P78 -> 0 | AB78: =Q78 -> 0 | AC78: =R78 -> 0 | ... AE78: =T78 -> 0
B79: Total Book Capitalization | C79: =SUM(C76:C78) -> 0 | D79: =SUM(D76:D78) -> 0 | E79: =SUM(E76:E78) -> 0 | F79: =SUM(F76:F78) -> 0 | H79: =SUM(H76:H78) -> 0 | I79: =SUM(I76:I78) -> 0 | J79: =SUM(J76:J78) -> 0 | K79: =SUM(K76:K78) -> #REF! | L79: =SUM(L76:L78) -> 0 | M79: =SUM(M76:M78) -> 0 | N79: =SUM(N76:N78) -> 0 | O79: =SUM(O76:O78) -> #REF! | ... T79: =SUM(T76:T78) -> 0 | V79: =SUM(V76:V78) -> #REF! | W79: =SUM(W76:W78) -> 0 | X79: =SUM(X76:X78) -> 0 | Y79: =SUM(Y76:Y78) -> 0 | Z79: =SUM(Z76:Z78) -> #REF! | AA79: =SUM(AA76:AA78) -> 0 | AB79: =SUM(AB76:AB78) -> 0 | AC79: =SUM(AC76:AC78) -> 0 | ... AE79: =SUM(AE76:AE78) -> 0
B81: Credit Metrics
B83: LTM Total Leverage | C83: =C76/C34 -> #DIV/0! | D83: =D76/D34 -> #DIV/0! | E83: =E76/E34 -> #DIV/0! | F83: =F76/F34 -> #DIV/0! | K83: =SUM(K76/SUM(H34:K34)) -> #REF! | L83: =SUM(L76/SUM(I34:L34)) -> #DIV/0! | M83: =SUM(M76/SUM(J34:M34)) -> #DIV/0! | N83: =SUM(N76/SUM(K34:N34)) -> #DIV/0! | O83: =SUM(O76/SUM(L34:O34)) -> #REF! | P83: =SUM(P76/SUM(M34:P34)) -> #DIV/0! | Q83: =SUM(Q76/SUM(N34:Q34)) -> #DIV/0! | R83: =SUM(R76/SUM(O34:R34)) -> #DIV/0! | ... T83: =SUM(T76/SUM(Q34:T34)) -> #DIV/0! | V83: =V76/V34 -> #REF! | W83: =W76/W34 -> #DIV/0! | X83: =X76/X34 -> #DIV/0! | Y83: =Y76/Y34 -> #DIV/0! | Z83: =Z76/Z34 -> #REF! | AA83: =AA76/AA34 -> #DIV/0! | AB83: =AB76/AB34 -> #DIV/0! | AC83: =AC76/AC34 -> #DIV/0! | ... AE83: =AE76/AE34 -> #DIV/0!
B84: LTM Net Leverage | C84: =SUM(C76-C54)/C34 -> #DIV/0! | D84: =SUM(D76-D54)/D34 -> #DIV/0! | E84: =SUM(E76-E54)/E34 -> #DIV/0! | F84: =SUM(F76-F54)/F34 -> #DIV/0! | K84: =SUM(K76-K54)/SUM(H34:K34) -> #REF! | L84: =SUM(L76-L54)/SUM(I34:L34) -> #DIV/0! | M84: =SUM(M76-M54)/SUM(J34:M34) -> #DIV/0! | N84: =SUM(N76-N54)/SUM(K34:N34) -> #DIV/0! | O84: =SUM(O76-O54)/SUM(L34:O34) -> #REF! | P84: =SUM(P76-P54)/SUM(M34:P34) -> #DIV/0! | Q84: =SUM(Q76-Q54)/SUM(N34:Q34) -> #DIV/0! | R84: =SUM(R76-R54)/SUM(O34:R34) -> #DIV/0! | ... T84: =SUM(T76-T54)/SUM(Q34:T34) -> #DIV/0! | V84: =SUM(V76-V54)/V34 -> #REF! | W84: =SUM(W76-W54)/W34 -> #DIV/0! | X84: =SUM(X76-X54)/X34 -> #DIV/0! | Y84: =SUM(Y76-Y54)/Y34 -> #DIV/0! | Z84: =SUM(Z76-Z54)/Z34 -> #REF! | AA84: =SUM(AA76-AA54)/AA34 -> #DIV/0! | AB84: =SUM(AB76-AB54)/AB34 -> #DIV/0! | AC84: =SUM(AC76-AC54)/AC34 -> #DIV/0! | ... AE84: =SUM(AE76-AE54)/AE34 -> #DIV/0!
B85: LTM Interest Coverage | C85: =C34/-C39 -> #DIV/0! | D85: =D34/-D39 -> #DIV/0! | E85: =E34/-E39 -> #DIV/0! | F85: =F34/-F39 -> #DIV/0! | K85: {=SUM(H34:K34)/SUM(-H39:K39)} -> #DIV/0! | L85: {=SUM(I34:L34)/SUM(-I39:L39)} -> #DIV/0! | M85: {=SUM(J34:M34)/SUM(-J39:M39)} -> #DIV/0! | N85: {=SUM(K34:N34)/SUM(-K39:N39)} -> #DIV/0! | O85: {=SUM(L34:O34)/SUM(-L39:O39)} -> #DIV/0! | P85: {=SUM(M34:P34)/SUM(-M39:P39)} -> #DIV/0! | Q85: {=SUM(N34:Q34)/SUM(-N39:Q39)} -> #DIV/0! | R85: {=SUM(O34:R34)/SUM(-O39:R39)} -> #DIV/0! | ... T85: {=SUM(Q34:T34)/SUM(-Q39:T39)} -> #DIV/0! | V85: =V34/-V39 -> #DIV/0! | W85: =W34/-W39 -> #DIV/0! | X85: =X34/-X39 -> #DIV/0! | Y85: =Y34/-Y39 -> #DIV/0! | Z85: =Z34/-Z39 -> #DIV/0! | AA85: =AA34/-AA39 -> #DIV/0! | AB85: =AB34/-AB39 -> #DIV/0! | AC85: =AC34/-AC39 -> #DIV/0! | ... AE85: =AE34/-AE39 -> #DIV/0!
B86: LTM Debt Service Coverage | C86: {=SUM(C34+C37)/SUM(-C38:C39)} -> #DIV/0! | D86: {=SUM(D34+D37)/SUM(-D38:D39)} -> #DIV/0! | E86: {=SUM(E34+E37)/SUM(-E38:E39)} -> #DIV/0! | F86: {=SUM(F34+F37)/SUM(-F38:F39)} -> #DIV/0! | K86: {=SUM(H34:K34+H37:K37)/SUM(-H38:K39)} -> #DIV/0! | L86: {=SUM(I34:L34+I37:L37)/SUM(-I38:L39)} -> #DIV/0! | M86: {=SUM(J34:M34+J37:M37)/SUM(-J38:M39)} -> #DIV/0! | N86: {=SUM(K34:N34+K37:N37)/SUM(-K38:N39)} -> #DIV/0! | O86: {=SUM(L34:O34+L37:O37)/SUM(-L38:O39)} -> #DIV/0! | P86: {=SUM(M34:P34+M37:P37)/SUM(-M38:P39)} -> #DIV/0! | Q86: {=SUM(N34:Q34+N37:Q37)/SUM(-N38:Q39)} -> #DIV/0! | R86: {=SUM(O34:R34+O37:R37)/SUM(-O38:R39)} -> #DIV/0! | ... T86: {=SUM(Q34:T34+Q37:T37)/SUM(-Q38:T39)} -> #DIV/0! | V86: {=SUM(V34+V37)/SUM(-V38:V39)} -> #DIV/0! | W86: {=SUM(W34+W37)/SUM(-W38:W39)} -> #DIV/0! | X86: {=SUM(X34+X37)/SUM(-X38:X39)} -> #DIV/0! | Y86: {=SUM(Y34+Y37)/SUM(-Y38:Y39)} -> #DIV/0! | Z86: {=SUM(Z34+Z37)/SUM(-Z38:Z39)} -> #DIV/0! | AA86: {=SUM(AA34+AA37)/SUM(-AA38:AA39)} -> #DIV/0! | AB86: {=SUM(AB34+AB37)/SUM(-AB38:AB39)} -> #DIV/0! | AC86: {=SUM(AC34+AC37)/SUM(-AC38:AC39)} -> #DIV/0! | ... AE86: {=SUM(AE34+AE37)/SUM(-AE38:AE39)} -> #DIV/0!
B87: LTM Fixed Charge Coverage | C87: {=SUM(C34)/SUM(-C37:C39)} -> #DIV/0! | D87: {=SUM(D34)/SUM(-D37:D39)} -> #DIV/0! | E87: {=SUM(E34)/SUM(-E37:E39)} -> #DIV/0! | F87: {=SUM(F34)/SUM(-F37:F39)} -> #DIV/0! | K87: {=SUM(H34:K34)/SUM(-H37:K39)} -> #DIV/0! | L87: {=SUM(I34:L34)/SUM(-I37:L39)} -> #DIV/0! | M87: {=SUM(J34:M34)/SUM(-J37:M39)} -> #DIV/0! | N87: {=SUM(K34:N34)/SUM(-K37:N39)} -> #DIV/0! | O87: {=SUM(L34:O34)/SUM(-L37:O39)} -> #DIV/0! | P87: {=SUM(M34:P34)/SUM(-M37:P39)} -> #DIV/0! | Q87: {=SUM(N34:Q34)/SUM(-N37:Q39)} -> #DIV/0! | R87: {=SUM(O34:R34)/SUM(-O37:R39)} -> #DIV/0! | ... T87: {=SUM(Q34:T34)/SUM(-Q37:T39)} -> #DIV/0! | V87: {=SUM(V34)/SUM(-V37:V39)} -> #DIV/0! | W87: {=SUM(W34)/SUM(-W37:W39)} -> #DIV/0! | X87: {=SUM(X34)/SUM(-X37:X39)} -> #DIV/0! | Y87: {=SUM(Y34)/SUM(-Y37:Y39)} -> #DIV/0! | Z87: {=SUM(Z34)/SUM(-Z37:Z39)} -> #DIV/0! | AA87: {=SUM(AA34)/SUM(-AA37:AA39)} -> #DIV/0! | AB87: {=SUM(AB34)/SUM(-AB37:AB39)} -> #DIV/0! | AC87: {=SUM(AC34)/SUM(-AC37:AC39)} -> #DIV/0! | ... AE87: {=SUM(AE34)/SUM(-AE37:AE39)} -> #DIV/0!
B88: Debt-to-Book Capitalization | C88: =C79/C76 -> #DIV/0! | D88: =D79/D76 -> #DIV/0! | E88: =E79/E76 -> #DIV/0! | F88: =F79/F76 -> #DIV/0! | K88: =K79/K76 -> #REF! | L88: =L79/L76 -> #DIV/0! | M88: =M79/M76 -> #DIV/0! | N88: =N79/N76 -> #DIV/0! | O88: =O79/O76 -> #REF! | P88: =P79/P76 -> #DIV/0! | Q88: =Q79/Q76 -> #DIV/0! | R88: =R79/R76 -> #DIV/0! | ... T88: =T79/T76 -> #DIV/0! | V88: =V79/V76 -> #REF! | W88: =W79/W76 -> #DIV/0! | X88: =X79/X76 -> #DIV/0! | Y88: =Y79/Y76 -> #DIV/0! | Z88: =Z79/Z76 -> #REF! | AA88: =AA79/AA76 -> #DIV/0! | AB88: =AB79/AB76 -> #DIV/0! | AC88: =AC79/AC76 -> #DIV/0! | ... AE88: =AE79/AE76 -> #DIV/0!
