Workbook

Sheet Historical Financials
B2: Netflix, Inc. (NASDAQ: NFLX)
B3: Historical Financials
B4: $ in thousands except per share
A6: X | B6: Income Statement | G6: FYE | O6: Quarterly | Y6: Quarterly | AN6: LTM | AO6: LTM | AU6: Variance
B7: Fiscal Period | C7: 2018 | D7: 2019 | E7: 2020 | F7: 2021 | G7: 2022 | H7: 2023 | I7: 2024 | K7: 1Q21 | L7: 2Q21 | M7: 3Q21 | N7: 4Q21 | O7: 1Q22 | P7: 2Q22 | Q7: 3Q22 | R7: 4Q22 | S7: 1Q23 | T7: 2Q23 | U7: 3Q23 | V7: 4Q23 | W7: 1Q24 | X7: 2Q24 | Y7: 3Q24 | Z7: 4Q24 | AA7: 1Q25 | AB7: 2Q25 | AC7: 3Q25 | AE7: =O7 -> 1Q22 | AF7: =P7 -> 2Q22 | AG7: =Q7 -> 3Q22 | AH7: =R7 -> 4Q22 | AI7: =S7 -> 1Q23 | AJ7: =T7 -> 2Q23 | AK7: =U7 -> 3Q23 | AL7: =V7 -> 4Q23 | ... AS7: =AC7 -> 3Q25
B8: Fiscal Period End Date | C8: 43465 | D8: 43830 | E8: 44196 | F8: 44561 | G8: 44926 | H8: 45291 | I8: 45657 | K8: 44286 | L8: 44377 | M8: 44469 | N8: =F8 -> 44561 | O8: 44651 | P8: 44742 | Q8: 44834 | R8: =G8 -> 44926 | S8: 45016 | T8: 45107 | U8: 45199 | V8: =H8 -> 45291 | W8: 45382 | X8: 45473 | Y8: 45565 | Z8: =I8 -> 45657 | AA8: 45747 | AB8: 45838 | AC8: 45930 | AE8: =O8 -> 44651 | AF8: =P8 -> 44742 | AG8: =Q8 -> 44834 | AH8: =R8 -> 44926 | AI8: =S8 -> 45016 | AJ8: =T8 -> 45107 | AK8: =U8 -> 45199 | AL8: =V8 -> 45291 | ... AS8: =AC8 -> 45930
B10: Consolidated Revenue | C10: 15794341 | D10: 20156447 | E10: 24996056 | F10: 29697844 | G10: 31615550 | H10: 33723297 | I10: 39000966 | K10: 7163282 | L10: 7341777 | M10: 7483467 | N10: =SUM(F10-SUM(K10:M10)) -> 7709318 | O10: 7867767 | P10: 7970141 | Q10: 7925589 | R10: =SUM(G10-SUM(O10:Q10)) -> 7852053 | S10: 8161503 | T10: 8187301 | U10: 8541668 | V10: =SUM(H10-SUM(S10:U10)) -> 8832825 | W10: 9370440 | X10: 9559310 | Y10: 9824703 | Z10: =SUM(I10-SUM(W10:Y10)) -> 10246513 | AA10: 10542801 | AB10: 11079166 | AC10: 11510307 | AE10: =SUM(L10:O10) -> 30402329 | AF10: =SUM(M10:P10) -> 31030693 | AG10: =SUM(N10:Q10) -> 31472815 | AH10: =SUM(O10:R10) -> 31615550 | AI10: =SUM(P10:S10) -> 31909286 | AJ10: =SUM(Q10:T10) -> 32126446 | AK10: =SUM(R10:U10) -> 32742525 | AL10: =SUM(S10:V10) -> 33723297 | ... AS10: =SUM(Z10:AC10) -> 43378787 | AU10: =SUM(AS10/AO10)-1 -> 0.15408163
B11: Total Revenue | C11: =+SUM(C10:C10) -> 15794341 | D11: =+SUM(D10:D10) -> 20156447 | E11: =+SUM(E10:E10) -> 24996056 | F11: =+SUM(F10:F10) -> 29697844 | G11: =+SUM(G10:G10) -> 31615550 | H11: =+SUM(H10:H10) -> 33723297 | I11: =+SUM(I10:I10) -> 39000966 | K11: =+SUM(K10:K10) -> 7163282 | L11: =+SUM(L10:L10) -> 7341777 | M11: =+SUM(M10:M10) -> 7483467 | N11: =+SUM(N10:N10) -> 7709318 | O11: =+SUM(O10:O10) -> 7867767 | P11: =+SUM(P10:P10) -> 7970141 | Q11: =+SUM(Q10:Q10) -> 7925589 | R11: =+SUM(R10:R10) -> 7852053 | ... AC11: =+SUM(AC10:AC10) -> 11510307 | AE11: =+SUM(AE10:AE10) -> 30402329 | AF11: =+SUM(AF10:AF10) -> 31030693 | AG11: =+SUM(AG10:AG10) -> 31472815 | AH11: =+SUM(AH10:AH10) -> 31615550 | AI11: =+SUM(AI10:AI10) -> 31909286 | AJ11: =+SUM(AJ10:AJ10) -> 32126446 | AK11: =+SUM(AK10:AK10) -> 32742525 | AL11: =+SUM(AL10:AL10) -> 33723297 | ... AS11: =+SUM(AS10:AS10) -> 43378787 | AU11: =SUM(AS11/AO11)-1 -> 0.15408163
B13: Amortization of content assets | C13: -7532088 | D13: -9216247 | E13: -10806912 | F13: -12230367 | G13: -14026132 | H13: -14197437 | I13: -15301517 | K13: -2719196 | L13: -2806803 | M13: -2963051 | N13: =SUM(F13-SUM(K13:M13)) -> -3741317 | O13: -3166365 | P13: -3261348 | Q13: -3653592 | R13: =SUM(G13-SUM(O13:Q13)) -> -3944827 | S13: -3459984 | T13: -3410021 | U13: -3573353 | V13: =SUM(H13-SUM(S13:U13)) -> -3754079 | W13: -3670805 | X13: -3769690 | Y13: -3699521 | Z13: =SUM(I13-SUM(W13:Y13)) -> -4161501 | AA13: -3823112 | AB13: -3832074 | AC13: -4002744 | AE13: =SUM(L13:O13) -> -12677536 | AF13: =SUM(M13:P13) -> -13132081 | AG13: =SUM(N13:Q13) -> -13822622 | AH13: =SUM(O13:R13) -> -14026132 | AI13: =SUM(P13:S13) -> -14319751 | AJ13: =SUM(Q13:T13) -> -14468424 | AK13: =SUM(R13:U13) -> -14388185 | AL13: =SUM(S13:V13) -> -14197437 | ... AS13: =SUM(Z13:AC13) -> -15819431
B14: Other Cost of Revenues | C14: =+C15-C13 -> -2435450 | D14: =+D15-D13 -> -3223966 | E14: =+E15-E13 -> -4469407 | F14: =+F15-F13 -> -5102316 | G14: =+G15-G13 -> -5142153 | H14: =+H15-H13 -> -5517931 | I14: =+I15-I13 -> -5736947 | K14: =+K15-K13 -> -1149315 | L14: =+L15-L13 -> -1211205 | M14: =+M15-M13 -> -1243538 | N14: =+N15-N13 -> -1498258 | O14: =+O15-O13 -> -1118340 | P14: =+P15-P13 -> -1429407 | Q14: =+Q15-Q13 -> -1135073 | R14: =+R15-R13 -> -1459333 | ... AC14: =+AC15-AC13 -> -2161506 | AE14: =SUM(L14:O14) -> -5071341 | AF14: =SUM(M14:P14) -> -5289543 | AG14: =SUM(N14:Q14) -> -5181078 | AH14: =SUM(O14:R14) -> -5142153 | AI14: =SUM(P14:S14) -> -5367454 | AJ14: =SUM(Q14:T14) -> -5201496 | AK14: =SUM(R14:U14) -> -5423858 | AL14: =SUM(S14:V14) -> -5517931 | ... AS14: =SUM(Z14:AC14) -> -6700641
B15: Total Cost of Revenue | C15: -9967538 | D15: -12440213 | E15: -15276319 | F15: -17332683 | G15: -19168285 | H15: -19715368 | I15: -21038464 | K15: -3868511 | L15: -4018008 | M15: -4206589 | N15: =SUM(F15-SUM(K15:M15)) -> -5239575 | O15: -4284705 | P15: -4690755 | Q15: -4788665 | R15: =SUM(G15-SUM(O15:Q15)) -> -5404160 | S15: -4803625 | T15: -4673470 | U15: -4930788 | V15: =SUM(H15-SUM(S15:U15)) -> -5307485 | W15: -4977073 | X15: -5174143 | Y15: -5119884 | Z15: =SUM(I15-SUM(W15:Y15)) -> -5767364 | AA15: -5263147 | AB15: -5325311 | AC15: -6164250 | AE15: =SUM(L15:O15) -> -17748877 | AF15: =SUM(M15:P15) -> -18421624 | AG15: =SUM(N15:Q15) -> -19003700 | AH15: =SUM(O15:R15) -> -19168285 | AI15: =SUM(P15:S15) -> -19687205 | AJ15: =SUM(Q15:T15) -> -19669920 | AK15: =SUM(R15:U15) -> -19812043 | AL15: =SUM(S15:V15) -> -19715368 | ... AS15: =SUM(Z15:AC15) -> -22520072
B16: Gross Profit | C16: =+SUM(C11+SUM(C13:C14)) -> 5826803 | D16: =+SUM(D11+SUM(D13:D14)) -> 7716234 | E16: =+SUM(E11+SUM(E13:E14)) -> 9719737 | F16: =+SUM(F11+SUM(F13:F14)) -> 12365161 | G16: =+SUM(G11+SUM(G13:G14)) -> 12447265 | H16: =+SUM(H11+SUM(H13:H14)) -> 14007929 | I16: =+SUM(I11+SUM(I13:I14)) -> 17962502 | K16: =+SUM(K11+SUM(K13:K14)) -> 3294771 | L16: =+SUM(L11+SUM(L13:L14)) -> 3323769 | M16: =+SUM(M11+SUM(M13:M14)) -> 3276878 | N16: =+SUM(N11+SUM(N13:N14)) -> 2469743 | O16: =+SUM(O11+SUM(O13:O14)) -> 3583062 | P16: =+SUM(P11+SUM(P13:P14)) -> 3279386 | Q16: =+SUM(Q11+SUM(Q13:Q14)) -> 3136924 | R16: =+SUM(R11+SUM(R13:R14)) -> 2447893 | ... AC16: =+SUM(AC11+SUM(AC13:AC14)) -> 5346057 | AE16: =+SUM(AE11+SUM(AE13:AE14)) -> 12653452 | AF16: =+SUM(AF11+SUM(AF13:AF14)) -> 12609069 | AG16: =+SUM(AG11+SUM(AG13:AG14)) -> 12469115 | AH16: =+SUM(AH11+SUM(AH13:AH14)) -> 12447265 | AI16: =+SUM(AI11+SUM(AI13:AI14)) -> 12222081 | AJ16: =+SUM(AJ11+SUM(AJ13:AJ14)) -> 12456526 | AK16: =+SUM(AK11+SUM(AK13:AK14)) -> 12930482 | AL16: =+SUM(AL11+SUM(AL13:AL14)) -> 14007929 | ... AS16: =+SUM(AS11+SUM(AS13:AS14)) -> 20858715 | AU16: =SUM(AS16/AO16)-1 -> 0.22635613
B17: Gross Margin (%) | C17: =C16/C11 -> 0.36891713 | D17: =D16/D11 -> 0.38281717 | E17: =E16/E11 -> 0.38885083 | F17: =F16/F11 -> 0.41636561 | G17: =G16/G11 -> 0.39370705 | H17: =H16/H11 -> 0.4153784 | I17: =I16/I11 -> 0.46056557 | K17: =K16/K11 -> 0.45995271 | L17: =L16/L11 -> 0.45271996 | M17: =M16/M11 -> 0.43788233 | N17: =N16/N11 -> 0.32035817 | O17: =O16/O11 -> 0.45541028 | P17: =P16/P11 -> 0.41145897 | Q17: =Q16/Q11 -> 0.39579696 | R17: =R16/R11 -> 0.31175197 | ... AC17: =AC16/AC11 -> 0.46445825 | AE17: =AE16/AE11 -> 0.41620009 | AF17: =AF16/AF11 -> 0.40634184 | AG17: =AG16/AG11 -> 0.39618684 | AH17: =AH16/AH11 -> 0.39370705 | AI17: =AI16/AI11 -> 0.38302584 | AJ17: =AJ16/AJ11 -> 0.38773433 | AK17: =AK16/AK11 -> 0.39491401 | AL17: =AL16/AL11 -> 0.4153784 | ... AS17: =AS16/AS11 -> 0.48085058 | AU17: =SUM(AS17-AO17)*1000 -> 28.338618
B19: Marketing | C19: -2369469 | D19: -2652462 | E19: -2228362 | F19: -2545146 | G19: -2530502 | H19: -2657883 | I19: -2917554 | K19: -512512 | L19: -603973 | M19: -635948 | N19: =SUM(F19-SUM(K19:M19)) -> -792713 | O19: -555978 | P19: -574960 | Q19: -567954 | R19: =SUM(G19-SUM(O19:Q19)) -> -831610 | S19: -555362 | T19: -627168 | U19: -558736 | V19: =SUM(H19-SUM(S19:U19)) -> -916617 | W19: -654340 | X19: -644084 | Y19: -642926 | Z19: =SUM(I19-SUM(W19:Y19)) -> -976204 | AA19: -688370 | AB19: -713265 | AC19: -786295 | AE19: =SUM(L19:O19) -> -2588612 | AF19: =SUM(M19:P19) -> -2559599 | AG19: =SUM(N19:Q19) -> -2491605 | AH19: =SUM(O19:R19) -> -2530502 | AI19: =SUM(P19:S19) -> -2529886 | AJ19: =SUM(Q19:T19) -> -2582094 | AK19: =SUM(R19:U19) -> -2572876 | AL19: =SUM(S19:V19) -> -2657883 | ... AS19: =SUM(Z19:AC19) -> -3164134 | AU19: =SUM(AS19/AO19)-1 -> 0.10712755
B20: Technology and Development (T&D) | C20: -1221814 | D20: -1545149 | E20: -1829600 | F20: -2273885 | G20: -2711041 | H20: -2675758 | I20: -2925295 | K20: -525207 | L20: -537321 | M20: -563887 | N20: =SUM(F20-SUM(K20:M20)) -> -647470 | O20: -657530 | P20: -716846 | Q20: -662739 | R20: =SUM(G20-SUM(O20:Q20)) -> -673926 | S20: -687275 | T20: -657983 | U20: -657159 | V20: =SUM(H20-SUM(S20:U20)) -> -673341 | W20: -702473 | X20: -711254 | Y20: -735063 | Z20: =SUM(I20-SUM(W20:Y20)) -> -776505 | AA20: -822823 | AB20: -824683 | AC20: -853584 | AE20: =SUM(L20:O20) -> -2406208 | AF20: =SUM(M20:P20) -> -2585733 | AG20: =SUM(N20:Q20) -> -2684585 | AH20: =SUM(O20:R20) -> -2711041 | AI20: =SUM(P20:S20) -> -2740786 | AJ20: =SUM(Q20:T20) -> -2681923 | AK20: =SUM(R20:U20) -> -2676343 | AL20: =SUM(S20:V20) -> -2675758 | ... AS20: =SUM(Z20:AC20) -> -3277595 | AU20: =SUM(AS20/AO20)-1 -> 0.1613901
B21: General and Administrative (G&A) | C21: -630294 | D21: -914369 | E21: -1076486 | F21: -1351621 | G21: -1572891 | H21: -1720285 | I21: -1702039 | K21: -297196 | L21: -334845 | M21: -321790 | N21: =SUM(F21-SUM(K21:M21)) -> -397790 | O21: -397928 | P21: -409297 | Q21: -373213 | R21: =SUM(G21-SUM(O21:Q21)) -> -392453 | S21: -400924 | T21: -401497 | U21: -478591 | V21: =SUM(H21-SUM(S21:U21)) -> -439273 | W21: -404020 | X21: -426992 | Y21: -417353 | Z21: =SUM(I21-SUM(W21:Y21)) -> -453674 | AA21: -421462 | AB21: -441213 | AC21: -457931 | AE21: =SUM(L21:O21) -> -1452353 | AF21: =SUM(M21:P21) -> -1526805 | AG21: =SUM(N21:Q21) -> -1578228 | AH21: =SUM(O21:R21) -> -1572891 | AI21: =SUM(P21:S21) -> -1575887 | AJ21: =SUM(Q21:T21) -> -1568087 | AK21: =SUM(R21:U21) -> -1673465 | AL21: =SUM(S21:V21) -> -1720285 | ... AS21: =SUM(Z21:AC21) -> -1774280 | AU21: =SUM(AS21/AO21)-1 -> 0.051339209
B22: Operating Profit | C22: =+SUM(C16+SUM(C19:C21)) -> 1605226 | D22: =+SUM(D16+SUM(D19:D21)) -> 2604254 | E22: =+SUM(E16+SUM(E19:E21)) -> 4585289 | F22: =+SUM(F16+SUM(F19:F21)) -> 6194509 | G22: =+SUM(G16+SUM(G19:G21)) -> 5632831 | H22: =+SUM(H16+SUM(H19:H21)) -> 6954003 | I22: =+SUM(I16+SUM(I19:I21)) -> 10417614 | K22: =+SUM(K16+SUM(K19:K21)) -> 1959856 | L22: =+SUM(L16+SUM(L19:L21)) -> 1847630 | M22: =+SUM(M16+SUM(M19:M21)) -> 1755253 | N22: =+SUM(N16+SUM(N19:N21)) -> 631770 | O22: =+SUM(O16+SUM(O19:O21)) -> 1971626 | P22: =+SUM(P16+SUM(P19:P21)) -> 1578283 | Q22: =+SUM(Q16+SUM(Q19:Q21)) -> 1533018 | R22: =+SUM(R16+SUM(R19:R21)) -> 549904 | ... AC22: =+SUM(AC16+SUM(AC19:AC21)) -> 3248247 | AE22: =+SUM(AE16+SUM(AE19:AE21)) -> 6206279 | AF22: =+SUM(AF16+SUM(AF19:AF21)) -> 5936932 | AG22: =+SUM(AG16+SUM(AG19:AG21)) -> 5714697 | AH22: =+SUM(AH16+SUM(AH19:AH21)) -> 5632831 | AI22: =+SUM(AI16+SUM(AI19:AI21)) -> 5375522 | AJ22: =+SUM(AJ16+SUM(AJ19:AJ21)) -> 5624422 | AK22: =+SUM(AK16+SUM(AK19:AK21)) -> 6007798 | AL22: =+SUM(AL16+SUM(AL19:AL21)) -> 6954003 | ... AS22: =+SUM(AS16+SUM(AS19:AS21)) -> 12642706 | AU22: =SUM(AS22/AO22)-1 -> 0.31135384
B23: Operating Margin (%) | C23: =C22/C11 -> 0.10163298 | D23: =D22/D11 -> 0.12920204 | E23: =E22/E11 -> 0.1834405 | F23: =F22/F11 -> 0.20858447 | G23: =G22/G11 -> 0.17816647 | H23: =H22/H11 -> 0.20620768 | I23: =I22/I11 -> 0.26711169 | K23: =K22/K11 -> 0.27359749 | L23: =L22/L11 -> 0.25165978 | M23: =M22/M11 -> 0.23455078 | N23: =N22/N11 -> 0.081948883 | O23: =O22/O11 -> 0.25059537 | P23: =P22/P11 -> 0.19802448 | Q23: =Q22/Q11 -> 0.19342638 | R23: =R22/R11 -> 0.070033149 | ... AC23: =AC22/AC11 -> 0.28220333 | AE23: =AE22/AE11 -> 0.20413828 | AF23: =AF22/AF11 -> 0.19132451 | AG23: =AG22/AG11 -> 0.18157566 | AH23: =AH22/AH11 -> 0.17816647 | AI23: =AI22/AI11 -> 0.16846262 | AJ23: =AJ22/AJ11 -> 0.1750714 | AK23: =AK22/AK11 -> 0.18348609 | AL23: =AL22/AL11 -> 0.20620768 | ... AS23: =AS22/AS11 -> 0.29144904 | AU23: =SUM(AS23-AO23)*1000 -> 34.953828
B25: Interest Income | C25: 0 | D25: 0 | E25: 0 | F25: 0 | G25: 60000 | H25: 281000 | I25: 294000 | K25: 0 | L25: 0 | M25: 0 | N25: =SUM(F25-SUM(K25:M25)) -> 0 | O25: 0 | P25: 0 | Q25: 0 | R25: =SUM(G25-SUM(O25:Q25)) -> 60000 | S25: 0 | T25: 0 | U25: 0 | V25: =SUM(H25-SUM(S25:U25)) -> 281000 | W25: 67000 | X25: 63000 | Y25: 76000 | Z25: =SUM(I25-SUM(W25:Y25)) -> 88000 | AA25: 82000 | AB25: 72000 | AC25: 67000 | AE25: =SUM(L25:O25) -> 0 | AF25: =SUM(M25:P25) -> 0 | AG25: =SUM(N25:Q25) -> 0 | AH25: =SUM(O25:R25) -> 60000 | AI25: =SUM(P25:S25) -> 60000 | AJ25: =SUM(Q25:T25) -> 60000 | AK25: =SUM(R25:U25) -> 60000 | AL25: =SUM(S25:V25) -> 281000 | ... AS25: =SUM(Z25:AC25) -> 309000 | AU25: =SUM(AS25/AO25)-1 -> -0.36550308
B26: Interest Expense | C26: -420493 | D26: -626023 | E26: -767499 | F26: -765620 | G26: -706212 | H26: -699826 | I26: -718733 | K26: -194440 | L26: -191322 | M26: -190429 | N26: =SUM(F26-SUM(K26:M26)) -> -189429 | O26: -187579 | P26: -175455 | Q26: -172575 | R26: =SUM(G26-SUM(O26:Q26)) -> -170603 | S26: -174239 | T26: -174812 | U26: -175563 | V26: =SUM(H26-SUM(S26:U26)) -> -175212 | W26: -173314 | X26: -167986 | Y26: -184830 | Z26: =SUM(I26-SUM(W26:Y26)) -> -192603 | AA26: -184172 | AB26: -182649 | AC26: -175294 | AE26: =SUM(L26:O26) -> -758759 | AF26: =SUM(M26:P26) -> -742892 | AG26: =SUM(N26:Q26) -> -725038 | AH26: =SUM(O26:R26) -> -706212 | AI26: =SUM(P26:S26) -> -692872 | AJ26: =SUM(Q26:T26) -> -692229 | AK26: =SUM(R26:U26) -> -695217 | AL26: =SUM(S26:V26) -> -699826 | ... AS26: =SUM(Z26:AC26) -> -734718 | AU26: =SUM(AS26/AO26)-1 -> 0.047588766
B27: Other Income & Expenses | C27: 41725 | D27: 84000 | E27: -618441 | F27: 411214 | G27: =337310-G25 -> 277310 | H27: =-48772-H25 -> -329772 | I27: =266776-I25 -> -27224 | K27: 269086 | L27: -62519 | M27: 96135 | N27: =SUM(F27-SUM(K27:M27)) -> 108512 | O27: 195645 | P27: 220226 | Q27: 261404 | R27: =SUM(G27-SUM(O27:Q27)) -> -399965 | S27: -71204 | T27: 26961 | U27: 168218 | V27: =SUM(H27-SUM(S27:U27)) -> -453747 | W27: =155359-W25 -> 88359 | X27: =79005-X25 -> 16005 | Y27: =-21693-Y25 -> -97693 | Z27: =SUM(I27-SUM(W27:Y27)) -> -33895 | AA27: =50899-AA25 -> -31101 | AB27: =39630-AB25 -> -32370 | AC27: =36457-AC25 -> -30543 | AE27: =SUM(L27:O27) -> 337773 | AF27: =SUM(M27:P27) -> 620518 | AG27: =SUM(N27:Q27) -> 785787 | AH27: =SUM(O27:R27) -> 277310 | AI27: =SUM(P27:S27) -> 10461 | AJ27: =SUM(Q27:T27) -> -182804 | AK27: =SUM(R27:U27) -> -275990 | AL27: =SUM(S27:V27) -> -329772 | ... AS27: =SUM(Z27:AC27) -> -127909 | AU27: =SUM(AS27/AO27)-1 -> -0.71389876
B28: Earning Before Taxes | C28: =SUM(C22+SUM(C25:C27)) -> 1226458 | D28: =SUM(D22+SUM(D25:D27)) -> 2062231 | E28: =SUM(E22+SUM(E25:E27)) -> 3199349 | F28: =SUM(F22+SUM(F25:F27)) -> 5840103 | G28: =SUM(G22+SUM(G25:G27)) -> 5263929 | H28: =SUM(H22+SUM(H25:H27)) -> 6205405 | I28: =SUM(I22+SUM(I25:I27)) -> 9965657 | K28: =SUM(K22+SUM(K25:K27)) -> 2034502 | L28: =SUM(L22+SUM(L25:L27)) -> 1593789 | M28: =SUM(M22+SUM(M25:M27)) -> 1660959 | N28: =SUM(N22+SUM(N25:N27)) -> 550853 | O28: =SUM(O22+SUM(O25:O27)) -> 1979692 | P28: =SUM(P22+SUM(P25:P27)) -> 1623054 | Q28: =SUM(Q22+SUM(Q25:Q27)) -> 1621847 | R28: =SUM(R22+SUM(R25:R27)) -> 39336 | ... AC28: =SUM(AC22+SUM(AC25:AC27)) -> 3109410 | AE28: =SUM(AE22+SUM(AE25:AE27)) -> 5785293 | AF28: =SUM(AF22+SUM(AF25:AF27)) -> 5814558 | AG28: =SUM(AG22+SUM(AG25:AG27)) -> 5775446 | AH28: =SUM(AH22+SUM(AH25:AH27)) -> 5263929 | AI28: =SUM(AI22+SUM(AI25:AI27)) -> 4753111 | AJ28: =SUM(AJ22+SUM(AJ25:AJ27)) -> 4809389 | AK28: =SUM(AK22+SUM(AK25:AK27)) -> 5096591 | AL28: =SUM(AL22+SUM(AL25:AL27)) -> 6205405 | ... AS28: =SUM(AS22+SUM(AS25:AS27)) -> 12089079 | AU28: =SUM(AS28/AO28)-1 -> 0.34629172
B29: EBT Margin (%) | C29: =C28/C11 -> 0.077651736 | D29: =D28/D11 -> 0.10231124 | E29: =E28/E11 -> 0.12799415 | F29: =F28/F11 -> 0.19665074 | G29: =G28/G11 -> 0.1664981 | H29: =H28/H11 -> 0.18400944 | I29: =I28/I11 -> 0.25552334 | K29: =K28/K11 -> 0.28401814 | L29: =L28/L11 -> 0.21708491 | M29: =M28/M11 -> 0.22195047 | N29: =N28/N11 -> 0.071452883 | O29: =O28/O11 -> 0.25162057 | P29: =P28/P11 -> 0.20364182 | Q29: =Q28/Q11 -> 0.20463425 | R29: =R28/R11 -> 0.0050096452 | ... AC29: =AC28/AC11 -> 0.27014136 | AE29: =AE28/AE11 -> 0.19029111 | AF29: =AF28/AF11 -> 0.18738086 | AG29: =AG28/AG11 -> 0.18350586 | AH29: =AH28/AH11 -> 0.1664981 | AI29: =AI28/AI11 -> 0.14895698 | AJ29: =AJ28/AJ11 -> 0.14970187 | AK29: =AK28/AK11 -> 0.15565663 | AL29: =AL28/AL11 -> 0.18400944 | ... AS29: =AS28/AS11 -> 0.27868642 | AU29: =SUM(AS29-AO29)*1000 -> 39.788065
B31: Provision for taxes | C31: -15216 | D31: -195315 | E31: -437954 | F31: -723875 | G31: -772005 | H31: -797415 | I31: -1254026 | K31: -327787 | L31: -240776 | M31: -211888 | N31: =SUM(F31-SUM(K31:M31)) -> 56576 | O31: -382245 | P31: -182103 | Q31: -223605 | R31: =SUM(G31-SUM(O31:Q31)) -> 15948 | S31: -163754 | T31: -191722 | U31: -231627 | V31: =SUM(H31-SUM(S31:U31)) -> -210312 | W31: -282370 | X31: -366550 | Y31: -339445 | Z31: =SUM(I31-SUM(W31:Y31)) -> -265661 | AA31: -323375 | AB31: -506262 | AC31: -562494 | AE31: =SUM(L31:O31) -> -778333 | AF31: =SUM(M31:P31) -> -719660 | AG31: =SUM(N31:Q31) -> -731377 | AH31: =SUM(O31:R31) -> -772005 | AI31: =SUM(P31:S31) -> -553514 | AJ31: =SUM(Q31:T31) -> -563133 | AK31: =SUM(R31:U31) -> -571155 | AL31: =SUM(S31:V31) -> -797415 | ... AS31: =SUM(Z31:AC31) -> -1657792 | AU31: =SUM(AS31/AO31)-1 -> 0.38301811
B32: Net loss | C32: =SUM(C28+SUM(C31:C31)) -> 1211242 | D32: =SUM(D28+SUM(D31:D31)) -> 1866916 | E32: =SUM(E28+SUM(E31:E31)) -> 2761395 | F32: =SUM(F28+SUM(F31:F31)) -> 5116228 | G32: =SUM(G28+SUM(G31:G31)) -> 4491924 | H32: =SUM(H28+SUM(H31:H31)) -> 5407990 | I32: =SUM(I28+SUM(I31:I31)) -> 8711631 | K32: =SUM(K28+SUM(K31:K31)) -> 1706715 | L32: =SUM(L28+SUM(L31:L31)) -> 1353013 | M32: =SUM(M28+SUM(M31:M31)) -> 1449071 | N32: =SUM(N28+SUM(N31:N31)) -> 607429 | O32: =SUM(O28+SUM(O31:O31)) -> 1597447 | P32: =SUM(P28+SUM(P31:P31)) -> 1440951 | Q32: =SUM(Q28+SUM(Q31:Q31)) -> 1398242 | R32: =SUM(R28+SUM(R31:R31)) -> 55284 | ... AC32: =SUM(AC28+SUM(AC31:AC31)) -> 2546916 | AE32: =SUM(AE28+SUM(AE31:AE31)) -> 5006960 | AF32: =SUM(AF28+SUM(AF31:AF31)) -> 5094898 | AG32: =SUM(AG28+SUM(AG31:AG31)) -> 5044069 | AH32: =SUM(AH28+SUM(AH31:AH31)) -> 4491924 | AI32: =SUM(AI28+SUM(AI31:AI31)) -> 4199597 | AJ32: =SUM(AJ28+SUM(AJ31:AJ31)) -> 4246256 | AK32: =SUM(AK28+SUM(AK31:AK31)) -> 4525436 | AL32: =SUM(AL28+SUM(AL31:AL31)) -> 5407990 | ... AS32: =SUM(AS28+SUM(AS31:AS31)) -> 10431287 | AU32: =SUM(AS32/AO32)-1 -> 0.34063385
B33: Net Margin (%) | C33: =C32/C11 -> 0.076688353 | D33: =D32/D11 -> 0.092621284 | E33: =E32/E11 -> 0.11047323 | F33: =F32/F11 -> 0.17227607 | G33: =G32/G11 -> 0.14207958 | H33: =H32/H11 -> 0.16036362 | I33: =I32/I11 -> 0.22336962 | K33: =K32/K11 -> 0.2382588 | L33: =L32/L11 -> 0.18428958 | M33: =M32/M11 -> 0.19363632 | N33: =N32/N11 -> 0.078791535 | O33: =O32/O11 -> 0.2030369 | P33: =P32/P11 -> 0.18079366 | Q33: =Q32/Q11 -> 0.17642121 | R33: =R32/R11 -> 0.0070407064 | ... AC33: =AC32/AC11 -> 0.22127264 | AE33: =AE32/AE11 -> 0.16469001 | AF33: =AF32/AF11 -> 0.16418899 | AG33: =AG32/AG11 -> 0.16026749 | AH33: =AH32/AH11 -> 0.14207958 | AI33: =AI32/AI11 -> 0.1316105 | AJ33: =AJ32/AJ11 -> 0.13217323 | AK33: =AK32/AK11 -> 0.1382128 | AL33: =AL32/AL11 -> 0.16036362 | ... AS33: =AS32/AS11 -> 0.24046977 | AU33: =SUM(AS33-AO33)*1000 -> 33.461911
B35: Basic EPS | AU35: =SUM(AS35/AO35)-1 -> #DIV/0!
B36: Fully Diluted EPS | AU36: =SUM(AS36/AO36)-1 -> #DIV/0!
A38: X | B38: Balance Sheet | AN38: LTM | AU38: Variance
B39: =B7 -> Fiscal Period | C39: =C7 -> 2018 | D39: =D7 -> 2019 | E39: =E7 -> 2020 | F39: =F7 -> 2021 | G39: =G7 -> 2022 | H39: =H7 -> 2023 | I39: =I7 -> 2024 | K39: =K7 -> 1Q21 | L39: =L7 -> 2Q21 | M39: =M7 -> 3Q21 | N39: =N7 -> 4Q21 | O39: =O7 -> 1Q22 | P39: =P7 -> 2Q22 | Q39: =Q7 -> 3Q22 | R39: =R7 -> 4Q22 | ... AC39: =AC7 -> 3Q25 | AE39: =AE7 -> 1Q22 | AF39: =AF7 -> 2Q22 | AG39: =AG7 -> 3Q22 | AH39: =AH7 -> 4Q22 | AI39: =AI7 -> 1Q23 | AJ39: =AJ7 -> 2Q23 | AK39: =AK7 -> 3Q23 | AL39: =AL7 -> 4Q23 | ... AS39: =AS7 -> 3Q25
B40: =B8 -> Fiscal Period End Date | C40: =C8 -> 43465 | D40: =D8 -> 43830 | E40: =E8 -> 44196 | F40: =F8 -> 44561 | G40: =G8 -> 44926 | H40: =H8 -> 45291 | I40: =I8 -> 45657 | K40: =K8 -> 44286 | L40: =L8 -> 44377 | M40: =M8 -> 44469 | N40: =N8 -> 44561 | O40: =O8 -> 44651 | P40: =P8 -> 44742 | Q40: =Q8 -> 44834 | R40: =R8 -> 44926 | ... AC40: =AC8 -> 45930 | AE40: =AE8 -> 44651 | AF40: =AF8 -> 44742 | AG40: =AG8 -> 44834 | AH40: =AH8 -> 44926 | AI40: =AI8 -> 45016 | AJ40: =AJ8 -> 45107 | AK40: =AK8 -> 45199 | AL40: =AL8 -> 45291 | ... AS40: =AS8 -> 45930
B42: Current Assets
B43: Cash and cash equivalents | C43: 3794483 | D43: 5018437 | E43: 8205550 | F43: 6027804 | G43: 5147176 | H43: 7116913 | I43: 7804733 | K43: 8403705 | L43: 7777530 | M43: 7526681 | N43: =F43 -> 6027804 | O43: 6008946 | P43: 5819449 | Q43: 6113733 | R43: =G43 -> 5147176 | S43: 6714594 | T43: 7662788 | U43: 7353245 | V43: =H43 -> 7116913 | W43: 7024766 | X43: 6624939 | Y43: 7457025 | Z43: =I43 -> 7804733 | AA43: 7199848 | AB43: 8177405 | AC43: 9287287 | AE43: =O43 -> 6008946 | AF43: =P43 -> 5819449 | AG43: =Q43 -> 6113733 | AH43: =R43 -> 5147176 | AI43: =S43 -> 6714594 | AJ43: =T43 -> 7662788 | AK43: =U43 -> 7353245 | AL43: =V43 -> 7116913 | ... AS43: =AC43 -> 9287287 | AU43: =SUM(AS43/AO43)-1 -> 0.24544131
B44: Other current assets | C44: 748466 | D44: 1160067 | E44: 1556030 | F44: 2042021 | G44: 3208021 | H44: 2780247 | I44: 3516640 | K44: 1703803 | L44: 1826746 | M44: 1889106 | N44: =F44 -> 2042021 | O44: 2089069 | P44: 2021329 | Q44: 2703170 | R44: =G44 -> 3208021 | S44: 2655119 | T44: 2929347 | U44: 2912028 | V44: =H44 -> 2780247 | W44: 2875574 | X44: 2959641 | Y44: 2905172 | Z44: =I44 -> 3516640 | AA44: 3326642 | AB44: 3602586 | AC44: 3638543 | AE44: =O44 -> 2089069 | AF44: =P44 -> 2021329 | AG44: =Q44 -> 2703170 | AH44: =R44 -> 3208021 | AI44: =S44 -> 2655119 | AJ44: =T44 -> 2929347 | AK44: =U44 -> 2912028 | AL44: =V44 -> 2780247 | ... AS44: =AC44 -> 3638543 | AU44: =SUM(AS44/AO44)-1 -> 0.25243634
B45: Short-term investments | C45: 0 | D45: 0 | E45: 0 | F45: 0 | G45: 911276 | H45: 20973 | I45: 1779006 | K45: 0 | L45: 0 | M45: 0 | N45: =F45 -> 0 | O45: 0 | P45: 0 | Q45: 0 | R45: =G45 -> 911276 | S45: 1112910 | T45: 914201 | U45: 514201 | V45: =H45 -> 20973 | W45: 20973 | X45: 30973 | Y45: 1766902 | Z45: =I45 -> 1779006 | AA45: 1171142 | AB45: 213115 | AC45: 37105 | AE45: =O45 -> 0 | AF45: =P45 -> 0 | AG45: =Q45 -> 0 | AH45: =R45 -> 911276 | AI45: =S45 -> 1112910 | AJ45: =T45 -> 914201 | AK45: =U45 -> 514201 | AL45: =V45 -> 20973 | ... AS45: =AC45 -> 37105 | AU45: =SUM(AS45/AO45)-1 -> -0.97899997
B46: Total Current Assets | C46: =SUM(C43:C45) -> 4542949 | D46: =SUM(D43:D45) -> 6178504 | E46: =SUM(E43:E45) -> 9761580 | F46: =SUM(F43:F45) -> 8069825 | G46: =SUM(G43:G45) -> 9266473 | H46: =SUM(H43:H45) -> 9918133 | I46: =SUM(I43:I45) -> 13100379 | K46: =SUM(K43:K45) -> 10107508 | L46: =SUM(L43:L45) -> 9604276 | M46: =SUM(M43:M45) -> 9415787 | N46: =SUM(N43:N45) -> 8069825 | O46: =SUM(O43:O45) -> 8098015 | P46: =SUM(P43:P45) -> 7840778 | Q46: =SUM(Q43:Q45) -> 8816903 | R46: =SUM(R43:R45) -> 9266473 | ... AC46: =SUM(AC43:AC45) -> 12962935 | AE46: =SUM(AE43:AE45) -> 8098015 | AF46: =SUM(AF43:AF45) -> 7840778 | AG46: =SUM(AG43:AG45) -> 8816903 | AH46: =SUM(AH43:AH45) -> 9266473 | AI46: =SUM(AI43:AI45) -> 10482623 | AJ46: =SUM(AJ43:AJ45) -> 11506336 | AK46: =SUM(AK43:AK45) -> 10779474 | AL46: =SUM(AL43:AL45) -> 9918133 | ... AS46: =SUM(AS43:AS45) -> 12962935 | AU46: =SUM(AS46/AO46)-1 -> 0.068746739
B48: Non-Current Assets
B49: Content assets, net | C49: 20102327 | D49: 24504567 | E49: 25383950 | F49: 30919539 | G49: 32736713 | H49: 31658056 | I49: 32452462 | K49: 26043991 | L49: 27291640 | M49: 28974045 | N49: =F49 -> 30919539 | O49: 31191920 | P49: 32533199 | Q49: 32777340 | R49: =G49 -> 32736713 | S49: 32349184 | T49: 32520774 | U49: 31749861 | V49: =H49 -> 31658056 | W49: 31662100 | X49: 31927355 | Y49: 32175382 | Z49: =I49 -> 32452462 | AA49: 32040839 | AB49: 32089394 | AC49: 32639879 | AE49: =O49 -> 31191920 | AF49: =P49 -> 32533199 | AG49: =Q49 -> 32777340 | AH49: =R49 -> 32736713 | AI49: =S49 -> 32349184 | AJ49: =T49 -> 32520774 | AK49: =U49 -> 31749861 | AL49: =V49 -> 31658056 | ... AS49: =AC49 -> 32639879 | AU49: =SUM(AS49/AO49)-1 -> 0.01443641
B50: Property and equipment, net | C50: 418281 | D50: 565221 | E50: 960183 | F50: 1323453 | G50: 1398257 | H50: 1491444 | I50: 1593756 | K50: 1015419 | L50: 1107437 | M50: 1220114 | N50: =F50 -> 1323453 | O50: 1383763 | P50: 1361920 | Q50: 1372754 | R50: =G50 -> 1398257 | S50: 1413094 | T50: 1471968 | U50: 1498391 | V50: =H50 -> 1491444 | W50: 1501168 | X50: 1510958 | Y50: 1568212 | Z50: =I50 -> 1593756 | AA50: 1644346 | AB50: 1743566 | AC50: 1837889 | AE50: =O50 -> 1383763 | AF50: =P50 -> 1361920 | AG50: =Q50 -> 1372754 | AH50: =R50 -> 1398257 | AI50: =S50 -> 1413094 | AJ50: =T50 -> 1471968 | AK50: =U50 -> 1498391 | AL50: =V50 -> 1491444 | ... AS50: =AC50 -> 1837889 | AU50: =SUM(AS50/AO50)-1 -> 0.17196463
B51: Other non-current assets | C51: 910843 | D51: 2727420 | E51: 3174646 | F51: 4271846 | G51: 5193325 | H51: 5664359 | I51: 6483777 | K51: 2956096 | L51: 2967616 | M51: 3129911 | N51: =F51 -> 4271846 | O51: 4657206 | P51: 4615038 | Q51: 4595190 | R51: =G51 -> 5193325 | S51: 5245444 | T51: 5318395 | U51: 5474060 | V51: =H51 -> 5664359 | W51: 5743140 | X51: 6045029 | Y51: 6409151 | Z51: =I51 -> 6483777 | AA51: 6704827 | AB51: 7273598 | AC51: 7494132 | AE51: =O51 -> 4657206 | AF51: =P51 -> 4615038 | AG51: =Q51 -> 4595190 | AH51: =R51 -> 5193325 | AI51: =S51 -> 5245444 | AJ51: =T51 -> 5318395 | AK51: =U51 -> 5474060 | AL51: =V51 -> 5664359 | ... AS51: =AC51 -> 7494132 | AU51: =SUM(AS51/AO51)-1 -> 0.16928623
B52: Total Assets | C52: =SUM(C49:C51)+C46 -> 25974400 | D52: =SUM(D49:D51)+D46 -> 33975712 | E52: =SUM(E49:E51)+E46 -> 39280359 | F52: =SUM(F49:F51)+F46 -> 44584663 | G52: =SUM(G49:G51)+G46 -> 48594768 | H52: =SUM(H49:H51)+H46 -> 48731992 | I52: =SUM(I49:I51)+I46 -> 53630374 | K52: =SUM(K49:K51)+K46 -> 40123014 | L52: =SUM(L49:L51)+L46 -> 40970969 | M52: =SUM(M49:M51)+M46 -> 42739857 | N52: =SUM(N49:N51)+N46 -> 44584663 | O52: =SUM(O49:O51)+O46 -> 45330904 | P52: =SUM(P49:P51)+P46 -> 46350935 | Q52: =SUM(Q49:Q51)+Q46 -> 47562187 | R52: =SUM(R49:R51)+R46 -> 48594768 | ... AC52: =SUM(AC49:AC51)+AC46 -> 54934835 | AE52: =SUM(AE49:AE51)+AE46 -> 45330904 | AF52: =SUM(AF49:AF51)+AF46 -> 46350935 | AG52: =SUM(AG49:AG51)+AG46 -> 47562187 | AH52: =SUM(AH49:AH51)+AH46 -> 48594768 | AI52: =SUM(AI49:AI51)+AI46 -> 49490345 | AJ52: =SUM(AJ49:AJ51)+AJ46 -> 50817473 | AK52: =SUM(AK49:AK51)+AK46 -> 49501786 | AL52: =SUM(AL49:AL51)+AL46 -> 48731992 | ... AS52: =SUM(AS49:AS51)+AS46 -> 54934835 | AU52: =SUM(AS52/AO52)-1 -> 0.050744021
B54: Current Liabilities
B55: Current content liabilities | C55: 4681562 | D55: 4413561 | E55: 4429536 | F55: 4292967 | G55: 4480150 | H55: 4466470 | I55: 4393681 | K55: 4297957 | L55: 4197874 | M55: 4110962 | N55: =F55 -> 4292967 | O55: 4066289 | P55: 4174966 | Q55: 4225890 | R55: =G55 -> 4480150 | S55: 4344580 | T55: 4440412 | U55: 4259582 | V55: =H55 -> 4466470 | W55: 4436021 | X55: 4391437 | Y55: 4489971 | Z55: =I55 -> 4393681 | AA55: 4128905 | AB55: 4091770 | AC55: 4102640 | AE55: =O55 -> 4066289 | AF55: =P55 -> 4174966 | AG55: =Q55 -> 4225890 | AH55: =R55 -> 4480150 | AI55: =S55 -> 4344580 | AJ55: =T55 -> 4440412 | AK55: =U55 -> 4259582 | AL55: =V55 -> 4466470 | ... AS55: =AC55 -> 4102640 | AU55: =SUM(AS55/AO55)-1 -> -0.086265813
B56: Accounts payable | C56: 562985 | D56: 674347 | E56: 656183 | F56: 837483 | G56: 671513 | H56: 747412 | I56: 899909 | K56: 532942 | L56: 622931 | M56: 643059 | N56: =F56 -> 837483 | O56: 617202 | P56: 504278 | Q56: 560156 | R56: =G56 -> 671513 | S56: 591987 | T56: 615374 | U56: 534429 | V56: =H56 -> 747412 | W56: 607348 | X56: 598557 | Y56: 641953 | Z56: =I56 -> 899909 | AA56: 614489 | AB56: 632718 | AC56: 793233 | AE56: =O56 -> 617202 | AF56: =P56 -> 504278 | AG56: =Q56 -> 560156 | AH56: =R56 -> 671513 | AI56: =S56 -> 591987 | AJ56: =T56 -> 615374 | AK56: =U56 -> 534429 | AL56: =V56 -> 747412 | ... AS56: =AC56 -> 793233 | AU56: =SUM(AS56/AO56)-1 -> 0.23565588
B57: Accrued expenses and other liabilities | C57: 481874 | D57: 843043 | E57: 1102196 | F57: 1449351 | G57: 1514650 | H57: 1803960 | I57: 2156544 | K57: 1291812 | L57: 1125591 | M57: 1413120 | N57: =F57 -> 1449351 | O57: 1817117 | P57: 1596035 | Q57: 1803555 | R57: =G57 -> 1514650 | S57: 1718069 | T57: 1908714 | U57: 1838908 | V57: =H57 -> 1803960 | W57: 1977428 | X57: 1876244 | Y57: 2241758 | Z57: =I57 -> 2156544 | AA57: 2359518 | AB57: 2489486 | AC57: 3111311 | AE57: =O57 -> 1817117 | AF57: =P57 -> 1596035 | AG57: =Q57 -> 1803555 | AH57: =R57 -> 1514650 | AI57: =S57 -> 1718069 | AJ57: =T57 -> 1908714 | AK57: =U57 -> 1838908 | AL57: =V57 -> 1803960 | ... AS57: =AC57 -> 3111311 | AU57: =SUM(AS57/AO57)-1 -> 0.38788888
B58: Deferred revenue | C58: 760899 | D58: 924745 | E58: 1117992 | F58: 1209342 | G58: 1264661 | H58: 1442969 | I58: 1520813 | K58: 1140271 | L58: 1187364 | M58: 1182632 | N58: =F58 -> 1209342 | O58: 1239048 | P58: 1224743 | Q58: 1176323 | R58: =G58 -> 1264661 | S58: 1262271 | T58: 1311918 | U58: 1306185 | V58: =H58 -> 1442969 | W58: 1469484 | X58: 1473720 | Y58: 1513048 | Z58: =I58 -> 1520813 | AA58: 1609726 | AB58: 1728361 | AC58: 1724675 | AE58: =O58 -> 1239048 | AF58: =P58 -> 1224743 | AG58: =Q58 -> 1176323 | AH58: =R58 -> 1264661 | AI58: =S58 -> 1262271 | AJ58: =T58 -> 1311918 | AK58: =U58 -> 1306185 | AL58: =V58 -> 1442969 | ... AS58: =AC58 -> 1724675 | AU58: =SUM(AS58/AO58)-1 -> 0.139868
B59: Short-term debt | C59: 0 | D59: 0 | E59: 499878 | F59: 699823 | G59: 0 | H59: 399844 | I59: 1784453 | K59: 698788 | L59: 699128 | M59: 699473 | N59: =F59 -> 699823 | O59: 0 | P59: 0 | Q59: 0 | R59: =G59 -> 0 | S59: 399163 | T59: 399387 | U59: 399614 | V59: =H59 -> 399844 | W59: 798936 | X59: 1800041 | Y59: 1820396 | Z59: =I59 -> 1784453 | AA59: 1005881 | AB59: 0 | AC59: 0 | AE59: =O59 -> 0 | AF59: =P59 -> 0 | AG59: =Q59 -> 0 | AH59: =R59 -> 0 | AI59: =S59 -> 399163 | AJ59: =T59 -> 399387 | AK59: =U59 -> 399614 | AL59: =V59 -> 399844 | ... AS59: =AC59 -> 0 | AU59: =SUM(AS59/AO59)-1 -> -1
B60: Total Current Liabilities | C60: =SUM(C55:C59) -> 6487320 | D60: =SUM(D55:D59) -> 6855696 | E60: =SUM(E55:E59) -> 7805785 | F60: =SUM(F55:F59) -> 8488966 | G60: =SUM(G55:G59) -> 7930974 | H60: =SUM(H55:H59) -> 8860655 | I60: =SUM(I55:I59) -> 10755400 | K60: =SUM(K55:K59) -> 7961770 | L60: =SUM(L55:L59) -> 7832888 | M60: =SUM(M55:M59) -> 8049246 | N60: =SUM(N55:N59) -> 8488966 | O60: =SUM(O55:O59) -> 7739656 | P60: =SUM(P55:P59) -> 7500022 | Q60: =SUM(Q55:Q59) -> 7765924 | R60: =SUM(R55:R59) -> 7930974 | ... AC60: =SUM(AC55:AC59) -> 9731859 | AE60: =SUM(AE55:AE59) -> 7739656 | AF60: =SUM(AF55:AF59) -> 7500022 | AG60: =SUM(AG55:AG59) -> 7765924 | AH60: =SUM(AH55:AH59) -> 7930974 | AI60: =SUM(AI55:AI59) -> 8316070 | AJ60: =SUM(AJ55:AJ59) -> 8675805 | AK60: =SUM(AK55:AK59) -> 8338718 | AL60: =SUM(AL55:AL59) -> 8860655 | ... AS60: =SUM(AS55:AS59) -> 9731859 | AU60: =SUM(AS60/AO60)-1 -> -0.091085787
B62: Non-Current Liabilities
B63: Non-current content liabilities | C63: 3759026 | D63: 3334323 | E63: 2618084 | F63: 3094213 | G63: 3081277 | H63: 2578173 | I63: 1780806 | K63: 2465626 | L63: 2265286 | M63: 2301026 | N63: =F63 -> 3094213 | O63: 2945221 | P63: 2989961 | Q63: 2955368 | R63: =G63 -> 3081277 | S63: 2908029 | T63: 2849387 | U63: 2668472 | V63: =H63 -> 2578173 | W63: 2370692 | X63: 2028782 | Y63: 1918089 | Z63: =I63 -> 1780806 | AA63: 1696662 | AB63: 1606404 | AC63: 1591973 | AE63: =O63 -> 2945221 | AF63: =P63 -> 2989961 | AG63: =Q63 -> 2955368 | AH63: =R63 -> 3081277 | AI63: =S63 -> 2908029 | AJ63: =T63 -> 2849387 | AK63: =U63 -> 2668472 | AL63: =V63 -> 2578173 | ... AS63: =AC63 -> 1591973 | AU63: =SUM(AS63/AO63)-1 -> -0.17002131
B64: Long-term debt | C64: 10360058 | D64: 14759260 | E64: 15809095 | F64: 14693072 | G64: 14353076 | H64: 14143417 | I64: 13798351 | K64: 14860552 | L64: 14926889 | M64: 14793691 | N64: =F64 -> 14693072 | O64: 14534561 | P64: 14233303 | Q64: 13888117 | R64: =G64 -> 14353076 | S64: 14037965 | T64: 14070151 | U64: 13900754 | V64: =H64 -> 14143417 | W64: 13217038 | X64: 12180024 | Y64: 14160932 | Z64: =I64 -> 13798351 | AA64: 14011037 | AB64: 14453206 | AC64: 14463020 | AE64: =O64 -> 14534561 | AF64: =P64 -> 14233303 | AG64: =Q64 -> 13888117 | AH64: =R64 -> 14353076 | AI64: =S64 -> 14037965 | AJ64: =T64 -> 14070151 | AK64: =U64 -> 13900754 | AL64: =V64 -> 14143417 | ... AS64: =AC64 -> 14463020 | AU64: =SUM(AS64/AO64)-1 -> 0.021332494
B65: Other non-current liabilities | C65: 129231 | D65: 1444276 | E65: 1982155 | F65: 2459164 | G65: 2452040 | H65: 2561434 | I65: 2552250 | K65: 1950986 | L65: 2082035 | M65: 2281277 | N65: =F65 -> 2459164 | O65: 2567427 | P65: 2551675 | Q65: 2424637 | R65: =G65 -> 2452040 | S65: 2400085 | T65: 2389915 | U65: 2486215 | V65: =H65 -> 2561434 | W65: 2585364 | X65: 2637397 | Y65: 2774961 | Z65: =I65 -> 2552250 | AA65: 2633353 | AB65: 3145820 | AC65: 3193948 | AE65: =O65 -> 2567427 | AF65: =P65 -> 2551675 | AG65: =Q65 -> 2424637 | AH65: =R65 -> 2452040 | AI65: =S65 -> 2400085 | AJ65: =T65 -> 2389915 | AK65: =U65 -> 2486215 | AL65: =V65 -> 2561434 | ... AS65: =AC65 -> 3193948 | AU65: =SUM(AS65/AO65)-1 -> 0.15098843
B66: Total Liabilities | C66: =SUM(C63:C65)+C60 -> 20735635 | D66: =SUM(D63:D65)+D60 -> 26393555 | E66: =SUM(E63:E65)+E60 -> 28215119 | F66: =SUM(F63:F65)+F60 -> 28735415 | G66: =SUM(G63:G65)+G60 -> 27817367 | H66: =SUM(H63:H65)+H60 -> 28143679 | I66: =SUM(I63:I65)+I60 -> 28886807 | K66: =SUM(K63:K65)+K60 -> 27238934 | L66: =SUM(L63:L65)+L60 -> 27107098 | M66: =SUM(M63:M65)+M60 -> 27425240 | N66: =SUM(N63:N65)+N60 -> 28735415 | O66: =SUM(O63:O65)+O60 -> 27786865 | P66: =SUM(P63:P65)+P60 -> 27274961 | Q66: =SUM(Q63:Q65)+Q60 -> 27034046 | R66: =SUM(R63:R65)+R60 -> 27817367 | ... AC66: =SUM(AC63:AC65)+AC60 -> 28980800 | AE66: =SUM(AE63:AE65)+AE60 -> 27786865 | AF66: =SUM(AF63:AF65)+AF60 -> 27274961 | AG66: =SUM(AG63:AG65)+AG60 -> 27034046 | AH66: =SUM(AH63:AH65)+AH60 -> 27817367 | AI66: =SUM(AI63:AI65)+AI60 -> 27662149 | AJ66: =SUM(AJ63:AJ65)+AJ60 -> 27985258 | AK66: =SUM(AK63:AK65)+AK60 -> 27394159 | AL66: =SUM(AL63:AL65)+AL60 -> 28143679 | ... AS66: =SUM(AS63:AS65)+AS60 -> 28980800 | AU66: =SUM(AS66/AO66)-1 -> -0.019630793
B68: Common stock | C68: 2315988 | D68: 2793929 | E68: 3447698 | F68: 4024561 | G68: 4637601 | H68: 5145172 | I68: 6252126 | K68: 3600084 | L68: 3721246 | M68: 3852531 | N68: =F68 -> 4024561 | O68: 4155580 | P68: 4316870 | Q68: 4473962 | R68: =G68 -> 4637601 | S68: 4762395 | T68: 4874208 | U68: 5011427 | V68: =H68 -> 5145172 | W68: 5489850 | X68: 5680061 | Y68: 5887903 | Z68: =I68 -> 6252126 | AA68: 6677469 | AB68: 6932828 | AC68: 7080325 | AE68: =O68 -> 4155580 | AF68: =P68 -> 4316870 | AG68: =Q68 -> 4473962 | AH68: =R68 -> 4637601 | AI68: =S68 -> 4762395 | AJ68: =T68 -> 4874208 | AK68: =U68 -> 5011427 | AL68: =V68 -> 5145172 | ... AS68: =AC68 -> 7080325 | AU68: =SUM(AS68/AO68)-1 -> 0.20252066
B69: Treasury stock at cost | C69: 0 | D69: 0 | E69: 0 | F69: -824190 | G69: -824190 | H69: -6922200 | I69: -13171638 | K69: 0 | L69: -500022 | M69: -600022 | N69: =F69 -> -824190 | O69: -824190 | P69: -824190 | Q69: -824190 | R69: =G69 -> -824190 | S69: -1228920 | T69: -1876753 | U69: -4399677 | V69: =H69 -> -6922200 | W69: -8934056 | X69: -10547055 | Y69: -12254855 | Z69: =I69 -> -13171638 | AA69: -16754929 | AB69: -18392942 | AC69: -20270631 | AE69: =O69 -> -824190 | AF69: =P69 -> -824190 | AG69: =Q69 -> -824190 | AH69: =R69 -> -824190 | AI69: =S69 -> -1228920 | AJ69: =T69 -> -1876753 | AK69: =U69 -> -4399677 | AL69: =V69 -> -6922200 | ... AS69: =AC69 -> -20270631 | AU69: =SUM(AS69/AO69)-1 -> 0.65408983
B70: Accumulated other comprehensive income (loss) | C70: -19582 | D70: -23521 | E70: 44398 | F70: -40495 | G70: -217306 | H70: -223945 | I70: 362162 | K70: 4137 | L70: 9775 | M70: -19835 | N70: =F70 -> -40495 | O70: -74170 | P70: -144476 | Q70: -247643 | R70: =G70 -> -217306 | S70: -191695 | T70: -139266 | U70: -155571 | V70: =H70 -> -223945 | W70: -111879 | X70: -89114 | Y70: -344622 | Z70: =I70 -> 362162 | AA70: -85735 | AB70: -904668 | AC70: -719256 | AE70: =O70 -> -74170 | AF70: =P70 -> -144476 | AG70: =Q70 -> -247643 | AH70: =R70 -> -217306 | AI70: =S70 -> -191695 | AJ70: =T70 -> -139266 | AK70: =U70 -> -155571 | AL70: =V70 -> -223945 | ... AS70: =AC70 -> -719256 | AU70: =SUM(AS70/AO70)-1 -> 1.0870867
B71: Retained earnings | C71: 2942359 | D71: 4811749 | E71: 7573144 | F71: 12689372 | G71: 17181296 | H71: 22589286 | I71: 31300917 | K71: 9279859 | L71: 10632872 | M71: 12081943 | N71: =F71 -> 12689372 | O71: 14286819 | P71: 15727770 | Q71: 17126012 | R71: =G71 -> 17181296 | S71: 18486416 | T71: 19974026 | U71: 21651448 | V71: =H71 -> 22589286 | W71: 24921495 | X71: 27068801 | Y71: 29432310 | Z71: =I71 -> 31300917 | AA71: 34191268 | AB71: 37316681 | AC71: 39863597 | AE71: =O71 -> 14286819 | AF71: =P71 -> 15727770 | AG71: =Q71 -> 17126012 | AH71: =R71 -> 17181296 | AI71: =S71 -> 18486416 | AJ71: =T71 -> 19974026 | AK71: =U71 -> 21651448 | AL71: =V71 -> 22589286 | ... AS71: =AC71 -> 39863597 | AU71: =SUM(AS71/AO71)-1 -> 0.35441618
B72: Total stockholders' equity | C72: =SUM(C68:C71) -> 5238765 | D72: =SUM(D68:D71) -> 7582157 | E72: =SUM(E68:E71) -> 11065240 | F72: =SUM(F68:F71) -> 15849248 | G72: =SUM(G68:G71) -> 20777401 | H72: =SUM(H68:H71) -> 20588313 | I72: =SUM(I68:I71) -> 24743567 | K72: =SUM(K68:K71) -> 12884080 | L72: =SUM(L68:L71) -> 13863871 | M72: =SUM(M68:M71) -> 15314617 | N72: =SUM(N68:N71) -> 15849248 | O72: =SUM(O68:O71) -> 17544039 | P72: =SUM(P68:P71) -> 19075974 | Q72: =SUM(Q68:Q71) -> 20528141 | R72: =SUM(R68:R71) -> 20777401 | ... AC72: =SUM(AC68:AC71) -> 25954035 | AE72: =SUM(AE68:AE71) -> 17544039 | AF72: =SUM(AF68:AF71) -> 19075974 | AG72: =SUM(AG68:AG71) -> 20528141 | AH72: =SUM(AH68:AH71) -> 20777401 | AI72: =SUM(AI68:AI71) -> 21828196 | AJ72: =SUM(AJ68:AJ71) -> 22832215 | AK72: =SUM(AK68:AK71) -> 22107627 | AL72: =SUM(AL68:AL71) -> 20588313 | ... AS72: =SUM(AS68:AS71) -> 25954035 | AU72: =SUM(AS72/AO72)-1 -> 0.14230609
B73: Total liabilities and stockholders' equity | C73: =SUM(C72+C66) -> 25974400 | D73: =SUM(D72+D66) -> 33975712 | E73: =SUM(E72+E66) -> 39280359 | F73: =SUM(F72+F66) -> 44584663 | G73: =SUM(G72+G66) -> 48594768 | H73: =SUM(H72+H66) -> 48731992 | I73: =SUM(I72+I66) -> 53630374 | K73: =SUM(K72+K66) -> 40123014 | L73: =SUM(L72+L66) -> 40970969 | M73: =SUM(M72+M66) -> 42739857 | N73: =SUM(N72+N66) -> 44584663 | O73: =SUM(O72+O66) -> 45330904 | P73: =SUM(P72+P66) -> 46350935 | Q73: =SUM(Q72+Q66) -> 47562187 | R73: =SUM(R72+R66) -> 48594768 | ... AC73: =SUM(AC72+AC66) -> 54934835 | AE73: =SUM(AE72+AE66) -> 45330904 | AF73: =SUM(AF72+AF66) -> 46350935 | AG73: =SUM(AG72+AG66) -> 47562187 | AH73: =SUM(AH72+AH66) -> 48594768 | AI73: =SUM(AI72+AI66) -> 49490345 | AJ73: =SUM(AJ72+AJ66) -> 50817473 | AK73: =SUM(AK72+AK66) -> 49501786 | AL73: =SUM(AL72+AL66) -> 48731992 | ... AS73: =SUM(AS72+AS66) -> 54934835 | AU73: =SUM(AS73/AO73)-1 -> 0.050744021
B75: Balance Check | C75: =C73-C52 -> 0 | D75: =D73-D52 -> 0 | E75: =E73-E52 -> 0 | F75: =F73-F52 -> 0 | G75: =G73-G52 -> 0 | H75: =H73-H52 -> 0 | I75: =I73-I52 -> 0 | K75: =K73-K52 -> 0 | L75: =L73-L52 -> 0 | M75: =M73-M52 -> 0 | N75: =N73-N52 -> 0 | O75: =O73-O52 -> 0 | P75: =P73-P52 -> 0 | Q75: =Q73-Q52 -> 0 | R75: =R73-R52 -> 0 | ... AC75: =AC73-AC52 -> 0 | AE75: =AE73-AE52 -> 0 | AF75: =AF73-AF52 -> 0 | AG75: =AG73-AG52 -> 0 | AH75: =AH73-AH52 -> 0 | AI75: =AI73-AI52 -> 0 | AJ75: =AJ73-AJ52 -> 0 | AK75: =AK73-AK52 -> 0 | AL75: =AL73-AL52 -> 0 | ... AS75: =AS73-AS52 -> 0
A78: X | B78: Cash-Flows Statement | AN78: LTM | AU78: Variance
B79: =B7 -> Fiscal Period | C79: =C7 -> 2018 | D79: =D7 -> 2019 | E79: =E7 -> 2020 | F79: =F7 -> 2021 | G79: =G7 -> 2022 | H79: =H7 -> 2023 | I79: =I7 -> 2024 | K79: =K7 -> 1Q21 | L79: =L7 -> 2Q21 | M79: =M7 -> 3Q21 | N79: =N7 -> 4Q21 | O79: =O7 -> 1Q22 | P79: =P7 -> 2Q22 | Q79: =Q7 -> 3Q22 | R79: =R7 -> 4Q22 | ... AC79: =AC7 -> 3Q25 | AE79: =AE7 -> 1Q22 | AF79: =AF7 -> 2Q22 | AG79: =AG7 -> 3Q22 | AH79: =AH7 -> 4Q22 | AI79: =AI7 -> 1Q23 | AJ79: =AJ7 -> 2Q23 | AK79: =AK7 -> 3Q23 | AL79: =AL7 -> 4Q23 | ... AS79: =AS7 -> 3Q25
B80: =B8 -> Fiscal Period End Date | C80: =C8 -> 43465 | D80: =D8 -> 43830 | E80: =E8 -> 44196 | F80: =F8 -> 44561 | G80: =G8 -> 44926 | H80: =H8 -> 45291 | I80: =I8 -> 45657 | K80: =K8 -> 44286 | L80: =L8 -> 44377 | M80: =M8 -> 44469 | N80: =N8 -> 44561 | O80: =O8 -> 44651 | P80: =P8 -> 44742 | Q80: =Q8 -> 44834 | R80: =R8 -> 44926 | ... AC80: =AC8 -> 45930 | AE80: =AE8 -> 44651 | AF80: =AF8 -> 44742 | AG80: =AG8 -> 44834 | AH80: =AH8 -> 44926 | AI80: =AI8 -> 45016 | AJ80: =AJ8 -> 45107 | AK80: =AK8 -> 45199 | AL80: =AL8 -> 45291 | ... AS80: =AS8 -> 45930
B82: Cash-Flows From Operating Activities
B83: Net income (loss) | C83: =C32 -> 1211242 | D83: =D32 -> 1866916 | E83: =E32 -> 2761395 | F83: =F32 -> 5116228 | G83: =G32 -> 4491924 | H83: =H32 -> 5407990 | I83: =I32 -> 8711631 | K83: =K32 -> 1706715 | L83: =L32 -> 1353013 | M83: =M32 -> 1449071 | N83: =N32 -> 607429 | O83: =O32 -> 1597447 | P83: =P32 -> 1440951 | Q83: =Q32 -> 1398242 | R83: =R32 -> 55284 | ... AC83: =AC32 -> 2546916 | AE83: =SUM(L83:O83) -> 5006960 | AF83: =SUM(M83:P83) -> 5094898 | AG83: =SUM(N83:Q83) -> 5044069 | AH83: =SUM(O83:R83) -> 4491924 | AI83: =SUM(P83:S83) -> 4199597 | AJ83: =SUM(Q83:T83) -> 4246256 | AK83: =SUM(R83:U83) -> 4525436 | AL83: =SUM(S83:V83) -> 5407990 | ... AS83: =SUM(Z83:AC83) -> 10431287 | AU83: =SUM(AS83/AO83)-1 -> 0.34063385
B85: Adjustments to reconcile net income:
B86: Additions to content assets | C86: -13043437 | D86: -13916683 | E86: -11779284 | F86: -17702202 | G86: -16839038 | H86: -12554703 | I86: -16223617 | K86: -3284576 | L86: -4096750 | M86: -4666237 | N86: =SUM(F86-SUM(K86:M86)) -> -5654639 | O86: -3584164 | P86: -4687011 | Q86: -4582671 | R86: =SUM(G86-SUM(O86:Q86)) -> -3985192 | S86: -2458666 | T86: -3683007 | U86: -2883839 | V86: =SUM(H86-SUM(S86:U86)) -> -3529191 | W86: -3728967 | X86: -4048852 | Y86: -4016396 | Z86: =SUM(I86-SUM(W86:Y86)) -> -4429402 | AA86: -3549657 | AB86: -3835813 | AC86: -4653935 | AE86: =SUM(L86:O86) -> -18001790 | AF86: =SUM(M86:P86) -> -18592051 | AG86: =SUM(N86:Q86) -> -18508485 | AH86: =SUM(O86:R86) -> -16839038 | AI86: =SUM(P86:S86) -> -15713540 | AJ86: =SUM(Q86:T86) -> -14709536 | AK86: =SUM(R86:U86) -> -13010704 | AL86: =SUM(S86:V86) -> -12554703 | ... AS86: =SUM(Z86:AC86) -> -16468807 | AU86: =SUM(AS86/AO86)-1 -> 0.07474846
B87: Change in content liabilities | C87: 999880 | D87: -694011 | E87: -757433 | F87: 232898 | G87: 179310 | H87: -585602 | I87: -779135 | K87: -266040 | L87: -312208 | M87: -29246 | N87: =SUM(F87-SUM(K87:M87)) -> 840392 | O87: -347149 | P87: 191228 | Q87: 60867 | R87: =SUM(G87-SUM(O87:Q87)) -> 274364 | S87: -354791 | T87: 46119 | U87: -325989 | V87: =SUM(H87-SUM(S87:U87)) -> 49059 | W87: -189441 | X87: -366572 | Y87: -83585 | Z87: =SUM(I87-SUM(W87:Y87)) -> -139537 | AA87: -411253 | AB87: -214052 | AC87: 24262 | AE87: =SUM(L87:O87) -> 151789 | AF87: =SUM(M87:P87) -> 655225 | AG87: =SUM(N87:Q87) -> 745338 | AH87: =SUM(O87:R87) -> 179310 | AI87: =SUM(P87:S87) -> 171668 | AJ87: =SUM(Q87:T87) -> 26559 | AK87: =SUM(R87:U87) -> -360297 | AL87: =SUM(S87:V87) -> -585602 | ... AS87: =SUM(Z87:AC87) -> -740580 | AU87: =SUM(AS87/AO87)-1 -> 0.25407467
B88: Amortization of content assets | C88: 7532088 | D88: 9216247 | E88: 10806912 | F88: 12230367 | G88: 14026132 | H88: 14197437 | I88: 15301517 | K88: 2719196 | L88: 2806803 | M88: 2963051 | N88: =SUM(F88-SUM(K88:M88)) -> 3741317 | O88: 3166365 | P88: 3261348 | Q88: 3653592 | R88: =SUM(G88-SUM(O88:Q88)) -> 3944827 | S88: 3459984 | T88: 3410021 | U88: 3573353 | V88: =SUM(H88-SUM(S88:U88)) -> 3754079 | W88: 3670805 | X88: 3769690 | Y88: 3699521 | Z88: =SUM(I88-SUM(W88:Y88)) -> 4161501 | AA88: 3823112 | AB88: 3832074 | AC88: 4002744 | AE88: =SUM(L88:O88) -> 12677536 | AF88: =SUM(M88:P88) -> 13132081 | AG88: =SUM(N88:Q88) -> 13822622 | AH88: =SUM(O88:R88) -> 14026132 | AI88: =SUM(P88:S88) -> 14319751 | AJ88: =SUM(Q88:T88) -> 14468424 | AK88: =SUM(R88:U88) -> 14388185 | AL88: =SUM(S88:V88) -> 14197437 | ... AS88: =SUM(Z88:AC88) -> 15819431 | AU88: =SUM(AS88/AO88)-1 -> 0.062127709
B89: Depreciation and amortization of property, equipment and intangibles | C89: 83157 | D89: 103579 | E89: 115710 | F89: 208412 | G89: 336682 | H89: 356947 | I89: 328914 | K89: 35741 | L89: 38434 | M89: 70253 | N89: =SUM(F89-SUM(K89:M89)) -> 63984 | O89: 74602 | P89: 83505 | Q89: 85188 | R89: =SUM(G89-SUM(O89:Q89)) -> 93387 | S89: 90335 | T89: 89385 | U89: 90660 | V89: =SUM(H89-SUM(S89:U89)) -> 86567 | W89: 87234 | X89: 81227 | Y89: 80914 | Z89: =SUM(I89-SUM(W89:Y89)) -> 79539 | AA89: 80067 | AB89: 80013 | AC89: 87326 | AE89: =SUM(L89:O89) -> 247273 | AF89: =SUM(M89:P89) -> 292344 | AG89: =SUM(N89:Q89) -> 307279 | AH89: =SUM(O89:R89) -> 336682 | AI89: =SUM(P89:S89) -> 352415 | AJ89: =SUM(Q89:T89) -> 358295 | AK89: =SUM(R89:U89) -> 363767 | AL89: =SUM(S89:V89) -> 356947 | ... AS89: =SUM(Z89:AC89) -> 326945 | AU89: =SUM(AS89/AO89)-1 -> -0.026781409
B90: Stock-based compensation expense | C90: 320657 | D90: 405376 | E90: 415180 | F90: 403220 | G90: 575452 | H90: 339368 | I90: 272588 | K90: 107230 | L90: 101583 | M90: 95078 | N90: =SUM(F90-SUM(K90:M90)) -> 99329 | O90: 119209 | P90: 150392 | Q90: 152062 | R90: =SUM(G90-SUM(O90:Q90)) -> 153789 | S90: 99099 | T90: 78030 | U90: 79720 | V90: =SUM(H90-SUM(S90:U90)) -> 82519 | W90: 76345 | X90: 68766 | Y90: 65650 | Z90: =SUM(I90-SUM(W90:Y90)) -> 61827 | AA90: 71977 | AB90: 80862 | AC90: 80986 | AE90: =SUM(L90:O90) -> 415199 | AF90: =SUM(M90:P90) -> 464008 | AG90: =SUM(N90:Q90) -> 520992 | AH90: =SUM(O90:R90) -> 575452 | AI90: =SUM(P90:S90) -> 555342 | AJ90: =SUM(Q90:T90) -> 482980 | AK90: =SUM(R90:U90) -> 410638 | AL90: =SUM(S90:V90) -> 339368 | ... AS90: =SUM(Z90:AC90) -> 295652 | AU90: =SUM(AS90/AO90)-1 -> 0.0080878342
B91: Foreign currency remeasurement loss (gain) on debt | C91: -73953 | D91: -45576 | E91: 533278 | F91: -430661 | G91: -353111 | H91: 176296 | I91: -121539 | K91: -253330 | L91: 63074 | M91: -136488 | N91: =SUM(F91-SUM(K91:M91)) -> -103917 | O91: -161821 | P91: -304513 | Q91: -348458 | R91: =SUM(G91-SUM(O91:Q91)) -> 461681 | S91: 80651 | T91: 28952 | U91: -172678 | V91: =SUM(H91-SUM(S91:U91)) -> 239371 | W91: -130801 | X91: -42692 | Y91: 104809 | Z91: =SUM(I91-SUM(W91:Y91)) -> -52855 | AA91: 28547 | AB91: 55238 | AC91: -1707 | AE91: =SUM(L91:O91) -> -339152 | AF91: =SUM(M91:P91) -> -706739 | AG91: =SUM(N91:Q91) -> -918709 | AH91: =SUM(O91:R91) -> -353111 | AI91: =SUM(P91:S91) -> -110639 | AJ91: =SUM(Q91:T91) -> 222826 | AK91: =SUM(R91:U91) -> 398606 | AL91: =SUM(S91:V91) -> 176296 | ... AS91: =SUM(Z91:AC91) -> 29223 | AU91: =SUM(AS91/AO91)-1 -> -0.82879188
B92: Other non-cash items | C92: 81640 | D92: 228230 | E92: 293126 | F92: 376777 | G92: 533543 | H92: 512075 | I92: 494778 | K92: 72657 | L92: 108103 | M92: 102211 | N92: =SUM(F92-SUM(K92:M92)) -> 93806 | O92: 101968 | P92: 205374 | Q92: 102513 | R92: =SUM(G92-SUM(O92:Q92)) -> 123688 | S92: 120008 | T92: 121483 | U92: 115688 | V92: =SUM(H92-SUM(S92:U92)) -> 154896 | W92: 97181 | X92: 138588 | Y92: 128082 | Z92: =SUM(I92-SUM(W92:Y92)) -> 130927 | AA92: 114730 | AB92: 120139 | AC92: 142293 | AE92: =SUM(L92:O92) -> 406088 | AF92: =SUM(M92:P92) -> 503359 | AG92: =SUM(N92:Q92) -> 503661 | AH92: =SUM(O92:R92) -> 533543 | AI92: =SUM(P92:S92) -> 551583 | AJ92: =SUM(Q92:T92) -> 467692 | AK92: =SUM(R92:U92) -> 480867 | AL92: =SUM(S92:V92) -> 512075 | ... AS92: =SUM(Z92:AC92) -> 508089 | AU92: =SUM(AS92/AO92)-1 -> -0.020545661
B93: Deferred income taxes | C93: -85520 | D93: -94443 | E93: 70066 | F93: 199548 | G93: -166550 | H93: -459359 | I93: -590698 | K93: 159733 | L93: 51127 | M93: 50967 | N93: =SUM(F93-SUM(K93:M93)) -> -62279 | O93: -68906 | P93: -115820 | Q93: -57797 | R93: =SUM(G93-SUM(O93:Q93)) -> 75973 | S93: -98782 | T93: -103172 | U93: -86277 | V93: =SUM(H93-SUM(S93:U93)) -> -171128 | W93: -107077 | X93: -209387 | Y93: -200982 | Z93: =SUM(I93-SUM(W93:Y93)) -> -73252 | AA93: -163928 | AB93: -135755 | AC93: 20539 | AE93: =SUM(L93:O93) -> -29091 | AF93: =SUM(M93:P93) -> -196038 | AG93: =SUM(N93:Q93) -> -304802 | AH93: =SUM(O93:R93) -> -166550 | AI93: =SUM(P93:S93) -> -196426 | AJ93: =SUM(Q93:T93) -> -183778 | AK93: =SUM(R93:U93) -> -212258 | AL93: =SUM(S93:V93) -> -459359 | ... AS93: =SUM(Z93:AC93) -> -352396 | AU93: =SUM(AS93/AO93)-1 -> -0.48822349
B94: Changes in assets and liabilities:
B95: Other current assets | C95: -200192 | D95: -252113 | E95: -187623 | F95: -369681 | G95: -353834 | H95: -181003 | I95: 22180 | K95: -221555 | L95: -52373 | M95: -95145 | N95: =SUM(F95-SUM(K95:M95)) -> -608 | O95: 41157 | P95: 123399 | Q95: -120071 | R95: =SUM(G95-SUM(O95:Q95)) -> -398319 | S95: -88522 | T95: -183049 | U95: 103766 | V95: =SUM(H95-SUM(S95:U95)) -> -13198 | W95: 38049 | X95: -28959 | Y95: 54956 | Z95: =SUM(I95-SUM(W95:Y95)) -> -41866 | AA95: -131367 | AB95: -176683 | AC95: -169597 | AE95: =SUM(L95:O95) -> -106969 | AF95: =SUM(M95:P95) -> 68803 | AG95: =SUM(N95:Q95) -> 43877 | AH95: =SUM(O95:R95) -> -353834 | AI95: =SUM(P95:S95) -> -483513 | AJ95: =SUM(Q95:T95) -> -789961 | AK95: =SUM(R95:U95) -> -566124 | AL95: =SUM(S95:V95) -> -181003 | ... AS95: =SUM(Z95:AC95) -> -519513 | AU95: =SUM(AS95/AO95)-1 -> -11.21698
B96: Accounts payable | C96: 199198 | D96: 96063 | E96: -41605 | F96: 145115 | G96: -158543 | H96: 93502 | I96: 121353 | K96: -137313 | L96: 72313 | M96: 24836 | N96: =SUM(F96-SUM(K96:M96)) -> 185279 | O96: -215444 | P96: -122048 | Q96: 53875 | R96: =SUM(G96-SUM(O96:Q96)) -> 125074 | S96: -89668 | T96: 38332 | U96: -68390 | V96: =SUM(H96-SUM(S96:U96)) -> 213228 | W96: -145265 | X96: -19358 | Y96: 30597 | Z96: =SUM(I96-SUM(W96:Y96)) -> 255379 | AA96: -276426 | AB96: 11046 | AC96: 139451 | AE96: =SUM(L96:O96) -> 66984 | AF96: =SUM(M96:P96) -> -127377 | AG96: =SUM(N96:Q96) -> -98338 | AH96: =SUM(O96:R96) -> -158543 | AI96: =SUM(P96:S96) -> -32767 | AJ96: =SUM(Q96:T96) -> 127613 | AK96: =SUM(R96:U96) -> 5348 | AL96: =SUM(S96:V96) -> 93502 | ... AS96: =SUM(Z96:AC96) -> 129450 | AU96: =SUM(AS96/AO96)-1 -> 0.63442842
B97: Accrued expenses and other liabilities | C97: 150422 | D97: 157778 | E97: 198183 | F97: 180338 | G97: -55513 | H97: 103565 | I97: 191899 | K97: 177897 | L97: -171430 | M97: 269774 | N97: =SUM(F97-SUM(K97:M97)) -> -95903 | O97: 350763 | P97: -238719 | Q97: 212072 | R97: =SUM(G97-SUM(O97:Q97)) -> -379629 | S97: 185299 | T97: 177831 | U97: -65029 | V97: =SUM(H97-SUM(S97:U97)) -> -194536 | W97: 251782 | X97: -114303 | Y97: 179011 | Z97: =SUM(I97-SUM(W97:Y97)) -> -124591 | AA97: 306413 | AB97: -267235 | AC97: 707151 | AE97: =SUM(L97:O97) -> 353204 | AF97: =SUM(M97:P97) -> 285915 | AG97: =SUM(N97:Q97) -> 228213 | AH97: =SUM(O97:R97) -> -55513 | AI97: =SUM(P97:S97) -> -220977 | AJ97: =SUM(Q97:T97) -> 195573 | AK97: =SUM(R97:U97) -> -81528 | AL97: =SUM(S97:V97) -> 103565 | ... AS97: =SUM(Z97:AC97) -> 621738 | AU97: =SUM(AS97/AO97)-1 -> 4.0981354
B98: Deferred revenue | C98: 142277 | D98: 163846 | E98: 193247 | F98: 91350 | G98: 27356 | H98: 178708 | I98: 77844 | K98: 22279 | L98: 47093 | M98: -4732 | N98: =SUM(F98-SUM(K98:M98)) -> 26710 | O98: 16743 | P98: -10376 | Q98: -48420 | R98: =SUM(G98-SUM(O98:Q98)) -> 69409 | S98: -2390 | T98: 49647 | U98: -5733 | V98: =SUM(H98-SUM(S98:U98)) -> 137184 | W98: 26515 | X98: 4236 | Y98: 39328 | Z98: =SUM(I98-SUM(W98:Y98)) -> 7765 | AA98: 88913 | AB98: 118635 | AC98: -3686 | AE98: =SUM(L98:O98) -> 85814 | AF98: =SUM(M98:P98) -> 28345 | AG98: =SUM(N98:Q98) -> -15343 | AH98: =SUM(O98:R98) -> 27356 | AI98: =SUM(P98:S98) -> 8223 | AJ98: =SUM(Q98:T98) -> 68246 | AK98: =SUM(R98:U98) -> 110933 | AL98: =SUM(S98:V98) -> 178708 | ... AS98: =SUM(Z98:AC98) -> 211627 | AU98: =SUM(AS98/AO98)-1 -> 0.021055374
B99: Other non-current assets and liabilities | C99: 2062 | D99: -122531 | E99: -194075 | F99: -289099 | G99: -217553 | H99: -310920 | I99: -446351 | K99: -61368 | L99: -72543 | M99: -11014 | N99: =SUM(F99-SUM(K99:M99)) -> -144174 | O99: -167931 | P99: 125040 | Q99: -4184 | R99: =SUM(G99-SUM(O99:Q99)) -> -170478 | S99: -68937 | T99: -117950 | U99: -40359 | V99: =SUM(H99-SUM(S99:U99)) -> -83674 | W99: -66047 | X99: -88843 | Y99: -124313 | Z99: =SUM(I99-SUM(W99:Y99)) -> -167148 | AA99: -82280 | AB99: -370624 | AC99: -97569 | AE99: =SUM(L99:O99) -> -395662 | AF99: =SUM(M99:P99) -> -198079 | AG99: =SUM(N99:Q99) -> -191249 | AH99: =SUM(O99:R99) -> -217553 | AI99: =SUM(P99:S99) -> -118559 | AJ99: =SUM(Q99:T99) -> -361549 | AK99: =SUM(R99:U99) -> -397724 | AL99: =SUM(S99:V99) -> -310920 | ... AS99: =SUM(Z99:AC99) -> -717621 | AU99: =SUM(AS99/AO99)-1 -> 0.97758745
B100: Net cash used in operating activities | C100: =SUM(C83:C99) -> -2680479 | D100: =SUM(D83:D99) -> -2887322 | E100: =SUM(E83:E99) -> 2427077 | F100: =SUM(F83:F99) -> 392610 | G100: =SUM(G83:G99) -> 2026257 | H100: =SUM(H83:H99) -> 7274301 | I100: =SUM(I83:I99) -> 7361364 | K100: =SUM(K83:K99) -> 777266 | L100: =SUM(L83:L99) -> -63761 | M100: =SUM(M83:M99) -> 82379 | N100: =SUM(N83:N99) -> -403274 | O100: =SUM(O83:O99) -> 922839 | P100: =SUM(P83:P99) -> 102750 | Q100: =SUM(Q83:Q99) -> 556810 | R100: =SUM(R83:R99) -> 443858 | ... AC100: =SUM(AC83:AC99) -> 2825174 | AE100: =SUM(AE83:AE99) -> 538183 | AF100: =SUM(AF83:AF99) -> 704694 | AG100: =SUM(AG83:AG99) -> 1179125 | AH100: =SUM(AH83:AH99) -> 2026257 | AI100: =SUM(AI83:AI99) -> 3282158 | AJ100: =SUM(AJ83:AJ99) -> 4619640 | AK100: =SUM(AK83:AK99) -> 6055145 | AL100: =SUM(AL83:AL99) -> 7274301 | ... AS100: =SUM(AS83:AS99) -> 9574525 | AU100: =SUM(AS100/AO100)-1 -> 0.27873729
B102: Cash flows from investing activities:
B103: Purchases of property and equipment | C103: -173946 | D103: -253035 | E103: -497923 | F103: -524585 | G103: -407729 | H103: -348552 | I103: -439538 | K103: -81001 | L103: -110278 | M103: -167327 | N103: =SUM(F103-SUM(K103:M103)) -> -165979 | O103: -121158 | P103: -90018 | Q103: -84960 | R103: =SUM(G103-SUM(O103:Q103)) -> -111593 | S103: -62019 | T103: -100972 | U103: -103929 | V103: =SUM(H103-SUM(S103:U103)) -> -81632 | W103: -75714 | X103: -78287 | Y103: -126863 | Z103: =SUM(I103-SUM(W103:Y103)) -> -158674 | AA103: -128277 | AB103: -155889 | AC103: -164719 | AE103: =SUM(L103:O103) -> -564742 | AF103: =SUM(M103:P103) -> -544482 | AG103: =SUM(N103:Q103) -> -462115 | AH103: =SUM(O103:R103) -> -407729 | AI103: =SUM(P103:S103) -> -348590 | AJ103: =SUM(Q103:T103) -> -359544 | AK103: =SUM(R103:U103) -> -378513 | AL103: =SUM(S103:V103) -> -348552 | ... AS103: =SUM(Z103:AC103) -> -607559 | AU103: =SUM(AS103/AO103)-1 -> 0.67604332
B104: Change in other assets | C104: -165174 | D104: -134029 | E104: -7431 | F104: -26919 | G104: 0 | H104: 0 | I104: 0 | K104: -4615 | L104: -1000 | M104: -21304 | N104: =SUM(F104-SUM(K104:M104)) -> 0 | O104: 0 | P104: 0 | Q104: 0 | R104: =SUM(G104-SUM(O104:Q104)) -> 0 | S104: 0 | T104: 0 | U104: 0 | V104: =SUM(H104-SUM(S104:U104)) -> 0 | W104: 0 | X104: 0 | Y104: 0 | Z104: =SUM(I104-SUM(W104:Y104)) -> 0 | AA104: 0 | AB104: 0 | AC104: 0 | AE104: =SUM(L104:O104) -> -22304 | AF104: =SUM(M104:P104) -> -21304 | AG104: =SUM(N104:Q104) -> 0 | AH104: =SUM(O104:R104) -> 0 | AI104: =SUM(P104:S104) -> 0 | AJ104: =SUM(Q104:T104) -> 0 | AK104: =SUM(R104:U104) -> 0 | AL104: =SUM(S104:V104) -> 0 | ... AS104: =SUM(Z104:AC104) -> 0 | AU104: =SUM(AS104/AO104)-1 -> #DIV/0!
B105: Acquisitions | C105: 0 | D105: 0 | E105: 0 | F105: -788349 | G105: -757387 | H105: 0 | I105: 0 | K105: 0 | L105: 0 | M105: 0 | N105: =SUM(F105-SUM(K105:M105)) -> -788349 | O105: -124521 | P105: -68876 | Q105: 0 | R105: =SUM(G105-SUM(O105:Q105)) -> -563990 | S105: 0 | T105: 0 | U105: 0 | V105: =SUM(H105-SUM(S105:U105)) -> 0 | W105: 0 | X105: 0 | Y105: 0 | Z105: =SUM(I105-SUM(W105:Y105)) -> 0 | AA105: 0 | AB105: -36190 | AC105: 36190 | AE105: =SUM(L105:O105) -> -912870 | AF105: =SUM(M105:P105) -> -981746 | AG105: =SUM(N105:Q105) -> -981746 | AH105: =SUM(O105:R105) -> -757387 | AI105: =SUM(P105:S105) -> -632866 | AJ105: =SUM(Q105:T105) -> -563990 | AK105: =SUM(R105:U105) -> -563990 | AL105: =SUM(S105:V105) -> 0 | ... AS105: =SUM(Z105:AC105) -> 0 | AU105: =SUM(AS105/AO105)-1 -> #DIV/0!
B106: Purchases of short-term investments | C106: 0 | D106: 0 | E106: 0 | F106: 0 | G106: -911276 | H106: -504862 | I106: -1742246 | K106: 0 | L106: 0 | M106: 0 | N106: =SUM(F106-SUM(K106:M106)) -> 0 | O106: 0 | P106: 0 | Q106: 0 | R106: =SUM(G106-SUM(O106:Q106)) -> -911276 | S106: -201634 | T106: -303228 | U106: 0 | V106: =SUM(H106-SUM(S106:U106)) -> 0 | W106: 0 | X106: 0 | Y106: -1742246 | Z106: =SUM(I106-SUM(W106:Y106)) -> 0 | AA106: -156015 | AB106: -1650 | AC106: -3850 | AE106: =SUM(L106:O106) -> 0 | AF106: =SUM(M106:P106) -> 0 | AG106: =SUM(N106:Q106) -> 0 | AH106: =SUM(O106:R106) -> -911276 | AI106: =SUM(P106:S106) -> -1112910 | AJ106: =SUM(Q106:T106) -> -1416138 | AK106: =SUM(R106:U106) -> -1416138 | AL106: =SUM(S106:V106) -> -504862 | ... AS106: =SUM(Z106:AC106) -> -161515 | AU106: =SUM(AS106/AO106)-1 -> -0.90729495
B107: Proceeds from maturities of short-term investments | C107: 0 | D107: 0 | E107: 0 | F107: 0 | G107: 0 | H107: 1395165 | I107: 0 | K107: 0 | L107: 0 | M107: 0 | N107: =SUM(F107-SUM(K107:M107)) -> 0 | O107: 0 | P107: 0 | Q107: 0 | R107: =SUM(G107-SUM(O107:Q107)) -> 0 | S107: 0 | T107: 501937 | U107: 400000 | V107: =SUM(H107-SUM(S107:U107)) -> 493228 | W107: 0 | X107: 0 | Y107: 0 | Z107: =SUM(I107-SUM(W107:Y107)) -> 0 | AA107: 769954 | AB107: 962413 | AC107: 176250 | AE107: =SUM(L107:O107) -> 0 | AF107: =SUM(M107:P107) -> 0 | AG107: =SUM(N107:Q107) -> 0 | AH107: =SUM(O107:R107) -> 0 | AI107: =SUM(P107:S107) -> 0 | AJ107: =SUM(Q107:T107) -> 501937 | AK107: =SUM(R107:U107) -> 901937 | AL107: =SUM(S107:V107) -> 1395165 | ... AS107: =SUM(Z107:AC107) -> 1908617 | AU107: =SUM(AS107/AO107)-1 -> 2.8696445
B108: Net cash used in investing activities | C108: =SUM(C103:C107) -> -339120 | D108: =SUM(D103:D107) -> -387064 | E108: =SUM(E103:E107) -> -505354 | F108: =SUM(F103:F107) -> -1339853 | G108: =SUM(G103:G107) -> -2076392 | H108: =SUM(H103:H107) -> 541751 | I108: =SUM(I103:I107) -> -2181784 | K108: =SUM(K103:K107) -> -85616 | L108: =SUM(L103:L107) -> -111278 | M108: =SUM(M103:M107) -> -188631 | N108: =SUM(N103:N107) -> -954328 | O108: =SUM(O103:O107) -> -245679 | P108: =SUM(P103:P107) -> -158894 | Q108: =SUM(Q103:Q107) -> -84960 | R108: =SUM(R103:R107) -> -1586859 | ... AC108: =SUM(AC103:AC107) -> 43871 | AE108: =SUM(AE103:AE107) -> -1499916 | AF108: =SUM(AF103:AF107) -> -1547532 | AG108: =SUM(AG103:AG107) -> -1443861 | AH108: =SUM(AH103:AH107) -> -2076392 | AI108: =SUM(AI103:AI107) -> -2094366 | AJ108: =SUM(AJ103:AJ107) -> -1837735 | AK108: =SUM(AK103:AK107) -> -1456704 | AL108: =SUM(AL103:AL107) -> 541751 | ... AS108: =SUM(AS103:AS107) -> 1139543 | AU108: =SUM(AS108/AO108)-1 -> -1.7071257
B110: Cash flows from financing activities: | AU110: =SUM(AS110/AO110)-1 -> #DIV/0!
B111: Proceeds from issuance of debt | C111: 3961852 | D111: 4469306 | E111: 1009464 | F111: 0 | G111: 0 | H111: 0 | I111: 1794460 | K111: 0 | L111: 0 | M111: 0 | N111: =SUM(F111-SUM(K111:M111)) -> 0 | O111: 0 | P111: 0 | Q111: 0 | R111: =SUM(G111-SUM(O111:Q111)) -> 0 | S111: 0 | T111: 0 | U111: 0 | V111: =SUM(H111-SUM(S111:U111)) -> 0 | W111: 0 | X111: 0 | Y111: 1794460 | Z111: =SUM(I111-SUM(W111:Y111)) -> 0 | AA111: 0 | AB111: 0 | AC111: 0 | AE111: =SUM(L111:O111) -> 0 | AF111: =SUM(M111:P111) -> 0 | AG111: =SUM(N111:Q111) -> 0 | AH111: =SUM(O111:R111) -> 0 | AI111: =SUM(P111:S111) -> 0 | AJ111: =SUM(Q111:T111) -> 0 | AK111: =SUM(R111:U111) -> 0 | AL111: =SUM(S111:V111) -> 0 | ... AS111: =SUM(Z111:AC111) -> 0 | AU111: =SUM(AS111/AO111)-1 -> -1
B112: Debt issuance costs | C112: -35871 | D112: -36134 | E112: -7559 | F112: 0 | G112: 0 | H112: 0 | I112: 0 | K112: 0 | L112: 0 | M112: 0 | N112: =SUM(F112-SUM(K112:M112)) -> 0 | O112: 0 | P112: 0 | Q112: 0 | R112: =SUM(G112-SUM(O112:Q112)) -> 0 | S112: 0 | T112: 0 | U112: 0 | V112: =SUM(H112-SUM(S112:U112)) -> 0 | W112: 0 | X112: 0 | Y112: 0 | Z112: =SUM(I112-SUM(W112:Y112)) -> 0 | AA112: 0 | AB112: 0 | AC112: 0 | AE112: =SUM(L112:O112) -> 0 | AF112: =SUM(M112:P112) -> 0 | AG112: =SUM(N112:Q112) -> 0 | AH112: =SUM(O112:R112) -> 0 | AI112: =SUM(P112:S112) -> 0 | AJ112: =SUM(Q112:T112) -> 0 | AK112: =SUM(R112:U112) -> 0 | AL112: =SUM(S112:V112) -> 0 | ... AS112: =SUM(Z112:AC112) -> 0
B113: Repayments of debt | C113: 0 | D113: 0 | E113: 0 | F113: -500000 | G113: -700000 | H113: 0 | I113: -400000 | K113: -500000 | L113: 0 | M113: 0 | N113: =SUM(F113-SUM(K113:M113)) -> 0 | O113: -700000 | P113: 0 | Q113: 0 | R113: =SUM(G113-SUM(O113:Q113)) -> 0 | S113: 0 | T113: 0 | U113: 0 | V113: =SUM(H113-SUM(S113:U113)) -> 0 | W113: -400000 | X113: 0 | Y113: 0 | Z113: =SUM(I113-SUM(W113:Y113)) -> 0 | AA113: -800000 | AB113: -1033450 | AC113: 0 | AE113: =SUM(L113:O113) -> -700000 | AF113: =SUM(M113:P113) -> -700000 | AG113: =SUM(N113:Q113) -> -700000 | AH113: =SUM(O113:R113) -> -700000 | AI113: =SUM(P113:S113) -> 0 | AJ113: =SUM(Q113:T113) -> 0 | AK113: =SUM(R113:U113) -> 0 | AL113: =SUM(S113:V113) -> 0 | ... AS113: =SUM(Z113:AC113) -> -1833450
B114: Proceeds from issuance of common stock | C114: 124502 | D114: 72490 | E114: 235406 | F114: 174414 | G114: 35746 | H114: 169990 | I114: 832887 | K114: 48071 | L114: 19749 | M114: 18445 | N114: =SUM(F114-SUM(K114:M114)) -> 88149 | O114: 13678 | P114: 11250 | Q114: 4113 | R114: =SUM(G114-SUM(O114:Q114)) -> 6705 | S114: 26028 | T114: 34717 | U114: 57818 | V114: =SUM(H114-SUM(S114:U114)) -> 51427 | W114: 268881 | X114: 118750 | Y114: 143244 | Z114: =SUM(I114-SUM(W114:Y114)) -> 302012 | AA114: 351602 | AB114: 169066 | AC114: 70215 | AE114: =SUM(L114:O114) -> 140021 | AF114: =SUM(M114:P114) -> 131522 | AG114: =SUM(N114:Q114) -> 117190 | AH114: =SUM(O114:R114) -> 35746 | AI114: =SUM(P114:S114) -> 48096 | AJ114: =SUM(Q114:T114) -> 71563 | AK114: =SUM(R114:U114) -> 125268 | AL114: =SUM(S114:V114) -> 169990 | ... AS114: =SUM(Z114:AC114) -> 892895
B115: Repurchases of common stock | C115: 0 | D115: 0 | E115: 0 | F115: -600022 | G115: 0 | H115: -6045347 | I115: -6263746 | K115: 0 | L115: -500022 | M115: -100000 | N115: =SUM(F115-SUM(K115:M115)) -> 0 | O115: 0 | P115: 0 | Q115: 0 | R115: =SUM(G115-SUM(O115:Q115)) -> 0 | S115: -400101 | T115: -645146 | U115: -2500100 | V115: =SUM(H115-SUM(S115:U115)) -> -2500000 | W115: -2000000 | X115: -1599998 | Y115: -1700000 | Z115: =SUM(I115-SUM(W115:Y115)) -> -963748 | AA115: -3536396 | AB115: -1654327 | AC115: -1856885 | AE115: =SUM(L115:O115) -> -600022 | AF115: =SUM(M115:P115) -> -100000 | AG115: =SUM(N115:Q115) -> 0 | AH115: =SUM(O115:R115) -> 0 | AI115: =SUM(P115:S115) -> -400101 | AJ115: =SUM(Q115:T115) -> -1045247 | AK115: =SUM(R115:U115) -> -3545347 | AL115: =SUM(S115:V115) -> -6045347 | ... AS115: =SUM(Z115:AC115) -> -8011356
B116: Taxes paid related to net share settlement of equity awards | C116: 0 | D116: 0 | E116: 0 | F116: -224168 | G116: 0 | H116: 0 | I116: -8285 | K116: 0 | L116: 0 | M116: 0 | N116: =SUM(F116-SUM(K116:M116)) -> -224168 | O116: 0 | P116: 0 | Q116: 0 | R116: =SUM(G116-SUM(O116:Q116)) -> 0 | S116: 0 | T116: 0 | U116: 0 | V116: =SUM(H116-SUM(S116:U116)) -> 0 | W116: -1825 | X116: -1883 | Y116: -2024 | Z116: =SUM(I116-SUM(W116:Y116)) -> -2553 | AA116: -27870 | AB116: -6114 | AC116: -6196 | AE116: =SUM(L116:O116) -> -224168 | AF116: =SUM(M116:P116) -> -224168 | AG116: =SUM(N116:Q116) -> -224168 | AH116: =SUM(O116:R116) -> 0 | AI116: =SUM(P116:S116) -> 0 | AJ116: =SUM(Q116:T116) -> 0 | AK116: =SUM(R116:U116) -> 0 | AL116: =SUM(S116:V116) -> 0 | ... AS116: =SUM(Z116:AC116) -> -42733 | AU116: =SUM(AS116/AO116)-1 -> 6.455164
B117: Other financing activities | C117: -1956 | D117: 0 | E117: 0 | F117: 0 | G117: 0 | H117: -75446 | I117: -29743 | K117: 0 | L117: 0 | M117: 0 | N117: =SUM(F117-SUM(K117:M117)) -> 0 | O117: 0 | P117: 0 | Q117: 0 | R117: =SUM(G117-SUM(O117:Q117)) -> 0 | S117: 0 | T117: -38920 | U117: -32826 | V117: =SUM(H117-SUM(S117:U117)) -> -3700 | W117: 0 | X117: -6250 | Y117: -9084 | Z117: =SUM(I117-SUM(W117:Y117)) -> -14409 | AA117: -15652 | AB117: 21957 | AC117: 55837 | AE117: =SUM(L117:O117) -> 0 | AF117: =SUM(M117:P117) -> 0 | AG117: =SUM(N117:Q117) -> 0 | AH117: =SUM(O117:R117) -> 0 | AI117: =SUM(P117:S117) -> 0 | AJ117: =SUM(Q117:T117) -> -38920 | AK117: =SUM(R117:U117) -> -71746 | AL117: =SUM(S117:V117) -> -75446 | ... AS117: =SUM(Z117:AC117) -> 47733 | AU117: =SUM(AS117/AO117)-1 -> -3.5077756
B118: Net cash provided by financing activities | C118: =SUM(C111:C117) -> 4048527 | D118: =SUM(D111:D117) -> 4505662 | E118: =SUM(E111:E117) -> 1237311 | F118: =SUM(F111:F117) -> -1149776 | G118: =SUM(G111:G117) -> -664254 | H118: =SUM(H111:H117) -> -5950803 | I118: =SUM(I111:I117) -> -4074427 | K118: =SUM(K111:K117) -> -451929 | L118: =SUM(L111:L117) -> -480273 | M118: =SUM(M111:M117) -> -81555 | N118: =SUM(N111:N117) -> -136019 | O118: =SUM(O111:O117) -> -686322 | P118: =SUM(P111:P117) -> 11250 | Q118: =SUM(Q111:Q117) -> 4113 | R118: =SUM(R111:R117) -> 6705 | ... AC118: =SUM(AC111:AC117) -> -1737029 | AE118: =SUM(AE111:AE117) -> -1384169 | AF118: =SUM(AF111:AF117) -> -892646 | AG118: =SUM(AG111:AG117) -> -806978 | AH118: =SUM(AH111:AH117) -> -664254 | AI118: =SUM(AI111:AI117) -> -352005 | AJ118: =SUM(AJ111:AJ117) -> -1012604 | AK118: =SUM(AK111:AK117) -> -3491825 | AL118: =SUM(AL111:AL117) -> -5950803 | ... AS118: =SUM(AS111:AS117) -> -8946911 | AU118: =SUM(AS118/AO118)-1 -> 0.52990902
B121: Unrestricted Cash BOP | C121: 2822795 | D121: =C128 -> 3794483 | E121: =D128 -> 5018437 | F121: =E128 -> 8205550 | G121: =F128 -> 6027804 | H121: =G128 -> 5147176 | I121: =H128 -> 7116913 | K121: =E128 -> 8205550 | L121: =K128 -> 8403705 | M121: =L128 -> 7777530 | N121: =M128 -> 7526681 | O121: =N128 -> 6027804 | P121: =O128 -> 6008946 | Q121: =P128 -> 5819449 | R121: =Q128 -> 6113733 | S121: =R128 -> 5147176 | ... AC121: =AB128 -> 8177405 | AE121: =K128 -> 8403705 | AF121: =L128 -> 7777530 | AG121: =M128 -> 7526681 | AH121: =N128 -> 6027804 | AI121: =O128 -> 6008946 | AJ121: =P128 -> 5819449 | AK121: =Q128 -> 6113733 | AL121: =R128 -> 5147176 | ... AS121: =Y128 -> 7457025
B122: BOP Restricted Cash Adjustment | C122: 0 | D122: =-C126 -> 17558 | E122: =-D126 -> 25349 | F122: =-E126 -> 33320 | G122: =-F126 -> 27307 | H122: =-G126 -> 23406 | I122: =-H126 -> 1602 | K122: =-E126 -> 33320 | L122: =-K126 -> 32748 | M122: =-L126 -> 27088 | N122: =-M126 -> 26287 | O122: =-N126 -> 27307 | P122: =-O126 -> 25555 | Q122: =-P126 -> 24960 | R122: =-Q126 -> 26581 | S122: =-R126 -> 23406 | ... AC122: =-AB126 -> 3168 | AE122: =-K126 -> 32748 | AF122: =-L126 -> 27088 | AG122: =-M126 -> 26287 | AH122: =-N126 -> 27307 | AI122: =-O126 -> 25555 | AJ122: =-P126 -> 24960 | AK122: =-Q126 -> 26581 | AL122: =-R126 -> 23406 | ... AS122: =-Y126 -> 2060
B123: Adjusted Cash Position BOP | C123: =SUM(C121:C122) -> 2822795 | D123: =SUM(D121:D122) -> 3812041 | E123: =SUM(E121:E122) -> 5043786 | F123: =SUM(F121:F122) -> 8238870 | G123: =SUM(G121:G122) -> 6055111 | H123: =SUM(H121:H122) -> 5170582 | I123: =SUM(I121:I122) -> 7118515 | K123: =SUM(K121:K122) -> 8238870 | L123: =SUM(L121:L122) -> 8436453 | M123: =SUM(M121:M122) -> 7804618 | N123: =SUM(N121:N122) -> 7552968 | O123: =SUM(O121:O122) -> 6055111 | P123: =SUM(P121:P122) -> 6034501 | Q123: =SUM(Q121:Q122) -> 5844409 | R123: =SUM(R121:R122) -> 6140314 | ... AC123: =SUM(AC121:AC122) -> 8180573 | AE123: =SUM(AE121:AE122) -> 8436453 | AF123: =SUM(AF121:AF122) -> 7804618 | AG123: =SUM(AG121:AG122) -> 7552968 | AH123: =SUM(AH121:AH122) -> 6055111 | AI123: =SUM(AI121:AI122) -> 6034501 | AJ123: =SUM(AJ121:AJ122) -> 5844409 | AK123: =SUM(AK121:AK122) -> 6140314 | AL123: =SUM(AL121:AL122) -> 5170582 | ... AS123: =SUM(AS121:AS122) -> 7459085
...

Sheet EPS
B2: ='Historical Financials'!B2 -> Netflix, Inc. (NASDAQ: NFLX)
B3: EPS Build-Up
B4: ($ in Bns, Including Shares)
B6: Stock Split Converter | C6: 1
B7: Stock Split Amount | C7: 20
B8: Stock Split End Period | C8: 2Q22
B10: Net Income Per Share | G10: FYE | O10: Quarterly | Y10: Quarterly | AO10: LTM | AP10: LTM
B11: Fiscal Period | C11: 2018 | D11: 2019 | E11: 2020 | F11: 2021 | G11: 2022 | H11: 2023 | I11: 2024 | K11: 1Q21 | L11: 2Q21 | M11: 3Q21 | N11: 4Q21 | O11: 1Q22 | P11: 2Q22 | Q11: 3Q22 | R11: 4Q22 | S11: 1Q23 | T11: 2Q23 | U11: 3Q23 | V11: 4Q23 | W11: 1Q24 | X11: 2Q24 | Y11: 3Q24 | Z11: 4Q24 | AA11: 1Q25 | AB11: 2Q25 | AC11: 3Q25 | AE11: =N11 -> 4Q21 | AF11: =O11 -> 1Q22 | AG11: =P11 -> 2Q22 | AH11: =Q11 -> 3Q22 | AI11: =R11 -> 4Q22 | AJ11: =S11 -> 1Q23 | AK11: =T11 -> 2Q23 | AL11: =U11 -> 3Q23 | ... AT11: =AC11 -> 3Q25
B12: Fiscal Period End Date | C12: 43465 | D12: 43830 | E12: 44196 | F12: 44561 | G12: 44926 | H12: 45291 | I12: 45657 | K12: 44289 | L12: 44380 | M12: 44471 | N12: 44561 | O12: 44653 | P12: 44744 | Q12: 44835 | R12: 44926 | S12: 45017 | T12: 45108 | U12: 45199 | V12: 45291 | W12: 45381 | X12: 45472 | Y12: 45563 | Z12: 45657 | AA12: 45745 | AB12: 45836 | AC12: 45927 | AE12: =N12 -> 44561 | AF12: =O12 -> 44653 | AG12: =P12 -> 44744 | AH12: =Q12 -> 44835 | AI12: =R12 -> 44926 | AJ12: =S12 -> 45017 | AK12: =T12 -> 45108 | AL12: =U12 -> 45199 | ... AT12: =AC12 -> 45927
A14: X | B14: Consolidated Basic EPS
B16: Consolidated Allocation of undistributed earnings | C16: =C29+C35+C41 -> 0 | D16: =D29+D35+D41 -> 0 | E16: =E29+E35+E41 -> 0 | F16: =F29+F35+F41 -> 0 | G16: =G29+G35+G41 -> 0 | H16: =H29+H35+H41 -> 0 | I16: =I29+I35+I41 -> 0 | K16: =K29+K35+K41 -> 17930 | L16: =L29+L35+L41 -> 18525 | M16: =M29+M35+M41 -> 18936 | N16: =N29+N35+N41 -> -55391 | O16: =O29+O35+O41 -> 16436 | P16: =P29+P35+P41 -> 16002 | Q16: =Q29+Q35+Q41 -> 13910 | R16: =R29+R35+R41 -> -46348 | ... AC16: =AC29+AC35+AC41 -> 34979 | AE16: =AE29+AE35+AE41 -> 0 | AF16: =AF29+AF35+AF41 -> -1494 | AG16: =AG29+AG35+AG41 -> -4017 | AH16: =AH29+AH35+AH41 -> -9043 | AI16: =AI29+AI35+AI41 -> 0 | AJ16: =AJ29+AJ35+AJ41 -> -1385 | AK16: =AK29+AK35+AK41 -> 981 | AL16: =AL29+AL35+AL41 -> 6760 | ... AT16: =AT29+AT35+AT41 -> 24133
B17: Consolidated Basic Shares | C17: =IF($C$6=1,C30+C35+C41,C31+C37+C43) -> 0 | D17: =IF($C$6=1,D30+D35+D41,D31+D37+D43) -> 0 | E17: =IF($C$6=1,E30+E35+E41,E31+E37+E43) -> 0 | F17: =IF($C$6=1,F30+F36+F42,F31+F37+F43) -> 0 | G17: =IF($C$6=1,G30+G36+G42,G31+G37+G43) -> 0 | H17: =IF($C$6=1,H30+H36+H42,H31+H37+H43) -> 0 | I17: =IF($C$6=1,I30+I36+I42,I31+I37+I43) -> 0 | K17: =IF($C$6=1,K30+K36+K42,K31+K37+K43) -> 13464.4 | L17: =IF($C$6=1,L30+L36+L42,L31+L37+L43) -> 13379.16 | M17: =IF($C$6=1,M30+M36+M42,M31+M37+M43) -> 13315.16 | N17: =IF($C$6=1,N30+N36+N42,N31+N37+N43) -> 0 | O17: =IF($C$6=1,O30+O36+O42,O31+O37+O43) -> 13203.42 | P17: =IF($C$6=1,P30+P36+P42,P31+P37+P43) -> 13133 | Q17: =IF($C$6=1,Q30+Q36+Q42,Q31+Q37+Q43) -> 13018 | R17: =IF($C$6=1,R30+R36+R42,R31+R37+R43) -> 0 | ... AC17: =IF($C$6=1,AC30+AC36+AC42,AC31+AC37+AC43) -> 12086 | AE17: =IF($C$6=1,AE30+AE36+AE42,AE31+AE37+AE43) -> 0 | AF17: =IF($C$6=1,AF30+AF36+AF42,AF31+AF37+AF43) -> 13203.42 | AG17: =IF($C$6=1,AG30+AG36+AG42,AG31+AG37+AG43) -> 13133 | AH17: =IF($C$6=1,AH30+AH36+AH42,AH31+AH37+AH43) -> 13018 | AI17: =IF($C$6=1,AI30+AI36+AI42,AI31+AI37+AI43) -> 0 | AJ17: =IF($C$6=1,AJ30+AJ36+AJ42,AJ31+AJ37+AJ43) -> 12781 | AK17: =IF($C$6=1,AK30+AK36+AK42,AK31+AK37+AK43) -> 12668 | AL17: =IF($C$6=1,AL30+AL36+AL42,AL31+AL37+AL43) -> 12581 | ... AT17: =IF($C$6=1,AT30+AT36+AT42,AT31+AT37+AT43) -> 12086
B18: Consolidated Basic EPS | C18: =C16/C17 -> #DIV/0! | D18: =D16/D17 -> #DIV/0! | E18: =E16/E17 -> #DIV/0! | F18: =F16/F17 -> #DIV/0! | G18: =G16/G17 -> #DIV/0! | H18: =H16/H17 -> #DIV/0! | I18: =I16/I17 -> #DIV/0! | K18: =K16/K17 -> 1.3316598 | L18: =L16/L17 -> 1.3846161 | M18: =M16/M17 -> 1.4221384 | N18: =N16/N17 -> #DIV/0! | O18: =O16/O17 -> 1.244829 | P18: =P16/P17 -> 1.2184573 | Q18: =Q16/Q17 -> 1.0685205 | R18: =R16/R17 -> #DIV/0! | ... AC18: =AC16/AC17 -> 2.8941751 | AE18: =AE16/AE17 -> #DIV/0! | AF18: =AF16/AF17 -> -0.1131525 | AG18: =AG16/AG17 -> -0.30587071 | AH18: =AH16/AH17 -> -0.69465356 | AI18: =AI16/AI17 -> #DIV/0! | AJ18: =AJ16/AJ17 -> -0.10836398 | AK18: =AK16/AK17 -> 0.077439217 | AL18: =AL16/AL17 -> 0.53731818 | ... AT18: =AT16/AT17 -> 1.9967731
A20: X | B20: Consolidated Fully Diluted EPS
B22: Consolidated Allocation of undistributed earnings | C22: =+C49+C58+C64 -> 0 | D22: =+D49+D58+D64 -> 0 | E22: =+E49+E58+E64 -> 0 | F22: =+F49+F58+F64 -> 0 | G22: =+G49+G58+G64 -> 0 | H22: =+H49+H58+H64 -> 0 | I22: =+I49+I58+I64 -> 0 | K22: =+K49+K58+K64 -> 19135 | L22: =+L49+L58+L64 -> 19771 | M22: =+M49+M58+M64 -> 20207 | N22: =+N49+N58+N64 -> -59113 | O22: =+O49+O58+O64 -> 17533 | P22: =+P49+P58+P64 -> 17074 | Q22: =+Q49+Q58+Q64 -> 14850 | R22: =+R49+R58+R64 -> -49457 | ... AC22: =+AC49+AC58+AC64 -> 37402 | AE22: =+AE49+AE58+AE64 -> 0 | AF22: =+AF49+AF58+AF64 -> -1602 | AG22: =+AG49+AG58+AG64 -> -4299 | AH22: =+AH49+AH58+AH64 -> -9656 | AI22: =+AI49+AI58+AI64 -> 0 | AJ22: =+AJ49+AJ58+AJ64 -> -1446 | AK22: =+AK49+AK58+AK64 -> 1113 | AL22: =+AL49+AL58+AL64 -> 7309 | ... AT22: =+AT49+AT58+AT64 -> 25827
B23: Consolidated Fully Diluted Shares | C23: =+C50+C59+C65 -> 0 | D23: =+D50+D59+D65 -> 0 | E23: =+E50+E59+E65 -> 0 | F23: =+F50+F59+F65 -> 0 | G23: =+G50+G59+G65 -> 0 | H23: =+H50+H59+H65 -> 0 | I23: =+I50+I59+I65 -> 0 | K23: =+K50+K59+K65 -> 14558.22 | L23: =+L50+L59+L65 -> 14506.08 | M23: =+M50+M59+M65 -> 14438.46 | N23: =+N50+N59+N65 -> -605.32 | O23: =+O50+O59+O65 -> 14241.72 | P23: =+P50+P59+P65 -> 14126 | Q23: =+Q50+Q59+Q65 -> 13982 | R23: =+R50+R59+R65 -> 0 | ... AC23: =+AC50+AC59+AC65 -> 13048 | AE23: =+AE50+AE59+AE65 -> -604.427 | AF23: =+AF50+AF59+AF65 -> 14241.625 | AG23: =+AG50+AG59+AG65 -> 14126 | AH23: =+AH50+AH59+AH65 -> 13982 | AI23: =+AI50+AI59+AI65 -> 0 | AJ23: =+AJ50+AJ59+AJ65 -> 13706 | AK23: =+AK50+AK59+AK65 -> 13616 | AL23: =+AL50+AL59+AL65 -> 13571 | ... AT23: =+AT50+AT59+AT65 -> 13048
B24: Consolidated Basic EPS | C24: =C22/C23 -> #DIV/0! | D24: =D22/D23 -> #DIV/0! | E24: =E22/E23 -> #DIV/0! | F24: =F22/F23 -> #DIV/0! | G24: =G22/G23 -> #DIV/0! | H24: =H22/H23 -> #DIV/0! | I24: =I22/I23 -> #DIV/0! | K24: =K22/K23 -> 1.3143777 | L24: =L22/L23 -> 1.3629457 | M24: =M22/M23 -> 1.399526 | N24: =N22/N23 -> 97.655785 | O24: =O22/O23 -> 1.2311013 | P24: =P22/P23 -> 1.2086932 | Q24: =Q22/Q23 -> 1.0620798 | R24: =R22/R23 -> #DIV/0! | ... AC24: =AC22/AC23 -> 2.8664929 | AE24: =AE22/AE23 -> 0 | AF24: =AF22/AF23 -> -0.11248716 | AG24: =AG22/AG23 -> -0.30433244 | AH24: =AH22/AH23 -> -0.6906022 | AI24: =AI22/AI23 -> #DIV/0! | AJ24: =AJ22/AJ23 -> -0.10550124 | AK24: =AK22/AK23 -> 0.081742068 | AL24: =AL22/AL23 -> 0.5385749 | ... AT24: =AT22/AT23 -> 1.9793838
A26: X | B26: Basic EPS Per Share Class
B28: Class A
B29: Allocation of undistributed earnings | K29: 8011 | L29: 8321 | M29: 8548 | N29: =SUM(F29-SUM(K29:M29)) -> -24880 | O29: 7481 | P29: 7329 | Q29: 6393 | R29: =SUM(G29-SUM(O29:Q29)) -> -21203 | S29: 7006 | T29: 8600 | U29: 9271 | V29: =SUM(H29-SUM(S29:U29)) -> -24877 | W29: 11213 | X29: 11219 | Y29: 12521 | Z29: =SUM(I29-SUM(W29:Y29)) -> -34953 | AA29: 16534 | AB29: 13536 | AC29: 16839 | AE29: =SUM(K29:N29) -> 0 | AF29: =SUM(L29:O29) -> -530 | AG29: =SUM(M29:P29) -> -1522 | AH29: =SUM(N29:Q29) -> -3677 | AI29: =SUM(O29:R29) -> 0 | AJ29: =SUM(P29:S29) -> -475 | AK29: =SUM(Q29:T29) -> 796 | AL29: =SUM(R29:U29) -> 3674 | ... AT29: =SUM(Z29:AC29) -> 11956
B30: Stock Split Adjusted Basic Shares | C30: =IF($C$6=1,C31*20,C31) -> 0 | D30: =IF($C$6=1,D31*20,D31) -> 0 | E30: =IF($C$6=1,E31*20,E31) -> 0 | F30: =IF($C$6=1,F31*20,F31) -> 0 | G30: =G31 -> 0 | H30: =H31 -> 0 | I30: =I31 -> 0 | K30: =IF($C$6=1,K31*20,K31) -> 6016 | L30: =IF($C$6=1,L31*20,L31) -> 6009.7 | M30: =IF($C$6=1,M31*20,M31) -> 6010.38 | N30: =IF($C$6=1,N31*20,N31) -> 0 | O30: =IF($C$6=1,O31*20,O31) -> 6009.56 | P30: =P31 -> 6015 | Q30: =Q31 -> 5983 | R30: =R31 -> 0 | S30: =S31 -> 5949 | T30: =T31 -> 5931 | U30: =U31 -> 5924 | V30: =V31 -> 0 | W30: =W31 -> 5883 | ... AC30: =AC31 -> 5818 | AE30: =N30 -> 0 | AF30: =O30 -> 6009.56 | AG30: =P30 -> 6015 | AH30: =Q30 -> 5983 | AI30: =R30 -> 0 | AJ30: =S30 -> 5949 | AK30: =T30 -> 5931 | AL30: =U30 -> 5924 | ... AT30: =AC30 -> 5818
B31: Unadjusted Basic Shares | K31: 300.8 | L31: 300.485 | M31: 300.519 | N31: =F31 -> 0 | O31: 300.478 | P31: 6015 | Q31: 5983 | R31: =G31 -> 0 | S31: 5949 | T31: 5931 | U31: 5924 | V31: =H31 -> 0 | W31: 5883 | X31: 5862 | Y31: 5850 | Z31: =I31 -> 0 | AA31: 5831 | AB31: 5819 | AC31: 5818 | AE31: =N31 -> 0 | AF31: =O31 -> 300.478 | AG31: =P31 -> 6015 | AH31: =Q31 -> 5983 | AI31: =R31 -> 0 | AJ31: =S31 -> 5949 | AK31: =T31 -> 5931 | AL31: =U31 -> 5924 | ... AT31: =AC31 -> 5818
B32: Class A Basic EPS | C32: =IF($C$6=1, C29/C30,C29/C31) -> #DIV/0! | D32: =IF($C$6=1, D29/D30,D29/D31) -> #DIV/0! | E32: =IF($C$6=1, E29/E30,E29/E31) -> #DIV/0! | F32: =IF($C$6=1, F29/F30,F29/F31) -> #DIV/0! | G32: =IF($C$6=1, G29/G30,G29/G31) -> #DIV/0! | H32: =IF($C$6=1, H29/H30,H29/H31) -> #DIV/0! | I32: =IF($C$6=1, I29/I30,I29/I31) -> #DIV/0! | K32: =IF($C$6=1, K29/K30,K29/K31) -> 1.3316157 | L32: =IF($C$6=1, L29/L30,L29/L31) -> 1.3845949 | M32: =IF($C$6=1, M29/M30,M29/M31) -> 1.4222062 | N32: =IF($C$6=1, N29/N30,N29/N31) -> #DIV/0! | O32: =IF($C$6=1, O29/O30,O29/O31) -> 1.2448499 | P32: =IF($C$6=1, P29/P30,P29/P31) -> 1.2184539 | Q32: =IF($C$6=1, Q29/Q30,Q29/Q31) -> 1.0685275 | R32: =IF($C$6=1, R29/R30,R29/R31) -> #DIV/0! | ... AC32: =IF($C$6=1, AC29/AC30,AC29/AC31) -> 2.8942936 | AE32: =IF($C$6=1, AE29/AE30,AE29/AE31) -> #DIV/0! | AF32: =IF($C$6=1, AF29/AF30,AF29/AF31) -> -0.088192813 | AG32: =IF($C$6=1, AG29/AG30,AG29/AG31) -> -0.25303408 | AH32: =IF($C$6=1, AH29/AH30,AH29/AH31) -> -0.61457463 | AI32: =IF($C$6=1, AI29/AI30,AI29/AI31) -> #DIV/0! | AJ32: =IF($C$6=1, AJ29/AJ30,AJ29/AJ31) -> -0.079845352 | AK32: =IF($C$6=1, AK29/AK30,AK29/AK31) -> 0.13421008 | AL32: =IF($C$6=1, AL29/AL30,AL29/AL31) -> 0.62018906 | ... AT32: =IF($C$6=1, AT29/AT30,AT29/AT31) -> 2.0550017
B34: Class B
B35: Allocation of undistributed earnings | K35: 1221 | L35: 1265 | M35: 1291 | N35: =SUM(F35-SUM(K35:M35)) -> -3777 | O35: 1109 | P35: 1081 | Q35: 946 | R35: =SUM(G35-SUM(O35:Q35)) -> -3136 | S35: 1040 | T35: 1275 | U35: 1369 | V35: =SUM(H35-SUM(S35:U35)) -> -3684 | W35: 1656 | X35: 1657 | Y35: 1851 | Z35: =SUM(I35-SUM(W35:Y35)) -> -5164 | AA35: 2435 | AB35: 1981 | AC35: 2445 | AE35: =SUM(K35:N35) -> 0 | AF35: =SUM(L35:O35) -> -112 | AG35: =SUM(M35:P35) -> -296 | AH35: =SUM(N35:Q35) -> -641 | AI35: =SUM(O35:R35) -> 0 | AJ35: =SUM(P35:S35) -> -69 | AK35: =SUM(Q35:T35) -> 125 | AL35: =SUM(R35:U35) -> 548 | ... AT35: =SUM(Z35:AC35) -> 1697
B36: Stock Split Adjusted Basic Shares | C36: =IF($C$6=1,C37*20,C37) -> 0 | D36: =IF($C$6=1,D37*20,D37) -> 0 | E36: =IF($C$6=1,E37*20,E37) -> 0 | F36: =IF($C$6=1,F37*20,F37) -> 0 | G36: =G37 -> 0 | H36: =H37 -> 0 | I36: =I37 -> 0 | K36: =IF($C$6=1,K37*20,K37) -> 916.8 | L36: =IF($C$6=1,L37*20,L37) -> 913.84 | M36: =IF($C$6=1,M37*20,M37) -> 908.08 | N36: =IF($C$6=1,N37*20,N37) -> 0 | O36: =IF($C$6=1,O37*20,O37) -> 890.7 | P36: =P37 -> 887 | Q36: =Q37 -> 885 | R36: =R37 -> 0 | S36: =S37 -> 883 | T36: =T37 -> 879 | U36: =U37 -> 875 | V36: =V37 -> 0 | W36: =W37 -> 869 | ... AC36: =AC37 -> 845 | AE36: =N36 -> 0 | AF36: =O36 -> 890.7 | AG36: =P36 -> 887 | AH36: =Q36 -> 885 | AI36: =R36 -> 0 | AJ36: =S36 -> 883 | AK36: =T36 -> 879 | AL36: =U36 -> 875 | ... AT36: =AC36 -> 845
B37: Unadjusted Basic Shares | K37: 45.84 | L37: 45.692 | M37: 45.404 | N37: =F37 -> 0 | O37: 44.535 | P37: 887 | Q37: 885 | R37: =G37 -> 0 | S37: 883 | T37: 879 | U37: 875 | V37: =H37 -> 0 | W37: 869 | X37: 866 | Y37: 865 | Z37: =I37 -> 0 | AA37: 859 | AB37: 852 | AC37: 845 | AE37: =N37 -> 0 | AF37: =O37 -> 44.535 | AG37: =P37 -> 887 | AH37: =Q37 -> 885 | AI37: =R37 -> 0 | AJ37: =S37 -> 883 | AK37: =T37 -> 879 | AL37: =U37 -> 875 | ... AT37: =AC37 -> 845
B38: Class B Basic EPS | C38: =IF($C$6=1, C35/C36,C35/C37) -> #DIV/0! | D38: =IF($C$6=1, D35/D36,D35/D37) -> #DIV/0! | E38: =IF($C$6=1, E35/E36,E35/E37) -> #DIV/0! | F38: =IF($C$6=1, F35/F36,F35/F37) -> #DIV/0! | G38: =IF($C$6=1, G35/G36,G35/G37) -> #DIV/0! | H38: =IF($C$6=1, H35/H36,H35/H37) -> #DIV/0! | I38: =IF($C$6=1, I35/I36,I35/I37) -> #DIV/0! | K38: =IF($C$6=1, K35/K36,K35/K37) -> 1.3318063 | L38: =IF($C$6=1, L35/L36,L35/L37) -> 1.3842686 | M38: =IF($C$6=1, M35/M36,M35/M37) -> 1.4216809 | N38: =IF($C$6=1, N35/N36,N35/N37) -> #DIV/0! | O38: =IF($C$6=1, O35/O36,O35/O37) -> 1.2450881 | P38: =IF($C$6=1, P35/P36,P35/P37) -> 1.2187148 | Q38: =IF($C$6=1, Q35/Q36,Q35/Q37) -> 1.0689266 | R38: =IF($C$6=1, R35/R36,R35/R37) -> #DIV/0! | ... AC38: =IF($C$6=1, AC35/AC36,AC35/AC37) -> 2.8934911 | AE38: =IF($C$6=1, AE35/AE36,AE35/AE37) -> #DIV/0! | AF38: =IF($C$6=1, AF35/AF36,AF35/AF37) -> -0.1257438 | AG38: =IF($C$6=1, AG35/AG36,AG35/AG37) -> -0.33370913 | AH38: =IF($C$6=1, AH35/AH36,AH35/AH37) -> -0.72429379 | AI38: =IF($C$6=1, AI35/AI36,AI35/AI37) -> #DIV/0! | AJ38: =IF($C$6=1, AJ35/AJ36,AJ35/AJ37) -> -0.078142695 | AK38: =IF($C$6=1, AK35/AK36,AK35/AK37) -> 0.14220705 | AL38: =IF($C$6=1, AL35/AL36,AL35/AL37) -> 0.62628571 | ... AT38: =IF($C$6=1, AT35/AT36,AT35/AT37) -> 2.008284
B40: Class C
B41: Allocation of undistributed earnings | K41: 8698 | L41: 8939 | M41: 9097 | N41: =SUM(F41-SUM(K41:M41)) -> -26734 | O41: 7846 | P41: 7592 | Q41: 6571 | R41: =SUM(G41-SUM(O41:Q41)) -> -22009 | S41: 7005 | T41: 8493 | U41: 9049 | V41: =SUM(H41-SUM(S41:U41)) -> -24547 | W41: 10793 | X41: 10743 | Y41: 11929 | Z41: =SUM(I41-SUM(W41:Y41)) -> -33465 | AA41: 15571 | AB41: 12679 | AC41: 15695 | AE41: =SUM(K41:N41) -> 0 | AF41: =SUM(L41:O41) -> -852 | AG41: =SUM(M41:P41) -> -2199 | AH41: =SUM(N41:Q41) -> -4725 | AI41: =SUM(O41:R41) -> 0 | AJ41: =SUM(P41:S41) -> -841 | AK41: =SUM(Q41:T41) -> 60 | AL41: =SUM(R41:U41) -> 2538 | ... AT41: =SUM(Z41:AC41) -> 10480
B42: Stock Split Adjusted Basic Shares | C42: =IF($C$6=1,C43*20,C43) -> 0 | D42: =IF($C$6=1,D43*20,D43) -> 0 | E42: =IF($C$6=1,E43*20,E43) -> 0 | F42: =IF($C$6=1,F43*20,F43) -> 0 | G42: =G43 -> 0 | H42: =H43 -> 0 | I42: =I43 -> 0 | K42: =IF($C$6=1,K43*20,K43) -> 6531.6 | L42: =IF($C$6=1,L43*20,L43) -> 6455.62 | M42: =IF($C$6=1,M43*20,M43) -> 6396.7 | N42: =IF($C$6=1,N43*20,N43) -> 0 | O42: =IF($C$6=1,O43*20,O43) -> 6303.16 | P42: =P43 -> 6231 | Q42: =Q43 -> 6150 | R42: =R43 -> 0 | S42: =S43 -> 5949 | T42: =T43 -> 5858 | U42: =U43 -> 5782 | V42: =V43 -> 0 | W42: =W43 -> 5663 | ... AC42: =AC43 -> 5423 | AE42: =N42 -> 0 | AF42: =O42 -> 6303.16 | AG42: =P42 -> 6231 | AH42: =Q42 -> 6150 | AI42: =R42 -> 0 | AJ42: =S42 -> 5949 | AK42: =T42 -> 5858 | AL42: =U42 -> 5782 | ... AT42: =AC42 -> 5423
B43: Unadjusted Basic Shares | K43: 326.58 | L43: 322.781 | M43: 319.835 | N43: =F43 -> 0 | O43: 315.158 | P43: 6231 | Q43: 6150 | R43: =G43 -> 0 | S43: 5949 | T43: 5858 | U43: 5782 | V43: =H43 -> 0 | W43: 5663 | X43: 5615 | Y43: 5575 | Z43: =I43 -> 0 | AA43: 5493 | AB43: 5451 | AC43: 5423 | AE43: =N43 -> 0 | AF43: =O43 -> 315.158 | AG43: =P43 -> 6231 | AH43: =Q43 -> 6150 | AI43: =R43 -> 0 | AJ43: =S43 -> 5949 | AK43: =T43 -> 5858 | AL43: =U43 -> 5782 | ... AT43: =AC43 -> 5423
B44: Class C Basic EPS | C44: =IF($C$6=1, C41/C42,C41/C43) -> #DIV/0! | D44: =IF($C$6=1, D41/D42,D41/D43) -> #DIV/0! | E44: =IF($C$6=1, E41/E42,E41/E43) -> #DIV/0! | F44: =IF($C$6=1, F41/F42,F41/F43) -> #DIV/0! | G44: =IF($C$6=1, G41/G42,G41/G43) -> #DIV/0! | H44: =IF($C$6=1, H41/H42,H41/H43) -> #DIV/0! | I44: =IF($C$6=1, I41/I42,I41/I43) -> #DIV/0! | K44: =IF($C$6=1, K41/K42,K41/K43) -> 1.3316798 | L44: =IF($C$6=1, L41/L42,L41/L43) -> 1.384685 | M44: =IF($C$6=1, M41/M42,M41/M43) -> 1.4221395 | N44: =IF($C$6=1, N41/N42,N41/N43) -> #DIV/0! | O44: =IF($C$6=1, O41/O42,O41/O43) -> 1.2447725 | P44: =IF($C$6=1, P41/P42,P41/P43) -> 1.218424 | Q44: =IF($C$6=1, Q41/Q42,Q41/Q43) -> 1.0684553 | R44: =IF($C$6=1, R41/R42,R41/R43) -> #DIV/0! | ... AC44: =IF($C$6=1, AC41/AC42,AC41/AC43) -> 2.8941545 | AE44: =IF($C$6=1, AE41/AE42,AE41/AE43) -> #DIV/0! | AF44: =IF($C$6=1, AF41/AF42,AF41/AF43) -> -0.1351703 | AG44: =IF($C$6=1, AG41/AG42,AG41/AG43) -> -0.35291286 | AH44: =IF($C$6=1, AH41/AH42,AH41/AH43) -> -0.76829268 | AI44: =IF($C$6=1, AI41/AI42,AI41/AI43) -> #DIV/0! | AJ44: =IF($C$6=1, AJ41/AJ42,AJ41/AJ43) -> -0.1413683 | AK44: =IF($C$6=1, AK41/AK42,AK41/AK43) -> 0.010242404 | AL44: =IF($C$6=1, AL41/AL42,AL41/AL43) -> 0.43894846 | ... AT44: =IF($C$6=1, AT41/AT42,AT41/AT43) -> 1.9325097
A46: X | B46: Fully Diluted EPS Per Share Class
B48: Class A
B49: Allocation of undistributed earnings | K49: 9113 | L49: 9437 | M49: 9683 | N49: =SUM(F49-SUM(K49:M49)) -> -28233 | O49: 8495 | P49: 8342 | Q49: 7294 | R49: =SUM(G49-SUM(O49:Q49)) -> -24131 | S49: 8019 | T49: 9800 | U49: 10544 | V49: =SUM(H49-SUM(S49:U49)) -> -28363 | W49: 12754 | X49: 12736 | Y49: 14237 | Z49: =SUM(I49-SUM(W49:Y49)) -> -39727 | AA49: 18813 | AB49: 15429 | AC49: 19113 | AE49: =SUM(K49:N49) -> 0 | AF49: =SUM(L49:O49) -> -618 | AG49: =SUM(M49:P49) -> -1713 | AH49: =SUM(N49:Q49) -> -4102 | AI49: =SUM(O49:R49) -> 0 | AJ49: =SUM(P49:S49) -> -476 | AK49: =SUM(Q49:T49) -> 982 | AL49: =SUM(R49:U49) -> 4232 | ... AT49: =SUM(Z49:AC49) -> 13628
B50: Fully Diluted Shares | C50: =SUM(C51:C53) -> 0 | D50: =SUM(D51:D53) -> 0 | E50: =SUM(E51:E53) -> 0 | F50: =SUM(F51:F53) -> 0 | G50: =SUM(G51:G53) -> 0 | H50: =SUM(H51:H53) -> 0 | I50: =SUM(I51:I53) -> 0 | K50: =SUM(K51:K53) -> 6933.16 | L50: =SUM(L51:L53) -> 6923.84 | M50: =SUM(M51:M53) -> 6918.74 | N50: =SUM(N51:N53) -> -0.94 | O50: =SUM(O51:O53) -> 6900.36 | P50: =SUM(P51:P53) -> 6902 | Q50: =SUM(Q51:Q53) -> 6868 | R50: =SUM(R51:R53) -> 0 | ... AC50: =SUM(AC51:AC53) -> 6663 | AE50: =SUM(AE51:AE53) -> -0.047 | AF50: =SUM(AF51:AF53) -> 6900.265 | AG50: =SUM(AG51:AG53) -> 6902 | AH50: =SUM(AH51:AH53) -> 6868 | AI50: =SUM(AI51:AI53) -> 0 | AJ50: =SUM(AJ51:AJ53) -> 6832 | AK50: =SUM(AK51:AK53) -> 6810 | AL50: =SUM(AL51:AL53) -> 6799 | ... AT50: =SUM(AT51:AT53) -> 6663
B51: Number of shares used in basic computation | C51: =IF($C$6=1,C30,C31) -> 0 | D51: =IF($C$6=1,D30,D31) -> 0 | E51: =IF($C$6=1,E30,E31) -> 0 | F51: =IF($C$6=1,F30,F31) -> 0 | G51: =IF($C$6=1,G30,G31) -> 0 | H51: =IF($C$6=1,H30,H31) -> 0 | I51: =IF($C$6=1,I30,I31) -> 0 | K51: =IF($C$6=1,K30,K31) -> 6016 | L51: =IF($C$6=1,L30,L31) -> 6009.7 | M51: =IF($C$6=1,M30,M31) -> 6010.38 | N51: =IF($C$6=1,N30,N31) -> 0 | O51: =IF($C$6=1,O30,O31) -> 6009.56 | P51: =IF($C$6=1,P30,P31) -> 6015 | Q51: =IF($C$6=1,Q30,Q31) -> 5983 | R51: =IF($C$6=1,R30,R31) -> 0 | ... AC51: =IF($C$6=1,AC30,AC31) -> 5818 | AE51: =IF($C$6=1,AE30,AE31) -> 0 | AF51: =IF($C$6=1,AF30,AF31) -> 6009.56 | AG51: =IF($C$6=1,AG30,AG31) -> 6015 | AH51: =IF($C$6=1,AH30,AH31) -> 5983 | AI51: =IF($C$6=1,AI30,AI31) -> 0 | AJ51: =IF($C$6=1,AJ30,AJ31) -> 5949 | AK51: =IF($C$6=1,AK30,AK31) -> 5931 | AL51: =IF($C$6=1,AL30,AL31) -> 5924 | ... AT51: =IF($C$6=1,AT30,AT31) -> 5818
B52: Conversion of Class B to Class A common shares outstanding | C52: =IF($C$6=1,C36,C37) -> 0 | D52: =IF($C$6=1,D36,D37) -> 0 | E52: =IF($C$6=1,E36,E37) -> 0 | F52: =IF($C$6=1,F36,F37) -> 0 | G52: =IF($C$6=1,G36,G37) -> 0 | H52: =IF($C$6=1,H36,H37) -> 0 | I52: =IF($C$6=1,I36,I37) -> 0 | K52: =IF($C$6=1,K36,K37) -> 916.8 | L52: =IF($C$6=1,L36,L37) -> 913.84 | M52: =IF($C$6=1,M36,M37) -> 908.08 | N52: =IF($C$6=1,N36,N37) -> 0 | O52: =IF($C$6=1,O36,O37) -> 890.7 | P52: =IF($C$6=1,P36,P37) -> 887 | Q52: =IF($C$6=1,Q36,Q37) -> 885 | R52: =IF($C$6=1,R36,R37) -> 0 | ... AC52: =IF($C$6=1,AC36,AC37) -> 845 | AE52: =IF($C$6=1,AE36,AE37) -> 0 | AF52: =IF($C$6=1,AF36,AF37) -> 890.7 | AG52: =IF($C$6=1,AG36,AG37) -> 887 | AH52: =IF($C$6=1,AH36,AH37) -> 885 | AI52: =IF($C$6=1,AI36,AI37) -> 0 | AJ52: =IF($C$6=1,AJ36,AJ37) -> 883 | AK52: =IF($C$6=1,AK36,AK37) -> 879 | AL52: =IF($C$6=1,AL36,AL37) -> 875 | ... AT52: =IF($C$6=1,AT36,AT37) -> 845
B53: Adjusted RSUs and other contingently issuable shares | C53: =IF($C$6=1,C54*20,C54) -> 0 | D53: =IF($C$6=1,D54*20,D54) -> 0 | E53: =IF($C$6=1,E54*20,E54) -> 0 | F53: =IF($C$6=1,F54*20,F54) -> 0 | G53: =IF($C$6=1,G54*20,G54) -> 0 | H53: =IF($C$6=1,H54*20,H54) -> 0 | I53: =IF($C$6=1,I54*20,I54) -> 0 | K53: =IF($C$6=1,K54*20,K54) -> 0.36 | L53: =IF($C$6=1,L54*20,L54) -> 0.3 | M53: =IF($C$6=1,M54*20,M54) -> 0.28 | N53: =IF($C$6=1,N54*20,N54) -> -0.94 | O53: =IF($C$6=1,O54*20,O54) -> 0.1 | P53: =IF($C$6=1,P54*20,P54) -> 0 | Q53: =Q54 -> 0 | R53: =R54 -> 0 | S53: =S54 -> 0 | T53: =T54 -> 0 | U53: =U54 -> 0 | V53: =V54 -> 0 | W53: =W54 -> 0 | X53: =X54 -> 0 | ... AC53: =AC54 -> 0 | AE53: =AE54 -> -0.047 | AF53: =AF54 -> 0.005 | AG53: =AG54 -> 0 | AH53: =AH54 -> 0 | AI53: =AI54 -> 0 | AJ53: =AJ54 -> 0 | AK53: =AK54 -> 0 | AL53: =AL54 -> 0 | ... AT53: =AT54 -> 0
B54: RSUs and other contingently issuable shares | K54: 0.018 | L54: 0.015 | M54: 0.014 | N54: =SUM(F54*4)-SUM(K54:M54) -> -0.047 | O54: 0.005 | P54: 0 | Q54: 0 | R54: =G54 -> 0 | S54: 0 | T54: 0 | U54: 0 | V54: =H54 -> 0 | W54: 0 | X54: 0 | Y54: 0 | Z54: =I54 -> 0 | AA54: 0 | AB54: 0 | AC54: 0 | AE54: =N54 -> -0.047 | AF54: =O54 -> 0.005 | AG54: =P54 -> 0 | AH54: =Q54 -> 0 | AI54: =R54 -> 0 | AJ54: =S54 -> 0 | AK54: =T54 -> 0 | AL54: =U54 -> 0 | ... AT54: =AC54 -> 0
B55: Fully Diluted EPS | C55: =C49/C50 -> #DIV/0! | D55: =D49/D50 -> #DIV/0! | E55: =E49/E50 -> #DIV/0! | F55: =F49/F50 -> #DIV/0! | G55: =G49/G50 -> #DIV/0! | H55: =H49/H50 -> #DIV/0! | I55: =I49/I50 -> #DIV/0! | K55: =K49/K50 -> 1.3144079 | L55: =L49/L50 -> 1.362972 | M55: =M49/M50 -> 1.3995323 | N55: =N49/N50 -> 30035.106 | O55: =O49/O50 -> 1.2310952 | P55: =P49/P50 -> 1.2086352 | Q55: =Q49/Q50 -> 1.0620268 | R55: =R49/R50 -> #DIV/0! | ... AC55: =AC49/AC50 -> 2.8685277 | AE55: =AE49/AE50 -> 0 | AF55: =AF49/AF50 -> -0.089561778 | AG55: =AG49/AG50 -> -0.24818893 | AH55: =AH49/AH50 -> -0.59726267 | AI55: =AI49/AI50 -> #DIV/0! | AJ55: =AJ49/AJ50 -> -0.069672131 | AK55: =AK49/AK50 -> 0.14419971 | AL55: =AL49/AL50 -> 0.62244448 | ... AT55: =AT49/AT50 -> 2.0453249
B57: Class B
B58: Allocation of undistributed earnings | K58: 1205 | L58: 1246 | M58: 1271 | N58: =SUM(F58-SUM(K58:M58)) -> -3722 | O58: 1097 | P58: 1072 | Q58: 940 | R58: =SUM(G58-SUM(O58:Q58)) -> -3109 | S58: 1036 | T58: 1265 | U58: 1357 | V58: =SUM(H58-SUM(S58:U58)) -> -3658 | W58: 1641 | X58: 1639 | Y58: 1834 | Z58: =SUM(I58-SUM(W58:Y58)) -> -5114 | AA58: 2415 | AB58: 1970 | AC58: 2423 | AE58: =SUM(K58:N58) -> 0 | AF58: =SUM(L58:O58) -> -108 | AG58: =SUM(M58:P58) -> -282 | AH58: =SUM(N58:Q58) -> -613 | AI58: =SUM(O58:R58) -> 0 | AJ58: =SUM(P58:S58) -> -61 | AK58: =SUM(Q58:T58) -> 132 | AL58: =SUM(R58:U58) -> 549 | ... AT58: =SUM(Z58:AC58) -> 1694
B59: Fully Diluted Shares | C59: =SUM(C60:C60) -> 0 | D59: =SUM(D60:D60) -> 0 | E59: =SUM(E60:E60) -> 0 | F59: =SUM(F60:F60) -> 0 | G59: =SUM(G60:G60) -> 0 | H59: =SUM(H60:H60) -> 0 | I59: =SUM(I60:I60) -> 0 | K59: =SUM(K60:K60) -> 916.8 | L59: =SUM(L60:L60) -> 913.84 | M59: =SUM(M60:M60) -> 908.08 | N59: =SUM(N60:N60) -> 0 | O59: =SUM(O60:O60) -> 890.7 | P59: =SUM(P60:P60) -> 887 | Q59: =SUM(Q60:Q60) -> 885 | R59: =SUM(R60:R60) -> 0 | ... AC59: =SUM(AC60:AC60) -> 845 | AE59: =SUM(AE60:AE60) -> 0 | AF59: =SUM(AF60:AF60) -> 890.7 | AG59: =SUM(AG60:AG60) -> 887 | AH59: =SUM(AH60:AH60) -> 885 | AI59: =SUM(AI60:AI60) -> 0 | AJ59: =SUM(AJ60:AJ60) -> 883 | AK59: =SUM(AK60:AK60) -> 879 | AL59: =SUM(AL60:AL60) -> 875 | ... AT59: =SUM(AT60:AT60) -> 845
B60: Number of shares used in basic computation | C60: =IF($C$6=1,C36,C37) -> 0 | D60: =IF($C$6=1,D36,D37) -> 0 | E60: =IF($C$6=1,E36,E37) -> 0 | F60: =IF($C$6=1,F36,F37) -> 0 | G60: =IF($C$6=1,G36,G37) -> 0 | H60: =IF($C$6=1,H36,H37) -> 0 | I60: =IF($C$6=1,I36,I37) -> 0 | K60: =IF($C$6=1,K36,K37) -> 916.8 | L60: =IF($C$6=1,L36,L37) -> 913.84 | M60: =IF($C$6=1,M36,M37) -> 908.08 | N60: =IF($C$6=1,N36,N37) -> 0 | O60: =IF($C$6=1,O36,O37) -> 890.7 | P60: =IF($C$6=1,P36,P37) -> 887 | Q60: =IF($C$6=1,Q36,Q37) -> 885 | R60: =G60 -> 0 | S60: =IF($C$6=1,S36,S37) -> 883 | T60: =IF($C$6=1,T36,T37) -> 879 | U60: =IF($C$6=1,U36,U37) -> 875 | V60: =IF($C$6=1,V36,V37) -> 0 | W60: =IF($C$6=1,W36,W37) -> 869 | X60: =IF($C$6=1,X36,X37) -> 866 | Y60: =IF($C$6=1,Y36,Y37) -> 865 | Z60: =IF($C$6=1,Z36,Z37) -> 0 | ... AC60: =IF($C$6=1,AC36,AC37) -> 845 | AE60: =N60 -> 0 | AF60: =O60 -> 890.7 | AG60: =P60 -> 887 | AH60: =Q60 -> 885 | AI60: =R60 -> 0 | AJ60: =S60 -> 883 | AK60: =T60 -> 879 | AL60: =U60 -> 875 | ... AT60: =AC60 -> 845
B61: Fully Diluted EPS | C61: =C58/C59 -> #DIV/0! | D61: =D58/D59 -> #DIV/0! | E61: =E58/E59 -> #DIV/0! | F61: =F58/F59 -> #DIV/0! | G61: =G58/G59 -> #DIV/0! | H61: =H58/H59 -> #DIV/0! | I61: =I58/I59 -> #DIV/0! | K61: =K58/K59 -> 1.3143543 | L61: =L58/L59 -> 1.3634772 | M61: =M58/M59 -> 1.3996564 | N61: =N58/N59 -> #DIV/0! | O61: =O58/O59 -> 1.2316156 | P61: =P58/P59 -> 1.2085682 | Q61: =Q58/Q59 -> 1.0621469 | R61: =R58/R59 -> #DIV/0! | ... AC61: =AC58/AC59 -> 2.8674556 | AE61: =AE58/AE59 -> #DIV/0! | AF61: =AF58/AF59 -> -0.12125295 | AG61: =AG58/AG59 -> -0.31792559 | AH61: =AH58/AH59 -> -0.69265537 | AI61: =AI58/AI59 -> #DIV/0! | AJ61: =AJ58/AJ59 -> -0.069082673 | AK61: =AK58/AK59 -> 0.15017065 | AL61: =AL58/AL59 -> 0.62742857 | ... AT61: =AT58/AT59 -> 2.0047337
B63: Class C
B64: Allocation of undistributed earnings | K64: 8817 | L64: 9088 | M64: 9253 | N64: =SUM(F64-SUM(K64:M64)) -> -27158 | O64: 7941 | P64: 7660 | Q64: 6616 | R64: =SUM(G64-SUM(O64:Q64)) -> -22217 | S64: 7032 | T64: 8568 | U64: 9145 | V64: =SUM(H64-SUM(S64:U64)) -> -24745 | W64: 10908 | X64: 10883 | Y64: 12064 | Z64: =SUM(I64-SUM(W64:Y64)) -> -33855 | AA64: 15727 | AB64: 12767 | AC64: 15866 | AE64: =SUM(K64:N64) -> 0 | AF64: =SUM(L64:O64) -> -876 | AG64: =SUM(M64:P64) -> -2304 | AH64: =SUM(N64:Q64) -> -4941 | AI64: =SUM(O64:R64) -> 0 | AJ64: =SUM(P64:S64) -> -909 | AK64: =SUM(Q64:T64) -> -1 | AL64: =SUM(R64:U64) -> 2528 | ... AT64: =SUM(Z64:AC64) -> 10505
B65: Fully Diluted Shares | C65: =SUM(C66:C67) -> 0 | D65: =SUM(D66:D67) -> 0 | E65: =SUM(E66:E67) -> 0 | F65: =SUM(F66:F67) -> 0 | G65: =SUM(G66:G67) -> 0 | H65: =SUM(H66:H67) -> 0 | I65: =SUM(I66:I67) -> 0 | K65: =SUM(K66:K67) -> 6708.26 | L65: =SUM(L66:L67) -> 6668.4 | M65: =SUM(M66:M67) -> 6611.64 | N65: =SUM(N66:N67) -> -604.38 | O65: =SUM(O66:O67) -> 6450.66 | P65: =SUM(P66:P67) -> 6337 | Q65: =SUM(Q66:Q67) -> 6229 | R65: =SUM(R66:R67) -> 0 | ... AC65: =SUM(AC66:AC67) -> 5540 | AE65: =SUM(AE66:AE67) -> -604.38 | AF65: =SUM(AF66:AF67) -> 6450.66 | AG65: =SUM(AG66:AG67) -> 6337 | AH65: =SUM(AH66:AH67) -> 6229 | AI65: =SUM(AI66:AI67) -> 0 | AJ65: =SUM(AJ66:AJ67) -> 5991 | AK65: =SUM(AK66:AK67) -> 5927 | AL65: =SUM(AL66:AL67) -> 5897 | ... AT65: =SUM(AT66:AT67) -> 5540
B66: Basic Shares | C66: =IF($C$6=1,C42,C43) -> 0 | D66: =IF($C$6=1,D42,D43) -> 0 | E66: =IF($C$6=1,E42,E43) -> 0 | F66: =IF($C$6=1,F42,F43) -> 0 | G66: =IF($C$6=1,G42,G43) -> 0 | H66: =IF($C$6=1,H42,H43) -> 0 | I66: =IF($C$6=1,I42,I43) -> 0 | K66: =IF($C$6=1,K42,K43) -> 6531.6 | L66: =IF($C$6=1,L42,L43) -> 6455.62 | M66: =IF($C$6=1,M42,M43) -> 6396.7 | N66: =IF($C$6=1,N42,N43) -> 0 | O66: =IF($C$6=1,O42,O43) -> 6303.16 | P66: =IF($C$6=1,P42,P43) -> 6231 | Q66: =IF($C$6=1,Q42,Q43) -> 6150 | R66: =IF($C$6=1,R42,R43) -> 0 | ... AC66: =IF($C$6=1,AC42,AC43) -> 5423 | AE66: =N66 -> 0 | AF66: =O66 -> 6303.16 | AG66: =P66 -> 6231 | AH66: =Q66 -> 6150 | AI66: =R66 -> 0 | AJ66: =S66 -> 5949 | AK66: =T66 -> 5858 | AL66: =U66 -> 5782 | ... AT66: =AC66 -> 5423
B67: Adjusted RSUs and other contingently issuable shares | C67: =IF($C$6=1,C68*20,C68) -> 0 | D67: =IF($C$6=1,D68*20,D68) -> 0 | E67: =IF($C$6=1,E68*20,E68) -> 0 | F67: =IF($C$6=1,F68*20,F68) -> 0 | G67: =IF($C$6=1,G68*20,G68) -> 0 | H67: =IF($C$6=1,H68*20,H68) -> 0 | I67: =IF($C$6=1,I68*20,I68) -> 0 | K67: =IF($C$6=1,K68*20,K68) -> 176.66 | L67: =IF($C$6=1,L68*20,L68) -> 212.78 | M67: =IF($C$6=1,M68*20,M68) -> 214.94 | N67: =IF($C$6=1,N68*20,N68) -> -604.38 | O67: =IF($C$6=1,O68*20,O68) -> 147.5 | P67: =P68 -> 106 | Q67: =Q68 -> 79 | R67: =R68 -> 0 | S67: =S68 -> 42 | T67: =T68 -> 69 | U67: =U68 -> 115 | V67: =V68 -> 0 | W67: =W68 -> 112 | ... AC67: =AC68 -> 117 | AE67: =N67 -> -604.38 | AF67: =O67 -> 147.5 | AG67: =P67 -> 106 | AH67: =Q67 -> 79 | AI67: =R67 -> 0 | AJ67: =S67 -> 42 | AK67: =T67 -> 69 | AL67: =U67 -> 115 | ... AT67: =AC67 -> 117
B68: RSUs and other contingently issuable shares | K68: 8.833 | L68: 10.639 | M68: 10.747 | N68: =SUM(F68*4)-SUM(K68:M68) -> -30.219 | O68: 7.375 | P68: 106 | Q68: 79 | R68: =G68 -> 0 | S68: 42 | T68: 69 | U68: 115 | V68: =H68 -> 0 | W68: 112 | X68: 152 | Y68: 129 | Z68: =I68 -> 0 | AA68: 108 | AB68: 76 | AC68: 117 | AE68: =N68 -> -30.219 | AF68: =O68 -> 7.375 | AG68: =P68 -> 106 | AH68: =Q68 -> 79 | AI68: =R68 -> 0 | AJ68: =S68 -> 42 | AK68: =T68 -> 69 | AL68: =U68 -> 115 | ... AT68: =AC68 -> 117
B69: Fully Diluted EPS | C69: =C64/C65 -> #DIV/0! | D69: =D64/D65 -> #DIV/0! | E69: =E64/E65 -> #DIV/0! | F69: =F64/F65 -> #DIV/0! | G69: =G64/G65 -> #DIV/0! | H69: =H64/H65 -> #DIV/0! | I69: =I64/I65 -> #DIV/0! | K69: =K64/K65 -> 1.3143498 | L69: =L64/L65 -> 1.3628457 | M69: =M64/M65 -> 1.3995015 | N69: =N64/N65 -> 44.935306 | O69: =O64/O65 -> 1.2310368 | P69: =P64/P65 -> 1.2087739 | Q69: =Q64/Q65 -> 1.0621288 | R69: =R64/R65 -> #DIV/0! | ... AC69: =AC64/AC65 -> 2.8638989 | AE69: =AE64/AE65 -> 0 | AF69: =AF64/AF65 -> -0.13580006 | AG69: =AG64/AG65 -> -0.36357898 | AH69: =AH64/AH65 -> -0.79322524 | AI69: =AI64/AI65 -> #DIV/0! | AJ69: =AJ64/AJ65 -> -0.15172759 | AK69: =AK64/AK65 -> -0.00016871942 | AL69: =AL64/AL65 -> 0.42869256 | ... AT69: =AT64/AT65 -> 1.8962094

Sheet Revenue Drivers
B2: Netflix, Inc. (NASDAQ: NFLX) | C2: FYE | G2: FYE | K2: Quarterly | S2: Quarterly | T2: Quarterly | AA2: LTM | AE2: LTM | AG2: LTM | AM2: Variance
B3: Segment Anaysis | C3: ='Historical Financials'!C7 -> 2018 | D3: ='Historical Financials'!D7 -> 2019 | E3: ='Historical Financials'!E7 -> 2020 | F3: ='Historical Financials'!F7 -> 2021 | G3: ='Historical Financials'!G7 -> 2022 | H3: ='Historical Financials'!H7 -> 2023 | I3: ='Historical Financials'!I7 -> 2024 | K3: ='Historical Financials'!O7 -> 1Q22 | L3: ='Historical Financials'!P7 -> 2Q22 | M3: ='Historical Financials'!Q7 -> 3Q22 | N3: ='Historical Financials'!R7 -> 4Q22 | O3: ='Historical Financials'!S7 -> 1Q23 | P3: ='Historical Financials'!T7 -> 2Q23 | Q3: ='Historical Financials'!U7 -> 3Q23 | R3: ='Historical Financials'!V7 -> 4Q23 | ... Y3: ='Historical Financials'!AC7 -> 3Q25 | AA3: =O3 -> 1Q23 | AB3: =P3 -> 2Q23 | AC3: =Q3 -> 3Q23 | AD3: =R3 -> 4Q23 | AE3: =S3 -> 1Q24 | AF3: =T3 -> 2Q24 | AG3: =U3 -> 3Q24 | AH3: =V3 -> 4Q24 | ... AK3: =Y3 -> 3Q25
B4: $ in thousands except per share | C4: ='Historical Financials'!C8 -> 43465 | D4: ='Historical Financials'!D8 -> 43830 | E4: ='Historical Financials'!E8 -> 44196 | F4: ='Historical Financials'!F8 -> 44561 | G4: ='Historical Financials'!G8 -> 44926 | H4: ='Historical Financials'!H8 -> 45291 | I4: ='Historical Financials'!I8 -> 45657 | K4: ='Historical Financials'!O8 -> 44651 | L4: ='Historical Financials'!P8 -> 44742 | M4: ='Historical Financials'!Q8 -> 44834 | N4: ='Historical Financials'!R8 -> 44926 | O4: ='Historical Financials'!S8 -> 45016 | P4: ='Historical Financials'!T8 -> 45107 | Q4: ='Historical Financials'!U8 -> 45199 | R4: ='Historical Financials'!V8 -> 45291 | ... Y4: ='Historical Financials'!AC8 -> 45930 | AA4: =O4 -> 45016 | AB4: =P4 -> 45107 | AC4: =Q4 -> 45199 | AD4: =R4 -> 45291 | AE4: =S4 -> 45382 | AF4: =T4 -> 45473 | AG4: =U4 -> 45565 | AH4: =V4 -> 45657 | ... AK4: =Y4 -> 45930
A6: X | B6: Offerings Drivers
B8: Disaggregated Revenues
B9: UCAN Revenue | C9: 8281532 | D9: 10051208 | E9: 11455396 | F9: 12972100 | G9: 14084643 | H9: 14873783 | I9: 17359369 | K9: 3350424 | L9: 3537863 | M9: 3601565 | N9: =SUM(G9-SUM(K9:M9)) -> 3594791 | O9: 3608645 | P9: 3599448 | Q9: 3735133 | R9: =SUM(H9-SUM(O9:Q9)) -> 3930557 | S9: 4224315 | T9: 4295560 | U9: 4322476 | V9: =SUM(I9-SUM(S9:U9)) -> 4517018 | W9: 4617098 | X9: 4929003 | Y9: 5071781 | AA9: =SUM(L9:O9) -> 14342864 | AB9: =SUM(M9:P9) -> 14404449 | AC9: =SUM(N9:Q9) -> 14538017 | AD9: =SUM(O9:R9) -> 14873783 | AE9: =SUM(P9:S9) -> 15489453 | AF9: =SUM(Q9:T9) -> 16185565 | AG9: =SUM(R9:U9) -> 16772908 | AH9: =SUM(S9:V9) -> 17359369 | ... AK9: =SUM(V9:Y9) -> 19134900 | AM9: =SUM(AK9/AG9)-1 -> 0.14082185
B10: EMEA Revenue | C10: 3963707 | D10: 5543067 | E10: 7772252 | F10: 9699819 | G10: 9745015 | H10: 10556487 | I10: 12387035 | K10: 2561831 | L10: 2457235 | M10: 2375814 | N10: =SUM(G10-SUM(K10:M10)) -> 2350135 | O10: 2517641 | P10: 2562170 | Q10: 2693146 | R10: =SUM(H10-SUM(O10:Q10)) -> 2783530 | S10: 2958193 | T10: 3007772 | U10: 3133466 | V10: =SUM(I10-SUM(S10:U10)) -> 3287604 | W10: 3404676 | X10: 3538175 | Y10: 3699052 | AG10: =SUM(R10:U10) -> 11882961 | AH10: =SUM(S10:V10) -> 12387035 | AI10: =SUM(T10:W10) -> 12833518 | AJ10: =SUM(U10:X10) -> 13363921 | AK10: =SUM(V10:Y10) -> 13929507 | AM10: =SUM(AK10/AG10)-1 -> 0.17222526
B11: LATAM Revenue | C11: 2237697 | D11: 2795434 | E11: 3156727 | F11: 3576976 | G11: 4069973 | H11: 4446461 | I11: 4839816 | K11: 998948 | L11: 1030234 | M11: 1023945 | N11: =SUM(G11-SUM(K11:M11)) -> 1016846 | O11: 1070192 | P11: 1077435 | Q11: 1142811 | R11: =SUM(H11-SUM(O11:Q11)) -> 1156023 | S11: 1165008 | T11: 1204145 | U11: 1240892 | V11: =SUM(I11-SUM(S11:U11)) -> 1229771 | W11: 1261934 | X11: 1306735 | Y11: 1370913 | AG11: =SUM(R11:U11) -> 4766068 | AH11: =SUM(S11:V11) -> 4839816 | AI11: =SUM(T11:W11) -> 4936742 | AJ11: =SUM(U11:X11) -> 5039332 | AK11: =SUM(V11:Y11) -> 5169353 | AM11: =SUM(AK11/AG11)-1 -> 0.084615872
B12: APAC Revenue | C12: 945816 | D12: 1469521 | E12: 2372300 | F12: 3266601 | G12: 3570221 | H12: 3763727 | I12: 4414746 | K12: 916754 | L12: 907719 | M12: 889037 | N12: =SUM(G12-SUM(K12:M12)) -> 856711 | O12: 933523 | P12: 919273 | Q12: 948216 | R12: =SUM(H12-SUM(O12:Q12)) -> 962715 | S12: 1022924 | T12: 1051833 | U12: 1127869 | V12: =SUM(I12-SUM(S12:U12)) -> 1212120 | W12: 1259093 | X12: 1305253 | Y12: 1368561 | AG12: =SUM(R12:U12) -> 4165341 | AH12: =SUM(S12:V12) -> 4414746 | AI12: =SUM(T12:W12) -> 4650915 | AJ12: =SUM(U12:X12) -> 4904335 | AK12: =SUM(V12:Y12) -> 5145027 | AM12: =SUM(AK12/AG12)-1 -> 0.23519947
B13: Domestic DVD Revenue | C13: 365589 | D13: 297217 | E13: 239381 | F13: 182348 | G13: 145698 | H13: 82839 | I13: 0 | K13: 39810 | L13: 37090 | M13: 35228 | N13: =SUM(G13-SUM(K13:M13)) -> 33570 | O13: 31502 | P13: 28975 | Q13: 22362 | R13: =SUM(H13-SUM(O13:Q13)) -> 0 | S13: 0 | T13: 0 | U13: 0 | V13: =SUM(I13-SUM(S13:U13)) -> 0 | W13: 0 | X13: 0 | Y13: 0 | AG13: =SUM(R13:U13) -> 0 | AH13: =SUM(S13:V13) -> 0 | AI13: =SUM(T13:W13) -> 0 | AJ13: =SUM(U13:X13) -> 0 | AK13: =SUM(V13:Y13) -> 0 | AM13: =SUM(AK13/AG13)-1 -> #DIV/0!
B14: Total Net Revenue | C14: =SUM(C9:C13) -> 15794341 | D14: =SUM(D9:D13) -> 20156447 | E14: =SUM(E9:E13) -> 24996056 | F14: =SUM(F9:F13) -> 29697844 | G14: =SUM(G9:G13) -> 31615550 | H14: =SUM(H9:H13) -> 33723297 | I14: =SUM(I9:I13) -> 39000966 | K14: =SUM(K9:K13) -> 7867767 | L14: =SUM(L9:L13) -> 7970141 | M14: =SUM(M9:M13) -> 7925589 | N14: =SUM(N9:N13) -> 7852053 | O14: =SUM(O9:O13) -> 8161503 | P14: =SUM(P9:P13) -> 8187301 | Q14: =SUM(Q9:Q13) -> 8541668 | R14: =SUM(R9:R13) -> 8832825 | ... Y14: =SUM(Y9:Y13) -> 11510307 | AA14: =SUM(AA9:AA13) -> 14342864 | AB14: =SUM(AB9:AB13) -> 14404449 | AC14: =SUM(AC9:AC13) -> 14538017 | AD14: =SUM(AD9:AD13) -> 14873783 | AE14: =SUM(AE9:AE13) -> 15489453 | AF14: =SUM(AF9:AF13) -> 16185565 | AG14: =SUM(AG9:AG13) -> 37587278 | AH14: =SUM(AH9:AH13) -> 39000966 | ... AK14: =SUM(AK9:AK13) -> 43378787 | AM14: =SUM(AK14/AG14)-1 -> 0.15408163
B15: Variance Check | C15: =+C14-'Historical Financials'!C11 -> 0 | D15: =+D14-'Historical Financials'!D11 -> 0 | E15: =+E14-'Historical Financials'!E11 -> 0 | F15: =+F14-'Historical Financials'!F11 -> 0 | G15: =+G14-'Historical Financials'!G11 -> 0 | H15: =+H14-'Historical Financials'!H11 -> 0 | I15: =+I14-'Historical Financials'!I11 -> 0 | K15: =K14-'Historical Financials'!O11 -> 0 | L15: =L14-'Historical Financials'!P11 -> 0 | M15: =M14-'Historical Financials'!Q11 -> 0 | N15: =N14-'Historical Financials'!R11 -> 0 | O15: =O14-'Historical Financials'!S11 -> 0 | P15: =P14-'Historical Financials'!T11 -> 0 | Q15: =Q14-'Historical Financials'!U11 -> 0 | R15: =R14-'Historical Financials'!V11 -> 0 | ... Y15: =Y14-'Historical Financials'!AC11 -> 0 | AA15: =+AA14-'Historical Financials'!AI11 -> -17566422 | AB15: =+AB14-'Historical Financials'!AJ11 -> -17721997 | AC15: =+AC14-'Historical Financials'!AK11 -> -18204508 | AD15: =+AD14-'Historical Financials'!AL11 -> -18849514 | AE15: =+AE14-'Historical Financials'!AM11 -> -19442781 | AF15: =+AF14-'Historical Financials'!AN11 -> -20118678 | AG15: =+AG14-'Historical Financials'!AO11 -> 0 | AH15: =+AH14-'Historical Financials'!AP11 -> 0 | ... AJ15: =+AJ14-'Historical Financials'!AR11 -> 0 | AK15: =AK14-'Historical Financials'!AS11 -> 0

Sheet FCF
B2: ='Historical Financials'!B2 -> Netflix, Inc. (NASDAQ: NFLX) | C2: FYE | E2: FYE | I2: Quarterly | S2: Quarterly | Y2: LTM | AF2: LTM | AG2: LTM | AM2: Variance
B3: FCF Analysis | C3: ='Historical Financials'!E7 -> 2020 | D3: ='Historical Financials'!F7 -> 2021 | E3: ='Historical Financials'!G7 -> 2022 | F3: ='Historical Financials'!H7 -> 2023 | G3: ='Historical Financials'!I7 -> 2024 | I3: ='Historical Financials'!O7 -> 1Q22 | J3: ='Historical Financials'!P7 -> 2Q22 | K3: ='Historical Financials'!Q7 -> 3Q22 | L3: ='Historical Financials'!R7 -> 4Q22 | M3: ='Historical Financials'!S7 -> 1Q23 | N3: ='Historical Financials'!T7 -> 2Q23 | O3: ='Historical Financials'!U7 -> 3Q23 | P3: ='Historical Financials'!V7 -> 4Q23 | ... W3: ='Historical Financials'!AC7 -> 3Q25 | Y3: =K3 -> 3Q22 | Z3: =L3 -> 4Q22 | AA3: =M3 -> 1Q23 | AB3: =N3 -> 2Q23 | AC3: =O3 -> 3Q23 | AD3: =P3 -> 4Q23 | AE3: =Q3 -> 1Q24 | AF3: =R3 -> 2Q24 | ... AK3: =W3 -> 3Q25
B4: $ mm except per share | C4: ='Historical Financials'!E8 -> 44196 | D4: ='Historical Financials'!F8 -> 44561 | E4: ='Historical Financials'!G8 -> 44926 | F4: ='Historical Financials'!H8 -> 45291 | G4: ='Historical Financials'!I8 -> 45657 | I4: ='Historical Financials'!O8 -> 44651 | J4: ='Historical Financials'!P8 -> 44742 | K4: ='Historical Financials'!Q8 -> 44834 | L4: ='Historical Financials'!R8 -> 44926 | M4: ='Historical Financials'!S8 -> 45016 | N4: ='Historical Financials'!T8 -> 45107 | O4: ='Historical Financials'!U8 -> 45199 | P4: ='Historical Financials'!V8 -> 45291 | ... W4: ='Historical Financials'!AC8 -> 45930 | Y4: =K4 -> 44834 | Z4: =L4 -> 44926 | AA4: =M4 -> 45016 | AB4: =N4 -> 45107 | AC4: =O4 -> 45199 | AD4: =P4 -> 45291 | AE4: =Q4 -> 45382 | AF4: =R4 -> 45473 | ... AK4: =W4 -> 45930
B6: ='Revenue Drivers'!B9 -> UCAN Revenue | C6: =('Revenue Drivers'!E9)/1000 -> 11455.396 | D6: =('Revenue Drivers'!F9)/1000 -> 12972.1 | E6: =('Revenue Drivers'!G9)/1000 -> 14084.643 | F6: =('Revenue Drivers'!H9)/1000 -> 14873.783 | G6: =('Revenue Drivers'!I9)/1000 -> 17359.369 | I6: =('Revenue Drivers'!K9)/1000 -> 3350.424 | J6: =('Revenue Drivers'!L9)/1000 -> 3537.863 | K6: =('Revenue Drivers'!M9)/1000 -> 3601.565 | L6: =('Revenue Drivers'!N9)/1000 -> 3594.791 | M6: =('Revenue Drivers'!O9)/1000 -> 3608.645 | N6: =('Revenue Drivers'!P9)/1000 -> 3599.448 | O6: =('Revenue Drivers'!Q9)/1000 -> 3735.133 | P6: =('Revenue Drivers'!R9)/1000 -> 3930.557 | ... W6: =('Revenue Drivers'!Y9)/1000 -> 5071.781 | Y6: =SUM(H6:K6) -> 10489.852 | Z6: =SUM(I6:L6) -> 14084.643 | AA6: =SUM(J6:M6) -> 14342.864 | AB6: =SUM(K6:N6) -> 14404.449 | AC6: =SUM(L6:O6) -> 14538.017 | AD6: =SUM(M6:P6) -> 14873.783 | AE6: =SUM(N6:Q6) -> 15489.453 | AF6: =SUM(O6:R6) -> 16185.565 | ... AK6: =SUM(T6:W6) -> 19134.9 | AM6: =SUM(AK6/AG6)-1 -> 0.14082185
B7: ='Revenue Drivers'!B10 -> EMEA Revenue | C7: =('Revenue Drivers'!E10)/1000 -> 7772.252 | D7: =('Revenue Drivers'!F10)/1000 -> 9699.819 | E7: =('Revenue Drivers'!G10)/1000 -> 9745.015 | F7: =('Revenue Drivers'!H10)/1000 -> 10556.487 | G7: =('Revenue Drivers'!I10)/1000 -> 12387.035 | I7: =('Revenue Drivers'!K10)/1000 -> 2561.831 | J7: =('Revenue Drivers'!L10)/1000 -> 2457.235 | K7: =('Revenue Drivers'!M10)/1000 -> 2375.814 | L7: =('Revenue Drivers'!N10)/1000 -> 2350.135 | M7: =('Revenue Drivers'!O10)/1000 -> 2517.641 | N7: =('Revenue Drivers'!P10)/1000 -> 2562.17 | O7: =('Revenue Drivers'!Q10)/1000 -> 2693.146 | P7: =('Revenue Drivers'!R10)/1000 -> 2783.53 | ... W7: =('Revenue Drivers'!Y10)/1000 -> 3699.052 | AG7: =SUM(P7:S7) -> 11882.961 | AH7: =SUM(Q7:T7) -> 12387.035 | AI7: =SUM(R7:U7) -> 12833.518 | AJ7: =SUM(S7:V7) -> 13363.921 | AK7: =SUM(T7:W7) -> 13929.507 | AM7: =SUM(AK7/AG7)-1 -> 0.17222526
B8: ='Revenue Drivers'!B11 -> LATAM Revenue | C8: =('Revenue Drivers'!E11)/1000 -> 3156.727 | D8: =('Revenue Drivers'!F11)/1000 -> 3576.976 | E8: =('Revenue Drivers'!G11)/1000 -> 4069.973 | F8: =('Revenue Drivers'!H11)/1000 -> 4446.461 | G8: =('Revenue Drivers'!I11)/1000 -> 4839.816 | I8: =('Revenue Drivers'!K11)/1000 -> 998.948 | J8: =('Revenue Drivers'!L11)/1000 -> 1030.234 | K8: =('Revenue Drivers'!M11)/1000 -> 1023.945 | L8: =('Revenue Drivers'!N11)/1000 -> 1016.846 | M8: =('Revenue Drivers'!O11)/1000 -> 1070.192 | N8: =('Revenue Drivers'!P11)/1000 -> 1077.435 | O8: =('Revenue Drivers'!Q11)/1000 -> 1142.811 | P8: =('Revenue Drivers'!R11)/1000 -> 1156.023 | ... W8: =('Revenue Drivers'!Y11)/1000 -> 1370.913 | AG8: =SUM(P8:S8) -> 4766.068 | AH8: =SUM(Q8:T8) -> 4839.816 | AI8: =SUM(R8:U8) -> 4936.742 | AJ8: =SUM(S8:V8) -> 5039.332 | AK8: =SUM(T8:W8) -> 5169.353 | AM8: =SUM(AK8/AG8)-1 -> 0.084615872
B9: ='Revenue Drivers'!B12 -> APAC Revenue | C9: =('Revenue Drivers'!E12)/1000 -> 2372.3 | D9: =('Revenue Drivers'!F12)/1000 -> 3266.601 | E9: =('Revenue Drivers'!G12)/1000 -> 3570.221 | F9: =('Revenue Drivers'!H12)/1000 -> 3763.727 | G9: =('Revenue Drivers'!I12)/1000 -> 4414.746 | I9: =('Revenue Drivers'!K12)/1000 -> 916.754 | J9: =('Revenue Drivers'!L12)/1000 -> 907.719 | K9: =('Revenue Drivers'!M12)/1000 -> 889.037 | L9: =('Revenue Drivers'!N12)/1000 -> 856.711 | M9: =('Revenue Drivers'!O12)/1000 -> 933.523 | N9: =('Revenue Drivers'!P12)/1000 -> 919.273 | O9: =('Revenue Drivers'!Q12)/1000 -> 948.216 | P9: =('Revenue Drivers'!R12)/1000 -> 962.715 | ... W9: =('Revenue Drivers'!Y12)/1000 -> 1368.561 | AG9: =SUM(P9:S9) -> 4165.341 | AH9: =SUM(Q9:T9) -> 4414.746 | AI9: =SUM(R9:U9) -> 4650.915 | AJ9: =SUM(S9:V9) -> 4904.335 | AK9: =SUM(T9:W9) -> 5145.027 | AM9: =SUM(AK9/AG9)-1 -> 0.23519947
B10: ='Revenue Drivers'!B13 -> Domestic DVD Revenue | C10: =('Revenue Drivers'!E13)/1000 -> 239.381 | D10: =('Revenue Drivers'!F13)/1000 -> 182.348 | E10: =('Revenue Drivers'!G13)/1000 -> 145.698 | F10: =('Revenue Drivers'!H13)/1000 -> 82.839 | G10: =('Revenue Drivers'!I13)/1000 -> 0 | I10: =('Revenue Drivers'!K13)/1000 -> 39.81 | J10: =('Revenue Drivers'!L13)/1000 -> 37.09 | K10: =('Revenue Drivers'!M13)/1000 -> 35.228 | L10: =('Revenue Drivers'!N13)/1000 -> 33.57 | M10: =('Revenue Drivers'!O13)/1000 -> 31.502 | N10: =('Revenue Drivers'!P13)/1000 -> 28.975 | O10: =('Revenue Drivers'!Q13)/1000 -> 22.362 | P10: =('Revenue Drivers'!R13)/1000 -> 0 | ... W10: =('Revenue Drivers'!Y13)/1000 -> 0 | AG10: =SUM(P10:S10) -> 0 | AH10: =SUM(Q10:T10) -> 0 | AI10: =SUM(R10:U10) -> 0 | AJ10: =SUM(S10:V10) -> 0 | AK10: =SUM(T10:W10) -> 0 | AM10: =SUM(AK10/AG10)-1 -> #DIV/0!
B11: Total Revenue | C11: =SUM(C6:C10) -> 24996.056 | D11: =SUM(D6:D10) -> 29697.844 | E11: =SUM(E6:E10) -> 31615.55 | F11: =SUM(F6:F10) -> 33723.297 | G11: =SUM(G6:G10) -> 39000.966 | I11: =SUM(I6:I10) -> 7867.767 | J11: =SUM(J6:J10) -> 7970.141 | K11: =SUM(K6:K10) -> 7925.589 | L11: =SUM(L6:L10) -> 7852.053 | M11: =SUM(M6:M10) -> 8161.503 | N11: =SUM(N6:N10) -> 8187.301 | O11: =SUM(O6:O10) -> 8541.668 | P11: =SUM(P6:P10) -> 8832.825 | ... W11: =SUM(W6:W10) -> 11510.307 | Y11: =SUM(Y6:Y10) -> 10489.852 | Z11: =SUM(Z6:Z10) -> 14084.643 | AA11: =SUM(AA6:AA10) -> 14342.864 | AB11: =SUM(AB6:AB10) -> 14404.449 | AC11: =SUM(AC6:AC10) -> 14538.017 | AD11: =SUM(AD6:AD10) -> 14873.783 | AE11: =SUM(AE6:AE10) -> 15489.453 | AF11: =SUM(AF6:AF10) -> 16185.565 | ... AK11: =SUM(AK6:AK10) -> 43378.787 | AM11: =SUM(AK11/AG11)-1 -> 0.15408163
B12: Y/Y Growth (%) | D12: =SUM(D11/C11)-1 -> 0.18810119 | E12: =SUM(E11/D11)-1 -> 0.064573913 | F12: =SUM(F11/E11)-1 -> 0.066668048 | G12: =SUM(G11/F11)-1 -> 0.1564992 | M12: =SUM(M11/I11)-1 -> 0.0373341 | N12: =SUM(N11/J11)-1 -> 0.027246695 | O12: =SUM(O11/K11)-1 -> 0.077732898 | P12: =SUM(P11/L11)-1 -> 0.12490644 | Q12: =SUM(Q11/M11)-1 -> 0.14812676 | R12: =SUM(R11/N11)-1 -> 0.16757769 | S12: =SUM(S11/O11)-1 -> 0.15020895 | T12: =SUM(T11/P11)-1 -> 0.16004936 | ... W12: =SUM(W11/S11)-1 -> 0.17156793 | AC12: =SUM(AC11/Y11)-1 -> 0.3859125 | AD12: =SUM(AD11/Z11)-1 -> 0.056028399 | AE12: =SUM(AE11/AA11)-1 -> 0.079941426 | AF12: =SUM(AF11/AB11)-1 -> 0.12365041 | AG12: =SUM(AG11/AC11)-1 -> 1.5854474 | AH12: =SUM(AH11/AD11)-1 -> 1.6221282 | AI12: =SUM(AI11/AE11)-1 -> 1.5935924 | AJ12: =SUM(AJ11/AF11)-1 -> 1.5759486 | AK12: =SUM(AK11/AG11)-1 -> 0.15408163 | AM12: =SUM(AK12-AG12)*10000 -> -14313.658
B13: Q/Q Growth (%) | C13: N/A | D13: N/A | E13: N/A | F13: N/A | G13: N/A | J13: =SUM(J11/I11)-1 -> 0.013011824 | K13: =SUM(K11/J11)-1 -> -0.0055898635 | L13: =SUM(L11/K11)-1 -> -0.009278301 | M13: =SUM(M11/L11)-1 -> 0.039410075 | N13: =SUM(N11/M11)-1 -> 0.0031609374 | O13: =SUM(O11/N11)-1 -> 0.043282518 | P13: =SUM(P11/O11)-1 -> 0.034086668 | Q13: =SUM(Q11/P11)-1 -> 0.060865578 | ... W13: =SUM(W11/V11)-1 -> 0.038914572 | Y13: N/A | Z13: N/A | AA13: N/A | AB13: N/A | AC13: N/A | AD13: N/A | AE13: N/A | AF13: N/A | AG13: N/A | AH13: N/A | AI13: N/A | AJ13: N/A | AK13: N/A
B15: (-) Amortization of content assets | C15: =('Historical Financials'!E13)/1000 -> -10806.912 | D15: =('Historical Financials'!F13)/1000 -> -12230.367 | E15: =('Historical Financials'!G13)/1000 -> -14026.132 | F15: =('Historical Financials'!H13)/1000 -> -14197.437 | G15: =('Historical Financials'!I13)/1000 -> -15301.517 | I15: =('Historical Financials'!O13)/1000 -> -3166.365 | J15: =('Historical Financials'!P13)/1000 -> -3261.348 | K15: =('Historical Financials'!Q13)/1000 -> -3653.592 | L15: =('Historical Financials'!R13)/1000 -> -3944.827 | M15: =('Historical Financials'!S13)/1000 -> -3459.984 | N15: =('Historical Financials'!T13)/1000 -> -3410.021 | O15: =('Historical Financials'!U13)/1000 -> -3573.353 | P15: =('Historical Financials'!V13)/1000 -> -3754.079 | ... W15: =('Historical Financials'!AC13)/1000 -> -4002.744 | Y15: =SUM(H15:K15) -> -10081.305 | Z15: =SUM(I15:L15) -> -14026.132 | AA15: =SUM(J15:M15) -> -14319.751 | AB15: =SUM(K15:N15) -> -14468.424 | AC15: =SUM(L15:O15) -> -14388.185 | AD15: =SUM(M15:P15) -> -14197.437 | AE15: =SUM(N15:Q15) -> -14408.258 | AF15: =SUM(O15:R15) -> -14767.927 | ... AK15: =SUM(T15:W15) -> -15819.431 | AM15: =SUM(AK15/AG15)-1 -> 0.062127709
B16: (-) Other Cost of Revenues | C16: =('Historical Financials'!E14)/1000 -> -4469.407 | D16: =('Historical Financials'!F14)/1000 -> -5102.316 | E16: =('Historical Financials'!G14)/1000 -> -5142.153 | F16: =('Historical Financials'!H14)/1000 -> -5517.931 | G16: =('Historical Financials'!I14)/1000 -> -5736.947 | I16: =('Historical Financials'!O14)/1000 -> -1118.34 | J16: =('Historical Financials'!P14)/1000 -> -1429.407 | K16: =('Historical Financials'!Q14)/1000 -> -1135.073 | L16: =('Historical Financials'!R14)/1000 -> -1459.333 | M16: =('Historical Financials'!S14)/1000 -> -1343.641 | N16: =('Historical Financials'!T14)/1000 -> -1263.449 | O16: =('Historical Financials'!U14)/1000 -> -1357.435 | P16: =('Historical Financials'!V14)/1000 -> -1553.406 | ... W16: =('Historical Financials'!AC14)/1000 -> -2161.506 | AG16: =SUM(P16:S16) -> -5684.49 | AH16: =SUM(Q16:T16) -> -5736.947 | AI16: =SUM(R16:U16) -> -5870.714 | AJ16: =SUM(S16:V16) -> -5959.498 | AK16: =SUM(T16:W16) -> -6700.641
B17: Gross Profit | C17: =SUM(C11+SUM(C15:C16)) -> 9719.737 | D17: =SUM(D11+SUM(D15:D16)) -> 12365.161 | E17: =SUM(E11+SUM(E15:E16)) -> 12447.265 | F17: =SUM(F11+SUM(F15:F16)) -> 14007.929 | G17: =SUM(G11+SUM(G15:G16)) -> 17962.502 | I17: =SUM(I11+SUM(I15:I16)) -> 3583.062 | J17: =SUM(J11+SUM(J15:J16)) -> 3279.386 | K17: =SUM(K11+SUM(K15:K16)) -> 3136.924 | L17: =SUM(L11+SUM(L15:L16)) -> 2447.893 | M17: =SUM(M11+SUM(M15:M16)) -> 3357.878 | N17: =SUM(N11+SUM(N15:N16)) -> 3513.831 | O17: =SUM(O11+SUM(O15:O16)) -> 3610.88 | P17: =SUM(P11+SUM(P15:P16)) -> 3525.34 | ... W17: =SUM(W11+SUM(W15:W16)) -> 5346.057 | Y17: =SUM(Y11+SUM(Y15:Y16)) -> 408.547 | Z17: =SUM(Z11+SUM(Z15:Z16)) -> 58.511 | AA17: =SUM(AA11+SUM(AA15:AA16)) -> 23.113 | AB17: =SUM(AB11+SUM(AB15:AB16)) -> -63.975 | AC17: =SUM(AC11+SUM(AC15:AC16)) -> 149.832 | AD17: =SUM(AD11+SUM(AD15:AD16)) -> 676.346 | AE17: =SUM(AE11+SUM(AE15:AE16)) -> 1081.195 | AF17: =SUM(AF11+SUM(AF15:AF16)) -> 1417.638 | ... AK17: =SUM(AK11+SUM(AK15:AK16)) -> 20858.715 | AM17: =SUM(AK17/AG17)-1 -> 0.22635613
B18: Gross Margin (%) | C18: =C17/C11 -> 0.38885083 | D18: =D17/D11 -> 0.41636561 | E18: =E17/E11 -> 0.39370705 | F18: =F17/F11 -> 0.4153784 | G18: =G17/G11 -> 0.46056557 | I18: =I17/I11 -> 0.45541028 | J18: =J17/J11 -> 0.41145897 | K18: =K17/K11 -> 0.39579696 | L18: =L17/L11 -> 0.31175197 | M18: =M17/M11 -> 0.41142888 | N18: =N17/N11 -> 0.42918063 | O18: =O17/O11 -> 0.4227371 | P18: =P17/P11 -> 0.39911806 | ... W18: =W17/W11 -> 0.46445825 | Y18: =Y17/Y11 -> 0.038946879 | Z18: =Z17/Z11 -> 0.0041542409 | AA18: =AA17/AA11 -> 0.0016114634 | AB18: =AB17/AB11 -> -0.0044413361 | AC18: =AC17/AC11 -> 0.01030622 | AD18: =AD17/AD11 -> 0.045472359 | AE18: =AE17/AE11 -> 0.069802013 | AF18: =AF17/AF11 -> 0.087586562 | ... AK18: =AK17/AK11 -> 0.48085058 | AM18: =SUM(AK18-AG18)*10000 -> 283.38618
B20: (-) Marketing | C20: =('Historical Financials'!E19)/1000 -> -2228.362 | D20: =('Historical Financials'!F19)/1000 -> -2545.146 | E20: =('Historical Financials'!G19)/1000 -> -2530.502 | F20: =('Historical Financials'!H19)/1000 -> -2657.883 | G20: =('Historical Financials'!I19)/1000 -> -2917.554 | I20: =('Historical Financials'!O19)/1000 -> -555.978 | J20: =('Historical Financials'!P19)/1000 -> -574.96 | K20: =('Historical Financials'!Q19)/1000 -> -567.954 | L20: =('Historical Financials'!R19)/1000 -> -831.61 | M20: =('Historical Financials'!S19)/1000 -> -555.362 | N20: =('Historical Financials'!T19)/1000 -> -627.168 | O20: =('Historical Financials'!U19)/1000 -> -558.736 | P20: =('Historical Financials'!V19)/1000 -> -916.617 | ... W20: =('Historical Financials'!AC19)/1000 -> -786.295 | Y20: =SUM(H20:K20) -> -1698.892 | Z20: =SUM(I20:L20) -> -2530.502 | AA20: =SUM(J20:M20) -> -2529.886 | AB20: =SUM(K20:N20) -> -2582.094 | AC20: =SUM(L20:O20) -> -2572.876 | AD20: =SUM(M20:P20) -> -2657.883 | AE20: =SUM(N20:Q20) -> -2756.861 | AF20: =SUM(O20:R20) -> -2773.777 | ... AK20: =SUM(T20:W20) -> -3164.134 | AM20: =SUM(AK20/AG20)-1 -> 0.10712755
B21: (-) Technology and Development (T&D) | C21: =('Historical Financials'!E20)/1000 -> -1829.6 | D21: =('Historical Financials'!F20)/1000 -> -2273.885 | E21: =('Historical Financials'!G20)/1000 -> -2711.041 | F21: =('Historical Financials'!H20)/1000 -> -2675.758 | G21: =('Historical Financials'!I20)/1000 -> -2925.295 | I21: =('Historical Financials'!O20)/1000 -> -657.53 | J21: =('Historical Financials'!P20)/1000 -> -716.846 | K21: =('Historical Financials'!Q20)/1000 -> -662.739 | L21: =('Historical Financials'!R20)/1000 -> -673.926 | M21: =('Historical Financials'!S20)/1000 -> -687.275 | N21: =('Historical Financials'!T20)/1000 -> -657.983 | O21: =('Historical Financials'!U20)/1000 -> -657.159 | P21: =('Historical Financials'!V20)/1000 -> -673.341 | ... W21: =('Historical Financials'!AC20)/1000 -> -853.584 | Y21: =SUM(H21:K21) -> -2037.115 | Z21: =SUM(I21:L21) -> -2711.041 | AA21: =SUM(J21:M21) -> -2740.786 | AB21: =SUM(K21:N21) -> -2681.923 | AC21: =SUM(L21:O21) -> -2676.343 | AD21: =SUM(M21:P21) -> -2675.758 | AE21: =SUM(N21:Q21) -> -2690.956 | AF21: =SUM(O21:R21) -> -2744.227 | ... AK21: =SUM(T21:W21) -> -3277.595 | AM21: =SUM(AK21/AG21)-1 -> 0.1613901
B22: (-) General and Administrative (G&A) | C22: =('Historical Financials'!E21)/1000 -> -1076.486 | D22: =('Historical Financials'!F21)/1000 -> -1351.621 | E22: =('Historical Financials'!G21)/1000 -> -1572.891 | F22: =('Historical Financials'!H21)/1000 -> -1720.285 | G22: =('Historical Financials'!I21)/1000 -> -1702.039 | I22: =('Historical Financials'!O21)/1000 -> -397.928 | J22: =('Historical Financials'!P21)/1000 -> -409.297 | K22: =('Historical Financials'!Q21)/1000 -> -373.213 | L22: =('Historical Financials'!R21)/1000 -> -392.453 | M22: =('Historical Financials'!S21)/1000 -> -400.924 | N22: =('Historical Financials'!T21)/1000 -> -401.497 | O22: =('Historical Financials'!U21)/1000 -> -478.591 | P22: =('Historical Financials'!V21)/1000 -> -439.273 | ... W22: =('Historical Financials'!AC21)/1000 -> -457.931 | Y22: =SUM(H22:K22) -> -1180.438 | Z22: =SUM(I22:L22) -> -1572.891 | AA22: =SUM(J22:M22) -> -1575.887 | AB22: =SUM(K22:N22) -> -1568.087 | AC22: =SUM(L22:O22) -> -1673.465 | AD22: =SUM(M22:P22) -> -1720.285 | AE22: =SUM(N22:Q22) -> -1723.381 | AF22: =SUM(O22:R22) -> -1748.876 | ... AK22: =SUM(T22:W22) -> -1774.28 | AM22: =SUM(AK22/AG22)-1 -> 0.051339209
B23: Earning before Interest & Taxes (EBIT) | C23: =SUM(C17+SUM(C20:C22)) -> 4585.289 | D23: =SUM(D17+SUM(D20:D22)) -> 6194.509 | E23: =SUM(E17+SUM(E20:E22)) -> 5632.831 | F23: =SUM(F17+SUM(F20:F22)) -> 6954.003 | G23: =SUM(G17+SUM(G20:G22)) -> 10417.614 | I23: =SUM(I17+SUM(I20:I22)) -> 1971.626 | J23: =SUM(J17+SUM(J20:J22)) -> 1578.283 | K23: =SUM(K17+SUM(K20:K22)) -> 1533.018 | L23: =SUM(L17+SUM(L20:L22)) -> 549.904 | M23: =SUM(M17+SUM(M20:M22)) -> 1714.317 | N23: =SUM(N17+SUM(N20:N22)) -> 1827.183 | O23: =SUM(O17+SUM(O20:O22)) -> 1916.394 | P23: =SUM(P17+SUM(P20:P22)) -> 1496.109 | ... W23: =SUM(W17+SUM(W20:W22)) -> 3248.247 | Y23: =SUM(Y17+SUM(Y20:Y22)) -> -4507.898 | Z23: =SUM(Z17+SUM(Z20:Z22)) -> -6755.923 | AA23: =SUM(AA17+SUM(AA20:AA22)) -> -6823.446 | AB23: =SUM(AB17+SUM(AB20:AB22)) -> -6896.079 | AC23: =SUM(AC17+SUM(AC20:AC22)) -> -6772.852 | AD23: =SUM(AD17+SUM(AD20:AD22)) -> -6377.58 | AE23: =SUM(AE17+SUM(AE20:AE22)) -> -6090.003 | AF23: =SUM(AF17+SUM(AF20:AF22)) -> -5849.242 | ... AK23: =SUM(AK17+SUM(AK20:AK22)) -> 12642.706 | AM23: =SUM(AK23/AG23)-1 -> 0.31135384
B24: Operating Margin (%) | C24: =C23/C11 -> 0.1834405 | D24: =D23/D11 -> 0.20858447 | E24: =E23/E11 -> 0.17816647 | F24: =F23/F11 -> 0.20620768 | G24: =G23/G11 -> 0.26711169 | I24: =I23/I11 -> 0.25059537 | J24: =J23/J11 -> 0.19802448 | K24: =K23/K11 -> 0.19342638 | L24: =L23/L11 -> 0.070033149 | M24: =M23/M11 -> 0.21004918 | N24: =N23/N11 -> 0.22317281 | O24: =O23/O11 -> 0.22435829 | P24: =P23/P11 -> 0.16938058 | ... W24: =W23/W11 -> 0.28220333 | Y24: =Y23/Y11 -> -0.42973895 | Z24: =Z23/Z11 -> -0.4796659 | AA24: =AA23/AA11 -> -0.47573804 | AB24: =AB23/AB11 -> -0.47874646 | AC24: =AC23/AC11 -> -0.46587179 | AD24: =AD23/AD11 -> -0.42877995 | AE24: =AE23/AE11 -> -0.39317095 | AF24: =AF23/AF11 -> -0.36138633 | ... AK24: =AK23/AK11 -> 0.29144904 | AM24: =SUM(AK24-AG24)*10000 -> 349.53828
B26: (+) Depreciation and amortization of PP&E and intangibles | C26: =('Historical Financials'!E89)/1000 -> 115.71 | D26: =('Historical Financials'!F89)/1000 -> 208.412 | E26: =('Historical Financials'!G89)/1000 -> 336.682 | F26: =('Historical Financials'!H89)/1000 -> 356.947 | G26: =('Historical Financials'!I89)/1000 -> 328.914 | I26: =('Historical Financials'!O89)/1000 -> 74.602 | J26: =('Historical Financials'!P89)/1000 -> 83.505 | K26: =('Historical Financials'!Q89)/1000 -> 85.188 | L26: =('Historical Financials'!R89)/1000 -> 93.387 | M26: =('Historical Financials'!S89)/1000 -> 90.335 | N26: =('Historical Financials'!T89)/1000 -> 89.385 | O26: =('Historical Financials'!U89)/1000 -> 90.66 | P26: =('Historical Financials'!V89)/1000 -> 86.567 | ... W26: =('Historical Financials'!AC89)/1000 -> 87.326 | Y26: =SUM(H26:K26) -> 243.295 | Z26: =SUM(I26:L26) -> 336.682 | AA26: =SUM(J26:M26) -> 352.415 | AB26: =SUM(K26:N26) -> 358.295 | AC26: =SUM(L26:O26) -> 363.767 | AD26: =SUM(M26:P26) -> 356.947 | AE26: =SUM(N26:Q26) -> 353.846 | AF26: =SUM(O26:R26) -> 345.688 | ... AK26: =SUM(T26:W26) -> 326.945 | AM26: =SUM(AK26/AG26)-1 -> -0.026781409
B27: (+) Amortization of content assets | C27: =-C15 -> 10806.912 | D27: =-D15 -> 12230.367 | E27: =-E15 -> 14026.132 | F27: =-F15 -> 14197.437 | G27: =-G15 -> 15301.517 | I27: =-I15 -> 3166.365 | J27: =-J15 -> 3261.348 | K27: =-K15 -> 3653.592 | L27: =-L15 -> 3944.827 | M27: =-M15 -> 3459.984 | N27: =-N15 -> 3410.021 | O27: =-O15 -> 3573.353 | P27: =-P15 -> 3754.079 | ... W27: =-W15 -> 4002.744 | Y27: =-Y15 -> 10081.305 | Z27: =-Z15 -> 14026.132 | AA27: =-AA15 -> 14319.751 | AB27: =-AB15 -> 14468.424 | AC27: =-AC15 -> 14388.185 | AD27: =-AD15 -> 14197.437 | AE27: =-AE15 -> 14408.258 | AF27: =-AF15 -> 14767.927 | ... AK27: =-AK15 -> 15819.431
B28: EBITDA | C28: =SUM(C23+SUM(C26:C27)) -> 15507.911 | D28: =SUM(D23+SUM(D26:D27)) -> 18633.288 | E28: =SUM(E23+SUM(E26:E27)) -> 19995.645 | F28: =SUM(F23+SUM(F26:F27)) -> 21508.387 | G28: =SUM(G23+SUM(G26:G27)) -> 26048.045 | I28: =SUM(I23+SUM(I26:I27)) -> 5212.593 | J28: =SUM(J23+SUM(J26:J27)) -> 4923.136 | K28: =SUM(K23+SUM(K26:K27)) -> 5271.798 | L28: =SUM(L23+SUM(L26:L27)) -> 4588.118 | M28: =SUM(M23+SUM(M26:M27)) -> 5264.636 | N28: =SUM(N23+SUM(N26:N27)) -> 5326.589 | O28: =SUM(O23+SUM(O26:O27)) -> 5580.407 | P28: =SUM(P23+SUM(P26:P27)) -> 5336.755 | ... W28: =SUM(W23+SUM(W26:W27)) -> 7338.317 | Y28: =SUM(Y23+SUM(Y26:Y27)) -> 5816.702 | Z28: =SUM(Z23+SUM(Z26:Z27)) -> 7606.891 | AA28: =SUM(AA23+SUM(AA26:AA27)) -> 7848.72 | AB28: =SUM(AB23+SUM(AB26:AB27)) -> 7930.64 | AC28: =SUM(AC23+SUM(AC26:AC27)) -> 7979.1 | AD28: =SUM(AD23+SUM(AD26:AD27)) -> 8176.804 | AE28: =SUM(AE23+SUM(AE26:AE27)) -> 8672.101 | AF28: =SUM(AF23+SUM(AF26:AF27)) -> 9264.373 | ... AK28: =SUM(AK23+SUM(AK26:AK27)) -> 28789.082 | AM28: =SUM(AK28/AG28)-1 -> 0.15753645
B29: EBITDA Margin (%) | C29: =C28/C11 -> 0.62041432 | D29: =D28/D11 -> 0.62742898 | E29: =E28/E11 -> 0.63246235 | F29: =F28/F11 -> 0.63779016 | G29: =G28/G11 -> 0.66788205 | I29: =I28/I11 -> 0.66252508 | J29: =J28/J11 -> 0.61769748 | K29: =K28/K11 -> 0.66516167 | L29: =L28/L11 -> 0.58432081 | M29: =M28/M11 -> 0.64505717 | N29: =N28/N11 -> 0.65059157 | O29: =O28/O11 -> 0.65331584 | P29: =P28/P11 -> 0.60419571 | ... W29: =W28/W11 -> 0.63754312 | Y29: =Y28/Y11 -> 0.55450754 | Z29: =Z28/Z11 -> 0.54008405 | AA29: =AA28/AA11 -> 0.54722125 | AB29: =AB28/AB11 -> 0.55056879 | AC29: =AC28/AC11 -> 0.54884377 | AD29: =AD28/AD11 -> 0.54974609 | AE29: =AE28/AE11 -> 0.55987135 | AF29: =AF28/AF11 -> 0.5723849 | ... AK29: =AK28/AK11 -> 0.66366729 | AM29: =SUM(AK29-AG29)*10000 -> 19.80801
B31: (+) Share-based Compensation | C31: =('Historical Financials'!E90)/1000 -> 415.18 | D31: =('Historical Financials'!F90)/1000 -> 403.22 | E31: =('Historical Financials'!G90)/1000 -> 575.452 | F31: =('Historical Financials'!H90)/1000 -> 339.368 | G31: =('Historical Financials'!I90)/1000 -> 272.588 | I31: =('Historical Financials'!O90)/1000 -> 119.209 | J31: =('Historical Financials'!P90)/1000 -> 150.392 | K31: =('Historical Financials'!Q90)/1000 -> 152.062 | L31: =('Historical Financials'!R90)/1000 -> 153.789 | M31: =('Historical Financials'!S90)/1000 -> 99.099 | N31: =('Historical Financials'!T90)/1000 -> 78.03 | O31: =('Historical Financials'!U90)/1000 -> 79.72 | P31: =('Historical Financials'!V90)/1000 -> 82.519 | ... W31: =('Historical Financials'!AC90)/1000 -> 80.986 | Y31: =SUM(H31:K31) -> 421.663 | Z31: =SUM(I31:L31) -> 575.452 | AA31: =SUM(J31:M31) -> 555.342 | AB31: =SUM(K31:N31) -> 482.98 | AC31: =SUM(L31:O31) -> 410.638 | AD31: =SUM(M31:P31) -> 339.368 | AE31: =SUM(N31:Q31) -> 316.614 | AF31: =SUM(O31:R31) -> 307.35 | ... AK31: =SUM(T31:W31) -> 295.652 | AM31: =SUM(AK31/AG31)-1 -> 0.0080878342
B32: Adj. EBITDA | C32: =+SUM(C28+SUM(C31:C31)) -> 15923.091 | D32: =+SUM(D28+SUM(D31:D31)) -> 19036.508 | E32: =+SUM(E28+SUM(E31:E31)) -> 20571.097 | F32: =+SUM(F28+SUM(F31:F31)) -> 21847.755 | G32: =+SUM(G28+SUM(G31:G31)) -> 26320.633 | I32: =+SUM(I28+SUM(I31:I31)) -> 5331.802 | J32: =+SUM(J28+SUM(J31:J31)) -> 5073.528 | K32: =+SUM(K28+SUM(K31:K31)) -> 5423.86 | L32: =+SUM(L28+SUM(L31:L31)) -> 4741.907 | M32: =+SUM(M28+SUM(M31:M31)) -> 5363.735 | N32: =+SUM(N28+SUM(N31:N31)) -> 5404.619 | O32: =+SUM(O28+SUM(O31:O31)) -> 5660.127 | P32: =+SUM(P28+SUM(P31:P31)) -> 5419.274 | ... W32: =+SUM(W28+SUM(W31:W31)) -> 7419.303 | Y32: =+SUM(Y28+SUM(Y31:Y31)) -> 6238.365 | Z32: =+SUM(Z28+SUM(Z31:Z31)) -> 8182.343 | AA32: =+SUM(AA28+SUM(AA31:AA31)) -> 8404.062 | AB32: =+SUM(AB28+SUM(AB31:AB31)) -> 8413.62 | AC32: =+SUM(AC28+SUM(AC31:AC31)) -> 8389.738 | AD32: =+SUM(AD28+SUM(AD31:AD31)) -> 8516.172 | AE32: =+SUM(AE28+SUM(AE31:AE31)) -> 8988.715 | AF32: =+SUM(AF28+SUM(AF31:AF31)) -> 9571.723 | ... AK32: =+SUM(AK28+SUM(AK31:AK31)) -> 29084.734 | AM32: =SUM(AK32/AG32)-1 -> 0.15579468
B33: Adj. EBITDA Margin (%) | C33: =C32/C11 -> 0.63702414 | D33: =D32/D11 -> 0.6410064 | E33: =E32/E11 -> 0.6506639 | F33: =F32/F11 -> 0.64785347 | G33: =G32/G11 -> 0.67487131 | I33: =I32/I11 -> 0.67767665 | J33: =J32/J11 -> 0.63656691 | K33: =K32/K11 -> 0.68434788 | L33: =L32/L11 -> 0.60390665 | M33: =M32/M11 -> 0.65719942 | N33: =N32/N11 -> 0.66012218 | O33: =O32/O11 -> 0.66264891 | P33: =P32/P11 -> 0.61353802 | ... W33: =W32/W11 -> 0.64457907 | Y33: =Y32/Y11 -> 0.59470477 | Z33: =Z32/Z11 -> 0.58094075 | AA33: =AA32/AA11 -> 0.5859403 | AB33: =AB32/AB11 -> 0.5840987 | AC33: =AC32/AC11 -> 0.57708957 | AD33: =AD32/AD11 -> 0.57256261 | AE33: =AE32/AE11 -> 0.58031197 | AF33: =AF32/AF11 -> 0.59137404 | ... AK33: =AK32/AK11 -> 0.67048288 | AM33: =SUM(AK33-AG33)*10000 -> 9.9375037
B35: (-) Capital Expenditures | C35: =('Historical Financials'!E103)/1000 -> -497.923 | D35: =('Historical Financials'!F103)/1000 -> -524.585 | E35: =('Historical Financials'!G103)/1000 -> -407.729 | F35: =('Historical Financials'!H103)/1000 -> -348.552 | G35: =('Historical Financials'!I103)/1000 -> -439.538 | I35: =('Historical Financials'!O103)/1000 -> -121.158 | J35: =('Historical Financials'!P103)/1000 -> -90.018 | K35: =('Historical Financials'!Q103)/1000 -> -84.96 | L35: =('Historical Financials'!R103)/1000 -> -111.593 | M35: =('Historical Financials'!S103)/1000 -> -62.019 | N35: =('Historical Financials'!T103)/1000 -> -100.972 | O35: =('Historical Financials'!U103)/1000 -> -103.929 | P35: =('Historical Financials'!V103)/1000 -> -81.632 | ... W35: =('Historical Financials'!AC103)/1000 -> -164.719 | Y35: =SUM(H35:K35) -> -296.136 | Z35: =SUM(I35:L35) -> -407.729 | AA35: =SUM(J35:M35) -> -348.59 | AB35: =SUM(K35:N35) -> -359.544 | AC35: =SUM(L35:O35) -> -378.513 | AD35: =SUM(M35:P35) -> -348.552 | AE35: =SUM(N35:Q35) -> -362.247 | AF35: =SUM(O35:R35) -> -339.562 | ... AK35: =SUM(T35:W35) -> -607.559 | AM35: =SUM(AK35/AG35)-1 -> 0.67604332
B36: (-) Cash Taxes | C36: =-('Historical Financials'!E133)/1000 -> -291.582 | D36: =-('Historical Financials'!F133)/1000 -> -509.265 | E36: =-('Historical Financials'!G133)/1000 -> -811.72 | F36: =-('Historical Financials'!H133)/1000 -> -1154.973 | G36: =-('Historical Financials'!I133)/1000 -> -1641.53 | I36: =('Historical Financials'!O31)/1000 -> -382.245 | J36: =('Historical Financials'!P31)/1000 -> -182.103 | K36: =('Historical Financials'!Q31)/1000 -> -223.605 | L36: =('Historical Financials'!R31)/1000 -> 15.948 | M36: =('Historical Financials'!S31)/1000 -> -163.754 | N36: =('Historical Financials'!T31)/1000 -> -191.722 | O36: =('Historical Financials'!U31)/1000 -> -231.627 | P36: =('Historical Financials'!V31)/1000 -> -210.312 | ... W36: =('Historical Financials'!AC31)/1000 -> -562.494 | Y36: =SUM(H36:K36) -> -787.953 | Z36: =SUM(I36:L36) -> -772.005 | AA36: =SUM(J36:M36) -> -553.514 | AB36: =SUM(K36:N36) -> -563.133 | AC36: =SUM(L36:O36) -> -571.155 | AD36: =SUM(M36:P36) -> -797.415 | AE36: =SUM(N36:Q36) -> -916.031 | AF36: =SUM(O36:R36) -> -1090.859 | ... AK36: =SUM(T36:W36) -> -1657.792 | AM36: =SUM(AK36/AG36)-1 -> 0.38301811
B37: (-) Cash Interest | C37: =-('Historical Financials'!E134)/1000 -> -762.904 | D37: =-('Historical Financials'!F134)/1000 -> -763.432 | E37: =-('Historical Financials'!G134)/1000 -> -701.693 | F37: =-('Historical Financials'!H134)/1000 -> -684.504 | G37: =-('Historical Financials'!I134)/1000 -> -674.502 | I37: =('Historical Financials'!O26)/1000 -> -187.579 | J37: =('Historical Financials'!P26)/1000 -> -175.455 | K37: =('Historical Financials'!Q26)/1000 -> -172.575 | L37: =('Historical Financials'!R26)/1000 -> -170.603 | M37: =('Historical Financials'!S26)/1000 -> -174.239 | N37: =('Historical Financials'!T26)/1000 -> -174.812 | O37: =('Historical Financials'!U26)/1000 -> -175.563 | P37: =('Historical Financials'!V26)/1000 -> -175.212 | ... W37: =('Historical Financials'!AC26)/1000 -> -175.294 | Y37: =SUM(H37:K37) -> -535.609 | Z37: =SUM(I37:L37) -> -706.212 | AA37: =SUM(J37:M37) -> -692.872 | AB37: =SUM(K37:N37) -> -692.229 | AC37: =SUM(L37:O37) -> -695.217 | AD37: =SUM(M37:P37) -> -699.826 | AE37: =SUM(N37:Q37) -> -698.901 | AF37: =SUM(O37:R37) -> -692.075 | ... AK37: =SUM(T37:W37) -> -734.718 | AM37: =SUM(AK37/AG37)-1 -> 0.047588766
B38: (+/-) Changes in NWC | C38: =SUM('Historical Financials'!E95:E99)/1000 -> -31.873 | D38: =SUM('Historical Financials'!F95:F99)/1000 -> -241.977 | E38: =SUM('Historical Financials'!G95:G99)/1000 -> -758.087 | F38: =SUM('Historical Financials'!H95:H99)/1000 -> -116.148 | G38: =SUM('Historical Financials'!I95:I99)/1000 -> -33.075 | I38: =SUM('Historical Financials'!O95:O99)/1000 -> 25.288 | J38: =SUM('Historical Financials'!P95:P99)/1000 -> -122.704 | K38: =SUM('Historical Financials'!Q95:Q99)/1000 -> 93.272 | L38: =SUM('Historical Financials'!R95:R99)/1000 -> -753.943 | M38: =SUM('Historical Financials'!S95:S99)/1000 -> -64.218 | N38: =SUM('Historical Financials'!T95:T99)/1000 -> -35.189 | O38: =SUM('Historical Financials'!U95:U99)/1000 -> -75.745 | P38: =SUM('Historical Financials'!V95:V99)/1000 -> 59.004 | ... W38: =SUM('Historical Financials'!AC95:AC99)/1000 -> 575.75 | Y38: =SUM(H38:K38) -> -4.144 | Z38: =SUM(I38:L38) -> -758.087 | AA38: =SUM(J38:M38) -> -847.593 | AB38: =SUM(K38:N38) -> -760.078 | AC38: =SUM(L38:O38) -> -929.095 | AD38: =SUM(M38:P38) -> -116.148 | AE38: =SUM(N38:Q38) -> 53.104 | AF38: =SUM(O38:R38) -> -158.934 | ... AK38: =SUM(T38:W38) -> -274.319 | AM38: =SUM(AK38/AG38)-1 -> -3.845928
B39: Discretionary Cash-Flows | C39: =SUM(C32+SUM(C35:C38)) -> 14338.809 | D39: =SUM(D32+SUM(D35:D38)) -> 16997.249 | E39: =SUM(E32+SUM(E35:E38)) -> 17891.868 | F39: =SUM(F32+SUM(F35:F38)) -> 19543.578 | G39: =SUM(G32+SUM(G35:G38)) -> 23531.988 | I39: =SUM(I32+SUM(I35:I38)) -> 4666.108 | J39: =SUM(J32+SUM(J35:J38)) -> 4503.248 | K39: =SUM(K32+SUM(K35:K38)) -> 5035.992 | L39: =SUM(L32+SUM(L35:L38)) -> 3721.716 | M39: =SUM(M32+SUM(M35:M38)) -> 4899.505 | N39: =SUM(N32+SUM(N35:N38)) -> 4901.924 | O39: =SUM(O32+SUM(O35:O38)) -> 5073.263 | P39: =SUM(P32+SUM(P35:P38)) -> 5011.122 | ... W39: =SUM(W32+SUM(W35:W38)) -> 7092.546 | Y39: =SUM(Y32+SUM(Y35:Y38)) -> 4614.523 | Z39: =SUM(Z32+SUM(Z35:Z38)) -> 5538.31 | AA39: =SUM(AA32+SUM(AA35:AA38)) -> 5961.493 | AB39: =SUM(AB32+SUM(AB35:AB38)) -> 6038.636 | AC39: =SUM(AC32+SUM(AC35:AC38)) -> 5815.758 | AD39: =SUM(AD32+SUM(AD35:AD38)) -> 6554.231 | AE39: =SUM(AE32+SUM(AE35:AE38)) -> 7064.64 | AF39: =SUM(AF32+SUM(AF35:AF38)) -> 7290.293 | ... AK39: =SUM(AK32+SUM(AK35:AK38)) -> 25810.346 | AM39: =SUM(AK39/AG39)-1 -> 0.12227928
B41: (+/-) Proceeds / (Purchases) of ST Investments | C41: =SUM('Historical Financials'!E106:E107)/1000 -> 0 | D41: =SUM('Historical Financials'!F106:F107)/1000 -> 0 | E41: =SUM('Historical Financials'!G106:G107)/1000 -> -911.276 | F41: =SUM('Historical Financials'!H106:H107)/1000 -> 890.303 | G41: =SUM('Historical Financials'!I106:I107)/1000 -> -1742.246 | I41: =SUM('Historical Financials'!O106:O107)/1000 -> 0 | J41: =SUM('Historical Financials'!P106:P107)/1000 -> 0 | K41: =SUM('Historical Financials'!Q106:Q107)/1000 -> 0 | L41: =SUM('Historical Financials'!R106:R107)/1000 -> -911.276 | M41: =SUM('Historical Financials'!S106:S107)/1000 -> -201.634 | N41: =SUM('Historical Financials'!T106:T107)/1000 -> 198.709 | O41: =SUM('Historical Financials'!U106:U107)/1000 -> 400 | P41: =SUM('Historical Financials'!V106:V107)/1000 -> 493.228 | ... W41: =SUM('Historical Financials'!AC106:AC107)/1000 -> 172.4 | Y41: =SUM(H41:K41) -> 0 | Z41: =SUM(I41:L41) -> -911.276 | AA41: =SUM(J41:M41) -> -1112.91 | AB41: =SUM(K41:N41) -> -914.201 | AC41: =SUM(L41:O41) -> -514.201 | AD41: =SUM(M41:P41) -> 890.303 | AE41: =SUM(N41:Q41) -> 1091.937 | AF41: =SUM(O41:R41) -> 893.228 | ... AK41: =SUM(T41:W41) -> 1747.102
B42: (+/-) Divestiture / Acquisitions | C42: =('Historical Financials'!E105)/1000 -> 0 | D42: =('Historical Financials'!F105)/1000 -> -788.349 | E42: =('Historical Financials'!G105)/1000 -> -757.387 | F42: =('Historical Financials'!H105)/1000 -> 0 | G42: =('Historical Financials'!I105)/1000 -> 0 | I42: =('Historical Financials'!O105)/1000 -> -124.521 | J42: =('Historical Financials'!P105)/1000 -> -68.876 | K42: =('Historical Financials'!Q105)/1000 -> 0 | L42: =('Historical Financials'!R105)/1000 -> -563.99 | M42: =('Historical Financials'!S105)/1000 -> 0 | N42: =('Historical Financials'!T105)/1000 -> 0 | O42: =('Historical Financials'!U105)/1000 -> 0 | P42: =('Historical Financials'!V105)/1000 -> 0 | ... W42: =('Historical Financials'!AC105)/1000 -> 36.19 | Y42: =SUM(H42:K42) -> -193.397 | Z42: =SUM(I42:L42) -> -757.387 | AA42: =SUM(J42:M42) -> -632.866 | AB42: =SUM(K42:N42) -> -563.99 | AC42: =SUM(L42:O42) -> -563.99 | AD42: =SUM(M42:P42) -> 0 | AE42: =SUM(N42:Q42) -> 0 | AF42: =SUM(O42:R42) -> 0 | ... AK42: =SUM(T42:W42) -> 0
B43: (-) Proceeds From Equity Issuances / (Share Repurchases) | C43: =SUM('Historical Financials'!E114:E115)/1000 -> 235.406 | D43: =SUM('Historical Financials'!F114:F115)/1000 -> -425.608 | E43: =SUM('Historical Financials'!G114:G115)/1000 -> 35.746 | F43: =SUM('Historical Financials'!H114:H115)/1000 -> -5875.357 | G43: =SUM('Historical Financials'!I114:I115)/1000 -> -5430.859 | I43: =SUM('Historical Financials'!O114:O115)/1000 -> 13.678 | J43: =SUM('Historical Financials'!P114:P115)/1000 -> 11.25 | K43: =SUM('Historical Financials'!Q114:Q115)/1000 -> 4.113 | L43: =SUM('Historical Financials'!R114:R115)/1000 -> 6.705 | M43: =SUM('Historical Financials'!S114:S115)/1000 -> -374.073 | N43: =SUM('Historical Financials'!T114:T115)/1000 -> -610.429 | O43: =SUM('Historical Financials'!U114:U115)/1000 -> -2442.282 | P43: =SUM('Historical Financials'!V114:V115)/1000 -> -2448.573 | ... W43: =SUM('Historical Financials'!AC114:AC115)/1000 -> -1786.67 | AG43: =SUM(P43:S43) -> -7217.696 | AH43: =SUM(Q43:T43) -> -5430.859 | AI43: =SUM(R43:U43) -> -6884.534 | AJ43: =SUM(S43:V43) -> -6888.547 | AK43: =SUM(T43:W43) -> -7118.461
B44: (-) 'Proceeds from issuance of Debt / (Repayment), net | C44: =SUM('Historical Financials'!E111:E113)/1000 -> 1001.905 | D44: =SUM('Historical Financials'!F111:F113)/1000 -> -500 | E44: =SUM('Historical Financials'!G111:G113)/1000 -> -700 | F44: =SUM('Historical Financials'!H111:H113)/1000 -> 0 | G44: =SUM('Historical Financials'!I111:I113)/1000 -> 1394.46 | I44: =SUM('Historical Financials'!O111:O113)/1000 -> -700 | J44: =SUM('Historical Financials'!P111:P113)/1000 -> 0 | K44: =SUM('Historical Financials'!Q111:Q113)/1000 -> 0 | L44: =SUM('Historical Financials'!R111:R113)/1000 -> 0 | M44: =SUM('Historical Financials'!S111:S113)/1000 -> 0 | N44: =SUM('Historical Financials'!T111:T113)/1000 -> 0 | O44: =SUM('Historical Financials'!U111:U113)/1000 -> 0 | P44: =SUM('Historical Financials'!V111:V113)/1000 -> 0 | ... W44: =SUM('Historical Financials'!AC111:AC113)/1000 -> 0 | AG44: =SUM(P44:S44) -> 1394.46 | AH44: =SUM(Q44:T44) -> 1394.46 | AI44: =SUM(R44:U44) -> 994.46 | AJ44: =SUM(S44:V44) -> -38.99 | AK44: =SUM(T44:W44) -> -1833.45
B45: (+/-) Changes in Additions to content assets | C45: =SUM('Historical Financials'!E86:E87)/1000 -> -12536.717 | D45: =SUM('Historical Financials'!F86:F87)/1000 -> -17469.304 | E45: =SUM('Historical Financials'!G86:G87)/1000 -> -16659.728 | F45: =SUM('Historical Financials'!H86:H87)/1000 -> -13140.305 | G45: =SUM('Historical Financials'!I86:I87)/1000 -> -17002.752 | I45: =SUM('Historical Financials'!O86:O87)/1000 -> -3931.313 | J45: =SUM('Historical Financials'!P86:P87)/1000 -> -4495.783 | K45: =SUM('Historical Financials'!Q86:Q87)/1000 -> -4521.804 | L45: =SUM('Historical Financials'!R86:R87)/1000 -> -3710.828 | M45: =SUM('Historical Financials'!S86:S87)/1000 -> -2813.457 | N45: =SUM('Historical Financials'!T86:T87)/1000 -> -3636.888 | O45: =SUM('Historical Financials'!U86:U87)/1000 -> -3209.828 | P45: =SUM('Historical Financials'!V86:V87)/1000 -> -3480.132 | ... W45: =SUM('Historical Financials'!AC86:AC87)/1000 -> -4629.673 | AF45: =SUM(O45:R45) -> -15023.792 | AG45: =SUM(P45:S45) -> -15913.945 | AH45: =SUM(Q45:T45) -> -17002.752 | AI45: =SUM(R45:U45) -> -17045.254 | AJ45: =SUM(S45:V45) -> -16679.695 | AK45: =SUM(T45:W45) -> -17209.387
B46: (+/-) Changes in Other Financing Activities | C46: =SUM('Historical Financials'!E116:E117)/1000 -> 0 | D46: =SUM('Historical Financials'!F116:F117)/1000 -> -224.168 | E46: =SUM('Historical Financials'!G116:G117)/1000 -> 0 | F46: =SUM('Historical Financials'!H116:H117)/1000 -> -75.446 | G46: =SUM('Historical Financials'!I116:I117)/1000 -> -38.028 | I46: =SUM('Historical Financials'!O116:O117)/1000 -> 0 | J46: =SUM('Historical Financials'!P116:P117)/1000 -> 0 | K46: =SUM('Historical Financials'!Q116:Q117)/1000 -> 0 | L46: =SUM('Historical Financials'!R116:R117)/1000 -> 0 | M46: =SUM('Historical Financials'!S116:S117)/1000 -> 0 | N46: =SUM('Historical Financials'!T116:T117)/1000 -> -38.92 | O46: =SUM('Historical Financials'!U116:U117)/1000 -> -32.826 | P46: =SUM('Historical Financials'!V116:V117)/1000 -> -3.7 | ... W46: =SUM('Historical Financials'!AC116:AC117)/1000 -> 49.641 | AG46: =SUM(P46:S46) -> -24.766 | AH46: =SUM(Q46:T46) -> -38.028 | AI46: =SUM(R46:U46) -> -79.725 | AJ46: =SUM(S46:V46) -> -55.749 | AK46: =SUM(T46:W46) -> 5
B47: (+/-) Other | D47: =SUM(D52-C52)-SUM(D39:D45) -> 8.266 | E47: =SUM(E52-D52)-SUM(E39:E45) -> 220.149 | F47: =SUM(F52-E52)-SUM(F39:F45) -> 551.518 | G47: =SUM(G52-F52)-SUM(G39:G46) -> -24.743 | I47: =SUM(I52-D52)-SUM(I39:I46) -> 57.19 | J47: =SUM(J52-I52)-SUM(J39:J46) -> -139.336 | K47: =SUM(K52-J52)-SUM(K39:K46) -> -224.017 | L47: =SUM(L52-K52)-SUM(L39:L46) -> 491.116 | M47: =SUM(M52-L52)-SUM(M39:M46) -> 57.077 | N47: =SUM(N52-M52)-SUM(N39:N46) -> 133.798 | O47: =SUM(O52-N52)-SUM(O39:O46) -> -97.87 | P47: =SUM(P52-O52)-SUM(P39:P46) -> 191.723 | Q47: =SUM(Q52-P52)-SUM(Q39:Q46) -> -81.349 | ... W47: =SUM(W52-V52)-SUM(W39:W46) -> 175.448 | Y47: =SUM(H47:K47) -> -306.163 | Z47: =SUM(I47:L47) -> 184.953 | AA47: =SUM(J47:M47) -> 184.84 | AB47: =SUM(K47:N47) -> 457.974 | AC47: =SUM(L47:O47) -> 584.121 | AD47: =SUM(M47:P47) -> 284.728 | AE47: =SUM(N47:Q47) -> 146.302 | AF47: =SUM(O47:R47) -> -144.988 | ... AK47: =SUM(T47:W47) -> 429.112
B48: Free-Cash Flows | C48: =SUM(C39+SUM(C41:C47)) -> 3039.403 | D48: =SUM(D39+SUM(D41:D47)) -> -2401.914 | E48: =SUM(E39+SUM(E41:E47)) -> -880.628 | F48: =SUM(F39+SUM(F41:F47)) -> 1894.291 | G48: =SUM(G39+SUM(G41:G47)) -> 687.82 | I48: =SUM(I39+SUM(I41:I47)) -> -18.858 | J48: =SUM(J39+SUM(J41:J47)) -> -189.497 | K48: =SUM(K39+SUM(K41:K47)) -> 294.284 | L48: =SUM(L39+SUM(L41:L47)) -> -966.557 | M48: =SUM(M39+SUM(M41:M47)) -> 1567.418 | N48: =SUM(N39+SUM(N41:N47)) -> 948.194 | O48: =SUM(O39+SUM(O41:O47)) -> -309.543 | P48: =SUM(P39+SUM(P41:P47)) -> -236.332 | ... W48: =SUM(W39+SUM(W41:W47)) -> 1109.882 | Y48: =SUM(Y39+SUM(Y41:Y47)) -> 4114.963 | Z48: =SUM(Z39+SUM(Z41:Z47)) -> 4054.6 | AA48: =SUM(AA39+SUM(AA41:AA47)) -> 4400.557 | AB48: =SUM(AB39+SUM(AB41:AB47)) -> 5018.419 | AC48: =SUM(AC39+SUM(AC41:AC47)) -> 5321.688 | AD48: =SUM(AD39+SUM(AD41:AD47)) -> 7729.262 | AE48: =SUM(AE39+SUM(AE41:AE47)) -> 8302.879 | AF48: =SUM(AF39+SUM(AF41:AF47)) -> -6985.259 | ... AK48: =SUM(AK39+SUM(AK41:AK47)) -> 1830.262
B50: Capitalization
B52: Cash & Cash Equivelants | C52: =('Historical Financials'!E43)/1000 -> 8205.55 | D52: =('Historical Financials'!F43)/1000 -> 6027.804 | E52: =('Historical Financials'!G43)/1000 -> 5147.176 | F52: =('Historical Financials'!H43)/1000 -> 7116.913 | G52: =('Historical Financials'!I43)/1000 -> 7804.733 | I52: =('Historical Financials'!O43)/1000 -> 6008.946 | J52: =('Historical Financials'!P43)/1000 -> 5819.449 | K52: =('Historical Financials'!Q43)/1000 -> 6113.733 | L52: =('Historical Financials'!R43)/1000 -> 5147.176 | M52: =('Historical Financials'!S43)/1000 -> 6714.594 | N52: =('Historical Financials'!T43)/1000 -> 7662.788 | O52: =('Historical Financials'!U43)/1000 -> 7353.245 | P52: =('Historical Financials'!V43)/1000 -> 7116.913 | ... W52: =('Historical Financials'!AC43)/1000 -> 9287.287 | Y52: =K52 -> 6113.733 | Z52: =L52 -> 5147.176 | AA52: =M52 -> 6714.594 | AB52: =N52 -> 7662.788 | AC52: =O52 -> 7353.245 | AD52: =P52 -> 7116.913 | AE52: =Q52 -> 7024.766 | AF52: =R52 -> 6624.939 | ... AK52: =W52 -> 9287.287
B53: Marketable Securities | C53: =('Historical Financials'!E45)/1000 -> 0 | D53: =('Historical Financials'!F45)/1000 -> 0 | E53: =('Historical Financials'!G45)/1000 -> 911.276 | F53: =('Historical Financials'!H45)/1000 -> 20.973 | G53: =('Historical Financials'!I45)/1000 -> 1779.006 | I53: =('Historical Financials'!O45)/1000 -> 0 | J53: =('Historical Financials'!P45)/1000 -> 0 | K53: =('Historical Financials'!Q45)/1000 -> 0 | L53: =('Historical Financials'!R45)/1000 -> 911.276 | M53: =('Historical Financials'!S45)/1000 -> 1112.91 | N53: =('Historical Financials'!T45)/1000 -> 914.201 | O53: =('Historical Financials'!U45)/1000 -> 514.201 | P53: =('Historical Financials'!V45)/1000 -> 20.973 | ... W53: =('Historical Financials'!AC45)/1000 -> 37.105 | AG53: =S53 -> 1766.902 | AH53: =T53 -> 1779.006 | AI53: =U53 -> 1171.142 | AJ53: =V53 -> 213.115 | AK53: =W53 -> 37.105
B54: $10Bn RCF due April 2025, April 2028 (CP Backstop) | AG54: =S54 -> 0 | AH54: =T54 -> 0 | AI54: =U54 -> 0 | AJ54: =V54 -> 0 | AK54: =W54 -> 0
B55: Total Liquidity | C55: =SUM(C52:C54) -> 8205.55 | D55: =SUM(D52:D54) -> 6027.804 | E55: =SUM(E52:E54) -> 6058.452 | F55: =SUM(F52:F54) -> 7137.886 | G55: =SUM(G52:G54) -> 9583.739 | I55: =SUM(I52:I54) -> 6008.946 | J55: =SUM(J52:J54) -> 5819.449 | K55: =SUM(K52:K54) -> 6113.733 | L55: =SUM(L52:L54) -> 6058.452 | M55: =SUM(M52:M54) -> 7827.504 | N55: =SUM(N52:N54) -> 8576.989 | O55: =SUM(O52:O54) -> 7867.446 | P55: =SUM(P52:P54) -> 7137.886 | ... W55: =SUM(W52:W54) -> 9324.392 | Y55: =SUM(Y52:Y52) -> 6113.733 | Z55: =SUM(Z52:Z52) -> 5147.176 | AA55: =SUM(AA52:AA52) -> 6714.594 | AB55: =SUM(AB52:AB52) -> 7662.788 | AC55: =SUM(AC52:AC52) -> 7353.245 | AD55: =SUM(AD52:AD52) -> 7116.913 | AE55: =SUM(AE52:AE52) -> 7024.766 | AF55: =SUM(AF52:AF52) -> 6624.939 | AG55: =SUM(AG52:AG54) -> 9223.927 | AH55: =SUM(AH52:AH54) -> 9583.739 | AI55: =SUM(AI52:AI54) -> 8370.99 | AJ55: =SUM(AJ52:AJ54) -> 8390.52 | AK55: =SUM(AK52:AK54) -> 9324.392
B57: Balance Sheet Metrics:
B58: Property and equipment, net | C58: =('Historical Financials'!E50)/1000 -> 960.183 | D58: =('Historical Financials'!F50)/1000 -> 1323.453 | E58: =('Historical Financials'!G50)/1000 -> 1398.257 | F58: =('Historical Financials'!H50)/1000 -> 1491.444 | G58: =('Historical Financials'!I50)/1000 -> 1593.756 | I58: =('Historical Financials'!O50)/1000 -> 1383.763 | J58: =('Historical Financials'!P50)/1000 -> 1361.92 | K58: =('Historical Financials'!Q50)/1000 -> 1372.754 | L58: =('Historical Financials'!R50)/1000 -> 1398.257 | M58: =('Historical Financials'!S50)/1000 -> 1413.094 | N58: =('Historical Financials'!T50)/1000 -> 1471.968 | O58: =('Historical Financials'!U50)/1000 -> 1498.391 | P58: =('Historical Financials'!V50)/1000 -> 1491.444 | ... W58: =('Historical Financials'!AC50)/1000 -> 1837.889 | Y58: =K58 -> 1372.754 | Z58: =L58 -> 1398.257 | AA58: =M58 -> 1413.094 | AB58: =N58 -> 1471.968 | AC58: =O58 -> 1498.391 | AD58: =P58 -> 1491.444 | AE58: =Q58 -> 1501.168 | AF58: =R58 -> 1510.958 | ... AK58: =W58 -> 1837.889
B59: Content Liabilities | C59: =('Historical Financials'!E55)/1000 -> 4429.536 | D59: =('Historical Financials'!F55)/1000 -> 4292.967 | E59: =('Historical Financials'!G55)/1000 -> 4480.15 | F59: =('Historical Financials'!H55)/1000 -> 4466.47 | G59: =('Historical Financials'!I55)/1000 -> 4393.681 | I59: =('Historical Financials'!O55)/1000 -> 4066.289 | J59: =('Historical Financials'!P55)/1000 -> 4174.966 | K59: =('Historical Financials'!Q55)/1000 -> 4225.89 | L59: =('Historical Financials'!R55)/1000 -> 4480.15 | M59: =('Historical Financials'!S55)/1000 -> 4344.58 | N59: =('Historical Financials'!T55)/1000 -> 4440.412 | O59: =('Historical Financials'!U55)/1000 -> 4259.582 | P59: =('Historical Financials'!V55)/1000 -> 4466.47 | ... W59: =('Historical Financials'!AC55)/1000 -> 4102.64 | Y59: =K59 -> 4225.89 | Z59: =L59 -> 4480.15 | AA59: =M59 -> 4344.58 | AB59: =N59 -> 4440.412 | AC59: =O59 -> 4259.582 | AD59: =P59 -> 4466.47 | AE59: =Q59 -> 4436.021 | AF59: =R59 -> 4391.437 | ... AK59: =W59 -> 4102.64
B60: Accounts payable | C60: =('Historical Financials'!E56)/1000 -> 656.183 | D60: =('Historical Financials'!F56)/1000 -> 837.483 | E60: =('Historical Financials'!G56)/1000 -> 671.513 | F60: =('Historical Financials'!H56)/1000 -> 747.412 | G60: =('Historical Financials'!I56)/1000 -> 899.909 | I60: =('Historical Financials'!O56)/1000 -> 617.202 | J60: =('Historical Financials'!P56)/1000 -> 504.278 | K60: =('Historical Financials'!Q56)/1000 -> 560.156 | L60: =('Historical Financials'!R56)/1000 -> 671.513 | M60: =('Historical Financials'!S56)/1000 -> 591.987 | N60: =('Historical Financials'!T56)/1000 -> 615.374 | O60: =('Historical Financials'!U56)/1000 -> 534.429 | P60: =('Historical Financials'!V56)/1000 -> 747.412 | ... W60: =('Historical Financials'!AC56)/1000 -> 793.233 | AG60: =S60 -> 641.953 | AH60: =T60 -> 899.909 | AI60: =U60 -> 614.489 | AJ60: =V60 -> 632.718 | AK60: =W60 -> 793.233
B61: Deferred Revenue | C61: =('Historical Financials'!E58)/1000 -> 1117.992 | D61: =('Historical Financials'!F58)/1000 -> 1209.342 | E61: =('Historical Financials'!G58)/1000 -> 1264.661 | F61: =('Historical Financials'!H58)/1000 -> 1442.969 | G61: =('Historical Financials'!I58)/1000 -> 1520.813 | I61: =('Historical Financials'!O58)/1000 -> 1239.048 | J61: =('Historical Financials'!P58)/1000 -> 1224.743 | K61: =('Historical Financials'!Q58)/1000 -> 1176.323 | L61: =('Historical Financials'!R58)/1000 -> 1264.661 | M61: =('Historical Financials'!S58)/1000 -> 1262.271 | N61: =('Historical Financials'!T58)/1000 -> 1311.918 | O61: =('Historical Financials'!U58)/1000 -> 1306.185 | P61: =('Historical Financials'!V58)/1000 -> 1442.969 | ... W61: =('Historical Financials'!AC58)/1000 -> 1724.675 | AG61: =S61 -> 1513.048 | AH61: =T61 -> 1520.813 | AI61: =U61 -> 1609.726 | AJ61: =V61 -> 1728.361 | AK61: =W61 -> 1724.675
B62: Current Liabilities | C62: =('Historical Financials'!E60)/1000 -> 7805.785 | D62: =('Historical Financials'!F60)/1000 -> 8488.966 | E62: =('Historical Financials'!G60)/1000 -> 7930.974 | F62: =('Historical Financials'!H60)/1000 -> 8860.655 | G62: =('Historical Financials'!I60)/1000 -> 10755.4 | I62: =('Historical Financials'!O60)/1000 -> 7739.656 | J62: =('Historical Financials'!P60)/1000 -> 7500.022 | K62: =('Historical Financials'!Q60)/1000 -> 7765.924 | L62: =('Historical Financials'!R60)/1000 -> 7930.974 | M62: =('Historical Financials'!S60)/1000 -> 8316.07 | N62: =('Historical Financials'!T60)/1000 -> 8675.805 | O62: =('Historical Financials'!U60)/1000 -> 8338.718 | P62: =('Historical Financials'!V60)/1000 -> 8860.655 | ... W62: =('Historical Financials'!AC60)/1000 -> 9731.859 | Y62: =K62 -> 7765.924 | Z62: =L62 -> 7930.974 | AA62: =M62 -> 8316.07 | AB62: =N62 -> 8675.805 | AC62: =O62 -> 8338.718 | AD62: =P62 -> 8860.655 | AE62: =Q62 -> 9289.217 | AF62: =R62 -> 10139.999 | ... AK62: =W62 -> 9731.859
B63: Total Liabilities | C63: =('Historical Financials'!E66)/1000 -> 28215.119 | D63: =('Historical Financials'!F66)/1000 -> 28735.415 | E63: =('Historical Financials'!G66)/1000 -> 27817.367 | F63: =('Historical Financials'!H66)/1000 -> 28143.679 | G63: =('Historical Financials'!I66)/1000 -> 28886.807 | I63: =('Historical Financials'!O66)/1000 -> 27786.865 | J63: =('Historical Financials'!P66)/1000 -> 27274.961 | K63: =('Historical Financials'!Q66)/1000 -> 27034.046 | L63: =('Historical Financials'!R66)/1000 -> 27817.367 | M63: =('Historical Financials'!S66)/1000 -> 27662.149 | N63: =('Historical Financials'!T66)/1000 -> 27985.258 | O63: =('Historical Financials'!U66)/1000 -> 27394.159 | P63: =('Historical Financials'!V66)/1000 -> 28143.679 | ... W63: =('Historical Financials'!AC66)/1000 -> 28980.8 | Y63: =K63 -> 27034.046 | Z63: =L63 -> 27817.367 | AA63: =M63 -> 27662.149 | AB63: =N63 -> 27985.258 | AC63: =O63 -> 27394.159 | AD63: =P63 -> 28143.679 | AE63: =Q63 -> 27462.311 | AF63: =R63 -> 26986.202 | ... AK63: =W63 -> 28980.8
B65: Summary Debt:
B66: CPLTD | C66: =('Historical Financials'!E59)/1000 -> 499.878 | D66: =('Historical Financials'!F59)/1000 -> 699.823 | E66: =('Historical Financials'!G59)/1000 -> 0 | F66: =('Historical Financials'!H59)/1000 -> 399.844 | G66: =('Historical Financials'!I59)/1000 -> 1784.453 | I66: =('Historical Financials'!O59)/1000 -> 0 | J66: =('Historical Financials'!P59)/1000 -> 0 | K66: =('Historical Financials'!Q59)/1000 -> 0 | L66: =('Historical Financials'!R59)/1000 -> 0 | M66: =('Historical Financials'!S59)/1000 -> 399.163 | N66: =('Historical Financials'!T59)/1000 -> 399.387 | O66: =('Historical Financials'!U59)/1000 -> 399.614 | P66: =('Historical Financials'!V59)/1000 -> 399.844 | ... W66: =('Historical Financials'!AC59)/1000 -> 0 | AG66: =S66 -> 1820.396 | AH66: =T66 -> 1784.453 | AI66: =U66 -> 1005.881 | AJ66: =V66 -> 0 | AK66: =W66 -> 0
B67: LTD | C67: =('Historical Financials'!E64)/1000 -> 15809.095 | D67: =('Historical Financials'!F64)/1000 -> 14693.072 | E67: =('Historical Financials'!G64)/1000 -> 14353.076 | F67: =('Historical Financials'!H64)/1000 -> 14143.417 | G67: =('Historical Financials'!I64)/1000 -> 13798.351 | I67: =('Historical Financials'!O64)/1000 -> 14534.561 | J67: =('Historical Financials'!P64)/1000 -> 14233.303 | K67: =('Historical Financials'!Q64)/1000 -> 13888.117 | L67: =('Historical Financials'!R64)/1000 -> 14353.076 | M67: =('Historical Financials'!S64)/1000 -> 14037.965 | N67: =('Historical Financials'!T64)/1000 -> 14070.151 | O67: =('Historical Financials'!U64)/1000 -> 13900.754 | P67: =('Historical Financials'!V64)/1000 -> 14143.417 | ... W67: =('Historical Financials'!AC64)/1000 -> 14463.02 | AG67: =S67 -> 14160.932 | AH67: =T67 -> 13798.351 | AI67: =U67 -> 14011.037 | AJ67: =V67 -> 14453.206 | AK67: =W67 -> 14463.02
B69: 5.750% Senior Notes due March 2024 | F69: 400 | G69: 0 | L69: =E69 -> 0 | P69: =F69 -> 400 | T69: =G69 -> 0 | Y69: =K69 -> 0 | Z69: =L69 -> 0 | AA69: =M69 -> 0 | AB69: =N69 -> 0 | AC69: =O69 -> 0 | AD69: =P69 -> 400 | AE69: =Q69 -> 0 | AF69: =R69 -> 0 | ... AK69: =W69 -> 0
B70: 5.875% Senior Notes due February 2025 | F70: 800 | G70: 800 | L70: =E70 -> 0 | P70: =F70 -> 800 | T70: =G70 -> 800 | AG70: =S70 -> 0 | AH70: =T70 -> 800 | AI70: =U70 -> 0 | AJ70: =V70 -> 0 | AK70: =W70 -> 0
B71: 3.000% Senior Notes due June 2025 | F71: 519 | G71: 487 | L71: =E71 -> 0 | P71: =F71 -> 519 | T71: =G71 -> 487 | AG71: =S71 -> 0 | AH71: =T71 -> 487 | AI71: =U71 -> 0 | AJ71: =V71 -> 0 | AK71: =W71 -> 0
B72: 3.625% Senior Notes due June 2025 | F72: 500 | G72: 500 | L72: =E72 -> 0 | P72: =F72 -> 500 | T72: =G72 -> 500 | AG72: =S72 -> 0 | AH72: =T72 -> 500 | AI72: =U72 -> 0 | AJ72: =V72 -> 0 | AK72: =W72 -> 0
B73: 4.375% Senior Notes due November 2026 | F73: 1000 | G73: 1000 | L73: =E73 -> 0 | P73: =F73 -> 1000 | T73: =G73 -> 1000 | AG73: =S73 -> 0 | AH73: =T73 -> 1000 | AI73: =U73 -> 0 | AJ73: =V73 -> 0 | AK73: =W73 -> 0
B74: 3.625% Senior Notes due May 2027 | F74: 1434 | G74: 1346 | L74: =E74 -> 0 | P74: =F74 -> 1434 | T74: =G74 -> 1346 | AG74: =S74 -> 0 | AH74: =T74 -> 1346 | AI74: =U74 -> 0 | AJ74: =V74 -> 0 | AK74: =W74 -> 0
B75: 4.875% Senior Notes due April 2028 | F75: 1600 | G75: 1600 | L75: =E75 -> 0 | P75: =F75 -> 1600 | T75: =G75 -> 1600 | AG75: =S75 -> 0 | AH75: =T75 -> 1600 | AI75: =U75 -> 0 | AJ75: =V75 -> 0 | AK75: =W75 -> 0
B76: 5.875% Senior Notes due November 2028 | F76: 1900 | G76: 1900 | L76: =E76 -> 0 | P76: =F76 -> 1900 | T76: =G76 -> 1900 | AG76: =S76 -> 0 | AH76: =T76 -> 1900 | AI76: =U76 -> 0 | AJ76: =V76 -> 0 | AK76: =W76 -> 0
B77: 4.625% Senior Notes due May 2029 | F77: 1215 | G77: 1139 | L77: =E77 -> 0 | P77: =F77 -> 1215 | T77: =G77 -> 1139 | AG77: =S77 -> 0 | AH77: =T77 -> 1139 | AI77: =U77 -> 0 | AJ77: =V77 -> 0 | AK77: =W77 -> 0
B78: 6.375% Senior Notes due May 2029 | F78: 800 | G78: 800 | L78: =E78 -> 0 | P78: =F78 -> 800 | T78: =G78 -> 800 | AG78: =S78 -> 0 | AH78: =T78 -> 800 | AI78: =U78 -> 0 | AJ78: =V78 -> 0 | AK78: =W78 -> 0
B79: 3.875% Senior Notes due November 2029 | F79: 1325 | G79: 1242 | L79: =E79 -> 0 | P79: =F79 -> 1325 | T79: =G79 -> 1242 | AG79: =S79 -> 0 | AH79: =T79 -> 1242 | AI79: =U79 -> 0 | AJ79: =V79 -> 0 | AK79: =W79 -> 0
B80: 5.375% Senior Notes due November 2029 | F80: 900 | G80: 900 | L80: =E80 -> 0 | P80: =F80 -> 900 | T80: =G80 -> 900 | AG80: =S80 -> 0 | AH80: =T80 -> 900 | AI80: =U80 -> 0 | AJ80: =V80 -> 0 | AK80: =W80 -> 0
B81: 3.625% Senior Notes due June 2030 | F81: 1215 | G81: 1139 | L81: =E81 -> 0 | P81: =F81 -> 1215 | T81: =G81 -> 1139 | AG81: =S81 -> 0 | AH81: =T81 -> 1139 | AI81: =U81 -> 0 | AJ81: =V81 -> 0 | AK81: =W81 -> 0
... B84: 5.400% Senior Notes due August 2054 | F84: 0 | G84: 800 | L84: =E84 -> 0 | P84: =F84 -> 0 | T84: =G84 -> 800 | AG84: =S84 -> 0 | AH84: =T84 -> 800 | AI84: =U84 -> 0 | AJ84: =V84 -> 0 | AK84: =W84 -> 0
B85: Total Debt | C85: =SUM(C69:C84) -> 0 | D85: =SUM(D69:D84) -> 0 | E85: =SUM(E69:E84) -> 0 | F85: =SUM(F69:F84) -> 14608 | G85: =SUM(G69:G84) -> 15653 | I85: =SUM(I69:I84) -> 0 | J85: =SUM(J69:J84) -> 0 | K85: =SUM(K69:K84) -> 0 | L85: =SUM(L69:L84) -> 0 | M85: =SUM(M69:M84) -> 0 | N85: =SUM(N69:N84) -> 0 | O85: =SUM(O69:O84) -> 0 | P85: =SUM(P69:P84) -> 14608 | ... W85: =SUM(W69:W84) -> 0 | Y85: =SUM(Y69:Y84) -> 0 | Z85: =SUM(Z69:Z84) -> 0 | AA85: =SUM(AA69:AA84) -> 0 | AB85: =SUM(AB69:AB84) -> 0 | AC85: =SUM(AC69:AC84) -> 0 | AD85: =SUM(AD69:AD84) -> 400 | AE85: =SUM(AE69:AE84) -> 0 | AF85: =SUM(AF69:AF84) -> 0 | ... AK85: =SUM(AK69:AK84) -> 0
B87: Total Shareholder Equity | C87: =('Historical Financials'!E72)/1000 -> 11065.24 | D87: =('Historical Financials'!F72)/1000 -> 15849.248 | E87: =('Historical Financials'!G72)/1000 -> 20777.401 | F87: =('Historical Financials'!H72)/1000 -> 20588.313 | G87: =('Historical Financials'!I72)/1000 -> 24743.567 | I87: =('Historical Financials'!O72)/1000 -> 17544.039 | J87: =('Historical Financials'!P72)/1000 -> 19075.974 | K87: =('Historical Financials'!Q72)/1000 -> 20528.141 | L87: =('Historical Financials'!R72)/1000 -> 20777.401 | M87: =('Historical Financials'!S72)/1000 -> 21828.196 | N87: =('Historical Financials'!T72)/1000 -> 22832.215 | O87: =('Historical Financials'!U72)/1000 -> 22107.627 | P87: =('Historical Financials'!V72)/1000 -> 20588.313 | ... W87: =('Historical Financials'!AC72)/1000 -> 25954.035 | Y87: =K87 -> 20528.141 | Z87: =L87 -> 20777.401 | AA87: =M87 -> 21828.196 | AB87: =N87 -> 22832.215 | AC87: =O87 -> 22107.627 | AD87: =P87 -> 20588.313 | AE87: =Q87 -> 21365.41 | AF87: =R87 -> 22112.693 | ... AK87: =W87 -> 25954.035
B88: Total Book Capitalization | C88: =SUM(C85:C87) -> 11065.24 | D88: =SUM(D85:D87) -> 15849.248 | E88: =SUM(E85:E87) -> 20777.401 | F88: =SUM(F85:F87) -> 35196.313 | G88: =SUM(G85:G87) -> 40396.567 | I88: =SUM(I85:I87) -> 17544.039 | J88: =SUM(J85:J87) -> 19075.974 | K88: =SUM(K85:K87) -> 20528.141 | L88: =SUM(L85:L87) -> 20777.401 | M88: =SUM(M85:M87) -> 21828.196 | N88: =SUM(N85:N87) -> 22832.215 | O88: =SUM(O85:O87) -> 22107.627 | P88: =SUM(P85:P87) -> 35196.313 | ... W88: =SUM(W85:W87) -> 25954.035 | Y88: =SUM(Y85:Y87) -> 20528.141 | Z88: =SUM(Z85:Z87) -> 20777.401 | AA88: =SUM(AA85:AA87) -> 21828.196 | AB88: =SUM(AB85:AB87) -> 22832.215 | AC88: =SUM(AC85:AC87) -> 22107.627 | AD88: =SUM(AD85:AD87) -> 20988.313 | AE88: =SUM(AE85:AE87) -> 21365.41 | AF88: =SUM(AF85:AF87) -> 22112.693 | ... AK88: =SUM(AK85:AK87) -> 25954.035
B90: Credit Metrics
B92: LTM Total Leverage | C92: =C85/C32 -> 0 | D92: =D85/D32 -> 0 | E92: =E85/E32 -> 0 | F92: =F85/F32 -> 0.66862705 | G92: =G85/G32 -> 0.59470454 | L92: =SUM(L85/SUM(I32:L32)) -> 0 | M92: =SUM(M85/SUM(J32:M32)) -> 0 | N92: =SUM(N85/SUM(K32:N32)) -> 0 | O92: =SUM(O85/SUM(L32:O32)) -> 0 | P92: =SUM(P85/SUM(M32:P32)) -> 0.66862705 | Q92: =SUM(Q85/SUM(N32:Q32)) -> 0 | R92: =SUM(R85/SUM(O32:R32)) -> 0 | S92: =SUM(S85/SUM(P32:S32)) -> 0 | ... W92: =SUM(W85/SUM(T32:W32)) -> 0 | Y92: =Y85/Y32 -> 0 | Z92: =Z85/Z32 -> 0 | AA92: =AA85/AA32 -> 0 | AB92: =AB85/AB32 -> 0 | AC92: =AC85/AC32 -> 0 | AD92: =AD85/AD32 -> 0.04696946 | AE92: =AE85/AE32 -> 0 | AF92: =AF85/AF32 -> 0 | ... AK92: =AK85/AK32 -> 0
B93: LTM Net Leverage | C93: =SUM(C85-C52)/C32 -> -0.51532394 | D93: =SUM(D85-D52)/D32 -> -0.31664442 | E93: =SUM(E85-E52)/E32 -> -0.25021398 | F93: =SUM(F85-F52)/F32 -> 0.34287674 | G93: =SUM(G85-G52)/G32 -> 0.29817926 | L93: =SUM(L85-L52)/SUM(I32:L32) -> -0.25021398 | M93: =SUM(M85-M52)/SUM(J32:M32) -> -0.32590323 | N93: =SUM(N85-N52)/SUM(K32:N32) -> -0.36604298 | O93: =SUM(O85-O52)/SUM(L32:O32) -> -0.34733634 | P93: =SUM(P85-P52)/SUM(M32:P32) -> 0.34287674 | Q93: =SUM(Q85-Q52)/SUM(N32:Q32) -> -0.30607751 | R93: =SUM(R85-R52)/SUM(O32:R32) -> -0.27524963 | S93: =SUM(S85-S52)/SUM(P32:S32) -> -0.2963338 | ... W93: =SUM(W85-W52)/SUM(T32:W32) -> -0.31931827 | Y93: =SUM(Y85-Y52)/Y32 -> -0.98002169 | Z93: =SUM(Z85-Z52)/Z32 -> -0.62905894 | AA93: =SUM(AA85-AA52)/AA32 -> -0.79897007 | AB93: =SUM(AB85-AB52)/AB32 -> -0.91075993 | AC93: =SUM(AC85-AC52)/AC32 -> -0.87645705 | AD93: =SUM(AD85-AD52)/AD32 -> -0.78872444 | AE93: =SUM(AE85-AE52)/AE32 -> -0.78150948 | AF93: =SUM(AF85-AF52)/AF32 -> -0.69213652 | ... AK93: =SUM(AK85-AK52)/AK32 -> -0.31931827
B94: LTM Interest Coverage | C94: =C32/-C37 -> 20.871684 | D94: =D32/-D37 -> 24.935434 | E94: =E32/-E37 -> 29.316378 | F94: =F32/-F37 -> 31.917644 | G94: =G32/-G37 -> 39.02232 | L94: {=SUM(I32:L32)/SUM(-I37:L37)} -> 29.128784 | M94: {=SUM(J32:M32)/SUM(-J37:M37)} -> 29.735694 | N94: {=SUM(K32:N32)/SUM(-K37:N37)} -> 30.241612 | O94: {=SUM(L32:O32)/SUM(-L37:O37)} -> 30.451482 | P94: {=SUM(M32:P32)/SUM(-M37:P37)} -> 31.218839 | Q94: {=SUM(N32:Q32)/SUM(-N37:Q37)} -> 32.838611 | R94: {=SUM(O32:R32)/SUM(-O37:R37)} -> 34.77779 | S94: {=SUM(P32:S32)/SUM(-P37:S37)} -> 35.880175 | ... W94: {=SUM(T32:W32)/SUM(-T37:W37)} -> 39.586255 | Y94: =Y32/-Y37 -> 11.647237 | Z94: =Z32/-Z37 -> 11.586242 | AA94: =AA32/-AA37 -> 12.129314 | AB94: =AB32/-AB37 -> 12.154388 | AC94: =AC32/-AC37 -> 12.067798 | AD94: =AD32/-AD37 -> 12.168985 | AE94: =AE32/-AE37 -> 12.861214 | AF94: =AF32/-AF37 -> 13.830471 | ... AK94: =AK32/-AK37 -> 39.586255
B95: LTM Debt Service Coverage | C95: {=SUM(C32+C35)/SUM(-C36:C37)} -> 14.628139 | D95: {=SUM(D32+D35)/SUM(-D36:D37)} -> 14.545428 | E95: {=SUM(E32+E35)/SUM(-E36:E37)} -> 13.32311 | F95: {=SUM(F32+F35)/SUM(-F36:F37)} -> 11.687672 | G95: {=SUM(G32+G35)/SUM(-G36:G37)} -> 11.174757 | L95: {=SUM(I32:L32+I35:L35)/SUM(-I36:L37)} -> 13.64033 | M95: {=SUM(J32:M32+J35:M35)/SUM(-J36:M37)} -> 16.250536 | N95: {=SUM(K32:N32+K35:N35)/SUM(-K36:N37)} -> 16.389358 | O95: {=SUM(L32:O32+L35:O35)/SUM(-L36:O37)} -> 16.418458 | P95: {=SUM(M32:P32+M35:P35)/SUM(-M36:P37)} -> 14.359213 | Q95: {=SUM(N32:Q32+N35:Q35)/SUM(-N36:Q37)} -> 13.987395 | R95: {=SUM(O32:R32+O35:R35)/SUM(-O36:R37)} -> 13.309117 | S95: {=SUM(P32:S32+P35:S35)/SUM(-P36:S37)} -> 13.053437 | ... W95: {=SUM(T32:W32+T35:W35)/SUM(-T36:W37)} -> 11.902636 | Y95: {=SUM(Y32+Y35)/SUM(-Y36:Y37)} -> 4.4895736 | Z95: {=SUM(Z32+Z35)/SUM(-Z36:Z37)} -> 5.2594538 | AA95: {=SUM(AA32+AA35)/SUM(-AA36:AA37)} -> 6.4630636 | AB95: {=SUM(AB32+AB35)/SUM(-AB36:AB37)} -> 6.4157398 | AC95: {=SUM(AC32+AC35)/SUM(-AC36:AC37)} -> 6.326123 | AD95: {=SUM(AD32+AD35)/SUM(-AD36:AD37)} -> 5.4551138 | AE95: {=SUM(AE32+AE35)/SUM(-AE36:AE37)} -> 5.3416912 | AF95: {=SUM(AF32+AF35)/SUM(-AF36:AF37)} -> 5.1780722 | ... AK95: {=SUM(AK32+AK35)/SUM(-AK36:AK37)} -> 11.902636
B96: LTM Fixed Charge Coverage | C96: {=SUM(C32)/SUM(-C35:C37)} -> 10.257021 | D96: {=SUM(D32)/SUM(-D35:D37)} -> 10.591831 | E96: {=SUM(E32)/SUM(-E35:E37)} -> 10.707744 | F96: {=SUM(F32)/SUM(-F35:F37)} -> 9.9851305 | G96: {=SUM(G32)/SUM(-G35:G37)} -> 9.5517926 | L96: {=SUM(I32:L32)/SUM(-I35:L37)} -> 10.907575 | M96: {=SUM(J32:M32)/SUM(-J35:M37)} -> 12.917455 | N96: {=SUM(K32:N32)/SUM(-K35:N37)} -> 12.963059 | O96: {=SUM(L32:O32)/SUM(-L35:O37)} -> 12.870437 | P96: {=SUM(M32:P32)/SUM(-M35:P37)} -> 11.836514 | Q96: {=SUM(N32:Q32)/SUM(-N35:Q37)} -> 11.607921 | R96: {=SUM(O32:R32)/SUM(-O35:R37)} -> 11.339875 | S96: {=SUM(P32:S32)/SUM(-P35:S37)} -> 11.122257 | ... W96: {=SUM(T32:W32)/SUM(-T35:W37)} -> 9.6946884 | Y96: {=SUM(Y32)/SUM(-Y35:Y37)} -> 3.8515606 | Z96: {=SUM(Z32)/SUM(-Z35:Z37)} -> 4.3385882 | AA96: {=SUM(AA32)/SUM(-AA35:AA37)} -> 5.2690837 | AB96: {=SUM(AB32)/SUM(-AB35:AB37)} -> 5.2099751 | AC96: {=SUM(AC32)/SUM(-AC35:AC37)} -> 5.1005013 | AD96: {=SUM(AD32)/SUM(-AD35:AD37)} -> 4.6138283 | AE96: {=SUM(AE32)/SUM(-AE35:AE37)} -> 4.5462323 | AF96: {=SUM(AF32)/SUM(-AF35:AF37)} -> 4.5096542 | ... AK96: {=SUM(AK32)/SUM(-AK35:AK37)} -> 9.6946884
B97: Debt-to-Book Capitalization | C97: =C88/C85 -> #DIV/0! | D97: =D88/D85 -> #DIV/0! | E97: =E88/E85 -> #DIV/0! | F97: =F88/F85 -> 2.4093862 | G97: =G88/G85 -> 2.5807556 | L97: =L88/L85 -> #DIV/0! | M97: =M88/M85 -> #DIV/0! | N97: =N88/N85 -> #DIV/0! | O97: =O88/O85 -> #DIV/0! | P97: =P88/P85 -> 2.4093862 | Q97: =Q88/Q85 -> #DIV/0! | R97: =R88/R85 -> #DIV/0! | S97: =S88/S85 -> #DIV/0! | ... W97: =W88/W85 -> #DIV/0! | Y97: =Y88/Y85 -> #DIV/0! | Z97: =Z88/Z85 -> #DIV/0! | AA97: =AA88/AA85 -> #DIV/0! | AB97: =AB88/AB85 -> #DIV/0! | AC97: =AC88/AC85 -> #DIV/0! | AD97: =AD88/AD85 -> 52.470782 | AE97: =AE88/AE85 -> #DIV/0! | AF97: =AF88/AF85 -> #DIV/0! | ... AK97: =AK88/AK85 -> #DIV/0!

Sheet 3-Statement Model
B2: ='Historical Financials'!B2 -> Netflix, Inc. (NASDAQ: NFLX)
B3: 3-Statement Model
B4: $ mm except per share
B6: Company name | C6: Beyond Meat, Inc. | I6: Select an operating scenario: | K6: Base case
B7: Ticker | C7: GOOG
B8: Circ break 1=off, 0=on | C8: 0
B9: Latest closing share price
B10: Latest closing share price date | C10: =NOW() -> 45986.813
B11: Latest fiscal year end date | C11: ='Historical Financials'!I8 -> 45657
B12: Shares outstanding (millions) | C12: 4443.265
A14: X | B14: Income Statement | C14: Actuals | G14: Forecast
B15: Fiscal year | C15: =D15-1 -> 2021 | D15: =E15-1 -> 2022 | E15: =F15-1 -> 2023 | F15: =YEAR(C11) -> 2024 | G15: =F15+1 -> 2025 | H15: =G15+1 -> 2026 | I15: =H15+1 -> 2027 | J15: =I15+1 -> 2028 | K15: =J15+1 -> 2029
B16: Fiscal year end date | C16: =EOMONTH(D16,-12) -> 44561 | D16: =EOMONTH(E16,-12) -> 44926 | E16: =EOMONTH(F16,-12) -> 45291 | F16: =C11 -> 45657 | G16: =EOMONTH(F16,12) -> 46022 | H16: =EOMONTH(G16,12) -> 46387 | I16: =EOMONTH(H16,12) -> 46752 | J16: =EOMONTH(I16,12) -> 47118 | K16: =EOMONTH(J16,12) -> 47483 | M16: Commentary
B18: Google Search & Other | C18: ='Revenue Drivers'!#REF! -> #REF! | D18: ='Revenue Drivers'!#REF! -> #REF! | E18: ='Revenue Drivers'!#REF! -> #REF! | F18: ='Revenue Drivers'!#REF! -> #REF! | G18: =F18*(1+G61) -> #REF! | H18: =G18*(1+H61) -> #REF! | I18: =H18*(1+I61) -> #REF! | J18: =I18*(1+J61) -> #REF! | K18: =J18*(1+K61) -> #REF!
B19: YouTube ads | C19: ='Revenue Drivers'!#REF! -> #REF! | D19: ='Revenue Drivers'!#REF! -> #REF! | E19: ='Revenue Drivers'!#REF! -> #REF! | F19: ='Revenue Drivers'!#REF! -> #REF!
B20: Google Network | C20: ='Revenue Drivers'!#REF! -> #REF! | D20: ='Revenue Drivers'!#REF! -> #REF! | E20: ='Revenue Drivers'!#REF! -> #REF! | F20: ='Revenue Drivers'!#REF! -> #REF!
B21: Total Advertising Revenue | C21: =SUM(C18:C20) -> #REF! | D21: =SUM(D18:D20) -> #REF! | E21: =SUM(E18:E20) -> #REF! | F21: =SUM(F18:F20) -> #REF! | G21: =SUM(G18:G20) -> #REF! | H21: =SUM(H18:H20) -> #REF! | I21: =SUM(I18:I20) -> #REF! | J21: =SUM(J18:J20) -> #REF! | K21: =SUM(K18:K20) -> #REF!
G27: =F27*(1+G66) -> 0 | H27: =G27*(1+H66) -> 0 | I27: =H27*(1+I66) -> 0 | J27: =I27*(1+J66) -> 0 | K27: =J27*(1+K66) -> 0
B28: Total Net Revenue | C28: =SUM(C18:C27) -> #REF! | D28: =SUM(D18:D27) -> #REF! | E28: =SUM(E18:E27) -> #REF! | F28: =SUM(F18:F27) -> #REF! | G28: =SUM(G18:G27) -> #REF! | H28: =SUM(H18:H27) -> #REF! | I28: =SUM(I18:I27) -> #REF! | J28: =SUM(J18:J27) -> #REF! | K28: =SUM(K18:K27) -> #REF!
B29: Y/Y Growth (%) | D29: =SUM(D28/C28)-1 -> #REF! | E29: =SUM(E28/D28)-1 -> #REF! | F29: =SUM(F28/E28)-1 -> #REF! | G29: =SUM(G28/F28)-1 -> #REF! | H29: =SUM(H28/G28)-1 -> #REF! | I29: =SUM(I28/H28)-1 -> #REF! | J29: =SUM(J28/I28)-1 -> #REF! | K29: =SUM(K28/J28)-1 -> #REF!
B31: Cost of Sales | C31: ='Historical Financials'!#REF! -> #REF! | D31: ='Historical Financials'!#REF! -> #REF! | E31: ='Historical Financials'!#REF! -> #REF! | F31: ='Historical Financials'!#REF! -> #REF! | G31: =+G32-G28 -> #REF! | H31: =+H32-H28 -> #REF! | I31: =+I32-I28 -> #REF! | J31: =+J32-J28 -> #REF! | K31: =+K32-K28 -> #REF! | M31: Plug = Revenue - Gross Profit
B32: Gross Profit | C32: =+C31+C28 -> #REF! | D32: =+D31+D28 -> #REF! | E32: =+E31+E28 -> #REF! | F32: =+F31+F28 -> #REF! | G32: =G68*G28 -> #REF! | H32: =H68*H28 -> #REF! | I32: =I68*I28 -> #REF! | J32: =J68*J28 -> #REF! | K32: =K68*K28 -> #REF! | M32: Revenue x Gross Profit Margin forecast
B33: Margin (%) | C33: =C32/C28 -> #REF! | D33: =D32/D28 -> #REF! | E33: =E32/E28 -> #REF! | F33: =F32/F28 -> #REF! | G33: =G32/G28 -> #REF! | H33: =H32/H28 -> #REF! | I33: =I32/I28 -> #REF! | J33: =J32/J28 -> #REF! | K33: =K32/K28 -> #REF!
B35: Selling, General & Administrative (SG&A) | G35: =-G69*G18 -> #REF! | H35: =-H69*H18 -> #REF! | I35: =-I69*I18 -> #REF! | J35: =-J69*J18 -> #REF! | K35: =-K69*K18 -> #REF! | M35: Revenue x SG&A % of sales forecast
B36: Research & Development (R&D) | G36: =-G18*G70 -> #REF! | H36: =-H18*H70 -> #REF! | I36: =-I18*I70 -> #REF! | J36: =-J18*J70 -> #REF! | K36: =-K18*K70 -> #REF! | M36: Revenue x R&D % of sales forecast
B37: Restructuring Charges & Other Impairments | G37: =-G27*G71 -> #REF! | H37: =-H27*H71 -> #REF! | I37: =-I27*I71 -> #REF! | J37: =-J27*J71 -> #REF! | K37: =-K27*K71 -> #REF! | M37: Consensus
B38: Operating profit (EBIT) | C38: =C32+C35+C36+C37 -> #REF! | D38: =D32+D35+D36+D37 -> #REF! | E38: =E32+E35+E36+E37 -> #REF! | F38: =F32+F35+F36+F37 -> #REF! | G38: =G32+G35+G36+G37 -> #REF! | H38: =H32+H35+H36+H37 -> #REF! | I38: =I32+I35+I36+I37 -> #REF! | J38: =J32+J35+J36+J37 -> #REF! | K38: =K32+K35+K36+K37 -> #REF!
B39: Margin (%) | C39: =C38/C28 -> #REF! | D39: =D38/D28 -> #REF! | E39: =E38/E28 -> #REF! | F39: =F38/F28 -> #REF! | G39: =G38/G28 -> #REF! | H39: =H38/H28 -> #REF! | I39: =I38/I28 -> #REF! | J39: =J38/J28 -> #REF! | K39: =K38/K28 -> #REF!
B41: Interest Income | M41: Reference from interest on cash schedule
B42: Interest expense | M42: Reference from interest expense schedule
B43: Other expense, net | G43: =F43 -> 0 | H43: =G43 -> 0 | I43: =H43 -> 0 | J43: =I43 -> 0 | K43: =J43 -> 0 | M43: Straight-line
B44: Pretax profit | C44: =SUM(C38:C43) -> #REF! | D44: =SUM(D38:D43) -> #REF! | E44: =SUM(E38:E43) -> #REF! | F44: =SUM(F38:F43) -> #REF! | G44: =SUM(G38:G43) -> #REF! | H44: =SUM(H38:H43) -> #REF! | I44: =SUM(I38:I43) -> #REF! | J44: =SUM(J38:J43) -> #REF! | K44: =SUM(K38:K43) -> #REF! | M44: EBIT + interest income less interest expense less other expense
B46: Taxes | G46: 0 | H46: 0 | I46: 0 | J46: 0 | K46: 0 | M46: Pre-tax Profit x Tax Rate forecast
B47: Net income | C47: =SUM(C44:C46) -> #REF! | D47: =SUM(D44:D46) -> #REF! | E47: =SUM(E44:E46) -> #REF! | F47: =SUM(F44:F46) -> #REF! | G47: =SUM(G44:G46) -> #REF! | H47: =SUM(H44:H46) -> #REF! | I47: =SUM(I44:I46) -> #REF! | J47: =SUM(J44:J46) -> #REF! | K47: =SUM(K44:K46) -> #REF! | M47: Pre-tax Profit less taxes
B48: Margin (%) | C48: =C47/C28 -> #REF! | D48: =D47/D28 -> #REF! | E48: =E47/E28 -> #REF! | F48: =F47/F28 -> #REF! | G48: =G47/G28 -> #REF! | H48: =H47/H28 -> #REF! | I48: =I47/I28 -> #REF! | J48: =J47/J28 -> #REF! | K48: =K47/K28 -> #REF!
B50: Depreciation & Amortization (D&A) | M50: Reference from D&A schedule
B51: EBITDA | C51: =C38+C50 -> #REF! | D51: =D38+D50 -> #REF! | E51: =E38+E50 -> #REF! | F51: =F38+F50 -> #REF! | G51: =G38+G50 -> #REF! | H51: =H38+H50 -> #REF! | I51: =I38+I50 -> #REF! | J51: =J38+J50 -> #REF! | K51: =K38+K50 -> #REF! | M51: EBIT + D&A
B52: Margin (%) | C52: =C51/C28 -> #REF! | D52: =D51/D28 -> #REF! | E52: =E51/E28 -> #REF! | F52: =F51/F28 -> #REF! | G52: =G51/G28 -> #REF! | H52: =H51/H28 -> #REF! | I52: =I51/I28 -> #REF! | J52: =J51/J28 -> #REF! | K52: =K51/K28 -> #REF!
B54: Stock-Based Compensation (SBC) | G54: =+(F54*G60)+F54 -> 0 | H54: =+(G54*H60)+G54 -> 0 | I54: =+(H54*I60)+H54 -> 0 | J54: =+(I54*J60)+I54 -> 0 | K54: =+(J54*K60)+J54 -> 0 | M54: grow SBC in-line with revenue growth
B55: Adjusted EBITDA | C55: =SUM(C51:C54) -> #REF! | D55: =SUM(D51:D54) -> #REF! | E55: =SUM(E51:E54) -> #REF! | F55: =SUM(F51:F54) -> #REF! | G55: =SUM(G51:G54) -> #REF! | H55: =SUM(H51:H54) -> #REF! | I55: =SUM(I51:I54) -> #REF! | J55: =SUM(J51:J54) -> #REF! | K55: =SUM(K51:K54) -> #REF! | M55: EBITDA + Stock-based compensation
B56: Margin (%) | C56: =C55/C28 -> #REF! | D56: =D55/D28 -> #REF! | E56: =E55/E28 -> #REF! | F56: =F55/F28 -> #REF! | G56: =G55/G28 -> #REF! | H56: =H55/H28 -> #REF! | I56: =I55/I28 -> #REF! | J56: =J55/J28 -> #REF! | K56: =K55/K28 -> #REF!
B58: Growth rates & margins
B60: Revenue growth | D60: =D28/C28-1 -> #REF! | E60: =E28/D28-1 -> #REF! | F60: =F28/E28-1 -> #REF! | M60: Consensus estimates
B61: Google Search & Other | D61: =SUM(D18/C18)-1 -> #REF! | E61: =SUM(E18/D18)-1 -> #REF! | F61: =SUM(F18/E18)-1 -> #REF! | M61: Consensus estimates
B66: Foodservice | D66: =SUM(D27/C27)-1 -> #DIV/0! | E66: =SUM(E27/D27)-1 -> #DIV/0! | F66: =SUM(F27/E27)-1 -> #DIV/0! | M66: Consensus estimates
B68: Gross profit margin | C68: =C32/C28 -> #REF! | D68: =D32/D28 -> #REF! | E68: =E32/E28 -> #REF! | F68: =F32/F28 -> #REF! | M68: BofA Estimate
B69: R&D % of sales | C69: =-C35/C18 -> #REF! | D69: =-D35/D18 -> #REF! | E69: =-E35/E18 -> #REF! | F69: =-F35/F18 -> #REF! | M69: Consensus estimates
B70: SG&A % of sales | C70: =-C36/C18 -> #REF! | D70: =-D36/D18 -> #REF! | E70: =-E36/E18 -> #REF! | F70: =-F36/F18 -> #REF! | M70: Consensus estimates
B71: Tax rate | C71: =-(C46/C44) -> #REF! | D71: =-(D46/D44) -> #REF! | E71: =-(E46/E44) -> #REF! | F71: =-(F46/F44) -> #REF! | G71: =F71 -> #REF! | H71: =G71 -> #REF! | I71: =H71 -> #REF! | J71: =I71 -> #REF! | K71: =J71 -> #REF! | M71: straight line
B73: D&A | D73: =D50/C50-1 -> #DIV/0! | E73: =E50/D50-1 -> #DIV/0! | F73: =F50/E50-1 -> #DIV/0! | M73: Consensus estimates
B74: SBC | D74: =D54/C54-1 -> #DIV/0! | E74: =E54/D54-1 -> #DIV/0! | F74: =F54/E54-1 -> #DIV/0! | M74: Consensus estimates
A76: X | B76: Balance Sheet | C76: Actuals | G76: Forecast
B77: =B15 -> Fiscal year | C77: =C15 -> 2021 | D77: =D15 -> 2022 | E77: =E15 -> 2023 | F77: =F15 -> 2024 | G77: =G15 -> 2025 | H77: =H15 -> 2026 | I77: =I15 -> 2027 | ... K77: =K15 -> 2029
B78: =B16 -> Fiscal year end date | C78: =C16 -> 44561 | D78: =D16 -> 44926 | E78: =E16 -> 45291 | F78: =F16 -> 45657 | G78: =G16 -> 46022 | H78: =H16 -> 46387 | I78: =I16 -> 46752 | ... K78: =K16 -> 47483
B80: Cash & equivalents, ST and LT marketable securities | G80: =+F80+G125 -> #REF! | H80: =+G80+H125 -> #REF! | I80: =+H80+I125 -> #REF! | J80: =+I80+J125 -> #REF! | K80: =+J80+K125 -> #REF! | M80: Reference from 'net change in cash' line on the cash flow statement
B81: Accounts receivable | G81: =F81*(1+G60) -> 0 | H81: =G81*(1+H60) -> 0 | I81: =H81*(1+I60) -> 0 | J81: =I81*(1+J60) -> 0 | K81: =J81*(1+K60) -> 0 | M81: Grow in-line with revenue growth
B82: Inventories | G82: =F82*G31/F31 -> #REF! | H82: =G82*H31/G31 -> #REF! | I82: =H82*I31/H31 -> #REF! | J82: =I82*J31/I31 -> #REF! | K82: =J82*K31/J31 -> #REF! | M82: Grow in-line with cost of sales growth
B83: Other current assets | G83: =F83*(1+G60) -> 0 | H83: =G83*(1+H60) -> 0 | I83: =H83*(1+I60) -> 0 | J83: =I83*(1+J60) -> 0 | K83: =J83*(1+K60) -> 0 | M83: Grow in-line with revenue growth
B84: Property, plant & equipment | M84: Reference from PP&E schedule
B85: Other non current assets | G85: =F85*(1+G60) -> 0 | H85: =G85*(1+H60) -> 0 | I85: =H85*(1+I60) -> 0 | J85: =I85*(1+J60) -> 0 | K85: =J85*(1+K60) -> 0 | M85: Grow in-line with revenue growth
B86: Total Assets | C86: =SUM(C80:C85) -> 0 | D86: =SUM(D80:D85) -> 0 | E86: =SUM(E80:E85) -> 0 | F86: =SUM(F80:F85) -> 0 | G86: =SUM(G80:G85) -> #REF! | H86: =SUM(H80:H85) -> #REF! | I86: =SUM(I80:I85) -> #REF! | J86: =SUM(J80:J85) -> #REF! | K86: =SUM(K80:K85) -> #REF!
B88: Accounts payable | G88: =F88*G31/F31 -> #REF! | H88: =G88*H31/G31 -> #REF! | I88: =H88*I31/H31 -> #REF! | J88: =I88*J31/I31 -> #REF! | K88: =J88*K31/J31 -> #REF! | M88: Grow in-line with cost of sales growth
B89: Other current liabilities | G89: =F89*(1+G60) -> 0 | H89: =G89*(1+H60) -> 0 | I89: =H89*(1+I60) -> 0 | J89: =I89*(1+J60) -> 0 | K89: =J89*(1+K60) -> 0 | M89: Grow in-line with revenue growth
B90: Deferred revenue (current) | G90: =F90*(1+G60) -> 0 | H90: =G90*(1+H60) -> 0 | I90: =H90*(1+I60) -> 0 | J90: =I90*(1+J60) -> 0 | K90: =J90*(1+K60) -> 0 | M90: Grow in-line with revenue growth
B91: Commercial paper / revolver | G91: =G175 -> #REF! | H91: =H175 -> #REF! | I91: =I175 -> #REF! | J91: =J175 -> #REF! | K91: =K175 -> #REF! | M91: Reference EOP balance from CP/revolver schedule
B92: Long term debt (includes current portion) | G92: =F92 -> 0 | H92: =G92 -> 0 | I92: =H92 -> 0 | J92: =I92 -> 0 | K92: =J92 -> 0 | M92: straight-line
B93: Other non current liabilities | G93: =F93*(1+G60) -> 0 | H93: =G93*(1+H60) -> 0 | I93: =H93*(1+I60) -> 0 | J93: =I93*(1+J60) -> 0 | K93: =J93*(1+K60) -> 0 | M93: Grow in-line with revenue growth
B94: Total liabilities | C94: =SUM(C88:C93) -> 0 | D94: =SUM(D88:D93) -> 0 | E94: =SUM(E88:E93) -> 0 | F94: =SUM(F88:F93) -> 0 | G94: =SUM(G88:G93) -> #REF! | H94: =SUM(H88:H93) -> #REF! | I94: =SUM(I88:I93) -> #REF! | J94: =SUM(J88:J93) -> #REF! | K94: =SUM(K88:K93) -> #REF!
B96: Common stock | G96: =F96+G54 -> 0 | H96: =G96+H54 -> 0 | I96: =H96+I54 -> 0 | J96: =I96+J54 -> 0 | K96: =J96+K54 -> 0 | M96: Increase by stock-based compensation forecasted in the I/S section
B97: Retained earnings | M97: Reference from Retained Earnings schedule
B98: Other comprehensive income | G98: =F98 -> 0 | H98: =G98 -> 0 | I98: =H98 -> 0 | J98: =I98 -> 0 | K98: =J98 -> 0 | M98: straight-line
B99: Total equity | C99: =SUM(C96:C98) -> 0 | D99: =SUM(D96:D98) -> 0 | E99: =SUM(E96:E98) -> 0 | F99: =SUM(F96:F98) -> 0 | G99: =SUM(G96:G98) -> 0 | H99: =SUM(H96:H98) -> 0 | I99: =SUM(I96:I98) -> 0 | J99: =SUM(J96:J98) -> 0 | K99: =SUM(K96:K98) -> 0
B100: Balance check | C100: =ROUND(C86-C94-C99,3) -> 0 | D100: =ROUND(D86-D94-D99,3) -> 0 | E100: =ROUND(E86-E94-E99,3) -> 0 | F100: =ROUND(F86-F94-F99,3) -> 0 | G100: =ROUND(G86-G94-G99,3) -> #REF! | H100: =ROUND(H86-H94-H99,3) -> #REF! | I100: =ROUND(I86-I94-I99,3) -> #REF! | J100: =ROUND(J86-J94-J99,3) -> #REF! | K100: =ROUND(K86-K94-K99,3) -> #REF!
A102: X | B102: Cash-Flows Statement | G102: Forecast
B103: =B15 -> Fiscal year | G103: =G15 -> 2025 | H103: =H15 -> 2026 | I103: =I15 -> 2027 | J103: =J15 -> 2028 | K103: =K15 -> 2029
B104: =B16 -> Fiscal year end date | G104: =G16 -> 46022 | H104: =H16 -> 46387 | I104: =I16 -> 46752 | J104: =J16 -> 47118 | K104: =K16 -> 47483
B106: Net income | G106: =G47 -> #REF! | H106: =H47 -> #REF! | I106: =I47 -> #REF! | J106: =J47 -> #REF! | K106: =K47 -> #REF! | M106: Reference from the I/S
B107: Depreciation and amortization | G107: =G50 -> 0 | H107: =H50 -> 0 | I107: =I50 -> 0 | J107: =J50 -> 0 | K107: =K50 -> 0 | M107: Reference from the I/S
B108: Stock based compensation | G108: =G54 -> 0 | H108: =H54 -> 0 | I108: =I54 -> 0 | J108: =J54 -> 0 | K108: =K54 -> 0
B109: Decreases / (Increases) in working capital assets | G109: =SUM(F81:F83)-SUM(G81:G83) -> #REF! | H109: =SUM(G81:G83)-SUM(H81:H83) -> #REF! | I109: =SUM(H81:H83)-SUM(I81:I83) -> #REF! | J109: =SUM(I81:I83)-SUM(J81:J83) -> #REF! | K109: =SUM(J81:J83)-SUM(K81:K83) -> #REF!
B110: Increases / (Decreases) in working capital liabilities | G110: =SUM(G88:G90)-SUM(F88:F90) -> #REF! | H110: =SUM(H88:H90)-SUM(G88:G90) -> #REF! | I110: =SUM(I88:I90)-SUM(H88:H90) -> #REF! | J110: =SUM(J88:J90)-SUM(I88:I90) -> #REF! | K110: =SUM(K88:K90)-SUM(J88:J90) -> #REF!
B111: Other non current assets | G111: =-G151 -> #REF! | H111: =-H151 -> #REF! | I111: =-I151 -> #REF! | J111: =-J151 -> #REF! | K111: =-K151 -> #REF! | M111: Reference from schedule NOT the B/S: Only include 'Additions' (as outflow)
B112: Other non current liabilities | G112: =G93-F93 -> 0 | H112: =H93-G93 -> 0 | I112: =I93-H93 -> 0 | J112: =J93-I93 -> 0 | K112: =K93-J93 -> 0
B113: Cash from Operating Activities | G113: =SUM(G106:G112) -> #REF! | H113: =SUM(H106:H112) -> #REF! | I113: =SUM(I106:I112) -> #REF! | J113: =SUM(J106:J112) -> #REF! | K113: =SUM(K106:K112) -> #REF!
B115: Capital Expenditures | G115: =-(G136) -> 0 | H115: =-(H136) -> 0 | I115: =-(I136) -> 0 | J115: =-(J136) -> 0 | K115: =-(K136) -> 0 | M115: Reference from PP&E schedule
B116: Cash from Investing Activities | G116: =IFERROR(G115,"NA") -> 0 | H116: =IFERROR(H115,"NA") -> 0 | I116: =IFERROR(I115,"NA") -> 0 | J116: =IFERROR(J115,"NA") -> 0 | K116: =IFERROR(K115,"NA") -> 0
B118: Long term debt | G118: =G92-F92 -> 0 | H118: =H92-G92 -> 0 | I118: =I92-H92 -> 0 | J118: =J92-I92 -> 0 | K118: =K92-J92 -> 0
B119: Commercial paper/ Revolver | G119: =G91-F91 -> #REF! | H119: =H91-G91 -> #REF! | I119: =I91-H91 -> #REF! | J119: =J91-I91 -> #REF! | K119: =K91-J91 -> #REF! | M119: Reference from B/S
B120: Share repurchases | G120: =G158 -> 0 | H120: =H158 -> 0 | I120: =I158 -> 0 | J120: =J158 -> 0 | K120: =K158 -> 0 | M120: Reference from Retained Earnings schedule
B121: Common dividends | G121: =G157 -> #REF! | H121: =H157 -> #REF! | I121: =I157 -> #REF! | J121: =J157 -> #REF! | K121: =K157 -> #REF! | M121: Reference from Retained Earnings schedule
B122: Common dividends | G122: =G158 -> 0 | H122: =H158 -> 0 | I122: =I158 -> 0 | J122: =J158 -> 0 | K122: =K158 -> 0 | M122: Reference from Retained Earnings schedule
B123: Cash from Financing Activities | G123: =SUM(G118:G121) -> #REF! | H123: =SUM(H118:H121) -> #REF! | I123: =SUM(I118:I121) -> #REF! | J123: =SUM(J118:J121) -> #REF! | K123: =SUM(K118:K121) -> #REF!
B125: Net change in cash during period | G125: =G113+G116+G123 -> #REF! | H125: =H113+H116+H123 -> #REF! | I125: =I113+I116+I123 -> #REF! | J125: =J113+J116+J123 -> #REF! | K125: =K113+K116+K123 -> #REF!
A127: X | B127: Supporting Schedules | C127: Actuals | G127: Forecast
B128: Fiscal year | C128: 2021 | D128: 2022 | E128: 2023 | F128: 2024 | G128: 2025 | H128: 2026 | I128: 2027 | J128: 2028 | K128: 2029
B129: Fiscal year end date | C129: 44469 | D129: 44834 | E129: 45199 | F129: 45559 | G129: 45930 | H129: 46295 | I129: 46660 | J129: 47026 | K129: 47391
A131: X | B131: PROPERTY, PLANT & EQUIPMENT
B132: =B15 -> Fiscal year | D132: =D15 -> 2022 | E132: =E15 -> 2023 | F132: =F15 -> 2024 | G132: =G15 -> 2025 | H132: =H15 -> 2026 | I132: =I15 -> 2027 | J132: =J15 -> 2028 | K132: =K15 -> 2029
B133: =B16 -> Fiscal year end date | D133: =D16 -> 44926 | E133: =E16 -> 45291 | F133: =F16 -> 45657 | G133: =G16 -> 46022 | H133: =H16 -> 46387 | I133: =I16 -> 46752 | J133: =J16 -> 47118 | K133: =K16 -> 47483
G134: Forecast
...

Sheet Sheet1
B2: ='Historical Financials'!B2 -> Netflix, Inc. (NASDAQ: NFLX)
B3: 3-Statement Model
B4: $ mm except per share
B6: Company name | C6: Alphabet Inc | O6: Select an operating scenario: | Q6: Base case
B7: Ticker | C7: GOOG
B8: Circ break 1=off, 0=on | C8: 0
B9: Latest closing share price
B10: Latest closing share price date
B11: Latest fiscal year end date
B12: Shares outstanding (millions)
B14: Income Statement | C14: Actuals | J14: CAGR | L14: Forecast | S14: CAGR
B15: Fiscal year | C15: 2019 | D15: 2020 | E15: 2021 | F15: 2022 | G15: 2023 | H15: 2024 | J15: 5-Year(A) | L15: =H15+1 -> 2025 | M15: =+L15+1 -> 2026 | N15: =+M15+1 -> 2027 | O15: =+N15+1 -> 2028 | P15: =+O15+1 -> 2029 | Q15: =+P15+1 -> 2030 | S15: 5-Year(F)
B16: Fiscal year end date | C16: 43830 | D16: 44196 | E16: 44561 | F16: 44926 | G16: 45291 | H16: 45657 | J16: =H16 -> 45657 | L16: =EOMONTH(H16,12) -> 46022 | M16: =EOMONTH(L16,12) -> 46387 | N16: =EOMONTH(M16,12) -> 46752 | O16: =EOMONTH(N16,12) -> 47118 | P16: =EOMONTH(O16,12) -> 47483 | Q16: =EOMONTH(P16,12) -> 47848 | S16: =Q16 -> 47848
B18: Google Search & Other | J18: =((H18/C18)^(1/COUNT(D18:H18))-1) -> #DIV/0! | S18: =((Q18/L18)^(1/COUNT(L18:Q18))-1) -> #DIV/0!
B19: YouTube ads | J19: =((H19/C19)^(1/COUNT(D19:H19))-1) -> #DIV/0! | S19: =((Q19/L19)^(1/COUNT(L19:Q19))-1) -> #DIV/0!
B20: Google Network | J20: =((H20/C20)^(1/COUNT(D20:H20))-1) -> #DIV/0! | S20: =((Q20/L20)^(1/COUNT(L20:Q20))-1) -> #DIV/0!
B21: Total Advertising Revenue | C21: =SUM(C18:C20) -> 0 | D21: =SUM(D18:D20) -> 0 | E21: =SUM(E18:E20) -> 0 | F21: =SUM(F18:F20) -> 0 | G21: =SUM(G18:G20) -> 0 | H21: =SUM(H18:H20) -> 0 | J21: =((H21/C21)^(1/COUNT(D21:H21))-1) -> #DIV/0! | L21: =SUM(L18:L20) -> 0 | M21: =SUM(M18:M20) -> 0 | N21: =SUM(N18:N20) -> 0 | O21: =SUM(O18:O20) -> 0 | P21: =SUM(P18:P20) -> 0 | Q21: =SUM(Q18:Q20) -> 0 | S21: =((Q21/L21)^(1/COUNT(L21:Q21))-1) -> #DIV/0!
B23: Google subscriptions, platforms, and devices | J23: =((H23/C23)^(1/COUNT(D23:H23))-1) -> #DIV/0! | S23: =((Q23/L23)^(1/COUNT(L23:Q23))-1) -> #DIV/0!
B24: Total Google Services Revenue | C24: =+C23+C21 -> 0 | D24: =+D23+D21 -> 0 | E24: =+E23+E21 -> 0 | F24: =+F23+F21 -> 0 | G24: =+G23+G21 -> 0 | H24: =+H23+H21 -> 0 | J24: =((H24/C24)^(1/COUNT(D24:H24))-1) -> #DIV/0! | L24: =+L23+L21 -> 0 | M24: =+M23+M21 -> 0 | N24: =+N23+N21 -> 0 | O24: =+O23+O21 -> 0 | P24: =+P23+P21 -> 0 | Q24: =+Q23+Q21 -> 0 | S24: =((Q24/L24)^(1/COUNT(L24:Q24))-1) -> #DIV/0!
B26: Google Cloud | J26: =((H26/C26)^(1/COUNT(D26:H26))-1) -> #DIV/0! | S26: =((Q26/L26)^(1/COUNT(L26:Q26))-1) -> #DIV/0!
B27: Other Bets | J27: =((H27/C27)^(1/COUNT(D27:H27))-1) -> #DIV/0! | S27: =((Q27/L27)^(1/COUNT(L27:Q27))-1) -> #DIV/0!
B28: Hedging gains (losses) | J28: =((H28/C28)^(1/COUNT(D28:H28))-1) -> #DIV/0! | S28: =((Q28/L28)^(1/COUNT(L28:Q28))-1) -> #DIV/0!
B29: Total Revenue | C29: =SUM(C26:C28)+C24 -> 0 | D29: =SUM(D26:D28)+D24 -> 0 | E29: =SUM(E26:E28)+E24 -> 0 | F29: =SUM(F26:F28)+F24 -> 0 | G29: =SUM(G26:G28)+G24 -> 0 | H29: =SUM(H26:H28)+H24 -> 0 | J29: =((H29/C29)^(1/COUNT(D29:H29))-1) -> #DIV/0! | L29: =SUM(L26:L28)+L24 -> 0 | M29: =SUM(M26:M28)+M24 -> 0 | N29: =SUM(N26:N28)+N24 -> 0 | O29: =SUM(O26:O28)+O24 -> 0 | P29: =SUM(P26:P28)+P24 -> 0 | Q29: =SUM(Q26:Q28)+Q24 -> 0 | S29: =((Q29/L29)^(1/COUNT(L29:Q29))-1) -> #DIV/0!
B31: Cost of sales | J31: =((H31/C31)^(1/COUNT(D31:H31))-1) -> #DIV/0! | S31: =((Q31/L31)^(1/COUNT(L31:Q31))-1) -> #DIV/0!
B32: Gross Profit | C32: =+C31+C29 -> 0 | D32: =+D31+D29 -> 0 | E32: =+E31+E29 -> 0 | F32: =+F31+F29 -> 0 | G32: =+G31+G29 -> 0 | H32: =+H31+H29 -> 0 | J32: =((H32/C32)^(1/COUNT(D32:H32))-1) -> #DIV/0! | L32: =+L29*L66 -> #DIV/0! | M32: =+M29*M66 -> #DIV/0! | N32: =+N29*N66 -> 0 | O32: =+O29*O66 -> 0 | P32: =+P29*P66 -> 0 | Q32: =+Q29*Q66 -> 0 | S32: =((Q32/L32)^(1/COUNT(L32:Q32))-1) -> #DIV/0!
B34: Research & Development (R&D) | J34: =((H34/C34)^(1/COUNT(D34:H34))-1) -> #DIV/0! | S34: =((Q34/L34)^(1/COUNT(L34:Q34))-1) -> #DIV/0!
B35: Sales and Marketing (S&M) | J35: =((H35/C35)^(1/COUNT(D35:H35))-1) -> #DIV/0! | S35: =((Q35/L35)^(1/COUNT(L35:Q35))-1) -> #DIV/0!
B36: General and Administrative (G&A) | J36: =((H36/C36)^(1/COUNT(D36:H36))-1) -> #DIV/0! | S36: =((Q36/L36)^(1/COUNT(L36:Q36))-1) -> #DIV/0!
B37: Operating profit (EBIT) | C37: =SUM(C34:C36)+C32 -> 0 | D37: =SUM(D34:D36)+D32 -> 0 | E37: =SUM(E34:E36)+E32 -> 0 | F37: =SUM(F34:F36)+F32 -> 0 | G37: =SUM(G34:G36)+G32 -> 0 | H37: =SUM(H34:H36)+H32 -> 0 | J37: =((H37/C37)^(1/COUNT(D37:H37))-1) -> #DIV/0! | L37: =SUM(L34:L36)+L32 -> #DIV/0! | M37: =SUM(M34:M36)+M32 -> #DIV/0! | N37: =SUM(N34:N36)+N32 -> 0 | O37: =SUM(O34:O36)+O32 -> 0 | P37: =SUM(P34:P36)+P32 -> 0 | Q37: =SUM(Q34:Q36)+Q32 -> 0 | S37: =((Q37/L37)^(1/COUNT(L37:Q37))-1) -> #DIV/0!
B39: Interest Income | J39: =((H39/C39)^(1/COUNT(D39:H39))-1) -> #DIV/0! | S39: =((Q39/L39)^(1/COUNT(L39:Q39))-1) -> #DIV/0! | U39: Reference from interest on cash schedule
B40: Interest Expense | J40: =((H40/C40)^(1/COUNT(D40:H40))-1) -> #DIV/0! | S40: =((Q40/L40)^(1/COUNT(L40:Q40))-1) -> #DIV/0! | U40: Reference from interest expense schedule
B41: Other Income/Gains (Expenses/Losses) | J41: =((H41/C41)^(1/COUNT(D41:H41))-1) -> #DIV/0! | S41: =((Q41/L41)^(1/COUNT(L41:Q41))-1) -> #DIV/0! | U41: Straight-line
B42: Pretax profit | C42: =SUM(C39:C41)+C37 -> 0 | D42: =SUM(D39:D41)+D37 -> 0 | E42: =SUM(E39:E41)+E37 -> 0 | F42: =SUM(F39:F41)+F37 -> 0 | G42: =SUM(G39:G41)+G37 -> 0 | H42: =SUM(H39:H41)+H37 -> 0 | J42: =((H42/C42)^(1/COUNT(D42:H42))-1) -> #DIV/0! | L42: =SUM(L39:L41)+L37 -> #DIV/0! | M42: =SUM(M39:M41)+M37 -> #DIV/0! | N42: =SUM(N39:N41)+N37 -> 0 | O42: =SUM(O39:O41)+O37 -> 0 | P42: =SUM(P39:P41)+P37 -> 0 | Q42: =SUM(Q39:Q41)+Q37 -> 0 | S42: =((Q42/L42)^(1/COUNT(L42:Q42))-1) -> #DIV/0!
B44: Taxes | J44: =((H44/C44)^(1/COUNT(D44:H44))-1) -> #DIV/0! | S44: =((Q44/L44)^(1/COUNT(L44:Q44))-1) -> #DIV/0!
B45: Net income | C45: =+C42+C44 -> 0 | D45: =+D42+D44 -> 0 | E45: =+E42+E44 -> 0 | F45: =+F42+F44 -> 0 | G45: =+G42+G44 -> 0 | H45: =+H42+H44 -> 0 | J45: =((H45/C45)^(1/COUNT(D45:H45))-1) -> #DIV/0! | L45: =+L42+L44 -> #DIV/0! | M45: =+M42+M44 -> #DIV/0! | N45: =+N42+N44 -> 0 | O45: =+O42+O44 -> 0 | P45: =+P42+P44 -> 0 | Q45: =+Q42+Q44 -> 0 | S45: =((Q45/L45)^(1/COUNT(L45:Q45))-1) -> #DIV/0!
B47: Depreciation & Amortization | J47: =((H47/C47)^(1/COUNT(D47:H47))-1) -> #DIV/0! | S47: =((Q47/L47)^(1/COUNT(L47:Q47))-1) -> #DIV/0! | U47: Reference from D&A schedule
B48: EBITDA | C48: =+C37+C47 -> 0 | D48: =+D37+D47 -> 0 | E48: =+E37+E47 -> 0 | F48: =+F37+F47 -> 0 | G48: =+G37+G47 -> 0 | H48: =+H37+H47 -> 0 | J48: =((H48/C48)^(1/COUNT(D48:H48))-1) -> #DIV/0! | L48: =+L37+L47 -> #DIV/0! | M48: =+M37+M47 -> #DIV/0! | N48: =+N37+N47 -> 0 | O48: =+O37+O47 -> 0 | P48: =+P37+P47 -> 0 | Q48: =+Q37+Q47 -> 0 | S48: =((Q48/L48)^(1/COUNT(L48:Q48))-1) -> #DIV/0!
B50: Stock Based Compensation | J50: =((H50/C50)^(1/COUNT(D50:H50))-1) -> #DIV/0! | S50: =((Q50/L50)^(1/COUNT(L50:Q50))-1) -> #DIV/0!
B51: Adj. EBITDA | C51: =+C48+C50 -> 0 | D51: =+D48+D50 -> 0 | E51: =+E48+E50 -> 0 | F51: =+F48+F50 -> 0 | G51: =+G48+G50 -> 0 | H51: =+H48+H50 -> 0 | J51: =((H51/C51)^(1/COUNT(D51:H51))-1) -> #DIV/0! | L51: =+L48+L50 -> #DIV/0! | M51: =+M48+M50 -> #DIV/0! | N51: =+N48+N50 -> 0 | O51: =+O48+O50 -> 0 | P51: =+P48+P50 -> 0 | Q51: =+Q48+Q50 -> 0 | S51: =((Q51/L51)^(1/COUNT(L51:Q51))-1) -> #DIV/0!
B53: Growth rates & margins
B55: Revenue growth
B56: Consolidated Revenue growth | D56: =SUM(D29/C29)-1 -> #DIV/0! | E56: =SUM(E29/D29)-1 -> #DIV/0! | F56: =SUM(F29/E29)-1 -> #DIV/0! | G56: =SUM(G29/F29)-1 -> #DIV/0! | H56: =SUM(H29/G29)-1 -> #DIV/0! | L56: =SUM(L29/H29)-1 -> #DIV/0! | M56: =SUM(M29/L29)-1 -> #DIV/0! | N56: =SUM(N29/M29)-1 -> #DIV/0! | O56: =SUM(O29/N29)-1 -> #DIV/0! | P56: =SUM(P29/O29)-1 -> #DIV/0! | Q56: =SUM(Q29/P29)-1 -> #DIV/0!
B57: Google Search & Other | D57: =SUM(D18/C18)-1 -> #DIV/0! | E57: =SUM(E18/D18)-1 -> #DIV/0! | F57: =SUM(F18/E18)-1 -> #DIV/0! | G57: =SUM(G18/F18)-1 -> #DIV/0! | H57: =SUM(H18/G18)-1 -> #DIV/0! | L57: =SUM(L18/H18)-1 -> #DIV/0! | M57: =SUM(M18/L18)-1 -> #DIV/0! | N57: =SUM(N18/M18)-1 -> #DIV/0! | O57: 0.08 | P57: 0.08 | Q57: 0.08
B58: YouTube ads | D58: =SUM(D19/C19)-1 -> #DIV/0! | E58: =SUM(E19/D19)-1 -> #DIV/0! | F58: =SUM(F19/E19)-1 -> #DIV/0! | G58: =SUM(G19/F19)-1 -> #DIV/0! | H58: =SUM(H19/G19)-1 -> #DIV/0! | L58: =SUM(L19/H19)-1 -> #DIV/0! | M58: =SUM(M19/L19)-1 -> #DIV/0! | N58: =SUM(N19/M19)-1 -> #DIV/0! | O58: 0.11 | P58: 0.1 | Q58: 0.09
B59: Google Network | D59: =SUM(D20/C20)-1 -> #DIV/0! | E59: =SUM(E20/D20)-1 -> #DIV/0! | F59: =SUM(F20/E20)-1 -> #DIV/0! | G59: =SUM(G20/F20)-1 -> #DIV/0! | H59: =SUM(H20/G20)-1 -> #DIV/0! | L59: =SUM(L20/H20)-1 -> #DIV/0! | M59: =SUM(M20/L20)-1 -> #DIV/0! | N59: =SUM(N20/M20)-1 -> #DIV/0! | O59: =AVERAGE(L59:N59) -> #DIV/0! | P59: =AVERAGE(M59:O59) -> #DIV/0! | Q59: =AVERAGE(N59:P59) -> #DIV/0!
B60: Google subscriptions, platforms, and devices | D60: =SUM(D23/C23)-1 -> #DIV/0! | E60: =SUM(E23/D23)-1 -> #DIV/0! | F60: =SUM(F23/E23)-1 -> #DIV/0! | G60: =SUM(G23/F23)-1 -> #DIV/0! | H60: =SUM(H23/G23)-1 -> #DIV/0! | L60: =SUM(L21/H21)-1 -> #DIV/0! | M60: =SUM(M21/L21)-1 -> #DIV/0! | N60: =SUM(N21/M21)-1 -> #DIV/0! | O60: =SUM(O21/N21)-1 -> #DIV/0! | P60: =SUM(P21/O21)-1 -> #DIV/0! | Q60: =SUM(Q21/P21)-1 -> #DIV/0!
B61: Google Cloud | D61: =SUM(D26/C26)-1 -> #DIV/0! | E61: =SUM(E26/D26)-1 -> #DIV/0! | F61: =SUM(F26/E26)-1 -> #DIV/0! | G61: =SUM(G26/F26)-1 -> #DIV/0! | H61: =SUM(H26/G26)-1 -> #DIV/0! | L61: =SUM(L23/H23)-1 -> #DIV/0! | M61: =SUM(M23/L23)-1 -> #DIV/0! | N61: =SUM(N23/M23)-1 -> #DIV/0! | O61: =N61 -> #DIV/0! | P61: =O61 -> #DIV/0! | Q61: =P61 -> #DIV/0!
B62: Other Bets | D62: =SUM(D27/C27)-1 -> #DIV/0! | E62: =SUM(E27/D27)-1 -> #DIV/0! | F62: =SUM(F27/E27)-1 -> #DIV/0! | G62: =SUM(G27/F27)-1 -> #DIV/0! | H62: =SUM(H27/G27)-1 -> #DIV/0! | L62: =SUM(L23/H27)-1 -> #DIV/0! | M62: =SUM(M23/L23)-1 -> #DIV/0! | N62: =SUM(N23/M23)-1 -> #DIV/0! | O62: =SUM(O23/N23)-1 -> #DIV/0! | P62: =SUM(P23/O23)-1 -> #DIV/0! | Q62: 0.03
B63: Hedging gains (losses) | D63: =SUM(D28/C28)-1 -> #DIV/0! | E63: =SUM(E28/D28)-1 -> #DIV/0! | F63: =SUM(F28/E28)-1 -> #DIV/0! | G63: =SUM(G28/F28)-1 -> #DIV/0! | H63: =SUM(H28/G28)-1 -> #DIV/0! | L63: 0 | M63: 0 | N63: 0 | O63: 0 | P63: 0 | Q63: 0
B65: Margins
B66: Gross Margin | C66: =C32/C24 -> #DIV/0! | D66: =D32/D24 -> #DIV/0! | E66: =E32/E24 -> #DIV/0! | F66: =F32/F24 -> #DIV/0! | G66: =G32/G24 -> #DIV/0! | H66: =H32/H24 -> #DIV/0! | L66: =H66 -> #DIV/0! | M66: =L66 -> #DIV/0! | N66: =Drivers!E185 -> 0.68188306 | O66: =Drivers!F185 -> 0.68188306 | P66: =Drivers!G185 -> 0.68188306 | Q66: =Drivers!H185 -> 0.68188306 | S66: BofA Estimate
B67: EBIT Margin | C67: =C37/C29 -> #DIV/0! | D67: =D37/D29 -> #DIV/0! | E67: =E37/E29 -> #DIV/0! | F67: =F37/F29 -> #DIV/0! | G67: =G37/G29 -> #DIV/0! | H67: =H37/H29 -> #DIV/0! | L67: =L37/L29 -> #DIV/0! | M67: =M37/M29 -> #DIV/0! | N67: =N37/N29 -> #DIV/0! | O67: =O37/O29 -> #DIV/0! | P67: =P37/P29 -> #DIV/0! | Q67: =Q37/Q29 -> #DIV/0!
B68: Tax Rate | C68: =-C44/C42 -> #DIV/0! | D68: =-D44/D42 -> #DIV/0! | E68: =-E44/E42 -> #DIV/0! | F68: =-F44/F42 -> #DIV/0! | G68: =-G44/G42 -> #DIV/0! | H68: =-H44/H42 -> #DIV/0! | L68: =H68 -> #DIV/0! | M68: =Drivers!D136 -> 0.16866667 | N68: =Drivers!E136 -> 0.17033333 | O68: =Drivers!F136 -> 0.17033333 | P68: =Drivers!G136 -> 0.17033333 | Q68: =Drivers!H136 -> 0.17033333 | S68: Consensus Estimate
B69: EBITDA Margin | C69: =C48/C29 -> #DIV/0! | D69: =D48/D29 -> #DIV/0! | E69: =E48/E29 -> #DIV/0! | F69: =F48/F29 -> #DIV/0! | G69: =G48/G29 -> #DIV/0! | H69: =H48/H29 -> #DIV/0! | S69: Consensus Estimate
B70: Adj. EBITDA Margin | C70: =C51/C29 -> #DIV/0! | D70: =D51/D29 -> #DIV/0! | E70: =E51/E29 -> #DIV/0! | F70: =F51/F29 -> #DIV/0! | G70: =G51/G29 -> #DIV/0! | H70: =H51/H29 -> #DIV/0! | L70: =L51/L29 -> #DIV/0! | M70: =M51/M29 -> #DIV/0! | N70: =N51/N29 -> #DIV/0! | O70: =O51/O29 -> #DIV/0! | P70: =P51/P29 -> #DIV/0! | Q70: =Q51/Q29 -> #DIV/0! | S70: Consensus Estimate
B72: % of Sales
B73: R&D as a % of Sales | C73: =-C34/C29 -> #DIV/0! | D73: =-D34/D29 -> #DIV/0! | E73: =-E34/E29 -> #DIV/0! | F73: =-F34/F29 -> #DIV/0! | G73: =-G34/G29 -> #DIV/0! | H73: =-H34/H29 -> #DIV/0! | L73: =H73 -> #DIV/0! | M73: =Drivers!D107 -> 0.18599543 | N73: =Drivers!E107 -> 0.1636369 | O73: =Drivers!F107 -> 0.14688959 | P73: =Drivers!G107 -> 0.13818684 | Q73: =P73 -> 0.13818684
B74: S&M as a % of Sales | C74: =-C35/C29 -> #DIV/0! | D74: =-D35/D29 -> #DIV/0! | E74: =-E35/E29 -> #DIV/0! | F74: =-F35/F29 -> #DIV/0! | G74: =-G35/G29 -> #DIV/0! | H74: =-H35/H29 -> #DIV/0! | L74: =Drivers!C118 -> 0.081950394 | M74: =Drivers!D118 -> 0.073305517 | N74: =Drivers!E118 -> 0.068958619 | O74: =Drivers!F118 -> 0.068958619 | P74: =Drivers!G118 -> 0.068958619 | Q74: =Drivers!H118 -> 0.068958619
B75: G&A as a % of Sales | C75: =-C36/C29 -> #DIV/0! | D75: =-D36/D29 -> #DIV/0! | E75: =-E36/E29 -> #DIV/0! | F75: =-F36/F29 -> #DIV/0! | G75: =-G36/G29 -> #DIV/0! | H75: =-H36/H29 -> #DIV/0! | L75: =Drivers!C126 -> 0.060782011 | M75: =Drivers!D126 -> 0.041976927 | N75: =M75 -> 0.041976927 | O75: =N75 -> 0.041976927 | P75: =O75 -> 0.041976927 | Q75: =P75 -> 0.041976927
B76: D&A as a % of Sales | C76: =C47/C29 -> #DIV/0! | D76: =D47/D29 -> #DIV/0! | E76: =E47/E29 -> #DIV/0! | F76: =F47/F29 -> #DIV/0! | G76: =G47/G29 -> #DIV/0! | H76: =H47/H29 -> #DIV/0! | L76: =L47/L29 -> #DIV/0! | M76: =M47/M29 -> #DIV/0! | N76: =N47/N29 -> #DIV/0! | O76: =O47/O29 -> #DIV/0! | P76: =P47/P29 -> #DIV/0! | Q76: =Q47/Q29 -> #DIV/0!
B77: SBC as a % of Sales | C77: =C50/C29 -> #DIV/0! | D77: =D50/D29 -> #DIV/0! | E77: =E50/E29 -> #DIV/0! | F77: =F50/F29 -> #DIV/0! | G77: =G50/G29 -> #DIV/0! | H77: =H50/H29 -> #DIV/0! | L77: =L50/L29 -> #DIV/0! | M77: =M50/M29 -> #DIV/0! | N77: =N50/N29 -> #DIV/0! | O77: =O50/O29 -> #DIV/0! | P77: =P50/P29 -> #DIV/0! | Q77: =Q50/Q29 -> #DIV/0!
A79: X | B79: Balance Sheet | C79: Actuals | K79: Forecast
B80: =B15 -> Fiscal year | C80: =C15 -> 2019 | D80: =D15 -> 2020 | E80: =E15 -> 2021 | F80: =F15 -> 2022 | G80: =G15 -> 2023 | H80: =H15 -> 2024 | K80: =K20 -> 0 | L80: =L15 -> 2025 | M80: =M15 -> 2026 | N80: =N15 -> 2027 | O80: =O15 -> 2028 | P80: =P15 -> 2029 | Q80: =Q15 -> 2030
B81: =B16 -> Fiscal year end date | C81: =C16 -> 43830 | D81: =D16 -> 44196 | E81: =E16 -> 44561 | F81: =F16 -> 44926 | G81: =G16 -> 45291 | H81: =H16 -> 45657 | K81: =K21 -> 0 | L81: =L16 -> 46022 | M81: =M16 -> 46387 | N81: =N16 -> 46752 | O81: =O16 -> 47118 | P81: =P16 -> 47483 | Q81: =Q16 -> 47848
B83: Current Assets
B84: Cash and Cash Equivalents | L84: =L146 -> #DIV/0! | M84: =M146 -> #DIV/0! | N84: =N146 -> #DIV/0! | O84: =O146 -> #DIV/0! | P84: =P146 -> #DIV/0! | Q84: =Q146 -> #DIV/0! | S84: Reference from 'net change in cash' line on the cash flow statement
B85: Marketable Securities | L85: =H85 -> 0 | M85: =L85 -> 0 | N85: =M85 -> 0 | O85: =N85 -> 0 | P85: =O85 -> 0 | Q85: =P85 -> 0
B86: Accounts Receivables | L86: =(H86*L56)+H86 -> #DIV/0! | M86: =(L86*M56)+L86 -> #DIV/0! | N86: =(M86*N56)+M86 -> #DIV/0! | O86: =(N86*O56)+N86 -> #DIV/0! | P86: =(O86*P56)+O86 -> #DIV/0! | Q86: =(P86*Q56)+P86 -> #DIV/0! | S86: Growth Assumption: Grow in-line with revenue
B87: Other Current Assets | L87: =(H87*L56)+H87 -> #DIV/0! | M87: =(L87*M56)+L87 -> #DIV/0! | N87: =(M87*N56)+M87 -> #DIV/0! | O87: =(N87*O56)+N87 -> #DIV/0! | P87: =(O87*P56)+O87 -> #DIV/0! | Q87: =(P87*Q56)+P87 -> #DIV/0! | S87: Growth Assumption: Grow in-line with revenue
