Workbook

Sheet Historical Financials
B2: Quantum Corporation (NASDAQ:QMCO)
B3: Historical Financials
B4: $ in thousands except per share
A6: X | B6: Income Statement | C6: FYE | G6: Quarterly | Q6: Quarterly | AB6: LTM | AH6: Variance
B7: Fiscal Period | C7: 2022 | D7: 2023 | E7: 2024 | G7: 1Q23 | H7: 2Q23 | I7: 3Q23 | J7: 4Q23 | K7: 1Q24 | L7: 2Q24 | M7: 3Q24 | N7: 4Q24 | O7: 1Q25 | P7: 2Q25 | V7: =J7 -> 4Q23 | W7: =K7 -> 1Q24 | X7: =L7 -> 2Q24 | Y7: =M7 -> 3Q24 | Z7: =N7 -> 4Q24 | AA7: =O7 -> 1Q25 | AB7: =P7 -> 2Q25 | AC7: =Q7 -> 0 | ... AF7: =T7 -> 0
B8: Fiscal Period End Date | C8: 44651 | D8: 45016 | E8: 45382 | G8: 44742 | H8: 44834 | I8: 44926 | J8: =D8 -> 45016 | K8: 45107 | L8: 45199 | M8: 45291 | N8: =E8 -> 45382 | O8: 45473 | P8: 45565 | V8: =J8 -> 45016 | W8: =K8 -> 45107 | X8: =L8 -> 45199 | Y8: =M8 -> 45291 | Z8: =N8 -> 45382 | AA8: =O8 -> 45473 | AB8: =P8 -> 45565 | AC8: =Q8 -> 0 | ... AF8: =T8 -> 0
B10: Consolidated Revenue | C10: 383432 | D10: 422077 | E10: 311600 | G10: 97074 | H10: 99137 | I10: 111196 | J10: =SUM(C10-SUM(G10:I10)) -> 76025 | K10: 91787 | L10: 75680 | M10: 71926 | N10: =SUM(D10-SUM(K10:M10)) -> 182684 | O10: 71343 | P10: 70469 | R10: =SUM(E10-SUM(O10:Q10)) -> 169788 | V10: =SUM(G10:J10) -> 383432 | W10: =SUM(H10:K10) -> 378145 | X10: =SUM(I10:L10) -> 354688 | Y10: =SUM(J10:M10) -> 315418 | Z10: =SUM(K10:N10) -> 422077 | AA10: =SUM(L10:O10) -> 401633 | AB10: =SUM(M10:P10) -> 396422 | AC10: =SUM(N10:Q10) -> 324496 | ... AF10: =SUM(Q10:T10) -> 169788 | AH10: =SUM(AF10/AB10)-1 -> -0.57169885
B11: Total Revenue | C11: =+SUM(C10:C10) -> 383432 | D11: =+SUM(D10:D10) -> 422077 | E11: =+SUM(E10:E10) -> 311600 | G11: =+SUM(G10:G10) -> 97074 | H11: =+SUM(H10:H10) -> 99137 | I11: =+SUM(I10:I10) -> 111196 | J11: =+SUM(J10:J10) -> 76025 | K11: =+SUM(K10:K10) -> 91787 | L11: =+SUM(L10:L10) -> 75680 | M11: =+SUM(M10:M10) -> 71926 | N11: =+SUM(N10:N10) -> 182684 | ... T11: =+SUM(T10:T10) -> 0 | V11: =+SUM(V10:V10) -> 383432 | W11: =+SUM(W10:W10) -> 378145 | X11: =+SUM(X10:X10) -> 354688 | Y11: =+SUM(Y10:Y10) -> 315418 | Z11: =+SUM(Z10:Z10) -> 422077 | AA11: =+SUM(AA10:AA10) -> 401633 | AB11: =+SUM(AB10:AB10) -> 396422 | AC11: =+SUM(AC10:AC10) -> 324496 | ... AF11: =+SUM(AF10:AF10) -> 169788 | AH11: =SUM(AF11/AB11)-1 -> -0.57169885
B13: Cost of Sales | C13: -225792 | D13: -278813 | E13: -186711 | G13: -63026 | H13: -71306 | I13: -70907 | J13: =SUM(C13-SUM(G13:I13)) -> -20553 | N13: =SUM(D13-SUM(K13:M13)) -> -278813 | R13: =SUM(E13-SUM(O13:Q13)) -> -186711 | V13: =SUM(H13:K13) -> -162766 | W13: =SUM(I13:L13) -> -91460 | X13: =SUM(J13:M13) -> -20553 | Y13: =SUM(K13:N13) -> -278813 | Z13: =SUM(L13:O13) -> -278813 | AA13: =SUM(M13:P13) -> -278813 | AB13: =SUM(M13:P13) -> -278813 | AC13: =SUM(N13:Q13) -> -278813 | AD13: =SUM(O13:R13) -> -186711 | AE13: =SUM(P13:S13) -> -186711 | AF13: =SUM(Q13:T13) -> -186711 | AH13: =SUM(AF13/AB13)-1 -> -0.3303361
B14: Gross Profit | C14: =+SUM(C11+SUM(C13:C13)) -> 157640 | D14: =+SUM(D11+SUM(D13:D13)) -> 143264 | E14: =+SUM(E11+SUM(E13:E13)) -> 124889 | G14: =+SUM(G11+SUM(G13:G13)) -> 34048 | H14: =+SUM(H11+SUM(H13:H13)) -> 27831 | I14: =+SUM(I11+SUM(I13:I13)) -> 40289 | J14: =+SUM(J11+SUM(J13:J13)) -> 55472 | K14: =+SUM(K11+SUM(K13:K13)) -> 91787 | L14: =+SUM(L11+SUM(L13:L13)) -> 75680 | M14: =+SUM(M11+SUM(M13:M13)) -> 71926 | N14: =+SUM(N11+SUM(N13:N13)) -> -96129 | ... T14: =+SUM(T11+SUM(T13:T13)) -> 0 | V14: =+SUM(V11+SUM(V13:V13)) -> 220666 | W14: =+SUM(W11+SUM(W13:W13)) -> 286685 | X14: =+SUM(X11+SUM(X13:X13)) -> 334135 | Y14: =+SUM(Y11+SUM(Y13:Y13)) -> 36605 | Z14: =+SUM(Z11+SUM(Z13:Z13)) -> 143264 | AA14: =+SUM(AA11+SUM(AA13:AA13)) -> 122820 | AB14: =+SUM(AB11+SUM(AB13:AB13)) -> 117609 | AC14: =+SUM(AC11+SUM(AC13:AC13)) -> 45683 | ... AF14: =+SUM(AF11+SUM(AF13:AF13)) -> -16923 | AH14: =SUM(AF14/AB14)-1 -> -1.143892
B15: Gross Margin (%) | C15: =C14/C11 -> 0.41112896 | D15: =D14/D11 -> 0.33942622 | E15: =E14/E11 -> 0.4007991 | G15: =G14/G11 -> 0.35074273 | H15: =H14/H11 -> 0.28073272 | I15: =I14/I11 -> 0.36232418 | J15: =J14/J11 -> 0.72965472 | K15: =K14/K11 -> 1 | L15: =L14/L11 -> 1 | M15: =M14/M11 -> 1 | N15: =N14/N11 -> -0.52620372 | ... T15: =T14/T11 -> #DIV/0! | V15: =V14/V11 -> 0.57550231 | W15: =W14/W11 -> 0.75813511 | X15: =X14/X11 -> 0.9420533 | Y15: =Y14/Y11 -> 0.11605235 | Z15: =Z14/Z11 -> 0.33942622 | AA15: =AA14/AA11 -> 0.30580157 | AB15: =AB14/AB11 -> 0.29667627 | AC15: =AC14/AC11 -> 0.1407814 | ... AF15: =AF14/AF11 -> -0.099671355 | AH15: =SUM(AF15-AB15)*1000 -> -396.34762
B17: Sales and marketing | C17: -62957 | D17: -66034 | E17: -60893 | G17: -15962 | H17: -15593 | I17: -16339 | J17: =SUM(C17-SUM(G17:I17)) -> -15063 | K17: -15839 | L17: -15717 | M17: -14244 | N17: =SUM(D17-SUM(K17:M17)) -> -20234 | O17: -13295 | P17: -13578 | R17: =SUM(E17-SUM(O17:Q17)) -> -34020 | V17: =SUM(H17:K17) -> -62834 | W17: =SUM(I17:L17) -> -62958 | X17: =SUM(J17:M17) -> -60863 | Y17: =SUM(K17:N17) -> -66034 | Z17: =SUM(L17:O17) -> -63490 | AA17: =SUM(M17:P17) -> -61351 | AB17: =SUM(M17:P17) -> -61351 | AC17: =SUM(N17:Q17) -> -47107 | AD17: =SUM(O17:R17) -> -60893 | AE17: =SUM(P17:S17) -> -47598 | AF17: =SUM(Q17:T17) -> -34020 | AH17: =SUM(AF17/AB17)-1 -> -0.44548581
B18: General and administrative | C18: -45256 | D18: -47752 | E18: -51547 | G18: -12314 | H18: -11940 | I18: -10969 | J18: =SUM(C18-SUM(G18:I18)) -> -10033 | K18: -12699 | L18: -10241 | M18: -11893 | N18: =SUM(D18-SUM(K18:M18)) -> -12919 | O18: -21065 | P18: -13977 | R18: =SUM(E18-SUM(O18:Q18)) -> -16505 | V18: =SUM(H18:K18) -> -45641 | W18: =SUM(I18:L18) -> -43942 | X18: =SUM(J18:M18) -> -44866 | Y18: =SUM(K18:N18) -> -47752 | Z18: =SUM(L18:O18) -> -56118 | AA18: =SUM(M18:P18) -> -59854 | AB18: =SUM(M18:P18) -> -59854 | AC18: =SUM(N18:Q18) -> -47961 | AD18: =SUM(O18:R18) -> -51547 | AE18: =SUM(P18:S18) -> -30482 | AF18: =SUM(Q18:T18) -> -16505 | AH18: =SUM(AF18/AB18)-1 -> -0.72424566
B19: Research and development | C19: -51812 | D19: -44555 | E19: -38046 | G19: -12125 | H19: -10546 | I19: -11254 | K19: -10913 | L19: -9152 | M19: -8763 | O19: -8308 | P19: -8264
B20: Restructuring charges | C20: -850 | D20: -1605 | E20: -3280 | G20: -725 | H20: -921 | I20: -41 | J20: =SUM(C20-SUM(G20:I20)) -> 837 | K20: -1329 | L20: -1338 | M20: -497 | N20: =SUM(D20-SUM(K20:M20)) -> 1559 | O20: -1192 | P20: -383 | R20: =SUM(E20-SUM(O20:Q20)) -> -1705 | V20: =SUM(H20:K20) -> -1454 | W20: =SUM(I20:L20) -> -1871 | X20: =SUM(J20:M20) -> -2327 | Y20: =SUM(K20:N20) -> -1605 | Z20: =SUM(L20:O20) -> -1468 | AA20: =SUM(M20:P20) -> -513 | AB20: =SUM(M20:P20) -> -513 | AC20: =SUM(N20:Q20) -> -16 | AD20: =SUM(O20:R20) -> -3280 | AE20: =SUM(P20:S20) -> -2088 | AF20: =SUM(Q20:T20) -> -1705 | AH20: =SUM(AF20/AB20)-1 -> 2.3235867
B21: Operating Profit | C21: =+SUM(C14+SUM(C17:C20)) -> -3235 | D21: =+SUM(D14+SUM(D17:D20)) -> -16682 | E21: =+SUM(E14+SUM(E17:E20)) -> -28877 | G21: =+SUM(G14+SUM(G17:G20)) -> -7078 | H21: =+SUM(H14+SUM(H17:H20)) -> -11169 | I21: =+SUM(I14+SUM(I17:I20)) -> 1686 | J21: =+SUM(J14+SUM(J17:J20)) -> 31213 | K21: =+SUM(K14+SUM(K17:K20)) -> 51007 | L21: =+SUM(L14+SUM(L17:L20)) -> 39232 | M21: =+SUM(M14+SUM(M17:M20)) -> 36529 | N21: =+SUM(N14+SUM(N17:N20)) -> -127723 | ... T21: =+SUM(T14+SUM(T17:T20)) -> 0 | V21: =+SUM(V14+SUM(V17:V20)) -> 110737 | W21: =+SUM(W14+SUM(W17:W20)) -> 177914 | X21: =+SUM(X14+SUM(X17:X20)) -> 226079 | Y21: =+SUM(Y14+SUM(Y17:Y20)) -> -78786 | Z21: =+SUM(Z14+SUM(Z17:Z20)) -> 22188 | AA21: =+SUM(AA14+SUM(AA17:AA20)) -> 1102 | AB21: =+SUM(AB14+SUM(AB17:AB20)) -> -4109 | AC21: =+SUM(AC14+SUM(AC17:AC20)) -> -49401 | ... AF21: =+SUM(AF14+SUM(AF17:AF20)) -> -69153 | AH21: =SUM(AF21/AB21)-1 -> 15.829642
B22: Operating Margin (%) | C22: =C21/C11 -> -0.0084369588 | D22: =D21/D11 -> -0.039523594 | E22: =E21/E11 -> -0.092673299 | G22: =G21/G11 -> -0.072913447 | H22: =H21/H11 -> -0.11266228 | I22: =I21/I11 -> 0.015162416 | J22: =J21/J11 -> 0.41056232 | K22: =K21/K11 -> 0.5557105 | L22: =L21/L11 -> 0.51839323 | M22: =M21/M11 -> 0.5078692 | N22: =N21/N11 -> -0.69914716 | ... T22: =T21/T11 -> #DIV/0! | V22: =V21/V11 -> 0.28880479 | W22: =W21/W11 -> 0.47049148 | X22: =X21/X11 -> 0.63740245 | Y22: =Y21/Y11 -> -0.24978283 | Z22: =Z21/Z11 -> 0.052568607 | AA22: =AA21/AA11 -> 0.0027437984 | AB22: =AB21/AB11 -> -0.010365217 | AC22: =AC21/AC11 -> -0.15223916 | ... AF22: =AF21/AF11 -> -0.40729027 | AH22: =SUM(AF22-AB22)*1000 -> -396.92505
B24: Other income (expense), net | C24: -251 | D24: 1956 | E24: -1746 | G24: 751 | H24: 2431 | I24: -544 | J24: =SUM(C24-SUM(G24:I24)) -> -2889 | K24: -998 | L24: 367 | M24: -1419 | N24: =SUM(D24-SUM(K24:M24)) -> 4006 | O24: -41 | P24: -1334 | R24: =SUM(E24-SUM(O24:Q24)) -> -371 | V24: =SUM(H24:K24) -> -2000 | W24: =SUM(I24:L24) -> -4064 | X24: =SUM(J24:M24) -> -4939 | Y24: =SUM(K24:N24) -> 1956 | Z24: =SUM(L24:O24) -> 2913 | AA24: =SUM(M24:P24) -> 1212 | AB24: =SUM(M24:P24) -> 1212 | AC24: =SUM(N24:Q24) -> 2631 | AD24: =SUM(O24:R24) -> -1746 | AE24: =SUM(P24:S24) -> -1705 | AF24: =SUM(Q24:T24) -> -371 | AH24: =SUM(AF24/AB24)-1 -> -1.3061056
B25: Interest expense | C25: -11888 | D25: -10560 | E25: -15089 | G25: -2091 | H25: -2745 | I25: -2701 | J25: =SUM(C25-SUM(G25:I25)) -> -4351 | K25: -3201 | L25: -3855 | M25: -3937 | N25: =SUM(D25-SUM(K25:M25)) -> 433 | O25: -3790 | P25: -6131 | R25: =SUM(E25-SUM(O25:Q25)) -> -5168 | AB25: =SUM(M25:P25) -> -13425 | AC25: =SUM(N25:Q25) -> -9488 | AD25: =SUM(O25:R25) -> -15089 | AE25: =SUM(P25:S25) -> -11299 | AF25: =SUM(Q25:T25) -> -5168 | AH25: =SUM(AF25/AB25)-1 -> -0.61504655
B26: Change in fair value of warrant liability | C26: 60030 | D26: 10250 | E26: 5137 | J26: =SUM(C26-SUM(G26:I26)) -> 60030 | K26: 0 | L26: 0 | M26: 2213 | N26: =SUM(D26-SUM(K26:M26)) -> 8037 | O26: 1666 | P26: 3550 | R26: =SUM(E26-SUM(O26:Q26)) -> -79 | AB26: =SUM(M26:P26) -> 15466 | AC26: =SUM(N26:Q26) -> 13253 | AD26: =SUM(O26:R26) -> 5137 | AE26: =SUM(P26:S26) -> 3471 | AF26: =SUM(Q26:T26) -> -79 | AH26: =SUM(AF26/AB26)-1 -> -1.005108
B27: Loss on debt extinguishment, net | C27: -4960 | D27: -1392 | E27: 0 | G27: -1392 | J27: =SUM(C27-SUM(G27:I27)) -> -3568 | K27: 0 | L27: 4402 | M27: 0 | N27: =SUM(D27-SUM(K27:M27)) -> -5794 | O27: -695 | P27: -2308 | R27: =SUM(E27-SUM(O27:Q27)) -> 3003 | AB27: =SUM(M27:P27) -> -8797 | AC27: =SUM(N27:Q27) -> -8797 | AD27: =SUM(O27:R27) -> 0 | AE27: =SUM(P27:S27) -> 695 | AF27: =SUM(Q27:T27) -> 3003 | AH27: =SUM(AF27/AB27)-1 -> -1.3413664
B28: Earning Before Taxes | C28: =SUM(C21+SUM(C24:C27)) -> 39696 | D28: =SUM(D21+SUM(D24:D27)) -> -16428 | E28: =SUM(E21+SUM(E24:E27)) -> -40575 | G28: =SUM(G21+SUM(G24:G27)) -> -9810 | H28: =SUM(H21+SUM(H24:H27)) -> -11483 | I28: =SUM(I21+SUM(I24:I27)) -> -1559 | J28: =SUM(J21+SUM(J24:J27)) -> 80435 | K28: =SUM(K21+SUM(K24:K27)) -> 46808 | L28: =SUM(L21+SUM(L24:L27)) -> 40146 | M28: =SUM(M21+SUM(M24:M27)) -> 33386 | N28: =SUM(N21+SUM(N24:N27)) -> -121041 | ... T28: =SUM(T21+SUM(T24:T27)) -> 0 | V28: =SUM(V21+SUM(V24:V27)) -> 108737 | W28: =SUM(W21+SUM(W24:W27)) -> 173850 | X28: =SUM(X21+SUM(X24:X27)) -> 221140 | Y28: =SUM(Y21+SUM(Y24:Y27)) -> -76830 | Z28: =SUM(Z21+SUM(Z24:Z27)) -> 25101 | AA28: =SUM(AA21+SUM(AA24:AA27)) -> 2314 | AB28: =SUM(AB21+SUM(AB24:AB27)) -> -9653 | AC28: =SUM(AC21+SUM(AC24:AC27)) -> -51802 | ... AF28: =SUM(AF21+SUM(AF24:AF27)) -> -71768 | AH28: =SUM(AF28/AB28)-1 -> 6.4347871
B29: EBT Margin (%) | C29: =C28/C11 -> 0.10352814 | D29: =D28/D11 -> -0.038921808 | E29: =E28/E11 -> -0.13021502 | G29: =G28/G11 -> -0.10105693 | H29: =H28/H11 -> -0.11582961 | I29: =I28/I11 -> -0.014020288 | J29: =J28/J11 -> 1.0580072 | K29: =K28/K11 -> 0.50996328 | L29: =L28/L11 -> 0.5304704 | M29: =M28/M11 -> 0.46417151 | N29: =N28/N11 -> -0.66257034 | ... T29: =T28/T11 -> #DIV/0! | V29: =V28/V11 -> 0.28358875 | W29: =W28/W11 -> 0.45974428 | X29: =X28/X11 -> 0.62347754 | Y29: =Y28/Y11 -> -0.24358153 | Z29: =Z28/Z11 -> 0.059470191 | AA29: =AA28/AA11 -> 0.0057614788 | AB29: =AB28/AB11 -> -0.024350314 | AC29: =AC28/AC11 -> -0.15963833 | ... AF29: =AF28/AF11 -> -0.42269183 | AH29: =SUM(AF29-AB29)*1000 -> -398.34151
B31: Provision for taxes | C31: -1341 | D31: -1940 | E31: -711 | G31: -410 | H31: -461 | I31: 693 | J31: =SUM(C31-SUM(G31:I31)) -> -1163 | K31: -530 | L31: -533 | M31: -510 | N31: =SUM(D31-SUM(K31:M31)) -> -367 | O31: -235 | P31: -370 | Q31: 0 | R31: =SUM(E31-SUM(O31:Q31)) -> -106 | S31: 0 | V31: =SUM(H31:K31) -> -1461 | W31: =SUM(I31:L31) -> -1533 | X31: =SUM(J31:M31) -> -2736 | Y31: =SUM(K31:N31) -> -1940 | Z31: =SUM(L31:O31) -> -1645 | AA31: =SUM(M31:P31) -> -1482 | AB31: =SUM(M31:P31) -> -1482 | AC31: =SUM(N31:Q31) -> -972 | AD31: =SUM(O31:R31) -> -711 | AE31: =SUM(P31:S31) -> -476 | AF31: =SUM(Q31:T31) -> -106 | AH31: =SUM(AF31/AB31)-1 -> -0.92847503
B32: Net loss | C32: =SUM(C28+C31) -> 38355 | D32: =SUM(D28+D31) -> -18368 | E32: =SUM(E28+E31) -> -41286 | G32: =SUM(G28+G31) -> -10220 | H32: =SUM(H28+H31) -> -11944 | I32: =SUM(I28+I31) -> -866 | J32: =SUM(J28+J31) -> 79272 | K32: =SUM(K28+K31) -> 46278 | L32: =SUM(L28+L31) -> 39613 | M32: =SUM(M28+M31) -> 32876 | N32: =SUM(N28+N31) -> -121408 | ... T32: =SUM(T28+T31) -> 0 | V32: =SUM(V28+V31) -> 107276 | W32: =SUM(W28+W31) -> 172317 | X32: =SUM(X28+X31) -> 218404 | Y32: =SUM(Y28+Y31) -> -78770 | Z32: =SUM(Z28+Z31) -> 23456 | AA32: =SUM(AA28+AA31) -> 832 | AB32: =SUM(AB28+AB31) -> -11135 | AC32: =SUM(AC28+AC31) -> -52774 | ... AF32: =SUM(AF28+AF31) -> -71874 | AH32: =SUM(AF32/AB32)-1 -> 5.4547822
B33: Net Margin (%) | C33: =C32/C11 -> 0.10003077 | D33: =D32/D11 -> -0.043518126 | E33: =E32/E11 -> -0.13249679 | G33: =G32/G11 -> -0.10528051 | H33: =H32/H11 -> -0.12047974 | I33: =I32/I11 -> -0.0077880499 | J33: =J32/J11 -> 1.0427096 | K33: =K32/K11 -> 0.50418905 | L33: =L32/L11 -> 0.52342759 | M33: =M32/M11 -> 0.45708089 | N33: =N32/N11 -> -0.66457927 | ... T33: =T32/T11 -> #DIV/0! | V33: =V32/V11 -> 0.27977842 | W33: =W32/W11 -> 0.45569028 | X33: =X32/X11 -> 0.61576371 | Y33: =Y32/Y11 -> -0.2497321 | Z33: =Z32/Z11 -> 0.055572798 | AA33: =AA32/AA11 -> 0.0020715429 | AB33: =AB32/AB11 -> -0.028088754 | AC33: =AC32/AC11 -> -0.16263375 | ... AF33: =AF32/AF11 -> -0.42331614 | AH33: =SUM(AF33-AB33)*1000 -> -395.22738
B35: Basic shares | J35: =C35 -> 0 | N35: =D35 -> 0 | R35: =E35 -> 0 | V35: =J35 -> 0 | W35: =K35 -> 0 | X35: =L35 -> 0 | Y35: =M35 -> 0 | Z35: =N35 -> 0 | AA35: =O35 -> 0 | AB35: =P35 -> 0 | AC35: =Q35 -> 0 | ... AF35: =T35 -> 0 | AH35: =SUM(AF35/AB35)-1 -> #DIV/0!
B36: Basic EPS | C36: =C32/C35 -> #DIV/0! | D36: =D32/D35 -> #DIV/0! | E36: =E32/E35 -> #DIV/0! | G36: =G32/G35 -> #DIV/0! | H36: =H32/H35 -> #DIV/0! | I36: =I32/I35 -> #DIV/0! | J36: =J32/J35 -> #DIV/0! | K36: =K32/K35 -> #DIV/0! | L36: =L32/L35 -> #DIV/0! | M36: =M32/M35 -> #DIV/0! | N36: =N32/N35 -> #DIV/0! | ... T36: =T32/T35 -> #DIV/0! | V36: =V32/V35 -> #DIV/0! | W36: =W32/W35 -> #DIV/0! | X36: =X32/X35 -> #DIV/0! | Y36: =Y32/Y35 -> #DIV/0! | Z36: =Z32/Z35 -> #DIV/0! | AA36: =AA32/AA35 -> #DIV/0! | AB36: =AB32/AB35 -> #DIV/0! | AC36: =AC32/AC35 -> #DIV/0! | ... AF36: =AF32/AF35 -> #DIV/0! | AH36: =SUM(AF36/AB36)-1 -> #DIV/0!
B38: Fully Diluted Shares | C38: 66017 | D38: 91188 | E38: 95087 | G38: 83641 | H38: 91550 | I38: 92752 | J38: =C38 -> 66017 | K38: 93673 | L38: 95010 | M38: 95806 | N38: =D38 -> 91188 | O38: 95850 | P38: 4793 | R38: =E38 -> 95087 | V38: =K38 -> 93673 | W38: =L38 -> 95010 | X38: =M38 -> 95806 | Y38: =N38 -> 91188 | Z38: =O38 -> 95850 | AA38: =P38 -> 4793 | AB38: =P38 -> 4793 | AC38: =Q38 -> 0 | AD38: =R38 -> 95087 | AE38: =S38 -> 0 | AF38: =T38 -> 0 | AH38: =SUM(AF38/AB38)-1 -> -1
B39: Diluted EPS | C39: =C32/C38 -> 0.58098672 | D39: =D32/D38 -> -0.20143001 | E39: =E32/E38 -> -0.43419185 | G39: =G32/G38 -> -0.12218888 | H39: =H32/H38 -> -0.13046423 | I39: =I32/I38 -> -0.0093367259 | J39: =J32/J38 -> 1.2007816 | K39: =K32/K38 -> 0.49403777 | L39: =L32/L38 -> 0.41693506 | M39: =M32/M38 -> 0.34315179 | N39: =N32/N38 -> -1.3314033 | ... T39: =T32/T38 -> #DIV/0! | V39: =V32/V38 -> 1.1452179 | W39: =W32/W38 -> 1.8136722 | X39: =X32/X38 -> 2.2796485 | Y39: =Y32/Y38 -> -0.8638198 | Z39: =Z32/Z38 -> 0.2447157 | AA39: =AA32/AA38 -> 0.17358648 | AB39: =AB32/AB38 -> -2.3231796 | AC39: =AC32/AC38 -> #DIV/0! | ... AF39: =AF32/AF38 -> #DIV/0! | AH39: =SUM(AF39/AB39)-1 -> #DIV/0!
A41: X | B41: Balance Sheet | C41: FYE | G41: Quarterly | Q41: Quarterly | AB41: LTM | AH41: Variance
B42: =B7 -> Fiscal Period | C42: =C7 -> 2022 | D42: =D7 -> 2023 | E42: =E7 -> 2024 | G42: =G7 -> 1Q23 | H42: =H7 -> 2Q23 | I42: =I7 -> 3Q23 | J42: =J7 -> 4Q23 | K42: =K7 -> 1Q24 | L42: =L7 -> 2Q24 | M42: =M7 -> 3Q24 | N42: =N7 -> 4Q24 | ... T42: =T7 -> 0 | V42: =V7 -> 4Q23 | W42: =W7 -> 1Q24 | X42: =X7 -> 2Q24 | Y42: =Y7 -> 3Q24 | Z42: =Z7 -> 4Q24 | AA42: =AA7 -> 1Q25 | AB42: =AB7 -> 2Q25 | AC42: =AC7 -> 0 | ... AF42: =AF7 -> 0
B43: =B8 -> Fiscal Period End Date | C43: =C8 -> 44651 | D43: =D8 -> 45016 | E43: =E8 -> 45382 | G43: =G8 -> 44742 | H43: =H8 -> 44834 | I43: =I8 -> 44926 | J43: =J8 -> 45016 | K43: =K8 -> 45107 | L43: =L8 -> 45199 | M43: =M8 -> 45291 | N43: =N8 -> 45382 | ... T43: =T8 -> 0 | V43: =V8 -> 45016 | W43: =W8 -> 45107 | X43: =X8 -> 45199 | Y43: =Y8 -> 45291 | Z43: =Z8 -> 45382 | AA43: =AA8 -> 45473 | AB43: =AB8 -> 45565 | AC43: =AC8 -> 0 | ... AF43: =AF8 -> 0
B45: Current Assets
B46: Cash and cash equivalents | C46: 5210 | D46: 25963 | E46: 25692 | G46: 26528 | H46: 25698 | I46: 26028 | J46: =C46 -> 5210 | K46: 25465 | L46: 25574 | M46: 24377 | N46: =D46 -> 25963 | O46: 17287 | P46: 16719 | R46: =E46 -> 25692 | V46: =J46 -> 5210 | W46: =K46 -> 25465 | X46: =L46 -> 25574 | Y46: =M46 -> 24377 | Z46: =N46 -> 25963 | AA46: =O46 -> 17287 | AB46: =P46 -> 16719 | AC46: =Q46 -> 0 | ... AF46: =T46 -> 0 | AH46: =SUM(AF46/AB46)-1 -> -1
B47: Restricted cash | C47: 283 | D47: 212 | E47: 168 | G47: 255 | H47: 223 | I47: 219 | J47: =C47 -> 283 | K47: 200 | L47: 180 | M47: 172 | N47: =D47 -> 212 | O47: 256 | P47: 241 | R47: =E47 -> 168 | V47: =J47 -> 283 | W47: =K47 -> 200 | X47: =L47 -> 180 | Y47: =M47 -> 172 | Z47: =N47 -> 212 | AA47: =O47 -> 256 | AB47: =P47 -> 241 | AC47: =Q47 -> 0 | ... AF47: =T47 -> 0 | AH47: =SUM(AF47/AB47)-1 -> -1
B48: Accounts receivable | C48: 69354 | D48: 72464 | E48: 67788 | G48: 64909 | H48: 61309 | I48: 72911 | J48: =C48 -> 69354 | K48: 66245 | L48: 51529 | M48: 60020 | N48: =D48 -> 72464 | O48: 61364 | P48: 51073 | R48: =E48 -> 67788
B49: Manufacturing inventories | C49: 33546 | D49: 19441 | E49: 17753 | G49: 32642 | H49: 23671 | I49: 32402 | J49: =C49 -> 33546 | K49: 20017 | L49: 21376 | M49: 20409 | N49: =D49 -> 19441 | O49: 18467 | P49: 18965 | R49: =E49 -> 17753
B50: Service parts inventories | C50: 24254 | D50: 25304 | E50: 9783 | G50: 25129 | H50: 25458 | I50: 25822 | J50: =C50 -> 24254 | K50: 25276 | L50: 25880 | M50: 25423 | N50: =D50 -> 25304 | O50: 8513 | P50: 9028 | R50: =E50 -> 9783
B51: Prepaid expenses | C51: 7853 | D51: 4158 | E51: 2186 | G51: 10715 | H51: 9241 | I51: 7198 | J51: =C51 -> 7853 | K51: 6444 | L51: 4149 | M51: 3763 | N51: =D51 -> 4158 | O51: 3880 | P51: 3632 | R51: =E51 -> 2186 | V51: =J51 -> 7853 | W51: =K51 -> 6444 | X51: =L51 -> 4149 | Y51: =M51 -> 3763 | Z51: =N51 -> 4158 | AA51: =O51 -> 3880 | AB51: =P51 -> 3632 | AC51: =Q51 -> 0 | ... AF51: =T51 -> 0 | AH51: =SUM(AF51/AB51)-1 -> -1
B52: Other current assets | C52: 4697 | D52: 5513 | E52: 8414 | G52: 4574 | H52: 4839 | I52: 7489 | J52: =C52 -> 4697 | K52: 6004 | L52: 5389 | M52: 7224 | N52: =D52 -> 5513 | O52: 8965 | P52: 9195 | R52: =E52 -> 8414 | V52: =J52 -> 4697 | W52: =K52 -> 6004 | X52: =L52 -> 5389 | Y52: =M52 -> 7224 | Z52: =N52 -> 5513 | AA52: =O52 -> 8965 | AB52: =P52 -> 9195 | AC52: =Q52 -> 0 | ... AF52: =T52 -> 0 | AH52: =SUM(AF52/AB52)-1 -> -1
B53: Total Current Assets | C53: =SUM(C46:C52) -> 145197 | D53: =SUM(D46:D52) -> 153055 | E53: =SUM(E46:E52) -> 131784 | G53: =SUM(G46:G52) -> 164752 | H53: =SUM(H46:H52) -> 150439 | I53: =SUM(I46:I52) -> 172069 | J53: =SUM(J46:J52) -> 145197 | K53: =SUM(K46:K52) -> 149651 | L53: =SUM(L46:L52) -> 134077 | M53: =SUM(M46:M52) -> 141388 | N53: =SUM(N46:N52) -> 153055 | ... T53: =SUM(T46:T52) -> 0 | V53: =SUM(V46:V52) -> 18043 | W53: =SUM(W46:W52) -> 38113 | X53: =SUM(X46:X52) -> 35292 | Y53: =SUM(Y46:Y52) -> 35536 | Z53: =SUM(Z46:Z52) -> 35846 | AA53: =SUM(AA46:AA52) -> 30388 | AB53: =SUM(AB46:AB52) -> 29787 | AC53: =SUM(AC46:AC52) -> 0 | ... AF53: =SUM(AF46:AF52) -> 0 | AH53: =SUM(AF53/AB53)-1 -> -1
B55: Non-Current Assets
B56: Property and equipment, net | C56: 12853 | D56: 16555 | E56: 12028 | G56: 14093 | H56: 15973 | I56: 16794 | J56: =C56 -> 12853 | K56: 15583 | L56: 14621 | M56: 13251 | N56: =D56 -> 16555 | O56: 10988 | P56: 11334 | R56: =E56 -> 12028 | V56: =J56 -> 12853 | W56: =K56 -> 15583 | X56: =L56 -> 14621 | Y56: =M56 -> 13251 | Z56: =N56 -> 16555 | AA56: =O56 -> 10988 | AB56: =P56 -> 11334 | AC56: =Q56 -> 0 | ... AF56: =T56 -> 0 | AH56: =SUM(AF56/AB56)-1 -> -1
B57: Intangible assets, net | C57: 9584 | D57: 4941 | E57: 1669 | G57: 8420 | H57: 7245 | I57: 6497 | J57: =C57 -> 9584 | K57: 3801 | L57: 2819 | M57: 1986 | N57: =D57 -> 4941 | O57: 1207 | P57: 742 | R57: =E57 -> 1669 | V57: =K57 -> 3801 | W57: =L57 -> 2819 | X57: =M57 -> 1986 | Y57: =N57 -> 4941 | Z57: =O57 -> 1207 | AA57: =P57 -> 742 | AB57: =P57 -> 742 | AC57: =Q57 -> 0 | AD57: =R57 -> 1669 | AE57: =S57 -> 0 | AF57: =T57 -> 0 | AH57: =SUM(AF57/AB57)-1 -> -1
B58: Goodwill | C58: 12969 | D58: 12969 | E58: 12969 | G58: 12969 | H58: 12969 | I58: 12969 | J58: =C58 -> 12969 | K58: 12969 | L58: 12969 | M58: 12969 | N58: =D58 -> 12969 | O58: 12969 | P58: 12969 | R58: =E58 -> 12969 | V58: =K58 -> 12969 | W58: =L58 -> 12969 | X58: =M58 -> 12969 | Y58: =N58 -> 12969 | Z58: =O58 -> 12969 | AA58: =P58 -> 12969 | AB58: =P58 -> 12969 | AC58: =Q58 -> 0 | AD58: =R58 -> 12969 | AE58: =S58 -> 0 | AF58: =T58 -> 0 | AH58: =SUM(AF58/AB58)-1 -> -1
B59: Right-of-use assets, net | C59: 11107 | D59: 10291 | E59: 9425 | G59: 10641 | H59: 10579 | I59: 10468 | J59: =C59 -> 11107 | K59: 10017 | L59: 9844 | M59: 9625 | N59: =D59 -> 10291 | O59: 9344 | P59: 9164 | R59: =E59 -> 9425 | V59: =K59 -> 10017 | W59: =L59 -> 9844 | X59: =M59 -> 9625 | Y59: =N59 -> 10291 | Z59: =O59 -> 9344 | AA59: =P59 -> 9164 | AB59: =P59 -> 9164 | AC59: =Q59 -> 0 | AD59: =R59 -> 9425 | AE59: =S59 -> 0 | AF59: =T59 -> 0 | AH59: =SUM(AF59/AB59)-1 -> -1
B60: Other long-term assets | C60: 9925 | D60: 15846 | E60: 19740 | G60: 10796 | H60: 12477 | I60: 13600 | J60: =C60 -> 9925 | K60: 18463 | L60: 20474 | M60: 19986 | N60: =D60 -> 15846 | O60: 19849 | P60: 20084 | R60: =E60 -> 19740 | V60: =K60 -> 18463 | W60: =L60 -> 20474 | X60: =M60 -> 19986 | Y60: =N60 -> 15846 | Z60: =O60 -> 19849 | AA60: =P60 -> 20084 | AB60: =P60 -> 20084 | AC60: =Q60 -> 0 | AD60: =R60 -> 19740 | AE60: =S60 -> 0 | AF60: =T60 -> 0 | AH60: =SUM(AF60/AB60)-1 -> -1
B61: Total Assets | C61: =SUM(C56:C60)+C53 -> 201635 | D61: =SUM(D56:D60)+D53 -> 213657 | E61: =SUM(E56:E60)+E53 -> 187615 | G61: =SUM(G56:G60)+G53 -> 221671 | H61: =SUM(H56:H60)+H53 -> 209682 | I61: =SUM(I56:I60)+I53 -> 232397 | J61: =SUM(J56:J60)+J53 -> 201635 | K61: =SUM(K56:K60)+K53 -> 210484 | L61: =SUM(L56:L60)+L53 -> 194804 | M61: =SUM(M56:M60)+M53 -> 199205 | N61: =SUM(N56:N60)+N53 -> 213657 | ... T61: =SUM(T56:T60)+T53 -> 0 | V61: =SUM(V56:V60)+V53 -> 76146 | W61: =SUM(W56:W60)+W53 -> 99802 | X61: =SUM(X56:X60)+X53 -> 94479 | Y61: =SUM(Y56:Y60)+Y53 -> 92834 | Z61: =SUM(Z56:Z60)+Z53 -> 95770 | AA61: =SUM(AA56:AA60)+AA53 -> 84335 | AB61: =SUM(AB56:AB60)+AB53 -> 84080 | AC61: =SUM(AC56:AC60)+AC53 -> 0 | ... AF61: =SUM(AF56:AF60)+AF53 -> 0 | AH61: =SUM(AF61/AB61)-1 -> -1
B63: Current Liabilities
B64: Accounts payable | C64: 34220 | D64: 35716 | E64: 26087 | G64: 33867 | H64: 34263 | I64: 41788 | J64: =C64 -> 34220 | K64: 30560 | L64: 26946 | M64: 22426 | N64: =D64 -> 35716 | O64: 31509 | P64: 30789 | R64: =E64 -> 26087 | V64: =K64 -> 30560 | W64: =L64 -> 26946 | X64: =M64 -> 22426 | Y64: =N64 -> 35716 | Z64: =O64 -> 31509 | AA64: =P64 -> 30789 | AB64: =P64 -> 30789 | AC64: =Q64 -> 0 | AD64: =R64 -> 26087 | AE64: =S64 -> 0 | AF64: =T64 -> 0 | AH64: =SUM(AF64/AB64)-1 -> -1
B65: Accrued compensation | C65: 16141 | D65: 15710 | E65: 18214 | G65: 14531 | H65: 13192 | I65: 15527 | J65: =C65 -> 16141 | K65: 14894 | L65: 13746 | M65: 15286 | N65: =D65 -> 15710 | O65: 16091 | P65: 13864 | R65: =E65 -> 18214 | V65: =K65 -> 14894 | W65: =L65 -> 13746 | X65: =M65 -> 15286 | Y65: =N65 -> 15710 | Z65: =O65 -> 16091 | AA65: =P65 -> 13864 | AB65: =P65 -> 13864 | AC65: =Q65 -> 0 | AD65: =R65 -> 18214 | AE65: =S65 -> 0 | AF65: =T65 -> 0 | AH65: =SUM(AF65/AB65)-1 -> -1
B66: Deferred revenue, current portion | C66: 87128 | D66: 79807 | E66: 78511 | G66: 74267 | H66: 70184 | I66: 72669 | J66: =C66 -> 87128 | K66: 79686 | L66: 70696 | M66: 73240 | N66: =D66 -> 79807 | O66: 74802 | P66: 69369 | R66: =E66 -> 78511
B67: Term debt, current portion | C67: 4375 | D67: 5000 | E67: 82496 | G67: 5000 | H67: 5000 | I67: 5000 | J67: =C67 -> 4375 | K67: 5000 | L67: 82681 | M67: 82587 | N67: =D67 -> 5000 | O67: 5000 | P67: 1579 | R67: =E67 -> 82496
B68: Revolving credit facility | C68: 0 | D68: 0 | E68: 26604 | G68: 0 | H68: 0 | I68: 0 | J68: =C68 -> 0 | K68: 0 | L68: 21450 | M68: 32000 | N68: =D68 -> 0 | O68: 0 | P68: 0 | R68: =E68 -> 26604 | AB68: =P68 -> 0 | AC68: =Q68 -> 0 | AD68: =R68 -> 26604 | AE68: =S68 -> 0 | AF68: =T68 -> 0 | AH68: =SUM(AF68/AB68)-1 -> #DIV/0!
B69: Warrant liabilities | C69: 18237 | D69: 7989 | E69: 4046 | G69: 0 | H69: 0 | I69: 0 | J69: =C69 -> 18237 | K69: 0 | L69: 4056 | M69: 1843 | N69: =D69 -> 7989 | O69: 3163 | P69: 2499 | R69: =E69 -> 4046 | AB69: =P69 -> 2499 | AC69: =Q69 -> 0 | AD69: =R69 -> 4046 | AE69: =S69 -> 0 | AF69: =T69 -> 0 | AH69: =SUM(AF69/AB69)-1 -> -1
B70: Other accrued liabilities | C70: 16562 | D70: 13666 | E70: 13986 | G70: 14157 | H70: 14502 | I70: 15852 | J70: =C70 -> 16562 | K70: 12715 | L70: 11724 | M70: 13854 | N70: =D70 -> 13666 | O70: 25043 | P70: 16501 | R70: =E70 -> 13986 | V70: =K70 -> 12715 | W70: =L70 -> 11724 | X70: =M70 -> 13854 | Y70: =N70 -> 13666 | Z70: =O70 -> 25043 | AA70: =P70 -> 16501 | AB70: =P70 -> 16501 | AC70: =Q70 -> 0 | AD70: =R70 -> 13986 | AE70: =S70 -> 0 | AF70: =T70 -> 0 | AH70: =SUM(AF70/AB70)-1 -> -1
B71: Total Current Liabilities | C71: =SUM(C64:C70) -> 176663 | D71: =SUM(D64:D70) -> 157888 | E71: =SUM(E64:E70) -> 249944 | G71: =SUM(G64:G70) -> 141822 | H71: =SUM(H64:H70) -> 137141 | I71: =SUM(I64:I70) -> 150836 | J71: =SUM(J64:J70) -> 176663 | K71: =SUM(K64:K70) -> 142855 | L71: =SUM(L64:L70) -> 231299 | M71: =SUM(M64:M70) -> 241236 | N71: =SUM(N64:N70) -> 157888 | ... T71: =SUM(T64:T70) -> 0 | V71: =SUM(V64:V70) -> 58169 | W71: =SUM(W64:W70) -> 52416 | X71: =SUM(X64:X70) -> 51566 | Y71: =SUM(Y64:Y70) -> 65092 | Z71: =SUM(Z64:Z70) -> 72643 | AA71: =SUM(AA64:AA70) -> 61154 | AB71: =SUM(AB64:AB70) -> 63653 | AC71: =SUM(AC64:AC70) -> 0 | ... AF71: =SUM(AF64:AF70) -> 0 | AH71: =SUM(AF71/AB71)-1 -> -1
B73: Non-Current Liabilities
B74: Deferred revenue, net of current portion | C74: 39788 | D74: 35495 | E74: 38176 | G74: 40196 | H74: 40165 | I74: 41076 | J74: =C74 -> 39788 | K74: 43903 | L74: 35337 | M74: 37281 | N74: =D74 -> 35495 | O74: 36759 | P74: 37164 | R74: =E74 -> 38176 | V74: =K74 -> 43903 | W74: =L74 -> 35337 | X74: =M74 -> 37281 | Y74: =N74 -> 35495 | Z74: =O74 -> 36759 | AA74: =P74 -> 37164 | AB74: =P74 -> 37164 | AC74: =Q74 -> 0 | AD74: =R74 -> 38176 | AE74: =S74 -> 0 | AF74: =T74 -> 0 | AH74: =SUM(AF74/AB74)-1 -> -1
B75: Revolving credit facility | C75: 17735 | D75: 16750 | E75: 0 | G75: 17300 | H75: 21500 | I75: 27736 | J75: =C75 -> 17735 | K75: 17800 | L75: 0 | M75: 0 | N75: =D75 -> 16750 | O75: 35800 | P75: 28300 | R75: =E75 -> 0 | V75: =K75 -> 17800 | W75: =L75 -> 0 | X75: =M75 -> 0 | Y75: =N75 -> 16750 | Z75: =O75 -> 35800 | AA75: =P75 -> 28300 | AB75: =P75 -> 28300 | AC75: =Q75 -> 0 | AD75: =R75 -> 0 | AE75: =S75 -> 0 | AF75: =T75 -> 0 | AH75: =SUM(AF75/AB75)-1 -> -1
B76: Term debt, net of current portion | C76: 89448 | D76: 66354 | E76: 0 | G76: 69195 | H76: 68250 | I76: 67306 | J76: =C76 -> 89448 | K76: 77814 | L76: 0 | M76: 0 | N76: =D76 -> 66354 | O76: 65132 | P76: 94746 | R76: =E76 -> 0 | AB76: =P76 -> 94746 | AC76: =Q76 -> 0 | AD76: =R76 -> 0 | AE76: =S76 -> 0 | AF76: =T76 -> 0 | AH76: =SUM(AF76/AB76)-1 -> -1
B77: Operating lease liabilities | C77: 9891 | D77: 10169 | E77: 9621 | G77: 9932 | H77: 10315 | I77: 10346 | J77: =C77 -> 9891 | K77: 10001 | L77: 10079 | M77: 9885 | N77: =D77 -> 10169 | O77: 9464 | P77: 9366 | R77: =E77 -> 9621 | AB77: =P77 -> 9366 | AC77: =Q77 -> 0 | AD77: =R77 -> 9621 | AE77: =S77 -> 0 | AF77: =T77 -> 0 | AH77: =SUM(AF77/AB77)-1 -> -1
B78: Other long-term liabilities | C78: 11849 | D78: 11370 | E78: 11372 | G78: 12013 | H78: 11653 | I78: 12150 | J78: =C78 -> 11849 | K78: 12191 | L78: 12522 | M78: 12734 | N78: =D78 -> 11370 | O78: 11577 | P78: 12372 | R78: =E78 -> 11372 | AB78: =P78 -> 12372 | AC78: =Q78 -> 0 | AD78: =R78 -> 11372 | AE78: =S78 -> 0 | AF78: =T78 -> 0 | AH78: =SUM(AF78/AB78)-1 -> -1
B79: Total Liabilities | C79: =SUM(C74:C78)+C71 -> 345374 | D79: =SUM(D74:D78)+D71 -> 298026 | E79: =SUM(E74:E78)+E71 -> 309113 | G79: =SUM(G74:G78)+G71 -> 290458 | H79: =SUM(H74:H78)+H71 -> 289024 | I79: =SUM(I74:I78)+I71 -> 309450 | J79: =SUM(J74:J78)+J71 -> 345374 | K79: =SUM(K74:K78)+K71 -> 304564 | L79: =SUM(L74:L78)+L71 -> 289237 | M79: =SUM(M74:M78)+M71 -> 301136 | N79: =SUM(N74:N78)+N71 -> 298026 | ... T79: =SUM(T74:T78)+T71 -> 0 | V79: =SUM(V74:V78)+V71 -> 119872 | W79: =SUM(W74:W78)+W71 -> 87753 | X79: =SUM(X74:X78)+X71 -> 88847 | Y79: =SUM(Y74:Y78)+Y71 -> 117337 | Z79: =SUM(Z74:Z78)+Z71 -> 145202 | AA79: =SUM(AA74:AA78)+AA71 -> 126618 | AB79: =SUM(AB74:AB78)+AB71 -> 245601 | AC79: =SUM(AC74:AC78)+AC71 -> 0 | ... AF79: =SUM(AF74:AF78)+AF71 -> 0 | AH79: =SUM(AF79/AB79)-1 -> -1
B81: Preferred stock | C81: 0 | D81: 0 | E81: 0 | G81: 0 | H81: 0 | I81: 0 | J81: =C81 -> 0 | K81: 0 | L81: 0 | M81: 0 | N81: =D81 -> 0 | O81: 0 | P81: 0 | R81: =E81 -> 0 | V81: =K81 -> 0 | W81: =L81 -> 0 | X81: =M81 -> 0 | Y81: =N81 -> 0 | Z81: =O81 -> 0 | AA81: =P81 -> 0 | AB81: =P81 -> 0 | AC81: =Q81 -> 0 | AD81: =R81 -> 0 | AE81: =S81 -> 0 | AF81: =T81 -> 0 | AH81: =SUM(AF81/AB81)-1 -> #DIV/0!
B82: Common stock | C82: 605 | D82: 936 | E82: 959 | G82: 907 | H82: 922 | I82: 932 | J82: =C82 -> 605 | K82: 938 | L82: 956 | M82: 959 | N82: =D82 -> 936 | O82: 959 | P82: 49 | R82: =E82 -> 959 | AB82: =P82 -> 49 | AC82: =Q82 -> 0 | AD82: =R82 -> 959 | AE82: =S82 -> 0 | AF82: =T82 -> 0 | AH82: =SUM(AF82/AB82)-1 -> -1
B83: Additional paid-in capital | C83: 624805 | D83: 702370 | E83: 707116 | G83: 714128 | H83: 716800 | I83: 719769 | J83: =C83 -> 624805 | K83: 725736 | L83: 705230 | M83: 706133 | N83: =D83 -> 702370 | O83: 708041 | P83: 709667 | R83: =E83 -> 707116 | AB83: =P83 -> 709667 | AC83: =Q83 -> 0 | AD83: =R83 -> 707116 | AE83: =S83 -> 0 | AF83: =T83 -> 0 | AH83: =SUM(AF83/AB83)-1 -> -1
B84: Accumulated deficit | C84: -767726 | D84: -786094 | E84: -827380 | G84: -781123 | H84: -793067 | I84: -795237 | J84: =C84 -> -767726 | K84: -819422 | L84: -798567 | M84: -808436 | N84: =D84 -> -786094 | O84: -848200 | P84: -861727 | R84: =E84 -> -827380 | V84: =K84 -> -819422 | W84: =L84 -> -798567 | X84: =M84 -> -808436 | Y84: =N84 -> -786094 | Z84: =O84 -> -848200 | AA84: =P84 -> -861727 | AB84: =P84 -> -861727 | AC84: =Q84 -> 0 | AD84: =R84 -> -827380 | AE84: =S84 -> 0 | AF84: =T84 -> 0 | AH84: =SUM(AF84/AB84)-1 -> -1
B85: Accumulated other comprehensive loss | C85: -1423 | D85: -1581 | E85: -2193 | G85: -2699 | H85: -3997 | I85: -2517 | J85: =C85 -> -1423 | K85: -1332 | L85: -2052 | M85: -587 | N85: =D85 -> -1581 | O85: -2051 | P85: -1392 | R85: =E85 -> -2193 | V85: =K85 -> -1332 | W85: =L85 -> -2052 | X85: =M85 -> -587 | Y85: =N85 -> -1581 | Z85: =O85 -> -2051 | AA85: =P85 -> -1392 | AB85: =P85 -> -1392 | AC85: =Q85 -> 0 | AD85: =R85 -> -2193 | AE85: =S85 -> 0 | AF85: =T85 -> 0 | AH85: =SUM(AF85/AB85)-1 -> -1
B86: Total stockholders' equity | C86: =SUM(C81:C85) -> -143739 | D86: =SUM(D81:D85) -> -84369 | E86: =SUM(E81:E85) -> -121498 | G86: =SUM(G81:G85) -> -68787 | H86: =SUM(H81:H85) -> -79342 | I86: =SUM(I81:I85) -> -77053 | J86: =SUM(J81:J85) -> -143739 | K86: =SUM(K81:K85) -> -94080 | L86: =SUM(L81:L85) -> -94433 | M86: =SUM(M81:M85) -> -101931 | N86: =SUM(N81:N85) -> -84369 | ... T86: =SUM(T81:T85) -> 0 | V86: =SUM(V81:V85) -> -820754 | W86: =SUM(W81:W85) -> -800619 | X86: =SUM(X81:X85) -> -809023 | Y86: =SUM(Y81:Y85) -> -787675 | Z86: =SUM(Z81:Z85) -> -850251 | AA86: =SUM(AA81:AA85) -> -863119 | AB86: =SUM(AB81:AB85) -> -153403 | AC86: =SUM(AC81:AC85) -> 0 | ... AF86: =SUM(AF81:AF85) -> 0 | AH86: =SUM(AF86/AB86)-1 -> -1
B87: Total liabilities and stockholders' equity | C87: =SUM(C86+C79) -> 201635 | D87: =SUM(D86+D79) -> 213657 | E87: =SUM(E86+E79) -> 187615 | G87: =SUM(G86+G79) -> 221671 | H87: =SUM(H86+H79) -> 209682 | I87: =SUM(I86+I79) -> 232397 | J87: =SUM(J86+J79) -> 201635 | K87: =SUM(K86+K79) -> 210484 | L87: =SUM(L86+L79) -> 194804 | M87: =SUM(M86+M79) -> 199205 | N87: =SUM(N86+N79) -> 213657 | ... T87: =SUM(T86+T79) -> 0 | V87: =SUM(V86+V79) -> -700882 | W87: =SUM(W86+W79) -> -712866 | X87: =SUM(X86+X79) -> -720176 | Y87: =SUM(Y86+Y79) -> -670338 | Z87: =SUM(Z86+Z79) -> -705049 | AA87: =SUM(AA86+AA79) -> -736501 | AB87: =SUM(AB86+AB79) -> 92198 | AC87: =SUM(AC86+AC79) -> 0 | ... AF87: =SUM(AF86+AF79) -> 0 | AH87: =SUM(AF87/AB87)-1 -> -1
B89: Balance Check | C89: =C87-C61 -> 0 | D89: =D87-D61 -> 0 | E89: =E87-E61 -> 0 | G89: =G87-G61 -> 0 | H89: =H87-H61 -> 0 | I89: =I87-I61 -> 0 | J89: =J87-J61 -> 0 | K89: =K87-K61 -> 0 | L89: =L87-L61 -> 0 | M89: =M87-M61 -> 0 | N89: =N87-N61 -> 0 | ... T89: =T87-T61 -> 0 | V89: =V87-V61 -> -777028 | W89: =W87-W61 -> -812668 | X89: =X87-X61 -> -814655 | Y89: =Y87-Y61 -> -763172 | Z89: =Z87-Z61 -> -800819 | AA89: =AA87-AA61 -> -820836 | AB89: =AB87-AB61 -> 8118 | AC89: =AC87-AC61 -> 0 | ... AF89: =AF87-AF61 -> 0
B91: 1) xxx
A93: X | B93: Cash-Flows Statement | C93: FYE | G93: Quarterly | Q93: Quarterly | AB93: LTM | AH93: Variance
B94: =B7 -> Fiscal Period | C94: =C7 -> 2022 | D94: =D7 -> 2023 | E94: =E7 -> 2024 | G94: =G7 -> 1Q23 | H94: =H7 -> 2Q23 | I94: =I7 -> 3Q23 | J94: =J7 -> 4Q23 | K94: =K7 -> 1Q24 | L94: =L7 -> 2Q24 | M94: =M7 -> 3Q24 | N94: =N7 -> 4Q24 | ... T94: =T7 -> 0 | V94: =V7 -> 4Q23 | W94: =W7 -> 1Q24 | X94: =X7 -> 2Q24 | Y94: =Y7 -> 3Q24 | Z94: =Z7 -> 4Q24 | AA94: =AA7 -> 1Q25 | AB94: =AB7 -> 2Q25 | AC94: =AC7 -> 0 | ... AF94: =AF7 -> 0
B95: =B8 -> Fiscal Period End Date | C95: =C8 -> 44651 | D95: =D8 -> 45016 | E95: =E8 -> 45382 | G95: =G8 -> 44742 | H95: =H8 -> 44834 | I95: =I8 -> 44926 | J95: =J8 -> 45016 | K95: =K8 -> 45107 | L95: =L8 -> 45199 | M95: =M8 -> 45291 | N95: =N8 -> 45382 | ... T95: =T8 -> 0 | V95: =V8 -> 45016 | W95: =W8 -> 45107 | X95: =X8 -> 45199 | Y95: =Y8 -> 45291 | Z95: =Z8 -> 45382 | AA95: =AA8 -> 45473 | AB95: =AB8 -> 45565 | AC95: =AC8 -> 0 | ... AF95: =AF8 -> 0
B97: Cash-Flows From Operating Activities
B98: Net income (loss) | C98: =C32 -> 38355 | D98: =D32 -> -18368 | E98: =E32 -> -41286 | G98: =G32 -> -10220 | H98: =H32 -> -11944 | I98: =I32 -> -866 | J98: =J32 -> 79272 | K98: =K32 -> 46278 | L98: =L32 -> 39613 | M98: =M32 -> 32876 | N98: =SUM(D98-SUM(K98:M98)) -> -137135 | O98: =O32 -> 24388 | P98: =P32 -> 27674 | Q98: =Q32 -> 0 | R98: =SUM(E98-SUM(O98:Q98)) -> -93348 | S98: =S32 -> 0 | T98: =T32 -> 0 | V98: =SUM(H98:K98) -> 112740 | W98: =SUM(I98:L98) -> 164297 | X98: =SUM(J98:M98) -> 198039 | Y98: =SUM(K98:N98) -> -18368 | Z98: =SUM(L98:O98) -> -40258 | AA98: =SUM(M98:P98) -> -52197 | AB98: =SUM(M98:P98) -> -52197 | AC98: =SUM(N98:Q98) -> -85073 | AD98: =SUM(O98:R98) -> -41286 | AE98: =SUM(P98:S98) -> -65674 | AF98: =SUM(Q98:T98) -> -93348 | AH98: =SUM(AF98/AB98)-1 -> 0.78837864
B100: Adjustments to reconcile net income:
B101: Depreciation and amortization | C101: 9418 | D101: 10118 | E101: 9313 | G101: 2586 | H101: =5133-G101 -> 2547 | I101: =7235-H101-G101 -> 2102 | J101: =SUM(D101-SUM(G101:I101)) -> 2883 | K101: 2752 | L101: =5295-K101 -> 2543 | M101: =7593-L101-K101 -> 2298 | N101: =SUM(E101-SUM(K101:M101)) -> 1720 | O101: 1780 | P101: =3347-O101 -> 1567 | R101: =SUM(E101-SUM(O101:Q101)) -> 5966 | V101: =SUM(H101:K101) -> 10284 | W101: =SUM(I101:L101) -> 10280 | X101: =SUM(J101:M101) -> 10476 | Y101: =SUM(K101:N101) -> 9313 | Z101: =SUM(L101:O101) -> 8341 | AA101: =SUM(M101:P101) -> 7365 | AB101: =SUM(M101:P101) -> 7365 | AC101: =SUM(N101:Q101) -> 5067 | AD101: =SUM(O101:R101) -> 9313 | AE101: =SUM(P101:S101) -> 7533 | AF101: =SUM(Q101:T101) -> 5966 | AH101: =SUM(AF101/AB101)-1 -> -0.18995248
B102: Amortization of debt issuance costs | C102: 2414 | D102: 1624 | E102: 2735 | G102: 336 | H102: =768-G102 -> 432 | I102: =1201-H102-G102 -> 433 | J102: =SUM(D102-SUM(G102:I102)) -> 423 | K102: 520 | L102: =1234-K102 -> 714 | M102: =1948-L102-K102 -> 714 | N102: =SUM(E102-SUM(K102:M102)) -> 787 | O102: 804 | P102: =2081-O102 -> 1277 | R102: =SUM(E102-SUM(O102:Q102)) -> 654 | V102: =SUM(H102:K102) -> 1808 | W102: =SUM(I102:L102) -> 2090 | X102: =SUM(J102:M102) -> 2371 | Y102: =SUM(K102:N102) -> 2735 | Z102: =SUM(L102:O102) -> 3019 | AA102: =SUM(M102:P102) -> 3582 | AB102: =SUM(M102:P102) -> 3582 | AC102: =SUM(N102:Q102) -> 2868 | AD102: =SUM(O102:R102) -> 2735 | AE102: =SUM(P102:S102) -> 1931 | AF102: =SUM(Q102:T102) -> 654 | AH102: =SUM(AF102/AB102)-1 -> -0.81742044
B103: Long-term debt related costs | C103: 8471 | D103: 992 | E103: 0 | G103: 992 | H103: =992-G103 -> 0 | I103: =992-H103-G103 -> 0 | J103: =SUM(D103-SUM(G103:I103)) -> 0 | K103: 0 | L103: 0 | M103: 0 | N103: =SUM(E103-SUM(K103:M103)) -> 0 | O103: 695 | P103: =3003-O103 -> 2308 | R103: =SUM(E103-SUM(O103:Q103)) -> -3003 | V103: =SUM(H103:K103) -> 0 | W103: =SUM(I103:L103) -> 0 | X103: =SUM(J103:M103) -> 0 | Y103: =SUM(K103:N103) -> 0 | Z103: =SUM(L103:O103) -> 695 | AA103: =SUM(M103:P103) -> 3003 | AB103: =SUM(M103:P103) -> 3003 | AC103: =SUM(N103:Q103) -> 3003 | AD103: =SUM(O103:R103) -> 0 | AE103: =SUM(P103:S103) -> -695 | AF103: =SUM(Q103:T103) -> -3003 | AH103: =SUM(AF103/AB103)-1 -> -2
B104: Provision for manufacturing and service inventories | C104: 5740 | D104: 18052 | E104: 6490 | G104: 1631 | H104: =9946-G104 -> 8315 | I104: =11334-H104-G104 -> 1388 | J104: =SUM(D104-SUM(G104:I104)) -> 6718 | K104: 516 | L104: =892-K104 -> 376 | M104: =3328-L104-K104 -> 2436 | N104: =SUM(E104-SUM(K104:M104)) -> 3162 | O104: 407 | P104: =1167-O104 -> 760 | R104: =SUM(E104-SUM(O104:Q104)) -> 5323 | V104: =SUM(H104:K104) -> 16937 | W104: =SUM(I104:L104) -> 8998 | X104: =SUM(J104:M104) -> 10046 | Y104: =SUM(K104:N104) -> 6490 | Z104: =SUM(L104:O104) -> 6381 | AA104: =SUM(M104:P104) -> 6765 | AB104: =SUM(M104:P104) -> 6765 | AC104: =SUM(N104:Q104) -> 4329 | AD104: =SUM(O104:R104) -> 6490 | AE104: =SUM(P104:S104) -> 6083 | AF104: =SUM(Q104:T104) -> 5323 | AH104: =SUM(AF104/AB104)-1 -> -0.21315595
B105: Stock-based compensation | C105: 13829 | D105: 10750 | E105: 4721 | G105: 3069 | H105: =5357-G105 -> 2288 | I105: =8340-H105-G105 -> 2983 | J105: =SUM(D105-SUM(G105:I105)) -> 2410 | K105: 1901 | L105: =2831-K105 -> 930 | M105: =3741-L105-K105 -> 910 | N105: =SUM(E105-SUM(K105:M105)) -> 980 | O105: 925 | P105: =1641-O105 -> 716 | R105: =SUM(E105-SUM(O105:Q105)) -> 3080 | AB105: =SUM(M105:P105) -> 3531 | AC105: =SUM(N105:Q105) -> 2621 | AD105: =SUM(O105:R105) -> 4721 | AE105: =SUM(P105:S105) -> 3796 | AF105: =SUM(Q105:T105) -> 3080 | AH105: =SUM(AF105/AB105)-1 -> -0.12772586
B106: Paid in kind interest | C106: 0 | D106: 0 | E106: 0 | G106: 0 | H106: 0 | I106: 0 | J106: =SUM(D106-SUM(G106:I106)) -> 0 | K106: 0 | L106: 0 | M106: 0 | N106: =SUM(E106-SUM(K106:M106)) -> 0 | O106: 0 | P106: 1844 | R106: =SUM(E106-SUM(O106:Q106)) -> -1844 | AB106: =SUM(M106:P106) -> 1844 | AC106: =SUM(N106:Q106) -> 1844 | AD106: =SUM(O106:R106) -> 0 | AE106: =SUM(P106:S106) -> 0 | AF106: =SUM(Q106:T106) -> -1844 | AH106: =SUM(AF106/AB106)-1 -> -2
B107: Change in fair value of warrant liabilities | C107: -60030 | D107: -10250 | E107: -5137 | G107: 0 | H107: 0 | I107: 0 | J107: =SUM(D107-SUM(G107:I107)) -> -10250 | K107: 0 | L107: -5127 | M107: =-7340-L107-K107 -> -2213 | N107: =SUM(E107-SUM(K107:M107)) -> 2203 | O107: -1666 | P107: =-5216-O107 -> -3550 | R107: =SUM(E107-SUM(O107:Q107)) -> 79 | AB107: =SUM(M107:P107) -> -5226 | AC107: =SUM(N107:Q107) -> -3013 | AD107: =SUM(O107:R107) -> -5137 | AE107: =SUM(P107:S107) -> -3471 | AF107: =SUM(Q107:T107) -> 79 | AH107: =SUM(AF107/AB107)-1 -> -1.0151167
B108: Change in fair value of warrant liabilities | C108: 0 | D108: 0 | E108: -3943 | G108: 0 | H108: 0 | I108: 0 | J108: =SUM(D108-SUM(G108:I108)) -> 0 | K108: 0 | L108: 0 | M108: 0 | N108: =SUM(E108-SUM(K108:M108)) -> -3943 | O108: 0 | P108: 0 | R108: =SUM(E108-SUM(O108:Q108)) -> -3943 | AB108: =SUM(M108:P108) -> -3943 | AC108: =SUM(N108:Q108) -> -3943 | AD108: =SUM(O108:R108) -> -3943 | AE108: =SUM(P108:S108) -> -3943 | AF108: =SUM(Q108:T108) -> -3943 | AH108: =SUM(AF108/AB108)-1 -> 0
B109: Other non-cash | C109: -832 | D109: -2067 | E109: 3304 | G109: -1469 | H109: =-152-G109 -> 1317 | I109: =-2059-H109-G109 -> -1907 | J109: =SUM(D109-SUM(G109:I109)) -> -8 | K109: 734 | L109: =826-K109 -> 92 | M109: =3010-L109-K109 -> 2184 | N109: =SUM(E109-SUM(K109:M109)) -> 294 | O109: 275 | P109: =851-O109 -> 576 | R109: =SUM(E109-SUM(O109:Q109)) -> 2453 | AB109: =SUM(M109:P109) -> 3329 | AC109: =SUM(N109:Q109) -> 1145 | AD109: =SUM(O109:R109) -> 3304 | AE109: =SUM(P109:S109) -> 3029 | AF109: =SUM(Q109:T109) -> 2453 | AH109: =SUM(AF109/AB109)-1 -> -0.26314208
B110: Unrealized foreign exchange loss | H110: =-2766-G110 -> -2766 | I110: =-1134-H110-G110 -> 1632 | J110: =SUM(D110-SUM(G110:I110)) -> 1134 | K110: 0 | L110: 0 | M110: 0 | R110: =SUM(E110-SUM(O110:Q110)) -> 0 | AB110: =SUM(M110:P110) -> 0 | AC110: =SUM(N110:Q110) -> 0 | AD110: =SUM(O110:R110) -> 0 | AE110: =SUM(P110:S110) -> 0 | AF110: =SUM(Q110:T110) -> 0 | AH110: =SUM(AF110/AB110)-1 -> #DIV/0!
B112: Changes in assets and liabilities:
B113: Accounts receivable | C113: 3651 | D113: -2966 | E113: 4846 | G113: 4677 | H113: =8264-G113 -> 3587 | I113: =-3367-H113-G113 -> -11631 | J113: =SUM(D113-SUM(G113:I113)) -> 401 | K113: 6255 | L113: =21109-K113 -> 14854 | M113: =12616-L113-K113 -> -8493 | N113: =SUM(E113-SUM(K113:M113)) -> -7770 | O113: 6346 | P113: =16638-O113 -> 10292 | R113: =SUM(E113-SUM(O113:Q113)) -> -11792 | V113: =SUM(H113:K113) -> -1388 | W113: =SUM(I113:L113) -> 9879 | X113: =SUM(J113:M113) -> 13017 | Y113: =SUM(K113:N113) -> 4846 | Z113: =SUM(L113:O113) -> 4937 | AA113: =SUM(M113:P113) -> 375 | AB113: =SUM(M113:P113) -> 375 | AC113: =SUM(N113:Q113) -> 8868 | AD113: =SUM(O113:R113) -> 4846 | AE113: =SUM(P113:S113) -> -1500 | AF113: =SUM(Q113:T113) -> -11792 | AH113: =SUM(AF113/AB113)-1 -> -32.445333
B114: Manufacturing inventories | C114: -12069 | D114: -1839 | E114: -1396 | G114: -412 | H114: =416-G114 -> 828 | I114: =-9352-H114-G114 -> -9768 | J114: =SUM(D114-SUM(G114:I114)) -> 7513 | K114: -692 | L114: =-2070-K114 -> -1378 | M114: =-3099-L114-K114 -> -1029 | N114: =SUM(E114-SUM(K114:M114)) -> 1703 | O114: -1325 | P114: =-2168-O114 -> -843
B115: Service parts inventories | C115: -4400 | D115: -3503 | E115: 11852 | G115: -1384 | H115: =-1971-G115 -> -587 | I115: =-2671-H115-G115 -> -700 | J115: =SUM(D115-SUM(G115:I115)) -> -832 | K115: -516 | L115: =-1505-K115 -> -989 | M115: =-1520-L115-K115 -> -15 | N115: =SUM(E115-SUM(K115:M115)) -> 13372 | O115: 1475 | P115: =543-O115 -> -932
B116: Accounts payable | C116: -1939 | D116: 1158 | E116: -11193 | G116: -175 | H116: =293-G116 -> 468 | I116: =7015-H116-G116 -> 6722 | J116: =SUM(D116-SUM(G116:I116)) -> -5857 | K116: -5421 | L116: =-9073-K116 -> -3652 | M116: =-13226-L116-K116 -> -4153 | N116: =SUM(E116-SUM(K116:M116)) -> 2033 | O116: 6828 | P116: =5253-O116 -> -1575
B117: Prepaid expenses | C117: -3959 | D117: 3695 | E117: 1971 | H117: =-1208-G117 -> -1208 | I117: =654-H117-G117 -> 1862 | J117: =SUM(D117-SUM(G117:I117)) -> 3041 | K117: -2287 | L117: =8-K117 -> 2295 | M117: =394-L117-K117 -> 386 | N117: =SUM(E117-SUM(K117:M117)) -> 1577 | O117: -1694 | P117: =-1446-O117 -> 248
B118: Deferred revenue | C118: -13119 | D118: -11611 | E118: 1386 | G118: -13634 | H118: =-17747-G118 -> -4113 | I118: =-14351-H118-G118 -> 3396 | J118: =SUM(D118-SUM(G118:I118)) -> 2740 | K118: -2221 | L118: =-9269-K118 -> -7048 | M118: =-4780-L118-K118 -> 4489 | N118: =SUM(E118-SUM(K118:M118)) -> 6166 | O118: -5126 | P118: =-10153-O118 -> -5027
B119: Accrued restructuring charges | C119: -580 | D119: 0 | E119: 0 | G119: 39 | H119: =115-G119 -> 76 | I119: =130-H119-G119 -> 15 | J119: =SUM(D119-SUM(G119:I119)) -> -130 | K119: 110 | L119: =0-K119 -> -110 | M119: =0-L119-K119 -> 0 | N119: =SUM(E119-SUM(K119:M119)) -> 0
B120: Accrued compensation | C120: -3073 | D120: -431 | E120: 2504 | G120: -1610 | H120: =-2949-G120 -> -1339 | I120: =-614-H120-G120 -> 2335 | J120: =SUM(D120-SUM(G120:I120)) -> 183 | K120: -816 | L120: =-1946-K120 -> -1130 | M120: =-425-L120-K120 -> 1521 | N120: =SUM(E120-SUM(K120:M120)) -> 2929 | O120: -2123 | P120: =-4350-O120 -> -2227
B121: Other assets | C121: -2602 | D121: -1270 | E121: -2197 | G121: =-2739-261 -> -3000 | H121: =SUM(-486-349)-G121 -> 2165 | I121: =SUM(1357-2812)-H121-G121 -> -620 | J121: =SUM(D121-SUM(G121:I121)) -> 185 | K121: =-487-935 -> -1422 | L121: =SUM(115-2354)-K121 -> -817 | M121: =SUM(-1698-1532)-L121-K121 -> -991 | N121: =SUM(E121-SUM(K121:M121)) -> 1033 | O121: =649-551 -> 98 | P121: =SUM(1280-780)-O121 -> 402 | R121: =SUM(E121-SUM(O121:Q121)) -> -2697 | V121: =SUM(H121:K121) -> 308 | W121: =SUM(I121:L121) -> -2674 | X121: =SUM(J121:M121) -> -3045 | Y121: =SUM(K121:N121) -> -2197 | Z121: =SUM(L121:O121) -> -677 | AA121: =SUM(M121:P121) -> 542 | AB121: =SUM(M121:P121) -> 542 | AC121: =SUM(N121:Q121) -> 1533 | AD121: =SUM(O121:R121) -> -2197 | AE121: =SUM(P121:S121) -> -2295 | AF121: =SUM(Q121:T121) -> -2697 | AH121: =SUM(AF121/AB121)-1 -> -5.9760148
...

Sheet Revenue Drivers
B2: XXX | H2: Quarterly | P2: Quarterly | Q2: Quarterly | W2: LTM | AA2: LTM | AC2: LTM
B3: Segment Anaysis | C3: ='Historical Financials'!#REF! -> #REF! | D3: ='Historical Financials'!C7 -> 2022 | E3: ='Historical Financials'!D7 -> 2023 | F3: ='Historical Financials'!E7 -> 2024 | H3: ='Historical Financials'!G7 -> 1Q23 | I3: ='Historical Financials'!H7 -> 2Q23 | J3: ='Historical Financials'!I7 -> 3Q23 | K3: ='Historical Financials'!J7 -> 4Q23 | L3: ='Historical Financials'!K7 -> 1Q24 | M3: ='Historical Financials'!L7 -> 2Q24 | N3: ='Historical Financials'!M7 -> 3Q24 | O3: ='Historical Financials'!N7 -> 4Q24 | ... U3: ='Historical Financials'!T7 -> 0 | W3: =L3 -> 1Q24 | X3: =M3 -> 2Q24 | Y3: =N3 -> 3Q24 | Z3: =O3 -> 4Q24 | AA3: =P3 -> 1Q25 | AB3: =Q3 -> 2Q25 | AC3: =S3 -> 0 | AD3: =T3 -> 0 | AE3: =U3 -> 0 | AF3: =#REF! -> #REF!
B4: $ in thousands except per share | C4: ='Historical Financials'!#REF! -> #REF! | D4: ='Historical Financials'!C8 -> 44651 | E4: ='Historical Financials'!D8 -> 45016 | F4: ='Historical Financials'!E8 -> 45382 | H4: ='Historical Financials'!G8 -> 44742 | I4: ='Historical Financials'!H8 -> 44834 | J4: ='Historical Financials'!I8 -> 44926 | K4: ='Historical Financials'!J8 -> 45016 | L4: ='Historical Financials'!K8 -> 45107 | M4: ='Historical Financials'!L8 -> 45199 | N4: ='Historical Financials'!M8 -> 45291 | O4: ='Historical Financials'!N8 -> 45382 | ... U4: ='Historical Financials'!T8 -> 0 | W4: =L4 -> 45107 | X4: =M4 -> 45199 | Y4: =N4 -> 45291 | Z4: =O4 -> 45382 | AA4: =P4 -> 45473 | AB4: =Q4 -> 45565 | AC4: =S4 -> 0 | AD4: =T4 -> 0 | AE4: =U4 -> 0 | AF4: =#REF! -> #REF!
A6: X | B6: Net Revenues by Channel
W7: =SUM(I7:L7) -> 0 | X7: =SUM(J7:M7) -> 0 | Y7: =SUM(K7:N7) -> 0 | Z7: =SUM(L7:O7) -> 0 | AA7: =SUM(M7:P7) -> 0 | AB7: =SUM(N7:Q7) -> 0 | AC7: =SUM(P7:S7) -> 0 | AD7: =SUM(Q7:T7) -> 0 | AE7: =SUM(R7:U7) -> 0 | AF7: =SUM(S7:U7) -> 0
W8: =SUM(I8:L8) -> 0 | X8: =SUM(J8:M8) -> 0 | Y8: =SUM(K8:N8) -> 0 | Z8: =SUM(L8:O8) -> 0 | AA8: =SUM(M8:P8) -> 0 | AB8: =SUM(N8:Q8) -> 0 | AC8: =SUM(P8:S8) -> 0 | AD8: =SUM(Q8:T8) -> 0 | AE8: =SUM(R8:U8) -> 0 | AF8: =SUM(S8:U8) -> 0
B9: Total Net Revenue | D9: =SUM(D7:D8) -> 0 | E9: =SUM(E7:E8) -> 0 | F9: =SUM(F7:F8) -> 0 | P9: =SUM(P7:P8) -> 0 | Q9: =SUM(Q7:Q8) -> 0 | R9: =SUM(R7:R8) -> 0 | S9: =SUM(S7:S8) -> 0 | T9: =SUM(T7:T8) -> 0 | U9: =SUM(U7:U8) -> 0 | W9: =SUM(W7:W8) -> 0 | X9: =SUM(X7:X8) -> 0 | Y9: =SUM(Y7:Y8) -> 0 | Z9: =SUM(Z7:Z8) -> 0 | AA9: =SUM(AA7:AA8) -> 0 | AB9: =SUM(AB7:AB8) -> 0 | AC9: =SUM(AC7:AC8) -> 0 | AD9: =SUM(AD7:AD8) -> 0 | ... AF9: =SUM(AF7:AF8) -> 0
B10: Balance Check | D10: =+D9-'Historical Financials'!C11 -> -383432 | E10: =+E9-'Historical Financials'!D11 -> -422077 | F10: =+F9-'Historical Financials'!E11 -> -311600 | P10: =+P9-'Historical Financials'!O11 -> -71343 | Q10: =+Q9-'Historical Financials'!P11 -> -70469 | R10: =+R9-'Historical Financials'!Q11 -> 0 | S10: =+S9-'Historical Financials'!R11 -> -169788 | T10: =+T9-'Historical Financials'!S11 -> 0 | U10: =+U9-'Historical Financials'!T11 -> 0 | W10: =W9-'Historical Financials'!V11 -> -383432 | X10: =X9-'Historical Financials'!W11 -> -378145 | Y10: =Y9-'Historical Financials'!X11 -> -354688 | Z10: =Z9-'Historical Financials'!Y11 -> -315418 | AA10: =AA9-'Historical Financials'!Z11 -> -422077 | AB10: =AB9-'Historical Financials'!AA11 -> -401633 | AC10: =AC9-'Historical Financials'!AC11 -> -324496 | AD10: =AD9-'Historical Financials'!AD11 -> -311600 | AE10: =AE9-'Historical Financials'!AE11 -> -240257 | AF10: =AF9-'Historical Financials'!AF11 -> -169788
A12: X | B12: Revenue by Channel
W13: =SUM(I13:L13) -> 0 | X13: =SUM(J13:M13) -> 0 | Y13: =SUM(K13:N13) -> 0 | Z13: =SUM(L13:O13) -> 0 | AA13: =SUM(M13:P13) -> 0 | AB13: =SUM(N13:Q13) -> 0 | AC13: =SUM(P13:S13) -> 0 | AD13: =SUM(Q13:T13) -> 0 | AE13: =SUM(R13:U13) -> 0 | AF13: =SUM(S13:U13) -> 0
W14: =SUM(I14:L14) -> 0 | X14: =SUM(J14:M14) -> 0 | Y14: =SUM(K14:N14) -> 0 | Z14: =SUM(L14:O14) -> 0 | AA14: =SUM(M14:P14) -> 0 | AB14: =SUM(N14:Q14) -> 0 | AC14: =SUM(P14:S14) -> 0 | AD14: =SUM(Q14:T14) -> 0 | AE14: =SUM(R14:U14) -> 0 | AF14: =SUM(S14:U14) -> 0
B15: Total Net U.S Revenue | D15: =SUM(D13:D14) -> 0 | E15: =SUM(E13:E14) -> 0 | F15: =SUM(F13:F14) -> 0 | P15: =SUM(P13:P14) -> 0 | Q15: =SUM(Q13:Q14) -> 0 | R15: =SUM(R13:R14) -> 0 | S15: =SUM(S13:S14) -> 0 | T15: =SUM(T13:T14) -> 0 | U15: =SUM(U13:U14) -> 0 | W15: =SUM(W13:W14) -> 0 | X15: =SUM(X13:X14) -> 0 | Y15: =SUM(Y13:Y14) -> 0 | Z15: =SUM(Z13:Z14) -> 0 | AA15: =SUM(AA13:AA14) -> 0 | AB15: =SUM(AB13:AB14) -> 0 | AC15: =SUM(AC13:AC14) -> 0 | AD15: =SUM(AD13:AD14) -> 0 | ... AF15: =SUM(AF13:AF14) -> 0
B16: Balance Check | D16: =+D15-D9 -> 0 | E16: =+E15-E9 -> 0 | F16: =+F15-F9 -> 0 | P16: =+P15-P9 -> 0 | Q16: =+Q15-Q9 -> 0 | R16: =+R15-R9 -> 0 | S16: =+S15-S9 -> 0 | T16: =+T15-T9 -> 0 | U16: =+U15-U9 -> 0 | W16: =W15-'Historical Financials'!V17 -> 62834 | X16: =X15-'Historical Financials'!W17 -> 62958 | Y16: =Y15-'Historical Financials'!X17 -> 60863 | Z16: =Z15-'Historical Financials'!Y17 -> 66034 | AA16: =AA15-'Historical Financials'!Z17 -> 63490 | AB16: =AB15-'Historical Financials'!AA17 -> 61351 | AC16: =+AC15-AC9 -> 0 | AD16: =+AD15-AD9 -> 0 | AE16: =+AE15-AE9 -> 0 | AF16: =+AF15-AF9 -> 0

Sheet FCF
B2: XXX | D2: FYE | H2: Quarterly | Q2: Quarterly | R2: Quarterly | X2: LTM | AE2: LTM | AK2: Variance
B3: FCF Analysis | C3: ='Historical Financials'!#REF! -> #REF! | D3: ='Historical Financials'!C7 -> 2022 | E3: ='Historical Financials'!D7 -> 2023 | F3: ='Historical Financials'!E7 -> 2024 | H3: ='Historical Financials'!G7 -> 1Q23 | I3: ='Historical Financials'!H7 -> 2Q23 | J3: ='Historical Financials'!I7 -> 3Q23 | K3: ='Historical Financials'!J7 -> 4Q23 | L3: ='Historical Financials'!K7 -> 1Q24 | M3: ='Historical Financials'!L7 -> 2Q24 | N3: ='Historical Financials'!M7 -> 3Q24 | O3: ='Historical Financials'!N7 -> 4Q24 | ... U3: ='Historical Financials'!T7 -> 0 | V3: ='Historical Financials'!#REF! -> #REF! | X3: =K3 -> 4Q23 | Y3: =L3 -> 1Q24 | Z3: =M3 -> 2Q24 | AA3: =N3 -> 3Q24 | AB3: =O3 -> 4Q24 | AC3: =P3 -> 1Q25 | AD3: =Q3 -> 2Q25 | AE3: =R3 -> 0 | ... AI3: =V3 -> #REF!
B4: $ in thousands except per share | C4: ='Historical Financials'!#REF! -> #REF! | D4: ='Historical Financials'!C8 -> 44651 | E4: ='Historical Financials'!D8 -> 45016 | F4: ='Historical Financials'!E8 -> 45382 | H4: ='Historical Financials'!G8 -> 44742 | I4: ='Historical Financials'!H8 -> 44834 | J4: ='Historical Financials'!I8 -> 44926 | K4: ='Historical Financials'!J8 -> 45016 | L4: ='Historical Financials'!K8 -> 45107 | M4: ='Historical Financials'!L8 -> 45199 | N4: ='Historical Financials'!M8 -> 45291 | O4: ='Historical Financials'!N8 -> 45382 | ... U4: ='Historical Financials'!T8 -> 0 | V4: ='Historical Financials'!#REF! -> #REF! | X4: =K4 -> 45016 | Y4: =L4 -> 45107 | Z4: =M4 -> 45199 | AA4: =N4 -> 45291 | AB4: =O4 -> 45382 | AC4: =P4 -> 45473 | AD4: =Q4 -> 45565 | AE4: =R4 -> 0 | ... AI4: =V4 -> #REF!
P6: ='Revenue Drivers'!P7 -> 0 | Q6: ='Revenue Drivers'!Q7 -> 0 | AC6: =SUM(M6:P6) -> 0 | AD6: =SUM(N6:Q6) -> 0 | AE6: =SUM(O6:R6) -> 0 | AF6: =SUM(P6:S6) -> 0 | AG6: =SUM(Q6:T6) -> 0 | AH6: =SUM(R6:U6) -> 0 | AI6: =SUM(S6:V6) -> 0 | AK6: =SUM(AI6/AE6)-1 -> #DIV/0!
P7: ='Revenue Drivers'!P8 -> 0 | Q7: ='Revenue Drivers'!Q8 -> 0 | AC7: =SUM(M7:P7) -> 0 | AD7: =SUM(N7:Q7) -> 0 | AE7: =SUM(O7:R7) -> 0 | AF7: =SUM(P7:S7) -> 0 | AG7: =SUM(Q7:T7) -> 0 | AH7: =SUM(R7:U7) -> 0 | AI7: =SUM(S7:V7) -> 0 | AK7: =SUM(AI7/AE7)-1 -> #DIV/0!
B8: Total Revenue | C8: ='Historical Financials'!#REF! -> #REF! | D8: =SUM(D6:D7) -> 0 | E8: =SUM(E6:E7) -> 0 | F8: =SUM(F6:F7) -> 0 | H8: ='Historical Financials'!G11 -> 97074 | I8: ='Historical Financials'!H11 -> 99137 | J8: ='Historical Financials'!I11 -> 111196 | K8: ='Historical Financials'!J11 -> 76025 | L8: ='Historical Financials'!K11 -> 91787 | M8: ='Historical Financials'!L11 -> 75680 | N8: ='Historical Financials'!M11 -> 71926 | O8: ='Historical Financials'!N11 -> 182684 | P8: =SUM(P6:P7) -> 0 | Q8: =SUM(Q6:Q7) -> 0 | R8: =SUM(R6:R7) -> 0 | S8: =SUM(S6:S7) -> 0 | T8: =SUM(T6:T7) -> 0 | U8: =SUM(U6:U7) -> 0 | V8: =SUM(V6:V7) -> 0 | X8: =SUM(H8:K8) -> 383432 | Y8: =SUM(I8:L8) -> 378145 | Z8: =SUM(J8:M8) -> 354688 | AA8: =SUM(K8:N8) -> 315418 | AB8: =SUM(L8:O8) -> 422077 | AC8: =SUM(AC6:AC7) -> 0 | AD8: =SUM(AD6:AD7) -> 0 | AE8: =SUM(AE6:AE7) -> 0 | AF8: =SUM(AF6:AF7) -> 0 | AG8: =SUM(AG6:AG7) -> 0 | AH8: =SUM(AH6:AH7) -> 0 | AI8: =SUM(AI6:AI7) -> 0 | AK8: =SUM(AI8/AE8)-1 -> #DIV/0!
B9: Y/Y Growth (%) | D9: =SUM(D8/C8)-1 -> #REF! | E9: =SUM(E8/D8)-1 -> #DIV/0! | F9: =SUM(F8/E8)-1 -> #DIV/0! | M9: =SUM(M8/I8)-1 -> -0.23661196 | N9: =SUM(N8/J8)-1 -> -0.35316019 | O9: =SUM(O8/K8)-1 -> 1.4029464 | P9: =SUM(P8/L8)-1 -> -1 | Q9: =SUM(Q8/M8)-1 -> -1 | R9: =SUM(R8/N8)-1 -> -1 | S9: =SUM(S8/O8)-1 -> -1 | T9: =SUM(T8/P8)-1 -> #DIV/0! | ... V9: =SUM(V8/R8)-1 -> #DIV/0! | AB9: =SUM(AB8/X8)-1 -> 0.1007871 | AC9: =SUM(AC8/Y8)-1 -> -1 | AD9: =SUM(AD8/Z8)-1 -> -1 | AE9: =SUM(AE8/AA8)-1 -> -1 | AF9: =SUM(AF8/AB8)-1 -> -1 | AG9: =SUM(AG8/AC8)-1 -> #DIV/0! | AH9: =SUM(AH8/AD8)-1 -> #DIV/0! | AI9: =SUM(AI8/AE8)-1 -> #DIV/0! | AK9: =SUM(AI9-AE9)*10000 -> #DIV/0!
B10: Q/Q Growth (%) | C10: N/A | D10: N/A | E10: N/A | F10: N/A | J10: =SUM(J8/I8)-1 -> 0.12163975 | K10: =SUM(K8/J8)-1 -> -0.31629735 | L10: =SUM(L8/K8)-1 -> 0.20732654 | M10: =SUM(M8/L8)-1 -> -0.17548237 | N10: =SUM(N8/M8)-1 -> -0.049603594 | O10: =SUM(O8/N8)-1 -> 1.5398882 | P10: =SUM(P8/O8)-1 -> -1 | Q10: =SUM(Q8/P8)-1 -> #DIV/0! | ... V10: =SUM(V8/U8)-1 -> #DIV/0! | X10: N/A | Y10: N/A | Z10: N/A | AA10: N/A | AB10: N/A | AC10: N/A | AD10: N/A | AE10: N/A | AF10: N/A | AG10: N/A | AH10: N/A | AI10: N/A
B12: (-) Cost of Sales | C12: ='Historical Financials'!#REF! -> #REF! | H12: ='Historical Financials'!G13 -> -63026 | I12: ='Historical Financials'!H13 -> -71306 | J12: ='Historical Financials'!I13 -> -70907 | K12: ='Historical Financials'!J13 -> -20553 | L12: ='Historical Financials'!K13 -> 0 | M12: ='Historical Financials'!L13 -> 0 | N12: ='Historical Financials'!M13 -> 0 | O12: ='Historical Financials'!N13 -> -278813 | ... Q12: ='Historical Financials'!P13 -> 0 | X12: =SUM(G12:K12) -> -225792 | Y12: =SUM(I12:L12) -> -162766 | Z12: =SUM(J12:M12) -> -91460 | AA12: =SUM(K12:N12) -> -20553 | AB12: =SUM(L12:O12) -> -278813 | AC12: =SUM(M12:P12) -> -278813 | AD12: =SUM(N12:Q12) -> -278813 | AE12: =SUM(O12:R12) -> -278813 | AF12: =SUM(P12:S12) -> 0 | ... AI12: =SUM(S12:V12) -> 0 | AK12: =SUM(AI12/AE12)-1 -> -1
B13: Gross Profit | C13: =+C8+C12 -> #REF! | D13: =+D8+D12 -> 0 | E13: =+E8+E12 -> 0 | F13: =+F8+F12 -> 0 | H13: =+H8+H12 -> 34048 | I13: =+I8+I12 -> 27831 | J13: =+J8+J12 -> 40289 | K13: =+K8+K12 -> 55472 | L13: =+L8+L12 -> 91787 | M13: =+M8+M12 -> 75680 | N13: =+N8+N12 -> 71926 | O13: =+O8+O12 -> -96129 | ... V13: =+V8+V12 -> 0 | X13: =+X8+X12 -> 157640 | Y13: =+Y8+Y12 -> 215379 | Z13: =+Z8+Z12 -> 263228 | AA13: =+AA8+AA12 -> 294865 | AB13: =+AB8+AB12 -> 143264 | AC13: =+AC8+AC12 -> -278813 | AD13: =+AD8+AD12 -> -278813 | AE13: =+AE8+AE12 -> -278813 | ... AI13: =+AI8+AI12 -> 0 | AK13: =SUM(AI13/AE13)-1 -> -1
B14: Gross Margin (%) | C14: =C13/C8 -> #REF! | D14: =D13/D8 -> #DIV/0! | E14: =E13/E8 -> #DIV/0! | F14: =F13/F8 -> #DIV/0! | H14: =H13/H8 -> 0.35074273 | I14: =I13/I8 -> 0.28073272 | J14: =J13/J8 -> 0.36232418 | K14: =K13/K8 -> 0.72965472 | L14: =L13/L8 -> 1 | M14: =M13/M8 -> 1 | N14: =N13/N8 -> 1 | O14: =O13/O8 -> -0.52620372 | ... V14: =V13/V8 -> #DIV/0! | X14: =X13/X8 -> 0.41112896 | Y14: =Y13/Y8 -> 0.56956723 | Z14: =Z13/Z8 -> 0.74213957 | AA14: =AA13/AA8 -> 0.93483885 | AB14: =AB13/AB8 -> 0.33942622 | AC14: =AC13/AC8 -> #DIV/0! | AD14: =AD13/AD8 -> #DIV/0! | AE14: =AE13/AE8 -> #DIV/0! | ... AI14: =AI13/AI8 -> #DIV/0! | AK14: =SUM(AI14-AE14)*10000 -> #DIV/0!
B16: (-) Research and development | C16: ='Historical Financials'!#REF! -> #REF! | H16: ='Historical Financials'!G17 -> -15962 | I16: ='Historical Financials'!H17 -> -15593 | J16: ='Historical Financials'!I17 -> -16339 | K16: ='Historical Financials'!J17 -> -15063 | L16: ='Historical Financials'!K17 -> -15839 | M16: ='Historical Financials'!L17 -> -15717 | N16: ='Historical Financials'!M17 -> -14244 | O16: ='Historical Financials'!N17 -> -20234 | ... Q16: ='Historical Financials'!P17 -> -13578 | X16: =SUM(G16:K16) -> -62957 | Y16: =SUM(I16:L16) -> -62834 | Z16: =SUM(J16:M16) -> -62958 | AA16: =SUM(K16:N16) -> -60863 | AB16: =SUM(L16:O16) -> -66034 | AC16: =SUM(M16:P16) -> -63490 | AD16: =SUM(N16:Q16) -> -61351 | AE16: =SUM(O16:R16) -> -47107 | AF16: =SUM(P16:S16) -> -26873 | ... AI16: =SUM(S16:V16) -> 0 | AK16: =SUM(AI16/AE16)-1 -> -1
B17: (-) Sales and marketing | C17: ='Historical Financials'!#REF! -> #REF! | H17: ='Historical Financials'!G18 -> -12314 | I17: ='Historical Financials'!H18 -> -11940 | J17: ='Historical Financials'!I18 -> -10969 | K17: ='Historical Financials'!J18 -> -10033 | L17: ='Historical Financials'!K18 -> -12699 | M17: ='Historical Financials'!L18 -> -10241 | N17: ='Historical Financials'!M18 -> -11893 | O17: ='Historical Financials'!N18 -> -12919 | ... Q17: ='Historical Financials'!P18 -> -13977 | X17: =SUM(G17:K17) -> -45256 | Y17: =SUM(I17:L17) -> -45641 | Z17: =SUM(J17:M17) -> -43942 | AA17: =SUM(K17:N17) -> -44866 | AB17: =SUM(L17:O17) -> -47752 | AC17: =SUM(M17:P17) -> -56118 | AD17: =SUM(N17:Q17) -> -59854 | AE17: =SUM(O17:R17) -> -47961 | AF17: =SUM(P17:S17) -> -35042 | ... AI17: =SUM(S17:V17) -> 0 | AK17: =SUM(AI17/AE17)-1 -> -1
B18: (-) General and administrative | C18: ='Historical Financials'!#REF! -> #REF! | H18: ='Historical Financials'!#REF! -> #REF! | I18: ='Historical Financials'!#REF! -> #REF! | J18: ='Historical Financials'!#REF! -> #REF! | K18: ='Historical Financials'!#REF! -> #REF! | L18: ='Historical Financials'!#REF! -> #REF! | M18: ='Historical Financials'!#REF! -> #REF! | N18: ='Historical Financials'!#REF! -> #REF! | O18: ='Historical Financials'!#REF! -> #REF! | ... Q18: ='Historical Financials'!#REF! -> #REF! | X18: =SUM(G18:K18) -> #REF! | Y18: =SUM(I18:L18) -> #REF! | Z18: =SUM(J18:M18) -> #REF! | AA18: =SUM(K18:N18) -> #REF! | AB18: =SUM(L18:O18) -> #REF! | AC18: =SUM(M18:P18) -> #REF! | AD18: =SUM(N18:Q18) -> #REF! | AE18: =SUM(O18:R18) -> #REF! | AF18: =SUM(P18:S18) -> #REF! | ... AI18: =SUM(S18:V18) -> 0 | AK18: =SUM(AI18/AE18)-1 -> #REF!
B19: (-) Depreciation and amortization | C19: ='Historical Financials'!#REF! -> #REF! | H19: ='Historical Financials'!G20 -> -725 | I19: ='Historical Financials'!H20 -> -921 | J19: ='Historical Financials'!I20 -> -41 | K19: ='Historical Financials'!J20 -> 837 | L19: ='Historical Financials'!K20 -> -1329 | M19: ='Historical Financials'!L20 -> -1338 | N19: ='Historical Financials'!M20 -> -497 | O19: ='Historical Financials'!N20 -> 1559 | ... Q19: ='Historical Financials'!P20 -> -383 | X19: =SUM(G19:K19) -> -850 | Y19: =SUM(I19:L19) -> -1454 | Z19: =SUM(J19:M19) -> -1871 | AA19: =SUM(K19:N19) -> -2327 | AB19: =SUM(L19:O19) -> -1605 | AC19: =SUM(M19:P19) -> -1468 | AD19: =SUM(N19:Q19) -> -513 | AE19: =SUM(O19:R19) -> -16 | AF19: =SUM(P19:S19) -> -1575 | ... AI19: =SUM(S19:V19) -> 0 | AK19: =SUM(AI19/AE19)-1 -> -1
B20: Earning before Interest & Taxes (EBIT) | C20: =SUM(C13+SUM(C16:C19)) -> #REF! | D20: =SUM(D13+SUM(D16:D19)) -> 0 | E20: =SUM(E13+SUM(E16:E19)) -> 0 | F20: =SUM(F13+SUM(F16:F19)) -> 0 | H20: =SUM(H13+SUM(H16:H19)) -> #REF! | I20: =SUM(I13+SUM(I16:I19)) -> #REF! | J20: =SUM(J13+SUM(J16:J19)) -> #REF! | K20: =SUM(K13+SUM(K16:K19)) -> #REF! | L20: =SUM(L13+SUM(L16:L19)) -> #REF! | M20: =SUM(M13+SUM(M16:M19)) -> #REF! | N20: =SUM(N13+SUM(N16:N19)) -> #REF! | O20: =SUM(O13+SUM(O16:O19)) -> #REF! | ... V20: =SUM(V13+SUM(V16:V19)) -> 0 | X20: =SUM(X13+SUM(X16:X19)) -> #REF! | Y20: =SUM(Y13+SUM(Y16:Y19)) -> #REF! | Z20: =SUM(Z13+SUM(Z16:Z19)) -> #REF! | AA20: =SUM(AA13+SUM(AA16:AA19)) -> #REF! | AB20: =SUM(AB13+SUM(AB16:AB19)) -> #REF! | AC20: =SUM(AC13+SUM(AC16:AC19)) -> #REF! | AD20: =SUM(AD13+SUM(AD16:AD19)) -> #REF! | AE20: =SUM(AE13+SUM(AE16:AE19)) -> #REF! | ... AI20: =SUM(AI13+SUM(AI16:AI19)) -> 0 | AK20: =SUM(AI20/AE20)-1 -> #REF!
B21: Operating Margin (%) | C21: =C20/C8 -> #REF! | D21: =D20/D8 -> #DIV/0! | E21: =E20/E8 -> #DIV/0! | F21: =F20/F8 -> #DIV/0! | H21: =H20/H8 -> #REF! | I21: =I20/I8 -> #REF! | J21: =J20/J8 -> #REF! | K21: =K20/K8 -> #REF! | L21: =L20/L8 -> #REF! | M21: =M20/M8 -> #REF! | N21: =N20/N8 -> #REF! | O21: =O20/O8 -> #REF! | ... V21: =V20/V8 -> #DIV/0! | X21: =X20/X8 -> #REF! | Y21: =Y20/Y8 -> #REF! | Z21: =Z20/Z8 -> #REF! | AA21: =AA20/AA8 -> #REF! | AB21: =AB20/AB8 -> #REF! | AC21: =AC20/AC8 -> #REF! | AD21: =AD20/AD8 -> #REF! | AE21: =AE20/AE8 -> #REF! | ... AI21: =AI20/AI8 -> #DIV/0! | AK21: =SUM(AI21-AE21)*10000 -> #DIV/0!
B23: (+) Depreciation and Amortization | C23: =-C19 -> #REF! | H23: =-H19 -> 725 | I23: =-I19 -> 921 | J23: =-J19 -> 41 | K23: =-K19 -> -837 | L23: =-L19 -> 1329 | M23: =-M19 -> 1338 | N23: =-N19 -> 497 | O23: =-O19 -> -1559 | ... Q23: =-Q19 -> 383 | X23: =SUM(G23:K23) -> 850 | Y23: =SUM(I23:L23) -> 1454 | Z23: =SUM(J23:M23) -> 1871 | AA23: =SUM(K23:N23) -> 2327 | AB23: =SUM(L23:O23) -> 1605 | AC23: =SUM(M23:P23) -> 1468 | AD23: =SUM(N23:Q23) -> 513 | AE23: =SUM(O23:R23) -> 16 | AF23: =SUM(P23:S23) -> 1575 | ... AI23: =SUM(S23:V23) -> 0 | AK23: =SUM(AI23/AE23)-1 -> -1
B24: EBITDA | C24: =SUM(C20+C23) -> #REF! | D24: =SUM(D20+D23) -> 0 | E24: =SUM(E20+E23) -> 0 | F24: =SUM(F20+F23) -> 0 | H24: =SUM(H20+H23) -> #REF! | I24: =SUM(I20+I23) -> #REF! | J24: =SUM(J20+J23) -> #REF! | K24: =SUM(K20+K23) -> #REF! | L24: =SUM(L20+L23) -> #REF! | M24: =SUM(M20+M23) -> #REF! | N24: =SUM(N20+N23) -> #REF! | O24: =SUM(O20+O23) -> #REF! | ... V24: =SUM(V20+V23) -> 0 | X24: =SUM(X20+X23) -> #REF! | Y24: =SUM(Y20+Y23) -> #REF! | Z24: =SUM(Z20+Z23) -> #REF! | AA24: =SUM(AA20+AA23) -> #REF! | AB24: =SUM(AB20+AB23) -> #REF! | AC24: =SUM(AC20+AC23) -> #REF! | AD24: =SUM(AD20+AD23) -> #REF! | AE24: =SUM(AE20+AE23) -> #REF! | ... AI24: =SUM(AI20+AI23) -> 0 | AK24: =SUM(AI24/AE24)-1 -> #REF!
B25: EBITDA Margin (%) | C25: =C24/C8 -> #REF! | D25: =D24/D8 -> #DIV/0! | E25: =E24/E8 -> #DIV/0! | F25: =F24/F8 -> #DIV/0! | H25: =H24/H8 -> #REF! | I25: =I24/I8 -> #REF! | J25: =J24/J8 -> #REF! | K25: =K24/K8 -> #REF! | L25: =L24/L8 -> #REF! | M25: =M24/M8 -> #REF! | N25: =N24/N8 -> #REF! | O25: =O24/O8 -> #REF! | ... V25: =V24/V8 -> #DIV/0! | X25: =X24/X8 -> #REF! | Y25: =Y24/Y8 -> #REF! | Z25: =Z24/Z8 -> #REF! | AA25: =AA24/AA8 -> #REF! | AB25: =AB24/AB8 -> #REF! | AC25: =AC24/AC8 -> #REF! | AD25: =AD24/AD8 -> #REF! | AE25: =AE24/AE8 -> #REF! | ... AI25: =AI24/AI8 -> #DIV/0! | AK25: =SUM(AI25-AE25)*10000 -> #DIV/0!
B27: (+) Share-based Compensation | C27: ='Historical Financials'!#REF! -> #REF! | H27: ='Historical Financials'!G102 -> 336 | I27: ='Historical Financials'!H102 -> 432 | J27: ='Historical Financials'!I102 -> 433 | K27: ='Historical Financials'!J102 -> 423 | L27: ='Historical Financials'!K102 -> 520 | M27: ='Historical Financials'!L102 -> 714 | N27: ='Historical Financials'!M102 -> 714 | O27: ='Historical Financials'!N102 -> 787 | ... Q27: ='Historical Financials'!P102 -> 1277 | X27: =SUM(G27:K27) -> 1624 | Y27: =SUM(I27:L27) -> 1808 | Z27: =SUM(J27:M27) -> 2090 | AA27: =SUM(K27:N27) -> 2371 | AB27: =SUM(L27:O27) -> 2735 | AC27: =SUM(M27:P27) -> 3019 | AD27: =SUM(N27:Q27) -> 3582 | AE27: =SUM(O27:R27) -> 2868 | AF27: =SUM(P27:S27) -> 2081 | ... AI27: =SUM(S27:V27) -> 0 | AK27: =SUM(AI27/AE27)-1 -> -1
B28: Adj. EBITDA | C28: =+SUM(C24+SUM(C27:C27)) -> #REF! | D28: =+SUM(D24+SUM(D27:D27)) -> 0 | E28: =+SUM(E24+SUM(E27:E27)) -> 0 | F28: =+SUM(F24+SUM(F27:F27)) -> 0 | H28: =+SUM(H24+SUM(H27:H27)) -> #REF! | I28: =+SUM(I24+SUM(I27:I27)) -> #REF! | J28: =+SUM(J24+SUM(J27:J27)) -> #REF! | K28: =+SUM(K24+SUM(K27:K27)) -> #REF! | L28: =+SUM(L24+SUM(L27:L27)) -> #REF! | M28: =+SUM(M24+SUM(M27:M27)) -> #REF! | N28: =+SUM(N24+SUM(N27:N27)) -> #REF! | O28: =+SUM(O24+SUM(O27:O27)) -> #REF! | ... V28: =+SUM(V24+SUM(V27:V27)) -> 0 | X28: =+SUM(X24+SUM(X27:X27)) -> #REF! | Y28: =+SUM(Y24+SUM(Y27:Y27)) -> #REF! | Z28: =+SUM(Z24+SUM(Z27:Z27)) -> #REF! | AA28: =+SUM(AA24+SUM(AA27:AA27)) -> #REF! | AB28: =+SUM(AB24+SUM(AB27:AB27)) -> #REF! | AC28: =+SUM(AC24+SUM(AC27:AC27)) -> #REF! | AD28: =+SUM(AD24+SUM(AD27:AD27)) -> #REF! | AE28: =+SUM(AE24+SUM(AE27:AE27)) -> #REF! | ... AI28: =+SUM(AI24+SUM(AI27:AI27)) -> 0 | AK28: =SUM(AI28/AE28)-1 -> #REF!
B29: Adj. EBITDA Margin (%) | C29: =C28/C8 -> #REF! | D29: =D28/D8 -> #DIV/0! | E29: =E28/E8 -> #DIV/0! | F29: =F28/F8 -> #DIV/0! | H29: =H28/H8 -> #REF! | I29: =I28/I8 -> #REF! | J29: =J28/J8 -> #REF! | K29: =K28/K8 -> #REF! | L29: =L28/L8 -> #REF! | M29: =M28/M8 -> #REF! | N29: =N28/N8 -> #REF! | O29: =O28/O8 -> #REF! | ... V29: =V28/V8 -> #DIV/0! | X29: =X28/X8 -> #REF! | Y29: =Y28/Y8 -> #REF! | Z29: =Z28/Z8 -> #REF! | AA29: =AA28/AA8 -> #REF! | AB29: =AB28/AB8 -> #REF! | AC29: =AC28/AC8 -> #REF! | AD29: =AD28/AD8 -> #REF! | AE29: =AE28/AE8 -> #REF! | ... AI29: =AI28/AI8 -> #DIV/0! | AK29: =SUM(AI29-AE29)*10000 -> #DIV/0!
B31: (-) Capital Expenditures | C31: =SUM('Historical Financials'!#REF!+'Historical Financials'!#REF!) -> #REF! | H31: =SUM('Historical Financials'!G126+'Historical Financials'!G127) -> -5036 | I31: =SUM('Historical Financials'!H126+'Historical Financials'!H127) -> -4759 | J31: =SUM('Historical Financials'!I126+'Historical Financials'!I127) -> -2849 | K31: =SUM('Historical Financials'!J126+'Historical Financials'!J127) -> -2957 | L31: =SUM('Historical Financials'!K126+'Historical Financials'!K127) -> -2299 | M31: =SUM('Historical Financials'!L126+'Historical Financials'!L127) -> -1626 | N31: =SUM('Historical Financials'!M126+'Historical Financials'!M127) -> -1100 | O31: =SUM('Historical Financials'!N126+'Historical Financials'!N127) -> -844 | ... Q31: =SUM('Historical Financials'!P126+'Historical Financials'!P127) -> -1608 | X31: =SUM(G31:K31) -> -15601 | Y31: =SUM(I31:L31) -> -12864 | Z31: =SUM(J31:M31) -> -9731 | AA31: =SUM(K31:N31) -> -7982 | AB31: =SUM(L31:O31) -> -5869 | AC31: =SUM(M31:P31) -> -5190 | AD31: =SUM(N31:Q31) -> -5172 | AE31: =SUM(O31:R31) -> -4072 | AF31: =SUM(P31:S31) -> -3228 | ... AI31: =SUM(S31:V31) -> 0 | AK31: =SUM(AI31/AE31)-1 -> -1
B32: (-) Cash Taxes | C32: ='Historical Financials'!#REF! -> #REF! | H32: ='Historical Financials'!G31 -> -410 | I32: ='Historical Financials'!H31 -> -461 | J32: ='Historical Financials'!I31 -> 693 | K32: ='Historical Financials'!J31 -> -1163 | L32: ='Historical Financials'!K31 -> -530 | M32: ='Historical Financials'!L31 -> -533 | N32: ='Historical Financials'!M31 -> -510 | O32: ='Historical Financials'!N31 -> -367 | ... Q32: ='Historical Financials'!P31 -> -370 | X32: =SUM(G32:K32) -> -1341 | Y32: =SUM(I32:L32) -> -1461 | Z32: =SUM(J32:M32) -> -1533 | AA32: =SUM(K32:N32) -> -2736 | AB32: =SUM(L32:O32) -> -1940 | AC32: =SUM(M32:P32) -> -1645 | AD32: =SUM(N32:Q32) -> -1482 | AE32: =SUM(O32:R32) -> -972 | AF32: =SUM(P32:S32) -> -605 | ... AI32: =SUM(S32:V32) -> 0 | AK32: =SUM(AI32/AE32)-1 -> -1
B33: (-) Cash Interest | C33: 0 | H33: 0 | I33: 0 | J33: 0 | K33: =D33 -> 0 | L33: 0 | M33: 0 | N33: 0 | O33: =E33 -> 0 | P33: 0 | Q33: 0 | X33: =SUM(G33:K33) -> 0 | Y33: =SUM(I33:L33) -> 0 | Z33: =SUM(J33:M33) -> 0 | AA33: =SUM(K33:N33) -> 0 | AB33: =SUM(L33:O33) -> 0 | AC33: =SUM(M33:P33) -> 0 | AD33: =SUM(N33:Q33) -> 0 | AE33: =SUM(O33:R33) -> 0 | AF33: =SUM(P33:S33) -> 0 | ... AI33: =SUM(S33:V33) -> 0 | AK33: =SUM(AI33/AE33)-1 -> #DIV/0!
B34: (+/-) Changes in NWC | C34: =SUM('Historical Financials'!#REF!) -> #REF! | H34: =SUM('Historical Financials'!G113:G122) -> -15271 | I34: =SUM('Historical Financials'!H113:H122) -> 222 | J34: =SUM('Historical Financials'!I113:I122) -> -6122 | K34: =SUM('Historical Financials'!J113:J122) -> 5426 | L34: =SUM('Historical Financials'!K113:K122) -> -6502 | M34: =SUM('Historical Financials'!L113:L122) -> 1679 | N34: =SUM('Historical Financials'!M113:M122) -> -5842 | O34: =SUM('Historical Financials'!N113:N122) -> 19175 | ... Q34: =SUM('Historical Financials'!P113:P122) -> -7269 | X34: =SUM(G34:K34) -> -15745 | Y34: =SUM(I34:L34) -> -6976 | Z34: =SUM(J34:M34) -> -5519 | AA34: =SUM(K34:N34) -> -5239 | AB34: =SUM(L34:O34) -> 8510 | AC34: =SUM(M34:P34) -> 30716 | AD34: =SUM(N34:Q34) -> 21768 | AE34: =SUM(O34:R34) -> 27610 | AF34: =SUM(P34:S34) -> 8435 | ... AI34: =SUM(S34:V34) -> 0 | AK34: =SUM(AI34/AE34)-1 -> -1
B35: Discretionary Cash-Flows | C35: =SUM(C28+SUM(C31:C34)) -> #REF! | D35: =SUM(D28+SUM(D31:D34)) -> 0 | E35: =SUM(E28+SUM(E31:E34)) -> 0 | F35: =SUM(F28+SUM(F31:F34)) -> 0 | H35: =SUM(H28+SUM(H31:H34)) -> #REF! | I35: =SUM(I28+SUM(I31:I34)) -> #REF! | J35: =SUM(J28+SUM(J31:J34)) -> #REF! | K35: =SUM(K28+SUM(K31:K34)) -> #REF! | L35: =SUM(L28+SUM(L31:L34)) -> #REF! | M35: =SUM(M28+SUM(M31:M34)) -> #REF! | N35: =SUM(N28+SUM(N31:N34)) -> #REF! | O35: =SUM(O28+SUM(O31:O34)) -> #REF! | ... V35: =SUM(V28+SUM(V31:V34)) -> 0 | X35: =SUM(X28+SUM(X31:X34)) -> #REF! | Y35: =SUM(Y28+SUM(Y31:Y34)) -> #REF! | Z35: =SUM(Z28+SUM(Z31:Z34)) -> #REF! | AA35: =SUM(AA28+SUM(AA31:AA34)) -> #REF! | AB35: =SUM(AB28+SUM(AB31:AB34)) -> #REF! | AC35: =SUM(AC28+SUM(AC31:AC34)) -> #REF! | AD35: =SUM(AD28+SUM(AD31:AD34)) -> #REF! | AE35: =SUM(AE28+SUM(AE31:AE34)) -> #REF! | ... AI35: =SUM(AI28+SUM(AI31:AI34)) -> 0 | AK35: =SUM(AI35/AE35)-1 -> #REF!
B37: (+/-) Proceeds / (Purchases) of Equity, net | C37: ='Historical Financials'!#REF! -> #REF! | H37: ='Historical Financials'!#REF! -> #REF! | I37: ='Historical Financials'!#REF! -> #REF! | J37: ='Historical Financials'!#REF! -> #REF! | K37: ='Historical Financials'!#REF! -> #REF! | L37: ='Historical Financials'!#REF! -> #REF! | M37: ='Historical Financials'!#REF! -> #REF! | N37: ='Historical Financials'!#REF! -> #REF! | O37: ='Historical Financials'!#REF! -> #REF! | ... Q37: ='Historical Financials'!#REF! -> #REF! | X37: =SUM(G37:K37) -> #REF! | Y37: =SUM(I37:L37) -> #REF! | Z37: =SUM(J37:M37) -> #REF! | AA37: =SUM(K37:N37) -> #REF! | AB37: =SUM(L37:O37) -> #REF! | AC37: =SUM(M37:P37) -> #REF! | AD37: =SUM(N37:Q37) -> #REF! | AE37: =SUM(O37:R37) -> #REF! | AF37: =SUM(P37:S37) -> #REF! | ... AI37: =SUM(S37:V37) -> 0
B38: (+/-) Maturities / (Purchases) of available-for-sale securities | C38: =SUM('Historical Financials'!#REF!) -> #REF! | H38: =SUM('Historical Financials'!#REF!) -> #REF! | I38: =SUM('Historical Financials'!#REF!) -> #REF! | J38: =SUM('Historical Financials'!#REF!) -> #REF! | K38: =SUM('Historical Financials'!#REF!) -> #REF! | L38: =SUM('Historical Financials'!#REF!) -> #REF! | M38: =SUM('Historical Financials'!#REF!) -> #REF! | N38: =SUM('Historical Financials'!#REF!) -> #REF! | O38: =SUM('Historical Financials'!#REF!) -> #REF! | ... Q38: =SUM('Historical Financials'!#REF!) -> #REF! | X38: =SUM(G38:K38) -> #REF! | Y38: =SUM(I38:L38) -> #REF! | Z38: =SUM(J38:M38) -> #REF! | AA38: =SUM(K38:N38) -> #REF! | AB38: =SUM(L38:O38) -> #REF! | AC38: =SUM(M38:P38) -> #REF! | AD38: =SUM(N38:Q38) -> #REF! | AE38: =SUM(O38:R38) -> #REF! | AF38: =SUM(P38:S38) -> #REF! | ... AI38: =SUM(S38:V38) -> 0
B39: (+/-) Divestitures / (Acquisitions) | C39: ='Historical Financials'!#REF! -> #REF! | H39: ='Historical Financials'!#REF! -> #REF! | I39: ='Historical Financials'!#REF! -> #REF! | J39: ='Historical Financials'!#REF! -> #REF! | K39: ='Historical Financials'!#REF! -> #REF! | L39: ='Historical Financials'!#REF! -> #REF! | M39: ='Historical Financials'!#REF! -> #REF! | N39: ='Historical Financials'!#REF! -> #REF! | O39: ='Historical Financials'!#REF! -> #REF! | ... Q39: ='Historical Financials'!#REF! -> #REF! | X39: =SUM(G39:K39) -> #REF! | Y39: =SUM(I39:L39) -> #REF! | Z39: =SUM(J39:M39) -> #REF! | AA39: =SUM(K39:N39) -> #REF! | AB39: =SUM(L39:O39) -> #REF! | AC39: =SUM(M39:P39) -> #REF! | AD39: =SUM(N39:Q39) -> #REF! | AE39: =SUM(O39:R39) -> #REF! | AF39: =SUM(P39:S39) -> #REF! | ... AI39: =SUM(S39:V39) -> 0
B40: (+/-) Other Investing Activities | C40: ='Historical Financials'!#REF! -> #REF! | H40: ='Historical Financials'!#REF! -> #REF! | I40: ='Historical Financials'!#REF! -> #REF! | J40: ='Historical Financials'!#REF! -> #REF! | K40: ='Historical Financials'!#REF! -> #REF! | L40: ='Historical Financials'!#REF! -> #REF! | M40: ='Historical Financials'!#REF! -> #REF! | N40: ='Historical Financials'!#REF! -> #REF! | O40: ='Historical Financials'!#REF! -> #REF! | ... Q40: ='Historical Financials'!#REF! -> #REF! | X40: =SUM(G40:K40) -> #REF! | Y40: =SUM(I40:L40) -> #REF! | Z40: =SUM(J40:M40) -> #REF! | AA40: =SUM(K40:N40) -> #REF! | AB40: =SUM(L40:O40) -> #REF! | AC40: =SUM(M40:P40) -> #REF! | AD40: =SUM(N40:Q40) -> #REF! | AE40: =SUM(O40:R40) -> #REF! | AF40: =SUM(P40:S40) -> #REF! | ... AI40: =SUM(S40:V40) -> 0
B41: (+/-) Other Financing Activities | C41: ='Historical Financials'!#REF! -> #REF! | H41: ='Historical Financials'!#REF! -> #REF! | I41: ='Historical Financials'!#REF! -> #REF! | J41: ='Historical Financials'!#REF! -> #REF! | K41: ='Historical Financials'!#REF! -> #REF! | L41: ='Historical Financials'!#REF! -> #REF! | M41: ='Historical Financials'!#REF! -> #REF! | N41: ='Historical Financials'!#REF! -> #REF! | O41: ='Historical Financials'!#REF! -> #REF! | ... Q41: ='Historical Financials'!#REF! -> #REF! | X41: =SUM(G41:K41) -> #REF! | Y41: =SUM(I41:L41) -> #REF! | Z41: =SUM(J41:M41) -> #REF! | AA41: =SUM(K41:N41) -> #REF! | AB41: =SUM(L41:O41) -> #REF! | AC41: =SUM(M41:P41) -> #REF! | AD41: =SUM(N41:Q41) -> #REF! | AE41: =SUM(O41:R41) -> #REF! | AF41: =SUM(P41:S41) -> #REF! | ... AI41: =SUM(S41:V41) -> 0
B42: (+/-) Other Operating Activities | C42: ='Historical Financials'!#REF! -> #REF! | H42: ='Historical Financials'!#REF! -> #REF! | I42: ='Historical Financials'!#REF! -> #REF! | J42: ='Historical Financials'!#REF! -> #REF! | K42: ='Historical Financials'!#REF! -> #REF! | L42: ='Historical Financials'!#REF! -> #REF! | M42: ='Historical Financials'!#REF! -> #REF! | N42: ='Historical Financials'!#REF! -> #REF! | O42: ='Historical Financials'!#REF! -> #REF! | ... Q42: ='Historical Financials'!#REF! -> #REF! | X42: =SUM(G42:K42) -> #REF! | Y42: =SUM(I42:L42) -> #REF! | Z42: =SUM(J42:M42) -> #REF! | AA42: =SUM(K42:N42) -> #REF! | AB42: =SUM(L42:O42) -> #REF! | AC42: =SUM(M42:P42) -> #REF! | AD42: =SUM(N42:Q42) -> #REF! | AE42: =SUM(O42:R42) -> #REF! | AF42: =SUM(P42:S42) -> #REF! | ... AI42: =SUM(S42:V42) -> 0
B43: (+/-) Other | H43: =SUM(H48:H49)-SUM(C48:C49)-SUM(H35:H42) -> #REF! | I43: =SUM(I48:I49)-SUM(H48:H49)-SUM(I35:I42) -> #REF! | J43: =SUM(J48:J49)-SUM(I48:I49)-SUM(J35:J42) -> #REF! | K43: =SUM(K48:K49)-SUM(J48:J49)-SUM(K35:K42) -> #REF! | L43: =SUM(L48:L49)-SUM(K48:K49)-SUM(L35:L42) -> #REF! | M43: =SUM(M48:M49)-SUM(L48:L49)-SUM(M35:M42) -> #REF! | N43: =SUM(N48:N49)-SUM(M48:M49)-SUM(N35:N42) -> #REF! | O43: =SUM(O48:O49)-SUM(N48:N49)-SUM(O35:O42) -> #REF! | P43: =SUM(P48:P49)-SUM(O48:O49)-SUM(P35:P42) -> #REF! | Q43: =SUM(Q48:Q49)-SUM(P48:P49)-SUM(Q35:Q42) -> #REF! | X43: =SUM(G43:K43) -> #REF! | Y43: =SUM(I43:L43) -> #REF! | Z43: =SUM(J43:M43) -> #REF! | AA43: =SUM(K43:N43) -> #REF! | AB43: =SUM(L43:O43) -> #REF! | AC43: =SUM(M43:P43) -> #REF! | AD43: =SUM(N43:Q43) -> #REF! | AE43: =SUM(O43:R43) -> #REF! | AF43: =SUM(P43:S43) -> #REF! | ... AI43: =SUM(S43:V43) -> 0
B44: Free-Cash Flows | C44: =SUM(C35+SUM(C37:C43)) -> #REF! | D44: =SUM(D35+SUM(D37:D43)) -> 0 | E44: =SUM(E35+SUM(E37:E43)) -> 0 | F44: =SUM(F35+SUM(F37:F43)) -> 0 | H44: =SUM(H35+SUM(H37:H43)) -> #REF! | I44: =SUM(I35+SUM(I37:I43)) -> #REF! | J44: =SUM(J35+SUM(J37:J43)) -> #REF! | K44: =SUM(K35+SUM(K37:K43)) -> #REF! | L44: =SUM(L35+SUM(L37:L43)) -> #REF! | M44: =SUM(M35+SUM(M37:M43)) -> #REF! | N44: =SUM(N35+SUM(N37:N43)) -> #REF! | O44: =SUM(O35+SUM(O37:O43)) -> #REF! | ... V44: =SUM(V35+SUM(V37:V43)) -> 0 | X44: =SUM(X35+SUM(X37:X43)) -> #REF! | Y44: =SUM(Y35+SUM(Y37:Y43)) -> #REF! | Z44: =SUM(Z35+SUM(Z37:Z43)) -> #REF! | AA44: =SUM(AA35+SUM(AA37:AA43)) -> #REF! | AB44: =SUM(AB35+SUM(AB37:AB43)) -> #REF! | AC44: =SUM(AC35+SUM(AC37:AC43)) -> #REF! | AD44: =SUM(AD35+SUM(AD37:AD43)) -> #REF! | AE44: =SUM(AE35+SUM(AE37:AE43)) -> #REF! | ... AI44: =SUM(AI35+SUM(AI37:AI43)) -> 0
B46: Capitalization
B48: Cash & Cash Equivelants | C48: ='Historical Financials'!#REF! -> #REF! | H48: ='Historical Financials'!G46 -> 26528 | I48: ='Historical Financials'!H46 -> 25698 | J48: ='Historical Financials'!I46 -> 26028 | K48: ='Historical Financials'!J46 -> 5210 | L48: ='Historical Financials'!K46 -> 25465 | M48: ='Historical Financials'!L46 -> 25574 | N48: ='Historical Financials'!M46 -> 24377 | O48: ='Historical Financials'!N46 -> 25963 | ... Q48: ='Historical Financials'!P46 -> 16719 | X48: =K48 -> 5210 | Y48: =L48 -> 25465 | Z48: =M48 -> 25574 | AA48: =N48 -> 24377 | AB48: =O48 -> 25963 | AC48: =P48 -> 17287 | AD48: =Q48 -> 16719 | AE48: =R48 -> 0 | ... AI48: =V48 -> 0
B49: Restricted Cash | C49: ='Historical Financials'!#REF! -> #REF! | H49: ='Historical Financials'!G52 -> 4574 | I49: ='Historical Financials'!H52 -> 4839 | J49: ='Historical Financials'!I52 -> 7489 | K49: ='Historical Financials'!J52 -> 4697 | L49: ='Historical Financials'!K52 -> 6004 | M49: ='Historical Financials'!L52 -> 5389 | N49: ='Historical Financials'!M52 -> 7224 | O49: ='Historical Financials'!N52 -> 5513 | ... Q49: ='Historical Financials'!P52 -> 9195 | X49: =K49 -> 4697 | Y49: =L49 -> 6004 | Z49: =M49 -> 5389 | AA49: =N49 -> 7224 | AB49: =O49 -> 5513 | AC49: =P49 -> 8965 | AD49: =Q49 -> 9195 | AE49: =R49 -> 0 | ... AI49: =V49 -> 0
B50: Short-term Investments | C50: ='Historical Financials'!#REF! -> #REF! | H50: ='Historical Financials'!#REF! -> #REF! | I50: ='Historical Financials'!#REF! -> #REF! | J50: ='Historical Financials'!#REF! -> #REF! | K50: ='Historical Financials'!#REF! -> #REF! | L50: ='Historical Financials'!#REF! -> #REF! | M50: ='Historical Financials'!#REF! -> #REF! | N50: ='Historical Financials'!#REF! -> #REF! | O50: ='Historical Financials'!#REF! -> #REF! | ... Q50: ='Historical Financials'!#REF! -> #REF! | X50: =K50 -> #REF! | Y50: =L50 -> #REF! | Z50: =M50 -> #REF! | AA50: =N50 -> #REF! | AB50: =O50 -> #REF! | AC50: =P50 -> #REF! | AD50: =Q50 -> #REF! | AE50: =R50 -> 0 | ... AI50: =V50 -> 0
B51: Long-term Investments | C51: ='Historical Financials'!#REF! -> #REF! | H51: ='Historical Financials'!G56 -> 14093 | I51: ='Historical Financials'!H56 -> 15973 | J51: ='Historical Financials'!I56 -> 16794 | K51: ='Historical Financials'!J56 -> 12853 | L51: ='Historical Financials'!K56 -> 15583 | M51: ='Historical Financials'!L56 -> 14621 | N51: ='Historical Financials'!M56 -> 13251 | O51: ='Historical Financials'!N56 -> 16555 | ... Q51: ='Historical Financials'!P56 -> 11334 | X51: =K51 -> 12853 | Y51: =L51 -> 15583 | Z51: =M51 -> 14621 | AA51: =N51 -> 13251 | AB51: =O51 -> 16555 | AC51: =P51 -> 10988 | AD51: =Q51 -> 11334 | AE51: =R51 -> 0 | ... AI51: =V51 -> 0
B52: Total Liquidity | C52: =SUM(C48:C51) -> #REF! | D52: =SUM(D48:D51) -> 0 | E52: =SUM(E48:E51) -> 0 | F52: =SUM(F48:F51) -> 0 | H52: =SUM(H48:H51) -> #REF! | I52: =SUM(I48:I51) -> #REF! | J52: =SUM(J48:J51) -> #REF! | K52: =SUM(K48:K51) -> #REF! | L52: =SUM(L48:L51) -> #REF! | M52: =SUM(M48:M51) -> #REF! | N52: =SUM(N48:N51) -> #REF! | O52: =SUM(O48:O51) -> #REF! | ... V52: =SUM(V48:V51) -> 0 | X52: =SUM(X48:X51) -> #REF! | Y52: =SUM(Y48:Y51) -> #REF! | Z52: =SUM(Z48:Z51) -> #REF! | AA52: =SUM(AA48:AA51) -> #REF! | AB52: =SUM(AB48:AB51) -> #REF! | AC52: =SUM(AC48:AC51) -> #REF! | AD52: =SUM(AD48:AD51) -> #REF! | AE52: =SUM(AE48:AE51) -> 0 | ... AI52: =SUM(AI48:AI51) -> 0
B54: Balance Sheet Metrics:
B55: Accounts Receivable | C55: ='Historical Financials'!#REF! -> #REF! | H55: ='Historical Financials'!#REF! -> #REF! | I55: ='Historical Financials'!#REF! -> #REF! | J55: ='Historical Financials'!#REF! -> #REF! | K55: ='Historical Financials'!#REF! -> #REF! | L55: ='Historical Financials'!#REF! -> #REF! | M55: ='Historical Financials'!#REF! -> #REF! | N55: ='Historical Financials'!#REF! -> #REF! | O55: ='Historical Financials'!#REF! -> #REF! | ... Q55: ='Historical Financials'!#REF! -> #REF! | X55: =K55 -> #REF! | Y55: =L55 -> #REF! | Z55: =M55 -> #REF! | AA55: =N55 -> #REF! | AB55: =O55 -> #REF! | AC55: =P55 -> #REF! | AD55: =Q55 -> #REF! | AE55: =R55 -> 0 | ... AI55: =V55 -> 0
B56: Accounts Payable | C56: ='Historical Financials'!#REF! -> #REF! | H56: ='Historical Financials'!G64 -> 33867 | I56: ='Historical Financials'!H64 -> 34263 | J56: ='Historical Financials'!I64 -> 41788 | K56: ='Historical Financials'!J64 -> 34220 | L56: ='Historical Financials'!K64 -> 30560 | M56: ='Historical Financials'!L64 -> 26946 | N56: ='Historical Financials'!M64 -> 22426 | O56: ='Historical Financials'!N64 -> 35716 | ... Q56: ='Historical Financials'!P64 -> 30789 | X56: =K56 -> 34220 | Y56: =L56 -> 30560 | Z56: =M56 -> 26946 | AA56: =N56 -> 22426 | AB56: =O56 -> 35716 | AC56: =P56 -> 31509 | AD56: =Q56 -> 30789 | AE56: =R56 -> 0 | ... AI56: =V56 -> 0
B57: Unearned Revenue, Current | C57: ='Historical Financials'!#REF! -> #REF! | H57: ='Historical Financials'!#REF! -> #REF! | I57: ='Historical Financials'!#REF! -> #REF! | J57: ='Historical Financials'!#REF! -> #REF! | K57: ='Historical Financials'!#REF! -> #REF! | L57: ='Historical Financials'!#REF! -> #REF! | M57: ='Historical Financials'!#REF! -> #REF! | N57: ='Historical Financials'!#REF! -> #REF! | O57: ='Historical Financials'!#REF! -> #REF! | ... Q57: ='Historical Financials'!#REF! -> #REF! | X57: =K57 -> #REF! | Y57: =L57 -> #REF! | Z57: =M57 -> #REF! | AA57: =N57 -> #REF! | AB57: =O57 -> #REF! | AC57: =P57 -> #REF! | AD57: =Q57 -> #REF! | AE57: =R57 -> 0 | ... AI57: =V57 -> 0
B58: Unearned Revenue, Non-Current | C58: ='Historical Financials'!#REF! -> #REF! | H58: ='Historical Financials'!#REF! -> #REF! | I58: ='Historical Financials'!#REF! -> #REF! | J58: ='Historical Financials'!#REF! -> #REF! | K58: ='Historical Financials'!#REF! -> #REF! | L58: ='Historical Financials'!#REF! -> #REF! | M58: ='Historical Financials'!#REF! -> #REF! | N58: ='Historical Financials'!#REF! -> #REF! | O58: ='Historical Financials'!#REF! -> #REF! | ... Q58: ='Historical Financials'!#REF! -> #REF! | X58: =K58 -> #REF! | Y58: =L58 -> #REF! | Z58: =M58 -> #REF! | AA58: =N58 -> #REF! | AB58: =O58 -> #REF! | AC58: =P58 -> #REF! | AD58: =Q58 -> #REF! | AE58: =R58 -> 0 | ... AI58: =V58 -> 0
B59: Property Plant, and Equiptment | C59: ='Historical Financials'!#REF! -> #REF! | H59: ='Historical Financials'!G58 -> 12969 | I59: ='Historical Financials'!H58 -> 12969 | J59: ='Historical Financials'!I58 -> 12969 | K59: ='Historical Financials'!J58 -> 12969 | L59: ='Historical Financials'!K58 -> 12969 | M59: ='Historical Financials'!L58 -> 12969 | N59: ='Historical Financials'!M58 -> 12969 | O59: ='Historical Financials'!N58 -> 12969 | ... Q59: ='Historical Financials'!P58 -> 12969 | X59: =K59 -> 12969 | Y59: =L59 -> 12969 | Z59: =M59 -> 12969 | AA59: =N59 -> 12969 | AB59: =O59 -> 12969 | AC59: =P59 -> 12969 | AD59: =Q59 -> 12969 | AE59: =R59 -> 0 | ... AI59: =V59 -> 0
B60: Current Liabilities | C60: ='Historical Financials'!#REF! -> #REF! | H60: ='Historical Financials'!G71 -> 141822 | I60: ='Historical Financials'!H71 -> 137141 | J60: ='Historical Financials'!I71 -> 150836 | K60: ='Historical Financials'!J71 -> 176663 | L60: ='Historical Financials'!K71 -> 142855 | M60: ='Historical Financials'!L71 -> 231299 | N60: ='Historical Financials'!M71 -> 241236 | O60: ='Historical Financials'!N71 -> 157888 | ... Q60: ='Historical Financials'!P71 -> 134601 | X60: =K60 -> 176663 | Y60: =L60 -> 142855 | Z60: =M60 -> 231299 | AA60: =N60 -> 241236 | AB60: =O60 -> 157888 | AC60: =P60 -> 155608 | AD60: =Q60 -> 134601 | AE60: =R60 -> 0 | ... AI60: =V60 -> 0
B61: Total Liabilities | C61: ='Historical Financials'!#REF! -> #REF! | H61: ='Historical Financials'!G79 -> 290458 | I61: ='Historical Financials'!H79 -> 289024 | J61: ='Historical Financials'!I79 -> 309450 | K61: ='Historical Financials'!J79 -> 345374 | L61: ='Historical Financials'!K79 -> 304564 | M61: ='Historical Financials'!L79 -> 289237 | N61: ='Historical Financials'!M79 -> 301136 | O61: ='Historical Financials'!N79 -> 298026 | ... Q61: ='Historical Financials'!P79 -> 316549 | X61: =K61 -> 345374 | Y61: =L61 -> 304564 | Z61: =M61 -> 289237 | AA61: =N61 -> 301136 | AB61: =O61 -> 298026 | AC61: =P61 -> 314340 | AD61: =Q61 -> 316549 | AE61: =R61 -> 0 | ... AI61: =V61 -> 0
B63: Consolidated Debt | C63: 0 | H63: 0 | I63: 0 | J63: 0 | K63: =D63 -> 0 | L63: 0 | M63: 0 | N63: 0 | O63: =E63 -> 0 | P63: 0 | Q63: 0 | X63: =K63 -> 0 | Y63: =L63 -> 0 | Z63: =M63 -> 0 | AA63: =N63 -> 0 | AB63: =O63 -> 0 | AC63: =P63 -> 0 | AD63: =Q63 -> 0 | AE63: =R63 -> 0 | ... AI63: =V63 -> 0
B64: Total Debt | C64: =SUM(C63:C63) -> 0 | D64: =SUM(D63:D63) -> 0 | E64: =SUM(E63:E63) -> 0 | F64: =SUM(F63:F63) -> 0 | H64: =SUM(H63:H63) -> 0 | I64: =SUM(I63:I63) -> 0 | J64: =SUM(J63:J63) -> 0 | K64: =SUM(K63:K63) -> 0 | L64: =SUM(L63:L63) -> 0 | M64: =SUM(M63:M63) -> 0 | N64: =SUM(N63:N63) -> 0 | O64: =SUM(O63:O63) -> 0 | ... V64: =SUM(V63:V63) -> 0 | X64: =SUM(X63:X63) -> 0 | Y64: =SUM(Y63:Y63) -> 0 | Z64: =SUM(Z63:Z63) -> 0 | AA64: =SUM(AA63:AA63) -> 0 | AB64: =SUM(AB63:AB63) -> 0 | AC64: =SUM(AC63:AC63) -> 0 | AD64: =SUM(AD63:AD63) -> 0 | AE64: =SUM(AE63:AE63) -> 0 | ... AI64: =SUM(AI63:AI63) -> 0
B66: Total Shareholder Equity | C66: ='Historical Financials'!#REF! -> #REF! | H66: ='Historical Financials'!G86 -> -68787 | I66: ='Historical Financials'!H86 -> -79342 | J66: ='Historical Financials'!I86 -> -77053 | K66: ='Historical Financials'!J86 -> -143739 | L66: ='Historical Financials'!K86 -> -94080 | M66: ='Historical Financials'!L86 -> -94433 | N66: ='Historical Financials'!M86 -> -101931 | O66: ='Historical Financials'!N86 -> -84369 | ... Q66: ='Historical Financials'!P86 -> -153403 | X66: =K66 -> -143739 | Y66: =L66 -> -94080 | Z66: =M66 -> -94433 | AA66: =N66 -> -101931 | AB66: =O66 -> -84369 | AC66: =P66 -> -141251 | AD66: =Q66 -> -153403 | AE66: =R66 -> 0 | ... AI66: =V66 -> 0
B67: Total Book Capitalization | C67: =SUM(C64:C66) -> #REF! | D67: =SUM(D64:D66) -> 0 | E67: =SUM(E64:E66) -> 0 | F67: =SUM(F64:F66) -> 0 | H67: =SUM(H64:H66) -> -68787 | I67: =SUM(I64:I66) -> -79342 | J67: =SUM(J64:J66) -> -77053 | K67: =SUM(K64:K66) -> -143739 | L67: =SUM(L64:L66) -> -94080 | M67: =SUM(M64:M66) -> -94433 | N67: =SUM(N64:N66) -> -101931 | O67: =SUM(O64:O66) -> -84369 | ... V67: =SUM(V64:V66) -> 0 | X67: =SUM(X64:X66) -> -143739 | Y67: =SUM(Y64:Y66) -> -94080 | Z67: =SUM(Z64:Z66) -> -94433 | AA67: =SUM(AA64:AA66) -> -101931 | AB67: =SUM(AB64:AB66) -> -84369 | AC67: =SUM(AC64:AC66) -> -141251 | AD67: =SUM(AD64:AD66) -> -153403 | AE67: =SUM(AE64:AE66) -> 0 | ... AI67: =SUM(AI64:AI66) -> 0
B69: Credit Metrics
B71: Total Leverage | C71: NM | L71: NM | M71: NM | N71: NM | O71: NM | P71: NM | Q71: NM | X71: NM | Y71: NM | Z71: NM | AA71: NM | AB71: NM | AC71: NM | AD71: NM
B72: Net Leverage (C&CE) | C72: NM | L72: NM | M72: NM | N72: NM | O72: NM | P72: NM | Q72: NM | X72: NM | Y72: NM | Z72: NM | AA72: NM | AB72: NM | AC72: NM | AD72: NM
B73: Interest Coverage | C73: NM | L73: NM | M73: NM | N73: NM | O73: NM | P73: NM | Q73: NM | X73: NM | Y73: NM | Z73: NM | AA73: NM | AB73: NM | AC73: NM | AD73: NM
B74: Debt Service Coverage | C74: NM | L74: NM | M74: NM | N74: NM | O74: NM | P74: NM | Q74: NM | X74: NM | Y74: NM | Z74: NM | AA74: NM | AB74: NM | AC74: NM | AD74: NM
B75: Fixed Charge Coverage | C75: NM | L75: NM | M75: NM | N75: NM | O75: NM | P75: NM | Q75: NM | X75: NM | Y75: NM | Z75: NM | AA75: NM | AB75: NM | AC75: NM | AD75: NM
B76: Debt-to-Book Capitalization | C76: NM | L76: NM | M76: NM | N76: NM | O76: NM | P76: NM | Q76: NM | X76: NM | Y76: NM | Z76: NM | AA76: NM | AB76: NM | AC76: NM | AD76: NM
