Workbook

Sheet Historical Financials
B2: Spirit Airlines, Inc. (NASDAQ: FLYYQ)
B3: Historical Financials
B4: $ in thousands except per share
A6: X | B6: Income Statement | F6: FYE | J6: Quarterly | P6: Quarterly | W6: LTM | X6: LTM | AD6: Variance
B7: Fiscal Period | C7: 2019 | D7: 2020 | E7: 2021 | F7: 2022 | G7: 2023 | H7: 2024 | J7: 1Q23 | K7: 2Q23 | L7: 3Q23 | M7: 4Q23 | N7: 1Q24 | O7: 2Q24 | P7: 3Q24 | Q7: 4Q24 | R7: 1Q25 | S7: 2Q25 | T7: 3Q25 | V7: =N7 -> 1Q24 | W7: =O7 -> 2Q24 | X7: =P7 -> 3Q24 | Y7: =Q7 -> 4Q24 | Z7: =R7 -> 1Q25 | AA7: =S7 -> 2Q25 | AB7: =T7 -> 3Q25
B8: Fiscal Period End Date | C8: 43830 | D8: 44196 | E8: 44561 | F8: 44926 | G8: 45291 | H8: 45657 | J8: 45016 | K8: 45107 | L8: 45199 | M8: =G8 -> 45291 | N8: 45382 | O8: 45473 | P8: 45565 | Q8: =H8 -> 45657 | R8: 45747 | S8: 45838 | T8: 45930 | V8: =N8 -> 45382 | W8: =O8 -> 45473 | X8: =P8 -> 45565 | Y8: =Q8 -> 45657 | Z8: =R8 -> 45747 | AA8: =S8 -> 45838 | AB8: =T8 -> 45930
B10: Consolidated Revenue | C10: 3830536 | D10: 1810022 | E10: 3230775 | F10: 5068447 | G10: 5362549 | H10: 4913421 | J10: 1349774 | K10: 1432472 | L10: 1258543 | M10: =SUM(G10-SUM(J10:L10)) -> 1321760 | N10: 1265537 | O10: 1280889 | P10: 1197104 | Q10: =SUM(H10-SUM(N10:P10)) -> 1169891 | R10: =755354+257045 -> 1012399 | S10: 1019833 | T10: 958524 | V10: =SUM(K10:N10) -> 5278312 | W10: =SUM(L10:O10) -> 5126729 | X10: =SUM(M10:P10) -> 5065290 | Y10: =SUM(N10:Q10) -> 4913421 | Z10: =SUM(O10:R10) -> 4660283 | AA10: =SUM(P10:S10) -> 4399227 | AB10: =SUM(Q10:T10) -> 4160647 | AD10: =SUM(AB10/X10)-1 -> -0.17859649
B11: Total Revenue | C11: =+SUM(C10:C10) -> 3830536 | D11: =+SUM(D10:D10) -> 1810022 | E11: =+SUM(E10:E10) -> 3230775 | F11: =+SUM(F10:F10) -> 5068447 | G11: =+SUM(G10:G10) -> 5362549 | H11: =+SUM(H10:H10) -> 4913421 | J11: =+SUM(J10:J10) -> 1349774 | K11: =+SUM(K10:K10) -> 1432472 | L11: =+SUM(L10:L10) -> 1258543 | M11: =+SUM(M10:M10) -> 1321760 | N11: =+SUM(N10:N10) -> 1265537 | O11: =+SUM(O10:O10) -> 1280889 | P11: =+SUM(P10:P10) -> 1197104 | Q11: =+SUM(Q10:Q10) -> 1169891 | ... T11: =+SUM(T10:T10) -> 958524 | V11: =+SUM(V10:V10) -> 5278312 | W11: =+SUM(W10:W10) -> 5126729 | X11: =+SUM(X10:X10) -> 5065290 | Y11: =+SUM(Y10:Y10) -> 4913421 | Z11: =+SUM(Z10:Z10) -> 4660283 | AA11: =+SUM(AA10:AA10) -> 4399227 | AB11: =+SUM(AB10:AB10) -> 4160647 | AD11: =SUM(AB11/X11)-1 -> -0.17859649
B13: Salaries, wages and benefits | C13: -865019 | D13: -909834 | E13: -1065461 | F13: -1251225 | G13: -1616803 | H13: -1689083 | J13: -389185 | K13: -407705 | L13: -404177 | M13: =SUM(G13-SUM(J13:L13)) -> -415736 | N13: -431483 | O13: -418378 | P13: -427125 | Q13: =SUM(H13-SUM(N13:P13)) -> -412097 | R13: =-76212-308585 -> -384797 | S13: -367361 | T13: -367356 | V13: =SUM(K13:N13) -> -1659101 | W13: =SUM(L13:O13) -> -1669774 | X13: =SUM(M13:P13) -> -1692722 | Y13: =SUM(N13:Q13) -> -1689083 | Z13: =SUM(O13:R13) -> -1642397 | AA13: =SUM(P13:S13) -> -1591380 | AB13: =SUM(Q13:T13) -> -1531611 | AD13: =SUM(AB13/X13)-1 -> -0.095178653
B14: Aircraft fuel | C14: -993478 | D14: -431000 | E14: -913945 | F14: -1929969 | G14: -1821165 | H14: -1479203 | J14: -487711 | K14: -391032 | L14: -455241 | M14: =SUM(G14-SUM(J14:L14)) -> -487181 | N14: -406351 | O14: -407296 | P14: -373399 | Q14: =SUM(H14-SUM(N14:P14)) -> -292157 | R14: =-60797-219922 -> -280719 | S14: -260486 | T14: -253308 | V14: =SUM(K14:N14) -> -1739805 | W14: =SUM(L14:O14) -> -1756069 | X14: =SUM(M14:P14) -> -1674227 | Y14: =SUM(N14:Q14) -> -1479203 | Z14: =SUM(O14:R14) -> -1353571 | AA14: =SUM(P14:S14) -> -1206761 | AB14: =SUM(Q14:T14) -> -1086670 | AD14: =SUM(AB14/X14)-1 -> -0.35094226
B15: Aircraft rent | C15: -182609 | D15: -196359 | E15: -246601 | F15: -282428 | G15: -381239 | H15: -541909 | J15: -85267 | K15: -92101 | L15: -97393 | M15: =SUM(G15-SUM(J15:L15)) -> -106478 | N15: -115206 | O15: -125339 | P15: -148511 | Q15: =SUM(H15-SUM(N15:P15)) -> -152853 | R15: =-30884-120183 -> -151067 | S15: -140693 | T15: -154064 | V15: =SUM(K15:N15) -> -411178 | W15: =SUM(L15:O15) -> -444416 | X15: =SUM(M15:P15) -> -495534 | Y15: =SUM(N15:Q15) -> -541909 | Z15: =SUM(O15:R15) -> -577770 | AA15: =SUM(P15:S15) -> -593124 | AB15: =SUM(Q15:T15) -> -598677 | AD15: =SUM(AB15/X15)-1 -> 0.20814515
B16: Landing fees and other rents | C16: -256275 | D16: -251028 | E16: -315999 | F16: -347268 | G16: -408262 | H16: -451008 | J16: -97345 | K16: -106487 | L16: -107525 | M16: =SUM(G16-SUM(J16:L16)) -> -96905 | N16: -106718 | O16: -116064 | P16: -130044 | Q16: =SUM(H16-SUM(N16:P16)) -> -98182 | R16: =-20944-87001 -> -107945 | S16: -101457 | T16: -104900 | V16: =SUM(K16:N16) -> -417635 | W16: =SUM(L16:O16) -> -427212 | X16: =SUM(M16:P16) -> -449731 | Y16: =SUM(N16:Q16) -> -451008 | Z16: =SUM(O16:R16) -> -452235 | AA16: =SUM(P16:S16) -> -437628 | AB16: =SUM(Q16:T16) -> -412484 | AD16: =SUM(AB16/X16)-1 -> -0.082820619
B17: Depreciation and amortization | C17: -225264 | D17: -278588 | E17: -297211 | F17: -313090 | G17: -320872 | H17: -325273 | J17: -77991 | K17: -80542 | L17: -82802 | M17: =SUM(G17-SUM(J17:L17)) -> -79537 | N17: -81346 | O17: -84486 | P17: -84028 | Q17: =SUM(H17-SUM(N17:P17)) -> -75413 | R17: =-11597-54853 -> -66450 | S17: -62886 | T17: -58032 | V17: =SUM(K17:N17) -> -324227 | W17: =SUM(L17:O17) -> -328171 | X17: =SUM(M17:P17) -> -329397 | Y17: =SUM(N17:Q17) -> -325273 | Z17: =SUM(O17:R17) -> -310377 | AA17: =SUM(P17:S17) -> -288777 | AB17: =SUM(Q17:T17) -> -262781 | AD17: =SUM(AB17/X17)-1 -> -0.20223621
B18: Maintenance, materials and repairs | C18: -143575 | D18: -111227 | E18: -159502 | F18: -187820 | G18: -223339 | H18: -217738 | J18: -54414 | K18: -56825 | L18: -56465 | M18: =SUM(G18-SUM(J18:L18)) -> -55635 | N18: -54915 | O18: -52453 | P18: -57368 | Q18: =SUM(H18-SUM(N18:P18)) -> -53002 | R18: =-11209-47498 -> -58707 | S18: -48747 | T18: -54849 | V18: =SUM(K18:N18) -> -223840 | W18: =SUM(L18:O18) -> -219468 | X18: =SUM(M18:P18) -> -220371 | Y18: =SUM(N18:Q18) -> -217738 | Z18: =SUM(O18:R18) -> -221530 | AA18: =SUM(P18:S18) -> -217824 | AB18: =SUM(Q18:T18) -> -215305 | AD18: =SUM(AB18/X18)-1 -> -0.022988506
B19: Distribution | C19: -153770 | D19: -85059 | E19: -132499 | F19: -177557 | G19: -190891 | H19: -197197 | J19: -48017 | K19: -50701 | L19: -46323 | M19: =SUM(G19-SUM(J19:L19)) -> -45850 | N19: -45176 | O19: -45923 | P19: -55687 | Q19: =SUM(H19-SUM(N19:P19)) -> -50411 | R19: =-10432-39461 -> -49893 | S19: -47139 | T19: -45833 | V19: =SUM(K19:N19) -> -188050 | W19: =SUM(L19:O19) -> -183272 | X19: =SUM(M19:P19) -> -192636 | Y19: =SUM(N19:Q19) -> -197197 | Z19: =SUM(O19:R19) -> -201914 | AA19: =SUM(P19:S19) -> -203130 | AB19: =SUM(Q19:T19) -> -193276 | AD19: =SUM(AB19/X19)-1 -> 0.0033223281
B20: Special Credits (Charges) | C20: -717 | D20: 302761 | E20: 377715 | F20: -420172 | G20: -69537 | H20: -36029 | J20: -13983 | K20: -19972 | L20: -12378 | M20: =SUM(G20-SUM(J20:L20)) -> -23204 | N20: -36258 | O20: 381 | P20: -151 | Q20: =SUM(H20-SUM(N20:P20)) -> -1 | R20: 4 | S20: 0 | T20: 0 | V20: =SUM(K20:N20) -> -91812 | W20: =SUM(L20:O20) -> -71459 | X20: =SUM(M20:P20) -> -59232 | Y20: =SUM(N20:Q20) -> -36029 | Z20: =SUM(O20:R20) -> 233 | AA20: =SUM(P20:S20) -> -148 | AB20: =SUM(Q20:T20) -> 3 | AD20: =SUM(AB20/X20)-1 -> -1.0000506
B21: Gains (Losses) on disposal of assets | C21: -17350 | D21: -2264 | E21: -3320 | F21: -46624 | G21: -33966 | H21: -273871 | J21: -7100 | K21: -802 | L21: 2250 | M21: =SUM(G21-SUM(J21:L21)) -> -28314 | N21: 3029 | O21: 14047 | P21: -3191 | Q21: =SUM(H21-SUM(N21:P21)) -> -287756 | R21: =-11655+19 -> -11636 | S21: 309 | T21: 113713 | V21: =SUM(K21:N21) -> -23837 | W21: =SUM(L21:O21) -> -8988 | X21: =SUM(M21:P21) -> -14429 | Y21: =SUM(N21:Q21) -> -273871 | Z21: =SUM(O21:R21) -> -288536 | AA21: =SUM(P21:S21) -> -302274 | AB21: =SUM(Q21:T21) -> -185370 | AD21: =SUM(AB21/X21)-1 -> 11.847044
B22: Other Operating Expenses | C22: -491432 | D22: -355186 | E22: -530826 | F22: -711211 | G22: -792232 | H22: -807488 | J22: -201156 | K22: -206094 | L22: -187249 | M22: =SUM(G22-SUM(J22:L22)) -> -197733 | N22: -198450 | O22: -197890 | P22: -214039 | Q22: =SUM(H22-SUM(N22:P22)) -> -197109 | R22: =-153395-36950 -> -190345 | S22: -175496 | T22: -168810 | V22: =SUM(K22:N22) -> -789526 | W22: =SUM(L22:O22) -> -781322 | X22: =SUM(M22:P22) -> -808112 | Y22: =SUM(N22:Q22) -> -807488 | Z22: =SUM(O22:R22) -> -799383 | AA22: =SUM(P22:S22) -> -776989 | AB22: =SUM(Q22:T22) -> -731760 | AD22: =SUM(AB22/X22)-1 -> -0.094481953
B23: Operating Profit | C23: =SUM(C11+SUM(C13:C22)) -> 501047 | D23: =SUM(D11+SUM(D13:D22)) -> -507762 | E23: =SUM(E11+SUM(E13:E22)) -> -56874 | F23: =SUM(F11+SUM(F13:F22)) -> -598917 | G23: =SUM(G11+SUM(G13:G22)) -> -495757 | H23: =SUM(H11+SUM(H13:H22)) -> -1105378 | J23: =SUM(J11+SUM(J13:J22)) -> -112395 | K23: =SUM(K11+SUM(K13:K22)) -> 20211 | L23: =SUM(L11+SUM(L13:L22)) -> -188760 | M23: =SUM(M11+SUM(M13:M22)) -> -214813 | N23: =SUM(N11+SUM(N13:N22)) -> -207337 | O23: =SUM(O11+SUM(O13:O22)) -> -152512 | P23: =SUM(P11+SUM(P13:P22)) -> -296439 | Q23: =SUM(Q11+SUM(Q13:Q22)) -> -449090 | ... T23: =SUM(T11+SUM(T13:T22)) -> -134915 | V23: {=SUM(V11+V14:V22)} -> 43294898 | W23: {=SUM(W11+W14:W22)} -> 41920184 | X23: =SUM(X11+SUM(X13:X22)) -> -871101 | Y23: =SUM(Y11+SUM(Y13:Y22)) -> -1105378 | Z23: =SUM(Z11+SUM(Z13:Z22)) -> -1187197 | AA23: =SUM(AA11+SUM(AA13:AA22)) -> -1218808 | AB23: =SUM(AB11+SUM(AB13:AB22)) -> -1057284 | AD23: =SUM(AB23/X23)-1 -> 0.21373297
B24: Operating Margin (%) | C24: =C23/C11 -> 0.13080337 | D24: =D23/D11 -> -0.28052808 | E24: =E23/E11 -> -0.017603826 | F24: =F23/F11 -> -0.11816578 | G24: =G23/G11 -> -0.092448013 | H24: =H23/H11 -> -0.22497116 | J24: =J23/J11 -> -0.083269495 | K24: =K23/K11 -> 0.014109176 | L24: =L23/L11 -> -0.14998296 | M24: =M23/M11 -> -0.16252043 | N24: =N23/N11 -> -0.16383322 | O24: =O23/O11 -> -0.1190673 | P24: =P23/P11 -> -0.24763011 | Q24: =Q23/Q11 -> -0.38387337 | ... T24: =T23/T11 -> -0.14075287 | V24: =V23/V11 -> 8.2024136 | W24: =W23/W11 -> 8.1767895 | X24: =X23/X11 -> -0.17197456 | Y24: =Y23/Y11 -> -0.22497116 | Z24: =Z23/Z11 -> -0.25474783 | AA24: =AA23/AA11 -> -0.27705049 | AB24: =AB23/AB11 -> -0.25411529 | AD24: =SUM(AB24-X24)*1000 -> -82.140729
B26: Interest Expense | C26: -101350 | D26: -134520 | E26: -155611 | F26: -139905 | G26: -169191 | H26: -219094 | J26: -51793 | K26: -28880 | L26: -41260 | M26: =SUM(G26-SUM(J26:L26)) -> -47258 | N26: -54809 | O26: -54307 | P26: -54135 | Q26: =SUM(H26-SUM(N26:P26)) -> -55843 | R26: =-47682-9777 -> -57459 | S26: -62103 | T26: -46261 | V26: =SUM(K26:N26) -> -172207 | W26: =SUM(L26:O26) -> -197634 | X26: =SUM(M26:P26) -> -210509 | Y26: =SUM(N26:Q26) -> -219094 | Z26: =SUM(O26:R26) -> -221744 | AA26: =SUM(P26:S26) -> -229540 | AB26: =SUM(Q26:T26) -> -221666 | AD26: =SUM(AB26/X26)-1 -> 0.053000109
B27: Interest Income | C27: 25133 | D27: 6314 | E27: 5374 | F27: 20083 | G27: 61647 | H27: 48324 | J27: 15434 | K27: 15962 | L27: 18442 | M27: =SUM(G27-SUM(J27:L27)) -> 11809 | N27: 13590 | O27: 12169 | P27: 11341 | Q27: =SUM(H27-SUM(N27:P27)) -> 11224 | R27: =8873+2003 -> 10876 | S27: 7142 | T27: 7001 | V27: =SUM(K27:N27) -> 59803 | W27: =SUM(L27:O27) -> 56010 | X27: =SUM(M27:P27) -> 48909 | Y27: =SUM(N27:Q27) -> 48324 | Z27: =SUM(O27:R27) -> 45610 | AA27: =SUM(P27:S27) -> 40583 | AB27: =SUM(Q27:T27) -> 36243 | AD27: =SUM(AB27/X27)-1 -> -0.25897074
B28: Capitalized Interest | C28: 12471 | D28: 15995 | E28: 18998 | F28: 22818 | G28: 33360 | H28: 18087 | J28: 7648 | K28: 8445 | L28: 8582 | M28: =SUM(G28-SUM(J28:L28)) -> 8685 | N28: 10003 | O28: 5689 | P28: 1173 | Q28: =SUM(H28-SUM(N28:P28)) -> 1222 | R28: =956+118 -> 1074 | S28: 557 | T28: 393 | V28: =SUM(K28:N28) -> 35715 | W28: =SUM(L28:O28) -> 32959 | X28: =SUM(M28:P28) -> 25550 | Y28: =SUM(N28:Q28) -> 18087 | Z28: =SUM(O28:R28) -> 9158 | AA28: =SUM(P28:S28) -> 4026 | AB28: =SUM(Q28:T28) -> 3246 | AD28: =SUM(AB28/X28)-1 -> -0.87295499
B29: Other Income / (Expenses) | C29: -875 | D29: -211 | E29: =-577-331630 -> -332207 | F29: -4818 | G29: =-4065+15411 -> 11346 | H29: =65694+14937 -> 80631 | J29: -542 | K29: -766 | L29: -649 | M29: =SUM(G29-SUM(J29:L29)) -> 13303 | N29: =14996+66490 -> 81486 | O29: -665 | P29: 23 | Q29: =SUM(H29-SUM(N29:P29)) -> -213 | R29: =87-902-50 -> -865 | S29: -262 | T29: =-2728-337 -> -3065 | V29: =SUM(K29:N29) -> 93374 | W29: =SUM(L29:O29) -> 93475 | X29: =SUM(M29:P29) -> 94147 | Y29: =SUM(N29:Q29) -> 80631 | Z29: =SUM(O29:R29) -> -1720 | AA29: =SUM(P29:S29) -> -1317 | AB29: =SUM(Q29:T29) -> -4405 | AD29: =SUM(AB29/X29)-1 -> -1.0467885
B30: Restructuring & Other Special Charges | C30: 0 | D30: 0 | E30: 0 | F30: 0 | G30: 0 | H30: =-15493-96780 -> -112273 | J30: 0 | K30: 0 | L30: 0 | M30: =SUM(G30-SUM(J30:L30)) -> 0 | N30: 0 | O30: 0 | P30: 0 | Q30: =SUM(H30-SUM(N30:P30)) -> -112273 | R30: =-5511-1376+421464 -> 414577 | S30: -11039 | T30: =-13026-125983 -> -139009 | V30: =SUM(K30:N30) -> 0 | W30: =SUM(L30:O30) -> 0 | X30: =SUM(M30:P30) -> 0 | Y30: =SUM(N30:Q30) -> -112273 | Z30: =SUM(O30:R30) -> 302304 | AA30: =SUM(P30:S30) -> 291265 | AB30: =SUM(Q30:T30) -> 152256 | AD30: =SUM(AB30/X30)-1 -> #DIV/0!
B31: Earning Before Taxes | C31: =SUM(C23+SUM(C26:C30)) -> 436426 | D31: =SUM(D23+SUM(D26:D30)) -> -620184 | E31: =SUM(E23+SUM(E26:E30)) -> -520320 | F31: =SUM(F23+SUM(F26:F30)) -> -700739 | G31: =SUM(G23+SUM(G26:G30)) -> -558595 | H31: =SUM(H23+SUM(H26:H30)) -> -1289703 | J31: =SUM(J23+SUM(J26:J30)) -> -141648 | K31: =SUM(K23+SUM(K26:K30)) -> 14972 | L31: =SUM(L23+SUM(L26:L30)) -> -203645 | M31: =SUM(M23+SUM(M26:M30)) -> -228274 | N31: =SUM(N23+SUM(N26:N30)) -> -157067 | O31: =SUM(O23+SUM(O26:O30)) -> -189626 | P31: =SUM(P23+SUM(P26:P30)) -> -338037 | Q31: =SUM(Q23+SUM(Q26:Q30)) -> -604973 | ... T31: =SUM(T23+SUM(T26:T30)) -> -315856 | V31: =SUM(V23+SUM(V26:V30)) -> 43311583 | W31: =SUM(W23+SUM(W26:W30)) -> 41904994 | X31: =SUM(X23+SUM(X26:X30)) -> -913004 | Y31: =SUM(Y23+SUM(Y26:Y30)) -> -1289703 | Z31: =SUM(Z23+SUM(Z26:Z30)) -> -1053589 | AA31: =SUM(AA23+SUM(AA26:AA30)) -> -1113791 | AB31: =SUM(AB23+SUM(AB26:AB30)) -> -1091610 | AD31: =SUM(AB31/X31)-1 -> 0.19562455
B32: EBT Margin (%) | C32: =C31/C11 -> 0.1139334 | D32: =D31/D11 -> -0.34263893 | E32: =E31/E11 -> -0.16105114 | F32: =F31/F11 -> -0.13825517 | G32: =G31/G11 -> -0.10416595 | H32: =H31/H11 -> -0.26248575 | J32: =J31/J11 -> -0.10494201 | K32: =K31/K11 -> 0.010451862 | L32: =L31/L11 -> -0.16181012 | M32: =M31/M11 -> -0.17270458 | N32: =N31/N11 -> -0.12411095 | O32: =O31/O11 -> -0.14804249 | P32: =P31/P11 -> -0.28237897 | Q32: =Q31/Q11 -> -0.51711912 | ... T32: =T31/T11 -> -0.32952331 | V32: =V31/V11 -> 8.2055746 | W32: =W31/W11 -> 8.1738266 | X32: =X31/X11 -> -0.18024713 | Y32: =Y31/Y11 -> -0.26248575 | Z32: =Z31/Z11 -> -0.22607833 | AA32: =AA31/AA11 -> -0.2531788 | AB32: =AB31/AB11 -> -0.26236544 | AD32: =SUM(AB32-X32)*1000 -> -82.118312
B34: Benefit (Provision) for Income Taxes | C34: -101171 | D34: 191484 | E34: 47751 | F34: 146589 | G34: 111131 | H34: 60208 | J34: 37737 | K34: -17321 | L34: 46093 | M34: =SUM(G34-SUM(J34:L34)) -> 44622 | N34: 14432 | O34: -3301 | P34: 29794 | Q34: =SUM(H34-SUM(N34:P34)) -> 19283 | R34: =-17870+103 -> -17767 | S34: 3997 | T34: -1620 | V34: =SUM(K34:N34) -> 87826 | W34: =SUM(L34:O34) -> 101846 | X34: =SUM(M34:P34) -> 85547 | Y34: =SUM(N34:Q34) -> 60208 | Z34: =SUM(O34:R34) -> 28009 | AA34: =SUM(P34:S34) -> 35307 | AB34: =SUM(Q34:T34) -> 3893 | AD34: =SUM(AB34/X34)-1 -> -0.95449285
B35: Net loss | C35: =SUM(C31+SUM(C34:C34)) -> 335255 | D35: =SUM(D31+SUM(D34:D34)) -> -428700 | E35: =SUM(E31+SUM(E34:E34)) -> -472569 | F35: =SUM(F31+SUM(F34:F34)) -> -554150 | G35: =SUM(G31+SUM(G34:G34)) -> -447464 | H35: =SUM(H31+SUM(H34:H34)) -> -1229495 | J35: =SUM(J31+SUM(J34:J34)) -> -103911 | K35: =SUM(K31+SUM(K34:K34)) -> -2349 | L35: =SUM(L31+SUM(L34:L34)) -> -157552 | M35: =SUM(M31+SUM(M34:M34)) -> -183652 | N35: =SUM(N31+SUM(N34:N34)) -> -142635 | O35: =SUM(O31+SUM(O34:O34)) -> -192927 | P35: =SUM(P31+SUM(P34:P34)) -> -308243 | Q35: =SUM(Q31+SUM(Q34:Q34)) -> -585690 | ... T35: =SUM(T31+SUM(T34:T34)) -> -317476 | V35: =SUM(V31+SUM(V34:V34)) -> 43399409 | W35: =SUM(W31+SUM(W34:W34)) -> 42006840 | X35: =SUM(X31+SUM(X34:X34)) -> -827457 | Y35: =SUM(Y31+SUM(Y34:Y34)) -> -1229495 | Z35: =SUM(Z31+SUM(Z34:Z34)) -> -1025580 | AA35: =SUM(AA31+SUM(AA34:AA34)) -> -1078484 | AB35: =SUM(AB31+SUM(AB34:AB34)) -> -1087717 | AD35: =SUM(AB35/X35)-1 -> 0.31452994
B36: Net Margin (%) | C36: =C35/C11 -> 0.087521694 | D36: =D35/D11 -> -0.23684795 | E36: =E35/E11 -> -0.1462711 | F36: =F35/F11 -> -0.10933329 | G36: =G35/G11 -> -0.083442408 | H36: =H35/H11 -> -0.25023197 | J36: =J35/J11 -> -0.076983999 | K36: =K35/K11 -> -0.0016398226 | L36: =L35/L11 -> -0.12518603 | M36: =M35/M11 -> -0.13894504 | N36: =N35/N11 -> -0.1127071 | O36: =O35/O11 -> -0.15061961 | P36: =P35/P11 -> -0.25749058 | Q36: =Q35/Q11 -> -0.50063638 | ... T36: =T35/T11 -> -0.33121341 | V36: =V35/V11 -> 8.2222137 | W36: =W35/W11 -> 8.1936923 | X36: =X35/X11 -> -0.16335827 | Y36: =Y35/Y11 -> -0.25023197 | Z36: =Z35/Z11 -> -0.22006818 | AA36: =AA35/AA11 -> -0.24515307 | AB36: =AB35/AB11 -> -0.26142977 | AD36: =SUM(AB36-X36)*1000 -> -98.071505
B38: Basic Shares | C38: 84692 | D38: 84692 | E38: 105000 | F38: 108751 | G38: 109152 | H38: 109495 | J38: 109110 | K38: 109161 | L38: 109164 | M38: =G38 -> 109152 | N38: 109430 | O38: 109506 | P38: 109521 | Q38: =H38 -> 109495 | R38: =19685+109525 -> 129210 | S38: 33972 | T38: 40322 | V38: =N38 -> 109430 | W38: =O38 -> 109506 | X38: =P38 -> 109521 | Y38: =Q38 -> 109495 | Z38: =R38 -> 129210 | AA38: =S38 -> 33972 | AB38: =T38 -> 40322 | AD38: =SUM(AB38/X38)-1 -> -0.63183316
B39: Basic EPS | C39: =C35/C38 -> 3.9585203 | D39: =D35/D38 -> -5.0618713 | E39: =E35/E38 -> -4.5006571 | F39: =F35/F38 -> -5.0955853 | G39: =G35/G38 -> -4.0994576 | H39: =H35/H38 -> -11.228778 | J39: =J35/J38 -> -0.95235084 | K39: =K35/K38 -> -0.021518674 | L39: =L35/L38 -> -1.4432597 | M39: =M35/M38 -> -1.6825344 | N39: =N35/N38 -> -1.303436 | O39: =O35/O38 -> -1.7617939 | P39: =P35/P38 -> -2.8144648 | Q39: =Q35/Q38 -> -5.3490114 | ... T39: =T35/T38 -> -7.8735182 | V39: =V35/V38 -> 396.59517 | W39: =W35/W38 -> 383.60309 | X39: =X35/X38 -> -7.555236 | Y39: =Y35/Y38 -> -11.228778 | Z39: =Z35/Z38 -> -7.9373114 | AA39: =AA35/AA38 -> -31.746262 | AB39: =AB35/AB38 -> -26.97577 | AD39: =SUM(AB39/X39)-1 -> 2.5704735
B41: Fully Diluted Shares | C41: 68559 | D41: 84692 | E41: 105000 | F41: 108751 | G41: 109152 | H41: 109495 | J41: 109110 | K41: 109161 | L41: 109164 | M41: =G41 -> 109152 | N41: 109430 | O41: 109506 | P41: 109521 | Q41: =H41 -> 109495 | R41: =19685+109525 -> 129210 | S41: 33972 | T41: 40322 | V41: =N41 -> 109430 | W41: =O41 -> 109506 | X41: =P41 -> 109521 | Y41: =Q41 -> 109495 | Z41: =R41 -> 129210 | AA41: =S41 -> 33972 | AB41: =T41 -> 40322 | AD41: =SUM(AB41/X41)-1 -> -0.63183316
B42: Fully Diluted EPS | C42: =C35/C41 -> 4.8900217 | D42: =D35/D41 -> -5.0618713 | E42: =E35/E41 -> -4.5006571 | F42: =F35/F41 -> -5.0955853 | G42: =G35/G41 -> -4.0994576 | H42: =H35/H41 -> -11.228778 | J42: =J35/J41 -> -0.95235084 | K42: =K35/K41 -> -0.021518674 | L42: =L35/L41 -> -1.4432597 | M42: =M35/M41 -> -1.6825344 | N42: =N35/N41 -> -1.303436 | O42: =O35/O41 -> -1.7617939 | P42: =P35/P41 -> -2.8144648 | Q42: =Q35/Q41 -> -5.3490114 | ... T42: =T35/T41 -> -7.8735182 | V42: =V35/V41 -> 396.59517 | W42: =W35/W41 -> 383.60309 | X42: =X35/X41 -> -7.555236 | Y42: =Y35/Y41 -> -11.228778 | Z42: =Z35/Z41 -> -7.9373114 | AA42: =AA35/AA41 -> -31.746262 | AB42: =AB35/AB41 -> -26.97577 | AD42: =SUM(AB42/X42)-1 -> 2.5704735
A44: X | B44: Balance Sheet | W44: LTM | AD44: Variance
B45: =B7 -> Fiscal Period | C45: =C7 -> 2019 | D45: =D7 -> 2020 | E45: =E7 -> 2021 | F45: =F7 -> 2022 | G45: =G7 -> 2023 | H45: =H7 -> 2024 | J45: =J7 -> 1Q23 | K45: =K7 -> 2Q23 | L45: =L7 -> 3Q23 | M45: =M7 -> 4Q23 | N45: =N7 -> 1Q24 | O45: =O7 -> 2Q24 | P45: =P7 -> 3Q24 | Q45: =Q7 -> 4Q24 | ... T45: =T7 -> 3Q25 | V45: =V7 -> 1Q24 | W45: =W7 -> 2Q24 | X45: =X7 -> 3Q24 | Y45: =Y7 -> 4Q24 | Z45: =Z7 -> 1Q25 | AA45: =AA7 -> 2Q25 | AB45: =AB7 -> 3Q25
B46: =B8 -> Fiscal Period End Date | C46: =C8 -> 43830 | D46: =D8 -> 44196 | E46: =E8 -> 44561 | F46: =F8 -> 44926 | G46: =G8 -> 45291 | H46: =H8 -> 45657 | J46: =J8 -> 45016 | K46: =K8 -> 45107 | L46: =L8 -> 45199 | M46: =M8 -> 45291 | N46: =N8 -> 45382 | O46: =O8 -> 45473 | P46: =P8 -> 45565 | Q46: =Q8 -> 45657 | ... T46: =T8 -> 45930 | V46: =V8 -> 45382 | W46: =W8 -> 45473 | X46: =X8 -> 45565 | Y46: =Y8 -> 45657 | Z46: =Z8 -> 45747 | AA46: =AA8 -> 45838 | AB46: =AB8 -> 45930
B48: Current Assets
B49: Cash and cash equivalents | C49: 978957 | D49: 1789723 | E49: 1333507 | F49: 1346350 | G49: 865211 | H49: 902057 | J49: 1287711 | K49: 1110688 | L49: 818323 | M49: =G49 -> 865211 | N49: 764788 | O49: 724794 | P49: 423547 | Q49: =H49 -> 902057 | R49: 487535 | S49: 407511 | T49: 250494 | V49: =N49 -> 764788 | W49: =O49 -> 724794 | X49: =P49 -> 423547 | Y49: =Q49 -> 902057 | Z49: =R49 -> 487535 | AA49: =S49 -> 407511 | AB49: =T49 -> 250494 | AD49: =SUM(AB49/X49)-1 -> -0.40858039
B50: Restricted cash | C50: 0 | D50: 71401 | E50: 95400 | F50: 119392 | G50: 119400 | H50: 168390 | J50: 119400 | K50: 119400 | L50: 119400 | M50: =G50 -> 119400 | N50: 133585 | O50: 120579 | P50: 170086 | Q50: =H50 -> 168390 | R50: 270522 | S50: 152088 | T50: 396103 | V50: =N50 -> 133585 | W50: =O50 -> 120579 | X50: =P50 -> 170086 | Y50: =Q50 -> 168390 | Z50: =R50 -> 270522 | AA50: =S50 -> 152088 | AB50: =T50 -> 396103 | AD50: =SUM(AB50/X50)-1 -> 1.3288395
B51: Short-term investment securities | C51: 105321 | D51: 106339 | E51: 106313 | F51: 107115 | G51: 112501 | H51: 118334 | J51: 108357 | K51: 109494 | L51: 110933 | M51: =G51 -> 112501 | N51: 113854 | O51: 115290 | P51: 117104 | Q51: =H51 -> 118334 | R51: 119575 | S51: 0 | T51: 0 | V51: =N51 -> 113854 | W51: =O51 -> 115290 | X51: =P51 -> 117104 | Y51: =Q51 -> 118334 | Z51: =R51 -> 119575 | AA51: =S51 -> 0 | AB51: =T51 -> 0 | AD51: =SUM(AB51/X51)-1 -> -1
B52: Accounts receivable, net | C52: 73807 | D52: 42940 | E52: 128828 | F52: 197276 | G52: 205468 | H52: 178955 | J52: 186070 | K52: 186739 | L52: 170959 | M52: =G52 -> 205468 | N52: 212469 | O52: 216650 | P52: 230079 | Q52: =H52 -> 178955 | R52: 211932 | S52: 219414 | T52: 114386 | V52: =N52 -> 212469 | W52: =O52 -> 216650 | X52: =P52 -> 230079 | Y52: =Q52 -> 178955 | Z52: =R52 -> 211932 | AA52: =S52 -> 219414 | AB52: =T52 -> 114386 | AD52: =SUM(AB52/X52)-1 -> -0.50284033
B53: Prepaid expenses and Other Current Assets | C53: =103439+102906+21013 -> 227358 | D53: =124983+73134+147460 -> 345577 | E53: =129827+10726+37890 -> 178443 | F53: =187589+36261 -> 223850 | G53: =207700+1847 -> 209547 | H53: =278366+463020 -> 741386 | J53: =180284+36261 -> 216545 | K53: =36261+210252 -> 246513 | L53: =228878+549 -> 229427 | M53: =G53 -> 209547 | N53: 263713 | O53: 247952 | P53: 276373 | Q53: =H53 -> 741386 | R53: =242527+447558 -> 690085 | S53: =253057+449149 -> 702206 | T53: =306263+3119 -> 309382 | V53: =N53 -> 263713 | W53: =O53 -> 247952 | X53: =P53 -> 276373 | Y53: =Q53 -> 741386 | Z53: =R53 -> 690085 | AA53: =S53 -> 702206 | AB53: =T53 -> 309382 | AD53: =SUM(AB53/X53)-1 -> 0.11943641
B54: Total Current Assets | C54: =SUM(C49:C53) -> 1385443 | D54: =SUM(D49:D53) -> 2355980 | E54: =SUM(E49:E53) -> 1842491 | F54: =SUM(F49:F53) -> 1993983 | G54: =SUM(G49:G53) -> 1512127 | H54: =SUM(H49:H53) -> 2109122 | J54: =SUM(J49:J53) -> 1918083 | K54: =SUM(K49:K53) -> 1772834 | L54: =SUM(L49:L53) -> 1449042 | M54: =SUM(M49:M53) -> 1512127 | N54: =SUM(N49:N53) -> 1488409 | O54: =SUM(O49:O53) -> 1425265 | P54: =SUM(P49:P53) -> 1217189 | Q54: =SUM(Q49:Q53) -> 2109122 | ... T54: =SUM(T49:T53) -> 1070365 | V54: =SUM(V49:V53) -> 1488409 | W54: =SUM(W49:W53) -> 1425265 | X54: =SUM(X49:X53) -> 1217189 | Y54: =SUM(Y49:Y53) -> 2109122 | Z54: =SUM(Z49:Z53) -> 1779649 | AA54: =SUM(AA49:AA53) -> 1481219 | AB54: =SUM(AB49:AB53) -> 1070365 | AD54: =SUM(AB54/X54)-1 -> -0.12062547
B56: Non-Current Assets
B57: Property and equipment, net | C57: 3530302 | D57: 3831568 | E57: 3856593 | F57: 3749498 | G57: 3519128 | H57: 2492784 | J57: 3738682 | K57: 3740500 | L57: 3731960 | M57: =G57 -> 3519128 | N57: 3400292 | O57: 3336335 | P57: 3299455 | Q57: =H57 -> 2492784 | R57: 2325965 | S57: 2289181 | T57: 2521158 | V57: =N57 -> 3400292 | W57: =O57 -> 3336335 | X57: =P57 -> 3299455 | Y57: =Q57 -> 2492784 | Z57: =R57 -> 2325965 | AA57: =S57 -> 2289181 | AB57: =T57 -> 2521158 | AD57: =SUM(AB57/X57)-1 -> -0.23588653
B58: Operating lease right-of-use assets: | C58: 1369555 | D58: 1417823 | E58: 1950520 | F58: 2699574 | G58: 3561028 | H58: 4583734 | J58: 2859829 | K58: 3058137 | L58: 3354082 | M58: =G58 -> 3561028 | N58: 3859596 | O58: 4156810 | P58: 4516298 | Q58: =H58 -> 4583734 | R58: 4425872 | S58: 4457889 | T58: 4646002 | V58: =N58 -> 3859596 | W58: =O58 -> 4156810 | X58: =P58 -> 4516298 | Y58: =Q58 -> 4583734 | Z58: =R58 -> 4425872 | AA58: =S58 -> 4457889 | AB58: =T58 -> 4646002 | AD58: =SUM(AB58/X58)-1 -> 0.028719097
B59: Pre-delivery deposits on flight equipment | C59: 291930 | D59: 356262 | E59: 484821 | F59: 487553 | G59: 480717 | H59: 113493 | J59: 516099 | K59: 508957 | L59: 495300 | M59: =G59 -> 480717 | N59: 443478 | O59: 307140 | P59: 124290 | Q59: =H59 -> 113493 | R59: 86319 | S59: 73572 | T59: 75376 | V59: =N59 -> 443478 | W59: =O59 -> 307140 | X59: =P59 -> 124290 | Y59: =Q59 -> 113493 | Z59: =R59 -> 86319 | AA59: =S59 -> 73572 | AB59: =T59 -> 75376 | AD59: =SUM(AB59/X59)-1 -> -0.39354735
B60: Deferred heavy maintenance, net | C60: 361603 | D60: 347907 | E60: 330062 | F60: 190349 | G60: 313505 | H60: 241094 | J60: 230014 | K60: 252682 | L60: 293299 | M60: =G60 -> 313505 | N60: 307276 | O60: 306746 | P60: 302600 | Q60: =H60 -> 241094 | R60: 132889 | S60: 115451 | T60: 110568 | V60: =N60 -> 307276 | W60: =O60 -> 306746 | X60: =P60 -> 302600 | Y60: =Q60 -> 241094 | Z60: =R60 -> 132889 | AA60: =S60 -> 115451 | AB60: =T60 -> 110568 | AD60: =SUM(AB60/X60)-1 -> -0.63460674
B61: Other long-term assets | C61: =36897+67682 -> 104579 | D61: =36127+53158 -> 89285 | E61: =37372+38166 -> 75538 | F61: 63817 | G61: 30732 | H61: 54951 | J61: 59610 | K61: 39017 | L61: 37867 | M61: =G61 -> 30732 | N61: 27444 | O61: 27160 | P61: 33217 | Q61: =H61 -> 54951 | R61: =75942+83482 -> 159424 | S61: =83482+75493 -> 158975 | T61: =83482+288093 -> 371575 | V61: =N61 -> 27444 | W61: =O61 -> 27160 | X61: =P61 -> 33217 | Y61: =Q61 -> 54951 | Z61: =R61 -> 159424 | AA61: =S61 -> 158975 | AB61: =T61 -> 371575 | AD61: =SUM(AB61/X61)-1 -> 10.18629
B62: Total Assets | C62: =SUM(C57:C61)+C54 -> 7043412 | D62: =SUM(D57:D61)+D54 -> 8398825 | E62: =SUM(E57:E61)+E54 -> 8540025 | F62: =SUM(F57:F61)+F54 -> 9184774 | G62: =SUM(G57:G61)+G54 -> 9417237 | H62: =SUM(H57:H61)+H54 -> 9595178 | J62: =SUM(J57:J61)+J54 -> 9322317 | K62: =SUM(K57:K61)+K54 -> 9372127 | L62: =SUM(L57:L61)+L54 -> 9361550 | M62: =SUM(M57:M61)+M54 -> 9417237 | N62: =SUM(N57:N61)+N54 -> 9526495 | O62: =SUM(O57:O61)+O54 -> 9559456 | P62: =SUM(P57:P61)+P54 -> 9493049 | Q62: =SUM(Q57:Q61)+Q54 -> 9595178 | ... T62: =SUM(T57:T61)+T54 -> 8795044 | V62: =SUM(V57:V61)+V54 -> 9526495 | W62: =SUM(W57:W61)+W54 -> 9559456 | X62: =SUM(X57:X61)+X54 -> 9493049 | Y62: =SUM(Y57:Y61)+Y54 -> 9595178 | Z62: =SUM(Z57:Z61)+Z54 -> 8910118 | AA62: =SUM(AA57:AA61)+AA54 -> 8576287 | AB62: =SUM(AB57:AB61)+AB54 -> 8795044 | AD62: =SUM(AB62/X62)-1 -> -0.07352801
B64: Current Liabilities
B65: Accounts payable | C65: 43601 | D65: 28454 | E65: 44952 | F65: 75449 | G65: 42098 | H65: 32385 | J65: 53046 | K65: 76158 | L65: 86297 | M65: =G65 -> 42098 | N65: 85074 | O65: 70014 | P65: 49637 | Q65: =H65 -> 32385 | R65: 101213 | S65: 147676 | T65: 149270 | V65: =N65 -> 85074 | W65: =O65 -> 70014 | X65: =P65 -> 49637 | Y65: =Q65 -> 32385 | Z65: =R65 -> 101213 | AA65: =S65 -> 147676 | AB65: =T65 -> 149270 | AD65: =SUM(AB65/X65)-1 -> 2.0072325
B66: Air traffic liability | C66: 315408 | D66: 401966 | E66: 382317 | F66: 429618 | G66: 383751 | H66: 436813 | J66: 566856 | K66: 479677 | L66: 429355 | M66: =G66 -> 383751 | N66: 475653 | O66: 496985 | P66: 459558 | Q66: =H66 -> 436813 | R66: 454521 | S66: 407473 | T66: 373096 | V66: =N66 -> 475653 | W66: =O66 -> 496985 | X66: =P66 -> 459558 | Y66: =Q66 -> 436813 | Z66: =R66 -> 454521 | AA66: =S66 -> 407473 | AB66: =T66 -> 373096 | AD66: =SUM(AB66/X66)-1 -> -0.18814165
B67: Current Portion of LTD, and finance leases. | C67: 258852 | D67: 384197 | E67: 208948 | F67: 346888 | G67: 315580 | H67: 436532 | J67: 261724 | K67: 235579 | L67: 235868 | M67: =G67 -> 315580 | N67: 156812 | O67: 142815 | P67: 1253376 | Q67: =H67 -> 436532 | R67: 191572 | S67: 121190 | T67: 119226 | V67: =N67 -> 156812 | W67: =O67 -> 142815 | X67: =P67 -> 1253376 | Y67: =Q67 -> 436532 | Z67: =R67 -> 191572 | AA67: =S67 -> 121190 | AB67: =T67 -> 119226 | AD67: =SUM(AB67/X67)-1 -> -0.90487611
B68: Current maturities of operating leases | C68: 120662 | D68: 133791 | E68: 158631 | F68: 188296 | G68: 224865 | H68: 257796 | J68: 195039 | K68: 201337 | L68: 210994 | M68: =G68 -> 224865 | N68: 234062 | O68: 243528 | P68: 255942 | Q68: =H68 -> 257796 | R68: 238685 | S68: 239633 | T68: 4201 | V68: =N68 -> 234062 | W68: =O68 -> 243528 | X68: =P68 -> 255942 | Y68: =Q68 -> 257796 | Z68: =R68 -> 238685 | AA68: =S68 -> 239633 | AB68: =T68 -> 4201 | AD68: =SUM(AB68/X68)-1 -> -0.98358612
B69: Other current liabilities | C69: 373521 | D69: 393614 | E69: 480754 | F69: 556330 | G69: 705298 | H69: 605839 | J69: 675944 | K69: 693211 | L69: 638286 | M69: =G69 -> 705298 | N69: 577433 | O69: 557806 | P69: 521690 | Q69: =H69 -> 605839 | R69: 591357 | S69: 537556 | T69: 364383 | V69: =N69 -> 577433 | W69: =O69 -> 557806 | X69: =P69 -> 521690 | Y69: =Q69 -> 605839 | Z69: =R69 -> 591357 | AA69: =S69 -> 537556 | AB69: =T69 -> 364383 | AD69: =SUM(AB69/X69)-1 -> -0.30153348
B70: Total Current Liabilities | C70: =SUM(C65:C69) -> 1112044 | D70: =SUM(D65:D69) -> 1342022 | E70: =SUM(E65:E69) -> 1275602 | F70: =SUM(F65:F69) -> 1596581 | G70: =SUM(G65:G69) -> 1671592 | H70: =SUM(H65:H69) -> 1769365 | J70: =SUM(J65:J69) -> 1752609 | K70: =SUM(K65:K69) -> 1685962 | L70: =SUM(L65:L69) -> 1600800 | M70: =SUM(M65:M69) -> 1671592 | N70: =SUM(N65:N69) -> 1529034 | O70: =SUM(O65:O69) -> 1511148 | P70: =SUM(P65:P69) -> 2540203 | Q70: =SUM(Q65:Q69) -> 1769365 | ... T70: =SUM(T65:T69) -> 1010176 | V70: =SUM(V65:V69) -> 1529034 | W70: =SUM(W65:W69) -> 1511148 | X70: =SUM(X65:X69) -> 2540203 | Y70: =SUM(Y65:Y69) -> 1769365 | Z70: =SUM(Z65:Z69) -> 1577348 | AA70: =SUM(AA65:AA69) -> 1453528 | AB70: =SUM(AB65:AB69) -> 1010176 | AD70: =SUM(AB70/X70)-1 -> -0.6023247
B72: Non-Current Liabilities
B73: LTD, and finance leases. | C73: 1960453 | D73: 3066635 | E73: 2975823 | F73: 3200376 | G73: 3055221 | H73: 1761215 | J73: 3164061 | K73: 3081192 | L73: 3043391 | M73: =G73 -> 3055221 | N73: 3175555 | O73: 3124079 | P73: 1986735 | Q73: =H73 -> 1761215 | R73: 2231335 | S73: 2242448 | T73: 750205 | V73: =N73 -> 3175555 | W73: =O73 -> 3124079 | X73: =P73 -> 1986735 | Y73: =Q73 -> 1761215 | Z73: =R73 -> 2231335 | AA73: =S73 -> 2242448 | AB73: =T73 -> 750205 | AD73: =SUM(AB73/X73)-1 -> -0.62239302
B74: Operating leases, less current maturities | C74: 1218014 | D74: 1248519 | E74: 1751351 | F74: 2455619 | G74: 3298871 | H74: 4335106 | J74: 2605011 | K74: 2793437 | L74: 3108399 | M74: =G74 -> 3298871 | N74: 3593771 | O74: 3895269 | P74: 4267577 | Q74: =H74 -> 4335106 | R74: 4200013 | S74: 4228832 | T74: 18426 | V74: =N74 -> 3593771 | W74: =O74 -> 3895269 | X74: =P74 -> 4267577 | Y74: =Q74 -> 4335106 | Z74: =R74 -> 4200013 | AA74: =S74 -> 4228832 | AB74: =T74 -> 18426 | AD74: =SUM(AB74/X74)-1 -> -0.99568233
B75: Deferred income taxes | C75: 469292 | D75: 439894 | E75: 375472 | F75: 226843 | G75: 107761 | H75: 51927 | J75: 189054 | K75: 205796 | L75: 160054 | M75: =G75 -> 107761 | N75: 92783 | O75: 96450 | P75: 71639 | Q75: =H75 -> 51927 | R75: 69305 | S75: 64757 | T75: 65988 | V75: =N75 -> 92783 | W75: =O75 -> 96450 | X75: =P75 -> 71639 | Y75: =Q75 -> 51927 | Z75: =R75 -> 69305 | AA75: =S75 -> 64757 | AB75: =T75 -> 65988 | AD75: =SUM(AB75/X75)-1 -> -0.078881615
B76: Deferred gains and other long-term liabilities | C76: 22277 | D76: 52060 | E76: 47742 | F76: 133704 | G76: 149450 | H76: 122595 | J76: 141736 | K76: 134668 | L76: 132861 | M76: =G76 -> 149450 | N76: 133095 | O76: 122848 | P76: 123146 | Q76: =H76 -> 122595 | R76: 108704 | S76: 107277 | T76: 94286 | V76: =N76 -> 133095 | W76: =O76 -> 122848 | X76: =P76 -> 123146 | Y76: =Q76 -> 122595 | Z76: =R76 -> 108704 | AA76: =S76 -> 107277 | AB76: =T76 -> 94286 | AD76: =SUM(AB76/X76)-1 -> -0.23435597
B77: Liabilities subject to compromise | C77: 0 | D77: 0 | E77: 0 | F77: 0 | G77: 0 | H77: 1635104 | J77: 0 | K77: 0 | L77: 0 | M77: =G77 -> 0 | N77: 0 | O77: 0 | P77: 0 | Q77: =H77 -> 1635104 | R77: 0 | S77: 0 | T77: 6691470 | V77: =N77 -> 0 | W77: =O77 -> 0 | X77: =P77 -> 0 | Y77: =Q77 -> 1635104 | Z77: =R77 -> 0 | AA77: =S77 -> 0 | AB77: =T77 -> 6691470 | AD77: =SUM(AB77/X77)-1 -> #DIV/0!
B78: Total Liabilities | C78: =SUM(C73:C77)+C70 -> 4782080 | D78: =SUM(D73:D77)+D70 -> 6149130 | E78: =SUM(E73:E77)+E70 -> 6425990 | F78: =SUM(F73:F77)+F70 -> 7613123 | G78: =SUM(G73:G77)+G70 -> 8282895 | H78: =SUM(H73:H77)+H70 -> 9675312 | J78: =SUM(J73:J77)+J70 -> 7852471 | K78: =SUM(K73:K77)+K70 -> 7901055 | L78: =SUM(L73:L77)+L70 -> 8045505 | M78: =SUM(M73:M77)+M70 -> 8282895 | N78: =SUM(N73:N77)+N70 -> 8524238 | O78: =SUM(O73:O77)+O70 -> 8749794 | P78: =SUM(P73:P77)+P70 -> 8989300 | Q78: =SUM(Q73:Q77)+Q70 -> 9675312 | ... T78: =SUM(T73:T77)+T70 -> 8630551 | V78: =SUM(V73:V77)+V70 -> 8524238 | W78: =SUM(W73:W77)+W70 -> 8749794 | X78: =SUM(X73:X77)+X70 -> 8989300 | Y78: =SUM(Y73:Y77)+Y70 -> 9675312 | Z78: =SUM(Z73:Z77)+Z70 -> 8186705 | AA78: =SUM(AA73:AA77)+AA70 -> 8096842 | AB78: =SUM(AB73:AB77)+AB70 -> 8630551 | AD78: =SUM(AB78/X78)-1 -> -0.039908447
B80: Common stock | C80: 7 | D80: 10 | E80: 11 | F80: 11 | G80: 11 | H80: 11 | J80: 11 | K80: 11 | L80: 11 | M80: =G80 -> 11 | N80: 11 | O80: 11 | P80: 11 | Q80: =H80 -> 11 | R80: 2 | S80: 2 | T80: 3 | V80: =N80 -> 11 | W80: =O80 -> 11 | X80: =P80 -> 11 | Y80: =Q80 -> 11 | Z80: =R80 -> 2 | AA80: =S80 -> 2 | AB80: =T80 -> 3 | AD80: =SUM(AB80/X80)-1 -> -0.72727273
B81: Additional paid-in-capital | C81: 379380 | D81: 799549 | E81: 1131826 | F81: 1146015 | G81: 1158278 | H81: 1173692 | J81: 1149588 | K81: 1153068 | L81: 1155637 | M81: =G81 -> 1158278 | N81: 1169562 | O81: 1169904 | P81: 1171856 | Q81: =H81 -> 1173692 | R81: 734368 | S81: 736212 | T81: 738733 | V81: =N81 -> 1169562 | W81: =O81 -> 1169904 | X81: =P81 -> 1171856 | Y81: =Q81 -> 1173692 | Z81: =R81 -> 734368 | AA81: =S81 -> 736212 | AB81: =T81 -> 738733 | AD81: =SUM(AB81/X81)-1 -> -0.36960429
B82: Treasury stock | C82: -72455 | D82: -74124 | E82: -75639 | F82: -77998 | G82: -80635 | H82: -81285 | J82: -79671 | K82: -79672 | L82: -79706 | M82: =G82 -> -80635 | N82: -81271 | O82: -81280 | P82: -81284 | Q82: =H82 -> -81285 | R82: 0 | S82: 0 | T82: 0 | V82: =N82 -> -81271 | W82: =O82 -> -81280 | X82: =P82 -> -81284 | Y82: =Q82 -> -81285 | Z82: =R82 -> 0 | AA82: =S82 -> 0 | AB82: =T82 -> 0 | AD82: =SUM(AB82/X82)-1 -> -1
B83: Retained earnings | C83: 1955187 | D83: 1524878 | E83: 1058369 | F83: 504219 | G83: 56755 | H83: -1172740 | J83: 400308 | K83: 397959 | L83: 240407 | M83: =G83 -> 56755 | N83: -85880 | O83: -278807 | P83: -587050 | Q83: =H83 -> -1172740 | R83: -10936 | S83: -256767 | T83: -574243 | V83: =N83 -> -85880 | W83: =O83 -> -278807 | X83: =P83 -> -587050 | Y83: =Q83 -> -1172740 | Z83: =R83 -> -10936 | AA83: =S83 -> -256767 | AB83: =T83 -> -574243 | AD83: =SUM(AB83/X83)-1 -> -0.021815859
B84: Accumulated other comprehensive income (loss) | C84: -787 | D84: -618 | E84: -532 | F84: -596 | G84: -67 | H84: 188 | J84: -390 | K84: -294 | L84: -304 | M84: =G84 -> -67 | N84: -165 | O84: -166 | P84: 216 | Q84: =H84 -> 188 | R84: -21 | S84: -2 | T84: 0 | V84: =N84 -> -165 | W84: =O84 -> -166 | X84: =P84 -> 216 | Y84: =Q84 -> 188 | Z84: =R84 -> -21 | AA84: =S84 -> -2 | AB84: =T84 -> 0 | AD84: =SUM(AB84/X84)-1 -> -1
B85: Total stockholders' equity | C85: =SUM(C80:C84) -> 2261332 | D85: =SUM(D80:D84) -> 2249695 | E85: =SUM(E80:E84) -> 2114035 | F85: =SUM(F80:F84) -> 1571651 | G85: =SUM(G80:G84) -> 1134342 | H85: =SUM(H80:H84) -> -80134 | J85: =SUM(J80:J84) -> 1469846 | K85: =SUM(K80:K84) -> 1471072 | L85: =SUM(L80:L84) -> 1316045 | M85: =SUM(M80:M84) -> 1134342 | N85: =SUM(N80:N84) -> 1002257 | O85: =SUM(O80:O84) -> 809662 | P85: =SUM(P80:P84) -> 503749 | Q85: =SUM(Q80:Q84) -> -80134 | ... T85: =SUM(T80:T84) -> 164493 | V85: =SUM(V80:V84) -> 1002257 | W85: =SUM(W80:W84) -> 809662 | X85: =SUM(X80:X84) -> 503749 | Y85: =SUM(Y80:Y84) -> -80134 | Z85: =SUM(Z80:Z84) -> 723413 | AA85: =SUM(AA80:AA84) -> 479445 | AB85: =SUM(AB80:AB84) -> 164493 | AD85: =SUM(AB85/X85)-1 -> -0.67346238
B86: Total liabilities and stockholders' equity | C86: =SUM(C85+C78) -> 7043412 | D86: =SUM(D85+D78) -> 8398825 | E86: =SUM(E85+E78) -> 8540025 | F86: =SUM(F85+F78) -> 9184774 | G86: =SUM(G85+G78) -> 9417237 | H86: =SUM(H85+H78) -> 9595178 | J86: =SUM(J85+J78) -> 9322317 | K86: =SUM(K85+K78) -> 9372127 | L86: =SUM(L85+L78) -> 9361550 | M86: =SUM(M85+M78) -> 9417237 | N86: =SUM(N85+N78) -> 9526495 | O86: =SUM(O85+O78) -> 9559456 | P86: =SUM(P85+P78) -> 9493049 | Q86: =SUM(Q85+Q78) -> 9595178 | ... T86: =SUM(T85+T78) -> 8795044 | V86: =SUM(V85+V78) -> 9526495 | W86: =SUM(W85+W78) -> 9559456 | X86: =SUM(X85+X78) -> 9493049 | Y86: =SUM(Y85+Y78) -> 9595178 | Z86: =SUM(Z85+Z78) -> 8910118 | AA86: =SUM(AA85+AA78) -> 8576287 | AB86: =SUM(AB85+AB78) -> 8795044 | AD86: =SUM(AB86/X86)-1 -> -0.07352801
B88: Balance Check | C88: =C86-C62 -> 0 | D88: =D86-D62 -> 0 | E88: =E86-E62 -> 0 | F88: =F86-F62 -> 0 | G88: =G86-G62 -> 0 | H88: =H86-H62 -> 0 | J88: =J86-J62 -> 0 | K88: =K86-K62 -> 0 | L88: =L86-L62 -> 0 | M88: =M86-M62 -> 0 | N88: =N86-N62 -> 0 | O88: =O86-O62 -> 0 | P88: =P86-P62 -> 0 | Q88: =Q86-Q62 -> 0 | ... T88: =T86-T62 -> 0 | V88: =V86-V62 -> 0 | W88: =W86-W62 -> 0 | X88: =X86-X62 -> 0 | Y88: =Y86-Y62 -> 0 | Z88: =Z86-Z62 -> 0 | AA88: =AA86-AA62 -> 0 | AB88: =AB86-AB62 -> 0
A91: X | B91: Cash-Flows Statement | W91: LTM | AD91: Variance
B92: =B7 -> Fiscal Period | C92: =C7 -> 2019 | D92: =D7 -> 2020 | E92: =E7 -> 2021 | F92: =F7 -> 2022 | G92: =G7 -> 2023 | H92: =H7 -> 2024 | J92: =J7 -> 1Q23 | K92: =K7 -> 2Q23 | L92: =L7 -> 3Q23 | M92: =M7 -> 4Q23 | N92: =N7 -> 1Q24 | O92: =O7 -> 2Q24 | P92: =P7 -> 3Q24 | Q92: =Q7 -> 4Q24 | ... T92: =T7 -> 3Q25 | V92: =V7 -> 1Q24 | W92: =W7 -> 2Q24 | X92: =X7 -> 3Q24 | Y92: =Y7 -> 4Q24 | Z92: =Z7 -> 1Q25 | AA92: =AA7 -> 2Q25 | AB92: =AB7 -> 3Q25
B93: =B8 -> Fiscal Period End Date | C93: =C8 -> 43830 | D93: =D8 -> 44196 | E93: =E8 -> 44561 | F93: =F8 -> 44926 | G93: =G8 -> 45291 | H93: =H8 -> 45657 | J93: =J8 -> 45016 | K93: =K8 -> 45107 | L93: =L8 -> 45199 | M93: =M8 -> 45291 | N93: =N8 -> 45382 | O93: =O8 -> 45473 | P93: =P8 -> 45565 | Q93: =Q8 -> 45657 | ... T93: =T8 -> 45930 | V93: =V8 -> 45382 | W93: =W8 -> 45473 | X93: =X8 -> 45565 | Y93: =Y8 -> 45657 | Z93: =Z8 -> 45747 | AA93: =AA8 -> 45838 | AB93: =AB8 -> 45930
B95: Cash-Flows From Operating Activities
B96: Net income (loss) | C96: =C35 -> 335255 | D96: =D35 -> -428700 | E96: =E35 -> -472569 | F96: =F35 -> -554150 | G96: =G35 -> -447464 | H96: =H35 -> -1229495 | J96: =J35 -> -103911 | K96: =K35 -> -2349 | L96: =L35 -> -157552 | M96: =M35 -> -183652 | N96: =N35 -> -142635 | O96: =O35 -> -192927 | P96: =P35 -> -308243 | Q96: =Q35 -> -585690 | ... T96: =T35 -> -317476 | V96: =SUM(K96:N96) -> -486188 | W96: =SUM(L96:O96) -> -676766 | X96: =SUM(M96:P96) -> -827457 | Y96: =SUM(N96:Q96) -> -1229495 | Z96: =SUM(O96:R96) -> -1025580 | AA96: =SUM(P96:S96) -> -1078484 | AB96: =SUM(Q96:T96) -> -1087717 | AD96: =SUM(AB96/X96)-1 -> 0.31452994
B98: Adjustments to reconcile net income: | AD98: =SUM(AB98/X98)-1 -> #DIV/0!
B99: Depreciation and Amortization (D&A) | C99: 225264 | D99: 278588 | E99: 297211 | F99: 313090 | G99: 320872 | H99: 325273 | J99: 77991 | K99: =158533-J99 -> 80542 | L99: =241335-K99-J99 -> 82802 | M99: =SUM(G99-SUM(J99:L99)) -> 79537 | N99: 81346 | O99: =165832-N99 -> 84486 | P99: =249860-O99-N99 -> 84028 | Q99: =SUM(H99-SUM(N99:P99)) -> 75413 | R99: =54853+11597 -> 66450 | S99: =74483+54853-R99 -> 62886 | T99: =54853+132515-S99-R99 -> 58032 | V99: =SUM(K99:N99) -> 324227 | W99: =SUM(L99:O99) -> 328171 | X99: =SUM(M99:P99) -> 329397 | Y99: =SUM(N99:Q99) -> 325273 | Z99: =SUM(O99:R99) -> 310377 | AA99: =SUM(P99:S99) -> 288777 | AB99: =SUM(Q99:T99) -> 262781 | AD99: =SUM(AB99/X99)-1 -> -0.20223621
B100: Share-Based Compensation (SBC) | C100: 8154 | D100: 11575 | E100: 12536 | F100: 11483 | G100: 11963 | H100: 7210 | J100: 3273 | K100: =6753-J100 -> 3480 | L100: =9322-K100-J100 -> 2569 | M100: =SUM(G100-SUM(J100:L100)) -> 2641 | N100: 3080 | O100: =3422-N100 -> 342 | P100: =5374-O100-N100 -> 1952 | Q100: =SUM(H100-SUM(N100:P100)) -> 1836 | R100: 1233 | S100: =1233+1844-R100 -> 1844 | T100: =4366+1233-S100-R100 -> 2522 | V100: =SUM(K100:N100) -> 11770 | W100: =SUM(L100:O100) -> 8632 | X100: =SUM(M100:P100) -> 8015 | Y100: =SUM(N100:Q100) -> 7210 | Z100: =SUM(O100:R100) -> 5363 | AA100: =SUM(P100:S100) -> 6865 | AB100: =SUM(Q100:T100) -> 7435 | AD100: =SUM(AB100/X100)-1 -> -0.072364317
B101: Loss (Gain) on Disposal of Assets | C101: 17350 | D101: 2264 | E101: 3320 | F101: 46624 | G101: 33966 | H101: 273871 | J101: 7100 | K101: =7902-J101 -> 802 | L101: =5652-K101-J101 -> -2250 | M101: =SUM(G101-SUM(J101:L101)) -> 28314 | N101: -3029 | O101: =-17076-N101 -> -14047 | P101: =-13885-O101-N101 -> 3191 | Q101: =SUM(H101-SUM(N101:P101)) -> 287756 | R101: =11655-19 -> 11636 | S101: =11655-328-R101 -> -309 | T101: =11655-114041-S101-R101 -> -113713 | V101: =SUM(K101:N101) -> 23837 | W101: =SUM(L101:O101) -> 8988 | X101: =SUM(M101:P101) -> 14429 | Y101: =SUM(N101:Q101) -> 273871 | Z101: =SUM(O101:R101) -> 288536 | AA101: =SUM(P101:S101) -> 302274 | AB101: =SUM(Q101:T101) -> 185370 | AD101: =SUM(AB101/X101)-1 -> 11.847044
B102: Deferred income tax benefit | C102: 115689 | D102: -46086 | E102: -49502 | F102: -148611 | G102: -119239 | H102: -58215 | J102: -37851 | K102: =-20998-J102 -> 16853 | L102: =-66877-K102-J102 -> -45879 | M102: =SUM(G102-SUM(J102:L102)) -> -52362 | N102: -15005 | O102: =-11345-N102 -> 3660 | P102: =-36208-O102-N102 -> -24863 | Q102: =SUM(H102-SUM(N102:P102)) -> -22007 | R102: =17481-103 -> 17378 | S102: =17481-4651-R102 -> -4548 | T102: =17481-3420-S102-R102 -> 1231 | V102: =SUM(K102:N102) -> -96393 | W102: =SUM(L102:O102) -> -109586 | X102: =SUM(M102:P102) -> -88570 | Y102: =SUM(N102:Q102) -> -58215 | Z102: =SUM(O102:R102) -> -25832 | AA102: =SUM(P102:S102) -> -34040 | AB102: =SUM(Q102:T102) -> -7946 | AD102: =SUM(AB102/X102)-1 -> -0.91028565
B103: Amortization of debt issuance costs | C103: 8654 | D103: 10752 | E103: 12912 | F103: 13468 | G103: 15454 | H103: 13100 | J103: 3981 | K103: =7829-J103 -> 3848 | L103: =11675-K103-J103 -> 3846 | M103: =SUM(G103-SUM(J103:L103)) -> 3779 | N103: 3582 | O103: =7069-N103 -> 3487 | P103: =10625-O103-N103 -> 3556 | Q103: =SUM(H103-SUM(N103:P103)) -> 2475 | R103: =1003+233 -> 1236 | S103: =1003+1349-R103 -> 1116 | T103: =1003+2296-S103-R103 -> 947 | V103: =SUM(K103:N103) -> 15055 | W103: =SUM(L103:O103) -> 14694 | X103: =SUM(M103:P103) -> 14404 | Y103: =SUM(N103:Q103) -> 13100 | Z103: =SUM(O103:R103) -> 10754 | AA103: =SUM(P103:S103) -> 8383 | AB103: =SUM(Q103:T103) -> 5774 | AD103: =SUM(AB103/X103)-1 -> -0.59913913
B104: Accretion of convertible debt and 8.00% senior secured notes | C104: 0 | D104: 10138 | E104: 1272 | F104: 1421 | G104: 4210 | H104: 3821 | J104: 1052 | K104: =2105-J104 -> 1053 | L104: =3157-K104-J104 -> 1052 | M104: =SUM(G104-SUM(J104:L104)) -> 1053 | N104: 1052 | O104: =2105-N104 -> 1053 | P104: =3157-O104-N104 -> 1052 | Q104: =SUM(H104-SUM(N104:P104)) -> 664 | R104: 0 | S104: 0 | T104: 0 | V104: =SUM(K104:N104) -> 4210 | W104: =SUM(L104:O104) -> 4210 | X104: =SUM(M104:P104) -> 4210 | Y104: =SUM(N104:Q104) -> 3821 | Z104: =SUM(O104:R104) -> 2769 | AA104: =SUM(P104:S104) -> 1716 | AB104: =SUM(Q104:T104) -> 664 | AD104: =SUM(AB104/X104)-1 -> -0.84228029
B105: Other Gains, Losses, Allowances, and Charges | C105: =315-822 -> -507 | D105: =-249+252+118 -> 121 | E105: =-88+226+731+331630 -> 332499 | F105: =-108+199+68+333691 -> 333850 | G105: =159+314-762 -> -289 | H105: =822+103-3082 -> -2157 | J105: =45+6 -435 -> -384 | K105: =88+6-1028-J105 -> -550 | L105: =-1890+159+129 -K105-J105 -> -668 | M105: =SUM(G105-SUM(J105:L105)) -> 1313 | N105: =19+1051+51 -> 1121 | O105: =38+823-1112-N105 -> -1372 | P105: =55+822-2203-O105-N105 -> -1075 | Q105: =SUM(H105-SUM(N105:P105)) -> -831 | R105: =-767-206+160+34 -2 -> -781 | S105: =34-2+215+11568-767-897-R105 -> 10932 | T105: =-767-897+19421-547+34-S105-R105 -> 7093 | V105: =SUM(K105:N105) -> 1216 | W105: =SUM(L105:O105) -> 394 | X105: =SUM(M105:P105) -> -13 | Y105: =SUM(N105:Q105) -> -2157 | Z105: =SUM(O105:R105) -> -4059 | AA105: =SUM(P105:S105) -> 8245 | AB105: =SUM(Q105:T105) -> 16413 | AD105: =SUM(AB105/X105)-1 -> -1263.5385
B106: Amortization of debt discount | C106: 0 | D106: 0 | E106: 0 | F106: 13962 | G106: 8145 | H106: 10156 | J106: 3808 | K106: =2378-J106 -> -1430 | L106: =5262-K106-J106 -> 2884 | M106: =SUM(G106-SUM(J106:L106)) -> 2883 | N106: 2883 | O106: =5767-N106 -> 2884 | P106: =8650-O106-N106 -> 2883 | Q106: =SUM(H106-SUM(N106:P106)) -> 1506 | R106: 0 | S106: =109-R106 -> 109 | T106: =219-S106-R106 -> 110 | V106: =SUM(K106:N106) -> 7220 | W106: =SUM(L106:O106) -> 11534 | X106: =SUM(M106:P106) -> 11533 | Y106: =SUM(N106:Q106) -> 10156 | Z106: =SUM(O106:R106) -> 7273 | AA106: =SUM(P106:S106) -> 4498 | AB106: =SUM(Q106:T106) -> 1725 | AD106: =SUM(AB106/X106)-1 -> -0.8504292
B107: Reorganization items | C107: 0 | D107: 0 | E107: 0 | F107: 0 | G107: 0 | H107: 85554 | J107: 0 | K107: 0 | L107: 0 | M107: =SUM(G107-SUM(J107:L107)) -> 0 | N107: 0 | O107: 0 | P107: 0 | Q107: =SUM(H107-SUM(N107:P107)) -> 85554 | R107: -421464 | S107: =-421464-R107 -> 0 | T107: =-421464+125983-S107-R107 -> 125983 | V107: =SUM(K107:N107) -> 0 | W107: =SUM(L107:O107) -> 0 | X107: =SUM(M107:P107) -> 0 | Y107: =SUM(N107:Q107) -> 85554 | Z107: =SUM(O107:R107) -> -335910 | AA107: =SUM(P107:S107) -> -335910 | AB107: =SUM(Q107:T107) -> -209927 | AD107: =SUM(AB107/X107)-1 -> #DIV/0!
B109: Changes in assets and liabilities:
B110: Accounts receivable, net | C110: -26147 | D110: 30486 | E110: -85800 | F110: -68340 | G110: -8351 | H110: 26797 | J110: 11200 | K110: =10531-J110 -> -669 | L110: =26158-K110-J110 -> 15627 | M110: =SUM(G110-SUM(J110:L110)) -> -34509 | N110: -8052 | O110: =-12005-N110 -> -3953 | P110: =-20972-O110-N110 -> -8967 | Q110: =SUM(H110-SUM(N110:P110)) -> 47769 | R110: =-22726-10251 -> -32977 | S110: =-22726-17948-R110 -> -7697 | T110: =-22726+87842-S110-R110 -> 105790 | V110: =SUM(K110:N110) -> -27603 | W110: =SUM(L110:O110) -> -30887 | X110: =SUM(M110:P110) -> -55481 | Y110: =SUM(N110:Q110) -> 26797 | Z110: =SUM(O110:R110) -> 1872 | AA110: =SUM(P110:S110) -> -1872 | AB110: =SUM(Q110:T110) -> 112885 | AD110: =SUM(AB110/X110)-1 -> -3.0346605
B111: Deposits and other assets | C111: =22453+14999+1431-21013 -> 17870 | D111: =23732-12944-223-126447 -> -115882 | E111: =47855+156+109570 -> 157581 | F111: =-28883+1629 -> -27254 | G111: =4215+36261 -> 40476 | H111: =-76744-96 -> -76840 | J111: 580 | K111: =-7339-J111 -> -7919 | L111: =35712-23105-K111-J111 -> 19946 | M111: =SUM(G111-SUM(J111:L111)) -> 27869 | N111: -49338 | O111: =-28990-N111 -> 20348 | P111: =-59303-4193-O111-N111 -> -34506 | Q111: =SUM(H111-SUM(N111:P111)) -> -13344 | R111: =13597+4668 -> 18265 | S111: =13597-4188-R111 -> -8856 | T111: =13597-242361-S111-R111 -> -238173 | V111: =SUM(K111:N111) -> -9442 | W111: =SUM(L111:O111) -> 18825 | X111: =SUM(M111:P111) -> -35627 | Y111: =SUM(N111:Q111) -> -76840 | Z111: =SUM(O111:R111) -> -9237 | AA111: =SUM(P111:S111) -> -38441 | AB111: =SUM(Q111:T111) -> -242108 | AD111: =SUM(AB111/X111)-1 -> 5.7956325
B112: Deferred heavy maintenance | C112: -175957 | D112: -75230 | E112: -74083 | F112: -149287 | G112: -202926 | H112: -86412 | J112: -56105 | K112: =-98656-J112 -> -42551 | L112: =-162675-K112-J112 -> -64019 | M112: =SUM(G112-SUM(J112:L112)) -> -40251 | N112: -21110 | O112: =-49224-N112 -> -28114 | P112: =-74739-O112-N112 -> -25515 | Q112: =SUM(H112-SUM(N112:P112)) -> -11673 | R112: =-26736-10639 -> -37375 | S112: =-26736-12345-R112 -> -1706 | T112: =-26736-24735-S112-R112 -> -12390 | V112: =SUM(K112:N112) -> -167931 | W112: =SUM(L112:O112) -> -153494 | X112: =SUM(M112:P112) -> -114990 | Y112: =SUM(N112:Q112) -> -86412 | Z112: =SUM(O112:R112) -> -102677 | AA112: =SUM(P112:S112) -> -76269 | AB112: =SUM(Q112:T112) -> -63144 | AD112: =SUM(AB112/X112)-1 -> -0.45087399
B113: Accounts payable | C113: 569 | D113: -17052 | E113: 13057 | F113: 9032 | G113: -34051 | H113: -40124 | J113: -37048 | K113: =-500-J113 -> 36548 | L113: =9406-K113-J113 -> 9906 | M113: =SUM(G113-SUM(J113:L113)) -> -43457 | N113: 38717 | O113: =-2599-N113 -> -41316 | P113: =-23508-O113-N113 -> -20909 | Q113: =SUM(H113-SUM(N113:P113)) -> -16616 | R113: =14240+54537 -> 68777 | S113: =14240+101000-R113 -> 46463 | T113: =14240+208243-S113-R113 -> 107243 | V113: =SUM(K113:N113) -> 41714 | W113: =SUM(L113:O113) -> -36150 | X113: =SUM(M113:P113) -> -66965 | Y113: =SUM(N113:Q113) -> -40124 | Z113: =SUM(O113:R113) -> -10064 | AA113: =SUM(P113:S113) -> 77715 | AB113: =SUM(Q113:T113) -> 205867 | AD113: =SUM(AB113/X113)-1 -> -4.0742477
B114: Air traffic liability | C114: 23429 | D114: 86558 | E114: -19649 | F114: 47301 | G114: -45867 | H114: 53062 | J114: 137238 | K114: =50059-J114 -> -87179 | L114: =-263-K114-J114 -> -50322 | M114: =SUM(G114-SUM(J114:L114)) -> -45604 | N114: 91902 | O114: =113234-N114 -> 21332 | P114: =75807-O114-N114 -> -37427 | Q114: =SUM(H114-SUM(N114:P114)) -> -22745 | R114: =81855-64147 -> 17708 | S114: =81855-111195-R114 -> -47048 | T114: =81855-144937-S114-R114 -> -33742 | V114: =SUM(K114:N114) -> -91203 | W114: =SUM(L114:O114) -> 17308 | X114: =SUM(M114:P114) -> 30203 | Y114: =SUM(N114:Q114) -> 53062 | Z114: =SUM(O114:R114) -> -21132 | AA114: =SUM(P114:S114) -> -89512 | AB114: =SUM(Q114:T114) -> -85827 | AD114: =SUM(AB114/X114)-1 -> -3.8416714
B115: Other liabilities | C115: 1698 | D115: 27194 | E115: 80103 | F115: 68389 | G115: 176440 | H115: -63688 | J115: 129853 | K115: =119309-J115 -> -10544 | L115: =106769-K115-J115 -> -12540 | M115: =SUM(G115-SUM(J115:L115)) -> 69671 | N115: -121489 | O115: =-110370-N115 -> 11119 | P115: =-109826-O115-N115 -> 544 | Q115: =SUM(H115-SUM(N115:P115)) -> 46138 | R115: =-20165+14516 -> -5649 | S115: =-20165-31906-R115 -> -46422 | T115: =-20165-131476-S115-R115 -> -99570 | V115: =SUM(K115:N115) -> -74902 | W115: =SUM(L115:O115) -> -53239 | X115: =SUM(M115:P115) -> -40155 | Y115: =SUM(N115:Q115) -> -63688 | Z115: =SUM(O115:R115) -> 52152 | AA115: =SUM(P115:S115) -> -5389 | AB115: =SUM(Q115:T115) -> -105503 | AD115: =SUM(AB115/X115)-1 -> 1.6273938
B116: Net cash used in operating activities | C116: =SUM(C96:C115) -> 551321 | D116: =SUM(D96:D115) -> -225274 | E116: =SUM(E96:E115) -> 208888 | F116: =SUM(F96:F115) -> -89022 | G116: =SUM(G96:G115) -> -246661 | H116: =SUM(H96:H115) -> -758087 | J116: =SUM(J96:J115) -> 140777 | K116: =SUM(K96:K115) -> -10065 | L116: =SUM(L96:L115) -> -194598 | M116: =SUM(M96:M115) -> -182775 | N116: =SUM(N96:N115) -> -136975 | O116: =SUM(O96:O115) -> -133018 | P116: =SUM(P96:P115) -> -364299 | Q116: =SUM(Q96:Q115) -> -123795 | ... T116: =SUM(T96:T115) -> -406113 | V116: =SUM(V96:V115) -> -524413 | W116: =SUM(W96:W115) -> -647366 | X116: =SUM(X96:X115) -> -817067 | Y116: =SUM(Y96:Y115) -> -758087 | Z116: =SUM(Z96:Z115) -> -855395 | AA116: =SUM(AA96:AA115) -> -961444 | AB116: =SUM(AB96:AB115) -> -1003258 | AD116: =SUM(AB116/X116)-1 -> 0.22787727
B118: Cash flows from investing activities:
B119: Purchase of property and equipment | C119: -334537 | D119: -393375 | E119: -213767 | F119: -237584 | G119: -255563 | H119: -110955 | J119: -60513 | K119: =-130979-J119 -> -70466 | L119: =-211083-K119-J119 -> -80104 | M119: =SUM(G119-SUM(J119:L119)) -> -44480 | N119: -64338 | O119: =-60551-N119 -> 3787 | P119: =-91754-O119-N119 -> -31203 | Q119: =SUM(H119-SUM(N119:P119)) -> -19201 | R119: =-7204-4154 -> -11358 | S119: =-7204-14081-R119 -> -9927 | T119: =-7204-26007-S119-R119 -> -11926 | V119: =SUM(K119:N119) -> -259388 | W119: =SUM(L119:O119) -> -185135 | X119: =SUM(M119:P119) -> -136234 | Y119: =SUM(N119:Q119) -> -110955 | Z119: =SUM(O119:R119) -> -57975 | AA119: =SUM(P119:S119) -> -71689 | AB119: =SUM(Q119:T119) -> -52412 | AD119: =SUM(AB119/X119)-1 -> -0.61527959
B120: Proceeds from sale of property and equipment | C120: 0 | D120: 0 | E120: 0 | F120: 0 | G120: 230788 | H120: 232564 | J120: 23845 | K120: =36151-J120 -> 12306 | L120: =52466-K120-J120 -> 16315 | M120: =SUM(G120-SUM(J120:L120)) -> 178322 | N120: 138771 | O120: =161581-N120 -> 22810 | P120: =164313-O120-N120 -> 2732 | Q120: =SUM(H120-SUM(N120:P120)) -> 68251 | R120: 0 | S120: 0 | T120: =271261-S120-R120 -> 271261 | V120: =SUM(K120:N120) -> 345714 | W120: =SUM(L120:O120) -> 356218 | X120: =SUM(M120:P120) -> 342635 | Y120: =SUM(N120:Q120) -> 232564 | Z120: =SUM(O120:R120) -> 93793 | AA120: =SUM(P120:S120) -> 70983 | AB120: =SUM(Q120:T120) -> 339512 | AD120: =SUM(AB120/X120)-1 -> -0.0091146555
B121: Proceeds / (Purchase) of available-for-sale investment securities | C121: =-122410+120830 -> -1580 | D121: =-118893+117665 -> -1228 | E121: =-105361+104500 -> -861 | F121: =-110690+109500 -> -1190 | G121: =-127627+125570 -> -2057 | H121: =-161745+160350 -> -1395 | J121: =-20593+20000 -> -593 | K121: =-55610+54410-J121 -> -607 | L121: =-95473+93770-K121-J121 -> -503 | M121: =SUM(G121-SUM(J121:L121)) -> -354 | N121: =58350-58676 -> -326 | O121: =94100-94724-N121 -> -298 | P121: =-132040+131100-O121-N121 -> -316 | Q121: =SUM(H121-SUM(N121:P121)) -> -455 | R121: =24750+8170-25072-8242 -> -394 | S121: =-25072-27996+24750+148186-R121 -> 120262 | T121: =-25072-27996+148186+24750-S121-R121 -> 0 | V121: =SUM(K121:N121) -> -1790 | W121: =SUM(L121:O121) -> -1481 | X121: =SUM(M121:P121) -> -1294 | Y121: =SUM(N121:Q121) -> -1395 | Z121: =SUM(O121:R121) -> -1463 | AA121: =SUM(P121:S121) -> 119097 | AB121: =SUM(Q121:T121) -> 119413 | AD121: =SUM(AB121/X121)-1 -> -93.282071
...

Sheet Revenue Drivers
B2: Netflix, Inc. (NASDAQ: NFLX) | F2: FYE | N2: Quarterly | O2: Quarterly | V2: LTM | Z2: LTM | AB2: LTM | AH2: Variance
B3: Segment Anaysis | C3: ='Historical Financials'!C7 -> 2019 | D3: ='Historical Financials'!D7 -> 2020 | E3: ='Historical Financials'!E7 -> 2021 | F3: ='Historical Financials'!F7 -> 2022 | G3: ='Historical Financials'!G7 -> 2023 | H3: ='Historical Financials'!H7 -> 2024 | J3: ='Historical Financials'!J7 -> 1Q23 | K3: ='Historical Financials'!K7 -> 2Q23 | L3: ='Historical Financials'!L7 -> 3Q23 | M3: ='Historical Financials'!M7 -> 4Q23 | N3: ='Historical Financials'!N7 -> 1Q24 | O3: ='Historical Financials'!O7 -> 2Q24 | P3: ='Historical Financials'!P7 -> 3Q24 | Q3: ='Historical Financials'!Q7 -> 4Q24 | ... T3: ='Historical Financials'!T7 -> 3Q25 | V3: =J3 -> 1Q23 | W3: =K3 -> 2Q23 | X3: =L3 -> 3Q23 | Y3: =M3 -> 4Q23 | Z3: =N3 -> 1Q24 | AA3: =O3 -> 2Q24 | AB3: =P3 -> 3Q24 | AC3: =Q3 -> 4Q24 | ... AF3: =T3 -> 3Q25
B4: $ in thousands except per share | C4: ='Historical Financials'!C8 -> 43830 | D4: ='Historical Financials'!D8 -> 44196 | E4: ='Historical Financials'!E8 -> 44561 | F4: ='Historical Financials'!F8 -> 44926 | G4: ='Historical Financials'!G8 -> 45291 | H4: ='Historical Financials'!H8 -> 45657 | J4: ='Historical Financials'!J8 -> 45016 | K4: ='Historical Financials'!K8 -> 45107 | L4: ='Historical Financials'!L8 -> 45199 | M4: ='Historical Financials'!M8 -> 45291 | N4: ='Historical Financials'!N8 -> 45382 | O4: ='Historical Financials'!O8 -> 45473 | P4: ='Historical Financials'!P8 -> 45565 | Q4: ='Historical Financials'!Q8 -> 45657 | ... T4: ='Historical Financials'!T8 -> 45930 | V4: =J4 -> 45016 | W4: =K4 -> 45107 | X4: =L4 -> 45199 | Y4: =M4 -> 45291 | Z4: =N4 -> 45382 | AA4: =O4 -> 45473 | AB4: =P4 -> 45565 | AC4: =Q4 -> 45657 | ... AF4: =T4 -> 45930
A6: X | B6: Offerings Drivers
B8: Disaggregated Revenues
B9: Passenger | C9: 3757605 | D9: 1765533 | E9: 3175802 | F9: 4989365 | G9: 5268161 | H9: 4811752 | J9: 1327473 | K9: 1410061 | L9: 1233912 | M9: =SUM(G9-SUM(J9:L9)) -> 1296715 | N9: 1239310 | O9: 1253803 | P9: 1171405 | Q9: =SUM(H9-SUM(N9:P9)) -> 1147234 | R9: =740610+252959 -> 993569 | S9: 1000806 | T9: =937126 -> 937126 | V9: =SUM(J9:J9) -> 1327473 | W9: =SUM(J9:K9) -> 2737534 | X9: =SUM(J9:L9) -> 3971446 | Y9: =SUM(J9:M9) -> 5268161 | Z9: =SUM(K9:N9) -> 5179998 | AA9: =SUM(L9:O9) -> 5023740 | AB9: =SUM(M9:P9) -> 4961233 | AC9: =SUM(N9:Q9) -> 4811752 | AD9: =SUM(O9:R9) -> 4566011 | AE9: =SUM(P9:S9) -> 4313014 | AF9: =SUM(Q9:T9) -> 4078735 | AH9: =SUM(AF9/AB9)-1 -> -0.17787877
B10: Other | C10: 72931 | D10: 44489 | E10: 54973 | F10: 79082 | G10: 94388 | H10: 101669 | J10: 22301 | K10: 22411 | L10: 24631 | M10: =SUM(G10-SUM(J10:L10)) -> 25045 | N10: 26227 | O10: 27086 | P10: 25699 | Q10: =SUM(H10-SUM(N10:P10)) -> 22657 | R10: =14744+4086 -> 18830 | S10: 19027 | T10: 21398 | AB10: =SUM(M10:P10) -> 104057 | AC10: =SUM(N10:Q10) -> 101669 | AD10: =SUM(O10:R10) -> 94272 | AE10: =SUM(P10:S10) -> 86213 | AF10: =SUM(Q10:T10) -> 81912 | AH10: =SUM(AF10/AB10)-1 -> -0.21281605
B11: Total Net Revenue | C11: =SUM(C9:C10) -> 3830536 | D11: =SUM(D9:D10) -> 1810022 | E11: =SUM(E9:E10) -> 3230775 | F11: =SUM(F9:F10) -> 5068447 | G11: =SUM(G9:G10) -> 5362549 | H11: =SUM(H9:H10) -> 4913421 | J11: =SUM(J9:J10) -> 1349774 | K11: =SUM(K9:K10) -> 1432472 | L11: =SUM(L9:L10) -> 1258543 | M11: =SUM(M9:M10) -> 1321760 | N11: =SUM(N9:N10) -> 1265537 | O11: =SUM(O9:O10) -> 1280889 | P11: =SUM(P9:P10) -> 1197104 | Q11: =SUM(Q9:Q10) -> 1169891 | ... T11: =SUM(T9:T10) -> 958524 | V11: =SUM(V9:V10) -> 1327473 | W11: =SUM(W9:W10) -> 2737534 | X11: =SUM(X9:X10) -> 3971446 | Y11: =SUM(Y9:Y10) -> 5268161 | Z11: =SUM(Z9:Z10) -> 5179998 | AA11: =SUM(AA9:AA10) -> 5023740 | AB11: =SUM(AB9:AB10) -> 5065290 | AC11: =SUM(AC9:AC10) -> 4913421 | ... AF11: =SUM(AF9:AF10) -> 4160647 | AH11: =SUM(AF11/AB11)-1 -> -0.17859649
B12: Variance Check | C12: =+C11-'Historical Financials'!C11 -> 0 | D12: =+D11-'Historical Financials'!D11 -> 0 | E12: =+E11-'Historical Financials'!E11 -> 0 | F12: =+F11-'Historical Financials'!F11 -> 0 | G12: =+G11-'Historical Financials'!G11 -> 0 | H12: ='Historical Financials'!H11-'Revenue Drivers'!H11 -> 0 | J12: =J11-'Historical Financials'!J11 -> 0 | K12: =K11-'Historical Financials'!K11 -> 0 | L12: =L11-'Historical Financials'!L11 -> 0 | M12: =M11-'Historical Financials'!M11 -> 0 | N12: =N11-'Historical Financials'!N11 -> 0 | O12: =O11-'Historical Financials'!O11 -> 0 | P12: =P11-'Historical Financials'!P11 -> 0 | Q12: =Q11-'Historical Financials'!Q11 -> 0 | ... T12: =T11-'Historical Financials'!T11 -> 0 | V12: =+V11-'Historical Financials'!#REF! -> #REF! | W12: =+W11-'Historical Financials'!#REF! -> #REF! | X12: =+X11-'Historical Financials'!#REF! -> #REF! | Y12: =+Y11-'Historical Financials'!#REF! -> #REF! | Z12: =+Z11-'Historical Financials'!V11 -> -98314 | AA12: =+AA11-'Historical Financials'!W11 -> -102989 | AB12: =+AB11-'Historical Financials'!X11 -> 0 | AC12: =+AC11-'Historical Financials'!Y11 -> 0 | AD12: =+AD11-'Historical Financials'!Z11 -> 0 | AE12: =+AE11-'Historical Financials'!AA11 -> 0 | AF12: =AF11-'Historical Financials'!AB11 -> 0

Sheet FCF
B2: ='Historical Financials'!B2 -> Spirit Airlines, Inc. (NASDAQ: FLYYQ) | C2: FYE | E2: FYE | I2: Quarterly | O2: Quarterly | Z2: LTM | AA2: LTM | AG2: Variance
B3: FCF Analysis | C3: ='Historical Financials'!D7 -> 2020 | D3: ='Historical Financials'!E7 -> 2021 | E3: ='Historical Financials'!F7 -> 2022 | F3: ='Historical Financials'!G7 -> 2023 | G3: ='Historical Financials'!H7 -> 2024 | I3: ='Historical Financials'!J7 -> 1Q23 | J3: ='Historical Financials'!K7 -> 2Q23 | K3: ='Historical Financials'!L7 -> 3Q23 | L3: ='Historical Financials'!M7 -> 4Q23 | M3: ='Historical Financials'!N7 -> 1Q24 | N3: ='Historical Financials'!O7 -> 2Q24 | O3: ='Historical Financials'!P7 -> 3Q24 | P3: ='Historical Financials'!Q7 -> 4Q24 | ... S3: ='Historical Financials'!T7 -> 3Q25 | U3: =I3 -> 1Q23 | V3: =J3 -> 2Q23 | W3: =K3 -> 3Q23 | X3: =L3 -> 4Q23 | Y3: =M3 -> 1Q24 | Z3: =N3 -> 2Q24 | AA3: =O3 -> 3Q24 | AB3: =P3 -> 4Q24 | ... AE3: =S3 -> 3Q25
B4: $ mm except per share | C4: ='Historical Financials'!D8 -> 44196 | D4: ='Historical Financials'!E8 -> 44561 | E4: ='Historical Financials'!F8 -> 44926 | F4: ='Historical Financials'!G8 -> 45291 | G4: ='Historical Financials'!H8 -> 45657 | I4: ='Historical Financials'!J8 -> 45016 | J4: ='Historical Financials'!K8 -> 45107 | K4: ='Historical Financials'!L8 -> 45199 | L4: ='Historical Financials'!M8 -> 45291 | M4: ='Historical Financials'!N8 -> 45382 | N4: ='Historical Financials'!O8 -> 45473 | O4: ='Historical Financials'!P8 -> 45565 | P4: ='Historical Financials'!Q8 -> 45657 | ... S4: ='Historical Financials'!T8 -> 45930 | U4: =I4 -> 45016 | V4: =J4 -> 45107 | W4: =K4 -> 45199 | X4: =L4 -> 45291 | Y4: =M4 -> 45382 | Z4: =N4 -> 45473 | AA4: =O4 -> 45565 | AB4: =P4 -> 45657 | ... AE4: =S4 -> 45930
B6: ='Revenue Drivers'!B9 -> Passenger | C6: ='Revenue Drivers'!D9/1000 -> 1765.533 | D6: ='Revenue Drivers'!E9/1000 -> 3175.802 | E6: ='Revenue Drivers'!F9/1000 -> 4989.365 | F6: ='Revenue Drivers'!G9/1000 -> 5268.161 | G6: ='Revenue Drivers'!H9/1000 -> 4811.752 | I6: ='Revenue Drivers'!J9/1000 -> 1327.473 | J6: ='Revenue Drivers'!K9/1000 -> 1410.061 | K6: ='Revenue Drivers'!L9/1000 -> 1233.912 | L6: ='Revenue Drivers'!M9/1000 -> 1296.715 | M6: ='Revenue Drivers'!N9/1000 -> 1239.31 | N6: ='Revenue Drivers'!O9/1000 -> 1253.803 | O6: ='Revenue Drivers'!P9/1000 -> 1171.405 | P6: ='Revenue Drivers'!Q9/1000 -> 1147.234 | ... S6: ='Revenue Drivers'!T9/1000 -> 937.126 | U6: =SUM(F6:I6) -> 11407.386 | V6: =SUM(G6:J6) -> 7549.286 | W6: =SUM(H6:K6) -> 3971.446 | X6: =SUM(I6:L6) -> 5268.161 | Y6: =SUM(J6:M6) -> 5179.998 | Z6: =SUM(K6:N6) -> 5023.74 | AA6: =SUM(L6:O6) -> 4961.233 | AB6: =SUM(M6:P6) -> 4811.752 | ... AE6: =SUM(P6:S6) -> 4078.735 | AG6: =SUM(AE6/AA6)-1 -> -0.17787877
B7: ='Revenue Drivers'!B10 -> Other | C7: ='Revenue Drivers'!D10/1000 -> 44.489 | D7: ='Revenue Drivers'!E10/1000 -> 54.973 | E7: ='Revenue Drivers'!F10/1000 -> 79.082 | F7: ='Revenue Drivers'!G10/1000 -> 94.388 | G7: ='Revenue Drivers'!H10/1000 -> 101.669 | I7: ='Revenue Drivers'!J10/1000 -> 22.301 | J7: ='Revenue Drivers'!K10/1000 -> 22.411 | K7: ='Revenue Drivers'!L10/1000 -> 24.631 | L7: ='Revenue Drivers'!M10/1000 -> 25.045 | M7: ='Revenue Drivers'!N10/1000 -> 26.227 | N7: ='Revenue Drivers'!O10/1000 -> 27.086 | O7: ='Revenue Drivers'!P10/1000 -> 25.699 | P7: ='Revenue Drivers'!Q10/1000 -> 22.657 | ... S7: ='Revenue Drivers'!T10/1000 -> 21.398 | U7: =SUM(F7:I7) -> 218.358 | V7: =SUM(G7:J7) -> 146.381 | W7: =SUM(H7:K7) -> 69.343 | X7: =SUM(I7:L7) -> 94.388 | Y7: =SUM(J7:M7) -> 98.314 | Z7: =SUM(K7:N7) -> 102.989 | AA7: =SUM(L7:O7) -> 104.057 | AB7: =SUM(M7:P7) -> 101.669 | ... AE7: =SUM(P7:S7) -> 81.912 | AG7: =SUM(AE7/AA7)-1 -> -0.21281605
B8: Total Revenue | C8: =SUM(C6:C7) -> 1810.022 | D8: =SUM(D6:D7) -> 3230.775 | E8: =SUM(E6:E7) -> 5068.447 | F8: =SUM(F6:F7) -> 5362.549 | G8: =SUM(G6:G7) -> 4913.421 | I8: =SUM(I6:I7) -> 1349.774 | J8: =SUM(J6:J7) -> 1432.472 | K8: =SUM(K6:K7) -> 1258.543 | L8: =SUM(L6:L7) -> 1321.76 | M8: =SUM(M6:M7) -> 1265.537 | N8: =SUM(N6:N7) -> 1280.889 | O8: =SUM(O6:O7) -> 1197.104 | P8: =SUM(P6:P7) -> 1169.891 | ... S8: =SUM(S6:S7) -> 958.524 | U8: =SUM(U6:U7) -> 11625.744 | V8: =SUM(V6:V7) -> 7695.667 | W8: =SUM(W6:W7) -> 4040.789 | X8: =SUM(X6:X7) -> 5362.549 | Y8: =SUM(Y6:Y7) -> 5278.312 | Z8: =SUM(Z6:Z7) -> 5126.729 | AA8: =SUM(AA6:AA7) -> 5065.29 | AB8: =SUM(AB6:AB7) -> 4913.421 | ... AE8: =SUM(AE6:AE7) -> 4160.647 | AG8: =SUM(AE8/AA8)-1 -> -0.17859649
B9: Y/Y Growth (%) | D9: =SUM(D8/C8)-1 -> 0.78493687 | E9: =SUM(E8/D8)-1 -> 0.56880222 | F9: =SUM(F8/E8)-1 -> 0.058026058 | G9: =SUM(G8/F8)-1 -> -0.083752708 | M9: =SUM(M8/I8)-1 -> -0.062408225 | N9: =SUM(N8/J8)-1 -> -0.10581917 | O9: =SUM(O8/K8)-1 -> -0.048817561 | P9: =SUM(P8/L8)-1 -> -0.11489907 | Q9: =SUM(Q8/M8)-1 -> -0.20002418 | R9: =SUM(R8/N8)-1 -> -0.20380845 | S9: =SUM(S8/O8)-1 -> -0.19929764 | W9: =SUM(W8/#REF!)-1 -> #REF! | X9: =SUM(X8/#REF!)-1 -> #REF! | Y9: =SUM(Y8/U8)-1 -> -0.54598071 | Z9: =SUM(Z8/V8)-1 -> -0.33381616 | AA9: =SUM(AA8/W8)-1 -> 0.25353984 | AB9: =SUM(AB8/X8)-1 -> -0.083752708 | AC9: =SUM(AC8/Y8)-1 -> -0.11708838 | AD9: =SUM(AD8/Z8)-1 -> -0.14190374 | AE9: =SUM(AE8/AA8)-1 -> -0.17859649 | AG9: =SUM(AE9-AA9)*10000 -> -4321.3633
B10: Q/Q Growth (%) | C10: N/A | D10: N/A | E10: N/A | F10: N/A | G10: N/A | J10: =SUM(J8/I8)-1 -> 0.061268035 | K10: =SUM(K8/J8)-1 -> -0.12141878 | L10: =SUM(L8/K8)-1 -> 0.050230306 | M10: =SUM(M8/L8)-1 -> -0.042536467 | N10: =SUM(N8/M8)-1 -> 0.012130819 | O10: =SUM(O8/N8)-1 -> -0.065411601 | P10: =SUM(P8/O8)-1 -> -0.022732361 | Q10: =SUM(Q8/P8)-1 -> -0.13462109 | ... S10: =SUM(S8/R8)-1 -> -0.060116705 | U10: N/A | V10: N/A | W10: N/A | X10: N/A | Y10: N/A | Z10: N/A | AA10: N/A | AB10: N/A | AC10: N/A | AD10: N/A | AE10: N/A
B13: (-) Salaries, wages and benefits | C13: ='Historical Financials'!D13/1000 -> -909.834 | D13: ='Historical Financials'!E13/1000 -> -1065.461 | E13: ='Historical Financials'!F13/1000 -> -1251.225 | F13: ='Historical Financials'!G13/1000 -> -1616.803 | G13: ='Historical Financials'!H13/1000 -> -1689.083 | I13: ='Historical Financials'!J13/1000 -> -389.185 | J13: ='Historical Financials'!K13/1000 -> -407.705 | K13: ='Historical Financials'!L13/1000 -> -404.177 | L13: ='Historical Financials'!M13/1000 -> -415.736 | M13: ='Historical Financials'!N13/1000 -> -431.483 | N13: ='Historical Financials'!O13/1000 -> -418.378 | O13: ='Historical Financials'!P13/1000 -> -427.125 | P13: ='Historical Financials'!Q13/1000 -> -412.097 | ... S13: ='Historical Financials'!T13/1000 -> -367.356 | U13: =SUM(F13:I13) -> -3695.071 | V13: =SUM(G13:J13) -> -2485.973 | W13: =SUM(H13:K13) -> -1201.067 | X13: =SUM(I13:L13) -> -1616.803 | Y13: =SUM(J13:M13) -> -1659.101 | Z13: =SUM(K13:N13) -> -1669.774 | AA13: =SUM(L13:O13) -> -1692.722 | AB13: =SUM(M13:P13) -> -1689.083 | ... AE13: =SUM(P13:S13) -> -1531.611 | AG13: =SUM(AE13/AA13)-1 -> -0.095178653
B14: (-) Aircraft fuel | C14: ='Historical Financials'!D14/1000 -> -431 | D14: ='Historical Financials'!E14/1000 -> -913.945 | E14: ='Historical Financials'!F14/1000 -> -1929.969 | F14: ='Historical Financials'!G14/1000 -> -1821.165 | G14: ='Historical Financials'!H14/1000 -> -1479.203 | I14: ='Historical Financials'!J14/1000 -> -487.711 | J14: ='Historical Financials'!K14/1000 -> -391.032 | K14: ='Historical Financials'!L14/1000 -> -455.241 | L14: ='Historical Financials'!M14/1000 -> -487.181 | M14: ='Historical Financials'!N14/1000 -> -406.351 | N14: ='Historical Financials'!O14/1000 -> -407.296 | O14: ='Historical Financials'!P14/1000 -> -373.399 | P14: ='Historical Financials'!Q14/1000 -> -292.157 | ... S14: ='Historical Financials'!T14/1000 -> -253.308 | U14: =SUM(F14:I14) -> -3788.079 | V14: =SUM(G14:J14) -> -2357.946 | W14: =SUM(H14:K14) -> -1333.984 | X14: =SUM(I14:L14) -> -1821.165 | Y14: =SUM(J14:M14) -> -1739.805 | Z14: =SUM(K14:N14) -> -1756.069 | AA14: =SUM(L14:O14) -> -1674.227 | AB14: =SUM(M14:P14) -> -1479.203 | ... AE14: =SUM(P14:S14) -> -1086.67 | AG14: =SUM(AE14/AA14)-1 -> -0.35094226
B15: (-) Aircraft rent | C15: ='Historical Financials'!D15/1000 -> -196.359 | D15: ='Historical Financials'!E15/1000 -> -246.601 | E15: ='Historical Financials'!F15/1000 -> -282.428 | F15: ='Historical Financials'!G15/1000 -> -381.239 | G15: ='Historical Financials'!H15/1000 -> -541.909 | I15: ='Historical Financials'!J15/1000 -> -85.267 | J15: ='Historical Financials'!K15/1000 -> -92.101 | K15: ='Historical Financials'!L15/1000 -> -97.393 | L15: ='Historical Financials'!M15/1000 -> -106.478 | M15: ='Historical Financials'!N15/1000 -> -115.206 | N15: ='Historical Financials'!O15/1000 -> -125.339 | O15: ='Historical Financials'!P15/1000 -> -148.511 | P15: ='Historical Financials'!Q15/1000 -> -152.853 | ... S15: ='Historical Financials'!T15/1000 -> -154.064 | U15: =SUM(F15:I15) -> -1008.415 | V15: =SUM(G15:J15) -> -719.277 | W15: =SUM(H15:K15) -> -274.761 | X15: =SUM(I15:L15) -> -381.239 | Y15: =SUM(J15:M15) -> -411.178 | Z15: =SUM(K15:N15) -> -444.416 | AA15: =SUM(L15:O15) -> -495.534 | AB15: =SUM(M15:P15) -> -541.909 | ... AE15: =SUM(P15:S15) -> -598.677 | AG15: =SUM(AE15/AA15)-1 -> 0.20814515
B16: (-) Landing fees and other rents | C16: ='Historical Financials'!D16/1000 -> -251.028 | D16: ='Historical Financials'!E16/1000 -> -315.999 | E16: ='Historical Financials'!F16/1000 -> -347.268 | F16: ='Historical Financials'!G16/1000 -> -408.262 | G16: ='Historical Financials'!H16/1000 -> -451.008 | I16: ='Historical Financials'!J16/1000 -> -97.345 | J16: ='Historical Financials'!K16/1000 -> -106.487 | K16: ='Historical Financials'!L16/1000 -> -107.525 | L16: ='Historical Financials'!M16/1000 -> -96.905 | M16: ='Historical Financials'!N16/1000 -> -106.718 | N16: ='Historical Financials'!O16/1000 -> -116.064 | O16: ='Historical Financials'!P16/1000 -> -130.044 | P16: ='Historical Financials'!Q16/1000 -> -98.182 | ... S16: ='Historical Financials'!T16/1000 -> -104.9 | U16: =SUM(F16:I16) -> -956.615 | V16: =SUM(G16:J16) -> -654.84 | W16: =SUM(H16:K16) -> -311.357 | X16: =SUM(I16:L16) -> -408.262 | Y16: =SUM(J16:M16) -> -417.635 | Z16: =SUM(K16:N16) -> -427.212 | AA16: =SUM(L16:O16) -> -449.731 | AB16: =SUM(M16:P16) -> -451.008 | ... AE16: =SUM(P16:S16) -> -412.484 | AG16: =SUM(AE16/AA16)-1 -> -0.082820619
B17: (-) Depreciation and amortization | C17: ='Historical Financials'!D17/1000 -> -278.588 | D17: ='Historical Financials'!E17/1000 -> -297.211 | E17: ='Historical Financials'!F17/1000 -> -313.09 | F17: ='Historical Financials'!G17/1000 -> -320.872 | G17: ='Historical Financials'!H17/1000 -> -325.273 | I17: ='Historical Financials'!J17/1000 -> -77.991 | J17: ='Historical Financials'!K17/1000 -> -80.542 | K17: ='Historical Financials'!L17/1000 -> -82.802 | L17: ='Historical Financials'!M17/1000 -> -79.537 | M17: ='Historical Financials'!N17/1000 -> -81.346 | N17: ='Historical Financials'!O17/1000 -> -84.486 | O17: ='Historical Financials'!P17/1000 -> -84.028 | P17: ='Historical Financials'!Q17/1000 -> -75.413 | ... S17: ='Historical Financials'!T17/1000 -> -58.032 | U17: =SUM(F17:I17) -> -724.136 | V17: =SUM(G17:J17) -> -483.806 | W17: =SUM(H17:K17) -> -241.335 | X17: =SUM(I17:L17) -> -320.872 | Y17: =SUM(J17:M17) -> -324.227 | Z17: =SUM(K17:N17) -> -328.171 | AA17: =SUM(L17:O17) -> -329.397 | AB17: =SUM(M17:P17) -> -325.273 | ... AE17: =SUM(P17:S17) -> -262.781 | AG17: =SUM(AE17/AA17)-1 -> -0.20223621
B18: (-) Maintenance, materials and repairs | C18: ='Historical Financials'!D18/1000 -> -111.227 | D18: ='Historical Financials'!E18/1000 -> -159.502 | E18: ='Historical Financials'!F18/1000 -> -187.82 | F18: ='Historical Financials'!G18/1000 -> -223.339 | G18: ='Historical Financials'!H18/1000 -> -217.738 | I18: ='Historical Financials'!J18/1000 -> -54.414 | J18: ='Historical Financials'!K18/1000 -> -56.825 | K18: ='Historical Financials'!L18/1000 -> -56.465 | L18: ='Historical Financials'!M18/1000 -> -55.635 | M18: ='Historical Financials'!N18/1000 -> -54.915 | N18: ='Historical Financials'!O18/1000 -> -52.453 | O18: ='Historical Financials'!P18/1000 -> -57.368 | P18: ='Historical Financials'!Q18/1000 -> -53.002 | ... S18: ='Historical Financials'!T18/1000 -> -54.849 | U18: =SUM(F18:I18) -> -495.491 | V18: =SUM(G18:J18) -> -328.977 | W18: =SUM(H18:K18) -> -167.704 | X18: =SUM(I18:L18) -> -223.339 | Y18: =SUM(J18:M18) -> -223.84 | Z18: =SUM(K18:N18) -> -219.468 | AA18: =SUM(L18:O18) -> -220.371 | AB18: =SUM(M18:P18) -> -217.738 | ... AE18: =SUM(P18:S18) -> -215.305 | AG18: =SUM(AE18/AA18)-1 -> -0.022988506
B19: (-) Distribution | C19: ='Historical Financials'!D19/1000 -> -85.059 | D19: ='Historical Financials'!E19/1000 -> -132.499 | E19: ='Historical Financials'!F19/1000 -> -177.557 | F19: ='Historical Financials'!G19/1000 -> -190.891 | G19: ='Historical Financials'!H19/1000 -> -197.197 | I19: ='Historical Financials'!J19/1000 -> -48.017 | J19: ='Historical Financials'!K19/1000 -> -50.701 | K19: ='Historical Financials'!L19/1000 -> -46.323 | L19: ='Historical Financials'!M19/1000 -> -45.85 | M19: ='Historical Financials'!N19/1000 -> -45.176 | N19: ='Historical Financials'!O19/1000 -> -45.923 | O19: ='Historical Financials'!P19/1000 -> -55.687 | P19: ='Historical Financials'!Q19/1000 -> -50.411 | ... S19: ='Historical Financials'!T19/1000 -> -45.833 | U19: =SUM(F19:I19) -> -436.105 | V19: =SUM(G19:J19) -> -295.915 | W19: =SUM(H19:K19) -> -145.041 | X19: =SUM(I19:L19) -> -190.891 | Y19: =SUM(J19:M19) -> -188.05 | Z19: =SUM(K19:N19) -> -183.272 | AA19: =SUM(L19:O19) -> -192.636 | AB19: =SUM(M19:P19) -> -197.197 | ... AE19: =SUM(P19:S19) -> -193.276 | AG19: =SUM(AE19/AA19)-1 -> 0.0033223281
B20: (-) Special Credits (Charges) | C20: ='Historical Financials'!D20/1000 -> 302.761 | D20: ='Historical Financials'!E20/1000 -> 377.715 | E20: ='Historical Financials'!F20/1000 -> -420.172 | F20: ='Historical Financials'!G20/1000 -> -69.537 | G20: ='Historical Financials'!H20/1000 -> -36.029 | I20: ='Historical Financials'!J20/1000 -> -13.983 | J20: ='Historical Financials'!K20/1000 -> -19.972 | K20: ='Historical Financials'!L20/1000 -> -12.378 | L20: ='Historical Financials'!M20/1000 -> -23.204 | M20: ='Historical Financials'!N20/1000 -> -36.258 | N20: ='Historical Financials'!O20/1000 -> 0.381 | O20: ='Historical Financials'!P20/1000 -> -0.151 | P20: ='Historical Financials'!Q20/1000 -> -0.001 | ... S20: ='Historical Financials'!T20/1000 -> 0 | U20: =SUM(F20:I20) -> -119.549 | V20: =SUM(G20:J20) -> -69.984 | W20: =SUM(H20:K20) -> -46.333 | X20: =SUM(I20:L20) -> -69.537 | Y20: =SUM(J20:M20) -> -91.812 | Z20: =SUM(K20:N20) -> -71.459 | AA20: =SUM(L20:O20) -> -59.232 | AB20: =SUM(M20:P20) -> -36.029 | ... AE20: =SUM(P20:S20) -> 0.003 | AG20: =SUM(AE20/AA20)-1 -> -1.0000506
B21: (-) Gains (Losses) on disposal of assets | C21: ='Historical Financials'!D21/1000 -> -2.264 | D21: ='Historical Financials'!E21/1000 -> -3.32 | E21: ='Historical Financials'!F21/1000 -> -46.624 | F21: ='Historical Financials'!G21/1000 -> -33.966 | G21: ='Historical Financials'!H21/1000 -> -273.871 | I21: ='Historical Financials'!J21/1000 -> -7.1 | J21: ='Historical Financials'!K21/1000 -> -0.802 | K21: ='Historical Financials'!L21/1000 -> 2.25 | L21: ='Historical Financials'!M21/1000 -> -28.314 | M21: ='Historical Financials'!N21/1000 -> 3.029 | N21: ='Historical Financials'!O21/1000 -> 14.047 | O21: ='Historical Financials'!P21/1000 -> -3.191 | P21: ='Historical Financials'!Q21/1000 -> -287.756 | ... S21: ='Historical Financials'!T21/1000 -> 113.713 | U21: =SUM(F21:I21) -> -314.937 | V21: =SUM(G21:J21) -> -281.773 | W21: =SUM(H21:K21) -> -5.652 | X21: =SUM(I21:L21) -> -33.966 | Y21: =SUM(J21:M21) -> -23.837 | Z21: =SUM(K21:N21) -> -8.988 | AA21: =SUM(L21:O21) -> -14.429 | AB21: =SUM(M21:P21) -> -273.871 | ... AE21: =SUM(P21:S21) -> -185.37 | AG21: =SUM(AE21/AA21)-1 -> 11.847044
B22: (-) Other Operating Expenses | C22: ='Historical Financials'!D22/1000 -> -355.186 | D22: ='Historical Financials'!E22/1000 -> -530.826 | E22: ='Historical Financials'!F22/1000 -> -711.211 | F22: ='Historical Financials'!G22/1000 -> -792.232 | G22: ='Historical Financials'!H22/1000 -> -807.488 | I22: ='Historical Financials'!J22/1000 -> -201.156 | J22: ='Historical Financials'!K22/1000 -> -206.094 | K22: ='Historical Financials'!L22/1000 -> -187.249 | L22: ='Historical Financials'!M22/1000 -> -197.733 | M22: ='Historical Financials'!N22/1000 -> -198.45 | N22: ='Historical Financials'!O22/1000 -> -197.89 | O22: ='Historical Financials'!P22/1000 -> -214.039 | P22: ='Historical Financials'!Q22/1000 -> -197.109 | ... S22: ='Historical Financials'!T22/1000 -> -168.81 | U22: =SUM(F22:I22) -> -1800.876 | V22: =SUM(G22:J22) -> -1214.738 | W22: =SUM(H22:K22) -> -594.499 | X22: =SUM(I22:L22) -> -792.232 | Y22: =SUM(J22:M22) -> -789.526 | Z22: =SUM(K22:N22) -> -781.322 | AA22: =SUM(L22:O22) -> -808.112 | AB22: =SUM(M22:P22) -> -807.488 | ... AE22: =SUM(P22:S22) -> -731.76 | AG22: =SUM(AE22/AA22)-1 -> -0.094481953
B23: Earning before Interest & Taxes (EBIT) | C23: =SUM(C8+SUM(C13:C22)) -> -507.762 | D23: =SUM(D8+SUM(D13:D22)) -> -56.874 | E23: =SUM(E8+SUM(E13:E22)) -> -598.917 | F23: =SUM(F8+SUM(F13:F22)) -> -495.757 | G23: =SUM(G8+SUM(G13:G22)) -> -1105.378 | I23: =SUM(I8+SUM(I13:I22)) -> -112.395 | J23: =SUM(J8+SUM(J13:J22)) -> 20.211 | K23: =SUM(K8+SUM(K13:K22)) -> -188.76 | L23: =SUM(L8+SUM(L13:L22)) -> -214.813 | M23: =SUM(M8+SUM(M13:M22)) -> -207.337 | N23: =SUM(N8+SUM(N13:N22)) -> -152.512 | O23: =SUM(O8+SUM(O13:O22)) -> -296.439 | P23: =SUM(P8+SUM(P13:P22)) -> -449.09 | ... S23: =SUM(S8+SUM(S13:S22)) -> -134.915 | U23: =SUM(U8+SUM(U13:U22)) -> -1713.53 | V23: =SUM(V8+SUM(V13:V22)) -> -1197.562 | W23: =SUM(W8+SUM(W13:W22)) -> -280.944 | X23: =SUM(X8+SUM(X13:X22)) -> -495.757 | Y23: =SUM(Y8+SUM(Y13:Y22)) -> -590.699 | Z23: =SUM(Z8+SUM(Z13:Z22)) -> -763.422 | AA23: =SUM(AA8+SUM(AA13:AA22)) -> -871.101 | AB23: =SUM(AB8+SUM(AB13:AB22)) -> -1105.378 | ... AE23: =SUM(AE8+SUM(AE13:AE22)) -> -1057.284 | AG23: =SUM(AE23/AA23)-1 -> 0.21373297
B24: Operating Margin (%) | C24: =C23/C8 -> -0.28052808 | D24: =D23/D8 -> -0.017603826 | E24: =E23/E8 -> -0.11816578 | F24: =F23/F8 -> -0.092448013 | G24: =G23/G8 -> -0.22497116 | I24: =I23/I8 -> -0.083269495 | J24: =J23/J8 -> 0.014109176 | K24: =K23/K8 -> -0.14998296 | L24: =L23/L8 -> -0.16252043 | M24: =M23/M8 -> -0.16383322 | N24: =N23/N8 -> -0.1190673 | O24: =O23/O8 -> -0.24763011 | P24: =P23/P8 -> -0.38387337 | ... S24: =S23/S8 -> -0.14075287 | U24: =U23/U8 -> -0.147391 | V24: =V23/V8 -> -0.1556151 | W24: =W23/W8 -> -0.069527016 | X24: =X23/X8 -> -0.092448013 | Y24: =Y23/Y8 -> -0.11191059 | Z24: =Z23/Z8 -> -0.14891015 | AA24: =AA23/AA8 -> -0.17197456 | AB24: =AB23/AB8 -> -0.22497116 | ... AE24: =AE23/AE8 -> -0.25411529 | AG24: =SUM(AE24-AA24)*10000 -> -821.40729
B26: (+) Depreciation and Amortization (D&A) | C26: =-C17 -> 278.588 | D26: =-D17 -> 297.211 | E26: =-E17 -> 313.09 | F26: =-F17 -> 320.872 | G26: =-G17 -> 325.273 | I26: =-I17 -> 77.991 | J26: =-J17 -> 80.542 | K26: =-K17 -> 82.802 | L26: =-L17 -> 79.537 | M26: =-M17 -> 81.346 | N26: =-N17 -> 84.486 | O26: =-O17 -> 84.028 | P26: =-P17 -> 75.413 | ... S26: =-S17 -> 58.032 | U26: =SUM(I26:I26) -> 77.991 | V26: =SUM(I26:J26) -> 158.533 | W26: =SUM(I26:K26) -> 241.335 | X26: =SUM(I26:L26) -> 320.872 | Y26: =SUM(J26:M26) -> 324.227 | Z26: =SUM(K26:N26) -> 328.171 | AA26: =SUM(L26:O26) -> 329.397 | AB26: =SUM(M26:P26) -> 325.273 | AC26: =SUM(N26:Q26) -> 310.377 | AD26: =SUM(O26:R26) -> 288.777 | AE26: =SUM(P26:S26) -> 262.781 | AG26: =SUM(AE26/AA26)-1 -> -0.20223621
B27: EBITDA | C27: =SUM(C23+SUM(C26:C26)) -> -229.174 | D27: =SUM(D23+SUM(D26:D26)) -> 240.337 | E27: =SUM(E23+SUM(E26:E26)) -> -285.827 | F27: =SUM(F23+SUM(F26:F26)) -> -174.885 | G27: =SUM(G23+SUM(G26:G26)) -> -780.105 | I27: =SUM(I23+SUM(I26:I26)) -> -34.404 | J27: =SUM(J23+SUM(J26:J26)) -> 100.753 | K27: =SUM(K23+SUM(K26:K26)) -> -105.958 | L27: =SUM(L23+SUM(L26:L26)) -> -135.276 | M27: =SUM(M23+SUM(M26:M26)) -> -125.991 | N27: =SUM(N23+SUM(N26:N26)) -> -68.026 | O27: =SUM(O23+SUM(O26:O26)) -> -212.411 | P27: =SUM(P23+SUM(P26:P26)) -> -373.677 | ... S27: =SUM(S23+SUM(S26:S26)) -> -76.883 | U27: =SUM(U23+SUM(U26:U26)) -> -1635.539 | V27: =SUM(V23+SUM(V26:V26)) -> -1039.029 | W27: =SUM(W23+SUM(W26:W26)) -> -39.609 | X27: =SUM(X23+SUM(X26:X26)) -> -174.885 | Y27: =SUM(Y23+SUM(Y26:Y26)) -> -266.472 | Z27: =SUM(Z23+SUM(Z26:Z26)) -> -435.251 | AA27: =SUM(AA23+SUM(AA26:AA26)) -> -541.704 | AB27: =SUM(AB23+SUM(AB26:AB26)) -> -780.105 | ... AE27: =SUM(AE23+SUM(AE26:AE26)) -> -794.503 | AG27: =SUM(AE27/AA27)-1 -> 0.46667368
B28: EBITDA Margin (%) | C28: =C27/C8 -> -0.12661393 | D28: =D27/D8 -> 0.074389891 | E28: =E27/E8 -> -0.056393408 | F28: =F27/F8 -> -0.032612289 | G28: =G27/G8 -> -0.15877023 | I28: =I27/I8 -> -0.025488711 | J28: =J27/J8 -> 0.070335057 | K28: =K27/K8 -> -0.084191005 | L28: =L27/L8 -> -0.10234536 | M28: =M27/M8 -> -0.099555367 | N28: =N27/N8 -> -0.053108427 | O28: =O27/O8 -> -0.17743738 | P28: =P27/P8 -> -0.31941181 | ... S28: =S27/S8 -> -0.080209781 | U28: =U27/U8 -> -0.14068252 | V28: =V27/V8 -> -0.13501481 | W28: =W27/W8 -> -0.0098022936 | X28: =X27/X8 -> -0.032612289 | Y28: =Y27/Y8 -> -0.050484322 | Z28: =Z27/Z8 -> -0.084898383 | AA28: =AA27/AA8 -> -0.10694432 | AB28: =AB27/AB8 -> -0.15877023 | ... AE28: =AE27/AE8 -> -0.1909566 | AG28: =SUM(AE28-AA28)*10000 -> -840.12278
B30: (+) Share-based Compensation | C30: ='Historical Financials'!D100/1000 -> 11.575 | D30: ='Historical Financials'!E100/1000 -> 12.536 | E30: ='Historical Financials'!F100/1000 -> 11.483 | F30: ='Historical Financials'!G100/1000 -> 11.963 | G30: ='Historical Financials'!H100/1000 -> 7.21 | I30: ='Historical Financials'!J100/1000 -> 3.273 | J30: ='Historical Financials'!K100/1000 -> 3.48 | K30: ='Historical Financials'!L100/1000 -> 2.569 | L30: ='Historical Financials'!M100/1000 -> 2.641 | M30: ='Historical Financials'!N100/1000 -> 3.08 | N30: ='Historical Financials'!O100/1000 -> 0.342 | O30: ='Historical Financials'!P100/1000 -> 1.952 | P30: ='Historical Financials'!Q100/1000 -> 1.836 | ... S30: ='Historical Financials'!T100/1000 -> 2.522 | U30: =SUM(F30:I30) -> 22.446 | V30: =SUM(G30:J30) -> 13.963 | W30: =SUM(H30:K30) -> 9.322 | X30: =SUM(I30:L30) -> 11.963 | Y30: =SUM(J30:M30) -> 11.77 | Z30: =SUM(K30:N30) -> 8.632 | AA30: =SUM(L30:O30) -> 8.015 | AB30: =SUM(M30:P30) -> 7.21 | ... AE30: =SUM(P30:S30) -> 7.435 | AG30: =SUM(AE30/AA30)-1 -> -0.072364317
B31: (+) Special Charges / (Credits) | C31: =-C20 -> -302.761 | D31: =-D20 -> -377.715 | E31: =-E20 -> 420.172 | F31: =-F20 -> 69.537 | G31: =-G20 -> 36.029 | I31: =-I20 -> 13.983 | J31: =-J20 -> 19.972 | K31: =-K20 -> 12.378 | L31: =-L20 -> 23.204 | M31: =-M20 -> 36.258 | N31: =-N20 -> -0.381 | O31: =-O20 -> 0.151 | P31: =-P20 -> 0.001 | ... S31: =-S20 -> 0 | U31: =SUM(F31:I31) -> 119.549 | V31: =SUM(G31:J31) -> 69.984 | W31: =SUM(H31:K31) -> 46.333 | X31: =SUM(I31:L31) -> 69.537 | Y31: =SUM(J31:M31) -> 91.812 | Z31: =SUM(K31:N31) -> 71.459 | AA31: =SUM(L31:O31) -> 59.232 | AB31: =SUM(M31:P31) -> 36.029 | ... AE31: =SUM(P31:S31) -> -0.003 | AG31: =SUM(AE31/AA31)-1 -> -1.0000506
B32: (+) Gains (Losses) on Disposal of Assets | C32: =-C21 -> 2.264 | D32: =-D21 -> 3.32 | E32: =-E21 -> 46.624 | F32: =-F21 -> 33.966 | G32: =-G21 -> 273.871 | I32: =-I21 -> 7.1 | J32: =-J21 -> 0.802 | K32: =-K21 -> -2.25 | L32: =-L21 -> 28.314 | M32: =-M21 -> -3.029 | N32: =-N21 -> -14.047 | O32: =-O21 -> 3.191 | P32: =-P21 -> 287.756 | ... S32: =-S21 -> -113.713 | U32: =SUM(F32:I32) -> 314.937 | V32: =SUM(G32:J32) -> 281.773 | W32: =SUM(H32:K32) -> 5.652 | X32: =SUM(I32:L32) -> 33.966 | Y32: =SUM(J32:M32) -> 23.837 | Z32: =SUM(K32:N32) -> 8.988 | AA32: =SUM(L32:O32) -> 14.429 | AB32: =SUM(M32:P32) -> 273.871 | ... AE32: =SUM(P32:S32) -> 185.37 | AG32: =SUM(AE32/AA32)-1 -> 11.847044
B33: Adj. EBITDA | C33: =+SUM(C27+SUM(C30:C32)) -> -518.096 | D33: =+SUM(D27+SUM(D30:D32)) -> -121.522 | E33: =+SUM(E27+SUM(E30:E32)) -> 192.452 | F33: =+SUM(F27+SUM(F30:F32)) -> -59.419 | G33: =+SUM(G27+SUM(G30:G32)) -> -462.995 | I33: =+SUM(I27+SUM(I30:I32)) -> -10.048 | J33: =+SUM(J27+SUM(J30:J32)) -> 125.007 | K33: =+SUM(K27+SUM(K30:K32)) -> -93.261 | L33: =+SUM(L27+SUM(L30:L32)) -> -81.117 | M33: =+SUM(M27+SUM(M30:M32)) -> -89.682 | N33: =+SUM(N27+SUM(N30:N32)) -> -82.112 | O33: =+SUM(O27+SUM(O30:O32)) -> -207.117 | P33: =+SUM(P27+SUM(P30:P32)) -> -84.084 | ... S33: =+SUM(S27+SUM(S30:S32)) -> -188.074 | U33: =+SUM(U27+SUM(U30:U30)) -> -1613.093 | V33: =+SUM(V27+SUM(V30:V30)) -> -1025.066 | W33: =+SUM(W27+SUM(W30:W30)) -> -30.287 | X33: =+SUM(X27+SUM(X30:X30)) -> -162.922 | Y33: =+SUM(Y27+SUM(Y30:Y30)) -> -254.702 | Z33: =+SUM(Z27+SUM(Z30:Z30)) -> -426.619 | AA33: =+SUM(AA27+SUM(AA30:AA32)) -> -460.028 | AB33: =+SUM(AB27+SUM(AB30:AB32)) -> -462.995 | AC33: =+SUM(AC27+SUM(AC30:AC32)) -> -583.154 | AD33: =+SUM(AD27+SUM(AD30:AD32)) -> -620.744 | AE33: =+SUM(AE27+SUM(AE30:AE32)) -> -601.701 | AG33: =SUM(AE33/AA33)-1 -> 0.30796604
B34: Adj. EBITDA Margin (%) | C34: =C33/C8 -> -0.2862374 | D34: =D33/D8 -> -0.037613885 | E34: =E33/E8 -> 0.037970605 | F34: =F33/F8 -> -0.011080365 | G34: =G33/G8 -> -0.09423068 | I34: =I33/I8 -> -0.0074442092 | J34: =J33/J8 -> 0.087266627 | K34: =K33/K8 -> -0.074102355 | L34: =L33/L8 -> -0.061370445 | M34: =M33/M8 -> -0.070864779 | N34: =N33/N8 -> -0.064105477 | O34: =O33/O8 -> -0.17301504 | P34: =P33/P8 -> -0.071873363 | ... S34: =S33/S8 -> -0.19621209 | U34: =U33/U8 -> -0.13875181 | V34: =V33/V8 -> -0.13320041 | W34: =W33/W8 -> -0.0074953184 | X34: =X33/X8 -> -0.030381447 | Y34: =Y33/Y8 -> -0.048254442 | Z34: =Z33/Z8 -> -0.083214658 | AA34: =AA33/AA8 -> -0.090819677 | AB34: =AB33/AB8 -> -0.09423068 | ... AE34: =AE33/AE8 -> -0.14461717 | AG34: =SUM(AE34-AA34)*10000 -> -537.97495
B36: (-) Capital Expenditures | C36: ='Historical Financials'!D119/1000 -> -393.375 | D36: ='Historical Financials'!E119/1000 -> -213.767 | E36: ='Historical Financials'!F119/1000 -> -237.584 | F36: ='Historical Financials'!G119/1000 -> -255.563 | G36: ='Historical Financials'!H119/1000 -> -110.955 | I36: ='Historical Financials'!J119/1000 -> -60.513 | J36: ='Historical Financials'!K119/1000 -> -70.466 | K36: ='Historical Financials'!L119/1000 -> -80.104 | L36: ='Historical Financials'!M119/1000 -> -44.48 | M36: ='Historical Financials'!N119/1000 -> -64.338 | N36: ='Historical Financials'!O119/1000 -> 3.787 | O36: ='Historical Financials'!P119/1000 -> -31.203 | P36: ='Historical Financials'!Q119/1000 -> -19.201 | ... S36: ='Historical Financials'!T119/1000 -> -11.926 | U36: =SUM(I36:I36) -> -60.513 | V36: =SUM(I36:J36) -> -130.979 | W36: =SUM(I36:K36) -> -211.083 | X36: =SUM(I36:L36) -> -255.563 | Y36: =SUM(J36:M36) -> -259.388 | Z36: =SUM(K36:N36) -> -185.135 | AA36: =SUM(L36:O36) -> -136.234 | AB36: =SUM(M36:P36) -> -110.955 | AC36: =SUM(N36:Q36) -> -57.975 | AD36: =SUM(O36:R36) -> -71.689 | AE36: =SUM(P36:S36) -> -52.412 | AG36: =SUM(AE36/AA36)-1 -> -0.61527959
B37: (-) Cash Taxes | C37: =-'Historical Financials'!D149/1000 -> 17.79 | D37: =-'Historical Financials'!E149/1000 -> 112.461 | E37: =-'Historical Financials'!F149/1000 -> 0.082 | F37: =-'Historical Financials'!G149/1000 -> 32.854 | G37: =-'Historical Financials'!H149/1000 -> -3.548 | I37: =-'Historical Financials'!J149/1000 -> -0.466 | J37: =-'Historical Financials'!K149/1000 -> -0.731 | K37: =-'Historical Financials'!L149/1000 -> 33.921 | L37: =-'Historical Financials'!M149/1000 -> 0.13 | M37: =-'Historical Financials'!N149/1000 -> -0.007 | N37: =-'Historical Financials'!O149/1000 -> -7.043 | O37: =-'Historical Financials'!P149/1000 -> -0.334 | P37: =-'Historical Financials'!Q149/1000 -> 3.836 | ... S37: =-'Historical Financials'!T149/1000 -> 0.092 | U37: =SUM(I37:I37) -> -0.466 | V37: =SUM(I37:J37) -> -1.197 | W37: =SUM(I37:K37) -> 32.724 | X37: =SUM(I37:L37) -> 32.854 | Y37: =SUM(J37:M37) -> 33.313 | Z37: =SUM(K37:N37) -> 27.001 | AA37: =SUM(L37:O37) -> -7.254 | AB37: =SUM(M37:P37) -> -3.548 | AC37: =SUM(N37:Q37) -> -3.809 | AD37: =SUM(O37:R37) -> 1.938 | AE37: =SUM(P37:S37) -> 2.364 | AG37: =SUM(AE37/AA37)-1 -> -1.3258892
B38: (-) Cash Interest | C38: =-'Historical Financials'!D148/1000 -> -80.837 | D38: =-'Historical Financials'!E148/1000 -> -135.5 | E38: =-'Historical Financials'!F148/1000 -> -107.443 | F38: =-'Historical Financials'!G148/1000 -> -138.38 | G38: =-'Historical Financials'!H148/1000 -> -176.187 | I38: =-'Historical Financials'!J148/1000 -> -31.999 | J38: =-'Historical Financials'!K148/1000 -> -37.467 | K38: =-'Historical Financials'!L148/1000 -> -32.263 | L38: =-'Historical Financials'!M148/1000 -> -36.651 | M38: =-'Historical Financials'!N148/1000 -> -39.897 | N38: =-'Historical Financials'!O148/1000 -> -43.774 | O38: =-'Historical Financials'!P148/1000 -> -42.456 | P38: =-'Historical Financials'!Q148/1000 -> -50.06 | ... S38: =-'Historical Financials'!T148/1000 -> -39.059 | U38: =SUM(I38:I38) -> -31.999 | V38: =SUM(I38:J38) -> -69.466 | W38: =SUM(I38:K38) -> -101.729 | X38: =SUM(I38:L38) -> -138.38 | Y38: =SUM(J38:M38) -> -146.278 | Z38: =SUM(K38:N38) -> -152.585 | AA38: =SUM(L38:O38) -> -162.778 | AB38: =SUM(M38:P38) -> -176.187 | AC38: =SUM(N38:Q38) -> -205.934 | AD38: =SUM(O38:R38) -> -179.154 | AE38: =SUM(P38:S38) -> -175.757 | AG38: =SUM(AE38/AA38)-1 -> 0.079734362
B39: (+/-) Changes in NWC | C39: =SUM('Historical Financials'!D110:D115)/1000 -> -63.926 | D39: =SUM('Historical Financials'!E110:E115)/1000 -> 71.209 | E39: =SUM('Historical Financials'!F110:F115)/1000 -> -120.159 | F39: =SUM('Historical Financials'!G110:G115)/1000 -> -74.279 | G39: =SUM('Historical Financials'!H110:H115)/1000 -> -187.205 | I39: =SUM('Historical Financials'!J110:J115)/1000 -> 185.718 | J39: =SUM('Historical Financials'!K110:K115)/1000 -> -112.314 | K39: =SUM('Historical Financials'!L110:L115)/1000 -> -81.402 | L39: =SUM('Historical Financials'!M110:M115)/1000 -> -66.281 | M39: =SUM('Historical Financials'!N110:N115)/1000 -> -69.37 | N39: =SUM('Historical Financials'!O110:O115)/1000 -> -20.584 | O39: =SUM('Historical Financials'!P110:P115)/1000 -> -126.78 | P39: =SUM('Historical Financials'!Q110:Q115)/1000 -> 29.529 | ... S39: =SUM('Historical Financials'!T110:T115)/1000 -> -170.842 | U39: =SUM(I39:I39) -> 185.718 | V39: =SUM(I39:J39) -> 73.404 | W39: =SUM(I39:K39) -> -7.998 | X39: =SUM(I39:L39) -> -74.279 | Y39: =SUM(J39:M39) -> -329.367 | Z39: =SUM(K39:N39) -> -237.637 | AA39: =SUM(L39:O39) -> -283.015 | AB39: =SUM(M39:P39) -> -187.205 | AC39: =SUM(N39:Q39) -> -89.086 | AD39: =SUM(O39:R39) -> -133.768 | AE39: =SUM(P39:S39) -> -177.83 | AG39: =SUM(AE39/AA39)-1 -> -0.37165875
B40: Discretionary Cash-Flows | C40: =SUM(C33+SUM(C36:C39)) -> -1038.444 | D40: =SUM(D33+SUM(D36:D39)) -> -287.119 | E40: =SUM(E33+SUM(E36:E39)) -> -272.652 | F40: =SUM(F33+SUM(F36:F39)) -> -494.787 | G40: =SUM(G33+SUM(G36:G39)) -> -940.89 | I40: =SUM(I33+SUM(I36:I39)) -> 82.692 | J40: =SUM(J33+SUM(J36:J39)) -> -95.971 | K40: =SUM(K33+SUM(K36:K39)) -> -253.109 | L40: =SUM(L33+SUM(L36:L39)) -> -228.399 | M40: =SUM(M33+SUM(M36:M39)) -> -263.294 | N40: =SUM(N33+SUM(N36:N39)) -> -149.726 | O40: =SUM(O33+SUM(O36:O39)) -> -407.89 | P40: =SUM(P33+SUM(P36:P39)) -> -119.98 | ... S40: =SUM(S33+SUM(S36:S39)) -> -409.809 | U40: =SUM(U33+SUM(U36:U39)) -> -1520.353 | V40: =SUM(V33+SUM(V36:V39)) -> -1153.304 | W40: =SUM(W33+SUM(W36:W39)) -> -318.373 | X40: =SUM(X33+SUM(X36:X39)) -> -598.29 | Y40: =SUM(Y33+SUM(Y36:Y39)) -> -956.422 | Z40: =SUM(Z33+SUM(Z36:Z39)) -> -974.975 | AA40: =SUM(AA33+SUM(AA36:AA39)) -> -1049.309 | AB40: =SUM(AB33+SUM(AB36:AB39)) -> -940.89 | ... AE40: =SUM(AE33+SUM(AE36:AE39)) -> -1005.336 | AG40: =SUM(AE40/AA40)-1 -> -0.041906626
B42: (+/-) Proceeds / (Purchase) of available-for-sale investment securities | C42: ='Historical Financials'!D121/1000 -> -1.228 | D42: ='Historical Financials'!E121/1000 -> -0.861 | E42: ='Historical Financials'!F121/1000 -> -1.19 | F42: ='Historical Financials'!G121/1000 -> -2.057 | G42: ='Historical Financials'!H121/1000 -> -1.395 | I42: ='Historical Financials'!J121/1000 -> -0.593 | J42: ='Historical Financials'!K121/1000 -> -0.607 | K42: ='Historical Financials'!L121/1000 -> -0.503 | L42: ='Historical Financials'!M121/1000 -> -0.354 | M42: ='Historical Financials'!N121/1000 -> -0.326 | N42: ='Historical Financials'!O121/1000 -> -0.298 | O42: ='Historical Financials'!P121/1000 -> -0.316 | P42: ='Historical Financials'!Q121/1000 -> -0.455 | ... S42: ='Historical Financials'!T121/1000 -> 0 | U42: =SUM(F42:I42) -> -4.045 | V42: =SUM(G42:J42) -> -2.595 | W42: =SUM(H42:K42) -> -1.703 | X42: =SUM(I42:L42) -> -2.057 | Y42: =SUM(J42:M42) -> -1.79 | Z42: =SUM(K42:N42) -> -1.481 | AA42: =SUM(L42:O42) -> -1.294 | AB42: =SUM(M42:P42) -> -1.395 | ... AE42: =SUM(P42:S42) -> 119.413
B43: (+/-) Pre-delivery deposit refunds on flight equipment, net of payments | C43: ='Historical Financials'!D123/1000 -> -143.22 | D43: ='Historical Financials'!E123/1000 -> -119.352 | E43: ='Historical Financials'!F123/1000 -> -8.498 | F43: ='Historical Financials'!G123/1000 -> 23.156 | G43: ='Historical Financials'!H123/1000 -> 356.294 | I43: ='Historical Financials'!J123/1000 -> -25.443 | J43: ='Historical Financials'!K123/1000 -> 10.309 | K43: ='Historical Financials'!L123/1000 -> 17.112 | L43: ='Historical Financials'!M123/1000 -> 21.178 | M43: ='Historical Financials'!N123/1000 -> 30.403 | N43: ='Historical Financials'!O123/1000 -> 131.756 | O43: ='Historical Financials'!P123/1000 -> 184.023 | P43: ='Historical Financials'!Q123/1000 -> 10.112 | ... S43: ='Historical Financials'!T123/1000 -> -1.411 | U43: =SUM(F43:I43) -> 354.007 | V43: =SUM(G43:J43) -> 341.16 | W43: =SUM(H43:K43) -> 1.978 | X43: =SUM(I43:L43) -> 23.156 | Y43: =SUM(J43:M43) -> 79.002 | Z43: =SUM(K43:N43) -> 200.449 | AA43: =SUM(L43:O43) -> 367.36 | AB43: =SUM(M43:P43) -> 356.294 | ... AE43: =SUM(P43:S43) -> 44.118
B44: (-) Proceeds from sale of property and equipment | C44: ='Historical Financials'!D120/1000 -> 0 | D44: ='Historical Financials'!E120/1000 -> 0 | E44: ='Historical Financials'!F120/1000 -> 0 | F44: ='Historical Financials'!G120/1000 -> 230.788 | G44: ='Historical Financials'!H120/1000 -> 232.564 | I44: ='Historical Financials'!J120/1000 -> 23.845 | J44: ='Historical Financials'!K120/1000 -> 12.306 | K44: ='Historical Financials'!L120/1000 -> 16.315 | L44: ='Historical Financials'!M120/1000 -> 178.322 | M44: ='Historical Financials'!N120/1000 -> 138.771 | N44: ='Historical Financials'!O120/1000 -> 22.81 | O44: ='Historical Financials'!P120/1000 -> 2.732 | P44: ='Historical Financials'!Q120/1000 -> 68.251 | ... S44: ='Historical Financials'!T120/1000 -> 271.261 | U44: =SUM(F44:I44) -> 487.197 | V44: =SUM(G44:J44) -> 268.715 | W44: =SUM(H44:K44) -> 52.466 | X44: =SUM(I44:L44) -> 230.788 | Y44: =SUM(J44:M44) -> 345.714 | Z44: =SUM(K44:N44) -> 356.218 | AA44: =SUM(L44:O44) -> 342.635 | AB44: =SUM(M44:P44) -> 232.564 | ... AE44: =SUM(P44:S44) -> 339.512
B45: (-) Proceeds / (Repayment) of Debt | C45: ='Historical Financials'!D128/1000 -> 1358.087 | D45: ='Historical Financials'!E128/1000 -> -660.197 | E45: ='Historical Financials'!F128/1000 -> 397.967 | F45: ='Historical Financials'!G128/1000 -> -202.776 | G45: ='Historical Financials'!H128/1000 -> 397.375 | I45: ='Historical Financials'!J128/1000 -> -129.435 | J45: ='Historical Financials'!K128/1000 -> -112.384 | K45: ='Historical Financials'!L128/1000 -> -45.186 | L45: ='Historical Financials'!M128/1000 -> 84.229 | M45: ='Historical Financials'!N128/1000 -> -47.325 | N45: ='Historical Financials'!O128/1000 -> -72.814 | O45: ='Historical Financials'!P128/1000 -> -31.885 | P45: ='Historical Financials'!Q128/1000 -> 549.399 | ... S45: ='Historical Financials'!T128/1000 -> 235.53 | U45: =SUM(F45:I45) -> 65.164 | V45: =SUM(G45:J45) -> 155.556 | W45: =SUM(H45:K45) -> -287.005 | X45: =SUM(I45:L45) -> -202.776 | Y45: =SUM(J45:M45) -> -120.666 | Z45: =SUM(K45:N45) -> -81.096 | AA45: =SUM(L45:O45) -> -67.795 | AB45: =SUM(M45:P45) -> 397.375 | ... AE45: =SUM(P45:S45) -> 280.328
B46: (+/-) Payments on finance lease obligations | C46: ='Historical Financials'!D129/1000 -> -25.401 | D46: ='Historical Financials'!E129/1000 -> -0.831 | E46: ='Historical Financials'!F129/1000 -> -0.842 | F46: ='Historical Financials'!G129/1000 -> -0.496 | G46: ='Historical Financials'!H129/1000 -> -0.312 | I46: ='Historical Financials'!J129/1000 -> -0.179 | J46: ='Historical Financials'!K129/1000 -> -0.114 | K46: ='Historical Financials'!L129/1000 -> -0.115 | L46: ='Historical Financials'!M129/1000 -> -0.088 | M46: ='Historical Financials'!N129/1000 -> -0.086 | N46: ='Historical Financials'!O129/1000 -> -0.091 | O46: ='Historical Financials'!P129/1000 -> -0.08 | P46: ='Historical Financials'!Q129/1000 -> -0.055 | ... S46: ='Historical Financials'!T129/1000 -> -0.055 | U46: =SUM(F46:I46) -> -0.987 | V46: =SUM(G46:J46) -> -0.605 | W46: =SUM(H46:K46) -> -0.408 | X46: =SUM(I46:L46) -> -0.496 | Y46: =SUM(J46:M46) -> -0.403 | Z46: =SUM(K46:N46) -> -0.38 | AA46: =SUM(L46:O46) -> -0.345 | AB46: =SUM(M46:P46) -> -0.312 | ... AE46: =SUM(P46:S46) -> -0.22
B47: (+/-) Equity Issuances / (Repurchase of Common Stock) | C47: ='Historical Financials'!D130/1000 -> 365.153 | D47: ='Historical Financials'!E130/1000 -> 374.147 | E47: ='Historical Financials'!F130/1000 -> -2.359 | F47: ='Historical Financials'!G130/1000 -> -2.637 | G47: ='Historical Financials'!H130/1000 -> -0.65 | I47: ='Historical Financials'!J130/1000 -> 0 | J47: ='Historical Financials'!K130/1000 -> -1.674 | K47: ='Historical Financials'!L130/1000 -> -0.034 | L47: ='Historical Financials'!M130/1000 -> -0.929 | M47: ='Historical Financials'!N130/1000 -> -0.636 | N47: ='Historical Financials'!O130/1000 -> -0.009 | O47: ='Historical Financials'!P130/1000 -> -0.004 | P47: ='Historical Financials'!Q130/1000 -> -0.001 | ... S47: ='Historical Financials'!T130/1000 -> 0 | U47: =SUM(F47:I47) -> -3.287 | V47: =SUM(G47:J47) -> -2.324 | W47: =SUM(H47:K47) -> -1.708 | X47: =SUM(I47:L47) -> -2.637 | Y47: =SUM(J47:M47) -> -3.273 | Z47: =SUM(K47:N47) -> -1.608 | AA47: =SUM(L47:O47) -> -1.578 | AB47: =SUM(M47:P47) -> -0.65 | ... AE47: =SUM(P47:S47) -> 349.999
B48: (+/-) Debt and equity financing costs | C48: ='Historical Financials'!D132/1000 -> -40.551 | D48: ='Historical Financials'!E132/1000 -> -2.775 | E48: ='Historical Financials'!F132/1000 -> -3.471 | F48: ='Historical Financials'!G132/1000 -> -3.027 | G48: ='Historical Financials'!H132/1000 -> -14.523 | I48: ='Historical Financials'!J132/1000 -> -0.555 | J48: ='Historical Financials'!K132/1000 -> 0 | K48: ='Historical Financials'!L132/1000 -> 0 | L48: ='Historical Financials'!M132/1000 -> -2.472 | M48: ='Historical Financials'!N132/1000 -> 0 | N48: ='Historical Financials'!O132/1000 -> 0 | O48: ='Historical Financials'!P132/1000 -> -8.603 | P48: ='Historical Financials'!Q132/1000 -> -5.92 | ... S48: ='Historical Financials'!T132/1000 -> 0 | U48: =SUM(F48:I48) -> -18.105 | V48: =SUM(G48:J48) -> -15.078 | W48: =SUM(H48:K48) -> -0.555 | X48: =SUM(I48:L48) -> -3.027 | Y48: =SUM(J48:M48) -> -2.472 | Z48: =SUM(K48:N48) -> -2.472 | AA48: =SUM(L48:O48) -> -11.075 | AB48: =SUM(M48:P48) -> -14.523 | ... AE48: =SUM(P48:S48) -> -21.114
B49: (+/-) Reorganization items | C49: ='Historical Financials'!D107/1000 -> 0 | D49: ='Historical Financials'!E107/1000 -> 0 | E49: ='Historical Financials'!F107/1000 -> 0 | F49: ='Historical Financials'!G107/1000 -> 0 | G49: ='Historical Financials'!H107/1000 -> 85.554 | I49: ='Historical Financials'!J107/1000 -> 0 | J49: ='Historical Financials'!K107/1000 -> 0 | K49: ='Historical Financials'!L107/1000 -> 0 | L49: ='Historical Financials'!M107/1000 -> 0 | M49: ='Historical Financials'!N107/1000 -> 0 | N49: ='Historical Financials'!O107/1000 -> 0 | O49: ='Historical Financials'!P107/1000 -> 0 | P49: ='Historical Financials'!Q107/1000 -> 85.554 | ... S49: ='Historical Financials'!T107/1000 -> 125.983 | U49: =SUM(F49:I49) -> 85.554 | V49: =SUM(G49:J49) -> 85.554 | W49: =SUM(H49:K49) -> 0 | X49: =SUM(I49:L49) -> 0 | Y49: =SUM(J49:M49) -> 0 | Z49: =SUM(K49:N49) -> 0 | AA49: =SUM(L49:O49) -> 0 | AB49: =SUM(M49:P49) -> 85.554 | ... AE49: =SUM(P49:S49) -> -209.927
B50: (+/-) Deferred income tax benefit | C50: ='Historical Financials'!D102/1000 -> -46.086 | D50: ='Historical Financials'!E102/1000 -> -49.502 | E50: ='Historical Financials'!F102/1000 -> -148.611 | F50: ='Historical Financials'!G102/1000 -> -119.239 | G50: ='Historical Financials'!H102/1000 -> -58.215 | I50: ='Historical Financials'!J102/1000 -> -37.851 | J50: ='Historical Financials'!K102/1000 -> 16.853 | K50: ='Historical Financials'!L102/1000 -> -45.879 | L50: ='Historical Financials'!M102/1000 -> -52.362 | M50: ='Historical Financials'!N102/1000 -> -15.005 | N50: ='Historical Financials'!O102/1000 -> 3.66 | O50: ='Historical Financials'!P102/1000 -> -24.863 | P50: ='Historical Financials'!Q102/1000 -> -22.007 | ... S50: ='Historical Financials'!T102/1000 -> 1.231 | U50: =SUM(F50:I50) -> -215.305 | V50: =SUM(G50:J50) -> -79.213 | W50: =SUM(H50:K50) -> -66.877 | X50: =SUM(I50:L50) -> -119.239 | Y50: =SUM(J50:M50) -> -96.393 | Z50: =SUM(K50:N50) -> -109.586 | AA50: =SUM(L50:O50) -> -88.57 | AB50: =SUM(M50:P50) -> -58.215 | ... AE50: =SUM(P50:S50) -> -7.946
B51: (+/-) Other | D51: =SUM(D56-C56)-SUM(D40:D50) -> 290.274 | E51: =SUM(E56-D56)-SUM(E40:E50) -> 52.499 | F51: =SUM(F56-E56)-SUM(F40:F50) -> 89.936 | G51: =SUM(G56-F56)-SUM(G40:G50) -> -18.956 | I51: =SUM(I56-E56)-SUM(I40:I50) -> 28.88 | J51: =SUM(J56-I56)-SUM(J40:J50) -> -5.741 | K51: =SUM(K56-J56)-SUM(K40:K50) -> 19.034 | L51: =SUM(L56-K56)-SUM(L40:L50) -> 47.763 | M51: =SUM(M56-L56)-SUM(M40:M50) -> 57.075 | N51: =SUM(N56-M56)-SUM(N40:N50) -> 24.718 | O51: =SUM(O56-N56)-SUM(O40:O50) -> -14.361 | P51: =SUM(P56-O56)-SUM(P40:P50) -> -86.388 | Q51: =SUM(Q56-P56)-SUM(Q40:Q50) -> 317.295 | ... S51: =SUM(S56-R56)-SUM(S40:S50) -> -379.747 | U51: =SUM(F51:I51) -> 99.86 | V51: =SUM(G51:J51) -> 4.183 | W51: =SUM(H51:K51) -> 42.173 | X51: =SUM(I51:L51) -> 89.936 | Y51: =SUM(J51:M51) -> 118.131 | Z51: =SUM(K51:N51) -> 148.59 | AA51: =SUM(L51:O51) -> 115.195 | AB51: =SUM(M51:P51) -> -18.956 | ... AE51: =SUM(P51:S51) -> -61.88
B52: Free-Cash Flows | C52: =SUM(C40+SUM(C42:C51)) -> 428.31 | D52: =SUM(D40+SUM(D42:D51)) -> -456.216 | E52: =SUM(E40+SUM(E42:E51)) -> 12.843 | F52: =SUM(F40+SUM(F42:F51)) -> -481.139 | G52: =SUM(G40+SUM(G42:G51)) -> 36.846 | I52: =SUM(I40+SUM(I42:I51)) -> -58.639 | J52: =SUM(J40+SUM(J42:J51)) -> -177.023 | K52: =SUM(K40+SUM(K42:K51)) -> -292.365 | L52: =SUM(L40+SUM(L42:L51)) -> 46.888 | M52: =SUM(M40+SUM(M42:M51)) -> -100.423 | N52: =SUM(N40+SUM(N42:N51)) -> -39.994 | O52: =SUM(O40+SUM(O42:O51)) -> -301.247 | P52: =SUM(P40+SUM(P42:P51)) -> 478.51 | ... S52: =SUM(S40+SUM(S42:S51)) -> -157.017 | U52: =SUM(U40+SUM(U42:U51)) -> -670.3 | V52: =SUM(V40+SUM(V42:V51)) -> -397.951 | W52: =SUM(W40+SUM(W42:W51)) -> -580.012 | X52: =SUM(X40+SUM(X42:X51)) -> -584.642 | Y52: =SUM(Y40+SUM(Y42:Y51)) -> -638.572 | Z52: =SUM(Z40+SUM(Z42:Z51)) -> -466.341 | AA52: =SUM(AA40+SUM(AA42:AA51)) -> -394.776 | AB52: =SUM(AB40+SUM(AB42:AB51)) -> 36.846 | ... AE52: =SUM(AE40+SUM(AE42:AE51)) -> -173.053
B54: Capitalization
B56: Cash and Cash Equivalents | C56: ='Historical Financials'!D49/1000 -> 1789.723 | D56: ='Historical Financials'!E49/1000 -> 1333.507 | E56: ='Historical Financials'!F49/1000 -> 1346.35 | F56: ='Historical Financials'!G49/1000 -> 865.211 | G56: ='Historical Financials'!H49/1000 -> 902.057 | I56: ='Historical Financials'!J49/1000 -> 1287.711 | J56: ='Historical Financials'!K49/1000 -> 1110.688 | K56: ='Historical Financials'!L49/1000 -> 818.323 | L56: ='Historical Financials'!M49/1000 -> 865.211 | M56: ='Historical Financials'!N49/1000 -> 764.788 | N56: ='Historical Financials'!O49/1000 -> 724.794 | O56: ='Historical Financials'!P49/1000 -> 423.547 | P56: ='Historical Financials'!Q49/1000 -> 902.057 | ... S56: ='Historical Financials'!T49/1000 -> 250.494 | U56: =I56 -> 1287.711 | V56: =J56 -> 1110.688 | W56: =K56 -> 818.323 | X56: =L56 -> 865.211 | Y56: =M56 -> 764.788 | Z56: =N56 -> 724.794 | AA56: =O56 -> 423.547 | AB56: =P56 -> 902.057 | ... AE56: =S56 -> 250.494
B57: Restricted Cash | C57: ='Historical Financials'!D50/1000 -> 71.401 | D57: ='Historical Financials'!E50/1000 -> 95.4 | E57: ='Historical Financials'!F50/1000 -> 119.392 | F57: ='Historical Financials'!G50/1000 -> 119.4 | G57: ='Historical Financials'!H50/1000 -> 168.39 | I57: ='Historical Financials'!J50/1000 -> 119.4 | J57: ='Historical Financials'!K50/1000 -> 119.4 | K57: ='Historical Financials'!L50/1000 -> 119.4 | L57: ='Historical Financials'!M50/1000 -> 119.4 | M57: ='Historical Financials'!N50/1000 -> 133.585 | N57: ='Historical Financials'!O50/1000 -> 120.579 | O57: ='Historical Financials'!P50/1000 -> 170.086 | P57: ='Historical Financials'!Q50/1000 -> 168.39 | ... S57: ='Historical Financials'!T50/1000 -> 396.103 | U57: =I57 -> 119.4 | V57: =J57 -> 119.4 | W57: =K57 -> 119.4 | X57: =L57 -> 119.4 | Y57: =M57 -> 133.585 | Z57: =N57 -> 120.579 | AA57: =O57 -> 170.086 | AB57: =P57 -> 168.39 | ... AE57: =S57 -> 396.103
B58: Short-Term Investment Securities | C58: ='Historical Financials'!D51/1000 -> 106.339 | D58: ='Historical Financials'!E51/1000 -> 106.313 | E58: ='Historical Financials'!F51/1000 -> 107.115 | F58: ='Historical Financials'!G51/1000 -> 112.501 | G58: ='Historical Financials'!H51/1000 -> 118.334 | I58: ='Historical Financials'!J51/1000 -> 108.357 | J58: ='Historical Financials'!K51/1000 -> 109.494 | K58: ='Historical Financials'!L51/1000 -> 110.933 | L58: ='Historical Financials'!M51/1000 -> 112.501 | M58: ='Historical Financials'!N51/1000 -> 113.854 | N58: ='Historical Financials'!O51/1000 -> 115.29 | O58: ='Historical Financials'!P51/1000 -> 117.104 | P58: ='Historical Financials'!Q51/1000 -> 118.334 | ... S58: ='Historical Financials'!T51/1000 -> 0 | U58: =I58 -> 108.357 | V58: =J58 -> 109.494 | W58: =K58 -> 110.933 | X58: =L58 -> 112.501 | Y58: =M58 -> 113.854 | Z58: =N58 -> 115.29 | AA58: =O58 -> 117.104 | AB58: =P58 -> 118.334 | ... AE58: =S58 -> 0
B59: $275MM RCF | C59: =350-C88-C89 -> 74.9 | D59: =350-D88-D89 -> 350 | E59: =350-E88-E89 -> 350 | F59: =300-F88-F89 -> 300 | G59: =300-G88-G89-G90 -> 0 | I59: =300-I88-I89 -> 300 | J59: =300-J88-J89 -> 300 | K59: =300-K88-K89 -> 300 | L59: =F59 -> 300 | M59: =300-M88-M89 -> 300 | N59: =300-N88-N89 -> 300 | O59: =300-O88-O89 -> 300 | P59: =G59 -> 0 | Q59: =275-Q88-Q89-Q90 -> 275 | R59: =275-R88-R89-R90 -> 275 | S59: =275-S88-S89-S90 -> 275 | U59: =I59 -> 300 | V59: =J59 -> 300 | W59: =K59 -> 300 | X59: =L59 -> 300 | Y59: =M59 -> 300 | Z59: =N59 -> 300 | AA59: =O59 -> 300 | AB59: =P59 -> 0 | ... AE59: =S59 -> 275
B60: Total Liquidity | C60: =SUM(C56:C59) -> 2042.363 | D60: =SUM(D56:D59) -> 1885.22 | E60: =SUM(E56:E59) -> 1922.857 | F60: =SUM(F56:F59) -> 1397.112 | G60: =SUM(G56:G59) -> 1188.781 | I60: =SUM(I56:I59) -> 1815.468 | J60: =SUM(J56:J59) -> 1639.582 | K60: =SUM(K56:K59) -> 1348.656 | L60: =SUM(L56:L59) -> 1397.112 | M60: =SUM(M56:M59) -> 1312.227 | N60: =SUM(N56:N59) -> 1260.663 | O60: =SUM(O56:O59) -> 1010.737 | P60: =SUM(P56:P59) -> 1188.781 | ... S60: =SUM(S56:S59) -> 921.597 | U60: =SUM(U56:U56) -> 1287.711 | V60: =SUM(V56:V56) -> 1110.688 | W60: =SUM(W56:W56) -> 818.323 | X60: =SUM(X56:X56) -> 865.211 | Y60: =SUM(Y56:Y56) -> 764.788 | Z60: =SUM(Z56:Z56) -> 724.794 | AA60: =SUM(AA56:AA59) -> 1010.737 | AB60: =SUM(AB56:AB59) -> 1188.781 | AC60: =SUM(AC56:AC59) -> 1152.632 | AD60: =SUM(AD56:AD59) -> 834.599 | AE60: =SUM(AE56:AE59) -> 921.597
B62: Balance Sheet Metrics:
B63: Accounts Receivable | C63: ='Historical Financials'!D52/1000 -> 42.94 | D63: ='Historical Financials'!E52/1000 -> 128.828 | E63: ='Historical Financials'!F52/1000 -> 197.276 | F63: ='Historical Financials'!G52/1000 -> 205.468 | G63: ='Historical Financials'!H52/1000 -> 178.955 | I63: ='Historical Financials'!J52/1000 -> 186.07 | J63: ='Historical Financials'!K52/1000 -> 186.739 | K63: ='Historical Financials'!L52/1000 -> 170.959 | L63: ='Historical Financials'!M52/1000 -> 205.468 | M63: ='Historical Financials'!N52/1000 -> 212.469 | N63: ='Historical Financials'!O52/1000 -> 216.65 | O63: ='Historical Financials'!P52/1000 -> 230.079 | P63: ='Historical Financials'!Q52/1000 -> 178.955 | ... S63: ='Historical Financials'!T52/1000 -> 114.386 | U63: =I63 -> 186.07 | V63: =J63 -> 186.739 | W63: =K63 -> 170.959 | X63: =L63 -> 205.468 | Y63: =M63 -> 212.469 | Z63: =N63 -> 216.65 | AA63: =O63 -> 230.079 | AB63: =P63 -> 178.955 | ... AE63: =S63 -> 114.386
B64: Property and Equipment | C64: ='Historical Financials'!D57/1000 -> 3831.568 | D64: ='Historical Financials'!E57/1000 -> 3856.593 | E64: ='Historical Financials'!F57/1000 -> 3749.498 | F64: ='Historical Financials'!G57/1000 -> 3519.128 | G64: ='Historical Financials'!H57/1000 -> 2492.784 | I64: ='Historical Financials'!J57/1000 -> 3738.682 | J64: ='Historical Financials'!K57/1000 -> 3740.5 | K64: ='Historical Financials'!L57/1000 -> 3731.96 | L64: ='Historical Financials'!M57/1000 -> 3519.128 | M64: ='Historical Financials'!N57/1000 -> 3400.292 | N64: ='Historical Financials'!O57/1000 -> 3336.335 | O64: ='Historical Financials'!P57/1000 -> 3299.455 | P64: ='Historical Financials'!Q57/1000 -> 2492.784 | ... S64: ='Historical Financials'!T57/1000 -> 2521.158 | U64: =I64 -> 3738.682 | V64: =J64 -> 3740.5 | W64: =K64 -> 3731.96 | X64: =L64 -> 3519.128 | Y64: =M64 -> 3400.292 | Z64: =N64 -> 3336.335 | AA64: =O64 -> 3299.455 | AB64: =P64 -> 2492.784 | ... AE64: =S64 -> 2521.158
B65: Accounts Payable | C65: ='Historical Financials'!D65/1000 -> 28.454 | D65: ='Historical Financials'!E65/1000 -> 44.952 | E65: ='Historical Financials'!F65/1000 -> 75.449 | F65: ='Historical Financials'!G65/1000 -> 42.098 | G65: ='Historical Financials'!H65/1000 -> 32.385 | I65: ='Historical Financials'!J65/1000 -> 53.046 | J65: ='Historical Financials'!K65/1000 -> 76.158 | K65: ='Historical Financials'!L65/1000 -> 86.297 | L65: ='Historical Financials'!M65/1000 -> 42.098 | M65: ='Historical Financials'!N65/1000 -> 85.074 | N65: ='Historical Financials'!O65/1000 -> 70.014 | O65: ='Historical Financials'!P65/1000 -> 49.637 | P65: ='Historical Financials'!Q65/1000 -> 32.385 | ... S65: ='Historical Financials'!T65/1000 -> 149.27 | U65: =I65 -> 53.046 | V65: =J65 -> 76.158 | W65: =K65 -> 86.297 | X65: =L65 -> 42.098 | Y65: =M65 -> 85.074 | Z65: =N65 -> 70.014 | AA65: =O65 -> 49.637 | AB65: =P65 -> 32.385 | ... AE65: =S65 -> 149.27
B66: Current Liabilities | C66: ='Historical Financials'!D70/1000 -> 1342.022 | D66: ='Historical Financials'!E70/1000 -> 1275.602 | E66: ='Historical Financials'!F70/1000 -> 1596.581 | F66: ='Historical Financials'!G70/1000 -> 1671.592 | G66: ='Historical Financials'!H70/1000 -> 1769.365 | I66: ='Historical Financials'!J70/1000 -> 1752.609 | J66: ='Historical Financials'!K70/1000 -> 1685.962 | K66: ='Historical Financials'!L70/1000 -> 1600.8 | L66: ='Historical Financials'!M70/1000 -> 1671.592 | M66: ='Historical Financials'!N70/1000 -> 1529.034 | N66: ='Historical Financials'!O70/1000 -> 1511.148 | O66: ='Historical Financials'!P70/1000 -> 2540.203 | P66: ='Historical Financials'!Q70/1000 -> 1769.365 | ... S66: ='Historical Financials'!T70/1000 -> 1010.176 | U66: =I66 -> 1752.609 | V66: =J66 -> 1685.962 | W66: =K66 -> 1600.8 | X66: =L66 -> 1671.592 | Y66: =M66 -> 1529.034 | Z66: =N66 -> 1511.148 | AA66: =O66 -> 2540.203 | AB66: =P66 -> 1769.365 | ... AE66: =S66 -> 1010.176
B67: Total Liabilities | C67: ='Historical Financials'!D78/1000 -> 6149.13 | D67: ='Historical Financials'!E78/1000 -> 6425.99 | E67: ='Historical Financials'!F78/1000 -> 7613.123 | F67: ='Historical Financials'!G78/1000 -> 8282.895 | G67: ='Historical Financials'!H78/1000 -> 9675.312 | I67: ='Historical Financials'!J78/1000 -> 7852.471 | J67: ='Historical Financials'!K78/1000 -> 7901.055 | K67: ='Historical Financials'!L78/1000 -> 8045.505 | L67: ='Historical Financials'!M78/1000 -> 8282.895 | M67: ='Historical Financials'!N78/1000 -> 8524.238 | N67: ='Historical Financials'!O78/1000 -> 8749.794 | O67: ='Historical Financials'!P78/1000 -> 8989.3 | P67: ='Historical Financials'!Q78/1000 -> 9675.312 | ... S67: ='Historical Financials'!T78/1000 -> 8630.551 | U67: =I67 -> 7852.471 | V67: =J67 -> 7901.055 | W67: =K67 -> 8045.505 | X67: =L67 -> 8282.895 | Y67: =M67 -> 8524.238 | Z67: =N67 -> 8749.794 | AA67: =O67 -> 8989.3 | AB67: =P67 -> 9675.312 | ... AE67: =S67 -> 8630.551
B69: Summary Debt:
B70: CPLTD | C70: ='Historical Financials'!D67/1000 -> 384.197 | D70: ='Historical Financials'!E67/1000 -> 208.948 | E70: ='Historical Financials'!F67/1000 -> 346.888 | F70: ='Historical Financials'!G67/1000 -> 315.58 | G70: ='Historical Financials'!H67/1000 -> 436.532 | I70: ='Historical Financials'!J67/1000 -> 261.724 | J70: ='Historical Financials'!K67/1000 -> 235.579 | K70: ='Historical Financials'!L67/1000 -> 235.868 | L70: ='Historical Financials'!M67/1000 -> 315.58 | M70: ='Historical Financials'!N67/1000 -> 156.812 | N70: ='Historical Financials'!O67/1000 -> 142.815 | O70: ='Historical Financials'!P67/1000 -> 1253.376 | P70: ='Historical Financials'!Q67/1000 -> 436.532 | ... S70: ='Historical Financials'!T67/1000 -> 119.226 | U70: =I70 -> 261.724 | V70: =J70 -> 235.579 | W70: =K70 -> 235.868 | X70: =L70 -> 315.58 | Y70: =M70 -> 156.812 | Z70: =N70 -> 142.815 | AA70: =O70 -> 1253.376 | AB70: =P70 -> 436.532 | ... AE70: =S70 -> 119.226
B71: LTD | C71: ='Historical Financials'!D73/1000 -> 3066.635 | D71: ='Historical Financials'!E73/1000 -> 2975.823 | E71: ='Historical Financials'!F73/1000 -> 3200.376 | F71: ='Historical Financials'!G73/1000 -> 3055.221 | G71: ='Historical Financials'!H73/1000 -> 1761.215 | I71: ='Historical Financials'!J73/1000 -> 3164.061 | J71: ='Historical Financials'!K73/1000 -> 3081.192 | K71: ='Historical Financials'!L73/1000 -> 3043.391 | L71: ='Historical Financials'!M73/1000 -> 3055.221 | M71: ='Historical Financials'!N73/1000 -> 3175.555 | N71: ='Historical Financials'!O73/1000 -> 3124.079 | O71: ='Historical Financials'!P73/1000 -> 1986.735 | P71: ='Historical Financials'!Q73/1000 -> 1761.215 | ... S71: ='Historical Financials'!T73/1000 -> 750.205 | U71: =I71 -> 3164.061 | V71: =J71 -> 3081.192 | W71: =K71 -> 3043.391 | X71: =L71 -> 3055.221 | Y71: =M71 -> 3175.555 | Z71: =N71 -> 3124.079 | AA71: =O71 -> 1986.735 | AB71: =P71 -> 1761.215 | ... AE71: =S71 -> 750.205
B73: DIP term loan due in 2025 | C73: 0 | D73: 0 | E73: 0 | F73: 0 | G73: 309 | I73: 0 | J73: 0 | K73: 0 | L73: =F73 -> 0 | M73: 0 | N73: 0 | O73: 0 | P73: =G73 -> 309 | Q73: 0 | R73: 0 | S73: 0 | U73: =I73 -> 0 | V73: =J73 -> 0 | W73: =K73 -> 0 | X73: =L73 -> 0 | Y73: =M73 -> 0 | Z73: =N73 -> 0 | AA73: =O73 -> 0 | AB73: =P73 -> 309 | ... AE73: =S73 -> 0
B74: 8.00% senior secured notes due in 2025 | C74: 850 | D74: 510 | E74: 1110 | F74: 1110 | G74: 0 | I74: 1110 | J74: 1110 | K74: 1110 | L74: =F74 -> 1110 | M74: 1110 | N74: 1110 | O74: 1110 | P74: =G74 -> 0 | Q74: 0 | R74: 0 | S74: 0 | U74: =I74 -> 1110 | V74: =J74 -> 1110 | W74: =K74 -> 1110 | X74: =L74 -> 1110 | Y74: =M74 -> 1110 | Z74: =N74 -> 1110 | AA74: =O74 -> 1110 | AB74: =P74 -> 0 | ... AE74: =S74 -> 0
B75: Fixed-rate term loans due through 2039 | C75: 1301.9 | D75: 1223.5 | E75: 1094.7 | F75: 1093.3 | G75: 972.2 | I75: 1061.9 | J75: 1028.3 | K75: 994.2 | L75: =F75 -> 1093.3 | M75: 1055.8 | N75: 1033.9 | O75: 1011.8 | P75: =G75 -> 972.2 | Q75: 904.9 | R75: 880.2 | S75: 294.6 | U75: =I75 -> 1061.9 | V75: =J75 -> 1028.3 | W75: =K75 -> 994.2 | X75: =L75 -> 1093.3 | Y75: =M75 -> 1055.8 | Z75: =N75 -> 1033.9 | AA75: =O75 -> 1011.8 | AB75: =P75 -> 972.2 | ... AE75: =S75 -> 294.6
B76: Unsecured term loans due in 2031 | C76: 73.3 | D76: 136.3 | E76: 136.3 | F76: 136.3 | G76: 136.3 | I76: 136.3 | J76: 136.3 | K76: 136.3 | L76: =F76 -> 136.3 | M76: 136.3 | N76: 136.3 | O76: 136.3 | P76: =G76 -> 136.3 | Q76: 136.3 | R76: 136.3 | S76: 0 | U76: =I76 -> 136.3 | V76: =J76 -> 136.3 | W76: =K76 -> 136.3 | X76: =L76 -> 136.3 | Y76: =M76 -> 136.3 | Z76: =N76 -> 136.3 | AA76: =O76 -> 136.3 | AB76: =P76 -> 136.3 | ... AE76: =S76 -> 0
B77: Fixed-rate class A 2015-1 EETC due through 2028 | C77: 322.6 | D77: 300.6 | E77: 278.6 | F77: 256.6 | G77: 234.6 | I77: 278.6 | J77: 267.6 | K77: 267.6 | L77: =F77 -> 256.6 | M77: 256.6 | N77: 245.6 | O77: 245.6 | P77: =G77 -> 234.6 | Q77: 234.6 | R77: 223.6 | S77: 223.6 | U77: =I77 -> 278.6 | V77: =J77 -> 267.6 | W77: =K77 -> 267.6 | X77: =L77 -> 256.6 | Y77: =M77 -> 256.6 | Z77: =N77 -> 245.6 | AA77: =O77 -> 245.6 | AB77: =P77 -> 234.6 | ... AE77: =S77 -> 223.6
B78: Fixed-rate class B 2015-1 EETC due through 2024 | C78: 64 | D78: 56 | E78: 48 | F78: 40 | G78: 0 | I78: 48 | J78: 44 | K78: 44 | L78: =F78 -> 40 | M78: 40 | N78: 0 | O78: 0 | P78: =G78 -> 0 | Q78: 0 | R78: 0 | S78: 0 | U78: =I78 -> 48 | V78: =J78 -> 44 | W78: =K78 -> 44 | X78: =L78 -> 40 | Y78: =M78 -> 40 | Z78: =N78 -> 0 | AA78: =O78 -> 0 | AB78: =P78 -> 0 | ... AE78: =S78 -> 0
B79: Fixed-rate class C 2015-1 EETC due through 2023 | C79: 86.6 | D79: 75.2 | E79: 63.8 | F79: 0 | G79: 0 | I79: 63.8 | J79: 0 | K79: 0 | L79: =F79 -> 0 | M79: 0 | N79: 0 | O79: 0 | P79: =G79 -> 0 | Q79: 0 | R79: 0 | S79: 0 | U79: =I79 -> 63.8 | V79: =J79 -> 0 | W79: =K79 -> 0 | X79: =L79 -> 0 | Y79: =M79 -> 0 | Z79: =N79 -> 0 | AA79: =O79 -> 0 | AB79: =P79 -> 0 | ... AE79: =S79 -> 0
B80: Fixed-rate class AA 2017-1 EETC due through 2030 | C80: 214.4 | D80: 200.3 | E80: 186.3 | F80: 172.2 | G80: 160.3 | I80: 179.2 | J80: 179.2 | K80: 172.2 | L80: =F80 -> 172.2 | M80: 166.2 | N80: 166.2 | O80: 160.3 | P80: =G80 -> 160.3 | Q80: 154.3 | R80: 154.3 | S80: 152.3 | U80: =I80 -> 179.2 | V80: =J80 -> 179.2 | W80: =K80 -> 172.2 | X80: =L80 -> 172.2 | Y80: =M80 -> 166.2 | Z80: =N80 -> 166.2 | AA80: =O80 -> 160.3 | AB80: =P80 -> 160.3 | ... AE80: =S80 -> 152.3
B81: Fixed-rate class A 2017-1 EETC due through 2030 | C81: 71.5 | D81: 66.8 | E81: 62.1 | F81: 57.4 | G81: 53.4 | I81: 59.7 | J81: 59.7 | K81: 57.4 | L81: =F81 -> 57.4 | M81: 55.4 | N81: 55.4 | O81: 53.4 | P81: =G81 -> 53.4 | Q81: 51.4 | R81: 51.4 | S81: 45.5 | U81: =I81 -> 59.7 | V81: =J81 -> 59.7 | W81: =K81 -> 57.4 | X81: =L81 -> 57.4 | Y81: =M81 -> 55.4 | Z81: =N81 -> 55.4 | AA81: =O81 -> 53.4 | AB81: =P81 -> 53.4 | ... AE81: =S81 -> 45.5
B82: Fixed-rate class B 2017-1 EETC due through 2026 | C82: 60.6 | D82: 55.8 | E82: 51.7 | F82: 48.2 | G82: 44.7 | I82: 49.9 | J82: 49.9 | K82: 48.2 | L82: =F82 -> 48.2 | M82: 46.4 | N82: 46.4 | O82: 44.7 | P82: =G82 -> 44.7 | Q82: 43 | R82: 0 | S82: 0 | U82: =I82 -> 49.9 | V82: =J82 -> 49.9 | W82: =K82 -> 48.2 | X82: =L82 -> 48.2 | Y82: =M82 -> 46.4 | Z82: =N82 -> 46.4 | AA82: =O82 -> 44.7 | AB82: =P82 -> 44.7 | ... AE82: =S82 -> 0
B83: Fixed-rate class C 2017-1 EETC due through 2023 | C83: 85.5 | D83: 85.5 | E83: 85.5 | F83: 0 | G83: 0 | I83: 0 | J83: 0 | K83: 0 | L83: =F83 -> 0 | M83: 0 | N83: 0 | O83: 0 | P83: =G83 -> 0 | Q83: 0 | R83: 0 | S83: 0 | U83: =I83 -> 0 | V83: =J83 -> 0 | W83: =K83 -> 0 | X83: =L83 -> 0 | Y83: =M83 -> 0 | Z83: =N83 -> 0 | AA83: =O83 -> 0 | AB83: =P83 -> 0 | ... AE83: =S83 -> 0
B84: 2025-1 EETC Class B | C84: 0 | D84: 0 | E84: 0 | F84: 0 | G84: 0 | I84: 0 | J84: 0 | K84: 0 | L84: =F84 -> 0 | M84: 0 | N84: 0 | O84: 0 | P84: =G84 -> 0 | Q84: 215 | R84: 215 | S84: 215 | U84: =I84 -> 0 | V84: =J84 -> 0 | W84: =K84 -> 0 | X84: =L84 -> 0 | Y84: =M84 -> 0 | Z84: =N84 -> 0 | AA84: =O84 -> 0 | AB84: =P84 -> 0 | ... AE84: =S84 -> 215
... B90: Revolving credit facility due in 2026 | C90: 0 | D90: 0 | E90: 0 | F90: 0 | G90: 300 | I90: 0 | J90: 0 | K90: 0 | L90: =F90 -> 0 | M90: 0 | N90: 0 | O90: 0 | P90: =G90 -> 300 | Q90: 0 | R90: 0 | S90: 0 | U90: =I90 -> 0 | V90: =J90 -> 0 | W90: =K90 -> 0 | X90: =L90 -> 0 | Y90: =M90 -> 0 | Z90: =N90 -> 0 | AA90: =O90 -> 0 | AB90: =P90 -> 300 | ... AE90: =S90 -> 0
B91: Total Debt | C91: =SUM(C73:C90) -> 3580.5 | D91: =SUM(D73:D90) -> 3238.2 | E91: =SUM(E73:E90) -> 3642.4 | F91: =SUM(F73:F90) -> 3439.1 | G91: =SUM(G73:G90) -> 2210.5 | I91: =SUM(I73:I90) -> 3512.5 | J91: =SUM(J73:J90) -> 3400.1 | K91: =SUM(K73:K90) -> 3355 | L91: =SUM(L73:L90) -> 3439.1 | M91: =SUM(M73:M90) -> 3391.8 | N91: =SUM(N73:N90) -> 3318.9 | O91: =SUM(O73:O90) -> 3287.2 | P91: =SUM(P73:P90) -> 2210.5 | ... S91: =SUM(S73:S90) -> 931 | U91: =SUM(U73:U90) -> 3512.5 | V91: =SUM(V73:V90) -> 3400.1 | W91: =SUM(W73:W90) -> 3355 | X91: =SUM(X73:X90) -> 3439.1 | Y91: =SUM(Y73:Y90) -> 3391.8 | Z91: =SUM(Z73:Z90) -> 3318.9 | AA91: =SUM(AA73:AA90) -> 3287.2 | AB91: =SUM(AB73:AB90) -> 2210.5 | ... AE91: =SUM(AE73:AE90) -> 931
B93: Total Shareholder Equity | C93: ='Historical Financials'!D85/1000 -> 2249.695 | D93: ='Historical Financials'!E85/1000 -> 2114.035 | E93: ='Historical Financials'!F85/1000 -> 1571.651 | F93: ='Historical Financials'!G85/1000 -> 1134.342 | G93: ='Historical Financials'!H85/1000 -> -80.134 | I93: ='Historical Financials'!J85/1000 -> 1469.846 | J93: ='Historical Financials'!K85/1000 -> 1471.072 | K93: ='Historical Financials'!L85/1000 -> 1316.045 | L93: ='Historical Financials'!M85/1000 -> 1134.342 | M93: ='Historical Financials'!N85/1000 -> 1002.257 | N93: ='Historical Financials'!O85/1000 -> 809.662 | O93: ='Historical Financials'!P85/1000 -> 503.749 | P93: ='Historical Financials'!Q85/1000 -> -80.134 | ... S93: ='Historical Financials'!T85/1000 -> 164.493 | U93: =I93 -> 1469.846 | V93: =J93 -> 1471.072 | W93: =K93 -> 1316.045 | X93: =L93 -> 1134.342 | Y93: =M93 -> 1002.257 | Z93: =N93 -> 809.662 | AA93: =O93 -> 503.749 | AB93: =P93 -> -80.134 | ... AE93: =S93 -> 164.493
B94: Total Book Capitalization | C94: =SUM(C91:C93) -> 5830.195 | D94: =SUM(D91:D93) -> 5352.235 | E94: =SUM(E91:E93) -> 5214.051 | F94: =SUM(F91:F93) -> 4573.442 | G94: =SUM(G91:G93) -> 2130.366 | I94: =SUM(I91:I93) -> 4982.346 | J94: =SUM(J91:J93) -> 4871.172 | K94: =SUM(K91:K93) -> 4671.045 | L94: =SUM(L91:L93) -> 4573.442 | M94: =SUM(M91:M93) -> 4394.057 | N94: =SUM(N91:N93) -> 4128.562 | O94: =SUM(O91:O93) -> 3790.949 | P94: =SUM(P91:P93) -> 2130.366 | ... S94: =SUM(S91:S93) -> 1095.493 | U94: =SUM(U91:U93) -> 4982.346 | V94: =SUM(V91:V93) -> 4871.172 | W94: =SUM(W91:W93) -> 4671.045 | X94: =SUM(X91:X93) -> 4573.442 | Y94: =SUM(Y91:Y93) -> 4394.057 | Z94: =SUM(Z91:Z93) -> 4128.562 | AA94: =SUM(AA91:AA93) -> 3790.949 | AB94: =SUM(AB91:AB93) -> 2130.366 | ... AE94: =SUM(AE91:AE93) -> 1095.493
B96: Credit Metrics
B98: LTM Total Leverage | C98: =C91/C33 -> -6.9108814 | D98: =D91/D33 -> -26.647027 | E98: =E91/E33 -> 18.926278 | F98: =F91/F33 -> -57.878793 | G98: =G91/G33 -> -4.7743496 | L98: =SUM(L91/SUM(I33:L33)) -> -57.878793 | M98: =SUM(M91/SUM(J33:M33)) -> -24.392138 | N98: =SUM(N91/SUM(K33:N33)) -> -9.5874305 | O98: =SUM(O91/SUM(L33:O33)) -> -7.145652 | P98: =SUM(P91/SUM(M33:P33)) -> -4.7743496 | Q98: =SUM(Q91/SUM(N33:Q33)) -> -4.4264465 | R98: =SUM(R91/SUM(O33:R33)) -> -4.0453069 | S98: =SUM(S91/SUM(P33:S33)) -> -1.5472801 | U98: =U91/U33 -> -2.1774938 | V98: =V91/V33 -> -3.3169572 | W98: =W91/W33 -> -110.7736 | X98: =X91/X33 -> -21.108874 | Y98: =Y91/Y33 -> -13.316739 | Z98: =Z91/Z33 -> -7.779541 | AA98: =AA91/AA33 -> -7.145652 | AB98: =AB91/AB33 -> -4.7743496 | ... AE98: =AE91/AE33 -> -1.5472801
B99: LTM Net Leverage | C99: =SUM(C91-C56)/C33 -> -3.4564579 | D99: =SUM(D91-D56)/D33 -> -15.673648 | E99: =SUM(E91-E56)/E33 -> 11.930507 | F99: =SUM(F91-F56)/F33 -> -43.317609 | G99: =SUM(G91-G56)/G33 -> -2.8260413 | L99: =SUM(L91-L56)/SUM(I33:L33) -> -43.317609 | M99: =SUM(M91-M56)/SUM(J33:M33) -> -18.892163 | N99: =SUM(N91-N56)/SUM(K33:N33) -> -7.493691 | O99: =SUM(O91-O56)/SUM(L33:O33) -> -6.2249537 | P99: =SUM(P91-P56)/SUM(M33:P33) -> -2.8260413 | Q99: =SUM(Q91-Q56)/SUM(N33:Q33) -> -3.5904152 | R99: =SUM(R91-R56)/SUM(O33:R33) -> -3.3888189 | S99: =SUM(S91-S56)/SUM(P33:S33) -> -1.1309704 | U99: =SUM(U91-U56)/U33 -> -1.3792069 | V99: =SUM(V91-V56)/V33 -> -2.2334289 | W99: =SUM(W91-W56)/W33 -> -83.754647 | X99: =SUM(X91-X56)/X33 -> -15.79829 | Y99: =SUM(Y91-Y56)/Y33 -> -10.314061 | Z99: =SUM(Z91-Z56)/Z33 -> -6.0806153 | AA99: =SUM(AA91-AA56)/AA33 -> -6.2249537 | AB99: =SUM(AB91-AB56)/AB33 -> -2.8260413 | ... AE99: =SUM(AE91-AE56)/AE33 -> -1.1309704
B100: LTM Interest Coverage | C100: =C33/-C38 -> -6.4091443 | D100: =D33/-D38 -> -0.89684133 | E100: =E33/-E38 -> 1.7912009 | F100: =F33/-F38 -> -0.42939009 | G100: =G33/-G38 -> -2.6278613 | L100: {=SUM(I33:L33)/SUM(-I38:L38)} -> -0.42939009 | M100: {=SUM(J33:M33)/SUM(-J38:M38)} -> -0.95060775 | N100: {=SUM(K33:N33)/SUM(-K38:N38)} -> -2.2687158 | O100: {=SUM(L33:O33)/SUM(-L38:O38)} -> -2.8261067 | P100: {=SUM(M33:P33)/SUM(-M38:P38)} -> -2.6278613 | Q100: {=SUM(N33:Q33)/SUM(-N38:Q38)} -> -2.8317519 | R100: {=SUM(O33:R33)/SUM(-O38:R38)} -> -3.4648626 | S100: {=SUM(P33:S33)/SUM(-P38:S38)} -> -3.4234824 | U100: =U33/-U38 -> -50.410732 | V100: =V33/-V38 -> -14.75637 | W100: =W33/-W38 -> -0.29772238 | X100: =X33/-X38 -> -1.1773522 | Y100: =Y33/-Y38 -> -1.7412188 | Z100: =Z33/-Z38 -> -2.7959432 | AA100: =AA33/-AA38 -> -2.8261067 | AB100: =AB33/-AB38 -> -2.6278613 | ... AE100: =AE33/-AE38 -> -3.4234824
B101: LTM Debt Service Coverage | C101: {=SUM(C33+C36)/SUM(-C37:C38)} -> -14.457008 | D101: {=SUM(D33+D36)/SUM(-D37:D38)} -> -14.553106 | E101: {=SUM(E33+E36)/SUM(-E37:E38)} -> -0.42037611 | F101: {=SUM(F33+F36)/SUM(-F37:F38)} -> -2.9848758 | G101: {=SUM(G33+G36)/SUM(-G37:G38)} -> -3.1933124 | L101: {=SUM(I33:L33+I36:L36)/SUM(-I37:L38)} -> -2.9848758 | M101: {=SUM(J33:M33+J36:M36)/SUM(-J37:M38)} -> -3.527119 | N101: {=SUM(K33:N33+K36:N36)/SUM(-K37:N38)} -> -4.2306902 | O101: {=SUM(L33:O33+L36:O36)/SUM(-L37:O38)} -> -3.5067634 | P101: {=SUM(M33:P33+M36:P36)/SUM(-M37:P38)} -> -3.1933124 | Q101: {=SUM(N33:Q33+N36:Q36)/SUM(-N37:Q38)} -> -3.0567361 | R101: {=SUM(O33:R33+O36:R36)/SUM(-O37:R38)} -> -3.9072826 | S101: {=SUM(P33:S33+P36:S36)/SUM(-P37:S38)} -> -3.7724303 | U101: {=SUM(U33+U36)/SUM(-U37:U38)} -> -51.551086 | V101: {=SUM(V33+V36)/SUM(-V37:V38)} -> -16.359976 | W101: {=SUM(W33+W36)/SUM(-W37:W38)} -> -3.4978625 | X101: {=SUM(X33+X36)/SUM(-X37:X38)} -> -3.9657051 | Y101: {=SUM(Y33+Y36)/SUM(-Y37:Y38)} -> -4.5508786 | Z101: {=SUM(Z33+Z36)/SUM(-Z37:Z38)} -> -4.8712734 | AA101: {=SUM(AA33+AA36)/SUM(-AA37:AA38)} -> -3.5067634 | AB101: {=SUM(AB33+AB36)/SUM(-AB37:AB38)} -> -3.1933124 | ... AE101: {=SUM(AE33+AE36)/SUM(-AE37:AE38)} -> -3.7724303
B102: LTM Fixed Charge Coverage | C102: {=SUM(C33)/SUM(-C36:C38)} -> -1.135125 | D102: {=SUM(D33)/SUM(-D36:D38)} -> -0.51317112 | E102: {=SUM(E33)/SUM(-E36:E38)} -> 0.55792083 | F102: {=SUM(F33)/SUM(-F36:F38)} -> -0.164555 | G102: {=SUM(G33)/SUM(-G36:G38)} -> -1.5927448 | L102: {=SUM(I33:L33)/SUM(-I36:L38)} -> -0.164555 | M102: {=SUM(J33:M33)/SUM(-J36:M38)} -> -0.37344402 | N102: {=SUM(K33:N33)/SUM(-K36:N38)} -> -1.1140999 | O102: {=SUM(L33:O33)/SUM(-L36:O38)} -> -1.5020538 | P102: {=SUM(M33:P33)/SUM(-M36:P38)} -> -1.5927448 | Q102: {=SUM(N33:Q33)/SUM(-N36:Q38)} -> -2.1782398 | R102: {=SUM(O33:R33)/SUM(-O36:R38)} -> -2.4938993 | S102: {=SUM(P33:S33)/SUM(-P36:S38)} -> -2.664693 | U102: {=SUM(U33)/SUM(-U36:U38)} -> -17.34919 | V102: {=SUM(V33)/SUM(-V36:V38)} -> -5.0835937 | W102: {=SUM(W33)/SUM(-W36:W38)} -> -0.10813387 | X102: {=SUM(X33)/SUM(-X36:X38)} -> -0.45119624 | Y102: {=SUM(Y33)/SUM(-Y36:Y38)} -> -0.6840337 | Z102: {=SUM(Z33)/SUM(-Z36:Z38)} -> -1.3730058 | AA102: {=SUM(AA33)/SUM(-AA36:AA38)} -> -1.5020538 | AB102: {=SUM(AB33)/SUM(-AB36:AB38)} -> -1.5927448 | ... AE102: {=SUM(AE33)/SUM(-AE36:AE38)} -> -2.664693
B103: Debt-to-Book Capitalization | C103: =C94/C91 -> 1.6283187 | D103: =D94/D91 -> 1.6528426 | E103: =E94/E91 -> 1.4314878 | F103: =F94/F91 -> 1.3298369 | G103: =G94/G91 -> 0.96374847 | L103: =L94/L91 -> 1.3298369 | M103: =M94/M91 -> 1.2954941 | N103: =N94/N91 -> 1.2439549 | O103: =O94/O91 -> 1.1532456 | P103: =P94/P91 -> 0.96374847 | Q103: =Q94/Q91 -> 1.2802514 | R103: =R94/R91 -> 1.1909303 | S103: =S94/S91 -> 1.1766842 | U103: =U94/U91 -> 1.4184615 | V103: =V94/V91 -> 1.4326555 | W103: =W94/W91 -> 1.3922638 | X103: =X94/X91 -> 1.3298369 | Y103: =Y94/Y91 -> 1.2954941 | Z103: =Z94/Z91 -> 1.2439549 | AA103: =AA94/AA91 -> 1.1532456 | AB103: =AB94/AB91 -> 0.96374847 | ... AE103: =AE94/AE91 -> 1.1766842
