Workbook

Sheet Historical Financials
B2: Best Buy Co Inc (NASDAQ: BBY)
B3: Historical Financials
B4: ($ In Millions, except EPS)
A6: X | B6: Income Statement | C6: FYE | F6: FYE | J6: Quarterly | P6: Quarterly | AF6: LTM | AL6: Variance
B7: Fiscal Period | C7: 2020 | D7: 2021 | E7: 2022 | F7: 2023 | G7: 2024 | H7: 2025 | J7: 1Q23 | K7: 2Q23 | L7: 3Q23 | M7: 4Q23 | N7: 1Q24 | O7: 2Q24 | P7: 3Q24 | Q7: 4Q24 | R7: 1Q25 | S7: 2Q25 | T7: 3Q25 | U7: 4Q25 | V7: 1Q26 | W7: 2Q26 | X7: 3Q26 | Z7: =N7 -> 1Q24 | AA7: =O7 -> 2Q24 | AB7: =P7 -> 3Q24 | AC7: =Q7 -> 4Q24 | AD7: =R7 -> 1Q25 | AE7: =S7 -> 2Q25 | AF7: =T7 -> 3Q25 | AG7: =U7 -> 4Q25 | ... AJ7: =X7 -> 3Q26
B8: Fiscal Period End Date | C8: 43862 | D8: 44226 | E8: 44590 | F8: 44954 | G8: 45325 | H8: 45689 | J8: 44681 | K8: 44772 | L8: 44863 | M8: =F8 -> 44954 | N8: 45045 | O8: 45136 | P8: 45227 | Q8: =G8 -> 45325 | R8: 45416 | S8: 45507 | T8: 45598 | U8: =H8 -> 45689 | V8: 45780 | W8: 45871 | X8: 45962 | Z8: =N8 -> 45045 | AA8: =O8 -> 45136 | AB8: =P8 -> 45227 | AC8: =Q8 -> 45325 | AD8: =R8 -> 45416 | AE8: =S8 -> 45507 | AF8: =T8 -> 45598 | AG8: =U8 -> 45689 | ... AJ8: =X8 -> 45962
B10: Consolidated Revenue | C10: 43638 | D10: 47262 | E10: 51761 | F10: 46298 | G10: 43452 | H10: 41528 | J10: 10647 | K10: 10329 | L10: 10587 | M10: =SUM(F10-SUM(J10:L10)) -> 14735 | N10: 9467 | O10: 9583 | P10: 9756 | Q10: =SUM(G10-SUM(N10:P10)) -> 14646 | R10: 8847 | S10: 9288 | T10: 9445 | U10: =SUM(H10-SUM(R10:T10)) -> 13948 | V10: 8767 | W10: 9438 | X10: 9672 | Z10: =SUM(K10:N10) -> 45118 | AA10: =SUM(L10:O10) -> 44372 | AB10: =SUM(M10:P10) -> 43541 | AC10: =SUM(N10:Q10) -> 43452 | AD10: =SUM(O10:R10) -> 42832 | AE10: =SUM(P10:S10) -> 42537 | AF10: =SUM(Q10:T10) -> 42226 | AG10: =SUM(R10:U10) -> 41528 | ... AJ10: =SUM(U10:X10) -> 41825 | AL10: =SUM(AJ10/AF10)-1 -> -0.0094965187
B11: Total Revenue | C11: =+SUM(C10:C10) -> 43638 | D11: =+SUM(D10:D10) -> 47262 | E11: =+SUM(E10:E10) -> 51761 | F11: =+SUM(F10:F10) -> 46298 | G11: =+SUM(G10:G10) -> 43452 | H11: =+SUM(H10:H10) -> 41528 | J11: =+SUM(J10:J10) -> 10647 | K11: =+SUM(K10:K10) -> 10329 | L11: =+SUM(L10:L10) -> 10587 | M11: =+SUM(M10:M10) -> 14735 | N11: =+SUM(N10:N10) -> 9467 | O11: =+SUM(O10:O10) -> 9583 | P11: =+SUM(P10:P10) -> 9756 | Q11: =+SUM(Q10:Q10) -> 14646 | ... X11: =+SUM(X10:X10) -> 9672 | Z11: =+SUM(Z10:Z10) -> 45118 | AA11: =+SUM(AA10:AA10) -> 44372 | AB11: =+SUM(AB10:AB10) -> 43541 | AC11: =+SUM(AC10:AC10) -> 43452 | AD11: =+SUM(AD10:AD10) -> 42832 | AE11: =+SUM(AE10:AE10) -> 42537 | AF11: =+SUM(AF10:AF10) -> 42226 | AG11: =+SUM(AG10:AG10) -> 41528 | ... AJ11: =+SUM(AJ10:AJ10) -> 41825 | AL11: =SUM(AJ11/AF11)-1 -> -0.0094965187
B13: Cost of Sales | C13: -33590 | D13: -36689 | E13: -40121 | F13: -36386 | G13: -33849 | H13: -32143 | J13: -8294 | K13: -8042 | L13: -8255 | M13: =SUM(F13-SUM(J13:L13)) -> -11795 | N13: -7317 | O13: -7363 | P13: -7524 | Q13: =SUM(G13-SUM(N13:P13)) -> -11645 | R13: -6783 | S13: -7102 | T13: -7228 | U13: =SUM(H13-SUM(R13:T13)) -> -11030 | V13: -6718 | W13: -7244 | X13: -7424 | Z13: =SUM(K13:N13) -> -35409 | AA13: =SUM(L13:O13) -> -34730 | AB13: =SUM(M13:P13) -> -33999 | AC13: =SUM(N13:Q13) -> -33849 | AD13: =SUM(O13:R13) -> -33315 | AE13: =SUM(P13:S13) -> -33054 | AF13: =SUM(Q13:T13) -> -32758 | AG13: =SUM(R13:U13) -> -32143 | ... AJ13: =SUM(U13:X13) -> -32416 | AL13: =SUM(AJ13/AF13)-1 -> -0.010440198
B14: Gross Profit | C14: =+SUM(C11+SUM(C13:C13)) -> 10048 | D14: =+SUM(D11+SUM(D13:D13)) -> 10573 | E14: =+SUM(E11+SUM(E13:E13)) -> 11640 | F14: =+SUM(F11+SUM(F13:F13)) -> 9912 | G14: =+SUM(G11+SUM(G13:G13)) -> 9603 | H14: =+SUM(H11+SUM(H13:H13)) -> 9385 | J14: =+SUM(J11+SUM(J13:J13)) -> 2353 | K14: =+SUM(K11+SUM(K13:K13)) -> 2287 | L14: =+SUM(L11+SUM(L13:L13)) -> 2332 | M14: =+SUM(M11+SUM(M13:M13)) -> 2940 | N14: =+SUM(N11+SUM(N13:N13)) -> 2150 | O14: =+SUM(O11+SUM(O13:O13)) -> 2220 | P14: =+SUM(P11+SUM(P13:P13)) -> 2232 | Q14: =+SUM(Q11+SUM(Q13:Q13)) -> 3001 | ... X14: =+SUM(X11+SUM(X13:X13)) -> 2248 | Z14: =+SUM(Z11+SUM(Z13:Z13)) -> 9709 | AA14: =+SUM(AA11+SUM(AA13:AA13)) -> 9642 | AB14: =+SUM(AB11+SUM(AB13:AB13)) -> 9542 | AC14: =+SUM(AC11+SUM(AC13:AC13)) -> 9603 | AD14: =+SUM(AD11+SUM(AD13:AD13)) -> 9517 | AE14: =+SUM(AE11+SUM(AE13:AE13)) -> 9483 | AF14: =+SUM(AF11+SUM(AF13:AF13)) -> 9468 | AG14: =+SUM(AG11+SUM(AG13:AG13)) -> 9385 | ... AJ14: =+SUM(AJ11+SUM(AJ13:AJ13)) -> 9409 | AL14: =SUM(AJ14/AF14)-1 -> -0.0062315167
B15: Gross Margin (%) | C15: =C14/C11 -> 0.23025803 | D15: =D14/D11 -> 0.22371038 | E15: =E14/E11 -> 0.22487974 | F15: =F14/F11 -> 0.21409132 | G15: =G14/G11 -> 0.22100249 | H15: =H14/H11 -> 0.2259921 | J15: =J14/J11 -> 0.22100122 | K15: =K14/K11 -> 0.22141543 | L15: =L14/L11 -> 0.22027014 | M15: =M14/M11 -> 0.19952494 | N15: =N14/N11 -> 0.22710468 | O15: =O14/O11 -> 0.23166023 | P15: =P14/P11 -> 0.22878229 | Q15: =Q14/Q11 -> 0.20490236 | ... X15: =X14/X11 -> 0.23242349 | Z15: =Z14/Z11 -> 0.21519128 | AA15: =AA14/AA11 -> 0.2172992 | AB15: =AB14/AB11 -> 0.21914977 | AC15: =AC14/AC11 -> 0.22100249 | AD15: =AD14/AD11 -> 0.22219369 | AE15: =AE14/AE11 -> 0.22293533 | AF15: =AF14/AF11 -> 0.22422204 | AG15: =AG14/AG11 -> 0.2259921 | ... AJ15: =AJ14/AJ11 -> 0.22496115 | AL15: =SUM(AJ15-AF15)*1000 -> 0.73910435
B17: Selling, general and administrative expenses | C17: -7998 | D17: -7928 | E17: -8635 | F17: -7970 | G17: -7876 | H17: -7651 | J17: -1890 | K17: -1882 | L17: -1941 | M17: =SUM(F17-SUM(J17:L17)) -> -2257 | N17: -1848 | O17: -1879 | P17: -1878 | Q17: =SUM(G17-SUM(N17:P17)) -> -2271 | R17: -1737 | S17: -1810 | T17: -1871 | U17: =SUM(H17-SUM(R17:T17)) -> -2233 | V17: -1721 | W17: -1829 | X17: -1884 | Z17: =SUM(K17:N17) -> -7928 | AA17: =SUM(L17:O17) -> -7925 | AB17: =SUM(M17:P17) -> -7862 | AC17: =SUM(N17:Q17) -> -7876 | AD17: =SUM(O17:R17) -> -7765 | AE17: =SUM(P17:S17) -> -7696 | AF17: =SUM(Q17:T17) -> -7689 | AG17: =SUM(R17:U17) -> -7651 | ... AJ17: =SUM(U17:X17) -> -7667 | AL17: =SUM(AJ17/AF17)-1 -> -0.0028612303
B18: Restructuring, Impairments, and Other Charges | C18: -41 | D18: -254 | E18: 34 | F18: -147 | G18: -153 | H18: =-475 +3 -> -472 | J18: -1 | K18: -34 | L18: -26 | M18: =SUM(F18-SUM(J18:L18)) -> -86 | N18: 9 | O18: 7 | P18: 0 | Q18: =SUM(G18-SUM(N18:P18)) -> -169 | R18: -15 | S18: 7 | T18: 4 | U18: =SUM(H18-SUM(R18:T18)) -> -468 | V18: -109 | W18: -114 | X18: =-171+5 -> -166 | Z18: =SUM(K18:N18) -> -137 | AA18: =SUM(L18:O18) -> -96 | AB18: =SUM(M18:P18) -> -70 | AC18: =SUM(N18:Q18) -> -153 | AD18: =SUM(O18:R18) -> -177 | AE18: =SUM(P18:S18) -> -177 | AF18: =SUM(Q18:T18) -> -173 | AG18: =SUM(R18:U18) -> -472 | ... AJ18: =SUM(U18:X18) -> -857 | AL18: =SUM(AJ18/AF18)-1 -> 3.9537572
B19: Operating Profit | C19: =+SUM(C14+SUM(C17:C18)) -> 2009 | D19: =+SUM(D14+SUM(D17:D18)) -> 2391 | E19: =+SUM(E14+SUM(E17:E18)) -> 3039 | F19: =+SUM(F14+SUM(F17:F18)) -> 1795 | G19: =+SUM(G14+SUM(G17:G18)) -> 1574 | H19: =+SUM(H14+SUM(H17:H18)) -> 1262 | J19: =+SUM(J14+SUM(J17:J18)) -> 462 | K19: =+SUM(K14+SUM(K17:K18)) -> 371 | L19: =+SUM(L14+SUM(L17:L18)) -> 365 | M19: =+SUM(M14+SUM(M17:M18)) -> 597 | N19: =+SUM(N14+SUM(N17:N18)) -> 311 | O19: =+SUM(O14+SUM(O17:O18)) -> 348 | P19: =+SUM(P14+SUM(P17:P18)) -> 354 | Q19: =+SUM(Q14+SUM(Q17:Q18)) -> 561 | ... X19: =+SUM(X14+SUM(X17:X18)) -> 198 | Z19: =+SUM(Z14+SUM(Z17:Z18)) -> 1644 | AA19: =+SUM(AA14+SUM(AA17:AA18)) -> 1621 | AB19: =+SUM(AB14+SUM(AB17:AB18)) -> 1610 | AC19: =+SUM(AC14+SUM(AC17:AC18)) -> 1574 | AD19: =+SUM(AD14+SUM(AD17:AD18)) -> 1575 | AE19: =+SUM(AE14+SUM(AE17:AE18)) -> 1610 | AF19: =+SUM(AF14+SUM(AF17:AF18)) -> 1606 | AG19: =+SUM(AG14+SUM(AG17:AG18)) -> 1262 | ... AJ19: =+SUM(AJ14+SUM(AJ17:AJ18)) -> 885 | AL19: =SUM(AJ19/AF19)-1 -> -0.44894147
B20: Operating Margin (%) | C20: =C19/C11 -> 0.046037857 | D20: =D19/D11 -> 0.050590326 | E20: =E19/E11 -> 0.058712158 | F20: =F19/F11 -> 0.038770573 | G20: =G19/G11 -> 0.036223879 | H20: =H19/H11 -> 0.030389135 | J20: =J19/J11 -> 0.043392505 | K20: =K19/K11 -> 0.035918288 | L20: =L19/L11 -> 0.034476244 | M20: =M19/M11 -> 0.040515779 | N20: =N19/N11 -> 0.032850956 | O20: =O19/O11 -> 0.036314307 | P20: =P19/P11 -> 0.036285363 | Q20: =Q19/Q11 -> 0.038303974 | ... X20: =X19/X11 -> 0.020471464 | Z20: =Z19/Z11 -> 0.036437785 | AA20: =AA19/AA11 -> 0.036532047 | AB20: =AB19/AB11 -> 0.036976643 | AC20: =AC19/AC11 -> 0.036223879 | AD20: =AD19/AD11 -> 0.036771573 | AE20: =AE19/AE11 -> 0.037849402 | AF20: =AF19/AF11 -> 0.038033439 | AG20: =AG19/AG11 -> 0.030389135 | ... AJ20: =AJ19/AJ11 -> 0.021159594 | AL20: =SUM(AJ20-AF20)*1000 -> -16.873846
B22: Gain (Loss) on sale of subsidiary, net | C22: 1 | D22: 1 | E22: 0 | F22: 0 | G22: 21 | H22: 0 | J22: 0 | K22: 0 | L22: 0 | M22: =SUM(F22-SUM(J22:L22)) -> 0 | N22: 0 | O22: 21 | P22: 0 | Q22: =SUM(G22-SUM(N22:P22)) -> 0 | R22: 0 | S22: 0 | T22: 0 | U22: =SUM(H22-SUM(R22:T22)) -> 0 | V22: 0 | W22: -4 | X22: 0 | Z22: =SUM(K22:N22) -> 0 | AA22: =SUM(L22:O22) -> 21 | AB22: =SUM(M22:P22) -> 21 | AC22: =SUM(N22:Q22) -> 21 | AD22: =SUM(O22:R22) -> 21 | AE22: =SUM(P22:S22) -> 0 | AF22: =SUM(Q22:T22) -> 0 | AG22: =SUM(R22:U22) -> 0 | ... AJ22: =SUM(U22:X22) -> -4 | AL22: =SUM(AJ22/AF22)-1 -> #DIV/0!
B23: Investment income and other | C23: 47 | D23: 37 | E23: 10 | F23: 28 | G23: 78 | H23: 84 | J23: -5 | K23: 3 | L23: 4 | M23: =SUM(F23-SUM(J23:L23)) -> 26 | N23: 21 | O23: 12 | P23: 8 | Q23: =SUM(G23-SUM(N23:P23)) -> 37 | R23: 25 | S23: 21 | T23: 19 | U23: =SUM(H23-SUM(R23:T23)) -> 19 | V23: 15 | W23: 18 | X23: 19 | Z23: =SUM(K23:N23) -> 54 | AA23: =SUM(L23:O23) -> 63 | AB23: =SUM(M23:P23) -> 67 | AC23: =SUM(N23:Q23) -> 78 | AD23: =SUM(O23:R23) -> 82 | AE23: =SUM(P23:S23) -> 91 | AF23: =SUM(Q23:T23) -> 102 | AG23: =SUM(R23:U23) -> 84 | ... AJ23: =SUM(U23:X23) -> 71 | AL23: =SUM(AJ23/AF23)-1 -> -0.30392157
B24: Interest Income (expense) | C24: -64 | D24: -52 | E24: -25 | F24: -35 | G24: -52 | H24: -51 | J24: -6 | K24: -7 | L24: -10 | M24: =SUM(F24-SUM(J24:L24)) -> -12 | N24: -12 | O24: -12 | P24: -14 | Q24: =SUM(G24-SUM(N24:P24)) -> -14 | R24: -12 | S24: -13 | T24: -13 | U24: =SUM(H24-SUM(R24:T24)) -> -13 | V24: -12 | W24: -12 | X24: -12 | Z24: =SUM(K24:N24) -> -41 | AA24: =SUM(L24:O24) -> -46 | AB24: =SUM(M24:P24) -> -50 | AC24: =SUM(N24:Q24) -> -52 | AD24: =SUM(O24:R24) -> -52 | AE24: =SUM(P24:S24) -> -53 | AF24: =SUM(Q24:T24) -> -52 | AG24: =SUM(R24:U24) -> -51 | ... AJ24: =SUM(U24:X24) -> -49 | AL24: =SUM(AJ24/AF24)-1 -> -0.057692308
B25: Earnings before income tax expense and equity in income of affiliates | C25: =SUM(C22:C24)+C19 -> 1993 | D25: =SUM(D22:D24)+D19 -> 2377 | E25: =SUM(E22:E24)+E19 -> 3024 | F25: =SUM(F22:F24)+F19 -> 1788 | G25: =SUM(G22:G24)+G19 -> 1621 | H25: =SUM(H22:H24)+H19 -> 1295 | J25: =SUM(J22:J24)+J19 -> 451 | K25: =SUM(K22:K24)+K19 -> 367 | L25: =SUM(L22:L24)+L19 -> 359 | M25: =SUM(M22:M24)+M19 -> 611 | N25: =SUM(N22:N24)+N19 -> 320 | O25: =SUM(O22:O24)+O19 -> 369 | P25: =SUM(P22:P24)+P19 -> 348 | Q25: =SUM(Q22:Q24)+Q19 -> 584 | ... X25: =SUM(X22:X24)+X19 -> 205 | Z25: =SUM(Z22:Z24)+Z19 -> 1657 | AA25: =SUM(AA22:AA24)+AA19 -> 1659 | AB25: =SUM(AB22:AB24)+AB19 -> 1648 | AC25: =SUM(AC22:AC24)+AC19 -> 1621 | AD25: =SUM(AD22:AD24)+AD19 -> 1626 | AE25: =SUM(AE22:AE24)+AE19 -> 1648 | AF25: =SUM(AF22:AF24)+AF19 -> 1656 | AG25: =SUM(AG22:AG24)+AG19 -> 1295 | ... AJ25: =SUM(AJ22:AJ24)+AJ19 -> 903 | AL25: =SUM(AJ25/AF25)-1 -> -0.45471014
B26: EBT Margin (%) | C26: =C25/C11 -> 0.045671204 | D26: =D25/D11 -> 0.050294105 | E26: =E25/E11 -> 0.058422364 | F26: =F25/F11 -> 0.038619379 | G26: =G25/G11 -> 0.037305533 | H26: =H25/H11 -> 0.03118378 | J26: =J25/J11 -> 0.04235935 | K26: =K25/K11 -> 0.035531029 | L26: =L25/L11 -> 0.033909512 | M26: =M25/M11 -> 0.041465898 | N26: =N25/N11 -> 0.033801627 | O26: =O25/O11 -> 0.038505687 | P26: =P25/P11 -> 0.035670357 | Q26: =Q25/Q11 -> 0.039874368 | ... X26: =X25/X11 -> 0.021195203 | Z26: =Z25/Z11 -> 0.036725919 | AA26: =AA25/AA11 -> 0.037388443 | AB26: =AB25/AB11 -> 0.037849383 | AC26: =AC25/AC11 -> 0.037305533 | AD26: =AD25/AD11 -> 0.037962271 | AE26: =AE25/AE11 -> 0.038742742 | AF26: =AF25/AF11 -> 0.039217544 | AG26: =AG25/AG11 -> 0.03118378 | ... AJ26: =AJ25/AJ11 -> 0.021589958 | AL26: =SUM(AJ26-AF26)*1000 -> -17.627586
B28: Income tax expense | C28: -452 | D28: -579 | E28: -574 | F28: -370 | G28: -381 | H28: -372 | J28: -110 | K28: -58 | L28: -84 | M28: =SUM(F28-SUM(J28:L28)) -> -118 | N28: -75 | O28: -96 | P28: -86 | Q28: =SUM(G28-SUM(N28:P28)) -> -124 | R28: -80 | S28: -101 | T28: -85 | U28: =SUM(H28-SUM(R28:T28)) -> -106 | V28: -19 | W28: -68 | X28: -64 | Z28: =SUM(K28:N28) -> -335 | AA28: =SUM(L28:O28) -> -373 | AB28: =SUM(M28:P28) -> -375 | AC28: =SUM(N28:Q28) -> -381 | AD28: =SUM(O28:R28) -> -386 | AE28: =SUM(P28:S28) -> -391 | AF28: =SUM(Q28:T28) -> -390 | AG28: =SUM(R28:U28) -> -372 | ... AJ28: =SUM(U28:X28) -> -257 | AL28: =SUM(AJ28/AF28)-1 -> -0.34102564
B29: Equity in income of affiliates | C29: 0 | D29: 0 | E29: 4 | F29: 1 | G29: 1 | H29: 4 | J29: 0 | K29: -3 | L29: 2 | M29: =SUM(F29-SUM(J29:L29)) -> 2 | N29: -1 | O29: 1 | P29: 1 | Q29: =SUM(G29-SUM(N29:P29)) -> 0 | R29: 1 | S29: 1 | T29: 2 | U29: =SUM(H29-SUM(R29:T29)) -> 0 | V29: -1 | W29: 1 | X29: -1 | Z29: =SUM(K29:N29) -> 0 | AA29: =SUM(L29:O29) -> 4 | AB29: =SUM(M29:P29) -> 3 | AC29: =SUM(N29:Q29) -> 1 | AD29: =SUM(O29:R29) -> 3 | AE29: =SUM(P29:S29) -> 3 | AF29: =SUM(Q29:T29) -> 4 | AG29: =SUM(R29:U29) -> 4 | ... AJ29: =SUM(U29:X29) -> -1 | AL29: =SUM(AJ29/AF29)-1 -> -1.25
B30: Net loss | C30: =SUM(C25+SUM(C28:C29)) -> 1541 | D30: =SUM(D25+SUM(D28:D29)) -> 1798 | E30: =SUM(E25+SUM(E28:E29)) -> 2454 | F30: =SUM(F25+SUM(F28:F29)) -> 1419 | G30: =SUM(G25+SUM(G28:G29)) -> 1241 | H30: =SUM(H25+SUM(H28:H29)) -> 927 | J30: =SUM(J25+SUM(J28:J29)) -> 341 | K30: =SUM(K25+SUM(K28:K29)) -> 306 | L30: =SUM(L25+SUM(L28:L29)) -> 277 | M30: =SUM(M25+SUM(M28:M29)) -> 495 | N30: =SUM(N25+SUM(N28:N29)) -> 244 | O30: =SUM(O25+SUM(O28:O29)) -> 274 | P30: =SUM(P25+SUM(P28:P29)) -> 263 | Q30: =SUM(Q25+SUM(Q28:Q29)) -> 460 | ... X30: =SUM(X25+SUM(X28:X29)) -> 140 | Z30: =SUM(Z25+SUM(Z28:Z29)) -> 1322 | AA30: =SUM(AA25+SUM(AA28:AA29)) -> 1290 | AB30: =SUM(AB25+SUM(AB28:AB29)) -> 1276 | AC30: =SUM(AC25+SUM(AC28:AC29)) -> 1241 | AD30: =SUM(AD25+SUM(AD28:AD29)) -> 1243 | AE30: =SUM(AE25+SUM(AE28:AE29)) -> 1260 | AF30: =SUM(AF25+SUM(AF28:AF29)) -> 1270 | AG30: =SUM(AG25+SUM(AG28:AG29)) -> 927 | ... AJ30: =SUM(AJ25+SUM(AJ28:AJ29)) -> 645 | AL30: =SUM(AJ30/AF30)-1 -> -0.49212598
B31: Net Margin (%) | C31: =C30/C11 -> 0.035313259 | D31: =D30/D11 -> 0.038043248 | E31: =E30/E11 -> 0.047410212 | F31: =F30/F11 -> 0.030649272 | G31: =G30/G11 -> 0.02856025 | H31: =H30/H11 -> 0.022322289 | J31: =J30/J11 -> 0.032027801 | K31: =K30/K11 -> 0.029625327 | L31: =L30/L11 -> 0.026164164 | M31: =M30/M11 -> 0.033593485 | N31: =N30/N11 -> 0.02577374 | O31: =O30/O11 -> 0.028592299 | P31: =P30/P11 -> 0.02695777 | Q31: =Q30/Q11 -> 0.031407893 | ... X31: =X30/X11 -> 0.014474773 | Z31: =Z30/Z11 -> 0.029300944 | AA31: =AA30/AA11 -> 0.029072388 | AB31: =AB30/AB11 -> 0.029305712 | AC31: =AC30/AC11 -> 0.02856025 | AD31: =AD30/AD11 -> 0.029020359 | AE31: =AE30/AE11 -> 0.029621271 | AF31: =AF30/AF11 -> 0.030076256 | AG31: =AG30/AG11 -> 0.022322289 | ... AJ31: =AJ30/AJ11 -> 0.015421399 | AL31: =SUM(AJ31-AF31)*1000 -> -14.654858
B33: Basic shares | C33: 264.9 | D33: 259.6 | E33: 246.8 | F33: 224.8 | G33: 217.7 | H33: 215.2 | J33: 226.8 | K33: 225.4 | L33: 225.5 | M33: =F33 -> 224.8 | N33: 218.9 | O33: 218.6 | P33: 217.8 | Q33: =G33 -> 217.7 | R33: 216.2 | S33: 216 | T33: 214.8 | U33: =H33 -> 215.2 | V33: 212 | W33: 211.5 | X33: 210.7 | Z33: =N33 -> 218.9 | AA33: =O33 -> 218.6 | AB33: =P33 -> 217.8 | AC33: =Q33 -> 217.7 | AD33: =R33 -> 216.2 | AE33: =S33 -> 216 | AF33: =T33 -> 214.8 | AG33: =U33 -> 215.2 | ... AJ33: =X33 -> 210.7 | AL33: =SUM(AJ33/AF33)-1 -> -0.019087523
B34: Basic EPS | C34: =C30/C33 -> 5.8172895 | D34: =D30/D33 -> 6.9260401 | E34: =E30/E33 -> 9.9432739 | F34: =F30/F33 -> 6.3122776 | G34: =G30/G33 -> 5.7005053 | H34: =H30/H33 -> 4.3076208 | J34: =J30/J33 -> 1.5035273 | K34: =K30/K33 -> 1.3575865 | L34: =L30/L33 -> 1.2283814 | M34: =M30/M33 -> 2.2019573 | N34: =N30/N33 -> 1.1146642 | O34: =O30/O33 -> 1.2534309 | P34: =P30/P33 -> 1.2075298 | Q34: =Q30/Q33 -> 2.1129995 | ... X34: =X30/X33 -> 0.66445183 | Z34: =Z30/Z33 -> 6.0392873 | AA34: =AA30/AA33 -> 5.9011894 | AB34: =AB30/AB33 -> 5.8585859 | AC34: =AC30/AC33 -> 5.7005053 | AD34: =AD30/AD33 -> 5.7493062 | AE34: =AE30/AE33 -> 5.8333333 | AF34: =AF30/AF33 -> 5.9124767 | AG34: =AG30/AG33 -> 4.3076208 | ... AJ34: =AJ30/AJ33 -> 3.0612245 | AL34: =SUM(AJ34/AF34)-1 -> -0.48224329
B36: Fully Diluted Shares | C36: 268.1 | D36: 263 | E36: 249.3 | F36: 225.7 | G36: 218.5 | H36: 216.6 | J36: 228.4 | K36: 226.1 | L36: 226.2 | M36: =F36 -> 225.7 | N36: 219.9 | O36: 219 | P36: 218.3 | Q36: =G36 -> 218.5 | R36: 217.2 | S36: 217.1 | T36: 216.7 | U36: =H36 -> 216.6 | V36: 213 | W36: 212 | X36: 212.1 | Z36: =N36 -> 219.9 | AA36: =O36 -> 219 | AB36: =P36 -> 218.3 | AC36: =Q36 -> 218.5 | AD36: =R36 -> 217.2 | AE36: =S36 -> 217.1 | AF36: =T36 -> 216.7 | AG36: =U36 -> 216.6 | ... AJ36: =X36 -> 212.1 | AL36: =SUM(AJ36/AF36)-1 -> -0.021227503
B37: Diluted EPS | C37: =C30/C36 -> 5.7478553 | D37: =D30/D36 -> 6.8365019 | E37: =E30/E36 -> 9.843562 | F37: =F30/F36 -> 6.2871068 | G37: =G30/G36 -> 5.6796339 | H37: =H30/H36 -> 4.2797784 | J37: =J30/J36 -> 1.4929947 | K37: =K30/K36 -> 1.3533835 | L37: =L30/L36 -> 1.22458 | M37: =M30/M36 -> 2.1931768 | N37: =N30/N36 -> 1.1095953 | O37: =O30/O36 -> 1.2511416 | P37: =P30/P36 -> 1.2047641 | Q37: =Q30/Q36 -> 2.1052632 | ... X37: =X30/X36 -> 0.66006601 | Z37: =Z30/Z36 -> 6.0118236 | AA37: =AA30/AA36 -> 5.890411 | AB37: =AB30/AB36 -> 5.8451672 | AC37: =AC30/AC36 -> 5.6796339 | AD37: =AD30/AD36 -> 5.7228361 | AE37: =AE30/AE36 -> 5.8037771 | AF37: =AF30/AF36 -> 5.8606368 | AG37: =AG30/AG36 -> 4.2797784 | ... AJ37: =AJ30/AJ36 -> 3.0410184 | AL37: =SUM(AJ37/AF37)-1 -> -0.48111127
A39: X | B39: Balance Sheet | C39: FYE | D39: FYE | E39: FYE | P39: Quarterly | AF39: LTM | AL39: Variance
B40: =B7 -> Fiscal Period | C40: =C7 -> 2020 | D40: =D7 -> 2021 | E40: =E7 -> 2022 | F40: =F7 -> 2023 | G40: =G7 -> 2024 | H40: =H7 -> 2025 | J40: =J7 -> 1Q23 | K40: =K7 -> 2Q23 | L40: =L7 -> 3Q23 | M40: =M7 -> 4Q23 | N40: =N7 -> 1Q24 | O40: =O7 -> 2Q24 | P40: =P7 -> 3Q24 | Q40: =Q7 -> 4Q24 | ... X40: =X7 -> 3Q26 | Z40: =Z7 -> 1Q24 | AA40: =AA7 -> 2Q24 | AB40: =AB7 -> 3Q24 | AC40: =AC7 -> 4Q24 | AD40: =AD7 -> 1Q25 | AE40: =AE7 -> 2Q25 | AF40: =AF7 -> 3Q25 | AG40: =AG7 -> 4Q25 | ... AJ40: =AJ7 -> 3Q26
B41: =B8 -> Fiscal Period End Date | C41: =C8 -> 43862 | D41: =D8 -> 44226 | E41: =E8 -> 44590 | F41: =F8 -> 44954 | G41: =G8 -> 45325 | H41: =H8 -> 45689 | J41: =J8 -> 44681 | K41: =K8 -> 44772 | L41: =L8 -> 44863 | M41: =M8 -> 44954 | N41: =N8 -> 45045 | O41: =O8 -> 45136 | P41: =P8 -> 45227 | Q41: =Q8 -> 45325 | ... X41: =X8 -> 45962 | Z41: =Z8 -> 45045 | AA41: =AA8 -> 45136 | AB41: =AB8 -> 45227 | AC41: =AC8 -> 45325 | AD41: =AD8 -> 45416 | AE41: =AE8 -> 45507 | AF41: =AF8 -> 45598 | AG41: =AG8 -> 45689 | ... AJ41: =AJ8 -> 45962
B43: Current Assets
B44: Cash and cash equivalents | C44: 2229 | D44: 5494 | E44: 2936 | F44: 1874 | G44: 1447 | H44: 1578 | J44: 640 | K44: 840 | L44: 932 | M44: =F44 -> 1874 | N44: 1030 | O44: 1093 | P44: 636 | Q44: =G44 -> 1447 | R44: 1214 | S44: 1387 | T44: 643 | U44: =H44 -> 1578 | V44: 1147 | W44: 1456 | X44: 923 | Z44: =N44 -> 1030 | AA44: =O44 -> 1093 | AB44: =P44 -> 636 | AC44: =Q44 -> 1447 | AD44: =R44 -> 1214 | AE44: =S44 -> 1387 | AF44: =T44 -> 643 | AG44: =U44 -> 1578 | ... AJ44: =X44 -> 923 | AL44: =SUM(AJ44/AF44)-1 -> 0.43545879
B45: Restricted Cash | C45: 126 | D45: 131 | E45: 269 | F45: 379 | G45: 346 | H45: 290 | J45: 320 | K45: 312 | L45: 361 | M45: =F45 -> 379 | N45: 402 | O45: 398 | P45: 423 | Q45: =G45 -> 346 | R45: 313 | S45: 311 | T45: 295 | U45: =H45 -> 290 | V45: 288 | W45: 257 | X45: 271 | Z45: =N45 -> 402 | AA45: =O45 -> 398 | AB45: =P45 -> 423 | AC45: =Q45 -> 346 | AD45: =R45 -> 313 | AE45: =S45 -> 311 | AF45: =T45 -> 295 | AG45: =U45 -> 290 | ... AJ45: =X45 -> 271 | AL45: =SUM(AJ45/AF45)-1 -> -0.081355932
B46: Receivables, net | C46: 1149 | D46: 1061 | E46: 1042 | F46: 1141 | G46: 939 | H46: 1044 | J46: 804 | K46: 840 | L46: 1050 | M46: =F46 -> 1141 | N46: 860 | O46: 856 | P46: 901 | Q46: =G46 -> 939 | R46: 770 | S46: 871 | T46: 932 | U46: =H46 -> 1044 | V46: 744 | W46: 917 | X46: 1017 | Z46: =N46 -> 860 | AA46: =O46 -> 856 | AB46: =P46 -> 901 | AC46: =Q46 -> 939 | AD46: =R46 -> 770 | AE46: =S46 -> 871 | AF46: =T46 -> 932 | AG46: =U46 -> 1044 | ... AJ46: =X46 -> 1017 | AL46: =SUM(AJ46/AF46)-1 -> 0.091201717
B47: Merchandise inventories | C47: 5174 | D47: 5612 | E47: 5965 | F47: 5140 | G47: 4958 | H47: 5085 | J47: 6258 | K47: 6043 | L47: 7294 | M47: =F47 -> 5140 | N47: 5219 | O47: 5651 | P47: 7562 | Q47: =G47 -> 4958 | R47: 5225 | S47: 5706 | T47: 7806 | U47: =H47 -> 5085 | V47: 5194 | W47: 5816 | X47: 7993 | Z47: =N47 -> 5219 | AA47: =O47 -> 5651 | AB47: =P47 -> 7562 | AC47: =Q47 -> 4958 | AD47: =R47 -> 5225 | AE47: =S47 -> 5706 | AF47: =T47 -> 7806 | AG47: =U47 -> 5085 | ... AJ47: =X47 -> 7993 | AL47: =SUM(AJ47/AF47)-1 -> 0.023955931
B48: Other current assets | C48: =305-C45 -> 179 | D48: =373-D45 -> 242 | E48: =596-E45 -> 327 | F48: =647-F45 -> 268 | G48: =553-G45 -> 207 | H48: =517-H45 -> 227 | J48: =613-J45 -> 293 | K48: =621-K45 -> 309 | L48: =646-L45 -> 285 | M48: =F48 -> 268 | N48: =653-N45 -> 251 | O48: =704-O45 -> 306 | P48: =766-P45 -> 343 | Q48: =G48 -> 207 | R48: =544-R45 -> 231 | S48: =598-S45 -> 287 | T48: =574-T45 -> 279 | U48: =H48 -> 227 | V48: =500-V45 -> 212 | W48: =688-W45 -> 431 | X48: =640-X45 -> 369 | Z48: =N48 -> 251 | AA48: =O48 -> 306 | AB48: =P48 -> 343 | AC48: =Q48 -> 207 | AD48: =R48 -> 231 | AE48: =S48 -> 287 | AF48: =T48 -> 279 | AG48: =U48 -> 227 | ... AJ48: =X48 -> 369 | AL48: =SUM(AJ48/AF48)-1 -> 0.32258065
B49: Total Current Assets | C49: =SUM(C44:C48) -> 8857 | D49: =SUM(D44:D48) -> 12540 | E49: =SUM(E44:E48) -> 10539 | F49: =SUM(F44:F48) -> 8802 | G49: =SUM(G44:G48) -> 7897 | H49: =SUM(H44:H48) -> 8224 | J49: =SUM(J44:J48) -> 8315 | K49: =SUM(K44:K48) -> 8344 | L49: =SUM(L44:L48) -> 9922 | M49: =SUM(M44:M48) -> 8802 | N49: =SUM(N44:N48) -> 7762 | O49: =SUM(O44:O48) -> 8304 | P49: =SUM(P44:P48) -> 9865 | Q49: =SUM(Q44:Q48) -> 7897 | ... X49: =SUM(X44:X48) -> 10573 | Z49: =SUM(Z44:Z48) -> 7762 | AA49: =SUM(AA44:AA48) -> 8304 | AB49: =SUM(AB44:AB48) -> 9865 | AC49: =SUM(AC44:AC48) -> 7897 | AD49: =SUM(AD44:AD48) -> 7753 | AE49: =SUM(AE44:AE48) -> 8562 | AF49: =SUM(AF44:AF48) -> 9955 | AG49: =SUM(AG44:AG48) -> 8224 | ... AJ49: =SUM(AJ44:AJ48) -> 10573 | AL49: =SUM(AJ49/AF49)-1 -> 0.062079357
B51: Non-Current Assets
B52: Net property and equipment | C52: 2328 | D52: 2260 | E52: 2250 | F52: 2352 | G52: 2260 | H52: 2122 | J52: 2251 | K52: 2319 | L52: 2373 | M52: =F52 -> 2352 | N52: 2321 | O52: 2305 | P52: 2313 | Q52: =G52 -> 2260 | R52: 2196 | S52: 2183 | T52: 2196 | U52: =H52 -> 2122 | V52: 2089 | W52: 2046 | X52: 2037 | Z52: =N52 -> 2321 | AA52: =O52 -> 2305 | AB52: =P52 -> 2313 | AC52: =Q52 -> 2260 | AD52: =R52 -> 2196 | AE52: =S52 -> 2183 | AF52: =T52 -> 2196 | AG52: =U52 -> 2122 | ... AJ52: =X52 -> 2037 | AL52: =SUM(AJ52/AF52)-1 -> -0.072404372
B53: Operating lease assets | C53: 2709 | D53: 2612 | E53: 2654 | F53: 2746 | G53: 2758 | H53: 2833 | J53: 2704 | K53: 2796 | L53: 2799 | M53: =F53 -> 2746 | N53: 2694 | O53: 2813 | P53: 2827 | Q53: =G53 -> 2758 | R53: 2771 | S53: 2860 | T53: 2842 | U53: =H53 -> 2833 | V53: 2821 | W53: 2816 | X53: 2838 | Z53: =N53 -> 2694 | AA53: =O53 -> 2813 | AB53: =P53 -> 2827 | AC53: =Q53 -> 2758 | AD53: =R53 -> 2771 | AE53: =S53 -> 2860 | AF53: =T53 -> 2842 | AG53: =U53 -> 2833 | ... AJ53: =X53 -> 2838 | AL53: =SUM(AJ53/AF53)-1 -> -0.0014074595
B54: Goodwill | C54: 984 | D54: 986 | E54: 1384 | F54: 1383 | G54: 1383 | H54: 908 | J54: 1385 | K54: 1385 | L54: 1383 | M54: =F54 -> 1383 | N54: 1383 | O54: 1383 | P54: 1383 | Q54: =G54 -> 1383 | R54: 1383 | S54: 1383 | T54: 1383 | U54: =H54 -> 908 | V54: 908 | W54: 908 | X54: 790 | Z54: =N54 -> 1383 | AA54: =O54 -> 1383 | AB54: =P54 -> 1383 | AC54: =Q54 -> 1383 | AD54: =R54 -> 1383 | AE54: =S54 -> 1383 | AF54: =T54 -> 1383 | AG54: =U54 -> 908 | ... AJ54: =X54 -> 790 | AL54: =SUM(AJ54/AF54)-1 -> -0.42877802
B55: Other assets | C55: 713 | D55: 669 | E55: 677 | F55: 520 | G55: 669 | H55: 695 | J55: 596 | K55: 575 | L55: 544 | M55: =F55 -> 520 | N55: 528 | O55: 513 | P55: 494 | Q55: =G55 -> 669 | R55: 649 | S55: 636 | T55: 642 | U55: =H55 -> 695 | V55: 725 | W55: 606 | X55: 548 | Z55: =N55 -> 528 | AA55: =O55 -> 513 | AB55: =P55 -> 494 | AC55: =Q55 -> 669 | AD55: =R55 -> 649 | AE55: =S55 -> 636 | AF55: =T55 -> 642 | AG55: =U55 -> 695 | ... AJ55: =X55 -> 548 | AL55: =SUM(AJ55/AF55)-1 -> -0.14641745
B56: Total Assets | C56: =SUM(C52:C55)+C49 -> 15591 | D56: =SUM(D52:D55)+D49 -> 19067 | E56: =SUM(E52:E55)+E49 -> 17504 | F56: =SUM(F52:F55)+F49 -> 15803 | G56: =SUM(G52:G55)+G49 -> 14967 | H56: =SUM(H52:H55)+H49 -> 14782 | J56: =SUM(J52:J55)+J49 -> 15251 | K56: =SUM(K52:K55)+K49 -> 15419 | L56: =SUM(L52:L55)+L49 -> 17021 | M56: =SUM(M52:M55)+M49 -> 15803 | N56: =SUM(N52:N55)+N49 -> 14688 | O56: =SUM(O52:O55)+O49 -> 15318 | P56: =SUM(P52:P55)+P49 -> 16882 | Q56: =SUM(Q52:Q55)+Q49 -> 14967 | ... X56: =SUM(X52:X55)+X49 -> 16786 | Z56: =SUM(Z52:Z55)+Z49 -> 14688 | AA56: =SUM(AA52:AA55)+AA49 -> 15318 | AB56: =SUM(AB52:AB55)+AB49 -> 16882 | AC56: =SUM(AC52:AC55)+AC49 -> 14967 | AD56: =SUM(AD52:AD55)+AD49 -> 14752 | AE56: =SUM(AE52:AE55)+AE49 -> 15624 | AF56: =SUM(AF52:AF55)+AF49 -> 17018 | AG56: =SUM(AG52:AG55)+AG49 -> 14782 | ... AJ56: =SUM(AJ52:AJ55)+AJ49 -> 16786 | AL56: =SUM(AJ56/AF56)-1 -> -0.013632624
B58: Current Liabilities
B59: Accounts payable | C59: 5288 | D59: 6979 | E59: 6803 | F59: 5687 | G59: 4637 | H59: 4980 | J59: 5492 | K59: 5406 | L59: 7056 | M59: =F59 -> 5687 | N59: 4874 | O59: 5471 | P59: 7133 | Q59: =G59 -> 4637 | R59: 4664 | S59: 5542 | T59: 7145 | U59: =H59 -> 4980 | V59: 4670 | W59: 5682 | X59: 7319 | Z59: =N59 -> 4874 | AA59: =O59 -> 5471 | AB59: =P59 -> 7133 | AC59: =Q59 -> 4637 | AD59: =R59 -> 4664 | AE59: =S59 -> 5542 | AF59: =T59 -> 7145 | AG59: =U59 -> 4980 | ... AJ59: =X59 -> 7319 | AL59: =SUM(AJ59/AF59)-1 -> 0.024352694
B60: Unredeemed gift card liabilities | C60: 281 | D60: 317 | E60: 316 | F60: 274 | G60: 253 | H60: 253 | J60: 284 | K60: 273 | L60: 273 | M60: =F60 -> 274 | N60: 256 | O60: 250 | P60: 245 | Q60: =G60 -> 253 | R60: 242 | S60: 243 | T60: 246 | U60: =H60 -> 253 | V60: 246 | W60: 230 | X60: 231 | Z60: =N60 -> 256 | AA60: =O60 -> 250 | AB60: =P60 -> 245 | AC60: =Q60 -> 253 | AD60: =R60 -> 242 | AE60: =S60 -> 243 | AF60: =T60 -> 246 | AG60: =U60 -> 253 | ... AJ60: =X60 -> 231 | AL60: =SUM(AJ60/AF60)-1 -> -0.06097561
B61: Deferred revenue | C61: 501 | D61: 711 | E61: 1103 | F61: 1116 | G61: 1000 | H61: 951 | J61: 1101 | K61: 1133 | L61: 1080 | M61: =F61 -> 1116 | N61: 1015 | O61: 996 | P61: 934 | Q61: =G61 -> 1000 | R61: 923 | S61: 940 | T61: 878 | U61: =H61 -> 951 | V61: 891 | W61: 889 | X61: 853 | Z61: =N61 -> 1015 | AA61: =O61 -> 996 | AB61: =P61 -> 934 | AC61: =Q61 -> 1000 | AD61: =R61 -> 923 | AE61: =S61 -> 940 | AF61: =T61 -> 878 | AG61: =U61 -> 951 | ... AJ61: =X61 -> 853 | AL61: =SUM(AJ61/AF61)-1 -> -0.028473804
B62: Accrued compensation and related expenses | C62: 410 | D62: 725 | E62: 845 | F62: 405 | G62: 486 | H62: 464 | J62: 336 | K62: 374 | L62: 363 | M62: =F62 -> 405 | N62: 364 | O62: 377 | P62: 309 | Q62: =G62 -> 486 | R62: 380 | S62: 347 | T62: 361 | U62: =H62 -> 464 | V62: 367 | W62: 448 | X62: 392 | Z62: =N62 -> 364 | AA62: =O62 -> 377 | AB62: =P62 -> 309 | AC62: =Q62 -> 486 | AD62: =R62 -> 380 | AE62: =S62 -> 347 | AF62: =T62 -> 361 | AG62: =U62 -> 464 | ... AJ62: =X62 -> 392 | AL62: =SUM(AJ62/AF62)-1 -> 0.085872576
B63: Accrued liabilities | C63: 906 | D63: 972 | E63: 946 | F63: 843 | G63: 902 | H63: 741 | J63: 771 | K63: 820 | L63: 744 | M63: =F63 -> 843 | N63: 759 | O63: 709 | P63: 760 | Q63: =G63 -> 902 | R63: 812 | S63: 756 | T63: 690 | U63: =H63 -> 741 | V63: 617 | W63: 684 | X63: 689 | Z63: =N63 -> 759 | AA63: =O63 -> 709 | AB63: =P63 -> 760 | AC63: =Q63 -> 902 | AD63: =R63 -> 812 | AE63: =S63 -> 756 | AF63: =T63 -> 690 | AG63: =U63 -> 741 | ... AJ63: =X63 -> 689 | AL63: =SUM(AJ63/AF63)-1 -> -0.0014492754
B64: Current portion of operating lease liabilities | C64: 660 | D64: 693 | E64: 648 | F64: 638 | G64: 618 | H64: 617 | J64: 636 | K64: 629 | L64: 638 | M64: =F64 -> 638 | N64: 625 | O64: 615 | P64: 614 | Q64: =G64 -> 618 | R64: 613 | S64: 610 | T64: 616 | U64: =H64 -> 617 | V64: 611 | W64: 610 | X64: 619 | Z64: =N64 -> 625 | AA64: =O64 -> 615 | AB64: =P64 -> 614 | AC64: =Q64 -> 618 | AD64: =R64 -> 613 | AE64: =S64 -> 610 | AF64: =T64 -> 616 | AG64: =U64 -> 617 | ... AJ64: =X64 -> 619 | AL64: =SUM(AJ64/AF64)-1 -> 0.0048701299
B65: Finance Lease Obligations, Current Portion | C65: 14 | D65: 14 | E65: 13 | F65: 16 | G65: 13 | H65: 10 | J65: 15 | K65: 15 | L65: 16 | M65: =F65 -> 16 | N65: 15 | O65: 15 | P65: 15 | Q65: =G65 -> 13 | R65: 15 | S65: 13 | T65: 12 | U65: =H65 -> 10 | V65: 10 | W65: 10 | X65: 10 | Z65: =N65 -> 15 | AA65: =O65 -> 15 | AB65: =P65 -> 15 | AC65: =Q65 -> 13 | AD65: =R65 -> 15 | AE65: =S65 -> 13 | AF65: =T65 -> 12 | AG65: =U65 -> 10 | ... AJ65: =X65 -> 10
B66: Current portion of long-term debt | C66: =14-C65 -> 0 | D66: =124-D65 -> 110 | E66: =13-E65 -> 0 | F66: =16-F65 -> 0 | G66: =13-G65 -> 0 | H66: =10-H65 -> 0 | J66: =15-J65 -> 0 | K66: =15-K65 -> 0 | L66: =16-L65 -> 0 | M66: =F66 -> 0 | N66: =15-N65 -> 0 | O66: =15-O65 -> 0 | P66: =15-P65 -> 0 | Q66: =G66 -> 0 | R66: =15-R65 -> 0 | S66: =13-S65 -> 0 | T66: =12-T65 -> 0 | U66: =H66 -> 0 | V66: =10-V65 -> 0 | W66: =10-W65 -> 0 | X66: =10-X65 -> 0 | Z66: =N66 -> 0 | AA66: =O66 -> 0 | AB66: =P66 -> 0 | AC66: =Q66 -> 0 | AD66: =R66 -> 0 | AE66: =S66 -> 0 | AF66: =T66 -> 0 | AG66: =U66 -> 0 | ... AJ66: =X66 -> 0 | AL66: =SUM(AJ66/AF66)-1 -> #DIV/0!
B67: Total Current Liabilities | C67: =SUM(C59:C66) -> 8060 | D67: =SUM(D59:D66) -> 10521 | E67: =SUM(E59:E66) -> 10674 | F67: =SUM(F59:F66) -> 8979 | G67: =SUM(G59:G66) -> 7909 | H67: =SUM(H59:H66) -> 8016 | J67: =SUM(J59:J66) -> 8635 | K67: =SUM(K59:K66) -> 8650 | L67: =SUM(L59:L66) -> 10170 | M67: =SUM(M59:M66) -> 8979 | N67: =SUM(N59:N66) -> 7908 | O67: =SUM(O59:O66) -> 8433 | P67: =SUM(P59:P66) -> 10010 | Q67: =SUM(Q59:Q66) -> 7909 | ... X67: =SUM(X59:X66) -> 10113 | Z67: =SUM(Z59:Z66) -> 7908 | AA67: =SUM(AA59:AA66) -> 8433 | AB67: =SUM(AB59:AB66) -> 10010 | AC67: =SUM(AC59:AC66) -> 7909 | AD67: =SUM(AD59:AD66) -> 7649 | AE67: =SUM(AE59:AE66) -> 8451 | AF67: =SUM(AF59:AF66) -> 9948 | AG67: =SUM(AG59:AG66) -> 8016 | ... AJ67: =SUM(AJ59:AJ66) -> 10113 | AL67: =SUM(AJ67/AF67)-1 -> 0.016586248
B69: Non-Current Liabilities
B70: Long-term operating lease liabilities | C70: 2138 | D70: 2012 | E70: 2061 | F70: 2164 | G70: 2199 | H70: 2282 | J70: 2121 | K70: 2221 | L70: 2216 | M70: =F70 -> 2164 | N70: 2128 | O70: 2254 | P70: 2270 | Q70: =G70 -> 2199 | R70: 2222 | S70: 2316 | T70: 2293 | U70: =H70 -> 2282 | V70: 2277 | W70: 2292 | X70: 2309 | Z70: =N70 -> 2128 | AA70: =O70 -> 2254 | AB70: =P70 -> 2270 | AC70: =Q70 -> 2199 | AD70: =R70 -> 2222 | AE70: =S70 -> 2316 | AF70: =T70 -> 2293 | AG70: =U70 -> 2282 | ... AJ70: =X70 -> 2309 | AL70: =SUM(AJ70/AF70)-1 -> 0.0069777584
B71: Long-term liabilities | C71: 657 | D71: 694 | E71: 533 | F71: 705 | G71: 654 | H71: 532 | J71: 558 | K71: 472 | L71: 500 | M71: =F71 -> 705 | N71: 704 | O71: 651 | P71: 660 | Q71: =G71 -> 654 | R71: 665 | S71: 593 | T71: 551 | U71: =H71 -> 532 | V71: 523 | W71: 528 | X71: 556 | Z71: =N71 -> 704 | AA71: =O71 -> 651 | AB71: =P71 -> 660 | AC71: =Q71 -> 654 | AD71: =R71 -> 665 | AE71: =S71 -> 593 | AF71: =T71 -> 551 | AG71: =U71 -> 532 | ... AJ71: =X71 -> 556 | AL71: =SUM(AJ71/AF71)-1 -> 0.0090744102
B72: Finance Lease Obligations, Net of Current Portion | C72: 24 | D72: 24 | E72: 27 | F72: 26 | G72: 21 | H72: 15 | J72: =41-J65 -> 26 | K72: =40-K65 -> 25 | L72: =44-L65 -> 28 | M72: =F72 -> 26 | N72: =40-N65 -> 25 | O72: =39-O65 -> 24 | P72: =39-P65 -> 24 | Q72: =G72 -> 21 | R72: =34-R65 -> 19 | S72: =29-S65 -> 16 | T72: =29-T65 -> 17 | U72: =H72 -> 15 | V72: =27-V65 -> 17 | W72: =30-W65 -> 20 | X72: =28-X65 -> 18 | Z72: =N72 -> 25 | AA72: =O72 -> 24 | AB72: =P72 -> 24 | AC72: =Q72 -> 21 | AD72: =R72 -> 19 | AE72: =S72 -> 16 | AF72: =T72 -> 17 | AG72: =U72 -> 15 | ... AJ72: =X72 -> 18
B73: Long-term debt | C73: =1257-C72 -> 1233 | D73: =1253-D72 -> 1229 | E73: =1216-E72 -> 1189 | F73: =1160-F72 -> 1134 | G73: =1152-G72 -> 1131 | H73: =1144-H72 -> 1129 | J73: =1170-J72 -> 1144 | K73: =1184-K72 -> 1159 | L73: =1142-L72 -> 1114 | M73: =F73 -> 1134 | N73: =1155-N72 -> 1130 | O73: =1145-O72 -> 1121 | P73: =1130-P72 -> 1106 | Q73: =G73 -> 1131 | R73: =1134-R72 -> 1115 | S73: =1157-S72 -> 1141 | T73: =1144-T72 -> 1127 | U73: =H73 -> 1129 | V73: =1153-V72 -> 1136 | W73: =1164-W72 -> 1144 | X73: =1155-X72 -> 1137 | Z73: =N73 -> 1130 | AA73: =O73 -> 1121 | AB73: =P73 -> 1106 | AC73: =Q73 -> 1131 | AD73: =R73 -> 1115 | AE73: =S73 -> 1141 | AF73: =T73 -> 1127 | AG73: =U73 -> 1129 | ... AJ73: =X73 -> 1137 | AL73: =SUM(AJ73/AF73)-1 -> 0.0088731145
B74: Total Liabilities | C74: =SUM(C70:C73)+C67 -> 12112 | D74: =SUM(D70:D73)+D67 -> 14480 | E74: =SUM(E70:E73)+E67 -> 14484 | F74: =SUM(F70:F73)+F67 -> 13008 | G74: =SUM(G70:G73)+G67 -> 11914 | H74: =SUM(H70:H73)+H67 -> 11974 | J74: =SUM(J70:J73)+J67 -> 12484 | K74: =SUM(K70:K73)+K67 -> 12527 | L74: =SUM(L70:L73)+L67 -> 14028 | M74: =SUM(M70:M73)+M67 -> 13008 | N74: =SUM(N70:N73)+N67 -> 11895 | O74: =SUM(O70:O73)+O67 -> 12483 | P74: =SUM(P70:P73)+P67 -> 14070 | Q74: =SUM(Q70:Q73)+Q67 -> 11914 | ... X74: =SUM(X70:X73)+X67 -> 14133 | Z74: =SUM(Z70:Z73)+Z67 -> 11895 | AA74: =SUM(AA70:AA73)+AA67 -> 12483 | AB74: =SUM(AB70:AB73)+AB67 -> 14070 | AC74: =SUM(AC70:AC73)+AC67 -> 11914 | AD74: =SUM(AD70:AD73)+AD67 -> 11670 | AE74: =SUM(AE70:AE73)+AE67 -> 12517 | AF74: =SUM(AF70:AF73)+AF67 -> 13936 | AG74: =SUM(AG70:AG73)+AG67 -> 11974 | ... AJ74: =SUM(AJ70:AJ73)+AJ67 -> 14133 | AL74: =SUM(AJ74/AF74)-1 -> 0.014136051
B76: Preferred stock | C76: 0 | D76: 0 | E76: 0 | F76: 0 | G76: 0 | H76: 0 | J76: 0 | K76: 0 | L76: 0 | M76: =F76 -> 0 | N76: 0 | O76: 0 | P76: 0 | Q76: =G76 -> 0 | R76: 0 | S76: 0 | T76: 0 | U76: =H76 -> 0 | V76: 0 | W76: 0 | X76: 0 | Z76: =N76 -> 0 | AA76: =O76 -> 0 | AB76: =P76 -> 0 | AC76: =Q76 -> 0 | AD76: =R76 -> 0 | AE76: =S76 -> 0 | AF76: =T76 -> 0 | AG76: =U76 -> 0 | ... AJ76: =X76 -> 0 | AL76: =SUM(AJ76/AF76)-1 -> #DIV/0!
B77: Common stock | C77: 26 | D77: 26 | E77: 23 | F77: 22 | G77: 22 | H77: 22 | J77: 22 | K77: 22 | L77: 22 | M77: =F77 -> 22 | N77: 22 | O77: 22 | P77: 22 | Q77: =G77 -> 22 | R77: 22 | S77: 22 | T77: 22 | U77: =H77 -> 22 | V77: 22 | W77: 22 | X77: 22 | Z77: =N77 -> 22 | AA77: =O77 -> 22 | AB77: =P77 -> 22 | AC77: =Q77 -> 22 | AD77: =R77 -> 22 | AE77: =S77 -> 22 | AF77: =T77 -> 22 | AG77: =U77 -> 22 | ... AJ77: =X77 -> 22 | AL77: =SUM(AJ77/AF77)-1 -> 0
B78: Additional paid-in capital | C78: 0 | D78: 0 | E78: 0 | F78: 21 | G78: 31 | H78: 0 | J78: 0 | K78: 20 | L78: 61 | M78: =F78 -> 21 | N78: 0 | O78: 0 | P78: 0 | Q78: =G78 -> 31 | R78: 26 | S78: 0 | T78: 0 | U78: =H78 -> 0 | V78: 0 | W78: 0 | X78: 16 | Z78: =N78 -> 0 | AA78: =O78 -> 0 | AB78: =P78 -> 0 | AC78: =Q78 -> 31 | AD78: =R78 -> 26 | AE78: =S78 -> 0 | AF78: =T78 -> 0 | AG78: =U78 -> 0 | ... AJ78: =X78 -> 16 | AL78: =SUM(AJ78/AF78)-1 -> #DIV/0!
B79: Retained earnings | C79: 3158 | D79: 4233 | E79: 2668 | F79: 2430 | G79: 2683 | H79: 2486 | J79: 2417 | K79: 2522 | L79: 2597 | M79: =F79 -> 2430 | N79: 2454 | O79: 2491 | P79: 2482 | Q79: =G79 -> 2683 | R79: 2722 | S79: 2775 | T79: 2751 | U79: =H79 -> 2486 | V79: 2428 | W79: 2381 | X79: 2306 | Z79: =N79 -> 2454 | AA79: =O79 -> 2491 | AB79: =P79 -> 2482 | AC79: =Q79 -> 2683 | AD79: =R79 -> 2722 | AE79: =S79 -> 2775 | AF79: =T79 -> 2751 | AG79: =U79 -> 2486 | ... AJ79: =X79 -> 2306 | AL79: =SUM(AJ79/AF79)-1 -> -0.16175936
B80: Accumulated other comprehensive income | C80: 295 | D80: 328 | E80: 329 | F80: 322 | G80: 317 | H80: 300 | J80: 328 | K80: 328 | L80: 313 | M80: =F80 -> 322 | N80: 317 | O80: 322 | P80: 308 | Q80: =G80 -> 317 | R80: 312 | S80: 310 | T80: 309 | U80: =H80 -> 300 | V80: 313 | W80: 313 | X80: 309 | Z80: =N80 -> 317 | AA80: =O80 -> 322 | AB80: =P80 -> 308 | AC80: =Q80 -> 317 | AD80: =R80 -> 312 | AE80: =S80 -> 310 | AF80: =T80 -> 309 | AG80: =U80 -> 300 | ... AJ80: =X80 -> 309 | AL80: =SUM(AJ80/AF80)-1 -> 0
B81: Total stockholders' equity | C81: =SUM(C76:C80) -> 3479 | D81: =SUM(D76:D80) -> 4587 | E81: =SUM(E76:E80) -> 3020 | F81: =SUM(F76:F80) -> 2795 | G81: =SUM(G76:G80) -> 3053 | H81: =SUM(H76:H80) -> 2808 | J81: =SUM(J76:J80) -> 2767 | K81: =SUM(K76:K80) -> 2892 | L81: =SUM(L76:L80) -> 2993 | M81: =SUM(M76:M80) -> 2795 | N81: =SUM(N76:N80) -> 2793 | O81: =SUM(O76:O80) -> 2835 | P81: =SUM(P76:P80) -> 2812 | Q81: =SUM(Q76:Q80) -> 3053 | ... X81: =SUM(X76:X80) -> 2653 | Z81: =SUM(Z76:Z80) -> 2793 | AA81: =SUM(AA76:AA80) -> 2835 | AB81: =SUM(AB76:AB80) -> 2812 | AC81: =SUM(AC76:AC80) -> 3053 | AD81: =SUM(AD76:AD80) -> 3082 | AE81: =SUM(AE76:AE80) -> 3107 | AF81: =SUM(AF76:AF80) -> 3082 | AG81: =SUM(AG76:AG80) -> 2808 | ... AJ81: =SUM(AJ76:AJ80) -> 2653 | AL81: =SUM(AJ81/AF81)-1 -> -0.13919533
B82: Total liabilities and stockholders' equity | C82: =SUM(C81+C74) -> 15591 | D82: =SUM(D81+D74) -> 19067 | E82: =SUM(E81+E74) -> 17504 | F82: =SUM(F81+F74) -> 15803 | G82: =SUM(G81+G74) -> 14967 | H82: =SUM(H81+H74) -> 14782 | J82: =SUM(J81+J74) -> 15251 | K82: =SUM(K81+K74) -> 15419 | L82: =SUM(L81+L74) -> 17021 | M82: =SUM(M81+M74) -> 15803 | N82: =SUM(N81+N74) -> 14688 | O82: =SUM(O81+O74) -> 15318 | P82: =SUM(P81+P74) -> 16882 | Q82: =SUM(Q81+Q74) -> 14967 | ... X82: =SUM(X81+X74) -> 16786 | Z82: =SUM(Z81+Z74) -> 14688 | AA82: =SUM(AA81+AA74) -> 15318 | AB82: =SUM(AB81+AB74) -> 16882 | AC82: =SUM(AC81+AC74) -> 14967 | AD82: =SUM(AD81+AD74) -> 14752 | AE82: =SUM(AE81+AE74) -> 15624 | AF82: =SUM(AF81+AF74) -> 17018 | AG82: =SUM(AG81+AG74) -> 14782 | ... AJ82: =SUM(AJ81+AJ74) -> 16786 | AL82: =SUM(AJ82/AF82)-1 -> -0.013632624
B84: Balance Check | C84: =C82-C56 -> 0 | D84: =D82-D56 -> 0 | E84: =E82-E56 -> 0 | F84: =F82-F56 -> 0 | G84: =G82-G56 -> 0 | H84: =H82-H56 -> 0 | J84: =J82-J56 -> 0 | K84: =K82-K56 -> 0 | L84: =L82-L56 -> 0 | M84: =M82-M56 -> 0 | N84: =N82-N56 -> 0 | O84: =O82-O56 -> 0 | P84: =P82-P56 -> 0 | Q84: =Q82-Q56 -> 0 | ... X84: =X82-X56 -> 0 | Z84: =Z82-Z56 -> 0 | AA84: =AA82-AA56 -> 0 | AB84: =AB82-AB56 -> 0 | AC84: =AC82-AC56 -> 0 | AD84: =AD82-AD56 -> 0 | AE84: =AE82-AE56 -> 0 | AF84: =AF82-AF56 -> 0 | AG84: =AG82-AG56 -> 0 | ... AJ84: =AJ82-AJ56 -> 0
A87: X | B87: Cash-Flows Statement | C87: FYE | D87: FYE | E87: FYE | P87: Quarterly | AF87: LTM | AL87: Variance
B88: =B7 -> Fiscal Period | C88: =C7 -> 2020 | D88: =D7 -> 2021 | E88: =E7 -> 2022 | F88: =F7 -> 2023 | G88: =G7 -> 2024 | H88: =H7 -> 2025 | J88: =J7 -> 1Q23 | K88: =K7 -> 2Q23 | L88: =L7 -> 3Q23 | M88: =M7 -> 4Q23 | N88: =N7 -> 1Q24 | O88: =O7 -> 2Q24 | P88: =P7 -> 3Q24 | Q88: =Q7 -> 4Q24 | ... X88: =X7 -> 3Q26 | Z88: =Z7 -> 1Q24 | AA88: =AA7 -> 2Q24 | AB88: =AB7 -> 3Q24 | AC88: =AC7 -> 4Q24 | AD88: =AD7 -> 1Q25 | AE88: =AE7 -> 2Q25 | AF88: =AF7 -> 3Q25 | AG88: =AG7 -> 4Q25 | ... AJ88: =AJ7 -> 3Q26
B89: =B8 -> Fiscal Period End Date | C89: =C8 -> 43862 | D89: =D8 -> 44226 | E89: =E8 -> 44590 | F89: =F8 -> 44954 | G89: =G8 -> 45325 | H89: =H8 -> 45689 | J89: =J8 -> 44681 | K89: =K8 -> 44772 | L89: =L8 -> 44863 | M89: =M8 -> 44954 | N89: =N8 -> 45045 | O89: =O8 -> 45136 | P89: =P8 -> 45227 | Q89: =Q8 -> 45325 | ... X89: =X8 -> 45962 | Z89: =Z8 -> 45045 | AA89: =AA8 -> 45136 | AB89: =AB8 -> 45227 | AC89: =AC8 -> 45325 | AD89: =AD8 -> 45416 | AE89: =AE8 -> 45507 | AF89: =AF8 -> 45598 | AG89: =AG8 -> 45689 | ... AJ89: =AJ8 -> 45962
B91: Cash-Flows From Operating Activities
B92: Net income (loss) | C92: =C30 -> 1541 | D92: =D30 -> 1798 | E92: =E30 -> 2454 | F92: =F30 -> 1419 | G92: =G30 -> 1241 | H92: =H30 -> 927 | J92: =J30 -> 341 | K92: =K30 -> 306 | L92: =L30 -> 277 | M92: =M30 -> 495 | N92: =N30 -> 244 | O92: =O30 -> 274 | P92: =P30 -> 263 | Q92: =Q30 -> 460 | ... X92: =X30 -> 140 | Z92: =Z30 -> 1322 | AA92: =AA30 -> 1290 | AB92: =AB30 -> 1276 | AC92: =AC30 -> 1241 | AD92: =AD30 -> 1243 | AE92: =AE30 -> 1260 | AF92: =AF30 -> 1270 | AG92: =AG30 -> 927 | ... AJ92: =AJ30 -> 645 | AL92: =SUM(AJ92/AF92)-1 -> -0.49212598
B94: Adjustments to reconcile net income:
B95: Depreciation and amortization | C95: 812 | D95: 839 | E95: 869 | F95: 918 | G95: 923 | H95: 866 | J95: 224 | K95: =453-J95 -> 229 | L95: =679-K95-J95 -> 226 | M95: =SUM(F95-SUM(J95:L95)) -> 239 | N95: 237 | O95: =473-N95 -> 236 | P95: =702-O95-N95 -> 229 | Q95: =SUM(G95-SUM(N95:P95)) -> 221 | R95: 219 | S95: =437-R95 -> 218 | T95: =650-S95-R95 -> 213 | U95: =SUM(H95-SUM(R95:T95)) -> 216 | V95: 211 | W95: =422-V95 -> 211 | X95: =628-W95-V95 -> 206 | Z95: =SUM(K95:N95) -> 931 | AA95: =SUM(L95:O95) -> 938 | AB95: =SUM(M95:P95) -> 941 | AC95: =SUM(N95:Q95) -> 923 | AD95: =SUM(O95:R95) -> 905 | AE95: =SUM(P95:S95) -> 887 | AF95: =SUM(Q95:T95) -> 871 | AG95: =SUM(R95:U95) -> 866 | ... AJ95: =SUM(U95:X95) -> 844 | AL95: =SUM(AJ95/AF95)-1 -> -0.030998852
B96: Restructuring charges | C96: 41 | D96: 254 | E96: -34 | F96: 147 | G96: 153 | H96: -3 | J96: 1 | K96: =35-J96 -> 34 | L96: =61-K96-J96 -> 26 | M96: =SUM(F96-SUM(J96:L96)) -> 86 | N96: -9 | O96: =-16-N96 -> -7 | P96: =-16-O96-N96 -> 0 | Q96: =SUM(G96-SUM(N96:P96)) -> 169 | R96: 15 | S96: =8-R96 -> -7 | T96: =4-S96-R96 -> -4 | U96: =SUM(H96-SUM(R96:T96)) -> -7 | V96: 109 | W96: =223-V96 -> 114 | X96: =218-W96-V96 -> -5 | Z96: =SUM(K96:N96) -> 137 | AA96: =SUM(L96:O96) -> 96 | AB96: =SUM(M96:P96) -> 70 | AC96: =SUM(N96:Q96) -> 153 | AD96: =SUM(O96:R96) -> 177 | AE96: =SUM(P96:S96) -> 177 | AF96: =SUM(Q96:T96) -> 173 | AG96: =SUM(R96:U96) -> -3 | ... AJ96: =SUM(U96:X96) -> 211 | AL96: =SUM(AJ96/AF96)-1 -> 0.21965318
B97: Stock-based compensation | C97: 143 | D97: 135 | E97: 141 | F97: 138 | G97: 145 | H97: 139 | J97: 39 | K97: =65-J97 -> 26 | L97: =98-K97-J97 -> 33 | M97: =SUM(F97-SUM(J97:L97)) -> 40 | N97: 38 | O97: =75-N97 -> 37 | P97: =110-O97-N97 -> 35 | Q97: =SUM(G97-SUM(N97:P97)) -> 35 | R97: 38 | S97: =74-R97 -> 36 | T97: =108-S97-R97 -> 34 | U97: =SUM(H97-SUM(R97:T97)) -> 31 | V97: 40 | W97: =75-V97 -> 35 | X97: =106-W97-V97 -> 31 | Z97: =SUM(K97:N97) -> 137 | AA97: =SUM(L97:O97) -> 148 | AB97: =SUM(M97:P97) -> 150 | AC97: =SUM(N97:Q97) -> 145 | AD97: =SUM(O97:R97) -> 145 | AE97: =SUM(P97:S97) -> 144 | AF97: =SUM(Q97:T97) -> 143 | AG97: =SUM(R97:U97) -> 139 | ... AJ97: =SUM(U97:X97) -> 137 | AL97: =SUM(AJ97/AF97)-1 -> -0.041958042
B98: Other, net | C98: =21+70 -> 91 | D98: =3-36 -> -33 | E98: =11+14 -> 25 | F98: =12+51 -> 63 | G98: =26-21-214 -> -209 | H98: =475+12-59 -> 428 | J98: 12 | K98: =19-J98 -> 7 | L98: =19-K98-J98 -> 0 | M98: =SUM(F98-SUM(J98:L98)) -> 44 | N98: 14 | O98: =-21+2-N98 -> -33 | P98: =-21+7-O98-N98 -> 5 | Q98: =SUM(G98-SUM(N98:P98)) -> -195 | R98: =14-2 -> 12 | S98: =10+2-R98 -> 0 | T98: =1+2-S98-R98 -> -9 | U98: =SUM(H98-SUM(R98:T98)) -> 425 | V98: =-51-2 -> -53 | W98: =45+4+4-V98 -> 106 | X98: =171+37+4+21+6-W98-V98 -> 186 | Z98: =SUM(K98:N98) -> 65 | AA98: =SUM(L98:O98) -> 25 | AB98: =SUM(M98:P98) -> 30 | AC98: =SUM(N98:Q98) -> -209 | AD98: =SUM(O98:R98) -> -211 | AE98: =SUM(P98:S98) -> -178 | AF98: =SUM(Q98:T98) -> -192 | AG98: =SUM(R98:U98) -> 428 | ... AJ98: =SUM(U98:X98) -> 664 | AL98: =SUM(AJ98/AF98)-1 -> -4.4583333
B100: Changes in assets and liabilities:
B101: Receivables | C101: -131 | D101: 73 | E101: 17 | F101: -103 | G101: 204 | H101: -111 | J101: 238 | K101: =201-J101 -> -37 | L101: =-14-K101-J101 -> -215 | M101: =SUM(F101-SUM(J101:L101)) -> -89 | N101: 279 | O101: =289-N101 -> 10 | P101: =240-O101-N101 -> -49 | Q101: =SUM(G101-SUM(N101:P101)) -> -36 | R101: 168 | S101: =66-R101 -> -102 | T101: =4-S101-R101 -> -62 | U101: =SUM(H101-SUM(R101:T101)) -> -115 | V101: 298 | W101: =123-V101 -> -175 | X101: =23-W101-V101 -> -100 | Z101: =SUM(K101:N101) -> -62 | AA101: =SUM(L101:O101) -> -15 | AB101: =SUM(M101:P101) -> 151 | AC101: =SUM(N101:Q101) -> 204 | AD101: =SUM(O101:R101) -> 93 | AE101: =SUM(P101:S101) -> -19 | AF101: =SUM(Q101:T101) -> -32 | AG101: =SUM(R101:U101) -> -111 | ... AJ101: =SUM(U101:X101) -> -92 | AL101: =SUM(AJ101/AF101)-1 -> 1.875
B102: Merchandise Inventories & Other Assets | C102: =237+16 -> 253 | D102: =-435-51 -> -486 | E102: =-328-14 -> -342 | F102: =809-21 -> 788 | G102: =178-18 -> 160 | H102: =-155+11 -> -144 | J102: =-297+4 -> -293 | K102: =-79-13-J102 -> 201 | L102: =-1365-1-K102-J102 -> -1274 | M102: =SUM(F102-SUM(J102:L102)) -> 2154 | N102: =-86-17 -> -103 | O102: =-508-32-N102 -> -437 | P102: =-2444-17-O102-N102 -> -1921 | Q102: =SUM(G102-SUM(N102:P102)) -> 2621 | R102: =-273-8 -> -281 | S102: =-761-11-R102 -> -491 | T102: =-2869-16-S102-R102 -> -2113 | U102: =SUM(H102-SUM(R102:T102)) -> 2741 | V102: =-95+7 -> -88 | W102: =-717-24-V102 -> -653 | X102: =-2903+3-W102-V102 -> -2159 | Z102: =SUM(K102:N102) -> 978 | AA102: =SUM(L102:O102) -> 340 | AB102: =SUM(M102:P102) -> -307 | AC102: =SUM(N102:Q102) -> 160 | AD102: =SUM(O102:R102) -> -18 | AE102: =SUM(P102:S102) -> -72 | AF102: =SUM(Q102:T102) -> -264 | AG102: =SUM(R102:U102) -> -144 | ... AJ102: =SUM(U102:X102) -> -159 | AL102: =SUM(AJ102/AF102)-1 -> -0.39772727
B103: Accounts payable | C103: 47 | D103: 1676 | E103: -201 | F103: -1099 | G103: -1025 | H103: 358 | J103: -1296 | K103: =-1434-J103 -> -138 | L103: =224-K103-J103 -> 1658 | M103: =SUM(F103-SUM(J103:L103)) -> -1323 | N103: -790 | O103: =-206-N103 -> 584 | P103: =1468-O103-N103 -> 1674 | Q103: =SUM(G103-SUM(N103:P103)) -> -2493 | R103: 43 | S103: =904-R103 -> 861 | T103: =2483-S103-R103 -> 1579 | U103: =SUM(H103-SUM(R103:T103)) -> -2125 | V103: -330 | W103: =693-V103 -> 1023 | X103: =2315-W103-V103 -> 1622 | Z103: =SUM(K103:N103) -> -593 | AA103: =SUM(L103:O103) -> 129 | AB103: =SUM(M103:P103) -> 145 | AC103: =SUM(N103:Q103) -> -1025 | AD103: =SUM(O103:R103) -> -192 | AE103: =SUM(P103:S103) -> 85 | AF103: =SUM(Q103:T103) -> -10 | AG103: =SUM(R103:U103) -> 358 | ... AJ103: =SUM(U103:X103) -> 190 | AL103: =SUM(AJ103/AF103)-1 -> -20
B104: Income taxes | C104: -132 | D104: 173 | E104: -156 | F104: 36 | G104: 52 | H104: -212 | J104: 63 | K104: =42-J104 -> -21 | L104: =28-K104-J104 -> -14 | M104: =SUM(F104-SUM(J104:L104)) -> 8 | N104: 46 | O104: =-148-N104 -> -194 | P104: =-200-O104-N104 -> -52 | Q104: =SUM(G104-SUM(N104:P104)) -> 252 | R104: 13 | S104: =-183-R104 -> -196 | T104: =-219-S104-R104 -> -36 | U104: =SUM(H104-SUM(R104:T104)) -> 7 | V104: 7 | W104: =-167-V104 -> -174 | X104: =-133-W104-V104 -> 34 | Z104: =SUM(K104:N104) -> 19 | AA104: =SUM(L104:O104) -> -154 | AB104: =SUM(M104:P104) -> -192 | AC104: =SUM(N104:Q104) -> 52 | AD104: =SUM(O104:R104) -> 19 | AE104: =SUM(P104:S104) -> 17 | AF104: =SUM(Q104:T104) -> 33 | AG104: =SUM(R104:U104) -> -212 | ... AJ104: =SUM(U104:X104) -> -126 | AL104: =SUM(AJ104/AF104)-1 -> -4.8181818
B105: Other liabilities | C105: -100 | D105: 498 | E105: 479 | F105: -483 | G105: -174 | H105: -150 | J105: -713 | K105: =-645-J105 -> 68 | L105: =-761-K105-J105 -> -116 | M105: =SUM(F105-SUM(J105:L105)) -> 278 | N105: -287 | O105: =-245-N105 -> 42 | P105: =-320-O105-N105 -> -75 | Q105: =SUM(G105-SUM(N105:P105)) -> 146 | R105: -317 | S105: =-266-R105 -> 51 | T105: =-397-S105-R105 -> -131 | U105: =SUM(H105-SUM(R105:T105)) -> 247 | V105: -362 | W105: =-286-V105 -> 76 | X105: =-340-W105-V105 -> -54 | Z105: =SUM(K105:N105) -> -57 | AA105: =SUM(L105:O105) -> -83 | AB105: =SUM(M105:P105) -> -42 | AC105: =SUM(N105:Q105) -> -174 | AD105: =SUM(O105:R105) -> -204 | AE105: =SUM(P105:S105) -> -195 | AF105: =SUM(Q105:T105) -> -251 | AG105: =SUM(R105:U105) -> -150 | ... AJ105: =SUM(U105:X105) -> -93 | AL105: =SUM(AJ105/AF105)-1 -> -0.62948207
B106: Net cash used in operating activities | C106: =SUM(C92:C105) -> 2565 | D106: =SUM(D92:D105) -> 4927 | E106: =SUM(E92:E105) -> 3252 | F106: =SUM(F92:F105) -> 1824 | G106: =SUM(G92:G105) -> 1470 | H106: =SUM(H92:H105) -> 2098 | J106: =SUM(J92:J105) -> -1384 | K106: =SUM(K92:K105) -> 675 | L106: =SUM(L92:L105) -> 601 | M106: =SUM(M92:M105) -> 1932 | N106: =SUM(N92:N105) -> -331 | O106: =SUM(O92:O105) -> 512 | P106: =SUM(P92:P105) -> 109 | Q106: =SUM(Q92:Q105) -> 1180 | ... X106: =SUM(X92:X105) -> -99 | Z106: =SUM(Z92:Z105) -> 2877 | AA106: =SUM(AA92:AA105) -> 2714 | AB106: =SUM(AB92:AB105) -> 2222 | AC106: =SUM(AC92:AC105) -> 1470 | AD106: =SUM(AD92:AD105) -> 1957 | AE106: =SUM(AE92:AE105) -> 2106 | AF106: =SUM(AF92:AF105) -> 1741 | AG106: =SUM(AG92:AG105) -> 2098 | ... AJ106: =SUM(AJ92:AJ105) -> 2221 | AL106: =SUM(AJ106/AF106)-1 -> 0.27570362
B108: Cash flows from investing activities:
B109: Additions to property and equipment | C109: -743 | D109: -713 | E109: -737 | F109: -930 | G109: -795 | H109: -706 | J109: -215 | K109: =-441-J109 -> -226 | L109: =-696-K109-J109 -> -255 | M109: =SUM(F109-SUM(J109:L109)) -> -234 | N109: -204 | O109: =-395-N109 -> -191 | P109: =-612-O109-N109 -> -217 | Q109: =SUM(G109-SUM(N109:P109)) -> -183 | R109: -152 | S109: =-335-R109 -> -183 | T109: =-528-S109-R109 -> -193 | U109: =SUM(H109-SUM(R109:T109)) -> -178 | V109: -166 | W109: =-341-V109 -> -175 | X109: =-529-W109-V109 -> -188 | Z109: =SUM(K109:N109) -> -919 | AA109: =SUM(L109:O109) -> -884 | AB109: =SUM(M109:P109) -> -846 | AC109: =SUM(N109:Q109) -> -795 | AD109: =SUM(O109:R109) -> -743 | AE109: =SUM(P109:S109) -> -735 | AF109: =SUM(Q109:T109) -> -711 | AG109: =SUM(R109:U109) -> -706 | ... AJ109: =SUM(U109:X109) -> -707 | AL109: =SUM(AJ109/AF109)-1 -> -0.005625879
B110: Divestitures / (Acquisitions) | C110: -145 | D110: 0 | E110: -468 | F110: 0 | G110: 14 | H110: 0 | J110: 0 | K110: 0 | L110: 0 | M110: =SUM(F110-SUM(J110:L110)) -> 0 | N110: 0 | O110: =14-N110 -> 14 | P110: =14-O110-N110 -> 0 | Q110: =SUM(G110-SUM(N110:P110)) -> 0 | R110: 0 | S110: 0 | T110: 0 | U110: =SUM(H110-SUM(R110:T110)) -> 0 | V110: 0 | W110: =-27-V110 -> -27 | X110: =-27-W110-V110 -> 0 | Z110: =SUM(K110:N110) -> 0 | AA110: =SUM(L110:O110) -> 14 | AB110: =SUM(M110:P110) -> 14 | AC110: =SUM(N110:Q110) -> 14 | AD110: =SUM(O110:R110) -> 14 | AE110: =SUM(P110:S110) -> 0 | AF110: =SUM(Q110:T110) -> 0 | AG110: =SUM(R110:U110) -> 0 | ... AJ110: =SUM(U110:X110) -> -27 | AL110: =SUM(AJ110/AF110)-1 -> #DIV/0!
B111: Sales / (Purchases) of investments | C111: =-330+322 -> -8 | D111: =-620+546 -> -74 | E111: =-233+66 -> -167 | F111: =-46+7 -> -39 | G111: =-9+7 -> -2 | H111: =-26+20 -> -6 | J111: 0 | K111: =-46-J111 -> -46 | L111: =-46-K111-J111 -> 0 | M111: =SUM(F111-SUM(J111:L111)) -> 7 | N111: 0 | O111: =-2-N111 -> -2 | P111: =-7-O111-N111 -> -5 | Q111: =SUM(G111-SUM(N111:P111)) -> 5 | R111: 0 | S111: 0 | T111: 0 | U111: =SUM(H111-SUM(R111:T111)) -> -6 | V111: 0 | W111: 0 | X111: 0 | Z111: =SUM(K111:N111) -> -39 | AA111: =SUM(L111:O111) -> 5 | AB111: =SUM(M111:P111) -> 0 | AC111: =SUM(N111:Q111) -> -2 | AD111: =SUM(O111:R111) -> -2 | AE111: =SUM(P111:S111) -> 0 | AF111: =SUM(Q111:T111) -> 5 | AG111: =SUM(R111:U111) -> -6 | ... AJ111: =SUM(U111:X111) -> -6 | AL111: =SUM(AJ111/AF111)-1 -> -2.2
B112: Other Investing Activities | C112: 1 | D112: -1 | E112: 0 | F112: 7 | G112: 2 | H112: 8 | J112: 2 | K112: =3-J112 -> 1 | L112: =6-K112-J112 -> 3 | M112: =SUM(F112-SUM(J112:L112)) -> 1 | N112: 0 | O112: =2-N112 -> 2 | P112: =5-O112-N112 -> 3 | Q112: =SUM(G112-SUM(N112:P112)) -> -3 | R112: -15 | S112: =-17-R112 -> -2 | T112: =6-S112-R112 -> 23 | U112: =SUM(H112-SUM(R112:T112)) -> 2 | V112: 0 | W112: =-1-V112 -> -1 | X112: =1-W112-V112 -> 2 | Z112: =SUM(K112:N112) -> 5 | AA112: =SUM(L112:O112) -> 6 | AB112: =SUM(M112:P112) -> 6 | AC112: =SUM(N112:Q112) -> 2 | AD112: =SUM(O112:R112) -> -13 | AE112: =SUM(P112:S112) -> -17 | AF112: =SUM(Q112:T112) -> 3 | AG112: =SUM(R112:U112) -> 8 | ... AJ112: =SUM(U112:X112) -> 3 | AL112: =SUM(AJ112/AF112)-1 -> 0
B113: Net cash used in investing activities | C113: =SUM(C109:C112) -> -895 | D113: =SUM(D109:D112) -> -788 | E113: =SUM(E109:E112) -> -1372 | F113: =SUM(F109:F112) -> -962 | G113: =SUM(G109:G112) -> -781 | H113: =SUM(H109:H112) -> -704 | J113: =SUM(J109:J112) -> -213 | K113: =SUM(K109:K112) -> -271 | L113: =SUM(L109:L112) -> -252 | M113: =SUM(M109:M112) -> -226 | N113: =SUM(N109:N112) -> -204 | O113: =SUM(O109:O112) -> -177 | P113: =SUM(P109:P112) -> -219 | Q113: =SUM(Q109:Q112) -> -181 | ... X113: =SUM(X109:X112) -> -186 | Z113: =SUM(Z109:Z112) -> -953 | AA113: =SUM(AA109:AA112) -> -859 | AB113: =SUM(AB109:AB112) -> -826 | AC113: =SUM(AC109:AC112) -> -781 | AD113: =SUM(AD109:AD112) -> -744 | AE113: =SUM(AE109:AE112) -> -752 | AF113: =SUM(AF109:AF112) -> -703 | AG113: =SUM(AG109:AG112) -> -704 | ... AJ113: =SUM(AJ109:AJ112) -> -737 | AL113: =SUM(AJ113/AF113)-1 -> 0.048364154
B115: Cash flows from financing activities:
B116: Proceeds from Equity Issuances / (Repurchases) | C116: =-1003+48 -> -955 | D116: =-312+28 -> -284 | E116: =-3502+29 -> -3473 | F116: =-1014+16 -> -998 | G116: =-340+19 -> -321 | H116: =-500+17 -> -483 | J116: -455 | K116: =-465-J116 -> -10 | L116: =-465-K116-J116 -> 0 | M116: =SUM(F116-SUM(J116:L116)) -> -533 | N116: -79 | O116: =-158-N116 -> -79 | P116: =-270-O116-N116 -> -112 | Q116: =SUM(G116-SUM(N116:P116)) -> -51 | R116: -50 | S116: =-148-R116 -> -98 | T116: =-285-S116-R116 -> -137 | U116: =SUM(H116-SUM(R116:T116)) -> -198 | V116: -100 | W116: =-165-V116 -> -65 | X116: =-200-W116-V116 -> -35 | Z116: =SUM(K116:N116) -> -622 | AA116: =SUM(L116:O116) -> -691 | AB116: =SUM(M116:P116) -> -803 | AC116: =SUM(N116:Q116) -> -321 | AD116: =SUM(O116:R116) -> -292 | AE116: =SUM(P116:S116) -> -311 | AF116: =SUM(Q116:T116) -> -336 | AG116: =SUM(R116:U116) -> -483 | ... AJ116: =SUM(U116:X116) -> -398 | AL116: =SUM(AJ116/AF116)-1 -> 0.18452381
B117: Dividends paid | C117: -527 | D117: -568 | E117: -688 | F117: -789 | G117: -801 | H117: -807 | J117: -199 | K117: =-397-J117 -> -198 | L117: =-595-K117-J117 -> -198 | M117: =SUM(F117-SUM(J117:L117)) -> -194 | N117: -202 | O117: =-402-N117 -> -200 | P117: =-603-O117-N117 -> -201 | Q117: =SUM(G117-SUM(N117:P117)) -> -198 | R117: -202 | S117: =-405-R117 -> -203 | T117: =-607-S117-R117 -> -202 | U117: =SUM(H117-SUM(R117:T117)) -> -200 | V117: -202 | W117: =-403-V117 -> -201 | X117: =-602-W117-V117 -> -199 | Z117: =SUM(K117:N117) -> -792 | AA117: =SUM(L117:O117) -> -794 | AB117: =SUM(M117:P117) -> -797 | AC117: =SUM(N117:Q117) -> -801 | AD117: =SUM(O117:R117) -> -801 | AE117: =SUM(P117:S117) -> -804 | AF117: =SUM(Q117:T117) -> -805 | AG117: =SUM(R117:U117) -> -807 | ... AJ117: =SUM(U117:X117) -> -802 | AL117: =SUM(AJ117/AF117)-1 -> -0.0037267081
B118: Proceeds from Debt Issuances / (Repayment) | C118: -15 | D118: =-1916+1892 -> -24 | E118: -133 | F118: -19 | G118: -19 | H118: -17 | J118: 0 | K118: 0 | L118: 0 | M118: =SUM(F118-SUM(J118:L118)) -> -19 | N118: 0 | O118: 0 | P118: 0 | Q118: =SUM(G118-SUM(N118:P118)) -> -19 | R118: 0 | S118: 0 | T118: =-13-S118-R118 -> -13 | U118: =SUM(H118-SUM(R118:T118)) -> -4 | V118: 0 | W118: 0 | X118: =-10-W118-V118 -> -10 | Z118: =SUM(K118:N118) -> -19 | AA118: =SUM(L118:O118) -> -19 | AB118: =SUM(M118:P118) -> -19 | AC118: =SUM(N118:Q118) -> -19 | AD118: =SUM(O118:R118) -> -19 | AE118: =SUM(P118:S118) -> -19 | AF118: =SUM(Q118:T118) -> -32 | AG118: =SUM(R118:U118) -> -17 | ... AJ118: =SUM(U118:X118) -> -14 | AL118: =SUM(AJ118/AF118)-1 -> -0.5625
B119: Other Financing Activities | C119: -1 | D119: 0 | E119: -3 | F119: 0 | G119: -3 | H119: -2 | J119: 4 | K119: =1-J119 -> -3 | L119: =2-K119-J119 -> 1 | M119: =SUM(F119-SUM(J119:L119)) -> -2 | N119: 0 | O119: 0 | P119: =1-O119-N119 -> 1 | Q119: =SUM(G119-SUM(N119:P119)) -> -4 | R119: 0 | S119: =-4-R119 -> -4 | T119: =13-S119-R119 -> 17 | U119: =SUM(H119-SUM(R119:T119)) -> -15 | V119: -3 | W119: =-6-V119 -> -3 | X119: =4-W119-V119 -> 10 | Z119: =SUM(K119:N119) -> -4 | AA119: =SUM(L119:O119) -> -1 | AB119: =SUM(M119:P119) -> -1 | AC119: =SUM(N119:Q119) -> -3 | AD119: =SUM(O119:R119) -> -3 | AE119: =SUM(P119:S119) -> -7 | AF119: =SUM(Q119:T119) -> 9 | AG119: =SUM(R119:U119) -> -2 | ... AJ119: =SUM(U119:X119) -> -11 | AL119: =SUM(AJ119/AF119)-1 -> -2.2222222
B120: Net cash provided by financing activities | C120: =SUM(C116:C119) -> -1498 | D120: =SUM(D116:D119) -> -876 | E120: =SUM(E116:E119) -> -4297 | F120: =SUM(F116:F119) -> -1806 | G120: =SUM(G116:G119) -> -1144 | H120: =SUM(H116:H119) -> -1309 | J120: =SUM(J116:J119) -> -650 | K120: =SUM(K116:K119) -> -211 | L120: =SUM(L116:L119) -> -197 | M120: =SUM(M116:M119) -> -748 | N120: =SUM(N116:N119) -> -281 | O120: =SUM(O116:O119) -> -279 | P120: =SUM(P116:P119) -> -312 | Q120: =SUM(Q116:Q119) -> -272 | ... X120: =SUM(X116:X119) -> -234 | Z120: =SUM(Z116:Z119) -> -1437 | AA120: =SUM(AA116:AA119) -> -1505 | AB120: =SUM(AB116:AB119) -> -1620 | AC120: =SUM(AC116:AC119) -> -1144 | AD120: =SUM(AD116:AD119) -> -1115 | AE120: =SUM(AE116:AE119) -> -1141 | AF120: =SUM(AF116:AF119) -> -1164 | AG120: =SUM(AG116:AG119) -> -1309 | ... AJ120: =SUM(AJ116:AJ119) -> -1225 | AL120: =SUM(AJ120/AF120)-1 -> 0.052405498
B123: Unrestricted Cash BOP | C123: 2184 | D123: =C130 -> 2229 | E123: =D130 -> 5494 | F123: =E130 -> 2936 | G123: =F130 -> 1874 | H123: =G130 -> 1447 | J123: =F123 -> 2936 | K123: =J130 -> 640 | L123: =K130 -> 840 | M123: =L130 -> 932 | N123: =M130 -> 1874 | O123: =N130 -> 1030 | P123: =O130 -> 1093 | Q123: =P130 -> 636 | R123: =Q130 -> 1447 | ... X123: =W130 -> 1456 | Z123: =M130 -> 1874 | AA123: =Z130 -> 1030 | AB123: =AA130 -> 1093 | AC123: =AB130 -> 636 | AD123: =AC130 -> 1447 | AE123: =AD130 -> 1214 | AF123: =AE130 -> 1387 | AG123: =AF130 -> 643 | AH123: =AG130 -> 1578 | ... AJ123: =AI130 -> 1456
B124: BOP Restricted Cash Adjustment | D124: =-C128 -> 126 | E124: =-D128 -> 131 | F124: =-E128 -> 269 | G124: =-F128 -> 379 | H124: =-G128 -> 346 | J124: =F124 -> 269 | K124: =-J128 -> 320 | L124: =-K128 -> 312 | M124: =-L128 -> 361 | N124: =-M128 -> 379 | O124: =-N128 -> 402 | P124: =-O128 -> 398 | Q124: =-P128 -> 423 | R124: =-Q128 -> 346 | ... X124: =-W128 -> 257 | Z124: =N124 -> 379 | AA124: =-Z128 -> 402 | AB124: =-AA128 -> 398 | AC124: =-AB128 -> 423 | AD124: =-AC128 -> 346 | AE124: =-AD128 -> 313 | AF124: =-AE128 -> 311 | AG124: =-AF128 -> 295 | AH124: =-AG128 -> 290 | ... AJ124: =-AI128 -> 257
B125: Adjusted Cash Position BOP | C125: =SUM(C123:C124) -> 2184 | D125: =SUM(D123:D124) -> 2355 | E125: =SUM(E123:E124) -> 5625 | F125: =SUM(F123:F124) -> 3205 | G125: =SUM(G123:G124) -> 2253 | H125: =SUM(H123:H124) -> 1793 | J125: =SUM(J123:J124) -> 3205 | K125: =SUM(K123:K124) -> 960 | L125: =SUM(L123:L124) -> 1152 | M125: =SUM(M123:M124) -> 1293 | N125: =SUM(N123:N124) -> 2253 | O125: =SUM(O123:O124) -> 1432 | P125: =SUM(P123:P124) -> 1491 | Q125: =SUM(Q123:Q124) -> 1059 | ... X125: =SUM(X123:X124) -> 1713 | Z125: =SUM(Z123:Z124) -> 2253 | AA125: =SUM(AA123:AA124) -> 1432 | AB125: =SUM(AB123:AB124) -> 1491 | AC125: =SUM(AC123:AC124) -> 1059 | AD125: =SUM(AD123:AD124) -> 1793 | AE125: =SUM(AE123:AE124) -> 1527 | AF125: =SUM(AF123:AF124) -> 1698 | AG125: =SUM(AG123:AG124) -> 938 | ... AJ125: =SUM(AJ123:AJ124) -> 1713
...

Sheet Revenue Drivers
B2: ='Historical Financials'!B2 -> Best Buy Co Inc (NASDAQ: BBY) | E2: FYE | P2: Quarterly | AF2: LTM
B3: Segment Anaysis | C3: ='Historical Financials'!C7 -> 2020 | D3: ='Historical Financials'!D7 -> 2021 | E3: ='Historical Financials'!E7 -> 2022 | F3: ='Historical Financials'!F7 -> 2023 | G3: ='Historical Financials'!G7 -> 2024 | H3: ='Historical Financials'!H7 -> 2025 | J3: ='Historical Financials'!J7 -> 1Q23 | K3: ='Historical Financials'!K7 -> 2Q23 | L3: ='Historical Financials'!L7 -> 3Q23 | M3: ='Historical Financials'!M7 -> 4Q23 | N3: ='Historical Financials'!N7 -> 1Q24 | O3: ='Historical Financials'!O7 -> 2Q24 | P3: ='Historical Financials'!P7 -> 3Q24 | Q3: ='Historical Financials'!Q7 -> 4Q24 | ... X3: ='Historical Financials'!X7 -> 3Q26 | Z3: =N3 -> 1Q24 | AA3: =O3 -> 2Q24 | AB3: =P3 -> 3Q24 | AC3: =Q3 -> 4Q24 | AD3: =R3 -> 1Q25 | AE3: =S3 -> 2Q25 | AF3: =T3 -> 3Q25 | AG3: =U3 -> 4Q25 | ... AJ3: =X3 -> 3Q26
B4: ($ In Millions) | C4: ='Historical Financials'!C8 -> 43862 | D4: ='Historical Financials'!D8 -> 44226 | E4: ='Historical Financials'!E8 -> 44590 | F4: ='Historical Financials'!F8 -> 44954 | G4: ='Historical Financials'!G8 -> 45325 | H4: ='Historical Financials'!H8 -> 45689 | J4: ='Historical Financials'!J8 -> 44681 | K4: ='Historical Financials'!K8 -> 44772 | L4: ='Historical Financials'!L8 -> 44863 | M4: ='Historical Financials'!M8 -> 44954 | N4: ='Historical Financials'!N8 -> 45045 | O4: ='Historical Financials'!O8 -> 45136 | P4: ='Historical Financials'!P8 -> 45227 | Q4: ='Historical Financials'!Q8 -> 45325 | ... X4: ='Historical Financials'!X8 -> 45962 | Z4: =N4 -> 45045 | AA4: =O4 -> 45136 | AB4: =P4 -> 45227 | AC4: =Q4 -> 45325 | AD4: =R4 -> 45416 | AE4: =S4 -> 45507 | AF4: =T4 -> 45598 | AG4: =U4 -> 45689 | ... AJ4: =X4 -> 45962
A6: X | B6: Revenue by reportable segment
A8: X | B8: Revenue Segment Anaysis
B9: Domestic | C9: 40114 | D9: 43293 | E9: 47830 | F9: 42794 | G9: 40097 | H9: 38238 | J9: 9894 | K9: 9569 | L9: 9800 | M9: =SUM(F9-SUM(J9:L9)) -> 13531 | N9: 8801 | O9: 8890 | P9: 8996 | Q9: =SUM(G9-SUM(N9:P9)) -> 13410 | R9: 8203 | S9: 8623 | T9: 8697 | U9: =SUM(H9-SUM(R9:T9)) -> 12715 | V9: 8127 | W9: 8698 | X9: 8878 | Z9: =SUM(K9:N9) -> 41701 | AA9: =SUM(L9:O9) -> 41022 | AB9: =SUM(M9:P9) -> 40218 | AC9: =SUM(N9:Q9) -> 40097 | AD9: =SUM(O9:R9) -> 39499 | AE9: =SUM(P9:S9) -> 39232 | AF9: =SUM(Q9:T9) -> 38933 | AG9: =SUM(R9:U9) -> 38238 | ... AJ9: =SUM(U9:X9) -> 38418
B10: International | C10: 3524 | D10: 3969 | E10: 3931 | F10: 3504 | G10: 3355 | H10: 3290 | J10: 753 | K10: 760 | L10: 787 | M10: =SUM(F10-SUM(J10:L10)) -> 1204 | N10: 666 | O10: 693 | P10: 760 | Q10: =SUM(G10-SUM(N10:P10)) -> 1236 | R10: 644 | S10: 665 | T10: 748 | U10: =SUM(H10-SUM(R10:T10)) -> 1233 | V10: 640 | W10: 740 | X10: 794 | Z10: =SUM(K10:N10) -> 3417 | AA10: =SUM(L10:O10) -> 3350 | AB10: =SUM(M10:P10) -> 3323 | AC10: =SUM(N10:Q10) -> 3355 | AD10: =SUM(O10:R10) -> 3333 | AE10: =SUM(P10:S10) -> 3305 | AF10: =SUM(Q10:T10) -> 3293 | AG10: =SUM(R10:U10) -> 3290 | ... AJ10: =SUM(U10:X10) -> 3407
B11: Total Net Revenue | C11: =SUM(C9:C10) -> 43638 | D11: =SUM(D9:D10) -> 47262 | E11: =SUM(E9:E10) -> 51761 | F11: =SUM(F9:F10) -> 46298 | G11: =SUM(G9:G10) -> 43452 | H11: =SUM(H9:H10) -> 41528 | J11: =SUM(J9:J10) -> 10647 | K11: =SUM(K9:K10) -> 10329 | L11: =SUM(L9:L10) -> 10587 | M11: =SUM(M9:M10) -> 14735 | N11: =SUM(N9:N10) -> 9467 | O11: =SUM(O9:O10) -> 9583 | P11: =SUM(P9:P10) -> 9756 | Q11: =SUM(Q9:Q10) -> 14646 | ... X11: =SUM(X9:X10) -> 9672 | Z11: =SUM(Z9:Z10) -> 45118 | AA11: =SUM(AA9:AA10) -> 44372 | AB11: =SUM(AB9:AB10) -> 43541 | AC11: =SUM(AC9:AC10) -> 43452 | AD11: =SUM(AD9:AD10) -> 42832 | AE11: =SUM(AE9:AE10) -> 42537 | AF11: =SUM(AF9:AF10) -> 42226 | AG11: =SUM(AG9:AG10) -> 41528 | ... AJ11: =SUM(AJ9:AJ10) -> 41825
B12: Balance Check | C12: =+C11-'Historical Financials'!C11 -> 0 | D12: =+D11-'Historical Financials'!D11 -> 0 | E12: =+E11-'Historical Financials'!E11 -> 0 | F12: =+F11-'Historical Financials'!F11 -> 0 | G12: =+G11-'Historical Financials'!G11 -> 0 | H12: =+H11-'Historical Financials'!H11 -> 0 | J12: =+J11-'Historical Financials'!J11 -> 0 | K12: =+K11-'Historical Financials'!K11 -> 0 | L12: =+L11-'Historical Financials'!L11 -> 0 | M12: =+M11-'Historical Financials'!M11 -> 0 | N12: =+N11-'Historical Financials'!N11 -> 0 | O12: =+O11-'Historical Financials'!O11 -> 0 | P12: =+P11-'Historical Financials'!P11 -> 0 | Q12: =+Q11-'Historical Financials'!Q11 -> 0 | ... X12: =+X11-'Historical Financials'!X11 -> 0 | Z12: =+Z11-'Historical Financials'!Z11 -> 0 | AA12: =+AA11-'Historical Financials'!AA11 -> 0 | AB12: =+AB11-'Historical Financials'!AB11 -> 0 | AC12: =+AC11-'Historical Financials'!AC11 -> 0 | AD12: =+AD11-'Historical Financials'!AD11 -> 0 | AE12: =+AE11-'Historical Financials'!AE11 -> 0 | AF12: =+AF11-'Historical Financials'!AF11 -> 0 | AG12: =+AG11-'Historical Financials'!AG11 -> 0 | ... AJ12: =+AJ11-'Historical Financials'!AJ11 -> 0
B14: =B9&"(%)" -> Domestic(%) | C14: =SUM(C9/C$11) -> 0.91924469 | D14: =SUM(D9/D$11) -> 0.91602133 | E14: =SUM(E9/E$11) -> 0.92405479 | F14: =SUM(F9/F$11) -> 0.92431639 | G14: =SUM(G9/G$11) -> 0.92278836 | H14: =SUM(H9/H$11) -> 0.92077634 | J14: =SUM(J9/J$11) -> 0.92927585 | K14: =SUM(K9/K$11) -> 0.92642076 | L14: =SUM(L9/L$11) -> 0.92566355 | M14: =SUM(M9/M$11) -> 0.91828979 | N14: =SUM(N9/N$11) -> 0.92965036 | O14: =SUM(O9/O$11) -> 0.92768444 | P14: =SUM(P9/P$11) -> 0.92209922 | Q14: =SUM(Q9/Q$11) -> 0.91560836 | ... X14: =SUM(X9/X$11) -> 0.91790736 | Z14: =J14 -> 0.92927585 | AA14: =K14 -> 0.92642076 | AB14: =L14 -> 0.92566355 | AC14: =M14 -> 0.91828979 | AD14: =N14 -> 0.92965036 | AE14: =O14 -> 0.92768444 | AF14: =P14 -> 0.92209922 | AG14: =Q14 -> 0.91560836 | ... AJ14: =T14 -> 0.92080466
B15: =B10&"(%)" -> International(%) | C15: =SUM(C10/C$11) -> 0.080755305 | D15: =SUM(D10/D$11) -> 0.083978672 | E15: =SUM(E10/E$11) -> 0.07594521 | F15: =SUM(F10/F$11) -> 0.075683615 | G15: =SUM(G10/G$11) -> 0.077211636 | H15: =SUM(H10/H$11) -> 0.079223656 | J15: =SUM(J10/J$11) -> 0.070724148 | K15: =SUM(K10/K$11) -> 0.073579243 | L15: =SUM(L10/L$11) -> 0.07433645 | M15: =SUM(M10/M$11) -> 0.081710214 | N15: =SUM(N10/N$11) -> 0.070349636 | O15: =SUM(O10/O$11) -> 0.072315559 | P15: =SUM(P10/P$11) -> 0.077900779 | Q15: =SUM(Q10/Q$11) -> 0.084391643 | ... X15: =SUM(X10/X$11) -> 0.082092639 | Z15: =J15 -> 0.070724148 | AA15: =K15 -> 0.073579243 | AB15: =L15 -> 0.07433645 | AC15: =M15 -> 0.081710214 | AD15: =N15 -> 0.070349636 | AE15: =O15 -> 0.072315559 | AF15: =P15 -> 0.077900779 | AG15: =Q15 -> 0.084391643 | ... AJ15: =T15 -> 0.079195341
A17: X | B17: Revenue by product category
A19: X | B19: Revenue by product category: Aggregate
B20: Computing and Mobile Phones | C20: =SUM(C37+C54) -> 19399 | D20: =SUM(D37+D54) -> 21653 | E20: =SUM(E37+E54) -> 22478 | F20: =SUM(F37+F54) -> 19766 | G20: =SUM(G37+G54) -> 18482 | H20: =SUM(H37+H54) -> 18681 | J20: =SUM(J37+J54) -> 4629 | K20: =SUM(K37+K54) -> 4291 | L20: =SUM(L37+L54) -> 4726 | M20: =SUM(M37+M54) -> 6120 | N20: =SUM(N37+N54) -> 4004 | O20: =SUM(O37+O54) -> 3983 | P20: =SUM(P37+P54) -> 4316 | Q20: =SUM(Q37+Q54) -> 6179 | ... X20: =SUM(X37+X54) -> 4788 | Z20: =SUM(K20:N20) -> 19141 | AA20: =SUM(L20:O20) -> 18833 | AB20: =SUM(M20:P20) -> 18423 | AC20: =SUM(N20:Q20) -> 18482 | AD20: =SUM(O20:R20) -> 18384 | AE20: =SUM(P20:S20) -> 18501 | AF20: =SUM(Q20:T20) -> 18636 | AG20: =SUM(R20:U20) -> 18681 | ... AJ20: =SUM(U20:X20) -> 19404
B21: Consumer Electronics | C21: =SUM(C38+C55) -> 14292 | D21: =SUM(D38+D55) -> 14211 | E21: =SUM(E38+E55) -> 16203 | F21: =SUM(F38+F55) -> 14094 | G21: =SUM(G38+G55) -> 12969 | H21: =SUM(H38+H55) -> 12065 | J21: =SUM(J38+J55) -> 3109 | K21: =SUM(K38+K55) -> 3068 | L21: =SUM(L38+L55) -> 3109 | M21: =SUM(M38+M55) -> 4808 | N21: =SUM(N38+N55) -> 2776 | O21: =SUM(O38+O55) -> 2852 | P21: =SUM(P38+P55) -> 2789 | Q21: =SUM(Q38+Q55) -> 4552 | ... X21: =SUM(X38+X55) -> 2553 | Z21: =SUM(K21:N21) -> 13761 | AA21: =SUM(L21:O21) -> 13545 | AB21: =SUM(M21:P21) -> 13225 | AC21: =SUM(N21:Q21) -> 12969 | AD21: =SUM(O21:R21) -> 12730 | AE21: =SUM(P21:S21) -> 12542 | AF21: =SUM(Q21:T21) -> 12372 | AG21: =SUM(R21:U21) -> 12065 | ... AJ21: =SUM(U21:X21) -> 11757
B22: Appliances | C22: =SUM(C39+C56) -> 4810 | D22: =SUM(D39+D56) -> 5873 | E22: =SUM(E39+E56) -> 7167 | F22: =SUM(F39+F56) -> 6736 | G22: =SUM(G39+G56) -> 5804 | H22: =SUM(H39+H56) -> 4910 | J22: =SUM(J39+J56) -> 1661 | K22: =SUM(K39+K56) -> 1761 | L22: =SUM(L39+L56) -> 1543 | M22: =SUM(M39+M56) -> 1771 | N22: =SUM(N39+N56) -> 1398 | O22: =SUM(O39+O56) -> 1476 | P22: =SUM(P39+P56) -> 1312 | Q22: =SUM(Q39+Q56) -> 1618 | ... X22: =SUM(X39+X56) -> 1029 | Z22: =SUM(K22:N22) -> 6473 | AA22: =SUM(L22:O22) -> 6188 | AB22: =SUM(M22:P22) -> 5957 | AC22: =SUM(N22:Q22) -> 5804 | AD22: =SUM(O22:R22) -> 5556 | AE22: =SUM(P22:S22) -> 5343 | AF22: =SUM(Q22:T22) -> 5155 | AG22: =SUM(R22:U22) -> 4910 | ... AJ22: =SUM(U22:X22) -> 4614
B23: Entertainment | C23: =SUM(C40+C57) -> 2597 | D23: =SUM(D40+D57) -> 3079 | E23: =SUM(E40+E57) -> 3275 | F23: =SUM(F40+F57) -> 3053 | G23: =SUM(G40+G57) -> 3363 | H23: =SUM(H40+H57) -> 2908 | J23: =SUM(J40+J57) -> 630 | K23: =SUM(K40+K57) -> 559 | L23: =SUM(L40+L57) -> 546 | M23: =SUM(M40+M57) -> 1318 | N23: =SUM(N40+N57) -> 651 | O23: =SUM(O40+O57) -> 594 | P23: =SUM(P40+P57) -> 648 | Q23: =SUM(Q40+Q57) -> 1470 | ... X23: =SUM(X40+X57) -> 597 | Z23: =SUM(K23:N23) -> 3074 | AA23: =SUM(L23:O23) -> 3109 | AB23: =SUM(M23:P23) -> 3211 | AC23: =SUM(N23:Q23) -> 3363 | AD23: =SUM(O23:R23) -> 3278 | AE23: =SUM(P23:S23) -> 3221 | AF23: =SUM(Q23:T23) -> 3099 | AG23: =SUM(R23:U23) -> 2908 | ... AJ23: =SUM(U23:X23) -> 3116
B24: Services | C24: =SUM(C41+C58) -> 2325 | D24: =SUM(D41+D58) -> 2252 | E24: =SUM(E41+E58) -> 2380 | F24: =SUM(F41+F58) -> 2332 | G24: =SUM(G41+G58) -> 2530 | H24: =SUM(H41+H58) -> 2631 | J24: =SUM(J41+J58) -> 543 | K24: =SUM(K41+K58) -> 553 | L24: =SUM(L41+L58) -> 576 | M24: =SUM(M41+M58) -> 660 | N24: =SUM(N41+N58) -> 573 | O24: =SUM(O41+O58) -> 588 | P24: =SUM(P41+P58) -> 608 | Q24: =SUM(Q41+Q58) -> 761 | ... X24: =SUM(X41+X58) -> 638 | Z24: =SUM(K24:N24) -> 2362 | AA24: =SUM(L24:O24) -> 2397 | AB24: =SUM(M24:P24) -> 2429 | AC24: =SUM(N24:Q24) -> 2530 | AD24: =SUM(O24:R24) -> 2574 | AE24: =SUM(P24:S24) -> 2614 | AF24: =SUM(Q24:T24) -> 2654 | AG24: =SUM(R24:U24) -> 2631 | ... AJ24: =SUM(U24:X24) -> 2612
B25: Other | C25: =SUM(C42+C59) -> 215 | D25: =SUM(D42+D59) -> 194 | E25: =SUM(E42+E59) -> 258 | F25: =SUM(F42+F59) -> 317 | G25: =SUM(G42+G59) -> 304 | H25: =SUM(H42+H59) -> 333 | J25: =SUM(J42+J59) -> 75 | K25: =SUM(K42+K59) -> 97 | L25: =SUM(L42+L59) -> 87 | M25: =SUM(M42+M59) -> 58 | N25: =SUM(N42+N59) -> 65 | O25: =SUM(O42+O59) -> 90 | P25: =SUM(P42+P59) -> 83 | Q25: =SUM(Q42+Q59) -> 66 | ... X25: =SUM(X42+X59) -> 67 | Z25: =SUM(K25:N25) -> 307 | AA25: =SUM(L25:O25) -> 300 | AB25: =SUM(M25:P25) -> 296 | AC25: =SUM(N25:Q25) -> 304 | AD25: =SUM(O25:R25) -> 310 | AE25: =SUM(P25:S25) -> 316 | AF25: =SUM(Q25:T25) -> 310 | AG25: =SUM(R25:U25) -> 333 | ... AJ25: =SUM(U25:X25) -> 322
B26: Total Domestic Revenue | C26: =SUM(C20:C25) -> 43638 | D26: =SUM(D20:D25) -> 47262 | E26: =SUM(E20:E25) -> 51761 | F26: =SUM(F20:F25) -> 46298 | G26: =SUM(G20:G25) -> 43452 | H26: =SUM(H20:H25) -> 41528 | J26: =SUM(J20:J25) -> 10647 | K26: =SUM(K20:K25) -> 10329 | L26: =SUM(L20:L25) -> 10587 | M26: =SUM(M20:M25) -> 14735 | N26: =SUM(N20:N25) -> 9467 | O26: =SUM(O20:O25) -> 9583 | P26: =SUM(P20:P25) -> 9756 | Q26: =SUM(Q20:Q25) -> 14646 | ... X26: =SUM(X20:X25) -> 9672 | Z26: =SUM(Z20:Z25) -> 45118 | AA26: =SUM(AA20:AA25) -> 44372 | AB26: =SUM(AB20:AB25) -> 43541 | AC26: =SUM(AC20:AC25) -> 43452 | AD26: =SUM(AD20:AD25) -> 42832 | AE26: =SUM(AE20:AE25) -> 42537 | AF26: =SUM(AF20:AF25) -> 42226 | AG26: =SUM(AG20:AG25) -> 41528 | ... AJ26: =SUM(AJ20:AJ25) -> 41825
B27: Balance Check | C27: =+C26-C11 -> 0 | D27: =+D26-D11 -> 0 | E27: =+E26-E11 -> 0 | F27: =+F26-F11 -> 0 | G27: =+G26-G11 -> 0 | H27: =+H26-H11 -> 0 | J27: =+J26-J11 -> 0 | K27: =+K26-K11 -> 0 | L27: =+L26-L11 -> 0 | M27: =+M26-M11 -> 0 | N27: =+N26-N11 -> 0 | O27: =+O26-O11 -> 0 | P27: =+P26-P11 -> 0 | Q27: =+Q26-Q11 -> 0 | ... X27: =+X26-X11 -> 0 | Z27: =+Z26-Z11 -> 0 | AA27: =+AA26-AA11 -> 0 | AB27: =+AB26-AB11 -> 0 | AC27: =+AC26-AC11 -> 0 | AD27: =+AD26-AD11 -> 0 | AE27: =+AE26-AE11 -> 0 | AF27: =+AF26-AF11 -> 0 | AG27: =+AG26-AG11 -> 0 | ... AJ27: =+AJ26-AJ11 -> 0
B29: =B20&"(%)" -> Computing and Mobile Phones (%) | C29: =C20/C$26 -> 0.44454375 | D29: =D20/D$26 -> 0.4581482 | E29: =E20/E$26 -> 0.43426518 | F29: =F20/F$26 -> 0.42692989 | G29: =G20/G$26 -> 0.42534291 | H29: =H20/H$26 -> 0.44984107 | J29: =J20/J$26 -> 0.43477036 | K29: =K20/K$26 -> 0.41543228 | L29: =L20/L$26 -> 0.44639652 | M29: =M20/M$26 -> 0.41533763 | N29: =N20/N$26 -> 0.42294285 | O29: =O20/O$26 -> 0.41563185 | P29: =P20/P$26 -> 0.44239442 | Q29: =Q20/Q$26 -> 0.42188994 | ... X29: =X20/X$26 -> 0.49503722 | Z29: =Z20/Z$26 -> 0.4242431 | AA29: =AA20/AA$26 -> 0.42443433 | AB29: =AB20/AB$26 -> 0.42311844 | AC29: =AC20/AC$26 -> 0.42534291 | AD29: =AD20/AD$26 -> 0.4292118 | AE29: =AE20/AE$26 -> 0.43493899 | AF29: =AF20/AF$26 -> 0.44133946 | AG29: =AG20/AG$26 -> 0.44984107 | ... AJ29: =AJ20/AJ$26 -> 0.46393305
B30: =B21&"(%)" -> Consumer Electronics (%) | C30: =C21/C$26 -> 0.32751272 | D30: =D21/D$26 -> 0.30068554 | E30: =E21/E$26 -> 0.31303491 | F30: =F21/F$26 -> 0.3044192 | G30: =G21/G$26 -> 0.29846727 | H30: =H21/H$26 -> 0.29052687 | J30: =J21/J$26 -> 0.29200714 | K30: =K21/K$26 -> 0.29702779 | L30: =L21/L$26 -> 0.29366204 | M30: =M21/M$26 -> 0.32629793 | N30: =N21/N$26 -> 0.29322911 | O30: =O21/O$26 -> 0.29761035 | P30: =P21/P$26 -> 0.28587536 | Q30: =Q21/Q$26 -> 0.31080158 | ... X30: =X21/X$26 -> 0.26395782 | Z30: =Z21/Z$26 -> 0.30500022 | AA30: =AA21/AA$26 -> 0.30526007 | AB30: =AB21/AB$26 -> 0.30373671 | AC30: =AC21/AC$26 -> 0.29846727 | AD30: =AD21/AD$26 -> 0.2972077 | AE30: =AE21/AE$26 -> 0.29484919 | AF30: =AF21/AF$26 -> 0.29299484 | AG30: =AG21/AG$26 -> 0.29052687 | ... AJ30: =AJ21/AJ$26 -> 0.28109982
B31: =B22&"(%)" -> Appliances (%) | C31: =C22/C$26 -> 0.11022503 | D31: =D22/D$26 -> 0.12426474 | E31: =E22/E$26 -> 0.13846332 | F31: =F22/F$26 -> 0.14549225 | G31: =G22/G$26 -> 0.13357268 | H31: =H22/H$26 -> 0.11823348 | J31: =J22/J$26 -> 0.15600639 | K31: =K22/K$26 -> 0.17049085 | L31: =L22/L$26 -> 0.14574478 | M31: =M22/M$26 -> 0.12019002 | N31: =N22/N$26 -> 0.14767086 | O31: =O22/O$26 -> 0.15402275 | P31: =P22/P$26 -> 0.13448134 | Q31: =Q22/Q$26 -> 0.11047385 | ... X31: =X22/X$26 -> 0.10638958 | Z31: =Z22/Z$26 -> 0.14346824 | AA31: =AA22/AA$26 -> 0.13945732 | AB31: =AB22/AB$26 -> 0.13681358 | AC31: =AC22/AC$26 -> 0.13357268 | AD31: =AD22/AD$26 -> 0.1297161 | AE31: =AE22/AE$26 -> 0.12560829 | AF31: =AF22/AF$26 -> 0.12208118 | AG31: =AG22/AG$26 -> 0.11823348 | ... AJ31: =AJ22/AJ$26 -> 0.1103168
B32: =B23&"(%)" -> Entertainment (%) | C32: =C23/C$26 -> 0.059512352 | D32: =D23/D$26 -> 0.065147476 | E32: =E23/E$26 -> 0.063271575 | F32: =F23/F$26 -> 0.065942373 | G32: =G23/G$26 -> 0.077395747 | H32: =H23/H$26 -> 0.070025043 | J32: =J23/J$26 -> 0.059171598 | K32: =K23/K$26 -> 0.054119469 | L32: =L23/L$26 -> 0.051572683 | M32: =M23/M$26 -> 0.089446895 | N32: =N23/N$26 -> 0.068765184 | O32: =O23/O$26 -> 0.061984765 | P32: =P23/P$26 -> 0.066420664 | Q32: =Q23/Q$26 -> 0.1003687 | ... X32: =X23/X$26 -> 0.061724566 | Z32: =Z23/Z$26 -> 0.068132453 | AA32: =AA23/AA$26 -> 0.070066709 | AB32: =AB23/AB$26 -> 0.073746584 | AC32: =AC23/AC$26 -> 0.077395747 | AD32: =AD23/AD$26 -> 0.076531565 | AE32: =AE23/AE$26 -> 0.075722312 | AF32: =AF23/AF$26 -> 0.073390802 | AG32: =AG23/AG$26 -> 0.070025043 | ... AJ32: =AJ23/AJ$26 -> 0.074500897
B33: =B24&"(%)" -> Services (%) | C33: =C24/C$26 -> 0.053279252 | D33: =D24/D$26 -> 0.047649274 | E33: =E24/E$26 -> 0.045980565 | F33: =F24/F$26 -> 0.050369346 | G33: =G24/G$26 -> 0.058225168 | H33: =H24/H$26 -> 0.063354845 | J33: =J24/J$26 -> 0.051000282 | K33: =K24/K$26 -> 0.053538581 | L33: =L24/L$26 -> 0.054406347 | M33: =M24/M$26 -> 0.044791313 | N33: =N24/N$26 -> 0.060526038 | O33: =O24/O$26 -> 0.061358656 | P33: =P24/P$26 -> 0.062320623 | Q33: =Q24/Q$26 -> 0.051959579 | ... X33: =X24/X$26 -> 0.065963606 | Z33: =Z24/Z$26 -> 0.052351611 | AA33: =AA24/AA$26 -> 0.054020554 | AB33: =AB24/AB$26 -> 0.0557865 | AC33: =AC24/AC$26 -> 0.058225168 | AD33: =AD24/AD$26 -> 0.060095256 | AE33: =AE24/AE$26 -> 0.061452383 | AF33: =AF24/AF$26 -> 0.062852271 | AG33: =AG24/AG$26 -> 0.063354845 | ... AJ33: =AJ24/AJ$26 -> 0.062450687
B34: =B25&"(%)" -> Other (%) | C34: =C25/C$26 -> 0.0049268986 | D34: =D25/D$26 -> 0.0041047776 | E34: =E25/E$26 -> 0.0049844478 | F34: =F25/F$26 -> 0.006846948 | G34: =G25/G$26 -> 0.0069962257 | H34: =H25/H$26 -> 0.0080186862 | J34: =J25/J$26 -> 0.0070442378 | K34: =K25/K$26 -> 0.009391035 | L34: =L25/L$26 -> 0.0082176254 | M34: =M25/M$26 -> 0.0039362063 | N34: =N25/N$26 -> 0.0068659554 | O34: =O25/O$26 -> 0.009391631 | P34: =P25/P$26 -> 0.0085075851 | Q34: =Q25/Q$26 -> 0.0045063499 | ... X34: =X25/X$26 -> 0.0069272126 | Z34: =Z25/Z$26 -> 0.0068043796 | AA34: =AA25/AA$26 -> 0.0067610205 | AB34: =AB25/AB$26 -> 0.0067981902 | AC34: =AC25/AC$26 -> 0.0069962257 | AD34: =AD25/AD$26 -> 0.0072375794 | AE34: =AE25/AE$26 -> 0.0074288267 | AF34: =AF25/AF$26 -> 0.0073414484 | AG34: =AG25/AG$26 -> 0.0080186862 | ... AJ34: =AJ25/AJ$26 -> 0.0076987448
A36: X | B36: Revenue by product category: Domestic
B37: Computing and Mobile Phones | C37: 17819 | D37: 19799 | E37: 20693 | F37: 18191 | G37: 16930 | H37: 17103 | J37: 4285 | K37: 3964 | L37: 4337 | M37: =SUM(F37-SUM(J37:L37)) -> 5605 | N37: 3688 | O37: 3674 | P37: 3938 | Q37: =SUM(G37-SUM(N37:P37)) -> 5630 | R37: 3588 | S37: 3792 | T37: 4065 | U37: =SUM(H37-SUM(R37:T37)) -> 5658 | V37: 3792 | W37: 3930 | X37: 4368 | Z37: =SUM(K37:N37) -> 17594 | AA37: =SUM(L37:O37) -> 17304 | AB37: =SUM(M37:P37) -> 16905 | AC37: =SUM(N37:Q37) -> 16930 | AD37: =SUM(O37:R37) -> 16830 | AE37: =SUM(P37:S37) -> 16948 | AF37: =SUM(Q37:T37) -> 17075 | AG37: =SUM(R37:U37) -> 17103 | ... AJ37: =SUM(U37:X37) -> 17748
B38: Consumer Electronics | C38: 13129 | D38: 13022 | E38: 15009 | F38: 13040 | G38: 12014 | H38: 11148 | J38: 2896 | K38: 2845 | L38: 2889 | M38: =SUM(F38-SUM(J38:L38)) -> 4410 | N38: 2592 | O38: 2658 | P38: 2589 | Q38: =SUM(G38-SUM(N38:P38)) -> 4175 | R38: 2364 | S38: 2478 | T38: 2425 | U38: =SUM(H38-SUM(R38:T38)) -> 3881 | V38: 2237 | W38: 2351 | X38: 2351 | Z38: =SUM(K38:N38) -> 12736 | AA38: =SUM(L38:O38) -> 12549 | AB38: =SUM(M38:P38) -> 12249 | AC38: =SUM(N38:Q38) -> 12014 | AD38: =SUM(O38:R38) -> 11786 | AE38: =SUM(P38:S38) -> 11606 | AF38: =SUM(Q38:T38) -> 11442 | AG38: =SUM(R38:U38) -> 11148 | ... AJ38: =SUM(U38:X38) -> 10820
B39: Appliances | C39: 4493 | D39: 5489 | E39: 6784 | F39: 6381 | G39: 5469 | H39: 4589 | J39: 1590 | K39: 1657 | L39: 1469 | M39: =SUM(F39-SUM(J39:L39)) -> 1665 | N39: 1339 | O39: 1384 | P39: 1238 | Q39: =SUM(G39-SUM(N39:P39)) -> 1508 | R39: 1090 | S39: 1177 | T39: 1057 | U39: =SUM(H39-SUM(R39:T39)) -> 1265 | V39: 1001 | W39: 1074 | X39: 965 | Z39: =SUM(K39:N39) -> 6130 | AA39: =SUM(L39:O39) -> 5857 | AB39: =SUM(M39:P39) -> 5626 | AC39: =SUM(N39:Q39) -> 5469 | AD39: =SUM(O39:R39) -> 5220 | AE39: =SUM(P39:S39) -> 5013 | AF39: =SUM(Q39:T39) -> 4832 | AG39: =SUM(R39:U39) -> 4589 | ... AJ39: =SUM(U39:X39) -> 4305
B40: Entertainment | C40: 2388 | D40: 2769 | E40: 2963 | F40: 2786 | G40: 3063 | H40: 2641 | J40: 573 | K40: 508 | L40: 500 | M40: =SUM(F40-SUM(J40:L40)) -> 1205 | N40: 591 | O40: 544 | P40: 594 | Q40: =SUM(G40-SUM(N40:P40)) -> 1334 | R40: 520 | S40: 498 | T40: 479 | U40: =SUM(H40-SUM(R40:T40)) -> 1144 | V40: 449 | W40: 681 | X40: 543 | Z40: =SUM(K40:N40) -> 2804 | AA40: =SUM(L40:O40) -> 2840 | AB40: =SUM(M40:P40) -> 2934 | AC40: =SUM(N40:Q40) -> 3063 | AD40: =SUM(O40:R40) -> 2992 | AE40: =SUM(P40:S40) -> 2946 | AF40: =SUM(Q40:T40) -> 2831 | AG40: =SUM(R40:U40) -> 2641 | ... AJ40: =SUM(U40:X40) -> 2817
B41: Services | C41: 2126 | D41: 2082 | E41: 2190 | F41: 2149 | G41: 2357 | H41: 2456 | J41: 489 | K41: 516 | L41: 533 | M41: =SUM(F41-SUM(J41:L41)) -> 611 | N41: 537 | O41: 550 | P41: 563 | Q41: =SUM(G41-SUM(N41:P41)) -> 707 | R41: 578 | S41: 590 | T41: 601 | U41: =SUM(H41-SUM(R41:T41)) -> 687 | V41: 579 | W41: 581 | X41: 591 | Z41: =SUM(K41:N41) -> 2197 | AA41: =SUM(L41:O41) -> 2231 | AB41: =SUM(M41:P41) -> 2261 | AC41: =SUM(N41:Q41) -> 2357 | AD41: =SUM(O41:R41) -> 2398 | AE41: =SUM(P41:S41) -> 2438 | AF41: =SUM(Q41:T41) -> 2476 | AG41: =SUM(R41:U41) -> 2456 | ... AJ41: =SUM(U41:X41) -> 2438
B42: Other | C42: 159 | D42: 132 | E42: 191 | F42: 247 | G42: 264 | H42: 301 | J42: 61 | K42: 79 | L42: 72 | M42: =SUM(F42-SUM(J42:L42)) -> 35 | N42: 54 | O42: 80 | P42: 74 | Q42: =SUM(G42-SUM(N42:P42)) -> 56 | R42: 63 | S42: 88 | T42: 70 | U42: =SUM(H42-SUM(R42:T42)) -> 80 | V42: 69 | W42: 81 | X42: 60 | Z42: =SUM(K42:N42) -> 240 | AA42: =SUM(L42:O42) -> 241 | AB42: =SUM(M42:P42) -> 243 | AC42: =SUM(N42:Q42) -> 264 | AD42: =SUM(O42:R42) -> 273 | AE42: =SUM(P42:S42) -> 281 | AF42: =SUM(Q42:T42) -> 277 | AG42: =SUM(R42:U42) -> 301 | ... AJ42: =SUM(U42:X42) -> 290
B43: Total Domestic Revenue | C43: =SUM(C37:C42) -> 40114 | D43: =SUM(D37:D42) -> 43293 | E43: =SUM(E37:E42) -> 47830 | F43: =SUM(F37:F42) -> 42794 | G43: =SUM(G37:G42) -> 40097 | H43: =SUM(H37:H42) -> 38238 | J43: =SUM(J37:J42) -> 9894 | K43: =SUM(K37:K42) -> 9569 | L43: =SUM(L37:L42) -> 9800 | M43: =SUM(M37:M42) -> 13531 | N43: =SUM(N37:N42) -> 8801 | O43: =SUM(O37:O42) -> 8890 | P43: =SUM(P37:P42) -> 8996 | Q43: =SUM(Q37:Q42) -> 13410 | ... X43: =SUM(X37:X42) -> 8878 | Z43: =SUM(Z37:Z42) -> 41701 | AA43: =SUM(AA37:AA42) -> 41022 | AB43: =SUM(AB37:AB42) -> 40218 | AC43: =SUM(AC37:AC42) -> 40097 | AD43: =SUM(AD37:AD42) -> 39499 | AE43: =SUM(AE37:AE42) -> 39232 | AF43: =SUM(AF37:AF42) -> 38933 | AG43: =SUM(AG37:AG42) -> 38238 | ... AJ43: =SUM(AJ37:AJ42) -> 38418
B44: Balance Check | C44: =+C43-C9 -> 0 | D44: =+D43-D9 -> 0 | E44: =+E43-E9 -> 0 | F44: =+F43-F9 -> 0 | G44: =+G43-G9 -> 0 | H44: =+H43-H9 -> 0 | J44: =+J43-J9 -> 0 | K44: =+K43-K9 -> 0 | L44: =+L43-L9 -> 0 | M44: =+M43-M9 -> 0 | N44: =+N43-N9 -> 0 | O44: =+O43-O9 -> 0 | P44: =+P43-P9 -> 0 | Q44: =+Q43-Q9 -> 0 | ... X44: =+X43-X9 -> 0 | Z44: =+Z43-Z9 -> 0 | AA44: =+AA43-AA9 -> 0 | AB44: =+AB43-AB9 -> 0 | AC44: =+AC43-AC9 -> 0 | AD44: =+AD43-AD9 -> 0 | AE44: =+AE43-AE9 -> 0 | AF44: =+AF43-AF9 -> 0 | AG44: =+AG43-AG9 -> 0 | ... AJ44: =+AJ43-AJ9 -> 0
B46: =B37&"(%)" -> Computing and Mobile Phones (%) | C46: =C37/C$43 -> 0.444209 | D46: =D37/D$43 -> 0.45732566 | E46: =E37/E$43 -> 0.43263642 | F46: =F37/F$43 -> 0.42508296 | G46: =G37/G$43 -> 0.4222261 | H46: =H37/H$43 -> 0.44727758 | J46: =J37/J$43 -> 0.43309076 | K46: =K37/K$43 -> 0.41425436 | L46: =L37/L$43 -> 0.44255102 | M46: =M37/M$43 -> 0.41423398 | N46: =N37/N$43 -> 0.41904329 | O46: =O37/O$43 -> 0.41327334 | P46: =P37/P$43 -> 0.43775011 | Q46: =Q37/Q$43 -> 0.41983594 | ... X46: =X37/X$43 -> 0.4920027 | Z46: =Z37/Z$43 -> 0.42190835 | AA46: =AA37/AA$43 -> 0.42182244 | AB46: =AB37/AB$43 -> 0.42033418 | AC46: =AC37/AC$43 -> 0.4222261 | AD46: =AD37/AD$43 -> 0.42608674 | AE46: =AE37/AE$43 -> 0.43199429 | AF46: =AF37/AF$43 -> 0.43857396 | AG46: =AG37/AG$43 -> 0.44727758 | ... AJ46: =AJ37/AJ$43 -> 0.46197095
B47: =B38&"(%)" -> Consumer Electronics (%) | C47: =C38/C$43 -> 0.32729222 | D47: =D38/D$43 -> 0.30078766 | E47: =E38/E$43 -> 0.31379887 | F47: =F38/F$43 -> 0.30471561 | G47: =G38/G$43 -> 0.29962341 | H47: =H38/H$43 -> 0.29154244 | J47: =J38/J$43 -> 0.29270265 | K47: =K38/K$43 -> 0.29731424 | L47: =L38/L$43 -> 0.29479592 | M47: =M38/M$43 -> 0.32591826 | N47: =N38/N$43 -> 0.29451199 | O47: =O38/O$43 -> 0.29898763 | P47: =P38/P$43 -> 0.28779458 | Q47: =Q38/Q$43 -> 0.31133482 | ... X47: =X38/X$43 -> 0.26481189 | Z47: =Z38/Z$43 -> 0.30541234 | AA47: =AA38/AA$43 -> 0.30590902 | AB47: =AB38/AB$43 -> 0.30456512 | AC47: =AC38/AC$43 -> 0.29962341 | AD47: =AD38/AD$43 -> 0.2983873 | AE47: =AE38/AE$43 -> 0.29582993 | AF47: =AF38/AF$43 -> 0.2938895 | AG47: =AG38/AG$43 -> 0.29154244 | ... AJ47: =AJ38/AJ$43 -> 0.28163882
B48: =B39&"(%)" -> Appliances (%) | C48: =C39/C$43 -> 0.11200578 | D48: =D39/D$43 -> 0.12678724 | E48: =E39/E$43 -> 0.14183567 | F48: =F39/F$43 -> 0.14910969 | G48: =G39/G$43 -> 0.13639424 | H48: =H39/H$43 -> 0.12001151 | J48: =J39/J$43 -> 0.16070346 | K48: =K39/K$43 -> 0.17316334 | L48: =L39/L$43 -> 0.14989796 | M48: =M39/M$43 -> 0.12305077 | N48: =N39/N$43 -> 0.1521418 | O48: =O39/O$43 -> 0.15568054 | P48: =P39/P$43 -> 0.13761672 | Q48: =Q39/Q$43 -> 0.11245339 | ... X48: =X39/X$43 -> 0.10869565 | Z48: =Z39/Z$43 -> 0.14699887 | AA48: =AA39/AA$43 -> 0.14277705 | AB48: =AB39/AB$43 -> 0.13988761 | AC48: =AC39/AC$43 -> 0.13639424 | AD48: =AD39/AD$43 -> 0.13215524 | AE48: =AE39/AE$43 -> 0.12777834 | AF48: =AF39/AF$43 -> 0.12411065 | AG48: =AG39/AG$43 -> 0.12001151 | ... AJ48: =AJ39/AJ$43 -> 0.11205685
B49: =B40&"(%)" -> Entertainment (%) | C49: =C40/C$43 -> 0.059530339 | D49: =D40/D$43 -> 0.063959532 | E49: =E40/E$43 -> 0.061948568 | F49: =F40/F$43 -> 0.065102584 | G49: =G40/G$43 -> 0.076389755 | H49: =H40/H$43 -> 0.06906742 | J49: =J40/J$43 -> 0.057913887 | K49: =K40/K$43 -> 0.053088097 | L49: =L40/L$43 -> 0.051020408 | M49: =M40/M$43 -> 0.089054763 | N49: =N40/N$43 -> 0.06715146 | O49: =O40/O$43 -> 0.061192351 | P49: =P40/P$43 -> 0.066029346 | Q49: =Q40/Q$43 -> 0.099478001 | ... X49: =X40/X$43 -> 0.061162424 | Z49: =Z40/Z$43 -> 0.067240594 | AA49: =AA40/AA$43 -> 0.069231144 | AB49: =AB40/AB$43 -> 0.072952409 | AC49: =AC40/AC$43 -> 0.076389755 | AD49: =AD40/AD$43 -> 0.075748753 | AE49: =AE40/AE$43 -> 0.075091762 | AF49: =AF40/AF$43 -> 0.072714664 | AG49: =AG40/AG$43 -> 0.06906742 | ... AJ49: =AJ40/AJ$43 -> 0.073325004
B50: =B41&"(%)" -> Services (%) | C50: =C41/C$43 -> 0.052998953 | D50: =D41/D$43 -> 0.048090915 | E50: =E41/E$43 -> 0.045787163 | F50: =F41/F$43 -> 0.05021732 | G50: =G41/G$43 -> 0.058782453 | H50: =H41/H$43 -> 0.064229301 | J50: =J41/J$43 -> 0.049423893 | K50: =K41/K$43 -> 0.05392413 | L50: =L41/L$43 -> 0.054387755 | M50: =M41/M$43 -> 0.045155569 | N50: =N41/N$43 -> 0.061015794 | O50: =O41/O$43 -> 0.061867267 | P50: =P41/P$43 -> 0.06258337 | Q50: =Q41/Q$43 -> 0.052721849 | ... X50: =X41/X$43 -> 0.066569047 | Z50: =Z41/Z$43 -> 0.052684588 | AA50: =AA41/AA$43 -> 0.054385452 | AB50: =AB41/AB$43 -> 0.056218609 | AC50: =AC41/AC$43 -> 0.058782453 | AD50: =AD41/AD$43 -> 0.060710398 | AE50: =AE41/AE$43 -> 0.062143148 | AF50: =AF41/AF$43 -> 0.063596435 | AG50: =AG41/AG$43 -> 0.064229301 | ... AJ50: =AJ41/AJ$43 -> 0.063459837
B51: =B42&"(%)" -> Other (%) | C51: =C42/C$43 -> 0.0039637034 | D51: =D42/D$43 -> 0.0030489918 | E51: =E42/E$43 -> 0.0039933096 | F51: =F42/F$43 -> 0.0057718372 | G51: =G42/G$43 -> 0.0065840337 | H51: =H42/H$43 -> 0.0078717506 | J51: =J42/J$43 -> 0.0061653527 | K51: =K42/K$43 -> 0.0082558261 | L51: =L42/L$43 -> 0.0073469388 | M51: =M42/M$43 -> 0.0025866529 | N51: =N42/N$43 -> 0.0061356664 | O51: =O42/O$43 -> 0.0089988751 | P51: =P42/P$43 -> 0.0082258782 | Q51: =Q42/Q$43 -> 0.0041759881 | ... X51: =X42/X$43 -> 0.0067582789 | Z51: =Z42/Z$43 -> 0.0057552577 | AA51: =AA42/AA$43 -> 0.0058748964 | AB51: =AB42/AB$43 -> 0.0060420707 | AC51: =AC42/AC$43 -> 0.0065840337 | AD51: =AD42/AD$43 -> 0.0069115674 | AE51: =AE42/AE$43 -> 0.0071625204 | AF51: =AF42/AF$43 -> 0.0071147869 | AG51: =AG42/AG$43 -> 0.0078717506 | ... AJ51: =AJ42/AJ$43 -> 0.007548545
A53: X | B53: Revenue by product category: International
B54: Computing and Mobile Phones | C54: 1580 | D54: 1854 | E54: 1785 | F54: 1575 | G54: 1552 | H54: 1578 | J54: 344 | K54: 327 | L54: 389 | M54: =SUM(F54-SUM(J54:L54)) -> 515 | N54: 316 | O54: 309 | P54: 378 | Q54: =SUM(G54-SUM(N54:P54)) -> 549 | R54: 318 | S54: 308 | T54: 386 | U54: =SUM(H54-SUM(R54:T54)) -> 566 | V54: 324 | W54: 346 | X54: 420 | Z54: =SUM(K54:N54) -> 1547 | AA54: =SUM(L54:O54) -> 1529 | AB54: =SUM(M54:P54) -> 1518 | AC54: =SUM(N54:Q54) -> 1552 | AD54: =SUM(O54:R54) -> 1554 | AE54: =SUM(P54:S54) -> 1553 | AF54: =SUM(Q54:T54) -> 1561 | AG54: =SUM(R54:U54) -> 1578 | ... AJ54: =SUM(U54:X54) -> 1656
B55: Consumer Electronics | C55: 1163 | D55: 1189 | E55: 1194 | F55: 1054 | G55: 955 | H55: 917 | J55: 213 | K55: 223 | L55: 220 | M55: =SUM(F55-SUM(J55:L55)) -> 398 | N55: 184 | O55: 194 | P55: 200 | Q55: =SUM(G55-SUM(N55:P55)) -> 377 | R55: 173 | S55: 186 | T55: 194 | U55: =SUM(H55-SUM(R55:T55)) -> 364 | V55: 173 | W55: 198 | X55: 202 | Z55: =SUM(K55:N55) -> 1025 | AA55: =SUM(L55:O55) -> 996 | AB55: =SUM(M55:P55) -> 976 | AC55: =SUM(N55:Q55) -> 955 | AD55: =SUM(O55:R55) -> 944 | AE55: =SUM(P55:S55) -> 936 | AF55: =SUM(Q55:T55) -> 930 | AG55: =SUM(R55:U55) -> 917 | ... AJ55: =SUM(U55:X55) -> 937
B56: Appliances | C56: 317 | D56: 384 | E56: 383 | F56: 355 | G56: 335 | H56: 321 | J56: 71 | K56: 104 | L56: 74 | M56: =SUM(F56-SUM(J56:L56)) -> 106 | N56: 59 | O56: 92 | P56: 74 | Q56: =SUM(G56-SUM(N56:P56)) -> 110 | R56: 60 | S56: 86 | T56: 67 | U56: =SUM(H56-SUM(R56:T56)) -> 108 | V56: 57 | W56: 80 | X56: 64 | Z56: =SUM(K56:N56) -> 343 | AA56: =SUM(L56:O56) -> 331 | AB56: =SUM(M56:P56) -> 331 | AC56: =SUM(N56:Q56) -> 335 | AD56: =SUM(O56:R56) -> 336 | AE56: =SUM(P56:S56) -> 330 | AF56: =SUM(Q56:T56) -> 323 | AG56: =SUM(R56:U56) -> 321 | ... AJ56: =SUM(U56:X56) -> 309
B57: Entertainment | C57: 209 | D57: 310 | E57: 312 | F57: 267 | G57: 300 | H57: 267 | J57: 57 | K57: 51 | L57: 46 | M57: =SUM(F57-SUM(J57:L57)) -> 113 | N57: 60 | O57: 50 | P57: 54 | Q57: =SUM(G57-SUM(N57:P57)) -> 136 | R57: 46 | S57: 39 | T57: 47 | U57: =SUM(H57-SUM(R57:T57)) -> 135 | V57: 42 | W57: 68 | X57: 54 | Z57: =SUM(K57:N57) -> 270 | AA57: =SUM(L57:O57) -> 269 | AB57: =SUM(M57:P57) -> 277 | AC57: =SUM(N57:Q57) -> 300 | AD57: =SUM(O57:R57) -> 286 | AE57: =SUM(P57:S57) -> 275 | AF57: =SUM(Q57:T57) -> 268 | AG57: =SUM(R57:U57) -> 267 | ... AJ57: =SUM(U57:X57) -> 299
B58: Services | C58: 199 | D58: 170 | E58: 190 | F58: 183 | G58: 173 | H58: 175 | J58: 54 | K58: 37 | L58: 43 | M58: =SUM(F58-SUM(J58:L58)) -> 49 | N58: 36 | O58: 38 | P58: 45 | Q58: =SUM(G58-SUM(N58:P58)) -> 54 | R58: 39 | S58: 38 | T58: 47 | U58: =SUM(H58-SUM(R58:T58)) -> 51 | V58: 37 | W58: 39 | X58: 47 | Z58: =SUM(K58:N58) -> 165 | AA58: =SUM(L58:O58) -> 166 | AB58: =SUM(M58:P58) -> 168 | AC58: =SUM(N58:Q58) -> 173 | AD58: =SUM(O58:R58) -> 176 | AE58: =SUM(P58:S58) -> 176 | AF58: =SUM(Q58:T58) -> 178 | AG58: =SUM(R58:U58) -> 175 | ... AJ58: =SUM(U58:X58) -> 174
B59: Other | C59: 56 | D59: 62 | E59: 67 | F59: 70 | G59: 40 | H59: 32 | J59: 14 | K59: 18 | L59: 15 | M59: =SUM(F59-SUM(J59:L59)) -> 23 | N59: 11 | O59: 10 | P59: 9 | Q59: =SUM(G59-SUM(N59:P59)) -> 10 | R59: 8 | S59: 8 | T59: 7 | U59: =SUM(H59-SUM(R59:T59)) -> 9 | V59: 7 | W59: 9 | X59: 7 | Z59: =SUM(K59:N59) -> 67 | AA59: =SUM(L59:O59) -> 59 | AB59: =SUM(M59:P59) -> 53 | AC59: =SUM(N59:Q59) -> 40 | AD59: =SUM(O59:R59) -> 37 | AE59: =SUM(P59:S59) -> 35 | AF59: =SUM(Q59:T59) -> 33 | AG59: =SUM(R59:U59) -> 32 | ... AJ59: =SUM(U59:X59) -> 32
B60: Total International Revenue | C60: =SUM(C54:C59) -> 3524 | D60: =SUM(D54:D59) -> 3969 | E60: =SUM(E54:E59) -> 3931 | F60: =SUM(F54:F59) -> 3504 | G60: =SUM(G54:G59) -> 3355 | H60: =SUM(H54:H59) -> 3290 | J60: =SUM(J54:J59) -> 753 | K60: =SUM(K54:K59) -> 760 | L60: =SUM(L54:L59) -> 787 | M60: =SUM(M54:M59) -> 1204 | N60: =SUM(N54:N59) -> 666 | O60: =SUM(O54:O59) -> 693 | P60: =SUM(P54:P59) -> 760 | Q60: =SUM(Q54:Q59) -> 1236 | ... X60: =SUM(X54:X59) -> 794 | Z60: =SUM(Z54:Z59) -> 3417 | AA60: =SUM(AA54:AA59) -> 3350 | AB60: =SUM(AB54:AB59) -> 3323 | AC60: =SUM(AC54:AC59) -> 3355 | AD60: =SUM(AD54:AD59) -> 3333 | AE60: =SUM(AE54:AE59) -> 3305 | AF60: =SUM(AF54:AF59) -> 3293 | AG60: =SUM(AG54:AG59) -> 3290 | ... AJ60: =SUM(AJ54:AJ59) -> 3407
B61: Balance Check | C61: =+C60-C10 -> 0 | D61: =+D60-D10 -> 0 | E61: =+E60-E10 -> 0 | F61: =+F60-F10 -> 0 | G61: =+G60-G10 -> 0 | H61: =+H60-H10 -> 0 | J61: =+J60-J10 -> 0 | K61: =+K60-K10 -> 0 | L61: =+L60-L10 -> 0 | M61: =+M60-M10 -> 0 | N61: =+N60-N10 -> 0 | O61: =+O60-O10 -> 0 | P61: =+P60-P10 -> 0 | Q61: =+Q60-Q10 -> 0 | ... X61: =+X60-X10 -> 0 | Z61: =+Z60-Z10 -> 0 | AA61: =+AA60-AA10 -> 0 | AB61: =+AB60-AB10 -> 0 | AC61: =+AC60-AC10 -> 0 | AD61: =+AD60-AD10 -> 0 | AE61: =+AE60-AE10 -> 0 | AF61: =+AF60-AF10 -> 0 | AG61: =+AG60-AG10 -> 0 | ... AJ61: =+AJ60-AJ10 -> 0
B63: =B54&"(%)" -> Computing and Mobile Phones (%) | C63: =C54/C$43 -> 0.039387745 | D63: =D54/D$43 -> 0.042824475 | E63: =E54/E$43 -> 0.037319674 | F63: =F54/F$43 -> 0.036804225 | G63: =G54/G$43 -> 0.038706138 | H63: =H54/H$43 -> 0.041267849 | J63: =J54/J$43 -> 0.034768547 | K63: =K54/K$43 -> 0.03417285 | L63: =L54/L$43 -> 0.039693878 | M63: =M54/M$43 -> 0.038060749 | N63: =N54/N$43 -> 0.035905011 | O63: =O54/O$43 -> 0.034758155 | P63: =P54/P$43 -> 0.042018675 | Q63: =Q54/Q$43 -> 0.040939597 | ... X63: =X54/X$43 -> 0.047307952 | Z63: =Z54/Z$43 -> 0.037097432 | AA63: =AA54/AA$43 -> 0.037272683 | AB63: =AB54/AB$43 -> 0.037744294 | AC63: =AC54/AC$43 -> 0.038706138 | AD63: =AD54/AD$43 -> 0.039342768 | AE63: =AE54/AE$43 -> 0.039585033 | AF63: =AF54/AF$43 -> 0.040094521 | AG63: =AG54/AG$43 -> 0.041267849 | ... AJ63: =AJ54/AJ$43 -> 0.043104795
B64: =B55&"(%)" -> Consumer Electronics (%) | C64: =C55/C$43 -> 0.028992372 | D64: =D55/D$43 -> 0.027464024 | E64: =E55/E$43 -> 0.024963412 | F64: =F55/F$43 -> 0.024629621 | G64: =G55/G$43 -> 0.023817243 | H64: =H55/H$43 -> 0.02398138 | J64: =J55/J$43 -> 0.021528199 | K64: =K55/K$43 -> 0.023304421 | L64: =L55/L$43 -> 0.02244898 | M64: =M55/M$43 -> 0.029413938 | N64: =N55/N$43 -> 0.020906715 | O64: =O55/O$43 -> 0.021822272 | P64: =P55/P$43 -> 0.022232103 | Q64: =Q55/Q$43 -> 0.028113348 | ... X64: =X55/X$43 -> 0.022752872 | Z64: =Z55/Z$43 -> 0.024579746 | AA64: =AA55/AA$43 -> 0.024279655 | AB64: =AB55/AB$43 -> 0.024267741 | AC64: =AC55/AC$43 -> 0.023817243 | AD64: =AD55/AD$43 -> 0.023899339 | AE64: =AE55/AE$43 -> 0.023858075 | AF64: =AF55/AF$43 -> 0.023887191 | AG64: =AG55/AG$43 -> 0.02398138 | ... AJ64: =AJ55/AJ$43 -> 0.024389609
B65: =B56&"(%)" -> Appliances (%) | C65: =C56/C$43 -> 0.0079024779 | D65: =D56/D$43 -> 0.0088697942 | E65: =E56/E$43 -> 0.0080075267 | F65: =F56/F$43 -> 0.0082955555 | G65: =G56/G$43 -> 0.0083547398 | H65: =H56/H$43 -> 0.0083947905 | J65: =J56/J$43 -> 0.0071760663 | K65: =K56/K$43 -> 0.010868429 | L65: =L56/L$43 -> 0.0075510204 | M65: =M56/M$43 -> 0.007833863 | N65: =N56/N$43 -> 0.0067037837 | O65: =O56/O$43 -> 0.010348706 | P65: =P56/P$43 -> 0.0082258782 | Q65: =Q56/Q$43 -> 0.0082028337 | ... X65: =X56/X$43 -> 0.0072088308 | Z65: =Z56/Z$43 -> 0.0082252224 | AA65: =AA56/AA$43 -> 0.0080688411 | AB65: =AB56/AB$43 -> 0.0082301457 | AC65: =AC56/AC$43 -> 0.0083547398 | AD65: =AD56/AD$43 -> 0.0085065445 | AE65: =AE56/AE$43 -> 0.0084115008 | AF65: =AF56/AF$43 -> 0.0082963039 | AG65: =AG56/AG$43 -> 0.0083947905 | ... AJ65: =AJ56/AJ$43 -> 0.0080431048
B66: =B57&"(%)" -> Entertainment (%) | C66: =C57/C$43 -> 0.0052101511 | D66: =D57/D$43 -> 0.0071605109 | E66: =E57/E$43 -> 0.0065231027 | F66: =F57/F$43 -> 0.0062391924 | G66: =G57/G$43 -> 0.0074818565 | H66: =H57/H$43 -> 0.0069825828 | J66: =J57/J$43 -> 0.0057610673 | K66: =K57/K$43 -> 0.0053297105 | L66: =L57/L$43 -> 0.0046938776 | M66: =M57/M$43 -> 0.0083511936 | N66: =N57/N$43 -> 0.0068174071 | O66: =O57/O$43 -> 0.005624297 | P66: =P57/P$43 -> 0.0060026679 | Q66: =Q57/Q$43 -> 0.010141685 | ... X66: =X57/X$43 -> 0.006082451 | Z66: =Z57/Z$43 -> 0.0064746649 | AA66: =AA57/AA$43 -> 0.006557457 | AB66: =AB57/AB$43 -> 0.0068874633 | AC66: =AC57/AC$43 -> 0.0074818565 | AD66: =AD57/AD$43 -> 0.0072406896 | AE66: =AE57/AE$43 -> 0.007009584 | AF66: =AF57/AF$43 -> 0.0068836206 | AG66: =AG57/AG$43 -> 0.0069825828 | ... AJ66: =AJ57/AJ$43 -> 0.0077828101
B67: =B58&"(%)" -> Services (%) | C67: =C58/C$43 -> 0.0049608615 | D67: =D58/D$43 -> 0.0039267318 | E67: =E58/E$43 -> 0.0039724023 | F67: =F58/F$43 -> 0.0042763004 | G67: =G58/G$43 -> 0.0043145372 | H67: =H58/H$43 -> 0.0045765992 | J67: =J58/J$43 -> 0.0054578532 | K67: =K58/K$43 -> 0.0038666527 | L67: =L58/L$43 -> 0.0043877551 | M67: =M58/M$43 -> 0.003621314 | N67: =N58/N$43 -> 0.0040904443 | O67: =O58/O$43 -> 0.0042744657 | P67: =P58/P$43 -> 0.0050022232 | Q67: =Q58/Q$43 -> 0.0040268456 | ... X67: =X58/X$43 -> 0.0052939851 | Z67: =Z58/Z$43 -> 0.0039567396 | AA67: =AA58/AA$43 -> 0.0040466091 | AB67: =AB58/AB$43 -> 0.0041772341 | AC67: =AC58/AC$43 -> 0.0043145372 | AD67: =AD58/AD$43 -> 0.004455809 | AE67: =AE58/AE$43 -> 0.0044861338 | AF67: =AF58/AF$43 -> 0.004571957 | AG67: =AG58/AG$43 -> 0.0045765992 | ... AJ67: =AJ58/AJ$43 -> 0.004529127
B68: =B59&"(%)" -> Other (%) | C68: =C59/C$43 -> 0.0013960213 | D68: =D59/D$43 -> 0.0014321022 | E68: =E59/E$43 -> 0.0014007945 | F68: =F59/F$43 -> 0.0016357433 | G68: =G59/G$43 -> 0.00099758087 | H68: =H59/H$43 -> 0.00083686385 | J68: =J59/J$43 -> 0.001414999 | K68: =K59/K$43 -> 0.0018810743 | L68: =L59/L$43 -> 0.0015306122 | M68: =M59/M$43 -> 0.0016998005 | N68: =N59/N$43 -> 0.001249858 | O68: =O59/O$43 -> 0.0011248594 | P68: =P59/P$43 -> 0.0010004446 | Q68: =Q59/Q$43 -> 0.00074571216 | ... X68: =X59/X$43 -> 0.00078846587 | Z68: =Z59/Z$43 -> 0.0016066761 | AA68: =AA59/AA$43 -> 0.0014382526 | AB68: =AB59/AB$43 -> 0.0013178179 | AC68: =AC59/AC$43 -> 0.00099758087 | AD68: =AD59/AD$43 -> 0.00093673258 | AE68: =AE59/AE$43 -> 0.00089212887 | AF68: =AF59/AF$43 -> 0.00084761 | AG68: =AG59/AG$43 -> 0.00083686385 | ... AJ68: =AJ59/AJ$43 -> 0.00083294289

Sheet FCF
B2: ='Historical Financials'!B2 -> Best Buy Co Inc (NASDAQ: BBY) | F2: FYE | J2: Quarterly | T2: Quarterly | AE2: LTM | AF2: LTM | AL2: Variance
B3: FCF Analysis | C3: ='Historical Financials'!C7 -> 2020 | D3: ='Historical Financials'!D7 -> 2021 | E3: ='Historical Financials'!E7 -> 2022 | F3: ='Historical Financials'!F7 -> 2023 | G3: ='Historical Financials'!G7 -> 2024 | H3: ='Historical Financials'!H7 -> 2025 | J3: ='Historical Financials'!J7 -> 1Q23 | K3: ='Historical Financials'!K7 -> 2Q23 | L3: ='Historical Financials'!L7 -> 3Q23 | M3: ='Historical Financials'!M7 -> 4Q23 | N3: ='Historical Financials'!N7 -> 1Q24 | O3: ='Historical Financials'!O7 -> 2Q24 | P3: ='Historical Financials'!P7 -> 3Q24 | Q3: ='Historical Financials'!Q7 -> 4Q24 | ... X3: ='Historical Financials'!X7 -> 3Q26 | Z3: =N3 -> 1Q24 | AA3: =O3 -> 2Q24 | AB3: =P3 -> 3Q24 | AC3: =Q3 -> 4Q24 | AD3: =R3 -> 1Q25 | AE3: =S3 -> 2Q25 | AF3: =T3 -> 3Q25 | AG3: =U3 -> 4Q25 | ... AJ3: =X3 -> 3Q26
B4: ($ In Millions) | C4: ='Historical Financials'!C8 -> 43862 | D4: ='Historical Financials'!D8 -> 44226 | E4: ='Historical Financials'!E8 -> 44590 | F4: ='Historical Financials'!F8 -> 44954 | G4: ='Historical Financials'!G8 -> 45325 | H4: ='Historical Financials'!H8 -> 45689 | J4: ='Historical Financials'!J8 -> 44681 | K4: ='Historical Financials'!K8 -> 44772 | L4: ='Historical Financials'!L8 -> 44863 | M4: ='Historical Financials'!M8 -> 44954 | N4: ='Historical Financials'!N8 -> 45045 | O4: ='Historical Financials'!O8 -> 45136 | P4: ='Historical Financials'!P8 -> 45227 | Q4: ='Historical Financials'!Q8 -> 45325 | ... X4: ='Historical Financials'!X8 -> 45962 | Z4: =N4 -> 45045 | AA4: =O4 -> 45136 | AB4: =P4 -> 45227 | AC4: =Q4 -> 45325 | AD4: =R4 -> 45416 | AE4: =S4 -> 45507 | AF4: =T4 -> 45598 | AG4: =U4 -> 45689 | ... AJ4: =X4 -> 45962
B6: Computing and Mobile Phones | C6: ='Revenue Drivers'!C20 -> 19399 | D6: ='Revenue Drivers'!D20 -> 21653 | E6: ='Revenue Drivers'!E20 -> 22478 | F6: ='Revenue Drivers'!F20 -> 19766 | G6: ='Revenue Drivers'!G20 -> 18482 | H6: ='Revenue Drivers'!H20 -> 18681 | J6: ='Revenue Drivers'!J20 -> 4629 | K6: ='Revenue Drivers'!K20 -> 4291 | L6: ='Revenue Drivers'!L20 -> 4726 | M6: ='Revenue Drivers'!M20 -> 6120 | N6: ='Revenue Drivers'!N20 -> 4004 | O6: ='Revenue Drivers'!O20 -> 3983 | P6: ='Revenue Drivers'!P20 -> 4316 | Q6: ='Revenue Drivers'!Q20 -> 6179 | ... X6: ='Revenue Drivers'!X20 -> 4788 | Z6: =SUM(K6:N6) -> 19141 | AA6: =SUM(L6:O6) -> 18833 | AB6: =SUM(M6:P6) -> 18423 | AC6: =SUM(N6:Q6) -> 18482 | AD6: =SUM(O6:R6) -> 18384 | AE6: =SUM(P6:S6) -> 18501 | AF6: =SUM(Q6:T6) -> 18636 | AG6: =SUM(R6:U6) -> 18681 | ... AJ6: =SUM(U6:X6) -> 19404 | AL6: =SUM(AJ6/AF6)-1 -> 0.04121056
B7: Consumer Electronics | C7: ='Revenue Drivers'!C21 -> 14292 | D7: ='Revenue Drivers'!D21 -> 14211 | E7: ='Revenue Drivers'!E21 -> 16203 | F7: ='Revenue Drivers'!F21 -> 14094 | G7: ='Revenue Drivers'!G21 -> 12969 | H7: ='Revenue Drivers'!H21 -> 12065 | J7: ='Revenue Drivers'!J21 -> 3109 | K7: ='Revenue Drivers'!K21 -> 3068 | L7: ='Revenue Drivers'!L21 -> 3109 | M7: ='Revenue Drivers'!M21 -> 4808 | N7: ='Revenue Drivers'!N21 -> 2776 | O7: ='Revenue Drivers'!O21 -> 2852 | P7: ='Revenue Drivers'!P21 -> 2789 | Q7: ='Revenue Drivers'!Q21 -> 4552 | ... X7: ='Revenue Drivers'!X21 -> 2553 | Z7: =SUM(K7:N7) -> 13761 | AA7: =SUM(L7:O7) -> 13545 | AB7: =SUM(M7:P7) -> 13225 | AC7: =SUM(N7:Q7) -> 12969 | AD7: =SUM(O7:R7) -> 12730 | AE7: =SUM(P7:S7) -> 12542 | AF7: =SUM(Q7:T7) -> 12372 | AG7: =SUM(R7:U7) -> 12065 | ... AJ7: =SUM(U7:X7) -> 11757 | AL7: =SUM(AJ7/AF7)-1 -> -0.04970902
B8: Appliances | C8: ='Revenue Drivers'!C22 -> 4810 | D8: ='Revenue Drivers'!D22 -> 5873 | E8: ='Revenue Drivers'!E22 -> 7167 | F8: ='Revenue Drivers'!F22 -> 6736 | G8: ='Revenue Drivers'!G22 -> 5804 | H8: ='Revenue Drivers'!H22 -> 4910 | J8: ='Revenue Drivers'!J22 -> 1661 | K8: ='Revenue Drivers'!K22 -> 1761 | L8: ='Revenue Drivers'!L22 -> 1543 | M8: ='Revenue Drivers'!M22 -> 1771 | N8: ='Revenue Drivers'!N22 -> 1398 | O8: ='Revenue Drivers'!O22 -> 1476 | P8: ='Revenue Drivers'!P22 -> 1312 | Q8: ='Revenue Drivers'!Q22 -> 1618 | ... X8: ='Revenue Drivers'!X22 -> 1029 | Z8: =SUM(K8:N8) -> 6473 | AA8: =SUM(L8:O8) -> 6188 | AB8: =SUM(M8:P8) -> 5957 | AC8: =SUM(N8:Q8) -> 5804 | AD8: =SUM(O8:R8) -> 5556 | AE8: =SUM(P8:S8) -> 5343 | AF8: =SUM(Q8:T8) -> 5155 | AG8: =SUM(R8:U8) -> 4910 | ... AJ8: =SUM(U8:X8) -> 4614 | AL8: =SUM(AJ8/AF8)-1 -> -0.10494665
B9: Entertainment | C9: ='Revenue Drivers'!C23 -> 2597 | D9: ='Revenue Drivers'!D23 -> 3079 | E9: ='Revenue Drivers'!E23 -> 3275 | F9: ='Revenue Drivers'!F23 -> 3053 | G9: ='Revenue Drivers'!G23 -> 3363 | H9: ='Revenue Drivers'!H23 -> 2908 | J9: ='Revenue Drivers'!J23 -> 630 | K9: ='Revenue Drivers'!K23 -> 559 | L9: ='Revenue Drivers'!L23 -> 546 | M9: ='Revenue Drivers'!M23 -> 1318 | N9: ='Revenue Drivers'!N23 -> 651 | O9: ='Revenue Drivers'!O23 -> 594 | P9: ='Revenue Drivers'!P23 -> 648 | Q9: ='Revenue Drivers'!Q23 -> 1470 | ... X9: ='Revenue Drivers'!X23 -> 597 | Z9: =SUM(K9:N9) -> 3074 | AA9: =SUM(L9:O9) -> 3109 | AB9: =SUM(M9:P9) -> 3211 | AC9: =SUM(N9:Q9) -> 3363 | AD9: =SUM(O9:R9) -> 3278 | AE9: =SUM(P9:S9) -> 3221 | AF9: =SUM(Q9:T9) -> 3099 | AG9: =SUM(R9:U9) -> 2908 | ... AJ9: =SUM(U9:X9) -> 3116 | AL9: =SUM(AJ9/AF9)-1 -> 0.0054856405
B10: Services | C10: ='Revenue Drivers'!C24 -> 2325 | D10: ='Revenue Drivers'!D24 -> 2252 | E10: ='Revenue Drivers'!E24 -> 2380 | F10: ='Revenue Drivers'!F24 -> 2332 | G10: ='Revenue Drivers'!G24 -> 2530 | H10: ='Revenue Drivers'!H24 -> 2631 | J10: ='Revenue Drivers'!J24 -> 543 | K10: ='Revenue Drivers'!K24 -> 553 | L10: ='Revenue Drivers'!L24 -> 576 | M10: ='Revenue Drivers'!M24 -> 660 | N10: ='Revenue Drivers'!N24 -> 573 | O10: ='Revenue Drivers'!O24 -> 588 | P10: ='Revenue Drivers'!P24 -> 608 | Q10: ='Revenue Drivers'!Q24 -> 761 | ... X10: ='Revenue Drivers'!X24 -> 638 | Z10: =SUM(K10:N10) -> 2362 | AA10: =SUM(L10:O10) -> 2397 | AB10: =SUM(M10:P10) -> 2429 | AC10: =SUM(N10:Q10) -> 2530 | AD10: =SUM(O10:R10) -> 2574 | AE10: =SUM(P10:S10) -> 2614 | AF10: =SUM(Q10:T10) -> 2654 | AG10: =SUM(R10:U10) -> 2631 | ... AJ10: =SUM(U10:X10) -> 2612 | AL10: =SUM(AJ10/AF10)-1 -> -0.01582517
B11: Other | C11: ='Revenue Drivers'!C25 -> 215 | D11: ='Revenue Drivers'!D25 -> 194 | E11: ='Revenue Drivers'!E25 -> 258 | F11: ='Revenue Drivers'!F25 -> 317 | G11: ='Revenue Drivers'!G25 -> 304 | H11: ='Revenue Drivers'!H25 -> 333 | J11: ='Revenue Drivers'!J25 -> 75 | K11: ='Revenue Drivers'!K25 -> 97 | L11: ='Revenue Drivers'!L25 -> 87 | M11: ='Revenue Drivers'!M25 -> 58 | N11: ='Revenue Drivers'!N25 -> 65 | O11: ='Revenue Drivers'!O25 -> 90 | P11: ='Revenue Drivers'!P25 -> 83 | Q11: ='Revenue Drivers'!Q25 -> 66 | ... X11: ='Revenue Drivers'!X25 -> 67 | Z11: =SUM(K11:N11) -> 307 | AA11: =SUM(L11:O11) -> 300 | AB11: =SUM(M11:P11) -> 296 | AC11: =SUM(N11:Q11) -> 304 | AD11: =SUM(O11:R11) -> 310 | AE11: =SUM(P11:S11) -> 316 | AF11: =SUM(Q11:T11) -> 310 | AG11: =SUM(R11:U11) -> 333 | ... AJ11: =SUM(U11:X11) -> 322 | AL11: =SUM(AJ11/AF11)-1 -> 0.038709677
B12: Total Revenue | C12: =SUM(C6:C11) -> 43638 | D12: =SUM(D6:D11) -> 47262 | E12: =SUM(E6:E11) -> 51761 | F12: =SUM(F6:F11) -> 46298 | G12: =SUM(G6:G11) -> 43452 | H12: =SUM(H6:H11) -> 41528 | J12: =SUM(J6:J11) -> 10647 | K12: =SUM(K6:K11) -> 10329 | L12: =SUM(L6:L11) -> 10587 | M12: =SUM(M6:M11) -> 14735 | N12: =SUM(N6:N11) -> 9467 | O12: =SUM(O6:O11) -> 9583 | P12: =SUM(P6:P11) -> 9756 | Q12: =SUM(Q6:Q11) -> 14646 | ... X12: =SUM(X6:X11) -> 9672 | Z12: =SUM(Z6:Z11) -> 45118 | AA12: =SUM(AA6:AA11) -> 44372 | AB12: =SUM(AB6:AB11) -> 43541 | AC12: =SUM(AC6:AC11) -> 43452 | AD12: =SUM(AD6:AD11) -> 42832 | AE12: =SUM(AE6:AE11) -> 42537 | AF12: =SUM(AF6:AF11) -> 42226 | AG12: =SUM(AG6:AG11) -> 41528 | ... AJ12: =SUM(AJ6:AJ11) -> 41825 | AL12: =SUM(AJ12/AF12)-1 -> -0.0094965187
B13: Y/Y Growth (%) | D13: =SUM(D12/C12)-1 -> 0.083046886 | E13: =SUM(E12/D12)-1 -> 0.095192755 | F13: =SUM(F12/E12)-1 -> -0.10554278 | G13: =SUM(G12/F12)-1 -> -0.061471338 | H13: =SUM(H12/G12)-1 -> -0.044278744 | N13: =SUM(N12/J12)-1 -> -0.11082934 | O13: =SUM(O12/K12)-1 -> -0.072223836 | P13: =SUM(P12/L12)-1 -> -0.078492491 | Q13: =SUM(Q12/M12)-1 -> -0.0060400407 | R13: =SUM(R12/N12)-1 -> -0.065490652 | S13: =SUM(S12/O12)-1 -> -0.030783679 | T13: =SUM(T12/P12)-1 -> -0.031877819 | U13: =SUM(U12/Q12)-1 -> -0.047658064 | ... X13: =SUM(X12/T12)-1 -> 0.02403388 | AD13: =SUM(AD12/Z12)-1 -> -0.05066714 | AE13: =SUM(AE12/AA12)-1 -> -0.041354909 | AF13: =SUM(AF12/AB12)-1 -> -0.030201419 | AG13: =SUM(AG12/AC12)-1 -> -0.044278744 | AH13: =SUM(AH12/AD12)-1 -> -0.03231229 | AI13: =SUM(AI12/AE12)-1 -> -0.022074899 | AJ13: =SUM(AJ12/AF12)-1 -> -0.0094965187 | AL13: =SUM(AJ13-AF13)*10000 -> 207.04901
B14: Q/Q Growth (%) | C14: N/A | D14: N/A | E14: N/A | F14: N/A | G14: N/A | H14: N/A | K14: =SUM(K12/J12)-1 -> -0.029867568 | L14: =SUM(L12/K12)-1 -> 0.024978217 | M14: =SUM(M12/L12)-1 -> 0.39180127 | N14: =SUM(N12/M12)-1 -> -0.35751612 | O14: =SUM(O12/N12)-1 -> 0.01225309 | P14: =SUM(P12/O12)-1 -> 0.018052802 | Q14: =SUM(Q12/P12)-1 -> 0.50123001 | R14: =SUM(R12/Q12)-1 -> -0.39594429 | ... X14: =SUM(X12/W12)-1 -> 0.024793388 | Z14: N/A | AA14: N/A | AB14: N/A | AC14: N/A | AD14: N/A | AE14: N/A | AF14: N/A | AG14: N/A | AH14: N/A | AI14: N/A | AJ14: N/A
B16: (-) Cost of Sales | C16: ='Historical Financials'!C13 -> -33590 | D16: ='Historical Financials'!D13 -> -36689 | E16: ='Historical Financials'!E13 -> -40121 | F16: ='Historical Financials'!F13 -> -36386 | G16: ='Historical Financials'!G13 -> -33849 | H16: ='Historical Financials'!H13 -> -32143 | J16: ='Historical Financials'!J13 -> -8294 | K16: ='Historical Financials'!K13 -> -8042 | L16: ='Historical Financials'!L13 -> -8255 | M16: ='Historical Financials'!M13 -> -11795 | N16: ='Historical Financials'!N13 -> -7317 | O16: ='Historical Financials'!O13 -> -7363 | P16: ='Historical Financials'!P13 -> -7524 | Q16: ='Historical Financials'!Q13 -> -11645 | ... X16: ='Historical Financials'!X13 -> -7424 | Z16: =SUM(K16:N16) -> -35409 | AA16: =SUM(L16:O16) -> -34730 | AB16: =SUM(M16:P16) -> -33999 | AC16: =SUM(N16:Q16) -> -33849 | AD16: =SUM(O16:R16) -> -33315 | AE16: =SUM(P16:S16) -> -33054 | AF16: =SUM(Q16:T16) -> -32758 | AG16: =SUM(R16:U16) -> -32143 | ... AJ16: =SUM(U16:X16) -> -32416 | AL16: =SUM(AJ16/AF16)-1 -> -0.010440198
B17: Gross Profit | C17: =SUM(C12+SUM(C16:C16)) -> 10048 | D17: =SUM(D12+SUM(D16:D16)) -> 10573 | E17: =SUM(E12+SUM(E16:E16)) -> 11640 | F17: =SUM(F12+SUM(F16:F16)) -> 9912 | G17: =SUM(G12+SUM(G16:G16)) -> 9603 | H17: =SUM(H12+SUM(H16:H16)) -> 9385 | J17: =SUM(J12+SUM(J16:J16)) -> 2353 | K17: =SUM(K12+SUM(K16:K16)) -> 2287 | L17: =SUM(L12+SUM(L16:L16)) -> 2332 | M17: =SUM(M12+SUM(M16:M16)) -> 2940 | N17: =SUM(N12+SUM(N16:N16)) -> 2150 | O17: =SUM(O12+SUM(O16:O16)) -> 2220 | P17: =SUM(P12+SUM(P16:P16)) -> 2232 | Q17: =SUM(Q12+SUM(Q16:Q16)) -> 3001 | ... X17: =SUM(X12+SUM(X16:X16)) -> 2248 | Z17: =SUM(Z12+SUM(Z16:Z16)) -> 9709 | AA17: =SUM(AA12+SUM(AA16:AA16)) -> 9642 | AB17: =SUM(AB12+SUM(AB16:AB16)) -> 9542 | AC17: =SUM(AC12+SUM(AC16:AC16)) -> 9603 | AD17: =SUM(AD12+SUM(AD16:AD16)) -> 9517 | AE17: =SUM(AE12+SUM(AE16:AE16)) -> 9483 | AF17: =SUM(AF12+SUM(AF16:AF16)) -> 9468 | AG17: =SUM(AG12+SUM(AG16:AG16)) -> 9385 | ... AJ17: =SUM(AJ12+SUM(AJ16:AJ16)) -> 9409 | AL17: =SUM(AJ17/AF17)-1 -> -0.0062315167
B18: Gross Margin (%) | C18: =C17/C12 -> 0.23025803 | D18: =D17/D12 -> 0.22371038 | E18: =E17/E12 -> 0.22487974 | F18: =F17/F12 -> 0.21409132 | G18: =G17/G12 -> 0.22100249 | H18: =H17/H12 -> 0.2259921 | J18: =J17/J12 -> 0.22100122 | K18: =K17/K12 -> 0.22141543 | L18: =L17/L12 -> 0.22027014 | M18: =M17/M12 -> 0.19952494 | N18: =N17/N12 -> 0.22710468 | O18: =O17/O12 -> 0.23166023 | P18: =P17/P12 -> 0.22878229 | Q18: =Q17/Q12 -> 0.20490236 | ... X18: =X17/X12 -> 0.23242349 | Z18: =Z17/Z12 -> 0.21519128 | AA18: =AA17/AA12 -> 0.2172992 | AB18: =AB17/AB12 -> 0.21914977 | AC18: =AC17/AC12 -> 0.22100249 | AD18: =AD17/AD12 -> 0.22219369 | AE18: =AE17/AE12 -> 0.22293533 | AF18: =AF17/AF12 -> 0.22422204 | AG18: =AG17/AG12 -> 0.2259921 | ... AJ18: =AJ17/AJ12 -> 0.22496115 | AL18: =SUM(AJ18-AF18)*10000 -> 7.3910435
B20: (-) Selling, general and administrative expenses | C20: ='Historical Financials'!C17 -> -7998 | D20: ='Historical Financials'!D17 -> -7928 | E20: ='Historical Financials'!E17 -> -8635 | F20: ='Historical Financials'!F17 -> -7970 | G20: ='Historical Financials'!G17 -> -7876 | H20: ='Historical Financials'!H17 -> -7651 | J20: ='Historical Financials'!J17 -> -1890 | K20: ='Historical Financials'!K17 -> -1882 | L20: ='Historical Financials'!L17 -> -1941 | M20: ='Historical Financials'!M17 -> -2257 | N20: ='Historical Financials'!N17 -> -1848 | O20: ='Historical Financials'!O17 -> -1879 | P20: ='Historical Financials'!P17 -> -1878 | Q20: ='Historical Financials'!Q17 -> -2271 | ... X20: ='Historical Financials'!X17 -> -1884 | Z20: =SUM(K20:N20) -> -7928 | AA20: =SUM(L20:O20) -> -7925 | AB20: =SUM(M20:P20) -> -7862 | AC20: =SUM(N20:Q20) -> -7876 | AD20: =SUM(O20:R20) -> -7765 | AE20: =SUM(P20:S20) -> -7696 | AF20: =SUM(Q20:T20) -> -7689 | AG20: =SUM(R20:U20) -> -7651 | ... AJ20: =SUM(U20:X20) -> -7667 | AL20: =SUM(AJ20/AF20)-1 -> -0.0028612303
B21: (-) Restructuring, Impairments, and Other Charges | C21: ='Historical Financials'!C18 -> -41 | D21: ='Historical Financials'!D18 -> -254 | E21: ='Historical Financials'!E18 -> 34 | F21: ='Historical Financials'!F18 -> -147 | G21: ='Historical Financials'!G18 -> -153 | H21: ='Historical Financials'!H18 -> -472 | J21: ='Historical Financials'!J18 -> -1 | K21: ='Historical Financials'!K18 -> -34 | L21: ='Historical Financials'!L18 -> -26 | M21: ='Historical Financials'!M18 -> -86 | N21: ='Historical Financials'!N18 -> 9 | O21: ='Historical Financials'!O18 -> 7 | P21: ='Historical Financials'!P18 -> 0 | Q21: ='Historical Financials'!Q18 -> -169 | ... X21: ='Historical Financials'!X18 -> -166 | Z21: =SUM(K21:N21) -> -137 | AA21: =SUM(L21:O21) -> -96 | AB21: =SUM(M21:P21) -> -70 | AC21: =SUM(N21:Q21) -> -153 | AD21: =SUM(O21:R21) -> -177 | AE21: =SUM(P21:S21) -> -177 | AF21: =SUM(Q21:T21) -> -173 | AG21: =SUM(R21:U21) -> -472 | ... AJ21: =SUM(U21:X21) -> -857 | AL21: =SUM(AJ21/AF21)-1 -> 3.9537572
B22: Earning before Interest & Taxes (EBIT) | C22: =SUM(C17+SUM(C20:C21)) -> 2009 | D22: =SUM(D17+SUM(D20:D21)) -> 2391 | E22: =SUM(E17+SUM(E20:E21)) -> 3039 | F22: =SUM(F17+SUM(F20:F21)) -> 1795 | G22: =SUM(G17+SUM(G20:G21)) -> 1574 | H22: =SUM(H17+SUM(H20:H21)) -> 1262 | J22: =SUM(J17+SUM(J20:J21)) -> 462 | K22: =SUM(K17+SUM(K20:K21)) -> 371 | L22: =SUM(L17+SUM(L20:L21)) -> 365 | M22: =SUM(M17+SUM(M20:M21)) -> 597 | N22: =SUM(N17+SUM(N20:N21)) -> 311 | O22: =SUM(O17+SUM(O20:O21)) -> 348 | P22: =SUM(P17+SUM(P20:P21)) -> 354 | Q22: =SUM(Q17+SUM(Q20:Q21)) -> 561 | ... X22: =SUM(X17+SUM(X20:X21)) -> 198 | Z22: =SUM(Z17+SUM(Z20:Z21)) -> 1644 | AA22: =SUM(AA17+SUM(AA20:AA21)) -> 1621 | AB22: =SUM(AB17+SUM(AB20:AB21)) -> 1610 | AC22: =SUM(AC17+SUM(AC20:AC21)) -> 1574 | AD22: =SUM(AD17+SUM(AD20:AD21)) -> 1575 | AE22: =SUM(AE17+SUM(AE20:AE21)) -> 1610 | AF22: =SUM(AF17+SUM(AF20:AF21)) -> 1606 | AG22: =SUM(AG17+SUM(AG20:AG21)) -> 1262 | ... AJ22: =SUM(AJ17+SUM(AJ20:AJ21)) -> 885 | AL22: =SUM(AJ22/AF22)-1 -> -0.44894147
B23: Operating Margin (%) | C23: =C22/C12 -> 0.046037857 | D23: =D22/D12 -> 0.050590326 | E23: =E22/E12 -> 0.058712158 | F23: =F22/F12 -> 0.038770573 | G23: =G22/G12 -> 0.036223879 | H23: =H22/H12 -> 0.030389135 | J23: =J22/J12 -> 0.043392505 | K23: =K22/K12 -> 0.035918288 | L23: =L22/L12 -> 0.034476244 | M23: =M22/M12 -> 0.040515779 | N23: =N22/N12 -> 0.032850956 | O23: =O22/O12 -> 0.036314307 | P23: =P22/P12 -> 0.036285363 | Q23: =Q22/Q12 -> 0.038303974 | ... X23: =X22/X12 -> 0.020471464 | Z23: =Z22/Z12 -> 0.036437785 | AA23: =AA22/AA12 -> 0.036532047 | AB23: =AB22/AB12 -> 0.036976643 | AC23: =AC22/AC12 -> 0.036223879 | AD23: =AD22/AD12 -> 0.036771573 | AE23: =AE22/AE12 -> 0.037849402 | AF23: =AF22/AF12 -> 0.038033439 | AG23: =AG22/AG12 -> 0.030389135 | ... AJ23: =AJ22/AJ12 -> 0.021159594 | AL23: =SUM(AJ23-AF23)*10000 -> -168.73846
B25: (+) Depreciation and Amortization (D&A) | C25: ='Historical Financials'!C95 -> 812 | D25: ='Historical Financials'!D95 -> 839 | E25: ='Historical Financials'!E95 -> 869 | F25: ='Historical Financials'!F95 -> 918 | G25: ='Historical Financials'!G95 -> 923 | H25: ='Historical Financials'!H95 -> 866 | J25: ='Historical Financials'!J95 -> 224 | K25: ='Historical Financials'!K95 -> 229 | L25: ='Historical Financials'!L95 -> 226 | M25: ='Historical Financials'!M95 -> 239 | N25: ='Historical Financials'!N95 -> 237 | O25: ='Historical Financials'!O95 -> 236 | P25: ='Historical Financials'!P95 -> 229 | Q25: ='Historical Financials'!Q95 -> 221 | ... X25: ='Historical Financials'!X95 -> 206 | Z25: =SUM(K25:N25) -> 931 | AA25: =SUM(L25:O25) -> 938 | AB25: =SUM(M25:P25) -> 941 | AC25: =SUM(N25:Q25) -> 923 | AD25: =SUM(O25:R25) -> 905 | AE25: =SUM(P25:S25) -> 887 | AF25: =SUM(Q25:T25) -> 871 | AG25: =SUM(R25:U25) -> 866 | ... AJ25: =SUM(U25:X25) -> 844 | AL25: =SUM(AJ25/AF25)-1 -> -0.030998852
B26: EBITDA | C26: =SUM(C22+SUM(C25:C25)) -> 2821 | D26: =SUM(D22+SUM(D25:D25)) -> 3230 | E26: =SUM(E22+SUM(E25:E25)) -> 3908 | F26: =SUM(F22+SUM(F25:F25)) -> 2713 | G26: =SUM(G22+SUM(G25:G25)) -> 2497 | H26: =SUM(H22+SUM(H25:H25)) -> 2128 | J26: =SUM(J22+SUM(J25:J25)) -> 686 | K26: =SUM(K22+SUM(K25:K25)) -> 600 | L26: =SUM(L22+SUM(L25:L25)) -> 591 | M26: =SUM(M22+SUM(M25:M25)) -> 836 | N26: =SUM(N22+SUM(N25:N25)) -> 548 | O26: =SUM(O22+SUM(O25:O25)) -> 584 | P26: =SUM(P22+SUM(P25:P25)) -> 583 | Q26: =SUM(Q22+SUM(Q25:Q25)) -> 782 | ... X26: =SUM(X22+SUM(X25:X25)) -> 404 | Z26: =SUM(Z22+SUM(Z25:Z25)) -> 2575 | AA26: =SUM(AA22+SUM(AA25:AA25)) -> 2559 | AB26: =SUM(AB22+SUM(AB25:AB25)) -> 2551 | AC26: =SUM(AC22+SUM(AC25:AC25)) -> 2497 | AD26: =SUM(AD22+SUM(AD25:AD25)) -> 2480 | AE26: =SUM(AE22+SUM(AE25:AE25)) -> 2497 | AF26: =SUM(AF22+SUM(AF25:AF25)) -> 2477 | AG26: =SUM(AG22+SUM(AG25:AG25)) -> 2128 | ... AJ26: =SUM(AJ22+SUM(AJ25:AJ25)) -> 1729 | AL26: =SUM(AJ26/AF26)-1 -> -0.3019782
B27: EBITDA Margin (%) | C27: =C26/C12 -> 0.064645492 | D27: =D26/D12 -> 0.068342432 | E27: =E26/E12 -> 0.07550086 | F27: =F26/F12 -> 0.058598644 | G27: =G26/G12 -> 0.057465709 | H27: =H26/H12 -> 0.051242535 | J27: =J26/J12 -> 0.064431295 | K27: =K26/K12 -> 0.058088876 | L27: =L26/L12 -> 0.055823179 | M27: =M26/M12 -> 0.056735663 | N27: =N26/N12 -> 0.057885286 | O27: =O26/O12 -> 0.06094125 | P27: =P26/P12 -> 0.059758098 | Q27: =Q26/Q12 -> 0.053393418 | ... X27: =X26/X12 -> 0.041770058 | Z27: =Z26/Z12 -> 0.057072565 | AA27: =AA26/AA12 -> 0.057671505 | AB27: =AB26/AB12 -> 0.058588457 | AC27: =AC26/AC12 -> 0.057465709 | AD27: =AD26/AD12 -> 0.057900635 | AE27: =AE26/AE12 -> 0.058701836 | AF27: =AF26/AF12 -> 0.058660541 | AG27: =AG26/AG12 -> 0.051242535 | ... AJ27: =AJ26/AJ12 -> 0.041338912 | AL27: =SUM(AJ27-AF27)*10000 -> -173.21629
B29: (+) Stock-Based Compensation (SBC) | C29: ='Historical Financials'!C97 -> 143 | D29: ='Historical Financials'!D97 -> 135 | E29: ='Historical Financials'!E97 -> 141 | F29: ='Historical Financials'!F97 -> 138 | G29: ='Historical Financials'!G97 -> 145 | H29: ='Historical Financials'!H97 -> 139 | J29: ='Historical Financials'!J97 -> 39 | K29: ='Historical Financials'!K97 -> 26 | L29: ='Historical Financials'!L97 -> 33 | M29: ='Historical Financials'!M97 -> 40 | N29: ='Historical Financials'!N97 -> 38 | O29: ='Historical Financials'!O97 -> 37 | P29: ='Historical Financials'!P97 -> 35 | Q29: ='Historical Financials'!Q97 -> 35 | ... X29: ='Historical Financials'!X97 -> 31 | Z29: =SUM(K29:N29) -> 137 | AA29: =SUM(L29:O29) -> 148 | AB29: =SUM(M29:P29) -> 150 | AC29: =SUM(N29:Q29) -> 145 | AD29: =SUM(O29:R29) -> 145 | AE29: =SUM(P29:S29) -> 144 | AF29: =SUM(Q29:T29) -> 143 | AG29: =SUM(R29:U29) -> 139 | ... AJ29: =SUM(U29:X29) -> 137 | AL29: =SUM(AJ29/AF29)-1 -> -0.041958042
B30: (+) Restructuring, Impairments, and Other Charges | C30: =-C21 -> 41 | D30: =-D21 -> 254 | E30: =-E21 -> -34 | F30: =-F21 -> 147 | G30: =-G21 -> 153 | H30: =-H21 -> 472 | J30: =-J21 -> 1 | K30: =-K21 -> 34 | L30: =-L21 -> 26 | M30: =-M21 -> 86 | N30: =-N21 -> -9 | O30: =-O21 -> -7 | P30: =-P21 -> 0 | Q30: =-Q21 -> 169 | ... X30: =-X21 -> 166 | Z30: =SUM(K30:N30) -> 137 | AA30: =SUM(L30:O30) -> 96 | AB30: =SUM(M30:P30) -> 70 | AC30: =SUM(N30:Q30) -> 153 | AD30: =SUM(O30:R30) -> 177 | AE30: =SUM(P30:S30) -> 177 | AF30: =SUM(Q30:T30) -> 173 | AG30: =SUM(R30:U30) -> 472 | ... AJ30: =SUM(U30:X30) -> 857 | AL30: =SUM(AJ30/AF30)-1 -> 3.9537572
B31: Adj. EBITDA | C31: =+SUM(C26+SUM(C29:C29)) -> 2964 | D31: =+SUM(D26+SUM(D29:D29)) -> 3365 | E31: =+SUM(E26+SUM(E29:E29)) -> 4049 | F31: =+SUM(F26+SUM(F29:F29)) -> 2851 | G31: =+SUM(G26+SUM(G29:G29)) -> 2642 | H31: =+SUM(H26+SUM(H29:H29)) -> 2267 | J31: =+SUM(J26+SUM(J29:J29)) -> 725 | K31: =+SUM(K26+SUM(K29:K29)) -> 626 | L31: =+SUM(L26+SUM(L29:L29)) -> 624 | M31: =+SUM(M26+SUM(M29:M29)) -> 876 | N31: =+SUM(N26+SUM(N29:N29)) -> 586 | O31: =+SUM(O26+SUM(O29:O29)) -> 621 | P31: =+SUM(P26+SUM(P29:P29)) -> 618 | Q31: =+SUM(Q26+SUM(Q29:Q29)) -> 817 | ... X31: =+SUM(X26+SUM(X29:X29)) -> 435 | Z31: =+SUM(Z26+SUM(Z29:Z29)) -> 2712 | AA31: =+SUM(AA26+SUM(AA29:AA29)) -> 2707 | AB31: =+SUM(AB26+SUM(AB29:AB29)) -> 2701 | AC31: =+SUM(AC26+SUM(AC29:AC29)) -> 2642 | AD31: =+SUM(AD26+SUM(AD29:AD29)) -> 2625 | AE31: =+SUM(AE26+SUM(AE29:AE29)) -> 2641 | AF31: =+SUM(AF26+SUM(AF29:AF29)) -> 2620 | AG31: =+SUM(AG26+SUM(AG29:AG29)) -> 2267 | ... AJ31: =+SUM(AJ26+SUM(AJ29:AJ29)) -> 1866 | AL31: =SUM(AJ31/AF31)-1 -> -0.28778626
B32: Adj. EBITDA Margin (%) | C32: =C31/C12 -> 0.067922453 | D32: =D31/D12 -> 0.071198849 | E32: =E31/E12 -> 0.078224918 | F32: =F31/F12 -> 0.061579334 | G32: =G31/G12 -> 0.060802725 | H32: =H31/H12 -> 0.054589674 | J32: =J31/J12 -> 0.068094299 | K32: =K31/K12 -> 0.060606061 | L32: =L31/L12 -> 0.05894021 | M32: =M31/M12 -> 0.059450288 | N32: =N31/N12 -> 0.061899229 | O32: =O31/O12 -> 0.064802254 | P32: =P31/P12 -> 0.063345633 | Q32: =Q31/Q12 -> 0.055783149 | ... X32: =X31/X12 -> 0.044975186 | Z32: =Z31/Z12 -> 0.060109047 | AA32: =AA31/AA12 -> 0.061006941 | AB32: =AB31/AB12 -> 0.062033486 | AC32: =AC31/AC12 -> 0.060802725 | AD32: =AD31/AD12 -> 0.061285954 | AE32: =AE31/AE12 -> 0.062087124 | AF32: =AF31/AF12 -> 0.06204708 | AG32: =AG31/AG12 -> 0.054589674 | ... AJ32: =AJ31/AJ12 -> 0.044614465 | AL32: =SUM(AJ32-AF32)*10000 -> -174.32615
B34: (-) Capital Expenditures | C34: ='Historical Financials'!C109 -> -743 | D34: ='Historical Financials'!D109 -> -713 | E34: ='Historical Financials'!E109 -> -737 | F34: ='Historical Financials'!F109 -> -930 | G34: ='Historical Financials'!G109 -> -795 | H34: ='Historical Financials'!H109 -> -706 | J34: ='Historical Financials'!J109 -> -215 | K34: ='Historical Financials'!K109 -> -226 | L34: ='Historical Financials'!L109 -> -255 | M34: ='Historical Financials'!M109 -> -234 | N34: ='Historical Financials'!N109 -> -204 | O34: ='Historical Financials'!O109 -> -191 | P34: ='Historical Financials'!P109 -> -217 | Q34: ='Historical Financials'!Q109 -> -183 | ... X34: ='Historical Financials'!X109 -> -188 | Z34: =SUM(K34:N34) -> -919 | AA34: =SUM(L34:O34) -> -884 | AB34: =SUM(M34:P34) -> -846 | AC34: =SUM(N34:Q34) -> -795 | AD34: =SUM(O34:R34) -> -743 | AE34: =SUM(P34:S34) -> -735 | AF34: =SUM(Q34:T34) -> -711 | AG34: =SUM(R34:U34) -> -706 | ... AJ34: =SUM(U34:X34) -> -707 | AL34: =SUM(AJ34/AF34)-1 -> -0.005625879
B35: (-) Cash Taxes | C35: =-'Historical Financials'!C136 -> -514 | D35: =-'Historical Financials'!D136 -> -442 | E35: =-'Historical Financials'!E136 -> -716 | F35: =-'Historical Financials'!F136 -> -283 | G35: =-'Historical Financials'!G136 -> -543 | H35: =-'Historical Financials'!H136 -> -643 | J35: ='Historical Financials'!J28 -> -110 | K35: ='Historical Financials'!K28 -> -58 | L35: ='Historical Financials'!L28 -> -84 | M35: ='Historical Financials'!M28 -> -118 | N35: ='Historical Financials'!N28 -> -75 | O35: ='Historical Financials'!O28 -> -96 | P35: ='Historical Financials'!P28 -> -86 | Q35: ='Historical Financials'!Q28 -> -124 | ... X35: ='Historical Financials'!X28 -> -64 | Z35: =SUM(K35:N35) -> -335 | AA35: =SUM(L35:O35) -> -373 | AB35: =SUM(M35:P35) -> -375 | AC35: =SUM(N35:Q35) -> -381 | AD35: =SUM(O35:R35) -> -386 | AE35: =SUM(P35:S35) -> -391 | AF35: =SUM(Q35:T35) -> -390 | AG35: =SUM(R35:U35) -> -372 | ... AJ35: =SUM(U35:X35) -> -257 | AL35: =SUM(AJ35/AF35)-1 -> -0.34102564
B36: (-) Cash Interest | C36: =-'Historical Financials'!C135 -> -62 | D36: =-'Historical Financials'!D135 -> -50 | E36: =-'Historical Financials'!E135 -> -22 | F36: =-'Historical Financials'!F135 -> -31 | G36: =-'Historical Financials'!G135 -> -51 | H36: =-'Historical Financials'!H135 -> -46 | J36: ='Historical Financials'!J24 -> -6 | K36: ='Historical Financials'!K24 -> -7 | L36: ='Historical Financials'!L24 -> -10 | M36: ='Historical Financials'!M24 -> -12 | N36: ='Historical Financials'!N24 -> -12 | O36: ='Historical Financials'!O24 -> -12 | P36: ='Historical Financials'!P24 -> -14 | Q36: ='Historical Financials'!Q24 -> -14 | ... X36: ='Historical Financials'!X24 -> -12 | Z36: =SUM(K36:N36) -> -41 | AA36: =SUM(L36:O36) -> -46 | AB36: =SUM(M36:P36) -> -50 | AC36: =SUM(N36:Q36) -> -52 | AD36: =SUM(O36:R36) -> -52 | AE36: =SUM(P36:S36) -> -53 | AF36: =SUM(Q36:T36) -> -52 | AG36: =SUM(R36:U36) -> -51 | ... AJ36: =SUM(U36:X36) -> -49 | AL36: =SUM(AJ36/AF36)-1 -> -0.057692308
B37: (+/-) Changes in NWC | C37: =SUM('Historical Financials'!C101:C105) -> -63 | D37: =SUM('Historical Financials'!D101:D105) -> 1934 | E37: =SUM('Historical Financials'!E101:E105) -> -203 | F37: =SUM('Historical Financials'!F101:F105) -> -861 | G37: =SUM('Historical Financials'!G101:G105) -> -783 | H37: =SUM('Historical Financials'!H101:H105) -> -259 | J37: =SUM('Historical Financials'!J101:J105) -> -2001 | K37: =SUM('Historical Financials'!K101:K105) -> 73 | L37: =SUM('Historical Financials'!L101:L105) -> 39 | M37: =SUM('Historical Financials'!M101:M105) -> 1028 | N37: =SUM('Historical Financials'!N101:N105) -> -855 | O37: =SUM('Historical Financials'!O101:O105) -> 5 | P37: =SUM('Historical Financials'!P101:P105) -> -423 | Q37: =SUM('Historical Financials'!Q101:Q105) -> 490 | ... X37: =SUM('Historical Financials'!X101:X105) -> -657 | Z37: =SUM(K37:N37) -> 285 | AA37: =SUM(L37:O37) -> 217 | AB37: =SUM(M37:P37) -> -245 | AC37: =SUM(N37:Q37) -> -783 | AD37: =SUM(O37:R37) -> -302 | AE37: =SUM(P37:S37) -> -184 | AF37: =SUM(Q37:T37) -> -524 | AG37: =SUM(R37:U37) -> -259 | ... AJ37: =SUM(U37:X37) -> -280 | AL37: =SUM(AJ37/AF37)-1 -> -0.46564885
B38: Discretionary Cash-Flows | C38: =SUM(C31+SUM(C34:C37)) -> 1582 | D38: =SUM(D31+SUM(D34:D37)) -> 4094 | E38: =SUM(E31+SUM(E34:E37)) -> 2371 | F38: =SUM(F31+SUM(F34:F37)) -> 746 | G38: =SUM(G31+SUM(G34:G37)) -> 470 | H38: =SUM(H31+SUM(H34:H37)) -> 613 | J38: =SUM(J31+SUM(J34:J37)) -> -1607 | K38: =SUM(K31+SUM(K34:K37)) -> 408 | L38: =SUM(L31+SUM(L34:L37)) -> 314 | M38: =SUM(M31+SUM(M34:M37)) -> 1540 | N38: =SUM(N31+SUM(N34:N37)) -> -560 | O38: =SUM(O31+SUM(O34:O37)) -> 327 | P38: =SUM(P31+SUM(P34:P37)) -> -122 | Q38: =SUM(Q31+SUM(Q34:Q37)) -> 986 | ... X38: =SUM(X31+SUM(X34:X37)) -> -486 | Z38: =SUM(Z31+SUM(Z34:Z37)) -> 1702 | AA38: =SUM(AA31+SUM(AA34:AA37)) -> 1621 | AB38: =SUM(AB31+SUM(AB34:AB37)) -> 1185 | AC38: =SUM(AC31+SUM(AC34:AC37)) -> 631 | AD38: =SUM(AD31+SUM(AD34:AD37)) -> 1142 | AE38: =SUM(AE31+SUM(AE34:AE37)) -> 1278 | AF38: =SUM(AF31+SUM(AF34:AF37)) -> 943 | AG38: =SUM(AG31+SUM(AG34:AG37)) -> 879 | ... AJ38: =SUM(AJ31+SUM(AJ34:AJ37)) -> 573 | AL38: =SUM(AJ38/AF38)-1 -> -0.39236479
B40: (+/-) Divestitures / (Acquisitions) | C40: ='Historical Financials'!C110 -> -145 | D40: ='Historical Financials'!D110 -> 0 | E40: ='Historical Financials'!E110 -> -468 | F40: ='Historical Financials'!F110 -> 0 | G40: ='Historical Financials'!G110 -> 14 | H40: ='Historical Financials'!H110 -> 0 | J40: ='Historical Financials'!J110 -> 0 | K40: ='Historical Financials'!K110 -> 0 | L40: ='Historical Financials'!L110 -> 0 | M40: ='Historical Financials'!M110 -> 0 | N40: ='Historical Financials'!N110 -> 0 | O40: ='Historical Financials'!O110 -> 14 | P40: ='Historical Financials'!P110 -> 0 | Q40: ='Historical Financials'!Q110 -> 0 | ... X40: ='Historical Financials'!X110 -> 0 | Z40: =SUM(K40:N40) -> 0 | AA40: =SUM(L40:O40) -> 14 | AB40: =SUM(M40:P40) -> 14 | AC40: =SUM(N40:Q40) -> 14 | AD40: =SUM(O40:R40) -> 14 | AE40: =SUM(P40:S40) -> 0 | AF40: =SUM(Q40:T40) -> 0 | AG40: =SUM(R40:U40) -> 0 | ... AJ40: =SUM(U40:X40) -> -27
B41: (+/-) Sales / (Purchases) of investments | C41: ='Historical Financials'!C111 -> -8 | D41: ='Historical Financials'!D111 -> -74 | E41: ='Historical Financials'!E111 -> -167 | F41: ='Historical Financials'!F111 -> -39 | G41: ='Historical Financials'!G111 -> -2 | H41: ='Historical Financials'!H111 -> -6 | J41: ='Historical Financials'!J111 -> 0 | K41: ='Historical Financials'!K111 -> -46 | L41: ='Historical Financials'!L111 -> 0 | M41: ='Historical Financials'!M111 -> 7 | N41: ='Historical Financials'!N111 -> 0 | O41: ='Historical Financials'!O111 -> -2 | P41: ='Historical Financials'!P111 -> -5 | Q41: ='Historical Financials'!Q111 -> 5 | ... X41: ='Historical Financials'!X111 -> 0 | Z41: =SUM(K41:N41) -> -39 | AA41: =SUM(L41:O41) -> 5 | AB41: =SUM(M41:P41) -> 0 | AC41: =SUM(N41:Q41) -> -2 | AD41: =SUM(O41:R41) -> -2 | AE41: =SUM(P41:S41) -> 0 | AF41: =SUM(Q41:T41) -> 5 | AG41: =SUM(R41:U41) -> -6 | ... AJ41: =SUM(U41:X41) -> -6
B42: (+/-) Proceeds from Equity Issuances / (Repurchases) | C42: ='Historical Financials'!C116 -> -955 | D42: ='Historical Financials'!D116 -> -284 | E42: ='Historical Financials'!E116 -> -3473 | F42: ='Historical Financials'!F116 -> -998 | G42: ='Historical Financials'!G116 -> -321 | H42: ='Historical Financials'!H116 -> -483 | J42: ='Historical Financials'!J116 -> -455 | K42: ='Historical Financials'!K116 -> -10 | L42: ='Historical Financials'!L116 -> 0 | M42: ='Historical Financials'!M116 -> -533 | N42: ='Historical Financials'!N116 -> -79 | O42: ='Historical Financials'!O116 -> -79 | P42: ='Historical Financials'!P116 -> -112 | Q42: ='Historical Financials'!Q116 -> -51 | ... X42: ='Historical Financials'!X116 -> -35 | Z42: =SUM(K42:N42) -> -622 | AA42: =SUM(L42:O42) -> -691 | AB42: =SUM(M42:P42) -> -803 | AC42: =SUM(N42:Q42) -> -321 | AD42: =SUM(O42:R42) -> -292 | AE42: =SUM(P42:S42) -> -311 | AF42: =SUM(Q42:T42) -> -336 | AG42: =SUM(R42:U42) -> -483 | ... AJ42: =SUM(U42:X42) -> -398
B43: (-) Dividends paid | C43: ='Historical Financials'!C117 -> -527 | D43: ='Historical Financials'!D117 -> -568 | E43: ='Historical Financials'!E117 -> -688 | F43: ='Historical Financials'!F117 -> -789 | G43: ='Historical Financials'!G117 -> -801 | H43: ='Historical Financials'!H117 -> -807 | J43: ='Historical Financials'!J117 -> -199 | K43: ='Historical Financials'!K117 -> -198 | L43: ='Historical Financials'!L117 -> -198 | M43: ='Historical Financials'!M117 -> -194 | N43: ='Historical Financials'!N117 -> -202 | O43: ='Historical Financials'!O117 -> -200 | P43: ='Historical Financials'!P117 -> -201 | Q43: ='Historical Financials'!Q117 -> -198 | ... X43: ='Historical Financials'!X117 -> -199 | Z43: =SUM(K43:N43) -> -792 | AA43: =SUM(L43:O43) -> -794 | AB43: =SUM(M43:P43) -> -797 | AC43: =SUM(N43:Q43) -> -801 | AD43: =SUM(O43:R43) -> -801 | AE43: =SUM(P43:S43) -> -804 | AF43: =SUM(Q43:T43) -> -805 | AG43: =SUM(R43:U43) -> -807 | ... AJ43: =SUM(U43:X43) -> -802
B44: (+/-) Proceeds from Debt Issuances / (Repayment) | C44: ='Historical Financials'!C118 -> -15 | D44: ='Historical Financials'!D118 -> -24 | E44: ='Historical Financials'!E118 -> -133 | F44: ='Historical Financials'!F118 -> -19 | G44: ='Historical Financials'!G118 -> -19 | H44: ='Historical Financials'!H118 -> -17 | J44: ='Historical Financials'!J118 -> 0 | K44: ='Historical Financials'!K118 -> 0 | L44: ='Historical Financials'!L118 -> 0 | M44: ='Historical Financials'!M118 -> -19 | N44: ='Historical Financials'!N118 -> 0 | O44: ='Historical Financials'!O118 -> 0 | P44: ='Historical Financials'!P118 -> 0 | Q44: ='Historical Financials'!Q118 -> -19 | ... X44: ='Historical Financials'!X118 -> -10 | Z44: =SUM(K44:N44) -> -19 | AA44: =SUM(L44:O44) -> -19 | AB44: =SUM(M44:P44) -> -19 | AC44: =SUM(N44:Q44) -> -19 | AD44: =SUM(O44:R44) -> -19 | AE44: =SUM(P44:S44) -> -19 | AF44: =SUM(Q44:T44) -> -32 | AG44: =SUM(R44:U44) -> -17 | ... AJ44: =SUM(U44:X44) -> -14
B45: (+/-) Other | D45: =SUM(D50:D51)-SUM(C50:C51)-SUM(D38:D44) -> 126 | E45: =SUM(E50:E51)-SUM(D50:D51)-SUM(E38:E44) -> 138 | F45: =SUM(F50:F51)-SUM(E50:E51)-SUM(F38:F44) -> 147 | G45: =SUM(G50:G51)-SUM(F50:F51)-SUM(G38:G44) -> 199 | H45: =SUM(H50:H51)-SUM(G50:G51)-SUM(H38:H44) -> 775 | K45: =SUM(K50:K51)-SUM(J50:J51)-SUM(K38:K44) -> 38 | L45: =SUM(L50:L51)-SUM(K50:K51)-SUM(L38:L44) -> 25 | M45: =SUM(M50:M51)-SUM(L50:L51)-SUM(M38:M44) -> 159 | N45: =SUM(N50:N51)-SUM(M50:M51)-SUM(N38:N44) -> 20 | O45: =SUM(O50:O51)-SUM(N50:N51)-SUM(O38:O44) -> -1 | P45: =SUM(P50:P51)-SUM(O50:O51)-SUM(P38:P44) -> 8 | Q45: =SUM(Q50:Q51)-SUM(P50:P51)-SUM(Q38:Q44) -> 11 | R45: =SUM(R50:R51)-SUM(Q50:Q51)-SUM(R38:R44) -> 35 | ... X45: =SUM(X50:X51)-SUM(W50:W51)-SUM(X38:X44) -> 211 | Z45: =SUM(K45:N45) -> 242 | AA45: =SUM(L45:O45) -> 203 | AB45: =SUM(M45:P45) -> 186 | AC45: =SUM(N45:Q45) -> 38 | AD45: =SUM(O45:R45) -> 53 | AE45: =SUM(P45:S45) -> 63 | AF45: =SUM(Q45:T45) -> 104 | AG45: =SUM(R45:U45) -> 509 | ... AJ45: =SUM(U45:X45) -> 930
B46: Free-Cash Flows | C46: =SUM(C38+SUM(C40:C45)) -> -68 | D46: =SUM(D38+SUM(D40:D45)) -> 3270 | E46: =SUM(E38+SUM(E40:E45)) -> -2420 | F46: =SUM(F38+SUM(F40:F45)) -> -952 | G46: =SUM(G38+SUM(G40:G45)) -> -460 | H46: =SUM(H38+SUM(H40:H45)) -> 75 | J46: =SUM(J38+SUM(J40:J45)) -> -2261 | K46: =SUM(K38+SUM(K40:K45)) -> 192 | L46: =SUM(L38+SUM(L40:L45)) -> 141 | M46: =SUM(M38+SUM(M40:M45)) -> 960 | N46: =SUM(N38+SUM(N40:N45)) -> -821 | O46: =SUM(O38+SUM(O40:O45)) -> 59 | P46: =SUM(P38+SUM(P40:P45)) -> -432 | Q46: =SUM(Q38+SUM(Q40:Q45)) -> 734 | ... X46: =SUM(X38+SUM(X40:X45)) -> -519 | Z46: =SUM(Z38+SUM(Z40:Z45)) -> 472 | AA46: =SUM(AA38+SUM(AA40:AA45)) -> 339 | AB46: =SUM(AB38+SUM(AB40:AB45)) -> -234 | AC46: =SUM(AC38+SUM(AC40:AC45)) -> -460 | AD46: =SUM(AD38+SUM(AD40:AD45)) -> 95 | AE46: =SUM(AE38+SUM(AE40:AE45)) -> 207 | AF46: =SUM(AF38+SUM(AF40:AF45)) -> -121 | AG46: =SUM(AG38+SUM(AG40:AG45)) -> 75 | ... AJ46: =SUM(AJ38+SUM(AJ40:AJ45)) -> 256
B48: Capitalization
B50: Cash & Cash Equivelants | C50: ='Historical Financials'!C44 -> 2229 | D50: ='Historical Financials'!D44 -> 5494 | E50: ='Historical Financials'!E44 -> 2936 | F50: ='Historical Financials'!F44 -> 1874 | G50: ='Historical Financials'!G44 -> 1447 | H50: ='Historical Financials'!H44 -> 1578 | J50: ='Historical Financials'!J44 -> 640 | K50: ='Historical Financials'!K44 -> 840 | L50: ='Historical Financials'!L44 -> 932 | M50: ='Historical Financials'!M44 -> 1874 | N50: ='Historical Financials'!N44 -> 1030 | O50: ='Historical Financials'!O44 -> 1093 | P50: ='Historical Financials'!P44 -> 636 | Q50: ='Historical Financials'!Q44 -> 1447 | ... X50: ='Historical Financials'!X44 -> 923 | Z50: =N50 -> 1030 | AA50: =O50 -> 1093 | AB50: =P50 -> 636 | AC50: =Q50 -> 1447 | AD50: =R50 -> 1214 | AE50: =S50 -> 1387 | AF50: =T50 -> 643 | AG50: =U50 -> 1578 | ... AJ50: =X50 -> 923
B51: Restricted Cash | C51: ='Historical Financials'!C45 -> 126 | D51: ='Historical Financials'!D45 -> 131 | E51: ='Historical Financials'!E45 -> 269 | F51: ='Historical Financials'!F45 -> 379 | G51: ='Historical Financials'!G45 -> 346 | H51: ='Historical Financials'!H45 -> 290 | J51: ='Historical Financials'!J45 -> 320 | K51: ='Historical Financials'!K45 -> 312 | L51: ='Historical Financials'!L45 -> 361 | M51: ='Historical Financials'!M45 -> 379 | N51: ='Historical Financials'!N45 -> 402 | O51: ='Historical Financials'!O45 -> 398 | P51: ='Historical Financials'!P45 -> 423 | Q51: ='Historical Financials'!Q45 -> 346 | ... X51: ='Historical Financials'!X45 -> 271 | Z51: =N51 -> 402 | AA51: =O51 -> 398 | AB51: =P51 -> 423 | AC51: =Q51 -> 346 | AD51: =R51 -> 313 | AE51: =S51 -> 311 | AF51: =T51 -> 295 | AG51: =U51 -> 290 | ... AJ51: =X51 -> 271
B52: $1.25Bn Sr. Unsecured Revolving Credit Facility due 2028 | C52: 1250 | D52: 1250 | E52: 1250 | F52: 1250 | G52: 1250 | H52: 1250 | J52: 1250 | K52: 1250 | L52: 1250 | M52: =F52 -> 1250 | N52: 1250 | O52: 1250 | P52: 1250 | Q52: =G52 -> 1250 | R52: 1250 | S52: 1250 | T52: 1250 | U52: =H52 -> 1250 | V52: 1250 | W52: 1250 | X52: 1250 | Z52: =N52 -> 1250 | AA52: =O52 -> 1250 | AB52: =P52 -> 1250 | AC52: =Q52 -> 1250 | AD52: =R52 -> 1250 | AE52: =S52 -> 1250 | AF52: =T52 -> 1250 | AG52: =U52 -> 1250 | ... AJ52: =X52 -> 1250
B53: Total Liquidity | C53: =SUM(C50:C52) -> 3605 | D53: =SUM(D50:D52) -> 6875 | E53: =SUM(E50:E52) -> 4455 | F53: =SUM(F50:F52) -> 3503 | G53: =SUM(G50:G52) -> 3043 | H53: =SUM(H50:H52) -> 3118 | J53: =SUM(J50:J52) -> 2210 | K53: =SUM(K50:K52) -> 2402 | L53: =SUM(L50:L52) -> 2543 | M53: =SUM(M50:M52) -> 3503 | N53: =SUM(N50:N52) -> 2682 | O53: =SUM(O50:O52) -> 2741 | P53: =SUM(P50:P52) -> 2309 | Q53: =SUM(Q50:Q52) -> 3043 | ... X53: =SUM(X50:X52) -> 2444 | Z53: =SUM(Z50:Z52) -> 2682 | AA53: =SUM(AA50:AA52) -> 2741 | AB53: =SUM(AB50:AB52) -> 2309 | AC53: =SUM(AC50:AC52) -> 3043 | AD53: =SUM(AD50:AD52) -> 2777 | AE53: =SUM(AE50:AE52) -> 2948 | AF53: =SUM(AF50:AF52) -> 2188 | AG53: =SUM(AG50:AG52) -> 3118 | ... AJ53: =SUM(AJ50:AJ52) -> 2444
B55: Balance Sheet Metrics:
B56: Accounts Receivable | C56: ='Historical Financials'!C46 -> 1149 | D56: ='Historical Financials'!D46 -> 1061 | E56: ='Historical Financials'!E46 -> 1042 | F56: ='Historical Financials'!F46 -> 1141 | G56: ='Historical Financials'!G46 -> 939 | H56: ='Historical Financials'!H46 -> 1044 | J56: ='Historical Financials'!J46 -> 804 | K56: ='Historical Financials'!K46 -> 840 | L56: ='Historical Financials'!L46 -> 1050 | M56: ='Historical Financials'!M46 -> 1141 | N56: ='Historical Financials'!N46 -> 860 | O56: ='Historical Financials'!O46 -> 856 | P56: ='Historical Financials'!P46 -> 901 | Q56: ='Historical Financials'!Q46 -> 939 | ... X56: ='Historical Financials'!X46 -> 1017 | Z56: =N56 -> 860 | AA56: =O56 -> 856 | AB56: =P56 -> 901 | AC56: =Q56 -> 939 | AD56: =R56 -> 770 | AE56: =S56 -> 871 | AF56: =T56 -> 932 | AG56: =U56 -> 1044 | ... AJ56: =X56 -> 1017
B57: Merchandise inventories | C57: ='Historical Financials'!C47 -> 5174 | D57: ='Historical Financials'!D47 -> 5612 | E57: ='Historical Financials'!E47 -> 5965 | F57: ='Historical Financials'!F47 -> 5140 | G57: ='Historical Financials'!G47 -> 4958 | H57: ='Historical Financials'!H47 -> 5085 | J57: ='Historical Financials'!J47 -> 6258 | K57: ='Historical Financials'!K47 -> 6043 | L57: ='Historical Financials'!L47 -> 7294 | M57: ='Historical Financials'!M47 -> 5140 | N57: ='Historical Financials'!N47 -> 5219 | O57: ='Historical Financials'!O47 -> 5651 | P57: ='Historical Financials'!P47 -> 7562 | Q57: ='Historical Financials'!Q47 -> 4958 | ... X57: ='Historical Financials'!X47 -> 7993 | Z57: =N57 -> 5219 | AA57: =O57 -> 5651 | AB57: =P57 -> 7562 | AC57: =Q57 -> 4958 | AD57: =R57 -> 5225 | AE57: =S57 -> 5706 | AF57: =T57 -> 7806 | AG57: =U57 -> 5085 | ... AJ57: =X57 -> 7993
B58: Property and equipment, net | C58: ='Historical Financials'!C52 -> 2328 | D58: ='Historical Financials'!D52 -> 2260 | E58: ='Historical Financials'!E52 -> 2250 | F58: ='Historical Financials'!F52 -> 2352 | G58: ='Historical Financials'!G52 -> 2260 | H58: ='Historical Financials'!H52 -> 2122 | J58: ='Historical Financials'!J52 -> 2251 | K58: ='Historical Financials'!K52 -> 2319 | L58: ='Historical Financials'!L52 -> 2373 | M58: ='Historical Financials'!M52 -> 2352 | N58: ='Historical Financials'!N52 -> 2321 | O58: ='Historical Financials'!O52 -> 2305 | P58: ='Historical Financials'!P52 -> 2313 | Q58: ='Historical Financials'!Q52 -> 2260 | ... X58: ='Historical Financials'!X52 -> 2037 | Z58: =N58 -> 2321 | AA58: =O58 -> 2305 | AB58: =P58 -> 2313 | AC58: =Q58 -> 2260 | AD58: =R58 -> 2196 | AE58: =S58 -> 2183 | AF58: =T58 -> 2196 | AG58: =U58 -> 2122 | ... AJ58: =X58 -> 2037
B59: Accounts Payable | C59: ='Historical Financials'!C59 -> 5288 | D59: ='Historical Financials'!D59 -> 6979 | E59: ='Historical Financials'!E59 -> 6803 | F59: ='Historical Financials'!F59 -> 5687 | G59: ='Historical Financials'!G59 -> 4637 | H59: ='Historical Financials'!H59 -> 4980 | J59: ='Historical Financials'!J59 -> 5492 | K59: ='Historical Financials'!K59 -> 5406 | L59: ='Historical Financials'!L59 -> 7056 | M59: ='Historical Financials'!M59 -> 5687 | N59: ='Historical Financials'!N59 -> 4874 | O59: ='Historical Financials'!O59 -> 5471 | P59: ='Historical Financials'!P59 -> 7133 | Q59: ='Historical Financials'!Q59 -> 4637 | ... X59: ='Historical Financials'!X59 -> 7319 | Z59: =N59 -> 4874 | AA59: =O59 -> 5471 | AB59: =P59 -> 7133 | AC59: =Q59 -> 4637 | AD59: =R59 -> 4664 | AE59: =S59 -> 5542 | AF59: =T59 -> 7145 | AG59: =U59 -> 4980 | ... AJ59: =X59 -> 7319
B60: Deferred Revenue | C60: ='Historical Financials'!C61 -> 501 | D60: ='Historical Financials'!D61 -> 711 | E60: ='Historical Financials'!E61 -> 1103 | F60: ='Historical Financials'!F61 -> 1116 | G60: ='Historical Financials'!G61 -> 1000 | H60: ='Historical Financials'!H61 -> 951 | J60: ='Historical Financials'!J61 -> 1101 | K60: ='Historical Financials'!K61 -> 1133 | L60: ='Historical Financials'!L61 -> 1080 | M60: ='Historical Financials'!M61 -> 1116 | N60: ='Historical Financials'!N61 -> 1015 | O60: ='Historical Financials'!O61 -> 996 | P60: ='Historical Financials'!P61 -> 934 | Q60: ='Historical Financials'!Q61 -> 1000 | ... X60: ='Historical Financials'!X61 -> 853 | Z60: =N60 -> 1015 | AA60: =O60 -> 996 | AB60: =P60 -> 934 | AC60: =Q60 -> 1000 | AD60: =R60 -> 923 | AE60: =S60 -> 940 | AF60: =T60 -> 878 | AG60: =U60 -> 951 | ... AJ60: =X60 -> 853
B61: Current Liabilities | C61: ='Historical Financials'!C67 -> 8060 | D61: ='Historical Financials'!D67 -> 10521 | E61: ='Historical Financials'!E67 -> 10674 | F61: ='Historical Financials'!F67 -> 8979 | G61: ='Historical Financials'!G67 -> 7909 | H61: ='Historical Financials'!H67 -> 8016 | J61: ='Historical Financials'!J67 -> 8635 | K61: ='Historical Financials'!K67 -> 8650 | L61: ='Historical Financials'!L67 -> 10170 | M61: ='Historical Financials'!M67 -> 8979 | N61: ='Historical Financials'!N67 -> 7908 | O61: ='Historical Financials'!O67 -> 8433 | P61: ='Historical Financials'!P67 -> 10010 | Q61: ='Historical Financials'!Q67 -> 7909 | ... X61: ='Historical Financials'!X67 -> 10113 | Z61: =N61 -> 7908 | AA61: =O61 -> 8433 | AB61: =P61 -> 10010 | AC61: =Q61 -> 7909 | AD61: =R61 -> 7649 | AE61: =S61 -> 8451 | AF61: =T61 -> 9948 | AG61: =U61 -> 8016 | ... AJ61: =X61 -> 10113
B62: Total Liabilities | C62: ='Historical Financials'!C74 -> 12112 | D62: ='Historical Financials'!D74 -> 14480 | E62: ='Historical Financials'!E74 -> 14484 | F62: ='Historical Financials'!F74 -> 13008 | G62: ='Historical Financials'!G74 -> 11914 | H62: ='Historical Financials'!H74 -> 11974 | J62: ='Historical Financials'!J74 -> 12484 | K62: ='Historical Financials'!K74 -> 12527 | L62: ='Historical Financials'!L74 -> 14028 | M62: ='Historical Financials'!M74 -> 13008 | N62: ='Historical Financials'!N74 -> 11895 | O62: ='Historical Financials'!O74 -> 12483 | P62: ='Historical Financials'!P74 -> 14070 | Q62: ='Historical Financials'!Q74 -> 11914 | ... X62: ='Historical Financials'!X74 -> 14133 | Z62: =N62 -> 11895 | AA62: =O62 -> 12483 | AB62: =P62 -> 14070 | AC62: =Q62 -> 11914 | AD62: =R62 -> 11670 | AE62: =S62 -> 12517 | AF62: =T62 -> 13936 | AG62: =U62 -> 11974 | ... AJ62: =X62 -> 14133
B64: Summary Debt:
B65: CPLTD | C65: ='Historical Financials'!C66+'Historical Financials'!C65 -> 14 | D65: ='Historical Financials'!D66+'Historical Financials'!D65 -> 124 | E65: ='Historical Financials'!E66+'Historical Financials'!E65 -> 13 | F65: ='Historical Financials'!F66+'Historical Financials'!F65 -> 16 | G65: ='Historical Financials'!G66+'Historical Financials'!G65 -> 13 | H65: ='Historical Financials'!H66+'Historical Financials'!H65 -> 10 | J65: ='Historical Financials'!J66+'Historical Financials'!J65 -> 15 | K65: ='Historical Financials'!K66+'Historical Financials'!K65 -> 15 | L65: ='Historical Financials'!L66+'Historical Financials'!L65 -> 16 | M65: ='Historical Financials'!M66+'Historical Financials'!M65 -> 16 | N65: ='Historical Financials'!N66+'Historical Financials'!N65 -> 15 | O65: ='Historical Financials'!O66+'Historical Financials'!O65 -> 15 | P65: ='Historical Financials'!P66+'Historical Financials'!P65 -> 15 | Q65: ='Historical Financials'!Q66+'Historical Financials'!Q65 -> 13 | ... X65: ='Historical Financials'!X66+'Historical Financials'!X65 -> 10 | Z65: =N65 -> 15 | AA65: =O65 -> 15 | AB65: =P65 -> 15 | AC65: =Q65 -> 13 | AD65: =R65 -> 15 | AE65: =S65 -> 13 | AF65: =T65 -> 12 | AG65: =U65 -> 10 | ... AJ65: =X65 -> 10
B66: LTD | C66: ='Historical Financials'!C72+'Historical Financials'!C73 -> 1257 | D66: ='Historical Financials'!D72+'Historical Financials'!D73 -> 1253 | E66: ='Historical Financials'!E72+'Historical Financials'!E73 -> 1216 | F66: ='Historical Financials'!F72+'Historical Financials'!F73 -> 1160 | G66: ='Historical Financials'!G72+'Historical Financials'!G73 -> 1152 | H66: ='Historical Financials'!H72+'Historical Financials'!H73 -> 1144 | J66: ='Historical Financials'!J72+'Historical Financials'!J73 -> 1170 | K66: ='Historical Financials'!K72+'Historical Financials'!K73 -> 1184 | L66: ='Historical Financials'!L72+'Historical Financials'!L73 -> 1142 | M66: ='Historical Financials'!M72+'Historical Financials'!M73 -> 1160 | N66: ='Historical Financials'!N72+'Historical Financials'!N73 -> 1155 | O66: ='Historical Financials'!O72+'Historical Financials'!O73 -> 1145 | P66: ='Historical Financials'!P72+'Historical Financials'!P73 -> 1130 | Q66: ='Historical Financials'!Q72+'Historical Financials'!Q73 -> 1152 | ... X66: ='Historical Financials'!X72+'Historical Financials'!X73 -> 1155 | Z66: =N66 -> 1155 | AA66: =O66 -> 1145 | AB66: =P66 -> 1130 | AC66: =Q66 -> 1152 | AD66: =R66 -> 1134 | AE66: =S66 -> 1157 | AF66: =T66 -> 1144 | AG66: =U66 -> 1144 | ... AJ66: =X66 -> 1155
B68: $650MM 5.500% Sr. Unsecured Notes due 2021 | C68: 650 | D68: 0 | E68: 0 | F68: 0 | G68: 0 | H68: 0 | J68: 0 | K68: 0 | L68: 0 | M68: =F68 -> 0 | N68: 0 | O68: 0 | P68: 0 | Q68: =G68 -> 0 | R68: 0 | S68: 0 | T68: 0 | U68: =H68 -> 0 | V68: 0 | W68: 0 | X68: 0 | Z68: =N68 -> 0 | AA68: =O68 -> 0 | AB68: =P68 -> 0 | AC68: =Q68 -> 0 | AD68: =R68 -> 0 | AE68: =S68 -> 0 | AF68: =T68 -> 0 | AG68: =U68 -> 0 | ... AJ68: =X68 -> 0
B69: $500MM 4.450% Sr. Unsecured Notes due 2028 | C69: 500 | D69: 500 | E69: 500 | F69: 500 | G69: 500 | H69: 500 | J69: 500 | K69: 500 | L69: 500 | M69: =F69 -> 500 | N69: 500 | O69: 500 | P69: 500 | Q69: =G69 -> 500 | R69: 500 | S69: 500 | T69: 500 | U69: =H69 -> 500 | V69: 500 | W69: 500 | X69: 500 | Z69: =N69 -> 500 | AA69: =O69 -> 500 | AB69: =P69 -> 500 | AC69: =Q69 -> 500 | AD69: =R69 -> 500 | AE69: =S69 -> 500 | AF69: =T69 -> 500 | AG69: =U69 -> 500 | ... AJ69: =X69 -> 500
B70: $650MM 1.950% Sr. Unsecured Notes due 2030 | C70: 0 | D70: 650 | E70: 650 | F70: 650 | G70: 650 | H70: 650 | J70: 650 | K70: 650 | L70: 650 | M70: =F70 -> 650 | N70: 650 | O70: 650 | P70: 650 | Q70: =G70 -> 650 | R70: 650 | S70: 650 | T70: 650 | U70: =H70 -> 650 | V70: 650 | W70: 650 | X70: 650 | Z70: =N70 -> 650 | AA70: =O70 -> 650 | AB70: =P70 -> 650 | AC70: =Q70 -> 650 | AD70: =R70 -> 650 | AE70: =S70 -> 650 | AF70: =T70 -> 650 | AG70: =U70 -> 650 | ... AJ70: =X70 -> 650
B71: Finance Lease Obligations | C71: ='Historical Financials'!C65+'Historical Financials'!C72 -> 38 | D71: ='Historical Financials'!D65+'Historical Financials'!D72 -> 38 | E71: ='Historical Financials'!E65+'Historical Financials'!E72 -> 40 | F71: ='Historical Financials'!F65+'Historical Financials'!F72 -> 42 | G71: ='Historical Financials'!G65+'Historical Financials'!G72 -> 34 | H71: ='Historical Financials'!H65+'Historical Financials'!H72 -> 25 | J71: ='Historical Financials'!J65+'Historical Financials'!J72 -> 41 | K71: ='Historical Financials'!K65+'Historical Financials'!K72 -> 40 | L71: ='Historical Financials'!L65+'Historical Financials'!L72 -> 44 | M71: ='Historical Financials'!M65+'Historical Financials'!M72 -> 42 | N71: ='Historical Financials'!N65+'Historical Financials'!N72 -> 40 | O71: ='Historical Financials'!O65+'Historical Financials'!O72 -> 39 | P71: ='Historical Financials'!P65+'Historical Financials'!P72 -> 39 | Q71: ='Historical Financials'!Q65+'Historical Financials'!Q72 -> 34 | ... X71: ='Historical Financials'!X65+'Historical Financials'!X72 -> 28 | Z71: =N71 -> 40 | AA71: =O71 -> 39 | AB71: =P71 -> 39 | AC71: =Q71 -> 34 | AD71: =R71 -> 34 | AE71: =S71 -> 29 | AF71: =T71 -> 29 | AG71: =U71 -> 25 | ... AJ71: =X71 -> 28
B72: Total Debt | C72: =SUM(C68:C71) -> 1188 | D72: =SUM(D68:D71) -> 1188 | E72: =SUM(E68:E71) -> 1190 | F72: =SUM(F68:F71) -> 1192 | G72: =SUM(G68:G71) -> 1184 | H72: =SUM(H68:H71) -> 1175 | J72: =SUM(J68:J71) -> 1191 | K72: =SUM(K68:K71) -> 1190 | L72: =SUM(L68:L71) -> 1194 | M72: =SUM(M68:M71) -> 1192 | N72: =SUM(N68:N71) -> 1190 | O72: =SUM(O68:O71) -> 1189 | P72: =SUM(P68:P71) -> 1189 | Q72: =SUM(Q68:Q71) -> 1184 | ... X72: =SUM(X68:X71) -> 1178 | Z72: =SUM(Z68:Z71) -> 1190 | AA72: =SUM(AA68:AA71) -> 1189 | AB72: =SUM(AB68:AB71) -> 1189 | AC72: =SUM(AC68:AC71) -> 1184 | AD72: =SUM(AD68:AD71) -> 1184 | AE72: =SUM(AE68:AE71) -> 1179 | AF72: =SUM(AF68:AF71) -> 1179 | AG72: =SUM(AG68:AG71) -> 1175 | ... AJ72: =SUM(AJ68:AJ71) -> 1178
B74: Total Shareholder Equity | C74: ='Historical Financials'!C81 -> 3479 | D74: ='Historical Financials'!D81 -> 4587 | E74: ='Historical Financials'!E81 -> 3020 | F74: ='Historical Financials'!F81 -> 2795 | G74: ='Historical Financials'!G81 -> 3053 | H74: ='Historical Financials'!H81 -> 2808 | J74: ='Historical Financials'!J81 -> 2767 | K74: ='Historical Financials'!K81 -> 2892 | L74: ='Historical Financials'!L81 -> 2993 | M74: ='Historical Financials'!M81 -> 2795 | N74: ='Historical Financials'!N81 -> 2793 | O74: ='Historical Financials'!O81 -> 2835 | P74: ='Historical Financials'!P81 -> 2812 | Q74: ='Historical Financials'!Q81 -> 3053 | ... X74: ='Historical Financials'!X81 -> 2653 | Z74: =N74 -> 2793 | AA74: =O74 -> 2835 | AB74: =P74 -> 2812 | AC74: =Q74 -> 3053 | AD74: =R74 -> 3082 | AE74: =S74 -> 3107 | AF74: =T74 -> 3082 | AG74: =U74 -> 2808 | ... AJ74: =X74 -> 2653
B75: Total Book Capitalization | C75: =SUM(C72:C74) -> 4667 | D75: =SUM(D72:D74) -> 5775 | E75: =SUM(E72:E74) -> 4210 | F75: =SUM(F72:F74) -> 3987 | G75: =SUM(G72:G74) -> 4237 | H75: =SUM(H72:H74) -> 3983 | J75: =SUM(J72:J74) -> 3958 | K75: =SUM(K72:K74) -> 4082 | L75: =SUM(L72:L74) -> 4187 | M75: =SUM(M72:M74) -> 3987 | N75: =SUM(N72:N74) -> 3983 | O75: =SUM(O72:O74) -> 4024 | P75: =SUM(P72:P74) -> 4001 | Q75: =SUM(Q72:Q74) -> 4237 | ... X75: =SUM(X72:X74) -> 3831 | Z75: =SUM(Z72:Z74) -> 3983 | AA75: =SUM(AA72:AA74) -> 4024 | AB75: =SUM(AB72:AB74) -> 4001 | AC75: =SUM(AC72:AC74) -> 4237 | AD75: =SUM(AD72:AD74) -> 4266 | AE75: =SUM(AE72:AE74) -> 4286 | AF75: =SUM(AF72:AF74) -> 4261 | AG75: =SUM(AG72:AG74) -> 3983 | ... AJ75: =SUM(AJ72:AJ74) -> 3831
B77: Credit Metrics
B79: LTM Total Leverage | C79: =C72/C31 -> 0.40080972 | D79: =D72/D31 -> 0.35304606 | E79: =E72/E31 -> 0.29389973 | F79: =F72/F31 -> 0.41809891 | G79: =G72/G31 -> 0.44814534 | H79: =H72/H31 -> 0.51830613 | M79: =SUM(M72/SUM(J31:M31)) -> 0.41809891 | N79: =SUM(N72/SUM(K31:N31)) -> 0.43879056 | O79: =SUM(O72/SUM(L31:O31)) -> 0.43923162 | P79: =SUM(P72/SUM(M31:P31)) -> 0.44020733 | Q79: =SUM(Q72/SUM(N31:Q31)) -> 0.44814534 | R79: =SUM(R72/SUM(O31:R31)) -> 0.45104762 | S79: =SUM(S72/SUM(P31:S31)) -> 0.44642181 | T79: =SUM(T72/SUM(Q31:T31)) -> 0.45 | ... X79: =SUM(X72/SUM(U31:X31)) -> 0.63129689 | Z79: =Z72/Z31 -> 0.43879056 | AA79: =AA72/AA31 -> 0.43923162 | AB79: =AB72/AB31 -> 0.44020733 | AC79: =AC72/AC31 -> 0.44814534 | AD79: =AD72/AD31 -> 0.45104762 | AE79: =AE72/AE31 -> 0.44642181 | AF79: =AF72/AF31 -> 0.45 | AG79: =AG72/AG31 -> 0.51830613 | ... AJ79: =AJ72/AJ31 -> 0.63129689
B80: LTM Net Leverage | C80: =SUM(C72-C50)/C31 -> -0.35121457 | D80: =SUM(D72-D50)/D31 -> -1.2796434 | E80: =SUM(E72-E50)/E31 -> -0.43121758 | F80: =SUM(F72-F50)/F31 -> -0.23921431 | G80: =SUM(G72-G50)/G31 -> -0.099545799 | H80: =SUM(H72-H50)/H31 -> -0.17776798 | M80: =SUM(M72-M50)/SUM(J31:M31) -> -0.23921431 | N80: =SUM(N72-N50)/SUM(K31:N31) -> 0.05899705 | O80: =SUM(O72-O50)/SUM(L31:O31) -> 0.035463613 | P80: =SUM(P72-P50)/SUM(M31:P31) -> 0.20473899 | Q80: =SUM(Q72-Q50)/SUM(N31:Q31) -> -0.099545799 | R80: =SUM(R72-R50)/SUM(O31:R31) -> -0.011428571 | S80: =SUM(S72-S50)/SUM(P31:S31) -> -0.078758046 | T80: =SUM(T72-T50)/SUM(Q31:T31) -> 0.20458015 | ... X80: =SUM(X72-X50)/SUM(U31:X31) -> 0.13665595 | Z80: =SUM(Z72-Z50)/Z31 -> 0.05899705 | AA80: =SUM(AA72-AA50)/AA31 -> 0.035463613 | AB80: =SUM(AB72-AB50)/AB31 -> 0.20473899 | AC80: =SUM(AC72-AC50)/AC31 -> -0.099545799 | AD80: =SUM(AD72-AD50)/AD31 -> -0.011428571 | AE80: =SUM(AE72-AE50)/AE31 -> -0.078758046 | AF80: =SUM(AF72-AF50)/AF31 -> 0.20458015 | AG80: =SUM(AG72-AG50)/AG31 -> -0.17776798 | ... AJ80: =SUM(AJ72-AJ50)/AJ31 -> 0.13665595
B81: LTM Interest Coverage | C81: =C31/-C36 -> 47.806452 | D81: =D31/-D36 -> 67.3 | E81: =E31/-E36 -> 184.04545 | F81: =F31/-F36 -> 91.967742 | G81: =G31/-G36 -> 51.803922 | H81: =H31/-H36 -> 49.282609 | M81: {=SUM(J31:M31)/SUM(-J36:M36)} -> 81.457143 | N81: {=SUM(K31:N31)/SUM(-K36:N36)} -> 66.146341 | O81: {=SUM(L31:O31)/SUM(-L36:O36)} -> 58.847826 | P81: {=SUM(M31:P31)/SUM(-M36:P36)} -> 54.02 | Q81: {=SUM(N31:Q31)/SUM(-N36:Q36)} -> 50.807692 | R81: {=SUM(O31:R31)/SUM(-O36:R36)} -> 50.480769 | S81: {=SUM(P31:S31)/SUM(-P36:S36)} -> 49.830189 | T81: {=SUM(Q31:T31)/SUM(-Q36:T36)} -> 50.384615 | ... X81: {=SUM(U31:X31)/SUM(-U36:X36)} -> 38.081633 | Z81: =Z31/-Z36 -> 66.146341 | AA81: =AA31/-AA36 -> 58.847826 | AB81: =AB31/-AB36 -> 54.02 | AC81: =AC31/-AC36 -> 50.807692 | AD81: =AD31/-AD36 -> 50.480769 | AE81: =AE31/-AE36 -> 49.830189 | AF81: =AF31/-AF36 -> 50.384615 | AG81: =AG31/-AG36 -> 44.45098 | ... AJ81: =AJ31/-AJ36 -> 38.081633
B82: LTM Debt Service Coverage | C82: {=SUM(C31+C34)/SUM(-C35:C36)} -> 3.8559028 | D82: {=SUM(D31+D34)/SUM(-D35:D36)} -> 5.3902439 | E82: {=SUM(E31+E34)/SUM(-E35:E36)} -> 4.4878049 | F82: {=SUM(F31+F34)/SUM(-F35:F36)} -> 6.1178344 | G82: {=SUM(G31+G34)/SUM(-G35:G36)} -> 3.1094276 | H82: {=SUM(H31+H34)/SUM(-H35:H36)} -> 2.2656023 | M82: {=SUM(J31:M31+J34:M34)/SUM(-J35:M36)} -> 4.7432099 | N82: {=SUM(K31:N31+K34:N34)/SUM(-K35:N36)} -> 4.768617 | O82: {=SUM(L31:O31+L34:O34)/SUM(-L35:O36)} -> 4.3508353 | P82: {=SUM(M31:P31+M34:P34)/SUM(-M35:P36)} -> 4.3647059 | Q82: {=SUM(N31:Q31+N34:Q34)/SUM(-N35:Q36)} -> 4.2655889 | R82: {=SUM(O31:R31+O34:R34)/SUM(-O35:R36)} -> 4.2968037 | S82: {=SUM(P31:S31+P34:S34)/SUM(-P35:S36)} -> 4.2927928 | T82: {=SUM(Q31:T31+Q34:T34)/SUM(-Q35:T36)} -> 4.3190045 | ... X82: {=SUM(U31:X31+U34:X34)/SUM(-U35:X36)} -> 3.7875817 | Z82: {=SUM(Z31+Z34)/SUM(-Z35:Z36)} -> 4.768617 | AA82: {=SUM(AA31+AA34)/SUM(-AA35:AA36)} -> 4.3508353 | AB82: {=SUM(AB31+AB34)/SUM(-AB35:AB36)} -> 4.3647059 | AC82: {=SUM(AC31+AC34)/SUM(-AC35:AC36)} -> 4.2655889 | AD82: {=SUM(AD31+AD34)/SUM(-AD35:AD36)} -> 4.2968037 | AE82: {=SUM(AE31+AE34)/SUM(-AE35:AE36)} -> 4.2927928 | AF82: {=SUM(AF31+AF34)/SUM(-AF35:AF36)} -> 4.3190045 | AG82: {=SUM(AG31+AG34)/SUM(-AG35:AG36)} -> 3.6903073 | ... AJ82: {=SUM(AJ31+AJ34)/SUM(-AJ35:AJ36)} -> 3.7875817
B83: LTM Fixed Charge Coverage | C83: {=SUM(C31)/SUM(-C34:C36)} -> 2.2471569 | D83: {=SUM(D31)/SUM(-D34:D36)} -> 2.7925311 | E83: {=SUM(E31)/SUM(-E34:E36)} -> 2.7450847 | F83: {=SUM(F31)/SUM(-F34:F36)} -> 2.2918006 | G83: {=SUM(G31)/SUM(-G34:G36)} -> 1.9020878 | H83: {=SUM(H31)/SUM(-H34:H36)} -> 1.6250896 | M83: {=SUM(J31:M31)/SUM(-J34:M36)} -> 2.1355805 | N83: {=SUM(K31:N31)/SUM(-K34:N36)} -> 2.0942085 | O83: {=SUM(L31:O31)/SUM(-L34:O36)} -> 2.0775134 | P83: {=SUM(M31:P31)/SUM(-M34:P36)} -> 2.1250983 | Q83: {=SUM(N31:Q31)/SUM(-N34:Q36)} -> 2.1514658 | R83: {=SUM(O31:R31)/SUM(-O34:R36)} -> 2.2226926 | S83: {=SUM(P31:S31)/SUM(-P34:S36)} -> 2.2400339 | T83: {=SUM(Q31:T31)/SUM(-Q34:T36)} -> 2.272333 | ... X83: {=SUM(U31:X31)/SUM(-U34:X36)} -> 1.8420533 | Z83: {=SUM(Z31)/SUM(-Z34:Z36)} -> 2.0942085 | AA83: {=SUM(AA31)/SUM(-AA34:AA36)} -> 2.0775134 | AB83: {=SUM(AB31)/SUM(-AB34:AB36)} -> 2.1250983 | AC83: {=SUM(AC31)/SUM(-AC34:AC36)} -> 2.1514658 | AD83: {=SUM(AD31)/SUM(-AD34:AD36)} -> 2.2226926 | AE83: {=SUM(AE31)/SUM(-AE34:AE36)} -> 2.2400339 | AF83: {=SUM(AF31)/SUM(-AF34:AF36)} -> 2.272333 | AG83: {=SUM(AG31)/SUM(-AG34:AG36)} -> 2.0079717 | ... AJ83: {=SUM(AJ31)/SUM(-AJ34:AJ36)} -> 1.8420533
B84: Debt-to-Book Capitalization | C84: =C75/C72 -> 3.9284512 | D84: =D75/D72 -> 4.8611111 | E84: =E75/E72 -> 3.5378151 | F84: =F75/F72 -> 3.3447987 | G84: =G75/G72 -> 3.5785473 | H84: =H75/H72 -> 3.3897872 | M84: =M75/M72 -> 3.3447987 | N84: =N75/N72 -> 3.3470588 | O84: =O75/O72 -> 3.3843566 | P84: =P75/P72 -> 3.3650126 | Q84: =Q75/Q72 -> 3.5785473 | R84: =R75/R72 -> 3.6030405 | S84: =S75/S72 -> 3.6352841 | T84: =T75/T72 -> 3.6140797 | ... X84: =X75/X72 -> 3.2521222 | Z84: =Z75/Z72 -> 3.3470588 | AA84: =AA75/AA72 -> 3.3843566 | AB84: =AB75/AB72 -> 3.3650126 | AC84: =AC75/AC72 -> 3.5785473 | AD84: =AD75/AD72 -> 3.6030405 | AE84: =AE75/AE72 -> 3.6352841 | AF84: =AF75/AF72 -> 3.6140797 | AG84: =AG75/AG72 -> 3.3897872 | ... AJ84: =AJ75/AJ72 -> 3.2521222
