Workbook

Sheet Base Financials
B2: Apple Inc. (NASDAQ: AAPL) | C2: FYE | D2: FYE | E2: FYE | F2: FYE | G2: FYE | I2: FYE | M2: Quarterly | S2: Quarterly | V2: Quarterly | W2: Quarterly | AI2: LTM | AO2: Variance
B3: Base Financials | C3: 2016 | D3: 2017 | E3: 2018 | F3: 2019 | G3: 2020 | H3: 2021 | I3: 2022 | J3: 2023 | K3: 2024 | M3: 1Q22 | N3: 2Q22 | O3: 3Q22 | P3: 4Q22 | Q3: 1Q23 | R3: 2Q23 | S3: 3Q23 | T3: 4Q23 | U3: 1Q24 | V3: 2Q24 | W3: 3Q24 | X3: 4Q24 | Y3: 1Q25 | Z3: 2Q25 | AA3: 3Q25 | AC3: =Q3 -> 1Q23 | AD3: =R3 -> 2Q23 | AE3: =S3 -> 3Q23 | AF3: =T3 -> 4Q23 | AG3: =U3 -> 1Q24 | AH3: =V3 -> 2Q24 | AI3: =W3 -> 3Q24 | AJ3: =X3 -> 4Q24 | ... AM3: =AA3 -> 3Q25
B4: ($ In Millions) | C4: 42643 | D4: 43008 | E4: 43372 | F4: 43737 | G4: 44104 | H4: 44469 | I4: 44834 | J4: 45192 | K4: 45559 | M4: 44560 | N4: 44650 | O4: 44742 | P4: =I4 -> 44834 | Q4: 44917 | R4: 45008 | S4: 45100 | T4: =J4 -> 45192 | U4: 45283 | V4: 45375 | W4: 45467 | X4: =K4 -> 45559 | Y4: 45650 | Z4: 45741 | AA4: 45833 | AC4: =Q4 -> 44917 | AD4: =R4 -> 45008 | AE4: =S4 -> 45100 | AF4: =T4 -> 45192 | AG4: =U4 -> 45283 | AH4: =V4 -> 45375 | AI4: =W4 -> 45467 | AJ4: =X4 -> 45559 | ... AM4: =AA4 -> 45833
A6: X | B6: Income Statement
B8: Consolidated Revenue | C8: 215639 | D8: 229234 | E8: 265595 | F8: 260174 | G8: 274515 | H8: 365817 | I8: 394328 | J8: 383285 | K8: 391035 | M8: 123945 | N8: 97278 | O8: 82959 | P8: =SUM(I8-SUM(M8:O8)) -> 90146 | Q8: 117154 | R8: 94836 | S8: 81797 | T8: =SUM(J8-SUM(Q8:S8)) -> 89498 | U8: 119575 | V8: 90753 | W8: 85777 | X8: =SUM(K8-SUM(U8:W8)) -> 94930 | Y8: 124300 | Z8: 95359 | AA8: 94036 | AC8: =SUM(N8:Q8) -> 387537 | AD8: =SUM(O8:R8) -> 385095 | AE8: =SUM(P8:S8) -> 383933 | AF8: =SUM(Q8:T8) -> 383285 | AG8: =SUM(R8:U8) -> 385706 | AH8: =SUM(S8:V8) -> 381623 | AI8: =SUM(T8:W8) -> 385603 | AJ8: =SUM(U8:X8) -> 391035 | ... AM8: =SUM(X8:AA8) -> 408625 | AO8: =SUM(AM8/AI8)-1 -> 0.059703892
B9: Total Revenue | C9: =+SUM(C8:C8) -> 215639 | D9: =+SUM(D8:D8) -> 229234 | E9: =+SUM(E8:E8) -> 265595 | F9: =+SUM(F8:F8) -> 260174 | G9: =+SUM(G8:G8) -> 274515 | H9: =+SUM(H8:H8) -> 365817 | I9: =+SUM(I8:I8) -> 394328 | J9: =+SUM(J8:J8) -> 383285 | K9: =+SUM(K8:K8) -> 391035 | M9: =+SUM(M8:M8) -> 123945 | N9: =+SUM(N8:N8) -> 97278 | O9: =+SUM(O8:O8) -> 82959 | P9: =+SUM(P8:P8) -> 90146 | Q9: =+SUM(Q8:Q8) -> 117154 | R9: =+SUM(R8:R8) -> 94836 | S9: =+SUM(S8:S8) -> 81797 | T9: =+SUM(T8:T8) -> 89498 | ... AA9: =+SUM(AA8:AA8) -> 94036 | AC9: =+SUM(AC8:AC8) -> 387537 | AD9: =+SUM(AD8:AD8) -> 385095 | AE9: =+SUM(AE8:AE8) -> 383933 | AF9: =+SUM(AF8:AF8) -> 383285 | AG9: =+SUM(AG8:AG8) -> 385706 | AH9: =+SUM(AH8:AH8) -> 381623 | AI9: =+SUM(AI8:AI8) -> 385603 | AJ9: =+SUM(AJ8:AJ8) -> 391035 | ... AM9: =+SUM(AM8:AM8) -> 408625 | AO9: =SUM(AM9/AI9)-1 -> 0.059703892
B11: Cost of Sales | C11: -131376 | D11: -141048 | E11: -163756 | F11: -161782 | G11: -169559 | H11: -212981 | I11: -223546 | J11: -214137 | K11: -210352 | M11: -69702 | N11: -54719 | O11: -47074 | P11: =SUM(I11-SUM(M11:O11)) -> -52051 | Q11: -66822 | R11: -52860 | S11: -45384 | T11: =SUM(J11-SUM(Q11:S11)) -> -49071 | U11: -64720 | V11: -48482 | W11: -46099 | X11: =SUM(K11-SUM(U11:W11)) -> -51051 | Y11: -66025 | Z11: -50492 | AA11: -50318 | AC11: =SUM(N11:Q11) -> -220666 | AD11: =SUM(O11:R11) -> -218807 | AE11: =SUM(P11:S11) -> -217117 | AF11: =SUM(Q11:T11) -> -214137 | AG11: =SUM(R11:U11) -> -212035 | AH11: =SUM(S11:V11) -> -207657 | AI11: =SUM(T11:W11) -> -208372 | AJ11: =SUM(U11:X11) -> -210352 | ... AM11: =SUM(X11:AA11) -> -217886 | AO11: =SUM(AM11/AI11)-1 -> 0.045658726
B12: Gross Profit | C12: =+SUM(C9+SUM(C11:C11)) -> 84263 | D12: =+SUM(D9+SUM(D11:D11)) -> 88186 | E12: =+SUM(E9+SUM(E11:E11)) -> 101839 | F12: =+SUM(F9+SUM(F11:F11)) -> 98392 | G12: =+SUM(G9+SUM(G11:G11)) -> 104956 | H12: =+SUM(H9+SUM(H11:H11)) -> 152836 | I12: =+SUM(I9+SUM(I11:I11)) -> 170782 | J12: =+SUM(J9+SUM(J11:J11)) -> 169148 | K12: =+SUM(K9+SUM(K11:K11)) -> 180683 | M12: =+SUM(M9+SUM(M11:M11)) -> 54243 | N12: =+SUM(N9+SUM(N11:N11)) -> 42559 | O12: =+SUM(O9+SUM(O11:O11)) -> 35885 | P12: =+SUM(P9+SUM(P11:P11)) -> 38095 | Q12: =+SUM(Q9+SUM(Q11:Q11)) -> 50332 | R12: =+SUM(R9+SUM(R11:R11)) -> 41976 | S12: =+SUM(S9+SUM(S11:S11)) -> 36413 | T12: =+SUM(T9+SUM(T11:T11)) -> 40427 | ... AA12: =+SUM(AA9+SUM(AA11:AA11)) -> 43718 | AC12: =+SUM(AC9+SUM(AC11:AC11)) -> 166871 | AD12: =+SUM(AD9+SUM(AD11:AD11)) -> 166288 | AE12: =+SUM(AE9+SUM(AE11:AE11)) -> 166816 | AF12: =+SUM(AF9+SUM(AF11:AF11)) -> 169148 | AG12: =+SUM(AG9+SUM(AG11:AG11)) -> 173671 | AH12: =+SUM(AH9+SUM(AH11:AH11)) -> 173966 | AI12: =+SUM(AI9+SUM(AI11:AI11)) -> 177231 | AJ12: =+SUM(AJ9+SUM(AJ11:AJ11)) -> 180683 | ... AM12: =+SUM(AM9+SUM(AM11:AM11)) -> 190739 | AO12: =SUM(AM12/AI12)-1 -> 0.076216915
B13: Gross Margin (%) | C13: =C12/C9 -> 0.39075956 | D13: =D12/D9 -> 0.3846986 | E13: =E12/E9 -> 0.38343719 | F13: =F12/F9 -> 0.37817768 | G13: =G12/G9 -> 0.38233248 | H13: =H12/H9 -> 0.4177936 | I13: =I12/I9 -> 0.43309631 | J13: =J12/J9 -> 0.4413113 | K13: =K12/K9 -> 0.4620635 | M13: =M12/M9 -> 0.43763766 | N13: =N12/N9 -> 0.43749872 | O13: =O12/O9 -> 0.43256307 | P13: =P12/P9 -> 0.42259224 | Q13: =Q12/Q9 -> 0.42962255 | R13: =R12/R9 -> 0.44261673 | S13: =S12/S9 -> 0.44516303 | T13: =T12/T9 -> 0.45170842 | ... AA13: =AA12/AA9 -> 0.46490706 | AC13: =AC12/AC9 -> 0.43059372 | AD13: =AD12/AD9 -> 0.43181033 | AE13: =AE12/AE9 -> 0.43449248 | AF13: =AF12/AF9 -> 0.4413113 | AG13: =AG12/AG9 -> 0.45026782 | AH13: =AH12/AH9 -> 0.45585827 | AI13: =AI12/AI9 -> 0.45962039 | AJ13: =AJ12/AJ9 -> 0.4620635 | ... AM13: =AM12/AM9 -> 0.4667825 | AO13: =SUM(AM13-AI13)*1000 -> 7.1621155
B15: Research & Development | C15: -10045 | D15: -11581 | E15: -14236 | F15: -16217 | G15: -18752 | H15: -21914 | I15: -26251 | J15: -29915 | K15: -31370 | M15: -6306 | N15: -6387 | O15: -6797 | P15: =SUM(I15-SUM(M15:O15)) -> -6761 | Q15: -7709 | R15: -7457 | S15: -7442 | T15: =SUM(J15-SUM(Q15:S15)) -> -7307 | U15: -7696 | V15: -7903 | W15: -8006 | X15: =SUM(K15-SUM(U15:W15)) -> -7765 | Y15: -8268 | Z15: -8550 | AA15: -8866 | AC15: =SUM(N15:Q15) -> -27654 | AD15: =SUM(O15:R15) -> -28724 | AE15: =SUM(P15:S15) -> -29369 | AF15: =SUM(Q15:T15) -> -29915 | AG15: =SUM(R15:U15) -> -29902 | AH15: =SUM(S15:V15) -> -30348 | AI15: =SUM(T15:W15) -> -30912 | AJ15: =SUM(U15:X15) -> -31370 | ... AM15: =SUM(X15:AA15) -> -33449 | AO15: =SUM(AM15/AI15)-1 -> 0.082071687
B16: Selling, General & Administrative | C16: -14194 | D16: -15261 | E16: -16705 | F16: -18245 | G16: -19916 | H16: -21973 | I16: -25094 | J16: -24932 | K16: -26097 | M16: -6449 | N16: -6193 | O16: -6012 | P16: =SUM(I16-SUM(M16:O16)) -> -6440 | Q16: -6607 | R16: -6201 | S16: -5973 | T16: =SUM(J16-SUM(Q16:S16)) -> -6151 | U16: -6786 | V16: -6468 | W16: -6320 | X16: =SUM(K16-SUM(U16:W16)) -> -6523 | Y16: -7175 | Z16: -6728 | AA16: -6650 | AC16: =SUM(N16:Q16) -> -25252 | AD16: =SUM(O16:R16) -> -25260 | AE16: =SUM(P16:S16) -> -25221 | AF16: =SUM(Q16:T16) -> -24932 | AG16: =SUM(R16:U16) -> -25111 | AH16: =SUM(S16:V16) -> -25378 | AI16: =SUM(T16:W16) -> -25725 | AJ16: =SUM(U16:X16) -> -26097 | ... AM16: =SUM(X16:AA16) -> -27076 | AO16: =SUM(AM16/AI16)-1 -> 0.052517007
B17: Profit From Operations | C17: =SUM(C12+SUM(C15:C16)) -> 60024 | D17: =SUM(D12+SUM(D15:D16)) -> 61344 | E17: =SUM(E12+SUM(E15:E16)) -> 70898 | F17: =SUM(F12+SUM(F15:F16)) -> 63930 | G17: =SUM(G12+SUM(G15:G16)) -> 66288 | H17: =SUM(H12+SUM(H15:H16)) -> 108949 | I17: =SUM(I12+SUM(I15:I16)) -> 119437 | J17: =SUM(J12+SUM(J15:J16)) -> 114301 | K17: =SUM(K12+SUM(K15:K16)) -> 123216 | M17: =SUM(M12+SUM(M15:M16)) -> 41488 | N17: =SUM(N12+SUM(N15:N16)) -> 29979 | O17: =SUM(O12+SUM(O15:O16)) -> 23076 | P17: =SUM(P12+SUM(P15:P16)) -> 24894 | Q17: =SUM(Q12+SUM(Q15:Q16)) -> 36016 | R17: =SUM(R12+SUM(R15:R16)) -> 28318 | S17: =SUM(S12+SUM(S15:S16)) -> 22998 | T17: =SUM(T12+SUM(T15:T16)) -> 26969 | ... AA17: =SUM(AA12+SUM(AA15:AA16)) -> 28202 | AC17: =SUM(AC12+SUM(AC15:AC16)) -> 113965 | AD17: =SUM(AD12+SUM(AD15:AD16)) -> 112304 | AE17: =SUM(AE12+SUM(AE15:AE16)) -> 112226 | AF17: =SUM(AF12+SUM(AF15:AF16)) -> 114301 | AG17: =SUM(AG12+SUM(AG15:AG16)) -> 118658 | AH17: =SUM(AH12+SUM(AH15:AH16)) -> 118240 | AI17: =SUM(AI12+SUM(AI15:AI16)) -> 120594 | AJ17: =SUM(AJ12+SUM(AJ15:AJ16)) -> 123216 | ... AM17: =SUM(AM12+SUM(AM15:AM16)) -> 130214 | AO17: =SUM(AM17/AI17)-1 -> 0.079771796
B18: Operating Margin (%) | C18: =C17/C9 -> 0.2783541 | D18: =D17/D9 -> 0.26760428 | E18: =E17/E9 -> 0.26694027 | F18: =F17/F9 -> 0.24572017 | G18: =G17/G9 -> 0.24147314 | H18: =H17/H9 -> 0.29782378 | I18: =I17/I9 -> 0.30288744 | J18: =J17/J9 -> 0.29821412 | K18: =K17/K9 -> 0.31510223 | M18: =M17/M9 -> 0.33472911 | N18: =N17/N9 -> 0.30817862 | O18: =O17/O9 -> 0.2781615 | P18: =P17/P9 -> 0.27615202 | Q18: =Q17/Q9 -> 0.30742442 | R18: =R17/R9 -> 0.29859969 | S18: =S17/S9 -> 0.28115946 | T18: =T17/T9 -> 0.30133634 | ... AA18: =AA17/AA9 -> 0.29990642 | AC18: =AC17/AC9 -> 0.29407515 | AD18: =AD17/AD9 -> 0.29162674 | AE18: =AE17/AE9 -> 0.29230621 | AF18: =AF17/AF9 -> 0.29821412 | AG18: =AG17/AG9 -> 0.30763846 | AH18: =AH17/AH9 -> 0.30983457 | AI18: =AI17/AI9 -> 0.31274134 | AJ18: =AJ17/AJ9 -> 0.31510223 | ... AM18: =AM17/AM9 -> 0.31866381 | AO18: =SUM(AM18-AI18)*1000 -> 5.9224688
B20: Other income/(expense), net | C20: 1348 | D20: 2745 | E20: 2005 | F20: 1807 | G20: 803 | H20: 258 | I20: -334 | J20: -565 | K20: 269 | M20: -247 | N20: 160 | O20: -10 | P20: =SUM(I20-SUM(M20:O20)) -> -237 | Q20: -393 | R20: 64 | S20: -265 | T20: =SUM(J20-SUM(Q20:S20)) -> 29 | U20: -50 | V20: 158 | W20: 142 | X20: =SUM(K20-SUM(U20:W20)) -> 19 | Y20: -248 | Z20: -279 | AA20: -171 | AC20: =SUM(N20:Q20) -> -480 | AD20: =SUM(O20:R20) -> -576 | AE20: =SUM(P20:S20) -> -831 | AF20: =SUM(Q20:T20) -> -565 | AG20: =SUM(R20:U20) -> -222 | AH20: =SUM(S20:V20) -> -128 | AI20: =SUM(T20:W20) -> 279 | AJ20: =SUM(U20:X20) -> 269 | ... AM20: =SUM(X20:AA20) -> -679 | AO20: =SUM(AM20/AI20)-1 -> -3.4336918
B21: Net loss before provision for income taxes | C21: =SUM(C20:C20)+C17 -> 61372 | D21: =SUM(D20:D20)+D17 -> 64089 | E21: =SUM(E20:E20)+E17 -> 72903 | F21: =SUM(F20:F20)+F17 -> 65737 | G21: =SUM(G20:G20)+G17 -> 67091 | H21: =SUM(H20:H20)+H17 -> 109207 | I21: =SUM(I20:I20)+I17 -> 119103 | J21: =SUM(J20:J20)+J17 -> 113736 | K21: =SUM(K20:K20)+K17 -> 123485 | M21: =SUM(M20:M20)+M17 -> 41241 | N21: =SUM(N20:N20)+N17 -> 30139 | O21: =SUM(O20:O20)+O17 -> 23066 | P21: =SUM(P20:P20)+P17 -> 24657 | Q21: =SUM(Q20:Q20)+Q17 -> 35623 | R21: =SUM(R20:R20)+R17 -> 28382 | S21: =SUM(S20:S20)+S17 -> 22733 | T21: =SUM(T20:T20)+T17 -> 26998 | ... AA21: =SUM(AA20:AA20)+AA17 -> 28031 | AC21: =SUM(AC20:AC20)+AC17 -> 113485 | AD21: =SUM(AD20:AD20)+AD17 -> 111728 | AE21: =SUM(AE20:AE20)+AE17 -> 111395 | AF21: =SUM(AF20:AF20)+AF17 -> 113736 | AG21: =SUM(AG20:AG20)+AG17 -> 118436 | AH21: =SUM(AH20:AH20)+AH17 -> 118112 | AI21: =SUM(AI20:AI20)+AI17 -> 120873 | AJ21: =SUM(AJ20:AJ20)+AJ17 -> 123485 | ... AM21: =SUM(AM20:AM20)+AM17 -> 129535 | AO21: =SUM(AM21/AI21)-1 -> 0.071661992
B23: Provision for taxes | C23: -15685 | D23: -15738 | E23: -13372 | F23: -10481 | G23: -9680 | H23: -14527 | I23: -19300 | J23: -16741 | K23: -29749 | M23: -6611 | N23: -5129 | O23: -3624 | P23: =SUM(I23-SUM(M23:O23)) -> -3936 | Q23: -5625 | R23: -4222 | S23: -2852 | T23: =SUM(J23-SUM(Q23:S23)) -> -4042 | U23: -6407 | V23: -4422 | W23: -4046 | X23: =SUM(K23-SUM(U23:W23)) -> -14874 | Y23: -6254 | Z23: -4530 | AA23: -4597 | AC23: =SUM(N23:Q23) -> -18314 | AD23: =SUM(O23:R23) -> -17407 | AE23: =SUM(P23:S23) -> -16635 | AF23: =SUM(Q23:T23) -> -16741 | AG23: =SUM(R23:U23) -> -17523 | AH23: =SUM(S23:V23) -> -17723 | AI23: =SUM(T23:W23) -> -18917 | AJ23: =SUM(U23:X23) -> -29749 | ... AM23: =SUM(X23:AA23) -> -30255 | AO23: =SUM(AM23/AI23)-1 -> 0.59935508
B24: Net loss | C24: =SUM(C21+C23) -> 45687 | D24: =SUM(D21+D23) -> 48351 | E24: =SUM(E21+E23) -> 59531 | F24: =SUM(F21+F23) -> 55256 | G24: =SUM(G21+G23) -> 57411 | H24: =SUM(H21+H23) -> 94680 | I24: =SUM(I21+I23) -> 99803 | J24: =SUM(J21+J23) -> 96995 | K24: =SUM(K21+K23) -> 93736 | M24: =SUM(M21+M23) -> 34630 | N24: =SUM(N21+N23) -> 25010 | O24: =SUM(O21+O23) -> 19442 | P24: =SUM(P21+P23) -> 20721 | Q24: =SUM(Q21+Q23) -> 29998 | R24: =SUM(R21+R23) -> 24160 | S24: =SUM(S21+S23) -> 19881 | T24: =SUM(T21+T23) -> 22956 | ... AA24: =SUM(AA21+AA23) -> 23434 | AC24: =SUM(AC21+AC23) -> 95171 | AD24: =SUM(AD21+AD23) -> 94321 | AE24: =SUM(AE21+AE23) -> 94760 | AF24: =SUM(AF21+AF23) -> 96995 | AG24: =SUM(AG21+AG23) -> 100913 | AH24: =SUM(AH21+AH23) -> 100389 | AI24: =SUM(AI21+AI23) -> 101956 | AJ24: =SUM(AJ21+AJ23) -> 93736 | ... AM24: =SUM(AM21+AM23) -> 99280 | AO24: =SUM(AM24/AI24)-1 -> -0.026246616
B25: Net Margin (%) | C25: =C24/C9 -> 0.21186798 | D25: =D24/D9 -> 0.21092421 | E25: =E24/E9 -> 0.22414202 | F25: =F24/F9 -> 0.21238095 | G25: =G24/G9 -> 0.20913611 | H25: =H24/H9 -> 0.25881793 | I25: =I24/I9 -> 0.25309641 | J25: =J24/J9 -> 0.25306234 | K25: =K24/K9 -> 0.23971256 | M25: =M24/M9 -> 0.27939812 | N25: =N24/N9 -> 0.25709821 | O25: =O24/O9 -> 0.23435673 | P25: =P24/P9 -> 0.22986045 | Q25: =Q24/Q9 -> 0.25605613 | R25: =R24/R9 -> 0.25475558 | S25: =S24/S9 -> 0.24305292 | T25: =T24/T9 -> 0.25649735 | ... AA25: =AA24/AA9 -> 0.24920243 | AC25: =AC24/AC9 -> 0.24557913 | AD25: =AD24/AD9 -> 0.24492917 | AE25: =AE24/AE9 -> 0.2468139 | AF25: =AF24/AF9 -> 0.25306234 | AG25: =AG24/AG9 -> 0.26163192 | AH25: =AH24/AH9 -> 0.26305804 | AI25: =AI24/AI9 -> 0.26440666 | AJ25: =AJ24/AJ9 -> 0.23971256 | ... AM25: =AM24/AM9 -> 0.24296115 | AO25: =SUM(AM25-AI25)*1000 -> -21.445506
B27: Basic shares | C27: 21883.281 | D27: 20868.968 | E27: 19821.51 | F27: 18471.336 | G27: 17352.119 | H27: 16701.272 | I27: 16215.963 | J27: 15744.231 | K27: 15343.783 | M27: 16391.724 | N27: 16278.802 | O27: 16162.945 | P27: =I27 -> 16215.963 | Q27: 15892.723 | R27: 15787.154 | S27: 15697.614 | T27: =J27 -> 15744.231 | U27: 15509.763 | V27: 15405.856 | W27: 15287.521 | X27: =K27 -> 15343.783 | Y27: 15081.724 | Z27: 14994.082 | AA27: 14902.886 | AC27: =Q27 -> 15892.723 | AD27: =R27 -> 15787.154 | AE27: =S27 -> 15697.614 | AF27: =T27 -> 15744.231 | AG27: =U27 -> 15509.763 | AH27: =V27 -> 15405.856 | AI27: =W27 -> 15287.521 | AJ27: =X27 -> 15343.783 | ... AM27: =AA27 -> 14902.886
B28: Basic EPS | C28: =C24/C27 -> 2.0877582 | D28: =D24/D27 -> 2.3168851 | E28: =E24/E27 -> 3.0033534 | F28: =F24/F27 -> 2.9914458 | G28: =G24/G27 -> 3.3085873 | H28: =H24/H27 -> 5.6690293 | I28: =I24/I27 -> 6.1546144 | J28: =J24/J27 -> 6.1606693 | K28: =K24/K27 -> 6.1090541 | M28: =M24/M27 -> 2.1126515 | N28: =N24/N27 -> 1.5363538 | O28: =O24/O27 -> 1.2028748 | P28: =P24/P27 -> 1.277815 | Q28: =Q24/Q27 -> 1.8875305 | R28: =R24/R27 -> 1.5303582 | S28: =S24/S27 -> 1.2664982 | T28: =T24/T27 -> 1.4580579 | ... AA28: =AA24/AA27 -> 1.5724471 | AC28: =AC24/AC27 -> 5.9883382 | AD28: =AD24/AD27 -> 5.9745411 | AE28: =AE24/AE27 -> 6.0365862 | AF28: =AF24/AF27 -> 6.1606693 | AG28: =AG24/AG27 -> 6.5064179 | AH28: =AH24/AH27 -> 6.5162884 | AI28: =AI24/AI27 -> 6.6692304 | AJ28: =AJ24/AJ27 -> 6.1090541 | ... AM28: =AM24/AM27 -> 6.6617969 | AO28: =SUM(AM28/AI28)-1 -> -0.0011145959
B30: Fully Diluted Shares | C30: 22001.127 | D30: 21006.767 | E30: 20000.436 | F30: 18595.651 | G30: 17528.214 | H30: 16864.919 | I30: 16325.819 | J30: 15812.547 | K30: 15408.095 | M30: 16519.291 | N30: 16403.316 | O30: 16262.203 | P30: =I30 -> 16325.819 | Q30: 15955.718 | R30: 15847.05 | S30: 15775.021 | T30: =J30 -> 15812.547 | U30: 15576.641 | V30: 15464.709 | W30: 15348.175 | X30: =K30 -> 15408.095 | Y30: 15150.865 | Z30: 15056.133 | AA30: 14948.179 | AC30: =Q30 -> 15955.718 | AD30: =R30 -> 15847.05 | AE30: =S30 -> 15775.021 | AF30: =T30 -> 15812.547 | AG30: =U30 -> 15576.641 | AH30: =V30 -> 15464.709 | AI30: =W30 -> 15348.175 | AJ30: =X30 -> 15408.095 | ... AM30: =AA30 -> 14948.179
B31: Diluted EPS | C31: =C24/C30 -> 2.0765754 | D31: =D24/D30 -> 2.3016869 | E31: =E24/E30 -> 2.9764851 | F31: =F24/F30 -> 2.9714475 | G31: =G24/G30 -> 3.275348 | H31: =H24/H30 -> 5.6140204 | I31: =I24/I30 -> 6.1132002 | J31: =J24/J30 -> 6.1340529 | K31: =K24/K30 -> 6.0835554 | M31: =M24/M30 -> 2.0963369 | N31: =N24/N30 -> 1.5246917 | O31: =O24/O30 -> 1.195533 | P31: =P24/P30 -> 1.2692166 | Q31: =Q24/Q30 -> 1.8800784 | R31: =R24/R30 -> 1.524574 | S31: =S24/S30 -> 1.2602836 | T31: =T24/T30 -> 1.4517585 | ... AA31: =AA24/AA30 -> 1.5676826 | AC31: =AC24/AC30 -> 5.9646955 | AD31: =AD24/AD30 -> 5.9519595 | AE31: =AE24/AE30 -> 6.0069651 | AF31: =AF24/AF30 -> 6.1340529 | AG31: =AG24/AG30 -> 6.4784827 | AH31: =AH24/AH30 -> 6.4914898 | AI31: =AI24/AI30 -> 6.6428745 | AJ31: =AJ24/AJ30 -> 6.0835554 | ... AM31: =AM24/AM30 -> 6.6416117 | AO31: =SUM(AM31/AI31)-1 -> -0.00019010064
A33: X | B33: Balance Sheet Statement
B35: Cash/Equivalents | C35: 20484 | D35: 20289 | E35: 25913 | F35: 48844 | G35: 38016 | H35: 34940 | I35: 23646 | J35: 29965 | K35: 29943 | M35: 37119 | N35: 28098 | O35: 27502 | P35: =I35 -> 23646 | Q35: 20535 | R35: 24687 | S35: 28408 | T35: =J35 -> 29965 | U35: 40760 | V35: 32695 | W35: 25565 | X35: =K35 -> 29943 | Y35: 30299 | Z35: 28162 | AA35: 36269 | AC35: =Q35 -> 20535 | AD35: =R35 -> 24687 | AE35: =S35 -> 28408 | AF35: =T35 -> 29965 | AG35: =U35 -> 40760 | AH35: =V35 -> 32695 | AI35: =W35 -> 25565 | AJ35: =X35 -> 29943 | ... AM35: =AA35 -> 36269 | AO35: =SUM(AM35/AI35)-1 -> 0.41869744
B36: Marketable Securities, Current | C36: 46671 | D36: 53892 | E36: 40388 | F36: 51713 | G36: 52927 | H36: 27699 | I36: 24658 | J36: 31590 | K36: 35228 | M36: 26794 | N36: 23413 | O36: 20729 | P36: =I36 -> 24658 | Q36: 30820 | R36: 31185 | S36: 34074 | T36: =J36 -> 31590 | U36: 32340 | V36: 34455 | W36: 36236 | X36: =K36 -> 35228 | Y36: 23476 | Z36: 20336 | AA36: 19103 | AC36: =Q36 -> 30820 | AD36: =R36 -> 31185 | AE36: =S36 -> 34074 | AF36: =T36 -> 31590 | AG36: =U36 -> 32340 | AH36: =V36 -> 34455 | AI36: =W36 -> 36236 | AJ36: =X36 -> 35228 | ... AM36: =AA36 -> 19103 | AO36: =SUM(AM36/AI36)-1 -> -0.47281709
B37: Accounts Receivable | C37: 15754 | D37: 17874 | E37: 23186 | F37: 22926 | G37: 16120 | H37: 26278 | I37: 28184 | J37: 29508 | K37: 66243 | M37: 30213 | N37: 20815 | O37: 21803 | P37: =I37 -> 28184 | Q37: 23752 | R37: 17936 | S37: 19549 | T37: =J37 -> 29508 | U37: 23194 | V37: 21837 | W37: 22795 | X37: =K37 -> 66243 | Y37: 29639 | Z37: 49798 | AA37: 46835 | AC37: =Q37 -> 23752 | AD37: =R37 -> 17936 | AE37: =S37 -> 19549 | AF37: =T37 -> 29508 | AG37: =U37 -> 23194 | AH37: =V37 -> 21837 | AI37: =W37 -> 22795 | AJ37: =X37 -> 66243 | ... AM37: =AA37 -> 46835 | AO37: =SUM(AM37/AI37)-1 -> 1.0546172
B38: Inventory | C38: 2132 | D38: 4855 | E38: 3956 | F38: 4106 | G38: 4061 | H38: 6580 | I38: 4946 | J38: 6331 | K38: 7286 | M38: 5876 | N38: 5460 | O38: 5433 | P38: =I38 -> 4946 | Q38: 6820 | R38: 7482 | S38: 7351 | T38: =J38 -> 6331 | U38: 6511 | V38: 6232 | W38: 6165 | X38: =K38 -> 7286 | Y38: 6911 | Z38: 6269 | AA38: 5925 | AC38: =Q38 -> 6820 | AD38: =R38 -> 7482 | AE38: =S38 -> 7351 | AF38: =T38 -> 6331 | AG38: =U38 -> 6511 | AH38: =V38 -> 6232 | AI38: =W38 -> 6165 | AJ38: =X38 -> 7286 | ... AM38: =AA38 -> 5925 | AO38: =SUM(AM38/AI38)-1 -> -0.03892944
B39: Other Current Assets | C39: 21828 | D39: =13936+17799 -> 31735 | E39: 37896 | F39: 35230 | G39: 32589 | H39: 39339 | I39: 53971 | J39: 46172 | K39: 14287 | M39: 53152 | N39: 40394 | O39: 36825 | P39: =I39 -> 53971 | Q39: 46850 | R39: 31623 | S39: 33277 | T39: =J39 -> 46172 | U39: 40887 | V39: 33197 | W39: 34674 | X39: =K39 -> 14287 | Y39: 42915 | Z39: 14109 | AA39: 14359 | AC39: =Q39 -> 46850 | AD39: =R39 -> 31623 | AE39: =S39 -> 33277 | AF39: =T39 -> 46172 | AG39: =U39 -> 40887 | AH39: =V39 -> 33197 | AI39: =W39 -> 34674 | AJ39: =X39 -> 14287 | ... AM39: =AA39 -> 14359 | AO39: =SUM(AM39/AI39)-1 -> -0.58588568
B40: Total Current Assets | C40: =SUM(C35:C39) -> 106869 | D40: =SUM(D35:D39) -> 128645 | E40: =SUM(E35:E39) -> 131339 | F40: =SUM(F35:F39) -> 162819 | G40: =SUM(G35:G39) -> 143713 | H40: =SUM(H35:H39) -> 134836 | I40: =SUM(I35:I39) -> 135405 | J40: =SUM(J35:J39) -> 143566 | K40: =SUM(K35:K39) -> 152987 | M40: =SUM(M35:M39) -> 153154 | N40: =SUM(N35:N39) -> 118180 | O40: =SUM(O35:O39) -> 112292 | P40: =SUM(P35:P39) -> 135405 | Q40: =SUM(Q35:Q39) -> 128777 | R40: =SUM(R35:R39) -> 112913 | S40: =SUM(S35:S39) -> 122659 | T40: =SUM(T35:T39) -> 143566 | ... AA40: =SUM(AA35:AA39) -> 122491 | AC40: =SUM(AC35:AC39) -> 128777 | AD40: =SUM(AD35:AD39) -> 112913 | AE40: =SUM(AE35:AE39) -> 122659 | AF40: =SUM(AF35:AF39) -> 143566 | AG40: =SUM(AG35:AG39) -> 143692 | AH40: =SUM(AH35:AH39) -> 128416 | AI40: =SUM(AI35:AI39) -> 125435 | AJ40: =SUM(AJ35:AJ39) -> 152987 | ... AM40: =SUM(AM35:AM39) -> 122491 | AO40: =SUM(AM40/AI40)-1 -> -0.023470323
B42: PP&E | C42: 27010 | D42: 33783 | E42: 41304 | F42: 37378 | G42: 36766 | H42: 39440 | I42: 42117 | J42: 43715 | K42: 45680 | M42: 39245 | N42: 39304 | O42: 40335 | P42: =I42 -> 42117 | Q42: 42951 | R42: 43398 | S42: 43550 | T42: =J42 -> 43715 | U42: 43666 | V42: 43546 | W42: 44502 | X42: =K42 -> 45680 | Y42: 46069 | Z42: 46876 | AA42: 48508 | AC42: =Q42 -> 42951 | AD42: =R42 -> 43398 | AE42: =S42 -> 43550 | AF42: =T42 -> 43715 | AG42: =U42 -> 43666 | AH42: =V42 -> 43546 | AI42: =W42 -> 44502 | AJ42: =X42 -> 45680 | ... AM42: =AA42 -> 48508 | AO42: =SUM(AM42/AI42)-1 -> 0.090018426
B43: Marketable Securities, Net of Current Portion | C43: 170430 | D43: 194714 | E43: 170799 | F43: 105341 | G43: 100887 | H43: 127877 | I43: 120805 | J43: 100544 | K43: 91479 | M43: 138683 | N43: 141219 | O43: 131077 | P43: =I43 -> 120805 | Q43: 114095 | R43: 110461 | S43: 104061 | T43: =J43 -> 100544 | U43: 99475 | V43: 95187 | W43: 91240 | X43: =K43 -> 91479 | Y43: 87593 | Z43: 84424 | AA43: 77614 | AC43: =Q43 -> 114095 | AD43: =R43 -> 110461 | AE43: =S43 -> 104061 | AF43: =T43 -> 100544 | AG43: =U43 -> 99475 | AH43: =V43 -> 95187 | AI43: =W43 -> 91240 | AJ43: =X43 -> 91479 | ... AM43: =AA43 -> 77614 | AO43: =SUM(AM43/AI43)-1 -> -0.14934239
B44: Other Assets | C44: =5414+3206+8757 -> 17377 | D44: 18177 | E44: 22283 | F44: 32978 | G44: 42522 | H44: 48849 | I44: 54428 | J44: 64758 | K44: 74834 | M44: 42071 | N44: 43921 | O44: 44567 | P44: =I44 -> 54428 | Q44: 52886 | R44: 57350 | S44: 56730 | T44: =J44 -> 64758 | U44: 58643 | V44: 62224 | W44: 62397 | X44: =K44 -> 74834 | Y44: 77183 | Z44: 81259 | AA44: 82882 | AC44: =Q44 -> 52886 | AD44: =R44 -> 57350 | AE44: =S44 -> 56730 | AF44: =T44 -> 64758 | AG44: =U44 -> 58643 | AH44: =V44 -> 62224 | AI44: =W44 -> 62397 | AJ44: =X44 -> 74834 | ... AM44: =AA44 -> 82882 | AO44: =SUM(AM44/AI44)-1 -> 0.32830104
B45: Total Assets | C45: =SUM(C42:C44)+C40 -> 321686 | D45: =SUM(D42:D44)+D40 -> 375319 | E45: =SUM(E42:E44)+E40 -> 365725 | F45: =SUM(F42:F44)+F40 -> 338516 | G45: =SUM(G42:G44)+G40 -> 323888 | H45: =SUM(H42:H44)+H40 -> 351002 | I45: =SUM(I42:I44)+I40 -> 352755 | J45: =SUM(J42:J44)+J40 -> 352583 | K45: =SUM(K42:K44)+K40 -> 364980 | M45: =SUM(M42:M44)+M40 -> 373153 | N45: =SUM(N42:N44)+N40 -> 342624 | O45: =SUM(O42:O44)+O40 -> 328271 | P45: =SUM(P42:P44)+P40 -> 352755 | Q45: =SUM(Q42:Q44)+Q40 -> 338709 | R45: =SUM(R42:R44)+R40 -> 324122 | S45: =SUM(S42:S44)+S40 -> 327000 | T45: =SUM(T42:T44)+T40 -> 352583 | ... AA45: =SUM(AA42:AA44)+AA40 -> 331495 | AC45: =SUM(AC42:AC44)+AC40 -> 338709 | AD45: =SUM(AD42:AD44)+AD40 -> 324122 | AE45: =SUM(AE42:AE44)+AE40 -> 327000 | AF45: =SUM(AF42:AF44)+AF40 -> 352583 | AG45: =SUM(AG42:AG44)+AG40 -> 345476 | AH45: =SUM(AH42:AH44)+AH40 -> 329373 | AI45: =SUM(AI42:AI44)+AI40 -> 323574 | AJ45: =SUM(AJ42:AJ44)+AJ40 -> 364980 | ... AM45: =SUM(AM42:AM44)+AM40 -> 331495 | AO45: =SUM(AM45/AI45)-1 -> 0.024479717
B47: Accounts Payable | C47: 37294 | D47: 44242 | E47: 55888 | F47: 46236 | G47: 42296 | H47: 54763 | I47: 64115 | J47: 62611 | K47: 68960 | M47: 74362 | N47: 52682 | O47: 48343 | P47: =I47 -> 64115 | Q47: 57918 | R47: 42945 | S47: 46699 | T47: =J47 -> 62611 | U47: 58146 | V47: 45753 | W47: 47574 | X47: =K47 -> 68960 | Y47: 61910 | Z47: 54126 | AA47: 50374 | AC47: =Q47 -> 57918 | AD47: =R47 -> 42945 | AE47: =S47 -> 46699 | AF47: =T47 -> 62611 | AG47: =U47 -> 58146 | AH47: =V47 -> 45753 | AI47: =W47 -> 47574 | AJ47: =X47 -> 68960 | ... AM47: =AA47 -> 50374 | AO47: =SUM(AM47/AI47)-1 -> 0.058855677
B48: Deferred Revenue - Current | C48: 8080 | D48: 7548 | E48: 7543 | F48: 5522 | G48: 6643 | H48: 7612 | I48: 7912 | J48: 8061 | K48: 8249 | M48: 7876 | N48: 7920 | O48: 7728 | P48: =I48 -> 7912 | Q48: 7992 | R48: 8131 | S48: 8158 | T48: =J48 -> 8061 | U48: 8264 | V48: 8012 | W48: 8053 | X48: =K48 -> 8249 | Y48: 8461 | Z48: 8976 | AA48: 8979 | AC48: =Q48 -> 7992 | AD48: =R48 -> 8131 | AE48: =S48 -> 8158 | AF48: =T48 -> 8061 | AG48: =U48 -> 8264 | AH48: =V48 -> 8012 | AI48: =W48 -> 8053 | AJ48: =X48 -> 8249 | ... AM48: =AA48 -> 8979 | AO48: =SUM(AM48/AI48)-1 -> 0.1149882
B49: Other Current Liabilities (accrued exp) | C49: 22027 | D49: 30551 | E49: 32687 | F49: 37720 | G49: 42684 | H49: 47493 | I49: 60845 | J49: 58829 | K49: 78304 | M49: 49167 | N49: 50248 | O49: 48811 | P49: =I49 -> 60845 | Q49: 59893 | R49: 56425 | S49: 58897 | T49: =J49 -> 58829 | U49: 54611 | V49: 57298 | W49: 60889 | X49: =K49 -> 78304 | Y49: 61151 | Z49: 61849 | AA49: 62499 | AC49: =Q49 -> 59893 | AD49: =R49 -> 56425 | AE49: =S49 -> 58897 | AF49: =T49 -> 58829 | AG49: =U49 -> 54611 | AH49: =V49 -> 57298 | AI49: =W49 -> 60889 | AJ49: =X49 -> 78304 | ... AM49: =AA49 -> 62499 | AO49: =SUM(AM49/AI49)-1 -> 0.026441558
B50: Commerical Paper | C50: 8105 | D50: 11977 | E50: 11964 | F50: 5980 | G50: 4996 | H50: 6000 | I50: 9982 | J50: 5985 | K50: 9967 | M50: 5000 | N50: 6999 | O50: 10982 | P50: 9982 | Q50: 1743 | R50: 1996 | S50: 3993 | T50: 5985 | U50: 1998 | V50: 1997 | W50: 2994 | X50: 9967 | Y50: 1995 | Z50: 5982 | AA50: 9923 | AI50: =W50 -> 2994 | AJ50: =X50 -> 9967 | AK50: =Y50 -> 1995 | AL50: =Z50 -> 5982 | AM50: =AA50 -> 9923
B51: Term Debt, Current Portion | C51: 3500 | D51: 6496 | E51: 8784 | F51: 10260 | G51: 8773 | H51: 9613 | I51: 11128 | J51: 9822 | K51: 10912 | M51: 11169 | N51: 9659 | O51: 14009 | P51: 11128 | Q51: 9740 | R51: 10578 | S51: 7216 | T51: 9822 | U51: 10954 | V51: 10762 | W51: 12114 | X51: 10912 | Y51: 10848 | Z51: 13638 | AA51: 9345 | AC51: =Q51 -> 9740 | AD51: =R51 -> 10578 | AE51: =S51 -> 7216 | AF51: =T51 -> 9822 | AG51: =U51 -> 10954 | AH51: =V51 -> 10762 | AI51: =W51 -> 12114 | AJ51: =X51 -> 10912 | ... AM51: =AA51 -> 9345 | AO51: =SUM(AM51/AI51)-1 -> -0.2285785
B52: Total Current Liabilities | C52: =SUM(C47:C51) -> 79006 | D52: =SUM(D47:D51) -> 100814 | E52: =SUM(E47:E51) -> 116866 | F52: =SUM(F47:F51) -> 105718 | G52: =SUM(G47:G51) -> 105392 | H52: =SUM(H47:H51) -> 125481 | I52: =SUM(I47:I51) -> 153982 | J52: =SUM(J47:J51) -> 145308 | K52: =SUM(K47:K51) -> 176392 | M52: =SUM(M47:M51) -> 147574 | N52: =SUM(N47:N51) -> 127508 | O52: =SUM(O47:O51) -> 129873 | P52: =SUM(P47:P51) -> 153982 | Q52: =SUM(Q47:Q51) -> 137286 | R52: =SUM(R47:R51) -> 120075 | S52: =SUM(S47:S51) -> 124963 | T52: =SUM(T47:T51) -> 145308 | ... AA52: =SUM(AA47:AA51) -> 141120 | AC52: =SUM(AC47:AC51) -> 135543 | AD52: =SUM(AD47:AD51) -> 118079 | AE52: =SUM(AE47:AE51) -> 120970 | AF52: =SUM(AF47:AF51) -> 139323 | AG52: =SUM(AG47:AG51) -> 131975 | AH52: =SUM(AH47:AH51) -> 121825 | AI52: =SUM(AI47:AI51) -> 131624 | AJ52: =SUM(AJ47:AJ51) -> 176392 | ... AM52: =SUM(AM47:AM51) -> 141120 | AO52: =SUM(AM52/AI52)-1 -> 0.072144898
B54: Long-Term Debt | C54: 75427 | D54: 97207 | E54: 93735 | F54: 91807 | G54: 98667 | H54: 109106 | I54: 98959 | J54: 95281 | K54: 85750 | M54: 106629 | N54: 103323 | O54: 94700 | P54: =I54 -> 98959 | Q54: 99627 | R54: 97041 | S54: 98071 | T54: =J54 -> 95281 | U54: 95088 | V54: 91831 | W54: 86196 | X54: =K54 -> 85750 | Y54: 83956 | Z54: 78566 | AA54: 82430 | AC54: =Q54 -> 99627 | AD54: =R54 -> 97041 | AE54: =S54 -> 98071 | AF54: =T54 -> 95281 | AG54: =U54 -> 95088 | AH54: =V54 -> 91831 | AI54: =W54 -> 86196 | AJ54: =X54 -> 85750 | ... AM54: =AA54 -> 82430 | AO54: =SUM(AM54/AI54)-1 -> -0.043691123
B55: Deferred Revenue - Non-Current | C55: 2930 | D55: 2836 | E55: 2797 | F55: 0 | G55: 0 | H55: 0 | I55: 0 | J55: 0 | K55: 0 | M55: 0 | N55: 0 | O55: 0 | P55: =I55 -> 0 | Q55: 0 | R55: 0 | S55: 0 | T55: =J55 -> 0 | U55: 0 | V55: 0 | W55: 0 | X55: =K55 -> 0 | Y55: 0 | Z55: 0 | AA55: 0 | AC55: =Q55 -> 0 | AD55: =R55 -> 0 | AE55: =S55 -> 0 | AF55: =T55 -> 0 | AG55: =U55 -> 0 | AH55: =V55 -> 0 | AI55: =W55 -> 0 | AJ55: =X55 -> 0 | ... AM55: =AA55 -> 0
B56: Other Non-Current Liabilities | C56: 36074 | D56: 40415 | E56: 45180 | F56: 50503 | G56: 54490 | H56: 53325 | I56: 49142 | J56: 49848 | K56: 45888 | M56: 55056 | N56: 52432 | O56: 53629 | P56: =I56 -> 49142 | Q56: 53107 | R56: 52886 | S56: 51730 | T56: =J56 -> 49848 | U56: 50353 | V56: 47564 | W56: 47084 | X56: =K56 -> 45888 | Y56: 49006 | Z56: 41300 | AA56: 42115 | AC56: =Q56 -> 53107 | AD56: =R56 -> 52886 | AE56: =S56 -> 51730 | AF56: =T56 -> 49848 | AG56: =U56 -> 50353 | AH56: =V56 -> 47564 | AI56: =W56 -> 47084 | AJ56: =X56 -> 45888 | ... AM56: =AA56 -> 42115 | AO56: =SUM(AM56/AI56)-1 -> -0.10553479
B57: Total Liabilities | C57: =SUM(C54:C56)+C52 -> 193437 | D57: =SUM(D54:D56)+D52 -> 241272 | E57: =SUM(E54:E56)+E52 -> 258578 | F57: =SUM(F54:F56)+F52 -> 248028 | G57: =SUM(G54:G56)+G52 -> 258549 | H57: =SUM(H54:H56)+H52 -> 287912 | I57: =SUM(I54:I56)+I52 -> 302083 | J57: =SUM(J54:J56)+J52 -> 290437 | K57: =SUM(K54:K56)+K52 -> 308030 | M57: =SUM(M54:M56)+M52 -> 309259 | N57: =SUM(N54:N56)+N52 -> 283263 | O57: =SUM(O54:O56)+O52 -> 278202 | P57: =SUM(P54:P56)+P52 -> 302083 | Q57: =SUM(Q54:Q56)+Q52 -> 290020 | R57: =SUM(R54:R56)+R52 -> 270002 | S57: =SUM(S54:S56)+S52 -> 274764 | T57: =SUM(T54:T56)+T52 -> 290437 | ... AA57: =SUM(AA54:AA56)+AA52 -> 265665 | AC57: =SUM(AC54:AC56)+AC52 -> 288277 | AD57: =SUM(AD54:AD56)+AD52 -> 268006 | AE57: =SUM(AE54:AE56)+AE52 -> 270771 | AF57: =SUM(AF54:AF56)+AF52 -> 284452 | AG57: =SUM(AG54:AG56)+AG52 -> 277416 | AH57: =SUM(AH54:AH56)+AH52 -> 261220 | AI57: =SUM(AI54:AI56)+AI52 -> 264904 | AJ57: =SUM(AJ54:AJ56)+AJ52 -> 308030 | ... AM57: =SUM(AM54:AM56)+AM52 -> 265665 | AO57: =SUM(AM57/AI57)-1 -> 0.0028727388
B59: Common Stock | C59: 31251 | D59: 35867 | E59: 40201 | F59: 45174 | G59: 50779 | H59: 57365 | I59: 64849 | J59: 73812 | K59: 83276 | M59: 58424 | N59: 61181 | O59: 62115 | P59: =I59 -> 64849 | Q59: 66399 | R59: 69568 | S59: 70667 | T59: =J59 -> 73812 | U59: 75236 | V59: 75236 | W59: 79850 | X59: =K59 -> 83276 | Y59: 84768 | Z59: 88711 | AA59: 89806 | AC59: =Q59 -> 66399 | AD59: =R59 -> 69568 | AE59: =S59 -> 70667 | AF59: =T59 -> 73812 | AG59: =U59 -> 75236 | AH59: =V59 -> 75236 | AI59: =W59 -> 79850 | AJ59: =X59 -> 83276 | ... AM59: =AA59 -> 89806 | AO59: =SUM(AM59/AI59)-1 -> 0.12468378
B60: Retained Earnings (Deficit) | C60: 96364 | D60: 98330 | E60: 70400 | F60: 45898 | G60: 14966 | H60: 5562 | I60: -3068 | J60: -214 | K60: -19154 | M60: 6397 | N60: 4674 | O60: -2749 | P60: =I60 -> -3068 | Q60: -4798 | R60: -3702 | S60: -6630 | T60: =J60 -> -214 | U60: 204 | V60: -120 | W60: -12764 | X60: =K60 -> -19154 | Y60: -11221 | Z60: -15552 | AA60: -17613 | AC60: =Q60 -> -4798 | AD60: =R60 -> -3702 | AE60: =S60 -> -6630 | AF60: =T60 -> -214 | AG60: =U60 -> 204 | AH60: =V60 -> -120 | AI60: =W60 -> -12764 | AJ60: =X60 -> -19154 | ... AM60: =AA60 -> -17613 | AO60: =SUM(AM60/AI60)-1 -> 0.37989658
B61: Accumulated Other comprehensive income | C61: 634 | D61: -150 | E61: -3454 | F61: -584 | G61: -406 | H61: 163 | I61: -11109 | J61: -11452 | K61: -7172 | M61: -927 | N61: -6494 | O61: -9297 | P61: =I61 -> -11109 | Q61: -12912 | R61: -11746 | S61: -11801 | T61: =J61 -> -11452 | U61: -9378 | V61: -8960 | W61: -8416 | X61: =K61 -> -7172 | Y61: -6789 | Z61: -6363 | AA61: -6363 | AC61: =Q61 -> -12912 | AD61: =R61 -> -11746 | AE61: =S61 -> -11801 | AF61: =T61 -> -11452 | AG61: =U61 -> -9378 | AH61: =V61 -> -8960 | AI61: =W61 -> -8416 | AJ61: =X61 -> -7172 | ... AM61: =AA61 -> -6363 | AO61: =SUM(AM61/AI61)-1 -> -0.24394011
B62: Total stockholders' equity | C62: =SUM(C59:C61) -> 128249 | D62: =SUM(D59:D61) -> 134047 | E62: =SUM(E59:E61) -> 107147 | F62: =SUM(F59:F61) -> 90488 | G62: =SUM(G59:G61) -> 65339 | H62: =SUM(H59:H61) -> 63090 | I62: =SUM(I59:I61) -> 50672 | J62: =SUM(J59:J61) -> 62146 | K62: =SUM(K59:K61) -> 56950 | M62: =SUM(M59:M61) -> 63894 | N62: =SUM(N59:N61) -> 59361 | O62: =SUM(O59:O61) -> 50069 | P62: =SUM(P59:P61) -> 50672 | Q62: =SUM(Q59:Q61) -> 48689 | R62: =SUM(R59:R61) -> 54120 | S62: =SUM(S59:S61) -> 52236 | T62: =SUM(T59:T61) -> 62146 | ... AA62: =SUM(AA59:AA61) -> 65830 | AC62: =SUM(AC59:AC61) -> 48689 | AD62: =SUM(AD59:AD61) -> 54120 | AE62: =SUM(AE59:AE61) -> 52236 | AF62: =SUM(AF59:AF61) -> 62146 | AG62: =SUM(AG59:AG61) -> 66062 | AH62: =SUM(AH59:AH61) -> 66156 | AI62: =SUM(AI59:AI61) -> 58670 | AJ62: =SUM(AJ59:AJ61) -> 56950 | ... AM62: =SUM(AM59:AM61) -> 65830 | AO62: =SUM(AM62/AI62)-1 -> 0.12203852
B63: Total liabilities and stockholders' equity | C63: =SUM(C62+C57) -> 321686 | D63: =SUM(D62+D57) -> 375319 | E63: =SUM(E62+E57) -> 365725 | F63: =SUM(F62+F57) -> 338516 | G63: =SUM(G62+G57) -> 323888 | H63: =SUM(H62+H57) -> 351002 | I63: =SUM(I62+I57) -> 352755 | J63: =SUM(J62+J57) -> 352583 | K63: =SUM(K62+K57) -> 364980 | M63: =SUM(M62+M57) -> 373153 | N63: =SUM(N62+N57) -> 342624 | O63: =SUM(O62+O57) -> 328271 | P63: =SUM(P62+P57) -> 352755 | Q63: =SUM(Q62+Q57) -> 338709 | R63: =SUM(R62+R57) -> 324122 | S63: =SUM(S62+S57) -> 327000 | T63: =SUM(T62+T57) -> 352583 | ... AA63: =SUM(AA62+AA57) -> 331495 | AC63: =SUM(AC62+AC57) -> 336966 | AD63: =SUM(AD62+AD57) -> 322126 | AE63: =SUM(AE62+AE57) -> 323007 | AF63: =SUM(AF62+AF57) -> 346598 | AG63: =SUM(AG62+AG57) -> 343478 | AH63: =SUM(AH62+AH57) -> 327376 | AI63: =SUM(AI62+AI57) -> 323574 | AJ63: =SUM(AJ62+AJ57) -> 364980 | ... AM63: =SUM(AM62+AM57) -> 331495 | AO63: =SUM(AM63/AI63)-1 -> 0.024479717
B65: Balance Check | C65: =C63-C45 -> 0 | D65: =D63-D45 -> 0 | E65: =E63-E45 -> 0 | F65: =F63-F45 -> 0 | G65: =G63-G45 -> 0 | H65: =H63-H45 -> 0 | I65: =I63-I45 -> 0 | J65: =J63-J45 -> 0 | K65: =K63-K45 -> 0 | M65: =M63-M45 -> 0 | N65: =N63-N45 -> 0 | O65: =O63-O45 -> 0 | P65: =P63-P45 -> 0 | Q65: =Q63-Q45 -> 0 | R65: =R63-R45 -> 0 | S65: =S63-S45 -> 0 | T65: =T63-T45 -> 0 | ... AA65: =AA63-AA45 -> 0 | AC65: =AC63-AC45 -> -1743 | AD65: =AD63-AD45 -> -1996 | AE65: =AE63-AE45 -> -3993 | AF65: =AF63-AF45 -> -5985 | AG65: =AG63-AG45 -> -1998 | AH65: =AH63-AH45 -> -1997 | AI65: =AI63-AI45 -> 0 | AJ65: =AJ63-AJ45 -> 0 | ... AM65: =AM63-AM45 -> 0
A67: X | B67: Cash-Flows Statement
B69: Cash-Flows From Operating Activities
B70: Net income (loss) | C70: =C24 -> 45687 | D70: =D24 -> 48351 | E70: =E24 -> 59531 | F70: =F24 -> 55256 | G70: =G24 -> 57411 | H70: =H24 -> 94680 | I70: =I24 -> 99803 | J70: =J24 -> 96995 | K70: =K24 -> 93736 | M70: =M24 -> 34630 | N70: =N24 -> 25010 | O70: =O24 -> 19442 | P70: =P24 -> 20721 | Q70: =Q24 -> 29998 | R70: =R24 -> 24160 | S70: =S24 -> 19881 | T70: =T24 -> 22956 | ... AA70: =AA24 -> 23434 | AC70: =SUM(N70:Q70) -> 95171 | AD70: =SUM(O70:R70) -> 94321 | AE70: =SUM(P70:S70) -> 94760 | AF70: =SUM(Q70:T70) -> 96995 | AG70: =SUM(R70:U70) -> 100913 | AH70: =SUM(S70:V70) -> 100389 | AI70: =SUM(T70:W70) -> 101956 | AJ70: =SUM(U70:X70) -> 93736 | ... AM70: =SUM(X70:AA70) -> 99280 | AO70: =SUM(AM70/AI70)-1 -> -0.026246616
B72: Adjustments to reconcile net income: | AO72: =SUM(AM72/AI72)-1 -> #DIV/0!
B73: Depreciation and Amortization | C73: 10505 | D73: 10157 | E73: 10903 | F73: 12547 | G73: 11056 | H73: 11284 | I73: 11104 | J73: 11519 | K73: 11445 | M73: 2697 | N73: =5434-M73 -> 2737 | O73: =8239-SUM(M73:N73) -> 2805 | P73: =SUM(I73-SUM(M73:O73)) -> 2865 | Q73: 2916 | R73: =5814-Q73 -> 2898 | S73: 3052 | T73: =SUM(J73-SUM(Q73:S73)) -> 2653 | U73: 2848 | V73: =5684-U73 -> 2836 | W73: =8534-V73-U73 -> 2850 | X73: =SUM(K73-SUM(U73:W73)) -> 2911 | Y73: 3080 | Z73: =5741-Y73 -> 2661 | AA73: =8571-Z73-Y73 -> 2830 | AC73: =SUM(N73:Q73) -> 11323 | AD73: =SUM(O73:R73) -> 11484 | AE73: =SUM(P73:S73) -> 11731 | AF73: =SUM(Q73:T73) -> 11519 | AG73: =SUM(R73:U73) -> 11451 | AH73: =SUM(S73:V73) -> 11389 | AI73: =SUM(T73:W73) -> 11187 | AJ73: =SUM(U73:X73) -> 11445 | ... AM73: =SUM(X73:AA73) -> 11482 | AO73: =SUM(AM73/AI73)-1 -> 0.026369894
B74: Stock Based Compensation | C74: 4210 | D74: 4840 | E74: 5340 | F74: 6068 | G74: 6829 | H74: 7906 | I74: 9038 | J74: 10833 | K74: 11688 | M74: 2265 | N74: =4517-M74 -> 2252 | O74: =6760-SUM(M74:N74) -> 2243 | P74: =SUM(I74-SUM(M74:O74)) -> 2278 | Q74: 2905 | R74: =5591-Q74 -> 2686 | S74: 2617 | T74: =SUM(J74-SUM(Q74:S74)) -> 2625 | U74: 2997 | V74: =5961-U74+3 -> 2967 | W74: =8830-V74-U74 -> 2866 | X74: =SUM(K74-SUM(U74:W74)) -> 2858 | Y74: 3286 | Z74: =6512-Y74 -> 3226 | AA74: =9680-Z74-Y74 -> 3168 | AC74: =SUM(N74:Q74) -> 9678 | AD74: =SUM(O74:R74) -> 10112 | AE74: =SUM(P74:S74) -> 10486 | AF74: =SUM(Q74:T74) -> 10833 | AG74: =SUM(R74:U74) -> 10925 | AH74: =SUM(S74:V74) -> 11206 | AI74: =SUM(T74:W74) -> 11455 | AJ74: =SUM(U74:X74) -> 11688 | ... AM74: =SUM(X74:AA74) -> 12538 | AO74: =SUM(AM74/AI74)-1 -> 0.094543867
B75: Deferred Taxes | C75: 4938 | D75: 5966 | E75: -32590 | F75: -340 | G75: -215 | H75: -4774 | I75: 895 | J75: 0 | K75: 0 | M75: 682 | N75: =1088-M75 -> 406 | O75: =2756-SUM(M75:N75) -> 1668 | P75: =SUM(I75-SUM(M75:O75)) -> -1861 | Q75: 0 | R75: =Q75 -> 0 | S75: 0 | T75: =SUM(J75-SUM(Q75:S75)) -> 0 | U75: =T75 -> 0 | V75: 0 | W75: 0 | X75: =SUM(K75-SUM(U75:W75)) -> 0 | Y75: =X75 -> 0 | Z75: =Y75 -> 0 | AA75: 0 | AC75: =SUM(N75:Q75) -> 213 | AD75: =SUM(O75:R75) -> -193 | AE75: =SUM(P75:S75) -> -1861 | AF75: =SUM(Q75:T75) -> 0 | AG75: =SUM(R75:U75) -> 0 | AH75: =SUM(S75:V75) -> 0 | AI75: =SUM(T75:W75) -> 0 | AJ75: =SUM(U75:X75) -> 0 | ... AM75: =SUM(X75:AA75) -> 0 | AO75: =SUM(AM75/AI75)-1 -> #DIV/0!
B76: Other - Loss on disposition of PPE | C76: 0 | D76: -166 | E76: -444 | F76: -652 | G76: -97 | H76: -147 | I76: 111 | J76: -2227 | K76: -2266 | M76: 167 | N76: =-20-M76 -> -187 | O76: =-61-SUM(M76:N76) -> -41 | P76: =SUM(I76-SUM(M76:O76)) -> 172 | Q76: -317 | R76: =-1732-Q76 -> -1415 | S76: 81 | T76: =SUM(J76-SUM(Q76:S76)) -> -576 | U76: -989 | V76: =-1971-U76 -> -982 | W76: =-1964-V76-U76 -> 7 | X76: =SUM(K76-SUM(U76:W76)) -> -302 | Y76: -2009 | Z76: =-2217-Y76 -> -208 | AA76: =-1748-Z76-Y76 -> 469 | AC76: =SUM(N76:Q76) -> -373 | AD76: =SUM(O76:R76) -> -1601 | AE76: =SUM(P76:S76) -> -1479 | AF76: =SUM(Q76:T76) -> -2227 | AG76: =SUM(R76:U76) -> -2899 | AH76: =SUM(S76:V76) -> -2466 | AI76: =SUM(T76:W76) -> -2540 | AJ76: =SUM(U76:X76) -> -2266 | ... AM76: =SUM(X76:AA76) -> -2050 | AO76: =SUM(AM76/AI76)-1 -> -0.19291339
B78: Changes in assets and liabilities: | AO78: =SUM(AM78/AI78)-1 -> #DIV/0!
B79: Accounts Receivable | C79: 1095 | D79: -2093 | E79: -5322 | F79: 245 | G79: 6917 | H79: -10125 | I79: -1823 | J79: -1688 | K79: -3788 | M79: -3934 | N79: =5542-M79 -> 9476 | O79: =4561-SUM(M79:N79) -> -981 | P79: =SUM(I79-SUM(M79:O79)) -> -6384 | Q79: 4275 | R79: =9596-Q79 -> 5321 | S79: -1987 | T79: =SUM(J79-SUM(Q79:S79)) -> -9297 | U79: 6555 | V79: =7727-U79 -> 1172 | W79: =6697-V79-U79 -> -1030 | X79: =SUM(K79-SUM(U79:W79)) -> -10485 | Y79: 3597 | Z79: =7266-Y79 -> 3669 | AA79: =5685-Z79-Y79 -> -1581 | AC79: =SUM(N79:Q79) -> 6386 | AD79: =SUM(O79:R79) -> 2231 | AE79: =SUM(P79:S79) -> 1225 | AF79: =SUM(Q79:T79) -> -1688 | AG79: =SUM(R79:U79) -> 592 | AH79: =SUM(S79:V79) -> -3557 | AI79: =SUM(T79:W79) -> -2600 | AJ79: =SUM(U79:X79) -> -3788 | ... AM79: =SUM(X79:AA79) -> -4800 | AO79: =SUM(AM79/AI79)-1 -> 0.84615385
B80: Inventory | C80: 217 | D80: -2723 | E80: 828 | F80: -289 | G80: -127 | H80: -2642 | I80: 1484 | J80: -1618 | K80: -1046 | M80: 681 | N80: =1065-M80 -> 384 | O80: =1049-SUM(M80:N80) -> -16 | P80: =SUM(I80-SUM(M80:O80)) -> 435 | Q80: -1807 | R80: =-2548-Q80 -> -741 | S80: -22 | T80: =SUM(J80-SUM(Q80:S80)) -> 952 | U80: -137 | V80: =53-U80 -> 190 | W80: =41-V80-U80 -> -12 | X80: =SUM(K80-SUM(U80:W80)) -> -1087 | Y80: 215 | Z80: =858-Y80 -> 643 | AA80: =1223-Z80-Y80 -> 365 | AC80: =SUM(N80:Q80) -> -1004 | AD80: =SUM(O80:R80) -> -2129 | AE80: =SUM(P80:S80) -> -2135 | AF80: =SUM(Q80:T80) -> -1618 | AG80: =SUM(R80:U80) -> 52 | AH80: =SUM(S80:V80) -> 983 | AI80: =SUM(T80:W80) -> 993 | AJ80: =SUM(U80:X80) -> -1046 | ... AM80: =SUM(X80:AA80) -> 136 | AO80: =SUM(AM80/AI80)-1 -> -0.86304129
B81: Other Current Assets | C81: 1039 | D81: -9572 | E81: -8433 | F81: 3804 | G81: -8035 | H81: -11945 | I81: -14019 | J81: -4413 | K81: -13087 | M81: =-9812-4921 -> -14733 | N81: =643-3542-M81 -> 11834 | O81: =4789-3289-SUM(M81:N81) -> 4399 | P81: =SUM(I81-SUM(M81:O81)) -> -15519 | Q81: =-4099+2320 -> -1779 | R81: =14785-4092-Q81 -> 12472 | S81: -2445 | T81: =SUM(J81-SUM(Q81:S81)) -> -12661 | U81: =4569-1457 -> 3112 | V81: =12161-4438-U81 -> 4611 | W81: =11100-5626-V81-U81 -> -2249 | X81: =SUM(K81-SUM(U81:W81)) -> -18561 | Y81: 4105 | Z81: =9171+-4371-Y81 -> 695 | AA81: =13555+-6116-Z81-Y81 -> 2639 | AC81: =SUM(N81:Q81) -> -1065 | AD81: =SUM(O81:R81) -> -427 | AE81: =SUM(P81:S81) -> -7271 | AF81: =SUM(Q81:T81) -> -4413 | AG81: =SUM(R81:U81) -> 478 | AH81: =SUM(S81:V81) -> -7383 | AI81: =SUM(T81:W81) -> -7187 | AJ81: =SUM(U81:X81) -> -13087 | ... AM81: =SUM(X81:AA81) -> -11122 | AO81: =SUM(AM81/AI81)-1 -> 0.54751635
B82: Accounts Payable | C82: 1791 | D82: 9618 | E82: 9175 | F82: -1923 | G82: -4062 | H82: 12326 | I82: 9448 | J82: -1889 | K82: 6020 | M82: 19813 | N82: =-1750-M82 -> -21563 | O82: =-6108-SUM(M82:N82) -> -4358 | P82: =SUM(I82-SUM(M82:O82)) -> 15556 | Q82: -6075 | R82: =-20764-Q82 -> -14689 | S82: 3974 | T82: =SUM(J82-SUM(Q82:S82)) -> 14901 | U82: -4542 | V82: =-16710-U82 -> -12168 | W82: =-15171-V82-U82 -> 1539 | X82: =SUM(K82-SUM(U82:W82)) -> 21191 | Y82: -6671 | Z82: =-14604-Y82 -> -7933 | AA82: =-18479-Z82-Y82 -> -3875 | AC82: =SUM(N82:Q82) -> -16440 | AD82: =SUM(O82:R82) -> -9566 | AE82: =SUM(P82:S82) -> -1234 | AF82: =SUM(Q82:T82) -> -1889 | AG82: =SUM(R82:U82) -> -356 | AH82: =SUM(S82:V82) -> 2165 | AI82: =SUM(T82:W82) -> -270 | AJ82: =SUM(U82:X82) -> 6020 | ... AM82: =SUM(X82:AA82) -> 2712 | AO82: =SUM(AM82/AI82)-1 -> -11.044444
B83: Deferred Revenue | C83: -1554 | D83: -626 | E83: -44 | F83: -625 | G83: 2081 | H83: 1676 | I83: 478 | J83: 0 | K83: 0 | M83: 462 | N83: =627-M83 -> 165 | O83: =260-SUM(M83:N83) -> -367 | P83: =SUM(I83-SUM(M83:O83)) -> 218 | Q83: 131 | R83: =0-Q83 -> -131 | S83: 0 | T83: =SUM(J83-SUM(Q83:S83)) -> 0 | U83: 0 | V83: 0 | W83: 0 | X83: =SUM(K83-SUM(U83:W83)) -> 0 | Y83: 0 | AA83: 0 | AC83: =SUM(N83:Q83) -> 147 | AD83: =SUM(O83:R83) -> -149 | AE83: =SUM(P83:S83) -> 218 | AF83: =SUM(Q83:T83) -> 0 | AG83: =SUM(R83:U83) -> -131 | AH83: =SUM(S83:V83) -> 0 | AI83: =SUM(T83:W83) -> 0 | AJ83: =SUM(U83:X83) -> 0 | ... AM83: =SUM(X83:AA83) -> 0 | AO83: =SUM(AM83/AI83)-1 -> #DIV/0!
B84: Other Asset and Other Liabilities | C84: -2104 | D84: -154 | E84: 38490 | F84: -4700 | G84: 8916 | H84: 5799 | I84: 5632 | J84: 3031 | K84: 15552 | M84: 4236 | N84: =1888-M84 -> -2348 | O84: =-14-SUM(M84:N84) -> -1902 | P84: =SUM(I84-SUM(M84:O84)) -> 5646 | Q84: 3758 | R84: =1757-Q84 -> -2001 | S84: 1229 | T84: =SUM(J84-SUM(Q84:S84)) -> 45 | U84: -3865 | V84: =-3437-U84 -> 428 | W84: =2-V84-U84 -> 3439 | X84: =SUM(K84-SUM(U84:W84)) -> 15550 | Y84: -11998 | Z84: =-15579-Y84 -> -3581 | AA84: =-15161-Z84-Y84 -> 418 | AC84: =SUM(N84:Q84) -> 5154 | AD84: =SUM(O84:R84) -> 5501 | AE84: =SUM(P84:S84) -> 8632 | AF84: =SUM(Q84:T84) -> 3031 | AG84: =SUM(R84:U84) -> -4592 | AH84: =SUM(S84:V84) -> -2163 | AI84: =SUM(T84:W84) -> 47 | AJ84: =SUM(U84:X84) -> 15552 | ... AM84: =SUM(X84:AA84) -> 389 | AO84: =SUM(AM84/AI84)-1 -> 7.2765957
B85: Net cash used in operating activities | C85: =SUM(C70:C84) -> 65824 | D85: =SUM(D70:D84) -> 63598 | E85: =SUM(E70:E84) -> 77434 | F85: =SUM(F70:F84) -> 69391 | G85: =SUM(G70:G84) -> 80674 | H85: =SUM(H70:H84) -> 104038 | I85: =SUM(I70:I84) -> 122151 | J85: =SUM(J70:J84) -> 110543 | K85: =SUM(K70:K84) -> 118254 | M85: =SUM(M70:M84) -> 46966 | N85: =SUM(N70:N84) -> 28166 | O85: =SUM(O70:O84) -> 22892 | P85: =SUM(P70:P84) -> 24127 | Q85: =SUM(Q70:Q84) -> 34005 | R85: =SUM(R70:R84) -> 28560 | S85: =SUM(S70:S84) -> 26380 | T85: =SUM(T70:T84) -> 21598 | ... AA85: =SUM(AA70:AA84) -> 27867 | AC85: =SUM(AC70:AC84) -> 109190 | AD85: =SUM(AD70:AD84) -> 109584 | AE85: =SUM(AE70:AE84) -> 113072 | AF85: =SUM(AF70:AF84) -> 110543 | AG85: =SUM(AG70:AG84) -> 116433 | AH85: =SUM(AH70:AH84) -> 110563 | AI85: =SUM(AI70:AI84) -> 113041 | AJ85: =SUM(AJ70:AJ84) -> 118254 | ... AM85: =SUM(AM70:AM84) -> 108565 | AO85: =SUM(AM85/AI85)-1 -> -0.039596253
B87: Cash flows from investing activities:
B88: Capital Expenditures | C88: -12734 | D88: -12451 | E88: -13313 | F88: -10495 | G88: -7309 | H88: -11085 | I88: -10708 | J88: -10959 | K88: -9447 | M88: -2803 | N88: =-5317-M88 -> -2514 | O88: =-7419-SUM(M88:N88) -> -2102 | P88: =SUM(I88-SUM(M88:O88)) -> -3289 | Q88: -3787 | R88: =-6703-Q88 -> -2916 | S88: -2093 | T88: =SUM(J88-SUM(Q88:S88)) -> -2163 | U88: -2392 | V88: =-4388-U88 -> -1996 | W88: =-6539-V88-U88 -> -2151 | X88: =SUM(K88-SUM(U88:W88)) -> -2908 | Y88: -2940 | Z88: =-6011-Y88 -> -3071 | AA88: =-9473-Z88-Y88 -> -3462 | AC88: =SUM(N88:Q88) -> -11692 | AD88: =SUM(O88:R88) -> -12094 | AE88: =SUM(P88:S88) -> -12085 | AF88: =SUM(Q88:T88) -> -10959 | AG88: =SUM(R88:U88) -> -9564 | AH88: =SUM(S88:V88) -> -8644 | AI88: =SUM(T88:W88) -> -8702 | AJ88: =SUM(U88:X88) -> -9447 | ... AM88: =SUM(X88:AA88) -> -12381 | AO88: =SUM(AM88/AI88)-1 -> 0.42277637
B89: Proceeds of investments | C89: 111794 | D89: 126339 | E89: 103719 | F89: 97090 | G89: 120391 | H89: 106483 | I89: 67363 | J89: 45514 | K89: 62346 | M89: =11309+10675 -> 21984 | N89: =18000+24668-M89 -> 20684 | O89: =24203+33609-SUM(M89:N89) -> 15144 | P89: =SUM(I89-SUM(M89:O89)) -> 9551 | Q89: =7127+509 -> 7636 | R89: =17124+1897-Q89 -> 11385 | S89: 12795 | T89: =SUM(J89-SUM(Q89:S89)) -> 13698 | U89: =13046+1337 -> 14383 | V89: =27462+4314-U89 -> 17393 | W89: =39838+7382-V89-U89 -> 15444 | X89: =SUM(K89-SUM(U89:W89)) -> 15126 | Y89: 19459 | Z89: =26587+5210-Y89 -> 12338 | AA89: =35036+10785-Z89-Y89 -> 14024 | AC89: =SUM(N89:Q89) -> 53015 | AD89: =SUM(O89:R89) -> 43716 | AE89: =SUM(P89:S89) -> 41367 | AF89: =SUM(Q89:T89) -> 45514 | AG89: =SUM(R89:U89) -> 52261 | AH89: =SUM(S89:V89) -> 58269 | AI89: =SUM(T89:W89) -> 60918 | AJ89: =SUM(U89:X89) -> 62346 | ... AM89: =SUM(X89:AA89) -> 60947 | AO89: =SUM(AM89/AI89)-1 -> 0.00047604977
B90: Purchase of Investments | C90: -142428 | D90: -159486 | E90: -71356 | F90: -39630 | G90: -114938 | H90: -109558 | I90: -76923 | J90: -29513 | K90: -48656 | M90: -34913 | N90: =-61987-M90 -> -27074 | O90: =-70178-SUM(M90:N90) -> -8191 | P90: =SUM(I90-SUM(M90:O90)) -> -6745 | Q90: -5153 | R90: =-11197-Q90 -> -6044 | S90: -9759 | T90: =SUM(J90-SUM(Q90:S90)) -> -8557 | U90: -9780 | V90: =-25042-U90 -> -15262 | W90: =-38074-V90-U90 -> -13032 | X90: =SUM(K90-SUM(U90:W90)) -> -10582 | Y90: -6124 | Z90: =-12442-Y90 -> -6318 | AA90: =-17591-Z90-Y90 -> -5149 | AC90: =SUM(N90:Q90) -> -47163 | AD90: =SUM(O90:R90) -> -26133 | AE90: =SUM(P90:S90) -> -27701 | AF90: =SUM(Q90:T90) -> -29513 | AG90: =SUM(R90:U90) -> -34140 | AH90: =SUM(S90:V90) -> -43358 | AI90: =SUM(T90:W90) -> -46631 | AJ90: =SUM(U90:X90) -> -48656 | ... AM90: =SUM(X90:AA90) -> -28173 | AO90: =SUM(AM90/AI90)-1 -> -0.3958311
B91: Acquisitions/intang assets | C91: -1111 | D91: -673 | E91: -721 | F91: -624 | G91: -1524 | H91: -33 | I91: -306 | J91: 0 | K91: 0 | M91: 0 | N91: -167 | O91: =-169-SUM(M91:N91) -> -2 | P91: =SUM(I91-SUM(M91:O91)) -> -137 | Q91: 0 | R91: 0 | S91: 0 | T91: =SUM(J91-SUM(Q91:S91)) -> 0 | U91: 0 | V91: 0 | W91: 0 | X91: =SUM(K91-SUM(U91:W91)) -> 0 | Y91: 0 | Z91: 0 | AA91: 0 | AC91: =SUM(N91:Q91) -> -306 | AD91: =SUM(O91:R91) -> -139 | AE91: =SUM(P91:S91) -> -137 | AF91: =SUM(Q91:T91) -> 0 | AG91: =SUM(R91:U91) -> 0 | AH91: =SUM(S91:V91) -> 0 | AI91: =SUM(T91:W91) -> 0 | AJ91: =SUM(U91:X91) -> 0 | ... AM91: =SUM(X91:AA91) -> 0 | AO91: =SUM(AM91/AI91)-1 -> #DIV/0!
B92: Other/Strategic investments | C92: -1498 | D92: -175 | E92: -2263 | F92: -445 | G92: -909 | H92: -352 | I92: -1780 | J92: -1337 | K92: -1308 | M92: -374 | N92: =-568-M92 -> -194 | O92: =-1183-SUM(M92:N92) -> -615 | P92: =SUM(I92-SUM(M92:O92)) -> -597 | Q92: -141 | R92: =-247-Q92 -> -106 | S92: -506 | T92: =SUM(J92-SUM(Q92:S92)) -> -584 | U92: -284 | V92: =-729-U92 -> -445 | W92: =-1117-V92-U92 -> -388 | X92: =SUM(K92-SUM(U92:W92)) -> -191 | Y92: -603 | Z92: =-635-Y92 -> -32 | AA92: =-975-Z92-Y92 -> -340 | AC92: =SUM(N92:Q92) -> -1547 | AD92: =SUM(O92:R92) -> -1459 | AE92: =SUM(P92:S92) -> -1350 | AF92: =SUM(Q92:T92) -> -1337 | AG92: =SUM(R92:U92) -> -1480 | AH92: =SUM(S92:V92) -> -1819 | AI92: =SUM(T92:W92) -> -1701 | AJ92: =SUM(U92:X92) -> -1308 | ... AM92: =SUM(X92:AA92) -> -1166 | AO92: =SUM(AM92/AI92)-1 -> -0.31452087
B93: Net cash used in investing activities | C93: =SUM(C88:C92) -> -45977 | D93: =SUM(D88:D92) -> -46446 | E93: =SUM(E88:E92) -> 16066 | F93: =SUM(F88:F92) -> 45896 | G93: =SUM(G88:G92) -> -4289 | H93: =SUM(H88:H92) -> -14545 | I93: =SUM(I88:I92) -> -22354 | J93: =SUM(J88:J92) -> 3705 | K93: =SUM(K88:K92) -> 2935 | M93: =SUM(M88:M92) -> -16106 | N93: =SUM(N88:N92) -> -9265 | O93: =SUM(O88:O92) -> 4234 | P93: =SUM(P88:P92) -> -1217 | Q93: =SUM(Q88:Q92) -> -1445 | R93: =SUM(R88:R92) -> 2319 | S93: =SUM(S88:S92) -> 437 | T93: =SUM(T88:T92) -> 2394 | ... AA93: =SUM(AA88:AA92) -> 5073 | AC93: =SUM(AC88:AC92) -> -7693 | AD93: =SUM(AD88:AD92) -> 3891 | AE93: =SUM(AE88:AE92) -> 94 | AF93: =SUM(AF88:AF92) -> 3705 | AG93: =SUM(AG88:AG92) -> 7077 | AH93: =SUM(AH88:AH92) -> 4448 | AI93: =SUM(AI88:AI92) -> 3884 | AJ93: =SUM(AJ88:AJ92) -> 2935 | ... AM93: =SUM(AM88:AM92) -> 19227 | AO93: =SUM(AM93/AI93)-1 -> 3.950309
B95: Cash flows from financing activities:
B96: Proceeds from the issuance of term debt, net | C96: 22454 | D96: 28662 | E96: 6969 | F96: 6963 | G96: 16091 | H96: 20393 | I96: 5465 | J96: 5228 | K96: 0 | M96: 0 | N96: 0 | O96: 0 | P96: =SUM(I96-SUM(M96:O96)) -> 5465 | Q96: 0 | R96: 0 | S96: 5228 | T96: =SUM(J96-SUM(Q96:S96)) -> 0 | U96: 0 | V96: 0 | W96: 0 | X96: =SUM(K96-SUM(U96:W96)) -> 0 | Y96: 0 | Z96: 0 | AA96: =4481-Z96-Y96 -> 4481 | AC96: =SUM(N96:Q96) -> 5465 | AD96: =SUM(O96:R96) -> 5465 | AE96: =SUM(P96:S96) -> 10693 | AF96: =SUM(Q96:T96) -> 5228 | AG96: =SUM(R96:U96) -> 5228 | AH96: =SUM(S96:V96) -> 5228 | AI96: =SUM(T96:W96) -> 0 | AJ96: =SUM(U96:X96) -> 0 | ... AM96: =SUM(X96:AA96) -> 4481 | AO96: =SUM(AM96/AI96)-1 -> #DIV/0!
B97: Repayments of term debt | C97: 0 | D97: -3500 | E97: -6500 | F97: -8805 | G97: -12629 | H97: -8750 | I97: -9543 | J97: -11151.108 | K97: -9958 | M97: 0 | N97: -3750 | O97: -3000 | P97: =SUM(I97-SUM(M97:O97)) -> -2793 | Q97: -1401 | R97: -2250 | S97: -7500 | T97: =SUM(J97-SUM(Q97:S97)) -> -0.108 | U97: 0 | V97: -3150 | W97: -4250 | X97: =SUM(K97-SUM(U97:W97)) -> -2558 | Y97: -1009 | Z97: =-4009-Y97 -> -3000 | AA97: =-9682-Z97-Y97 -> -5673 | AC97: =SUM(N97:Q97) -> -10944 | AD97: =SUM(O97:R97) -> -9444 | AE97: =SUM(P97:S97) -> -13944 | AF97: =SUM(Q97:T97) -> -11151.108 | AG97: =SUM(R97:U97) -> -9750.108 | AH97: =SUM(S97:V97) -> -10650.108 | AI97: =SUM(T97:W97) -> -7400.108 | AJ97: =SUM(U97:X97) -> -9958 | ... AM97: =SUM(X97:AA97) -> -12240 | AO97: =SUM(AM97/AI97)-1 -> 0.65402991
B98: Issuance of Common | C98: 495 | D98: 555 | E98: 669 | F98: 781 | G98: 880 | H98: 1105 | I98: 0 | J98: 0 | K98: 0 | M98: 0 | N98: 0 | O98: 0 | P98: =SUM(I98-SUM(M98:O98)) -> 0 | Q98: 0 | R98: 0 | S98: 0 | T98: =SUM(J98-SUM(Q98:S98)) -> 0 | U98: 0 | V98: 0 | W98: 0 | X98: =SUM(K98-SUM(U98:W98)) -> 0 | Y98: 0 | Z98: 0 | AA98: 0 | AC98: =SUM(N98:Q98) -> 0 | AD98: =SUM(O98:R98) -> 0 | AE98: =SUM(P98:S98) -> 0 | AF98: =SUM(Q98:T98) -> 0 | AG98: =SUM(R98:U98) -> 0 | AH98: =SUM(S98:V98) -> 0 | AI98: =SUM(T98:W98) -> 0 | AJ98: =SUM(U98:X98) -> 0 | ... AM98: =SUM(X98:AA98) -> 0 | AO98: =SUM(AM98/AI98)-1 -> #DIV/0!
B99: Treasury Stock | C99: -29722 | D99: -32900 | E99: -72738 | F99: -66897 | G99: -72358 | H99: -85971 | I99: -89402 | J99: -77550 | K99: -94949 | M99: -20478 | N99: =-43109-M99 -> -22631 | O99: =-64974-SUM(M99:N99) -> -21865 | P99: =SUM(I99-SUM(M99:O99)) -> -24428 | Q99: -19475 | R99: =-39069-Q99 -> -19594 | S99: -17478 | T99: =SUM(J99-SUM(Q99:S99)) -> -21003 | U99: -20139 | V99: =-43344-U99 -> -23205 | W99: =-69866-V99-U99 -> -26522 | X99: =SUM(K99-SUM(U99:W99)) -> -25083 | Y99: -23606 | Z99: =-49504-Y99 -> -25898 | AA99: =-70579-Z99-Y99 -> -21075 | AC99: =SUM(N99:Q99) -> -88399 | AD99: =SUM(O99:R99) -> -85362 | AE99: =SUM(P99:S99) -> -80975 | AF99: =SUM(Q99:T99) -> -77550 | AG99: =SUM(R99:U99) -> -78214 | AH99: =SUM(S99:V99) -> -81825 | AI99: =SUM(T99:W99) -> -90869 | AJ99: =SUM(U99:X99) -> -94949 | ... AM99: =SUM(X99:AA99) -> -95662 | AO99: =SUM(AM99/AI99)-1 -> 0.052746261
B100: Change in commercial paper, net | C100: -397 | D100: 3852 | E100: -37 | F100: -5977 | G100: -963 | H100: 1022 | I100: 3955 | J100: -3978 | K100: 3960 | M100: -1000 | N100: =999-M100 -> 1999 | O100: =4970-SUM(M100:N100) -> 3971 | P100: =SUM(I100-SUM(M100:O100)) -> -1015 | Q100: -8214 | R100: =-7960-Q100 -> 254 | S100: 1989 | T100: =SUM(J100-SUM(Q100:S100)) -> 1993 | U100: -3984 | V100: =-3982-U100 -> 2 | W100: =-2985-V100-U100 -> 997 | X100: =SUM(K100-SUM(U100:W100)) -> 6945 | Y100: -7944 | Z100: =-3968-Y100 -> 3976 | AA100: =-65-Z100-Y100 -> 3903 | AC100: =SUM(N100:Q100) -> -3259 | AD100: =SUM(O100:R100) -> -5004 | AE100: =SUM(P100:S100) -> -6986 | AF100: =SUM(Q100:T100) -> -3978 | AG100: =SUM(R100:U100) -> 252 | AH100: =SUM(S100:V100) -> 0 | AI100: =SUM(T100:W100) -> -992 | AJ100: =SUM(U100:X100) -> 3960 | ... AM100: =SUM(X100:AA100) -> 6880 | AO100: =SUM(AM100/AI100)-1 -> -7.9354839
B101: Preferred Stock | C101: 0 | D101: 0 | E101: 0 | F101: 0 | G101: 0 | H101: 0 | I101: 0 | J101: 0 | K101: 0 | M101: 0 | N101: 0 | O101: 0 | P101: =SUM(I101-SUM(M101:O101)) -> 0 | Q101: 0 | R101: 0 | S101: 0 | T101: =SUM(J101-SUM(Q101:S101)) -> 0 | U101: 0 | V101: 0 | W101: 0 | X101: =SUM(K101-SUM(U101:W101)) -> 0 | Y101: 0 | Z101: 0 | AA101: 0 | AC101: =SUM(N101:Q101) -> 0 | AD101: =SUM(O101:R101) -> 0 | AE101: =SUM(P101:S101) -> 0 | AF101: =SUM(Q101:T101) -> 0 | AG101: =SUM(R101:U101) -> 0 | AH101: =SUM(S101:V101) -> 0 | AI101: =SUM(T101:W101) -> 0 | AJ101: =SUM(U101:X101) -> 0 | ... AM101: =SUM(X101:AA101) -> 0 | AO101: =SUM(AM101/AI101)-1 -> #DIV/0!
B102: Other | C102: -1163 | D102: -1247 | E102: -2527 | F102: -2922 | G102: -3760 | H102: -6685 | I102: -6383 | J102: -6012 | K102: -5802 | M102: =-2888-61 -> -2949 | N102: =-3218-105-M102 -> -374 | O102: =-148-5915-SUM(M102:N102) -> -2740 | P102: =SUM(I102-SUM(M102:O102)) -> -320 | Q102: =-2316-389 -> -2705 | R102: =-2734-455-Q102 -> -484 | S102: -2438 | T102: =SUM(J102-SUM(Q102:S102)) -> -385 | U102: =-2591-46 -> -2637 | V102: =-2875-U102-132 -> -370 | W102: =-5163-191-V102-U102 -> -2347 | X102: =SUM(K102-SUM(U102:W102)) -> -448 | Y102: =-2921-35 -> -2956 | Z102: =-3205+-77-Y102 -> -326 | AA102: =-5719+-87-Z102-Y102 -> -2524 | AC102: =SUM(N102:Q102) -> -6139 | AD102: =SUM(O102:R102) -> -6249 | AE102: =SUM(P102:S102) -> -5947 | AF102: =SUM(Q102:T102) -> -6012 | AG102: =SUM(R102:U102) -> -5944 | AH102: =SUM(S102:V102) -> -5830 | AI102: =SUM(T102:W102) -> -5739 | AJ102: =SUM(U102:X102) -> -5802 | ... AM102: =SUM(X102:AA102) -> -6254 | AO102: =SUM(AM102/AI102)-1 -> 0.089736888
B103: Dividends | C103: -12150 | D103: -12769 | E103: -13712 | F103: -14119 | G103: -14081 | H103: -14467 | I103: -14841 | J103: -14875 | K103: -15234 | M103: -3732 | N103: =-7327-M103 -> -3595 | O103: =-11138-SUM(M103:N103) -> -3811 | P103: =SUM(I103-SUM(M103:O103)) -> -3703 | Q103: -3768 | R103: =-7418-Q103 -> -3650 | S103: -3849 | T103: =SUM(J103-SUM(Q103:S103)) -> -3608 | U103: -3825 | V103: =-7535-U103 -> -3710 | W103: =-11430-V103-U103 -> -3895 | X103: =SUM(K103-SUM(U103:W103)) -> -3804 | Y103: -3856 | Z103: =-7614-Y103 -> -3758 | AA103: =-11559-Z103-Y103 -> -3945 | AC103: =SUM(N103:Q103) -> -14877 | AD103: =SUM(O103:R103) -> -14932 | AE103: =SUM(P103:S103) -> -14970 | AF103: =SUM(Q103:T103) -> -14875 | AG103: =SUM(R103:U103) -> -14932 | AH103: =SUM(S103:V103) -> -14992 | AI103: =SUM(T103:W103) -> -15038 | AJ103: =SUM(U103:X103) -> -15234 | ... AM103: =SUM(X103:AA103) -> -15363 | AO103: =SUM(AM103/AI103)-1 -> 0.021611916
B104: Net cash provided by financing activities | C104: =SUM(C96:C103) -> -20483 | D104: =SUM(D96:D103) -> -17347 | E104: =SUM(E96:E103) -> -87876 | F104: =SUM(F96:F103) -> -90976 | G104: =SUM(G96:G103) -> -86820 | H104: =SUM(H96:H103) -> -93353 | I104: =SUM(I96:I103) -> -110749 | J104: =SUM(J96:J103) -> -108338.11 | K104: =SUM(K96:K103) -> -121983 | M104: =SUM(M96:M103) -> -28159 | N104: =SUM(N96:N103) -> -28351 | O104: =SUM(O96:O103) -> -27445 | P104: =SUM(P96:P103) -> -26794 | Q104: =SUM(Q96:Q103) -> -35563 | R104: =SUM(R96:R103) -> -25724 | S104: =SUM(S96:S103) -> -24048 | T104: =SUM(T96:T103) -> -23003.108 | ... AA104: =SUM(AA96:AA103) -> -24833 | AC104: =SUM(AC96:AC103) -> -118153 | AD104: =SUM(AD96:AD103) -> -115526 | AE104: =SUM(AE96:AE103) -> -112129 | AF104: =SUM(AF96:AF103) -> -108338.11 | AG104: =SUM(AG96:AG103) -> -103360.11 | AH104: =SUM(AH96:AH103) -> -108069.11 | AI104: =SUM(AI96:AI103) -> -120038.11 | AJ104: =SUM(AJ96:AJ103) -> -121983 | ... AM104: =SUM(AM96:AM103) -> -118158 | AO104: =SUM(AM104/AI104)-1 -> -0.015662593
B107: Cash BOP | C107: 48844 | D107: 48844 | E107: 48844 | F107: 48844 | G107: 48844 | H107: =G113 -> 38016 | I107: =H113 -> 34940 | J107: =I113 -> 23646 | K107: =J113 -> 29965 | M107: =H113 -> 34940 | N107: =M113 -> 37119 | O107: =N113 -> 28098 | P107: =O113 -> 27502 | Q107: =P113 -> 23646 | R107: =Q113 -> 20535 | S107: =R113 -> 24687 | T107: =S113 -> 28408 | U107: =T113 -> 29965 | ... AA107: =Z113 -> 28162 | AC107: =M113 -> 37119 | AD107: =N113 -> 28098 | AE107: =O113 -> 27502 | AF107: =P113 -> 23646 | AG107: =Q113 -> 20535 | AH107: =R113 -> 24687 | AI107: =S113 -> 28408 | AJ107: =T113 -> 29965 | ... AM107: =W113 -> 25565
B108: BOP Restricted Cash Adjustments | F108: =23+1357 -> 1380 | G108: =23+1357 -> 1380 | H108: =-G111 -> 1773 | I108: =-H111 -> 989 | J108: =-I111 -> 1331 | K108: =-J111 -> 921.892 | M108: =-H111 -> 989 | N108: =-M111 -> 1511 | O108: =-N111 -> 1082 | P108: =-O111 -> 1359 | Q108: =-P111 -> 1331 | R108: =-Q111 -> 1439 | S108: =-R111 -> 2442 | T108: =-S111 -> 1490 | U108: =-T111 -> 921.892 | ... AA108: =-Z111 -> 149.892 | AC108: =-M111 -> 1511 | AD108: =-N111 -> 1082 | AE108: =-O111 -> 1359 | AF108: =-P111 -> 1331 | AG108: =-Q111 -> 1439 | AH108: =-R111 -> 2442 | AI108: =-S111 -> 1490 | AJ108: =-T111 -> 921.892 | ... AM108: =-W111 -> 1219.892
B109: Adjusted Cash Position BOP | C109: =SUM(C107:C108) -> 48844 | D109: =SUM(D107:D108) -> 48844 | E109: =SUM(E107:E108) -> 48844 | F109: =SUM(F107:F108) -> 50224 | G109: =SUM(G107:G108) -> 50224 | H109: =SUM(H107:H108) -> 39789 | I109: =SUM(I107:I108) -> 35929 | J109: =SUM(J107:J108) -> 24977 | K109: =SUM(K107:K108) -> 30886.892 | M109: =SUM(M107:M108) -> 35929 | N109: =SUM(N107:N108) -> 38630 | O109: =SUM(O107:O108) -> 29180 | P109: =SUM(P107:P108) -> 28861 | Q109: =SUM(Q107:Q108) -> 24977 | R109: =SUM(R107:R108) -> 21974 | S109: =SUM(S107:S108) -> 27129 | T109: =SUM(T107:T108) -> 29898 | ... AA109: =SUM(AA107:AA108) -> 28311.892 | AC109: =SUM(AC107:AC108) -> 38630 | AD109: =SUM(AD107:AD108) -> 29180 | AE109: =SUM(AE107:AE108) -> 28861 | AF109: =SUM(AF107:AF108) -> 24977 | AG109: =SUM(AG107:AG108) -> 21974 | AH109: =SUM(AH107:AH108) -> 27129 | AI109: =SUM(AI107:AI108) -> 29898 | AJ109: =SUM(AJ107:AJ108) -> 30886.892 | ... AM109: =SUM(AM107:AM108) -> 26784.892
B111: EOP Restricted Cash Adjustments | G111: =-(1737+36) -> -1773 | H111: -989 | I111: -1331 | J111: -921.892 | K111: -149.892 | M111: -1511 | N111: -1082 | O111: -1359 | P111: -1331 | Q111: -1439 | R111: -2442 | S111: -1490 | T111: -921.892 | U111: -1363.892 | V111: -1375.892 | W111: -1219.892 | X111: -149.892 | Y111: -149.892 | Z111: -149.892 | AA111: -149.892 | AC111: =Q111 -> -1439 | AD111: =R111 -> -2442 | AE111: =S111 -> -1490 | AF111: =T111 -> -921.892 | AG111: =U111 -> -1363.892 | AH111: =V111 -> -1375.892 | AI111: =W111 -> -1219.892 | AJ111: =X111 -> -149.892 | ... AM111: =AA111 -> -149.892
B112: Net Change in Cash | C112: =+C104+C93+C85 -> -636 | D112: =+D104+D93+D85 -> -195 | E112: =+E104+E93+E85 -> 5624 | F112: =+F104+F93+F85 -> 24311 | G112: =+G104+G93+G85 -> -10435 | H112: =+H104+H93+H85 -> -3860 | I112: =+I104+I93+I85 -> -10952 | J112: =+J104+J93+J85 -> 5909.892 | K112: =+K104+K93+K85 -> -794 | M112: =+M104+M93+M85 -> 2701 | N112: =+N104+N93+N85 -> -9450 | O112: =+O104+O93+O85 -> -319 | P112: =+P104+P93+P85 -> -3884 | Q112: =+Q104+Q93+Q85 -> -3003 | R112: =+R104+R93+R85 -> 5155 | S112: =+S104+S93+S85 -> 2769 | T112: =+T104+T93+T85 -> 988.892 | ... AA112: =+AA104+AA93+AA85 -> 8107 | AC112: =+AC104+AC93+AC85 -> -16656 | AD112: =+AD104+AD93+AD85 -> -2051 | AE112: =+AE104+AE93+AE85 -> 1037 | AF112: =+AF104+AF93+AF85 -> 5909.892 | AG112: =+AG104+AG93+AG85 -> 20149.892 | AH112: =+AH104+AH93+AH85 -> 6941.892 | AI112: =+AI104+AI93+AI85 -> -3113.108 | AJ112: =+AJ104+AJ93+AJ85 -> -794 | ... AM112: =+AM104+AM93+AM85 -> 9634
B113: Adjusted Cash Position EOP | C113: =SUM(C109:C112) -> 48208 | D113: =SUM(D109:D112) -> 48649 | E113: =SUM(E109:E112) -> 54468 | F113: =SUM(F109:F112) -> 74535 | G113: =SUM(G109:G112) -> 38016 | H113: =SUM(H109:H112) -> 34940 | I113: =SUM(I109:I112) -> 23646 | J113: =SUM(J109:J112) -> 29965 | K113: =SUM(K109:K112) -> 29943 | M113: =SUM(M109:M112) -> 37119 | N113: =SUM(N109:N112) -> 28098 | O113: =SUM(O109:O112) -> 27502 | P113: =SUM(P109:P112) -> 23646 | Q113: =SUM(Q109:Q112) -> 20535 | R113: =SUM(R109:R112) -> 24687 | S113: =SUM(S109:S112) -> 28408 | T113: =SUM(T109:T112) -> 29965 | ... AA113: =SUM(AA109:AA112) -> 36269 | AC113: =SUM(AC109:AC112) -> 20535 | AD113: =SUM(AD109:AD112) -> 24687 | AE113: =SUM(AE109:AE112) -> 28408 | AF113: =SUM(AF109:AF112) -> 29965 | AG113: =SUM(AG109:AG112) -> 40760 | AH113: =SUM(AH109:AH112) -> 32695 | AI113: =SUM(AI109:AI112) -> 25565 | AJ113: =SUM(AJ109:AJ112) -> 29943 | ... AM113: =SUM(AM109:AM112) -> 36269
B115: Balance Check | C115: =C113-C35 -> 27724 | D115: =D113-D35 -> 28360 | E115: =E113-E35 -> 28555 | F115: =F113-F35 -> 25691 | G115: =G113-G35 -> 0 | H115: =H113-H35 -> 0 | I115: =I113-I35 -> 0 | J115: =J113-J35 -> 0 | K115: =K113-K35 -> 0 | M115: =M113-M35 -> 0 | N115: =N113-N35 -> 0 | O115: =O113-O35 -> 0 | P115: =P113-P35 -> 0 | Q115: =Q113-Q35 -> 0 | R115: =R113-R35 -> 0 | S115: =S113-S35 -> 0 | T115: =T113-T35 -> 0 | ... AA115: =AA113-AA35 -> 0 | AC115: =AC113-AC35 -> 0 | AD115: =AD113-AD35 -> 0 | AE115: =AE113-AE35 -> 0 | AF115: =AF113-AF35 -> 0 | AG115: =AG113-AG35 -> 0 | AH115: =AH113-AH35 -> 0 | AI115: =AI113-AI35 -> 0 | AJ115: =AJ113-AJ35 -> 0 | ... AM115: =AM113-AM35 -> 0
B117: Cash paid during the period for:
B118: Cash paid for income taxes, net | D118: 11591 | E118: 10417 | F118: 15263 | G118: 9501 | H118: 25385 | I118: 19573 | J118: 18679 | K118: 26102 | M118: 5235 | N118: =9301-M118 -> 4066 | O118: =12251-N118-M118 -> 2950 | P118: =SUM(I118-SUM(M118:O118)) -> 7322 | Q118: 828 | R118: =4894-Q118 -> 4066 | S118: =7020-R118-Q118 -> 2126 | T118: =SUM(J118-SUM(Q118:S118)) -> 11659 | U118: 7255 | V118: =14531-U118 -> 7276 | W118: =19230-V118-U118 -> 4699 | X118: =SUM(K118-SUM(U118:W118)) -> 6872 | Y118: 18651 | Z118: =31683-Y118 -> 13032 | AA118: =37332-Z118-Y118 -> 5649 | AC118: =SUM(N118:Q118) -> 15166 | AD118: =SUM(O118:R118) -> 15166 | AE118: =SUM(P118:S118) -> 14342 | AF118: =SUM(Q118:T118) -> 18679 | AG118: =SUM(R118:U118) -> 25106 | AH118: =SUM(S118:V118) -> 28316 | AI118: =SUM(T118:W118) -> 30889 | AJ118: =SUM(U118:X118) -> 26102 | ... AM118: =SUM(X118:AA118) -> 44204
B119: Cash paid for interest | D119: 2092 | E119: 3022 | F119: 3423 | G119: 3002 | H119: 2687 | I119: 2865 | J119: 3803 | K119: 0 | M119: 531 | N119: =1406-M119 -> 875 | O119: =1910-N119-M119 -> 504 | P119: =SUM(I119-SUM(M119:O119)) -> 955 | Q119: 703 | R119: =1873-Q119 -> 1170 | S119: =2590-R119-Q119 -> 717 | T119: =SUM(J119-SUM(Q119:S119)) -> 1213 | U119: 0 | V119: 0 | W119: 0 | X119: =SUM(K119-SUM(U119:W119)) -> 0 | Y119: 0 | Z119: 0 | AA119: 0 | AC119: =SUM(N119:Q119) -> 3037 | AD119: =SUM(O119:R119) -> 3332 | AE119: =SUM(P119:S119) -> 3545 | AF119: =SUM(Q119:T119) -> 3803 | AG119: =SUM(R119:U119) -> 3100 | AH119: =SUM(S119:V119) -> 1930 | AI119: =SUM(T119:W119) -> 1213 | AJ119: =SUM(U119:X119) -> 0 | ... AM119: =SUM(X119:AA119) -> 0
B121: 1) Includes $50MM cash recorded within other current assets on the Consolidated Condensed Balance Sheets relating to Altera cash held for sale.

Sheet Revenue Drivers
B2: Apple Inc. (NASDAQ: AAPL) | C2: FYE | D2: FYE | E2: FYE | I2: Quarterly | Q2: Quarterly | R2: Quarterly | Y2: LTM | AC2: LTM | AK2: Variance
B3: Segment Anaysis | C3: ='Base Financials'!G3 -> 2020 | D3: ='Base Financials'!H3 -> 2021 | E3: ='Base Financials'!I3 -> 2022 | F3: ='Base Financials'!J3 -> 2023 | G3: ='Base Financials'!K3 -> 2024 | I3: ='Base Financials'!M3 -> 1Q22 | J3: ='Base Financials'!N3 -> 2Q22 | K3: ='Base Financials'!O3 -> 3Q22 | L3: ='Base Financials'!P3 -> 4Q22 | M3: ='Base Financials'!Q3 -> 1Q23 | N3: ='Base Financials'!R3 -> 2Q23 | O3: ='Base Financials'!S3 -> 3Q23 | P3: ='Base Financials'!T3 -> 4Q23 | ... W3: ='Base Financials'!AA3 -> 3Q25 | Y3: =M3 -> 1Q23 | Z3: =N3 -> 2Q23 | AA3: =O3 -> 3Q23 | AB3: =P3 -> 4Q23 | AC3: =Q3 -> 1Q24 | AD3: =R3 -> 2Q24 | AE3: =S3 -> 3Q24 | AF3: =T3 -> 4Q24 | ... AI3: =W3 -> 3Q25
B4: ($ In Millions) | C4: ='Base Financials'!G4 -> 44104 | D4: ='Base Financials'!H4 -> 44469 | E4: ='Base Financials'!I4 -> 44834 | F4: ='Base Financials'!J4 -> 45192 | G4: ='Base Financials'!K4 -> 45559 | I4: ='Base Financials'!M4 -> 44560 | J4: ='Base Financials'!N4 -> 44650 | K4: ='Base Financials'!O4 -> 44742 | L4: ='Base Financials'!P4 -> 44834 | M4: ='Base Financials'!Q4 -> 44917 | N4: ='Base Financials'!R4 -> 45008 | O4: ='Base Financials'!S4 -> 45100 | P4: ='Base Financials'!T4 -> 45192 | ... W4: ='Base Financials'!AA4 -> 45833 | Y4: =M4 -> 44917 | Z4: =N4 -> 45008 | AA4: =O4 -> 45100 | AB4: =P4 -> 45192 | AC4: =Q4 -> 45283 | AD4: =R4 -> 45375 | AE4: =S4 -> 45467 | AF4: =T4 -> 45559 | ... AI4: =W4 -> 45833
A6: X | B6: Revenue by End Product
B7: iPhone Revenue | C7: 137781 | D7: 191973 | E7: 205489 | F7: 200583 | G7: 201183 | I7: 71628 | J7: 50570 | K7: 40665 | L7: 42626 | M7: 65775 | N7: 51334 | O7: 39669 | P7: 43805 | Q7: 69702 | R7: 45963 | S7: 39296 | T7: 46222 | U7: 69138 | V7: 46841 | W7: 44582 | Y7: =SUM(J7:M7) -> 199636 | Z7: =SUM(K7:N7) -> 200400 | AA7: =SUM(L7:O7) -> 199404 | AB7: =SUM(M7:P7) -> 200583 | AC7: =SUM(N7:Q7) -> 204510 | AD7: =SUM(O7:R7) -> 199139 | AE7: =SUM(P7:S7) -> 198766 | AF7: =SUM(Q7:T7) -> 201183 | ... AI7: =SUM(T7:W7) -> 206783 | AK7: =SUM(AI7/AE7)-1 -> 0.04033386
B8: Mac Revenue | C8: 28622 | D8: 35190 | E8: 40177 | F8: 29357 | G8: 29984 | I8: 10852 | J8: 10435 | K8: 7382 | L8: 11508 | M8: 7735 | N8: 7168 | O8: 6840 | P8: 7614 | Q8: 7780 | R8: 7451 | S8: 7009 | T8: 7744 | U8: 8987 | V8: 7949 | W8: 8046 | Y8: =SUM(J8:M8) -> 37060 | Z8: =SUM(K8:N8) -> 33793 | AA8: =SUM(L8:O8) -> 33251 | AB8: =SUM(M8:P8) -> 29357 | AC8: =SUM(N8:Q8) -> 29402 | AD8: =SUM(O8:R8) -> 29685 | AE8: =SUM(P8:S8) -> 29854 | AF8: =SUM(Q8:T8) -> 29984 | ... AI8: =SUM(T8:W8) -> 32726 | AK8: =SUM(AI8/AE8)-1 -> 0.096201514
B9: iPad Revenue | C9: 23724 | D9: 31862 | E9: 29292 | F9: 28300 | G9: 26694 | I9: 7248 | J9: 7646 | K9: 7224 | L9: 7174 | M9: 9396 | N9: 6670 | O9: 5791 | P9: 6443 | Q9: 7023 | R9: 5559 | S9: 7162 | T9: 6950 | U9: 8088 | V9: 6402 | W9: 6581 | Y9: =SUM(J9:M9) -> 31440 | Z9: =SUM(K9:N9) -> 30464 | AA9: =SUM(L9:O9) -> 29031 | AB9: =SUM(M9:P9) -> 28300 | AC9: =SUM(N9:Q9) -> 25927 | AD9: =SUM(O9:R9) -> 24816 | AE9: =SUM(P9:S9) -> 26187 | AF9: =SUM(Q9:T9) -> 26694 | ... AI9: =SUM(T9:W9) -> 28021 | AK9: =SUM(AI9/AE9)-1 -> 0.07003475
B10: Services Revenue | C10: 53768 | D10: 68425 | E10: 78129 | F10: 85200 | G10: 96169 | I10: 19516 | J10: 19821 | K10: 19604 | L10: 19188 | M10: 20766 | N10: 20907 | O10: 21213 | P10: 22314 | Q10: 23117 | R10: 23867 | S10: 24213 | T10: 24972 | U10: 26340 | V10: 26645 | W10: 27423 | AE10: =SUM(P10:S10) -> 93511 | AF10: =SUM(Q10:T10) -> 96169 | AG10: =SUM(R10:U10) -> 99392 | AH10: =SUM(S10:V10) -> 102170 | AI10: =SUM(T10:W10) -> 105380
B11: Wearables, Home, and Accessories Revenue | C11: 30620 | D11: 38367 | E11: 41241 | F11: 39845 | G11: 37005 | I11: 14701 | J11: 8806 | K11: 8084 | L11: 9650 | M11: 13482 | N11: 8757 | O11: 8284 | P11: 9322 | Q11: 11953 | R11: 7913 | S11: 8097 | T11: 9042 | U11: 11747 | V11: 7522 | W11: 7404 | AE11: =SUM(P11:S11) -> 37285 | AF11: =SUM(Q11:T11) -> 37005 | AG11: =SUM(R11:U11) -> 36799 | AH11: =SUM(S11:V11) -> 36408 | AI11: =SUM(T11:W11) -> 35715
B12: Total Net Revenue | C12: =SUM(C7:C11) -> 274515 | D12: =SUM(D7:D11) -> 365817 | E12: =SUM(E7:E11) -> 394328 | F12: =SUM(F7:F11) -> 383285 | G12: =SUM(G7:G11) -> 391035 | I12: =SUM(I7:I11) -> 123945 | J12: =SUM(J7:J11) -> 97278 | K12: =SUM(K7:K11) -> 82959 | L12: =SUM(L7:L11) -> 90146 | M12: =SUM(M7:M11) -> 117154 | N12: =SUM(N7:N11) -> 94836 | O12: =SUM(O7:O11) -> 81797 | P12: =SUM(P7:P11) -> 89498 | ... W12: =SUM(W7:W11) -> 94036 | Y12: =SUM(Y7:Y9) -> 268136 | Z12: =SUM(Z7:Z9) -> 264657 | AA12: =SUM(AA7:AA9) -> 261686 | AB12: =SUM(AB7:AB9) -> 258240 | AC12: =SUM(AC7:AC9) -> 259839 | AD12: =SUM(AD7:AD9) -> 253640 | AE12: =SUM(AE7:AE11) -> 385603 | AF12: =SUM(AF7:AF11) -> 391035 | AG12: =SUM(AG7:AG11) -> 395760 | AH12: =SUM(AH7:AH11) -> 400366 | AI12: =SUM(AI7:AI11) -> 408625 | AK12: =SUM(AI12/AE12)-1 -> 0.059703892
B13: Balance Check | C13: =C12-'Base Financials'!G9 -> 0 | D13: =D12-'Base Financials'!H9 -> 0 | E13: =E12-'Base Financials'!I9 -> 0 | F13: =F12-'Base Financials'!J9 -> 0 | G13: =G12-'Base Financials'!K9 -> 0 | I13: =I12-'Base Financials'!M9 -> 0 | J13: =J12-'Base Financials'!N9 -> 0 | K13: =K12-'Base Financials'!O9 -> 0 | L13: =L12-'Base Financials'!P9 -> 0 | M13: =M12-'Base Financials'!Q9 -> 0 | N13: =N12-'Base Financials'!R9 -> 0 | O13: =O12-'Base Financials'!S9 -> 0 | P13: =P12-'Base Financials'!T9 -> 0 | ... W13: =W12-'Base Financials'!AA9 -> 0 | Y13: =Y12-'Base Financials'!AC9 -> -119401 | Z13: =Z12-'Base Financials'!AD9 -> -120438 | AA13: =AA12-'Base Financials'!AE9 -> -122247 | AB13: =AB12-'Base Financials'!AF9 -> -125045 | AC13: =AC12-'Base Financials'!AG9 -> -125867 | AD13: =AD12-'Base Financials'!AH9 -> -127983 | AE13: =AE12-'Base Financials'!AI9 -> 0 | AF13: =AF12-'Base Financials'!AJ9 -> 0 | ... AI13: =AI12-'Base Financials'!AM9 -> 0
A15: X | B15: Revenue by Product Offerings: Wearables, Home, and Accessories
B16: Accessories | C16: 16019.941 | D16: 20596.468 | E16: 21262.875 | F16: 19827.709 | G16: 18865.888 | I16: 5656.6733 | J16: 6070.4168 | K16: 4391.8204 | L16: 5143.9643 | M16: 4250.8013 | N16: 5709.2465 | O16: 4595.9109 | P16: 5271.75 | Q16: 4111.1639 | R16: 5174.0625 | S16: 4782.089 | T16: 4798.5722 | U16: 3839.2947 | V16: 4674.9385 | W16: 4052.9944 | Y16: =SUM(J16:M16) -> 19857.003 | Z16: =SUM(K16:N16) -> 19495.832 | AA16: =SUM(L16:O16) -> 19699.923 | AB16: =SUM(M16:P16) -> 19827.709 | AC16: =SUM(N16:Q16) -> 19688.071 | AD16: =SUM(O16:R16) -> 19152.887 | AE16: =SUM(P16:S16) -> 19339.065 | AF16: =SUM(Q16:T16) -> 18865.888 | ... AI16: =SUM(T16:W16) -> 17365.8 | AK16: =SUM(AI16/AE16)-1 -> -0.10203521
B17: Apple Watch | C17: 14229.125 | D17: 17479.962 | E17: 19750.272 | F17: 19838.618 | G17: 17999.002 | I17: 8954.015 | J17: 2690.982 | K17: 3644.0381 | L17: 4461.2373 | M17: 9160.4076 | N17: 3012.7635 | O17: 3650.3329 | P17: 4015.1136 | Q17: 7786.3465 | R17: 2711.4871 | S17: 3285.2996 | T17: 4215.8692 | U17: 7864.2099 | V17: 2847.0615 | W17: 3351.0056 | Y17: =SUM(J17:M17) -> 19956.665 | Z17: =SUM(K17:N17) -> 20278.447 | AA17: =SUM(L17:O17) -> 20284.741 | AB17: =SUM(M17:P17) -> 19838.618 | AC17: =SUM(N17:Q17) -> 18464.556 | AD17: =SUM(O17:R17) -> 18163.28 | AE17: =SUM(P17:S17) -> 17798.247 | AF17: =SUM(Q17:T17) -> 17999.002 | ... AI17: =SUM(T17:W17) -> 18278.146 | AK17: =SUM(AI17/AE17)-1 -> 0.026963301
B18: Total Intel Products Revenue | C18: =SUM(C16:C17) -> 30249.066 | D18: =SUM(D16:D17) -> 38076.431 | E18: =SUM(E16:E17) -> 41013.147 | F18: =SUM(F16:F17) -> 39666.326 | G18: =SUM(G16:G17) -> 36864.89 | I18: =SUM(I16:I17) -> 14610.688 | J18: =SUM(J16:J17) -> 8761.3988 | K18: =SUM(K16:K17) -> 8035.8585 | L18: =SUM(L16:L17) -> 9605.2016 | M18: =SUM(M16:M17) -> 13411.209 | N18: =SUM(N16:N17) -> 8722.01 | O18: =SUM(O16:O17) -> 8246.2439 | P18: =SUM(P16:P17) -> 9286.8636 | ... W18: =SUM(W16:W17) -> 7404 | Y18: =SUM(Y16:Y17) -> 39813.668 | Z18: =SUM(Z16:Z17) -> 39774.279 | AA18: =SUM(AA16:AA17) -> 39984.664 | AB18: =SUM(AB16:AB17) -> 39666.326 | AC18: =SUM(AC16:AC17) -> 38152.628 | AD18: =SUM(AD16:AD17) -> 37316.167 | AE18: =SUM(AE16:AE17) -> 37137.312 | AF18: =SUM(AF16:AF17) -> 36864.89 | ... AI18: =SUM(AI16:AI17) -> 35643.946 | AK18: =SUM(AI18/AE18)-1 -> -0.040212015
B19: Balance Check | C19: =C11-C18 -> 370.93376 | D19: =D11-D18 -> 290.56925 | E19: =E11-E18 -> 227.85276 | F19: =F11-F18 -> 178.67374 | G19: =G11-G18 -> 140.10996 | I19: =I11-I18 -> 90.311719 | J19: =J11-J18 -> 44.601177 | K19: =K11-K18 -> 48.141511 | L19: =L11-L18 -> 44.798357 | M19: =M11-M18 -> 70.79113 | N19: =N11-N18 -> 34.990036 | O19: =O11-O18 -> 37.756146 | P19: =P11-P18 -> 35.136432 | ... W19: =W11-W18 -> 0 | Y19: =Y7-Y18 -> 159822.33 | Z19: =Z7-Z18 -> 160625.72 | AA19: =AA7-AA18 -> 159419.34 | AB19: =AB7-AB18 -> 160916.67 | AC19: =AC7-AC18 -> 166357.37 | AD19: =AD7-AD18 -> 161822.83 | AE19: =AE7-AE18 -> 161628.69 | AF19: =AF7-AF18 -> 164318.11 | ... AI19: =AI7-AI18 -> 171139.05

Sheet FCF
B2: Apple Inc. (NASDAQ: AAPL) | C2: FYE | I2: Quarterly | Q2: Quarterly | S2: Quarterly | Y2: LTM | AC2: LTM | AF2: LTM | AL2: Variance
B3: FCF Analysis | C3: ='Base Financials'!G3 -> 2020 | D3: ='Base Financials'!H3 -> 2021 | E3: ='Base Financials'!I3 -> 2022 | F3: ='Base Financials'!J3 -> 2023 | G3: ='Base Financials'!K3 -> 2024 | I3: ='Base Financials'!M3 -> 1Q22 | J3: ='Base Financials'!N3 -> 2Q22 | K3: ='Base Financials'!O3 -> 3Q22 | L3: ='Base Financials'!P3 -> 4Q22 | M3: ='Base Financials'!Q3 -> 1Q23 | N3: ='Base Financials'!R3 -> 2Q23 | O3: ='Base Financials'!S3 -> 3Q23 | P3: ='Base Financials'!T3 -> 4Q23 | ... W3: ='Base Financials'!AA3 -> 3Q25 | Y3: =L3 -> 4Q22 | Z3: =M3 -> 1Q23 | AA3: =N3 -> 2Q23 | AB3: =O3 -> 3Q23 | AC3: =P3 -> 4Q23 | AD3: =Q3 -> 1Q24 | AE3: =R3 -> 2Q24 | AF3: =S3 -> 3Q24 | ... AJ3: =W3 -> 3Q25
B4: ($ In Thousands) | C4: ='Base Financials'!G4 -> 44104 | D4: ='Base Financials'!H4 -> 44469 | E4: ='Base Financials'!I4 -> 44834 | F4: ='Base Financials'!J4 -> 45192 | G4: ='Base Financials'!K4 -> 45559 | I4: ='Base Financials'!M4 -> 44560 | J4: ='Base Financials'!N4 -> 44650 | K4: ='Base Financials'!O4 -> 44742 | L4: ='Base Financials'!P4 -> 44834 | M4: ='Base Financials'!Q4 -> 44917 | N4: ='Base Financials'!R4 -> 45008 | O4: ='Base Financials'!S4 -> 45100 | P4: ='Base Financials'!T4 -> 45192 | ... W4: ='Base Financials'!AA4 -> 45833 | Y4: =L4 -> 44834 | Z4: =M4 -> 44917 | AA4: =N4 -> 45008 | AB4: =O4 -> 45100 | AC4: =P4 -> 45192 | AD4: =Q4 -> 45283 | AE4: =R4 -> 45375 | AF4: =S4 -> 45467 | ... AJ4: =W4 -> 45833
B6: ='Revenue Drivers'!B7 -> iPhone Revenue | C6: ='Revenue Drivers'!C7 -> 137781 | D6: ='Revenue Drivers'!D7 -> 191973 | E6: ='Revenue Drivers'!E7 -> 205489 | F6: ='Revenue Drivers'!F7 -> 200583 | G6: ='Revenue Drivers'!G7 -> 201183 | I6: ='Revenue Drivers'!I7 -> 71628 | J6: ='Revenue Drivers'!J7 -> 50570 | K6: ='Revenue Drivers'!K7 -> 40665 | L6: ='Revenue Drivers'!L7 -> 42626 | M6: ='Revenue Drivers'!M7 -> 65775 | N6: ='Revenue Drivers'!N7 -> 51334 | O6: ='Revenue Drivers'!O7 -> 39669 | P6: ='Revenue Drivers'!P7 -> 43805 | ... W6: ='Revenue Drivers'!W7 -> 44582 | Y6: =SUM(I6:L6) -> 205489 | Z6: =SUM(J6:M6) -> 199636 | AA6: =SUM(K6:N6) -> 200400 | AB6: =SUM(L6:O6) -> 199404 | AC6: =SUM(M6:P6) -> 200583 | AD6: =SUM(N6:Q6) -> 204510 | AE6: =SUM(O6:R6) -> 199139 | AF6: =SUM(P6:S6) -> 198766 | ... AJ6: =SUM(T6:W6) -> 206783 | AL6: =SUM(AJ6/AF6)-1 -> 0.04033386
B7: ='Revenue Drivers'!B8 -> Mac Revenue | C7: ='Revenue Drivers'!C8 -> 28622 | D7: ='Revenue Drivers'!D8 -> 35190 | E7: ='Revenue Drivers'!E8 -> 40177 | F7: ='Revenue Drivers'!F8 -> 29357 | G7: ='Revenue Drivers'!G8 -> 29984 | I7: ='Revenue Drivers'!I8 -> 10852 | J7: ='Revenue Drivers'!J8 -> 10435 | K7: ='Revenue Drivers'!K8 -> 7382 | L7: ='Revenue Drivers'!L8 -> 11508 | M7: ='Revenue Drivers'!M8 -> 7735 | N7: ='Revenue Drivers'!N8 -> 7168 | O7: ='Revenue Drivers'!O8 -> 6840 | P7: ='Revenue Drivers'!P8 -> 7614 | ... W7: ='Revenue Drivers'!W8 -> 8046 | Y7: =SUM(I7:L7) -> 40177 | Z7: =SUM(J7:M7) -> 37060 | AA7: =SUM(K7:N7) -> 33793 | AB7: =SUM(L7:O7) -> 33251 | AC7: =SUM(M7:P7) -> 29357 | AD7: =SUM(N7:Q7) -> 29402 | AE7: =SUM(O7:R7) -> 29685 | AF7: =SUM(P7:S7) -> 29854 | ... AJ7: =SUM(T7:W7) -> 32726 | AL7: =SUM(AJ7/AF7)-1 -> 0.096201514
B8: ='Revenue Drivers'!B9 -> iPad Revenue | C8: ='Revenue Drivers'!C9 -> 23724 | D8: ='Revenue Drivers'!D9 -> 31862 | E8: ='Revenue Drivers'!E9 -> 29292 | F8: ='Revenue Drivers'!F9 -> 28300 | G8: ='Revenue Drivers'!G9 -> 26694 | I8: ='Revenue Drivers'!I9 -> 7248 | J8: ='Revenue Drivers'!J9 -> 7646 | K8: ='Revenue Drivers'!K9 -> 7224 | L8: ='Revenue Drivers'!L9 -> 7174 | M8: ='Revenue Drivers'!M9 -> 9396 | N8: ='Revenue Drivers'!N9 -> 6670 | O8: ='Revenue Drivers'!O9 -> 5791 | P8: ='Revenue Drivers'!P9 -> 6443 | ... W8: ='Revenue Drivers'!W9 -> 6581 | Y8: =SUM(I8:L8) -> 29292 | Z8: =SUM(J8:M8) -> 31440 | AA8: =SUM(K8:N8) -> 30464 | AB8: =SUM(L8:O8) -> 29031 | AC8: =SUM(M8:P8) -> 28300 | AD8: =SUM(N8:Q8) -> 25927 | AE8: =SUM(O8:R8) -> 24816 | AF8: =SUM(P8:S8) -> 26187 | ... AJ8: =SUM(T8:W8) -> 28021 | AL8: =SUM(AJ8/AF8)-1 -> 0.07003475
B9: ='Revenue Drivers'!B10 -> Services Revenue | C9: ='Revenue Drivers'!C10 -> 53768 | D9: ='Revenue Drivers'!D10 -> 68425 | E9: ='Revenue Drivers'!E10 -> 78129 | F9: ='Revenue Drivers'!F10 -> 85200 | G9: ='Revenue Drivers'!G10 -> 96169 | I9: ='Revenue Drivers'!I10 -> 19516 | J9: ='Revenue Drivers'!J10 -> 19821 | K9: ='Revenue Drivers'!K10 -> 19604 | L9: ='Revenue Drivers'!L10 -> 19188 | M9: ='Revenue Drivers'!M10 -> 20766 | N9: ='Revenue Drivers'!N10 -> 20907 | O9: ='Revenue Drivers'!O10 -> 21213 | P9: ='Revenue Drivers'!P10 -> 22314 | ... W9: ='Revenue Drivers'!W10 -> 27423 | Y9: =SUM(I9:L9) -> 78129 | Z9: =SUM(J9:M9) -> 79379 | AA9: =SUM(K9:N9) -> 80465 | AB9: =SUM(L9:O9) -> 82074 | AC9: =SUM(M9:P9) -> 85200 | AD9: =SUM(N9:Q9) -> 87551 | AE9: =SUM(O9:R9) -> 90511 | AF9: =SUM(P9:S9) -> 93511 | ... AJ9: =SUM(T9:W9) -> 105380 | AL9: =SUM(AJ9/AF9)-1 -> 0.12692624
B10: ='Revenue Drivers'!B11 -> Wearables, Home, and Accessories Revenue | C10: ='Revenue Drivers'!C11 -> 30620 | D10: ='Revenue Drivers'!D11 -> 38367 | E10: ='Revenue Drivers'!E11 -> 41241 | F10: ='Revenue Drivers'!F11 -> 39845 | G10: ='Revenue Drivers'!G11 -> 37005 | I10: ='Revenue Drivers'!I11 -> 14701 | J10: ='Revenue Drivers'!J11 -> 8806 | K10: ='Revenue Drivers'!K11 -> 8084 | L10: ='Revenue Drivers'!L11 -> 9650 | M10: ='Revenue Drivers'!M11 -> 13482 | N10: ='Revenue Drivers'!N11 -> 8757 | O10: ='Revenue Drivers'!O11 -> 8284 | P10: ='Revenue Drivers'!P11 -> 9322 | ... W10: ='Revenue Drivers'!W11 -> 7404 | Y10: =SUM(I10:L10) -> 41241 | Z10: =SUM(J10:M10) -> 40022 | AA10: =SUM(K10:N10) -> 39973 | AB10: =SUM(L10:O10) -> 40173 | AC10: =SUM(M10:P10) -> 39845 | AD10: =SUM(N10:Q10) -> 38316 | AE10: =SUM(O10:R10) -> 37472 | AF10: =SUM(P10:S10) -> 37285 | ... AJ10: =SUM(T10:W10) -> 35715 | AL10: =SUM(AJ10/AF10)-1 -> -0.042108086
B11: Total Revenue | C11: =SUM(C6:C10) -> 274515 | D11: =SUM(D6:D10) -> 365817 | E11: =SUM(E6:E10) -> 394328 | F11: =SUM(F6:F10) -> 383285 | G11: =SUM(G6:G10) -> 391035 | I11: =SUM(I6:I10) -> 123945 | J11: =SUM(J6:J10) -> 97278 | K11: =SUM(K6:K10) -> 82959 | L11: =SUM(L6:L10) -> 90146 | M11: =SUM(M6:M10) -> 117154 | N11: =SUM(N6:N10) -> 94836 | O11: =SUM(O6:O10) -> 81797 | P11: =SUM(P6:P10) -> 89498 | ... W11: =SUM(W6:W10) -> 94036 | Y11: =SUM(Y6:Y10) -> 394328 | Z11: =SUM(Z6:Z10) -> 387537 | AA11: =SUM(AA6:AA10) -> 385095 | AB11: =SUM(AB6:AB10) -> 383933 | AC11: =SUM(AC6:AC10) -> 383285 | AD11: =SUM(AD6:AD10) -> 385706 | AE11: =SUM(AE6:AE10) -> 381623 | AF11: =SUM(AF6:AF10) -> 385603 | ... AJ11: =SUM(AJ6:AJ10) -> 408625 | AL11: =SUM(AJ11/AF11)-1 -> 0.059703892
B12: Y/Y Growth (%) | D12: =SUM(D11/C11)-1 -> 0.33259385 | E12: =SUM(E11/D11)-1 -> 0.077937876 | F12: =SUM(F11/E11)-1 -> -0.028004605 | G12: =SUM(G11/F11)-1 -> 0.020219941 | M12: =SUM(M11/I11)-1 -> -0.054790431 | N12: =SUM(N11/J11)-1 -> -0.025103312 | O12: =SUM(O11/K11)-1 -> -0.014006919 | P12: =SUM(P11/L11)-1 -> -0.0071883389 | Q12: =SUM(Q11/M11)-1 -> 0.020665107 | R12: =SUM(R11/N11)-1 -> -0.043053271 | S12: =SUM(S11/O11)-1 -> 0.048657041 | T12: =SUM(T11/P11)-1 -> 0.060694094 | ... W12: =SUM(W11/S11)-1 -> 0.096284552 | AC12: =SUM(AC11/Y11)-1 -> -0.028004605 | AD12: =SUM(AD11/Z11)-1 -> -0.0047247102 | AE12: =SUM(AE11/AA11)-1 -> -0.0090159571 | AF12: =SUM(AF11/AB11)-1 -> 0.0043497173 | AG12: =SUM(AG11/AC11)-1 -> 0.020219941 | AH12: =SUM(AH11/AD11)-1 -> 0.026066486 | AI12: =SUM(AI11/AE11)-1 -> 0.049113916 | AJ12: =SUM(AJ11/AF11)-1 -> 0.059703892 | AL12: =SUM(AJ12-AF12)*10000 -> 553.54175
B13: Q/Q Growth (%) | C13: N/A | D13: N/A | E13: N/A | F13: N/A | G13: N/A | J13: =SUM(J11/I11)-1 -> -0.21515188 | K13: =SUM(K11/J11)-1 -> -0.14719669 | L13: =SUM(L11/K11)-1 -> 0.086633156 | M13: =SUM(M11/L11)-1 -> 0.29960287 | N13: =SUM(N11/M11)-1 -> -0.19050139 | O13: =SUM(O11/N11)-1 -> -0.13748998 | P13: =SUM(P11/O11)-1 -> 0.094147707 | Q13: =SUM(Q11/P11)-1 -> 0.33606338 | ... W13: =SUM(W11/V11)-1 -> -0.013873887 | Y13: N/A | Z13: N/A | AA13: N/A | AB13: N/A | AC13: N/A | AD13: N/A | AE13: N/A | AF13: N/A | AG13: N/A | AH13: N/A | AI13: N/A | AJ13: N/A
B15: (-) Cost of Sales | C15: ='Base Financials'!G11 -> -169559 | D15: ='Base Financials'!H11 -> -212981 | E15: ='Base Financials'!I11 -> -223546 | F15: ='Base Financials'!J11 -> -214137 | G15: ='Base Financials'!K11 -> -210352 | I15: ='Base Financials'!M11 -> -69702 | J15: ='Base Financials'!N11 -> -54719 | K15: ='Base Financials'!O11 -> -47074 | L15: ='Base Financials'!P11 -> -52051 | M15: ='Base Financials'!Q11 -> -66822 | N15: ='Base Financials'!R11 -> -52860 | O15: ='Base Financials'!S11 -> -45384 | P15: ='Base Financials'!T11 -> -49071 | ... W15: ='Base Financials'!AA11 -> -50318 | Y15: =SUM(I15:L15) -> -223546 | Z15: =SUM(J15:M15) -> -220666 | AA15: =SUM(K15:N15) -> -218807 | AB15: =SUM(L15:O15) -> -217117 | AC15: =SUM(M15:P15) -> -214137 | AD15: =SUM(N15:Q15) -> -212035 | AE15: =SUM(O15:R15) -> -207657 | AF15: =SUM(P15:S15) -> -208372 | ... AJ15: =SUM(T15:W15) -> -217886 | AL15: =SUM(AJ15/AF15)-1 -> 0.045658726
B16: Gross Profit | C16: =+C11+C15 -> 104956 | D16: =+D11+D15 -> 152836 | E16: =+E11+E15 -> 170782 | F16: =+F11+F15 -> 169148 | G16: =+G11+G15 -> 180683 | I16: =+I11+I15 -> 54243 | J16: =+J11+J15 -> 42559 | K16: =+K11+K15 -> 35885 | L16: =+L11+L15 -> 38095 | M16: =+M11+M15 -> 50332 | N16: =+N11+N15 -> 41976 | O16: =+O11+O15 -> 36413 | P16: =+P11+P15 -> 40427 | ... W16: =+W11+W15 -> 43718 | Y16: =+Y11+Y15 -> 170782 | Z16: =+Z11+Z15 -> 166871 | AA16: =+AA11+AA15 -> 166288 | AB16: =+AB11+AB15 -> 166816 | AC16: =+AC11+AC15 -> 169148 | AD16: =+AD11+AD15 -> 173671 | AE16: =+AE11+AE15 -> 173966 | AF16: =+AF11+AF15 -> 177231 | ... AJ16: =+AJ11+AJ15 -> 190739 | AL16: =SUM(AJ16/AF16)-1 -> 0.076216915
B17: Gross Margin (%) | C17: =C16/C11 -> 0.38233248 | D17: =D16/D11 -> 0.4177936 | E17: =E16/E11 -> 0.43309631 | F17: =F16/F11 -> 0.4413113 | G17: =G16/G11 -> 0.4620635 | I17: =I16/I11 -> 0.43763766 | J17: =J16/J11 -> 0.43749872 | K17: =K16/K11 -> 0.43256307 | L17: =L16/L11 -> 0.42259224 | M17: =M16/M11 -> 0.42962255 | N17: =N16/N11 -> 0.44261673 | O17: =O16/O11 -> 0.44516303 | P17: =P16/P11 -> 0.45170842 | ... W17: =W16/W11 -> 0.46490706 | Y17: =Y16/Y11 -> 0.43309631 | Z17: =Z16/Z11 -> 0.43059372 | AA17: =AA16/AA11 -> 0.43181033 | AB17: =AB16/AB11 -> 0.43449248 | AC17: =AC16/AC11 -> 0.4413113 | AD17: =AD16/AD11 -> 0.45026782 | AE17: =AE16/AE11 -> 0.45585827 | AF17: =AF16/AF11 -> 0.45962039 | ... AJ17: =AJ16/AJ11 -> 0.4667825 | AL17: =SUM(AJ17-AF17)*10000 -> 71.621155
B19: (-) Research and Development (R&D) | C19: ='Base Financials'!G15 -> -18752 | D19: ='Base Financials'!H15 -> -21914 | E19: ='Base Financials'!I15 -> -26251 | F19: ='Base Financials'!J15 -> -29915 | G19: ='Base Financials'!K15 -> -31370 | I19: ='Base Financials'!M15 -> -6306 | J19: ='Base Financials'!N15 -> -6387 | K19: ='Base Financials'!O15 -> -6797 | L19: ='Base Financials'!P15 -> -6761 | M19: ='Base Financials'!Q15 -> -7709 | N19: ='Base Financials'!R15 -> -7457 | O19: ='Base Financials'!S15 -> -7442 | P19: ='Base Financials'!T15 -> -7307 | ... W19: ='Base Financials'!AA15 -> -8866 | Y19: =SUM(I19:L19) -> -26251 | Z19: =SUM(J19:M19) -> -27654 | AA19: =SUM(K19:N19) -> -28724 | AB19: =SUM(L19:O19) -> -29369 | AC19: =SUM(M19:P19) -> -29915 | AD19: =SUM(N19:Q19) -> -29902 | AE19: =SUM(O19:R19) -> -30348 | AF19: =SUM(P19:S19) -> -30912 | ... AJ19: =SUM(T19:W19) -> -33449 | AL19: =SUM(AJ19/AF19)-1 -> 0.082071687
B20: (-) Selling, General & Administrative (SG&A) | C20: ='Base Financials'!G16 -> -19916 | D20: ='Base Financials'!H16 -> -21973 | E20: ='Base Financials'!I16 -> -25094 | F20: ='Base Financials'!J16 -> -24932 | G20: ='Base Financials'!K16 -> -26097 | I20: ='Base Financials'!M16 -> -6449 | J20: ='Base Financials'!N16 -> -6193 | K20: ='Base Financials'!O16 -> -6012 | L20: ='Base Financials'!P16 -> -6440 | M20: ='Base Financials'!Q16 -> -6607 | N20: ='Base Financials'!R16 -> -6201 | O20: ='Base Financials'!S16 -> -5973 | P20: ='Base Financials'!T16 -> -6151 | ... W20: ='Base Financials'!AA16 -> -6650 | Y20: =SUM(I20:L20) -> -25094 | Z20: =SUM(J20:M20) -> -25252 | AA20: =SUM(K20:N20) -> -25260 | AB20: =SUM(L20:O20) -> -25221 | AC20: =SUM(M20:P20) -> -24932 | AD20: =SUM(N20:Q20) -> -25111 | AE20: =SUM(O20:R20) -> -25378 | AF20: =SUM(P20:S20) -> -25725 | ... AJ20: =SUM(T20:W20) -> -27076 | AL20: =SUM(AJ20/AF20)-1 -> 0.052517007
B21: Earning before Interest & Taxes (EBIT) | C21: =SUM(C16+SUM(C19:C20)) -> 66288 | D21: =SUM(D16+SUM(D19:D20)) -> 108949 | E21: =SUM(E16+SUM(E19:E20)) -> 119437 | F21: =SUM(F16+SUM(F19:F20)) -> 114301 | G21: =SUM(G16+SUM(G19:G20)) -> 123216 | I21: =SUM(I16+SUM(I19:I20)) -> 41488 | J21: =SUM(J16+SUM(J19:J20)) -> 29979 | K21: =SUM(K16+SUM(K19:K20)) -> 23076 | L21: =SUM(L16+SUM(L19:L20)) -> 24894 | M21: =SUM(M16+SUM(M19:M20)) -> 36016 | N21: =SUM(N16+SUM(N19:N20)) -> 28318 | O21: =SUM(O16+SUM(O19:O20)) -> 22998 | P21: =SUM(P16+SUM(P19:P20)) -> 26969 | ... W21: =SUM(W16+SUM(W19:W20)) -> 28202 | Y21: =SUM(Y16+SUM(Y19:Y20)) -> 119437 | Z21: =SUM(Z16+SUM(Z19:Z20)) -> 113965 | AA21: =SUM(AA16+SUM(AA19:AA20)) -> 112304 | AB21: =SUM(AB16+SUM(AB19:AB20)) -> 112226 | AC21: =SUM(AC16+SUM(AC19:AC20)) -> 114301 | AD21: =SUM(AD16+SUM(AD19:AD20)) -> 118658 | AE21: =SUM(AE16+SUM(AE19:AE20)) -> 118240 | AF21: =SUM(AF16+SUM(AF19:AF20)) -> 120594 | ... AJ21: =SUM(AJ16+SUM(AJ19:AJ20)) -> 130214 | AL21: =SUM(AJ21/AF21)-1 -> 0.079771796
B22: Operating Margin (%) | C22: =C21/C11 -> 0.24147314 | D22: =D21/D11 -> 0.29782378 | E22: =E21/E11 -> 0.30288744 | F22: =F21/F11 -> 0.29821412 | G22: =G21/G11 -> 0.31510223 | I22: =I21/I11 -> 0.33472911 | J22: =J21/J11 -> 0.30817862 | K22: =K21/K11 -> 0.2781615 | L22: =L21/L11 -> 0.27615202 | M22: =M21/M11 -> 0.30742442 | N22: =N21/N11 -> 0.29859969 | O22: =O21/O11 -> 0.28115946 | P22: =P21/P11 -> 0.30133634 | ... W22: =W21/W11 -> 0.29990642 | Y22: =Y21/Y11 -> 0.30288744 | Z22: =Z21/Z11 -> 0.29407515 | AA22: =AA21/AA11 -> 0.29162674 | AB22: =AB21/AB11 -> 0.29230621 | AC22: =AC21/AC11 -> 0.29821412 | AD22: =AD21/AD11 -> 0.30763846 | AE22: =AE21/AE11 -> 0.30983457 | AF22: =AF21/AF11 -> 0.31274134 | ... AJ22: =AJ21/AJ11 -> 0.31866381 | AL22: =SUM(AJ22-AF22)*10000 -> 59.224688
B24: (+) Depreciation and Amortization | C24: ='Base Financials'!G73 -> 11056 | D24: ='Base Financials'!H73 -> 11284 | E24: ='Base Financials'!I73 -> 11104 | F24: ='Base Financials'!J73 -> 11519 | G24: ='Base Financials'!K73 -> 11445 | I24: ='Base Financials'!M73 -> 2697 | J24: ='Base Financials'!N73 -> 2737 | K24: ='Base Financials'!O73 -> 2805 | L24: ='Base Financials'!P73 -> 2865 | M24: ='Base Financials'!Q73 -> 2916 | N24: ='Base Financials'!R73 -> 2898 | O24: ='Base Financials'!S73 -> 3052 | P24: ='Base Financials'!T73 -> 2653 | ... W24: ='Base Financials'!AA73 -> 2830 | Y24: =SUM(I24:L24) -> 11104 | Z24: =SUM(J24:M24) -> 11323 | AA24: =SUM(K24:N24) -> 11484 | AB24: =SUM(L24:O24) -> 11731 | AC24: =SUM(M24:P24) -> 11519 | AD24: =SUM(N24:Q24) -> 11451 | AE24: =SUM(O24:R24) -> 11389 | AF24: =SUM(P24:S24) -> 11187 | ... AJ24: =SUM(T24:W24) -> 11482 | AL24: =SUM(AJ24/AF24)-1 -> 0.026369894
B25: EBITDA | C25: =SUM(C21+C24) -> 77344 | D25: =SUM(D21+D24) -> 120233 | E25: =SUM(E21+E24) -> 130541 | F25: =SUM(F21+F24) -> 125820 | G25: =SUM(G21+G24) -> 134661 | I25: =SUM(I21+I24) -> 44185 | J25: =SUM(J21+J24) -> 32716 | K25: =SUM(K21+K24) -> 25881 | L25: =SUM(L21+L24) -> 27759 | M25: =SUM(M21+M24) -> 38932 | N25: =SUM(N21+N24) -> 31216 | O25: =SUM(O21+O24) -> 26050 | P25: =SUM(P21+P24) -> 29622 | ... W25: =SUM(W21+W24) -> 31032 | Y25: =SUM(Y21+Y24) -> 130541 | Z25: =SUM(Z21+Z24) -> 125288 | AA25: =SUM(AA21+AA24) -> 123788 | AB25: =SUM(AB21+AB24) -> 123957 | AC25: =SUM(AC21+AC24) -> 125820 | AD25: =SUM(AD21+AD24) -> 130109 | AE25: =SUM(AE21+AE24) -> 129629 | AF25: =SUM(AF21+AF24) -> 131781 | ... AJ25: =SUM(AJ21+AJ24) -> 141696 | AL25: =SUM(AJ25/AF25)-1 -> 0.075238464
B26: EBITDA Margin (%) | C26: =C25/C11 -> 0.28174781 | D26: =D25/D11 -> 0.3286698 | E26: =E25/E11 -> 0.33104674 | F26: =F25/F11 -> 0.32826748 | G26: =G25/G11 -> 0.34437071 | I26: =I25/I11 -> 0.35648877 | J26: =J25/J11 -> 0.33631448 | K26: =K25/K11 -> 0.31197338 | L26: =L25/L11 -> 0.3079338 | M26: =M25/M11 -> 0.33231473 | N26: =N25/N11 -> 0.3291577 | O26: =O25/O11 -> 0.31847134 | P26: =P25/P11 -> 0.33097946 | ... W26: =W25/W11 -> 0.33000128 | Y26: =Y25/Y11 -> 0.33104674 | Z26: =Z25/Z11 -> 0.323293 | AA26: =AA25/AA11 -> 0.32144795 | AB26: =AB25/AB11 -> 0.32286102 | AC26: =AC25/AC11 -> 0.32826748 | AD26: =AD25/AD11 -> 0.33732688 | AE26: =AE25/AE11 -> 0.33967816 | AF26: =AF25/AF11 -> 0.34175305 | ... AJ26: =AJ25/AJ11 -> 0.34676292 | AL26: =SUM(AJ26-AF26)*10000 -> 50.098779
B28: (+) Share-based Compensation | C28: ='Base Financials'!G74 -> 6829 | D28: ='Base Financials'!H74 -> 7906 | E28: ='Base Financials'!I74 -> 9038 | F28: ='Base Financials'!J74 -> 10833 | G28: ='Base Financials'!K74 -> 11688 | I28: ='Base Financials'!M74 -> 2265 | J28: ='Base Financials'!N74 -> 2252 | K28: ='Base Financials'!O74 -> 2243 | L28: ='Base Financials'!P74 -> 2278 | M28: ='Base Financials'!Q74 -> 2905 | N28: ='Base Financials'!R74 -> 2686 | O28: ='Base Financials'!S74 -> 2617 | P28: ='Base Financials'!T74 -> 2625 | ... W28: ='Base Financials'!AA74 -> 3168 | Y28: =SUM(I28:L28) -> 9038 | Z28: =SUM(J28:M28) -> 9678 | AA28: =SUM(K28:N28) -> 10112 | AB28: =SUM(L28:O28) -> 10486 | AC28: =SUM(M28:P28) -> 10833 | AD28: =SUM(N28:Q28) -> 10925 | AE28: =SUM(O28:R28) -> 11206 | AF28: =SUM(P28:S28) -> 11455 | ... AJ28: =SUM(T28:W28) -> 12538 | AL28: =SUM(AJ28/AF28)-1 -> 0.094543867
B29: Adj. EBITDA | C29: =+SUM(C25+SUM(C28:C28)) -> 84173 | D29: =+SUM(D25+SUM(D28:D28)) -> 128139 | E29: =+SUM(E25+SUM(E28:E28)) -> 139579 | F29: =+SUM(F25+SUM(F28:F28)) -> 136653 | G29: =+SUM(G25+SUM(G28:G28)) -> 146349 | I29: =+SUM(I25+SUM(I28:I28)) -> 46450 | J29: =+SUM(J25+SUM(J28:J28)) -> 34968 | K29: =+SUM(K25+SUM(K28:K28)) -> 28124 | L29: =+SUM(L25+SUM(L28:L28)) -> 30037 | M29: =+SUM(M25+SUM(M28:M28)) -> 41837 | N29: =+SUM(N25+SUM(N28:N28)) -> 33902 | O29: =+SUM(O25+SUM(O28:O28)) -> 28667 | P29: =+SUM(P25+SUM(P28:P28)) -> 32247 | ... W29: =+SUM(W25+SUM(W28:W28)) -> 34200 | Y29: =+SUM(Y25+SUM(Y28:Y28)) -> 139579 | Z29: =+SUM(Z25+SUM(Z28:Z28)) -> 134966 | AA29: =+SUM(AA25+SUM(AA28:AA28)) -> 133900 | AB29: =+SUM(AB25+SUM(AB28:AB28)) -> 134443 | AC29: =+SUM(AC25+SUM(AC28:AC28)) -> 136653 | AD29: =+SUM(AD25+SUM(AD28:AD28)) -> 141034 | AE29: =+SUM(AE25+SUM(AE28:AE28)) -> 140835 | AF29: =+SUM(AF25+SUM(AF28:AF28)) -> 143236 | ... AJ29: =+SUM(AJ25+SUM(AJ28:AJ28)) -> 154234 | AL29: =SUM(AJ29/AF29)-1 -> 0.076782373
B30: Adj. EBITDA Margin (%) | C30: =C29/C11 -> 0.30662441 | D30: =D29/D11 -> 0.3502817 | E30: =E29/E11 -> 0.35396675 | F30: =F29/F11 -> 0.35653104 | G30: =G29/G11 -> 0.37426062 | I30: =I29/I11 -> 0.374763 | J30: =J29/J11 -> 0.35946463 | K30: =K29/K11 -> 0.33901084 | L30: =L29/L11 -> 0.33320391 | M30: =M29/M11 -> 0.35711115 | N30: =N29/N11 -> 0.35748028 | O30: =O29/O11 -> 0.35046518 | P30: =P29/P11 -> 0.36030973 | ... W30: =W29/W11 -> 0.3636905 | Y30: =Y29/Y11 -> 0.35396675 | Z30: =Z29/Z11 -> 0.3482661 | AA30: =AA29/AA11 -> 0.34770641 | AB30: =AB29/AB11 -> 0.35017308 | AC30: =AC29/AC11 -> 0.35653104 | AD30: =AD29/AD11 -> 0.36565156 | AE30: =AE29/AE11 -> 0.36904222 | AF30: =AF29/AF11 -> 0.37145977 | ... AJ30: =AJ29/AJ11 -> 0.37744631 | AL30: =SUM(AJ30-AF30)*10000 -> 59.865482
B32: (-) Capital Expenditures | C32: ='Base Financials'!G88 -> -7309 | D32: ='Base Financials'!H88 -> -11085 | E32: ='Base Financials'!I88 -> -10708 | F32: ='Base Financials'!J88 -> -10959 | G32: ='Base Financials'!K88 -> -9447 | I32: ='Base Financials'!M88 -> -2803 | J32: ='Base Financials'!N88 -> -2514 | K32: ='Base Financials'!O88 -> -2102 | L32: ='Base Financials'!P88 -> -3289 | M32: ='Base Financials'!Q88 -> -3787 | N32: ='Base Financials'!R88 -> -2916 | O32: ='Base Financials'!S88 -> -2093 | P32: ='Base Financials'!T88 -> -2163 | ... W32: ='Base Financials'!AA88 -> -3462 | Y32: =SUM(I32:L32) -> -10708 | Z32: =SUM(J32:M32) -> -11692 | AA32: =SUM(K32:N32) -> -12094 | AB32: =SUM(L32:O32) -> -12085 | AC32: =SUM(M32:P32) -> -10959 | AD32: =SUM(N32:Q32) -> -9564 | AE32: =SUM(O32:R32) -> -8644 | AF32: =SUM(P32:S32) -> -8702 | ... AJ32: =SUM(T32:W32) -> -12381 | AL32: =SUM(AJ32/AF32)-1 -> 0.42277637
B33: (-) Cash Taxes | C33: =-'Base Financials'!G118 -> -9501 | D33: =-'Base Financials'!H118 -> -25385 | E33: =-'Base Financials'!I118 -> -19573 | F33: =-'Base Financials'!J118 -> -18679 | G33: =-'Base Financials'!K118 -> -26102 | I33: =-'Base Financials'!M118 -> -5235 | J33: =-'Base Financials'!N118 -> -4066 | K33: =-'Base Financials'!O118 -> -2950 | L33: =-'Base Financials'!P118 -> -7322 | M33: =-'Base Financials'!Q118 -> -828 | N33: =-'Base Financials'!R118 -> -4066 | O33: =-'Base Financials'!S118 -> -2126 | P33: =-'Base Financials'!T118 -> -11659 | ... W33: =-'Base Financials'!AA118 -> -5649 | Y33: =SUM(I33:L33) -> -19573 | Z33: =SUM(J33:M33) -> -15166 | AA33: =SUM(K33:N33) -> -15166 | AB33: =SUM(L33:O33) -> -14342 | AC33: =SUM(M33:P33) -> -18679 | AD33: =SUM(N33:Q33) -> -25106 | AE33: =SUM(O33:R33) -> -28316 | AF33: =SUM(P33:S33) -> -30889 | ... AJ33: =SUM(T33:W33) -> -44204 | AL33: =SUM(AJ33/AF33)-1 -> 0.4310596
B34: (-) Cash Interest | C34: =-'Base Financials'!G119 -> -3002 | D34: =-'Base Financials'!H119 -> -2687 | E34: =-'Base Financials'!I119 -> -2865 | F34: =-'Base Financials'!J119 -> -3803 | G34: =-'Base Financials'!K119 -> 0 | I34: =-'Base Financials'!M119 -> -531 | J34: =-'Base Financials'!N119 -> -875 | K34: =-'Base Financials'!O119 -> -504 | L34: =-'Base Financials'!P119 -> -955 | M34: =-'Base Financials'!Q119 -> -703 | N34: =-'Base Financials'!R119 -> -1170 | O34: =-'Base Financials'!S119 -> -717 | P34: =-'Base Financials'!T119 -> -1213 | ... W34: =-'Base Financials'!AA119 -> 0 | Y34: =SUM(I34:L34) -> -2865 | Z34: =SUM(J34:M34) -> -3037 | AA34: =SUM(K34:N34) -> -3332 | AB34: =SUM(L34:O34) -> -3545 | AC34: =SUM(M34:P34) -> -3803 | AD34: =SUM(N34:Q34) -> -3100 | AE34: =SUM(O34:R34) -> -1930 | AF34: =SUM(P34:S34) -> -1213 | ... AJ34: =SUM(T34:W34) -> 0 | AL34: =SUM(AJ34/AF34)-1 -> -1
B35: (+/-) Changes in NWC | C35: =SUM('Base Financials'!G79:G84) -> 5690 | D35: =SUM('Base Financials'!H79:H84) -> -4911 | E35: =SUM('Base Financials'!I79:I84) -> 1200 | F35: =SUM('Base Financials'!J79:J84) -> -6577 | G35: =SUM('Base Financials'!K79:K84) -> 3651 | I35: =SUM('Base Financials'!M79:M84) -> 6525 | J35: =SUM('Base Financials'!N79:N84) -> -2052 | K35: =SUM('Base Financials'!O79:O84) -> -3225 | L35: =SUM('Base Financials'!P79:P84) -> -48 | M35: =SUM('Base Financials'!Q79:Q84) -> -1497 | N35: =SUM('Base Financials'!R79:R84) -> 231 | O35: =SUM('Base Financials'!S79:S84) -> 749 | P35: =SUM('Base Financials'!T79:T84) -> -6060 | ... W35: =SUM('Base Financials'!AA79:AA84) -> -2034 | Y35: =SUM(I35:L35) -> 1200 | Z35: =SUM(J35:M35) -> -6822 | AA35: =SUM(K35:N35) -> -4539 | AB35: =SUM(L35:O35) -> -565 | AC35: =SUM(M35:P35) -> -6577 | AD35: =SUM(N35:Q35) -> -3957 | AE35: =SUM(O35:R35) -> -9955 | AF35: =SUM(P35:S35) -> -9017 | ... AJ35: =SUM(T35:W35) -> -12685 | AL35: =SUM(AJ35/AF35)-1 -> 0.40678718
B36: Discretionary Cash-Flows | C36: =SUM(C29+SUM(C32:C35)) -> 70051 | D36: =SUM(D29+SUM(D32:D35)) -> 84071 | E36: =SUM(E29+SUM(E32:E35)) -> 107633 | F36: =SUM(F29+SUM(F32:F35)) -> 96635 | G36: =SUM(G29+SUM(G32:G35)) -> 114451 | I36: =SUM(I29+SUM(I32:I35)) -> 44406 | J36: =SUM(J29+SUM(J32:J35)) -> 25461 | K36: =SUM(K29+SUM(K32:K35)) -> 19343 | L36: =SUM(L29+SUM(L32:L35)) -> 18423 | M36: =SUM(M29+SUM(M32:M35)) -> 35022 | N36: =SUM(N29+SUM(N32:N35)) -> 25981 | O36: =SUM(O29+SUM(O32:O35)) -> 24480 | P36: =SUM(P29+SUM(P32:P35)) -> 11152 | ... W36: =SUM(W29+SUM(W32:W35)) -> 23055 | Y36: =SUM(Y29+SUM(Y32:Y35)) -> 107633 | Z36: =SUM(Z29+SUM(Z32:Z35)) -> 98249 | AA36: =SUM(AA29+SUM(AA32:AA35)) -> 98769 | AB36: =SUM(AB29+SUM(AB32:AB35)) -> 103906 | AC36: =SUM(AC29+SUM(AC32:AC35)) -> 96635 | AD36: =SUM(AD29+SUM(AD32:AD35)) -> 99307 | AE36: =SUM(AE29+SUM(AE32:AE35)) -> 91990 | AF36: =SUM(AF29+SUM(AF32:AF35)) -> 93415 | ... AJ36: =SUM(AJ29+SUM(AJ32:AJ35)) -> 84964 | AL36: =SUM(AJ36/AF36)-1 -> -0.09046727
B38: (+/-) Proceeds / (Purchases) of Investments | C38: =SUM('Base Financials'!G89:G90) -> 5453 | D38: =SUM('Base Financials'!H89:H90) -> -3075 | E38: =SUM('Base Financials'!I89:I90) -> -9560 | F38: =SUM('Base Financials'!J89:J90) -> 16001 | G38: =SUM('Base Financials'!K89:K90) -> 13690 | I38: =SUM('Base Financials'!M89:M90) -> -12929 | J38: =SUM('Base Financials'!N89:N90) -> -6390 | K38: =SUM('Base Financials'!O89:O90) -> 6953 | L38: =SUM('Base Financials'!P89:P90) -> 2806 | M38: =SUM('Base Financials'!Q89:Q90) -> 2483 | N38: =SUM('Base Financials'!R89:R90) -> 5341 | O38: =SUM('Base Financials'!S89:S90) -> 3036 | P38: =SUM('Base Financials'!T89:T90) -> 5141 | ... W38: =SUM('Base Financials'!AA89:AA90) -> 8875 | Y38: =SUM(I38:L38) -> -9560 | Z38: =SUM(J38:M38) -> 5852 | AA38: =SUM(K38:N38) -> 17583 | AB38: =SUM(L38:O38) -> 13666 | AC38: =SUM(M38:P38) -> 16001 | AD38: =SUM(N38:Q38) -> 18121 | AE38: =SUM(O38:R38) -> 14911 | AF38: =SUM(P38:S38) -> 14287 | ... AJ38: =SUM(T38:W38) -> 32774
B39: (+/-) Proceeds / (Purchases) of Other/Strategic investments | C39: ='Base Financials'!G92 -> -909 | D39: ='Base Financials'!H92 -> -352 | E39: ='Base Financials'!I92 -> -1780 | F39: ='Base Financials'!J92 -> -1337 | G39: ='Base Financials'!K92 -> -1308 | I39: ='Base Financials'!M92 -> -374 | J39: ='Base Financials'!N92 -> -194 | K39: ='Base Financials'!O92 -> -615 | L39: ='Base Financials'!P92 -> -597 | M39: ='Base Financials'!Q92 -> -141 | N39: ='Base Financials'!R92 -> -106 | O39: ='Base Financials'!S92 -> -506 | P39: ='Base Financials'!T92 -> -584 | ... W39: ='Base Financials'!AA92 -> -340 | Y39: =SUM(I39:L39) -> -1780 | Z39: =SUM(J39:M39) -> -1547 | AA39: =SUM(K39:N39) -> -1459 | AB39: =SUM(L39:O39) -> -1350 | AC39: =SUM(M39:P39) -> -1337 | AD39: =SUM(N39:Q39) -> -1480 | AE39: =SUM(O39:R39) -> -1819 | AF39: =SUM(P39:S39) -> -1701 | ... AJ39: =SUM(T39:W39) -> -1166
B40: (+/-) Issuance / (Repayment) of Debt | C40: =SUM('Base Financials'!G96:G97) -> 3462 | D40: =SUM('Base Financials'!H96:H97) -> 11643 | E40: =SUM('Base Financials'!I96:I97) -> -4078 | F40: =SUM('Base Financials'!J96:J97) -> -5923.108 | G40: =SUM('Base Financials'!K96:K97) -> -9958 | I40: =SUM('Base Financials'!M96:M97) -> 0 | J40: =SUM('Base Financials'!N96:N97) -> -3750 | K40: =SUM('Base Financials'!O96:O97) -> -3000 | L40: =SUM('Base Financials'!P96:P97) -> 2672 | M40: =SUM('Base Financials'!Q96:Q97) -> -1401 | N40: =SUM('Base Financials'!R96:R97) -> -2250 | O40: =SUM('Base Financials'!S96:S97) -> -2272 | P40: =SUM('Base Financials'!T96:T97) -> -0.108 | ... W40: =SUM('Base Financials'!AA96:AA97) -> -1192 | Y40: =SUM(I40:L40) -> -4078 | Z40: =SUM(J40:M40) -> -5479 | AA40: =SUM(K40:N40) -> -3979 | AB40: =SUM(L40:O40) -> -3251 | AC40: =SUM(M40:P40) -> -5923.108 | AD40: =SUM(N40:Q40) -> -4522.108 | AE40: =SUM(O40:R40) -> -5422.108 | AF40: =SUM(P40:S40) -> -7400.108 | ... AJ40: =SUM(T40:W40) -> -7759
B41: (+/-) Issuances / (Share Repurchases) | C41: =SUM('Base Financials'!G98:G99) -> -71478 | D41: =SUM('Base Financials'!H98:H99) -> -84866 | E41: =SUM('Base Financials'!I98:I99) -> -89402 | F41: =SUM('Base Financials'!J98:J99) -> -77550 | G41: =SUM('Base Financials'!K98:K99) -> -94949 | I41: =SUM('Base Financials'!M98:M99) -> -20478 | J41: =SUM('Base Financials'!N98:N99) -> -22631 | K41: =SUM('Base Financials'!O98:O99) -> -21865 | L41: =SUM('Base Financials'!P98:P99) -> -24428 | M41: =SUM('Base Financials'!Q98:Q99) -> -19475 | N41: =SUM('Base Financials'!R98:R99) -> -19594 | O41: =SUM('Base Financials'!S98:S99) -> -17478 | P41: =SUM('Base Financials'!T98:T99) -> -21003 | ... W41: =SUM('Base Financials'!AA98:AA99) -> -21075 | Y41: =SUM(I41:L41) -> -89402 | Z41: =SUM(J41:M41) -> -88399 | AA41: =SUM(K41:N41) -> -85362 | AB41: =SUM(L41:O41) -> -80975 | AC41: =SUM(M41:P41) -> -77550 | AD41: =SUM(N41:Q41) -> -78214 | AE41: =SUM(O41:R41) -> -81825 | AF41: =SUM(P41:S41) -> -90869 | ... AJ41: =SUM(T41:W41) -> -95662
B42: (+/-) Change in commercial paper, net | C42: ='Base Financials'!G100 -> -963 | D42: ='Base Financials'!H100 -> 1022 | E42: ='Base Financials'!I100 -> 3955 | F42: ='Base Financials'!J100 -> -3978 | G42: ='Base Financials'!K100 -> 3960 | I42: ='Base Financials'!M100 -> -1000 | J42: ='Base Financials'!N100 -> 1999 | K42: ='Base Financials'!O100 -> 3971 | L42: ='Base Financials'!P100 -> -1015 | M42: ='Base Financials'!Q100 -> -8214 | N42: ='Base Financials'!R100 -> 254 | O42: ='Base Financials'!S100 -> 1989 | P42: ='Base Financials'!T100 -> 1993 | ... W42: ='Base Financials'!AA100 -> 3903 | Y42: =SUM(I42:L42) -> 3955 | Z42: =SUM(J42:M42) -> -3259 | AA42: =SUM(K42:N42) -> -5004 | AB42: =SUM(L42:O42) -> -6986 | AC42: =SUM(M42:P42) -> -3978 | AD42: =SUM(N42:Q42) -> 252 | AE42: =SUM(O42:R42) -> 0 | AF42: =SUM(P42:S42) -> -992 | ... AJ42: =SUM(T42:W42) -> 6880
B43: (+/-) Dividends | C43: ='Base Financials'!G103 -> -14081 | D43: ='Base Financials'!H103 -> -14467 | E43: ='Base Financials'!I103 -> -14841 | F43: ='Base Financials'!J103 -> -14875 | G43: ='Base Financials'!K103 -> -15234 | I43: ='Base Financials'!M103 -> -3732 | J43: ='Base Financials'!N103 -> -3595 | K43: ='Base Financials'!O103 -> -3811 | L43: ='Base Financials'!P103 -> -3703 | M43: ='Base Financials'!Q103 -> -3768 | N43: ='Base Financials'!R103 -> -3650 | O43: ='Base Financials'!S103 -> -3849 | P43: ='Base Financials'!T103 -> -3608 | ... W43: ='Base Financials'!AA103 -> -3945 | AE43: =SUM(O43:R43) -> -14992 | AF43: =SUM(P43:S43) -> -15038 | AG43: =SUM(Q43:T43) -> -15234 | AH43: =SUM(R43:U43) -> -15265 | AI43: =SUM(S43:V43) -> -15313 | AJ43: =SUM(T43:W43) -> -15363
B44: (+/-) Other | D44: =SUM(D49-C49)-SUM(D36:D43) -> 2948 | E44: =SUM(E49-D49)-SUM(E36:E43) -> -3221 | F44: =SUM(F49-E49)-SUM(F36:F43) -> -2653.892 | G44: =SUM(G49-F49)-SUM(G36:G43) -> -10674 | I44: =SUM(I49-D49)-SUM(I36:I43) -> -3714 | J44: =SUM(J49-I49)-SUM(J36:J43) -> 79 | K44: =SUM(K49-J49)-SUM(K36:K43) -> -1572 | L44: =SUM(L49-K49)-SUM(L36:L43) -> 1986 | M44: =SUM(M49-L49)-SUM(M36:M43) -> -7617 | N44: =SUM(N49-M49)-SUM(N36:N43) -> -1824 | O44: =SUM(O49-N49)-SUM(O36:O43) -> -1679 | P44: =SUM(P49-O49)-SUM(P36:P43) -> 8466.108 | Q44: =SUM(Q49-P49)-SUM(Q36:Q43) -> -3270 | ... W44: =SUM(W49-V49)-SUM(W36:W43) -> -1174 | Y44: =SUM(I44:L44) -> -3221 | Z44: =SUM(J44:M44) -> -7124 | AA44: =SUM(K44:N44) -> -9027 | AB44: =SUM(L44:O44) -> -9134 | AC44: =SUM(M44:P44) -> -2653.892 | AD44: =SUM(N44:Q44) -> 1693.108 | AE44: =SUM(O44:R44) -> 5165.108 | AF44: =SUM(P44:S44) -> 5455.108 | ... AJ44: =SUM(T44:W44) -> 6036
B45: Free-Cash Flows | C45: =SUM(C36+SUM(C38:C44)) -> -8465 | D45: =SUM(D36+SUM(D38:D44)) -> -3076 | E45: =SUM(E36+SUM(E38:E44)) -> -11294 | F45: =SUM(F36+SUM(F38:F44)) -> 6319 | G45: =SUM(G36+SUM(G38:G44)) -> -22 | I45: =SUM(I36+SUM(I38:I44)) -> 2179 | J45: =SUM(J36+SUM(J38:J44)) -> -9021 | K45: =SUM(K36+SUM(K38:K44)) -> -596 | L45: =SUM(L36+SUM(L38:L44)) -> -3856 | M45: =SUM(M36+SUM(M38:M44)) -> -3111 | N45: =SUM(N36+SUM(N38:N44)) -> 4152 | O45: =SUM(O36+SUM(O38:O44)) -> 3721 | P45: =SUM(P36+SUM(P38:P44)) -> 1557 | ... W45: =SUM(W36+SUM(W38:W44)) -> 8107 | Y45: =SUM(Y36+SUM(Y38:Y44)) -> 3547 | Z45: =SUM(Z36+SUM(Z38:Z44)) -> -1707 | AA45: =SUM(AA36+SUM(AA38:AA44)) -> 11521 | AB45: =SUM(AB36+SUM(AB38:AB44)) -> 15876 | AC45: =SUM(AC36+SUM(AC38:AC44)) -> 21194 | AD45: =SUM(AD36+SUM(AD38:AD44)) -> 35157 | AE45: =SUM(AE36+SUM(AE38:AE44)) -> 8008 | AF45: =SUM(AF36+SUM(AF38:AF44)) -> -2843 | ... AJ45: =SUM(AJ36+SUM(AJ38:AJ44)) -> 10704
B47: Capitalization
B49: Cash & Cash Equivelants | C49: ='Base Financials'!G35 -> 38016 | D49: ='Base Financials'!H35 -> 34940 | E49: ='Base Financials'!I35 -> 23646 | F49: ='Base Financials'!J35 -> 29965 | G49: ='Base Financials'!K35 -> 29943 | I49: ='Base Financials'!M35 -> 37119 | J49: ='Base Financials'!N35 -> 28098 | K49: ='Base Financials'!O35 -> 27502 | L49: ='Base Financials'!P35 -> 23646 | M49: ='Base Financials'!Q35 -> 20535 | N49: ='Base Financials'!R35 -> 24687 | O49: ='Base Financials'!S35 -> 28408 | P49: ='Base Financials'!T35 -> 29965 | ... W49: ='Base Financials'!AA35 -> 36269 | Y49: =L49 -> 23646 | Z49: =M49 -> 20535 | AA49: =N49 -> 24687 | AB49: =O49 -> 28408 | AC49: =P49 -> 29965 | AD49: =Q49 -> 40760 | AE49: =R49 -> 32695 | AF49: =S49 -> 25565 | ... AJ49: =W49 -> 36269
B50: Marketable Securities, Current | C50: ='Base Financials'!G36 -> 52927 | D50: ='Base Financials'!H36 -> 27699 | E50: ='Base Financials'!I36 -> 24658 | F50: ='Base Financials'!J36 -> 31590 | G50: ='Base Financials'!K36 -> 35228 | I50: ='Base Financials'!M36 -> 26794 | J50: ='Base Financials'!N36 -> 23413 | K50: ='Base Financials'!O36 -> 20729 | L50: ='Base Financials'!P36 -> 24658 | M50: ='Base Financials'!Q36 -> 30820 | N50: ='Base Financials'!R36 -> 31185 | O50: ='Base Financials'!S36 -> 34074 | P50: ='Base Financials'!T36 -> 31590 | ... W50: ='Base Financials'!AA36 -> 19103 | Y50: =L50 -> 24658 | Z50: =M50 -> 30820 | AA50: =N50 -> 31185 | AB50: =O50 -> 34074 | AC50: =P50 -> 31590 | AD50: =Q50 -> 32340 | AE50: =R50 -> 34455 | AF50: =S50 -> 36236 | ... AJ50: =W50 -> 19103
B51: Marketable Securities, Net of Current Portion | C51: ='Base Financials'!G43 -> 100887 | D51: ='Base Financials'!H43 -> 127877 | E51: ='Base Financials'!I43 -> 120805 | F51: ='Base Financials'!J43 -> 100544 | G51: ='Base Financials'!K43 -> 91479 | I51: ='Base Financials'!M43 -> 138683 | J51: ='Base Financials'!N43 -> 141219 | K51: ='Base Financials'!O43 -> 131077 | L51: ='Base Financials'!P43 -> 120805 | M51: ='Base Financials'!Q43 -> 114095 | N51: ='Base Financials'!R43 -> 110461 | O51: ='Base Financials'!S43 -> 104061 | P51: ='Base Financials'!T43 -> 100544 | ... W51: ='Base Financials'!AA43 -> 77614 | Y51: =L51 -> 120805 | Z51: =M51 -> 114095 | AA51: =N51 -> 110461 | AB51: =O51 -> 104061 | AC51: =P51 -> 100544 | AD51: =Q51 -> 99475 | AE51: =R51 -> 95187 | AF51: =S51 -> 91240 | ... AJ51: =W51 -> 77614
B52: Total Liquidity | C52: =SUM(C49:C51) -> 191830 | D52: =SUM(D49:D51) -> 190516 | E52: =SUM(E49:E51) -> 169109 | F52: =SUM(F49:F51) -> 162099 | G52: =SUM(G49:G51) -> 156650 | I52: =SUM(I49:I51) -> 202596 | J52: =SUM(J49:J51) -> 192730 | K52: =SUM(K49:K51) -> 179308 | L52: =SUM(L49:L51) -> 169109 | M52: =SUM(M49:M51) -> 165450 | N52: =SUM(N49:N51) -> 166333 | O52: =SUM(O49:O51) -> 166543 | P52: =SUM(P49:P51) -> 162099 | ... W52: =SUM(W49:W51) -> 132986 | Y52: =SUM(Y49:Y51) -> 169109 | Z52: =SUM(Z49:Z51) -> 165450 | AA52: =SUM(AA49:AA51) -> 166333 | AB52: =SUM(AB49:AB51) -> 166543 | AC52: =SUM(AC49:AC51) -> 162099 | AD52: =SUM(AD49:AD51) -> 172575 | AE52: =SUM(AE49:AE51) -> 162337 | AF52: =SUM(AF49:AF51) -> 153041 | ... AJ52: =SUM(AJ49:AJ51) -> 132986
B54: Balance Sheet Metrics:
B55: Accounts Receivable | C55: ='Base Financials'!G37 -> 16120 | D55: ='Base Financials'!H37 -> 26278 | E55: ='Base Financials'!I37 -> 28184 | F55: ='Base Financials'!J37 -> 29508 | G55: ='Base Financials'!K37 -> 66243 | I55: ='Base Financials'!M37 -> 30213 | J55: ='Base Financials'!N37 -> 20815 | K55: ='Base Financials'!O37 -> 21803 | L55: ='Base Financials'!P37 -> 28184 | M55: ='Base Financials'!Q37 -> 23752 | N55: ='Base Financials'!R37 -> 17936 | O55: ='Base Financials'!S37 -> 19549 | P55: ='Base Financials'!T37 -> 29508 | ... W55: ='Base Financials'!AA37 -> 46835 | Y55: =L55 -> 28184 | Z55: =M55 -> 23752 | AA55: =N55 -> 17936 | AB55: =O55 -> 19549 | AC55: =P55 -> 29508 | AD55: =Q55 -> 23194 | AE55: =R55 -> 21837 | AF55: =S55 -> 22795 | ... AJ55: =W55 -> 46835
B56: Accounts Payable | C56: ='Base Financials'!G47 -> 42296 | D56: ='Base Financials'!H47 -> 54763 | E56: ='Base Financials'!I47 -> 64115 | F56: ='Base Financials'!J47 -> 62611 | G56: ='Base Financials'!K47 -> 68960 | I56: ='Base Financials'!M47 -> 74362 | J56: ='Base Financials'!N47 -> 52682 | K56: ='Base Financials'!O47 -> 48343 | L56: ='Base Financials'!P47 -> 64115 | M56: ='Base Financials'!Q47 -> 57918 | N56: ='Base Financials'!R47 -> 42945 | O56: ='Base Financials'!S47 -> 46699 | P56: ='Base Financials'!T47 -> 62611 | ... W56: ='Base Financials'!AA47 -> 50374 | Y56: =L56 -> 64115 | Z56: =M56 -> 57918 | AA56: =N56 -> 42945 | AB56: =O56 -> 46699 | AC56: =P56 -> 62611 | AD56: =Q56 -> 58146 | AE56: =R56 -> 45753 | AF56: =S56 -> 47574 | ... AJ56: =W56 -> 50374
B57: Inventories | C57: ='Base Financials'!G38 -> 4061 | D57: ='Base Financials'!H38 -> 6580 | E57: ='Base Financials'!I38 -> 4946 | F57: ='Base Financials'!J38 -> 6331 | G57: ='Base Financials'!K38 -> 7286 | I57: ='Base Financials'!M38 -> 5876 | J57: ='Base Financials'!N38 -> 5460 | K57: ='Base Financials'!O38 -> 5433 | L57: ='Base Financials'!P38 -> 4946 | M57: ='Base Financials'!Q38 -> 6820 | N57: ='Base Financials'!R38 -> 7482 | O57: ='Base Financials'!S38 -> 7351 | P57: ='Base Financials'!T38 -> 6331 | ... W57: ='Base Financials'!AA38 -> 5925 | AE57: =R57 -> 6232 | AF57: =S57 -> 6165 | AG57: =T57 -> 7286 | AH57: =U57 -> 6911 | AI57: =V57 -> 6269 | AJ57: =W57 -> 5925
B58: Property Plant, and Equiptment | C58: ='Base Financials'!G42 -> 36766 | D58: ='Base Financials'!H42 -> 39440 | E58: ='Base Financials'!I42 -> 42117 | F58: ='Base Financials'!J42 -> 43715 | G58: ='Base Financials'!K42 -> 45680 | I58: ='Base Financials'!M42 -> 39245 | J58: ='Base Financials'!N42 -> 39304 | K58: ='Base Financials'!O42 -> 40335 | L58: ='Base Financials'!P42 -> 42117 | M58: ='Base Financials'!Q42 -> 42951 | N58: ='Base Financials'!R42 -> 43398 | O58: ='Base Financials'!S42 -> 43550 | P58: ='Base Financials'!T42 -> 43715 | ... W58: ='Base Financials'!AA42 -> 48508 | Y58: =L58 -> 42117 | Z58: =M58 -> 42951 | AA58: =N58 -> 43398 | AB58: =O58 -> 43550 | AC58: =P58 -> 43715 | AD58: =Q58 -> 43666 | AE58: =R58 -> 43546 | AF58: =S58 -> 44502 | ... AJ58: =W58 -> 48508
B59: Current Liabilities | C59: ='Base Financials'!G57 -> 258549 | D59: ='Base Financials'!H57 -> 287912 | E59: ='Base Financials'!I57 -> 302083 | F59: ='Base Financials'!J57 -> 290437 | G59: ='Base Financials'!K57 -> 308030 | I59: ='Base Financials'!M57 -> 309259 | J59: ='Base Financials'!N57 -> 283263 | K59: ='Base Financials'!O57 -> 278202 | L59: ='Base Financials'!P57 -> 302083 | M59: ='Base Financials'!Q57 -> 290020 | N59: ='Base Financials'!R57 -> 270002 | O59: ='Base Financials'!S57 -> 274764 | P59: ='Base Financials'!T57 -> 290437 | ... W59: ='Base Financials'!AA57 -> 265665 | Y59: =L59 -> 302083 | Z59: =M59 -> 290020 | AA59: =N59 -> 270002 | AB59: =O59 -> 274764 | AC59: =P59 -> 290437 | AD59: =Q59 -> 279414 | AE59: =R59 -> 263217 | AF59: =S59 -> 264904 | ... AJ59: =W59 -> 265665
B60: Total Liabilities | C60: ='Base Financials'!G57 -> 258549 | D60: ='Base Financials'!H57 -> 287912 | E60: ='Base Financials'!I57 -> 302083 | F60: ='Base Financials'!J57 -> 290437 | G60: ='Base Financials'!K57 -> 308030 | I60: ='Base Financials'!M57 -> 309259 | J60: ='Base Financials'!N57 -> 283263 | K60: ='Base Financials'!O57 -> 278202 | L60: ='Base Financials'!P57 -> 302083 | M60: ='Base Financials'!Q57 -> 290020 | N60: ='Base Financials'!R57 -> 270002 | O60: ='Base Financials'!S57 -> 274764 | P60: ='Base Financials'!T57 -> 290437 | ... W60: ='Base Financials'!AA57 -> 265665 | Y60: =L60 -> 302083 | Z60: =M60 -> 290020 | AA60: =N60 -> 270002 | AB60: =O60 -> 274764 | AC60: =P60 -> 290437 | AD60: =Q60 -> 279414 | AE60: =R60 -> 263217 | AF60: =S60 -> 264904 | ... AJ60: =W60 -> 265665
B62: Summary Debt (BS):
B63: CPLTD | C63: =+'Base Financials'!G50+'Base Financials'!G51 -> 13769 | D63: =+'Base Financials'!H50+'Base Financials'!H51 -> 15613 | E63: =+'Base Financials'!I50+'Base Financials'!I51 -> 21110 | F63: =+'Base Financials'!J50+'Base Financials'!J51 -> 15807 | G63: =+'Base Financials'!K50+'Base Financials'!K51 -> 20879 | I63: =+'Base Financials'!M50+'Base Financials'!M51 -> 16169 | J63: =+'Base Financials'!N50+'Base Financials'!N51 -> 16658 | K63: =+'Base Financials'!O50+'Base Financials'!O51 -> 24991 | L63: =+'Base Financials'!P50+'Base Financials'!P51 -> 21110 | M63: =+'Base Financials'!Q50+'Base Financials'!Q51 -> 11483 | N63: =+'Base Financials'!R50+'Base Financials'!R51 -> 12574 | O63: =+'Base Financials'!S50+'Base Financials'!S51 -> 11209 | P63: =+'Base Financials'!T50+'Base Financials'!T51 -> 15807 | ... W63: =+'Base Financials'!AA50+'Base Financials'!AA51 -> 19268 | Y63: =L63 -> 21110 | Z63: =M63 -> 11483 | AA63: =N63 -> 12574 | AB63: =O63 -> 11209 | AC63: =P63 -> 15807 | AD63: =Q63 -> 12952 | AE63: =R63 -> 12759 | AF63: =S63 -> 15108 | ... AJ63: =W63 -> 19268
B64: LTD | C64: ='Base Financials'!G54 -> 98667 | D64: ='Base Financials'!H54 -> 109106 | E64: ='Base Financials'!I54 -> 98959 | F64: ='Base Financials'!J54 -> 95281 | G64: ='Base Financials'!K54 -> 85750 | I64: ='Base Financials'!M54 -> 106629 | J64: ='Base Financials'!N54 -> 103323 | K64: ='Base Financials'!O54 -> 94700 | L64: ='Base Financials'!P54 -> 98959 | M64: ='Base Financials'!Q54 -> 99627 | N64: ='Base Financials'!R54 -> 97041 | O64: ='Base Financials'!S54 -> 98071 | P64: ='Base Financials'!T54 -> 95281 | ... W64: ='Base Financials'!AA54 -> 82430 | Y64: =L64 -> 98959 | Z64: =M64 -> 99627 | AA64: =N64 -> 97041 | AB64: =O64 -> 98071 | AC64: =P64 -> 95281 | AD64: =Q64 -> 95088 | AE64: =R64 -> 91831 | AF64: =S64 -> 86196 | ... AJ64: =W64 -> 82430
B66: Commercial Paper Outstanding | C66: ='Base Financials'!G50 -> 4996 | D66: ='Base Financials'!H50 -> 6000 | E66: ='Base Financials'!I50 -> 9982 | F66: ='Base Financials'!J50 -> 5985 | G66: ='Base Financials'!K50 -> 9967 | I66: ='Base Financials'!M50 -> 5000 | J66: ='Base Financials'!N50 -> 6999 | K66: ='Base Financials'!O50 -> 10982 | L66: ='Base Financials'!P50 -> 9982 | M66: ='Base Financials'!Q50 -> 1743 | N66: ='Base Financials'!R50 -> 1996 | O66: ='Base Financials'!S50 -> 3993 | P66: ='Base Financials'!T50 -> 5985 | ... W66: ='Base Financials'!AA50 -> 9923 | Y66: =L66 -> 9982 | Z66: =M66 -> 1743 | AA66: =N66 -> 1996 | AB66: =O66 -> 3993 | AC66: =P66 -> 5985 | AD66: =Q66 -> 1998 | AE66: =R66 -> 1997 | AF66: =S66 -> 2994 | ... AJ66: =W66 -> 9923
B67: Aggregate Term Debt, Current Portion | C67: ='Base Financials'!G51 -> 8773 | D67: ='Base Financials'!H51 -> 9613 | E67: ='Base Financials'!I51 -> 11128 | F67: ='Base Financials'!J51 -> 9822 | G67: ='Base Financials'!K51 -> 10912 | I67: ='Base Financials'!M51 -> 11169 | J67: ='Base Financials'!N51 -> 9659 | K67: ='Base Financials'!O51 -> 14009 | L67: ='Base Financials'!P51 -> 11128 | M67: ='Base Financials'!Q51 -> 9740 | N67: ='Base Financials'!R51 -> 10578 | O67: ='Base Financials'!S51 -> 7216 | P67: ='Base Financials'!T51 -> 9822 | ... W67: ='Base Financials'!AA51 -> 9345 | AF67: =S67 -> 12114 | AG67: =T67 -> 10912 | AH67: =U67 -> 10848 | AI67: =V67 -> 13638 | AJ67: =W67 -> 9345
B68: Aggregate Term Debt, Net of Current Portion | C68: ='Base Financials'!G54 -> 98667 | D68: ='Base Financials'!H54 -> 109106 | E68: ='Base Financials'!I54 -> 98959 | F68: ='Base Financials'!J54 -> 95281 | G68: ='Base Financials'!K54 -> 85750 | I68: ='Base Financials'!M54 -> 106629 | J68: ='Base Financials'!N54 -> 103323 | K68: ='Base Financials'!O54 -> 94700 | L68: ='Base Financials'!P54 -> 98959 | M68: ='Base Financials'!Q54 -> 99627 | N68: ='Base Financials'!R54 -> 97041 | O68: ='Base Financials'!S54 -> 98071 | P68: ='Base Financials'!T54 -> 95281 | ... W68: ='Base Financials'!AA54 -> 82430 | Y68: =L68 -> 98959 | Z68: =M68 -> 99627 | AA68: =N68 -> 97041 | AB68: =O68 -> 98071 | AC68: =P68 -> 95281 | AD68: =Q68 -> 95088 | AE68: =R68 -> 91831 | AF68: =S68 -> 86196 | ... AJ68: =W68 -> 82430
B69: Total Debt | C69: =SUM(C66:C68) -> 112436 | D69: =SUM(D66:D68) -> 124719 | E69: =SUM(E66:E68) -> 120069 | F69: =SUM(F66:F68) -> 111088 | G69: =SUM(G66:G68) -> 106629 | I69: =SUM(I66:I68) -> 122798 | J69: =SUM(J66:J68) -> 119981 | K69: =SUM(K66:K68) -> 119691 | L69: =SUM(L66:L68) -> 120069 | M69: =SUM(M66:M68) -> 111110 | N69: =SUM(N66:N68) -> 109615 | O69: =SUM(O66:O68) -> 109280 | P69: =SUM(P66:P68) -> 111088 | ... W69: =SUM(W66:W68) -> 101698 | Y69: =SUM(Y66:Y68) -> 108941 | Z69: =SUM(Z66:Z68) -> 101370 | AA69: =SUM(AA66:AA68) -> 99037 | AB69: =SUM(AB66:AB68) -> 102064 | AC69: =SUM(AC66:AC68) -> 101266 | AD69: =SUM(AD66:AD68) -> 97086 | AE69: =SUM(AE66:AE68) -> 93828 | AF69: =SUM(AF66:AF68) -> 101304 | ... AJ69: =SUM(AJ66:AJ68) -> 101698
B71: Total Shareholder Equity | C71: ='Base Financials'!G62 -> 65339 | D71: ='Base Financials'!H62 -> 63090 | E71: ='Base Financials'!I62 -> 50672 | F71: ='Base Financials'!J62 -> 62146 | G71: ='Base Financials'!K62 -> 56950 | I71: ='Base Financials'!M62 -> 63894 | J71: ='Base Financials'!N62 -> 59361 | K71: ='Base Financials'!O62 -> 50069 | L71: ='Base Financials'!P62 -> 50672 | M71: ='Base Financials'!Q62 -> 48689 | N71: ='Base Financials'!R62 -> 54120 | O71: ='Base Financials'!S62 -> 52236 | P71: ='Base Financials'!T62 -> 62146 | ... W71: ='Base Financials'!AA62 -> 65830 | Y71: =L71 -> 50672 | Z71: =M71 -> 48689 | AA71: =N71 -> 54120 | AB71: =O71 -> 52236 | AC71: =P71 -> 62146 | AD71: =Q71 -> 66062 | AE71: =R71 -> 66156 | AF71: =S71 -> 58670 | ... AJ71: =W71 -> 65830
B72: Total Book Capitalization | C72: =SUM(C69:C71) -> 177775 | D72: =SUM(D69:D71) -> 187809 | E72: =SUM(E69:E71) -> 170741 | F72: =SUM(F69:F71) -> 173234 | G72: =SUM(G69:G71) -> 163579 | I72: =SUM(I69:I71) -> 186692 | J72: =SUM(J69:J71) -> 179342 | K72: =SUM(K69:K71) -> 169760 | L72: =SUM(L69:L71) -> 170741 | M72: =SUM(M69:M71) -> 159799 | N72: =SUM(N69:N71) -> 163735 | O72: =SUM(O69:O71) -> 161516 | P72: =SUM(P69:P71) -> 173234 | ... W72: =SUM(W69:W71) -> 167528 | Y72: =SUM(Y69:Y71) -> 159613 | Z72: =SUM(Z69:Z71) -> 150059 | AA72: =SUM(AA69:AA71) -> 153157 | AB72: =SUM(AB69:AB71) -> 154300 | AC72: =SUM(AC69:AC71) -> 163412 | AD72: =SUM(AD69:AD71) -> 163148 | AE72: =SUM(AE69:AE71) -> 159984 | AF72: =SUM(AF69:AF71) -> 159974 | ... AJ72: =SUM(AJ69:AJ71) -> 167528
B74: Credit Metrics
B76: Total Leverage | C76: =C69/C29 -> 1.3357728 | D76: =D69/D29 -> 0.97331023 | E76: =E69/E29 -> 0.86022253 | F76: =F69/F29 -> 0.81292032 | G76: =G69/G29 -> 0.72859398 | L76: =SUM(L69/SUM(I29:L29)) -> 0.86022253 | M76: =SUM(M69/SUM(J29:M29)) -> 0.82324437 | N76: =SUM(N69/SUM(K29:N29)) -> 0.81863331 | O76: =SUM(O69/SUM(L29:O29)) -> 0.81283518 | P76: =SUM(P69/SUM(M29:P29)) -> 0.81292032 | Q76: =SUM(Q69/SUM(N29:Q29)) -> 0.76605641 | R76: =SUM(R69/SUM(O29:R29)) -> 0.7426421 | S76: =SUM(S69/SUM(P29:S29)) -> 0.70725237 | ... W76: =SUM(W69/SUM(T29:W29)) -> 0.65937472 | Y76: =Y69/Y29 -> 0.78049707 | Z76: =Z69/Z29 -> 0.75107805 | AA76: =AA69/AA29 -> 0.73963406 | AB76: =AB69/AB29 -> 0.75916188 | AC76: =AC69/AC29 -> 0.74104484 | AD76: =AD69/AD29 -> 0.6883872 | AE76: =AE69/AE29 -> 0.66622644 | AF76: =AF69/AF29 -> 0.70725237 | ... AJ76: =AJ69/AJ29 -> 0.65937472
B77: Net Leverage (C&CE) | C77: =SUM(C69-C49)/C29 -> 0.88413149 | D77: =SUM(D69-D49)/D29 -> 0.70063759 | E77: =SUM(E69-E49)/E29 -> 0.69081309 | F77: =SUM(F69-F49)/F29 -> 0.59364229 | G77: =SUM(G69-G49)/G29 -> 0.52399401 | L77: =SUM(L69-L49)/SUM(I29:L29) -> 0.69081309 | M77: =SUM(M69-M49)/SUM(J29:M29) -> 0.67109494 | N77: =SUM(N69-N49)/SUM(K29:N29) -> 0.63426438 | O77: =SUM(O69-O49)/SUM(L29:O29) -> 0.60153374 | P77: =SUM(P69-P49)/SUM(M29:P29) -> 0.59364229 | Q77: =SUM(Q69-Q49)/SUM(N29:Q29) -> 0.47704809 | R77: =SUM(R69-R49)/SUM(O29:R29) -> 0.510491 | S77: =SUM(S69-S49)/SUM(P29:S29) -> 0.5287707 | ... W77: =SUM(W69-W49)/SUM(T29:W29) -> 0.42421904 | Y77: =SUM(Y69-Y49)/Y29 -> 0.61108763 | Z77: =SUM(Z69-Z49)/Z29 -> 0.59892862 | AA77: =SUM(AA69-AA49)/AA29 -> 0.55526512 | AB77: =SUM(AB69-AB49)/AB29 -> 0.54786043 | AC77: =SUM(AC69-AC49)/AC29 -> 0.52176681 | AD77: =SUM(AD69-AD49)/AD29 -> 0.39937887 | AE77: =SUM(AE69-AE49)/AE29 -> 0.43407534 | AF77: =SUM(AF69-AF49)/AF29 -> 0.5287707 | ... AJ77: =SUM(AJ69-AJ49)/AJ29 -> 0.42421904
B78: Interest Coverage | C78: =C29/-C33 -> 8.8593832 | D78: =D29/-D33 -> 5.0478235 | E78: =E29/-E33 -> 7.1312011 | F78: =F29/-F33 -> 7.3158627 | G78: =G29/-G33 -> 5.6068117 | L78: {=SUM(I29:L29)/SUM(-I33:L33)} -> 7.1312011 | M78: {=SUM(J29:M29)/SUM(-J33:M33)} -> 8.8992483 | N78: {=SUM(K29:N29)/SUM(-K33:N33)} -> 8.8289595 | O78: {=SUM(L29:O29)/SUM(-L33:O33)} -> 9.3740761 | P78: {=SUM(M29:P29)/SUM(-M33:P33)} -> 7.3158627 | Q78: {=SUM(N29:Q29)/SUM(-N33:Q33)} -> 5.6175416 | R78: {=SUM(O29:R29)/SUM(-O33:R33)} -> 4.9736898 | S78: {=SUM(P29:S29)/SUM(-P33:S33)} -> 4.63712 | ... W78: {=SUM(T29:W29)/SUM(-T33:W33)} -> 3.4891413 | Y78: =Y29/-Y33 -> 7.1312011 | Z78: =Z29/-Z33 -> 8.8992483 | AA78: =AA29/-AA33 -> 8.8289595 | AB78: =AB29/-AB33 -> 9.3740761 | AC78: =AC29/-AC33 -> 7.3158627 | AD78: =AD29/-AD33 -> 5.6175416 | AE78: =AE29/-AE33 -> 4.9736898 | AF78: =AF29/-AF33 -> 4.63712 | ... AJ78: =AJ29/-AJ33 -> 3.4891413
B79: Debt Service Coverage | C79: {=SUM(C29+C32)/SUM(-C33:C34)} -> 6.1476446 | D79: {=SUM(D29+D32)/SUM(-D33:D34)} -> 4.1697777 | E79: {=SUM(E29+E32)/SUM(-E33:E34)} -> 5.7434263 | F79: {=SUM(F29+F32)/SUM(-F33:F34)} -> 5.5908727 | G79: {=SUM(G29+G32)/SUM(-G33:G34)} -> 5.2448854 | L79: {=SUM(I29:L29+I32:L32)/SUM(-I33:L34)} -> 5.7434263 | M79: {=SUM(J29:M29+J32:M32)/SUM(-J33:M34)} -> 6.7721804 | N79: {=SUM(K29:N29+K32:N32)/SUM(-K33:N34)} -> 6.58482 | O79: {=SUM(L29:O29+L32:O32)/SUM(-L33:O34)} -> 6.8406105 | P79: {=SUM(M29:P29+M32:P32)/SUM(-M33:P34)} -> 5.5908727 | Q79: {=SUM(N29:Q29+N32:Q32)/SUM(-N33:Q34)} -> 4.661065 | R79: {=SUM(O29:R29+O32:R32)/SUM(-O33:R34)} -> 4.3705283 | S79: {=SUM(P29:S29+P32:S32)/SUM(-P33:S34)} -> 4.1908292 | ... W79: {=SUM(T29:W29+T32:W32)/SUM(-T33:W34)} -> 3.2090535 | Y79: {=SUM(Y29+Y32)/SUM(-Y33:Y34)} -> 5.7434263 | Z79: {=SUM(Z29+Z32)/SUM(-Z33:Z34)} -> 6.7721804 | AA79: {=SUM(AA29+AA32)/SUM(-AA33:AA34)} -> 6.58482 | AB79: {=SUM(AB29+AB32)/SUM(-AB33:AB34)} -> 6.8406105 | AC79: {=SUM(AC29+AC32)/SUM(-AC33:AC34)} -> 5.5908727 | AD79: {=SUM(AD29+AD32)/SUM(-AD33:AD34)} -> 4.661065 | AE79: {=SUM(AE29+AE32)/SUM(-AE33:AE34)} -> 4.3705283 | AF79: {=SUM(AF29+AF32)/SUM(-AF33:AF34)} -> 4.1908292 | ... AJ79: {=SUM(AJ29+AJ32)/SUM(-AJ33:AJ34)} -> 3.2090535
B80: Fixed Charge Coverage | C80: {=SUM(C29)/SUM(-C32:C34)} -> 4.2485867 | D80: {=SUM(D29)/SUM(-D32:D34)} -> 3.2724417 | E80: {=SUM(E29)/SUM(-E32:E34)} -> 4.211036 | F80: {=SUM(F29)/SUM(-F32:F34)} -> 4.086391 | G80: {=SUM(G29)/SUM(-G32:G34)} -> 4.1168247 | L80: {=SUM(I29:L29)/SUM(-I32:L34)} -> 4.211036 | M80: {=SUM(J29:M29)/SUM(-J32:M34)} -> 4.514668 | N80: {=SUM(K29:N29)/SUM(-K32:N34)} -> 4.3769613 | O80: {=SUM(L29:O29)/SUM(-L32:O34)} -> 4.4856199 | P80: {=SUM(M29:P29)/SUM(-M32:P34)} -> 4.086391 | Q80: {=SUM(N29:Q29)/SUM(-N32:Q34)} -> 3.7340217 | R80: {=SUM(O29:R29)/SUM(-O32:R34)} -> 3.621368 | S80: {=SUM(P29:S29)/SUM(-P32:S34)} -> 3.5103421 | ... W80: {=SUM(T29:W29)/SUM(-T32:W34)} -> 2.7257047 | Y80: {=SUM(Y29)/SUM(-Y32:Y34)} -> 4.211036 | Z80: {=SUM(Z29)/SUM(-Z32:Z34)} -> 4.514668 | AA80: {=SUM(AA29)/SUM(-AA32:AA34)} -> 4.3769613 | AB80: {=SUM(AB29)/SUM(-AB32:AB34)} -> 4.4856199 | AC80: {=SUM(AC29)/SUM(-AC32:AC34)} -> 4.086391 | AD80: {=SUM(AD29)/SUM(-AD32:AD34)} -> 3.7340217 | AE80: {=SUM(AE29)/SUM(-AE32:AE34)} -> 3.621368 | AF80: {=SUM(AF29)/SUM(-AF32:AF34)} -> 3.5103421 | ... AJ80: {=SUM(AJ29)/SUM(-AJ32:AJ34)} -> 2.7257047
B81: Debt-to-Book Capitalization | C81: =C72/C69 -> 1.5811217 | D81: =D72/D69 -> 1.5058572 | E81: =E72/E69 -> 1.422024 | F81: =F72/F69 -> 1.5594304 | G81: =G72/G69 -> 1.5340949 | L81: =L72/L69 -> 1.422024 | M81: =M72/M69 -> 1.4382054 | N81: =N72/N69 -> 1.493728 | O81: =O72/O69 -> 1.4780015 | P81: =P72/P69 -> 1.5594304 | Q81: =Q72/Q69 -> 1.6114587 | R81: =R72/R69 -> 1.632527 | S81: =S72/S69 -> 1.5791479 | ... W81: =W72/W69 -> 1.6473087 | Y81: =Y72/Y69 -> 1.4651325 | Z81: =Z72/Z69 -> 1.4803098 | AA81: =AA72/AA69 -> 1.5464624 | AB81: =AB72/AB69 -> 1.5117965 | AC81: =AC72/AC69 -> 1.6136907 | AD81: =AD72/AD69 -> 1.6804483 | AE81: =AE72/AE69 -> 1.7050774 | AF81: =AF72/AF69 -> 1.5791479 | ... AJ81: =AJ72/AJ69 -> 1.6473087

Sheet 3-Statement Model
C2: ="Financial Statement Model for "&D5 -> Financial Statement Model for Apple
C3: $ in thousands except per share
C5: Company name | D5: Apple | I5: Select an operating scenario: | L5: Base case
C6: Ticker | D6: AAPL
C7: Circ break 1=off, 0=on | D7: 1
C8: Latest closing share price | D8: 262.82
C9: Latest closing share price date | D9: =NOW() -> 45957.003
C10: Latest fiscal year end date | D10: ='Base Financials'!K4 -> 45559
C11: Shares outstanding (millions) | D11: 4443.265
C13: INCOME STATEMENT
C14: Fiscal year | D14: =E14-1 -> 2021 | E14: =F14-1 -> 2022 | F14: =G14-1 -> 2023 | G14: =YEAR(D10) -> 2024 | H14: =G14+1 -> 2025 | I14: =H14+1 -> 2026 | J14: =I14+1 -> 2027 | K14: =J14+1 -> 2028 | L14: =K14+1 -> 2029
C15: Fiscal year end date | D15: =EOMONTH(E15,-12) -> 44469 | E15: =EOMONTH(F15,-12) -> 44834 | F15: =EOMONTH(G15,-12) -> 45199 | G15: =D10 -> 45559 | H15: =EOMONTH(G15,12) -> 45930 | I15: =EOMONTH(H15,12) -> 46295 | J15: =EOMONTH(I15,12) -> 46660 | K15: =EOMONTH(J15,12) -> 47026 | L15: =EOMONTH(K15,12) -> 47391 | N15: WSP Comments
C17: Revenue | D17: ='Base Financials'!H8 -> 365817 | E17: ='Base Financials'!I8 -> 394328 | F17: ='Base Financials'!J8 -> 383285 | G17: ='Base Financials'!K8 -> 391035 | H17: =G17*(1+H36) -> 414497.1 | I17: =H17*(1+I36) -> 443097.4 | J17: =I17*(1+J36) -> 473671.12 | K17: =J17*(1+K36) -> 506354.43 | L17: =K17*(1+L36) -> 541292.88 | N17: Previous year's revenues x (1+revenue growth rate)
C18: Cost of sales (enter as -) | D18: ='Base Financials'!H11 -> -212981 | E18: ='Base Financials'!I11 -> -223546 | F18: ='Base Financials'!J11 -> -214137 | G18: ='Base Financials'!K11 -> -210352 | H18: =H19-H17 -> -222973.12 | I18: =I19-I17 -> -238358.27 | J18: =J19-J17 -> -254804.99 | K18: =K19-K17 -> -272386.53 | L18: =L19-L17 -> -291181.2 | N18: Plug = Revenue - Gross Profit
C19: Gross Profit | D19: =SUM(D17:D18) -> 152836 | E19: =SUM(E17:E18) -> 170782 | F19: =SUM(F17:F18) -> 169148 | G19: =SUM(G17:G18) -> 180683 | H19: =H17*H37 -> 191523.98 | I19: =I17*I37 -> 204739.13 | J19: =J17*J37 -> 218866.13 | K19: =K17*K37 -> 233967.9 | L19: =L17*L37 -> 250111.68 | N19: Revenue x Gross Profit Margin forecast
C20: Research & development (enter as -) | D20: ='Base Financials'!H15 -> -21914 | E20: ='Base Financials'!I15 -> -26251 | F20: ='Base Financials'!J15 -> -29915 | G20: ='Base Financials'!K15 -> -31370 | H20: =-H38*H17 -> -33252.2 | I20: =-I38*I17 -> -35546.602 | J20: =-J38*J17 -> -37999.317 | K20: =-K38*K17 -> -40621.27 | L20: =-L38*L17 -> -43424.138 | N20: Revenue x R&D % of sales forecast
C21: Selling, general & administrative (enter as -) | D21: ='Base Financials'!H16 -> -21973 | E21: ='Base Financials'!I16 -> -25094 | F21: ='Base Financials'!J16 -> -24932 | G21: ='Base Financials'!K16 -> -26097 | H21: =-H17*H39 -> -27662.82 | I21: =-I17*I39 -> -29571.555 | J21: =-J17*J39 -> -31611.992 | K21: =-K17*K39 -> -33793.219 | L21: =-L17*L39 -> -36124.951 | N21: Revenue x SG&A % of sales forecast
C22: Operating profit (EBIT) | D22: =D19+D20+D21 -> 108949 | E22: =E19+E20+E21 -> 119437 | F22: =F19+F20+F21 -> 114301 | G22: =+SUM(G19+SUM(G20:G21)) -> 123216 | H22: =H19+H20+H21 -> 130608.96 | I22: =I19+I20+I21 -> 139620.98 | J22: =J19+J20+J21 -> 149254.83 | K22: =K19+K20+K21 -> 159553.41 | L22: =L19+L20+L21 -> 170562.59 | N22: Gross Profit - R&D - SG&A
C23: Interest income | D23: 2843 | E23: 2825 | F23: 3750 | G23: 1583.2957 | H23: =H157 -> 1644.6593 | I23: =I157 -> 1828.8949 | J23: =J157 -> 2080.4624 | K23: =K157 -> 2413.8716 | L23: =L157 -> 2835.356 | N23: Reference from interest on cash schedule; Area of Model Mess Up
C24: Interest expense (enter as -) | D24: -2645 | E24: -2931 | F24: -3933 | G24: -515 | H24: =-H143 -> -660.51368 | I24: =-I143 -> -711.33868 | J24: =-J143 -> -711.33868 | K24: =-K143 -> -711.33868 | L24: =-L143 -> -711.33868 | N24: Reference from interest expense schedule
C25: Other expense, net (enter as -) | D25: 60 | E25: -228 | F25: -382 | G25: -799.29575 | H25: =G25 -> -799.29575 | I25: =H25 -> -799.29575 | J25: =I25 -> -799.29575 | K25: =J25 -> -799.29575 | L25: =K25 -> -799.29575 | N25: Straight-line
C26: Pretax profit | D26: =SUM(D22:D25) -> 109207 | E26: =SUM(E22:E25) -> 119103 | F26: =SUM(F22:F25) -> 113736 | G26: =SUM(G22:G25) -> 123485 | H26: =SUM(H22:H25) -> 130793.81 | I26: =SUM(I22:I25) -> 139939.24 | J26: =SUM(J22:J25) -> 149824.65 | K26: =SUM(K22:K25) -> 160456.65 | L26: =SUM(L22:L25) -> 171887.32 | N26: EBIT + interest income less interest expense less other expense
C27: Taxes (enter expense as -) | D27: ='Base Financials'!H23 -> -14527 | E27: ='Base Financials'!I23 -> -19300 | F27: ='Base Financials'!J23 -> -16741 | G27: ='Base Financials'!K23 -> -29749 | H27: =-H40*H26 -> -20796.216 | I27: =-I40*I26 -> -22250.339 | J27: =-J40*J26 -> -23822.12 | K27: =-K40*K26 -> -25512.607 | L27: =-L40*L26 -> -27330.083 | N27: Pre-tax Profit x Tax Rate forecast
C28: Net income | D28: =SUM(D26:D27) -> 94680 | E28: =SUM(E26:E27) -> 99803 | F28: =SUM(F26:F27) -> 96995 | G28: =SUM(G26:G27) -> 93736 | H28: =SUM(H26:H27) -> 109997.59 | I28: =SUM(I26:I27) -> 117688.9 | J28: =SUM(J26:J27) -> 126002.53 | K28: =SUM(K26:K27) -> 134944.04 | L28: =SUM(L26:L27) -> 144557.23 | N28: Pre-tax Profit less taxes
C30: Depreciation & amortization | D30: ='Base Financials'!H73 -> 11284 | E30: ='Base Financials'!I73 -> 11104 | F30: ='Base Financials'!J73 -> 11519 | G30: ='Base Financials'!K73 -> 11445 | H30: =H107 -> 13089.456 | I30: =I107 -> 14337.351 | J30: =J107 -> 15684.388 | K30: =K107 -> 17137.408 | L30: =L107 -> 18703.722 | N30: Reference from D&A schedule
C31: EBITDA | D31: =D22+D30 -> 120233 | E31: =E22+E30 -> 130541 | F31: =F22+F30 -> 125820 | G31: =G22+G30 -> 134661 | H31: =H22+H30 -> 143698.42 | I31: =I22+I30 -> 153958.33 | J31: =J22+J30 -> 164939.21 | K31: =K22+K30 -> 176690.82 | L31: =L22+L30 -> 189266.32 | N31: EBIT + D&A
C32: Stock based compensation | D32: ='Base Financials'!H74 -> 7906 | E32: ='Base Financials'!I74 -> 9038 | F32: ='Base Financials'!J74 -> 10833 | G32: ='Base Financials'!K74 -> 11688 | H32: =G32*(1+H36) -> 12389.28 | I32: =H32*(1+I36) -> 13244.14 | J32: =I32*(1+J36) -> 14157.986 | K32: =J32*(1+K36) -> 15134.887 | L32: =K32*(1+L36) -> 16179.194 | N32: WSP assumption: grow SBC in-line with revenue growth
C33: Adjusted EBITDA | D33: =SUM(D31:D32) -> 128139 | E33: =SUM(E31:E32) -> 139579 | F33: =SUM(F31:F32) -> 136653 | G33: =SUM(G31:G32) -> 146349 | H33: =SUM(H31:H32) -> 156087.7 | I33: =SUM(I31:I32) -> 167202.47 | J33: =SUM(J31:J32) -> 179097.2 | K33: =SUM(K31:K32) -> 191825.7 | L33: =SUM(L31:L32) -> 205445.51 | N33: EBITDA + Stock-based compensation
C35: Growth rates & margins
C36: Revenue growth | E36: =E17/D17-1 -> 0.077937876 | F36: =F17/E17-1 -> -0.028004605 | G36: =G17/F17-1 -> 0.020219941 | H36: =H184 -> 0.06 | I36: =I184 -> 0.069 | J36: =J184 -> 0.069 | K36: =K184 -> 0.069 | L36: =L184 -> 0.069 | N36: Consensus estimates through 2021; straight-line growth rate thereafter
C37: Gross profit margin | D37: =D19/D17 -> 0.4177936 | E37: =E19/E17 -> 0.43309631 | F37: =F19/F17 -> 0.4413113 | G37: =G19/G17 -> 0.4620635 | H37: =G37 -> 0.4620635 | I37: =H37 -> 0.4620635 | J37: =I37 -> 0.4620635 | K37: =J37 -> 0.4620635 | L37: =K37 -> 0.4620635 | N37: Straight line last historical year
C38: R&D % of sales | D38: =-D20/D17 -> 0.059904269 | E38: =-E20/E17 -> 0.066571484 | F38: =-F20/F17 -> 0.078048971 | G38: =-G20/G17 -> 0.080222998 | H38: =G38 -> 0.080222998 | I38: =H38 -> 0.080222998 | J38: =I38 -> 0.080222998 | K38: =J38 -> 0.080222998 | L38: =K38 -> 0.080222998 | N38: Straight line last historical year
C39: SG&A % of sales | D39: =-D21/D17 -> 0.060065552 | E39: =-E21/E17 -> 0.063637378 | F39: =-F21/F17 -> 0.065048202 | G39: =-G21/G17 -> 0.066738272 | H39: =G39 -> 0.066738272 | I39: =H39 -> 0.066738272 | J39: =I39 -> 0.066738272 | K39: =J39 -> 0.066738272 | L39: =K39 -> 0.066738272 | N39: Straight line last historical year
C40: Tax rate | D40: =-(D27/D26) -> 0.13302261 | E40: =-(E27/E26) -> 0.16204462 | F40: =-(F27/F26) -> 0.14719174 | G40: =-(G27/G26) -> 0.24091185 | H40: 0.159 | I40: =H40 -> 0.159 | J40: =I40 -> 0.159 | K40: =J40 -> 0.159 | L40: =K40 -> 0.159 | N40: Straight line last historical year
C42: BALANCE SHEET
C43: =C14 -> Fiscal year | D43: =D14 -> 2021 | E43: =E14 -> 2022 | F43: =F14 -> 2023 | G43: =G14 -> 2024 | H43: =H14 -> 2025 | I43: =I14 -> 2026 | J43: =J14 -> 2027 | ... L43: =L14 -> 2029
C44: =C15 -> Fiscal year end date | D44: =D15 -> 44469 | E44: =E15 -> 44834 | F44: =F15 -> 45199 | G44: =G15 -> 45559 | H44: =H15 -> 45930 | I44: =I15 -> 46295 | J44: =J15 -> 46660 | ... L44: =L15 -> 47391
C45: Cash & equivalents, ST and LT marketable securities | D45: ='Base Financials'!H35+'Base Financials'!H36+'Base Financials'!H43 -> 190516 | E45: ='Base Financials'!I35+'Base Financials'!I36+'Base Financials'!I43 -> 169109 | F45: ='Base Financials'!J35+'Base Financials'!J36+'Base Financials'!J43 -> 162099 | G45: ='Base Financials'!K35+'Base Financials'!K36+'Base Financials'!K43 -> 156650 | H45: =+G45+H91 -> 172281.85 | I45: =+H45+I91 -> 193497.12 | J45: =+I45+J91 -> 222595.36 | K45: =+J45+K91 -> 260178.95 | L45: =+K45+L91 -> 306892.25 | N45: Reference from 'net change in cash' line on the cash flow statement
C46: Accounts receivable | D46: ='Base Financials'!H37 -> 26278 | E46: ='Base Financials'!I37 -> 28184 | F46: ='Base Financials'!J37 -> 29508 | G46: ='Base Financials'!K37 -> 66243 | H46: =G46*(1+H36) -> 70217.58 | I46: =H46*(1+I36) -> 75062.593 | J46: =I46*(1+J36) -> 80241.912 | K46: =J46*(1+K36) -> 85778.604 | L46: =K46*(1+L36) -> 91697.328 | N46: Grow in-line with revenue growth
C47: Inventories | D47: ='Base Financials'!H38 -> 6580 | E47: ='Base Financials'!I38 -> 4946 | F47: ='Base Financials'!J38 -> 6331 | G47: ='Base Financials'!K38 -> 7286 | H47: =G47*H18/G18 -> 7723.16 | I47: =H47*I18/H18 -> 8256.058 | J47: =I47*J18/I18 -> 8825.726 | K47: =J47*K18/J18 -> 9434.7011 | L47: =K47*L18/K18 -> 10085.696 | N47: Grow in-line with cost of sales growth
C48: Other current assets | D48: ='Base Financials'!H39 -> 39339 | E48: ='Base Financials'!I39 -> 53971 | F48: ='Base Financials'!J39 -> 46172 | G48: ='Base Financials'!K39 -> 14287 | H48: =G48*(1+H36) -> 15144.22 | I48: =H48*(1+I36) -> 16189.171 | J48: =I48*(1+J36) -> 17306.224 | K48: =J48*(1+K36) -> 18500.353 | L48: =K48*(1+L36) -> 19776.878 | N48: Grow in-line with revenue growth
C49: Property, plant & equipment | D49: ='Base Financials'!H42 -> 39440 | E49: ='Base Financials'!I42 -> 42117 | F49: ='Base Financials'!J42 -> 43715 | G49: ='Base Financials'!K42 -> 45680 | H49: =H100 -> 43967.244 | I49: =I100 -> 42443.428 | J49: =J100 -> 41108.552 | K49: =K100 -> 39962.616 | L49: =L100 -> 39005.62 | N49: Reference from PP&E schedule
C50: Other non current assets | D50: ='Base Financials'!H44 -> 48849 | E50: ='Base Financials'!I44 -> 54428 | F50: ='Base Financials'!J44 -> 64758 | G50: ='Base Financials'!K44 -> 74834 | H50: =G50*(1+H36) -> 79324.04 | I50: =H50*(1+I36) -> 84797.399 | J50: =I50*(1+J36) -> 90648.419 | K50: =J50*(1+K36) -> 96903.16 | L50: =K50*(1+L36) -> 103589.48 | N50: Grow in-line with revenue growth
C51: Total assets | D51: =SUM(D45:D50) -> 351002 | E51: =SUM(E45:E50) -> 352755 | F51: =SUM(F45:F50) -> 352583 | G51: =SUM(G45:G50) -> 364980 | H51: =SUM(H45:H50) -> 388658.1 | I51: =SUM(I45:I50) -> 420245.77 | J51: =SUM(J45:J50) -> 460726.2 | K51: =SUM(K45:K50) -> 510758.39 | L51: =SUM(L45:L50) -> 571047.25
C53: Accounts payable | D53: ='Base Financials'!H47 -> 54763 | E53: ='Base Financials'!I47 -> 64115 | F53: ='Base Financials'!J47 -> 62611 | G53: ='Base Financials'!K47 -> 68960 | H53: =G53*H18/G18 -> 73097.6 | I53: =H53*I18/H18 -> 78141.334 | J53: =I53*J18/I18 -> 83533.086 | K53: =J53*K18/J18 -> 89296.869 | L53: =K53*L18/K18 -> 95458.353 | N53: Grow in-line with cost of sales growth
C54: Other current liabilities | D54: ='Base Financials'!H49 -> 47493 | E54: ='Base Financials'!I49 -> 60845 | F54: ='Base Financials'!J49 -> 58829 | G54: ='Base Financials'!K49 -> 78304 | H54: =G54*(1+H36) -> 83002.24 | I54: =H54*(1+I36) -> 88729.395 | J54: =I54*(1+J36) -> 94851.723 | K54: =J54*(1+K36) -> 101396.49 | L54: =K54*(1+L36) -> 108392.85 | N54: Grow in-line with revenue growth
C55: Deferred revenue (current) | D55: ='Base Financials'!H48 -> 7612 | E55: ='Base Financials'!I48 -> 7912 | F55: ='Base Financials'!J48 -> 8061 | G55: ='Base Financials'!K48 -> 8249 | H55: =G55*(1+H36) -> 8743.94 | I55: =H55*(1+I36) -> 9347.2719 | J55: =I55*(1+J36) -> 9992.2336 | K55: =J55*(1+K36) -> 10681.698 | L55: =K55*(1+L36) -> 11418.735 | N55: Grow in-line with revenue growth
C56: Commercial paper / revolver | D56: ='Base Financials'!H50 -> 6000 | E56: ='Base Financials'!I50 -> 9982 | F56: ='Base Financials'!J50 -> 5985 | G56: ='Base Financials'!K50 -> 9967 | H56: =H136 -> 12000 | I56: =I136 -> 12000 | J56: =J136 -> 12000 | K56: =K136 -> 12000 | L56: =L136 -> 12000 | N56: Reference EOP balance from CP/revolver schedule
C57: Long term debt (includes current portion) | D57: =+'Base Financials'!H51+'Base Financials'!H54 -> 118719 | E57: =+'Base Financials'!I51+'Base Financials'!I54 -> 110087 | F57: =+'Base Financials'!J51+'Base Financials'!J54 -> 105103 | G57: =+'Base Financials'!K51+'Base Financials'!K54 -> 96662 | H57: =G57 -> 96662 | I57: =H57 -> 96662 | J57: =I57 -> 96662 | K57: =J57 -> 96662 | L57: =K57 -> 96662 | N57: WSP assumption: straight-line
C58: Other non current liabilities | D58: ='Base Financials'!H56 -> 53325 | E58: ='Base Financials'!I56 -> 49142 | F58: ='Base Financials'!J56 -> 49848 | G58: ='Base Financials'!K56 -> 45888 | H58: =G58*(1+H36) -> 48641.28 | I58: =H58*(1+I36) -> 51997.528 | J58: =I58*(1+J36) -> 55585.358 | K58: =J58*(1+K36) -> 59420.747 | L58: =K58*(1+L36) -> 63520.779 | N58: Grow in-line with revenue growth
C59: Total liabilities | D59: =SUM(D53:D58) -> 287912 | E59: =SUM(E53:E58) -> 302083 | F59: =SUM(F53:F58) -> 290437 | G59: =SUM(G53:G58) -> 308030 | H59: =SUM(H53:H58) -> 322147.06 | I59: =SUM(I53:I58) -> 336877.53 | J59: =SUM(J53:J58) -> 352624.4 | K59: =SUM(K53:K58) -> 369457.81 | L59: =SUM(L53:L58) -> 387452.72
C61: Common stock | D61: ='Base Financials'!H59 -> 57365 | E61: ='Base Financials'!I59 -> 64849 | F61: ='Base Financials'!J59 -> 73812 | G61: ='Base Financials'!K59 -> 83276 | H61: =G61+H32 -> 95665.28 | I61: =H61+I32 -> 108909.42 | J61: =I61+J32 -> 123067.41 | K61: =J61+K32 -> 138202.29 | L61: =K61+L32 -> 154381.49 | N61: Increase by stock-based compensation forecasted in the I/S section
C62: Retained earnings | D62: ='Base Financials'!H60 -> 5562 | E62: ='Base Financials'!I60 -> -3068 | F62: ='Base Financials'!J60 -> -214 | G62: ='Base Financials'!K60 -> -19154 | H62: =H120 -> -21982.245 | I62: =I120 -> -18369.177 | J62: =J120 -> -7793.6085 | K62: =K120 -> 10270.289 | L62: =L120 -> 36385.041 | N62: Reference from Retained Earnings schedule
C63: Other comprehensive income | D63: ='Base Financials'!H61 -> 163 | E63: ='Base Financials'!I61 -> -11109 | F63: ='Base Financials'!J61 -> -11452 | G63: ='Base Financials'!K61 -> -7172 | H63: =G63 -> -7172 | I63: =H63 -> -7172 | J63: =I63 -> -7172 | K63: =J63 -> -7172 | L63: =K63 -> -7172 | N63: WSP assumption: straight-line
C64: Total equity | D64: =SUM(D61:D63) -> 63090 | E64: =SUM(E61:E63) -> 50672 | F64: =SUM(F61:F63) -> 62146 | G64: =SUM(G61:G63) -> 56950 | H64: =SUM(H61:H63) -> 66511.035 | I64: =SUM(I61:I63) -> 83368.244 | J64: =SUM(J61:J63) -> 108101.8 | K64: =SUM(K61:K63) -> 141300.58 | L64: =SUM(L61:L63) -> 183594.53
C66: Balance check | D66: =ROUND(D51-D59-D64,3) -> 0 | E66: =ROUND(E51-E59-E64,3) -> 0 | F66: =ROUND(F51-F59-F64,3) -> 0 | G66: =ROUND(G51-G59-G64,3) -> 0 | H66: =ROUND(H51-H59-H64,3) -> 0 | I66: =ROUND(I51-I59-I64,3) -> 0 | J66: =ROUND(J51-J59-J64,3) -> 0 | K66: =ROUND(K51-K59-K64,3) -> 0 | L66: =ROUND(L51-L59-L64,3) -> 0
C68: CASH FLOW STATEMENT
C69: =C14 -> Fiscal year | D69: =D43 -> 2021 | E69: =E43 -> 2022 | F69: =F43 -> 2023 | G69: =G43 -> 2024 | H69: =H14 -> 2025 | I69: =I14 -> 2026 | J69: =J14 -> 2027 | K69: =K14 -> 2028 | L69: =L14 -> 2029
C70: =C15 -> Fiscal year end date | D70: =D44 -> 44469 | E70: =E44 -> 44834 | F70: =F44 -> 45199 | G70: =G44 -> 45559 | H70: =H15 -> 45930 | I70: =I15 -> 46295 | J70: =J15 -> 46660 | K70: =K15 -> 47026 | L70: =L15 -> 47391
C72: Net income | E72: =E28 -> 99803 | F72: =F28 -> 96995 | G72: =G28 -> 93736 | H72: =H28 -> 109997.59 | I72: =I28 -> 117688.9 | J72: =J28 -> 126002.53 | K72: =K28 -> 134944.04 | L72: =L28 -> 144557.23 | N72: Reference from the I/S
C73: Depreciation and amortization | E73: =E30 -> 11104 | F73: =F30 -> 11519 | G73: =G30 -> 11445 | H73: =H30 -> 13089.456 | I73: =I30 -> 14337.351 | J73: =J30 -> 15684.388 | K73: =K30 -> 17137.408 | L73: =L30 -> 18703.722 | N73: Reference from the I/S
C74: Stock based compensation | E74: =E32 -> 9038 | F74: =F32 -> 10833 | G74: =G32 -> 11688 | H74: =H32 -> 12389.28 | I74: =I32 -> 13244.14 | J74: =J32 -> 14157.986 | K74: =K32 -> 15134.887 | L74: =L32 -> 16179.194
C75: Decreases / (Increases) in working capital assets | E75: =SUM(D46:D48)-SUM(E46:E48) -> -14904 | F75: =SUM(E46:E48)-SUM(F46:F48) -> 5090 | G75: =SUM(F46:F48)-SUM(G46:G48) -> -5805 | H75: =SUM(G46:G48)-SUM(H46:H48) -> -5268.96 | I75: =SUM(H46:H48)-SUM(I46:I48) -> -6422.8622 | J75: =SUM(I46:I48)-SUM(J46:J48) -> -6866.0397 | K75: =SUM(J46:J48)-SUM(K46:K48) -> -7339.7965 | L75: =SUM(K46:K48)-SUM(L46:L48) -> -7846.2424
C76: Increases / (Decreases) in working capital liabilities | E76: =SUM(E53:E55)-SUM(D53:D55) -> 23004 | F76: =SUM(F53:F55)-SUM(E53:E55) -> -3371 | G76: =SUM(G53:G55)-SUM(F53:F55) -> 26012 | H76: =SUM(H53:H55)-SUM(G53:G55) -> 9330.78 | I76: =SUM(I53:I55)-SUM(H53:H55) -> 11374.221 | J76: =SUM(J53:J55)-SUM(I53:I55) -> 12159.042 | K76: =SUM(K53:K55)-SUM(J53:J55) -> 12998.016 | L76: =SUM(L53:L55)-SUM(K53:K55) -> 13894.879
C77: Other non current assets | E77: =-E112 -> 0 | F77: =-F112 -> 0 | G77: =-G112 -> 0 | H77: =-H112 -> -25313.74 | I77: =-I112 -> -27733.894 | J77: =-J112 -> -29647.533 | K77: =-K112 -> -31693.213 | L77: =-L112 -> -33880.044 | N77: Reference from schedule NOT the B/S: Only include 'Additions' (as outflow)
C78: Other non current liabilities | E78: =E58-D58 -> -4183 | F78: =F58-E58 -> 706 | G78: =G58-F58 -> -3960 | H78: =H58-G58 -> 2753.28 | I78: =I58-H58 -> 3356.2483 | J78: =J58-I58 -> 3587.8295 | K78: =K58-J58 -> 3835.3897 | L78: =L58-K58 -> 4100.0316
C79: Cash from operating activities | E79: =SUM(E72:E78) -> 123862 | F79: =SUM(F72:F78) -> 121772 | G79: =SUM(G72:G78) -> 133116 | H79: =SUM(H72:H78) -> 116977.69 | I79: =SUM(I72:I78) -> 125844.1 | J79: =SUM(J72:J78) -> 135078.21 | K79: =SUM(K72:K78) -> 145016.73 | L79: =SUM(L72:L78) -> 155708.77
C81: Capital expenditures | E81: =-(E98) -> 10708 | F81: =-(F98) -> 10959 | G81: =-(G98) -> 9447 | H81: =-(H98) -> 9447 | I81: =-(I98) -> 9447 | J81: =-(J98) -> 9447 | K81: =-(K98) -> 9447 | L81: =-(L98) -> 9447 | N81: Reference from PP&E schedule
C82: Cash from investing activities | E82: =IFERROR(E81,"NA") -> 10708 | F82: =IFERROR(F81,"NA") -> 10959 | G82: =IFERROR(G81,"NA") -> 9447 | H82: =IFERROR(H81,"NA") -> 9447 | I82: =IFERROR(I81,"NA") -> 9447 | J82: =IFERROR(J81,"NA") -> 9447 | K82: =IFERROR(K81,"NA") -> 9447 | L82: =IFERROR(L81,"NA") -> 9447
C84: Long term debt | E84: =E57-D57 -> -8632 | F84: =F57-E57 -> -4984 | G84: =G57-F57 -> -8441 | H84: =H57-G57 -> 0 | I84: =I57-H57 -> 0 | J84: =J57-I57 -> 0 | K84: =K57-J57 -> 0 | L84: =L57-K57 -> 0
C85: Commercial paper/ Revolver | E85: =E56-D56 -> 3982 | F85: =F56-E56 -> -3997 | G85: =G56-F56 -> 3982 | H85: =H56-G56 -> 2033 | I85: =I56-H56 -> 0 | J85: =J56-I56 -> 0 | K85: =K56-J56 -> 0 | L85: =L56-K56 -> 0 | N85: Reference from B/S
C86: Share repurchases | E86: =E119 -> 0 | F86: =F119 -> 0 | G86: =G119 -> -94949 | H86: =H119 -> -94949 | I86: =I119 -> -94949 | J86: =J119 -> -94949 | K86: =K119 -> -94949 | L86: =L119 -> -94949 | N86: Reference from Retained Earnings schedule
C87: Common dividends | E87: =E118 -> 0 | F87: =F118 -> 0 | G87: =G118 -> -15234 | H87: =H118 -> -17876.839 | I87: =I118 -> -19126.832 | J87: =J118 -> -20477.966 | K87: =K118 -> -21931.142 | L87: =L118 -> -23493.48 | N87: Reference from Retained Earnings schedule
C88: Common dividends | E88: =E119 -> 0 | F88: =F119 -> 0 | G88: =G119 -> -94949 | H88: =H119 -> -94949 | I88: =I119 -> -94949 | J88: =J119 -> -94949 | K88: =K119 -> -94949 | L88: =L119 -> -94949 | N88: Reference from Retained Earnings schedule
C89: Cash from financing activities | E89: =SUM(E84:E87) -> -4650 | F89: =SUM(F84:F87) -> -8981 | G89: =SUM(G84:G87) -> -114642 | H89: =SUM(H84:H87) -> -110792.84 | I89: =SUM(I84:I87) -> -114075.83 | J89: =SUM(J84:J87) -> -115426.97 | K89: =SUM(K84:K87) -> -116880.14 | L89: =SUM(L84:L87) -> -118442.48
C91: Net change in cash during period | E91: =E79+E82+E89 -> 129920 | F91: =F79+F82+F89 -> 123750 | G91: =G79+G82+G89 -> 27921 | H91: =H79+H82+H89 -> 15631.851 | I91: =I79+I82+I89 -> 21215.272 | J91: =J79+J82+J89 -> 29098.241 | K91: =K79+K82+K89 -> 37583.589 | L91: =L79+L82+L89 -> 46713.292
C93: PROPERTY, PLANT & EQUIPMENT
C94: =C14 -> Fiscal year | E94: =E14 -> 2022 | F94: =F14 -> 2023 | G94: =G14 -> 2024 | H94: =H14 -> 2025 | I94: =I14 -> 2026 | J94: =J14 -> 2027 | K94: =K14 -> 2028 | L94: =L14 -> 2029
C95: =C15 -> Fiscal year end date | E95: =E15 -> 44834 | F95: =F15 -> 45199 | G95: =G15 -> 45559 | H95: =H15 -> 45930 | I95: =I15 -> 46295 | J95: =J15 -> 46660 | K95: =K15 -> 47026 | L95: =L15 -> 47391
H96: Forecast
C97: Beginning of period | E97: =D100 -> 39440 | F97: =E100 -> 42117 | G97: =F100 -> 43715 | H97: =G100 -> 45680 | I97: =H100 -> 43967.244 | J97: =I100 -> 42443.428 | K97: =J100 -> 41108.552 | L97: =K100 -> 39962.616 | N97: BOP = Previous year EOP
C98: Plus: Capital expenditures | D98: ='Base Financials'!H88 -> -11085 | E98: ='Base Financials'!I88 -> -10708 | F98: ='Base Financials'!J88 -> -10959 | G98: ='Base Financials'!K88 -> -9447 | H98: =G98 -> -9447 | I98: =H98 -> -9447 | J98: =I98 -> -9447 | K98: =J98 -> -9447 | L98: =K98 -> -9447 | N98: First two years - consensus estimates, then grow with revenue
C99: Less: Depreciation | D99: 9500 | E99: 8700 | F99: 8500 | G99: 8200 | H99: =-(H102*H98) -> 7734.2441 | I99: =-(I102*I98) -> 7923.1841 | J99: =-(J102*J98) -> 8112.1241 | K99: =-(K102*K98) -> 8301.0641 | L99: =-(L102*L98) -> 8490.0041 | N99: Capex x 'D&A related to PP&E as a % of capex' ratio (below)
C100: End of period | D100: =D49 -> 39440 | E100: =E49 -> 42117 | F100: =F49 -> 43715 | G100: =G49 -> 45680 | H100: =SUM(H97:H99) -> 43967.244 | I100: =SUM(I97:I99) -> 42443.428 | J100: =SUM(J97:J99) -> 41108.552 | K100: =SUM(K97:K99) -> 39962.616 | L100: =SUM(L97:L99) -> 39005.62 | N100: BOP + Capex - Depreciation
N101: Step
C102: D&A related to PP&E as a % of capex | D102: =-(D99/D98) -> 0.85701398 | E102: =-(E99/E98) -> 0.81247665 | F102: =-(F99/F98) -> 0.77561821 | G102: =-(G99/G98) -> 0.86800042 | H102: =AVERAGE(E102:G102) -> 0.81869843 | I102: =H102+$N$102 -> 0.83869843 | J102: =I102+$N$102 -> 0.85869843 | K102: =J102+$N$102 -> 0.87869843 | L102: =K102+$N$102 -> 0.89869843 | N102: 0.02
C104: IMPUTING TOTAL DEPRECIATION & AMORTIZATION
C105: D&A not related to PP&E | D105: =D107+D99 -> 20784 | E105: =E107+E99 -> 19804 | F105: =F107+F99 -> 20019 | G105: =G107+G99 -> 19645 | H105: =H106*H17 -> 20823.7 | I105: =I106*I17 -> 22260.535 | J105: =J106*J17 -> 23796.512 | K105: =K106*K17 -> 25438.472 | L105: =L106*L17 -> 27193.726 | N105: Revenue x 'as % of revenue' assumption
C106: as % of revenue | D106: =D105/D17 -> 0.056815293 | E106: =E105/E17 -> 0.05022215 | F106: =F105/F17 -> 0.052230064 | G106: =G105/G17 -> 0.05023847 | H106: =G106 -> 0.05023847 | I106: =H106 -> 0.05023847 | J106: =I106 -> 0.05023847 | K106: =J106 -> 0.05023847 | L106: =K106 -> 0.05023847 | N106: Straight line last historical % of revenue - WSP assumption
C107: Depreciation & Amortization - Total | D107: =D30 -> 11284 | E107: =E30 -> 11104 | F107: =F30 -> 11519 | G107: =G30 -> 11445 | H107: =-H99+H105 -> 13089.456 | I107: =-I99+I105 -> 14337.351 | J107: =-J99+J105 -> 15684.388 | K107: =-K99+K105 -> 17137.408 | L107: =-L99+L105 -> 18703.722 | N107: D&A from PP&E + D&A not from PP&E
C109: OTHER NON-CURRENT ASSETS
C110: Beginning of period | H110: =G113 -> 74834 | I110: =H113 -> 79324.04 | J110: =I113 -> 84797.399 | K110: =J113 -> 90648.419 | L110: =K113 -> 96903.16 | N110: BOP = Previous year EOP
C111: Less: Amortization of intangible assets | H111: =-(H105) -> -20823.7 | I111: =-(I105) -> -22260.535 | J111: =-(J105) -> -23796.512 | K111: =-(K105) -> -25438.472 | L111: =-(L105) -> -27193.726 | N111: Assume all D&A not from PP&E is in non-current assets
C112: Plus: Additions | H112: =H113-H111-H110 -> 25313.74 | I112: =I113-I111-I110 -> 27733.894 | J112: =J113-J111-J110 -> 29647.533 | K112: =K113-K111-K110 -> 31693.213 | L112: =L113-L111-L110 -> 33880.044 | N112: Because we already know the EOP balance, this is a plug: EOP - D&A not from PP&E - BOP
C113: End of period | E113: =E50 -> 54428 | F113: =F50 -> 64758 | G113: =G50 -> 74834 | H113: =H50 -> 79324.04 | I113: =I50 -> 84797.399 | J113: =J50 -> 90648.419 | K113: =K50 -> 96903.16 | L113: =L50 -> 103589.48 | N113: Referenced from balance sheet
C115: RETAINED EARNINGS
C116: Beginning of period | H116: =G120 -> -19154 | I116: =H120 -> -21982.245 | J116: =I120 -> -18369.177 | K116: =J120 -> -7793.6085 | L116: =K120 -> 10270.289 | N116: BOP = Previous year EOP
C117: Plus: Net income | G117: =G28 -> 93736 | H117: =H28 -> 109997.59 | I117: =I28 -> 117688.9 | J117: =J28 -> 126002.53 | K117: =K28 -> 134944.04 | L117: =L28 -> 144557.23 | N117: Reference from income statement
C118: Less: Dividends | G118: =FCF!G43 -> -15234 | H118: =H117*G118/G117 -> -17876.839 | I118: =I117*H118/H117 -> -19126.832 | J118: =J117*I118/I117 -> -20477.966 | K118: =K117*J118/J117 -> -21931.142 | L118: =L117*K118/K117 -> -23493.48 | N118: WSP assumption: Hold last historical year's dividend payout ratio constant
C119: Less: Repurchases | G119: ='Base Financials'!K99 -> -94949 | H119: =G119 -> -94949 | I119: =H119 -> -94949 | J119: =I119 -> -94949 | K119: =J119 -> -94949 | L119: =K119 -> -94949 | N119: WSP assumption: Straight-line last historical year repurchases
...

Sheet DCF
B2: Discounted Cash Flow Valuation
B3: ='[1]Financials '!$B$3 -> $ and shares in millions, except per share data
B4: Most recent fiscal year end | D4: ='Base Financials'!K4 -> 45559 | F4: Discount rate (WACC) | H4: ='[1]WACC Done'!E21 -> 0.077864311 | I4: Link from WACC
B5: End of first fiscal year | D5: =EOMONTH(D4,12) -> 45930 | F5: Share price (Public Co) | H5: 262.82 | I5: Source: CIQ
B6: Most recent quarter end date | D6: ='Base Financials'!AA4 -> 45833 | F6: Share price date | H6: 45956
B7: Valuation date | D7: 45956 | F7: Midyear adjustment? | H7: 1
B8: Portion of First Year Cash Flows | D8: =YEARFRAC(D7,D5) -> 0.072222222
F9: Case active: | H9: ='[1]2019 FSM Update Complete'!L5 -> Base case
B10: Unlevered Free Cash Flows
C11: LTM | D11: Actual | E11: Forecasts
B12: Fiscal year ended | C12: =D7 -> 45956 | D12: =D4 -> 45559 | E12: =EOMONTH(D12,12) -> 45930 | F12: =EOMONTH(E12,12) -> 46295 | G12: =EOMONTH(F12,12) -> 46660 | H12: =EOMONTH(G12,12) -> 47026 | I12: =EOMONTH(H12,12) -> 47391
B14: Revenue | C14: =FCF!AJ11 -> 408625 | D14: =FCF!G11 -> 391035 | E14: ='3-Statement Model'!H17 -> 414497.1 | F14: ='3-Statement Model'!I17 -> 443097.4 | G14: ='3-Statement Model'!J17 -> 473671.12 | H14: ='3-Statement Model'!K17 -> 506354.43 | I14: ='3-Statement Model'!L17 -> 541292.88
B15: % growth | E15: =SUM(E14/D14)-1 -> 0.06 | F15: =SUM(F14/E14)-1 -> 0.069 | G15: =SUM(G14/F14)-1 -> 0.069 | H15: =SUM(H14/G14)-1 -> 0.069 | I15: =SUM(I14/H14)-1 -> 0.069
B16: EBITDA | C16: =FCF!AJ25 -> 141696 | D16: =FCF!G25 -> 134661 | E16: ='3-Statement Model'!H31 -> 143698.42 | F16: ='3-Statement Model'!I31 -> 153958.33 | G16: ='3-Statement Model'!J31 -> 164939.21 | H16: ='3-Statement Model'!K31 -> 176690.82 | I16: ='3-Statement Model'!L31 -> 189266.32
B17: % margin | D17: =D16/D14 -> 0.34437071 | E17: =E16/E14 -> 0.34668135 | F17: =F16/F14 -> 0.34745934 | G17: =G16/G14 -> 0.34821463 | H17: =H16/H14 -> 0.34894692 | I17: =I16/I14 -> 0.34965602
B18: EBIT | C18: =FCF!AJ21 -> 130214 | D18: =FCF!G21 -> 123216 | E18: ='3-Statement Model'!H22 -> 130608.96 | F18: ='3-Statement Model'!I22 -> 139620.98 | G18: ='3-Statement Model'!J22 -> 149254.83 | H18: ='3-Statement Model'!K22 -> 159553.41 | I18: ='3-Statement Model'!L22 -> 170562.59
B19: % margin | D19: =D18/D14 -> 0.31510223 | E19: =E18/E14 -> 0.31510223 | F19: =F18/F14 -> 0.31510223 | G19: =G18/G14 -> 0.31510223 | H19: =H18/H14 -> 0.31510223 | I19: =I18/I14 -> 0.31510223
B21: Tax on EBIT | D21: ='3-Statement Model'!G27 -> -29749 | E21: =+E18*E22 -> 20766.825 | F21: =+F18*F22 -> 22199.736 | G21: =+G18*G22 -> 23731.517 | H21: =+H18*H22 -> 25368.992 | I21: =+I18*I22 -> 27119.452
B22: Tax rate | D22: =D21/D18 -> -0.2414378 | E22: ='3-Statement Model'!H40 -> 0.159 | F22: ='3-Statement Model'!I40 -> 0.159 | G22: ='3-Statement Model'!J40 -> 0.159 | H22: ='3-Statement Model'!K40 -> 0.159 | I22: ='3-Statement Model'!L40 -> 0.159
B23: NOPAT (aka EBIAT) | D23: =+D21+D18 -> 93467 | E23: =E18*(1-E22) -> 109842.14 | F23: =F18*(1-F22) -> 117421.24 | G23: =G18*(1-G22) -> 125523.31 | H23: =H18*(1-H22) -> 134184.42 | I23: =I18*(1-I22) -> 143443.14
B25: Depreciation & amortization | D25: ='3-Statement Model'!G30 -> 11445 | E25: ='3-Statement Model'!H30 -> 13089.456 | F25: ='3-Statement Model'!I30 -> 14337.351 | G25: ='3-Statement Model'!J30 -> 15684.388 | H25: ='3-Statement Model'!K30 -> 17137.408 | I25: ='3-Statement Model'!L30 -> 18703.722
B26: Changes in net working capital | E26: =D32-E32 -> 17217.26 | F26: =E32-F32 -> -3197.3431 | G26: =F32-G32 -> -1227.9987 | H26: =G32-H32 -> -1312.7306 | I26: =H32-I32 -> -1403.3091
B27: Capital expenditures | E27: =-'3-Statement Model'!H81 -> -9447 | F27: =-'3-Statement Model'!I81 -> -9447 | G27: =-'3-Statement Model'!J81 -> -9447 | H27: =-'3-Statement Model'!K81 -> -9447 | I27: =-'3-Statement Model'!L81 -> -9447
B28: as % of revenue | E28: =E27/E14 -> -0.022791474 | F28: =F27/F14 -> -0.021320369 | G28: =G27/G14 -> -0.019944218 | H28: =H27/H14 -> -0.018656892 | I28: =I27/I14 -> -0.017452659
B30: Unlevered free cash flows (UFCF) | E30: =+E23+E25+E26+E27 -> 130701.85 | F30: =+F23+F25+F26+F27 -> 119114.25 | G30: =+G23+G25+G26+G27 -> 130532.7 | H30: =+H23+H25+H26+H27 -> 140562.09 | I30: =+I23+I25+I26+I27 -> 151296.55
B32: Net working capital (WC Assets - WC liabilities) | D32: =SUM('3-Statement Model'!G76)-SUM('3-Statement Model'!G75) -> 31817 | E32: =SUM('3-Statement Model'!H76)-SUM('3-Statement Model'!H75) -> 14599.74 | F32: =SUM('3-Statement Model'!I76)-SUM('3-Statement Model'!I75) -> 17797.083 | G32: =SUM('3-Statement Model'!J76)-SUM('3-Statement Model'!J75) -> 19025.082 | H32: =SUM('3-Statement Model'!K76)-SUM('3-Statement Model'!K75) -> 20337.812 | I32: =SUM('3-Statement Model'!L76)-SUM('3-Statement Model'!L75) -> 21741.121
B33: as % of revenue | E33: =+E32/E14 -> 0.03522278 | F33: =+F32/F14 -> 0.040165172 | G33: =+G32/G14 -> 0.040165172 | H33: =+H32/H14 -> 0.040165172 | I33: =+I32/I14 -> 0.040165172
B35: ="Present value of UFCF on "&TEXT(D7,"mmm dd, yyyy")&" valuation date" -> Present value of UFCF on Oct 26, 2025 valuation date
D36: Val date | E36: Yr 1 - Stub | F36: Year 2 | G36: Year 3 | H36: Year 4 | I36: Year 5
B37: Date for discounting cash flows | D37: =D7 -> 45956 | E37: =IF($H$7=1,AVERAGE(E12,D37),E12) -> 45943 | F37: =IF($H$7=1,AVERAGE(F12,E12),F12) -> 46112.5 | G37: =IF($H$7=1,AVERAGE(G12,F12),G12) -> 46477.5 | H37: =IF($H$7=1,AVERAGE(H12,G12),H12) -> 46843 | I37: =IF($H$7=1,AVERAGE(I12,H12),I12) -> 47208.5
B38: Unlevered free cash flows (UFCF) stub adjusted | C38: =D8 -> 0.072222222 | E38: =E30*C38 -> 9439.5781 | F38: =F30 -> 119114.25 | G38: =G30 -> 130532.7 | H38: =H30 -> 140562.09 | I38: =I30 -> 151296.55 | K38: <-Stub year counts first year cash flows starting at the valuation date
B39: Present value of of unlevered free cash flows | E39: =E38/(1+$H$4)^((E37-$D$7)/365) -> 9464.821 | F39: =F38/(1+$H$4)^((F37-$D$7)/365) -> 115345.67 | G39: =G38/(1+$H$4)^((G37-$D$7)/365) -> 117271.59 | H39: =H38/(1+$H$4)^((H37-$D$7)/365) -> 117147.5 | I39: =I38/(1+$H$4)^((I37-$D$7)/365) -> 116972.87
B41: Terminal value - growth in perpetuity approach | E41: Terminal value - EBITDA multiple approach
B42: Long term growth rate | C42: 0.03 | E42: Terminal year EBITDA | I42: =I16 -> 189266.32
B43: =YEAR(I12)&" FCF x (1+g)" -> 2029 FCF x (1+g) | C43: =I38*(1+C42) -> 155835.45 | E43: EBITDA multiple | I43: 12.515439
B44: ="Terminal value in "&YEAR(I12) -> Terminal value in 2029 | C44: =C43/(H4-C42) -> 3255775.5 | E44: ="Terminal value in "&YEAR(I12) -> Terminal value in 2029 | I44: =I42*I43 -> 2368751
B45: Present value of terminal value | C45: =C44/(1+H4)^((I37-$D$37)/365) -> 2517158.4 | E45: Present value of terminal value | I45: =I44/(1+H4)^((I37-D37)/365) -> 1831367.5
B46: Present value of stage 1 cash flows | C46: =SUM(E39:I39) -> 476202.45 | E46: Present value of stage 1 cash flows | I46: =C46 -> 476202.45
B47: Total enterprise value (TEV) | C47: =C46+C45 -> 2993360.9 | E47: Enterprise value (stage 1 + 2) | I47: =SUM(I45:I46) -> 2307569.9
B49: Terminal value as % of TEV | C49: =C45/$C$47 -> 0.84091379 | E49: Terminal value as % of TEV | I49: =+I45/I47 -> 0.79363466
B50: Stage 1 cash flows as % of TEV | C50: =1-C49 -> 0.15908621 | E50: Cash flows as % of TEV | I50: =1-I49 -> 0.20636534
B51: Implied TV exit EBITDA multiple | C51: =(C44/I16) -> 17.202086 | E51: Implied terminal growth rate | I51: =(H4-I38/I44)/(1+I38/I44) -> 0.013152374
B53: Net debt | E53: Shares outstanding
B54: Source doc | C54: 3Q25 10Q
B55: Source date | C55: =D6 -> 45833 | G55: Source doc | H55: Date | I55: Shares
B56: Gross debt and equivalents | E56: Basic shares | G56: Capital IQ | H56: =NOW() -> 45957.003 | I56: 14840.39
B57: Debt | C57: =FCF!AJ69 -> 101698 | E57: Restricted stock / RSUs | G57: 3Q25 10Q | H57: 45833
B58: Convertible debt | C58: =[1]Shares!E25+[1]Shares!E31 -> 0 | E58: Options / warrants | G58: 3Q25 10Q | H58: 45833 | I58: 0 | K58: <-These are for illustrative purposes, Apple doesn't have options
B59: Preferred stock | C59: =[1]Shares!E34+[1]Shares!E41 -> 0 | E59: Convertible debt | G59: 3Q25 10Q | H59: 45833 | I59: 0 | K59: <-These are for illustrative purposes, Apple doesn't have convertible debt
B60: Noncontrolling (minority) interests | C60: 0 | E60: Convertible preferred stock | G60: 3Q25 10Q | H60: 45833 | I60: 0 | K60: <-These are for illustrative purposes, Apple doesn't have convertible preferred stock
B61: Nonoperating assets | E61: Net diluted shares outstanding | I61: =SUM(I56:I60) -> 14840.39
B62: Cash | C62: =FCF!AJ52 -> 132986
B63: Equity investments | C63: 0
B65: Net debt | C65: =SUM(C57:C60)-SUM(C62:C63) -> -31288
B67: Valuation
C68: Perpetuity | D68: EBITDA
B69: Enterprise value | C69: =C47 -> 2993360.9 | D69: =I47 -> 2307569.9
B70: Net debt | C70: =$C$65 -> -31288 | D70: =C70 -> -31288
B71: Equity value | C71: =C69-C70 -> 3024648.9 | D71: =D69-D70 -> 2338857.9
B72: Shares outstanding | C72: =$I$61 -> 14840.39 | D72: =C72 -> 14840.39
B73: Equity value per share | C73: =C71/C72 -> 203.81195 | D73: =D71/D72 -> 157.60084
C75: Last twelve months (LTM)
C76: Perpetuity | D76: EBITDA
B77: EV / Revenue | C77: =C$69/$C$14 -> 7.3254472 | D77: =D$69/$C$14 -> 5.647158
B78: EV / EBITDA | C78: =C69/$C$16 -> 21.125232 | D78: =D69/$C$16 -> 16.285357
B79: EV / EBIT | C79: =C69/$C$18 -> 22.988011 | D79: =D69/$C$18 -> 17.721366
C80: Year 1
C81: Perpetuity | D81: EBITDA
B82: EV / Revenue | C82: =C69/$E$14 -> 7.221669 | D82: =D69/$E$14 -> 5.5671558
B83: EV / EBITDA | C83: =C69/$E$16 -> 20.830855 | D83: =D69/$E$16 -> 16.058423
B84: EV / EBIT | C84: =C69/$E$18 -> 22.918495 | D84: =D69/$E$18 -> 17.667777
B86: Outputs
D88: Equity value per share | L88: LTM EBITDA multiple
E89: Long term growth rate (g):
D90: =C73 -> 203.81195 | E90: =F90-0.005 -> 0.02 | F90: =G90-0.005 -> 0.025 | G90: 0.03 | H90: =G90+0.005 -> 0.035 | I90: =H90+0.005 -> 0.04 | L90: =C78 -> 21.125232 | M90: =N90-0.005 -> 0.02 | N90: =O90-0.005 -> 0.025 | O90: 0.03 | P90: =O90+0.005 -> 0.035 | Q90: =P90+0.005 -> 0.04
D91: =D92+0.01 -> 0.11 | E91: 20.680633 | F91: 20.680633 | G91: 20.680633 | H91: 20.680633 | I91: 20.680633 | L91: =L92+0.01 -> 0.11 | M91: #DIV/0! | N91: #DIV/0! | O91: #DIV/0! | P91: #DIV/0! | Q91: #DIV/0!
D92: =D93+0.01 -> 0.1 | E92: 20.680633 | F92: 20.680633 | G92: 20.680633 | H92: 20.680633 | I92: 20.680633 | L92: =L93+0.01 -> 0.1 | M92: #DIV/0! | N92: #DIV/0! | O92: #DIV/0! | P92: #DIV/0! | Q92: #DIV/0!
C93: WACC: | D93: 0.09 | E93: 20.680633 | F93: 20.680633 | G93: 20.680633 | H93: 20.680633 | I93: 20.680633 | K93: WACC: | L93: 0.09 | M93: #DIV/0! | N93: #DIV/0! | O93: #DIV/0! | P93: #DIV/0! | Q93: #DIV/0!
D94: =D93-0.01 -> 0.08 | E94: 20.680633 | F94: 20.680633 | G94: 20.680633 | H94: 20.680633 | I94: 20.680633 | L94: =L93-0.01 -> 0.08 | M94: #DIV/0! | N94: #DIV/0! | O94: #DIV/0! | P94: #DIV/0! | Q94: #DIV/0!
B95: Data | D95: =D94-0.01 -> 0.07 | E95: 20.680633 | F95: 20.680633 | G95: 20.680633 | H95: 20.680633 | I95: 20.680633 | L95: =L94-0.01 -> 0.07 | M95: #DIV/0! | N95: #DIV/0! | O95: #DIV/0! | P95: #DIV/0! | Q95: #DIV/0!
B96: Tables
D97: Equity value per share | L97: LTM EBITDA multiple
E98: Exit EBITDA Multiple | M98: Exit EBITDA Multiple
D99: =D73 -> 157.60084 | E99: =F99-1 -> 11 | F99: =G99-1 -> 12 | G99: 13 | H99: =G99+1 -> 14 | I99: =H99+1 -> 15 | L99: =D78 -> 16.285357 | M99: =N99-1 -> 11 | N99: =O99-1 -> 12 | O99: 13 | P99: =O99+1 -> 14 | Q99: =P99+1 -> 15
D100: =D101+0.01 -> 0.11 | E100: 20.680633 | F100: 20.680633 | G100: 20.680633 | H100: 20.680633 | I100: 20.680633 | L100: =L101+0.01 -> 0.11 | M100: #DIV/0! | N100: #DIV/0! | O100: #DIV/0! | P100: #DIV/0! | Q100: #DIV/0!
D101: =D102+0.01 -> 0.1 | E101: 20.680633 | F101: 20.680633 | G101: 20.680633 | H101: 20.680633 | I101: 20.680633 | L101: =L102+0.01 -> 0.1 | M101: #DIV/0! | N101: #DIV/0! | O101: #DIV/0! | P101: #DIV/0! | Q101: #DIV/0!
C102: WACC: | D102: 0.09 | E102: 20.680633 | F102: 20.680633 | G102: 20.680633 | H102: 20.680633 | I102: 20.680633 | K102: WACC: | L102: 0.09 | M102: #DIV/0! | N102: #DIV/0! | O102: #DIV/0! | P102: #DIV/0! | Q102: #DIV/0!
D103: =D102-0.01 -> 0.08 | E103: 20.680633 | F103: 20.680633 | G103: 20.680633 | H103: 20.680633 | I103: 20.680633 | L103: =L102-0.01 -> 0.08 | M103: #DIV/0! | N103: #DIV/0! | O103: #DIV/0! | P103: #DIV/0! | Q103: #DIV/0!
D104: =D103-0.01 -> 0.07 | E104: 20.680633 | F104: 20.680633 | G104: 20.680633 | H104: 20.680633 | I104: 20.680633 | L104: =L103-0.01 -> 0.07 | M104: #DIV/0! | N104: #DIV/0! | O104: #DIV/0! | P104: #DIV/0! | Q104: #DIV/0!
B106: Equity value range | G106: Football field
C127: Low | D127: Diff. | E127: High | O127: Low | P127: Diff. | Q127: High
B128: ="DCF Value at "&TEXT(E99,"0.0x")&"-"&TEXT(I99,"0.0x")&" Exit EBITDA Range at "&TEXT(D102,"0.0%")&" WACC" -> DCF Value at 11.0x-15.0x Exit EBITDA Range at 9.0% WACC | C128: =E102 -> 20.680633 | D128: =E128-C128 -> 0 | E128: =I102 -> 20.680633 | G128: ="LTM EBITDA Purchase Multiple at "&TEXT(M90,"0.0%")&"-"&TEXT(Q90,"0.0%")&" Perpetuity Growth at "&TEXT(L93,"0.0%")&" WACC" -> LTM EBITDA Purchase Multiple at 2.0%-4.0% Perpetuity Growth at 9.0% WACC | O128: =M93 -> #DIV/0! | P128: =Q128-O128 -> #DIV/0! | Q128: =Q93 -> #DIV/0!
B129: ="DCF Value at "&TEXT(E90,"0.0%")&"-"&TEXT(I90,"0.0%")&" Perpetuity Range at "&TEXT(D102,"0.0%")&" WACC" -> DCF Value at 2.0%-4.0% Perpetuity Range at 9.0% WACC | C129: =E93 -> 20.680633 | D129: =E129-C129 -> 0 | E129: =I93 -> 20.680633 | G129: ="LTM EBITDA Purchase Multiple at "&TEXT(M102,"0.0x")&"-"&TEXT(Q102,"0.0x")&" Exit EBITDA Multiple at "&TEXT(L102,"0.0%")&" WACC" -> #DIV/0! | O129: =M102 -> #DIV/0! | P129: =Q129-O129 -> #DIV/0! | Q129: =Q102 -> #DIV/0!
B130: 52 Week Market High/Low | C130: 169.5 | D130: =E130-C130 -> 158.35 | E130: 327.85 | G130: ="LTM EBITDA Purchase Multiple at "&TEXT(L104,"0.0%")&"-"&TEXT(L100,"0.0%")&" WACC at "&TEXT(O99,"0.0x")&" Exit EBITDA" -> LTM EBITDA Purchase Multiple at 7.0%-11.0% WACC at 13.0x Exit EBITDA | O130: =O100 -> #DIV/0! | P130: =Q130-O130 -> #DIV/0! | Q130: =O104 -> #DIV/0!

Sheet WACC
B2: WACC Buildup
B3: ='[1]Financials '!$B$3 -> $ and shares in millions, except per share data
B4: Cost of capital assumptions
E5: Source
B6: Cost of debt | C6: 0.0175 | E6: Bloomberg - YTM on 2.2% 9/29 Bond
B7: Tax rate | C7: ='[1]Simple DCF Done'!I22 -> 0.173 | E7: From terminal year of UFCF forecast
B8: Cost of debt (after tax) | C8: =C6*(1-C7) -> 0.0144725 | E8: Cost of debt x (1 - tax rate)
B10: Risk free rate | C10: 0.0123 | E10: WSJ: 10 Year US Treasury Yield
B11: Beta | C11: =IF(C32="Observed",C34,C35) -> 1.099 | E11: Bloomberg 2 year weekly adjusted beta
B12: Market risk premium | C12: 0.055 | E12: Market risk premium from D&P May 1, 2019
B13: Cost of equity | C13: =C10+C11*C12 -> 0.072745 | E13: RfR + Beta x MRP
B15: Capital weights (capital structure)
D16: Target
C17: Current | D17: (override) | E17: % of total
B18: Equity | C18: ='[1]Simple DCF Done'!H5*'[1]Simple DCF Done'!I61 -> 1223044.7 | E18: =IF(D18,D18,C18/(C18+C19)) -> 1.0878512
B19: Debt | C19: ='[1]Simple DCF Done'!C65 -> -98769 | D19: =1-D18 -> 1 | E19: =1-E18 -> -0.087851229
B21: Cost of capital (WACC) | E21: =C8*E19+C13*E18 -> 0.077864311
B23: WACC sensitivity to MRP and Beta
D24: Beta
C25: =E21 -> 0.077864311 | D25: =E25-0.1 -> 0.999 | E25: 1.099 | F25: =E25+0.1 -> 1.199
C26: =C27-0.005 -> 0.045 | D26: 0.061013495 | E26: 0.065908826 | F26: 0.070804156
B27: Market | C27: =C28-0.005 -> 0.05 | D27: 0.066447312 | E27: 0.071886568 | F27: 0.077325824
B28: Risk | C28: 0.055 | D28: 0.071881129 | E28: 0.077864311 | F28: 0.083847492
B29: Premium | C29: =C28+0.005 -> 0.06 | D29: 0.077314946 | E29: 0.083842053 | F29: 0.090369161
C30: =C29+0.005 -> 0.065 | D30: 0.082748763 | E30: 0.089819796 | F30: 0.096890829
B32: Select Beta for model | C32: Observed
B34: Observed | C34: 1.099 | D34: Bloomberg 2 year weekly adjusted beta
B35: Industry beta | C35: =C46 -> 1.178138 | D35: From schedule below
B37: Industry beta
C39: Observed b | D39: Share price | E39: Dil. shares | F39: Market cap | G39: Net Debt | H39: Tax rate | I39: Delev. b
B40: Microsoft MSFT | C40: 1.21 | D40: 136.96 | E40: 7662.8 | F40: =D40*E40 -> 1049497.1 | G40: =86343-131536 -> -45193 | H40: 0.164 | I40: =C40/(1+(1-H40)*(G40)/F40) -> 1.255186
B41: Alphabet (GOOG) | C41: 0.96 | D41: 1116.79 | E41: 694.2 | F41: =D41*E41 -> 775275.62 | G41: =12272-113488 -> -101216 | H41: 0.139 | I41: =C41/(1+(1-H41)*(G41)/F41) -> 1.0815777
B42: Amazon (AMZN) | C42: 1.58 | D42: 1952.32 | E42: 492.3 | F42: =D42*E42 -> 961127.14 | G42: =69005-37020 -> 31985 | H42: 0.127 | I42: =C42/(1+(1-H42)*(G42)/F42) -> 1.5353934
B43: Apple (AAPL) | C43: =C34 -> 1.099 | F43: =C18 -> 1223044.7 | G43: =C19 -> -98769 | H43: =C7 -> 0.173 | I43: =C43/(1+(1-H43)*(G43)/F43) -> 1.1776503
B45: Industry average delevered beta | C45: =AVERAGE(I40:I43) -> 1.2624518
B46: =B43&" beta" -> Apple (AAPL) beta | C46: =C45*(1+(1-H43)*(G43)/F43) -> 1.178138

Sheet Shares
B2: Shares - Options and Convertibles
B3: ='[1]Financials '!$B$3 -> $ and shares in millions, except per share data
B4: Current share price | E4: =DCF!H5 -> 262.82
B6: Stock options - Treasury stock method
C7: Outstanding | D7: Exercise | E7: In-the-$
C8: options | D8: price | E8: options
B9: Tranche 1 | C9: 10 | D9: 67.45 | E9: =IF(D9<=$E$4,C9,0) -> 10
B10: Tranche 2 | C10: 50 | D10: 112.63 | E10: =IF(D10<=$E$4,C10,0) -> 50
B11: Tranche 3 | C11: 10 | D11: 146.29 | E11: =IF(D11<=$E$4,C11,0) -> 10
B12: Tranche 4 | C12: 42 | D12: 218.91 | E12: =IF(D12<=$E$4,C12,0) -> 42
B13: Tranche 5 | C13: 20 | D13: 265.13 | E13: =IF(D13<=$E$4,C13,0) -> 0
B14: Tranche 6 | C14: 28 | D14: 302.61 | E14: =IF(D14<=$E$4,C14,0) -> 0
B15: Tranche 7 | C15: 45 | D15: 309.74 | E15: =IF(D15<=$E$4,C15,0) -> 0
B16: Total | C16: =SUM(C9:C15) -> 205 | E16: =SUM(E9:E15) -> 112
B18: Total proceeds ($mm) | E18: =SUMPRODUCT(D9:D15,E9:E15) -> 16963.12
B19: Total shares repurchased (mm) | E19: =-(E18/E4) -> -64.542729
B20: Net dilutive impact of stock options | E20: =E16+E19 -> 47.457271
B22: Convertible securities "if-converted" test
B24: Convertible Debt
B25: Principal Outstanding | E25: 14543
B26: Each $1,000 in principal convertible into (Conversion ratio) | E26: 4
B27: Conversion price | E27: =E25/E28 -> 250
B28: Common shares convertible into | E28: =E26*E25/1000 -> 58.172
B30: Dilutive impact of convertible securities | E30: =IF(E27<E4,E28,0) -> 58.172
B31: Elimination of liability from net debt | E31: =IF(E30>0,-E25,0) -> -14543
B33: Convertible Preferred Stock
B34: Convertible Preferred Par Value | E34: 34654
B35: Preferred shares outstanding | E35: 45.5
B36: Conversion ratio | E36: 4.3
B37: Common shares convertible into | E37: =E35*E36 -> 195.65
B38: Conversion price | E38: =E34/E37 -> 177.12241
B40: Dilutive impact of convertible securities | E40: =IF(E38<E4,E37,0) -> 195.65
B41: Elimination of liability from net debt | E41: =IF(E40>0,-E34,0) -> -34654
