Workbook

Sheet Historical Financials
B2: Beyond Meat, Inc. (NASDAQ: BYND)
B3: Historical Financials
B4: $ mm except per share
A6: X | B6: Income Statement | G6: FYE | K6: Quarterly | AA6: Quarterly | AK6: Quarterly | AQ6: LTM | BE6: LTM | BF6: LTM | BL6: Variance
B7: Fiscal Period | C7: 2018 | D7: 2019 | E7: 2020 | F7: 2021 | G7: 2022 | H7: 2023 | I7: 2024 | K7: 1Q18 | L7: 2Q18 | M7: 3Q18 | N7: 4Q18 | O7: 1Q19 | P7: 2Q19 | Q7: 3Q19 | R7: 4Q19 | S7: 1Q20 | T7: 2Q20 | U7: 3Q20 | V7: 4Q20 | W7: 1Q21 | X7: 2Q21 | Y7: 3Q21 | Z7: 4Q21 | AA7: 1Q22 | AB7: 2Q22 | AC7: 3Q22 | AD7: 4Q22 | AE7: 1Q23 | AF7: 2Q23 | AG7: 3Q23 | AH7: 4Q23 | AI7: 1Q24 | AJ7: 2Q24 | AK7: 3Q24 | AL7: 4Q24 | AM7: 1Q25 | AN7: 2Q25 | AO7: 3Q25 | AQ7: =V7 -> 4Q20 | AR7: =W7 -> 1Q21 | AS7: =X7 -> 2Q21 | AT7: =Y7 -> 3Q21 | AU7: =Z7 -> 4Q21 | AV7: =AA7 -> 1Q22 | AW7: =AB7 -> 2Q22 | AX7: =AC7 -> 3Q22 | ... BJ7: =AO7 -> 3Q25
B8: Fiscal Period End Date | C8: 43465 | D8: 43830 | E8: 44196 | F8: 44561 | G8: 44926 | H8: 45291 | I8: 45657 | K8: 43190 | L8: 43281 | M8: 43372 | N8: 43465 | O8: 43554 | P8: 43645 | Q8: 43736 | R8: 43830 | S8: 43918 | T8: 44009 | U8: 44100 | V8: 44196 | W8: 44289 | X8: 44380 | Y8: 44471 | Z8: 44561 | AA8: 44653 | AB8: 44744 | AC8: 44835 | AD8: 44926 | AE8: 45017 | AF8: 45108 | AG8: 45199 | AH8: 45291 | AI8: 45381 | AJ8: 45472 | AK8: 45563 | AL8: 45657 | AM8: 45745 | AN8: 45836 | AO8: 45927 | AQ8: =V8 -> 44196 | AR8: =W8 -> 44289 | AS8: =X8 -> 44380 | AT8: =Y8 -> 44471 | AU8: =Z8 -> 44561 | AV8: =AA8 -> 44653 | AW8: =AB8 -> 44744 | AX8: =AC8 -> 44835 | ... BJ8: =AO8 -> 45927
B10: Consolidated Revenue | C10: 87934 | D10: 297897 | E10: 406785 | F10: 464700 | G10: 418933 | H10: 343376 | I10: 326452 | K10: 12776 | L10: 17367 | M10: 26277 | N10: =SUM(C10-SUM(K10:M10)) -> 31514 | O10: 40206 | P10: 67251 | Q10: 91961 | R10: =SUM(D10-SUM(O10:Q10)) -> 98479 | S10: 97074 | T10: 113338 | U10: 94436 | V10: =SUM(E10-SUM(S10:U10)) -> 101937 | W10: 108164 | X10: 149426 | Y10: 106432 | Z10: =SUM(F10-SUM(W10:Y10)) -> 100678 | AA10: 109455 | AB10: 147040 | AC10: 82500 | AD10: =SUM(G10-SUM(AA10:AC10)) -> 79938 | AE10: 92236 | AF10: 102149 | AG10: 75312 | AH10: =SUM(H10-SUM(AE10:AG10)) -> 73679 | AI10: 75603 | AJ10: 93185 | AK10: 81006 | AL10: =SUM(I10-SUM(AI10:AK10)) -> 76658 | AM10: 68731 | AN10: 74958 | AO10: 70218 | AQ10: =SUM(S10:V10) -> 406785 | AR10: =SUM(T10:W10) -> 417875 | AS10: =SUM(U10:X10) -> 453963 | AT10: =SUM(V10:Y10) -> 465959 | AU10: =SUM(W10:Z10) -> 464700 | AV10: =SUM(X10:AA10) -> 465991 | AW10: =SUM(Y10:AB10) -> 463605 | AX10: =SUM(Z10:AC10) -> 439673 | ... BJ10: =SUM(AL10:AO10) -> 290565 | BL10: =SUM(BI10/BE10)-1 -> -0.051690011
B11: Total Revenue | C11: =+SUM(C10:C10) -> 87934 | D11: =+SUM(D10:D10) -> 297897 | E11: =+SUM(E10:E10) -> 406785 | F11: =+SUM(F10:F10) -> 464700 | G11: =+SUM(G10:G10) -> 418933 | H11: =+SUM(H10:H10) -> 343376 | I11: =+SUM(I10:I10) -> 326452 | K11: =+SUM(K10:K10) -> 12776 | L11: =+SUM(L10:L10) -> 17367 | M11: =+SUM(M10:M10) -> 26277 | N11: =+SUM(N10:N10) -> 31514 | O11: =+SUM(O10:O10) -> 40206 | P11: =+SUM(P10:P10) -> 67251 | Q11: =+SUM(Q10:Q10) -> 91961 | R11: =+SUM(R10:R10) -> 98479 | ... AO11: =+SUM(AO10:AO10) -> 70218 | AQ11: =+SUM(AQ10:AQ10) -> 406785 | AR11: =+SUM(AR10:AR10) -> 417875 | AS11: =+SUM(AS10:AS10) -> 453963 | AT11: =+SUM(AT10:AT10) -> 465959 | AU11: =+SUM(AU10:AU10) -> 464700 | AV11: =+SUM(AV10:AV10) -> 465991 | AW11: =+SUM(AW10:AW10) -> 463605 | AX11: =+SUM(AX10:AX10) -> 439673 | ... BJ11: =+SUM(BJ10:BJ10) -> 290565 | BL11: =SUM(BI11/BE11)-1 -> -0.051690011
B13: Cost of Sales | C13: -70360 | D13: -198141 | E13: -284510 | F13: -347419 | G13: -442676 | H13: -426031 | I13: -284753 | K13: -10719 | L13: -14755 | M13: -21235 | N13: =SUM(C13-SUM(K13:M13)) -> -23651 | O13: -29435 | P13: -44510 | Q13: -59178 | R13: =SUM(D13-SUM(O13:Q13)) -> -65018 | S13: -59383 | T13: -79687 | U13: -68908 | V13: =SUM(E13-SUM(S13:U13)) -> -76532 | W13: -75456 | X13: -102074 | Y13: -83456 | Z13: =SUM(F13-SUM(W13:Y13)) -> -86433 | AA13: -109265 | AB13: -153202 | AC13: -97340 | AD13: =SUM(G13-SUM(AA13:AC13)) -> -82869 | AE13: -86051 | AF13: -99876 | AG13: -82566 | AH13: =SUM(H13-SUM(AE13:AG13)) -> -157538 | AI13: -71935 | AJ13: -79468 | AK13: -66698 | AL13: =SUM(I13-SUM(AI13:AK13)) -> -66652 | AM13: -69796 | AN13: -66367 | AO13: -62988 | AQ13: =SUM(S13:V13) -> -284510 | AR13: =SUM(T13:W13) -> -300583 | AS13: =SUM(U13:X13) -> -322970 | AT13: =SUM(V13:Y13) -> -337518 | AU13: =SUM(W13:Z13) -> -347419 | AV13: =SUM(X13:AA13) -> -381228 | AW13: =SUM(Y13:AB13) -> -432356 | AX13: =SUM(Z13:AC13) -> -446240 | ... BJ13: =SUM(AL13:AO13) -> -265803 | BL13: =SUM(BI13/BE13)-1 -> -0.31160107
B14: Gross Profit | C14: =+SUM(C11+SUM(C13:C13)) -> 17574 | D14: =+SUM(D11+SUM(D13:D13)) -> 99756 | E14: =+SUM(E11+SUM(E13:E13)) -> 122275 | F14: =+SUM(F11+SUM(F13:F13)) -> 117281 | G14: =+SUM(G11+SUM(G13:G13)) -> -23743 | H14: =+SUM(H11+SUM(H13:H13)) -> -82655 | I14: =+SUM(I11+SUM(I13:I13)) -> 41699 | K14: =+SUM(K11+SUM(K13:K13)) -> 2057 | L14: =+SUM(L11+SUM(L13:L13)) -> 2612 | M14: =+SUM(M11+SUM(M13:M13)) -> 5042 | N14: =+SUM(N11+SUM(N13:N13)) -> 7863 | O14: =+SUM(O11+SUM(O13:O13)) -> 10771 | P14: =+SUM(P11+SUM(P13:P13)) -> 22741 | Q14: =+SUM(Q11+SUM(Q13:Q13)) -> 32783 | R14: =+SUM(R11+SUM(R13:R13)) -> 33461 | ... AO14: =+SUM(AO11+SUM(AO13:AO13)) -> 7230 | AQ14: =+SUM(AQ11+SUM(AQ13:AQ13)) -> 122275 | AR14: =+SUM(AR11+SUM(AR13:AR13)) -> 117292 | AS14: =+SUM(AS11+SUM(AS13:AS13)) -> 130993 | AT14: =+SUM(AT11+SUM(AT13:AT13)) -> 128441 | AU14: =+SUM(AU11+SUM(AU13:AU13)) -> 117281 | AV14: =+SUM(AV11+SUM(AV13:AV13)) -> 84763 | AW14: =+SUM(AW11+SUM(AW13:AW13)) -> 31249 | AX14: =+SUM(AX11+SUM(AX13:AX13)) -> -6567 | ... BJ14: =+SUM(BJ11+SUM(BJ13:BJ13)) -> 24762 | BL14: =SUM(BI14/BE14)-1 -> -1.4318576
B15: Gross Margin (%) | C15: =C14/C11 -> 0.19985444 | D15: =D14/D11 -> 0.33486742 | E15: =E14/E11 -> 0.30058876 | F15: =F14/F11 -> 0.25238003 | G15: =G14/G11 -> -0.056674934 | H15: =H14/H11 -> -0.2407128 | I15: =I14/I11 -> 0.12773394 | K15: =K14/K11 -> 0.16100501 | L15: =L14/L11 -> 0.15040018 | M15: =M14/M11 -> 0.19187883 | N15: =N14/N11 -> 0.24950816 | O15: =O14/O11 -> 0.26789534 | P15: =P14/P11 -> 0.33815111 | Q15: =Q14/Q11 -> 0.35648808 | R15: =R14/R11 -> 0.33977802 | ... AO15: =AO14/AO11 -> 0.10296505 | AQ15: =AQ14/AQ11 -> 0.30058876 | AR15: =AR14/AR11 -> 0.28068681 | AS15: =AS14/AS11 -> 0.28855435 | AT15: =AT14/AT11 -> 0.27564872 | AU15: =AU14/AU11 -> 0.25238003 | AV15: =AV14/AV11 -> 0.18189836 | AW15: =AW14/AW11 -> 0.067404364 | AX15: =AX14/AX11 -> -0.0149361 | ... BJ15: =BJ14/BJ11 -> 0.085220174 | BL15: =SUM(BI15-BE15)*1000 -> 337.66712
B17: Selling, General & Administrative (SG&A) | C17: -34461 | D17: -74726 | E17: -133655 | F17: -209474 | G17: -239505 | H17: -220344 | I17: -169674 | K17: -5737 | L17: -7043 | M17: -10353 | N17: =SUM(C17-SUM(K17:M17)) -> -11328 | O17: -11177 | P17: -15515 | Q17: -20944 | R17: =SUM(D17-SUM(O17:Q17)) -> -27090 | S17: -27315 | T17: -34292 | U17: -33560 | V17: =SUM(E17-SUM(S17:U17)) -> -38488 | W17: -38954 | X17: -48286 | Y17: -56362 | Z17: =SUM(F17-SUM(W17:Y17)) -> -65872 | AA17: -75114 | AB17: -63015 | AC17: -54495 | AD17: =SUM(G17-SUM(AA17:AC17)) -> -46881 | AE17: -51900 | AF17: -47455 | AG17: -53252 | AH17: =SUM(H17-SUM(AE17:AG17)) -> -67737 | AI17: -47282 | AJ17: -42163 | AK17: -39084 | AL17: =SUM(I17-SUM(AI17:AK17)) -> -41145 | AM17: -47672 | AN17: -37696 | AO17: -37230 | AQ17: =SUM(S17:V17) -> -133655 | AR17: =SUM(T17:W17) -> -145294 | AS17: =SUM(U17:X17) -> -159288 | AT17: =SUM(V17:Y17) -> -182090 | AU17: =SUM(W17:Z17) -> -209474 | AV17: =SUM(X17:AA17) -> -245634 | AW17: =SUM(Y17:AB17) -> -260363 | AX17: =SUM(Z17:AC17) -> -258496 | ... BJ17: =SUM(AL17:AO17) -> -163743 | BL17: =SUM(BI17/BE17)-1 -> -0.21306918
B18: Research & Development (R&D) | C18: -9587 | D18: -20650 | E18: -31535 | F18: -66946 | G18: -62264 | H18: -39530 | I18: -28149 | K18: -1605 | L18: -2497 | M18: -2165 | N18: =SUM(C18-SUM(K18:M18)) -> -3320 | O18: -4498 | P18: -4212 | Q18: -5951 | R18: =SUM(D18-SUM(O18:Q18)) -> -5989 | S18: -6194 | T18: -6016 | U18: -8278 | V18: =SUM(E18-SUM(S18:U18)) -> -11047 | W18: -15925 | X18: -13823 | Y18: -14862 | Z18: =SUM(F18-SUM(W18:Y18)) -> -22336 | AA18: -19678 | AB18: -16202 | AC18: -13413 | AD18: =SUM(G18-SUM(AA18:AC18)) -> -12971 | AE18: -12432 | AF18: -8773 | AG18: -9118 | AH18: =SUM(H18-SUM(AE18:AG18)) -> -9207 | AI18: -9860 | AJ18: -5485 | AK18: -6133 | AL18: =SUM(I18-SUM(AI18:AK18)) -> -6671 | AM18: -7462 | AN18: -5807 | AO18: -4917 | AQ18: =SUM(S18:V18) -> -31535 | AR18: =SUM(T18:W18) -> -41266 | AS18: =SUM(U18:X18) -> -49073 | AT18: =SUM(V18:Y18) -> -55657 | AU18: =SUM(W18:Z18) -> -66946 | AV18: =SUM(X18:AA18) -> -70699 | AW18: =SUM(Y18:AB18) -> -73078 | AX18: =SUM(Z18:AC18) -> -71629 | ... BJ18: =SUM(AL18:AO18) -> -24857 | BL18: =SUM(BI18/BE18)-1 -> -0.22563113
B19: Restructuring Charges & Other Impairments | C19: =-1515-1128 -> -2643 | D19: -4869 | E19: -6430 | F19: -15794 | G19: -17259 | H19: 631 | I19: 0 | K19: =-47-294 -> -341 | L19: =-28-348 -> -376 | M19: =-313-528 -> -841 | N19: =SUM(C19-SUM(K19:M19)) -> -1085 | O19: =-733-394 -> -1127 | P19: =-741-847 -> -1588 | Q19: =-855-2319 -> -3174 | R19: =SUM(D19-SUM(O19:Q19)) -> 1020 | S19: -2373 | T19: -1509 | U19: -2146 | V19: =SUM(E19-SUM(S19:U19)) -> -402 | W19: -2474 | X19: -3844 | Y19: -5750 | Z19: =SUM(F19-SUM(W19:Y19)) -> -3726 | AA19: -3026 | AB19: -4302 | AC19: -6993 | AD19: =SUM(G19-SUM(AA19:AC19)) -> -2938 | AE19: 426 | AF19: 201 | AG19: 4 | AH19: =SUM(H19-SUM(AE19:AG19)) -> 0 | AI19: 0 | AJ19: 0 | AK19: 0 | AL19: =SUM(I19-SUM(AI19:AK19)) -> 0 | AM19: 0 | AN19: 0 | AO19: -77414 | AQ19: =SUM(S19:V19) -> -6430 | AR19: =SUM(T19:W19) -> -6531 | AS19: =SUM(U19:X19) -> -8866 | AT19: =SUM(V19:Y19) -> -12470 | AU19: =SUM(W19:Z19) -> -15794 | AV19: =SUM(X19:AA19) -> -16346 | AW19: =SUM(Y19:AB19) -> -16804 | AX19: =SUM(Z19:AC19) -> -18047 | ... BJ19: =SUM(AL19:AO19) -> -77414
B20: Operating Profit | C20: =+SUM(C14+SUM(C17:C19)) -> -29117 | D20: =+SUM(D14+SUM(D17:D19)) -> -489 | E20: =+SUM(E14+SUM(E17:E19)) -> -49345 | F20: =+SUM(F14+SUM(F17:F19)) -> -174933 | G20: =+SUM(G14+SUM(G17:G19)) -> -342771 | H20: =+SUM(H14+SUM(H17:H19)) -> -341898 | I20: =+SUM(I14+SUM(I17:I19)) -> -156124 | K20: =+SUM(K14+SUM(K17:K19)) -> -5626 | L20: =+SUM(L14+SUM(L17:L19)) -> -7304 | M20: =+SUM(M14+SUM(M17:M19)) -> -8317 | N20: =+SUM(N14+SUM(N17:N19)) -> -7870 | O20: =+SUM(O14+SUM(O17:O19)) -> -6031 | P20: =+SUM(P14+SUM(P17:P19)) -> 1426 | Q20: =+SUM(Q14+SUM(Q17:Q19)) -> 2714 | R20: =+SUM(R14+SUM(R17:R19)) -> 1402 | ... AO20: =+SUM(AO14+SUM(AO17:AO19)) -> -112331 | AQ20: =+SUM(AQ14+SUM(AQ17:AQ19)) -> -49345 | AR20: =+SUM(AR14+SUM(AR17:AR19)) -> -75799 | AS20: =+SUM(AS14+SUM(AS17:AS19)) -> -86234 | AT20: =+SUM(AT14+SUM(AT17:AT19)) -> -121776 | AU20: =+SUM(AU14+SUM(AU17:AU19)) -> -174933 | AV20: =+SUM(AV14+SUM(AV17:AV19)) -> -247916 | AW20: =+SUM(AW14+SUM(AW17:AW19)) -> -318996 | AX20: =+SUM(AX14+SUM(AX17:AX19)) -> -354739 | ... BJ20: =+SUM(BJ14+SUM(BJ17:BJ19)) -> -241252 | BL20: =SUM(BI20/BE20)-1 -> -0.49711794
B21: Operating Margin (%) | C21: =C20/C11 -> -0.33112334 | D21: =D20/D11 -> -0.001641507 | E21: =E20/E11 -> -0.12130487 | F21: =F20/F11 -> -0.37644287 | G21: =G20/G11 -> -0.81820005 | H21: =H20/H11 -> -0.99569568 | I21: =I20/I11 -> -0.47824489 | K21: =K20/K11 -> -0.44035692 | L21: =L20/L11 -> -0.42056774 | M21: =M20/M11 -> -0.31651254 | N21: =N20/N11 -> -0.24973028 | O21: =O20/O11 -> -0.15000249 | P21: =P20/P11 -> 0.021204146 | Q21: =Q20/Q11 -> 0.029512511 | R21: =R20/R11 -> 0.014236538 | ... AO21: =AO20/AO11 -> -1.5997465 | AQ21: =AQ20/AQ11 -> -0.12130487 | AR21: =AR20/AR11 -> -0.18139156 | AS21: =AS20/AS11 -> -0.18995821 | AT21: =AT20/AT11 -> -0.26134488 | AU21: =AU20/AU11 -> -0.37644287 | AV21: =AV20/AV11 -> -0.53201886 | AW21: =AW20/AW11 -> -0.68807713 | AX21: =AX20/AX11 -> -0.80682462 | ... BJ21: =BJ20/BJ11 -> -0.83028582
B23: Interest Expense | C23: 352 | D23: -3071 | E23: -2576 | F23: -3648 | G23: -3966 | H23: -3955 | I23: -4097 | K23: -70 | L23: 38 | M23: -31 | N23: =SUM(C23-SUM(K23:M23)) -> 415 | O23: 141 | P23: 898 | Q23: 0 | R23: =SUM(D23-SUM(O23:Q23)) -> -4110 | S23: -705 | T23: -569 | U23: -689 | V23: =SUM(E23-SUM(S23:U23)) -> -613 | W23: -629 | X23: -1022 | Y23: -1005 | Z23: =SUM(F23-SUM(W23:Y23)) -> -992 | AA23: -1025 | AB23: -1108 | AC23: -1040 | AD23: =SUM(G23-SUM(AA23:AC23)) -> -793 | AE23: -989 | AF23: -989 | AG23: -989 | AH23: =SUM(H23-SUM(AE23:AG23)) -> -988 | AI23: -1015 | AJ23: -1029 | AK23: -1028 | AL23: =SUM(I23-SUM(AI23:AK23)) -> -1025 | AM23: -1024 | AN23: -2002 | AO23: -4418 | AQ23: =SUM(S23:V23) -> -2576 | AR23: =SUM(T23:W23) -> -2500 | AS23: =SUM(U23:X23) -> -2953 | AT23: =SUM(V23:Y23) -> -3269 | AU23: =SUM(W23:Z23) -> -3648 | AV23: =SUM(X23:AA23) -> -4044 | AW23: =SUM(Y23:AB23) -> -4130 | AX23: =SUM(Z23:AC23) -> -4165 | ... BJ23: =SUM(AL23:AO23) -> -8469 | BL23: =SUM(BI23/BE23)-1 -> 0.26311863
B24: Other, Net | C24: -1120 | D24: 3629 | E24: -759 | F24: -487 | G24: -420 | H24: 11616 | I24: -10 | K24: 0 | L24: 0 | M24: 0 | N24: =SUM(C24-SUM(K24:M24)) -> -1120 | O24: 0 | P24: 0 | Q24: 1385 | R24: =SUM(D24-SUM(O24:Q24)) -> 2244 | S24: 0 | T24: 0 | U24: 0 | V24: =SUM(E24-SUM(S24:U24)) -> -759 | W24: 0 | X24: 0 | Y24: 0 | Z24: =SUM(F24-SUM(W24:Y24)) -> -487 | AA24: 0 | AB24: 0 | AC24: 0 | AD24: =SUM(G24-SUM(AA24:AC24)) -> -420 | AE24: 0 | AF24: 0 | AG24: 0 | AH24: =SUM(H24-SUM(AE24:AG24)) -> 11616 | AI24: 0 | AJ24: 0 | AK24: 0 | AL24: =SUM(I24-SUM(AI24:AK24)) -> -10 | AM24: 0 | AN24: 0 | AO24: 750 | AQ24: =SUM(S24:V24) -> -759 | AR24: =SUM(T24:W24) -> -759 | AS24: =SUM(U24:X24) -> -759 | AT24: =SUM(V24:Y24) -> -759 | AU24: =SUM(W24:Z24) -> -487 | AV24: =SUM(X24:AA24) -> -487 | AW24: =SUM(Y24:AB24) -> -487 | AX24: =SUM(Z24:AC24) -> -487 | ... BJ24: =SUM(AL24:AO24) -> 740 | BL24: =SUM(BI24/BE24)-1 -> -1.0008609
B25: Remeasurement of Warrant Liability | C25: 0 | D25: -12503 | E25: 0 | F25: 0 | G25: 0 | H25: 0 | I25: 0 | K25: 0 | L25: -130 | M25: -994 | N25: =SUM(C25-SUM(K25:M25)) -> 1124 | O25: -759 | P25: -11744 | Q25: 0 | R25: =SUM(D25-SUM(O25:Q25)) -> 0 | S25: 710 | T25: -1454 | U25: -85 | V25: =SUM(E25-SUM(S25:U25)) -> 829 | W25: -1570 | X25: 180 | Y25: 759 | Z25: =SUM(F25-SUM(W25:Y25)) -> 631 | AA25: -1124 | AB25: -4902 | AC25: -2151 | AD25: =SUM(G25-SUM(AA25:AC25)) -> 8177 | AE25: 2908 | AF25: 1746 | AG25: 243 | AH25: =SUM(H25-SUM(AE25:AG25)) -> -4897 | AI25: 123 | AJ25: 477 | AK25: 5405 | AL25: =SUM(I25-SUM(AI25:AK25)) -> -6005 | AM25: 4318 | AN25: 7731 | AO25: 5318 | AQ25: =SUM(S25:V25) -> 0 | AR25: =SUM(T25:W25) -> -2280 | AS25: =SUM(U25:X25) -> -646 | AT25: =SUM(V25:Y25) -> 198 | AU25: =SUM(W25:Z25) -> 0 | AV25: =SUM(X25:AA25) -> 446 | AW25: =SUM(Y25:AB25) -> -4636 | AX25: =SUM(Z25:AC25) -> -7546 | ... BJ25: =SUM(AL25:AO25) -> 11362 | BL25: =SUM(BI25/BE25)-1 -> -3.8241243
B26: Earning Before Taxes | C26: =SUM(C20+SUM(C23:C25)) -> -29885 | D26: =SUM(D20+SUM(D23:D25)) -> -12434 | E26: =SUM(E20+SUM(E23:E25)) -> -52680 | F26: =SUM(F20+SUM(F23:F25)) -> -179068 | G26: =SUM(G20+SUM(G23:G25)) -> -347157 | H26: =SUM(H20+SUM(H23:H25)) -> -334237 | I26: =SUM(I20+SUM(I23:I25)) -> -160231 | K26: =SUM(K20+SUM(K23:K25)) -> -5696 | L26: =SUM(L20+SUM(L23:L25)) -> -7396 | M26: =SUM(M20+SUM(M23:M25)) -> -9342 | N26: =SUM(N20+SUM(N23:N25)) -> -7451 | O26: =SUM(O20+SUM(O23:O25)) -> -6649 | P26: =SUM(P20+SUM(P23:P25)) -> -9420 | Q26: =SUM(Q20+SUM(Q23:Q25)) -> 4099 | R26: =SUM(R20+SUM(R23:R25)) -> -464 | ... AO26: =SUM(AO20+SUM(AO23:AO25)) -> -110681 | AQ26: =SUM(AQ20+SUM(AQ23:AQ25)) -> -52680 | AR26: =SUM(AR20+SUM(AR23:AR25)) -> -81338 | AS26: =SUM(AS20+SUM(AS23:AS25)) -> -90592 | AT26: =SUM(AT20+SUM(AT23:AT25)) -> -125606 | AU26: =SUM(AU20+SUM(AU23:AU25)) -> -179068 | AV26: =SUM(AV20+SUM(AV23:AV25)) -> -252001 | AW26: =SUM(AW20+SUM(AW23:AW25)) -> -328249 | AX26: =SUM(AX20+SUM(AX23:AX25)) -> -366937 | ... BJ26: =SUM(BJ20+SUM(BJ23:BJ25)) -> -237619 | BL26: =SUM(BI26/BE26)-1 -> -0.51168836
B27: EBT Margin (%) | C27: =C26/C11 -> -0.33985717 | D27: =D26/D11 -> -0.041739259 | E27: =E26/E11 -> -0.1295033 | F27: =F26/F11 -> -0.38534108 | G27: =G26/G11 -> -0.8286695 | H27: =H26/H11 -> -0.97338486 | I27: =I26/I11 -> -0.4908256 | K27: =K26/K11 -> -0.44583594 | L27: =L26/L11 -> -0.42586515 | M27: =M26/M11 -> -0.35552004 | N27: =N26/N11 -> -0.2364346 | O27: =O26/O11 -> -0.16537333 | P27: =P26/P11 -> -0.14007227 | Q27: =Q26/Q11 -> 0.044573243 | R27: =R26/R11 -> -0.0047116644 | ... AO27: =AO26/AO11 -> -1.5762483 | AQ27: =AQ26/AQ11 -> -0.1295033 | AR27: =AR26/AR11 -> -0.19464672 | AS27: =AS26/AS11 -> -0.19955811 | AT27: =AT26/AT11 -> -0.26956449 | AU27: =AU26/AU11 -> -0.38534108 | AV27: =AV26/AV11 -> -0.54078512 | AW27: =AW26/AW11 -> -0.70803594 | AX27: =AX26/AX11 -> -0.83456796 | ... BJ27: =BJ26/BJ11 -> -0.8177826 | BL27: =SUM(BI27-BE27)*1000 -> 479.74137
B29: Provision for taxes | C29: -1 | D29: -9 | E29: -72 | F29: -60 | G29: -32 | H29: -5 | I29: 26 | K29: 0 | L29: 0 | M29: 0 | N29: =SUM(C29-SUM(K29:M29)) -> -1 | O29: 0 | P29: -21 | Q29: 0 | R29: =SUM(D29-SUM(O29:Q29)) -> 12 | S29: 1 | T29: -16 | U29: -55 | V29: =SUM(E29-SUM(S29:U29)) -> -2 | W29: -48 | X29: -2 | Y29: 23 | Z29: =SUM(F29-SUM(W29:Y29)) -> -33 | AA29: -10 | AB29: -11 | AC29: 0 | AD29: =SUM(G29-SUM(AA29:AC29)) -> -11 | AE29: 0 | AF29: -5 | AG29: 0 | AH29: =SUM(H29-SUM(AE29:AG29)) -> 0 | AI29: -2 | AJ29: 34 | AK29: -6 | AL29: =SUM(I29-SUM(AI29:AK29)) -> 0 | AM29: 0 | AN29: 0 | AO29: 0 | AQ29: =SUM(S29:V29) -> -72 | AR29: =SUM(T29:W29) -> -121 | AS29: =SUM(U29:X29) -> -107 | AT29: =SUM(V29:Y29) -> -29 | AU29: =SUM(W29:Z29) -> -60 | AV29: =SUM(X29:AA29) -> -22 | AW29: =SUM(Y29:AB29) -> -31 | AX29: =SUM(Z29:AC29) -> -54 | ... BJ29: =SUM(AL29:AO29) -> 0 | BL29: =SUM(BI29/BE29)-1 -> -1.1875
B30: Equity in Losses of Unconsolidated Joint Venture | C30: 0 | D30: 0 | E30: 0 | F30: -2977 | G30: -18948 | H30: -3902 | I30: -73 | K30: 0 | L30: 0 | M30: 0 | N30: =SUM(C30-SUM(K30:M30)) -> 0 | O30: 0 | P30: 0 | Q30: 0 | R30: =SUM(D30-SUM(O30:Q30)) -> 0 | S30: 0 | T30: 0 | U30: 0 | V30: =SUM(E30-SUM(S30:U30)) -> 0 | W30: -374 | X30: -207 | Y30: -595 | Z30: -1801 | AA30: -671 | AB30: -1432 | AC30: -8746 | AD30: -8099 | AE30: -3235 | AF30: -503 | AG30: -126 | AH30: -38 | AI30: 7 | AJ30: -30 | AK30: -38 | AL30: -12 | AM30: -11 | AN30: -59 | AO30: -7 | AQ30: =SUM(S30:V30) -> 0 | AR30: =SUM(T30:W30) -> -374 | AS30: =SUM(U30:X30) -> -581 | AT30: =SUM(V30:Y30) -> -1176 | AU30: =SUM(W30:Z30) -> -2977 | AV30: =SUM(X30:AA30) -> -3274 | AW30: =SUM(Y30:AB30) -> -4499 | AX30: =SUM(Z30:AC30) -> -12650 | ... BJ30: =SUM(AL30:AO30) -> -89
B31: Net loss | C31: =SUM(C26+SUM(C29:C30)) -> -29886 | D31: =SUM(D26+SUM(D29:D30)) -> -12443 | E31: =SUM(E26+SUM(E29:E30)) -> -52752 | F31: =SUM(F26+SUM(F29:F30)) -> -182105 | G31: =SUM(G26+SUM(G29:G30)) -> -366137 | H31: =SUM(H26+SUM(H29:H30)) -> -338144 | I31: =SUM(I26+SUM(I29:I30)) -> -160278 | K31: =SUM(K26+SUM(K29:K30)) -> -5696 | L31: =SUM(L26+SUM(L29:L30)) -> -7396 | M31: =SUM(M26+SUM(M29:M30)) -> -9342 | N31: =SUM(N26+SUM(N29:N30)) -> -7452 | O31: =SUM(O26+SUM(O29:O30)) -> -6649 | P31: =SUM(P26+SUM(P29:P30)) -> -9441 | Q31: =SUM(Q26+SUM(Q29:Q30)) -> 4099 | R31: =SUM(R26+SUM(R29:R30)) -> -452 | ... AO31: =SUM(AO26+SUM(AO29:AO30)) -> -110688 | AQ31: =SUM(AQ26+SUM(AQ29:AQ30)) -> -52752 | AR31: =SUM(AR26+SUM(AR29:AR30)) -> -81833 | AS31: =SUM(AS26+SUM(AS29:AS30)) -> -91280 | AT31: =SUM(AT26+SUM(AT29:AT30)) -> -126811 | AU31: =SUM(AU26+SUM(AU29:AU30)) -> -182105 | AV31: =SUM(AV26+SUM(AV29:AV30)) -> -255297 | AW31: =SUM(AW26+SUM(AW29:AW30)) -> -332779 | AX31: =SUM(AX26+SUM(AX29:AX30)) -> -379641 | ... BJ31: =SUM(BJ26+SUM(BJ29:BJ30)) -> -237708 | BL31: =SUM(BI31/BE31)-1 -> -0.51152836
B32: Net Margin (%) | C32: =C31/C11 -> -0.33986854 | D32: =D31/D11 -> -0.041769471 | E32: =E31/E11 -> -0.1296803 | F32: =F31/F11 -> -0.39187648 | G32: =G31/G11 -> -0.87397507 | H32: =H31/H11 -> -0.98476306 | I32: =I31/I11 -> -0.49096958 | K32: =K31/K11 -> -0.44583594 | L32: =L31/L11 -> -0.42586515 | M32: =M31/M11 -> -0.35552004 | N32: =N31/N11 -> -0.23646633 | O32: =O31/O11 -> -0.16537333 | P32: =P31/P11 -> -0.14038453 | Q32: =Q31/Q11 -> 0.044573243 | R32: =R31/R11 -> -0.004589811 | ... AO32: =AO31/AO11 -> -1.5763479 | AQ32: =AQ31/AQ11 -> -0.1296803 | AR32: =AR31/AR11 -> -0.19583129 | AS32: =AS31/AS11 -> -0.20107366 | AT32: =AT31/AT11 -> -0.27215055 | AU32: =AU31/AU11 -> -0.39187648 | AV32: =AV31/AV11 -> -0.54785822 | AW32: =AW31/AW11 -> -0.71780718 | AX32: =AX31/AX11 -> -0.86346216 | ... BJ32: =BJ31/BJ11 -> -0.8180889 | BL32: =SUM(BI32-BE32)*1000 -> 479.81102
B34: Basic shares | C34: 0 | D34: 61845.096 | E34: 62940.338 | F34: 63455.45 | G34: 64094.519 | H34: 64677.261 | I34: 76131.339 | M34: 6441.838 | N34: =D34 -> 61845.096 | O34: 60122.797 | P34: 60178.252 | Q34: 60415.866 | R34: =H34 -> 64677.261 | S34: 61679.929 | T34: 62098.861 | U34: 62487.152 | V34: =E34 -> 62940.338 | W34: 62941.748 | X34: 63121.4 | Y34: 63280.122 | Z34: =F34 -> 63455.45 | AA34: 63465.205 | AB34: 63573.658 | AC34: 63694.592 | AD34: =G34 -> 64094.519 | AE34: 64004.894 | AF34: 64246.048 | AG34: 64398.448 | AH34: =H34 -> 64677.261 | AI34: 64702.249 | AJ34: 64901.584 | AK34: 65060.729 | AL34: =I34 -> 76131.339 | AM34: 76194.916 | AN34: 76491.594 | AO34: 76670.868 | AQ34: =V34 -> 62940.338 | AR34: =W34 -> 62941.748 | AS34: =X34 -> 63121.4 | AT34: =Y34 -> 63280.122 | AU34: =Z34 -> 63455.45 | AV34: =AA34 -> 63465.205 | AW34: =AB34 -> 63573.658 | AX34: =AC34 -> 63694.592 | ... BJ34: =AO34 -> 76670.868
B35: Basic EPS | C35: =C31/C34 -> #DIV/0! | D35: =D31/D34 -> -0.20119623 | E35: =E31/E34 -> -0.83812705 | F35: =F31/F34 -> -2.8698087 | G35: =G31/G34 -> -5.7124541 | H35: =H31/H34 -> -5.2281744 | I35: =I31/I34 -> -2.1052828 | K35: =K31/K34 -> #DIV/0! | L35: =L31/L34 -> #DIV/0! | M35: =M31/M34 -> -1.4502072 | N35: =N31/N34 -> -0.1204946 | O35: =O31/O34 -> -0.11059033 | P35: =P31/P34 -> -0.15688392 | Q35: =Q31/Q34 -> 0.067846416 | R35: =R31/R34 -> -0.0069885458 | ... AO35: =AO31/AO34 -> -1.4436774 | AQ35: =AQ31/AQ34 -> -0.83812705 | AR35: =AR31/AR34 -> -1.3001387 | AS35: =AS31/AS34 -> -1.4461023 | AT35: =AT31/AT34 -> -2.0039626 | AU35: =AU31/AU34 -> -2.8698087 | AV35: =AV31/AV34 -> -4.0226294 | AW35: =AW31/AW34 -> -5.2345423 | AX35: =AX31/AX34 -> -5.9603333 | ... BJ35: =BJ31/BJ34 -> -3.1003692 | BL35: =SUM(BI35/BE35)-1 -> -0.5855416
B37: Fully Diluted Shares | C37: 6287.172 | D37: 42274.777 | E37: 62290.445 | F37: 63172.368 | G37: 63622.432 | H37: 64300.099 | I37: 66004.815 | K37: 5793.801 | L37: 6072.319 | M37: 6441.838 | N37: =D37 -> 42274.777 | O37: 6974.301 | P37: 39081.359 | Q37: 66026.49 | R37: =H37 -> 64300.099 | S37: 65927.988 | T37: 62098.861 | U37: 62487.152 | V37: =E37 -> 62290.445 | W37: 62941.748 | X37: 63121.4 | Y37: 63280.122 | Z37: =F37 -> 63172.368 | AA37: 63465.205 | AB37: 63573.658 | AC37: 63694.592 | AD37: =G37 -> 63622.432 | AE37: 64004.894 | AF37: 64246.048 | AG37: 64398.448 | AH37: =H37 -> 64300.099 | AI37: 64702.249 | AJ37: 64901.584 | AK37: 65060.729 | AL37: =I37 -> 66004.815 | AM37: 76194.916 | AN37: 76491.594 | AO37: 76670.868 | AQ37: =V37 -> 62290.445 | AR37: =W37 -> 62941.748 | AS37: =X37 -> 63121.4 | AT37: =Y37 -> 63280.122 | AU37: =Z37 -> 63172.368 | AV37: =AA37 -> 63465.205 | AW37: =AB37 -> 63573.658 | AX37: =AC37 -> 63694.592 | ... BJ37: =AO37 -> 76670.868
B38: Diluted EPS | C38: =C31/C37 -> -4.7534885 | D38: =D31/D37 -> -0.29433627 | E38: =E31/E37 -> -0.84687146 | F38: =F31/F37 -> -2.8826686 | G38: =G31/G37 -> -5.7548413 | H38: =H31/H37 -> -5.258841 | I38: =I31/I37 -> -2.4282774 | K38: =K31/K37 -> -0.98311972 | L38: =L31/L37 -> -1.2179861 | M38: =M31/M37 -> -1.4502072 | N38: =N31/N37 -> -0.17627532 | O38: =O31/O37 -> -0.95335719 | P38: =P31/P37 -> -0.24157297 | Q38: =Q31/Q37 -> 0.062081143 | R38: =R31/R37 -> -0.0070295382 | ... AO38: =AO31/AO37 -> -1.4436774 | AQ38: =AQ31/AQ37 -> -0.84687146 | AR38: =AR31/AR37 -> -1.3001387 | AS38: =AS31/AS37 -> -1.4461023 | AT38: =AT31/AT37 -> -2.0039626 | AU38: =AU31/AU37 -> -2.8826686 | AV38: =AV31/AV37 -> -4.0226294 | AW38: =AW31/AW37 -> -5.2345423 | AX38: =AX31/AX37 -> -5.9603333 | ... BJ38: =BJ31/BJ37 -> -3.1003692 | BL38: =SUM(BI38/BE38)-1 -> -0.5855416
A40: X | B40: Balance Sheet | K40: Quarterly | BE40: LTM | BL40: Variance
B41: =B7 -> Fiscal Period | C41: =C7 -> 2018 | D41: =D7 -> 2019 | E41: =E7 -> 2020 | F41: =F7 -> 2021 | G41: =G7 -> 2022 | H41: =H7 -> 2023 | I41: =I7 -> 2024 | K41: =K7 -> 1Q18 | L41: =L7 -> 2Q18 | M41: =M7 -> 3Q18 | N41: =N7 -> 4Q18 | O41: =O7 -> 1Q19 | P41: =P7 -> 2Q19 | Q41: =Q7 -> 3Q19 | R41: =R7 -> 4Q19 | ... AO41: =AO7 -> 3Q25 | AQ41: =AQ7 -> 4Q20 | AR41: =AR7 -> 1Q21 | AS41: =AS7 -> 2Q21 | AT41: =AT7 -> 3Q21 | AU41: =AU7 -> 4Q21 | AV41: =AV7 -> 1Q22 | AW41: =AW7 -> 2Q22 | AX41: =AX7 -> 3Q22 | ... BJ41: =BJ7 -> 3Q25
B42: =B8 -> Fiscal Period End Date | C42: =C8 -> 43465 | D42: =D8 -> 43830 | E42: =E8 -> 44196 | F42: =F8 -> 44561 | G42: =G8 -> 44926 | H42: =H8 -> 45291 | I42: =I8 -> 45657 | K42: =K8 -> 43190 | L42: =L8 -> 43281 | M42: =M8 -> 43372 | N42: =N8 -> 43465 | O42: =O8 -> 43554 | P42: =P8 -> 43645 | Q42: =Q8 -> 43736 | R42: =R8 -> 43830 | ... AO42: =AO8 -> 45927 | AQ42: =AQ8 -> 44196 | AR42: =AR8 -> 44289 | AS42: =AS8 -> 44380 | AT42: =AT8 -> 44471 | AU42: =AU8 -> 44561 | AV42: =AV8 -> 44653 | AW42: =AW8 -> 44744 | AX42: =AX8 -> 44835 | ... BJ42: =BJ8 -> 45927
B44: Current Assets
B45: Cash and Cash Equivalents | C45: 54271 | D45: 275988 | E45: 159127 | F45: 733294 | G45: 309922 | H45: 190505 | I45: 131913 | K45: 29047 | L45: 23489 | M45: 49780 | N45: =C45 -> 54271 | O45: 35409 | P45: 276987 | Q45: 312451 | R45: =D45 -> 275988 | S45: 246410 | T45: 222334 | U45: 214615 | V45: =E45 -> 159127 | W45: 1125017 | X45: 1009337 | Y45: 886442 | Z45: =F45 -> 733294 | AA45: 547858 | AB45: 454674 | AC45: 390176 | AD45: =G45 -> 309922 | AE45: 258566 | AF45: 210781 | AG45: 217545 | AH45: =H45 -> 190505 | AI45: 157913 | AJ45: 144873 | AK45: 121732 | AL45: =I45 -> 131913 | AM45: 102143 | AN45: 103497 | AO45: 117296 | AQ45: =V45 -> 159127 | AR45: =W45 -> 1125017 | AS45: =X45 -> 1009337 | AT45: =Y45 -> 886442 | AU45: =Z45 -> 733294 | AV45: =AA45 -> 547858 | AW45: =AB45 -> 454674 | AX45: =AC45 -> 390176 | ... BJ45: =AO45 -> 117296 | BL45: =SUM(BI45/BE45)-1 -> -0.28560187
B46: Restricted Cash | C46: 0 | D46: 0 | E46: 0 | F46: 0 | G46: 0 | H46: 2830 | I46: 1041 | N46: =C46 -> 0 | O46: 0 | P46: 0 | Q46: 0 | R46: =D46 -> 0 | S46: 0 | T46: 0 | U46: 0 | V46: =E46 -> 0 | W46: 0 | X46: 0 | Y46: 0 | Z46: =F46 -> 0 | AA46: 0 | AB46: 0 | AC46: 0 | AD46: =G46 -> 0 | AE46: 2426 | AF46: 2552 | AG46: 2689 | AH46: =H46 -> 2830 | AI46: 2971 | AJ46: 536 | AK46: 558 | AL46: =I46 -> 1041 | AM46: 1083 | AN46: 1172 | AO46: 1170 | AQ46: =V46 -> 0 | AR46: =W46 -> 0 | AS46: =X46 -> 0 | AT46: =Y46 -> 0 | AU46: =Z46 -> 0 | AV46: =AA46 -> 0 | AW46: =AB46 -> 0 | AX46: =AC46 -> 0 | ... BJ46: =AO46 -> 1170
B47: Accounts Receivables | C47: 12626 | D47: 40080 | E47: 35975 | F47: 43806 | G47: 34198 | H47: 31730 | I47: 26862 | N47: =C47 -> 12626 | O47: 16194 | P47: 34388 | Q47: 34482 | R47: =D47 -> 40080 | S47: 36333 | T47: 45986 | U47: 29760 | V47: =E47 -> 35975 | W47: 36653 | X47: 63369 | Y47: 48849 | Z47: =F47 -> 43806 | AA47: 52675 | AB47: 77154 | AC47: 34949 | AD47: =G47 -> 34198 | AE47: 42395 | AF47: 50821 | AG47: 35763 | AH47: =H47 -> 31730 | AI47: 35648 | AJ47: 34463 | AK47: 34674 | AL47: =I47 -> 26862 | AM47: 33267 | AN47: 37338 | AO47: 27920 | AQ47: =V47 -> 35975 | AR47: =W47 -> 36653 | AS47: =X47 -> 63369 | AT47: =Y47 -> 48849 | AU47: =Z47 -> 43806 | AV47: =AA47 -> 52675 | AW47: =AB47 -> 77154 | AX47: =AC47 -> 34949 | ... BJ47: =AO47 -> 27920 | BL47: =SUM(BI47/BE47)-1 -> 0.083422801
B48: Inventory | C48: 30257 | D48: 81596 | E48: 121717 | F48: 241870 | G48: 235696 | H48: 130336 | I48: 113444 | N48: =C48 -> 30257 | O48: 34281 | P48: 42695 | Q48: 60270 | R48: =D48 -> 81596 | S48: 120702 | T48: 143033 | U48: 132359 | V48: =E48 -> 121717 | W48: 145524 | X48: 165746 | Y48: 193490 | Z48: =F48 -> 241870 | AA48: 283754 | AB48: 254653 | AC48: 246987 | AD48: =G48 -> 235696 | AE48: 222370 | AF48: 207138 | AG48: 194570 | AH48: =H48 -> 130336 | AI48: 122538 | AJ48: 119532 | AK48: 125158 | AL48: =I48 -> 113444 | AM48: 100068 | AN48: 110868 | AO48: 110294 | AQ48: =V48 -> 121717 | AR48: =W48 -> 145524 | AS48: =X48 -> 165746 | AT48: =Y48 -> 193490 | AU48: =Z48 -> 241870 | AV48: =AA48 -> 283754 | AW48: =AB48 -> 254653 | AX48: =AC48 -> 246987 | ... BJ48: =AO48 -> 110294
B49: Prepaid Expenses and Other Current Assets (1) | C49: 5672 | D49: 5930 | E49: 15407 | F49: 33078 | G49: =20700+5943 -> 26643 | H49: =12904+4539 -> 17443 | I49: =11332+1864 -> 13196 | N49: =C49 -> 5672 | O49: 6525 | P49: 7726 | Q49: 11742 | R49: =D49 -> 5930 | S49: 12498 | T49: 17990 | U49: 14195 | V49: =E49 -> 15407 | W49: 17788 | X49: 25630 | Y49: 24341 | Z49: =F49 -> 33078 | AA49: 33010 | AB49: 33029 | AC49: 23868 | AD49: =G49 -> 26643 | AE49: =16561+4737 -> 21298 | AF49: =26051+98 -> 26149 | AG49: =20938+118 -> 21056 | AH49: =H49 -> 17443 | AI49: =15032+2401 -> 17433 | AJ49: =15538+2323 -> 17861 | AK49: =13016+2275 -> 15291 | AL49: =I49 -> 13196 | AM49: =19135+1576 -> 20711 | AN49: =42596+1664 -> 44260 | AO49: =31048+910 -> 31958 | AQ49: =V49 -> 15407 | AR49: =W49 -> 17788 | AS49: =X49 -> 25630 | AT49: =Y49 -> 24341 | AU49: =Z49 -> 33078 | AV49: =AA49 -> 33010 | AW49: =AB49 -> 33029 | AX49: =AC49 -> 23868 | ... BJ49: =AO49 -> 31958
B50: Total Current Assets | C50: =SUM(C45:C49) -> 102826 | D50: =SUM(D45:D49) -> 403594 | E50: =SUM(E45:E49) -> 332226 | F50: =SUM(F45:F49) -> 1052048 | G50: =SUM(G45:G49) -> 606459 | H50: =SUM(H45:H49) -> 372844 | I50: =SUM(I45:I49) -> 286456 | K50: =SUM(K45:K49) -> 29047 | L50: =SUM(L45:L49) -> 23489 | M50: =SUM(M45:M49) -> 49780 | N50: =SUM(N45:N49) -> 102826 | O50: =SUM(O45:O49) -> 92409 | P50: =SUM(P45:P49) -> 361796 | Q50: =SUM(Q45:Q49) -> 418945 | R50: =SUM(R45:R49) -> 403594 | ... AO50: =SUM(AO45:AO49) -> 288638 | AQ50: =SUM(AQ45:AQ49) -> 332226 | AR50: =SUM(AR45:AR49) -> 1324982 | AS50: =SUM(AS45:AS49) -> 1264082 | AT50: =SUM(AT45:AT49) -> 1153122 | AU50: =SUM(AU45:AU49) -> 1052048 | AV50: =SUM(AV45:AV49) -> 917297 | AW50: =SUM(AW45:AW49) -> 819510 | AX50: =SUM(AX45:AX49) -> 695980 | ... BJ50: =SUM(BJ45:BJ49) -> 288638 | BL50: =SUM(BI50/BE50)-1 -> -0.063448537
B52: Non-Current Assets | BL52: =SUM(BI52/BE52)-1 -> #DIV/0!
B53: Restricted Cash, Non-Current | C53: 0 | D53: 0 | E53: 0 | F53: 0 | G53: 12627 | H53: 12600 | I53: 12600 | N53: =C53 -> 0 | O53: 0 | P53: 0 | Q53: 0 | R53: 0 | S53: 0 | T53: 0 | U53: 0 | V53: =E53 -> 0 | W53: 0 | X53: 0 | Y53: 0 | Z53: =F53 -> 0 | AA53: 0 | AB53: 0 | AC53: 0 | AD53: =G53 -> 12627 | AE53: 12600 | AF53: 12600 | AG53: 12600 | AH53: =H53 -> 12600 | AI53: 12600 | AJ53: 12600 | AK53: 12600 | AL53: =I53 -> 12600 | AM53: 12600 | AN53: 12600 | AO53: 12600 | AQ53: =V53 -> 0 | AR53: =W53 -> 0 | AS53: =X53 -> 0 | AT53: =Y53 -> 0 | AU53: =Z53 -> 0 | AV53: =AA53 -> 0 | AW53: =AB53 -> 0 | AX53: =AC53 -> 0 | ... BJ53: =AO53 -> 12600
B54: Operating Lease Right-of-use Assets | C54: 396 | D54: 855 | E54: 14570 | F54: 26815 | G54: 87595 | H54: 130460 | I54: 123975 | N54: =C54 -> 396 | O54: 887 | P54: 792 | Q54: 846 | R54: =D54 -> 855 | S54: 12431 | T54: 13793 | U54: 13736 | V54: =E54 -> 14570 | W54: 13938 | X54: 14672 | Y54: 25444 | Z54: =F54 -> 26815 | AA54: 25692 | AB54: 25464 | AC54: 88335 | AD54: =G54 -> 87595 | AE54: 75056 | AF54: 136264 | AG54: 132671 | AH54: =H54 -> 130460 | AI54: 129379 | AJ54: 127679 | AK54: 126092 | AL54: =I54 -> 123975 | AM54: 121131 | AN54: 6527 | AO54: 5218 | AQ54: =V54 -> 14570 | AR54: =W54 -> 13938 | AS54: =X54 -> 14672 | AT54: =Y54 -> 25444 | AU54: =Z54 -> 26815 | AV54: =AA54 -> 25692 | AW54: =AB54 -> 25464 | AX54: =AC54 -> 88335 | ... BJ54: =AO54 -> 5218
B55: Property, Plant and Equipment, Net | C55: 30527 | D55: 47474 | E55: 115299 | F55: 226489 | G55: 257002 | H55: 194046 | I55: 184887 | N55: =C55 -> 30527 | O55: 31861 | P55: 34473 | Q55: 35050 | R55: =D55 -> 47474 | S55: 61758 | T55: 70286 | U55: 77002 | V55: =E55 -> 115299 | W55: 132094 | X55: 157449 | Y55: 197290 | Z55: =F55 -> 226489 | AA55: 241389 | AB55: 258075 | AC55: 262595 | AD55: =G55 -> 257002 | AE55: 251218 | AF55: 250335 | AG55: 245373 | AH55: =H55 -> 194046 | AI55: 190896 | AJ55: 186584 | AK55: 188115 | AL55: =I55 -> 184887 | AM55: 180781 | AN55: 320988 | AO55: 254387 | AQ55: =V55 -> 115299 | AR55: =W55 -> 132094 | AS55: =X55 -> 157449 | AT55: =Y55 -> 197290 | AU55: =Z55 -> 226489 | AV55: =AA55 -> 241389 | AW55: =AB55 -> 258075 | AX55: =AC55 -> 262595 | ... BJ55: =AO55 -> 254387
B56: Investments in Unconsolidated Joint Ventures | C56: 0 | D56: 0 | E56: 0 | F56: 8023 | G56: 2325 | H56: 1673 | I56: 1601 | N56: =C56 -> 0 | O56: 0 | P56: 0 | Q56: 0 | R56: 0 | S56: 0 | T56: 0 | U56: 0 | V56: =E56 -> 0 | W56: 0 | X56: 0 | Y56: 0 | Z56: =F56 -> 8023 | AA56: 7353 | AB56: 5920 | AC56: 7174 | AD56: =G56 -> 2325 | AE56: 2340 | AF56: 1837 | AG56: 1711 | AH56: =H56 -> 1673 | AI56: 1680 | AJ56: 1650 | AK56: 1612 | AL56: =I56 -> 1601 | AM56: 1589 | AN56: 1531 | AO56: 1523 | AQ56: =V56 -> 0 | AR56: =W56 -> 0 | AS56: =X56 -> 0 | AT56: =Y56 -> 0 | AU56: =Z56 -> 8023 | AV56: =AA56 -> 7353 | AW56: =AB56 -> 5920 | AX56: =AC56 -> 7174 | ... BJ56: =AO56 -> 1523
B57: Prepaid lease Costs, non-current | C57: 0 | D57: 0 | E57: 0 | F57: 59188 | G57: 85472 | H57: 61635 | I57: 68005 | N57: =C57 -> 0 | O57: 0 | P57: 0 | Q57: 0 | R57: 0 | S57: 0 | T57: 0 | U57: 0 | V57: =E57 -> 0 | W57: 0 | X57: 26578 | Y57: 49456 | Z57: =F57 -> 59188 | AA57: 96166 | AB57: 102839 | AC57: 80533 | AD57: =G57 -> 85472 | AE57: 88035 | AF57: 60794 | AG57: 60680 | AH57: =H57 -> 61635 | AI57: 63264 | AJ57: 64822 | AK57: 66444 | AL57: =I57 -> 68005 | AM57: 69814 | AN57: 52272 | AO57: 35704 | AQ57: =V57 -> 0 | AR57: =W57 -> 0 | AS57: =X57 -> 26578 | AT57: =Y57 -> 49456 | AU57: =Z57 -> 59188 | AV57: =AA57 -> 96166 | AW57: =AB57 -> 102839 | AX57: =AC57 -> 80533 | ... BJ57: =AO57 -> 35704
B58: Other Non-current Assets (Net) | C58: 0 | D58: 0 | E58: 5911 | F58: 6836 | G58: 10744 | H58: 1192 | I58: 622 | N58: =C58 -> 0 | O58: 0 | P58: 0 | Q58: 0 | R58: 0 | S58: 1501 | T58: 4552 | U58: 4970 | V58: =E58 -> 5911 | W58: 4505 | X58: 3739 | Y58: 7062 | Z58: =F58 -> 6836 | AA58: 6613 | AB58: 6301 | AC58: 6670 | AD58: =G58 -> 10744 | AE58: 10273 | AF58: 9314 | AG58: 4550 | AH58: =H58 -> 1192 | AI58: 704 | AJ58: 634 | AK58: 662 | AL58: =I58 -> 622 | AM58: 643 | AN58: 688 | AO58: 1599 | AQ58: =V58 -> 5911 | AR58: =W58 -> 4505 | AS58: =X58 -> 3739 | AT58: =Y58 -> 7062 | AU58: =Z58 -> 6836 | AV58: =AA58 -> 6613 | AW58: =AB58 -> 6301 | AX58: =AC58 -> 6670 | ... BJ58: =AO58 -> 1599
B59: Total Assets | C59: =SUM(C53:C58)+C50 -> 133749 | D59: =SUM(D53:D58)+D50 -> 451923 | E59: =SUM(E53:E58)+E50 -> 468006 | F59: =SUM(F53:F58)+F50 -> 1379399 | G59: =SUM(G53:G58)+G50 -> 1062224 | H59: =SUM(H53:H58)+H50 -> 774450 | I59: =SUM(I53:I58)+I50 -> 678146 | K59: =SUM(K53:K58)+K50 -> 29047 | L59: =SUM(L53:L58)+L50 -> 23489 | M59: =SUM(M53:M58)+M50 -> 49780 | N59: =SUM(N53:N58)+N50 -> 133749 | O59: =SUM(O53:O58)+O50 -> 125157 | P59: =SUM(P53:P58)+P50 -> 397061 | Q59: =SUM(Q53:Q58)+Q50 -> 454841 | R59: =SUM(R53:R58)+R50 -> 451923 | ... AO59: =SUM(AO53:AO58)+AO50 -> 599669 | AQ59: =SUM(AQ53:AQ58)+AQ50 -> 468006 | AR59: =SUM(AR53:AR58)+AR50 -> 1475519 | AS59: =SUM(AS53:AS58)+AS50 -> 1466520 | AT59: =SUM(AT53:AT58)+AT50 -> 1432374 | AU59: =SUM(AU53:AU58)+AU50 -> 1379399 | AV59: =SUM(AV53:AV58)+AV50 -> 1294510 | AW59: =SUM(AW53:AW58)+AW50 -> 1218109 | AX59: =SUM(AX53:AX58)+AX50 -> 1141287 | ... BJ59: =SUM(BJ53:BJ58)+BJ50 -> 599669 | BL59: =SUM(BI59/BE59)-1 -> -0.027407295
B61: Current Liabilities
B62: Accounts Payable | C62: 17247 | D62: 26923 | E62: 53071 | F62: 69040 | G62: 55300 | H62: 56032 | I62: 37571 | N62: =C62 -> 17247 | O62: 11663 | P62: 27383 | Q62: 38348 | R62: =D62 -> 26923 | S62: 48219 | T62: 51567 | U62: 30531 | V62: =E62 -> 53071 | W62: 51456 | X62: 49951 | Y62: 45387 | Z62: =F62 -> 69040 | AA62: 67387 | AB62: 74430 | AC62: 68676 | AD62: =G62 -> 55300 | AE62: 41131 | AF62: 39508 | AG62: 61861 | AH62: =H62 -> 56032 | AI62: 55836 | AJ62: 59449 | AK62: 59633 | AL62: =I62 -> 37571 | AM62: 50512 | AN62: 68837 | AO62: 46091 | AQ62: =V62 -> 53071 | AR62: =W62 -> 51456 | AS62: =X62 -> 49951 | AT62: =Y62 -> 45387 | AU62: =Z62 -> 69040 | AV62: =AA62 -> 67387 | AW62: =AB62 -> 74430 | AX62: =AC62 -> 68676 | ... BJ62: =AO62 -> 46091
B63: Accrued Expenses, Other Current Liabilities, and Other Payables (2) | C63: =2391+2312+1918+1255 -> 7876 | D63: =3805+4129+1768-D65 -> 9630 | E63: =4830+57+2843-E65 -> 7659 | F63: =20226+128+155-F65 -> 20327 | G63: =16729-G65 -> 16505 | H63: =9855+4790-H65 -> 14449 | I63: =11925+582+7250-I65 -> 18906 | N63: =C63 -> 7876 | O63: =3094+3387+2677+1085 -> 10243 | P63: =3622+2157+1208 -> 6987 | Q63: =4113+3181+1433 -> 8727 | R63: =D63 -> 9630 | S63: =5297+723+1949 -> 7969 | T63: =8829+1416+2024 -> 12269 | U63: =10241+43+2289 -> 12573 | V63: =E63 -> 7659 | W63: =11903+2565+3899 -> 18367 | X63: =14369+2696+648 -> 17713 | Y63: =19091+1400+4269 -> 24760 | Z63: =F63 -> 20327 | AA63: =22807+2754+3406 -> 28967 | AB63: =22975+4333+2984 -> 30292 | AC63: =14693+148+2348 -> 17189 | AD63: =G63 -> 16505 | AE63: =15826-AE65 -> 15580 | AF63: =12009-AF65 -> 11791 | AG63: =13914-AG65 -> 13705 | AH63: =H63 -> 14449 | AI63: =10665+822+7500-AI65 -> 18224 | AJ63: =12051+393+7500-AJ65 -> 18939 | AK63: =15260+345+7250-AK65 -> 21715 | AL63: =I63 -> 18906 | AM63: =14199+7250-AM65 -> 20620 | AN63: =15618 -> 15618 | AO63: 11244 | AQ63: =V63 -> 7659 | AR63: =W63 -> 18367 | AS63: =X63 -> 17713 | AT63: =Y63 -> 24760 | AU63: =Z63 -> 20327 | AV63: =AA63 -> 28967 | AW63: =AB63 -> 30292 | AX63: =AC63 -> 17189 | ... BJ63: =AO63 -> 11244
B64: Current Portion of Operating Lease Liabilities | C64: 0 | D64: 0 | E64: 3095 | F64: 4458 | G64: 3812 | H64: 3677 | I64: 4125 | N64: =C64 -> 0 | O64: 0 | P64: 0 | Q64: 0 | R64: =D64 -> 0 | S64: 1628 | T64: 2367 | U64: 2481 | V64: =E64 -> 3095 | W64: 3101 | X64: 3651 | Y64: 3962 | Z64: =F64 -> 4458 | AA64: 4454 | AB64: 4595 | AC64: 4585 | AD64: =G64 -> 3812 | AE64: 2960 | AF64: 3127 | AG64: 3083 | AH64: =H64 -> 3677 | AI64: 3976 | AJ64: 4125 | AK64: 4103 | AL64: =I64 -> 4125 | AM64: 3941 | AN64: 1798 | AO64: 1753 | AQ64: =V64 -> 3095 | AR64: =W64 -> 3101 | AS64: =X64 -> 3651 | AT64: =Y64 -> 3962 | AU64: =Z64 -> 4458 | AV64: =AA64 -> 4454 | AW64: =AB64 -> 4595 | AX64: =AC64 -> 4585 | ... BJ64: =AO64 -> 1753
B65: Current Portion of Finance Lease Liabilities | C65: 44 | D65: 72 | E65: 71 | F65: 182 | G65: 224 | H65: 196 | I65: 851 | N65: =C65 -> 44 | O65: 36 | P65: 33 | Q65: 30 | R65: =D65 -> 72 | S65: 73 | T65: 72 | U65: 72 | V65: =E65 -> 71 | W65: 185 | X65: 184 | Y65: 183 | Z65: =F65 -> 182 | AA65: 183 | AB65: 210 | AC65: 226 | AD65: =G65 -> 224 | AE65: 246 | AF65: 218 | AG65: 209 | AH65: =H65 -> 196 | AI65: 763 | AJ65: 1005 | AK65: 1140 | AL65: =I65 -> 851 | AM65: 829 | AN65: 3934 | AO65: 4554 | AQ65: =V65 -> 71 | AR65: =W65 -> 185 | AS65: =X65 -> 184 | AT65: =Y65 -> 183 | AU65: =Z65 -> 182 | AV65: =AA65 -> 183 | AW65: =AB65 -> 210 | AX65: =AC65 -> 226 | ... BJ65: =AO65 -> 4554
B66: Consolidated Short-Term Borrowings (3) | C66: 0 | D66: =11000+72 -> 11072 | E66: =25000+71 -> 25071 | F66: 182 | G66: 0 | H66: 0 | I66: 0 | N66: =C66 -> 0 | O66: 0 | P66: =6000 -> 6000 | Q66: =9087 -> 9087 | R66: =D66 -> 11072 | S66: =14094 -> 14094 | T66: 0 | U66: 0 | V66: =E66 -> 25071 | W66: 0 | X66: 0 | Y66: 0 | Z66: =F66 -> 182 | AA66: 0 | AB66: 0 | AC66: 0 | AD66: =G66 -> 0 | AE66: 0 | AF66: 0 | AG66: 0 | AH66: =H66 -> 0 | AI66: 0 | AJ66: 0 | AK66: 0 | AL66: =I66 -> 0 | AM66: 0 | AN66: 0 | AO66: 0 | AQ66: =V66 -> 25071 | AR66: =W66 -> 0 | AS66: =X66 -> 0 | AT66: =Y66 -> 0 | AU66: =Z66 -> 182 | AV66: =AA66 -> 0 | AW66: =AB66 -> 0 | AX66: =AC66 -> 0 | ... BJ66: =AO66 -> 0
B67: Total Current Liabilities | C67: =SUM(C62:C66) -> 25167 | D67: =SUM(D62:D66) -> 47697 | E67: =SUM(E62:E66) -> 88967 | F67: =SUM(F62:F66) -> 94189 | G67: =SUM(G62:G66) -> 75841 | H67: =SUM(H62:H66) -> 74354 | I67: =SUM(I62:I66) -> 61453 | K67: =SUM(K62:K66) -> 0 | L67: =SUM(L62:L66) -> 0 | M67: =SUM(M62:M66) -> 0 | N67: =SUM(N62:N66) -> 25167 | O67: =SUM(O62:O66) -> 21942 | P67: =SUM(P62:P66) -> 40403 | Q67: =SUM(Q62:Q66) -> 56192 | R67: =SUM(R62:R66) -> 47697 | ... AO67: =SUM(AO62:AO66) -> 63642 | AQ67: =SUM(AQ62:AQ66) -> 88967 | AR67: =SUM(AR62:AR66) -> 73109 | AS67: =SUM(AS62:AS66) -> 71499 | AT67: =SUM(AT62:AT66) -> 74292 | AU67: =SUM(AU62:AU66) -> 94189 | AV67: =SUM(AV62:AV66) -> 100991 | AW67: =SUM(AW62:AW66) -> 109527 | AX67: =SUM(AX62:AX66) -> 90676 | ... BJ67: =SUM(BJ62:BJ66) -> 63642 | BL67: =SUM(BI67/BE67)-1 -> 0.07985105
B69: Non-Current Liabilities
B70: Convertible Senior Notes, Net | C70: 0 | D70: 0 | E70: 0 | F70: 1129674 | G70: 1133608 | H70: 1137542 | I70: 1141476 | N70: =C70 -> 0 | O70: 0 | P70: 0 | Q70: 0 | R70: =D70 -> 0 | S70: 0 | T70: 0 | U70: 0 | V70: =E70 -> 0 | W70: 1126723 | X70: 1127707 | Y70: 1128690 | Z70: =F70 -> 1129674 | AA70: 1130657 | AB70: 1131641 | AC70: 1132624 | AD70: =G70 -> 1133608 | AE70: 1134591 | AF70: 1135575 | AG70: 1136558 | AH70: =H70 -> 1137542 | AI70: 1138525 | AJ70: 1139509 | AK70: 1140492 | AL70: =I70 -> 1141476 | AM70: 1142459 | AN70: 1143443 | AO70: 1144427 | AQ70: =V70 -> 0 | AR70: =W70 -> 1126723 | AS70: =X70 -> 1127707 | AT70: =Y70 -> 1128690 | AU70: =Z70 -> 1129674 | AV70: =AA70 -> 1130657 | AW70: =AB70 -> 1131641 | AX70: =AC70 -> 1132624 | ... BJ70: =AO70 -> 1144427
B71: Consolidated Other Long-Term Borrowings (4) | C71: =6000+19388+5000 -> 30388 | D71: =4932+14637 -> 19569 | E71: 0 | F71: 0 | G71: 0 | H71: 0 | I71: 0 | N71: =C71 -> 30388 | O71: =4914+19533+6000 -> 30447 | P71: =4924+19543 -> 24467 | Q71: =4922+16503 -> 21425 | R71: =D71 -> 19569 | S71: =12185+4347 -> 16532 | T71: 50000 | U71: 50000 | V71: =E71 -> 0 | W71: 0 | X71: 0 | Y71: 0 | Z71: =F71 -> 0 | AA71: 0 | AB71: 0 | AC71: 0 | AD71: =G71 -> 0 | AE71: 0 | AF71: 0 | AG71: 0 | AH71: =H71 -> 0 | AI71: 0 | AJ71: 0 | AK71: 0 | AL71: =I71 -> 0 | AM71: 0 | AN71: 0 | AO71: 0 | AQ71: =V71 -> 0 | AR71: =W71 -> 0 | AS71: =X71 -> 0 | AT71: =Y71 -> 0 | AU71: =Z71 -> 0 | AV71: =AA71 -> 0 | AW71: =AB71 -> 0 | AX71: =AC71 -> 0 | ... BJ71: =AO71 -> 0
B72: Delayed draw term loan, net | C72: 0 | D72: 0 | E72: 0 | F72: 0 | G72: 0 | H72: 0 | I72: 0 | N72: =C72 -> 0 | O72: 0 | P72: 0 | Q72: 0 | R72: =D72 -> 0 | S72: 0 | T72: 0 | U72: 0 | V72: =E72 -> 0 | W72: 0 | X72: 0 | Y72: 0 | Z72: =F72 -> 0 | AA72: 0 | AB72: 0 | AC72: 0 | AD72: =G72 -> 0 | AE72: 0 | AF72: 0 | AG72: 0 | AH72: =H72 -> 0 | AI72: 0 | AJ72: 0 | AK72: 0 | AL72: =I72 -> 0 | AM72: 0 | AN72: =30525 -> 30525 | AO72: 77734 | AQ72: =V72 -> 0 | AR72: =W72 -> 0 | AS72: =X72 -> 0 | AT72: =Y72 -> 0 | AU72: =Z72 -> 0 | AV72: =AA72 -> 0 | AW72: =AB72 -> 0 | AX72: =AC72 -> 0 | ... BJ72: =AO72 -> 77734
B73: Delayed draw term loan warrants | C73: 0 | D73: 0 | E73: 0 | F73: 0 | G73: 0 | H73: 0 | I73: 0 | N73: =C73 -> 0 | O73: 0 | P73: 0 | Q73: 0 | R73: =D73 -> 0 | S73: 0 | T73: 0 | U73: 0 | V73: =E73 -> 0 | W73: 0 | X73: 0 | Y73: 0 | Z73: =F73 -> 0 | AA73: 0 | AB73: 0 | AC73: 0 | AD73: =G73 -> 0 | AE73: 0 | AF73: 0 | AG73: 0 | AH73: =H73 -> 0 | AI73: 0 | AJ73: 0 | AK73: 0 | AL73: =I73 -> 0 | AM73: 0 | AN73: 20143 | AO73: 14825 | AQ73: =V73 -> 0 | AR73: =W73 -> 0 | AS73: =X73 -> 0 | AT73: =Y73 -> 0 | AU73: =Z73 -> 0 | AV73: =AA73 -> 0 | AW73: =AB73 -> 0 | AX73: =AC73 -> 0 | ... BJ73: =AO73 -> 14825
B74: Finance Lease Obligations and Other Long-term Liabilities | C74: 404 | D74: 567 | E74: 149 | F74: 442 | G74: 469 | H74: 274 | I74: 2812 | N74: =C74 -> 404 | O74: 406 | P74: 406 | Q74: 396 | R74: =D74 -> 567 | S74: 202 | T74: 185 | U74: 167 | V74: =E74 -> 149 | W74: 579 | X74: 533 | Y74: 488 | Z74: =F74 -> 442 | AA74: 396 | AB74: 3739 | AC74: 3547 | AD74: =G74 -> 469 | AE74: 416 | AF74: 362 | AG74: 316 | AH74: =H74 -> 274 | AI74: 3623 | AJ74: 3348 | AK74: 3273 | AL74: =I74 -> 2812 | AM74: 2853 | AN74: =80025 -> 80025 | AO74: 79083 | AQ74: =V74 -> 149 | AR74: =W74 -> 579 | AS74: =X74 -> 533 | AT74: =Y74 -> 488 | AU74: =Z74 -> 442 | AV74: =AA74 -> 396 | AW74: =AB74 -> 3739 | AX74: =AC74 -> 3547 | ... BJ74: =AO74 -> 79083
B75: Operating Lease Liabilities, Net of Current Portion | C75: 0 | D75: 0 | E75: 11793 | F75: 22599 | G75: 55854 | H75: 75648 | I75: 73613 | N75: =C75 -> 0 | O75: 0 | P75: 0 | Q75: 0 | R75: =D75 -> 0 | S75: 10935 | T75: 11604 | U75: 11413 | V75: =E75 -> 11793 | W75: 11061 | X75: 11300 | Y75: 21799 | Z75: =F75 -> 22599 | AA75: 21485 | AB75: 21143 | AC75: 56484 | AD75: =G75 -> 55854 | AE75: 44787 | AF75: 77122 | AG75: 76382 | AH75: =H75 -> 75648 | AI75: 75490 | AJ75: 74884 | AK75: 74506 | AL75: =I75 -> 73613 | AM75: 72147 | AN75: 4441 | AO75: 4023 | AQ75: =V75 -> 11793 | AR75: =W75 -> 11061 | AS75: =X75 -> 11300 | AT75: =Y75 -> 21799 | AU75: =Z75 -> 22599 | AV75: =AA75 -> 21485 | AW75: =AB75 -> 21143 | AX75: =AC75 -> 56484 | ... BJ75: =AO75 -> 4023 | BL75: =SUM(BI75/BE75)-1 -> -0.94069494
B76: Total Liabilities | C76: =SUM(C70:C75)+C67 -> 55959 | D76: =SUM(D70:D75)+D67 -> 67833 | E76: =SUM(E70:E75)+E67 -> 100909 | F76: =SUM(F70:F75)+F67 -> 1246904 | G76: =SUM(G70:G75)+G67 -> 1265772 | H76: =SUM(H70:H75)+H67 -> 1287818 | I76: =SUM(I70:I75)+I67 -> 1279354 | K76: =SUM(K70:K75)+K67 -> 0 | L76: =SUM(L70:L75)+L67 -> 0 | M76: =SUM(M70:M75)+M67 -> 0 | N76: =SUM(N70:N75)+N67 -> 55959 | O76: =SUM(O70:O75)+O67 -> 52795 | P76: =SUM(P70:P75)+P67 -> 65276 | Q76: =SUM(Q70:Q75)+Q67 -> 78013 | R76: =SUM(R70:R75)+R67 -> 67833 | ... AO76: =SUM(AO70:AO75)+AO67 -> 1383734 | AQ76: =SUM(AQ70:AQ75)+AQ67 -> 100909 | AR76: =SUM(AR70:AR75)+AR67 -> 1211472 | AS76: =SUM(AS70:AS75)+AS67 -> 1211039 | AT76: =SUM(AT70:AT75)+AT67 -> 1225269 | AU76: =SUM(AU70:AU75)+AU67 -> 1246904 | AV76: =SUM(AV70:AV75)+AV67 -> 1253529 | AW76: =SUM(AW70:AW75)+AW67 -> 1266050 | AX76: =SUM(AX70:AX75)+AX67 -> 1283331 | ... BJ76: =SUM(BJ70:BJ75)+BJ67 -> 1383734 | BL76: =SUM(BI76/BE76)-1 -> 0.051876683
B78: Preferred Stock Convertible | C78: =2000+4999+14882+24948+17214+29840+55658+49999 -> 199540 | D78: 0 | E78: 0 | F78: 0 | G78: 0 | H78: 0 | I78: 0 | N78: =C78 -> 199540 | O78: =2000+4999+14882+24948+17214+29840+55658+49999 -> 199540 | P78: 0 | Q78: 0 | R78: =D78 -> 0 | S78: 0 | T78: 0 | U78: 0 | V78: =E78 -> 0 | W78: 0 | X78: 0 | Y78: 0 | Z78: =F78 -> 0 | AA78: 0 | AB78: 0 | AC78: 0 | AD78: 0 | AE78: 0 | AF78: 0 | AG78: 0 | AH78: =H78 -> 0 | AI78: 0 | AJ78: 0 | AK78: 0 | AL78: =I78 -> 0 | AM78: 0 | AN78: 0 | AO78: 0 | AQ78: =V78 -> 0 | AR78: =W78 -> 0 | AS78: =X78 -> 0 | AT78: =Y78 -> 0 | AU78: =Z78 -> 0 | AV78: =AA78 -> 0 | AW78: =AB78 -> 0 | AX78: =AC78 -> 0 | ... BJ78: =AO78 -> 0
B79: Common Stock - Par Value | C79: 1 | D79: 6 | E79: 6 | F79: 6 | G79: 6 | H79: 6 | I79: 8 | N79: =C79 -> 1 | O79: 1 | P79: 6 | Q79: 6 | R79: =D79 -> 6 | S79: 6 | T79: 6 | U79: 6 | V79: =E79 -> 6 | W79: 6 | X79: 6 | Y79: 6 | Z79: =F79 -> 6 | AA79: 6 | AB79: 6 | AC79: 6 | AD79: 6 | AE79: 6 | AF79: 6 | AG79: 6 | AH79: =H79 -> 6 | AI79: 6 | AJ79: 6 | AK79: 6 | AL79: =I79 -> 8 | AM79: 8 | AN79: 8 | AO79: 8 | AQ79: =V79 -> 6 | AR79: =W79 -> 6 | AS79: =X79 -> 6 | AT79: =Y79 -> 6 | AU79: =Z79 -> 6 | AV79: =AA79 -> 6 | AW79: =AB79 -> 6 | AX79: =AC79 -> 6 | ... BJ79: =AO79 -> 8
B80: Additional Paid in Capital | C80: 7921 | D80: 526199 | E80: 560210 | F80: 510014 | G80: 544357 | H80: 573128 | I80: 644004 | N80: =C80 -> 7921 | O80: 9142 | P80: 477541 | Q80: 518485 | R80: =D80 -> 526199 | S80: 532275 | T80: 540576 | U80: 548706 | V80: =E80 -> 560210 | W80: 485684 | X80: 496210 | Y80: 503690 | Z80: =F80 -> 510014 | AA80: 519681 | AB80: 530152 | AC80: 539399 | AD80: 544357 | AE80: 553805 | AF80: 561484 | AG80: 567927 | AH80: =H80 -> 573128 | AI80: 578773 | AJ80: 584441 | AK80: 590282 | AL80: =I80 -> 644004 | AM80: 649637 | AN80: 653855 | AO80: 657549 | AQ80: =V80 -> 560210 | AR80: =W80 -> 485684 | AS80: =X80 -> 496210 | AT80: =Y80 -> 503690 | AU80: =Z80 -> 510014 | AV80: =AA80 -> 519681 | AW80: =AB80 -> 530152 | AX80: =AC80 -> 539399 | ... BJ80: =AO80 -> 657549
B81: Accumulated Deficit | C81: -129672 | D81: -142115 | E81: -194867 | F81: -376972 | G81: -743109 | H81: -1081253 | I81: -1241531 | N81: =C81 -> -129672 | O81: -136321 | P81: -145762 | Q81: -141663 | R81: =D81 -> -142115 | S81: -140300 | T81: -150505 | U81: -169790 | V81: =E81 -> -194867 | W81: -222133 | X81: -241785 | Y81: -296601 | Z81: =F81 -> -376972 | AA81: -477430 | AB81: -574564 | AC81: -676242 | AD81: -743109 | AE81: -802146 | AF81: -855651 | AG81: -926143 | AH81: =H81 -> -1081253 | AI81: -1135614 | AJ81: -1170093 | AK81: -1196669 | AL81: =I81 -> -1241531 | AM81: -1294447 | AN81: -1323689 | AO81: -1434377 | AQ81: =V81 -> -194867 | AR81: =W81 -> -222133 | AS81: =X81 -> -241785 | AT81: =Y81 -> -296601 | AU81: =Z81 -> -376972 | AV81: =AA81 -> -477430 | AW81: =AB81 -> -574564 | AX81: =AC81 -> -676242 | ... BJ81: =AO81 -> -1434377
B82: Accumulated Other Comprehensive (Loss) income | C82: 0 | D82: 0 | E82: 1748 | F82: -553 | G82: -4802 | H82: -5249 | I82: -3689 | N82: =C82 -> 0 | O82: 0 | P82: 0 | R82: =D82 -> 0 | S82: 0 | T82: -167 | U82: 478 | V82: =E82 -> 1748 | W82: 490 | X82: 1050 | Y82: 10 | Z82: =F82 -> -553 | AA82: -1276 | AB82: -3535 | AC82: -5207 | AD82: -4802 | AE82: -4799 | AF82: -4957 | AG82: -4696 | AH82: =H82 -> -5249 | AI82: -4576 | AJ82: -4379 | AK82: -5543 | AL82: =I82 -> -3689 | AM82: -4729 | AN82: -7197 | AO82: -7245 | AQ82: =V82 -> 1748 | AR82: =W82 -> 490 | AS82: =X82 -> 1050 | AT82: =Y82 -> 10 | AU82: =Z82 -> -553 | AV82: =AA82 -> -1276 | AW82: =AB82 -> -3535 | AX82: =AC82 -> -5207 | ... BJ82: =AO82 -> -7245
B83: Total stockholders' equity | C83: =SUM(C78:C82) -> 77790 | D83: =SUM(D78:D82) -> 384090 | E83: =SUM(E78:E82) -> 367097 | F83: =SUM(F78:F82) -> 132495 | G83: =SUM(G78:G82) -> -203548 | H83: =SUM(H78:H82) -> -513368 | I83: =SUM(I78:I82) -> -601208 | K83: =SUM(K78:K82) -> 0 | L83: =SUM(L78:L82) -> 0 | M83: =SUM(M78:M82) -> 0 | N83: =SUM(N78:N82) -> 77790 | O83: =SUM(O78:O82) -> 72362 | P83: =SUM(P78:P82) -> 331785 | Q83: =SUM(Q78:Q82) -> 376828 | R83: =SUM(R78:R82) -> 384090 | ... AO83: =SUM(AO78:AO82) -> -784065 | AQ83: =SUM(AQ78:AQ82) -> 367097 | AR83: =SUM(AR78:AR82) -> 264047 | AS83: =SUM(AS78:AS82) -> 255481 | AT83: =SUM(AT78:AT82) -> 207105 | AU83: =SUM(AU78:AU82) -> 132495 | AV83: =SUM(AV78:AV82) -> 40981 | AW83: =SUM(AW78:AW82) -> -47941 | AX83: =SUM(AX78:AX82) -> -142044 | ... BJ83: =SUM(BJ78:BJ82) -> -784065 | BL83: =SUM(BI83/BE83)-1 -> 0.14744799
B84: Total liabilities and stockholders' equity | C84: =SUM(C83+C76) -> 133749 | D84: =SUM(D83+D76) -> 451923 | E84: =SUM(E83+E76) -> 468006 | F84: =SUM(F83+F76) -> 1379399 | G84: =SUM(G83+G76) -> 1062224 | H84: =SUM(H83+H76) -> 774450 | I84: =SUM(I83+I76) -> 678146 | K84: =SUM(K83+K76) -> 0 | L84: =SUM(L83+L76) -> 0 | M84: =SUM(M83+M76) -> 0 | N84: =SUM(N83+N76) -> 133749 | O84: =SUM(O83+O76) -> 125157 | P84: =SUM(P83+P76) -> 397061 | Q84: =SUM(Q83+Q76) -> 454841 | R84: =SUM(R83+R76) -> 451923 | ... AO84: =SUM(AO83+AO76) -> 599669 | AQ84: =SUM(AQ83+AQ76) -> 468006 | AR84: =SUM(AR83+AR76) -> 1475519 | AS84: =SUM(AS83+AS76) -> 1466520 | AT84: =SUM(AT83+AT76) -> 1432374 | AU84: =SUM(AU83+AU76) -> 1379399 | AV84: =SUM(AV83+AV76) -> 1294510 | AW84: =SUM(AW83+AW76) -> 1218109 | AX84: =SUM(AX83+AX76) -> 1141287 | ... BJ84: =SUM(BJ83+BJ76) -> 599669 | BL84: =SUM(BI84/BE84)-1 -> -0.027407295
B86: Balance Check | C86: =C84-C59 -> 0 | D86: =D84-D59 -> 0 | E86: =E84-E59 -> 0 | F86: =F84-F59 -> 0 | G86: =G84-G59 -> 0 | H86: =H84-H59 -> 0 | I86: =I84-I59 -> 0 | N86: =N84-N59 -> 0 | O86: =O84-O59 -> 0 | P86: =P84-P59 -> 0 | Q86: =Q84-Q59 -> 0 | R86: =R84-R59 -> 0 | S86: =S84-S59 -> 0 | T86: =T84-T59 -> 0 | U86: =U84-U59 -> 0 | ... AO86: =AO84-AO59 -> 0 | AQ86: =AQ84-AQ59 -> 0 | AR86: =AR84-AR59 -> 0 | AS86: =AS84-AS59 -> 0 | AT86: =AT84-AT59 -> 0 | AU86: =AU84-AU59 -> 0 | AV86: =AV84-AV59 -> 0 | AW86: =AW84-AW59 -> 0 | AX86: =AX84-AX59 -> 0 | ... BJ86: =BJ84-BJ59 -> 0
B88: 1) Prepaid Expenses and Other Current Assets consists of: Prepaid Expenses and Other Current Assets + Asset Held for Sale.
B89: 2) Accrued Expenses, Other Current Liabilities, and Other Payables consists of: Accrued Expenses and Other Current Liabilities + Accrued Bonus + Stock warrant liability + Accrued Litigation Settlement + Wages Payable.
B90: 3) Consolidated Short-Term Borrowings consists of: Short-term borrowings under revolving credit Facility + Short-term borrowings under revolving credit line and bank term loan + Short-term Finance Lease Liabilities.
B91: 4) Consolidated Other Long-Term Borrowings consists of: Revolving Credit Line + Long-term Portion of Bank Term Loan, Net + Equipment loan, net + Delayed draw term loan, net + Delayed draw term loan warrants.
A93: X | B93: Cash-Flows Statement | K93: Quarterly | BE93: LTM | BL93: Variance
B94: =B7 -> Fiscal Period | C94: =C7 -> 2018 | D94: =D7 -> 2019 | E94: =E7 -> 2020 | F94: =F7 -> 2021 | G94: =G7 -> 2022 | H94: =H7 -> 2023 | I94: =I7 -> 2024 | K94: =K7 -> 1Q18 | L94: =L7 -> 2Q18 | M94: =M7 -> 3Q18 | N94: =N7 -> 4Q18 | O94: =O7 -> 1Q19 | P94: =P7 -> 2Q19 | Q94: =Q7 -> 3Q19 | R94: =R7 -> 4Q19 | ... AO94: =AO7 -> 3Q25 | AQ94: =AQ7 -> 4Q20 | AR94: =AR7 -> 1Q21 | AS94: =AS7 -> 2Q21 | AT94: =AT7 -> 3Q21 | AU94: =AU7 -> 4Q21 | AV94: =AV7 -> 1Q22 | AW94: =AW7 -> 2Q22 | AX94: =AX7 -> 3Q22 | ... BJ94: =BJ7 -> 3Q25
B95: =B8 -> Fiscal Period End Date | C95: =C8 -> 43465 | D95: =D8 -> 43830 | E95: =E8 -> 44196 | F95: =F8 -> 44561 | G95: =G8 -> 44926 | H95: =H8 -> 45291 | I95: =I8 -> 45657 | K95: =K8 -> 43190 | L95: =L8 -> 43281 | M95: =M8 -> 43372 | N95: =N8 -> 43465 | O95: =O8 -> 43554 | P95: =P8 -> 43645 | Q95: =Q8 -> 43736 | R95: =R8 -> 43830 | ... AO95: =AO8 -> 45927 | AQ95: =AQ8 -> 44196 | AR95: =AR8 -> 44289 | AS95: =AS8 -> 44380 | AT95: =AT8 -> 44471 | AU95: =AU8 -> 44561 | AV95: =AV8 -> 44653 | AW95: =AW8 -> 44744 | AX95: =AX8 -> 44835 | ... BJ95: =BJ8 -> 45927
B97: Cash-Flows From Operating Activities
B98: Net income (loss) | C98: =C31 -> -29886 | D98: =D31 -> -12443 | E98: =E31 -> -52752 | F98: =F31 -> -182105 | G98: =G31 -> -366137 | H98: =H31 -> -338144 | I98: =I31 -> -160278 | K98: =K31 -> -5696 | L98: =L31 -> -7396 | M98: =M31 -> -9342 | N98: =N31 -> -7452 | O98: =O31 -> -6649 | P98: =P31 -> -9441 | Q98: =Q31 -> 4099 | R98: =SUM(D98-SUM(O98:Q98)) -> -452 | S98: =S31 -> 1815 | T98: =T31 -> -10205 | U98: =U31 -> -19285 | V98: =SUM(E98-SUM(S98:U98)) -> -25077 | W98: =W31 -> -27266 | X98: =X31 -> -19652 | Y98: =Y31 -> -54816 | Z98: =SUM(F98-SUM(W98:Y98)) -> -80371 | AA98: =AA31 -> -100458 | AB98: =AB31 -> -97134 | AC98: =AC31 -> -101678 | AD98: =SUM(G98-SUM(AA98:AC98)) -> -66867 | AE98: =AE31 -> -59037 | AF98: =AF31 -> -53505 | AG98: =AG31 -> -70492 | AH98: =AH31 -> -155110 | AI98: =AI31 -> -54361 | AJ98: =AJ31 -> -34479 | AK98: =AK31 -> -26576 | AL98: =AL31 -> -44862 | ... AO98: =AO31 -> -110688 | AQ98: =SUM(S98:V98) -> -52752 | AR98: =SUM(T98:W98) -> -81833 | AS98: =SUM(U98:X98) -> -91280 | AT98: =SUM(V98:Y98) -> -126811 | AU98: =SUM(W98:Z98) -> -182105 | AV98: =SUM(X98:AA98) -> -255297 | AW98: =SUM(Y98:AB98) -> -332779 | AX98: =SUM(Z98:AC98) -> -379641 | ... BJ98: =SUM(AL98:AO98) -> -237708 | BL98: =SUM(BI98/BE98)-1 -> -0.51152836
B100: Adjustments to reconcile net income: | BL100: =SUM(BI100/BE100)-1 -> #DIV/0!
B101: Depreciation and Amortization | C101: 4921 | D101: 8106 | E101: 13299 | F101: 21663 | G101: 32582 | H101: 48094 | I101: 23121 | K101: 733 | L101: =1620-K101 -> 887 | M101: =3046-L101-K101 -> 1426 | N101: =SUM(C101-SUM(K101:M101)) -> 1875 | O101: 1905 | P101: =3957-O101 -> 2052 | Q101: =5980-P101-O101 -> 2023 | R101: =SUM(D101-SUM(O101:Q101)) -> 2126 | S101: 2583 | T101: =5855-S101 -> 3272 | U101: =9276-T101-S101 -> 3421 | V101: =SUM(E101-SUM(S101:U101)) -> 4023 | W101: 4326 | X101: =9207-W101 -> 4881 | Y101: =14910-X101-W101 -> 5703 | Z101: =SUM(F101-SUM(W101:Y101)) -> 6753 | AA101: 7091 | AB101: =14820-AA101 -> 7729 | AC101: =23255-AB101-AA101 -> 8435 | AD101: =SUM(G101-SUM(AA101:AC101)) -> 9327 | AE101: 6049 | AF101: =11928-AE101 -> 5879 | AG101: =17707-AF101-AE101 -> 5779 | AH101: =SUM(H101-SUM(AE101:AG101)) -> 30387 | AI101: 6969 | AJ101: =12182-AI101 -> 5213 | AK101: =17464-AJ101-AI101 -> 5282 | AL101: =SUM(I101-SUM(AI101:AK101)) -> 5657 | AM101: 7416 | AN101: =15682-AM101 -> 8266 | AO101: =25043-AN101-AM101 -> 9361 | AQ101: =SUM(S101:V101) -> 13299 | AR101: =SUM(T101:W101) -> 15042 | AS101: =SUM(U101:X101) -> 16651 | AT101: =SUM(V101:Y101) -> 18933 | AU101: =SUM(W101:Z101) -> 21663 | AV101: =SUM(X101:AA101) -> 24428 | AW101: =SUM(Y101:AB101) -> 27276 | AX101: =SUM(Z101:AC101) -> 30008 | ... BJ101: =SUM(AL101:AO101) -> 30700 | BL101: =SUM(BI101/BE101)-1 -> -0.44938777
B102: Share-based Compensation Expense | C102: 2241 | D102: 12807 | E102: 27279 | F102: 27698 | G102: 33857 | H102: 29098 | I102: 23923 | K102: 260 | L102: =710-K102 -> 450 | M102: =1090-L102-K102 -> 380 | N102: =SUM(C102-SUM(K102:M102)) -> 1151 | O102: 855 | P102: =2678-O102 -> 1823 | Q102: =5807-P102-O102 -> 3129 | R102: =SUM(D102-SUM(O102:Q102)) -> 7000 | S102: 5949 | T102: =13535-S102 -> 7586 | U102: =20377-T102-S102 -> 6842 | V102: =SUM(E102-SUM(S102:U102)) -> 6902 | W102: 7376 | X102: =15239-W102 -> 7863 | Y102: =21624-X102-W102 -> 6385 | Z102: =SUM(F102-SUM(W102:Y102)) -> 6074 | AA102: 9292 | AB102: =19598-AA102 -> 10306 | AC102: =28848-AB102-AA102 -> 9250 | AD102: =SUM(G102-SUM(AA102:AC102)) -> 5009 | AE102: 9565 | AF102: =17313-AE102 -> 7748 | AG102: =23791-AF102-AE102 -> 6478 | AH102: =SUM(H102-SUM(AE102:AG102)) -> 5307 | AI102: 6075 | AJ102: =11848-AI102 -> 5773 | AK102: =17753-AJ102-AI102 -> 5905 | AL102: =SUM(I102-SUM(AI102:AK102)) -> 6170 | AM102: 5853 | AN102: =10157-AM102 -> 4304 | AO102: =13924-AN102-AM102 -> 3767 | AQ102: =SUM(S102:V102) -> 27279 | AR102: =SUM(T102:W102) -> 28706 | AS102: =SUM(U102:X102) -> 28983 | AT102: =SUM(V102:Y102) -> 28526 | AU102: =SUM(W102:Z102) -> 27698 | AV102: =SUM(X102:AA102) -> 29614 | AW102: =SUM(Y102:AB102) -> 32057 | AX102: =SUM(Z102:AC102) -> 34922 | ... BJ102: =SUM(AL102:AO102) -> 20094
B103: Non-cash Lease Expense | C103: 0 | D103: 0 | E103: 2341 | F103: 3418 | G103: 5167 | H103: 8140 | I103: 8279 | K103: 0 | L103: 0 | M103: 0 | N103: =SUM(C103-SUM(K103:M103)) -> 0 | O103: 0 | P103: 0 | Q103: 0 | R103: =SUM(D103-SUM(O103:Q103)) -> 0 | S103: 445 | T103: =1193-S103 -> 748 | U103: =1573-T103-S103 -> 380 | V103: =SUM(E103-SUM(S103:U103)) -> 768 | W103: 724 | X103: =1580-W103 -> 856 | Y103: =2351-X103-W103 -> 771 | Z103: =SUM(F103-SUM(W103:Y103)) -> 1067 | AA103: 1118 | AB103: =2091-AA103 -> 973 | AC103: =3389-AB103-AA103 -> 1298 | AD103: =SUM(G103-SUM(AA103:AC103)) -> 1778 | AE103: 1783 | AF103: =3613-AE103 -> 1830 | AG103: =5997-AF103-AE103 -> 2384 | AH103: =SUM(H103-SUM(AE103:AG103)) -> 2143 | AI103: 2074 | AJ103: =4130-AI103 -> 2056 | AK103: =6198-AJ103-AI103 -> 2068 | AL103: =SUM(I103-SUM(AI103:AK103)) -> 2081 | AM103: 2079 | AN103: =2889-AM103 -> 810 | AO103: =3331-AN103-AM103 -> 442 | AQ103: =SUM(S103:V103) -> 2341 | AR103: =SUM(T103:W103) -> 2620 | AS103: =SUM(U103:X103) -> 2728 | AT103: =SUM(V103:Y103) -> 3119 | AU103: =SUM(W103:Z103) -> 3418 | AV103: =SUM(X103:AA103) -> 3812 | AW103: =SUM(Y103:AB103) -> 3929 | AX103: =SUM(Z103:AC103) -> 4456 | ... BJ103: =SUM(AL103:AO103) -> 5412
B104: Amortization of Debt Issuance Costs | C104: 109 | D104: 181 | E104: 256 | F104: 3322 | G104: 3934 | H104: 3934 | I104: 3934 | K104: 9 | L104: =35-K104 -> 26 | M104: =51-L104-K104 -> 16 | N104: =SUM(C104-SUM(K104:M104)) -> 58 | O104: 58 | P104: =78-O104 -> 20 | Q104: =124-P104-O104 -> 46 | R104: =SUM(D104-SUM(O104:Q104)) -> 57 | S104: 57 | T104: =93-S104 -> 36 | U104: =195-T104-S104 -> 102 | V104: =SUM(E104-SUM(S104:U104)) -> 61 | W104: 369 | X104: =1352-W104 -> 983 | Y104: =2338-X104-W104 -> 986 | Z104: =SUM(F104-SUM(W104:Y104)) -> 984 | AA104: 984 | AB104: =1967-AA104 -> 983 | AC104: =2951-AB104-AA104 -> 984 | AD104: =SUM(G104-SUM(AA104:AC104)) -> 983 | AE104: 984 | AF104: =1967-AE104 -> 983 | AG104: =2951-AF104-AE104 -> 984 | AH104: =SUM(H104-SUM(AE104:AG104)) -> 983 | AI104: 984 | AJ104: =1967-AI104 -> 983 | AK104: =2951-AJ104-AI104 -> 984 | AL104: =SUM(I104-SUM(AI104:AK104)) -> 983 | AM104: 984 | AN104: =1970-AM104 -> 986 | AO104: =2987-AN104-AM104 -> 1017 | AQ104: =SUM(S104:V104) -> 256 | AR104: =SUM(T104:W104) -> 568 | AS104: =SUM(U104:X104) -> 1515 | AT104: =SUM(V104:Y104) -> 2399 | AU104: =SUM(W104:Z104) -> 3322 | AV104: =SUM(X104:AA104) -> 3937 | AW104: =SUM(Y104:AB104) -> 3937 | AX104: =SUM(Z104:AC104) -> 3935 | ... BJ104: =SUM(AL104:AO104) -> 3970
B105: Equity in Losses of Unconsolidated Joint Ventures | C105: 0 | D105: 0 | E105: 0 | F105: 2977 | G105: 18948 | H105: 3902 | I105: 73 | K105: 0 | L105: 0 | M105: 0 | N105: =SUM(C105-SUM(K105:M105)) -> 0 | O105: 0 | P105: 0 | Q105: 0 | R105: =SUM(D105-SUM(O105:Q105)) -> 0 | S105: 0 | T105: 0 | U105: 0 | V105: =SUM(E105-SUM(S105:U105)) -> 0 | W105: 374 | X105: =581-W105 -> 207 | Y105: =1176-X105-W105 -> 595 | Z105: =SUM(F105-SUM(W105:Y105)) -> 1801 | AA105: 0 | AB105: =2103-AA105 -> 2103 | AC105: =10849-AB105-AA105 -> 8746 | AD105: =SUM(G105-SUM(AA105:AC105)) -> 8099 | AE105: 3235 | AF105: =3738-AE105 -> 503 | AG105: =3864-AF105-AE105 -> 126 | AH105: =SUM(H105-SUM(AE105:AG105)) -> 38 | AI105: -7 | AJ105: =23-AI105 -> 30 | AK105: =61-AJ105-AI105 -> 38 | AL105: =SUM(I105-SUM(AI105:AK105)) -> 12 | AM105: 11 | AN105: =70-AM105 -> 59 | AO105: =77-AN105-AM105 -> 7 | AQ105: =SUM(S105:V105) -> 0 | AR105: =SUM(T105:W105) -> 374 | AS105: =SUM(U105:X105) -> 581 | AT105: =SUM(V105:Y105) -> 1176 | AU105: =SUM(W105:Z105) -> 2977 | AV105: =SUM(X105:AA105) -> 2603 | AW105: =SUM(Y105:AB105) -> 4499 | AX105: =SUM(Z105:AC105) -> 12650 | ... BJ105: =SUM(AL105:AO105) -> 89
B106: Other Changes in Gains, Losses, and provisions, net | C106: =76+1120 -> 1196 | D106: =93+12503 -> 12596 | E106: =222+1538 -> 1760 | F106: =199+1037 -> 1236 | G106: =486+5106 -> 5592 | H106: =20515-1822+3795 -> 22488 | I106: =809+5113+221 -> 6143 | K106: 129 | L106: =259-K106 -> 130 | M106: =76+1253-L106-K106 -> 1070 | N106: =SUM(C106-SUM(K106:M106)) -> -133 | O106: 759 | P106: =12503-O106 -> 11744 | Q106: =12503-P106-O106 -> 0 | R106: =SUM(D106-SUM(O106:Q106)) -> 93 | S106: 0 | T106: =183+1538-S106 -> 1721 | U106: =218+1538-T106-S106 -> 35 | V106: =SUM(E106-SUM(S106:U106)) -> 4 | W106: =3+1037 -> 1040 | X106: =111+1037-W106 -> 108 | Y106: =199+1037-X106-W106 -> 88 | Z106: =SUM(F106-SUM(W106:Y106)) -> 0 | AA106: =315+671 -> 986 | AB106: =400+7076-AA106 -> 6490 | AC106: =946+11160-AB106-AA106 -> 4630 | AD106: =SUM(G106-SUM(AA106:AC106)) -> -6514 | AE106: =3907-731 -> 3176 | AF106: =3804+213-AE106 -> 841 | AG106: =3876+2740+3795-AF106-AE106 -> 6394 | AH106: =SUM(H106-SUM(AE106:AG106)) -> 12077 | AI106: =183+2173 -> 2356 | AJ106: =363+2671+232-AI106 -> 910 | AK106: =493-1118+232-AJ106-AI106 -> -3659 | AL106: =SUM(I106-SUM(AI106:AK106)) -> 6536 | AM106: =98-3571 -> -3473 | AN106: =223-11161-AM106 -> -7465 | AO106: =77414-198+128-11193-5318+1499-AN106-AM106 -> 73270 | AQ106: =SUM(S106:V106) -> 1760 | AR106: =SUM(T106:W106) -> 2800 | AS106: =SUM(U106:X106) -> 1187 | AT106: =SUM(V106:Y106) -> 1240 | AU106: =SUM(W106:Z106) -> 1236 | AV106: =SUM(X106:AA106) -> 1182 | AW106: =SUM(Y106:AB106) -> 7564 | AX106: =SUM(Z106:AC106) -> 12106 | ... BJ106: =SUM(AL106:AO106) -> 68868
B108: Changes in assets and liabilities: | BL108: =SUM(BI108/BE108)-1 -> #DIV/0!
B109: Accounts Receivable | C109: -9045 | D109: -27454 | E109: 4516 | F109: -8463 | G109: 9063 | H109: 2717 | I109: 4193 | K109: -991 | L109: =-2788-K109 -> -1797 | M109: =-8499-L109-K109 -> -5711 | N109: =SUM(C109-SUM(K109:M109)) -> -546 | O109: -3568 | P109: =-21762-O109 -> -18194 | Q109: =-21856-P109-O109 -> -94 | R109: =SUM(D109-SUM(O109:Q109)) -> -5598 | S109: 3746 | T109: =-5907-S109 -> -9653 | U109: =10365-T109-S109 -> 16272 | V109: =SUM(E109-SUM(S109:U109)) -> -5849 | W109: -963 | X109: =-27713-W109 -> -26750 | Y109: =-13495-X109-W109 -> 14218 | Z109: =SUM(F109-SUM(W109:Y109)) -> 5032 | AA109: -9108 | AB109: =-30158-AA109 -> -21050 | AC109: =7703-AB109-AA109 -> 37861 | AD109: =SUM(G109-SUM(AA109:AC109)) -> 1360 | AE109: -8078 | AF109: =-16462-AE109 -> -8384 | AG109: =-1806-AF109-AE109 -> 14656 | AH109: =SUM(H109-SUM(AE109:AG109)) -> 4523 | AI109: -4143 | AJ109: =-3273-AI109 -> 870 | AK109: =-2977-AJ109-AI109 -> 296 | AL109: =SUM(I109-SUM(AI109:AK109)) -> 7170 | AM109: -6038 | AN109: =-9291-AM109 -> -3253 | AO109: =-38-AN109-AM109 -> 9253 | AQ109: =SUM(S109:V109) -> 4516 | AR109: =SUM(T109:W109) -> -193 | AS109: =SUM(U109:X109) -> -17290 | AT109: =SUM(V109:Y109) -> -19344 | AU109: =SUM(W109:Z109) -> -8463 | AV109: =SUM(X109:AA109) -> -16608 | AW109: =SUM(Y109:AB109) -> -10908 | AX109: =SUM(Z109:AC109) -> 12735 | ... BJ109: =SUM(AL109:AO109) -> 7132 | BL109: =SUM(BI109/BE109)-1 -> -1.1147366
B110: Inventories | C110: -22113 | D110: -51339 | E110: -38863 | F110: -122666 | G110: 2572 | H110: 106087 | I110: 15576 | K110: -1144 | L110: =-6178-K110 -> -5034 | M110: =-9627-L110-K110 -> -3449 | N110: =SUM(C110-SUM(K110:M110)) -> -12486 | O110: -4025 | P110: =-12438-O110 -> -8413 | Q110: =-30013-P110-O110 -> -17575 | R110: =SUM(D110-SUM(O110:Q110)) -> -21326 | S110: -39106 | T110: =-61437-S110 -> -22331 | U110: =-50263-T110-S110 -> 11174 | V110: =SUM(E110-SUM(S110:U110)) -> 11400 | W110: -24729 | X110: =-44741-W110 -> -20012 | Y110: =-73557-X110-W110 -> -28816 | Z110: =SUM(F110-SUM(W110:Y110)) -> -49109 | AA110: -43043 | AB110: =-17036-AA110 -> 26007 | AC110: =-12411-AB110-AA110 -> 4625 | AD110: =SUM(G110-SUM(AA110:AC110)) -> 14983 | AE110: 13779 | AF110: =28975-AE110 -> 15196 | AG110: =40470-AF110-AE110 -> 11495 | AH110: =SUM(H110-SUM(AE110:AG110)) -> 65617 | AI110: 7162 | AJ110: =10005-AI110 -> 2843 | AK110: =5361-AJ110-AI110 -> -4644 | AL110: =SUM(I110-SUM(AI110:AK110)) -> 10215 | AM110: 14113 | AN110: =4709-AM110 -> -9404 | AO110: =5334-AN110-AM110 -> 625 | AQ110: =SUM(S110:V110) -> -38863 | AR110: =SUM(T110:W110) -> -24486 | AS110: =SUM(U110:X110) -> -22167 | AT110: =SUM(V110:Y110) -> -62157 | AU110: =SUM(W110:Z110) -> -122666 | AV110: =SUM(X110:AA110) -> -140980 | AW110: =SUM(Y110:AB110) -> -94961 | AX110: =SUM(Z110:AC110) -> -61520 | ... BJ110: =SUM(AL110:AO110) -> 15549
B111: Prepaid Expense and Other Assets | C111: 325 | D111: -2362 | E111: -9699 | F111: -21414 | G111: 11595 | H111: 12873 | I111: 2013 | K111: 60 | L111: =-154-K111 -> -214 | M111: =-615-L111-K111 -> -461 | N111: =SUM(C111-SUM(K111:M111)) -> 940 | O111: 122 | P111: =-2131-O111 -> -2253 | Q111: =-1878-P111-O111 -> 253 | R111: =SUM(D111-SUM(O111:Q111)) -> -484 | S111: -6255 | T111: =-12192-S111 -> -5937 | U111: =-9444-T111-S111 -> 2748 | V111: =SUM(E111-SUM(S111:U111)) -> -255 | W111: -2877 | X111: =-9943-W111 -> -7066 | Y111: =-13249-X111-W111 -> -3306 | Z111: =SUM(F111-SUM(W111:Y111)) -> -8165 | AA111: -213 | AB111: =-992-AA111 -> -779 | AC111: =7802-AB111-AA111 -> 8794 | AD111: =SUM(G111-SUM(AA111:AC111)) -> 3793 | AE111: 3926 | AF111: =-4705-AE111 -> -8631 | AG111: =1282-AF111-AE111 -> 5987 | AH111: =SUM(H111-SUM(AE111:AG111)) -> 11591 | AI111: 410 | AJ111: =-2450-AI111 -> -2860 | AK111: =144-AJ111-AI111 -> 2594 | AL111: =SUM(I111-SUM(AI111:AK111)) -> 1869 | AM111: -4425 | AN111: =-8473-AM111 -> -4048 | AO111: =-1322-AN111-AM111 -> 7151 | AQ111: =SUM(S111:V111) -> -9699 | AR111: =SUM(T111:W111) -> -6321 | AS111: =SUM(U111:X111) -> -7450 | AT111: =SUM(V111:Y111) -> -13504 | AU111: =SUM(W111:Z111) -> -21414 | AV111: =SUM(X111:AA111) -> -18750 | AW111: =SUM(Y111:AB111) -> -12463 | AX111: =SUM(Z111:AC111) -> -363 | ... BJ111: =SUM(AL111:AO111) -> 547
B112: Accounts Payable | C112: 10455 | D112: 10149 | E112: 16027 | F112: 21665 | G112: -10826 | H112: 3004 | I112: -20564 | K112: 1845 | L112: =6623-K112 -> 4778 | M112: =7670-L112-K112 -> 1047 | N112: =SUM(C112-SUM(K112:M112)) -> 2785 | O112: -4349 | P112: =9799-O112 -> 14148 | Q112: =20206-P112-O112 -> 10407 | R112: =SUM(D112-SUM(O112:Q112)) -> -10057 | S112: 16651 | T112: =21564-S112 -> 4913 | U112: =2442-T112-S112 -> -19122 | V112: =SUM(E112-SUM(S112:U112)) -> 13585 | W112: 1098 | X112: =-2197-W112 -> -3295 | Y112: =965-X112-W112 -> 3162 | Z112: =SUM(F112-SUM(W112:Y112)) -> 20700 | AA112: -2295 | AB112: =-206-AA112 -> 2089 | AC112: =-2922-AB112-AA112 -> -2716 | AD112: =SUM(G112-SUM(AA112:AC112)) -> -7904 | AE112: -13271 | AF112: =-14177-AE112 -> -906 | AG112: =8335-AF112-AE112 -> 22512 | AH112: =SUM(H112-SUM(AE112:AG112)) -> -5331 | AI112: 214 | AJ112: =3633-AI112 -> 3419 | AK112: =-797-AJ112-AI112 -> -4430 | AL112: =SUM(I112-SUM(AI112:AK112)) -> -19767 | AM112: 13976 | AN112: =25710-AM112 -> 11734 | AO112: =-1379-AN112-AM112 -> -27089 | AQ112: =SUM(S112:V112) -> 16027 | AR112: =SUM(T112:W112) -> 474 | AS112: =SUM(U112:X112) -> -7734 | AT112: =SUM(V112:Y112) -> 14550 | AU112: =SUM(W112:Z112) -> 21665 | AV112: =SUM(X112:AA112) -> 18272 | AW112: =SUM(Y112:AB112) -> 23656 | AX112: =SUM(Z112:AC112) -> 17778 | ... BJ112: =SUM(AL112:AO112) -> -21146
B113: Accrued Expenses and Other Current Liabilities | C113: 3798 | D113: 2743 | E113: -1965 | F113: 13961 | G113: -7148 | H113: -2492 | I113: 4511 | K113: -133 | L113: =259-K113 -> 392 | M113: =3573-L113-K113 -> 3314 | N113: =SUM(C113-SUM(K113:M113)) -> 225 | O113: 1608 | P113: =1028-O113 -> -580 | Q113: =2768-P113-O113 -> 1740 | R113: =SUM(D113-SUM(O113:Q113)) -> -25 | S113: -2608 | T113: =818-S113 -> 3426 | U113: =245-T113-S113 -> -573 | V113: =SUM(E113-SUM(S113:U113)) -> -2210 | W113: 10689 | X113: =10157-W113 -> -532 | Y113: =18176-X113-W113 -> 8019 | Z113: =SUM(F113-SUM(W113:Y113)) -> -4215 | AA113: 8527 | AB113: =7949-AA113 -> -578 | AC113: =-3429-AB113-AA113 -> -11378 | AD113: =SUM(G113-SUM(AA113:AC113)) -> -3719 | AE113: -528 | AF113: =-4852-AE113 -> -4324 | AG113: =-2752-AF113-AE113 -> 2100 | AH113: =SUM(H113-SUM(AE113:AG113)) -> 260 | AI113: 2953 | AJ113: =4557-AI113 -> 1604 | AK113: =7135-AJ113-AI113 -> 2578 | AL113: =SUM(I113-SUM(AI113:AK113)) -> -2624 | AM113: -1031 | AN113: =-3638-AM113 -> -2607 | AO113: =-7847-AN113-AM113 -> -4209 | AQ113: =SUM(S113:V113) -> -1965 | AR113: =SUM(T113:W113) -> 11332 | AS113: =SUM(U113:X113) -> 7374 | AT113: =SUM(V113:Y113) -> 15966 | AU113: =SUM(W113:Z113) -> 13961 | AV113: =SUM(X113:AA113) -> 11799 | AW113: =SUM(Y113:AB113) -> 11753 | AX113: =SUM(Z113:AC113) -> -7644 | ... BJ113: =SUM(AL113:AO113) -> -10471 | BL113: =SUM(BI113/BE113)-1 -> -1.5326008
B114: Prepaid lease costs, non-current | C114: 0 | D114: 0 | E114: 0 | F114: -59188 | G114: -55110 | H114: -4245 | I114: -6502 | K114: 0 | L114: 0 | M114: 0 | N114: =SUM(C114-SUM(K114:M114)) -> 0 | O114: 0 | P114: 0 | Q114: 0 | R114: =SUM(D114-SUM(O114:Q114)) -> 0 | S114: 0 | T114: 0 | U114: 0 | V114: =SUM(E114-SUM(S114:U114)) -> 0 | W114: 0 | X114: =-26578-W114 -> -26578 | Y114: =-49456-X114-W114 -> -22878 | Z114: =SUM(F114-SUM(W114:Y114)) -> -9732 | AA114: -36978 | AB114: =-43651-AA114 -> -6673 | AC114: =-49063-AB114-AA114 -> -5412 | AD114: =SUM(G114-SUM(AA114:AC114)) -> -6047 | AE114: -3082 | AF114: =-4593-AE114 -> -1511 | AG114: =-3254-AF114-AE114 -> 1339 | AH114: =SUM(H114-SUM(AE114:AG114)) -> -991 | AI114: -1669 | AJ114: =-3236-AI114 -> -1567 | AK114: =-4933-AJ114-AI114 -> -1697 | AL114: =SUM(I114-SUM(AI114:AK114)) -> -1569 | AM114: -1768 | AN114: =-3888-AM114 -> -2120 | AO114: =-5117-AN114-AM114 -> -1229 | AQ114: =SUM(S114:V114) -> 0 | AR114: =SUM(T114:W114) -> 0 | AS114: =SUM(U114:X114) -> -26578 | AT114: =SUM(V114:Y114) -> -49456 | AU114: =SUM(W114:Z114) -> -59188 | AV114: =SUM(X114:AA114) -> -96166 | AW114: =SUM(Y114:AB114) -> -76261 | AX114: =SUM(Z114:AC114) -> -58795 | ... BJ114: =SUM(AL114:AO114) -> -6686 | BL114: =SUM(BI114/BE114)-1 -> 1.4771468
B115: Operating Lease Liabilities and Other Long-term Liabilities | C115: 278 | D115: 21 | E115: -2194 | F115: -3474 | G115: -4333 | H115: -3281 | I115: -3235 | K115: 40 | L115: =39-K115 -> -1 | M115: =39-L115-K115 -> 0 | N115: =SUM(C115-SUM(K115:M115)) -> 239 | O115: 4 | P115: =12-O115 -> 8 | Q115: =11-P115-O115 -> -1 | R115: =SUM(D115-SUM(O115:Q115)) -> 10 | S115: -479 | T115: =-1188-S115 -> -709 | U115: =-1584-T115-S115 -> -396 | V115: =SUM(E115-SUM(S115:U115)) -> -610 | W115: -818 | X115: =-1619-W115 -> -801 | Y115: =-2332-X115-W115 -> -713 | Z115: =SUM(F115-SUM(W115:Y115)) -> -1142 | AA115: -1113 | AB115: =-2059-AA115 -> -946 | AC115: =-3177+3022-AB115-AA115 -> 1904 | AD115: =SUM(G115-SUM(AA115:AC115)) -> -4178 | AE115: -678 | AF115: =-2556-AE115 -> -1878 | AG115: =-3244-AF115-AE115 -> -688 | AH115: =SUM(H115-SUM(AE115:AG115)) -> -37 | AI115: -822 | AJ115: =-1626-AI115 -> -804 | AK115: =-2412-AJ115-AI115 -> -786 | AL115: =SUM(I115-SUM(AI115:AK115)) -> -823 | AM115: -927 | AN115: =-2156-AM115 -> -1229 | AO115: =-2617-AN115-AM115 -> -461 | AQ115: =SUM(S115:V115) -> -2194 | AR115: =SUM(T115:W115) -> -2533 | AS115: =SUM(U115:X115) -> -2625 | AT115: =SUM(V115:Y115) -> -2942 | AU115: =SUM(W115:Z115) -> -3474 | AV115: =SUM(X115:AA115) -> -3769 | AW115: =SUM(Y115:AB115) -> -3914 | AX115: =SUM(Z115:AC115) -> -1297 | ... BJ115: =SUM(AL115:AO115) -> -3440 | BL115: =SUM(BI115/BE115)-1 -> 0.60144619
B116: Net cash used in operating activities | C116: =SUM(C98:C115) -> -37721 | D116: =SUM(D98:D115) -> -46995 | E116: =SUM(E98:E115) -> -39995 | F116: =SUM(F98:F115) -> -301370 | G116: =SUM(G98:G115) -> -320244 | H116: =SUM(H98:H115) -> -107825 | I116: =SUM(I98:I115) -> -98813 | K116: =SUM(K98:K115) -> -4888 | L116: =SUM(L98:L115) -> -7779 | M116: =SUM(M98:M115) -> -11710 | N116: =SUM(N98:N115) -> -13344 | O116: =SUM(O98:O115) -> -13280 | P116: =SUM(P98:P115) -> -9086 | Q116: =SUM(Q98:Q115) -> 4027 | R116: =SUM(R98:R115) -> -28656 | ... AO116: =SUM(AO98:AO115) -> -38783 | AQ116: =SUM(AQ98:AQ115) -> -39995 | AR116: =SUM(AR98:AR115) -> -53450 | AS116: =SUM(AS98:AS115) -> -116105 | AT116: =SUM(AT98:AT115) -> -188305 | AU116: =SUM(AU98:AU115) -> -301370 | AV116: =SUM(AV98:AV115) -> -435923 | AW116: =SUM(AW98:AW115) -> -416615 | AX116: =SUM(AX98:AX115) -> -380670 | ... BJ116: =SUM(BJ98:BJ115) -> -127090 | BL116: =SUM(BI116/BE116)-1 -> 0.63965945
B118: Cash flows from investing activities:
B119: Purchase of Property Plant, and Equipment | C119: -22228 | D119: -23795 | E119: -57696 | F119: -135961 | G119: -70475 | H119: -10564 | I119: -11015 | K119: -3719 | L119: =-9973-K119 -> -6254 | M119: =-18250-L119-K119 -> -8277 | N119: =SUM(C119-SUM(K119:M119)) -> -3978 | O119: -3795 | P119: =-7502-O119 -> -3707 | Q119: =-9515-P119-O119 -> -2013 | R119: =SUM(D119-SUM(O119:Q119)) -> -14280 | S119: -12398 | T119: =-26031-S119 -> -13633 | U119: =-38048-T119-S119 -> -12017 | V119: =SUM(E119-SUM(S119:U119)) -> -19648 | W119: -23363 | X119: =-51420-W119 -> -28057 | Y119: =-104301-X119-W119 -> -52881 | Z119: =SUM(F119-SUM(W119:Y119)) -> -31660 | AA119: -21548 | AB119: =-41965-AA119 -> -20417 | AC119: =-59952-AB119-AA119 -> -17987 | AD119: =SUM(G119-SUM(AA119:AC119)) -> -10523 | AE119: -5302 | AF119: =-7139-AE119 -> -1837 | AG119: =-8567-AF119-AE119 -> -1428 | AH119: =SUM(H119-SUM(AE119:AG119)) -> -1997 | AI119: -1197 | AJ119: =-2520-AI119 -> -1323 | AK119: =-4540-AJ119-AI119 -> -2020 | AL119: =SUM(I119-SUM(AI119:AK119)) -> -6475 | AM119: -4485 | AN119: =-6423-AM119 -> -1938 | AO119: =-9330-AN119-AM119 -> -2907 | AQ119: =SUM(S119:V119) -> -57696 | AR119: =SUM(T119:W119) -> -68661 | AS119: =SUM(U119:X119) -> -83085 | AT119: =SUM(V119:Y119) -> -123949 | AU119: =SUM(W119:Z119) -> -135961 | AV119: =SUM(X119:AA119) -> -134146 | AW119: =SUM(Y119:AB119) -> -126506 | AX119: =SUM(Z119:AC119) -> -91612 | ... BJ119: =SUM(AL119:AO119) -> -15805
B120: Proceeds from Sale of Fixed Assets | C120: 67 | D120: 299 | E120: 599 | F120: 0 | G120: 0 | H120: 4323 | I120: 4348 | K120: 0 | L120: 0 | M120: =104-L120-K120 -> 104 | N120: =SUM(C120-SUM(K120:M120)) -> -37 | O120: 132 | P120: =232-O120 -> 100 | Q120: =307-P120-O120 -> 75 | R120: =SUM(D120-SUM(O120:Q120)) -> -8 | S120: 0 | T120: 0 | U120: 0 | V120: =SUM(E120-SUM(S120:U120)) -> 599 | W120: 0 | X120: 0 | Y120: 0 | Z120: =SUM(F120-SUM(W120:Y120)) -> 0 | AA120: 0 | AB120: 0 | AC120: 0 | AD120: =SUM(G120-SUM(AA120:AC120)) -> 0 | AE120: 2250 | AF120: =2316-AE120 -> 66 | AG120: =2477-AF120-AE120 -> 161 | AH120: =SUM(H120-SUM(AE120:AG120)) -> 1846 | AI120: 429 | AJ120: =3157-AI120 -> 2728 | AK120: =4093-AJ120-AI120 -> 936 | AL120: =SUM(I120-SUM(AI120:AK120)) -> 255 | AM120: 348 | AN120: =348-AM120 -> 0 | AO120: =1256-AN120-AM120 -> 908 | AQ120: =SUM(S120:V120) -> 599 | AR120: =SUM(T120:W120) -> 599 | AS120: =SUM(U120:X120) -> 599 | AT120: =SUM(V120:Y120) -> 599 | AU120: =SUM(W120:Z120) -> 0 | AV120: =SUM(X120:AA120) -> 0 | AW120: =SUM(Y120:AB120) -> 0 | AX120: =SUM(Z120:AC120) -> 0 | ... BJ120: =SUM(AL120:AO120) -> 1511
B121: Purchases of Property, Plant and Equipment, Held for Sale | C121: -1022 | D121: -2123 | E121: -2288 | F121: 0 | G121: -2821 | H121: 0 | I121: 0 | K121: 0 | L121: 0 | M121: 0 | N121: =SUM(C121-SUM(K121:M121)) -> -1022 | O121: -829 | P121: =-3121-O121 -> -2292 | Q121: =-7403-P121-O121 -> -4282 | R121: =SUM(D121-SUM(O121:Q121)) -> 5280 | S121: -964 | T121: =-2288-S121 -> -1324 | U121: =-2288-T121-S121 -> 0 | V121: =SUM(E121-SUM(S121:U121)) -> 0 | W121: 0 | X121: 0 | Y121: 0 | Z121: =SUM(F121-SUM(W121:Y121)) -> 0 | AA121: 0 | AB121: 0 | AC121: 0 | AD121: =SUM(G121-SUM(AA121:AC121)) -> -2821 | AE121: 0 | AF121: 0 | AG121: 0 | AH121: =SUM(H121-SUM(AE121:AG121)) -> 0 | AI121: 0 | AJ121: 0 | AK121: 0 | AL121: =SUM(I121-SUM(AI121:AK121)) -> 0 | AM121: 0 | AN121: 0 | AO121: 0 | AQ121: =SUM(S121:V121) -> -2288 | AR121: =SUM(T121:W121) -> -1324 | AS121: =SUM(U121:X121) -> 0 | AT121: =SUM(V121:Y121) -> 0 | AU121: =SUM(W121:Z121) -> 0 | AV121: =SUM(X121:AA121) -> 0 | AW121: =SUM(Y121:AB121) -> 0 | AX121: =SUM(Z121:AC121) -> 0 | ... BJ121: =SUM(AL121:AO121) -> 0
B122: Asset Acquisitions | C122: 0 | D122: 0 | E122: -15482 | F122: 0 | G122: 0 | H122: 0 | I122: 0 | K122: 0 | L122: 0 | M122: 0 | N122: =SUM(C122-SUM(K122:M122)) -> 0 | O122: 0 | P122: 0 | Q122: 0 | R122: =SUM(D122-SUM(O122:Q122)) -> 0 | S122: 0 | T122: 0 | U122: 0 | V122: =SUM(E122-SUM(S122:U122)) -> -15482 | W122: 0 | X122: 0 | Y122: 0 | Z122: =SUM(F122-SUM(W122:Y122)) -> 0 | AA122: 0 | AB122: 0 | AC122: 0 | AD122: =SUM(G122-SUM(AA122:AC122)) -> 0 | AE122: 0 | AF122: 0 | AG122: 0 | AH122: =SUM(H122-SUM(AE122:AG122)) -> 0 | AI122: 0 | AJ122: 0 | AK122: 0 | AL122: =SUM(I122-SUM(AI122:AK122)) -> 0 | AM122: 0 | AN122: 0 | AO122: 0 | AQ122: =SUM(S122:V122) -> -15482 | AR122: =SUM(T122:W122) -> -15482 | AS122: =SUM(U122:X122) -> -15482 | AT122: =SUM(V122:Y122) -> -15482 | AU122: =SUM(W122:Z122) -> 0 | AV122: =SUM(X122:AA122) -> 0 | AW122: =SUM(Y122:AB122) -> 0 | AX122: =SUM(Z122:AC122) -> 0 | ... BJ122: =SUM(AL122:AO122) -> 0
...

Sheet Revenue Drivers
B2: Beyond Meat, Inc. (NASDAQ: BYND) | C2: FYE | G2: FYE | K2: Quarterly | S2: Quarterly | T2: Quarterly | AA2: LTM | AE2: LTM | AG2: LTM | AM2: Variance
B3: Segment Anaysis | C3: ='Historical Financials'!C7 -> 2018 | D3: ='Historical Financials'!D7 -> 2019 | E3: ='Historical Financials'!E7 -> 2020 | F3: ='Historical Financials'!F7 -> 2021 | G3: ='Historical Financials'!G7 -> 2022 | H3: ='Historical Financials'!H7 -> 2023 | I3: ='Historical Financials'!I7 -> 2024 | K3: ='Historical Financials'!AA7 -> 1Q22 | L3: ='Historical Financials'!AB7 -> 2Q22 | M3: ='Historical Financials'!AC7 -> 3Q22 | N3: ='Historical Financials'!AD7 -> 4Q22 | O3: ='Historical Financials'!AE7 -> 1Q23 | P3: ='Historical Financials'!AF7 -> 2Q23 | Q3: ='Historical Financials'!AG7 -> 3Q23 | R3: ='Historical Financials'!AH7 -> 4Q23 | ... Y3: ='Historical Financials'!AO7 -> 3Q25 | AA3: =O3 -> 1Q23 | AB3: =P3 -> 2Q23 | AC3: =Q3 -> 3Q23 | AD3: =R3 -> 4Q23 | AE3: =S3 -> 1Q24 | AF3: =T3 -> 2Q24 | AG3: =U3 -> 3Q24 | AH3: =V3 -> 4Q24 | ... AK3: =Y3 -> 3Q25
B4: $ mm except per share | C4: ='Historical Financials'!C8 -> 43465 | D4: ='Historical Financials'!D8 -> 43830 | E4: ='Historical Financials'!E8 -> 44196 | F4: ='Historical Financials'!F8 -> 44561 | G4: ='Historical Financials'!G8 -> 44926 | H4: ='Historical Financials'!H8 -> 45291 | I4: ='Historical Financials'!I8 -> 45657 | K4: ='Historical Financials'!AA8 -> 44653 | L4: ='Historical Financials'!AB8 -> 44744 | M4: ='Historical Financials'!AC8 -> 44835 | N4: ='Historical Financials'!AD8 -> 44926 | O4: ='Historical Financials'!AE8 -> 45017 | P4: ='Historical Financials'!AF8 -> 45108 | Q4: ='Historical Financials'!AG8 -> 45199 | R4: ='Historical Financials'!AH8 -> 45291 | ... Y4: ='Historical Financials'!AO8 -> 45927 | AA4: =O4 -> 45017 | AB4: =P4 -> 45108 | AC4: =Q4 -> 45199 | AD4: =R4 -> 45291 | AE4: =S4 -> 45381 | AF4: =T4 -> 45472 | AG4: =U4 -> 45563 | AH4: =V4 -> 45657 | ... AK4: =Y4 -> 45927
A6: X | B6: Net Revenues by Channel
B7: Retail | C7: =+C13+C18 -> 50779 | D7: =+D13+D18 -> 144809 | E7: =+E13+E18 -> 300583 | F7: =+F13+F18 -> 324843 | G7: =+G13+G18 -> 295651 | H7: =+H13+H18 -> 216963 | I7: =+I13+I18 -> 210595 | K7: =+K13+K18 -> 84397 | L7: =+L13+L18 -> 102553 | M7: =+M13+M18 -> 56372 | N7: =+N13+N18 -> 52329 | O7: =+O13+O18 -> 58448 | P7: =+P13+P18 -> 68485 | Q7: =+Q13+Q18 -> 44671 | R7: =+R13+R18 -> 45359 | ... Y7: =+Y13+Y18 -> 44347 | AA7: =SUM(L7:O7) -> 269702 | AB7: =SUM(M7:P7) -> 235634 | AC7: =SUM(N7:Q7) -> 223933 | AD7: =SUM(O7:R7) -> 216963 | AE7: =SUM(P7:S7) -> 208181 | AF7: =SUM(Q7:T7) -> 202150 | AG7: =SUM(R7:U7) -> 209013 | AH7: =SUM(S7:V7) -> 210595 | ... AK7: =SUM(V7:Y7) -> 184106 | AM7: =SUM(AK7/AG7)-1 -> -0.11916484
B8: Foodservice | C8: =+C14+C19 -> 37155 | D8: =+D14+D19 -> 153088 | E8: =+E14+E19 -> 106202 | F8: =+F14+F19 -> 139857 | G8: =+G14+G19 -> 123282 | H8: =+H14+H19 -> 126413 | I8: =+I14+I19 -> 115857 | K8: =+K14+K19 -> 25058 | L8: =+L14+L19 -> 44487 | M8: =+M14+M19 -> 26128 | N8: =+N14+N19 -> 27609 | O8: =+O14+O19 -> 33788 | P8: =+P14+P19 -> 33664 | Q8: =+Q14+Q19 -> 30641 | R8: =+R14+R19 -> 28320 | ... Y8: =+Y14+Y19 -> 25871 | AA8: =SUM(L8:O8) -> 132012 | AB8: =SUM(M8:P8) -> 121189 | AC8: =SUM(N8:Q8) -> 125702 | AD8: =SUM(O8:R8) -> 126413 | AE8: =SUM(P8:S8) -> 118562 | AF8: =SUM(Q8:T8) -> 115629 | AG8: =SUM(R8:U8) -> 114460 | AH8: =SUM(S8:V8) -> 115857 | ... AK8: =SUM(V8:Y8) -> 106459 | AM8: =SUM(AK8/AG8)-1 -> -0.069902149
B9: Total Net Revenue | C9: =SUM(C7:C8) -> 87934 | D9: =SUM(D7:D8) -> 297897 | E9: =SUM(E7:E8) -> 406785 | F9: =SUM(F7:F8) -> 464700 | G9: =SUM(G7:G8) -> 418933 | H9: =SUM(H7:H8) -> 343376 | I9: =SUM(I7:I8) -> 326452 | K9: =SUM(K7:K8) -> 109455 | L9: =SUM(L7:L8) -> 147040 | M9: =SUM(M7:M8) -> 82500 | N9: =SUM(N7:N8) -> 79938 | O9: =SUM(O7:O8) -> 92236 | P9: =SUM(P7:P8) -> 102149 | Q9: =SUM(Q7:Q8) -> 75312 | R9: =SUM(R7:R8) -> 73679 | ... Y9: =SUM(Y7:Y8) -> 70218 | AA9: =SUM(AA7:AA8) -> 401714 | AB9: =SUM(AB7:AB8) -> 356823 | AC9: =SUM(AC7:AC8) -> 349635 | AD9: =SUM(AD7:AD8) -> 343376 | AE9: =SUM(AE7:AE8) -> 326743 | AF9: =SUM(AF7:AF8) -> 317779 | AG9: =SUM(AG7:AG8) -> 323473 | AH9: =SUM(AH7:AH8) -> 326452 | ... AK9: =SUM(AK7:AK8) -> 290565 | AM9: =SUM(AK9/AG9)-1 -> -0.10173337
B10: Balance Check | C10: =+C9-'Historical Financials'!C11 -> 0 | D10: =+D9-'Historical Financials'!D11 -> 0 | E10: =+E9-'Historical Financials'!E11 -> 0 | F10: =+F9-'Historical Financials'!F11 -> 0 | G10: =+G9-'Historical Financials'!G11 -> 0 | H10: =+H9-'Historical Financials'!H11 -> 0 | I10: =+I9-'Historical Financials'!I11 -> 0 | K10: =K9-'Historical Financials'!AA11 -> 0 | L10: =L9-'Historical Financials'!AB11 -> 0 | M10: =M9-'Historical Financials'!AC11 -> 0 | N10: =N9-'Historical Financials'!AD11 -> 0 | O10: =O9-'Historical Financials'!AE11 -> 0 | P10: =P9-'Historical Financials'!AF11 -> 0 | Q10: =Q9-'Historical Financials'!AG11 -> 0 | R10: =R9-'Historical Financials'!AH11 -> 0 | ... Y10: =Y9-'Historical Financials'!AO11 -> 0 | AA10: =+AA9-'Historical Financials'!AZ11 -> 0 | AB10: =+AB9-'Historical Financials'!BA11 -> 0 | AC10: =+AC9-'Historical Financials'!BB11 -> 0 | AD10: =+AD9-'Historical Financials'!BC11 -> 0 | AE10: =+AE9-'Historical Financials'!BD11 -> 0 | AF10: =+AF9-'Historical Financials'!BE11 -> 0 | AG10: =+AG9-'Historical Financials'!BF11 -> 0 | AH10: =+AH9-'Historical Financials'!BG11 -> 0 | ... AK10: =+AK9-'Historical Financials'!BJ11 -> 0
A12: X | B12: Revenue by Channel: U.S
B13: Retail | C13: 49772 | D13: 129383 | E13: 264111 | F13: 243360 | G13: 234744 | H13: 155240 | I13: 150812 | K13: 68260 | L13: 78861 | M13: 46177 | N13: =SUM(G13-SUM(K13:M13)) -> 41446 | O13: 44159 | P13: 48490 | Q13: 30518 | R13: =SUM(H13-SUM(O13:Q13)) -> 32073 | S13: 37088 | T13: 44869 | U13: 34969 | V13: =SUM(I13-SUM(S13:U13)) -> 33886 | W13: 31360 | X13: 32909 | Y13: 28537 | AA13: =SUM(L13:O13) -> 210643 | AB13: =SUM(M13:P13) -> 180272 | AC13: =SUM(N13:Q13) -> 164613 | AD13: =SUM(O13:R13) -> 155240 | AE13: =SUM(P13:S13) -> 148169 | AF13: =SUM(Q13:T13) -> 144548 | AG13: =SUM(R13:U13) -> 148999 | AH13: =SUM(S13:V13) -> 150812 | ... AK13: =SUM(V13:Y13) -> 126692 | AM13: =SUM(AK13/AG13)-1 -> -0.14971241
B14: Foodservice | C14: 20717 | D14: 70372 | E14: 60763 | F14: 76475 | G14: 69289 | H14: 50647 | I14: 47584 | K14: 15493 | L14: 23389 | M14: 15994 | N14: =SUM(G14-SUM(K14:M14)) -> 14413 | O14: 14675 | P14: 12764 | Q14: 12535 | R14: =SUM(H14-SUM(O14:Q14)) -> 10673 | S14: 12304 | T14: 10350 | U14: 14478 | V14: =SUM(I14-SUM(S14:U14)) -> 10452 | W14: 9413 | X14: 11055 | Y14: 10524 | AA14: =SUM(L14:O14) -> 68471 | AB14: =SUM(M14:P14) -> 57846 | AC14: =SUM(N14:Q14) -> 54387 | AD14: =SUM(O14:R14) -> 50647 | AE14: =SUM(P14:S14) -> 48276 | AF14: =SUM(Q14:T14) -> 45862 | AG14: =SUM(R14:U14) -> 47805 | AH14: =SUM(S14:V14) -> 47584 | ... AK14: =SUM(V14:Y14) -> 41444 | AM14: =SUM(AK14/AG14)-1 -> -0.1330614
B15: Total Net U.S Revenue | C15: =SUM(C13:C14) -> 70489 | D15: =SUM(D13:D14) -> 199755 | E15: =SUM(E13:E14) -> 324874 | F15: =SUM(F13:F14) -> 319835 | G15: =SUM(G13:G14) -> 304033 | H15: =SUM(H13:H14) -> 205887 | I15: =SUM(I13:I14) -> 198396 | K15: =SUM(K13:K14) -> 83753 | L15: =SUM(L13:L14) -> 102250 | M15: =SUM(M13:M14) -> 62171 | N15: =SUM(N13:N14) -> 55859 | O15: =SUM(O13:O14) -> 58834 | P15: =SUM(P13:P14) -> 61254 | Q15: =SUM(Q13:Q14) -> 43053 | R15: =SUM(R13:R14) -> 42746 | ... Y15: =SUM(Y13:Y14) -> 39061 | AA15: =SUM(AA13:AA14) -> 279114 | AB15: =SUM(AB13:AB14) -> 238118 | AC15: =SUM(AC13:AC14) -> 219000 | AD15: =SUM(AD13:AD14) -> 205887 | AE15: =SUM(AE13:AE14) -> 196445 | AF15: =SUM(AF13:AF14) -> 190410 | AG15: =SUM(AG13:AG14) -> 196804 | AH15: =SUM(AH13:AH14) -> 198396 | ... AK15: =SUM(AK13:AK14) -> 168136 | AM15: =SUM(AK15/AG15)-1 -> -0.14566777
A17: X | B17: Revenue by Channel: International
B18: Retail | C18: 1007 | D18: 15426 | E18: 36472 | F18: 81483 | G18: 60907 | H18: 61723 | I18: 59783 | K18: 16137 | L18: 23692 | M18: 10195 | N18: =SUM(G18-SUM(K18:M18)) -> 10883 | O18: 14289 | P18: 19995 | Q18: 14153 | R18: =SUM(H18-SUM(O18:Q18)) -> 13286 | S18: 12578 | T18: 17585 | U18: 16565 | V18: =SUM(I18-SUM(S18:U18)) -> 13055 | W18: 12682 | X18: 15867 | Y18: 15810 | AA18: =SUM(L18:O18) -> 59059 | AB18: =SUM(M18:P18) -> 55362 | AC18: =SUM(N18:Q18) -> 59320 | AD18: =SUM(O18:R18) -> 61723 | AE18: =SUM(P18:S18) -> 60012 | AF18: =SUM(Q18:T18) -> 57602 | AG18: =SUM(R18:U18) -> 60014 | AH18: =SUM(S18:V18) -> 59783 | ... AK18: =SUM(V18:Y18) -> 57414 | AM18: =SUM(AK18/AG18)-1 -> -0.043323225
B19: Foodservice | C19: 16438 | D19: 82716 | E19: 45439 | F19: 63382 | G19: 53993 | H19: 75766 | I19: 68273 | K19: 9565 | L19: 21098 | M19: 10134 | N19: =SUM(G19-SUM(K19:M19)) -> 13196 | O19: 19113 | P19: 20900 | Q19: 18106 | R19: =SUM(H19-SUM(O19:Q19)) -> 17647 | S19: 13633 | T19: 20381 | U19: 14994 | V19: =SUM(I19-SUM(S19:U19)) -> 19265 | W19: 15276 | X19: 15127 | Y19: 15347 | AA19: =SUM(L19:O19) -> 63541 | AB19: =SUM(M19:P19) -> 63343 | AC19: =SUM(N19:Q19) -> 71315 | AD19: =SUM(O19:R19) -> 75766 | AE19: =SUM(P19:S19) -> 70286 | AF19: =SUM(Q19:T19) -> 69767 | AG19: =SUM(R19:U19) -> 66655 | AH19: =SUM(S19:V19) -> 68273 | ... AK19: =SUM(V19:Y19) -> 65015 | AM19: =SUM(AK19/AG19)-1 -> -0.024604306
B20: Total Net International Revenue | C20: =SUM(C18:C19) -> 17445 | D20: =SUM(D18:D19) -> 98142 | E20: =SUM(E18:E19) -> 81911 | F20: =SUM(F18:F19) -> 144865 | G20: =SUM(G18:G19) -> 114900 | H20: =SUM(H18:H19) -> 137489 | I20: =SUM(I18:I19) -> 128056 | K20: =SUM(K18:K19) -> 25702 | L20: =SUM(L18:L19) -> 44790 | M20: =SUM(M18:M19) -> 20329 | N20: =SUM(N18:N19) -> 24079 | O20: =SUM(O18:O19) -> 33402 | P20: =SUM(P18:P19) -> 40895 | Q20: =SUM(Q18:Q19) -> 32259 | R20: =SUM(R18:R19) -> 30933 | ... Y20: =SUM(Y18:Y19) -> 31157 | AA20: =SUM(AA18:AA19) -> 122600 | AB20: =SUM(AB18:AB19) -> 118705 | AC20: =SUM(AC18:AC19) -> 130635 | AD20: =SUM(AD18:AD19) -> 137489 | AE20: =SUM(AE18:AE19) -> 130298 | AF20: =SUM(AF18:AF19) -> 127369 | AG20: =SUM(AG18:AG19) -> 126669 | AH20: =SUM(AH18:AH19) -> 128056 | ... AK20: =SUM(AK18:AK19) -> 122429 | AM20: =SUM(AK20/AG20)-1 -> -0.033473068

Sheet FCF
B2: Beyond Meat, Inc. (NASDAQ: BYND) | C2: FYE | E2: FYE | I2: Quarterly | S2: Quarterly | Y2: LTM | AF2: LTM | AG2: LTM | AM2: Variance
B3: FCF Analysis | C3: ='Historical Financials'!E7 -> 2020 | D3: ='Historical Financials'!F7 -> 2021 | E3: ='Historical Financials'!G7 -> 2022 | F3: ='Historical Financials'!H7 -> 2023 | G3: ='Historical Financials'!I7 -> 2024 | I3: ='Historical Financials'!AA7 -> 1Q22 | J3: ='Historical Financials'!AB7 -> 2Q22 | K3: ='Historical Financials'!AC7 -> 3Q22 | L3: ='Historical Financials'!AD7 -> 4Q22 | M3: ='Historical Financials'!AE7 -> 1Q23 | N3: ='Historical Financials'!AF7 -> 2Q23 | O3: ='Historical Financials'!AG7 -> 3Q23 | P3: ='Historical Financials'!AH7 -> 4Q23 | ... W3: ='Historical Financials'!AO7 -> 3Q25 | Y3: =K3 -> 3Q22 | Z3: =L3 -> 4Q22 | AA3: =M3 -> 1Q23 | AB3: =N3 -> 2Q23 | AC3: =O3 -> 3Q23 | AD3: =P3 -> 4Q23 | AE3: =Q3 -> 1Q24 | AF3: =R3 -> 2Q24 | ... AK3: =W3 -> 3Q25
B4: $ mm except per share | C4: ='Historical Financials'!E8 -> 44196 | D4: ='Historical Financials'!F8 -> 44561 | E4: ='Historical Financials'!G8 -> 44926 | F4: ='Historical Financials'!H8 -> 45291 | G4: ='Historical Financials'!I8 -> 45657 | I4: ='Historical Financials'!AA8 -> 44653 | J4: ='Historical Financials'!AB8 -> 44744 | K4: ='Historical Financials'!AC8 -> 44835 | L4: ='Historical Financials'!AD8 -> 44926 | M4: ='Historical Financials'!AE8 -> 45017 | N4: ='Historical Financials'!AF8 -> 45108 | O4: ='Historical Financials'!AG8 -> 45199 | P4: ='Historical Financials'!AH8 -> 45291 | ... W4: ='Historical Financials'!AO8 -> 45927 | Y4: =K4 -> 44835 | Z4: =L4 -> 44926 | AA4: =M4 -> 45017 | AB4: =N4 -> 45108 | AC4: =O4 -> 45199 | AD4: =P4 -> 45291 | AE4: =Q4 -> 45381 | AF4: =R4 -> 45472 | ... AK4: =W4 -> 45927
B6: ='Revenue Drivers'!B7 -> Retail | C6: ='Revenue Drivers'!E7 -> 300583 | D6: ='Revenue Drivers'!F7 -> 324843 | E6: ='Revenue Drivers'!G7 -> 295651 | F6: ='Revenue Drivers'!H7 -> 216963 | G6: ='Revenue Drivers'!I7 -> 210595 | I6: ='Revenue Drivers'!K7 -> 84397 | J6: ='Revenue Drivers'!L7 -> 102553 | K6: ='Revenue Drivers'!M7 -> 56372 | L6: ='Revenue Drivers'!N7 -> 52329 | M6: ='Revenue Drivers'!O7 -> 58448 | N6: ='Revenue Drivers'!P7 -> 68485 | O6: ='Revenue Drivers'!Q7 -> 44671 | P6: ='Revenue Drivers'!R7 -> 45359 | ... W6: ='Revenue Drivers'!Y7 -> 44347 | Y6: =SUM(H6:K6) -> 243322 | Z6: =SUM(I6:L6) -> 295651 | AA6: =SUM(J6:M6) -> 269702 | AB6: =SUM(K6:N6) -> 235634 | AC6: =SUM(L6:O6) -> 223933 | AD6: =SUM(M6:P6) -> 216963 | AE6: =SUM(N6:Q6) -> 208181 | AF6: =SUM(O6:R6) -> 202150 | ... AK6: =SUM(T6:W6) -> 184106 | AM6: =SUM(AK6/AG6)-1 -> -0.11916484
B7: ='Revenue Drivers'!B8 -> Foodservice | C7: ='Revenue Drivers'!E8 -> 106202 | D7: ='Revenue Drivers'!F8 -> 139857 | E7: ='Revenue Drivers'!G8 -> 123282 | F7: ='Revenue Drivers'!H8 -> 126413 | G7: ='Revenue Drivers'!I8 -> 115857 | I7: ='Revenue Drivers'!K8 -> 25058 | J7: ='Revenue Drivers'!L8 -> 44487 | K7: ='Revenue Drivers'!M8 -> 26128 | L7: ='Revenue Drivers'!N8 -> 27609 | M7: ='Revenue Drivers'!O8 -> 33788 | N7: ='Revenue Drivers'!P8 -> 33664 | O7: ='Revenue Drivers'!Q8 -> 30641 | P7: ='Revenue Drivers'!R8 -> 28320 | ... W7: ='Revenue Drivers'!Y8 -> 25871 | Y7: =SUM(H7:K7) -> 95673 | Z7: =SUM(I7:L7) -> 123282 | AA7: =SUM(J7:M7) -> 132012 | AB7: =SUM(K7:N7) -> 121189 | AC7: =SUM(L7:O7) -> 125702 | AD7: =SUM(M7:P7) -> 126413 | AE7: =SUM(N7:Q7) -> 118562 | AF7: =SUM(O7:R7) -> 115629 | ... AK7: =SUM(T7:W7) -> 106459 | AM7: =SUM(AK7/AG7)-1 -> -0.069902149
B8: Total Revenue | C8: =SUM(C6:C7) -> 406785 | D8: =SUM(D6:D7) -> 464700 | E8: =SUM(E6:E7) -> 418933 | F8: =SUM(F6:F7) -> 343376 | G8: =SUM(G6:G7) -> 326452 | I8: =SUM(I6:I7) -> 109455 | J8: =SUM(J6:J7) -> 147040 | K8: =SUM(K6:K7) -> 82500 | L8: =SUM(L6:L7) -> 79938 | M8: =SUM(M6:M7) -> 92236 | N8: =SUM(N6:N7) -> 102149 | O8: =SUM(O6:O7) -> 75312 | P8: =SUM(P6:P7) -> 73679 | ... W8: =SUM(W6:W7) -> 70218 | Y8: =SUM(Y6:Y7) -> 338995 | Z8: =SUM(Z6:Z7) -> 418933 | AA8: =SUM(AA6:AA7) -> 401714 | AB8: =SUM(AB6:AB7) -> 356823 | AC8: =SUM(AC6:AC7) -> 349635 | AD8: =SUM(AD6:AD7) -> 343376 | AE8: =SUM(AE6:AE7) -> 326743 | AF8: =SUM(AF6:AF7) -> 317779 | ... AK8: =SUM(AK6:AK7) -> 290565 | AM8: =SUM(AK8/AG8)-1 -> -0.10173337
B9: Y/Y Growth (%) | D9: =SUM(D8/C8)-1 -> 0.14237251 | E9: =SUM(E8/D8)-1 -> -0.098487196 | F9: =SUM(F8/E8)-1 -> -0.18035581 | G9: =SUM(G8/F8)-1 -> -0.049287079 | M9: =SUM(M8/I8)-1 -> -0.15731579 | N9: =SUM(N8/J8)-1 -> -0.30529788 | O9: =SUM(O8/K8)-1 -> -0.087127273 | P9: =SUM(P8/L8)-1 -> -0.078298181 | Q9: =SUM(Q8/M8)-1 -> -0.18033089 | R9: =SUM(R8/N8)-1 -> -0.087754163 | S9: =SUM(S8/O8)-1 -> 0.075605481 | T9: =SUM(T8/P8)-1 -> 0.040432145 | ... W9: =SUM(W8/S8)-1 -> -0.13317532 | AC9: =SUM(AC8/Y8)-1 -> 0.031386894 | AD9: =SUM(AD8/Z8)-1 -> -0.18035581 | AE9: =SUM(AE8/AA8)-1 -> -0.1866278 | AF9: =SUM(AF8/AB8)-1 -> -0.1094212 | AG9: =SUM(AG8/AC8)-1 -> -0.074826605 | AH9: =SUM(AH8/AD8)-1 -> -0.049287079 | AI9: =SUM(AI8/AE8)-1 -> -0.021922428 | AJ9: =SUM(AJ8/AF8)-1 -> -0.051690011 | AK9: =SUM(AK8/AG8)-1 -> -0.10173337 | AM9: =SUM(AK9-AG9)*10000 -> -269.0677
B10: Q/Q Growth (%) | C10: N/A | D10: N/A | E10: N/A | F10: N/A | G10: N/A | J10: =SUM(J8/I8)-1 -> 0.34338313 | K10: =SUM(K8/J8)-1 -> -0.43892818 | L10: =SUM(L8/K8)-1 -> -0.031054545 | M10: =SUM(M8/L8)-1 -> 0.15384423 | N10: =SUM(N8/M8)-1 -> 0.10747431 | O10: =SUM(O8/N8)-1 -> -0.26272406 | P10: =SUM(P8/O8)-1 -> -0.021683132 | Q10: =SUM(Q8/P8)-1 -> 0.026113275 | ... W10: =SUM(W8/V8)-1 -> -0.063235412 | Y10: N/A | Z10: N/A | AA10: N/A | AB10: N/A | AC10: N/A | AD10: N/A | AE10: N/A | AF10: N/A | AG10: N/A | AH10: N/A | AI10: N/A | AJ10: N/A | AK10: N/A
B12: (-) Cost of Sales | C12: ='Historical Financials'!E13 -> -284510 | D12: ='Historical Financials'!F13 -> -347419 | E12: ='Historical Financials'!G13 -> -442676 | F12: ='Historical Financials'!H13 -> -426031 | G12: ='Historical Financials'!I13 -> -284753 | I12: ='Historical Financials'!AA13 -> -109265 | J12: ='Historical Financials'!AB13 -> -153202 | K12: ='Historical Financials'!AC13 -> -97340 | L12: ='Historical Financials'!AD13 -> -82869 | M12: ='Historical Financials'!AE13 -> -86051 | N12: ='Historical Financials'!AF13 -> -99876 | O12: ='Historical Financials'!AG13 -> -82566 | P12: ='Historical Financials'!AH13 -> -157538 | ... W12: ='Historical Financials'!AO13 -> -62988 | Y12: =SUM(H12:K12) -> -359807 | Z12: =SUM(I12:L12) -> -442676 | AA12: =SUM(J12:M12) -> -419462 | AB12: =SUM(K12:N12) -> -366136 | AC12: =SUM(L12:O12) -> -351362 | AD12: =SUM(M12:P12) -> -426031 | AE12: =SUM(N12:Q12) -> -411915 | AF12: =SUM(O12:R12) -> -391507 | ... AK12: =SUM(T12:W12) -> -265803 | AM12: =SUM(AK12/AG12)-1 -> -0.29239775
B13: Gross Profit | C13: =+C8+C12 -> 122275 | D13: =+D8+D12 -> 117281 | E13: =+E8+E12 -> -23743 | F13: =+F8+F12 -> -82655 | G13: =+G8+G12 -> 41699 | I13: =+I8+I12 -> 190 | J13: =+J8+J12 -> -6162 | K13: =+K8+K12 -> -14840 | L13: =+L8+L12 -> -2931 | M13: =+M8+M12 -> 6185 | N13: =+N8+N12 -> 2273 | O13: =+O8+O12 -> -7254 | P13: =+P8+P12 -> -83859 | ... W13: =+W8+W12 -> 7230 | Y13: =+Y8+Y12 -> -20812 | Z13: =+Z8+Z12 -> -23743 | AA13: =+AA8+AA12 -> -17748 | AB13: =+AB8+AB12 -> -9313 | AC13: =+AC8+AC12 -> -1727 | AD13: =+AD8+AD12 -> -82655 | AE13: =+AE8+AE12 -> -85172 | AF13: =+AF8+AF12 -> -73728 | ... AK13: =+AK8+AK12 -> 24762 | AM13: =SUM(AK13/AG13)-1 -> -1.474677
B14: Gross Margin (%) | C14: =C13/C8 -> 0.30058876 | D14: =D13/D8 -> 0.25238003 | E14: =E13/E8 -> -0.056674934 | F14: =F13/F8 -> -0.2407128 | G14: =G13/G8 -> 0.12773394 | I14: =I13/I8 -> 0.0017358732 | J14: =J13/J8 -> -0.041906964 | K14: =K13/K8 -> -0.17987879 | L14: =L13/L8 -> -0.036665916 | M14: =M13/M8 -> 0.067056247 | N14: =N13/N8 -> 0.022251809 | O14: =O13/O8 -> -0.096319312 | P14: =P13/P8 -> -1.1381669 | ... W14: =W13/W8 -> 0.10296505 | Y14: =Y13/Y8 -> -0.061393236 | Z14: =Z13/Z8 -> -0.056674934 | AA14: =AA13/AA8 -> -0.044180686 | AB14: =AB13/AB8 -> -0.026099775 | AC14: =AC13/AC8 -> -0.0049394368 | AD14: =AD13/AD8 -> -0.2407128 | AE14: =AE13/AE8 -> -0.2606697 | AF14: =AF13/AF8 -> -0.2320103 | ... AK14: =AK13/AK8 -> 0.085220174 | AM14: =SUM(AK14-AG14)*10000 -> 2464.8866
B16: (-) Selling, General & Administrative (SG&A) | C16: ='Historical Financials'!E17 -> -133655 | D16: ='Historical Financials'!F17 -> -209474 | E16: ='Historical Financials'!G17 -> -239505 | F16: ='Historical Financials'!H17 -> -220344 | G16: ='Historical Financials'!I17 -> -169674 | I16: ='Historical Financials'!AA17 -> -75114 | J16: ='Historical Financials'!AB17 -> -63015 | K16: ='Historical Financials'!AC17 -> -54495 | L16: ='Historical Financials'!AD17 -> -46881 | M16: ='Historical Financials'!AE17 -> -51900 | N16: ='Historical Financials'!AF17 -> -47455 | O16: ='Historical Financials'!AG17 -> -53252 | P16: ='Historical Financials'!AH17 -> -67737 | ... W16: ='Historical Financials'!AO17 -> -37230 | Y16: =SUM(H16:K16) -> -192624 | Z16: =SUM(I16:L16) -> -239505 | AA16: =SUM(J16:M16) -> -216291 | AB16: =SUM(K16:N16) -> -200731 | AC16: =SUM(L16:O16) -> -199488 | AD16: =SUM(M16:P16) -> -220344 | AE16: =SUM(N16:Q16) -> -215726 | AF16: =SUM(O16:R16) -> -210434 | ... AK16: =SUM(T16:W16) -> -163743 | AM16: =SUM(AK16/AG16)-1 -> -0.16570878
B17: (-) Research and Development (R&D) | C17: ='Historical Financials'!E18 -> -31535 | D17: ='Historical Financials'!F18 -> -66946 | E17: ='Historical Financials'!G18 -> -62264 | F17: ='Historical Financials'!H18 -> -39530 | G17: ='Historical Financials'!I18 -> -28149 | I17: ='Historical Financials'!AA18 -> -19678 | J17: ='Historical Financials'!AB18 -> -16202 | K17: ='Historical Financials'!AC18 -> -13413 | L17: ='Historical Financials'!AD18 -> -12971 | M17: ='Historical Financials'!AE18 -> -12432 | N17: ='Historical Financials'!AF18 -> -8773 | O17: ='Historical Financials'!AG18 -> -9118 | P17: ='Historical Financials'!AH18 -> -9207 | ... W17: ='Historical Financials'!AO18 -> -4917 | Y17: =SUM(H17:K17) -> -49293 | Z17: =SUM(I17:L17) -> -62264 | AA17: =SUM(J17:M17) -> -55018 | AB17: =SUM(K17:N17) -> -47589 | AC17: =SUM(L17:O17) -> -43294 | AD17: =SUM(M17:P17) -> -39530 | AE17: =SUM(N17:Q17) -> -36958 | AF17: =SUM(O17:R17) -> -33670 | ... AK17: =SUM(T17:W17) -> -24857 | AM17: =SUM(AK17/AG17)-1 -> -0.18992993
B18: (-) Restructuring Charges & Other Impairments | C18: ='Historical Financials'!E19 -> -6430 | D18: ='Historical Financials'!F19 -> -15794 | E18: ='Historical Financials'!G19 -> -17259 | F18: ='Historical Financials'!H19 -> 631 | G18: ='Historical Financials'!I19 -> 0 | I18: ='Historical Financials'!AA19 -> -3026 | J18: ='Historical Financials'!AB19 -> -4302 | K18: ='Historical Financials'!AC19 -> -6993 | L18: ='Historical Financials'!AD19 -> -2938 | M18: ='Historical Financials'!AE19 -> 426 | N18: ='Historical Financials'!AF19 -> 201 | O18: ='Historical Financials'!AG19 -> 4 | P18: ='Historical Financials'!AH19 -> 0 | ... W18: ='Historical Financials'!AO19 -> -77414 | Y18: =SUM(H18:K18) -> -14321 | Z18: =SUM(I18:L18) -> -17259 | AA18: =SUM(J18:M18) -> -13807 | AB18: =SUM(K18:N18) -> -9304 | AC18: =SUM(L18:O18) -> -2307 | AD18: =SUM(M18:P18) -> 631 | AE18: =SUM(N18:Q18) -> 205 | AF18: =SUM(O18:R18) -> 4 | ... AK18: =SUM(T18:W18) -> -77414 | AM18: =SUM(AK18/AG18)-1 -> #DIV/0!
B19: Earning before Interest & Taxes (EBIT) | C19: =SUM(C13+SUM(C16:C18)) -> -49345 | D19: =SUM(D13+SUM(D16:D18)) -> -174933 | E19: =SUM(E13+SUM(E16:E18)) -> -342771 | F19: =SUM(F13+SUM(F16:F18)) -> -341898 | G19: =SUM(G13+SUM(G16:G18)) -> -156124 | I19: =SUM(I13+SUM(I16:I18)) -> -97628 | J19: =SUM(J13+SUM(J16:J18)) -> -89681 | K19: =SUM(K13+SUM(K16:K18)) -> -89741 | L19: =SUM(L13+SUM(L16:L18)) -> -65721 | M19: =SUM(M13+SUM(M16:M18)) -> -57721 | N19: =SUM(N13+SUM(N16:N18)) -> -53754 | O19: =SUM(O13+SUM(O16:O18)) -> -69620 | P19: =SUM(P13+SUM(P16:P18)) -> -160803 | ... W19: =SUM(W13+SUM(W16:W18)) -> -112331 | Y19: =SUM(Y13+SUM(Y16:Y18)) -> -277050 | Z19: =SUM(Z13+SUM(Z16:Z18)) -> -342771 | AA19: =SUM(AA13+SUM(AA16:AA18)) -> -302864 | AB19: =SUM(AB13+SUM(AB16:AB18)) -> -266937 | AC19: =SUM(AC13+SUM(AC16:AC18)) -> -246816 | AD19: =SUM(AD13+SUM(AD16:AD18)) -> -341898 | AE19: =SUM(AE13+SUM(AE16:AE18)) -> -337651 | AF19: =SUM(AF13+SUM(AF16:AF18)) -> -317828 | ... AK19: =SUM(AK13+SUM(AK16:AK18)) -> -241252 | AM19: =SUM(AK19/AG19)-1 -> -0.13565996
B20: Operating Margin (%) | C20: =C19/C8 -> -0.12130487 | D20: =D19/D8 -> -0.37644287 | E20: =E19/E8 -> -0.81820005 | F20: =F19/F8 -> -0.99569568 | G20: =G19/G8 -> -0.47824489 | I20: =I19/I8 -> -0.89194646 | J20: =J19/J8 -> -0.60990887 | K20: =K19/K8 -> -1.0877697 | L20: =L19/L8 -> -0.82214967 | M20: =M19/M8 -> -0.62579687 | N20: =N19/N8 -> -0.52623129 | O20: =O19/O8 -> -0.92442107 | P20: =P19/P8 -> -2.1824808 | ... W20: =W19/W8 -> -1.5997465 | Y20: =Y19/Y8 -> -0.81726869 | Z20: =Z19/Z8 -> -0.81820005 | AA20: =AA19/AA8 -> -0.75392941 | AB20: =AB19/AB8 -> -0.74809359 | AC20: =AC19/AC8 -> -0.70592475 | AD20: =AD19/AD8 -> -0.99569568 | AE20: =AE19/AE8 -> -1.033384 | AF20: =AF19/AF8 -> -1.0001542 | ... AK20: =AK19/AK8 -> -0.83028582 | AM20: =SUM(AK20-AG20)*10000 -> 325.89904
B22: (+) Depreciation and Amortization | C22: ='Historical Financials'!E101 -> 13299 | D22: ='Historical Financials'!F101 -> 21663 | E22: ='Historical Financials'!G101 -> 32582 | F22: ='Historical Financials'!H101 -> 48094 | G22: ='Historical Financials'!I101 -> 23121 | I22: ='Historical Financials'!AA101 -> 7091 | J22: ='Historical Financials'!AB101 -> 7729 | K22: ='Historical Financials'!AC101 -> 8435 | L22: ='Historical Financials'!AD101 -> 9327 | M22: ='Historical Financials'!AE101 -> 6049 | N22: ='Historical Financials'!AF101 -> 5879 | O22: ='Historical Financials'!AG101 -> 5779 | P22: ='Historical Financials'!AH101 -> 30387 | ... W22: ='Historical Financials'!AO101 -> 9361 | Y22: =SUM(H22:K22) -> 23255 | Z22: =SUM(I22:L22) -> 32582 | AA22: =SUM(J22:M22) -> 31540 | AB22: =SUM(K22:N22) -> 29690 | AC22: =SUM(L22:O22) -> 27034 | AD22: =SUM(M22:P22) -> 48094 | AE22: =SUM(N22:Q22) -> 49014 | AF22: =SUM(O22:R22) -> 48348 | ... AK22: =SUM(T22:W22) -> 30700 | AM22: =SUM(AK22/AG22)-1 -> -0.35842511
B23: EBITDA | C23: =SUM(C19+C22) -> -36046 | D23: =SUM(D19+D22) -> -153270 | E23: =SUM(E19+E22) -> -310189 | F23: =SUM(F19+F22) -> -293804 | G23: =SUM(G19+G22) -> -133003 | I23: =SUM(I19+I22) -> -90537 | J23: =SUM(J19+J22) -> -81952 | K23: =SUM(K19+K22) -> -81306 | L23: =SUM(L19+L22) -> -56394 | M23: =SUM(M19+M22) -> -51672 | N23: =SUM(N19+N22) -> -47875 | O23: =SUM(O19+O22) -> -63841 | P23: =SUM(P19+P22) -> -130416 | ... W23: =SUM(W19+W22) -> -102970 | Y23: =SUM(Y19+Y22) -> -253795 | Z23: =SUM(Z19+Z22) -> -310189 | AA23: =SUM(AA19+AA22) -> -271324 | AB23: =SUM(AB19+AB22) -> -237247 | AC23: =SUM(AC19+AC22) -> -219782 | AD23: =SUM(AD19+AD22) -> -293804 | AE23: =SUM(AE19+AE22) -> -288637 | AF23: =SUM(AF19+AF22) -> -269480 | ... AK23: =SUM(AK19+AK22) -> -210552 | AM23: =SUM(AK23/AG23)-1 -> -0.089567857
B24: EBITDA Margin (%) | C24: =C23/C8 -> -0.08861192 | D24: =D23/D8 -> -0.32982569 | E24: =E23/E8 -> -0.74042627 | F24: =F23/F8 -> -0.85563347 | G24: =G23/G8 -> -0.40741977 | I24: =I23/I8 -> -0.82716185 | J24: =J23/J8 -> -0.55734494 | K24: =K23/K8 -> -0.98552727 | L24: =L23/L8 -> -0.70547174 | M24: =M23/M8 -> -0.5602151 | N24: =N23/N8 -> -0.46867811 | O24: =O23/O8 -> -0.84768696 | P24: =P23/P8 -> -1.7700566 | ... W24: =W23/W8 -> -1.4664331 | Y24: =Y23/Y8 -> -0.74866886 | Z24: =Z23/Z8 -> -0.74042627 | AA24: =AA23/AA8 -> -0.67541584 | AB24: =AB23/AB8 -> -0.66488707 | AC24: =AC23/AC8 -> -0.62860412 | AD24: =AD23/AD8 -> -0.85563347 | AE24: =AE23/AE8 -> -0.88337623 | AF24: =AF23/AF8 -> -0.84801072 | ... AK24: =AK23/AK8 -> -0.7246296 | AM24: =SUM(AK24-AG24)*10000 -> -96.827584
B26: (+) Share-based Compensation | C26: ='Historical Financials'!E102 -> 27279 | D26: ='Historical Financials'!F102 -> 27698 | E26: ='Historical Financials'!G102 -> 33857 | F26: ='Historical Financials'!H102 -> 29098 | G26: ='Historical Financials'!I102 -> 23923 | I26: ='Historical Financials'!AA102 -> 9292 | J26: ='Historical Financials'!AB102 -> 10306 | K26: ='Historical Financials'!AC102 -> 9250 | L26: ='Historical Financials'!AD102 -> 5009 | M26: ='Historical Financials'!AE102 -> 9565 | N26: ='Historical Financials'!AF102 -> 7748 | O26: ='Historical Financials'!AG102 -> 6478 | P26: ='Historical Financials'!AH102 -> 5307 | ... W26: ='Historical Financials'!AO102 -> 3767 | Y26: =SUM(H26:K26) -> 28848 | Z26: =SUM(I26:L26) -> 33857 | AA26: =SUM(J26:M26) -> 34130 | AB26: =SUM(K26:N26) -> 31572 | AC26: =SUM(L26:O26) -> 28800 | AD26: =SUM(M26:P26) -> 29098 | AE26: =SUM(N26:Q26) -> 25608 | AF26: =SUM(O26:R26) -> 23633 | ... AK26: =SUM(T26:W26) -> 20094 | AM26: =SUM(AK26/AG26)-1 -> -0.12862099
B27: (+) Restructuring Expenses | C27: =-C18 -> 6430 | D27: =-D18 -> 15794 | E27: =-E18 -> 17259 | F27: =-F18 -> -631 | G27: =-G18 -> 0 | I27: =-I18 -> 3026 | J27: =-J18 -> 4302 | K27: =-K18 -> 6993 | L27: =-L18 -> 2938 | M27: =-M18 -> -426 | N27: =-N18 -> -201 | O27: =-O18 -> -4 | P27: =-P18 -> 0 | ... W27: =-W18 -> 77414 | AF27: =SUM(O27:R27) -> -4 | AG27: =SUM(P27:S27) -> 0 | AH27: =SUM(Q27:T27) -> 0 | AI27: =SUM(R27:U27) -> 0 | AJ27: =SUM(S27:V27) -> 0 | AK27: =SUM(T27:W27) -> 77414 | AM27: =SUM(AK27/AG27)-1 -> #DIV/0!
B28: (+) Accrued litigation settlement costs & other charges | C28: 0 | D28: 0 | E28: 0 | F28: 0 | G28: 7500 | I28: 0 | J28: 0 | K28: 0 | L28: =SUM(E28-SUM(I28:K28)) -> 0 | M28: 0 | N28: 0 | O28: 0 | P28: =SUM(F28-SUM(M28:O28)) -> 0 | Q28: 7500 | R28: 0 | S28: 0 | T28: =SUM(G28-SUM(Q28:S28)) -> 0 | U28: 2083 | V28: 1739 | W28: =1757-750 -> 1007 | AF28: =SUM(O28:R28) -> 7500 | AG28: =SUM(P28:S28) -> 7500 | AH28: =SUM(Q28:T28) -> 7500 | AI28: =SUM(R28:U28) -> 2083 | AJ28: =SUM(S28:V28) -> 3822 | AK28: =SUM(T28:W28) -> 4829 | AM28: =SUM(AK28/AG28)-1 -> -0.35613333
B29: Adj. EBITDA | C29: =+SUM(C23+SUM(C26:C28)) -> -2337 | D29: =+SUM(D23+SUM(D26:D28)) -> -109778 | E29: =+SUM(E23+SUM(E26:E28)) -> -259073 | F29: =+SUM(F23+SUM(F26:F28)) -> -265337 | G29: =+SUM(G23+SUM(G26:G28)) -> -101580 | I29: =+SUM(I23+SUM(I26:I28)) -> -78219 | J29: =+SUM(J23+SUM(J26:J28)) -> -67344 | K29: =+SUM(K23+SUM(K26:K28)) -> -65063 | L29: =+SUM(L23+SUM(L26:L28)) -> -48447 | M29: =+SUM(M23+SUM(M26:M28)) -> -42533 | N29: =+SUM(N23+SUM(N26:N28)) -> -40328 | O29: =+SUM(O23+SUM(O26:O28)) -> -57367 | P29: =+SUM(P23+SUM(P26:P28)) -> -125109 | ... W29: =+SUM(W23+SUM(W26:W28)) -> -20782 | Y29: =+SUM(Y23+SUM(Y26:Y28)) -> -224947 | Z29: =+SUM(Z23+SUM(Z26:Z28)) -> -276332 | AA29: =+SUM(AA23+SUM(AA26:AA28)) -> -237194 | AB29: =+SUM(AB23+SUM(AB26:AB28)) -> -205675 | AC29: =+SUM(AC23+SUM(AC26:AC28)) -> -190982 | AD29: =+SUM(AD23+SUM(AD26:AD28)) -> -264706 | AE29: =+SUM(AE23+SUM(AE26:AE28)) -> -263029 | AF29: =+SUM(AF23+SUM(AF26:AF28)) -> -238351 | ... AK29: =+SUM(AK23+SUM(AK26:AK28)) -> -108215 | AM29: =SUM(AK29/AG29)-1 -> -0.46082828
B30: Adj. EBITDA Margin (%) | C30: =C29/C8 -> -0.0057450496 | D30: =D29/D8 -> -0.23623413 | E30: =E29/E8 -> -0.61841154 | F30: =F29/F8 -> -0.77273018 | G30: =G29/G8 -> -0.31116366 | I30: =I29/I8 -> -0.71462245 | J30: =J29/J8 -> -0.45799782 | K30: =K29/K8 -> -0.78864242 | L30: =L29/L8 -> -0.60605719 | M30: =M29/M8 -> -0.46113231 | N30: =N29/N8 -> -0.39479584 | O30: =O29/O8 -> -0.76172456 | P30: =P29/P8 -> -1.6980279 | ... W30: =W29/W8 -> -0.295964 | Y30: =Y29/Y8 -> -0.66357026 | Z30: =Z29/Z8 -> -0.65960905 | AA30: =AA29/AA8 -> -0.5904549 | AB30: =AB29/AB8 -> -0.57640623 | AC30: =AC29/AC8 -> -0.5462325 | AD30: =AD29/AD8 -> -0.77089255 | AE30: =AE29/AE8 -> -0.80500271 | AF30: =AF29/AF8 -> -0.75005271 | ... AK30: =AK29/AK8 -> -0.37242958 | AM30: =SUM(AK30-AG30)*10000 -> 2480.4261
B32: (-) Capital Expenditures | C32: ='Historical Financials'!E119 -> -57696 | D32: ='Historical Financials'!F119 -> -135961 | E32: ='Historical Financials'!G119 -> -70475 | F32: ='Historical Financials'!H119 -> -10564 | G32: ='Historical Financials'!I119 -> -11015 | I32: ='Historical Financials'!AA119 -> -21548 | J32: ='Historical Financials'!AB119 -> -20417 | K32: ='Historical Financials'!AC119 -> -17987 | L32: ='Historical Financials'!AD119 -> -10523 | M32: ='Historical Financials'!AE119 -> -5302 | N32: ='Historical Financials'!AF119 -> -1837 | O32: ='Historical Financials'!AG119 -> -1428 | P32: ='Historical Financials'!AH119 -> -1997 | ... W32: ='Historical Financials'!AO119 -> -2907 | Y32: =SUM(H32:K32) -> -59952 | Z32: =SUM(I32:L32) -> -70475 | AA32: =SUM(J32:M32) -> -54229 | AB32: =SUM(K32:N32) -> -35649 | AC32: =SUM(L32:O32) -> -19090 | AD32: =SUM(M32:P32) -> -10564 | AE32: =SUM(N32:Q32) -> -6459 | AF32: =SUM(O32:R32) -> -5945 | ... AK32: =SUM(T32:W32) -> -15805 | AM32: =SUM(AK32/AG32)-1 -> 1.4177757
B33: (-) Cash Taxes | C33: =-'Historical Financials'!E152 -> -18 | D33: =-'Historical Financials'!F152 -> 10 | E33: =-'Historical Financials'!G152 -> -38 | F33: =-'Historical Financials'!H152 -> 1 | G33: =-'Historical Financials'!I152 -> -6 | I33: =-'Historical Financials'!AA152 -> -52 | J33: =-'Historical Financials'!AB152 -> 31 | K33: =-'Historical Financials'!AC152 -> 0 | L33: =-'Historical Financials'!AD152 -> -17 | M33: =-'Historical Financials'!AE152 -> 0 | N33: =-'Historical Financials'!AF152 -> -9 | O33: =-'Historical Financials'!AG152 -> 0 | P33: =-'Historical Financials'!AH152 -> 10 | ... W33: =-'Historical Financials'!AO152 -> 0 | Y33: =SUM(H33:K33) -> -21 | Z33: =SUM(I33:L33) -> -38 | AA33: =SUM(J33:M33) -> 14 | AB33: =SUM(K33:N33) -> -26 | AC33: =SUM(L33:O33) -> -26 | AD33: =SUM(M33:P33) -> 1 | AE33: =SUM(N33:Q33) -> -1 | AF33: =SUM(O33:R33) -> -6 | ... AK33: =SUM(T33:W33) -> 8 | AM33: =SUM(AK33/AG33)-1 -> -2.3333333
B34: (-) Cash Interest | C34: =-'Historical Financials'!E153 -> -2564 | D34: =-'Historical Financials'!F153 -> -348 | E34: =-'Historical Financials'!G153 -> -10 | F34: =-'Historical Financials'!H153 -> 0 | G34: =-'Historical Financials'!I153 -> 0 | I34: =-'Historical Financials'!AA153 -> -17 | J34: =-'Historical Financials'!AB153 -> -136 | K34: =-'Historical Financials'!AC153 -> 150 | L34: =-'Historical Financials'!AD153 -> -7 | M34: =-'Historical Financials'!AE153 -> 0 | N34: =-'Historical Financials'!AF153 -> 0 | O34: =-'Historical Financials'!AG153 -> 0 | P34: =-'Historical Financials'!AH153 -> 0 | ... W34: =-'Historical Financials'!AO153 -> 0 | Y34: =SUM(H34:K34) -> -3 | Z34: =SUM(I34:L34) -> -10 | AA34: =SUM(J34:M34) -> 7 | AB34: =SUM(K34:N34) -> 143 | AC34: =SUM(L34:O34) -> -7 | AD34: =SUM(M34:P34) -> 0 | AE34: =SUM(N34:Q34) -> 0 | AF34: =SUM(O34:R34) -> 0 | ... AK34: =SUM(T34:W34) -> 0 | AM34: =SUM(AK34/AG34)-1 -> #DIV/0!
B35: (+/-) Changes in NWC | C35: =SUM('Historical Financials'!E109:E115) -> -32178 | D35: =SUM('Historical Financials'!F109:F115) -> -179579 | E35: =SUM('Historical Financials'!G109:G115) -> -54187 | F35: =SUM('Historical Financials'!H109:H115) -> 114663 | G35: =SUM('Historical Financials'!I109:I115) -> -4008 | I35: =SUM('Historical Financials'!AA109:AA115) -> -84223 | J35: =SUM('Historical Financials'!AB109:AB115) -> -1930 | K35: =SUM('Historical Financials'!AC109:AC115) -> 33678 | L35: =SUM('Historical Financials'!AD109:AD115) -> -1712 | M35: =SUM('Historical Financials'!AE109:AE115) -> -7932 | N35: =SUM('Historical Financials'!AF109:AF115) -> -10438 | O35: =SUM('Historical Financials'!AG109:AG115) -> 57401 | P35: =SUM('Historical Financials'!AH109:AH115) -> 75632 | ... W35: =SUM('Historical Financials'!AO109:AO115) -> -15959 | Y35: =SUM(H35:K35) -> -52475 | Z35: =SUM(I35:L35) -> -54187 | AA35: =SUM(J35:M35) -> 22104 | AB35: =SUM(K35:N35) -> 13596 | AC35: =SUM(L35:O35) -> 37319 | AD35: =SUM(M35:P35) -> 114663 | AE35: =SUM(N35:Q35) -> 126700 | AF35: =SUM(O35:R35) -> 140643 | ... AK35: =SUM(T35:W35) -> -18515 | AM35: =SUM(AK35/AG35)-1 -> -1.2399777
B36: Discretionary Cash-Flows | C36: =SUM(C29+SUM(C32:C35)) -> -94793 | D36: =SUM(D29+SUM(D32:D35)) -> -425656 | E36: =SUM(E29+SUM(E32:E35)) -> -383783 | F36: =SUM(F29+SUM(F32:F35)) -> -161237 | G36: =SUM(G29+SUM(G32:G35)) -> -116609 | I36: =SUM(I29+SUM(I32:I35)) -> -184059 | J36: =SUM(J29+SUM(J32:J35)) -> -89796 | K36: =SUM(K29+SUM(K32:K35)) -> -49222 | L36: =SUM(L29+SUM(L32:L35)) -> -60706 | M36: =SUM(M29+SUM(M32:M35)) -> -55767 | N36: =SUM(N29+SUM(N32:N35)) -> -52612 | O36: =SUM(O29+SUM(O32:O35)) -> -1394 | P36: =SUM(P29+SUM(P32:P35)) -> -51464 | ... W36: =SUM(W29+SUM(W32:W35)) -> -39648 | Y36: =SUM(Y29+SUM(Y32:Y35)) -> -337398 | Z36: =SUM(Z29+SUM(Z32:Z35)) -> -401042 | AA36: =SUM(AA29+SUM(AA32:AA35)) -> -269298 | AB36: =SUM(AB29+SUM(AB32:AB35)) -> -227611 | AC36: =SUM(AC29+SUM(AC32:AC35)) -> -172786 | AD36: =SUM(AD29+SUM(AD32:AD35)) -> -160606 | AE36: =SUM(AE29+SUM(AE32:AE35)) -> -142789 | AF36: =SUM(AF29+SUM(AF32:AF35)) -> -103659 | ... AK36: =SUM(AK29+SUM(AK32:AK35)) -> -142527 | AM36: =SUM(AK36/AG36)-1 -> 0.095552515
B38: (+/-) Proceeds / (Purchases) of Equity, net | C38: =SUM('Historical Financials'!E129:E133) -> 25732 | D38: =SUM('Historical Financials'!F129:F133) -> 1046104 | E38: =SUM('Historical Financials'!G129:G133) -> 486 | F38: =SUM('Historical Financials'!H129:H133) -> -327 | G38: =SUM('Historical Financials'!I129:I133) -> 46954 | I38: =SUM('Historical Financials'!AA129:AA133) -> 376 | J38: =SUM('Historical Financials'!AB129:AB133) -> 164 | K38: =SUM('Historical Financials'!AC129:AC133) -> -3 | L38: =SUM('Historical Financials'!AD129:AD133) -> -51 | M38: =SUM('Historical Financials'!AE129:AE133) -> -116 | N38: =SUM('Historical Financials'!AF129:AF133) -> -69 | O38: =SUM('Historical Financials'!AG129:AG133) -> -35 | P38: =SUM('Historical Financials'!AH129:AH133) -> -107 | ... W38: =SUM('Historical Financials'!AO129:AO133) -> -73 | Y38: =SUM(H38:K38) -> 537 | Z38: =SUM(I38:L38) -> 486 | AA38: =SUM(J38:M38) -> -6 | AB38: =SUM(K38:N38) -> -239 | AC38: =SUM(L38:O38) -> -271 | AD38: =SUM(M38:P38) -> -327 | AE38: =SUM(N38:Q38) -> -641 | AF38: =SUM(O38:R38) -> -676 | ... AK38: =SUM(T38:W38) -> 47174
B39: (+/-) Issuance / (Repayment) of Debt, net | C39: =SUM('Historical Financials'!E135:E137) -> -27424 | D39: =SUM('Historical Financials'!F135:F137) -> -23605 | E39: =SUM('Historical Financials'!G135:G137) -> 0 | F39: =SUM('Historical Financials'!H135:H137) -> 0 | G39: =SUM('Historical Financials'!I135:I137) -> 0 | I39: =SUM('Historical Financials'!AA135:AA137) -> 0 | J39: =SUM('Historical Financials'!AB135:AB137) -> 0 | K39: =SUM('Historical Financials'!AC135:AC137) -> 0 | L39: =SUM('Historical Financials'!AD135:AD137) -> 0 | M39: =SUM('Historical Financials'!AE135:AE137) -> 0 | N39: =SUM('Historical Financials'!AF135:AF137) -> 0 | O39: =SUM('Historical Financials'!AG135:AG137) -> 0 | P39: =SUM('Historical Financials'!AH135:AH137) -> 0 | ... W39: =SUM('Historical Financials'!AO135:AO137) -> 54803 | Y39: =SUM(H39:K39) -> 0 | Z39: =SUM(I39:L39) -> 0 | AA39: =SUM(J39:M39) -> 0 | AB39: =SUM(K39:N39) -> 0 | AC39: =SUM(L39:O39) -> 0 | AD39: =SUM(M39:P39) -> 0 | AE39: =SUM(N39:Q39) -> 0 | AF39: =SUM(O39:R39) -> 0 | ... AK39: =SUM(T39:W39) -> 89686
B40: (+/-) Payments of Capital Lease Obligations | C40: ='Historical Financials'!E134 -> -70 | D40: ='Historical Financials'!F134 -> -177 | E40: ='Historical Financials'!G134 -> -210 | F40: ='Historical Financials'!H134 -> -223 | G40: ='Historical Financials'!I134 -> -1177 | I40: ='Historical Financials'!AA134 -> -45 | J40: ='Historical Financials'!AB134 -> 2 | K40: ='Historical Financials'!AC134 -> -109 | L40: ='Historical Financials'!AD134 -> -58 | M40: ='Historical Financials'!AE134 -> -33 | N40: ='Historical Financials'!AF134 -> -82 | O40: ='Historical Financials'!AG134 -> -53 | P40: ='Historical Financials'!AH134 -> -55 | ... W40: ='Historical Financials'!AO134 -> -549 | Y40: =SUM(H40:K40) -> -152 | Z40: =SUM(I40:L40) -> -210 | AA40: =SUM(J40:M40) -> -198 | AB40: =SUM(K40:N40) -> -282 | AC40: =SUM(L40:O40) -> -226 | AD40: =SUM(M40:P40) -> -223 | AE40: =SUM(N40:Q40) -> -701 | AF40: =SUM(O40:R40) -> -622 | ... AK40: =SUM(T40:W40) -> -1980
B41: (+/-) Other Financing Activities | C41: =SUM('Historical Financials'!E120:E125) -> -17204 | D41: =SUM('Historical Financials'!F120:F125) -> -11518 | E41: =SUM('Historical Financials'!G120:G125) -> -17052 | F41: =SUM('Historical Financials'!H120:H125) -> 1073 | G41: =SUM('Historical Financials'!I120:I125) -> 4783 | I41: =SUM('Historical Financials'!AA120:AA125) -> 49 | J41: =SUM('Historical Financials'!AB120:AB125) -> -72 | K41: =SUM('Historical Financials'!AC120:AC125) -> -10729 | L41: =SUM('Historical Financials'!AD120:AD125) -> -6300 | M41: =SUM('Historical Financials'!AE120:AE125) -> -1000 | N41: =SUM('Historical Financials'!AF120:AF125) -> 66 | O41: =SUM('Historical Financials'!AG120:AG125) -> 161 | P41: =SUM('Historical Financials'!AH120:AH125) -> 1846 | ... W41: =SUM('Historical Financials'!AO120:AO125) -> 991 | AF41: =SUM(O41:R41) -> 5696 | AG41: =SUM(P41:S41) -> 6376 | AH41: =SUM(Q41:T41) -> 4783 | AI41: =SUM(R41:U41) -> 4236 | AJ41: =SUM(S41:V41) -> 1442 | AK41: =SUM(T41:W41) -> 1592
B42: (+/-) Other | D42: =SUM(D47-C47)-SUM(D36:D41) -> -10981 | E42: =SUM(E47-D47)-SUM(E36:E41) -> -22813 | F42: =SUM(F47-E47)-SUM(F36:F41) -> 41297 | G42: =SUM(G47-F47)-SUM(G36:G41) -> 7457 | I42: =SUM(I47-D47)-SUM(I36:I41) -> -1757 | J42: =SUM(J47-I47)-SUM(J36:J41) -> -3482 | K42: =SUM(K47-J47)-SUM(K36:K41) -> -4435 | L42: =SUM(L47-K47)-SUM(L36:L41) -> -13139 | M42: =SUM(M47-L47)-SUM(M36:M41) -> 5560 | N42: =SUM(N47-M47)-SUM(N36:N41) -> 4912 | O42: =SUM(O47-N47)-SUM(O36:O41) -> 8085 | P42: =SUM(P47-O47)-SUM(P36:P41) -> 22740 | Q42: =SUM(Q47-P47)-SUM(Q36:Q41) -> -2522 | ... W42: =SUM(W47-V47)-SUM(W36:W41) -> -1725 | Y42: =SUM(H42:K42) -> -9674 | Z42: =SUM(I42:L42) -> -22813 | AA42: =SUM(J42:M42) -> -15496 | AB42: =SUM(K42:N42) -> -7102 | AC42: =SUM(L42:O42) -> 5418 | AD42: =SUM(M42:P42) -> 41297 | AE42: =SUM(N42:Q42) -> 33215 | AF42: =SUM(O42:R42) -> 33353 | ... AK42: =SUM(T42:W42) -> 1619
B43: Free-Cash Flows | C43: =SUM(C36+SUM(C38:C42)) -> -113759 | D43: =SUM(D36+SUM(D38:D42)) -> 574167 | E43: =SUM(E36+SUM(E38:E42)) -> -423372 | F43: =SUM(F36+SUM(F38:F42)) -> -119417 | G43: =SUM(G36+SUM(G38:G42)) -> -58592 | I43: =SUM(I36+SUM(I38:I42)) -> -185436 | J43: =SUM(J36+SUM(J38:J42)) -> -93184 | K43: =SUM(K36+SUM(K38:K42)) -> -64498 | L43: =SUM(L36+SUM(L38:L42)) -> -80254 | M43: =SUM(M36+SUM(M38:M42)) -> -51356 | N43: =SUM(N36+SUM(N38:N42)) -> -47785 | O43: =SUM(O36+SUM(O38:O42)) -> 6764 | P43: =SUM(P36+SUM(P38:P42)) -> -27040 | ... W43: =SUM(W36+SUM(W38:W42)) -> 13799 | Y43: =SUM(Y36+SUM(Y38:Y42)) -> -346687 | Z43: =SUM(Z36+SUM(Z38:Z42)) -> -423579 | AA43: =SUM(AA36+SUM(AA38:AA42)) -> -284998 | AB43: =SUM(AB36+SUM(AB38:AB42)) -> -235234 | AC43: =SUM(AC36+SUM(AC38:AC42)) -> -167865 | AD43: =SUM(AD36+SUM(AD38:AD42)) -> -119859 | AE43: =SUM(AE36+SUM(AE38:AE42)) -> -110916 | AF43: =SUM(AF36+SUM(AF38:AF42)) -> -65908 | ... AK43: =SUM(AK36+SUM(AK38:AK42)) -> -4436
B45: Capitalization
B47: Cash & Cash Equivelants | C47: ='Historical Financials'!E45 -> 159127 | D47: ='Historical Financials'!F45 -> 733294 | E47: ='Historical Financials'!G45 -> 309922 | F47: ='Historical Financials'!H45 -> 190505 | G47: ='Historical Financials'!I45 -> 131913 | I47: ='Historical Financials'!AA45 -> 547858 | J47: ='Historical Financials'!AB45 -> 454674 | K47: ='Historical Financials'!AC45 -> 390176 | L47: ='Historical Financials'!AD45 -> 309922 | M47: ='Historical Financials'!AE45 -> 258566 | N47: ='Historical Financials'!AF45 -> 210781 | O47: ='Historical Financials'!AG45 -> 217545 | P47: ='Historical Financials'!AH45 -> 190505 | ... W47: ='Historical Financials'!AO45 -> 117296 | Y47: =K47 -> 390176 | Z47: =L47 -> 309922 | AA47: =M47 -> 258566 | AB47: =N47 -> 210781 | AC47: =O47 -> 217545 | AD47: =P47 -> 190505 | AE47: =Q47 -> 157913 | AF47: =R47 -> 144873 | ... AK47: =W47 -> 117296
B48: Restricted Cash, Current | C48: ='Historical Financials'!E46 -> 0 | D48: ='Historical Financials'!F46 -> 0 | E48: ='Historical Financials'!G46 -> 0 | F48: ='Historical Financials'!H46 -> 2830 | G48: ='Historical Financials'!I46 -> 1041 | I48: ='Historical Financials'!AA46 -> 0 | J48: ='Historical Financials'!AB46 -> 0 | K48: ='Historical Financials'!AC46 -> 0 | L48: ='Historical Financials'!AD46 -> 0 | M48: ='Historical Financials'!AE46 -> 2426 | N48: ='Historical Financials'!AF46 -> 2552 | O48: ='Historical Financials'!AG46 -> 2689 | P48: ='Historical Financials'!AH46 -> 2830 | ... W48: ='Historical Financials'!AO46 -> 1170 | Y48: =K48 -> 0 | Z48: =L48 -> 0 | AA48: =M48 -> 2426 | AB48: =N48 -> 2552 | AC48: =O48 -> 2689 | AD48: =P48 -> 2830 | AE48: =Q48 -> 2971 | AF48: =R48 -> 536 | ... AK48: =W48 -> 1170
B49: Restricted Cash, Non-Current | C49: ='Historical Financials'!E53 -> 0 | D49: ='Historical Financials'!F53 -> 0 | E49: ='Historical Financials'!G53 -> 12627 | F49: ='Historical Financials'!H53 -> 12600 | G49: ='Historical Financials'!I53 -> 12600 | I49: ='Historical Financials'!AA53 -> 0 | J49: ='Historical Financials'!AB53 -> 0 | K49: ='Historical Financials'!AC53 -> 0 | L49: ='Historical Financials'!AD53 -> 12627 | M49: ='Historical Financials'!AE53 -> 12600 | N49: ='Historical Financials'!AF53 -> 12600 | O49: ='Historical Financials'!AG53 -> 12600 | P49: ='Historical Financials'!AH53 -> 12600 | ... W49: ='Historical Financials'!AO53 -> 12600 | Y49: =K49 -> 0 | Z49: =L49 -> 12627 | AA49: =M49 -> 12600 | AB49: =N49 -> 12600 | AC49: =O49 -> 12600 | AD49: =P49 -> 12600 | AE49: =Q49 -> 12600 | AF49: =R49 -> 12600 | ... AK49: =W49 -> 12600
B50: $150MM Sr. Secured 3.500% RCF due April 21, 2025 (Terminated) | C50: =150000-C66-C52 -> 112500 | D50: 0 | E50: 0 | F50: 0 | G50: 0 | I50: 0 | J50: 0 | K50: 0 | L50: =E50 -> 0 | M50: 0 | N50: 0 | O50: 0 | P50: =F50 -> 0 | Q50: 0 | R50: 0 | S50: 0 | T50: =G50 -> 0 | U50: 0 | V50: 0 | W50: 0 | Y50: =K50 -> 0 | Z50: =L50 -> 0 | AA50: =M50 -> 0 | AB50: =N50 -> 0 | AC50: =O50 -> 0 | AD50: =P50 -> 0 | AE50: =Q50 -> 0 | AF50: =R50 -> 0 | ... AK50: =W50 -> 0
B51: Total Liquidity | C51: =SUM(C47:C50) -> 271627 | D51: =SUM(D47:D50) -> 733294 | E51: =SUM(E47:E50) -> 322549 | F51: =SUM(F47:F50) -> 205935 | G51: =SUM(G47:G50) -> 145554 | I51: =SUM(I47:I50) -> 547858 | J51: =SUM(J47:J50) -> 454674 | K51: =SUM(K47:K50) -> 390176 | L51: =SUM(L47:L50) -> 322549 | M51: =SUM(M47:M50) -> 273592 | N51: =SUM(N47:N50) -> 225933 | O51: =SUM(O47:O50) -> 232834 | P51: =SUM(P47:P50) -> 205935 | ... W51: =SUM(W47:W50) -> 131066 | Y51: =SUM(Y47:Y49) -> 390176 | Z51: =SUM(Z47:Z49) -> 322549 | AA51: =SUM(AA47:AA49) -> 273592 | AB51: =SUM(AB47:AB49) -> 225933 | AC51: =SUM(AC47:AC49) -> 232834 | AD51: =SUM(AD47:AD49) -> 205935 | AE51: =SUM(AE47:AE49) -> 173484 | AF51: =SUM(AF47:AF49) -> 158009 | ... AK51: =SUM(AK47:AK49) -> 131066
B52: Outstanding L/Cs | C52: 12500 | D52: N/A | E52: N/A | F52: N/A | G52: N/A | I52: N/A | J52: N/A | K52: N/A | L52: N/A | M52: N/A | N52: N/A | O52: N/A | P52: N/A | Q52: N/A | R52: N/A | S52: N/A | T52: N/A | U52: N/A | V52: N/A | W52: N/A | Y52: N/A | Z52: N/A | AA52: N/A | AB52: N/A | AC52: N/A | AD52: N/A | AE52: N/A | AF52: N/A | AG52: N/A | AH52: N/A | AI52: N/A | AJ52: N/A | AK52: N/A
B54: Balance Sheet Metrics:
B55: Accounts Receivable | C55: ='Historical Financials'!E47 -> 35975 | D55: ='Historical Financials'!F47 -> 43806 | E55: ='Historical Financials'!G47 -> 34198 | F55: ='Historical Financials'!H47 -> 31730 | G55: ='Historical Financials'!I47 -> 26862 | I55: ='Historical Financials'!AA47 -> 52675 | J55: ='Historical Financials'!AB47 -> 77154 | K55: ='Historical Financials'!AC47 -> 34949 | L55: ='Historical Financials'!AD47 -> 34198 | M55: ='Historical Financials'!AE47 -> 42395 | N55: ='Historical Financials'!AF47 -> 50821 | O55: ='Historical Financials'!AG47 -> 35763 | P55: ='Historical Financials'!AH47 -> 31730 | ... W55: ='Historical Financials'!AO47 -> 27920 | Y55: =K55 -> 34949 | Z55: =L55 -> 34198 | AA55: =M55 -> 42395 | AB55: =N55 -> 50821 | AC55: =O55 -> 35763 | AD55: =P55 -> 31730 | AE55: =Q55 -> 35648 | AF55: =R55 -> 34463 | ... AK55: =W55 -> 27920
B56: Accounts Payable | C56: ='Historical Financials'!E62 -> 53071 | D56: ='Historical Financials'!F62 -> 69040 | E56: ='Historical Financials'!G62 -> 55300 | F56: ='Historical Financials'!H62 -> 56032 | G56: ='Historical Financials'!I62 -> 37571 | I56: ='Historical Financials'!AA62 -> 67387 | J56: ='Historical Financials'!AB62 -> 74430 | K56: ='Historical Financials'!AC62 -> 68676 | L56: ='Historical Financials'!AD62 -> 55300 | M56: ='Historical Financials'!AE62 -> 41131 | N56: ='Historical Financials'!AF62 -> 39508 | O56: ='Historical Financials'!AG62 -> 61861 | P56: ='Historical Financials'!AH62 -> 56032 | ... W56: ='Historical Financials'!AO62 -> 46091 | Y56: =K56 -> 68676 | Z56: =L56 -> 55300 | AA56: =M56 -> 41131 | AB56: =N56 -> 39508 | AC56: =O56 -> 61861 | AD56: =P56 -> 56032 | AE56: =Q56 -> 55836 | AF56: =R56 -> 59449 | ... AK56: =W56 -> 46091
B57: Inventories | C57: ='Historical Financials'!E48 -> 121717 | D57: ='Historical Financials'!F48 -> 241870 | E57: ='Historical Financials'!G48 -> 235696 | F57: ='Historical Financials'!H48 -> 130336 | G57: ='Historical Financials'!I48 -> 113444 | I57: ='Historical Financials'!AA48 -> 283754 | J57: ='Historical Financials'!AB48 -> 254653 | K57: ='Historical Financials'!AC48 -> 246987 | L57: ='Historical Financials'!AD48 -> 235696 | M57: ='Historical Financials'!AE48 -> 222370 | N57: ='Historical Financials'!AF48 -> 207138 | O57: ='Historical Financials'!AG48 -> 194570 | P57: ='Historical Financials'!AH48 -> 130336 | ... W57: ='Historical Financials'!AO48 -> 110294 | Y57: =K57 -> 246987 | Z57: =L57 -> 235696 | AA57: =M57 -> 222370 | AB57: =N57 -> 207138 | AC57: =O57 -> 194570 | AD57: =P57 -> 130336 | AE57: =Q57 -> 122538 | AF57: =R57 -> 119532 | ... AK57: =W57 -> 110294
B58: Property Plant, and Equiptment | C58: ='Historical Financials'!E55 -> 115299 | D58: ='Historical Financials'!F55 -> 226489 | E58: ='Historical Financials'!G55 -> 257002 | F58: ='Historical Financials'!H55 -> 194046 | G58: ='Historical Financials'!I55 -> 184887 | I58: ='Historical Financials'!AA55 -> 241389 | J58: ='Historical Financials'!AB55 -> 258075 | K58: ='Historical Financials'!AC55 -> 262595 | L58: ='Historical Financials'!AD55 -> 257002 | M58: ='Historical Financials'!AE55 -> 251218 | N58: ='Historical Financials'!AF55 -> 250335 | O58: ='Historical Financials'!AG55 -> 245373 | P58: ='Historical Financials'!AH55 -> 194046 | ... W58: ='Historical Financials'!AO55 -> 254387 | Y58: =K58 -> 262595 | Z58: =L58 -> 257002 | AA58: =M58 -> 251218 | AB58: =N58 -> 250335 | AC58: =O58 -> 245373 | AD58: =P58 -> 194046 | AE58: =Q58 -> 190896 | AF58: =R58 -> 186584 | ... AK58: =W58 -> 254387
B59: Current Liabilities | C59: ='Historical Financials'!E50 -> 332226 | D59: ='Historical Financials'!F50 -> 1052048 | E59: ='Historical Financials'!G50 -> 606459 | F59: ='Historical Financials'!H50 -> 372844 | G59: ='Historical Financials'!I50 -> 286456 | I59: ='Historical Financials'!AA50 -> 917297 | J59: ='Historical Financials'!AB50 -> 819510 | K59: ='Historical Financials'!AC50 -> 695980 | L59: ='Historical Financials'!AD50 -> 606459 | M59: ='Historical Financials'!AE50 -> 547055 | N59: ='Historical Financials'!AF50 -> 497441 | O59: ='Historical Financials'!AG50 -> 471623 | P59: ='Historical Financials'!AH50 -> 372844 | ... W59: ='Historical Financials'!AO50 -> 288638 | Y59: =K59 -> 695980 | Z59: =L59 -> 606459 | AA59: =M59 -> 547055 | AB59: =N59 -> 497441 | AC59: =O59 -> 471623 | AD59: =P59 -> 372844 | AE59: =Q59 -> 336503 | AF59: =R59 -> 317265 | ... AK59: =W59 -> 288638
B60: Total Liabilities | C60: ='Historical Financials'!E76 -> 100909 | D60: ='Historical Financials'!F76 -> 1246904 | E60: ='Historical Financials'!G76 -> 1265772 | F60: ='Historical Financials'!H76 -> 1287818 | G60: ='Historical Financials'!I76 -> 1279354 | I60: ='Historical Financials'!AA76 -> 1253529 | J60: ='Historical Financials'!AB76 -> 1266050 | K60: ='Historical Financials'!AC76 -> 1283331 | L60: ='Historical Financials'!AD76 -> 1265772 | M60: ='Historical Financials'!AE76 -> 1239711 | N60: ='Historical Financials'!AF76 -> 1267703 | O60: ='Historical Financials'!AG76 -> 1292114 | P60: ='Historical Financials'!AH76 -> 1287818 | ... W60: ='Historical Financials'!AO76 -> 1383734 | Y60: =K60 -> 1283331 | Z60: =L60 -> 1265772 | AA60: =M60 -> 1239711 | AB60: =N60 -> 1267703 | AC60: =O60 -> 1292114 | AD60: =P60 -> 1287818 | AE60: =Q60 -> 1296437 | AF60: =R60 -> 1301259 | ... AK60: =W60 -> 1383734
B62: Summary Debt (BS):
B63: CPLTD | C63: =+'Historical Financials'!E65+'Historical Financials'!E66 -> 25142 | D63: =+'Historical Financials'!F65+'Historical Financials'!F66 -> 364 | E63: =+'Historical Financials'!G65+'Historical Financials'!G66 -> 224 | F63: =+'Historical Financials'!H65+'Historical Financials'!H66 -> 196 | G63: =+'Historical Financials'!I65+'Historical Financials'!I66 -> 851 | I63: =+'Historical Financials'!AA65+'Historical Financials'!AA66 -> 183 | J63: =+'Historical Financials'!AB65+'Historical Financials'!AB66 -> 210 | K63: =+'Historical Financials'!AC65+'Historical Financials'!AC66 -> 226 | L63: =+'Historical Financials'!AD65+'Historical Financials'!AD66 -> 224 | M63: =+'Historical Financials'!AE65+'Historical Financials'!AE66 -> 246 | N63: =+'Historical Financials'!AF65+'Historical Financials'!AF66 -> 218 | O63: =+'Historical Financials'!AG65+'Historical Financials'!AG66 -> 209 | P63: =+'Historical Financials'!AH65+'Historical Financials'!AH66 -> 196 | ... W63: =+'Historical Financials'!AO65+'Historical Financials'!AO66 -> 4554 | Y63: =K63 -> 226 | Z63: =L63 -> 224 | AA63: =M63 -> 246 | AB63: =N63 -> 218 | AC63: =O63 -> 209 | AD63: =P63 -> 196 | AE63: =Q63 -> 763 | AF63: =R63 -> 1005 | ... AK63: =W63 -> 4554
B64: LTD | C64: =+'Historical Financials'!E70+'Historical Financials'!E71+'Historical Financials'!E74 -> 149 | D64: =+'Historical Financials'!F70+'Historical Financials'!F71+'Historical Financials'!F74 -> 1130116 | E64: =+'Historical Financials'!G70+'Historical Financials'!G71+'Historical Financials'!G74 -> 1134077 | F64: =+'Historical Financials'!H70+'Historical Financials'!H71+'Historical Financials'!H74 -> 1137816 | G64: =+'Historical Financials'!I70+'Historical Financials'!I71+'Historical Financials'!I74 -> 1144288 | I64: =+'Historical Financials'!AA70+'Historical Financials'!AA71+'Historical Financials'!AA74 -> 1131053 | J64: =+'Historical Financials'!AB70+'Historical Financials'!AB71+'Historical Financials'!AB74 -> 1135380 | K64: =+'Historical Financials'!AC70+'Historical Financials'!AC71+'Historical Financials'!AC74 -> 1136171 | L64: =+'Historical Financials'!AD70+'Historical Financials'!AD71+'Historical Financials'!AD74 -> 1134077 | M64: =+'Historical Financials'!AE70+'Historical Financials'!AE71+'Historical Financials'!AE74 -> 1135007 | N64: =+'Historical Financials'!AF70+'Historical Financials'!AF71+'Historical Financials'!AF74 -> 1135937 | O64: =+'Historical Financials'!AG70+'Historical Financials'!AG71+'Historical Financials'!AG74 -> 1136874 | P64: =+'Historical Financials'!AH70+'Historical Financials'!AH71+'Historical Financials'!AH74 -> 1137816 | ... W64: =+'Historical Financials'!AO70+'Historical Financials'!AO71+'Historical Financials'!AO74 -> 1223510 | Y64: =K64 -> 1136171 | Z64: =L64 -> 1134077 | AA64: =M64 -> 1135007 | AB64: =N64 -> 1135937 | AC64: =O64 -> 1136874 | AD64: =P64 -> 1137816 | AE64: =Q64 -> 1142148 | AF64: =R64 -> 1142857 | ... AK64: =W64 -> 1223510
B66: $150MM Sr. Secured 3.500% RCF due April 21, 2025 (Terminated) | C66: 25000 | D66: 0 | E66: 0 | F66: 0 | G66: 0 | I66: 0 | J66: 0 | K66: 0 | L66: =E66 -> 0 | M66: 0 | N66: 0 | O66: 0 | P66: =F66 -> 0 | Q66: 0 | R66: 0 | S66: 0 | T66: =G66 -> 0 | U66: 0 | V66: 0 | W66: 0 | Y66: =K66 -> 0 | Z66: =L66 -> 0 | AA66: =M66 -> 0 | AB66: =N66 -> 0 | AC66: =O66 -> 0 | AD66: =P66 -> 0 | AE66: =Q66 -> 0 | AF66: =R66 -> 0 | ... AK66: =W66 -> 0
B67: $1.0Bn 0.00% Convertible Senior Notes due March 15, 2027 | C67: 0 | D67: 1129674 | E67: 1133608 | F67: 1137542 | G67: 1141476 | I67: 1130657 | J67: 1131641 | K67: 1132624 | L67: =E67 -> 1133608 | M67: 1134591 | N67: 1135575 | O67: 1136558 | P67: =F67 -> 1137542 | Q67: 1138525 | R67: 1139509 | S67: 1140493 | T67: =G67 -> 1141476 | U67: 1142460 | V67: 1143443 | W67: 1144427 | Y67: =K67 -> 1132624 | Z67: =L67 -> 1133608 | AA67: =M67 -> 1134591 | AB67: =N67 -> 1135575 | AC67: =O67 -> 1136558 | AD67: =P67 -> 1137542 | AE67: =Q67 -> 1138525 | AF67: =R67 -> 1139509 | ... AK67: =W67 -> 1144427
B68: $100MM Delayed Draw Term Loan | C68: 0 | D68: 0 | E68: 0 | F68: 0 | G68: 0 | I68: 0 | J68: 0 | K68: 0 | L68: =E68 -> 0 | M68: 0 | N68: 0 | O68: 0 | P68: =F68 -> 0 | Q68: 0 | R68: 0 | S68: 0 | T68: =G68 -> 0 | U68: 0 | V68: 30525 | W68: 77734 | Y68: =K68 -> 0 | Z68: =L68 -> 0 | AA68: =M68 -> 0 | AB68: =N68 -> 0 | AC68: =O68 -> 0 | AD68: =P68 -> 0 | AE68: =Q68 -> 0 | AF68: =R68 -> 0 | ... AK68: =W68 -> 77734
B69: Finance Lease Obligations | C69: =+'Historical Financials'!E65+'Historical Financials'!E74 -> 220 | D69: =+'Historical Financials'!F65+'Historical Financials'!F74 -> 624 | E69: =+'Historical Financials'!G65+'Historical Financials'!G74 -> 693 | F69: =+'Historical Financials'!H65+'Historical Financials'!H74 -> 470 | G69: =+'Historical Financials'!I65+'Historical Financials'!I74 -> 3663 | I69: =+'Historical Financials'!AA65+'Historical Financials'!AA74 -> 579 | J69: =+'Historical Financials'!AB65+'Historical Financials'!AB74 -> 3949 | K69: =+'Historical Financials'!AC65+'Historical Financials'!AC74 -> 3773 | L69: =+'Historical Financials'!AD65+'Historical Financials'!AD74 -> 693 | M69: =+'Historical Financials'!AE65+'Historical Financials'!AE74 -> 662 | N69: =+'Historical Financials'!AF65+'Historical Financials'!AF74 -> 580 | O69: =+'Historical Financials'!AG65+'Historical Financials'!AG74 -> 525 | P69: =+'Historical Financials'!AH65+'Historical Financials'!AH74 -> 470 | ... X69: =+'Historical Financials'!AP65+'Historical Financials'!AP74 -> 0 | Y69: =K69 -> 3773 | Z69: =L69 -> 693 | AA69: =M69 -> 662 | AB69: =N69 -> 580 | AC69: =O69 -> 525 | AD69: =P69 -> 470 | AE69: =Q69 -> 4386 | AF69: =R69 -> 4353 | ... AK69: =W69 -> 83637
B70: Total Debt | C70: =SUM(C66:C69) -> 25220 | D70: =SUM(D66:D69) -> 1130298 | E70: =SUM(E66:E69) -> 1134301 | F70: =SUM(F66:F69) -> 1138012 | G70: =SUM(G66:G69) -> 1145139 | I70: =SUM(I66:I69) -> 1131236 | J70: =SUM(J66:J69) -> 1135590 | K70: =SUM(K66:K69) -> 1136397 | L70: =SUM(L66:L69) -> 1134301 | M70: =SUM(M66:M69) -> 1135253 | N70: =SUM(N66:N69) -> 1136155 | O70: =SUM(O66:O69) -> 1137083 | P70: =SUM(P66:P69) -> 1138012 | ... W70: =SUM(W66:W69) -> 1305798 | Y70: =SUM(Y66:Y69) -> 1136397 | Z70: =SUM(Z66:Z69) -> 1134301 | AA70: =SUM(AA66:AA69) -> 1135253 | AB70: =SUM(AB66:AB69) -> 1136155 | AC70: =SUM(AC66:AC69) -> 1137083 | AD70: =SUM(AD66:AD69) -> 1138012 | AE70: =SUM(AE66:AE69) -> 1142911 | AF70: =SUM(AF66:AF69) -> 1143862 | ... AK70: =SUM(AK66:AK69) -> 1305798
B72: Total Shareholder Equity | C72: ='Historical Financials'!E83 -> 367097 | D72: ='Historical Financials'!F83 -> 132495 | E72: ='Historical Financials'!G83 -> -203548 | F72: ='Historical Financials'!H83 -> -513368 | G72: ='Historical Financials'!I83 -> -601208 | I72: ='Historical Financials'!AA83 -> 40981 | J72: ='Historical Financials'!AB83 -> -47941 | K72: ='Historical Financials'!AC83 -> -142044 | L72: ='Historical Financials'!AD83 -> -203548 | M72: ='Historical Financials'!AE83 -> -253134 | N72: ='Historical Financials'!AF83 -> -299118 | O72: ='Historical Financials'!AG83 -> -362906 | P72: ='Historical Financials'!AH83 -> -513368 | ... W72: ='Historical Financials'!AO83 -> -784065 | Y72: =K72 -> -142044 | Z72: =L72 -> -203548 | AA72: =M72 -> -253134 | AB72: =N72 -> -299118 | AC72: =O72 -> -362906 | AD72: =P72 -> -513368 | AE72: =Q72 -> -561411 | AF72: =R72 -> -590025 | ... AK72: =W72 -> -784065
B73: Total Book Capitalization | C73: =SUM(C70:C72) -> 392317 | D73: =SUM(D70:D72) -> 1262793 | E73: =SUM(E70:E72) -> 930753 | F73: =SUM(F70:F72) -> 624644 | G73: =SUM(G70:G72) -> 543931 | I73: =SUM(I70:I72) -> 1172217 | J73: =SUM(J70:J72) -> 1087649 | K73: =SUM(K70:K72) -> 994353 | L73: =SUM(L70:L72) -> 930753 | M73: =SUM(M70:M72) -> 882119 | N73: =SUM(N70:N72) -> 837037 | O73: =SUM(O70:O72) -> 774177 | P73: =SUM(P70:P72) -> 624644 | ... W73: =SUM(W70:W72) -> 521733 | Y73: =SUM(Y70:Y72) -> 994353 | Z73: =SUM(Z70:Z72) -> 930753 | AA73: =SUM(AA70:AA72) -> 882119 | AB73: =SUM(AB70:AB72) -> 837037 | AC73: =SUM(AC70:AC72) -> 774177 | AD73: =SUM(AD70:AD72) -> 624644 | AE73: =SUM(AE70:AE72) -> 581500 | AF73: =SUM(AF70:AF72) -> 553837 | ... AK73: =SUM(AK70:AK72) -> 521733
B75: Credit Metrics
B77: Total Leverage | C77: =C70/C29 -> -10.791613 | D77: =D70/D29 -> -10.296216 | E77: =E70/E29 -> -4.3783065 | F77: =F70/F29 -> -4.2889307 | G77: =G70/G29 -> -11.273272 | L77: =SUM(L70/SUM(I29:L29)) -> -4.3783065 | M77: =SUM(M70/SUM(J29:M29)) -> -5.0820012 | N77: =SUM(N70/SUM(K29:N29)) -> -5.7857576 | O77: =SUM(O70/SUM(L29:O29)) -> -6.0266755 | P77: =SUM(P70/SUM(M29:P29)) -> -4.2889307 | Q77: =SUM(Q70/SUM(N29:Q29)) -> -4.4691398 | R77: =SUM(R70/SUM(O29:R29)) -> -4.7990652 | S77: =SUM(S70/SUM(P29:S29)) -> -5.7043935 | ... W77: =SUM(W70/SUM(T29:W29)) -> -12.066701 | Y77: =Y70/Y29 -> -5.0518433 | Z77: =Z70/Z29 -> -4.1048485 | AA77: =AA70/AA29 -> -4.7861792 | AB77: =AB70/AB29 -> -5.5240306 | AC77: =AC70/AC29 -> -5.9538752 | AD77: =AD70/AD29 -> -4.2991545 | AE77: =AE70/AE29 -> -4.3451901 | AF77: =AF70/AF29 -> -4.7990652 | ... AK77: =AK70/AK29 -> -12.066701
B78: Net Leverage (C&CE) | C78: =SUM(C70-C47)/C29 -> 57.298674 | D78: =SUM(D70-D47)/D29 -> -3.6164259 | E78: =SUM(E70-E47)/E29 -> -3.1820336 | F78: =SUM(F70-F47)/F29 -> -3.5709569 | G78: =SUM(G70-G47)/G29 -> -9.9746604 | L78: =SUM(L70-L47)/SUM(I29:L29) -> -3.1820336 | M78: =SUM(M70-M47)/SUM(J29:M29) -> -3.9245211 | N78: =SUM(N70-N47)/SUM(K29:N29) -> -4.7123761 | O78: =SUM(O70-O47)/SUM(L29:O29) -> -4.8736611 | P78: =SUM(P70-P47)/SUM(M29:P29) -> -3.5709569 | Q78: =SUM(Q70-Q47)/SUM(N29:Q29) -> -3.8516505 | R78: =SUM(R70-R47)/SUM(O29:R29) -> -4.1912516 | S78: =SUM(S70-S47)/SUM(P29:S29) -> -5.0978745 | ... W78: =SUM(W70-W47)/SUM(T29:W29) -> -10.982784 | Y78: =SUM(Y70-Y47)/Y29 -> -3.3173192 | Z78: =SUM(Z70-Z47)/Z29 -> -2.9832918 | AA78: =SUM(AA70-AA47)/AA29 -> -3.6960758 | AB78: =SUM(AB70-AB47)/AB29 -> -4.4992051 | AC78: =SUM(AC70-AC47)/AC29 -> -4.8147888 | AD78: =SUM(AD70-AD47)/AD29 -> -3.5794693 | AE78: =SUM(AE70-AE47)/AE29 -> -3.7448266 | AF78: =SUM(AF70-AF47)/AF29 -> -4.1912516 | ... AK78: =SUM(AK70-AK47)/AK29 -> -10.982784
B79: Interest Coverage | C79: =C29/-C34 -> -0.91146646 | D79: =D29/-D34 -> -315.45402 | E79: =E29/-E34 -> -25907.3 | F79: =F29/-F34 -> #DIV/0! | G79: =G29/-G34 -> #DIV/0! | L79: {=SUM(I29:L29)/SUM(-I34:L34)} -> -25907.3 | M79: {=SUM(J29:M29)/SUM(-J34:M34)} -> 31912.429 | N79: {=SUM(K29:N29)/SUM(-K34:N34)} -> 1373.2238 | O79: {=SUM(L29:O29)/SUM(-L34:O34)} -> -26953.571 | P79: {=SUM(M29:P29)/SUM(-M34:P34)} -> #DIV/0! | Q79: {=SUM(N29:Q29)/SUM(-N34:Q34)} -> #DIV/0! | R79: {=SUM(O29:R29)/SUM(-O34:R34)} -> #DIV/0! | S79: {=SUM(P29:S29)/SUM(-P34:S34)} -> #DIV/0! | ... W79: {=SUM(T29:W29)/SUM(-T34:W34)} -> #DIV/0! | Y79: =Y29/-Y34 -> -74982.333 | Z79: =Z29/-Z34 -> -27633.2 | AA79: =AA29/-AA34 -> 33884.857 | AB79: =AB29/-AB34 -> 1438.2867 | AC79: =AC29/-AC34 -> -27283.143 | AD79: =AD29/-AD34 -> #DIV/0! | AE79: =AE29/-AE34 -> #DIV/0! | AF79: =AF29/-AF34 -> #DIV/0! | ... AK79: =AK29/-AK34 -> #DIV/0!
B80: Debt Service Coverage | C80: {=SUM(C29+C32)/SUM(-C33:C34)} -> -23.250581 | D80: {=SUM(D29+D32)/SUM(-D33:D34)} -> -727.03846 | E80: {=SUM(E29+E32)/SUM(-E33:E34)} -> -6865.5833 | F80: {=SUM(F29+F32)/SUM(-F33:F34)} -> 275901 | G80: {=SUM(G29+G32)/SUM(-G33:G34)} -> -18765.833 | L80: {=SUM(I29:L29+I32:L32)/SUM(-I33:L34)} -> -6865.5833 | M80: {=SUM(J29:M29+J32:M32)/SUM(-J33:M34)} -> 13219.81 | N80: {=SUM(K29:N29+K32:N32)/SUM(-K33:N34)} -> 1983.0769 | O80: {=SUM(L29:O29+L32:O32)/SUM(-L33:O34)} -> -6295.9091 | P80: {=SUM(M29:P29+M32:P32)/SUM(-M33:P34)} -> 275901 | Q80: {=SUM(N29:Q29+N32:Q32)/SUM(-N33:Q34)} -> -262193 | R80: {=SUM(O29:R29+O32:R32)/SUM(-O33:R34)} -> -40716 | S80: {=SUM(P29:S29+P32:S32)/SUM(-P33:S34)} -> -34540.5 | ... W80: {=SUM(T29:W29+T32:W32)/SUM(-T33:W34)} -> 15502.5 | Y80: {=SUM(Y29+Y32)/SUM(-Y33:Y34)} -> -11870.792 | Z80: {=SUM(Z29+Z32)/SUM(-Z33:Z34)} -> -7225.1458 | AA80: {=SUM(AA29+AA32)/SUM(-AA33:AA34)} -> 13877.286 | AB80: {=SUM(AB29+AB32)/SUM(-AB33:AB34)} -> 2062.5983 | AC80: {=SUM(AC29+AC32)/SUM(-AC33:AC34)} -> -6365.8182 | AD80: {=SUM(AD29+AD32)/SUM(-AD33:AD34)} -> 275270 | AE80: {=SUM(AE29+AE32)/SUM(-AE33:AE34)} -> -269488 | AF80: {=SUM(AF29+AF32)/SUM(-AF33:AF34)} -> -40716 | ... AK80: {=SUM(AK29+AK32)/SUM(-AK33:AK34)} -> 15502.5
B81: Fixed Charge Coverage | C81: {=SUM(C29)/SUM(-C32:C34)} -> -0.038770364 | D81: {=SUM(D29)/SUM(-D32:D34)} -> -0.80542044 | E81: {=SUM(E29)/SUM(-E32:E34)} -> -3.6735958 | F81: {=SUM(F29)/SUM(-F32:F34)} -> -25.119474 | G81: {=SUM(G29)/SUM(-G32:G34)} -> -9.2169495 | L81: {=SUM(I29:L29)/SUM(-I32:L34)} -> -3.6735958 | M81: {=SUM(J29:M29)/SUM(-J32:M34)} -> -4.1209231 | N81: {=SUM(K29:N29)/SUM(-K32:N34)} -> -5.5265957 | O81: {=SUM(L29:O29)/SUM(-L32:O34)} -> -9.8663913 | P81: {=SUM(M29:P29)/SUM(-M32:P34)} -> -25.119474 | Q81: {=SUM(N29:Q29)/SUM(-N32:Q34)} -> -39.587307 | R81: {=SUM(O29:R29)/SUM(-O32:R34)} -> -40.05226 | S81: {=SUM(P29:S29)/SUM(-P32:S34)} -> -30.67492 | ... W81: {=SUM(T29:W29)/SUM(-T32:W34)} -> -6.8503513 | Y81: {=SUM(Y29)/SUM(-Y32:Y34)} -> -3.7506169 | Z81: {=SUM(Z29)/SUM(-Z32:Z34)} -> -3.9183245 | AA81: {=SUM(AA29)/SUM(-AA32:AA34)} -> -4.3756272 | AB81: {=SUM(AB29)/SUM(-AB32:AB34)} -> -5.7884442 | AC81: {=SUM(AC29)/SUM(-AC32:AC34)} -> -9.9870313 | AD81: {=SUM(AD29)/SUM(-AD32:AD34)} -> -25.059737 | AE81: {=SUM(AE29)/SUM(-AE32:AE34)} -> -40.716563 | AF81: {=SUM(AF29)/SUM(-AF32:AF34)} -> -40.05226 | ... AK81: {=SUM(AK29)/SUM(-AK32:AK34)} -> -6.8503513
B82: Debt-to-Book Capitalization | C82: =C73/C70 -> 15.555789 | D82: =D73/D70 -> 1.1172213 | E82: =E73/E70 -> 0.82055204 | F82: =F73/F70 -> 0.54889052 | G82: =G73/G70 -> 0.47499125 | L82: =L73/L70 -> 0.82055204 | M82: =M73/M70 -> 0.77702415 | N82: =N73/N70 -> 0.73672782 | O82: =O73/O70 -> 0.68084476 | P82: =P73/P70 -> 0.54889052 | Q82: =Q73/Q70 -> 0.50878852 | R82: =R73/R70 -> 0.48418166 | S82: =S73/S70 -> 0.46552468 | ... W82: =W73/W70 -> 0.39955108 | Y82: =Y73/Y70 -> 0.87500495 | Z82: =Z73/Z70 -> 0.82055204 | AA82: =AA73/AA70 -> 0.77702415 | AB82: =AB73/AB70 -> 0.73672782 | AC82: =AC73/AC70 -> 0.68084476 | AD82: =AD73/AD70 -> 0.54889052 | AE82: =AE73/AE70 -> 0.50878852 | AF82: =AF73/AF70 -> 0.48418166 | ... AK82: =AK73/AK70 -> 0.39955108

Sheet 3-Statement Model
B2: =C6&"(NASDAQ: BYND)" -> Beyond Meat, Inc.(NASDAQ: BYND)
B3: 3-Statement Model
B4: $ mm except per share
B6: Company name | C6: Beyond Meat, Inc. | I6: Select an operating scenario: | K6: Base case
B7: Ticker | C7: BYND
B8: Circ break 1=off, 0=on | C8: 1
B9: Latest closing share price
B10: Latest closing share price date | C10: =NOW() -> 45973.843
B11: Latest fiscal year end date | C11: ='Historical Financials'!I8 -> 45657
B12: Shares outstanding (millions) | C12: 4443.265
A14: X | B14: Income Statement | C14: Actuals | G14: Forecast
B15: Fiscal year | C15: =D15-1 -> 2021 | D15: =E15-1 -> 2022 | E15: =F15-1 -> 2023 | F15: =YEAR(C11) -> 2024 | G15: =F15+1 -> 2025 | H15: =G15+1 -> 2026 | I15: =H15+1 -> 2027 | J15: =I15+1 -> 2028 | K15: =J15+1 -> 2029
B16: Fiscal year end date | C16: =EOMONTH(D16,-12) -> 44561 | D16: =EOMONTH(E16,-12) -> 44926 | E16: =EOMONTH(F16,-12) -> 45291 | F16: =C11 -> 45657 | G16: =EOMONTH(F16,12) -> 46022 | H16: =EOMONTH(G16,12) -> 46387 | I16: =EOMONTH(H16,12) -> 46752 | J16: =EOMONTH(I16,12) -> 47118 | K16: =EOMONTH(J16,12) -> 47483 | M16: Commentary
B18: ='Revenue Drivers'!B7 -> Retail | C18: ='Revenue Drivers'!F7 -> 324843 | D18: ='Revenue Drivers'!G7 -> 295651 | E18: ='Revenue Drivers'!H7 -> 216963 | F18: ='Revenue Drivers'!I7 -> 210595 | G18: =F18*(1+G54) -> 210595 | H18: =G18*(1+H54) -> 210595 | I18: =H18*(1+I54) -> 210595 | J18: =I18*(1+J54) -> 210595 | K18: =J18*(1+K54) -> 210595
B19: ='Revenue Drivers'!B8 -> Foodservice | C19: ='Revenue Drivers'!F8 -> 139857 | D19: ='Revenue Drivers'!G8 -> 123282 | E19: ='Revenue Drivers'!H8 -> 126413 | F19: ='Revenue Drivers'!I8 -> 115857 | G19: =F19*(1+G55) -> 115857 | H19: =G19*(1+H55) -> 115857 | I19: =H19*(1+I55) -> 115857 | J19: =I19*(1+J55) -> 115857 | K19: =J19*(1+K55) -> 115857
B20: Total Net Revenue | C20: =SUM(C18:C19) -> 464700 | D20: =SUM(D18:D19) -> 418933 | E20: =SUM(E18:E19) -> 343376 | F20: =SUM(F18:F19) -> 326452 | G20: =SUM(G18:G19) -> 326452 | H20: =SUM(H18:H19) -> 326452 | I20: =SUM(I18:I19) -> 326452 | J20: =SUM(J18:J19) -> 326452 | K20: =SUM(K18:K19) -> 326452
B21: Y/Y Growth (%) | D21: =SUM(D20/C20)-1 -> -0.098487196 | E21: =SUM(E20/D20)-1 -> -0.18035581 | F21: =SUM(F20/E20)-1 -> -0.049287079 | G21: =SUM(G20/F20)-1 -> 0 | H21: =SUM(H20/G20)-1 -> 0 | I21: =SUM(I20/H20)-1 -> 0 | J21: =SUM(J20/I20)-1 -> 0 | K21: =SUM(K20/J20)-1 -> 0
B23: Cost of Sales | C23: ='Historical Financials'!F13 -> -347419 | D23: ='Historical Financials'!G13 -> -442676 | E23: ='Historical Financials'!H13 -> -426031 | F23: ='Historical Financials'!I13 -> -284753 | G23: =+G24-G20 -> -326452 | H23: =+H24-H20 -> -326452 | I23: =+I24-I20 -> -326452 | J23: =+J24-J20 -> -326452 | K23: =+K24-K20 -> -326452 | M23: Plug = Revenue - Gross Profit
B24: Gross Profit | C24: =+C23+C20 -> 117281 | D24: =+D23+D20 -> -23743 | E24: =+E23+E20 -> -82655 | F24: =+F23+F20 -> 41699 | G24: =G57*G20 -> 0 | H24: =H57*H20 -> 0 | I24: =I57*I20 -> 0 | J24: =J57*J20 -> 0 | K24: =K57*K20 -> 0 | M24: Revenue x Gross Profit Margin forecast
B25: Margin (%) | C25: =C24/C20 -> 0.25238003 | D25: =D24/D20 -> -0.056674934 | E25: =E24/E20 -> -0.2407128 | F25: =F24/F20 -> 0.12773394 | G25: =G24/G20 -> 0 | H25: =H24/H20 -> 0 | I25: =I24/I20 -> 0 | J25: =J24/J20 -> 0 | K25: =K24/K20 -> 0
B27: Selling, General & Administrative (SG&A) | C27: ='Historical Financials'!F17 -> -209474 | D27: ='Historical Financials'!G17 -> -239505 | E27: ='Historical Financials'!H17 -> -220344 | F27: ='Historical Financials'!I17 -> -169674 | G27: =-G58*G18 -> 0 | H27: =-H58*H18 -> 0 | I27: =-I58*I18 -> 0 | J27: =-J58*J18 -> 0 | K27: =-K58*K18 -> 0 | M27: Revenue x SG&A % of sales forecast
B28: Research & Development (R&D) | C28: ='Historical Financials'!F18 -> -66946 | D28: ='Historical Financials'!G18 -> -62264 | E28: ='Historical Financials'!H18 -> -39530 | F28: ='Historical Financials'!I18 -> -28149 | G28: =-G18*G59 -> 0 | H28: =-H18*H59 -> 0 | I28: =-I18*I59 -> 0 | J28: =-J18*J59 -> 0 | K28: =-K18*K59 -> 0 | M28: Revenue x R&D % of sales forecast
B29: Restructuring Charges & Other Impairments | C29: ='Historical Financials'!F19 -> -15794 | D29: ='Historical Financials'!G19 -> -17259 | E29: ='Historical Financials'!H19 -> 631 | F29: ='Historical Financials'!I19 -> 0 | G29: =-G19*G60 -> -18.799564 | H29: =-H19*H60 -> -18.799564 | I29: =-I19*I60 -> -18.799564 | J29: =-J19*J60 -> -18.799564 | K29: =-K19*K60 -> -18.799564 | M29: Consensus
B30: Operating profit (EBIT) | C30: =C24+C27+C28+C29 -> -174933 | D30: =D24+D27+D28+D29 -> -342771 | E30: =E24+E27+E28+E29 -> -341898 | F30: =F24+F27+F28+F29 -> -156124 | G30: =G24+G27+G28+G29 -> -18.799564 | H30: =H24+H27+H28+H29 -> -18.799564 | I30: =I24+I27+I28+I29 -> -18.799564 | J30: =J24+J27+J28+J29 -> -18.799564 | K30: =K24+K27+K28+K29 -> -18.799564
B31: Margin (%) | C31: =C30/C20 -> -0.37644287 | D31: =D30/D20 -> -0.81820005 | E31: =E30/E20 -> -0.99569568 | F31: =F30/F20 -> -0.47824489 | G31: =G30/G20 -> -5.758753e-05 | H31: =H30/H20 -> -5.758753e-05 | I31: =I30/I20 -> -5.758753e-05 | J31: =J30/J20 -> -5.758753e-05 | K31: =K30/K20 -> -5.758753e-05
B33: Interest Income | C33: 0 | D33: 0 | E33: 0 | F33: 0 | M33: Reference from interest on cash schedule
B34: Interest expense | C34: ='Historical Financials'!F23 -> -3648 | D34: ='Historical Financials'!G23 -> -3966 | E34: ='Historical Financials'!H23 -> -3955 | F34: ='Historical Financials'!I23 -> -4097 | M34: Reference from interest expense schedule
B35: Other expense, net | C35: ='Historical Financials'!F24 -> -487 | D35: ='Historical Financials'!G24 -> -420 | E35: ='Historical Financials'!H24 -> 11616 | F35: ='Historical Financials'!I24 -> -10 | G35: =F35 -> -10 | H35: =G35 -> -10 | I35: =H35 -> -10 | J35: =I35 -> -10 | K35: =J35 -> -10 | M35: Straight-line
B36: Pretax profit | C36: =SUM(C30:C35) -> -179068.38 | D36: =SUM(D30:D35) -> -347157.82 | E36: =SUM(E30:E35) -> -334238 | F36: =SUM(F30:F35) -> -160231.48 | G36: =SUM(G30:G35) -> -28.799622 | H36: =SUM(H30:H35) -> -28.799622 | I36: =SUM(I30:I35) -> -28.799622 | J36: =SUM(J30:J35) -> -28.799622 | K36: =SUM(K30:K35) -> -28.799622 | M36: EBIT + interest income less interest expense less other expense
B38: Taxes | C38: ='Historical Financials'!F29 -> -60 | D38: ='Historical Financials'!G29 -> -32 | E38: ='Historical Financials'!H29 -> -5 | F38: ='Historical Financials'!I29 -> 26 | G38: 0 | H38: 0 | I38: 0 | J38: 0 | K38: 0 | M38: Pre-tax Profit x Tax Rate forecast
B39: Equity in Losses of Unconsolidated Joint Venture | C39: ='Historical Financials'!F30 -> -2977 | D39: ='Historical Financials'!G30 -> -18948 | E39: ='Historical Financials'!H30 -> -3902 | F39: ='Historical Financials'!I30 -> -73 | G39: =F39 -> -73 | H39: =G39 -> -73 | I39: =H39 -> -73 | J39: =I39 -> -73 | K39: =J39 -> -73 | M39: Straight Line
B40: Net income | C40: =SUM(C36:C39) -> -182105.38 | D40: =SUM(D36:D39) -> -366137.82 | E40: =SUM(E36:E39) -> -338145 | F40: =SUM(F36:F39) -> -160278.48 | G40: =SUM(G36:G39) -> -101.79962 | H40: =SUM(H36:H39) -> -101.79962 | I40: =SUM(I36:I39) -> -101.79962 | J40: =SUM(J36:J39) -> -101.79962 | K40: =SUM(K36:K39) -> -101.79962 | M40: Pre-tax Profit less taxes
B41: Margin (%) | C41: =C40/C20 -> -0.39187729 | D41: =D40/D20 -> -0.87397703 | E41: =E40/E20 -> -0.98476596 | F41: =F40/F20 -> -0.49097104 | G41: =G40/G20 -> -0.00031183642 | H41: =H40/H20 -> -0.00031183642 | I41: =I40/I20 -> -0.00031183642 | J41: =J40/J20 -> -0.00031183642 | K41: =K40/K20 -> -0.00031183642
B43: Depreciation & Amortization (D&A) | C43: ='Historical Financials'!F101 -> 21663 | D43: ='Historical Financials'!G101 -> 32582 | E43: ='Historical Financials'!H101 -> 48094 | F43: ='Historical Financials'!I101 -> 23121 | M43: Reference from D&A schedule
B44: EBITDA | C44: =C30+C43 -> -153270 | D44: =D30+D43 -> -310189 | E44: =E30+E43 -> -293804 | F44: =F30+F43 -> -133003 | G44: =G30+G43 -> -18.799564 | H44: =H30+H43 -> -18.799564 | I44: =I30+I43 -> -18.799564 | J44: =J30+J43 -> -18.799564 | K44: =K30+K43 -> -18.799564 | M44: EBIT + D&A
B45: Margin (%) | C45: =C44/C20 -> -0.32982569 | D45: =D44/D20 -> -0.74042627 | E45: =E44/E20 -> -0.85563347 | F45: =F44/F20 -> -0.40741977 | G45: =G44/G20 -> -5.758753e-05 | H45: =H44/H20 -> -5.758753e-05 | I45: =I44/I20 -> -5.758753e-05 | J45: =J44/J20 -> -5.758753e-05 | K45: =K44/K20 -> -5.758753e-05
B47: Stock-Based Compensation (SBC) | C47: ='Historical Financials'!F102 -> 27698 | D47: ='Historical Financials'!G102 -> 33857 | E47: ='Historical Financials'!H102 -> 29098 | F47: ='Historical Financials'!I102 -> 23923 | G47: =+(F47*G53)+F47 -> 23923 | H47: =+(G47*H53)+G47 -> 23923 | I47: =+(H47*I53)+H47 -> 23923 | J47: =+(I47*J53)+I47 -> 23923 | K47: =+(J47*K53)+J47 -> 23923 | M47: grow SBC in-line with revenue growth
B48: Adjusted EBITDA | C48: =SUM(C44:C47) -> -125572.33 | D48: =SUM(D44:D47) -> -276332.74 | E48: =SUM(E44:E47) -> -264706.86 | F48: =SUM(F44:F47) -> -109080.41 | G48: =SUM(G44:G47) -> 23904.2 | H48: =SUM(H44:H47) -> 23904.2 | I48: =SUM(I44:I47) -> 23904.2 | J48: =SUM(J44:J47) -> 23904.2 | K48: =SUM(K44:K47) -> 23904.2 | M48: EBITDA + Stock-based compensation
B49: Margin (%) | C49: =C48/C20 -> -0.27022236 | D49: =D48/D20 -> -0.65961082 | E49: =E48/E20 -> -0.77089504 | F49: =F48/F20 -> -0.33413919 | G49: =G48/G20 -> 0.073224242 | H49: =H48/H20 -> 0.073224242 | I49: =I48/I20 -> 0.073224242 | J49: =J48/J20 -> 0.073224242 | K49: =K48/K20 -> 0.073224242
B51: Growth rates & margins
B53: Revenue growth | D53: =D20/C20-1 -> -0.098487196 | E53: =E20/D20-1 -> -0.18035581 | F53: =F20/E20-1 -> -0.049287079 | M53: Consensus estimates
B54: Retail | D54: =SUM(D18/C18)-1 -> -0.08986495 | E54: =SUM(E18/D18)-1 -> -0.26615165 | F54: =SUM(F18/E18)-1 -> -0.029350627 | M54: Consensus estimates
B55: Foodservice | D55: =SUM(D19/C19)-1 -> -0.11851391 | E55: =SUM(E19/D19)-1 -> 0.025397057 | F55: =SUM(F19/E19)-1 -> -0.08350407 | M55: Consensus estimates
B57: Gross profit margin | C57: =C24/C20 -> 0.25238003 | D57: =D24/D20 -> -0.056674934 | E57: =E24/E20 -> -0.2407128 | F57: =F24/F20 -> 0.12773394 | M57: Consensus estimates
B58: R&D % of sales | C58: =-C27/C18 -> 0.6448469 | D58: =-D27/D18 -> 0.81009366 | E58: =-E27/E18 -> 1.0155833 | F58: =-F27/F18 -> 0.80568864 | M58: Consensus estimates
B59: SG&A % of sales | C59: =-C28/C18 -> 0.20608725 | D59: =-D28/D18 -> 0.21059966 | E59: =-E28/E18 -> 0.18219696 | F59: =-F28/F18 -> 0.13366414 | M59: Consensus estimates
B60: Tax rate | C60: =-(C38/C36) -> -0.00033506754 | D60: =-(D38/D36) -> -9.2177097e-05 | E60: =-(E38/E36) -> -1.49594e-05 | F60: =-(F38/F36) -> 0.00016226524 | G60: =F60 -> 0.00016226524 | H60: =G60 -> 0.00016226524 | I60: =H60 -> 0.00016226524 | J60: =I60 -> 0.00016226524 | K60: =J60 -> 0.00016226524 | M60: straight line
B62: D&A | D62: =D43/C43-1 -> 0.50403915 | E62: =E43/D43-1 -> 0.47609109 | F62: =F43/E43-1 -> -0.51925396 | M62: Consensus estimates
B63: SBC | D63: =D47/C47-1 -> 0.22236263 | E63: =E47/D47-1 -> -0.14056177 | F63: =F47/E47-1 -> -0.17784727 | M63: Consensus estimates
A65: X | B65: Balance Sheet | C65: Actuals | G65: Forecast
B66: =B15 -> Fiscal year | C66: =C15 -> 2021 | D66: =D15 -> 2022 | E66: =E15 -> 2023 | F66: =F15 -> 2024 | G66: =G15 -> 2025 | H66: =H15 -> 2026 | I66: =I15 -> 2027 | ... K66: =K15 -> 2029
B67: =B16 -> Fiscal year end date | C67: =C16 -> 44561 | D67: =D16 -> 44926 | E67: =E16 -> 45291 | F67: =F16 -> 45657 | G67: =G16 -> 46022 | H67: =H16 -> 46387 | I67: =I16 -> 46752 | ... K67: =K16 -> 47483
B69: Cash & equivalents, ST and LT marketable securities | G69: =+F69+G114 -> 700.20038 | H69: =+G69+H114 -> 1400.4008 | I69: =+H69+I114 -> 2100.6011 | J69: =+I69+J114 -> 2800.8015 | K69: =+J69+K114 -> 3501.0019 | M69: Reference from 'net change in cash' line on the cash flow statement
B70: Accounts receivable | G70: =F70*(1+G53) -> 0 | H70: =G70*(1+H53) -> 0 | I70: =H70*(1+I53) -> 0 | J70: =I70*(1+J53) -> 0 | K70: =J70*(1+K53) -> 0 | M70: Grow in-line with revenue growth
B71: Inventories | G71: =F71*G23/F23 -> 0 | H71: =G71*H23/G23 -> 0 | I71: =H71*I23/H23 -> 0 | J71: =I71*J23/I23 -> 0 | K71: =J71*K23/J23 -> 0 | M71: Grow in-line with cost of sales growth
B72: Other current assets | G72: =F72*(1+G53) -> 0 | H72: =G72*(1+H53) -> 0 | I72: =H72*(1+I53) -> 0 | J72: =I72*(1+J53) -> 0 | K72: =J72*(1+K53) -> 0 | M72: Grow in-line with revenue growth
B73: Property, plant & equipment | M73: Reference from PP&E schedule
B74: Other non current assets | G74: =F74*(1+G53) -> 0 | H74: =G74*(1+H53) -> 0 | I74: =H74*(1+I53) -> 0 | J74: =I74*(1+J53) -> 0 | K74: =J74*(1+K53) -> 0 | M74: Grow in-line with revenue growth
B75: Total Assets | C75: =SUM(C69:C74) -> 0 | D75: =SUM(D69:D74) -> 0 | E75: =SUM(E69:E74) -> 0 | F75: =SUM(F69:F74) -> 0 | G75: =SUM(G69:G74) -> 700.20038 | H75: =SUM(H69:H74) -> 1400.4008 | I75: =SUM(I69:I74) -> 2100.6011 | J75: =SUM(J69:J74) -> 2800.8015 | K75: =SUM(K69:K74) -> 3501.0019
B77: Accounts payable | G77: =F77*G23/F23 -> 0 | H77: =G77*H23/G23 -> 0 | I77: =H77*I23/H23 -> 0 | J77: =I77*J23/I23 -> 0 | K77: =J77*K23/J23 -> 0 | M77: Grow in-line with cost of sales growth
B78: Other current liabilities | G78: =F78*(1+G53) -> 0 | H78: =G78*(1+H53) -> 0 | I78: =H78*(1+I53) -> 0 | J78: =I78*(1+J53) -> 0 | K78: =J78*(1+K53) -> 0 | M78: Grow in-line with revenue growth
B79: Deferred revenue (current) | G79: =F79*(1+G53) -> 0 | H79: =G79*(1+H53) -> 0 | I79: =H79*(1+I53) -> 0 | J79: =I79*(1+J53) -> 0 | K79: =J79*(1+K53) -> 0 | M79: Grow in-line with revenue growth
B80: Commercial paper / revolver | G80: =G164 -> 0 | H80: =H164 -> 0 | I80: =I164 -> 0 | J80: =J164 -> 0 | K80: =K164 -> 0 | M80: Reference EOP balance from CP/revolver schedule
B81: Long term debt (includes current portion) | G81: =F81 -> 0 | H81: =G81 -> 0 | I81: =H81 -> 0 | J81: =I81 -> 0 | K81: =J81 -> 0 | M81: straight-line
B82: Other non current liabilities | G82: =F82*(1+G53) -> 0 | H82: =G82*(1+H53) -> 0 | I82: =H82*(1+I53) -> 0 | J82: =I82*(1+J53) -> 0 | K82: =J82*(1+K53) -> 0 | M82: Grow in-line with revenue growth
B83: Total liabilities | C83: =SUM(C77:C82) -> 0 | D83: =SUM(D77:D82) -> 0 | E83: =SUM(E77:E82) -> 0 | F83: =SUM(F77:F82) -> 0 | G83: =SUM(G77:G82) -> 0 | H83: =SUM(H77:H82) -> 0 | I83: =SUM(I77:I82) -> 0 | J83: =SUM(J77:J82) -> 0 | K83: =SUM(K77:K82) -> 0
B85: Common stock | G85: =F85+G47 -> 23923 | H85: =G85+H47 -> 47846 | I85: =H85+I47 -> 71769 | J85: =I85+J47 -> 95692 | K85: =J85+K47 -> 119615 | M85: Increase by stock-based compensation forecasted in the I/S section
B86: Retained earnings | M86: Reference from Retained Earnings schedule
B87: Other comprehensive income | G87: =F87 -> 0 | H87: =G87 -> 0 | I87: =H87 -> 0 | J87: =I87 -> 0 | K87: =J87 -> 0 | M87: straight-line
B88: Total equity | C88: =SUM(C85:C87) -> 0 | D88: =SUM(D85:D87) -> 0 | E88: =SUM(E85:E87) -> 0 | F88: =SUM(F85:F87) -> 0 | G88: =SUM(G85:G87) -> 23923 | H88: =SUM(H85:H87) -> 47846 | I88: =SUM(I85:I87) -> 71769 | J88: =SUM(J85:J87) -> 95692 | K88: =SUM(K85:K87) -> 119615
B89: Balance check | C89: =ROUND(C75-C83-C88,3) -> 0 | D89: =ROUND(D75-D83-D88,3) -> 0 | E89: =ROUND(E75-E83-E88,3) -> 0 | F89: =ROUND(F75-F83-F88,3) -> 0 | G89: =ROUND(G75-G83-G88,3) -> -23222.8 | H89: =ROUND(H75-H83-H88,3) -> -46445.599 | I89: =ROUND(I75-I83-I88,3) -> -69668.399 | J89: =ROUND(J75-J83-J88,3) -> -92891.198 | K89: =ROUND(K75-K83-K88,3) -> -116114
A91: X | B91: Cash-Flows Statement | C91: Actuals | G91: Forecast
B92: =B15 -> Fiscal year | C92: =C66 -> 2021 | D92: =D66 -> 2022 | E92: =E66 -> 2023 | F92: =F66 -> 2024 | G92: =G15 -> 2025 | H92: =H15 -> 2026 | I92: =I15 -> 2027 | J92: =J15 -> 2028 | K92: =K15 -> 2029
B93: =B16 -> Fiscal year end date | C93: =C67 -> 44561 | D93: =D67 -> 44926 | E93: =E67 -> 45291 | F93: =F67 -> 45657 | G93: =G16 -> 46022 | H93: =H16 -> 46387 | I93: =I16 -> 46752 | J93: =J16 -> 47118 | K93: =K16 -> 47483
B95: Net income | D95: =D40 -> -366137.82 | E95: =E40 -> -338145 | F95: =F40 -> -160278.48 | G95: =G40 -> -101.79962 | H95: =H40 -> -101.79962 | I95: =I40 -> -101.79962 | J95: =J40 -> -101.79962 | K95: =K40 -> -101.79962 | M95: Reference from the I/S
B96: Depreciation and amortization | D96: =D43 -> 32582 | E96: =E43 -> 48094 | F96: =F43 -> 23121 | G96: =G43 -> 0 | H96: =H43 -> 0 | I96: =I43 -> 0 | J96: =J43 -> 0 | K96: =K43 -> 0 | M96: Reference from the I/S
B97: Stock based compensation | D97: =D47 -> 33857 | E97: =E47 -> 29098 | F97: =F47 -> 23923 | G97: =G47 -> 23923 | H97: =H47 -> 23923 | I97: =I47 -> 23923 | J97: =J47 -> 23923 | K97: =K47 -> 23923
B98: Decreases / (Increases) in working capital assets | D98: =SUM(C70:C72)-SUM(D70:D72) -> 0 | E98: =SUM(D70:D72)-SUM(E70:E72) -> 0 | F98: =SUM(E70:E72)-SUM(F70:F72) -> 0 | G98: =SUM(F70:F72)-SUM(G70:G72) -> 0 | H98: =SUM(G70:G72)-SUM(H70:H72) -> 0 | I98: =SUM(H70:H72)-SUM(I70:I72) -> 0 | J98: =SUM(I70:I72)-SUM(J70:J72) -> 0 | K98: =SUM(J70:J72)-SUM(K70:K72) -> 0
B99: Increases / (Decreases) in working capital liabilities | D99: =SUM(D77:D79)-SUM(C77:C79) -> 0 | E99: =SUM(E77:E79)-SUM(D77:D79) -> 0 | F99: =SUM(F77:F79)-SUM(E77:E79) -> 0 | G99: =SUM(G77:G79)-SUM(F77:F79) -> 0 | H99: =SUM(H77:H79)-SUM(G77:G79) -> 0 | I99: =SUM(I77:I79)-SUM(H77:H79) -> 0 | J99: =SUM(J77:J79)-SUM(I77:I79) -> 0 | K99: =SUM(K77:K79)-SUM(J77:J79) -> 0
B100: Other non current assets | D100: =-D140 -> 0 | E100: =-E140 -> 0 | F100: =-F140 -> 0 | G100: =-G140 -> -23121 | H100: =-H140 -> -23121 | I100: =-I140 -> -23121 | J100: =-J140 -> -23121 | K100: =-K140 -> -23121 | M100: Reference from schedule NOT the B/S: Only include 'Additions' (as outflow)
B101: Other non current liabilities | D101: =D82-C82 -> 0 | E101: =E82-D82 -> 0 | F101: =F82-E82 -> 0 | G101: =G82-F82 -> 0 | H101: =H82-G82 -> 0 | I101: =I82-H82 -> 0 | J101: =J82-I82 -> 0 | K101: =K82-J82 -> 0
B102: Cash from Operating Activities | D102: =SUM(D95:D101) -> -299698.82 | E102: =SUM(E95:E101) -> -260953 | F102: =SUM(F95:F101) -> -113234.48 | G102: =SUM(G95:G101) -> 700.20038 | H102: =SUM(H95:H101) -> 700.20038 | I102: =SUM(I95:I101) -> 700.20038 | J102: =SUM(J95:J101) -> 700.20038 | K102: =SUM(K95:K101) -> 700.20038
B104: Capital Expenditures | D104: =-(D125) -> 0 | E104: =-(E125) -> 0 | F104: =-(F125) -> 0 | G104: =-(G125) -> 0 | H104: =-(H125) -> 0 | I104: =-(I125) -> 0 | J104: =-(J125) -> 0 | K104: =-(K125) -> 0 | M104: Reference from PP&E schedule
B105: Cash from Investing Activities | D105: =IFERROR(D104,"NA") -> 0 | E105: =IFERROR(E104,"NA") -> 0 | F105: =IFERROR(F104,"NA") -> 0 | G105: =IFERROR(G104,"NA") -> 0 | H105: =IFERROR(H104,"NA") -> 0 | I105: =IFERROR(I104,"NA") -> 0 | J105: =IFERROR(J104,"NA") -> 0 | K105: =IFERROR(K104,"NA") -> 0
B107: Long term debt | D107: =D81-C81 -> 0 | E107: =E81-D81 -> 0 | F107: =F81-E81 -> 0 | G107: =G81-F81 -> 0 | H107: =H81-G81 -> 0 | I107: =I81-H81 -> 0 | J107: =J81-I81 -> 0 | K107: =K81-J81 -> 0
B108: Commercial paper/ Revolver | D108: =D80-C80 -> 0 | E108: =E80-D80 -> 0 | F108: =F80-E80 -> 0 | G108: =G80-F80 -> 0 | H108: =H80-G80 -> 0 | I108: =I80-H80 -> 0 | J108: =J80-I80 -> 0 | K108: =K80-J80 -> 0 | M108: Reference from B/S
B109: Share repurchases | D109: =D147 -> 0 | E109: =E147 -> 0 | F109: =F147 -> 0 | G109: =G147 -> 0 | H109: =H147 -> 0 | I109: =I147 -> 0 | J109: =J147 -> 0 | K109: =K147 -> 0 | M109: Reference from Retained Earnings schedule
B110: Common dividends | D110: =D146 -> 0 | E110: =E146 -> 0 | F110: =F146 -> 0 | G110: =G146 -> 0 | H110: =H146 -> 0 | I110: =I146 -> 0 | J110: =J146 -> 0 | K110: =K146 -> 0 | M110: Reference from Retained Earnings schedule
B111: Common dividends | D111: =D147 -> 0 | E111: =E147 -> 0 | F111: =F147 -> 0 | G111: =G147 -> 0 | H111: =H147 -> 0 | I111: =I147 -> 0 | J111: =J147 -> 0 | K111: =K147 -> 0 | M111: Reference from Retained Earnings schedule
B112: Cash from Financing Activities | D112: =SUM(D107:D110) -> 0 | E112: =SUM(E107:E110) -> 0 | F112: =SUM(F107:F110) -> 0 | G112: =SUM(G107:G110) -> 0 | H112: =SUM(H107:H110) -> 0 | I112: =SUM(I107:I110) -> 0 | J112: =SUM(J107:J110) -> 0 | K112: =SUM(K107:K110) -> 0
B114: Net change in cash during period | D114: =D102+D105+D112 -> -299698.82 | E114: =E102+E105+E112 -> -260953 | F114: =F102+F105+F112 -> -113234.48 | G114: =G102+G105+G112 -> 700.20038 | H114: =H102+H105+H112 -> 700.20038 | I114: =I102+I105+I112 -> 700.20038 | J114: =J102+J105+J112 -> 700.20038 | K114: =K102+K105+K112 -> 700.20038
A116: X | B116: Supporting Schedules | C116: Actuals | G116: Forecast
B117: Fiscal year | C117: 2021 | D117: 2022 | E117: 2023 | F117: 2024 | G117: 2025 | H117: 2026 | I117: 2027 | J117: 2028 | K117: 2029
B118: Fiscal year end date | C118: 44469 | D118: 44834 | E118: 45199 | F118: 45559 | G118: 45930 | H118: 46295 | I118: 46660 | J118: 47026 | K118: 47391
A120: X | B120: PROPERTY, PLANT & EQUIPMENT
B121: =B15 -> Fiscal year | D121: =D15 -> 2022 | E121: =E15 -> 2023 | F121: =F15 -> 2024 | G121: =G15 -> 2025 | H121: =H15 -> 2026 | I121: =I15 -> 2027 | J121: =J15 -> 2028 | K121: =K15 -> 2029
B122: =B16 -> Fiscal year end date | D122: =D16 -> 44926 | E122: =E16 -> 45291 | F122: =F16 -> 45657 | G122: =G16 -> 46022 | H122: =H16 -> 46387 | I122: =I16 -> 46752 | J122: =J16 -> 47118 | K122: =K16 -> 47483
G123: Forecast
B124: Beginning of period | D124: =C127 -> 0 | E124: =D127 -> 0 | F124: =E127 -> 0 | G124: =F127 -> 0 | H124: =G127 -> #DIV/0! | I124: =H127 -> #DIV/0! | J124: =I127 -> #DIV/0! | K124: =J127 -> #DIV/0! | M124: BOP = Previous year EOP
B125: Plus: Capital expenditures | M125: First two years - consensus estimates, then grow with revenue
...

Sheet DCF
B2: ='3-Statement Model'!C6&"(NASDAQ: AAPL)" -> Beyond Meat, Inc.(NASDAQ: AAPL)
B3: Discounted Cash Flow Valuation
B4: $ and shares in millions, except per share data
B6: Most recent fiscal year end | C6: ='Historical Financials'!I8 -> 45657 | F6: Discount rate (WACC) | I6: Link from WACC
B7: End of first fiscal year | C7: =EOMONTH(C6,12) -> 46022 | F7: Share price (Public Co) | I7: Source: CIQ
B8: Most recent quarter end date | F8: Share price date
B9: Valuation date | C9: 45956 | F9: Midyear adjustment? | H9: 1
B10: Portion of First Year Cash Flows | C10: =YEARFRAC(C9,C7) -> 0.18055556 | F10: Case active: | H10: ='3-Statement Model'!K6 -> Base case
B12: Unlevered Free Cash Flows
C13: LTM | D13: Actual | E13: Forecasts
B14: Fiscal year ended | C14: =C9 -> 45956 | D14: =C6 -> 45657 | E14: =EOMONTH(D14,12) -> 46022 | F14: =EOMONTH(E14,12) -> 46387 | G14: =EOMONTH(F14,12) -> 46752 | H14: =EOMONTH(G14,12) -> 47118 | I14: =EOMONTH(H14,12) -> 47483
B16: Revenue
B17: % growth | E17: =SUM(E16/D16)-1 -> #DIV/0! | F17: =SUM(F16/E16)-1 -> #DIV/0! | G17: =SUM(G16/F16)-1 -> #DIV/0! | H17: =SUM(H16/G16)-1 -> #DIV/0! | I17: =SUM(I16/H16)-1 -> #DIV/0!
B18: EBITDA
B19: % margin | D19: =D18/D16 -> #DIV/0! | E19: =E18/E16 -> #DIV/0! | F19: =F18/F16 -> #DIV/0! | G19: =G18/G16 -> #DIV/0! | H19: =H18/H16 -> #DIV/0! | I19: =I18/I16 -> #DIV/0!
B20: EBIT
B21: % margin | D21: =D20/D16 -> #DIV/0! | E21: =E20/E16 -> #DIV/0! | F21: =F20/F16 -> #DIV/0! | G21: =G20/G16 -> #DIV/0! | H21: =H20/H16 -> #DIV/0! | I21: =I20/I16 -> #DIV/0!
B23: Tax on EBIT | E23: =+E20*E24 -> 0 | F23: =+F20*F24 -> 0 | G23: =+G20*G24 -> 0 | H23: =+H20*H24 -> 0 | I23: =+I20*I24 -> 0
B24: Tax rate | D24: =D23/D20 -> #DIV/0!
B25: NOPAT (aka EBIAT) | D25: =+D23+D20 -> 0 | E25: =E20*(1-E24) -> 0 | F25: =F20*(1-F24) -> 0 | G25: =G20*(1-G24) -> 0 | H25: =H20*(1-H24) -> 0 | I25: =I20*(1-I24) -> 0
B27: Depreciation & amortization | D27: ='3-Statement Model'!F43 -> 23121
B28: Changes in net working capital | E28: =D34-E34 -> 0 | F28: =E34-F34 -> 0 | G28: =F34-G34 -> 0 | H28: =G34-H34 -> 0 | I28: =H34-I34 -> 0
B29: Capital expenditures
B30: as % of revenue | E30: =E29/E16 -> #DIV/0! | F30: =F29/F16 -> #DIV/0! | G30: =G29/G16 -> #DIV/0! | H30: =H29/H16 -> #DIV/0! | I30: =I29/I16 -> #DIV/0!
B32: Unlevered free cash flows (UFCF) | E32: =+E25+E27+E28+E29 -> 0 | F32: =+F25+F27+F28+F29 -> 0 | G32: =+G25+G27+G28+G29 -> 0 | H32: =+H25+H27+H28+H29 -> 0 | I32: =+I25+I27+I28+I29 -> 0
B34: Net working capital (WC Assets - WC liabilities)
B35: as % of revenue | E35: =+E34/E16 -> #DIV/0! | F35: =+F34/F16 -> #DIV/0! | G35: =+G34/G16 -> #DIV/0! | H35: =+H34/H16 -> #DIV/0! | I35: =+I34/I16 -> #DIV/0!
B37: ="Present value of UFCF on "&TEXT(C9,"mmm dd, yyyy")&" valuation date" -> Present value of UFCF on Oct 26, 2025 valuation date
D39: Val date | E39: Yr 1 - Stub | F39: Year 2 | G39: Year 3 | H39: Year 4 | I39: Year 5
B40: Date for discounting cash flows | D40: =C9 -> 45956 | E40: =IF($H$9=1,AVERAGE(E14,D40),E14) -> 45989 | F40: =IF($H$9=1,AVERAGE(F14,E14),F14) -> 46204.5 | G40: =IF($H$9=1,AVERAGE(G14,F14),G14) -> 46569.5 | H40: =IF($H$9=1,AVERAGE(H14,G14),H14) -> 46935 | I40: =IF($H$9=1,AVERAGE(I14,H14),I14) -> 47300.5
B41: Unlevered free cash flows (UFCF) stub adjusted | C41: =C10 -> 0.18055556 | E41: =E32*C41 -> 0 | F41: =F32 -> 0 | G41: =G32 -> 0 | H41: =H32 -> 0 | I41: =I32 -> 0 | K41: <-Stub year counts first year cash flows starting at the valuation date
B42: Present value of of unlevered free cash flows | E42: =E41/(1+$H$6)^((E40-$C$9)/365) -> 0 | F42: =F41/(1+$H$6)^((F40-$C$9)/365) -> 0 | G42: =G41/(1+$H$6)^((G40-$C$9)/365) -> 0 | H42: =H41/(1+$H$6)^((H40-$C$9)/365) -> 0 | I42: =I41/(1+$H$6)^((I40-$C$9)/365) -> 0
B44: Terminal value - growth in perpetuity approach | E44: Terminal value - EBITDA multiple approach
B46: Long term growth rate | E46: Terminal year EBITDA | I46: =I18 -> 0
B47: =YEAR(I14)&" FCF x (1+g)" -> 2029 FCF x (1+g) | C47: =I41*(1+C46) -> 0 | E47: EBITDA multiple
B48: ="Terminal value in "&YEAR(I14) -> Terminal value in 2029 | C48: =C47/(H6-C46) -> #DIV/0! | E48: ="Terminal value in "&YEAR(I14) -> Terminal value in 2029 | I48: =I46*I47 -> 0
B49: Present value of terminal value | C49: =C48/(1+H6)^((I40-$D$40)/365) -> #DIV/0! | E49: Present value of terminal value | I49: =I48/(1+H6)^((I40-D40)/365) -> 0
B50: Present value of stage 1 cash flows | C50: =SUM(E42:I42) -> 0 | E50: Present value of stage 1 cash flows | I50: =C50 -> 0
B51: Total enterprise value (TEV) | C51: =C50+C49 -> #DIV/0! | E51: Enterprise value (stage 1 + 2) | I51: =SUM(I49:I50) -> 0
B53: Terminal value as % of TEV | C53: =C49/$C$51 -> #DIV/0! | E53: Terminal value as % of TEV | I53: =+I49/I51 -> #DIV/0!
B54: Stage 1 cash flows as % of TEV | C54: =1-C53 -> #DIV/0! | E54: Cash flows as % of TEV | I54: =1-I53 -> #DIV/0!
B55: Implied TV exit EBITDA multiple | C55: =(C48/I18) -> #DIV/0! | E55: Implied terminal growth rate | I55: =(H6-I41/I48)/(1+I41/I48) -> #DIV/0!
B57: Net debt | E57: Shares outstanding
B58: Source doc
B59: Source date | G59: Source doc | H59: Date | I59: Shares
B60: Gross debt and equivalents | E60: Basic shares
B61: Debt | E61: Restricted stock / RSUs
B62: Convertible debt | E62: Options / warrants
B63: Preferred stock | E63: Convertible debt
B64: Noncontrolling (minority) interests | E64: Convertible preferred stock
B65: Nonoperating assets | E65: Net diluted shares outstanding | I65: =SUM(I60:I64) -> 0
B66: Cash
B67: Equity investments
B68: Net debt | C68: =SUM(C61:C64)-SUM(C66:C67) -> 0
B70: Valuation
C72: Perpetuity | D72: EBITDA
B73: Enterprise value | C73: =C51 -> #DIV/0! | D73: =I51 -> 0
B74: Net debt | C74: =$C$68 -> 0 | D74: =C74 -> 0
B75: Equity value | C75: =C73-C74 -> #DIV/0! | D75: =D73-D74 -> 0
B76: Shares outstanding | C76: =$I$65 -> 0 | D76: =C76 -> 0
B77: Equity value per share | C77: =C75/C76 -> #DIV/0! | D77: =D75/D76 -> #DIV/0!
C79: Last twelve months (LTM)
C80: Perpetuity | D80: EBITDA
B81: EV / Revenue | C81: =C$73/$C$16 -> #DIV/0! | D81: =D$73/$C$16 -> #DIV/0!
B82: EV / EBITDA | C82: =C73/$C$18 -> #DIV/0! | D82: =D73/$C$18 -> #DIV/0!
B83: EV / EBIT | C83: =C73/$C$20 -> #DIV/0! | D83: =D73/$C$20 -> #DIV/0!
C84: Year 1
C85: Perpetuity | D85: EBITDA
B86: EV / Revenue | C86: =C73/$E$16 -> #DIV/0! | D86: =D73/$E$16 -> #DIV/0!
B87: EV / EBITDA | C87: =C73/$E$18 -> #DIV/0! | D87: =D73/$E$18 -> #DIV/0!
B88: EV / EBIT | C88: =C73/$E$20 -> #DIV/0! | D88: =D73/$E$20 -> #DIV/0!
B90: Outputs
D92: Equity value per share | L92: LTM EBITDA multiple
E93: Long term growth rate (g):
D94: =C77 -> #DIV/0! | E94: =F94-0.005 -> 0.02 | F94: =G94-0.005 -> 0.025 | G94: 0.03 | H94: =G94+0.005 -> 0.035 | I94: =H94+0.005 -> 0.04 | L94: =C82 -> #DIV/0! | M94: =N94-0.005 -> 0.02 | N94: =O94-0.005 -> 0.025 | O94: 0.03 | P94: =O94+0.005 -> 0.035 | Q94: =P94+0.005 -> 0.04
D95: =D96+0.01 -> 0.11 | E95: 20.680633 | F95: 20.680633 | G95: 20.680633 | H95: 20.680633 | I95: 20.680633 | L95: =L96+0.01 -> 0.11 | M95: #DIV/0! | N95: #DIV/0! | O95: #DIV/0! | P95: #DIV/0! | Q95: #DIV/0!
D96: =D97+0.01 -> 0.1 | E96: 20.680633 | F96: 20.680633 | G96: 20.680633 | H96: 20.680633 | I96: 20.680633 | L96: =L97+0.01 -> 0.1 | M96: #DIV/0! | N96: #DIV/0! | O96: #DIV/0! | P96: #DIV/0! | Q96: #DIV/0!
C97: WACC: | D97: 0.09 | E97: 20.680633 | F97: 20.680633 | G97: 20.680633 | H97: 20.680633 | I97: 20.680633 | K97: WACC: | L97: 0.09 | M97: #DIV/0! | N97: #DIV/0! | O97: #DIV/0! | P97: #DIV/0! | Q97: #DIV/0!
D98: =D97-0.01 -> 0.08 | E98: 20.680633 | F98: 20.680633 | G98: 20.680633 | H98: 20.680633 | I98: 20.680633 | L98: =L97-0.01 -> 0.08 | M98: #DIV/0! | N98: #DIV/0! | O98: #DIV/0! | P98: #DIV/0! | Q98: #DIV/0!
B99: Data | D99: =D98-0.01 -> 0.07 | E99: 20.680633 | F99: 20.680633 | G99: 20.680633 | H99: 20.680633 | I99: 20.680633 | L99: =L98-0.01 -> 0.07 | M99: #DIV/0! | N99: #DIV/0! | O99: #DIV/0! | P99: #DIV/0! | Q99: #DIV/0!
B100: Tables
D101: Equity value per share | L101: LTM EBITDA multiple
E102: Exit EBITDA Multiple | M102: Exit EBITDA Multiple
D103: =D77 -> #DIV/0! | E103: =F103-1 -> 11 | F103: =G103-1 -> 12 | G103: 13 | H103: =G103+1 -> 14 | I103: =H103+1 -> 15 | L103: =D82 -> #DIV/0! | M103: =N103-1 -> 11 | N103: =O103-1 -> 12 | O103: 13 | P103: =O103+1 -> 14 | Q103: =P103+1 -> 15
D104: =D105+0.01 -> 0.11 | E104: 20.680633 | F104: 20.680633 | G104: 20.680633 | H104: 20.680633 | I104: 20.680633 | L104: =L105+0.01 -> 0.11 | M104: #DIV/0! | N104: #DIV/0! | O104: #DIV/0! | P104: #DIV/0! | Q104: #DIV/0!
D105: =D106+0.01 -> 0.1 | E105: 20.680633 | F105: 20.680633 | G105: 20.680633 | H105: 20.680633 | I105: 20.680633 | L105: =L106+0.01 -> 0.1 | M105: #DIV/0! | N105: #DIV/0! | O105: #DIV/0! | P105: #DIV/0! | Q105: #DIV/0!
C106: WACC: | D106: 0.09 | E106: 20.680633 | F106: 20.680633 | G106: 20.680633 | H106: 20.680633 | I106: 20.680633 | K106: WACC: | L106: 0.09 | M106: #DIV/0! | N106: #DIV/0! | O106: #DIV/0! | P106: #DIV/0! | Q106: #DIV/0!
D107: =D106-0.01 -> 0.08 | E107: 20.680633 | F107: 20.680633 | G107: 20.680633 | H107: 20.680633 | I107: 20.680633 | L107: =L106-0.01 -> 0.08 | M107: #DIV/0! | N107: #DIV/0! | O107: #DIV/0! | P107: #DIV/0! | Q107: #DIV/0!
D108: =D107-0.01 -> 0.07 | E108: 20.680633 | F108: 20.680633 | G108: 20.680633 | H108: 20.680633 | I108: 20.680633 | L108: =L107-0.01 -> 0.07 | M108: #DIV/0! | N108: #DIV/0! | O108: #DIV/0! | P108: #DIV/0! | Q108: #DIV/0!
B110: Equity value range | G110: Football field
C131: Low | D131: Diff. | E131: High | O131: Low | P131: Diff. | Q131: High
B132: ="DCF Value at "&TEXT(E103,"0.0x")&"-"&TEXT(I103,"0.0x")&" Exit EBITDA Range at "&TEXT(D106,"0.0%")&" WACC" -> DCF Value at 11.0x-15.0x Exit EBITDA Range at 9.0% WACC | C132: =E106 -> 20.680633 | D132: =E132-C132 -> 0 | E132: =I106 -> 20.680633 | G132: ="LTM EBITDA Purchase Multiple at "&TEXT(M94,"0.0%")&"-"&TEXT(Q94,"0.0%")&" Perpetuity Growth at "&TEXT(L97,"0.0%")&" WACC" -> LTM EBITDA Purchase Multiple at 2.0%-4.0% Perpetuity Growth at 9.0% WACC | O132: =M97 -> #DIV/0! | P132: =Q132-O132 -> #DIV/0! | Q132: =Q97 -> #DIV/0!
B133: ="DCF Value at "&TEXT(E94,"0.0%")&"-"&TEXT(I94,"0.0%")&" Perpetuity Range at "&TEXT(D106,"0.0%")&" WACC" -> DCF Value at 2.0%-4.0% Perpetuity Range at 9.0% WACC | C133: =E97 -> 20.680633 | D133: =E133-C133 -> 0 | E133: =I97 -> 20.680633 | G133: ="LTM EBITDA Purchase Multiple at "&TEXT(M106,"0.0x")&"-"&TEXT(Q106,"0.0x")&" Exit EBITDA Multiple at "&TEXT(L106,"0.0%")&" WACC" -> #DIV/0! | O133: =M106 -> #DIV/0! | P133: =Q133-O133 -> #DIV/0! | Q133: =Q106 -> #DIV/0!
B134: 52 Week Market High/Low | C134: 169.5 | D134: =E134-C134 -> 158.35 | E134: 327.85 | G134: ="LTM EBITDA Purchase Multiple at "&TEXT(L108,"0.0%")&"-"&TEXT(L104,"0.0%")&" WACC at "&TEXT(O103,"0.0x")&" Exit EBITDA" -> LTM EBITDA Purchase Multiple at 7.0%-11.0% WACC at 13.0x Exit EBITDA | O134: =O104 -> #DIV/0! | P134: =Q134-O134 -> #DIV/0! | Q134: =O108 -> #DIV/0!

Sheet WACC
B2: ='3-Statement Model'!C6&"(NASDAQ: AAPL)" -> Beyond Meat, Inc.(NASDAQ: AAPL)
B3: WACC Buildup
B4: $ and shares in millions, except per share data
B6: Cost of capital assumptions | E6: Source
B8: Cost of debt | E8: TBD
B9: Tax rate | E9: From terminal year of UFCF forecast
B10: Cost of debt (after tax) | C10: =C8*(1-C9) -> 0 | E10: Cost of debt x (1 - tax rate)
B12: Risk free rate | E12: WSJ: 10 Year US Treasury Yield
B13: Beta | C13: =IF(C34="Observed",C36,C37) -> 0 | E13: Bloomberg 2 year weekly adjusted beta
B14: Market risk premium | E14: Market risk premium from D&P - TBD
B15: Cost of equity | C15: =C12+C13*C14 -> 0 | E15: RfR + Beta x MRP
B17: Capital weights (capital structure)
D18: Target
C19: Current | D19: (override) | E19: % of total
B20: Equity | E20: =IF(D20,D20,C20/(C20+C21)) -> #DIV/0!
B21: Debt | C21: =DCF!C61 -> 0 | D21: =1-D20 -> 1 | E21: =1-E20 -> #DIV/0!
B23: Cost of capital (WACC) | E23: =C10*E21+C15*E20 -> #DIV/0!
B25: WACC sensitivity to MRP and Beta
D26: Beta
C27: =E23 -> #DIV/0! | D27: =E27-0.1 -> -0.1 | F27: =E27+0.1 -> 0.1
C28: =C29-0.005 -> -0.01 | D28: 0.061013495 | E28: 0.065908826 | F28: 0.070804156
B29: Market | C29: =C30-0.005 -> -0.005 | D29: 0.066447312 | E29: 0.071886568 | F29: 0.077325824
B30: Risk | D30: 0.071881129 | E30: 0.077864311 | F30: 0.083847492
B31: Premium | C31: =C30+0.005 -> 0.005 | D31: 0.077314946 | E31: 0.083842053 | F31: 0.090369161
C32: =C31+0.005 -> 0.01 | D32: 0.082748763 | E32: 0.089819796 | F32: 0.096890829
B34: Select Beta for model | C34: Observed
B36: Observed | D36: Bloomberg 2 year weekly adjusted beta
B37: Industry beta | C37: =C48 -> #DIV/0! | D37: From schedule below
B39: Industry beta
C41: Observed b | D41: Share price | E41: Dil. shares | F41: Market cap | G41: Net Debt | H41: Tax rate | I41: Delev. b
F42: =D42*E42 -> 0 | I42: =C42/(1+(1-H42)*(G42)/F42) -> #DIV/0!
F43: =D43*E43 -> 0 | I43: =C43/(1+(1-H43)*(G43)/F43) -> #DIV/0!
F44: =D44*E44 -> 0 | I44: =C44/(1+(1-H44)*(G44)/F44) -> #DIV/0!
C45: =C36 -> 0 | F45: =C20 -> 0 | G45: =C21 -> 0 | H45: =C9 -> 0 | I45: =C45/(1+(1-H45)*(G45)/F45) -> #DIV/0!
B47: Industry average delevered beta | C47: =AVERAGE(I42:I45) -> #DIV/0!
B48: =B45&" beta" -> beta | C48: =C47*(1+(1-H45)*(G45)/F45) -> #DIV/0!

Sheet Shares
B2: ='3-Statement Model'!C6&"(NASDAQ: AAPL)" -> Beyond Meat, Inc.(NASDAQ: AAPL)
B3: Shares - Options and Convertibles
B4: $ and shares in millions, except per share data
B6: Current share price | E6: =DCF!H7 -> 0
A9: X | B9: Stock options - Treasury stock method | C9: Outstanding | D9: Exercise | E9: In-the-$
B10: As of 3Q25 (period ended x/xx/xx) | C10: options | D10: price | E10: options
B12: Tranche 1 | E12: =IF(D12<=$E$6,C12,0) -> 0
B13: Tranche 2 | E13: =IF(D13<=$E$6,C13,0) -> 0
B14: Tranche 3 | E14: =IF(D14<=$E$6,C14,0) -> 0
B15: Tranche 4 | E15: =IF(D15<=$E$6,C15,0) -> 0
B16: Tranche 5 | E16: =IF(D16<=$E$6,C16,0) -> 0
B17: Tranche 6 | E17: =IF(D17<=$E$6,C17,0) -> 0
B18: Tranche 7 | E18: =IF(D18<=$E$6,C18,0) -> 0
B19: Total | C19: =SUM(C12:C18) -> 0 | E19: =SUM(E12:E18) -> 0
B21: Total proceeds ($mm) | E21: =SUMPRODUCT(D12:D18,E12:E18) -> 0
B22: Total shares repurchased (mm) | E22: =-(E21/E6) -> #DIV/0!
B23: Net dilutive impact of stock options | E23: =E19+E22 -> #DIV/0!
A25: X | B25: Convertible securities "if-converted" test
B27: Convertible Debt
B28: Principal Outstanding
B29: Each $1,000 in principal convertible into (Conversion ratio)
B30: Conversion price | E30: =E28/E31 -> #DIV/0!
B31: Common shares convertible into | E31: =E29*E28/1000 -> 0
B33: Dilutive impact of convertible securities | E33: =IF(E30<E6,E31,0) -> #DIV/0!
B34: Elimination of liability from net debt | E34: =IF(E33>0,-E28,0) -> #DIV/0!
B36: Convertible Preferred Stock
B37: Convertible Preferred Par Value
B38: Preferred shares outstanding
B39: Conversion ratio
B40: Common shares convertible into | E40: =E38*E39 -> 0
B41: Conversion price | E41: =E37/E40 -> #DIV/0!
B43: Dilutive impact of convertible securities | E43: =IF(E41<E6,E40,0) -> #DIV/0!
B44: Elimination of liability from net debt | E44: =IF(E43>0,-E37,0) -> #DIV/0!
